Workbook
Name \A: #REF!
Name \B: #REF!
Name \C: #REF!
Name \P: #REF!
Name \Q: #REF!
Name \R: #REF!
Name \S: #REF!
Name \T: #REF!
Name \X: #REF!
Name ___CON1: #REF!
Name ___CON2: #REF!
Name ___ddn400: #REF!
Name ___ddn600: #REF!
Name ___E99999: #REF!
Name ___gon4: #REF!
Name ___IV999999: #REF!
Name ___IZ53: #REF!
Name ___JZ123: #REF!
Name ___lap1: #REF!
Name ___lap2: #REF!
Name ___LI10: OFFSET(#REF!,4,0,COUNTA(#REF!)-1,1)
Name ___LI3: OFFSET(#REF!,4,0,COUNTA(#REF!)-1,1)
Name ___LI6: OFFSET(#REF!,4,0,COUNTA(#REF!)-1,1)
Name ___LI7: OFFSET(#REF!,4,0,COUNTA(#REF!)-1,1)
Name ___LZ123: #REF!
Name ___MAC12: #REF!
Name ___MAC46: #REF!
Name ___MZ53: #REF!
Name ___NCL100: #REF!
Name ___NCL200: #REF!
Name ___NCL250: #REF!
Name ___NET2: #REF!
Name ___nin190: #REF!
Name ___sc1: #REF!
Name ___SC2: #REF!
Name ___sc3: #REF!
Name ___SN3: #REF!
Name ___TB1: #REF!
Name ___TL1: #REF!
Name ___TL2: #REF!
Name ___TL3: #REF!
Name ___TLA120: #REF!
Name ___TLA35: #REF!
Name ___TLA50: #REF!
Name ___TLA70: #REF!
Name ___TLA95: #REF!
Name ___VL100: #REF!
Name ___VL200: #REF!
Name ___VL250: #REF!
Name ___XY123: #REF!
Name __1: #REF!
Name __2: #REF!
Name __CON1: #REF!
Name __CON2: #REF!
Name __ddn400: #REF!
Name __ddn600: #REF!
Name __E99999: #REF!
Name __gon4: #REF!
Name __IV17532: #REF!
Name __IV19999: #REF!

Sheet Instruction
B1: Actual Reporting
B2: 1. | C2: Please update copertura for the period / data entry - line 53 onwords
B3: 2. | C3: Please update the actual cost for the period / data entry - line 75 onwords
B4: 3. | C4: Update columns "Q" & "R" in the data entry and budget assumption tab
B6: 4. | C6: YTD and MTD variances, as well as the report is populated automatically
B7: 5. | C7: Please provide the rootcauses for the variances YTD and MTD Report (column J-P)
C8: Checkline in column "U" needs to be zero in each line
B9: 6. | C9: SAP extraction actual cost lines as separate sheet
B11: FCST Reporting
B13: 1. | C13: Please fill in the copertura and actuals for the upcoming months _ data entry tab - lines 53-94
B14: 2. | C14: FCST tab is populated automatically , please check the correctness
B15: 3. | C15: Provide root cause split for the upcoming periods variances
B16: 4. | C16: Paste values previous submitted FCST in "FCST25" sheet lines 47-87
B17: 5. | C17: Check variances vs last forecast in "FCST25" sheet lines 91-131
B18: 6. | C18: Update column AE & AF in "FCST CPU"
B19: 7. | C19: Update Material & Freight In part in "FCST CPU"

Sheet Root cause explanations
B2: Budget Cost | C2: Budgeted cost of the period @ Budget FX rate
B4: ACE | C4: Permanent saving, linked to ACE projects. This line needs to give us the deviation versus the budgeted ACE improvements
B6: MFG Efficiency | C6: Saving / Cost in relation with current year standard production process not linked to price , one off or ACE ; e.g delay of hiring , not spending the budget for a specific line or additional consumption due to breakdown etc
B8: S&OP | C8: Increase or decrease of cost due to volume fluctuations; Excess of Manpower, Additional / less vertical closure days impact, Incremental cost increase / decrease on the fixed cost due to volume change
B10: Price / Inflation | C10: Pure Price or Inflation impact
B12: fX translation | C12: fx impact act fx versus budget fx
B14: One off | C14: Extraordinary expense/income not linked to current year standard production process; previous years income/ loss, write off and sale of assets , one time expenses like restructuring program, cost related to opening ceremony, extra ordinary donations etc
B16: Oth Functions | C16: Cost related to claims , which in the past was recharged to R&D, Procurement , Logistics
B18: Actual Cost | C18: Actual cost of the period converted @ actual fx rate

Sheet HC 2026
A1: Headcount 2026 (ACT + FCST)
C3: Jan | D3: Feb | E3: March | F3: April | G3: May | H3: June | I3: July | J3: August | K3: Sept | L3: Oct | M3: Nov | N3: Dec | O3: Total
A4: Direct HC | B4: Production | C4: 236.73 | D4: 215 | E4: 132 | F4: 245 | G4: 253.01372 | H4: 245.10067 | I4: 242.74113 | J4: 238.75755 | K4: 242.0053 | L4: 244.84655 | M4: 243.1902 | N4: 245.46848 | O4: =AVERAGE(C4:N4) -> 231.9878
B5: Shared | O5: =AVERAGE(C5:N5) -> #DIV/0!
B6: Total | C6: =C4+C5 -> 236.73 | D6: =D4+D5 -> 215 | E6: =E4+E5 -> 132 | F6: =F4+F5 -> 245 | G6: =G4+G5 -> 253.01372 | H6: =H4+H5 -> 245.10067 | I6: =I4+I5 -> 242.74113 | J6: =J4+J5 -> 238.75755 | ... N6: =N4+N5 -> 245.46848 | O6: =AVERAGE(C6:N6) -> 231.9878
B8: Assigned hours | O8: =AVERAGE(C8:N8) -> #DIV/0!
C10: Jan | D10: Feb | E10: March | F10: April | G10: May | H10: June | I10: July | J10: August | K10: Sept | L10: Oct | M10: Nov | N10: Dec | O10: Total
A11: Indirect HC | B11: Production | C11: 85 | D11: 82 | E11: 69 | F11: 85 | G11: 85 | H11: 85 | I11: 85 | J11: 85 | K11: 85 | L11: 85 | M11: 85 | N11: 85 | O11: =AVERAGE(C11:N11) -> 83.416667
B12: Shared | O12: =AVERAGE(C12:N12) -> #DIV/0!
B13: Total | C13: =C11+C12 -> 85 | D13: =D11+D12 -> 82 | E13: =E11+E12 -> 69 | F13: =F11+F12 -> 85 | G13: =G11+G12 -> 85 | H13: =H11+H12 -> 85 | I13: =I11+I12 -> 85 | J13: =J11+J12 -> 85 | ... N13: =N11+N12 -> 85 | O13: =AVERAGE(C13:N13) -> 83.416667
C16: Jan | D16: Feb | E16: March | F16: April | G16: May | H16: June | I16: July | J16: August | K16: Sept | L16: Oct | M16: Nov | N16: Dec | O16: Total
A17: Fixed HC | B17: Production | C17: 22 | D17: 22 | E17: 22 | F17: 22 | G17: 22 | H17: 22 | I17: 22 | J17: 23 | K17: 23 | L17: 23 | M17: 23 | N17: 23 | O17: =AVERAGE(C17:N17) -> 22.416667
B18: Shared | C18: 3.5 | D18: 3.5 | E18: 3.5 | F18: 4.5 | G18: 4.5 | H18: 4.5 | I18: 4.5 | J18: 4.5 | K18: 4.5 | L18: 4.5 | M18: 4.5 | N18: 4.5 | O18: =AVERAGE(C18:N18) -> 4.25
B19: Lapro | O19: =AVERAGE(C19:N19) -> #DIV/0!
B20: Total | C20: =C17+C18+C19 -> 25.5 | D20: =D17+D18+D19 -> 25.5 | E20: =E17+E18+E19 -> 25.5 | F20: =F17+F18+F19 -> 26.5 | G20: =G17+G18+G19 -> 26.5 | H20: =H17+H18+H19 -> 26.5 | I20: =I17+I18+I19 -> 26.5 | J20: =J17+J18+J19 -> 27.5 | ... N20: =N17+N18+N19 -> 27.5 | O20: =AVERAGE(C20:N20) -> 26.666667
C24: Jan | D24: Feb | E24: March | F24: April | G24: May | H24: June | I24: July | J24: Aug | K24: Sep | L24: Oct | M24: Nov | N24: Dec | O24: Total
B25: Direct HC | C25: =+C6 -> 236.73 | D25: =+D6 -> 215 | E25: =+E6 -> 132 | F25: =+F6 -> 245 | G25: =+G6 -> 253.01372 | H25: =+H6 -> 245.10067 | I25: =+I6 -> 242.74113 | J25: =+J6 -> 238.75755 | ... N25: =+N6 -> 245.46848 | O25: =O6 -> 231.9878
B26: Indirect HC | C26: =+C13 -> 85 | D26: =+D13 -> 82 | E26: =+E13 -> 69 | F26: =+F13 -> 85 | G26: =+G13 -> 85 | H26: =+H13 -> 85 | I26: =+I13 -> 85 | J26: =+J13 -> 85 | ... N26: =+N13 -> 85 | O26: =O13 -> 83.416667
B27: Total HC | C27: =C25+C26 -> 321.73 | D27: =D25+D26 -> 297 | E27: =E25+E26 -> 201 | F27: =F25+F26 -> 330 | G27: =G25+G26 -> 338.01372 | H27: =H25+H26 -> 330.10067 | I27: =I25+I26 -> 327.74113 | J27: =J25+J26 -> 323.75755 | ... O27: =O25+O26 -> 315.40447
B29: Temporary ratio | C29: =+C26/C27 -> 0.26419669 | D29: =+D26/D27 -> 0.27609428 | E29: =+E26/E27 -> 0.34328358 | F29: =+F26/F27 -> 0.25757576 | G29: =+G26/G27 -> 0.25146908 | H29: =+H26/H27 -> 0.25749721 | I29: =+I26/I27 -> 0.25935103 | J29: =+J26/J27 -> 0.26254214 | ... N29: =+N26/N27 -> 0.25721061
A32: BUDGET | C32: Jan | D32: Feb | E32: March | F32: April | G32: May | H32: June | I32: July | J32: August | K32: Sept | L32: Oct | M32: Nov | N32: Dec | O32: Total
A33: Direct HC | B33: Production | C33: 244 | D33: 244 | E33: 244 | F33: 244 | G33: 247 | H33: 245 | I33: 245 | J33: 251 | K33: 252 | L33: 250 | M33: 251 | N33: 252 | O33: =AVERAGE(C33:N33) -> 247.41667
B34: Shared | O34: =AVERAGE(C34:N34) -> #DIV/0!
B35: Total | C35: =C33+C34 -> 244 | D35: =D33+D34 -> 244 | E35: =E33+E34 -> 244 | F35: =F33+F34 -> 244 | G35: =G33+G34 -> 247 | H35: =H33+H34 -> 245 | I35: =I33+I34 -> 245 | J35: =J33+J34 -> 251 | ... N35: =N33+N34 -> 252 | O35: =AVERAGE(C35:N35) -> 247.41667
B37: Assigned hours | O37: =AVERAGE(C37:N37) -> #DIV/0!
A39: BUDGET | C39: Jan | D39: Feb | E39: March | F39: April | G39: May | H39: June | I39: July | J39: August | K39: Sept | L39: Oct | M39: Nov | N39: Dec | O39: Total
A40: Indirect HC | B40: Production | C40: 85 | D40: 85 | E40: 85 | F40: 85 | G40: 85 | H40: 85 | I40: 85 | J40: 85 | K40: 85 | L40: 85 | M40: 85 | N40: 85 | O40: =AVERAGE(C40:N40) -> 85
B41: Shared | O41: =AVERAGE(C41:N41) -> #DIV/0!
B42: Total | C42: =C40+C41 -> 85 | D42: =D40+D41 -> 85 | E42: =E40+E41 -> 85 | F42: =F40+F41 -> 85 | G42: =G40+G41 -> 85 | H42: =H40+H41 -> 85 | I42: =I40+I41 -> 85 | J42: =J40+J41 -> 85 | ... N42: =N40+N41 -> 85 | O42: =AVERAGE(C42:N42) -> 85
A45: BUDGET | C45: Jan | D45: Feb | E45: March | F45: April | G45: May | H45: June | I45: July | J45: August | K45: Sept | L45: Oct | M45: Nov | N45: Dec | O45: Total
A46: Fixed HC | B46: Production | C46: 22 | D46: 22 | E46: 22 | F46: 22 | G46: 22 | H46: 22 | I46: 22 | J46: 23 | K46: 23 | L46: 23 | M46: 23 | N46: 23 | O46: =AVERAGE(C46:N46) -> 22.416667
B47: Shared | C47: 4.5 | D47: 4.5 | E47: 4.5 | F47: 4.5 | G47: 4.5 | H47: 4.5 | I47: 4.5 | J47: 4.5 | K47: 4.5 | L47: 4.5 | M47: 4.5 | N47: 4.5 | O47: =AVERAGE(C47:N47) -> 4.5 | P47: 1.5 hqd included
B48: Lapro | O48: =AVERAGE(C48:N48) -> #DIV/0!
B49: Total | C49: =C46+C47+C48 -> 26.5 | D49: =D46+D47+D48 -> 26.5 | E49: =E46+E47+E48 -> 26.5 | F49: =F46+F47+F48 -> 26.5 | G49: =G46+G47+G48 -> 26.5 | H49: =H46+H47+H48 -> 26.5 | I49: =I46+I47+I48 -> 26.5 | J49: =J46+J47+J48 -> 27.5 | ... N49: =N46+N47+N48 -> 27.5 | O49: =AVERAGE(C49:N49) -> 26.916667

Sheet G&A _Out of Per_
C2: RENTA | I2: EURASIA | K2: TOTAL
C3: TD | D3: DW | E3: CK | F3: INFRA | G3: TOTAL | I3: TOTAL | M3: Highlights;
B4: Association dues (MESS Payment) | G4: =SUM(C4:F4) -> 0 | K4: =G4+I4 -> 0
B5: G&A Recharge Eurosia - Renta | G5: =SUM(C5:F5) -> 0 | K5: =G5+I5 -> 0
B6: IT Recharge Group | G6: =SUM(C6:F6) -> 0 | K6: =G6+I6 -> 0
B7: Controlling Expenses | G7: =SUM(C7:F7) -> 0 | K7: =G7+I7 -> 0
B8: Enterprice Property Insurance | G8: =SUM(C8:F8) -> 0 | K8: =G8+I8 -> 0
B9: Profit on Asset Sale | G9: =SUM(C9:F9) -> 0 | K9: =G9+I9 -> 0
B10: Loss on Asset Sale | G10: =SUM(C10:F10) -> 0 | K10: =G10+I10 -> 0
B11: Litigation fee | G11: =SUM(C11:F11) -> 0 | K11: =G11+I11 -> 0
B12: INFRA | G12: =SUM(C12:F12) -> 0 | K12: =G12+I12 -> 0
B13: …...... | G13: =SUM(C13:F13) -> 0 | K13: =G13+I13 -> 0
B14: G&A _ Out of Perimeter | C14: =SUM(C4:C13) -> 0 | D14: =SUM(D4:D13) -> 0 | E14: =SUM(E4:E13) -> 0 | F14: =SUM(F4:F13) -> 0 | G14: =SUM(G4:G13) -> 0 | I14: =SUM(I4:I13) -> 0 | K14: =SUM(K4:K13) -> 0

Sheet CC
I2: MFG | J2: PTK4M00WAB
J3: PTK4M00WAC
J4: PTK4M00WAD
J5: PTK4M00WAE
J6: PTK4M00WAF
J7: PTK4M00WAG
J8: PTK4M00WAH
J9: PTK4M00WAI
J10: PTK4M00WAJ
J11: PTK4M00WAK
J12: PTK4M00WYD
I13: Overhead | J13: PTK4Y00WYE

Sheet ACE 2026
A1: YTD | B1: =IF($V$3>=B$2,1,0) -> 1 | C1: =IF($V$3>=C$2,1,0) -> 0 | D1: =IF($V$3>=D$2,1,0) -> 0 | E1: =IF($V$3>=E$2,1,0) -> 0 | F1: =IF($V$3>=F$2,1,0) -> 0 | G1: =IF($V$3>=G$2,1,0) -> 0 | H1: =IF($V$3>=H$2,1,0) -> 0 | I1: =IF($V$3>=I$2,1,0) -> 0 | ... M1: =IF($V$3>=M$2,1,0) -> 0
A2: MTD | B2: 1 | C2: 2 | D2: 3 | E2: 4 | F2: 5 | G2: 6 | H2: 7 | I2: 8 | J2: 9 | K2: 10 | L2: 11 | M2: 12
T3: Month | U3: Jan | V3: =VLOOKUP(U3,List!$C$2:$D$13,2,0) -> 1 | W3: =VLOOKUP(U3,List!$C$2:$E$13,3,0) -> 1
A4: ACE Budget | B4: Jan | C4: Feb | D4: March | E4: April | F4: May | G4: June | H4: July | I4: August | J4: Sept | K4: Oct | L4: Nov | M4: Dec | N4: Total | P4: MTD | Q4: YTD
A5: Direct Labour | B5: 4644.3971 | C5: 5010.6746 | D5: 5057.5234 | E5: 4872.7558 | F5: 15380.89 | G5: 49280.033 | H5: 49328.755 | I5: 49547.308 | J5: 58604.946 | K5: 54442.467 | L5: 52437.071 | M5: 52468.259 | N5: =SUM(B5:M5) -> 401075.08 | P5: =+SUMIFS(B5:M5,$B$2:$M$2,$V$3)/1000 -> 4.6443971 | Q5: =+SUMIFS(B5:M5,$B$1:$M$1,$W$3)/1000 -> 4.6443971
A6: Variable Utilities | B6: 0 | C6: 0 | D6: 0 | E6: 0 | F6: 0 | G6: 0 | H6: 0 | I6: 0 | J6: 0 | K6: 0 | L6: 0 | M6: 0 | N6: =SUM(B6:M6) -> 0 | P6: =+SUMIFS(B6:M6,$B$2:$M$2,$V$3)/1000 -> 0 | Q6: =+SUMIFS(B6:M6,$B$1:$M$1,$W$3)/1000 -> 0
A7: Scrap | B7: 0 | C7: 0 | D7: 0 | E7: 6811.5 | F7: 5019 | G7: 7528.5 | H7: 6094.5 | I7: 5557.5 | J7: 7780.5 | K7: 6669 | L7: 7410 | M7: 5570.25 | N7: =SUM(B7:M7) -> 58440.75 | P7: =+SUMIFS(B7:M7,$B$2:$M$2,$V$3)/1000 -> 0 | Q7: =+SUMIFS(B7:M7,$B$1:$M$1,$W$3)/1000 -> 0
A8: Scrap Reselling | B8: 0 | C8: 0 | D8: 0 | E8: 0 | F8: 0 | G8: 0 | H8: 0 | I8: 0 | J8: 0 | K8: 0 | L8: 0 | M8: 0 | N8: =SUM(B8:M8) -> 0 | P8: =+SUMIFS(B8:M8,$B$2:$M$2,$V$3)/1000 -> 0 | Q8: =+SUMIFS(B8:M8,$B$1:$M$1,$W$3)/1000 -> 0
A9: Variable Costs | B9: 1000 | C9: 1000 | D9: 1000 | E9: 1000 | F9: 1000 | G9: 1000 | H9: 1000 | I9: 1000 | J9: 1000 | K9: 1000 | L9: 1000 | M9: 1000 | N9: =SUM(B9:M9) -> 12000 | P9: =+SUMIFS(B9:M9,$B$2:$M$2,$V$3)/1000 -> 1 | Q9: =+SUMIFS(B9:M9,$B$1:$M$1,$W$3)/1000 -> 1
A10: VARIABLE CONVERSION | B10: =SUM(B5:B9) -> 5644.3971 | C10: =SUM(C5:C9) -> 6010.6746 | D10: =SUM(D5:D9) -> 6057.5234 | E10: =SUM(E5:E9) -> 12684.256 | F10: =SUM(F5:F9) -> 21399.89 | G10: =SUM(G5:G9) -> 57808.533 | H10: =SUM(H5:H9) -> 56423.255 | I10: =SUM(I5:I9) -> 56104.808 | ... M10: =SUM(M5:M9) -> 59038.509 | N10: =SUM(B10:M10) -> 471515.83 | P10: =SUM(P5:P9) -> 5.6443971 | Q10: =SUM(Q5:Q9) -> 5.6443971
A11: Indirect Labour | B11: 0 | C11: 0 | D11: 0 | E11: 0 | F11: 0 | G11: 0 | H11: 0 | I11: 0 | J11: 0 | K11: 0 | L11: 0 | M11: 0 | N11: =SUM(B11:M11) -> 0 | P11: =+SUMIFS(B11:M11,$B$2:$M$2,$V$3)/1000 -> 0 | Q11: =+SUMIFS(B11:M11,$B$1:$M$1,$W$3)/1000 -> 0
A12: Fixed Labour | B12: 0 | C12: 0 | D12: 0 | E12: 0 | F12: 0 | G12: 0 | H12: 0 | I12: 0 | J12: 0 | K12: 0 | L12: 0 | M12: 0 | N12: =SUM(B12:M12) -> 0 | P12: =+SUMIFS(B12:M12,$B$2:$M$2,$V$3)/1000 -> 0 | Q12: =+SUMIFS(B12:M12,$B$1:$M$1,$W$3)/1000 -> 0
A13: Semifixed | B13: 0 | C13: 0 | D13: 0 | E13: 0 | F13: 0 | G13: 0 | H13: 0 | I13: 0 | J13: 0 | K13: 0 | L13: 0 | M13: 0 | N13: =SUM(B13:M13) -> 0 | P13: =+SUMIFS(B13:M13,$B$2:$M$2,$V$3)/1000 -> 0 | Q13: =+SUMIFS(B13:M13,$B$1:$M$1,$W$3)/1000 -> 0
A14: Fixed utilities | B14: 1100 | C14: 1100 | D14: 1100 | E14: 1100 | F14: 1100 | G14: 1100 | H14: 1100 | I14: 1100 | J14: 1100 | K14: 1100 | L14: 1100 | M14: 1100 | N14: =SUM(B14:M14) -> 13200 | P14: =+SUMIFS(B14:M14,$B$2:$M$2,$V$3)/1000 -> 1.1 | Q14: =+SUMIFS(B14:M14,$B$1:$M$1,$W$3)/1000 -> 1.1
A15: Fixed Cost | B15: 0 | C15: 0 | D15: 0 | E15: 0 | F15: 0 | G15: 0 | H15: 0 | I15: 0 | J15: 0 | K15: 0 | L15: 0 | M15: 0 | N15: =SUM(B15:M15) -> 0 | P15: =+SUMIFS(B15:M15,$B$2:$M$2,$V$3)/1000 -> 0 | Q15: =+SUMIFS(B15:M15,$B$1:$M$1,$W$3)/1000 -> 0
A16: Obsolete | N16: =SUM(B16:M16) -> 0 | P16: =+SUMIFS(B16:M16,$B$2:$M$2,$V$3)/1000 -> 0 | Q16: =+SUMIFS(B16:M16,$B$1:$M$1,$W$3)/1000 -> 0
A17: Depreciation | N17: =SUM(B17:M17) -> 0 | P17: =+SUMIFS(B17:M17,$B$2:$M$2,$V$3)/1000 -> 0 | Q17: =+SUMIFS(B17:M17,$B$1:$M$1,$W$3)/1000 -> 0
A18: FIXED CONVERSION | B18: =SUM(B11:B17) -> 1100 | C18: =SUM(C11:C17) -> 1100 | D18: =SUM(D11:D17) -> 1100 | E18: =SUM(E11:E17) -> 1100 | F18: =SUM(F11:F17) -> 1100 | G18: =SUM(G11:G17) -> 1100 | H18: =SUM(H11:H17) -> 1100 | I18: =SUM(I11:I17) -> 1100 | ... M18: =SUM(M11:M17) -> 1100 | N18: =SUM(B18:M18) -> 13200 | P18: =SUM(P11:P17) -> 1.1 | Q18: =SUM(Q11:Q17) -> 1.1
A19: OVH AND OTHERS | B19: 0 | C19: 0 | D19: 0 | E19: 0 | F19: 0 | G19: 0 | H19: 0 | I19: 0 | J19: 0 | K19: 0 | L19: 0 | M19: 0 | N19: =SUM(B19:M19) -> 0 | P19: =+SUMIFS(B19:M19,$B$2:$M$2,$V$3)/1000 -> 0 | Q19: =+SUMIFS(B19:M19,$B$1:$M$1,$W$3)/1000 -> 0
A20: Grand Total | B20: =SUM(B10,B18,B19) -> 6744.3971 | C20: =SUM(C10,C18,C19) -> 7110.6746 | D20: =SUM(D10,D18,D19) -> 7157.5234 | E20: =SUM(E10,E18,E19) -> 13784.256 | F20: =SUM(F10,F18,F19) -> 22499.89 | G20: =SUM(G10,G18,G19) -> 58908.533 | H20: =SUM(H10,H18,H19) -> 57523.255 | I20: =SUM(I10,I18,I19) -> 57204.808 | ... M20: =SUM(M10,M18,M19) -> 60138.509 | N20: =SUM(B20:M20) -> 484715.83 | P20: =P18+P10+P19 -> 6.7443971 | Q20: =Q18+Q10+Q19 -> 6.7443971
A23: F-Matrix Actual | B23: Jan | C23: Feb | D23: March | E23: April | F23: May | G23: June | H23: July | I23: August | J23: Sept | K23: Oct | L23: Nov | M23: Dec | N23: Total | P23: MTD | Q23: YTD
A24: Direct Labour | B24: 40450.38 | C24: 48560.941 | D24: 24543.182 | E24: 26853.444 | F24: 26083.254 | G24: 29086.995 | H24: 27265.034 | I24: 27115.925 | J24: 29457.764 | K24: 28696.971 | L24: 29000.118 | M24: 27498.863 | N24: =SUM(B24:M24) -> 364612.87 | P24: =+SUMIFS(B24:M24,$B$2:$M$2,$V$3)/1000 -> 40.45038 | Q24: =+SUMIFS(B24:M24,$B$1:$M$1,$W$3)/1000 -> 40.45038
A25: Variable Utilities | N25: =SUM(B25:M25) -> 0 | P25: =+SUMIFS(B25:M25,$B$2:$M$2,$V$3)/1000 -> 0 | Q25: =+SUMIFS(B25:M25,$B$1:$M$1,$W$3)/1000 -> 0
A26: Scrap | B26: 0 | C26: 0 | D26: 0 | E26: 0 | F26: 5251.9342 | G26: 8355.3499 | H26: 6472.9293 | I26: 6318.8726 | J26: 8738.4228 | K26: 7952.3833 | L26: 8265.5896 | M26: 6714.5183 | N26: =SUM(B26:M26) -> 58070 | P26: =+SUMIFS(B26:M26,$B$2:$M$2,$V$3)/1000 -> 0 | Q26: =+SUMIFS(B26:M26,$B$1:$M$1,$W$3)/1000 -> 0
A27: Scrap Reselling | N27: =SUM(B27:M27) -> 0 | P27: =+SUMIFS(B27:M27,$B$2:$M$2,$V$3)/1000 -> 0 | Q27: =+SUMIFS(B27:M27,$B$1:$M$1,$W$3)/1000 -> 0
A28: Variable Costs | B28: 1000 | C28: 1000 | D28: 1000 | E28: 1000 | F28: 1000 | G28: 1000 | H28: 1000 | I28: 1000 | J28: 1000 | K28: 1000 | L28: 1000 | M28: 1000 | N28: =SUM(B28:M28) -> 12000 | P28: =+SUMIFS(B28:M28,$B$2:$M$2,$V$3)/1000 -> 1 | Q28: =+SUMIFS(B28:M28,$B$1:$M$1,$W$3)/1000 -> 1
A29: VARIABLE CONVERSION | B29: =SUM(B24:B28) -> 41450.38 | C29: =SUM(C24:C28) -> 49560.941 | D29: =SUM(D24:D28) -> 25543.182 | E29: =SUM(E24:E28) -> 27853.444 | F29: =SUM(F24:F28) -> 32335.188 | G29: =SUM(G24:G28) -> 38442.345 | H29: =SUM(H24:H28) -> 34737.963 | I29: =SUM(I24:I28) -> 34434.797 | ... M29: =SUM(M24:M28) -> 35213.382 | N29: =SUM(B29:M29) -> 434682.87 | P29: =SUM(P24:P28) -> 41.45038 | Q29: =SUM(Q24:Q28) -> 41.45038
A30: Indirect Labour | B30: 0 | C30: 2240.8813 | D30: 2240.8813 | E30: 2240.8813 | F30: 2240.8813 | G30: 2240.8813 | H30: 2240.8813 | I30: 2240.8813 | J30: 2240.8813 | K30: 2240.8813 | L30: 2240.8813 | M30: 2240.8813 | N30: =SUM(B30:M30) -> 24649.694 | P30: =+SUMIFS(B30:M30,$B$2:$M$2,$V$3)/1000 -> 0 | Q30: =+SUMIFS(B30:M30,$B$1:$M$1,$W$3)/1000 -> 0
A31: Fixed Labour | N31: =SUM(B31:M31) -> 0 | P31: =+SUMIFS(B31:M31,$B$2:$M$2,$V$3)/1000 -> 0 | Q31: =+SUMIFS(B31:M31,$B$1:$M$1,$W$3)/1000 -> 0
A32: Semifixed | B32: 0 | C32: 211.30421 | D32: 211.30421 | E32: 211.30421 | F32: 211.30421 | G32: 211.30421 | H32: 845.21684 | I32: 845.21684 | J32: 845.21684 | K32: 845.21684 | L32: 845.21684 | M32: 845.21684 | N32: =SUM(B32:M32) -> 6127.8221 | P32: =+SUMIFS(B32:M32,$B$2:$M$2,$V$3)/1000 -> 0 | Q32: =+SUMIFS(B32:M32,$B$1:$M$1,$W$3)/1000 -> 0
A33: Fixed utilities | B33: 0 | C33: 0 | D33: 922.8 | E33: 922.8 | F33: 922.8 | G33: 922.8 | H33: 922.8 | I33: 922.8 | J33: 922.8 | K33: 922.8 | L33: 922.8 | M33: 922.8 | N33: =SUM(B33:M33) -> 9228 | P33: =+SUMIFS(B33:M33,$B$2:$M$2,$V$3)/1000 -> 0 | Q33: =+SUMIFS(B33:M33,$B$1:$M$1,$W$3)/1000 -> 0
A34: Fixed Cost | N34: =SUM(B34:M34) -> 0 | P34: =+SUMIFS(B34:M34,$B$2:$M$2,$V$3)/1000 -> 0 | Q34: =+SUMIFS(B34:M34,$B$1:$M$1,$W$3)/1000 -> 0
A35: Obsolete | N35: =SUM(B35:M35) -> 0 | P35: =+SUMIFS(B35:M35,$B$2:$M$2,$V$3)/1000 -> 0 | Q35: =+SUMIFS(B35:M35,$B$1:$M$1,$W$3)/1000 -> 0
A36: Depreciation | N36: =SUM(B36:M36) -> 0 | P36: =+SUMIFS(B36:M36,$B$2:$M$2,$V$3)/1000 -> 0 | Q36: =+SUMIFS(B36:M36,$B$1:$M$1,$W$3)/1000 -> 0
A37: FIXED CONVERSION | B37: =SUM(B30:B36) -> 0 | C37: =SUM(C30:C36) -> 2452.1855 | D37: =SUM(D30:D36) -> 3374.9855 | E37: =SUM(E30:E36) -> 3374.9855 | F37: =SUM(F30:F36) -> 3374.9855 | G37: =SUM(G30:G36) -> 3374.9855 | H37: =SUM(H30:H36) -> 4008.8981 | I37: =SUM(I30:I36) -> 4008.8981 | ... M37: =SUM(M30:M36) -> 4008.8981 | N37: =SUM(B37:M37) -> 40005.516 | P37: =SUM(P30:P36) -> 0 | Q37: =SUM(Q30:Q36) -> 0
A38: OVH AND OTHERS | N38: =SUM(B38:M38) -> 0 | P38: =+SUMIFS(B38:M38,$B$2:$M$2,$V$3)/1000 -> 0 | Q38: =+SUMIFS(B38:M38,$B$1:$M$1,$W$3)/1000 -> 0
A39: Grand Total | B39: =B29+B37+B38 -> 41450.38 | C39: =C29+C37+C38 -> 52013.126 | D39: =D29+D37+D38 -> 28918.168 | E39: =E29+E37+E38 -> 31228.429 | F39: =F29+F37+F38 -> 35710.174 | G39: =G29+G37+G38 -> 41817.33 | H39: =H29+H37+H38 -> 38746.861 | I39: =I29+I37+I38 -> 38443.695 | ... M39: =M29+M37+M38 -> 39222.28 | N39: =SUM(B39:M39) -> 474688.39 | P39: =P37+P29+P38 -> 41.45038 | Q39: =Q37+Q29+Q38 -> 41.45038
N40: =+N39-'ACE Details_FULL'!P42 -> -131622.82
A42: Over /Underabsorption | B42: Jan | C42: Feb | D42: March | E42: April | F42: May | G42: June | H42: July | I42: August | J42: Sept | K42: Oct | L42: Nov | M42: Dec | N42: Total | P42: MTD | Q42: YTD
A43: Direct Labour | B43: =B24-B5 -> 35805.983 | C43: =C24-C5 -> 43550.266 | D43: =D24-D5 -> 19485.659 | E43: =E24-E5 -> 21980.688 | F43: =F24-F5 -> 10702.364 | G43: =G24-G5 -> -20193.038 | H43: =H24-H5 -> -22063.721 | I43: =I24-I5 -> -22431.383 | ... M43: =M24-M5 -> -24969.396 | N43: =SUM(B43:M43) -> -36462.209 | P43: =+SUMIFS(B43:M43,$B$2:$M$2,$V$3)/1000 -> 35.805983 | Q43: =+SUMIFS(B43:M43,$B$1:$M$1,$W$3)/1000 -> 35.805983
A44: Variable Utilities | B44: =B25-B6 -> 0 | C44: =C25-C6 -> 0 | D44: =D25-D6 -> 0 | E44: =E25-E6 -> 0 | F44: =F25-F6 -> 0 | G44: =G25-G6 -> 0 | H44: =H25-H6 -> 0 | I44: =I25-I6 -> 0 | ... M44: =M25-M6 -> 0 | N44: =SUM(B44:M44) -> 0 | P44: =+SUMIFS(B44:M44,$B$2:$M$2,$V$3)/1000 -> 0 | Q44: =+SUMIFS(B44:M44,$B$1:$M$1,$W$3)/1000 -> 0
A45: Scrap | B45: =B26-B7 -> 0 | C45: =C26-C7 -> 0 | D45: =D26-D7 -> 0 | E45: =E26-E7 -> -6811.5 | F45: =F26-F7 -> 232.93421 | G45: =G26-G7 -> 826.84989 | H45: =H26-H7 -> 378.42934 | I45: =I26-I7 -> 761.37261 | ... M45: =M26-M7 -> 1144.2683 | N45: =SUM(B45:M45) -> -370.75 | P45: =+SUMIFS(B45:M45,$B$2:$M$2,$V$3)/1000 -> 0 | Q45: =+SUMIFS(B45:M45,$B$1:$M$1,$W$3)/1000 -> 0
A46: Scrap Reselling | B46: =B27-B8 -> 0 | C46: =C27-C8 -> 0 | D46: =D27-D8 -> 0 | E46: =E27-E8 -> 0 | F46: =F27-F8 -> 0 | G46: =G27-G8 -> 0 | H46: =H27-H8 -> 0 | I46: =I27-I8 -> 0 | ... M46: =M27-M8 -> 0 | N46: =SUM(B46:M46) -> 0 | P46: =+SUMIFS(B46:M46,$B$2:$M$2,$V$3)/1000 -> 0 | Q46: =+SUMIFS(B46:M46,$B$1:$M$1,$W$3)/1000 -> 0
A47: Variable Costs | B47: =B28-B9 -> 0 | C47: =C28-C9 -> 0 | D47: =D28-D9 -> 0 | E47: =E28-E9 -> 0 | F47: =F28-F9 -> 0 | G47: =G28-G9 -> 0 | H47: =H28-H9 -> 0 | I47: =I28-I9 -> 0 | ... M47: =M28-M9 -> 0 | N47: =SUM(B47:M47) -> 0 | P47: =+SUMIFS(B47:M47,$B$2:$M$2,$V$3)/1000 -> 0 | Q47: =+SUMIFS(B47:M47,$B$1:$M$1,$W$3)/1000 -> 0
A48: VARIABLE CONVERSION | B48: =SUM(B43:B47) -> 35805.983 | C48: =SUM(C43:C47) -> 43550.266 | D48: =SUM(D43:D47) -> 19485.659 | E48: =SUM(E43:E47) -> 15169.188 | F48: =SUM(F43:F47) -> 10935.299 | G48: =SUM(G43:G47) -> -19366.189 | H48: =SUM(H43:H47) -> -21685.292 | I48: =SUM(I43:I47) -> -21670.011 | ... M48: =SUM(M43:M47) -> -23825.127 | N48: =SUM(B48:M48) -> -36832.959 | P48: =SUM(P43:P47) -> 35.805983 | Q48: =SUM(Q43:Q47) -> 35.805983
A49: Indirect Labour | B49: =B30-B11 -> 0 | C49: =C30-C11 -> 2240.8813 | D49: =D30-D11 -> 2240.8813 | E49: =E30-E11 -> 2240.8813 | F49: =F30-F11 -> 2240.8813 | G49: =G30-G11 -> 2240.8813 | H49: =H30-H11 -> 2240.8813 | I49: =I30-I11 -> 2240.8813 | ... M49: =M30-M11 -> 2240.8813 | N49: =SUM(B49:M49) -> 24649.694 | P49: =+SUMIFS(B49:M49,$B$2:$M$2,$V$3)/1000 -> 0 | Q49: =+SUMIFS(B49:M49,$B$1:$M$1,$W$3)/1000 -> 0
A50: Fixed Labour | B50: =B31-B12 -> 0 | C50: =C31-C12 -> 0 | D50: =D31-D12 -> 0 | E50: =E31-E12 -> 0 | F50: =F31-F12 -> 0 | G50: =G31-G12 -> 0 | H50: =H31-H12 -> 0 | I50: =I31-I12 -> 0 | ... M50: =M31-M12 -> 0 | N50: =SUM(B50:M50) -> 0 | P50: =+SUMIFS(B50:M50,$B$2:$M$2,$V$3)/1000 -> 0 | Q50: =+SUMIFS(B50:M50,$B$1:$M$1,$W$3)/1000 -> 0
A51: Semifixed | B51: =B32-B13 -> 0 | C51: =C32-C13 -> 211.30421 | D51: =D32-D13 -> 211.30421 | E51: =E32-E13 -> 211.30421 | F51: =F32-F13 -> 211.30421 | G51: =G32-G13 -> 211.30421 | H51: =H32-H13 -> 845.21684 | I51: =I32-I13 -> 845.21684 | ... M51: =M32-M13 -> 845.21684 | N51: =SUM(B51:M51) -> 6127.8221 | P51: =+SUMIFS(B51:M51,$B$2:$M$2,$V$3)/1000 -> 0 | Q51: =+SUMIFS(B51:M51,$B$1:$M$1,$W$3)/1000 -> 0
A52: Fixed utilities | B52: =B33-B14 -> -1100 | C52: =C33-C14 -> -1100 | D52: =D33-D14 -> -177.2 | E52: =E33-E14 -> -177.2 | F52: =F33-F14 -> -177.2 | G52: =G33-G14 -> -177.2 | H52: =H33-H14 -> -177.2 | I52: =I33-I14 -> -177.2 | ... M52: =M33-M14 -> -177.2 | N52: =SUM(B52:M52) -> -3972 | P52: =+SUMIFS(B52:M52,$B$2:$M$2,$V$3)/1000 -> -1.1 | Q52: =+SUMIFS(B52:M52,$B$1:$M$1,$W$3)/1000 -> -1.1
A53: Fixed Cost | B53: =B34-B15 -> 0 | C53: =C34-C15 -> 0 | D53: =D34-D15 -> 0 | E53: =E34-E15 -> 0 | F53: =F34-F15 -> 0 | G53: =G34-G15 -> 0 | H53: =H34-H15 -> 0 | I53: =I34-I15 -> 0 | ... M53: =M34-M15 -> 0 | N53: =SUM(B53:M53) -> 0 | P53: =+SUMIFS(B53:M53,$B$2:$M$2,$V$3)/1000 -> 0 | Q53: =+SUMIFS(B53:M53,$B$1:$M$1,$W$3)/1000 -> 0
A54: Obsolete | B54: =B35-B16 -> 0 | C54: =C35-C16 -> 0 | D54: =D35-D16 -> 0 | E54: =E35-E16 -> 0 | F54: =F35-F16 -> 0 | G54: =G35-G16 -> 0 | H54: =H35-H16 -> 0 | I54: =I35-I16 -> 0 | ... M54: =M35-M16 -> 0 | N54: =SUM(B54:M54) -> 0 | P54: =+SUMIFS(B54:M54,$B$2:$M$2,$V$3)/1000 -> 0 | Q54: =+SUMIFS(B54:M54,$B$1:$M$1,$W$3)/1000 -> 0
A55: Depreciation | B55: =B36-B17 -> 0 | C55: =C36-C17 -> 0 | D55: =D36-D17 -> 0 | E55: =E36-E17 -> 0 | F55: =F36-F17 -> 0 | G55: =G36-G17 -> 0 | H55: =H36-H17 -> 0 | I55: =I36-I17 -> 0 | ... M55: =M36-M17 -> 0 | N55: =SUM(B55:M55) -> 0 | P55: =+SUMIFS(B55:M55,$B$2:$M$2,$V$3)/1000 -> 0 | Q55: =+SUMIFS(B55:M55,$B$1:$M$1,$W$3)/1000 -> 0
A56: FIXED CONVERSION | B56: =SUM(B49:B55) -> -1100 | C56: =SUM(C49:C55) -> 1352.1855 | D56: =SUM(D49:D55) -> 2274.9855 | E56: =SUM(E49:E55) -> 2274.9855 | F56: =SUM(F49:F55) -> 2274.9855 | G56: =SUM(G49:G55) -> 2274.9855 | H56: =SUM(H49:H55) -> 2908.8981 | I56: =SUM(I49:I55) -> 2908.8981 | ... M56: =SUM(M49:M55) -> 2908.8981 | N56: =SUM(B56:M56) -> 26805.516 | P56: =SUM(P49:P55) -> -1.1 | Q56: =SUM(Q49:Q55) -> -1.1
A57: OVH AND OTHERS | B57: =B38-B19 -> 0 | C57: =C38-C19 -> 0 | D57: =D38-D19 -> 0 | E57: =E38-E19 -> 0 | F57: =F38-F19 -> 0 | G57: =G38-G19 -> 0 | H57: =H38-H19 -> 0 | I57: =I38-I19 -> 0 | ... M57: =M38-M19 -> 0 | N57: =SUM(B57:M57) -> 0 | P57: =+SUMIFS(B57:M57,$B$2:$M$2,$V$3)/1000 -> 0 | Q57: =+SUMIFS(B57:M57,$B$1:$M$1,$W$3)/1000 -> 0
A58: Grand Total | B58: =B48+B56+B57 -> 34705.983 | C58: =C48+C56+C57 -> 44902.451 | D58: =D48+D56+D57 -> 21760.644 | E58: =E48+E56+E57 -> 17444.174 | F58: =F48+F56+F57 -> 13210.284 | G58: =G48+G56+G57 -> -17091.203 | H58: =H48+H56+H57 -> -18776.394 | I58: =I48+I56+I57 -> -18761.113 | ... M58: =M48+M56+M57 -> -20916.229 | N58: =SUM(B58:M58) -> -10027.443 | P58: =P56+P48+P57 -> 34.705983 | Q58: =Q56+Q48+Q57 -> 34.705983

Sheet VOLUME
B2: MTD | C2: Jan | D2: Feb | E2: Mar | F2: Apr | G2: May | H2: Jun | I2: Jul | J2: Aug | K2: Sep | L2: Oct | M2: Nov | N2: Dec | O2: Total
B3: Budget Volume | C3: 50463 | D3: 50446 | E3: 50447 | F3: 48050 | G3: 36788 | H3: 53265 | I3: 42049 | J3: 39150 | K3: 53732 | L3: 48548 | M3: 51408 | N3: 40676 | O3: =SUM(C3:N3) -> 565022
B5: STD Volume | C5: 46000 | D5: 46000 | E5: 46000 | F5: 48300 | G5: 32200 | H5: 71500 | I5: 57750 | J5: 52250 | K5: 71500 | L5: 71500 | M5: 68750 | N5: 62561 | O5: =SUM(C5:N5) -> 674311
B7: Actual Volume | C7: =+C10 -> 47357 | D7: =+D10 -> 42593.001 | E7: =+E10 -> 23002.001 | F7: =+F10 -> 44096 | G7: 36000 | H7: 54500.001 | I7: 41500 | J7: 39000.001 | K7: 54085 | L7: 49968 | M7: 51936 | N7: 42190 | O7: =SUM(C7:N7) -> 526227
B10: DW 2 | C10: =SUM(C11:C13) -> 47357 | D10: =SUM(D11:D13) -> 42593.001 | E10: =SUM(E11:E13) -> 23002.001 | F10: =SUM(F11:F13) -> 44096 | G10: 36000 | H10: 54500.001 | I10: 41500 | J10: 39000.001 | K10: 54085 | L10: 49968 | M10: 51936 | N10: 42190 | O10: =SUM(C10:N10) -> 526227
B11: FS | C11: 19805 | D11: 18495 | E11: 10482 | F11: 21500 | O11: =SUM(C11:N11) -> 70282
B12: BI | C12: 27552 | D12: 24098 | E12: 12520 | F12: 21500 | O12: =SUM(C12:N12) -> 85670
B13: KIT | D13: 0.001 | E13: 0.001 | F13: 1096 | O13: =SUM(C13:N13) -> 1096.002

Sheet HQD
A1: PERIMETER | B1: HQD REPORTING -EXCLUDED COST ITEMS | C1: IN | D1: OUT
A3: PERIMETER | B3: Direct Labor | C3: X
A4: PERIMETER | B4: Variable Utilities | C4: X
A5: PERIMETER | B5: Scrap | D5: X
A6: PERIMETER | B6: Scrap Reselling | D6: X
A7: PERIMETER | B7: Other Variable (Production Consumable, Inventory ADJ)
A8: PERIMETER | B8: Inventory Adjustment | D8: X
A9: PERIMETER | B9: Production Consummables | C9: X
A10: PERIMETER | B10: Variable Conv.
A11: PERIMETER | B11: Indirect Labour | C11: X
A12: PERIMETER | B12: Fixed Labour | C12: X
A13: PERIMETER | B13: Semifixed | C13: X
A14: PERIMETER | B14: Fixed utilities | C14: X
A15: PERIMETER | B15: Fixed Cost | C15: X
A16: PERIMETER | B16: IT LOCAL | C16: Should be under shares
A17: PERIMETER | B17: Security | C17: Should be under shares
A18: PERIMETER | B18: Obsolete | D18: X
A19: PERIMETER | B19: Depreciation | C19: X
A20: PERIMETER | B20: Fixed Conv.
A21: PERIMETER | B21: TOTAL MFG COST w/o SHARES
A22: PERIMETER | B22: TOTAL SHARES
A23: PERIMETER | B23: Mess Union Fee | C23: X | E23: Target'tan çıkarılırken bütçe değerleri alınabilir.
A24: PERIMETER | B24: IT LOCAL | C24: X | E24: Target'tan çıkarılırken bütçe değerleri alınabilir.
A25: PERIMETER | B25: Security | C25: X | E25: Target'tan çıkarılırken bütçe değerleri alınabilir.
A26: PERIMETER | B26: IT GLOBAL | D26: X
A27: PERIMETER | B27: G&A(Insurance included) | D27: X
A28: PERIMETER | B28: TOTAL MFG COST w/ SHARES
A29: PERIMETER | B29: Functional Currency Impact | C29: X
A32: OTHERS | B32: Scrap
A33: OTHERS | B33: Scrap Reselling
A34: OTHERS | B34: Inventory Adjustment
A35: OTHERS | B35: Obsolete
A36: OTHERS | B36: Asset Sales
A38: OVERHEAD | B38: IT GLOBAL
A39: OVERHEAD | B39: G&A(Insurance included)

Sheet >>>

Sheet MTD Report  (HQD) (deneme)
B2: TD MTD Oct | C2: Actual Cost | I2: GP | M2: TC ALL | N2: TC WO GP | O2: GP TC
M3: 38.12 | N3: 37.43 | O3: 49.19 | P3: =O3/M3-1 -> 0.29039874 | T3: HC | U3: Unit price TRY
C4: ='data entry '!Q115 -> 44096 | I4: 6565 | T4: =(G7+G11+G12) -> 48.06191
B5: - Gain / +Loss | S5: Working meal | T5: =T4 -> 48.06191 | U5: 165.3 | V5: =T5*U5 -> 7944.6338
C6: EUR/000 | D6: €/pc | F6: HC | G6: GP | I6: EUR/000 | J6: €/pc | S6: Transport | T6: =T5 -> 48.06191 | U6: 185.43 | V6: =T6*U6*2 -> 17824.24
A7: MFG PERIMETER | B7: Direct Labor | C7: 961.83748 | D7: 8.5640541 | F7: 447 | G7: 34 | I7: =C7/F7*G7 -> 73.159898 | J7: =I7/$I$4*1000 -> 11.14393 | M7: =J7/D7-1 -> 0.30124465 | V7: =SUM(V4:V6) -> 25768.874
A8: MFG PERIMETER | B8: Variable Utilities | C8: 63.35664 | D8: 0.56411785 | I8: =D8*$I$4/1000 -> 3.7034337 | J8: =I8/$I$4*1000 -> 0.56411785
A9: MFG PERIMETER | B9: Other Variable (Production Consumable) | C9: 41.55311 | D9: 0.36998255 | I9: =D9*$I$4/1000 -> 2.4289354 | J9: =I9/$I$4*1000 -> 0.36998255
A10: MFG PERIMETER | B10: Variable Conv. | C10: 1066.7472 | D10: 9.4981545 | I10: =SUM(I7:I9) -> 79.292267 | J10: =SUM(J7:J9) -> 12.07803
A11: MFG PERIMETER | B11: Indirect Labour | C11: 409.57862 | D11: 3.6468255 | F11: 157 | G11: =9 -> 9 | I11: =C11/F11*G11 -> 23.479029 | J11: =I11/$I$4*1000 -> 3.5763944 | K11: 4 | M11: =C11/F11*K11 -> 10.435124 | N11: =M11*1000/I4 -> 1.5895086 | O11: CKD Impact
A12: MFG PERIMETER | B12: Fixed Labour | C12: 105.67001 | D12: 0.94086964 | F12: 34 | G12: =F12/C4*I4 -> 5.0619104 | I12: =D12*I4/1000 -> 6.1768092 | J12: =I12/$I$4*1000 -> 0.94086964
A13: MFG PERIMETER | B13: Semifixed | C13: 191.79625 | D13: 1.7077245 | I13: =D13*I4/1000 -> 11.211212 | J13: =I13/$I$4*1000 -> 1.7077245
A14: MFG PERIMETER | B14: Fixed utilities | C14: 4.03094 | D14: 0.035890874 | I14: =D14*$I$4/1000 -> 0.23562359 | J14: =I14/$I$4*1000 -> 0.035890874
A15: MFG PERIMETER | B15: Fixed Cost | C15: 52.07714 | D15: 0.46368691 | I15: =D15*$I$4/1000 -> 3.0441045 | J15: =I15/$I$4*1000 -> 0.46368691
A16: MFG PERIMETER | B16: Depreciation | C16: 78.79631 | D16: 0.70159032 | I16: =D16*$I$4/1000 -> 4.6059404 | J16: =I16/$I$4*1000 -> 0.70159032
A17: MFG PERIMETER | B17: Fixed Conv. | C17: 841.94927 | D17: 7.4965878 | I17: =SUM(I11:I16) -> 48.752718 | J17: =SUM(J11:J16) -> 7.4261567
A18: MFG PERIMETER | B18: TOTAL MFG COST w/o SHARES | C18: 1908.6965 | D18: 16.994742 | I18: =I17+I10 -> 128.04499 | J18: =I18/$I$4*1000 -> 19.504187
A19: MFG PERIMETER | B19: TOTAL SHARES | C19: 16.80699 | D19: 0.14964687 | I19: =D19*$I$4/1000 -> 0.98243172 | J19: =I19/$I$4*1000 -> 0.14964687
A20: MFG PERIMETER | B20: TOTAL MFG COST w/ SHARES | C20: 1925.5035 | D20: 17.144389 | I20: =I19+I18 -> 129.02742 | J20: =I20/$I$4*1000 -> 19.653834
A21: MFG PERIMETER | B21: Functional Currency Impact | C21: 263.21196 | D21: 2.3435991 | I21: =D21*$I$4/1000 -> 15.385728 | J21: =I21/$I$4*1000 -> 2.3435991
A22: MFG PERIMETER | B22: TOTAL Including FC | C22: 2188.7155 | D22: 19.487988 | I22: =I21+I20 -> 144.41315 | J22: =I22/$I$4*1000 -> 21.997433 | M22: =J22/D22-1 -> 0.12876878
J23: =I23/$I$4*1000 -> 0
A24: OTHERS | B24: Scrap | C24: 43.39548 | D24: 0.38638673 | J24: =I24/$I$4*1000 -> 0
A25: OTHERS | B25: Scrap Reselling | C25: -128.11905 | D25: -1.1407525 | J25: =I25/$I$4*1000 -> 0
A26: OTHERS | B26: Other Variable (Inventory Adj) | C26: 11.52424 | D26: 0.10261007 | J26: =I26/$I$4*1000 -> 0
A27: OTHERS | B27: Obsolete | C27: 25 | D27: 0.22259618 | J27: =I27/$I$4*1000 -> 0
A28: OTHERS | B28: Asset Sales | C28: 0 | D28: 0 | J28: =I28/$I$4*1000 -> 0
A29: OTHERS | B29: TOTAL OTHERS | C29: -48.19933 | D29: -0.42915948 | J29: =I29/$I$4*1000 -> 0
J30: =I30/$I$4*1000 -> 0
A31: OVERHEAD | B31: IT GLOBAL | C31: 213.47408 | D31: 1.9007406 | J31: =I31/$I$4*1000 -> 0
A32: OVERHEAD | B32: G&A(Insurance included) | C32: 93.09748 | D32: 0.82892575 | J32: =I32/$I$4*1000 -> 0
A33: OVERHEAD | B33: TOTAL OVERHEAD | C33: 306.57156 | D33: 2.7296664 | J33: =I33/$I$4*1000 -> 0
J34: =I34/$I$4*1000 -> 0
A35: ALL | B35: TOTAL ALL | C35: 2447.0877 | D35: 21.788495 | J35: =I35/$I$4*1000 -> 0
A37: Check | C37: 0 | D37: 0

Sheet MTD Report  (HQD)
B2: DW MTD JAN | C2: Budget25 | F2: Actual Cost | I2: 1+11 Forecast | L2: Delta FCST vs ACT
C4: =+'MTD Report(HQD)_variance'!B4 -> 48050 | F4: =+'MTD Report(HQD)_variance'!Q4 -> 44096
B5: - Gain / +Loss
C6: EUR/000 | D6: €/pc | F6: EUR/000 | G6: €/pc | I6: EUR/000 | J6: €/pc
A7: MFG PERIMETER | B7: Direct Labor | C7: =+'MTD Report(HQD)_variance'!B7 -> 509 | D7: =+C7*1000/$C$4 -> 10.593132 | F7: =+'MTD Report(HQD)_variance'!Q7 -> 363.73443 | G7: =+F7*1000/$F$4 -> 8.2486945
A8: MFG PERIMETER | B8: Variable Utilities | C8: =+'MTD Report(HQD)_variance'!B8 -> 35.733562 | D8: =+C8*1000/$C$4 -> 0.74367454 | F8: =+'MTD Report(HQD)_variance'!Q8 -> 28.06842 | G8: =+F8*1000/$F$4 -> 0.63652984
A9: MFG PERIMETER | B9: Other Variable (Production Consumable) | C9: =+'MTD Report(HQD)_variance'!B9 -> 15.8935 | D9: =+C9*1000/$C$4 -> 0.33077003 | F9: =+'MTD Report(HQD)_variance'!Q9 -> 38.19678 | G9: =+F9*1000/$F$4 -> 0.8662187
A10: MFG PERIMETER | B10: Variable Conv. | C10: =+'MTD Report(HQD)_variance'!B10 -> 560.62706 | D10: =+C10*1000/$C$4 -> 11.667577 | F10: =+'MTD Report(HQD)_variance'!Q10 -> 429.99963 | G10: =+F10*1000/$F$4 -> 9.751443
A11: MFG PERIMETER | B11: Indirect Labour | C11: =+'MTD Report(HQD)_variance'!B11 -> 204.69927 | D11: =+C11*1000/$C$4 -> 4.2601306 | F11: =+'MTD Report(HQD)_variance'!Q11 -> 211.92001 | G11: =+F11*1000/$F$4 -> 4.8058783
A12: MFG PERIMETER | B12: Fixed Labour | C12: =+'MTD Report(HQD)_variance'!B12 -> 104.32865 | D12: =+C12*1000/$C$4 -> 2.1712517 | F12: =+'MTD Report(HQD)_variance'!Q12 -> 86.26424 | G12: =+F12*1000/$F$4 -> 1.9562827
A13: MFG PERIMETER | B13: Semifixed | C13: =+'MTD Report(HQD)_variance'!B13 -> 177.19911 | D13: =+C13*1000/$C$4 -> 3.6878066 | F13: =+'MTD Report(HQD)_variance'!Q13 -> 86.23783 | G13: =+F13*1000/$F$4 -> 1.9556837
A14: MFG PERIMETER | B14: Fixed utilities | C14: =+'MTD Report(HQD)_variance'!B14 -> 5 | D14: =+C14*1000/$C$4 -> 0.10405827 | F14: =+'MTD Report(HQD)_variance'!Q14 -> 3.80533 | G14: =+F14*1000/$F$4 -> 0.086296489
A15: MFG PERIMETER | B15: Fixed Cost | C15: =+'MTD Report(HQD)_variance'!B15 -> 43.218668 | D15: =+C15*1000/$C$4 -> 0.899452 | F15: =+'MTD Report(HQD)_variance'!Q15 -> -2.69822 | G15: =+F15*1000/$F$4 -> -0.061189677
A16: MFG PERIMETER | B16: Depreciation | C16: =+'MTD Report(HQD)_variance'!B16 -> 155.0923 | D16: =+C16*1000/$C$4 -> 3.2277274 | F16: =+'MTD Report(HQD)_variance'!Q16 -> -7.09792 | G16: =+F16*1000/$F$4 -> -0.16096517
A17: MFG PERIMETER | B17: Fixed Conv. | C17: =+'MTD Report(HQD)_variance'!B17 -> 689.538 | D17: =+C17*1000/$C$4 -> 14.350427 | F17: =+'MTD Report(HQD)_variance'!Q17 -> 378.43127 | G17: =+F17*1000/$F$4 -> 8.5819863
A18: MFG PERIMETER | B18: TOTAL MFG COST w/o SHARES | C18: =+'MTD Report(HQD)_variance'!B18 -> 1250.1651 | D18: =+C18*1000/$C$4 -> 26.018003 | F18: =+'MTD Report(HQD)_variance'!Q18 -> 808.4309 | G18: =+F18*1000/$F$4 -> 18.333429
... A20: MFG PERIMETER | B20: TOTAL MFG COST w/ SHARES | C20: =+'MTD Report(HQD)_variance'!B20 -> 1270.7321 | D20: =+C20*1000/$C$4 -> 26.446038 | F20: =+'MTD Report(HQD)_variance'!Q20 -> 821.47837 | G20: =+F20*1000/$F$4 -> 18.629317
A21: MFG PERIMETER | B21: Functional Currency Impact | C21: =+'MTD Report(HQD)_variance'!B22 -> 413.13905 | D21: =+C21*1000/$C$4 -> 8.5981072 | F21: =+'YTD Report(HQD)_variance '!Q22 -> 3696.26 | G21: =+F21*1000/$F$4 -> 83.823022
A22: MFG PERIMETER | B22: TOTAL Including FC | C22: =+C21+C20 -> 1683.8712 | D22: =+C22*1000/$C$4 -> 35.044145 | F22: =+F21+F20 -> 4517.7383 | G22: =+F22*1000/$F$4 -> 102.45234
A24: OTHERS | B24: Scrap | C24: =+'MTD Report(HQD)_variance'!B25 -> 19 | D24: =+C24*1000/$C$4 -> 0.39542144 | F24: =+'MTD Report(HQD)_variance'!Q25 -> 50.45741 | G24: =+F24*1000/$F$4 -> 1.1442627
A25: OTHERS | B25: Scrap Reselling | C25: =+'MTD Report(HQD)_variance'!B26 -> -48 | D25: =+C25*1000/$C$4 -> -0.99895942 | F25: =+'MTD Report(HQD)_variance'!Q26 -> -53.89348 | G25: =+F25*1000/$F$4 -> -1.2221852
A26: OTHERS | B26: Other Variable (Inventory Adj) | C26: =+'MTD Report(HQD)_variance'!B27 -> 0 | D26: =+C26*1000/$C$4 -> 0 | F26: =+'MTD Report(HQD)_variance'!Q27 -> 65.57718 | G26: =+F26*1000/$F$4 -> 1.4871458
A27: OTHERS | B27: Obsolete | C27: =+'MTD Report(HQD)_variance'!B28 -> 9 | D27: =+C27*1000/$C$4 -> 0.18730489 | F27: =+'MTD Report(HQD)_variance'!Q28 -> -177.1679 | G27: =+F27*1000/$F$4 -> -4.0177771
A28: OTHERS | B28: Asset Sales | C28: =+'MTD Report(HQD)_variance'!B29 -> 0 | D28: =+C28*1000/$C$4 -> 0 | F28: =+'MTD Report(HQD)_variance'!Q29 -> 0 | G28: =+F28*1000/$F$4 -> 0
A29: OTHERS | B29: TOTAL OTHERS | C29: =+'MTD Report(HQD)_variance'!B30 -> -20 | D29: =+C29*1000/$C$4 -> -0.41623309 | F29: =+'MTD Report(HQD)_variance'!Q30 -> -115.02679 | G29: =+F29*1000/$F$4 -> -2.6085538
A31: OVERHEAD | B31: IT GLOBAL | C31: =+'MTD Report(HQD)_variance'!B32 -> 90.697223 | D31: =+C31*1000/$C$4 -> 1.8875593 | F31: =+'MTD Report(HQD)_variance'!Q32 -> 89.41512 | G31: =+F31*1000/$F$4 -> 2.0277377
A32: OVERHEAD | B32: G&A(Insurance included) | C32: =+'MTD Report(HQD)_variance'!B33 -> 94.532002 | D32: =+C32*1000/$C$4 -> 1.9673674 | F32: =+'MTD Report(HQD)_variance'!Q33 -> 68.80723 | G32: =+F32*1000/$F$4 -> 1.5603962
A33: OVERHEAD | B33: TOTAL OVERHEAD | C33: =SUM(C31:C32) -> 185.22922 | D33: =+C33*1000/$C$4 -> 3.8549266 | F33: =SUM(F31:F32) -> 158.22235 | G33: =+F33*1000/$F$4 -> 3.5881338
A35: ALL | B35: TOTAL ALL | C35: =+C33+C29+C22 -> 1849.1004 | D35: =+C35*1000/$C$4 -> 38.482838 | F35: =+F33+F29+F22 -> 4560.9339 | G35: =+F35*1000/$F$4 -> 103.43192
A37: Check
G40: =G35-G21 -> 19.608897
F42: ASP DEC | G42: 175.20902
F43: MFG RATE | G43: =G20/G42 -> 0.10632625
G44: =G22/G42 -> 0.58474352

Sheet MTD VAR 
A1: Volume | B1: =+'Budget assumption'!Q35 -> 46000 | C1: =H1-B1 -> 4463 | H1: ='Budget assumption'!Q66 -> 50463 | I1: ='Budget assumption'!Q321 -> 0 | K1: ='data entry '!Q82 -> 44096 | M1: ='data entry '!Q115 -> 44096 | AA1: EFF | AB1: variable cost | AC1: Actual minus Copertura
B2: EUR | C2: EUR | H2: EUR | I2: EUR | K2: EUR | M2: EUR | Q2: Variances vs Budget | V2: Variances vs STD | AB2: fixed cost | AC2: Actual minus Budget
A3: Cost Elements | B3: STD | C3: Delta Volume | D3: ACE | E3: HW / TW | F3: Price FX | G3: Seasonality | H3: Plan Costs | I3: Budget VAR | K3: Copertura | M3: Act. Costs | O3: Variance vs STD | Q3: EFF | R3: FCA | S3: Total Variance | V3: EFF | W3: FCA | X3: Total Variance
D4: ACE
I5: FCA
A6: Direct Labour | B6: ='Budget assumption'!Q37 -> 523.40092 | C6: ='Budget assumption'!Q70 -> 50.781268 | D6: ='Budget assumption'!Q118 -> -4.6443971 | E6: ='Budget assumption'!Q149 -> -36.708483 | F6: ='Budget assumption'!Q180 -> -13.073388 | G6: ='Budget assumption'!Q242+'Budget assumption'!Q273 -> -34.755923 | H6: ='Budget assumption'!Q211 -> 485 | J6: =H6-SUM(B6:G6) -> 0 | K6: ='data entry '!Q84 -> 465.28736 | M6: ='data entry '!Q117 -> 363.73443 | O6: =M6-K6 -> -101.55293 | Q6: =M6-K6-E6-F6-D6-G6 -> -12.370737 | S6: =Q6+R6 -> -12.370737 | V6: =M6-K6 -> -101.55293 | X6: =V6+W6 -> -101.55293
A7: Variable Utilities | B7: ='Budget assumption'!Q38 -> 35.473246 | C7: ='Budget assumption'!Q71 -> 3.441676 | D7: ='Budget assumption'!Q119 -> 0 | E7: ='Budget assumption'!Q150 -> 0 | F7: ='Budget assumption'!Q181 -> -1.9248994 | G7: ='Budget assumption'!Q243+'Budget assumption'!Q274 -> 1.526754 | H7: ='Budget assumption'!Q212 -> 38.516777 | J7: =H7-SUM(B7:G7) -> 0 | K7: ='data entry '!Q85 -> 30.915274 | M7: ='data entry '!Q118 -> 28.06842 | O7: =M7-K7 -> -2.8468537 | Q7: =M7-K7-E7-F7-D7-G7 -> -2.4487083 | S7: =Q7+R7 -> -2.4487083 | V7: =M7-K7 -> -2.8468537 | X7: =V7+W7 -> -2.8468537
A8: Variable Costs | B8: ='Budget assumption'!Q39 -> 16.169661 | C8: ='Budget assumption'!Q72 -> 1.5688086 | D8: ='Budget assumption'!Q120 -> -1 | E8: ='Budget assumption'!Q151 -> 0 | F8: ='Budget assumption'!Q182 -> -0.0088085913 | G8: ='Budget assumption'!Q244+'Budget assumption'!Q275 -> 0.00033941312 | H8: ='Budget assumption'!Q213 -> 16.73 | J8: =H8-SUM(B8:G8) -> 0 | K8: ='data entry '!Q86 -> 13.272976 | M8: ='data entry '!Q119 -> 38.19678 | O8: =M8-K8 -> 24.923804 | Q8: =M8-K8-E8-F8-D8-G8 -> 25.932273 | S8: =Q8+R8 -> 25.932273 | V8: =M8-K8 -> 24.923804 | X8: =V8+W8 -> 24.923804
A9: VARIABLE CONVERSION | B9: =SUM(B6:B8) -> 575.04383 | C9: =SUM(C6:C8) -> 55.791752 | D9: =SUM(D6:D8) -> -5.6443971 | E9: =SUM(E6:E8) -> -36.708483 | F9: =SUM(F6:F8) -> -15.007095 | G9: =SUM(G6:G8) -> -33.22883 | H9: =SUM(H6:H8) -> 540.24678 | I9: =SUM(I6:I8) -> 0 | J9: =H9-SUM(B9:G9) -> 0 | K9: =SUM(K6:K8) -> 509.47561 | M9: =SUM(M6:M8) -> 429.99963 | O9: =SUM(O6:O8) -> -79.475978 | Q9: =SUM(Q6:Q8) -> 11.112828 | R9: =SUM(R6:R8) -> 0 | S9: =SUM(S6:S8) -> 11.112828 | V9: =SUM(V6:V8) -> -79.475978 | W9: =SUM(W6:W8) -> 0 | X9: =SUM(X6:X8) -> -79.475978
A10: Indirect Labour | B10: ='Budget assumption'!Q41 -> 205.29186 | D10: ='Budget assumption'!Q122 -> 0 | E10: ='Budget assumption'!Q153 -> -42 | F10: ='Budget assumption'!Q184 -> 36.808953 | G10: ='Budget assumption'!Q246+'Budget assumption'!Q277 -> -5.3518609 | H10: ='Budget assumption'!Q215 -> 194.74895 | I10: ='Budget assumption'!Q323 -> -19.917773 | J10: =H10-SUM(B10:G10) -> 0 | K10: ='data entry '!Q88 -> 184.03658 | M10: ='data entry '!Q121 -> 211.92001 | O10: =M10-K10 -> 27.883431 | Q10: =M10-H10 -> 17.171054 | R10: =H10-K10-E10-I10-F10-G10-D10 -> 41.173058 | S10: =Q10+R10 -> 58.344112 | V10: =M10-B10 -> 6.6281465 | W10: =B10-K10 -> 21.255285 | X10: =V10+W10 -> 27.883431
A11: Fixed Labour | B11: ='Budget assumption'!Q42 -> 74.257783 | D11: ='Budget assumption'!Q123 -> 0 | E11: ='Budget assumption'!Q154 -> 7 | F11: ='Budget assumption'!Q185 -> 16.249995 | G11: ='Budget assumption'!Q247+'Budget assumption'!Q278 -> 9.0722169 | H11: ='Budget assumption'!Q216 -> 106.58 | I11: ='Budget assumption'!Q324 -> -7.2046193 | J11: =H11-SUM(B11:G11) -> 0 | K11: ='data entry '!Q89 -> 65.067655 | M11: ='data entry '!Q122 -> 86.26424 | O11: =M11-K11 -> 21.196585 | Q11: =M11-H11 -> -20.315755 | R11: =H11-K11-E11-I11-F11-G11-D11 -> 16.394747 | S11: =Q11+R11 -> -3.9210082 | V11: =M11-B11 -> 12.006457 | W11: =B11-K11 -> 9.1901279 | X11: =V11+W11 -> 21.196585
A12: Semifixed | B12: ='Budget assumption'!Q43 -> 143.36581 | D12: ='Budget assumption'!Q124 -> 0 | E12: ='Budget assumption'!Q155 -> -13.179534 | F12: ='Budget assumption'!Q186 -> 45.529224 | G12: ='Budget assumption'!Q248+'Budget assumption'!Q279 -> 7.314194 | H12: ='Budget assumption'!Q217 -> 183.02969 | I12: ='Budget assumption'!Q325 -> -13.9096 | J12: =H12-SUM(B12:G12) -> 0 | K12: ='data entry '!Q90 -> 126.16662 | M12: ='data entry '!Q123 -> 86.23783 | O12: =M12-K12 -> -39.928792 | Q12: =M12-H12 -> -96.791861 | R12: =H12-K12-E12-I12-F12-G12-D12 -> 31.108784 | S12: =Q12+R12 -> -65.683076 | V12: =M12-B12 -> -57.127976 | W12: =B12-K12 -> 17.199184 | X12: =V12+W12 -> -39.928792
A13: Fixed utilities | B13: ='Budget assumption'!Q44 -> 9.1207173 | D13: ='Budget assumption'!Q125 -> -1.1 | E13: ='Budget assumption'!Q156 -> -2 | F13: ='Budget assumption'!Q187 -> -0.6 | G13: ='Budget assumption'!Q249+'Budget assumption'!Q280 -> -0.4207173 | H13: ='Budget assumption'!Q218 -> 5 | I13: ='Budget assumption'!Q326 -> -0.88490785 | J13: =H13-SUM(B13:G13) -> 0 | K13: ='data entry '!Q91 -> 6.95061 | M13: ='data entry '!Q124 -> 3.80533 | O13: =M13-K13 -> -3.14528 | Q13: =M13-H13 -> -1.19467 | R13: =H13-K13-E13-I13-F13-G13-D13 -> 3.0550151 | S13: =Q13+R13 -> 1.8603451 | V13: =M13-B13 -> -5.3153873 | W13: =B13-K13 -> 2.1701073 | X13: =V13+W13 -> -3.14528
A14: Fixed Cost | B14: ='Budget assumption'!Q45 -> 32.000366 | D14: ='Budget assumption'!Q126 -> 0 | E14: ='Budget assumption'!Q157 -> 0 | F14: ='Budget assumption'!Q188 -> 5.7693193 | G14: ='Budget assumption'!Q250+'Budget assumption'!Q281 -> 7.0905739 | H14: ='Budget assumption'!Q219 -> 44.860259 | I14: ='Budget assumption'!Q327 -> -3.1047312 | J14: =H14-SUM(B14:G14) -> 0 | K14: ='data entry '!Q92 -> 32.152644 | M14: ='data entry '!Q125 -> -2.69822 | O14: =M14-K14 -> -34.850864 | Q14: =M14-H14 -> -47.558479 | R14: =H14-K14-E14-I14-F14-G14-D14 -> 2.9524536 | S14: =Q14+R14 -> -44.606026 | V14: =M14-B14 -> -34.698586 | W14: =B14-K14 -> -0.15227756 | X14: =V14+W14 -> -34.850864
A15: Depreciation | B15: ='Budget assumption'!Q46 -> 125.28658 | D15: ='Budget assumption'!Q127 -> 0 | E15: ='Budget assumption'!Q158 -> -5.7388242 | F15: ='Budget assumption'!Q189 -> -0.0008 | G15: ='Budget assumption'!Q251+'Budget assumption'!Q282 -> 42.244789 | H15: ='Budget assumption'!Q220 -> 161.79174 | I15: ='Budget assumption'!Q329 -> -12.155522 | J15: =H15-SUM(B15:G15) -> 0 | K15: ='data entry '!Q93 -> 424.54616 | M15: ='data entry '!Q126 -> -7.09792 | O15: =M15-K15 -> -431.64408 | Q15: =M15-H15 -> -168.88966 | R15: =H15-K15-E15-I15-F15-G15-D15 -> -287.10406 | S15: =Q15+R15 -> -455.99373 | V15: =M15-B15 -> -132.3845 | W15: =B15-K15 -> -299.25959 | X15: =V15+W15 -> -431.64408
A16: FIXED CONVERSION | B16: =SUM(B10:B15) -> 589.32311 | C16: =SUM(C10:C15) -> 0 | D16: =SUM(D10:D15) -> -1.1 | E16: =SUM(E10:E15) -> -55.918358 | F16: =SUM(F10:F15) -> 103.75669 | G16: =SUM(G10:G15) -> 59.949196 | H16: =SUM(H10:H15) -> 696.01064 | I16: =SUM(I10:I15) -> -57.177153 | J16: =H16-SUM(B16:G16) -> 0 | K16: =SUM(K10:K15) -> 838.92027 | M16: =SUM(M10:M15) -> 378.43127 | O16: =SUM(O10:O15) -> -460.489 | Q16: =SUM(Q10:Q15) -> -317.57937 | R16: =SUM(R10:R15) -> -192.42001 | S16: =Q16+R16 -> -509.99938 | V16: =SUM(V10:V15) -> -210.89184 | W16: =SUM(W10:W15) -> -249.59716 | X16: =SUM(X10:X15) -> -460.489
A17: TOTAL MFG COST w/o SHARES | B17: =B9+B16 -> 1164.3669 | C17: =C9+C16 -> 55.791752 | D17: =D9+D16 -> -6.7443971 | E17: =E9+E16 -> -92.626841 | F17: =F9+F16 -> 88.749597 | G17: =G9+G16 -> 26.720366 | H17: =H9+H16 -> 1236.2574 | I17: =I9+I16 -> -57.177153 | J17: =H17-SUM(B17:G17) -> 0 | K17: =K9+K16 -> 1348.3959 | M17: =M9+M16 -> 808.4309 | O17: =M17-K17 -> -539.96498 | Q17: =Q9+Q16 -> -306.46655 | R17: =R9+R16 -> -192.42001 | S17: =Q17+R17 -> -498.88655 | V17: =V9+V16 -> -290.36782 | W17: =W9+W16 -> -249.59716 | X17: =X9+X16 -> -539.96498
A18: TOTAL SHARES | B18: ='Budget assumption'!Q49 -> 8.2249305 | D18: ='Budget assumption'!Q130 -> 0 | E18: ='Budget assumption'!Q161 -> 0 | F18: ='Budget assumption'!Q192 -> 10.41394 | G18: ='Budget assumption'!Q254+'Budget assumption'!Q285 -> 2.4941295 | H18: ='Budget assumption'!Q223 -> 21.133 | I18: ='Budget assumption'!V49 -> 0 | J18: =H18-SUM(B18:G18) -> 0 | K18: ='data entry '!Q96 -> 0 | M18: ='data entry '!Q129 -> 13.04747 | O18: =M18-K18 -> 13.04747 | Q18: =M18-H18 -> -8.0855299 | R18: =H18-K18-E18-I18-F18-G18-D18 -> 8.2249305 | S18: =Q18+R18 -> 0.13940057 | V18: =M18-B18 -> 4.8225395 | W18: =B18-K18 -> 8.2249305 | X18: =V18+W18 -> 13.04747
A19: TOTAL MFG COST w/ SHARES | B19: =B17+B18 -> 1172.5919 | C19: =C17+C18 -> 55.791752 | D19: =D17+D18 -> -6.7443971 | E19: =E17+E18 -> -92.626841 | F19: =F17+F18 -> 99.163537 | G19: =G17+G18 -> 29.214495 | H19: =H17+H18 -> 1257.3904 | I19: =I17+I18 -> -57.177153 | J19: =H19-SUM(B19:G19) -> 0 | K19: =K17+K18 -> 1348.3959 | M19: =M17+M18 -> 821.47837 | O19: =O17+O18 -> -526.91751 | Q19: =Q17+Q18 -> -314.55208 | R19: =R17+R18 -> -184.19508 | S19: =Q19+R19 -> -498.74715 | V19: =V17+V18 -> -285.54528 | W19: =W17+W18 -> -241.37223 | X19: =X17+X18 -> -526.91751
A20: Functional Currency Impact | B20: ='Budget assumption'!Q51 -> 344.37647 | D20: ='Budget assumption'!Q132 -> 0 | E20: ='Budget assumption'!Q163 -> 0 | F20: ='Budget assumption'!Q194 -> 0 | G20: ='Budget assumption'!Q256+'Budget assumption'!Q287 -> 71.312162 | H20: ='Budget assumption'!Q225 -> 415.68863 | I20: ='Budget assumption'!V51 -> 0 | J20: =H20-SUM(B20:G20) -> 0 | K20: ='data entry '!Q98 -> 0 | M20: ='data entry '!Q131 -> 36.99522 | O20: =M20-K20 -> 36.99522 | Q20: =M20-H20 -> -378.69341 | R20: =H20-K20-E20-I20-F20-G20-D20 -> 344.37647 | S20: =Q20+R20 -> -34.316942 | V20: =M20-B20 -> -307.38125 | W20: =B20-K20 -> 344.37647 | X20: =V20+W20 -> 36.99522
A21: TOTAL Including FC | B21: =B19+B20 -> 1516.9683 | C21: =C19+C20 -> 55.791752 | D21: =D19+D20 -> -6.7443971 | E21: =E19+E20 -> -92.626841 | F21: =F19+F20 -> 99.163537 | G21: =G19+G20 -> 100.52666 | H21: =H19+H20 -> 1673.0791 | I21: =I19+I20 -> -57.177153 | J21: =H21-SUM(B21:G21) -> 0 | K21: =K19+K20 -> 1348.3959 | M21: =M19+M20 -> 858.47359 | O21: =M21-K21 -> -489.92229 | Q21: =Q19+Q20 -> -693.24549 | R21: =R19+R20 -> 160.1814 | S21: =Q21+R21 -> -533.06409 | V21: =V19+V20 -> -592.92653 | W21: =W19+W20 -> 103.00424 | X21: =X19+X20 -> -489.92229
A22: Scrap | B22: ='Budget assumption'!Q53 -> 23.02009 | C22: ='Budget assumption'!Q74 -> 2.2334492 | D22: ='Budget assumption'!Q134 -> 0 | E22: ='Budget assumption'!Q165 -> 0 | F22: ='Budget assumption'!Q196 -> 1.7464607 | G22: ='Budget assumption'!Q258+'Budget assumption'!Q289 -> 0 | H22: ='Budget assumption'!Q227 -> 27 | J22: =H22-SUM(B22:G22) -> 0 | K22: ='data entry '!Q100 -> 19.811558 | M22: ='data entry '!Q133 -> 50.45741 | O22: =M22-K22 -> 30.645852 | Q22: =M22-K22-E22-F22-D22-G22 -> 28.899391 | S22: =Q22+R22 -> 28.899391 | V22: =M22-K22 -> 30.645852 | X22: =V22+W22 -> 30.645852
A23: Scrap Reselling | B23: ='Budget assumption'!Q54 -> -56.58 | C23: ='Budget assumption'!Q75 -> -5.48949 | D23: ='Budget assumption'!Q135 -> 0 | E23: ='Budget assumption'!Q166 -> 0 | F23: ='Budget assumption'!Q197 -> 7.06949 | G23: ='Budget assumption'!Q259+'Budget assumption'!Q290 -> 0 | H23: ='Budget assumption'!Q228 -> -55 | J23: =H23-SUM(B23:G23) -> 0 | K23: ='data entry '!Q101 -> -48.888273 | M23: ='data entry '!Q134 -> -53.89348 | O23: =M23-K23 -> -5.0052074 | Q23: =M23-K23-E23-F23-D23-G23 -> -12.074697 | S23: =Q23+R23 -> -12.074697 | V23: =M23-K23 -> -5.0052074 | X23: =V23+W23 -> -5.0052074
A24: Other Variable (Inventory Adj) | B24: ='Budget assumption'!Q55 -> 0 | C24: ='Budget assumption'!Q76+'Budget assumption'!Q291 -> 0 | D24: ='Budget assumption'!Q136 -> 0 | E24: ='Budget assumption'!Q167 -> 0 | F24: ='Budget assumption'!Q198 -> 0 | G24: ='Budget assumption'!Q260+'Budget assumption'!Q291 -> 0 | H24: ='Budget assumption'!Q229 -> 0 | J24: =H24-SUM(B24:G24) -> 0 | K24: ='data entry '!Q102 -> 0 | M24: ='data entry '!Q135 -> 65.57718 | O24: =M24-K24 -> 65.57718 | Q24: =M24-K24-E24-F24-D24-G24 -> 65.57718 | S24: =Q24+R24 -> 65.57718 | V24: =M24-K24 -> 65.57718 | X24: =V24+W24 -> 65.57718
A25: Obsolete | B25: ='Budget assumption'!Q56 -> 0 | C25: ='Budget assumption'!Q77+'Budget assumption'!Q292 -> 0 | D25: ='Budget assumption'!Q137 -> 0 | E25: ='Budget assumption'!Q168 -> 8.3333333 | F25: ='Budget assumption'!Q199 -> 0.66666667 | G25: ='Budget assumption'!Q261+'Budget assumption'!Q292 -> 0 | H25: ='Budget assumption'!Q230 -> 9 | J25: =H25-SUM(B25:G25) -> 0 | K25: ='data entry '!Q103 -> 0 | M25: ='data entry '!Q136 -> -177.1679 | O25: =M25-K25 -> -177.1679 | Q25: =M25-H25 -> -186.1679 | R25: =H25-K25-E25-I25-F25-G25-D25 -> 0 | S25: =Q25+R25 -> -186.1679 | V25: =M25-B25 -> -177.1679 | W25: =B25-K25 -> 0 | X25: =V25+W25 -> -177.1679
A26: Asset Sales | B26: ='Budget assumption'!Q57 -> 0 | C26: ='Budget assumption'!Q78+'Budget assumption'!Q293 -> 0 | D26: ='Budget assumption'!Q138 -> 0 | E26: ='Budget assumption'!Q169 -> 0 | F26: ='Budget assumption'!Q200 -> 0 | G26: ='Budget assumption'!Q262+'Budget assumption'!Q293 -> 0 | H26: ='Budget assumption'!Q231 -> 0 | J26: =H26-SUM(B26:G26) -> 0 | K26: ='data entry '!Q104 -> 0 | M26: ='data entry '!Q137 -> 0 | O26: =M26-K26 -> 0 | Q26: =M26-H26 -> 0 | R26: =H26-K26-E26-I26-F26-G26-D26 -> 0 | S26: =Q26+R26 -> 0 | V26: =M26-B26 -> 0 | W26: =B26-K26 -> 0 | X26: =V26+W26 -> 0
A27: TOTAL OTHERS | B27: =SUM(B22:B26) -> -33.55991 | C27: =SUM(C22:C26) -> -3.2560408 | D27: =SUM(D22:D26) -> 0 | E27: =SUM(E22:E26) -> 8.3333333 | F27: =SUM(F22:F26) -> 9.4826174 | G27: =SUM(G22:G26) -> 0 | H27: =SUM(H22:H26) -> -19 | I27: =SUM(I22:I26) -> 0 | J27: =H27-SUM(B27:G27) -> 0 | K27: =SUM(K22:K26) -> -29.076715 | M27: =SUM(M22:M26) -> -115.02679 | O27: =M27-K27 -> -85.950075 | Q27: =SUM(Q22:Q26) -> -103.76603 | R27: =SUM(R22:R26) -> 0 | S27: =Q27+R27 -> -103.76603 | V27: =SUM(V22:V26) -> -85.950075 | W27: =SUM(W22:W26) -> 0 | X27: =SUM(X22:X26) -> -85.950075
A28: IT GLOBAL | B28: ='Budget assumption'!Q59 -> 79.533064 | D28: ='Budget assumption'!Q140 -> 0 | E28: ='Budget assumption'!Q171 -> 16.558794 | F28: ='Budget assumption'!Q202 -> -25.911571 | G28: ='Budget assumption'!Q264+'Budget assumption'!Q295 -> 20.516936 | H28: ='Budget assumption'!Q233 -> 90.697223 | I28: ='Budget assumption'!Q337 -> -14.234309 | J28: =H28-SUM(B28:G28) -> 0 | K28: ='data entry '!Q106 -> 64.814167 | M28: ='data entry '!Q139 -> 89.41512 | O28: =M28-K28 -> 24.600953 | Q28: =M28-H28 -> -1.2821025 | R28: =H28-K28-E28-I28-F28-G28-D28 -> 28.953206 | S28: =Q28+R28 -> 27.671104 | V28: =M28-B28 -> 9.8820559 | W28: =B28-K28 -> 14.718897 | X28: =V28+W28 -> 24.600953
A29: G&A(Insurance included) | B29: ='Budget assumption'!Q60 -> 67.179506 | D29: ='Budget assumption'!Q141 -> 0 | E29: ='Budget assumption'!Q172 -> 0 | F29: ='Budget assumption'!Q203 -> 24.722002 | G29: ='Budget assumption'!Q265+'Budget assumption'!Q296 -> 2.6304938 | H29: ='Budget assumption'!Q234 -> 94.532002 | J29: =H29-SUM(B29:G29) -> 0 | K29: ='data entry '!Q107 -> 67.554582 | M29: ='data entry '!Q140 -> 68.80723 | O29: =M29-K29 -> 1.252648 | Q29: =M29-H29 -> -25.724772 | R29: =H29-K29-E29-I29-F29-G29-D29 -> -0.37507579 | S29: =Q29+R29 -> -26.099848 | V29: =M29-B29 -> 1.6277238 | X29: =V29+W29 -> 1.6277238
A30: TOTAL OVERHEAD | B30: =B28+B29 -> 146.71257 | C30: =C28+C29 -> 0 | D30: =D28+D29 -> 0 | E30: =E28+E29 -> 16.558794 | F30: =F28+F29 -> -1.189569 | G30: =G28+G29 -> 23.14743 | H30: =H28+H29 -> 185.22922 | I30: =I28+I29 -> -14.234309 | J30: =H30-SUM(B30:G30) -> 0 | K30: =K28+K29 -> 132.36875 | M30: =M28+M29 -> 158.22235 | O30: =O28+O29 -> 25.853601 | Q30: =Q28+Q29 -> -27.006875 | R30: =R28+R29 -> 28.57813 | S30: =S28+S29 -> 1.5712556 | V30: =V28+V29 -> 11.50978 | W30: =W28+W29 -> 14.718897 | X30: =X28+X29 -> 26.228677
D31: ='Budget assumption'!Q143 -> 0 | G31: ='Budget assumption'!Q267 -> 0 | J31: =H31-SUM(B31:G31) -> 0 | K31: ='data entry '!Q109 -> 0 | M31: ='data entry '!Q142 -> 0 | O31: =M31-K31 -> 0 | Q31: =M31-K31-E31-F31-D31-G31 -> 0 | S31: =Q31+R31 -> 0
A32: TOTAL ALL | B32: =B21+B27+B30 -> 1630.121 | C32: =C21+C27+C30 -> 52.535712 | D32: =D21+D27+D30 -> -6.7443971 | E32: =E21+E27+E30 -> -67.734714 | F32: =F21+F27+F30 -> 107.45659 | G32: =G21+G27+G30 -> 123.67409 | H32: =H21+H27+H30 -> 1839.3083 | I32: =I21+I27+I30 -> -71.411462 | J32: =H32-SUM(B32:G32) -> 0 | K32: =K21+K27+K30 -> 1451.6879 | M32: =M21+M27+M30 -> 901.66915 | O32: =M32-K32 -> -550.01876 | Q32: =Q21+Q27+Q30 -> -824.01839 | R32: =R21+R27+R30 -> 188.75953 | S32: =Q32+R32 -> -635.25886 | V32: =V21+V27+V30 -> -667.36683 | W32: =W21+W27+W30 -> 117.72314 | X32: =X21+X27+X30 -> -549.64369

Sheet Budget assumption
A1: YTD | B1: =IF($X$3>=B$2,1,0) -> 1 | C1: =IF($X$3>=C$2,1,0) -> 1 | D1: =IF($X$3>=D$2,1,0) -> 1 | E1: =IF($X$3>=E$2,1,0) -> 1 | F1: =IF($X$3>=F$2,1,0) -> 1 | G1: =IF($X$3>=G$2,1,0) -> 1 | H1: =IF($X$3>=H$2,1,0) -> 1 | I1: =IF($X$3>=I$2,1,0) -> 1 | ... M1: =IF($X$3>=M$2,1,0) -> 1
A2: MTD | B2: 1 | C2: 0 | D2: 0 | E2: 0 | F2: 0 | G2: 0 | H2: 0 | I2: 0 | J2: 0 | K2: 0 | L2: 0 | M2: 0
A3: Total Units (incl. accessories) | B3: 46000 | C3: 46000 | D3: 46000 | E3: 48300 | F3: 32200 | G3: 71500 | H3: 57750 | I3: 52250 | J3: 71500 | K3: 71500 | L3: 68750 | M3: 62561 | N3: =SUM(B3:M3) -> 674311 | V3: Month | W3: Jan | X3: 12 | Y3: 1
A4: STD 2026 _1st round | B4: STD | C4: STD | D4: STD | E4: STD | F4: STD | G4: STD | H4: STD | I4: STD | J4: STD | K4: STD | L4: STD | M4: STD | N4: STD
A5: Direct Labour | B5: 488.645 | C5: 521.785 | D5: 488.645 | E5: 488.645 | F5: 531.6 | G5: 732.38 | H5: 732.38 | I5: 732.38 | J5: 758.9 | K5: 732.38 | L5: 732.38 | M5: 732.38 | N5: =SUM(B5:M5) -> 7672.5 | O5: =N5/$N$3*1000 -> 11.378281
A6: Variable Utilities | B6: 37 | C6: 37 | D6: 37 | E6: 38 | F6: 23 | G6: 54 | H6: 44 | I6: 46 | J6: 45 | K6: 49 | L6: 57 | M6: 53 | N6: =SUM(B6:M6) -> 520 | O6: =N6/$N$3*1000 -> 0.77115752
A7: Variable Costs | B7: 16.17 | C7: 16.17 | D7: 16.17 | E7: 16.98 | F7: 11.32 | G7: 25.13 | H7: 20.3 | I7: 18.37 | J7: 25.13 | K7: 25.13 | L7: 24.17 | M7: 21.99 | N7: =SUM(B7:M7) -> 237.03 | O7: =N7/$N$3*1000 -> 0.35151436
A8: VARIABLE CONVERSION | B8: =SUM(B5:B7) -> 541.815 | C8: =SUM(C5:C7) -> 574.955 | D8: =SUM(D5:D7) -> 541.815 | E8: =SUM(E5:E7) -> 543.625 | F8: =SUM(F5:F7) -> 565.92 | G8: =SUM(G5:G7) -> 811.51 | H8: =SUM(H5:H7) -> 796.68 | I8: =SUM(I5:I7) -> 796.75 | ... N8: =SUM(N5:N7) -> 8429.53 | O8: =N8/$N$3*1000 -> 12.500953
A9: Indirect Labour | B9: 199.94 | C9: 212.35 | D9: 199.94 | E9: 199.94 | F9: 216.03 | G9: 278.18 | H9: 306.13 | I9: 278.18 | J9: 287.4 | K9: 278.18 | L9: 278.18 | M9: 274.91 | N9: =SUM(B9:M9) -> 3009.36 | O9: =N9/$N$3*1000 -> 4.4628665
A10: Fixed Labour | B10: 83.33 | C10: 92.97 | D10: 88.32 | E10: 88.32 | F10: 94.14 | G10: 88.33 | H10: 88.33 | I10: 91.82 | J10: 94.14 | K10: 92.92 | L10: 92.92 | M10: 93 | N10: =SUM(B10:M10) -> 1088.54 | O10: =N10/$N$3*1000 -> 1.6142996
A11: Semifixed | B11: 150.68 | C11: 150.68 | D11: 150.68 | E11: 154.21 | F11: 129.48 | G11: 206.14 | H11: 181.95 | I11: 172.45 | J11: 206.37 | K11: 206.37 | L11: 201.52 | M11: 191.06 | N11: =SUM(B11:M11) -> 2101.59 | O11: =N11/$N$3*1000 -> 3.116648
A12: Fixed utilities | B12: 8.7 | C12: 8.7 | D12: 8.7 | E12: 9.13 | F12: 6 | G12: 14.27 | H12: 11.55 | I12: 10.46 | J12: 14.27 | K12: 14.78 | L12: 14.2 | M12: 12.94 | N12: =SUM(B12:M12) -> 133.7 | O12: =N12/$N$3*1000 -> 0.19827646
A13: Fixed Cost | B13: 39.09094 | C13: 39.09094 | D13: 39.09094 | E13: 39.09094 | F13: 39.09094 | G13: 39.09094 | H13: 39.09094 | I13: 39.09094 | J13: 39.09094 | K13: 39.09094 | L13: 39.09094 | M13: 39.09094 | N13: =SUM(B13:M13) -> 469.09128 | O13: =N13/$N$3*1000 -> 0.69566013
A14: Depreciation | B14: 167.53137 | C14: 156.90109 | D14: 161.53885 | E14: 156.82095 | F14: 156.55436 | G14: 151.73734 | H14: 152.7794 | I14: 151.49565 | J14: 148.06127 | K14: 147.53007 | L14: 142.92661 | M14: 142.69082 | N14: =SUM(B14:M14) -> 1836.5678 | O14: =N14/$N$3*1000 -> 2.7236212
A15: FIXED CONVERSION | B15: =SUM(B9:B14) -> 649.27231 | C15: =SUM(C9:C14) -> 660.69203 | D15: =SUM(D9:D14) -> 648.26979 | E15: =SUM(E9:E14) -> 647.51189 | F15: =SUM(F9:F14) -> 641.2953 | G15: =SUM(G9:G14) -> 777.74828 | H15: =SUM(H9:H14) -> 779.83034 | I15: =SUM(I9:I14) -> 743.49659 | ... N15: =SUM(N9:N14) -> 8638.849 | O15: =N15/$N$3*1000 -> 12.811372
A16: TOTAL MFG COST w/o SHARES | B16: =B8+B15 -> 1191.0873 | C16: =C8+C15 -> 1235.647 | D16: =D8+D15 -> 1190.0848 | E16: =E8+E15 -> 1191.1369 | F16: =F8+F15 -> 1207.2153 | G16: =G8+G15 -> 1589.2583 | H16: =H8+H15 -> 1576.5103 | I16: =I8+I15 -> 1540.2466 | ... N16: =N8+N15 -> 17068.379 | O16: =N16/$N$3*1000 -> 25.312325
A17: TOTAL SHARES | B17: 10.71906 | C17: 10.67906 | D17: 10.69906 | E17: 10.69906 | F17: 10.64906 | G17: 9.75906 | H17: 9.06906 | I17: 9.06906 | J17: 10.02906 | K17: 9.77906 | L17: 9.61906 | M17: 9.79906 | N17: =SUM(B17:M17) -> 120.56872 | O17: =N17/$N$3*1000 -> 0.17880284 | Q17: Mess, Local IT, Security
A18: TOTAL MFG COST w/ SHARES | B18: =B16+B17 -> 1201.8064 | C18: =C16+C17 -> 1246.3261 | D18: =D16+D17 -> 1200.7838 | E18: =E16+E17 -> 1201.8359 | F18: =F16+F17 -> 1217.8644 | G18: =G16+G17 -> 1599.0173 | H18: =H16+H17 -> 1585.5794 | I18: =I16+I17 -> 1549.3156 | ... N18: =N16+N17 -> 17188.948 | O18: =N18/$N$3*1000 -> 25.491128
A19: Functional Currency Impact | B19: 415.68863 | C19: 386.88891 | D19: 421.50115 | E19: 413.13905 | F19: 424.61564 | G19: 416.35266 | H19: 428.1206 | I19: 429.39435 | J19: 419.28873 | K19: 432.68993 | L19: 423.80339 | M19: 436.70918 | N19: =SUM(B19:M19) -> 5048.1922 | O19: =N19/$N$3*1000 -> 7.486445
A20: TOTAL Including FC | B20: =B18+B19 -> 1617.495 | C20: =C18+C19 -> 1633.215 | D20: =D18+D19 -> 1622.285 | E20: =E18+E19 -> 1614.975 | F20: =F18+F19 -> 1642.48 | G20: =G18+G19 -> 2015.37 | H20: =H18+H19 -> 2013.7 | I20: =I18+I19 -> 1978.71 | ... N20: =N18+N19 -> 22237.14 | O20: =N20/$N$3*1000 -> 32.977573
A21: Scrap | B21: 23.02 | C21: 23.02 | D21: 23.02 | E21: 24.17 | F21: 16.11 | G21: 35.78 | H21: 28.9 | I21: 26.15 | J21: 35.78 | K21: 35.78 | L21: 34.41 | M21: 31.31 | N21: =SUM(B21:M21) -> 337.45 | O21: =N21/$N$3*1000 -> 0.50043674
A22: Scrap Reselling | B22: -56.58 | C22: -56.58 | D22: -56.58 | E22: -59.409 | F22: -39.606 | G22: -87.945 | H22: -71.0325 | I22: -64.2675 | J22: -87.945 | K22: -87.945 | L22: -84.5625 | M22: -76.95003 | N22: =SUM(B22:M22) -> -829.40253 | O22: =N22/$N$3*1000 -> -1.23
A23: Other Variable (Inventory Adj) | O23: =N23/$N$3*1000 -> 0
A24: Obsolete | O24: =N24/$N$3*1000 -> 0
A25: Asset Sales | O25: =N25/$N$3*1000 -> 0
A26: TOTAL OTHERS | B26: =SUM(B21:B25) -> -33.56 | C26: =SUM(C21:C25) -> -33.56 | D26: =SUM(D21:D25) -> -33.56 | E26: =SUM(E21:E25) -> -35.239 | F26: =SUM(F21:F25) -> -23.496 | G26: =SUM(G21:G25) -> -52.165 | H26: =SUM(H21:H25) -> -42.1325 | I26: =SUM(I21:I25) -> -38.1175 | ... N26: =SUM(N21:N25) -> -491.95253 | O26: =N26/$N$3*1000 -> -0.72956326
A27: IT GLOBAL | B27: 100.05 | C27: 100.69 | D27: 100.03 | E27: 100.04 | F27: 110.02 | G27: 100.04 | H27: 100.05 | I27: 100.05 | J27: 100.05 | K27: 100.05 | L27: 100.05 | M27: 54.75 | N27: =SUM(B27:M27) -> 1165.87 | O27: =N27/$N$3*1000 -> 1.7289797
A28: G&A(Insurance included) | B28: 69.81 | C28: 138.12 | D28: 114.27 | E28: 56.21 | F28: 81.91 | G28: 79.92 | H28: 74.09 | I28: 74.09 | J28: 74.09 | K28: 74.09 | L28: 74.09 | M28: 74.09 | N28: =SUM(B28:M28) -> 984.78 | O28: =N28/$N$3*1000 -> 1.460424
A29: TOTAL OVERHEAD | B29: =B27 -> 100.05 | C29: =C27 -> 100.69 | D29: =D27 -> 100.03 | E29: =E27 -> 100.04 | F29: =F27 -> 110.02 | G29: =G27 -> 100.04 | H29: =H27 -> 100.05 | I29: =I27 -> 100.05 | ... M29: =M27 -> 54.75 | N29: =N27+N28 -> 2150.65 | O29: =N29/$N$3*1000 -> 3.1894037
O30: =N30/$N$3*1000 -> 0
A31: TOTAL ALL | B31: =B20+B26+B29 -> 1683.985 | C31: =C20+C26+C29 -> 1700.345 | D31: =D20+D26+D29 -> 1688.755 | E31: =E20+E26+E29 -> 1679.776 | F31: =F20+F26+F29 -> 1729.004 | G31: =G20+G26+G29 -> 2063.245 | H31: =H20+H26+H29 -> 2071.6175 | I31: =I20+I26+I29 -> 2040.6425 | ... N31: =N20+N26+N29 -> 23895.837 | O31: =N31/$N$3*1000 -> 35.437413
B32: =B31/B3*1000 -> 36.60837 | C32: =C31/C3*1000 -> 36.964022 | D32: =D31/D3*1000 -> 36.712065 | E32: =E31/E3*1000 -> 34.777971 | F32: =F31/F3*1000 -> 53.695776 | G32: =G31/G3*1000 -> 28.856573 | H32: =H31/H3*1000 -> 35.872165 | I32: =I31/I3*1000 -> 39.055359 | ... N32: =N31/N3*1000 -> 35.437413
A34: Assigned hours
A35: Total Units (incl. accessories) | B35: =B3 -> 46000 | C35: =C3 -> 46000 | D35: =D3 -> 46000 | E35: =E3 -> 48300 | F35: =F3 -> 32200 | G35: =G3 -> 71500 | H35: =H3 -> 57750 | I35: =I3 -> 52250 | ... N35: =N3 -> 674311 | Q35: =SUMPRODUCT(B35:M35,B$2:M$2) -> 46000 | R35: =SUMIFS(B35:M35,$B$1:$M$1,$Y$3) -> 674311
A36: STD 2026 _flex | B36: STD | C36: STD | D36: STD | E36: STD | F36: STD | G36: STD | H36: STD | I36: STD | J36: STD | K36: STD | L36: STD | M36: STD | N36: STD | Q36: MTD | R36: YTD | AB36: FCA
A37: Direct Labour | B37: =$O5*B$35/1000 -> 523.40092 | C37: =$O5*C$35/1000 -> 523.40092 | D37: =$O5*D$35/1000 -> 523.40092 | E37: =$O5*E$35/1000 -> 549.57097 | F37: =$O5*F$35/1000 -> 366.38065 | G37: =$O5*G$35/1000 -> 813.54709 | H37: =$O5*H$35/1000 -> 657.09572 | I37: =$O5*I$35/1000 -> 594.51518 | ... M37: =$O5*M$35/1000 -> 711.83663 | N37: =SUM(B37:M37) -> 7672.5 | Q37: =SUMPRODUCT(B37:M37,B$2:M$2) -> 523.40092 | R37: =SUMIFS(B37:M37,$B$1:$M$1,$Y$3) -> 7672.5
A38: Variable Utilities | B38: =$O6*B$35/1000 -> 35.473246 | C38: =$O6*C$35/1000 -> 35.473246 | D38: =$O6*D$35/1000 -> 35.473246 | E38: =$O6*E$35/1000 -> 37.246908 | F38: =$O6*F$35/1000 -> 24.831272 | G38: =$O6*G$35/1000 -> 55.137763 | H38: =$O6*H$35/1000 -> 44.534347 | I38: =$O6*I$35/1000 -> 40.292981 | ... M38: =$O6*M$35/1000 -> 48.244386 | N38: =SUM(B38:M38) -> 520 | Q38: =SUMPRODUCT(B38:M38,B$2:M$2) -> 35.473246 | R38: =SUMIFS(B38:M38,$B$1:$M$1,$Y$3) -> 520
A39: Variable Costs | B39: =$O7*B$35/1000 -> 16.169661 | C39: =$O7*C$35/1000 -> 16.169661 | D39: =$O7*D$35/1000 -> 16.169661 | E39: =$O7*E$35/1000 -> 16.978144 | F39: =$O7*F$35/1000 -> 11.318762 | G39: =$O7*G$35/1000 -> 25.133277 | H39: =$O7*H$35/1000 -> 20.299954 | I39: =$O7*I$35/1000 -> 18.366625 | ... M39: =$O7*M$35/1000 -> 21.99109 | N39: =SUM(B39:M39) -> 237.03 | Q39: =SUMPRODUCT(B39:M39,B$2:M$2) -> 16.169661 | R39: =SUMIFS(B39:M39,$B$1:$M$1,$Y$3) -> 237.03
A40: VARIABLE CONVERSION | B40: =SUM(B37:B39) -> 575.04383 | C40: =SUM(C37:C39) -> 575.04383 | D40: =SUM(D37:D39) -> 575.04383 | E40: =SUM(E37:E39) -> 603.79602 | F40: =SUM(F37:F39) -> 402.53068 | G40: =SUM(G37:G39) -> 893.81813 | H40: =SUM(H37:H39) -> 721.93003 | I40: =SUM(I37:I39) -> 653.17479 | ... N40: =SUM(N37:N39) -> 8429.53 | Q40: =SUMPRODUCT(B40:M40,B$2:M$2) -> 575.04383 | R40: =SUMIFS(B40:M40,$B$1:$M$1,$Y$3) -> 8429.53
A41: Indirect Labour | B41: =$O9*B$35/1000 -> 205.29186 | C41: =$O9*C$35/1000 -> 205.29186 | D41: =$O9*D$35/1000 -> 205.29186 | E41: =$O9*E$35/1000 -> 215.55645 | F41: =$O9*F$35/1000 -> 143.7043 | G41: =$O9*G$35/1000 -> 319.09496 | H41: =$O9*H$35/1000 -> 257.73054 | I41: =$O9*I$35/1000 -> 233.18478 | ... M41: =$O9*M$35/1000 -> 279.20139 | N41: =SUM(B41:M41) -> 3009.36 | Q41: =SUMPRODUCT(B41:M41,B$2:M$2) -> 205.29186 | R41: =SUMIFS(B41:M41,$B$1:$M$1,$Y$3) -> 3009.36
A42: Fixed Labour | B42: =$O10*B$35/1000 -> 74.257783 | C42: =$O10*C$35/1000 -> 74.257783 | D42: =$O10*D$35/1000 -> 74.257783 | E42: =$O10*E$35/1000 -> 77.970672 | F42: =$O10*F$35/1000 -> 51.980448 | G42: =$O10*G$35/1000 -> 115.42242 | H42: =$O10*H$35/1000 -> 93.225804 | I42: =$O10*I$35/1000 -> 84.347156 | ... M42: =$O10*M$35/1000 -> 100.9922 | N42: =SUM(B42:M42) -> 1088.54 | Q42: =SUMPRODUCT(B42:M42,B$2:M$2) -> 74.257783 | R42: =SUMIFS(B42:M42,$B$1:$M$1,$Y$3) -> 1088.54
A43: Semifixed | B43: =$O11*B$35/1000 -> 143.36581 | C43: =$O11*C$35/1000 -> 143.36581 | D43: =$O11*D$35/1000 -> 143.36581 | E43: =$O11*E$35/1000 -> 150.5341 | F43: =$O11*F$35/1000 -> 100.35606 | G43: =$O11*G$35/1000 -> 222.84033 | H43: =$O11*H$35/1000 -> 179.98642 | I43: =$O11*I$35/1000 -> 162.84486 | ... M43: =$O11*M$35/1000 -> 194.98061 | N43: =SUM(B43:M43) -> 2101.59 | Q43: =SUMPRODUCT(B43:M43,B$2:M$2) -> 143.36581 | R43: =SUMIFS(B43:M43,$B$1:$M$1,$Y$3) -> 2101.59
A44: Fixed utilities | B44: =$O12*B$35/1000 -> 9.1207173 | C44: =$O12*C$35/1000 -> 9.1207173 | D44: =$O12*D$35/1000 -> 9.1207173 | E44: =$O12*E$35/1000 -> 9.5767532 | F44: =$O12*F$35/1000 -> 6.3845021 | G44: =$O12*G$35/1000 -> 14.176767 | H44: =$O12*H$35/1000 -> 11.450466 | I44: =$O12*I$35/1000 -> 10.359945 | ... M44: =$O12*M$35/1000 -> 12.404374 | N44: =SUM(B44:M44) -> 133.7 | Q44: =SUMPRODUCT(B44:M44,B$2:M$2) -> 9.1207173 | R44: =SUMIFS(B44:M44,$B$1:$M$1,$Y$3) -> 133.7 | AB44: 4.13681
A45: Fixed Cost | B45: =$O13*B$35/1000 -> 32.000366 | C45: =$O13*C$35/1000 -> 32.000366 | D45: =$O13*D$35/1000 -> 32.000366 | E45: =$O13*E$35/1000 -> 33.600384 | F45: =$O13*F$35/1000 -> 22.400256 | G45: =$O13*G$35/1000 -> 49.7397 | H45: =$O13*H$35/1000 -> 40.174373 | I45: =$O13*I$35/1000 -> 36.348242 | ... M45: =$O13*M$35/1000 -> 43.521194 | N45: =SUM(B45:M45) -> 469.09128 | Q45: =SUMPRODUCT(B45:M45,B$2:M$2) -> 32.000366 | R45: =SUMIFS(B45:M45,$B$1:$M$1,$Y$3) -> 469.09128 | AB45: 1.797501
A46: Depreciation | B46: =$O14*B$35/1000 -> 125.28658 | C46: =$O14*C$35/1000 -> 125.28658 | D46: =$O14*D$35/1000 -> 125.28658 | E46: =$O14*E$35/1000 -> 131.55091 | F46: =$O14*F$35/1000 -> 87.700604 | G46: =$O14*G$35/1000 -> 194.73892 | H46: =$O14*H$35/1000 -> 157.28913 | I46: =$O14*I$35/1000 -> 142.30921 | ... M46: =$O14*M$35/1000 -> 170.39247 | N46: =SUM(B46:M46) -> 1836.5678 | Q46: =SUMPRODUCT(B46:M46,B$2:M$2) -> 125.28658 | R46: =SUMIFS(B46:M46,$B$1:$M$1,$Y$3) -> 1836.5678 | AB46: 3.645188
A47: FIXED CONVERSION | B47: =SUM(B41:B46) -> 589.32311 | C47: =SUM(C41:C46) -> 589.32311 | D47: =SUM(D41:D46) -> 589.32311 | E47: =SUM(E41:E46) -> 618.78927 | F47: =SUM(F41:F46) -> 412.52618 | G47: =SUM(G41:G46) -> 916.0131 | H47: =SUM(H41:H46) -> 739.85673 | I47: =SUM(I41:I46) -> 669.39419 | ... N47: =SUM(N41:N46) -> 8638.849 | Q47: =SUMPRODUCT(B47:M47,B$2:M$2) -> 589.32311 | R47: =SUMIFS(B47:M47,$B$1:$M$1,$Y$3) -> 8638.849 | AB47: 0.10130454
A48: TOTAL MFG COST w/o SHARES | B48: =B40+B47 -> 1164.3669 | C48: =C40+C47 -> 1164.3669 | D48: =D40+D47 -> 1164.3669 | E48: =E40+E47 -> 1222.5853 | F48: =F40+F47 -> 815.05686 | G48: =G40+G47 -> 1809.8312 | H48: =H40+H47 -> 1461.7868 | I48: =I40+I47 -> 1322.569 | ... N48: =N40+N47 -> 17068.379 | Q48: =SUMPRODUCT(B48:M48,B$2:M$2) -> 1164.3669 | R48: =SUMIFS(B48:M48,$B$1:$M$1,$Y$3) -> 17068.379 | AB48: 1.1195978
A49: TOTAL SHARES | B49: =$O17*B$35/1000 -> 8.2249305 | C49: =$O17*C$35/1000 -> 8.2249305 | D49: =$O17*D$35/1000 -> 8.2249305 | E49: =$O17*E$35/1000 -> 8.636177 | F49: =$O17*F$35/1000 -> 5.7574514 | G49: =$O17*G$35/1000 -> 12.784403 | H49: =$O17*H$35/1000 -> 10.325864 | I49: =$O17*I$35/1000 -> 9.3424482 | ... M49: =$O17*M$35/1000 -> 11.186084 | N49: =SUM(B49:M49) -> 120.56872 | Q49: =SUMPRODUCT(B49:M49,B$2:M$2) -> 8.2249305 | R49: =SUMIFS(B49:M49,$B$1:$M$1,$Y$3) -> 120.56872 | AB49: 0.33711994
A50: TOTAL MFG COST w/ SHARES | B50: =B48+B49 -> 1172.5919 | C50: =C48+C49 -> 1172.5919 | D50: =D48+D49 -> 1172.5919 | E50: =E48+E49 -> 1231.2215 | F50: =F48+F49 -> 820.81431 | G50: =G48+G49 -> 1822.6156 | H50: =H48+H49 -> 1472.1126 | I50: =I48+I49 -> 1331.9114 | ... N50: =N48+N49 -> 17188.948 | Q50: =SUMPRODUCT(B50:M50,B$2:M$2) -> 1172.5919 | R50: =SUMIFS(B50:M50,$B$1:$M$1,$Y$3) -> 17188.948 | AB50: 2.5085095
A51: Functional Currency Impact | B51: =$O19*B$35/1000 -> 344.37647 | C51: =$O19*C$35/1000 -> 344.37647 | D51: =$O19*D$35/1000 -> 344.37647 | E51: =$O19*E$35/1000 -> 361.5953 | F51: =$O19*F$35/1000 -> 241.06353 | G51: =$O19*G$35/1000 -> 535.28082 | H51: =$O19*H$35/1000 -> 432.3422 | I51: =$O19*I$35/1000 -> 391.16675 | ... M51: =$O19*M$35/1000 -> 468.35949 | N51: =SUM(B51:M51) -> 5048.1922 | Q51: =SUMPRODUCT(B51:M51,B$2:M$2) -> 344.37647 | R51: =SUMIFS(B51:M51,$B$1:$M$1,$Y$3) -> 5048.1922 | AB51: 13.646031
A52: TOTAL Including FC | B52: =B50+B51 -> 1516.9683 | C52: =C50+C51 -> 1516.9683 | D52: =D50+D51 -> 1516.9683 | E52: =E50+E51 -> 1592.8168 | F52: =F50+F51 -> 1061.8778 | G52: =G50+G51 -> 2357.8964 | H52: =H50+H51 -> 1904.4548 | I52: =I50+I51 -> 1723.0782 | ... N52: =N50+N51 -> 22237.14 | Q52: =SUMPRODUCT(B52:M52,B$2:M$2) -> 1516.9683 | R52: =SUMIFS(B52:M52,$B$1:$M$1,$Y$3) -> 22237.14 | AB52: 4.200919
A53: Scrap | B53: =$O21*B$35/1000 -> 23.02009 | C53: =$O21*C$35/1000 -> 23.02009 | D53: =$O21*D$35/1000 -> 23.02009 | E53: =$O21*E$35/1000 -> 24.171095 | F53: =$O21*F$35/1000 -> 16.114063 | G53: =$O21*G$35/1000 -> 35.781227 | H53: =$O21*H$35/1000 -> 28.900222 | I53: =$O21*I$35/1000 -> 26.14782 | ... M53: =$O21*M$35/1000 -> 31.307823 | N53: =SUM(B53:M53) -> 337.45 | Q53: =SUMPRODUCT(B53:M53,B$2:M$2) -> 23.02009 | R53: =SUMIFS(B53:M53,$B$1:$M$1,$Y$3) -> 337.45 | AB53: 0
A54: Scrap Reselling | B54: =$O22*B$35/1000 -> -56.58 | C54: =$O22*C$35/1000 -> -56.58 | D54: =$O22*D$35/1000 -> -56.58 | E54: =$O22*E$35/1000 -> -59.409 | F54: =$O22*F$35/1000 -> -39.606 | G54: =$O22*G$35/1000 -> -87.945 | H54: =$O22*H$35/1000 -> -71.0325 | I54: =$O22*I$35/1000 -> -64.2675 | ... M54: =$O22*M$35/1000 -> -76.95003 | N54: =SUM(B54:M54) -> -829.40253 | Q54: =SUMPRODUCT(B54:M54,B$2:M$2) -> -56.58 | R54: =SUMIFS(B54:M54,$B$1:$M$1,$Y$3) -> -829.40253 | AB54: 0
A55: Other Variable (Inventory Adj) | B55: =$O23*B$35/1000 -> 0 | C55: =$O23*C$35/1000 -> 0 | D55: =$O23*D$35/1000 -> 0 | E55: =$O23*E$35/1000 -> 0 | F55: =$O23*F$35/1000 -> 0 | G55: =$O23*G$35/1000 -> 0 | H55: =$O23*H$35/1000 -> 0 | I55: =$O23*I$35/1000 -> 0 | ... M55: =$O23*M$35/1000 -> 0 | N55: =SUM(B55:M55) -> 0 | Q55: =SUMPRODUCT(B55:M55,B$2:M$2) -> 0 | R55: =SUMIFS(B55:M55,$B$1:$M$1,$Y$3) -> 0 | AB55: 4.200919
A56: Obsolete | B56: =$O24*B$35/1000 -> 0 | C56: =$O24*C$35/1000 -> 0 | D56: =$O24*D$35/1000 -> 0 | E56: =$O24*E$35/1000 -> 0 | F56: =$O24*F$35/1000 -> 0 | G56: =$O24*G$35/1000 -> 0 | H56: =$O24*H$35/1000 -> 0 | I56: =$O24*I$35/1000 -> 0 | ... M56: =$O24*M$35/1000 -> 0 | N56: =SUM(B56:M56) -> 0 | Q56: =SUMPRODUCT(B56:M56,B$2:M$2) -> 0 | R56: =SUMIFS(B56:M56,$B$1:$M$1,$Y$3) -> 0 | AB56: 17.84695
A57: Asset Sales | N57: =SUM(B57:M57) -> 0 | Q57: =SUMPRODUCT(B57:M57,B$2:M$2) -> 0 | R57: =SUMIFS(B57:M57,$B$1:$M$1,$Y$3) -> 0
A58: TOTAL OTHERS | B58: =SUM(B53:B57) -> -33.55991 | C58: =SUM(C53:C57) -> -33.55991 | D58: =SUM(D53:D57) -> -33.55991 | E58: =SUM(E53:E57) -> -35.237905 | F58: =SUM(F53:F57) -> -23.491937 | G58: =SUM(G53:G57) -> -52.163773 | H58: =SUM(H53:H57) -> -42.132278 | I58: =SUM(I53:I57) -> -38.11968 | ... N58: =SUM(N53:N57) -> -491.95253 | Q58: =SUMPRODUCT(B58:M58,B$2:M$2) -> -33.55991 | R58: =SUMIFS(B58:M58,$B$1:$M$1,$Y$3) -> -491.95253
A59: IT GLOBAL | B59: =$O27*B$35/1000 -> 79.533064 | C59: =$O27*C$35/1000 -> 79.533064 | D59: =$O27*D$35/1000 -> 79.533064 | E59: =$O27*E$35/1000 -> 83.509717 | F59: =$O27*F$35/1000 -> 55.673145 | G59: =$O27*G$35/1000 -> 123.62205 | H59: =$O27*H$35/1000 -> 99.848575 | I59: =$O27*I$35/1000 -> 90.339187 | ... M59: =$O27*M$35/1000 -> 108.1667 | N59: =SUM(B59:M59) -> 1165.87 | Q59: =SUMPRODUCT(B59:M59,B$2:M$2) -> 79.533064 | R59: =SUMIFS(B59:M59,$B$1:$M$1,$Y$3) -> 1165.87
A60: G&A(Insurance included) | B60: =$O28*B$35/1000 -> 67.179506 | C60: =$O28*C$35/1000 -> 67.179506 | D60: =$O28*D$35/1000 -> 67.179506 | E60: =$O28*E$35/1000 -> 70.538482 | F60: =$O28*F$35/1000 -> 47.025654 | G60: =$O28*G$35/1000 -> 104.42032 | H60: =$O28*H$35/1000 -> 84.339489 | I60: =$O28*I$35/1000 -> 76.307156 | ... M60: =$O28*M$35/1000 -> 91.365589 | N60: =SUM(B60:M60) -> 984.78 | Q60: =SUMPRODUCT(B60:M60,B$2:M$2) -> 67.179506 | R60: =SUMIFS(B60:M60,$B$1:$M$1,$Y$3) -> 984.78
A61: TOTAL OVERHEAD | B61: =B59+B60 -> 146.71257 | C61: =C59+C60 -> 146.71257 | D61: =D59+D60 -> 146.71257 | E61: =E59+E60 -> 154.0482 | F61: =F59+F60 -> 102.6988 | G61: =G59+G60 -> 228.04236 | H61: =H59+H60 -> 184.18806 | I61: =I59+I60 -> 166.64634 | ... N61: =N59+N60 -> 2150.65 | Q61: =SUMPRODUCT(B61:M61,B$2:M$2) -> 146.71257 | R61: =SUMIFS(B61:M61,$B$1:$M$1,$Y$3) -> 2150.65
N62: =SUM(B62:M62) -> 0 | Q62: =SUMPRODUCT(B62:M62,B$2:M$2) -> 0 | R62: =SUMIFS(B62:M62,$B$1:$M$1,$Y$3) -> 0
A63: TOTAL ALL | B63: =B52+B58+B61 -> 1630.121 | C63: =C52+C58+C61 -> 1630.121 | D63: =D52+D58+D61 -> 1630.121 | E63: =E52+E58+E61 -> 1711.6271 | F63: =F52+F58+F61 -> 1141.0847 | G63: =G52+G58+G61 -> 2533.775 | H63: =H52+H58+H61 -> 2046.5106 | I63: =I52+I58+I61 -> 1851.6048 | ... N63: =N52+N58+N61 -> 23895.837 | Q63: =SUMPRODUCT(B63:M63,B$2:M$2) -> 1630.121 | R63: =SUMIFS(B63:M63,$B$1:$M$1,$Y$3) -> 23895.837
A66: Budget Volume | B66: 50463 | C66: 50446 | D66: 50447 | E66: 48050 | F66: 36788 | G66: 53265 | H66: 42049 | I66: 39150 | J66: 53732 | K66: 48548 | L66: 51408 | M66: =40676 -> 40676 | N66: =SUM(B66:M66)-22 -> 565000 | Q66: =SUMPRODUCT(B66:M66,B$2:M$2) -> 50463 | R66: =SUMIFS(B66:M66,$B$1:$M$1,$Y$3) -> 565022
A67: Total assigned hours Budget
A69: Volume Mix | B69: STD | C69: STD | D69: STD | E69: STD | F69: STD | G69: STD | H69: STD | I69: STD | J69: STD | K69: STD | L69: STD | M69: STD | N69: STD | Q69: MTD | R69: YTD
A70: Direct Labour | B70: =$O5*B$66/1000-B37 -> 50.781268 | C70: =$O5*C$66/1000-C37 -> 50.587837 | D70: =$O5*D$66/1000-D37 -> 50.599215 | E70: =$O5*E$66/1000-E37 -> -2.8445702 | F70: =$O5*F$66/1000-F37 -> 52.203553 | G70: =$O5*G$66/1000-G37 -> -207.48295 | H70: =$O5*H$66/1000-H37 -> -178.65039 | I70: =$O5*I$66/1000-I37 -> -149.05548 | ... M70: =$O5*M$66/1000-M37 -> -249.01368 | N70: =SUM(B70:M70) -> -1243.5209 | Q70: =SUMPRODUCT(B70:M70,B$2:M$2) -> 50.781268 | R70: =SUMIFS(B70:M70,$B$1:$M$1,$Y$3) -> -1243.5209
A71: Variable Utilities | B71: =$O6*B$66/1000-B38 -> 3.441676 | C71: =$O6*C$66/1000-C38 -> 3.4285663 | D71: =$O6*D$66/1000-D38 -> 3.4293375 | E71: =$O6*E$66/1000-E38 -> -0.19278938 | F71: =$O6*F$66/1000-F38 -> 3.5380707 | G71: =$O6*G$66/1000-G38 -> -14.062057 | H71: =$O6*H$66/1000-H38 -> -12.107944 | I71: =$O6*I$66/1000-I38 -> -10.102164 | ... M71: =$O6*M$66/1000-M38 -> -16.876782 | N71: =SUM(B71:M71) -> -84.279034 | Q71: =SUMPRODUCT(B71:M71,B$2:M$2) -> 3.441676 | R71: =SUMIFS(B71:M71,$B$1:$M$1,$Y$3) -> -84.279034
A72: Variable Costs | B72: =$O7*B$66/1000-B39 -> 1.5688086 | C72: =$O7*C$66/1000-C39 -> 1.5628328 | D72: =$O7*D$66/1000-D39 -> 1.5631844 | E72: =$O7*E$66/1000-E39 -> -0.08787859 | F72: =$O7*F$66/1000-F39 -> 1.6127479 | G72: =$O7*G$66/1000-G39 -> -6.4098644 | H72: =$O7*H$66/1000-H39 -> -5.519127 | I72: =$O7*I$66/1000-I39 -> -4.6048381 | ... M72: =$O7*M$66/1000-M39 -> -7.6928918 | N72: =SUM(B72:M72) -> -38.416653 | Q72: =SUMPRODUCT(B72:M72,B$2:M$2) -> 1.5688086 | R72: =SUMIFS(B72:M72,$B$1:$M$1,$Y$3) -> -38.416653
A73: VARIABLE CONVERSION | B73: =SUM(B70:B72) -> 55.791752 | C73: =SUM(C70:C72) -> 55.579236 | D73: =SUM(D70:D72) -> 55.591737 | E73: =SUM(E70:E72) -> -3.1252382 | F73: =SUM(F70:F72) -> 57.354372 | G73: =SUM(G70:G72) -> -227.95487 | H73: =SUM(H70:H72) -> -196.27746 | I73: =SUM(I70:I72) -> -163.76248 | ... N73: =SUM(N70:N72) -> -1366.2166 | Q73: =SUMPRODUCT(B73:M73,B$2:M$2) -> 55.791752 | R73: =SUMIFS(B73:M73,$B$1:$M$1,$Y$3) -> -1366.2166
A74: Scrap | B74: =$O21*B$66/1000-B53 -> 2.2334492 | C74: =$O21*C$66/1000-C53 -> 2.2249418 | D74: =$O21*D$66/1000-D53 -> 2.2254422 | E74: =$O21*E$66/1000-E53 -> -0.12510919 | F74: =$O21*F$66/1000-F53 -> 2.2960038 | G74: =$O21*G$66/1000-G53 -> -9.125464 | H74: =$O21*H$66/1000-H53 -> -7.8573573 | I74: =$O21*I$66/1000-I53 -> -6.5557213 | ... M74: =$O21*M$66/1000-M53 -> -10.952058 | N74: =SUM(B74:M74) -> -54.692231 | Q74: =SUMPRODUCT(B74:M74,B$2:M$2) -> 2.2334492 | R74: =SUMIFS(B74:M74,$B$1:$M$1,$Y$3) -> -54.692231
A75: Scrap Reselling | B75: =$O22*B$66/1000-B54 -> -5.48949 | C75: =$O22*C$66/1000-C54 -> -5.46858 | D75: =$O22*D$66/1000-D54 -> -5.46981 | E75: =$O22*E$66/1000-E54 -> 0.3075 | F75: =$O22*F$66/1000-F54 -> -5.64324 | G75: =$O22*G$66/1000-G54 -> 22.42905 | H75: =$O22*H$66/1000-H54 -> 19.31223 | I75: =$O22*I$66/1000-I54 -> 16.113 | ... M75: =$O22*M$66/1000-M54 -> 26.91855 | N75: =SUM(B75:M75) -> 134.42547 | Q75: =SUMPRODUCT(B75:M75,B$2:M$2) -> -5.48949 | R75: =SUMIFS(B75:M75,$B$1:$M$1,$Y$3) -> 134.42547
A76: Other Variable (Inventory Adj) | B76: =$O23*B$66/1000-B55 -> 0 | C76: =$O23*C$66/1000-C55 -> 0 | D76: =$O23*D$66/1000-D55 -> 0 | E76: =$O23*E$66/1000-E55 -> 0 | F76: =$O23*F$66/1000-F55 -> 0 | G76: =$O23*G$66/1000-G55 -> 0 | H76: =$O23*H$66/1000-H55 -> 0 | I76: =$O23*I$66/1000-I55 -> 0 | ... M76: =$O23*M$66/1000-M55 -> 0 | N76: =SUM(B76:M76) -> 0 | Q76: =SUMPRODUCT(B76:M76,B$2:M$2) -> 0 | R76: =SUMIFS(B76:M76,$B$1:$M$1,$Y$3) -> 0
Q77: =SUMPRODUCT(B77:M77,B$2:M$2) -> 0 | R77: =SUMIFS(B77:M77,$B$1:$M$1,$Y$3) -> 0
Q78: =SUMPRODUCT(B78:M78,B$2:M$2) -> 0 | R78: =SUMIFS(B78:M78,$B$1:$M$1,$Y$3) -> 0
A79: TOTAL OTHERS | B79: =SUM(B74:B78) -> -3.2560408 | C79: =SUM(C74:C78) -> -3.2436382 | D79: =SUM(D74:D78) -> -3.2443678 | E79: =SUM(E74:E78) -> 0.18239081 | F79: =SUM(F74:F78) -> -3.3472362 | G79: =SUM(G74:G78) -> 13.303586 | H79: =SUM(H74:H78) -> 11.454873 | I79: =SUM(I74:I78) -> 9.5572787 | ... N79: =SUM(N74:N78) -> 79.733239 | Q79: =SUMPRODUCT(B79:M79,B$2:M$2) -> -3.2560408 | R79: =SUMIFS(B79:M79,$B$1:$M$1,$Y$3) -> 79.733239
N80: =SUM(B80:M80) -> 0 | Q80: =SUMPRODUCT(B80:M80,B$2:M$2) -> 0 | R80: =SUMIFS(B80:M80,$B$1:$M$1,$Y$3) -> 0
A81: TOTAL ALL | B81: =B73+B79 -> 52.535712 | C81: =C73+C79 -> 52.335598 | D81: =D73+D79 -> 52.347369 | E81: =E73+E79 -> -2.9428474 | F81: =F73+F79 -> 54.007135 | G81: =G73+G79 -> -214.65129 | H81: =H73+H79 -> -184.82259 | I81: =I73+I79 -> -154.2052 | ... N81: =N73+N79 -> -1286.4834 | Q81: =SUMPRODUCT(B81:M81,B$2:M$2) -> 52.535712 | R81: =SUMIFS(B81:M81,$B$1:$M$1,$Y$3) -> -1286.4834
A85: Tariffa 2025 adj by volume | B85: Jan | C85: Feb | D85: March | E85: April | F85: May | G85: June | H85: July | I85: August | J85: Sept | K85: Oct | L85: Nov | M85: Dec | N85: Total | Q85: MTD | R85: YTD
A86: Direct Labour | B86: =B37+B70 -> 574.18219 | C86: =C37+C70 -> 573.98876 | D86: =D37+D70 -> 574.00014 | E86: =E37+E70 -> 546.7264 | F86: =F37+F70 -> 418.5842 | G86: =G37+G70 -> 606.06413 | H86: =H37+H70 -> 478.44534 | I86: =I37+I70 -> 445.4597 | ... M86: =M37+M70 -> 462.82296 | N86: =SUM(B86:M86) -> 6428.9791 | Q86: =SUMPRODUCT(B86:M86,B$2:M$2) -> 574.18219 | R86: =SUMIFS(B86:M86,$B$1:$M$1,$Y$3) -> 6428.9791
A87: Variable Utilities | B87: =B38+B71 -> 38.914922 | C87: =C38+C71 -> 38.901812 | D87: =D38+D71 -> 38.902584 | E87: =E38+E71 -> 37.054119 | F87: =F38+F71 -> 28.369343 | G87: =G38+G71 -> 41.075705 | H87: =H38+H71 -> 32.426403 | I87: =I38+I71 -> 30.190817 | ... M87: =M38+M71 -> 31.367603 | N87: =SUM(B87:M87) -> 435.72097 | Q87: =SUMPRODUCT(B87:M87,B$2:M$2) -> 38.914922 | R87: =SUMIFS(B87:M87,$B$1:$M$1,$Y$3) -> 435.72097
A88: Variable Costs | B88: =B39+B72 -> 17.738469 | C88: =C39+C72 -> 17.732493 | D88: =D39+D72 -> 17.732845 | E88: =E39+E72 -> 16.890265 | F88: =F39+F72 -> 12.93151 | G88: =G39+G72 -> 18.723412 | H88: =H39+H72 -> 14.780827 | I88: =I39+I72 -> 13.761787 | ... M88: =M39+M72 -> 14.298198 | N88: =SUM(B88:M88) -> 198.61335 | Q88: =SUMPRODUCT(B88:M88,B$2:M$2) -> 17.738469 | R88: =SUMIFS(B88:M88,$B$1:$M$1,$Y$3) -> 198.61335
A89: VARIABLE CONVERSION | B89: =SUM(B86:B88) -> 630.83558 | C89: =SUM(C86:C88) -> 630.62307 | D89: =SUM(D86:D88) -> 630.63557 | E89: =SUM(E86:E88) -> 600.67078 | F89: =SUM(F86:F88) -> 459.88505 | G89: =SUM(G86:G88) -> 665.86325 | H89: =SUM(H86:H88) -> 525.65257 | I89: =SUM(I86:I88) -> 489.4123 | ... N89: =SUM(N86:N88) -> 7063.3134 | Q89: =SUMPRODUCT(B89:M89,B$2:M$2) -> 630.83558 | R89: =SUMIFS(B89:M89,$B$1:$M$1,$Y$3) -> 7063.3134
A90: Indirect Labour | B90: =B41 -> 205.29186 | C90: =C41 -> 205.29186 | D90: =D41 -> 205.29186 | E90: =E41 -> 215.55645 | F90: =F41 -> 143.7043 | G90: =G41 -> 319.09496 | H90: =H41 -> 257.73054 | I90: =I41 -> 233.18478 | ... M90: =M41 -> 279.20139 | N90: =SUM(B90:M90) -> 3009.36 | Q90: =SUMPRODUCT(B90:M90,B$2:M$2) -> 205.29186 | R90: =SUMIFS(B90:M90,$B$1:$M$1,$Y$3) -> 3009.36
A91: Fixed Labour | B91: =B42 -> 74.257783 | C91: =C42 -> 74.257783 | D91: =D42 -> 74.257783 | E91: =E42 -> 77.970672 | F91: =F42 -> 51.980448 | G91: =G42 -> 115.42242 | H91: =H42 -> 93.225804 | I91: =I42 -> 84.347156 | ... M91: =M42 -> 100.9922 | N91: =SUM(B91:M91) -> 1088.54 | Q91: =SUMPRODUCT(B91:M91,B$2:M$2) -> 74.257783 | R91: =SUMIFS(B91:M91,$B$1:$M$1,$Y$3) -> 1088.54
A92: Semifixed | B92: =B43 -> 143.36581 | C92: =C43 -> 143.36581 | D92: =D43 -> 143.36581 | E92: =E43 -> 150.5341 | F92: =F43 -> 100.35606 | G92: =G43 -> 222.84033 | H92: =H43 -> 179.98642 | I92: =I43 -> 162.84486 | ... M92: =M43 -> 194.98061 | N92: =SUM(B92:M92) -> 2101.59 | Q92: =SUMPRODUCT(B92:M92,B$2:M$2) -> 143.36581 | R92: =SUMIFS(B92:M92,$B$1:$M$1,$Y$3) -> 2101.59
A93: Fixed utilities | B93: =B44 -> 9.1207173 | C93: =C44 -> 9.1207173 | D93: =D44 -> 9.1207173 | E93: =E44 -> 9.5767532 | F93: =F44 -> 6.3845021 | G93: =G44 -> 14.176767 | H93: =H44 -> 11.450466 | I93: =I44 -> 10.359945 | ... M93: =M44 -> 12.404374 | N93: =SUM(B93:M93) -> 133.7 | Q93: =SUMPRODUCT(B93:M93,B$2:M$2) -> 9.1207173 | R93: =SUMIFS(B93:M93,$B$1:$M$1,$Y$3) -> 133.7
A94: Fixed Cost | B94: =B45 -> 32.000366 | C94: =C45 -> 32.000366 | D94: =D45 -> 32.000366 | E94: =E45 -> 33.600384 | F94: =F45 -> 22.400256 | G94: =G45 -> 49.7397 | H94: =H45 -> 40.174373 | I94: =I45 -> 36.348242 | ... M94: =M45 -> 43.521194 | N94: =SUM(B94:M94) -> 469.09128 | Q94: =SUMPRODUCT(B94:M94,B$2:M$2) -> 32.000366 | R94: =SUMIFS(B94:M94,$B$1:$M$1,$Y$3) -> 469.09128
A95: Depreciation | B95: =B46 -> 125.28658 | C95: =C46 -> 125.28658 | D95: =D46 -> 125.28658 | E95: =E46 -> 131.55091 | F95: =F46 -> 87.700604 | G95: =G46 -> 194.73892 | H95: =H46 -> 157.28913 | I95: =I46 -> 142.30921 | ... M95: =M46 -> 170.39247 | N95: =SUM(B95:M95) -> 1836.5678 | Q95: =SUMPRODUCT(B95:M95,B$2:M$2) -> 125.28658 | R95: =SUMIFS(B95:M95,$B$1:$M$1,$Y$3) -> 1836.5678
A96: FIXED CONVERSION | B96: =SUM(B90:B95) -> 589.32311 | C96: =SUM(C90:C95) -> 589.32311 | D96: =SUM(D90:D95) -> 589.32311 | E96: =SUM(E90:E95) -> 618.78927 | F96: =SUM(F90:F95) -> 412.52618 | G96: =SUM(G90:G95) -> 916.0131 | H96: =SUM(H90:H95) -> 739.85673 | I96: =SUM(I90:I95) -> 669.39419 | ... N96: =SUM(N90:N95) -> 8638.849 | Q96: =SUMPRODUCT(B96:M96,B$2:M$2) -> 589.32311 | R96: =SUMIFS(B96:M96,$B$1:$M$1,$Y$3) -> 8638.849
A97: TOTAL MFG COST w/o SHARES | B97: =B89+B96 -> 1220.1587 | C97: =C89+C96 -> 1219.9462 | D97: =D89+D96 -> 1219.9587 | E97: =E89+E96 -> 1219.46 | F97: =F89+F96 -> 872.41123 | G97: =G89+G96 -> 1581.8763 | H97: =H89+H96 -> 1265.5093 | I97: =I89+I96 -> 1158.8065 | ... N97: =N89+N96 -> 15702.162 | Q97: =SUMPRODUCT(B97:M97,B$2:M$2) -> 1220.1587 | R97: =SUMIFS(B97:M97,$B$1:$M$1,$Y$3) -> 15702.162
A98: TOTAL SHARES | B98: =B49 -> 8.2249305 | C98: =C49 -> 8.2249305 | D98: =D49 -> 8.2249305 | E98: =E49 -> 8.636177 | F98: =F49 -> 5.7574514 | G98: =G49 -> 12.784403 | H98: =H49 -> 10.325864 | I98: =I49 -> 9.3424482 | ... M98: =M49 -> 11.186084 | N98: =SUM(B98:M98) -> 120.56872 | Q98: =SUMPRODUCT(B98:M98,B$2:M$2) -> 8.2249305 | R98: =SUMIFS(B98:M98,$B$1:$M$1,$Y$3) -> 120.56872
A99: TOTAL MFG COST w/ SHARES | B99: =B97+B98 -> 1228.3836 | C99: =C97+C98 -> 1228.1711 | D99: =D97+D98 -> 1228.1836 | E99: =E97+E98 -> 1228.0962 | F99: =F97+F98 -> 878.16868 | G99: =G97+G98 -> 1594.6608 | H99: =H97+H98 -> 1275.8352 | I99: =I97+I98 -> 1168.1489 | ... N99: =N97+N98 -> 15822.731 | Q99: =SUMPRODUCT(B99:M99,B$2:M$2) -> 1228.3836 | R99: =SUMIFS(B99:M99,$B$1:$M$1,$Y$3) -> 15822.731
A100: Functional Currency Impact | B100: =B51 -> 344.37647 | C100: =C51 -> 344.37647 | D100: =D51 -> 344.37647 | E100: =E51 -> 361.5953 | F100: =F51 -> 241.06353 | G100: =G51 -> 535.28082 | H100: =H51 -> 432.3422 | I100: =I51 -> 391.16675 | ... M100: =M51 -> 468.35949 | N100: =SUM(B100:M100) -> 5048.1922 | Q100: =SUMPRODUCT(B100:M100,B$2:M$2) -> 344.37647 | R100: =SUMIFS(B100:M100,$B$1:$M$1,$Y$3) -> 5048.1922
A101: TOTAL Including FC | B101: =B99+B100 -> 1572.7601 | C101: =C99+C100 -> 1572.5476 | D101: =D99+D100 -> 1572.5601 | E101: =E99+E100 -> 1589.6915 | F101: =F99+F100 -> 1119.2322 | G101: =G99+G100 -> 2129.9416 | H101: =H99+H100 -> 1708.1774 | I101: =I99+I100 -> 1559.3157 | ... N101: =N99+N100 -> 20870.923 | Q101: =SUMPRODUCT(B101:M101,B$2:M$2) -> 1572.7601 | R101: =SUMIFS(B101:M101,$B$1:$M$1,$Y$3) -> 20870.923
A102: Scrap | B102: =B53+B74 -> 25.253539 | C102: =C53+C74 -> 25.245032 | D102: =D53+D74 -> 25.245532 | E102: =E53+E74 -> 24.045985 | F102: =F53+F74 -> 18.410067 | G102: =G53+G74 -> 26.655763 | H102: =H53+H74 -> 21.042865 | I102: =I53+I74 -> 19.592098 | ... M102: =M53+M74 -> 20.355765 | N102: =SUM(B102:M102) -> 282.75777 | Q102: =SUMPRODUCT(B102:M102,B$2:M$2) -> 25.253539 | R102: =SUMIFS(B102:M102,$B$1:$M$1,$Y$3) -> 282.75777
A103: Scrap Reselling | B103: =B54+B75 -> -62.06949 | C103: =C54+C75 -> -62.04858 | D103: =D54+D75 -> -62.04981 | E103: =E54+E75 -> -59.1015 | F103: =F54+F75 -> -45.24924 | G103: =G54+G75 -> -65.51595 | H103: =H54+H75 -> -51.72027 | I103: =I54+I75 -> -48.1545 | ... M103: =M54+M75 -> -50.03148 | N103: =SUM(B103:M103) -> -694.97706 | Q103: =SUMPRODUCT(B103:M103,B$2:M$2) -> -62.06949 | R103: =SUMIFS(B103:M103,$B$1:$M$1,$Y$3) -> -694.97706
A104: Other Variable (Inventory Adj) | B104: =B55+B76 -> 0 | C104: =C55+C76 -> 0 | D104: =D55+D76 -> 0 | E104: =E55+E76 -> 0 | F104: =F55+F76 -> 0 | G104: =G55+G76 -> 0 | H104: =H55+H76 -> 0 | I104: =I55+I76 -> 0 | ... M104: =M55+M76 -> 0 | N104: =SUM(B104:M104) -> 0 | Q104: =SUMPRODUCT(B104:M104,B$2:M$2) -> 0 | R104: =SUMIFS(B104:M104,$B$1:$M$1,$Y$3) -> 0
A105: Obsolete | N105: =SUM(B105:M105) -> 0 | Q105: =SUMPRODUCT(B105:M105,B$2:M$2) -> 0 | R105: =SUMIFS(B105:M105,$B$1:$M$1,$Y$3) -> 0
A106: Asset Sales | Q106: =SUMPRODUCT(B106:M106,B$2:M$2) -> 0 | R106: =SUMIFS(B106:M106,$B$1:$M$1,$Y$3) -> 0
A107: TOTAL OTHERS | B107: =SUM(B102:B106) -> -36.815951 | C107: =SUM(C102:C106) -> -36.803548 | D107: =SUM(D102:D106) -> -36.804278 | E107: =SUM(E102:E106) -> -35.055515 | F107: =SUM(F102:F106) -> -26.839173 | G107: =SUM(G102:G106) -> -38.860187 | H107: =SUM(H102:H106) -> -30.677405 | I107: =SUM(I102:I106) -> -28.562402 | ... N107: =SUM(N102:N106) -> -412.21929 | Q107: =SUMPRODUCT(B107:M107,B$2:M$2) -> -36.815951 | R107: =SUMIFS(B107:M107,$B$1:$M$1,$Y$3) -> -412.21929
...

Sheet MTD Report(HQD)_variance
A2: DW MTD JAN | B2: Budget25 | E2: Volume Variance | F2: Copertura | G2: HWTW&ACE | H2: Budget FCA | I2: Budget Flex. | J2: ACE | K2: MFG Efficiency | L2: S&OP | M2: Price / Inflation | N2: fX translation | O2: Oth Functions | P2: VARIANCE | Q2: Actual Cost | V2: BDG FX | W2: 52.48869
V3: ACT FX | W3: 50.745776
B4: ='data entry '!Q3 -> 48050 | E4: =Q4-B4 -> -3954 | Q4: ='data entry '!Q115 -> 44096
A5: - Gain / +Loss | E5: =E4/B4 -> -0.082289282 | T5: checkline
B6: EUR/000 | C6: €/pc | E6: EUR/000 | F6: EUR/000 | G6: EUR/000 | H6: EUR/000 | I6: EUR/000 | J6: EUR/000 | K6: EUR/000 | L6: EUR/000 | M6: EUR/000 | N6: EUR/001 | O6: EUR/000 | P6: EUR/000 | Q6: EUR/000 | R6: €/pc | W6: MFG | X6: PRICE&FX | Y6: GROSS | AB6: Direct Labour | AC6: Ace | AD6: -3 K€ gain --> Line speed 130 to 135 & Injection parts TC improvement(3 sec)
A7: Direct Labor | B7: ='data entry '!Q5 -> 509 | C7: =B7/$B$4*1000 -> 10.593132 | E7: =I7-B7 -> -81.439038 | F7: ='data entry '!Q84 -> 465.28736 | G7: ='data entry '!Q39 -> -37.726399 | I7: =F7+G7 -> 427.56096 | J7: =+('ACE Details_FULL'!D29)/1000*-1+('ACE Details_FULL'!D5-'ACE Details_FULL'!D24)/1000 -> -2.6503804 | K7: =19-23 -> -4 | L7: =(248-302)*1600/1000-3.3 -> -89.7 | M7: =12+10-4+7.36 -> 25.36 | N7: 5.3312814 | P7: =SUM(J7:O7) -> -65.659099 | Q7: ='data entry '!Q117 -> 363.73443 | R7: =Q7*1000/$Q$4 -> 8.2486945 | T7: =+Q7-I7-P7 -> 1.83257 | W7: =SUM(I7:L7)*1000/$Q$4 -> 7.5111253 | X7: =+Y7-W7 -> 0.7375692 | Y7: =R7 -> 8.2486945 | Z7: =+SUM(M7:O7)*1000/$Q$4-X7 -> -0.041558644 | AC7: MFG | AD7: Act 94.96 % eff vs Bdg 98 %--> 19 K€ loss, with transfer 99.75 % --> -23 K€ gain
A8: Variable Utilities | B8: ='data entry '!Q6 -> 35.733562 | C8: =B8/$B$4*1000 -> 0.74367454 | E8: =I8-B8 -> -6.1388453 | F8: ='data entry '!Q85 -> 30.915274 | G8: ='data entry '!Q40 -> -1.3205572 | I8: =F8+G8 -> 29.594716 | K8: -6.31 | M8: -1 | N8: 0.4177415 | P8: =SUM(J8:O8) -> -6.8922585 | Q8: ='data entry '!Q118 -> 28.06842 | R8: =Q8*1000/$Q$4 -> 0.63652984 | T8: =+Q8-I8-P8 -> 5.365962 | W8: =SUM(I8:L8)*1000/$Q$4 -> 0.528046 | X8: =+Y8-W8 -> 0.10848384 | Y8: =R8 -> 0.63652984 | Z8: =+SUM(M8:O8)*1000/$Q$4-X8 -> -0.12168818 | AC8: Price | AD8: 12 K€ loss salary,10 K€ loss overtime, -4 K€ gain annual leave, 7.36 K€ loss indemnity,
A9: Other Variable (Production Consumable) | B9: ='data entry '!Q7 -> 15.8935 | C9: =B9/$B$4*1000 -> 0.33077003 | E9: =I9-B9 -> -3.621002 | F9: ='data entry '!Q86 -> 13.272976 | G9: ='data entry '!Q41 -> -1.0004778 | I9: =F9+G9 -> 12.272498 | J9: =+'ACE Details_FULL'!D32/1000*-1 -> -1 | K9: -1.09 | N9: 0.25443126 | P9: =SUM(J9:O9) -> -1.8355687 | Q9: ='data entry '!Q119 -> 38.19678 | R9: =Q9*1000/$Q$4 -> 0.8662187 | T9: =+Q9-I9-P9 -> 27.759851 | W9: =SUM(I9:L9)*1000/$Q$4 -> 0.23091659 | X9: =+Y9-W9 -> 0.63530211 | Y9: =R9 -> 0.8662187 | Z9: =+SUM(M9:O9)*1000/$Q$4-X9 -> -0.62953217
A10: Variable Conv. | B10: =SUM(B7:B9) -> 560.62706 | C10: =B10/$B$4*1000 -> 11.667577 | E10: =SUM(E7:E9) -> -91.198886 | F10: =SUM(F7:F9) -> 509.47561 | G10: =SUM(G7:G9) -> -40.047434 | H10: =SUM(H7:H9) -> 0 | I10: =SUM(I7:I9) -> 469.42818 | J10: =SUM(J7:J9) -> -3.6503804 | K10: =SUM(K7:K9) -> -11.4 | L10: =SUM(L7:L9) -> -89.7 | ... Q10: =SUM(Q7:Q9) -> 429.99963 | R10: =Q10*1000/$Q$4 -> 9.751443 | T10: =+Q10-I10-P10 -> 34.958383 | W10: =SUM(I10:L10)*1000/$Q$4 -> 8.2700879 | X10: =+Y10-W10 -> 1.4813552 | Y10: =R10 -> 9.751443 | Z10: =+SUM(M10:O10)*1000/$Q$4-X10 -> -0.792779 | AB10: Indirect Labour | AC10: MFG | AD10: 9K€ loss 593 HOURS UNION PROTEST DIR TO IND + 17 K€ loss 1156 HOURS INVENTORY COUNT DIR TO IND
A11: Indirect Labour | B11: ='data entry '!Q9 -> 204.69927 | C11: =B11/$B$4*1000 -> 4.2601306 | F11: ='data entry '!Q88 -> 184.03658 | G11: ='data entry '!Q43 -> -10.85718 | H11: ='Budget assumption'!Q323 -> -19.917773 | I11: =B11 -> 204.69927 | K11: 26.69 | M11: 12.64 | N11: 2.44 | P11: =SUM(J11:O11) -> 41.77 | Q11: ='data entry '!Q121 -> 211.92001 | R11: =Q11*1000/$Q$4 -> 4.8058783 | T11: =+Q11-I11-P11 -> -34.549267 | W11: =SUM(I11:L11)*1000/$Q$4 -> 5.2473983 | X11: =+Y11-W11 -> -0.44152001 | Y11: =R11 -> 4.8058783 | Z11: =+SUM(M11:O11)*1000/$Q$4-X11 -> 0.78350115 | AC11: Price | AD11: 5.22 K€ loss salary, (Bdg 25 % vs act 30%) 3.6 K€ loss overtime salary, 3 K€ loss annual leave, 0.9 K€ loss indemnity,
A12: Fixed Labour | B12: ='data entry '!Q10 -> 104.32865 | C12: =B12/$B$4*1000 -> 2.1712517 | F12: ='data entry '!Q89 -> 65.067655 | G12: ='data entry '!Q44 -> 26.357974 | H12: ='Budget assumption'!Q324 -> -7.2046193 | I12: =B12 -> 104.32865 | K12: -2.35 | M12: =8+2.8 -> 10.8 | N12: 0.14392454 | P12: =SUM(J12:O12) -> 8.5939245 | Q12: ='data entry '!Q122 -> 86.26424 | R12: =Q12*1000/$Q$4 -> 1.9562827 | T12: =+Q12-I12-P12 -> -26.658331 | W12: =SUM(I12:L12)*1000/$Q$4 -> 2.3126507 | X12: =+Y12-W12 -> -0.35636807 | Y12: =R12 -> 1.9562827 | Z12: =+SUM(M12:O12)*1000/$Q$4-X12 -> 0.60455214
A13: Semifixed | B13: ='data entry '!Q11 -> 177.19911 | C13: =B13/$B$4*1000 -> 3.6878066 | F13: ='data entry '!Q90 -> 126.16662 | G13: ='data entry '!Q45 -> 26.665011 | H13: ='Budget assumption'!Q325 -> -13.9096 | I13: =B13 -> 177.19911 | K13: -23.07 | M13: -2 | N13: 6.1386217 | P13: =SUM(J13:O13) -> -18.931378 | Q13: ='data entry '!Q123 -> 86.23783 | R13: =Q13*1000/$Q$4 -> 1.9556837 | T13: =+Q13-I13-P13 -> -72.029899 | W13: =SUM(I13:L13)*1000/$Q$4 -> 3.4953081 | X13: =+Y13-W13 -> -1.5396244 | Y13: =R13 -> 1.9556837 | Z13: =+SUM(M13:O13)*1000/$Q$4-X13 -> 1.6334792 | AB13: Fixed Labour | AC13: MFG | AD13: -2.3 K€ shared gain (1 HC HQD)
A14: Fixed utilities | B14: ='data entry '!Q12 -> 5 | C14: =B14/$B$4*1000 -> 0.10405827 | F14: ='data entry '!Q91 -> 6.95061 | G14: ='data entry '!Q46 -> -4.5767532 | H14: ='Budget assumption'!Q326 -> -0.88490785 | I14: =B14 -> 5 | M14: -0.78 | N14: 0.060051175 | P14: =SUM(J14:O14) -> -0.71994883 | Q14: ='data entry '!Q124 -> 3.80533 | R14: =Q14*1000/$Q$4 -> 0.086296489 | T14: =+Q14-I14-P14 -> -0.47472117 | W14: =SUM(I14:L14)*1000/$Q$4 -> 0.11338897 | X14: =+Y14-W14 -> -0.02709248 | Y14: =R14 -> 0.086296489 | Z14: =+SUM(M14:O14)*1000/$Q$4-X14 -> 0.010765629 | AC14: Price | AD14: 7 K€ loss annual leave, 1 K€ loss MBO, 2.8 K€ loss others
A15: Fixed Cost | B15: ='data entry '!Q13 -> 43.218668 | C15: =B15/$B$4*1000 -> 0.899452 | F15: ='data entry '!Q92 -> 32.152644 | G15: ='data entry '!Q47 -> 9.6182841 | H15: ='Budget assumption'!Q327 -> -3.1047312 | I15: =B15 -> 43.218668 | K15: 2.19 | N15: 1.2860963 | P15: =SUM(J15:O15) -> 3.4760963 | Q15: ='data entry '!Q125 -> -2.69822 | R15: =Q15*1000/$Q$4 -> -0.061189677 | T15: =+Q15-I15-P15 -> -49.392985 | W15: =SUM(I15:L15)*1000/$Q$4 -> 1.0297684 | X15: =+Y15-W15 -> -1.0909581 | Y15: =R15 -> -0.061189677 | Z15: =+SUM(M15:O15)*1000/$Q$4-X15 -> 1.1201239
A16: Depreciation | B16: ='data entry '!Q14 -> 155.0923 | C16: =B16/$B$4*1000 -> 3.2277274 | F16: ='data entry '!Q93 -> 424.54616 | G16: ='data entry '!Q48 -> 23.541396 | H16: ='Budget assumption'!Q329 -> -12.155522 | I16: =B16 -> 155.0923 | N16: 9.56 | P16: =SUM(J16:O16) -> 9.56 | Q16: ='data entry '!Q126 -> -7.09792 | R16: =Q16*1000/$Q$4 -> -0.16096517 | T16: =+Q16-I16-P16 -> -171.75022 | W16: =SUM(I16:L16)*1000/$Q$4 -> 3.5171512 | X16: =+Y16-W16 -> -3.6781164 | Y16: =R16 -> -0.16096517 | Z16: =+SUM(M16:O16)*1000/$Q$4-X16 -> 3.8949161 | AB16: Variable Utilities | AC16: MFG | AD16: -4.31 K€ Direct Electricity consumption Effect, -2 K€ gas consumption effect
A17: Fixed Conv. | B17: =SUM(B11:B16) -> 689.538 | C17: =B17/$B$4*1000 -> 14.350427 | E17: =SUM(E11:E16) -> 0 | F17: =SUM(F11:F16) -> 838.92027 | G17: =SUM(G11:G16) -> 70.748731 | H17: =SUM(H11:H16) -> -57.177153 | I17: =SUM(I11:I16) -> 689.538 | J17: =SUM(J11:J16) -> 0 | K17: =SUM(K11:K16) -> 3.46 | L17: =SUM(L11:L16) -> 0 | ... Q17: =SUM(Q11:Q16) -> 378.43127 | R17: =Q17*1000/$Q$4 -> 8.5819863 | T17: =+Q17-I17-P17 -> -354.85542 | W17: =SUM(I17:L17)*1000/$Q$4 -> 15.715666 | X17: =+Y17-W17 -> -7.1336795 | Y17: =R17 -> 8.5819863 | Z17: =+SUM(M17:O17)*1000/$Q$4-X17 -> 8.0473382 | AC17: Price | AD17: -1 K€ grid price electiricity gain
A18: TOTAL MFG COST w/o SHARES | B18: =B10+B17 -> 1250.1651 | C18: =B18/$B$4*1000 -> 26.018003 | E18: =E10+E17 -> -91.198886 | F18: =F10+F17 -> 1348.3959 | G18: =G10+G17 -> 30.701297 | H18: =H10+H17 -> -57.177153 | I18: =I10+I17 -> 1158.9662 | J18: =J10+J17 -> -3.6503804 | K18: =K10+K17 -> -7.94 | L18: =L10+L17 -> -89.7 | ... Q18: =Q10+Q17 -> 808.4309 | R18: =Q18*1000/$Q$4 -> 18.333429 | T18: =+Q18-I18-P18 -> -319.89704 | W18: =SUM(I18:L18)*1000/$Q$4 -> 23.985754 | X18: =+Y18-W18 -> -5.6523243 | Y18: =R18 -> 18.333429 | Z18: =+SUM(M18:O18)*1000/$Q$4-X18 -> 7.2545592
A19: TOTAL SHARES | B19: ='data entry '!Q17 -> 20.567044 | C19: =B19/$B$4*1000 -> 0.42803422 | F19: ='data entry '!Q96 -> 0 | G19: ='data entry '!Q51 -> 11.930867 | H19: ='Budget assumption'!Q331 -> -0.79799706 | I19: =B19 -> 20.567044 | K19: -3.85 | P19: =SUM(J19:O19) -> -3.85 | Q19: ='data entry '!Q129 -> 13.04747 | R19: =Q19*1000/$Q$4 -> 0.29588784 | T19: =+Q19-I19-P19 -> -3.669574 | W19: =SUM(I19:L19)*1000/$Q$4 -> 0.37910568 | X19: =+Y19-W19 -> -0.083217844 | Y19: =R19 -> 0.29588784 | Z19: =+SUM(M19:O19)*1000/$Q$4-X19 -> 0.083217844 | AB19: Semifixed | AC19: MFG | AD19: -12.4 K€ gain maintenance, -8 K€ gain meals, -1.3 K€ gain shuttle, -1.3 K€ gain stationery,
A20: TOTAL MFG COST w/ SHARES | B20: =B18+B19 -> 1270.7321 | C20: =B20/$B$4*1000 -> 26.446038 | E20: =E18+E19 -> -91.198886 | F20: =F18+F19 -> 1348.3959 | G20: =G18+G19 -> 42.632164 | H20: =H18+H19 -> -57.97515 | I20: =I18+I19 -> 1179.5332 | J20: =J18+J19 -> -3.6503804 | K20: =K18+K19 -> -11.79 | L20: =L18+L19 -> -89.7 | ... Q20: =Q18+Q19 -> 821.47837 | R20: =Q20*1000/$Q$4 -> 18.629317 | T20: =+Q20-I20-P20 -> -323.56661 | W20: =SUM(I20:L20)*1000/$Q$4 -> 24.364859 | X20: =+Y20-W20 -> -5.7355422 | Y20: =R20 -> 18.629317 | Z20: =+SUM(M20:O20)*1000/$Q$4-X20 -> 7.337777 | AC20: Price | AD20: -1 k€ gain meals, -1 K€ gain shuttle
T21: =+Q21-I21-P21 -> 0
A22: Functional Currency Impact | B22: ='data entry '!Q19 -> 413.13905 | C22: =B22/$B$4*1000 -> 8.5981072 | F22: ='data entry '!Q98 -> 0 | G22: ='data entry '!Q53 -> 51.543756 | H22: =+'Budget assumption'!Q333 -> -33.412004 | I22: =B22 -> 413.13905 | N22: -22.79 | P22: =SUM(J22:O22) -> -22.79 | Q22: ='data entry '!Q131 -> 36.99522 | R22: =Q22*1000/$Q$4 -> 0.83896997 | T22: =+Q22-I22-P22 -> -353.35383 | W22: =SUM(I22:L22)*1000/$Q$4 -> 9.3690823 | X22: =+Y22-W22 -> -8.5301123 | Y22: =R22 -> 0.83896997 | Z22: =+SUM(M22:O22)*1000/$Q$4-X22 -> 8.0132854 | AB22: Fixed Utiliites | AC22: Price | AD22: -1 K€ price gain
A23: TOTAL Including FC | B23: =+B22+B20 -> 1683.8712 | C23: =B23/$B$4*1000 -> 35.044145 | E23: =+E22+E20 -> -91.198886 | F23: =+F22+F20 -> 1348.3959 | G23: =+G22+G20 -> 94.17592 | H23: =+H22+H20 -> -91.387154 | I23: =+I22+I20 -> 1592.6723 | J23: =+J22+J20 -> -3.6503804 | K23: =+K22+K20 -> -11.79 | L23: =+L22+L20 -> -89.7 | ... Q23: =+Q22+Q20 -> 858.47359 | R23: =Q23*1000/$Q$4 -> 19.468287 | T23: =+Q23-I23-P23 -> -676.92045 | W23: =SUM(I23:L23)*1000/$Q$4 -> 33.733942 | X23: =+Y23-W23 -> -14.265654 | Y23: =R23 -> 19.468287 | Z23: =+SUM(M23:O23)*1000/$Q$4-X23 -> 15.351062
T24: =+Q24-I24-P24 -> 0 | Y24: =R24 -> 0 | AB24: Fixed Cost | AC24: MFG | AD24: 7 K€ loss accrual for suitcase, -2 K€ gain travel, -2.5 K€ gain training
A25: Scrap | B25: ='data entry '!Q21 -> 19 | C25: =B25/$B$4*1000 -> 0.39542144 | E25: =I25-B25 -> -4.2333329 | F25: ='data entry '!Q100 -> 19.811558 | G25: ='data entry '!Q55 -> -5.0448908 | I25: =F25+G25 -> 14.766667 | K25: =+(0.4-0.54)*Q4/1000-0.49 -> -6.66344 | M25: =-519.09/1000 -> -0.51909 | N25: 1.2846767 | P25: =SUM(J25:O25) -> -5.8978533 | Q25: ='data entry '!Q133 -> 50.45741 | R25: =Q25*1000/$Q$4 -> 1.1442627 | T25: =+Q25-I25-P25 -> 41.588596 | W25: =SUM(I25:L25)*1000/$Q$4 -> 0.18376331 | X25: =+Y25-W25 -> 0.96049943 | Y25: =R25 -> 1.1442627 | Z25: =+SUM(M25:O25)*1000/$Q$4-X25 -> -0.94313761
A26: Scrap Reselling | B26: ='data entry '!Q22 -> -48 | C26: =B26/$B$4*1000 -> -0.99895942 | E26: =I26-B26 -> 10.213227 | F26: ='data entry '!Q101 -> -48.888273 | G26: ='data entry '!Q56 -> 11.1015 | I26: =F26+G26 -> -37.786773 | K26: 6 | M26: =-1-10.13 -> -11.13 | N26: -2 | P26: =SUM(J26:O26) -> -7.13 | Q26: ='data entry '!Q134 -> -53.89348 | R26: =Q26*1000/$Q$4 -> -1.2221852 | T26: =+Q26-I26-P26 -> -8.9767074 | W26: =SUM(I26:L26)*1000/$Q$4 -> -0.72085388 | X26: =+Y26-W26 -> -0.50133135 | Y26: =R26 -> -1.2221852 | Z26: =+SUM(M26:O26)*1000/$Q$4-X26 -> 0.20357192 | AB26: Scrap | AC26: MFG | AD26: Act 0.40 €/box, bdg 0.54 €/box
A27: Other Variable (Inventory Adj) | B27: ='data entry '!Q23 -> 0 | C27: =B27/$B$4*1000 -> 0 | F27: ='data entry '!Q102 -> 0 | G27: ='data entry '!Q57 -> 0 | I27: =F27+G27 -> 0 | K27: -0.23 | M27: -2.5 | P27: =SUM(J27:O27) -> -2.73 | Q27: ='data entry '!Q135 -> 65.57718 | R27: =Q27*1000/$Q$4 -> 1.4871458 | T27: =+Q27-I27-P27 -> 68.30718 | W27: =SUM(I27:L27)*1000/$Q$4 -> -0.0052158926 | X27: =+Y27-W27 -> 1.4923617 | Y27: =R27 -> 1.4871458 | Z27: =+SUM(M27:O27)*1000/$Q$4-X27 -> -1.5490562
A28: Obsolete | B28: ='data entry '!Q24 -> 9 | C28: =B28/$B$4*1000 -> 0.18730489 | F28: ='data entry '!Q103 -> 0 | G28: ='data entry '!Q58 -> 9 | H28: ='Budget assumption'!Q328 -> 0 | I28: =B28 -> 9 | K28: -35.07 | P28: =SUM(J28:O28) -> -35.07 | Q28: ='data entry '!Q136 -> -177.1679 | R28: =Q28*1000/$Q$4 -> -4.0177771 | T28: =+Q28-I28-P28 -> -151.0979 | W28: =SUM(I28:L28)*1000/$Q$4 -> -0.59121009 | X28: =+Y28-W28 -> -3.426567 | Y28: =R28 -> -4.0177771 | Z28: =+SUM(M28:O28)*1000/$Q$4-X28 -> 3.426567 | AB28: Scrap Reselling | AC28: MFG
A29: Asset Sales | B29: ='data entry '!Q25 -> 0 | C29: =B29/$B$4*1000 -> 0 | F29: ='data entry '!Q104 -> 0 | G29: ='data entry '!Q59 -> 0 | I29: =B29 -> 0 | P29: =SUM(J29:O29) -> 0 | Q29: ='data entry '!Q137 -> 0 | R29: =Q29*1000/$Q$4 -> 0 | T29: =+Q29-I29-P29 -> 0 | W29: =SUM(I29:L29)*1000/$Q$4 -> 0 | X29: =+Y29-W29 -> 0 | Y29: =R29 -> 0 | Z29: =+SUM(M29:O29)*1000/$Q$4-X29 -> 0 | AC29: Price
A30: TOTAL OTHERS | B30: =SUM(B25:B29) -> -20 | C30: =B30/$B$4*1000 -> -0.41623309 | E30: =SUM(E25:E29) -> 5.9798944 | F30: =SUM(F25:F29) -> -29.076715 | G30: =SUM(G25:G29) -> 15.056609 | H30: =SUM(H25:H29) -> 0 | I30: =SUM(I25:I29) -> -14.020106 | J30: =SUM(J25:J29) -> 0 | K30: =SUM(K25:K29) -> -35.96344 | L30: =SUM(L25:L29) -> 0 | ... Q30: =SUM(Q25:Q29) -> -115.02679 | R30: =Q30*1000/$Q$4 -> -2.6085538 | T30: =+Q30-I30-P30 -> -50.178831 | W30: =SUM(I30:L30)*1000/$Q$4 -> -1.1335165 | X30: =+Y30-W30 -> -1.4750373 | Y30: =R30 -> -2.6085538 | Z30: =+SUM(M30:O30)*1000/$Q$4-X30 -> 1.1379452
T31: =+Q31-I31-P31 -> 0 | AB31: Obsolete | AC31: MFG | AD31: 172 K € stock aging report accrual, Yend 197 K€
A32: IT GLOBAL | B32: ='data entry '!Q27 -> 90.697223 | C32: =B32/$B$4*1000 -> 1.8875593 | F32: ='data entry '!Q106 -> 64.814167 | G32: ='data entry '!Q61 -> 7.1875052 | H32: ='Budget assumption'!Q335 -> -7.7164362 | I32: =B32 -> 90.697223 | N32: -1.81 | P32: =SUM(J32:O32) -> -1.81 | Q32: ='data entry '!Q139 -> 89.41512 | R32: =Q32*1000/$Q$4 -> 2.0277377 | T32: =+Q32-I32-P32 -> 0.5278975 | W32: =SUM(I32:L32)*1000/$Q$4 -> 2.0568129 | X32: =+Y32-W32 -> -0.029075256 | Y32: =R32 -> 2.0277377 | Z32: =+SUM(M32:O32)*1000/$Q$4-X32 -> -0.011971551
A33: G&A(Insurance included) | B33: ='data entry '!Q28 -> 94.532002 | C33: =B33/$B$4*1000 -> 1.9673674 | F33: ='data entry '!Q107 -> 67.554582 | G33: ='data entry '!Q62 -> 23.993521 | H33: ='Budget assumption'!Q336 -> -6.5178725 | I33: =B33 -> 94.532002 | M33: 24.48 | P33: =SUM(J33:O33) -> 24.48 | Q33: ='data entry '!Q140 -> 68.80723 | R33: =Q33*1000/$Q$4 -> 1.5603962 | T33: =+Q33-I33-P33 -> -50.204772 | W33: =SUM(I33:L33)*1000/$Q$4 -> 2.1437773 | X33: =+Y33-W33 -> -0.58338108 | Y33: =R33 -> 1.5603962 | Z33: =+SUM(M33:O33)*1000/$Q$4-X33 -> 1.1385335 | AB33: G&A(Insurance included) | AC33: Price | AD33: 7 K€ loss will be corrected in Feb closure related to insurance cycle
A34: TOTAL OVERHEAD | B34: =B32+B33 -> 185.22922 | C34: =B34/$B$4*1000 -> 3.8549266 | E34: =E32+E33 -> 0 | F34: =F32+F33 -> 132.36875 | G34: =G32+G33 -> 31.181026 | H34: =H32+H33 -> -14.234309 | I34: =I32+I33 -> 185.22922 | J34: =J32+J33 -> 0 | K34: =K32+K33 -> 0 | L34: =L32+L33 -> 0 | ... Q34: =Q32+Q33 -> 158.22235 | R34: =Q34*1000/$Q$4 -> 3.5881338 | T34: =+Q34-I34-P34 -> -49.676875 | W34: =SUM(I34:L34)*1000/$Q$4 -> 4.2005902 | X34: =+Y34-W34 -> -0.61245634 | Y34: =R34 -> 3.5881338 | Z34: =+SUM(M34:O34)*1000/$Q$4-X34 -> 1.1265619 | AD34: 15 K€ loss will be corrected in Feb closure related to IT cycle
R35: =Q35*1000/$Q$4 -> 0 | T35: =+Q35-I35-P35 -> 0 | AD35: 18 K€ loss labour loss related with unused vacation accruals
A36: TOTAL ALL | B36: =B23+B30+B34 -> 1849.1004 | C36: =B36/$B$4*1000 -> 38.482838 | E36: =E23+E30+E34 -> -85.218991 | F36: =F23+F30+F34 -> 1451.6879 | G36: =G23+G30+G34 -> 140.41355 | H36: =H23+H30+H34 -> -105.62146 | I36: =I23+I30+I34 -> 1763.8814 | J36: =J23+J30+J34 -> -3.6503804 | K36: =K23+K30+K34 -> -47.75344 | L36: =L23+L30+L34 -> -89.7 | ... Q36: =Q23+Q30+Q34 -> 901.66915 | R36: =Q36*1000/$Q$4 -> 20.447867 | T36: =+Q36-I36-P36 -> -776.77615 | W36: =SUM(I36:L36)*1000/$Q$4 -> 36.801015 | X36: =+Y36-W36 -> -16.353148 | Y36: =R36 -> 20.447867 | Z36: =+SUM(M36:O36)*1000/$Q$4-X36 -> 17.615569
A38: Highlights;
A41: Direct Labour | B41: Ace | C41: -3 K€ gain --> Line speed 130 to 135 & Injection parts TC improvement(3 sec)
B42: MFG | C42: Act 94.96 % eff vs Bdg 98 %--> 19 K€ loss, with transfer 99.75 % --> -23 K€ gain
B43: Price | C43: 12 K€ loss salary,10 K€ loss overtime, -4 K€ gain annual leave, 7.36 K€ loss indemnity,
A45: Indirect Labour | B45: MFG | C45: 9K€ loss 593 HOURS UNION PROTEST DIR TO IND + 17 K€ loss 1156 HOURS INVENTORY COUNT DIR TO IND
B46: Price | C46: 5.22 K€ loss salary, (Bdg 25 % vs act 30%) 3.6 K€ loss overtime salary, 3 K€ loss annual leave, 0.9 K€ loss indemnity,
A48: Fixed Labour | B48: MFG | C48: -2.3 K€ shared gain (1 HC HQD)
B49: Price | C49: 7 K€ loss annual leave, 1 K€ loss MBO, 2.8 K€ loss others
A51: Variable Utilities | B51: MFG | C51: -4.31 K€ Direct Electricity consumption Effect, -2 K€ gas consumption effect
B52: Price | C52: -1 K€ grid price electiricity gain
A54: Semifixed | B54: MFG | C54: -12.4 K€ gain maintenance, -8 K€ gain meals, -1.3 K€ gain shuttle, -1.3 K€ gain stationery,
B55: Price | C55: -1 k€ gain meals, -1 K€ gain shuttle
A57: Fixed Utiliites | B57: Price | C57: -1 K€ price gain
A59: Fixed Cost | B59: MFG | C59: 7 K€ loss accrual for suitcase, -2 K€ gain travel, -2.5 K€ gain training
A61: Scrap | B61: MFG | C61: Act 0.40 €/box, bdg 0.54 €/box
A63: Scrap Reselling | B63: MFG
B64: Price
A66: Obsolete | B66: MFG | C66: 172 K € stock aging report accrual, Yend 197 K€
A68: G&A(Insurance included) | B68: Price | C68: 7 K€ loss will be corrected in Feb closure related to insurance cycle
C69: 15 K€ loss will be corrected in Feb closure related to IT cycle
C70: 18 K€ loss labour loss related with unused vacation accruals

Sheet YTD Report(HQD)_variance 
A2: DW MTD JAN | B2: Budget25 | E2: Volume Variance | F2: Copertura | G2: HWTW&ACE | H2: Budget FCA | I2: Budget Flex. | J2: ACE | K2: MFG Efficiency | L2: S&OP | M2: Price / Inflation | N2: fX translation | O2: Oth Functions | P2: VARIANCE | Q2: Actual Cost
B4: ='data entry '!R3 -> 565022 | E4: =Q4-B4 -> -38794.996 | Q4: ='data entry '!R115 -> 526227
A5: - Gain / +Loss | E5: =E4/B4 -> -0.068661036 | T5: checkline
B6: EUR/000 | C6: €/pc | E6: EUR/000 | F6: EUR/000 | G6: EUR/000 | H6: EUR/000 | I6: EUR/000 | J6: EUR/000 | K6: EUR/000 | L6: EUR/000 | M6: EUR/000 | N6: EUR/001 | O6: EUR/000 | P6: EUR/000 | Q6: EUR/000 | R6: €/pc
A7: Direct Labor | B7: ='data entry '!R5 -> 6077 | C7: =B7/$B$4*1000 -> 10.755333 | E7: =I7-B7 -> -468.46359 | F7: ='data entry '!R84 -> 5960.5155 | G7: ='data entry '!R39 -> -351.97905 | I7: =F7+G7 -> 5608.5364 | P7: =SUM(J7:O7) -> 0 | Q7: ='data entry '!R117 -> 5008.7027 | R7: =Q7*1000/$Q$4 -> 9.5181408 | T7: =I7+P7-Q7 -> 599.8337
A8: Variable Utilities | B8: ='data entry '!R6 -> 405.32207 | C8: =B8/$B$4*1000 -> 0.71735626 | E8: =I8-B8 -> -34.043398 | F8: ='data entry '!R85 -> 401.67757 | G8: ='data entry '!R40 -> -30.398899 | I8: =F8+G8 -> 371.27867 | P8: =SUM(J8:O8) -> 0 | Q8: ='data entry '!R118 -> 359.05777 | R8: =Q8*1000/$Q$4 -> 0.68232487 | T8: =I8+P8-Q8 -> 12.220895
A9: Other Variable (Production Consumable) | B9: ='data entry '!R7 -> 185.03175 | C9: =B9/$B$4*1000 -> 0.32747707 | E9: =I9-B9 -> -18.780879 | F9: ='data entry '!R86 -> 179.83247 | G9: ='data entry '!R41 -> -13.581597 | I9: =F9+G9 -> 166.25087 | P9: =SUM(J9:O9) -> 0 | Q9: ='data entry '!R119 -> 187.28832 | R9: =Q9*1000/$Q$4 -> 0.35590785 | T9: =I9+P9-Q9 -> -21.037449
A10: Variable Conv. | B10: =SUM(B7:B9) -> 6667.3538 | C10: =B10/$B$4*1000 -> 11.800167 | E10: =SUM(E7:E9) -> -521.28787 | F10: =SUM(F7:F9) -> 6542.0255 | G10: =SUM(G7:G9) -> -395.95955 | H10: =SUM(H7:H9) -> 0 | I10: =SUM(I7:I9) -> 6146.0659 | J10: =SUM(J7:J9) -> 0 | K10: =SUM(K7:K9) -> 0 | L10: =SUM(L7:L9) -> 0 | ... Q10: =SUM(Q7:Q9) -> 5555.0488 | R10: =Q10*1000/$Q$4 -> 10.556374 | T10: =I10+P10-Q10 -> 591.01714
A11: Indirect Labour | B11: ='data entry '!R9 -> 2701.3288 | C11: =B11/$B$4*1000 -> 4.7809268 | F11: ='data entry '!R88 -> 2343.4368 | G11: ='data entry '!R43 -> -308.03119 | H11: ='Budget assumption'!R323 -> 487.74222 | I11: =B11 -> 2701.3288 | P11: =SUM(J11:O11) -> 0 | Q11: ='data entry '!R121 -> 2800.1829 | R11: =Q11*1000/$Q$4 -> 5.3212451 | T11: =I11+P11-Q11 -> -98.854048
A12: Fixed Labour | B12: ='data entry '!R10 -> 1249.4242 | C12: =B12/$B$4*1000 -> 2.2112842 | F12: ='data entry '!R89 -> 842.15253 | G12: ='data entry '!R44 -> 160.88421 | H12: ='Budget assumption'!R324 -> 176.42519 | I12: =B12 -> 1249.4242 | P12: =SUM(J12:O12) -> 0 | Q12: ='data entry '!R122 -> 1250.2818 | R12: =Q12*1000/$Q$4 -> 2.3759362 | T12: =I12+P12-Q12 -> -0.85756869
A13: Semifixed | B13: ='data entry '!R11 -> 2155.81 | C13: =B13/$B$4*1000 -> 3.8154444 | F13: ='data entry '!R90 -> 1627.5617 | G13: ='data entry '!R45 -> 54.22 | H13: ='Budget assumption'!R325 -> 340.61534 | I13: =B13 -> 2155.81 | P13: =SUM(J13:O13) -> 0 | Q13: ='data entry '!R123 -> 2131.3842 | R13: =Q13*1000/$Q$4 -> 4.0503133 | T13: =I13+P13-Q13 -> 24.425766
A14: Fixed utilities | B14: ='data entry '!R12 -> 66 | C14: =B14/$B$4*1000 -> 0.11680961 | F14: ='data entry '!R91 -> 99.464137 | G14: ='data entry '!R46 -> -67.7 | H14: ='Budget assumption'!R326 -> 21.669436 | I14: =B14 -> 66 | P14: =SUM(J14:O14) -> 0 | Q14: ='data entry '!R124 -> 65.036253 | R14: =Q14*1000/$Q$4 -> 0.12358973 | T14: =I14+P14-Q14 -> 0.96374675
A15: Fixed Cost | B15: ='data entry '!R13 -> 513.11153 | C15: =B15/$B$4*1000 -> 0.90812664 | F15: ='data entry '!R92 -> 415.82133 | G15: ='data entry '!R47 -> 44.020248 | H15: ='Budget assumption'!R327 -> 76.028 | I15: =B15 -> 513.11153 | P15: =SUM(J15:O15) -> 0 | Q15: ='data entry '!R125 -> 477.52255 | R15: =Q15*1000/$Q$4 -> 0.90744593 | T15: =I15+P15-Q15 -> 35.588975
A16: Depreciation | B16: ='data entry '!R14 -> 1955.7778 | C16: =B16/$B$4*1000 -> 3.4614188 | F16: ='data entry '!R93 -> 5371.6817 | G16: ='data entry '!R48 -> 119.21 | H16: ='Budget assumption'!R329 -> 297.66184 | I16: =B16 -> 1955.7778 | P16: =SUM(J16:O16) -> 0 | Q16: ='data entry '!R126 -> 1779.6216 | R16: =Q16*1000/$Q$4 -> 3.3818516 | T16: =I16+P16-Q16 -> 176.15614
A17: Fixed Conv. | B17: =SUM(B11:B16) -> 8641.4523 | C17: =B17/$B$4*1000 -> 15.29401 | E17: =SUM(E11:E16) -> 0 | F17: =SUM(F11:F16) -> 10700.118 | G17: =SUM(G11:G16) -> 2.6032609 | H17: =SUM(H11:H16) -> 1400.142 | I17: =SUM(I11:I16) -> 8641.4523 | J17: =SUM(J11:J16) -> 0 | K17: =SUM(K11:K16) -> 0 | L17: =SUM(L11:L16) -> 0 | ... Q17: =SUM(Q11:Q16) -> 8504.0293 | R17: =Q17*1000/$Q$4 -> 16.160382 | T17: =I17+P17-Q17 -> 137.42301
A18: TOTAL MFG COST w/o SHARES | B18: =B10+B17 -> 15308.806 | C18: =B18/$B$4*1000 -> 27.094177 | E18: =E10+E17 -> -521.28787 | F18: =F10+F17 -> 17242.144 | G18: =G10+G17 -> -393.35629 | H18: =H10+H17 -> 1400.142 | I18: =I10+I17 -> 14787.518 | J18: =J10+J17 -> 0 | K18: =K10+K17 -> 0 | L18: =L10+L17 -> 0 | ... Q18: =Q10+Q17 -> 14059.078 | R18: =Q18*1000/$Q$4 -> 26.716755 | T18: =I18+P18-Q18 -> 728.44015
A19: TOTAL SHARES | B19: ='data entry '!R17 -> 245.4643 | C19: =B19/$B$4*1000 -> 0.43443318 | F19: ='data entry '!R96 -> 0 | G19: ='data entry '!R51 -> 124.89558 | H19: ='Budget assumption'!R331 -> 19.541183 | I19: =B19 -> 245.4643 | P19: =SUM(J19:O19) -> 0 | Q19: ='data entry '!R129 -> 218.78146 | R19: =Q19*1000/$Q$4 -> 0.41575491 | T19: =I19+P19-Q19 -> 26.682843
A20: TOTAL MFG COST w/ SHARES | B20: =B18+B19 -> 15554.27 | C20: =B20/$B$4*1000 -> 27.52861 | E20: =E18+E19 -> -521.28787 | F20: =F18+F19 -> 17242.144 | G20: =G18+G19 -> -268.46071 | H20: =H18+H19 -> 1419.6832 | I20: =I18+I19 -> 15032.983 | J20: =J18+J19 -> 0 | K20: =K18+K19 -> 0 | L20: =L18+L19 -> 0 | ... Q20: =Q18+Q19 -> 14277.86 | R20: =Q20*1000/$Q$4 -> 27.13251 | T20: =I20+P20-Q20 -> 755.123
T21: =I21+P21-Q21 -> 0
A22: Functional Currency Impact | B22: ='data entry '!R19 -> 5048.1922 | C22: =B22/$B$4*1000 -> 8.9345056 | F22: ='data entry '!R98 -> 0 | G22: ='data entry '!R53 -> 3.4106051e-13 | I22: =B22 -> 5048.1922 | P22: =SUM(J22:O22) -> 0 | Q22: ='data entry '!R131 -> 3696.26 | R22: =Q22*1000/$Q$4 -> 7.0240789 | T22: =I22+P22-Q22 -> 1351.9323
A23: TOTAL Including FC | B23: =B22 -> 5048.1922 | C23: =B23/$B$4*1000 -> 8.9345056 | E23: =E22 -> 0 | F23: =F22 -> 0 | G23: =G22 -> 3.4106051e-13 | H23: =H22 -> 0 | I23: =I22 -> 5048.1922 | J23: =J22 -> 0 | K23: =K22 -> 0 | L23: =L22 -> 0 | ... Q23: =Q22 -> 3696.26 | R23: =Q23*1000/$Q$4 -> 7.0240789
A25: Scrap | B25: ='data entry '!R21 -> 247 | C25: =B25/$B$4*1000 -> 0.43715112 | E25: =I25-B25 -> -23.149368 | F25: ='data entry '!R100 -> 259.6084 | G25: ='data entry '!R55 -> -35.757769 | I25: =F25+G25 -> 223.85063 | P25: =SUM(J25:O25) -> 0 | Q25: ='data entry '!R133 -> 253.55175 | R25: =Q25*1000/$Q$4 -> 0.48182961 | T25: =I25+P25-Q25 -> -29.701118
A26: Scrap Reselling | B26: ='data entry '!R22 -> -585 | C26: =B26/$B$4*1000 -> -1.0353579 | E26: =I26-B26 -> 55.969652 | F26: ='data entry '!R101 -> -639.00741 | G26: ='data entry '!R56 -> 109.97706 | I26: =F26+G26 -> -529.03035 | P26: =SUM(J26:O26) -> 0 | Q26: ='data entry '!R134 -> -551.41871 | R26: =Q26*1000/$Q$4 -> -1.0478723 | T26: =I26+P26-Q26 -> 22.388364
A27: Other Variable (Inventory Adj) | B27: ='data entry '!R23 -> 0 | C27: =B27/$B$4*1000 -> 0 | F27: ='data entry '!R102 -> 0 | G27: ='data entry '!R57 -> 0 | I27: =F27+G27 -> 0 | P27: =SUM(J27:O27) -> 0 | Q27: ='data entry '!R135 -> 62.13421 | R27: =Q27*1000/$Q$4 -> 0.11807492 | T27: =I27+P27-Q27 -> -62.13421
A28: Obsolete | B28: ='data entry '!R24 -> 100 | C28: =B28/$B$4*1000 -> 0.17698426 | F28: ='data entry '!R103 -> 0 | G28: ='data entry '!R58 -> 100 | H28: ='Budget assumption'!R328 -> 0 | I28: =B28 -> 100 | P28: =SUM(J28:O28) -> 0 | Q28: ='data entry '!R136 -> 66.435382 | R28: =Q28*1000/$Q$4 -> 0.12624852 | T28: =I28+P28-Q28 -> 33.564618
A29: Asset Sales | B29: ='data entry '!R25 -> 0 | C29: =B29/$B$4*1000 -> 0 | F29: ='data entry '!R104 -> 0 | G29: ='data entry '!R59 -> 0 | I29: =B29 -> 0 | P29: =SUM(J29:O29) -> 0 | Q29: ='data entry '!R137 -> 0 | R29: =Q29*1000/$Q$4 -> 0 | T29: =I29+P29-Q29 -> 0
A30: TOTAL OTHERS | B30: =SUM(B25:B29) -> -238 | C30: =B30/$B$4*1000 -> -0.42122254 | E30: =SUM(E25:E29) -> 32.820285 | F30: =SUM(F25:F29) -> -379.39901 | G30: =SUM(G25:G29) -> 174.21929 | H30: =SUM(H25:H29) -> 0 | I30: =SUM(I25:I29) -> -205.17972 | J30: =SUM(J25:J29) -> 0 | K30: =SUM(K25:K29) -> 0 | L30: =SUM(L25:L29) -> 0 | ... Q30: =SUM(Q25:Q29) -> -169.29737 | R30: =Q30*1000/$Q$4 -> -0.32171927 | T30: =I30+P30-Q30 -> -35.882346
A32: IT GLOBAL | B32: ='data entry '!R27 -> 1088.3667 | C32: =B32/$B$4*1000 -> 1.9262377 | F32: ='data entry '!R106 -> 835.65604 | G32: ='data entry '!R61 -> -77.50333 | H32: =+'Budget assumption'!R335 -> 188.95846 | I32: =B32 -> 1088.3667 | P32: =SUM(J32:O32) -> 0 | Q32: ='data entry '!R139 -> 1082.7135 | R32: =Q32*1000/$Q$4 -> 2.0575027 | T32: =I32+P32-Q32 -> 5.6531911
A33: G&A(Insurance included) | B33: ='data entry '!R28 -> 1134.384 | C33: =B33/$B$4*1000 -> 2.0076812 | F33: ='data entry '!R107 -> 870.9885 | G33: ='data entry '!R62 -> 149.60403 | H33: =+'Budget assumption'!R336 -> 159.60828 | I33: =B33 -> 1134.384 | P33: =SUM(J33:O33) -> 0 | Q33: ='data entry '!R140 -> 1079.9199 | R33: =Q33*1000/$Q$4 -> 2.052194 | T33: =I33+P33-Q33 -> 54.464149
A34: TOTAL OVERHEAD | B34: =B32+B33 -> 2222.7507 | C34: =B34/$B$4*1000 -> 3.9339188 | E34: =E32+E33 -> 0 | F34: =F32+F33 -> 1706.6445 | G34: =G32+G33 -> 72.100696 | H34: =H32+H33 -> 348.56674 | I34: =I32+I33 -> 2222.7507 | J34: =J32+J33 -> 0 | K34: =K32+K33 -> 0 | L34: =L32+L33 -> 0 | ... Q34: =Q32+Q33 -> 2162.6334 | R34: =Q34*1000/$Q$4 -> 4.1096967 | T34: =I34+P34-Q34 -> 60.11734
R35: =Q35*1000/$Q$4 -> 0
A36: TOTAL ALL | B36: =B20+B23+B30+B34 -> 22587.213 | C36: =B36/$B$4*1000 -> 39.975812 | E36: =E20+E23+E30+E34 -> -488.46758 | F36: =F20+F23+F30+F34 -> 18569.389 | G36: =G20+G23+G30+G34 -> -22.14072 | H36: =H20+H23+H30+H34 -> 1768.25 | I36: =I20+I23+I30+I34 -> 22098.746 | J36: =J20+J23+J30+J34 -> 0 | K36: =K20+K23+K30+K34 -> 0 | L36: =L20+L23+L30+L34 -> 0 | ... Q36: =Q20+Q23+Q30+Q34 -> 19967.456 | R36: =Q36*1000/$Q$4 -> 37.944566 | T36: =I36+P36-Q36 -> 2131.2903

Sheet YTD VAR
A1: Volume | B1: =+'Budget assumption'!R35 -> 674311 | C1: =H1-B1 -> -109289 | H1: =+'Budget assumption'!R66 -> 565022 | I1: ='Budget assumption'!Q321 -> 0 | K1: ='data entry '!R82 -> 526227 | M1: ='data entry '!R115 -> 526227 | AA1: EFF | AB1: variable cost | AC1: Actual minus Copertura
B2: EUR | C2: EUR | H2: EUR | I2: EUR | K2: EUR | M2: EUR | Q2: Variances vs Budget | V2: Variances vs STD | AB2: fixed cost | AC2: Actual minus Budget
A3: Cost Elements | B3: STD | C3: Delta Volume | D3: ACE | E3: HW / TW | F3: Price FX | G3: Seasonality | H3: Plan Costs | I3: Budget VAR | K3: Copertura | M3: Act. Costs | O3: Variance vs STD | Q3: EFF | R3: FCA | S3: Total Variance | V3: EFF | W3: FCA | X3: Total Variance
D4: ACE
I5: FCA
A6: Direct Labour | B6: ='Budget assumption'!R37 -> 7672.5 | C6: ='Budget assumption'!R70 -> -1243.5209 | D6: ='Budget assumption'!R118 -> -401.07508 | E6: ='Budget assumption'!R149 -> -411.016 | F6: ='Budget assumption'!R180 -> 460.11203 | G6: ='Budget assumption'!R242+'Budget assumption'!R273 -> 5.1159077e-13 | H6: ='Budget assumption'!R211 -> 6077 | J6: =H6-SUM(B6:G6) -> 0 | K6: ='data entry '!R84 -> 5960.5155 | M6: ='data entry '!R117 -> 5008.7027 | O6: =M6-K6 -> -951.81275 | Q6: =M6-K6-E6-F6-D6-G6 -> -599.8337 | S6: =Q6+R6 -> -599.8337 | V6: =M6-K6 -> -951.81275 | X6: =V6+W6 -> -951.81275
A7: Variable Utilities | B7: ='Budget assumption'!R38 -> 520 | C7: ='Budget assumption'!R71 -> -84.279034 | D7: ='Budget assumption'!R119 -> 0 | E7: ='Budget assumption'!R150 -> 0 | F7: ='Budget assumption'!R181 -> -30.398899 | G7: ='Budget assumption'!R243+'Budget assumption'!R274 -> 9.2370556e-14 | H7: ='Budget assumption'!R212 -> 405.32207 | J7: =H7-SUM(B7:G7) -> 0 | K7: ='data entry '!R85 -> 401.67757 | M7: ='data entry '!R118 -> 359.05777 | O7: =M7-K7 -> -42.619793 | Q7: =M7-K7-E7-F7-D7-G7 -> -12.220895 | S7: =Q7+R7 -> -12.220895 | V7: =M7-K7 -> -42.619793 | X7: =V7+W7 -> -42.619793
A8: Variable Costs | B8: ='Budget assumption'!R39 -> 237.03 | C8: ='Budget assumption'!R72 -> -38.416653 | D8: ='Budget assumption'!R120 -> -12 | E8: ='Budget assumption'!R151 -> 0 | F8: ='Budget assumption'!R182 -> -1.581597 | G8: ='Budget assumption'!R244+'Budget assumption'!R275 -> 5.5067062e-14 | H8: ='Budget assumption'!R213 -> 185.03175 | J8: =H8-SUM(B8:G8) -> 0 | K8: ='data entry '!R86 -> 179.83247 | M8: ='data entry '!R119 -> 187.28832 | O8: =M8-K8 -> 7.4558518 | Q8: =M8-K8-E8-F8-D8-G8 -> 21.037449 | S8: =Q8+R8 -> 21.037449 | V8: =M8-K8 -> 7.4558518 | X8: =V8+W8 -> 7.4558518
A9: VARIABLE CONVERSION | B9: =SUM(B6:B8) -> 8429.53 | C9: =SUM(C6:C8) -> -1366.2166 | D9: =SUM(D6:D8) -> -413.07508 | E9: =SUM(E6:E8) -> -411.016 | F9: =SUM(F6:F8) -> 428.13153 | G9: =SUM(G6:G8) -> 6.5902839e-13 | H9: =SUM(H6:H8) -> 6667.3538 | I9: =SUM(I6:I8) -> 0 | J9: =H9-SUM(B9:G9) -> 0 | K9: =SUM(K6:K8) -> 6542.0255 | M9: =SUM(M6:M8) -> 5555.0488 | O9: =SUM(O6:O8) -> -986.97669 | Q9: =SUM(Q6:Q8) -> -591.01714 | R9: =SUM(R6:R8) -> 0 | S9: =SUM(S6:S8) -> -591.01714 | V9: =SUM(V6:V8) -> -986.97669 | W9: =SUM(W6:W8) -> 0 | X9: =SUM(X6:X8) -> -986.97669
A10: Indirect Labour | B10: ='Budget assumption'!R41 -> 3009.36 | D10: ='Budget assumption'!R122 -> 0 | E10: ='Budget assumption'!R153 -> -429 | F10: ='Budget assumption'!R184 -> 120.96881 | G10: ='Budget assumption'!R246+'Budget assumption'!R277 -> 1.9895197e-13 | H10: ='Budget assumption'!R215 -> 2701.3288 | I10: ='Budget assumption'!Q323 -> -19.917773 | J10: =H10-SUM(B10:G10) -> 0 | K10: ='data entry '!R88 -> 2343.4368 | M10: ='data entry '!R121 -> 2800.1829 | O10: =M10-K10 -> 456.74605 | Q10: =M10-H10 -> 98.854048 | R10: =H10-K10-E10-I10-F10-G10-D10 -> 685.84097 | S10: =Q10+R10 -> 784.69502 | V10: =M10-B10 -> -209.17715 | W10: =B10-K10 -> 665.9232 | X10: =V10+W10 -> 456.74605
A11: Fixed Labour | B11: ='Budget assumption'!R42 -> 1088.54 | D11: ='Budget assumption'!R123 -> 0 | E11: ='Budget assumption'!R154 -> 83 | F11: ='Budget assumption'!R185 -> 77.884207 | G11: ='Budget assumption'!R247+'Budget assumption'!R278 -> -4.2632564e-14 | H11: ='Budget assumption'!R216 -> 1249.4242 | I11: ='Budget assumption'!Q324 -> -7.2046193 | J11: =H11-SUM(B11:G11) -> 0 | K11: ='data entry '!R89 -> 842.15253 | M11: ='data entry '!R122 -> 1250.2818 | O11: =M11-K11 -> 408.12925 | Q11: =M11-H11 -> 0.85756869 | R11: =H11-K11-E11-I11-F11-G11-D11 -> 253.59209 | S11: =Q11+R11 -> 254.44966 | V11: =M11-B11 -> 161.74178 | W11: =B11-K11 -> 246.38747 | X11: =V11+W11 -> 408.12925
A12: Semifixed | B12: ='Budget assumption'!R43 -> 2101.59 | D12: ='Budget assumption'!R124 -> 0 | E12: ='Budget assumption'!R155 -> -148.55618 | F12: ='Budget assumption'!R186 -> 202.77618 | G12: ='Budget assumption'!R248+'Budget assumption'!R279 -> 5.1159077e-13 | H12: ='Budget assumption'!R217 -> 2155.81 | I12: ='Budget assumption'!Q325 -> -13.9096 | J12: =H12-SUM(B12:G12) -> 0 | K12: ='data entry '!R90 -> 1627.5617 | M12: ='data entry '!R123 -> 2131.3842 | O12: =M12-K12 -> 503.82251 | Q12: =M12-H12 -> -24.425766 | R12: =H12-K12-E12-I12-F12-G12-D12 -> 487.93788 | S12: =Q12+R12 -> 463.51211 | V12: =M12-B12 -> 29.794234 | W12: =B12-K12 -> 474.02828 | X12: =V12+W12 -> 503.82251
A13: Fixed utilities | B13: ='Budget assumption'!R44 -> 133.7 | D13: ='Budget assumption'!R125 -> -13.2 | E13: ='Budget assumption'!R156 -> -24 | F13: ='Budget assumption'!R187 -> -30.5 | G13: ='Budget assumption'!R249+'Budget assumption'!R280 -> 1.5987212e-14 | H13: ='Budget assumption'!R218 -> 66 | I13: ='Budget assumption'!Q326 -> -0.88490785 | J13: =H13-SUM(B13:G13) -> 0 | K13: ='data entry '!R91 -> 99.464137 | M13: ='data entry '!R124 -> 65.036253 | O13: =M13-K13 -> -34.427883 | Q13: =M13-H13 -> -0.96374675 | R13: =H13-K13-E13-I13-F13-G13-D13 -> 35.120771 | S13: =Q13+R13 -> 34.157024 | V13: =M13-B13 -> -68.663747 | W13: =B13-K13 -> 34.235863 | X13: =V13+W13 -> -34.427883
A14: Fixed Cost | B14: ='Budget assumption'!R45 -> 469.09128 | D14: ='Budget assumption'!R126 -> 0 | E14: ='Budget assumption'!R157 -> 0 | F14: ='Budget assumption'!R188 -> 44.020248 | G14: ='Budget assumption'!R250+'Budget assumption'!R281 -> 1.4210855e-13 | H14: ='Budget assumption'!R219 -> 513.11153 | I14: ='Budget assumption'!Q327 -> -3.1047312 | J14: =H14-SUM(B14:G14) -> 0 | K14: ='data entry '!R92 -> 415.82133 | M14: ='data entry '!R125 -> 477.52255 | O14: =M14-K14 -> 61.701227 | Q14: =M14-H14 -> -35.588975 | R14: =H14-K14-E14-I14-F14-G14-D14 -> 56.374685 | S14: =Q14+R14 -> 20.78571 | V14: =M14-B14 -> 8.4312729 | W14: =B14-K14 -> 53.269954 | X14: =V14+W14 -> 61.701227
A15: Depreciation | B15: ='Budget assumption'!R46 -> 1836.5678 | D15: ='Budget assumption'!R127 -> 0 | E15: ='Budget assumption'!R158 -> 119.2092 | F15: ='Budget assumption'!R189 -> 0.0008 | G15: ='Budget assumption'!R251+'Budget assumption'!R282 -> -1.7053026e-13 | H15: ='Budget assumption'!R220 -> 1955.7778 | I15: ='Budget assumption'!Q329 -> -12.155522 | J15: =H15-SUM(B15:G15) -> 0 | K15: ='data entry '!R93 -> 5371.6817 | M15: ='data entry '!R126 -> 1779.6216 | O15: =M15-K15 -> -3592.0601 | Q15: =M15-H15 -> -176.15614 | R15: =H15-K15-E15-I15-F15-G15-D15 -> -3522.9584 | S15: =Q15+R15 -> -3699.1146 | V15: =M15-B15 -> -56.94614 | W15: =B15-K15 -> -3535.114 | X15: =V15+W15 -> -3592.0601
A16: FIXED CONVERSION | B16: =SUM(B10:B15) -> 8638.849 | C16: =SUM(C10:C15) -> 0 | D16: =SUM(D10:D15) -> -13.2 | E16: =SUM(E10:E15) -> -399.34698 | F16: =SUM(F10:F15) -> 415.15024 | G16: =SUM(G10:G15) -> 6.5547567e-13 | H16: =SUM(H10:H15) -> 8641.4523 | I16: =SUM(I10:I15) -> -57.177153 | J16: =H16-SUM(B16:G16) -> 0 | K16: =SUM(K10:K15) -> 10700.118 | M16: =SUM(M10:M15) -> 8504.0293 | O16: =M16-K16 -> -2196.089 | Q16: =SUM(Q10:Q15) -> -137.42301 | R16: =SUM(R10:R15) -> -2004.0921 | S16: =Q16+R16 -> -2141.5151 | V16: =SUM(V10:V15) -> -134.81975 | W16: =SUM(W10:W15) -> -2061.2692 | X16: =SUM(X10:X15) -> -2196.089
A17: TOTAL MFG COST w/o SHARES | B17: =B9+B16 -> 17068.379 | C17: =C9+C16 -> -1366.2166 | D17: =D9+D16 -> -426.27508 | E17: =E9+E16 -> -810.36299 | F17: =F9+F16 -> 843.28178 | G17: =G9+G16 -> 1.3145041e-12 | H17: =H9+H16 -> 15308.806 | I17: =I9+I16 -> -57.177153 | J17: =H17-SUM(B17:G17) -> 0 | K17: =K9+K16 -> 17242.144 | M17: =M9+M16 -> 14059.078 | O17: =M17-K17 -> -3183.0656 | Q17: =Q9+Q16 -> -728.44015 | R17: =R9+R16 -> -2004.0921 | S17: =Q17+R17 -> -2732.5322 | V17: =V9+V16 -> -1121.7964 | W17: =W9+W16 -> -2061.2692 | X17: =X9+X16 -> -3183.0656
A18: TOTAL SHARES | B18: ='Budget assumption'!R49 -> 120.56872 | D18: ='Budget assumption'!R130 -> 0 | E18: ='Budget assumption'!R161 -> 0 | F18: ='Budget assumption'!R192 -> 124.89558 | G18: ='Budget assumption'!R254+'Budget assumption'!R285 -> -7.1054274e-15 | H18: ='Budget assumption'!R223 -> 245.4643 | I18: ='Budget assumption'!V49 -> 0 | J18: =H18-SUM(B18:G18) -> 0 | K18: ='data entry '!R96 -> 0 | M18: ='data entry '!R129 -> 218.78146 | O18: =M18-K18 -> 218.78146 | Q18: =M18-H18 -> -26.682843 | R18: =H18-K18-E18-I18-F18-G18-D18 -> 120.56872 | S18: =Q18+R18 -> 93.885877 | V18: =M18-B18 -> 98.212739 | W18: =B18-K18 -> 120.56872 | X18: =V18+W18 -> 218.78146
A19: TOTAL MFG COST w/ SHARES | B19: =B17+B18 -> 17188.948 | C19: =C17+C18 -> -1366.2166 | D19: =D17+D18 -> -426.27508 | E19: =E17+E18 -> -810.36299 | F19: =F17+F18 -> 968.17736 | G19: =G17+G18 -> 1.3073986e-12 | H19: =H17+H18 -> 15554.27 | I19: =I17+I18 -> -57.177153 | J19: =H19-SUM(B19:G19) -> 0 | K19: =K17+K18 -> 17242.144 | M19: =M17+M18 -> 14277.86 | O19: =O17+O18 -> -2964.2842 | Q19: =Q17+Q18 -> -755.123 | R19: =R17+R18 -> -1883.5233 | S19: =Q19+R19 -> -2638.6463 | V19: =V17+V18 -> -1023.5837 | W19: =W17+W18 -> -1940.7005 | X19: =X17+X18 -> -2964.2842
A20: Functional Currency Impact | B20: ='Budget assumption'!R51 -> 5048.1922 | D20: ='Budget assumption'!R132 -> 0 | E20: ='Budget assumption'!R163 -> 0 | F20: ='Budget assumption'!R194 -> 0 | G20: ='Budget assumption'!R256+'Budget assumption'!R287 -> 3.4106051e-13 | H20: ='Budget assumption'!R225 -> 5048.1922 | I20: ='Budget assumption'!V51 -> 0 | J20: =H20-SUM(B20:G20) -> 0 | K20: ='data entry '!R98 -> 0 | M20: ='data entry '!R131 -> 3696.26 | O20: =M20-K20 -> 3696.26 | Q20: =M20-H20 -> -1351.9323 | R20: =H20-K20-E20-I20-F20-G20-D20 -> 5048.1922 | S20: =Q20+R20 -> 3696.26 | V20: =M20-B20 -> -1351.9323 | W20: =B20-K20 -> 5048.1922 | X20: =V20+W20 -> 3696.26
A21: TOTAL Including FC | B21: =B19+B20 -> 22237.14 | C21: =C19+C20 -> -1366.2166 | D21: =D19+D20 -> -426.27508 | E21: =E19+E20 -> -810.36299 | F21: =F19+F20 -> 968.17736 | G21: =G19+G20 -> 1.6484591e-12 | H21: =H19+H20 -> 20602.463 | I21: =I19+I20 -> -57.177153 | J21: =H21-SUM(B21:G21) -> 0 | K21: =K19+K20 -> 17242.144 | M21: =M19+M20 -> 17974.12 | O21: =M21-K21 -> 731.97579 | Q21: =Q19+Q20 -> -2107.0553 | R21: =R19+R20 -> 3164.6689 | S21: =Q21+R21 -> 1057.6136 | V21: =V19+V20 -> -2375.516 | W21: =W19+W20 -> 3107.4918 | X21: =X19+X20 -> 731.97579
A22: Scrap | B22: ='Budget assumption'!R53 -> 337.45 | C22: ='Budget assumption'!R74 -> -54.692231 | D22: ='Budget assumption'!R134 -> -58.44075 | E22: ='Budget assumption'!R165 -> 0 | F22: ='Budget assumption'!R196 -> 22.682981 | G22: ='Budget assumption'!R258+'Budget assumption'!R289 -> 0 | H22: ='Budget assumption'!R227 -> 247 | J22: =H22-SUM(B22:G22) -> 0 | K22: ='data entry '!R100 -> 259.6084 | M22: ='data entry '!R133 -> 253.55175 | O22: =M22-K22 -> -6.0566514 | Q22: =M22-K22-E22-F22-D22-G22 -> 29.701118 | S22: =Q22+R22 -> 29.701118 | V22: =M22-K22 -> -6.0566514 | X22: =V22+W22 -> -6.0566514
A23: Scrap Reselling | B23: ='Budget assumption'!R54 -> -829.40253 | C23: ='Budget assumption'!R75 -> 134.42547 | D23: ='Budget assumption'!R135 -> 0 | E23: ='Budget assumption'!R166 -> 0 | F23: ='Budget assumption'!R197 -> 109.97706 | G23: ='Budget assumption'!R259+'Budget assumption'!R290 -> 0 | H23: ='Budget assumption'!R228 -> -585 | J23: =H23-SUM(B23:G23) -> 0 | K23: ='data entry '!R101 -> -639.00741 | M23: ='data entry '!R134 -> -551.41871 | O23: =M23-K23 -> 87.588696 | Q23: =M23-K23-E23-F23-D23-G23 -> -22.388364 | S23: =Q23+R23 -> -22.388364 | V23: =M23-K23 -> 87.588696 | X23: =V23+W23 -> 87.588696
A24: Other Variable (Inventory Adj) | B24: ='Budget assumption'!R55 -> 0 | C24: ='Budget assumption'!R76+'Budget assumption'!R291 -> 0 | D24: ='Budget assumption'!R136 -> 0 | E24: ='Budget assumption'!R167 -> 0 | F24: ='Budget assumption'!R198 -> 0 | G24: ='Budget assumption'!R260+'Budget assumption'!R291 -> 0 | H24: ='Budget assumption'!R229 -> 0 | J24: =H24-SUM(B24:G24) -> 0 | K24: ='data entry '!R102 -> 0 | M24: ='data entry '!R135 -> 62.13421 | O24: =M24-K24 -> 62.13421 | Q24: =M24-K24-E24-F24-D24-G24 -> 62.13421 | S24: =Q24+R24 -> 62.13421 | V24: =M24-K24 -> 62.13421 | X24: =V24+W24 -> 62.13421
A25: Obsolete | B25: ='Budget assumption'!R56 -> 0 | C25: ='Budget assumption'!R77+'Budget assumption'!R292 -> 0 | D25: ='Budget assumption'!R137 -> 0 | E25: ='Budget assumption'!R168 -> 100 | F25: ='Budget assumption'!R199 -> -7.1054274e-15 | G25: ='Budget assumption'!R261+'Budget assumption'!R292 -> 0 | H25: ='Budget assumption'!R230 -> 100 | J25: =H25-SUM(B25:G25) -> 0 | K25: ='data entry '!R103 -> 0 | M25: ='data entry '!R136 -> 66.435382 | O25: =M25-K25 -> 66.435382 | Q25: =M25-H25 -> -33.564618 | R25: =H25-K25-E25-I25-F25-G25-D25 -> 2.1316282e-14 | S25: =Q25+R25 -> -33.564618 | V25: =M25-B25 -> 66.435382 | W25: =B25-K25 -> 0 | X25: =V25+W25 -> 66.435382
A26: Asset Sales | B26: ='Budget assumption'!R57 -> 0 | C26: ='Budget assumption'!R78+'Budget assumption'!R293 -> 0 | D26: ='Budget assumption'!R138 -> 0 | E26: ='Budget assumption'!R169 -> 0 | F26: ='Budget assumption'!R200 -> 0 | G26: ='Budget assumption'!R262+'Budget assumption'!R293 -> 0 | H26: ='Budget assumption'!R231 -> 0 | J26: =H26-SUM(B26:G26) -> 0 | K26: ='data entry '!R104 -> 0 | M26: ='data entry '!R137 -> 0 | O26: =M26-K26 -> 0 | Q26: =M26-H26 -> 0 | R26: =H26-K26-E26-I26-F26-G26-D26 -> 0 | S26: =Q26+R26 -> 0 | V26: =M26-B26 -> 0 | W26: =B26-K26 -> 0 | X26: =V26+W26 -> 0
A27: TOTAL OTHERS | B27: =SUM(B22:B26) -> -491.95253 | C27: =SUM(C22:C26) -> 79.733239 | D27: =SUM(D22:D26) -> -58.44075 | E27: =SUM(E22:E26) -> 100 | F27: =SUM(F22:F26) -> 132.66004 | G27: =SUM(G22:G26) -> 0 | H27: =SUM(H22:H26) -> -238 | I27: =SUM(I22:I26) -> 0 | J27: =H27-SUM(B27:G27) -> 0 | K27: =SUM(K22:K26) -> -379.39901 | M27: =SUM(M22:M26) -> -169.29737 | O27: =M27-K27 -> 210.10164 | Q27: =SUM(Q22:Q26) -> 35.882346 | R27: =SUM(R22:R26) -> 2.1316282e-14 | S27: =Q27+R27 -> 35.882346 | V27: =SUM(V22:V26) -> 210.10164 | W27: =SUM(W22:W26) -> 0 | X27: =SUM(X22:X26) -> 210.10164
A28: IT GLOBAL | B28: ='Budget assumption'!R59 -> 1165.87 | D28: ='Budget assumption'!R140 -> 0 | E28: ='Budget assumption'!R171 -> 103.46221 | F28: ='Budget assumption'!R202 -> -180.96554 | G28: ='Budget assumption'!R264+'Budget assumption'!R295 -> 1.8474111e-13 | H28: ='Budget assumption'!R233 -> 1088.3667 | I28: ='Budget assumption'!Q337 -> -14.234309 | J28: =H28-SUM(B28:G28) -> 0 | K28: ='data entry '!R106 -> 835.65604 | M28: ='data entry '!R139 -> 1082.7135 | O28: =M28-K28 -> 247.05744 | Q28: =M28-H28 -> -5.6531911 | R28: =H28-K28-E28-I28-F28-G28-D28 -> 344.44827 | S28: =Q28+R28 -> 338.79508 | V28: =M28-B28 -> -83.156521 | W28: =B28-K28 -> 330.21396 | X28: =V28+W28 -> 247.05744
A29: G&A(Insurance included) | B29: ='Budget assumption'!R60 -> 984.78 | D29: ='Budget assumption'!R141 -> 0 | E29: ='Budget assumption'!R172 -> 0 | F29: ='Budget assumption'!R203 -> 149.60403 | G29: ='Budget assumption'!R265+'Budget assumption'!R296 -> -1.563194e-13 | H29: ='Budget assumption'!R234 -> 1134.384 | J29: =H29-SUM(B29:G29) -> 0 | K29: ='data entry '!R107 -> 870.9885 | M29: ='data entry '!R140 -> 1079.9199 | O29: =M29-K29 -> 208.93137 | Q29: =M29-H29 -> -54.464149 | R29: =H29-K29-E29-I29-F29-G29-D29 -> 113.7915 | S29: =Q29+R29 -> 59.327347 | V29: =M29-B29 -> 95.139877 | X29: =V29+W29 -> 95.139877
A30: TOTAL OVERHEAD | B30: =B28+B29 -> 2150.65 | C30: =C28+C29 -> 0 | D30: =D28+D29 -> 0 | E30: =E28+E29 -> 103.46221 | F30: =F28+F29 -> -31.361509 | G30: =G28+G29 -> 2.8421709e-14 | H30: =H28+H29 -> 2222.7507 | I30: =I28+I29 -> -14.234309 | J30: =H30-SUM(B30:G30) -> 0 | K30: =K28+K29 -> 1706.6445 | M30: =M28+M29 -> 2162.6334 | O30: =O28+O29 -> 455.98881 | Q30: =Q28+Q29 -> -60.11734 | R30: =R28+R29 -> 458.23977 | S30: =S28+S29 -> 398.12243 | V30: =V28+V29 -> 11.983356 | W30: =W28+W29 -> 330.21396 | X30: =X28+X29 -> 342.19732
D31: ='Budget assumption'!R143 -> 0 | G31: ='Budget assumption'!R267 -> 0 | J31: =H31-SUM(B31:G31) -> 0 | K31: ='data entry '!Q109 -> 0 | M31: ='data entry '!R142 -> 0 | O31: =M31-K31 -> 0 | Q31: =M31-K31-E31-F31-D31-G31 -> 0 | S31: =Q31+R31 -> 0
A32: TOTAL ALL | B32: =B21+B27+B30 -> 23895.837 | C32: =C21+C27+C30 -> -1286.4834 | D32: =D21+D27+D30 -> -484.71583 | E32: =E21+E27+E30 -> -606.90078 | F32: =F21+F27+F30 -> 1069.4759 | G32: =G21+G27+G30 -> 1.6768809e-12 | H32: =H21+H27+H30 -> 22587.213 | I32: =I21+I27+I30 -> -71.411462 | J32: =H32-SUM(B32:G32) -> 0 | K32: =K21+K27+K30 -> 18569.389 | M32: =M21+M27+M30 -> 19967.456 | O32: =M32-K32 -> 1398.0662 | Q32: =Q21+Q27+Q30 -> -2131.2903 | R32: =R21+R27+R30 -> 3622.9087 | S32: =Q32+R32 -> 1491.6184 | V32: =V21+V27+V30 -> -2153.431 | W32: =W21+W27+W30 -> 3437.7057 | X32: =X21+X27+X30 -> 1284.2747

Sheet List
C2: Jan | D2: 1 | E2: 1
C3: Feb | D3: 2 | E3: 1
C4: March | D4: 3 | E4: 1
C5: April | D5: 4 | E5: 1
C6: May | D6: 5 | E6: 1
C7: June | D7: 6 | E7: 1
C8: July | D8: 7 | E8: 1
C9: August | D9: 8 | E9: 1
C10: Sept | D10: 9 | E10: 1
C11: Oct | D11: 10 | E11: 1
C12: Nov | D12: 11 | E12: 1
C13: Dec | D13: 12 | E13: 1

Sheet data entry 
A1: YTD | B1: =IF($X$3>=B$2,1,0) -> 1 | C1: =IF($X$3>=C$2,1,0) -> 1 | D1: =IF($X$3>=D$2,1,0) -> 1 | E1: =IF($X$3>=E$2,1,0) -> 1 | F1: =IF($X$3>=F$2,1,0) -> 1 | G1: =IF($X$3>=G$2,1,0) -> 1 | H1: =IF($X$3>=H$2,1,0) -> 1 | I1: =IF($X$3>=I$2,1,0) -> 1 | ... M1: =IF($X$3>=M$2,1,0) -> 1
A2: MTD | B2: 0 | C2: 0 | D2: 0 | E2: 1 | F2: 0 | G2: 0 | H2: 0 | I2: 0 | J2: 0 | K2: 0 | L2: 0 | M2: 0
A3: Budget Volume | B3: ='Budget assumption'!B66 -> 50463 | C3: ='Budget assumption'!C66 -> 50446 | D3: ='Budget assumption'!D66 -> 50447 | E3: ='Budget assumption'!E66 -> 48050 | F3: ='Budget assumption'!F66 -> 36788 | G3: ='Budget assumption'!G66 -> 53265 | H3: ='Budget assumption'!H66 -> 42049 | I3: ='Budget assumption'!I66 -> 39150 | ... M3: ='Budget assumption'!M66 -> 40676 | N3: =SUM(B3:M3) -> 565022 | Q3: =SUMPRODUCT(B3:M3,B$2:M$2) -> 48050 | R3: =SUMPRODUCT(B3:M3,B$1:M$1) -> 565022 | V3: Month | W3: Dec | X3: =VLOOKUP(W3,List!$C$2:$D$13,2,0) -> 12 | Y3: =VLOOKUP(W3,List!$C$2:$E$13,3,0) -> 1
A4: Budget 2025 | B4: Jan | C4: Feb | D4: March | E4: April | F4: May | G4: June | H4: July | I4: August | J4: Sept | K4: Oct | L4: Nov | M4: Dec | N4: Total | Q4: MTD | R4: YTD
A5: Direct Labour | B5: ='Budget assumption'!B211 -> 485 | C5: ='Budget assumption'!C211 -> 524 | D5: ='Budget assumption'!D211 -> 529 | E5: ='Budget assumption'!E211 -> 509 | F5: ='Budget assumption'!F211 -> 579 | G5: ='Budget assumption'!G211 -> 503 | H5: ='Budget assumption'!H211 -> 451 | I5: ='Budget assumption'!I211 -> 460 | ... M5: ='Budget assumption'!M211 -> 492 | N5: =SUM(B5:M5) -> 6077 | Q5: =SUMPRODUCT(B5:M5,B$2:M$2) -> 509 | R5: =SUMPRODUCT(B5:M5,B$1:M$1) -> 6077
A6: Variable Utilities | B6: ='Budget assumption'!B212 -> 38.516777 | C6: ='Budget assumption'!C212 -> 37.591302 | D6: ='Budget assumption'!D212 -> 37.944559 | E6: ='Budget assumption'!E212 -> 35.733562 | F6: ='Budget assumption'!F212 -> 24.021199 | G6: ='Budget assumption'!G212 -> 35.762038 | H6: ='Budget assumption'!H212 -> 29.53027 | I6: ='Budget assumption'!I212 -> 31.209684 | ... M6: ='Budget assumption'!M212 -> 31.787008 | N6: =SUM(B6:M6) -> 405.32207 | Q6: =SUMPRODUCT(B6:M6,B$2:M$2) -> 35.733562 | R6: =SUMPRODUCT(B6:M6,B$1:M$1) -> 405.32207
A7: Variable Costs | B7: ='Budget assumption'!B213 -> 16.73 | C7: ='Budget assumption'!C213 -> 16.73 | D7: ='Budget assumption'!D213 -> 16.73 | E7: ='Budget assumption'!E213 -> 15.8935 | F7: ='Budget assumption'!F213 -> 11.711 | G7: ='Budget assumption'!G213 -> 17.5665 | H7: ='Budget assumption'!H213 -> 14.2205 | I7: ='Budget assumption'!I213 -> 12.9675 | ... M7: ='Budget assumption'!M213 -> 11.47725 | N7: =SUM(B7:M7) -> 185.03175 | Q7: =SUMPRODUCT(B7:M7,B$2:M$2) -> 15.8935 | R7: =SUMPRODUCT(B7:M7,B$1:M$1) -> 185.03175
A8: VARIABLE CONVERSION | B8: =SUM(B5:B7) -> 540.24678 | C8: =SUM(C5:C7) -> 578.3213 | D8: =SUM(D5:D7) -> 583.67456 | E8: =SUM(E5:E7) -> 560.62706 | F8: =SUM(F5:F7) -> 614.7322 | G8: =SUM(G5:G7) -> 556.32854 | H8: =SUM(H5:H7) -> 494.75077 | I8: =SUM(I5:I7) -> 504.17718 | ... M8: =SUM(M5:M7) -> 535.26426 | N8: =SUM(B8:M8) -> 6667.3538 | Q8: =SUMPRODUCT(B8:M8,B$2:M$2) -> 560.62706 | R8: =SUMPRODUCT(B8:M8,B$1:M$1) -> 6667.3538
A9: Indirect Labour | B9: ='Budget assumption'!B215 -> 194.74895 | C9: ='Budget assumption'!C215 -> 207.51639 | D9: ='Budget assumption'!D215 -> 211.95318 | E9: ='Budget assumption'!E215 -> 204.69927 | F9: ='Budget assumption'!F215 -> 228.48499 | G9: ='Budget assumption'!G215 -> 217.31856 | H9: ='Budget assumption'!H215 -> 251.55222 | I9: ='Budget assumption'!I215 -> 229.24655 | ... M9: ='Budget assumption'!M215 -> 288.17726 | N9: =SUM(B9:M9) -> 2701.3288 | Q9: =SUMPRODUCT(B9:M9,B$2:M$2) -> 204.69927 | R9: =SUMPRODUCT(B9:M9,B$1:M$1) -> 2701.3288
A10: Fixed Labour | B10: ='Budget assumption'!B216 -> 106.58 | C10: ='Budget assumption'!C216 -> 112.97149 | D10: ='Budget assumption'!D216 -> 102.64253 | E10: ='Budget assumption'!E216 -> 104.32865 | F10: ='Budget assumption'!F216 -> 110.75817 | G10: ='Budget assumption'!G216 -> 107.62726 | H10: ='Budget assumption'!H216 -> 100.46411 | I10: ='Budget assumption'!I216 -> 101.53527 | ... M10: ='Budget assumption'!M216 -> 96.810882 | N10: =SUM(B10:M10) -> 1249.4242 | Q10: =SUMPRODUCT(B10:M10,B$2:M$2) -> 104.32865 | R10: =SUMPRODUCT(B10:M10,B$1:M$1) -> 1249.4242
A11: Semifixed | B11: ='Budget assumption'!B217 -> 183.02969 | C11: ='Budget assumption'!C217 -> 179.83513 | D11: ='Budget assumption'!D217 -> 176.70014 | E11: ='Budget assumption'!E217 -> 177.19911 | F11: ='Budget assumption'!F217 -> 155.71007 | G11: ='Budget assumption'!G217 -> 188.37864 | H11: ='Budget assumption'!H217 -> 178.57404 | I11: ='Budget assumption'!I217 -> 171.83302 | ... M11: ='Budget assumption'!M217 -> 176.72183 | N11: =SUM(B11:M11) -> 2155.81 | Q11: =SUMPRODUCT(B11:M11,B$2:M$2) -> 177.19911 | R11: =SUMPRODUCT(B11:M11,B$1:M$1) -> 2155.81
A12: Fixed utilities | B12: ='Budget assumption'!B218 -> 5 | C12: ='Budget assumption'!C218 -> 6 | D12: ='Budget assumption'!D218 -> 6 | E12: ='Budget assumption'!E218 -> 5 | F12: ='Budget assumption'!F218 -> 4 | G12: ='Budget assumption'!G218 -> 6 | H12: ='Budget assumption'!H218 -> 5 | I12: ='Budget assumption'!I218 -> 4 | ... M12: ='Budget assumption'!M218 -> 5 | N12: =SUM(B12:M12) -> 66 | Q12: =SUMPRODUCT(B12:M12,B$2:M$2) -> 5 | R12: =SUMPRODUCT(B12:M12,B$1:M$1) -> 66
A13: Fixed Cost | B13: ='Budget assumption'!B219 -> 44.860259 | C13: ='Budget assumption'!C219 -> 44.262155 | D13: ='Budget assumption'!D219 -> 43.675204 | E13: ='Budget assumption'!E219 -> 43.218668 | F13: ='Budget assumption'!F219 -> 42.76888 | G13: ='Budget assumption'!G219 -> 43.825739 | H13: ='Budget assumption'!H219 -> 42.091273 | I13: ='Budget assumption'!I219 -> 41.858668 | ... M13: ='Budget assumption'!M219 -> 43.146735 | N13: =SUM(B13:M13) -> 513.11153 | Q13: =SUMPRODUCT(B13:M13,B$2:M$2) -> 43.218668 | R13: =SUMPRODUCT(B13:M13,B$1:M$1) -> 513.11153
A14: Depreciation | B14: ='Budget assumption'!B220 -> 161.79174 | C14: ='Budget assumption'!C220 -> 149.59309 | D14: ='Budget assumption'!D220 -> 160.35867 | E14: ='Budget assumption'!E220 -> 155.0923 | F14: ='Budget assumption'!F220 -> 155.61965 | G14: ='Budget assumption'!G220 -> 152.87378 | H14: ='Budget assumption'!H220 -> 171.28341 | I14: ='Budget assumption'!I220 -> 170.28855 | ... M14: ='Budget assumption'!M220 -> 176.92268 | N14: =SUM(B14:M14) -> 1955.7778 | Q14: =SUMPRODUCT(B14:M14,B$2:M$2) -> 155.0923 | R14: =SUMPRODUCT(B14:M14,B$1:M$1) -> 1955.7778
A15: FIXED CONVERSION | B15: =SUM(B9:B14) -> 696.01064 | C15: =SUM(C9:C14) -> 700.17825 | D15: =SUM(D9:D14) -> 701.32971 | E15: =SUM(E9:E14) -> 689.538 | F15: =SUM(F9:F14) -> 697.34176 | G15: =SUM(G9:G14) -> 716.02398 | H15: =SUM(H9:H14) -> 748.96506 | I15: =SUM(I9:I14) -> 718.76205 | ... M15: =SUM(M9:M14) -> 786.77939 | N15: =SUM(B15:M15) -> 8641.4523 | Q15: =SUMPRODUCT(B15:M15,B$2:M$2) -> 689.538 | R15: =SUMPRODUCT(B15:M15,B$1:M$1) -> 8641.4523
A16: TOTAL MFG COST w/o SHARES | B16: =B8+B15 -> 1236.2574 | C16: =C8+C15 -> 1278.4995 | D16: =D8+D15 -> 1285.0043 | E16: =E8+E15 -> 1250.1651 | F16: =F8+F15 -> 1312.074 | G16: =G8+G15 -> 1272.3525 | H16: =H8+H15 -> 1243.7158 | I16: =I8+I15 -> 1222.9392 | ... M16: =M8+M15 -> 1322.0436 | N16: =SUM(B16:M16) -> 15308.806 | Q16: =SUMPRODUCT(B16:M16,B$2:M$2) -> 1250.1651 | R16: =SUMPRODUCT(B16:M16,B$1:M$1) -> 15308.806
A17: TOTAL SHARES | B17: ='Budget assumption'!B223 -> 21.133 | C17: ='Budget assumption'!C223 -> 21.209825 | D17: ='Budget assumption'!D223 -> 20.932865 | E17: ='Budget assumption'!E223 -> 20.567044 | F17: ='Budget assumption'!F223 -> 21.018478 | G17: ='Budget assumption'!G223 -> 20.474517 | H17: ='Budget assumption'!H223 -> 20.217401 | I17: ='Budget assumption'!I223 -> 20.03887 | ... M17: ='Budget assumption'!M223 -> 19.789757 | N17: =SUM(B17:M17) -> 245.4643 | Q17: =SUMPRODUCT(B17:M17,B$2:M$2) -> 20.567044 | R17: =SUMPRODUCT(B17:M17,B$1:M$1) -> 245.4643
A18: TOTAL MFG COST w/ SHARES | B18: =B16+B17 -> 1257.3904 | C18: =C16+C17 -> 1299.7094 | D18: =D16+D17 -> 1305.9371 | E18: =E16+E17 -> 1270.7321 | F18: =F16+F17 -> 1333.0924 | G18: =G16+G17 -> 1292.827 | H18: =H16+H17 -> 1263.9332 | I18: =I16+I17 -> 1242.9781 | ... M18: =M16+M17 -> 1341.8334 | N18: =SUM(B18:M18) -> 15554.27 | Q18: =SUMPRODUCT(B18:M18,B$2:M$2) -> 1270.7321 | R18: =SUMPRODUCT(B18:M18,B$1:M$1) -> 15554.27
A19: Functional Currency Impact | B19: ='Budget assumption'!B225 -> 415.68863 | C19: ='Budget assumption'!C225 -> 386.88891 | D19: ='Budget assumption'!D225 -> 421.50115 | E19: ='Budget assumption'!E225 -> 413.13905 | F19: ='Budget assumption'!F225 -> 424.61564 | G19: ='Budget assumption'!G225 -> 416.35266 | H19: ='Budget assumption'!H225 -> 428.1206 | I19: ='Budget assumption'!I225 -> 429.39435 | ... M19: ='Budget assumption'!M225 -> 436.70918 | N19: =SUM(B19:M19) -> 5048.1922 | Q19: =SUMPRODUCT(B19:M19,B$2:M$2) -> 413.13905 | R19: =SUMPRODUCT(B19:M19,B$1:M$1) -> 5048.1922
A20: TOTAL Including FC | B20: =B18+B19 -> 1673.0791 | C20: =C18+C19 -> 1686.5983 | D20: =D18+D19 -> 1727.4383 | E20: =E18+E19 -> 1683.8712 | F20: =F18+F19 -> 1757.7081 | G20: =G18+G19 -> 1709.1797 | H20: =H18+H19 -> 1692.0538 | I20: =I18+I19 -> 1672.3725 | ... M20: =M18+M19 -> 1778.5426 | N20: =SUM(B20:M20) -> 20602.463 | Q20: =SUMPRODUCT(B20:M20,B$2:M$2) -> 1683.8712 | R20: =SUMPRODUCT(B20:M20,B$1:M$1) -> 20602.463
A21: Scrap | B21: ='Budget assumption'!B227 -> 27 | C21: ='Budget assumption'!C227 -> 27 | D21: ='Budget assumption'!D227 -> 27 | E21: ='Budget assumption'!E227 -> 19 | F21: ='Budget assumption'!F227 -> 15 | G21: ='Budget assumption'!G227 -> 21 | H21: ='Budget assumption'!H227 -> 17 | I21: ='Budget assumption'!I227 -> 16 | ... M21: ='Budget assumption'!M227 -> 16 | N21: =SUM(B21:M21) -> 247 | Q21: =SUMPRODUCT(B21:M21,B$2:M$2) -> 19 | R21: =SUMPRODUCT(B21:M21,B$1:M$1) -> 247
A22: Scrap Reselling | B22: ='Budget assumption'!B228 -> -55 | C22: ='Budget assumption'!C228 -> -55 | D22: ='Budget assumption'!D228 -> -56 | E22: ='Budget assumption'!E228 -> -48 | F22: ='Budget assumption'!F228 -> -36 | G22: ='Budget assumption'!G228 -> -53 | H22: ='Budget assumption'!H228 -> -44 | I22: ='Budget assumption'!I228 -> -40 | ... M22: ='Budget assumption'!M228 -> -41 | N22: =SUM(B22:M22) -> -585 | O22: 23.011403 | Q22: =SUMPRODUCT(B22:M22,B$2:M$2) -> -48 | R22: =SUMPRODUCT(B22:M22,B$1:M$1) -> -585
A23: Other Variable (Inventory Adj) | B23: ='Budget assumption'!B229 -> 0 | C23: ='Budget assumption'!C229 -> 0 | D23: ='Budget assumption'!D229 -> 0 | E23: ='Budget assumption'!E229 -> 0 | F23: ='Budget assumption'!F229 -> 0 | G23: ='Budget assumption'!G229 -> 0 | H23: ='Budget assumption'!H229 -> 0 | I23: ='Budget assumption'!I229 -> 0 | ... M23: ='Budget assumption'!M229 -> 0 | N23: =SUM(B23:M23) -> 0 | Q23: =SUMPRODUCT(B23:M23,B$2:M$2) -> 0 | R23: =SUMPRODUCT(B23:M23,B$1:M$1) -> 0
A24: Obsolete | B24: ='Budget assumption'!B230 -> 9 | C24: ='Budget assumption'!C230 -> 9 | D24: ='Budget assumption'!D230 -> 9 | E24: ='Budget assumption'!E230 -> 9 | F24: ='Budget assumption'!F230 -> 8 | G24: ='Budget assumption'!G230 -> 8 | H24: ='Budget assumption'!H230 -> 8 | I24: ='Budget assumption'!I230 -> 8 | ... M24: ='Budget assumption'!M230 -> 8 | N24: =SUM(B24:M24) -> 100 | Q24: =SUMPRODUCT(B24:M24,B$2:M$2) -> 9 | R24: =SUMPRODUCT(B24:M24,B$1:M$1) -> 100
A25: Asset Sales | B25: ='Budget assumption'!B231 -> 0 | C25: ='Budget assumption'!C231 -> 0 | D25: ='Budget assumption'!D231 -> 0 | E25: ='Budget assumption'!E231 -> 0 | F25: ='Budget assumption'!F231 -> 0 | G25: ='Budget assumption'!G231 -> 0 | H25: ='Budget assumption'!H231 -> 0 | I25: ='Budget assumption'!I231 -> 0 | ... M25: ='Budget assumption'!M231 -> 0 | N25: =SUM(B25:M25) -> 0 | Q25: =SUMPRODUCT(B25:M25,B$2:M$2) -> 0 | R25: =SUMPRODUCT(B25:M25,B$1:M$1) -> 0
A26: TOTAL OTHERS | B26: =SUM(B21:B25) -> -19 | C26: =SUM(C21:C25) -> -19 | D26: =SUM(D21:D25) -> -20 | E26: =SUM(E21:E25) -> -20 | F26: =SUM(F21:F25) -> -13 | G26: =SUM(G21:G25) -> -24 | H26: =SUM(H21:H25) -> -19 | I26: =SUM(I21:I25) -> -16 | ... M26: =SUM(M21:M25) -> -17 | N26: =SUM(B26:M26) -> -238 | Q26: =SUMPRODUCT(B26:M26,B$2:M$2) -> -20 | R26: =SUMPRODUCT(B26:M26,B$1:M$1) -> -238
A27: IT GLOBAL | B27: ='Budget assumption'!B233 -> 90.697223 | C27: ='Budget assumption'!C233 -> 90.697223 | D27: ='Budget assumption'!D233 -> 90.697223 | E27: ='Budget assumption'!E233 -> 90.697223 | F27: ='Budget assumption'!F233 -> 90.697223 | G27: ='Budget assumption'!G233 -> 90.697223 | H27: ='Budget assumption'!H233 -> 90.697223 | I27: ='Budget assumption'!I233 -> 90.697223 | ... M27: ='Budget assumption'!M233 -> 90.697223 | N27: =SUM(B27:M27) -> 1088.3667 | Q27: =SUMPRODUCT(B27:M27,B$2:M$2) -> 90.697223 | R27: =SUMPRODUCT(B27:M27,B$1:M$1) -> 1088.3667
A28: G&A(Insurance included) | B28: ='Budget assumption'!B234 -> 94.532002 | C28: ='Budget assumption'!C234 -> 94.532002 | D28: ='Budget assumption'!D234 -> 94.532002 | E28: ='Budget assumption'!E234 -> 94.532002 | F28: ='Budget assumption'!F234 -> 94.532002 | G28: ='Budget assumption'!G234 -> 94.532002 | H28: ='Budget assumption'!H234 -> 94.532002 | I28: ='Budget assumption'!I234 -> 94.532002 | ... M28: ='Budget assumption'!M234 -> 94.532002 | N28: =SUM(B28:M28) -> 1134.384 | Q28: =SUMPRODUCT(B28:M28,B$2:M$2) -> 94.532002 | R28: =SUMPRODUCT(B28:M28,B$1:M$1) -> 1134.384
A29: TOTAL OVERHEAD | B29: =SUM(B27:B28) -> 185.22922 | C29: =SUM(C27:C28) -> 185.22922 | D29: =SUM(D27:D28) -> 185.22922 | E29: =SUM(E27:E28) -> 185.22922 | F29: =SUM(F27:F28) -> 185.22922 | G29: =SUM(G27:G28) -> 185.22922 | H29: =SUM(H27:H28) -> 185.22922 | I29: =SUM(I27:I28) -> 185.22922 | ... M29: =SUM(M27:M28) -> 185.22922 | N29: =SUM(B29:M29) -> 2222.7507 | Q29: =SUMPRODUCT(B29:M29,B$2:M$2) -> 185.22922 | R29: =SUMPRODUCT(B29:M29,B$1:M$1) -> 2222.7507
N30: =SUM(B30:M30) -> 0 | Q30: =SUMPRODUCT(B30:M30,B$2:M$2) -> 0 | R30: =SUMPRODUCT(B30:M30,B$1:M$1) -> 0
A31: TOTAL ALL | B31: =B20+B26+B29 -> 1839.3083 | C31: =C20+C26+C29 -> 1852.8275 | D31: =D20+D26+D29 -> 1892.6675 | E31: =E20+E26+E29 -> 1849.1004 | F31: =F20+F26+F29 -> 1929.9373 | G31: =G20+G26+G29 -> 1870.4089 | H31: =H20+H26+H29 -> 1858.283 | I31: =I20+I26+I29 -> 1841.6017 | ... M31: =M20+M26+M29 -> 1946.7718 | N31: =SUM(B31:M31) -> 22587.213 | Q31: =SUMPRODUCT(B31:M31,B$2:M$2) -> 1849.1004 | R31: =SUMPRODUCT(B31:M31,B$1:M$1) -> 22587.213
A38: ACE + HWTW+ price +seasonality | B38: Jan | C38: Feb | D38: March | E38: April | F38: May | G38: June | H38: July | I38: August | J38: Sept | K38: Oct | L38: Nov | M38: Dec | N38: Total | Q38: MTD | R38: YTD
A39: Direct Labour | B39: ='Budget assumption'!B118+'Budget assumption'!B149+'Budget assumption'!B180+'Budget assumption'!B242+'Budget assumption'!B273 -> -89.182191 | C39: ='Budget assumption'!C118+'Budget assumption'!C149+'Budget assumption'!C180+'Budget assumption'!C242+'Budget assumption'!C273 -> -49.98876 | D39: ='Budget assumption'!D118+'Budget assumption'!D149+'Budget assumption'!D180+'Budget assumption'!D242+'Budget assumption'!D273 -> -45.000139 | E39: ='Budget assumption'!E118+'Budget assumption'!E149+'Budget assumption'!E180+'Budget assumption'!E242+'Budget assumption'!E273 -> -37.726399 | F39: ='Budget assumption'!F118+'Budget assumption'!F149+'Budget assumption'!F180+'Budget assumption'!F242+'Budget assumption'!F273 -> 160.4158 | G39: ='Budget assumption'!G118+'Budget assumption'!G149+'Budget assumption'!G180+'Budget assumption'!G242+'Budget assumption'!G273 -> -103.06413 | H39: ='Budget assumption'!H118+'Budget assumption'!H149+'Budget assumption'!H180+'Budget assumption'!H242+'Budget assumption'!H273 -> -27.445335 | I39: ='Budget assumption'!I118+'Budget assumption'!I149+'Budget assumption'!I180+'Budget assumption'!I242+'Budget assumption'!I273 -> 14.540301 | ... M39: ='Budget assumption'!M118+'Budget assumption'!M149+'Budget assumption'!M180+'Budget assumption'!M242+'Budget assumption'!M273 -> 29.177044 | N39: ='Budget assumption'!N118+'Budget assumption'!N149+'Budget assumption'!N180+'Budget assumption'!N242 -> -351.88797 | Q39: =SUMPRODUCT(B39:M39,B$2:M$2) -> -37.726399 | R39: =SUMPRODUCT(B39:M39,B$1:M$1) -> -351.97905
A40: Variable Utilities | B40: ='Budget assumption'!B119+'Budget assumption'!B150+'Budget assumption'!B181+'Budget assumption'!B243+'Budget assumption'!B274 -> -0.39814539 | C40: ='Budget assumption'!C119+'Budget assumption'!C150+'Budget assumption'!C181+'Budget assumption'!C243+'Budget assumption'!C274 -> -1.3105109 | D40: ='Budget assumption'!D119+'Budget assumption'!D150+'Budget assumption'!D181+'Budget assumption'!D243+'Budget assumption'!D274 -> -0.95802494 | E40: ='Budget assumption'!E119+'Budget assumption'!E150+'Budget assumption'!E181+'Budget assumption'!E243+'Budget assumption'!E274 -> -1.3205572 | F40: ='Budget assumption'!F119+'Budget assumption'!F150+'Budget assumption'!F181+'Budget assumption'!F243+'Budget assumption'!F274 -> -4.3481435 | G40: ='Budget assumption'!G119+'Budget assumption'!G150+'Budget assumption'!G181+'Budget assumption'!G243+'Budget assumption'!G274 -> -5.3136673 | H40: ='Budget assumption'!H119+'Budget assumption'!H150+'Budget assumption'!H181+'Budget assumption'!H243+'Budget assumption'!H274 -> -2.8961328 | I40: ='Budget assumption'!I119+'Budget assumption'!I150+'Budget assumption'!I181+'Budget assumption'!I243+'Budget assumption'!I274 -> 1.0188675 | ... M40: ='Budget assumption'!M119+'Budget assumption'!M150+'Budget assumption'!M181+'Budget assumption'!M243+'Budget assumption'!M274 -> 0.41940466 | N40: ='Budget assumption'!N119+'Budget assumption'!N150+'Budget assumption'!N181+'Budget assumption'!N243 -> -30.398899 | Q40: =SUMPRODUCT(B40:M40,B$2:M$2) -> -1.3205572 | R40: =SUMPRODUCT(B40:M40,B$1:M$1) -> -30.398899
A41: Variable Costs | B41: ='Budget assumption'!B120+'Budget assumption'!B151+'Budget assumption'!B182+'Budget assumption'!B244 -> -1.009148 | C41: ='Budget assumption'!C120+'Budget assumption'!C151+'Budget assumption'!C182+'Budget assumption'!C244 -> -1.0031723 | D41: ='Budget assumption'!D120+'Budget assumption'!D151+'Budget assumption'!D182+'Budget assumption'!D244 -> -1.0035238 | E41: ='Budget assumption'!E120+'Budget assumption'!E151+'Budget assumption'!E182+'Budget assumption'!E244 -> -1.0004778 | F41: ='Budget assumption'!F120+'Budget assumption'!F151+'Budget assumption'!F182+'Budget assumption'!F244 -> -1.2229855 | G41: ='Budget assumption'!G120+'Budget assumption'!G151+'Budget assumption'!G182+'Budget assumption'!G244 -> -1.1503589 | H41: ='Budget assumption'!H120+'Budget assumption'!H151+'Budget assumption'!H182+'Budget assumption'!H244 -> -0.5604187 | I41: ='Budget assumption'!I120+'Budget assumption'!I151+'Budget assumption'!I182+'Budget assumption'!I244 -> -0.80103654 | ... N41: ='Budget assumption'!N120+'Budget assumption'!N151+'Budget assumption'!N182+'Budget assumption'!N244 -> -13.581597 | Q41: =SUMPRODUCT(B41:M41,B$2:M$2) -> -1.0004778 | R41: =SUMPRODUCT(B41:M41,B$1:M$1) -> -13.581597
A42: VARIABLE CONVERSION | B42: =SUM(B39:B41) -> -90.589485 | C42: =SUM(C39:C41) -> -52.302444 | D42: =SUM(D39:D41) -> -46.961687 | E42: =SUM(E39:E41) -> -40.047434 | F42: =SUM(F39:F41) -> 154.84467 | G42: =SUM(G39:G41) -> -109.52816 | H42: =SUM(H39:H41) -> -30.901887 | I42: =SUM(I39:I41) -> 14.758132 | ... N42: =SUM(N39:N41) -> -395.86847 | Q42: =SUMPRODUCT(B42:M42,B$2:M$2) -> -40.047434 | R42: =SUMPRODUCT(B42:M42,B$1:M$1) -> -395.95955
A43: Indirect Labour | B43: ='Budget assumption'!B122+'Budget assumption'!B153+'Budget assumption'!B184+'Budget assumption'!B246+'Budget assumption'!B277 -> -10.542907 | C43: ='Budget assumption'!C122+'Budget assumption'!C153+'Budget assumption'!C184+'Budget assumption'!C246+'Budget assumption'!C277 -> 2.2245259 | D43: ='Budget assumption'!D122+'Budget assumption'!D153+'Budget assumption'!D184+'Budget assumption'!D246+'Budget assumption'!D277 -> 6.6613201 | E43: ='Budget assumption'!E122+'Budget assumption'!E153+'Budget assumption'!E184+'Budget assumption'!E246+'Budget assumption'!E277 -> -10.85718 | F43: ='Budget assumption'!F122+'Budget assumption'!F153+'Budget assumption'!F184+'Budget assumption'!F246+'Budget assumption'!F277 -> 84.780684 | G43: ='Budget assumption'!G122+'Budget assumption'!G153+'Budget assumption'!G184+'Budget assumption'!G246+'Budget assumption'!G277 -> -101.7764 | H43: ='Budget assumption'!H122+'Budget assumption'!H153+'Budget assumption'!H184+'Budget assumption'!H246+'Budget assumption'!H277 -> -6.1783218 | I43: ='Budget assumption'!I122+'Budget assumption'!I153+'Budget assumption'!I184+'Budget assumption'!I246+'Budget assumption'!I277 -> -3.9382299 | ... N43: ='Budget assumption'!N122+'Budget assumption'!N153+'Budget assumption'!N184+'Budget assumption'!N246+'Budget assumption'!N277 -> -308.03119 | Q43: =SUMPRODUCT(B43:M43,B$2:M$2) -> -10.85718 | R43: =SUMPRODUCT(B43:M43,B$1:M$1) -> -308.03119
A44: Fixed Labour | B44: ='Budget assumption'!B123+'Budget assumption'!B154+'Budget assumption'!B185+'Budget assumption'!B247+'Budget assumption'!B278 -> 32.322212 | C44: ='Budget assumption'!C123+'Budget assumption'!C154+'Budget assumption'!C185+'Budget assumption'!C247+'Budget assumption'!C278 -> 38.713702 | D44: ='Budget assumption'!D123+'Budget assumption'!D154+'Budget assumption'!D185+'Budget assumption'!D247+'Budget assumption'!D278 -> 28.384742 | E44: ='Budget assumption'!E123+'Budget assumption'!E154+'Budget assumption'!E185+'Budget assumption'!E247+'Budget assumption'!E278 -> 26.357974 | F44: ='Budget assumption'!F123+'Budget assumption'!F154+'Budget assumption'!F185+'Budget assumption'!F247+'Budget assumption'!F278 -> 58.777722 | G44: ='Budget assumption'!G123+'Budget assumption'!G154+'Budget assumption'!G185+'Budget assumption'!G247+'Budget assumption'!G278 -> -7.7951589 | H44: ='Budget assumption'!H123+'Budget assumption'!H154+'Budget assumption'!H185+'Budget assumption'!H247+'Budget assumption'!H278 -> 7.2383097 | I44: ='Budget assumption'!I123+'Budget assumption'!I154+'Budget assumption'!I185+'Budget assumption'!I247+'Budget assumption'!I278 -> 17.188109 | ... N44: ='Budget assumption'!N123+'Budget assumption'!N154+'Budget assumption'!N185+'Budget assumption'!N247+'Budget assumption'!N278 -> 160.88421 | Q44: =SUMPRODUCT(B44:M44,B$2:M$2) -> 26.357974 | R44: =SUMPRODUCT(B44:M44,B$1:M$1) -> 160.88421
A45: Semifixed | B45: ='Budget assumption'!B124+'Budget assumption'!B155+'Budget assumption'!B186+'Budget assumption'!B248+'Budget assumption'!B279 -> 39.663885 | C45: ='Budget assumption'!C124+'Budget assumption'!C155+'Budget assumption'!C186+'Budget assumption'!C248+'Budget assumption'!C279 -> 36.46932 | D45: ='Budget assumption'!D124+'Budget assumption'!D155+'Budget assumption'!D186+'Budget assumption'!D248+'Budget assumption'!D279 -> 33.33433 | E45: ='Budget assumption'!E124+'Budget assumption'!E155+'Budget assumption'!E186+'Budget assumption'!E248+'Budget assumption'!E279 -> 26.665011 | F45: ='Budget assumption'!F124+'Budget assumption'!F155+'Budget assumption'!F186+'Budget assumption'!F248+'Budget assumption'!F279 -> 55.35401 | G45: ='Budget assumption'!G124+'Budget assumption'!G155+'Budget assumption'!G186+'Budget assumption'!G248+'Budget assumption'!G279 -> -34.461693 | H45: ='Budget assumption'!H124+'Budget assumption'!H155+'Budget assumption'!H186+'Budget assumption'!H248+'Budget assumption'!H279 -> -1.4123817 | I45: ='Budget assumption'!I124+'Budget assumption'!I155+'Budget assumption'!I186+'Budget assumption'!I248+'Budget assumption'!I279 -> 8.9881641 | ... N45: ='Budget assumption'!N124+'Budget assumption'!N155+'Budget assumption'!N186+'Budget assumption'!N248+'Budget assumption'!N279 -> 54.22 | Q45: =SUMPRODUCT(B45:M45,B$2:M$2) -> 26.665011 | R45: =SUMPRODUCT(B45:M45,B$1:M$1) -> 54.22
A46: Fixed utilities | B46: ='Budget assumption'!B125+'Budget assumption'!B156+'Budget assumption'!B187+'Budget assumption'!B249+'Budget assumption'!B280 -> -4.1207173 | C46: ='Budget assumption'!C125+'Budget assumption'!C156+'Budget assumption'!C187+'Budget assumption'!C249+'Budget assumption'!C280 -> -3.1207173 | D46: ='Budget assumption'!D125+'Budget assumption'!D156+'Budget assumption'!D187+'Budget assumption'!D249+'Budget assumption'!D280 -> -3.1207173 | E46: ='Budget assumption'!E125+'Budget assumption'!E156+'Budget assumption'!E187+'Budget assumption'!E249+'Budget assumption'!E280 -> -4.5767532 | F46: ='Budget assumption'!F125+'Budget assumption'!F156+'Budget assumption'!F187+'Budget assumption'!F249+'Budget assumption'!F280 -> -2.3845021 | G46: ='Budget assumption'!G125+'Budget assumption'!G156+'Budget assumption'!G187+'Budget assumption'!G249+'Budget assumption'!G280 -> -8.1767671 | H46: ='Budget assumption'!H125+'Budget assumption'!H156+'Budget assumption'!H187+'Budget assumption'!H249+'Budget assumption'!H280 -> -6.4504657 | I46: ='Budget assumption'!I125+'Budget assumption'!I156+'Budget assumption'!I187+'Budget assumption'!I249+'Budget assumption'!I280 -> -6.3599452 | ... N46: ='Budget assumption'!N125+'Budget assumption'!N156+'Budget assumption'!N187+'Budget assumption'!N249+'Budget assumption'!N280 -> -67.7 | Q46: =SUMPRODUCT(B46:M46,B$2:M$2) -> -4.5767532 | R46: =SUMPRODUCT(B46:M46,B$1:M$1) -> -67.7
A47: Fixed Cost | B47: ='Budget assumption'!B126+'Budget assumption'!B157+'Budget assumption'!B188+'Budget assumption'!B250+'Budget assumption'!B281 -> 12.859893 | C47: ='Budget assumption'!C126+'Budget assumption'!C157+'Budget assumption'!C188+'Budget assumption'!C250+'Budget assumption'!C281 -> 12.261789 | D47: ='Budget assumption'!D126+'Budget assumption'!D157+'Budget assumption'!D188+'Budget assumption'!D250+'Budget assumption'!D281 -> 11.674837 | E47: ='Budget assumption'!E126+'Budget assumption'!E157+'Budget assumption'!E188+'Budget assumption'!E250+'Budget assumption'!E281 -> 9.6182841 | F47: ='Budget assumption'!F126+'Budget assumption'!F157+'Budget assumption'!F188+'Budget assumption'!F250+'Budget assumption'!F281 -> 20.368624 | G47: ='Budget assumption'!G126+'Budget assumption'!G157+'Budget assumption'!G188+'Budget assumption'!G250+'Budget assumption'!G281 -> -5.9139603 | H47: ='Budget assumption'!H126+'Budget assumption'!H157+'Budget assumption'!H188+'Budget assumption'!H250+'Budget assumption'!H281 -> 1.9169003 | I47: ='Budget assumption'!I126+'Budget assumption'!I157+'Budget assumption'!I188+'Budget assumption'!I250+'Budget assumption'!I281 -> 5.5104257 | ... N47: ='Budget assumption'!N126+'Budget assumption'!N157+'Budget assumption'!N188+'Budget assumption'!N250+'Budget assumption'!N281 -> 44.020248 | Q47: =SUMPRODUCT(B47:M47,B$2:M$2) -> 9.6182841 | R47: =SUMPRODUCT(B47:M47,B$1:M$1) -> 44.020248
A48: Depreciation | B48: ='Budget assumption'!B127+'Budget assumption'!B158+'Budget assumption'!B189+'Budget assumption'!B251+'Budget assumption'!B282 -> 36.505165 | C48: ='Budget assumption'!C127+'Budget assumption'!C158+'Budget assumption'!C189+'Budget assumption'!C251+'Budget assumption'!C282 -> 24.306514 | D48: ='Budget assumption'!D127+'Budget assumption'!D158+'Budget assumption'!D189+'Budget assumption'!D251+'Budget assumption'!D282 -> 35.072092 | E48: ='Budget assumption'!E127+'Budget assumption'!E158+'Budget assumption'!E189+'Budget assumption'!E251+'Budget assumption'!E282 -> 23.541396 | F48: ='Budget assumption'!F127+'Budget assumption'!F158+'Budget assumption'!F189+'Budget assumption'!F251+'Budget assumption'!F282 -> 67.919042 | G48: ='Budget assumption'!G127+'Budget assumption'!G158+'Budget assumption'!G189+'Budget assumption'!G251+'Budget assumption'!G282 -> -41.865138 | H48: ='Budget assumption'!H127+'Budget assumption'!H158+'Budget assumption'!H189+'Budget assumption'!H251+'Budget assumption'!H282 -> 13.994285 | I48: ='Budget assumption'!I127+'Budget assumption'!I158+'Budget assumption'!I189+'Budget assumption'!I251+'Budget assumption'!I282 -> 27.979342 | ... N48: ='Budget assumption'!N127+'Budget assumption'!N158+'Budget assumption'!N189+'Budget assumption'!N251+'Budget assumption'!N282 -> 119.21 | Q48: =SUMPRODUCT(B48:M48,B$2:M$2) -> 23.541396 | R48: =SUMPRODUCT(B48:M48,B$1:M$1) -> 119.21
A49: FIXED CONVERSION | B49: =SUM(B43:B48) -> 106.68753 | C49: =SUM(C43:C48) -> 110.85514 | D49: =SUM(D43:D48) -> 112.0066 | E49: =SUM(E43:E48) -> 70.748731 | F49: =SUM(F43:F48) -> 284.81558 | G49: =SUM(G43:G48) -> -199.98912 | H49: =SUM(H43:H48) -> 9.1083261 | I49: =SUM(I43:I48) -> 49.367866 | ... N49: =SUM(N43:N48) -> 2.6032609 | Q49: =SUMPRODUCT(B49:M49,B$2:M$2) -> 70.748731 | R49: =SUMPRODUCT(B49:M49,B$1:M$1) -> 2.6032609
A50: TOTAL MFG COST w/o SHARES | B50: =B42+B49 -> 16.098046 | C50: =C42+C49 -> 58.552692 | D50: =D42+D49 -> 65.044917 | E50: =E42+E49 -> 30.701297 | F50: =F42+F49 -> 439.66025 | G50: =G42+G49 -> -309.51728 | H50: =H42+H49 -> -21.793561 | I50: =I42+I49 -> 64.125998 | ... N50: =N42+N49 -> -393.26521 | Q50: =SUMPRODUCT(B50:M50,B$2:M$2) -> 30.701297 | R50: =SUMPRODUCT(B50:M50,B$1:M$1) -> -393.35629
A51: TOTAL SHARES | B51: ='Budget assumption'!B130+'Budget assumption'!B161+'Budget assumption'!B192+'Budget assumption'!B254+'Budget assumption'!B285 -> 12.908069 | C51: ='Budget assumption'!C130+'Budget assumption'!C161+'Budget assumption'!C192+'Budget assumption'!C254+'Budget assumption'!C285 -> 12.984894 | D51: ='Budget assumption'!D130+'Budget assumption'!D161+'Budget assumption'!D192+'Budget assumption'!D254+'Budget assumption'!D285 -> 12.707935 | E51: ='Budget assumption'!E130+'Budget assumption'!E161+'Budget assumption'!E192+'Budget assumption'!E254+'Budget assumption'!E285 -> 11.930867 | F51: ='Budget assumption'!F130+'Budget assumption'!F161+'Budget assumption'!F192+'Budget assumption'!F254+'Budget assumption'!F285 -> 15.261027 | G51: ='Budget assumption'!G130+'Budget assumption'!G161+'Budget assumption'!G192+'Budget assumption'!G254+'Budget assumption'!G285 -> 7.6901145 | H51: ='Budget assumption'!H130+'Budget assumption'!H161+'Budget assumption'!H192+'Budget assumption'!H254+'Budget assumption'!H285 -> 9.8915375 | I51: ='Budget assumption'!I130+'Budget assumption'!I161+'Budget assumption'!I192+'Budget assumption'!I254+'Budget assumption'!I285 -> 10.696422 | ... M51: ='Budget assumption'!M130+'Budget assumption'!M161+'Budget assumption'!M192+'Budget assumption'!M254+'Budget assumption'!M285 -> 8.6036731 | N51: =SUM(B51:M51) -> 124.89558 | Q51: =SUMPRODUCT(B51:M51,B$2:M$2) -> 11.930867 | R51: =SUMPRODUCT(B51:M51,B$1:M$1) -> 124.89558
A52: TOTAL MFG COST w/ SHARES | B52: =B50+B51 -> 29.006115 | C52: =C50+C51 -> 71.537586 | D52: =D50+D51 -> 77.752852 | E52: =E50+E51 -> 42.632164 | F52: =F50+F51 -> 454.92128 | G52: =G50+G51 -> -301.82716 | H52: =H50+H51 -> -11.902023 | I52: =I50+I51 -> 74.822421 | ... N52: =N50+N51 -> -268.36962 | Q52: =SUMPRODUCT(B52:M52,B$2:M$2) -> 42.632164 | R52: =SUMPRODUCT(B52:M52,B$1:M$1) -> -268.46071
A53: Functional Currency Impact | B53: ='Budget assumption'!B132+'Budget assumption'!B163+'Budget assumption'!B194+'Budget assumption'!B256+'Budget assumption'!B287 -> 71.312162 | C53: ='Budget assumption'!C132+'Budget assumption'!C163+'Budget assumption'!C194+'Budget assumption'!C256+'Budget assumption'!C287 -> 42.512443 | D53: ='Budget assumption'!D132+'Budget assumption'!D163+'Budget assumption'!D194+'Budget assumption'!D256+'Budget assumption'!D287 -> 77.124682 | E53: ='Budget assumption'!E132+'Budget assumption'!E163+'Budget assumption'!E194+'Budget assumption'!E256+'Budget assumption'!E287 -> 51.543756 | F53: ='Budget assumption'!F132+'Budget assumption'!F163+'Budget assumption'!F194+'Budget assumption'!F256+'Budget assumption'!F287 -> 183.55211 | G53: ='Budget assumption'!G132+'Budget assumption'!G163+'Budget assumption'!G194+'Budget assumption'!G256+'Budget assumption'!G287 -> -118.92816 | H53: ='Budget assumption'!H132+'Budget assumption'!H163+'Budget assumption'!H194+'Budget assumption'!H256+'Budget assumption'!H287 -> -4.2216047 | I53: ='Budget assumption'!I132+'Budget assumption'!I163+'Budget assumption'!I194+'Budget assumption'!I256+'Budget assumption'!I287 -> 38.227599 | ... M53: ='Budget assumption'!M132+'Budget assumption'!M163+'Budget assumption'!M194+'Budget assumption'!M256+'Budget assumption'!M287 -> -31.650306 | N53: ='Budget assumption'!N132+'Budget assumption'!N163+'Budget assumption'!N194+'Budget assumption'!N256 -> -3.4106051e-13 | Q53: =SUMPRODUCT(B53:M53,B$2:M$2) -> 51.543756 | R53: =SUMPRODUCT(B53:M53,B$1:M$1) -> 3.4106051e-13
A54: TOTAL Including FC | B54: =B52+B53 -> 100.31828 | C54: =C52+C53 -> 114.05003 | D54: =D52+D53 -> 154.87753 | E54: =E52+E53 -> 94.17592 | F54: =F52+F53 -> 638.47338 | G54: =G52+G53 -> -420.75532 | H54: =H52+H53 -> -16.123628 | I54: =I52+I53 -> 113.05002 | ... N54: =N52+N53 -> -268.36962 | Q54: =SUMPRODUCT(B54:M54,B$2:M$2) -> 94.17592 | R54: =SUMPRODUCT(B54:M54,B$1:M$1) -> -268.46071
A55: Scrap | B55: ='Budget assumption'!B134+'Budget assumption'!B165+'Budget assumption'!B196+'Budget assumption'!B258 -> 1.7465508 | C55: ='Budget assumption'!C134+'Budget assumption'!C165+'Budget assumption'!C196+'Budget assumption'!C258 -> 1.7550582 | D55: ='Budget assumption'!D134+'Budget assumption'!D165+'Budget assumption'!D196+'Budget assumption'!D258 -> 1.7545578 | E55: ='Budget assumption'!E134+'Budget assumption'!E165+'Budget assumption'!E196+'Budget assumption'!E258 -> -5.0448908 | F55: ='Budget assumption'!F134+'Budget assumption'!F165+'Budget assumption'!F196+'Budget assumption'!F258 -> -3.4060038 | G55: ='Budget assumption'!G134+'Budget assumption'!G165+'Budget assumption'!G196+'Budget assumption'!G258 -> -5.654536 | H55: ='Budget assumption'!H134+'Budget assumption'!H165+'Budget assumption'!H196+'Budget assumption'!H258 -> -4.0426427 | I55: ='Budget assumption'!I134+'Budget assumption'!I165+'Budget assumption'!I196+'Budget assumption'!I258 -> -3.5942787 | ... N55: ='Budget assumption'!N134+'Budget assumption'!N165+'Budget assumption'!N196+'Budget assumption'!N258 -> -35.317019 | Q55: =SUMPRODUCT(B55:M55,B$2:M$2) -> -5.0448908 | R55: =SUMPRODUCT(B55:M55,B$1:M$1) -> -35.757769
A56: Scrap Reselling | B56: ='Budget assumption'!B135+'Budget assumption'!B166+'Budget assumption'!B197+'Budget assumption'!B259 -> 7.06949 | C56: ='Budget assumption'!C135+'Budget assumption'!C166+'Budget assumption'!C197+'Budget assumption'!C259 -> 7.04858 | D56: ='Budget assumption'!D135+'Budget assumption'!D166+'Budget assumption'!D197+'Budget assumption'!D259 -> 6.04981 | E56: ='Budget assumption'!E135+'Budget assumption'!E166+'Budget assumption'!E197+'Budget assumption'!E259 -> 11.1015 | F56: ='Budget assumption'!F135+'Budget assumption'!F166+'Budget assumption'!F197+'Budget assumption'!F259 -> 9.24924 | G56: ='Budget assumption'!G135+'Budget assumption'!G166+'Budget assumption'!G197+'Budget assumption'!G259 -> 12.51595 | H56: ='Budget assumption'!H135+'Budget assumption'!H166+'Budget assumption'!H197+'Budget assumption'!H259 -> 7.72027 | I56: ='Budget assumption'!I135+'Budget assumption'!I166+'Budget assumption'!I197+'Budget assumption'!I259 -> 8.1545 | ... N56: ='Budget assumption'!N135+'Budget assumption'!N166+'Budget assumption'!N197+'Budget assumption'!N259 -> 109.97706 | Q56: =SUMPRODUCT(B56:M56,B$2:M$2) -> 11.1015 | R56: =SUMPRODUCT(B56:M56,B$1:M$1) -> 109.97706
A57: Other Variable (Inventory Adj) | B57: ='Budget assumption'!B136+'Budget assumption'!B167+'Budget assumption'!B198+'Budget assumption'!B260 -> 0 | C57: ='Budget assumption'!C136+'Budget assumption'!C167+'Budget assumption'!C198+'Budget assumption'!C260 -> 0 | D57: ='Budget assumption'!D136+'Budget assumption'!D167+'Budget assumption'!D198+'Budget assumption'!D260 -> 0 | E57: ='Budget assumption'!E136+'Budget assumption'!E167+'Budget assumption'!E198+'Budget assumption'!E260 -> 0 | F57: ='Budget assumption'!F136+'Budget assumption'!F167+'Budget assumption'!F198+'Budget assumption'!F260 -> 0 | G57: ='Budget assumption'!G136+'Budget assumption'!G167+'Budget assumption'!G198+'Budget assumption'!G260 -> 0 | H57: ='Budget assumption'!H136+'Budget assumption'!H167+'Budget assumption'!H198+'Budget assumption'!H260 -> 0 | I57: ='Budget assumption'!I136+'Budget assumption'!I167+'Budget assumption'!I198+'Budget assumption'!I260 -> 0 | ... N57: ='Budget assumption'!N136+'Budget assumption'!N167+'Budget assumption'!N198+'Budget assumption'!N260 -> 0 | Q57: =SUMPRODUCT(B57:M57,B$2:M$2) -> 0 | R57: =SUMPRODUCT(B57:M57,B$1:M$1) -> 0
A58: Obsolete | B58: ='Budget assumption'!B137+'Budget assumption'!B168+'Budget assumption'!B199+'Budget assumption'!B261 -> 9 | C58: ='Budget assumption'!C137+'Budget assumption'!C168+'Budget assumption'!C199+'Budget assumption'!C261 -> 9 | D58: ='Budget assumption'!D137+'Budget assumption'!D168+'Budget assumption'!D199+'Budget assumption'!D261 -> 9 | E58: ='Budget assumption'!E137+'Budget assumption'!E168+'Budget assumption'!E199+'Budget assumption'!E261 -> 9 | F58: ='Budget assumption'!F137+'Budget assumption'!F168+'Budget assumption'!F199+'Budget assumption'!F261 -> 8 | G58: ='Budget assumption'!G137+'Budget assumption'!G168+'Budget assumption'!G199+'Budget assumption'!G261 -> 8 | H58: ='Budget assumption'!H137+'Budget assumption'!H168+'Budget assumption'!H199+'Budget assumption'!H261 -> 8 | I58: ='Budget assumption'!I137+'Budget assumption'!I168+'Budget assumption'!I199+'Budget assumption'!I261 -> 8 | ... N58: ='Budget assumption'!N137+'Budget assumption'!N168+'Budget assumption'!N199+'Budget assumption'!N261 -> 100 | Q58: =SUMPRODUCT(B58:M58,B$2:M$2) -> 9 | R58: =SUMPRODUCT(B58:M58,B$1:M$1) -> 100
A59: Asset Sales | B59: ='Budget assumption'!B138+'Budget assumption'!B169+'Budget assumption'!B200+'Budget assumption'!B262 -> 0 | C59: ='Budget assumption'!C138+'Budget assumption'!C169+'Budget assumption'!C200+'Budget assumption'!C262 -> 0 | D59: ='Budget assumption'!D138+'Budget assumption'!D169+'Budget assumption'!D200+'Budget assumption'!D262 -> 0 | E59: ='Budget assumption'!E138+'Budget assumption'!E169+'Budget assumption'!E200+'Budget assumption'!E262 -> 0 | F59: ='Budget assumption'!F138+'Budget assumption'!F169+'Budget assumption'!F200+'Budget assumption'!F262 -> 0 | G59: ='Budget assumption'!G138+'Budget assumption'!G169+'Budget assumption'!G200+'Budget assumption'!G262 -> 0 | H59: ='Budget assumption'!H138+'Budget assumption'!H169+'Budget assumption'!H200+'Budget assumption'!H262 -> 0 | I59: ='Budget assumption'!I138+'Budget assumption'!I169+'Budget assumption'!I200+'Budget assumption'!I262 -> 0 | ... N59: ='Budget assumption'!N138+'Budget assumption'!N169+'Budget assumption'!N200+'Budget assumption'!N262 -> 0 | Q59: =SUMPRODUCT(B59:M59,B$2:M$2) -> 0 | R59: =SUMPRODUCT(B59:M59,B$1:M$1) -> 0
A60: TOTAL OTHERS | B60: =SUM(B55:B59) -> 17.816041 | C60: =SUM(C55:C59) -> 17.803638 | D60: =SUM(D55:D59) -> 16.804368 | E60: =SUM(E55:E59) -> 15.056609 | F60: =SUM(F55:F59) -> 13.843236 | G60: =SUM(G55:G59) -> 14.861414 | H60: =SUM(H55:H59) -> 11.677627 | I60: =SUM(I55:I59) -> 12.560221 | ... N60: =SUM(N55:N59) -> 174.66004 | Q60: =SUMPRODUCT(B60:M60,B$2:M$2) -> 15.056609 | R60: =SUMPRODUCT(B60:M60,B$1:M$1) -> 174.21929
A61: IT GLOBAL | B61: ='Budget assumption'!B140+'Budget assumption'!B171+'Budget assumption'!B202+'Budget assumption'!B264+'Budget assumption'!B295 -> 11.164158 | C61: ='Budget assumption'!C140+'Budget assumption'!C171+'Budget assumption'!C202+'Budget assumption'!C264+'Budget assumption'!C295 -> 11.164158 | D61: ='Budget assumption'!D140+'Budget assumption'!D171+'Budget assumption'!D202+'Budget assumption'!D264+'Budget assumption'!D295 -> 11.164158 | E61: ='Budget assumption'!E140+'Budget assumption'!E171+'Budget assumption'!E202+'Budget assumption'!E264+'Budget assumption'!E295 -> 7.1875052 | F61: ='Budget assumption'!F140+'Budget assumption'!F171+'Budget assumption'!F202+'Budget assumption'!F264+'Budget assumption'!F295 -> 35.024078 | G61: ='Budget assumption'!G140+'Budget assumption'!G171+'Budget assumption'!G202+'Budget assumption'!G264+'Budget assumption'!G295 -> -32.924823 | H61: ='Budget assumption'!H140+'Budget assumption'!H171+'Budget assumption'!H202+'Budget assumption'!H264+'Budget assumption'!H295 -> -9.1513526 | I61: ='Budget assumption'!I140+'Budget assumption'!I171+'Budget assumption'!I202+'Budget assumption'!I264+'Budget assumption'!I295 -> 0.35803554 | ... N61: ='Budget assumption'!N140+'Budget assumption'!N171+'Budget assumption'!N202+'Budget assumption'!N264+'Budget assumption'!N295 -> -77.50333 | Q61: =SUMPRODUCT(B61:M61,B$2:M$2) -> 7.1875052 | R61: =SUMPRODUCT(B61:M61,B$1:M$1) -> -77.50333
A62: G&A(Insurance included) | B62: ='Budget assumption'!B141+'Budget assumption'!B172+'Budget assumption'!B203+'Budget assumption'!B265+'Budget assumption'!B296 -> 27.352496 | C62: ='Budget assumption'!C141+'Budget assumption'!C172+'Budget assumption'!C203+'Budget assumption'!C265+'Budget assumption'!C296 -> 27.352496 | D62: ='Budget assumption'!D141+'Budget assumption'!D172+'Budget assumption'!D203+'Budget assumption'!D265+'Budget assumption'!D296 -> 27.352496 | E62: ='Budget assumption'!E141+'Budget assumption'!E172+'Budget assumption'!E203+'Budget assumption'!E265+'Budget assumption'!E296 -> 23.993521 | F62: ='Budget assumption'!F141+'Budget assumption'!F172+'Budget assumption'!F203+'Budget assumption'!F265+'Budget assumption'!F296 -> 47.506348 | G62: ='Budget assumption'!G141+'Budget assumption'!G172+'Budget assumption'!G203+'Budget assumption'!G265+'Budget assumption'!G296 -> -9.8883173 | H62: ='Budget assumption'!H141+'Budget assumption'!H172+'Budget assumption'!H203+'Budget assumption'!H265+'Budget assumption'!H296 -> 10.192513 | I62: ='Budget assumption'!I141+'Budget assumption'!I172+'Budget assumption'!I203+'Budget assumption'!I265+'Budget assumption'!I296 -> 18.224846 | ... N62: ='Budget assumption'!N141+'Budget assumption'!N172+'Budget assumption'!N203+'Budget assumption'!N265+'Budget assumption'!N296 -> 149.60403 | Q62: =SUMPRODUCT(B62:M62,B$2:M$2) -> 23.993521 | R62: =SUMPRODUCT(B62:M62,B$1:M$1) -> 149.60403
A63: TOTAL OVERHEAD | B63: =SUM(B61:B62) -> 38.516654 | C63: =SUM(C61:C62) -> 38.516654 | D63: =SUM(D61:D62) -> 38.516654 | E63: =SUM(E61:E62) -> 31.181026 | F63: =SUM(F61:F62) -> 82.530425 | G63: =SUM(G61:G62) -> -42.81314 | H63: =SUM(H61:H62) -> 1.0411608 | I63: =SUM(I61:I62) -> 18.582881 | ... N63: =SUM(N61:N62) -> 72.100696 | Q63: =SUMPRODUCT(B63:M63,B$2:M$2) -> 31.181026 | R63: =SUMPRODUCT(B63:M63,B$1:M$1) -> 72.100696
Q64: =SUMPRODUCT(B64:M64,B$2:M$2) -> 0 | R64: =SUMPRODUCT(B64:M64,B$1:M$1) -> 0
A65: TOTAL ALL | B65: =B54+B60+B63 -> 156.65097 | C65: =C54+C60+C63 -> 170.37032 | D65: =D54+D60+D63 -> 210.19856 | E65: =E54+E60+E63 -> 140.41355 | F65: =F54+F60+F63 -> 734.84705 | G65: =G54+G60+G63 -> -448.70705 | H65: =H54+H60+H63 -> -3.4048398 | I65: =I54+I60+I63 -> 144.19312 | ... N65: =N54+N60+N63 -> -21.608887 | Q65: =SUMPRODUCT(B65:M65,B$2:M$2) -> 140.41355 | R65: =SUMPRODUCT(B65:M65,B$1:M$1) -> -22.14072
A71: Budget Variances | B71: Jan | C71: Feb | D71: March | E71: April | F71: May | G71: June | H71: July | I71: August | J71: Sept | K71: Oct | L71: Nov | M71: Dec | N71: Total
A72: ='Budget assumption'!A316 -> mfg vs upload | B72: ='Budget assumption'!B316 -> 0 | C72: ='Budget assumption'!C316 -> 0 | D72: ='Budget assumption'!D316 -> 0 | E72: ='Budget assumption'!E316 -> 0 | F72: ='Budget assumption'!F316 -> 0 | G72: ='Budget assumption'!G316 -> 0 | H72: ='Budget assumption'!H316 -> 0 | ... N72: ='Budget assumption'!N316 -> 0 | Q72: =SUMPRODUCT(B72:M72,B$2:M$2) -> 0 | R72: =SUMPRODUCT(B72:M72,B$1:M$1) -> 0
A73: ACE | B73: ='Budget assumption'!B306 -> -6.7443971 | C73: ='Budget assumption'!C306 -> -7.1106746 | D73: ='Budget assumption'!D306 -> -7.1575234 | E73: ='Budget assumption'!E306 -> -13.784256 | F73: ='Budget assumption'!F306 -> -22.49989 | G73: ='Budget assumption'!G306 -> -58.908533 | H73: ='Budget assumption'!H306 -> -57.523255 | I73: ='Budget assumption'!I306 -> -57.204808 | ... N73: ='Budget assumption'!N306 -> -484 | Q73: =SUMPRODUCT(B73:M73,B$2:M$2) -> -13.784256 | R73: =SUMPRODUCT(B73:M73,B$1:M$1) -> -484.71583
A74: HWTW | B74: ='Budget assumption'!B308 -> -67.734714 | C74: ='Budget assumption'!C308 -> -136.5981 | D74: ='Budget assumption'!D308 -> -106.87028 | E74: ='Budget assumption'!E308 -> -47.120574 | F74: ='Budget assumption'!F308 -> -70.370518 | G74: ='Budget assumption'!G308 -> -71.974601 | H74: ='Budget assumption'!H308 -> -11.001751 | I74: ='Budget assumption'!I308 -> -7.4535707 | ... N74: ='Budget assumption'!N308 -> -605.66 | Q74: =SUMPRODUCT(B74:M74,B$2:M$2) -> -47.120574 | R74: =SUMPRODUCT(B74:M74,B$1:M$1) -> -606.90078
A75: Price & FX | B75: ='Budget assumption'!B307 -> 107.45659 | C75: ='Budget assumption'!C307 -> 105.7356 | D75: ='Budget assumption'!D307 -> 151.32286 | E75: ='Budget assumption'!E307 -> 176.96096 | F75: ='Budget assumption'!F307 -> 157.8825 | G75: ='Budget assumption'!G307 -> 72.777114 | H75: ='Budget assumption'!H307 -> -34.077079 | I75: ='Budget assumption'!I307 -> -54.265054 | ... N75: ='Budget assumption'!N307 -> 1069.4759 | Q75: =SUMPRODUCT(B75:M75,B$2:M$2) -> 176.96096 | R75: =SUMPRODUCT(B75:M75,B$1:M$1) -> 1069.4759
A76: FCA | B76: ='Budget assumption'!B310 -> -105.62146 | C76: ='Budget assumption'!C310 -> -105.21914 | D76: ='Budget assumption'!D310 -> -105.24281 | E76: ='Budget assumption'!E310 -> 5.9165059 | F76: ='Budget assumption'!F310 -> -108.57972 | G76: ='Budget assumption'!G310 -> 431.54994 | H76: ='Budget assumption'!H310 -> 371.58024 | I76: ='Budget assumption'!I310 -> 310.02491 | ... N76: ='Budget assumption'!N310 -> 2586.436 | Q76: =SUMPRODUCT(B76:M76,B$2:M$2) -> 5.9165059 | R76: =SUMPRODUCT(B76:M76,B$1:M$1) -> 2586.436
A77: seasonlaity | B77: ='Budget assumption'!B309 -> 123.67409 | C77: ='Budget assumption'!C309 -> 208.34409 | D77: ='Budget assumption'!D309 -> 172.90409 | E77: ='Budget assumption'!E309 -> 24.360042 | F77: ='Budget assumption'!F309 -> 669.83336 | G77: ='Budget assumption'!G309 -> -390.60881 | H77: ='Budget assumption'!H309 -> 99.197115 | I77: ='Budget assumption'!I309 -> 263.12548 | ... N77: ='Budget assumption'!N309 -> -1.9566099 | Q77: =SUMPRODUCT(B77:M77,B$2:M$2) -> 24.360042 | R77: =SUMPRODUCT(B77:M77,B$1:M$1) -> 1.66267e-12
A78: round 2 var | B78: =SUM(B72:B77) -> 51.030098 | C78: =SUM(C72:C77) -> 65.151769 | D78: =SUM(D72:D77) -> 104.95634 | E78: =SUM(E72:E77) -> 146.33268 | F78: =SUM(F72:F77) -> 626.26574 | G78: =SUM(G72:G77) -> -17.164891 | H78: =SUM(H72:H77) -> 368.17527 | I78: =SUM(I72:I77) -> 454.22696 | ... N78: =SUM(N72:N77) -> 2564.2953 | Q78: =SUMPRODUCT(B78:M78,B$2:M$2) -> 146.33268 | R78: =SUMPRODUCT(B78:M78,B$1:M$1) -> 2564.2953
B81: 3 | C81: 4 | D81: 5 | E81: 6 | F81: 7 | G81: 8 | H81: 9 | I81: 10 | J81: 11 | K81: 12 | L81: 13 | M81: 14
A82: Volume | B82: =+VOLUME!C7 -> 47357 | C82: =+VOLUME!D7 -> 42593.001 | D82: =+VOLUME!E7 -> 23002.001 | E82: =+VOLUME!F7 -> 44096 | F82: =+VOLUME!G7 -> 36000 | G82: =+VOLUME!H7 -> 54500.001 | H82: =+VOLUME!I7 -> 41500 | I82: =+VOLUME!J7 -> 39000.001 | ... N82: =+VOLUME!O7 -> 526227 | Q82: =SUMPRODUCT(B82:M82,B$2:M$2) -> 44096 | R82: =SUMPRODUCT(B82:M82,B$1:M$1) -> 526227
A83: Copertura | B83: Jan | C83: Feb | D83: March | E83: April | F83: May | G83: June | H83: July | I83: August | J83: Sept | K83: Oct | L83: Nov | M83: Dec | N83: Total | Q83: MTD | R83: YTD
A84: Direct Labour | B84: 536.4458 | C84: 482.03678 | D84: 276.12312 | E84: 465.28736 | F84: 409.61811 | G84: 620.11632 | H84: 472.19866 | I84: 443.75297 | J84: 615.39432 | K84: 568.54994 | L84: 590.9424 | M84: 480.04967 | N84: =SUM(B84:M84) -> 5960.5155 | Q84: =SUMPRODUCT(B84:M84,B$2:M$2) -> 465.28736 | R84: =SUMPRODUCT(B84:M84,B$1:M$1) -> 5960.5155
A85: Variable Utilities | B85: 35.686211 | C85: 32.002356 | D85: 18.351187 | E85: 30.915274 | F85: 27.76434 | G85: 42.032127 | H85: 32.006114 | I85: 30.078036 | J85: 41.712065 | K85: 38.536904 | L85: 40.054688 | M85: 32.538264 | N85: =SUM(B85:M85) -> 401.67757 | Q85: =SUMPRODUCT(B85:M85,B$2:M$2) -> 30.915274 | R85: =SUMPRODUCT(B85:M85,B$1:M$1) -> 401.67757
A86: Variable Costs | B86: 15.1712 | C86: 13.746193 | D86: 7.8790032 | E86: 13.272976 | F86: 12.653676 | G86: 19.15626 | H86: 14.586877 | I86: 13.708149 | J86: 19.010391 | K86: 17.563302 | L86: 18.255037 | M86: 14.829405 | N86: =SUM(B86:M86) -> 179.83247 | Q86: =SUMPRODUCT(B86:M86,B$2:M$2) -> 13.272976 | R86: =SUMPRODUCT(B86:M86,B$1:M$1) -> 179.83247
A87: VARIABLE CONVERSION | B87: =SUM(B84:B86) -> 587.30321 | C87: =SUM(C84:C86) -> 527.78533 | D87: =SUM(D84:D86) -> 302.35331 | E87: =SUM(E84:E86) -> 509.47561 | F87: =SUM(F84:F86) -> 450.03613 | G87: =SUM(G84:G86) -> 681.30471 | H87: =SUM(H84:H86) -> 518.79165 | I87: =SUM(I84:I86) -> 487.53915 | ... M87: =SUM(M84:M86) -> 527.41734 | N87: =SUM(B87:M87) -> 6542.0255 | Q87: =SUMPRODUCT(B87:M87,B$2:M$2) -> 509.47561 | R87: =SUMPRODUCT(B87:M87,B$1:M$1) -> 6542.0255
A88: Indirect Labour | B88: 212.14049 | C88: 190.5489 | D88: 109.11422 | E88: 184.03658 | F88: 160.6632 | G88: 243.22623 | H88: 185.20896 | I88: 174.0518 | J88: 241.37414 | K88: 223.00052 | L88: 231.78344 | M88: 188.28834 | N88: =SUM(B88:M88) -> 2343.4368 | Q88: =SUMPRODUCT(B88:M88,B$2:M$2) -> 184.03658 | R88: =SUMPRODUCT(B88:M88,B$1:M$1) -> 2343.4368
A89: Fixed Labour | B89: 74.965892 | C89: 67.454868 | D89: 38.698586 | E89: 65.067655 | F89: 58.114787 | G89: 87.979332 | H89: 66.993435 | I89: 62.957687 | J89: 87.309396 | K89: 80.663324 | L89: 83.840266 | M89: 68.107302 | N89: =SUM(B89:M89) -> 842.15253 | Q89: =SUMPRODUCT(B89:M89,B$2:M$2) -> 65.067655 | R89: =SUMPRODUCT(B89:M89,B$1:M$1) -> 842.15253
A90: Semifixed | B90: 145.37437 | C90: 130.62199 | D90: 74.809423 | E90: 126.16662 | F90: 112.19819 | G90: 169.8556 | H90: 129.33958 | I90: 121.54804 | J90: 168.5622 | K90: 155.73109 | L90: 161.86459 | M90: 131.49004 | N90: =SUM(B90:M90) -> 1627.5617 | Q90: =SUMPRODUCT(B90:M90,B$2:M$2) -> 126.16662 | R90: =SUMPRODUCT(B90:M90,B$1:M$1) -> 1627.5617
A91: Fixed utilities | B91: 7.9978 | C91: 7.23397 | D91: 4.08225 | E91: 6.95061 | F91: 7.1379527 | G91: 10.806067 | H91: 8.2284732 | I91: 7.7327823 | J91: 10.723782 | K91: 9.9074783 | L91: 10.297686 | M91: 8.365284 | N91: =SUM(B91:M91) -> 99.464137 | Q91: =SUMPRODUCT(B91:M91,B$2:M$2) -> 6.95061 | R91: =SUMPRODUCT(B91:M91,B$1:M$1) -> 99.464137
A92: Fixed Cost | B92: 37.110271 | C92: 33.289206 | D92: 19.053177 | E92: 32.152644 | F92: 28.690085 | G92: 43.433602 | H92: 33.073293 | I92: 31.080926 | J92: 43.102868 | K92: 39.821838 | L92: 41.390229 | M92: 33.623186 | N92: =SUM(B92:M92) -> 415.82133 | Q92: =SUMPRODUCT(B92:M92,B$2:M$2) -> 32.152644 | R92: =SUMPRODUCT(B92:M92,B$1:M$1) -> 415.82133
A93: Depreciation | B93: 489.95651 | C93: 441.20391 | D93: 246.63262 | E93: 424.54616 | F93: 367.56243 | G93: 556.44869 | H93: 423.7178 | I93: 398.19264 | J93: 552.2115 | K93: 510.17665 | L93: 530.27006 | M93: 430.76275 | N93: =SUM(B93:M93) -> 5371.6817 | Q93: =SUMPRODUCT(B93:M93,B$2:M$2) -> 424.54616 | R93: =SUMPRODUCT(B93:M93,B$1:M$1) -> 5371.6817
A94: FIXED CONVERSION | B94: =SUM(B88:B93) -> 967.54534 | C94: =SUM(C88:C93) -> 870.35285 | D94: =SUM(D88:D93) -> 492.39028 | E94: =SUM(E88:E93) -> 838.92027 | F94: =SUM(F88:F93) -> 734.36664 | G94: =SUM(G88:G93) -> 1111.7495 | H94: =SUM(H88:H93) -> 846.56154 | I94: =SUM(I88:I93) -> 795.56388 | ... M94: =SUM(M88:M93) -> 860.6369 | N94: =SUM(B94:M94) -> 10700.118 | Q94: =SUMPRODUCT(B94:M94,B$2:M$2) -> 838.92027 | R94: =SUMPRODUCT(B94:M94,B$1:M$1) -> 10700.118
A95: TOTAL MFG COST w/o SHARES | B95: =B87+B94 -> 1554.8485 | C95: =C87+C94 -> 1398.1382 | D95: =D87+D94 -> 794.74359 | E95: =E87+E94 -> 1348.3959 | F95: =F87+F94 -> 1184.4028 | G95: =G87+G94 -> 1793.0542 | H95: =H87+H94 -> 1365.3532 | I95: =I87+I94 -> 1283.103 | ... N95: =N87+N94 -> 17242.144 | Q95: =SUMPRODUCT(B95:M95,B$2:M$2) -> 1348.3959 | R95: =SUMPRODUCT(B95:M95,B$1:M$1) -> 17242.144
A96: TOTAL SHARES | Q96: =SUMPRODUCT(B96:M96,B$2:M$2) -> 0 | R96: =SUMPRODUCT(B96:M96,B$1:M$1) -> 0
A97: TOTAL MFG COST w/ SHARES | Q97: =SUMPRODUCT(B97:M97,B$2:M$2) -> 0 | R97: =SUMPRODUCT(B97:M97,B$1:M$1) -> 0
A98: Functional Currency Impact | Q98: =SUMPRODUCT(B98:M98,B$2:M$2) -> 0 | R98: =SUMPRODUCT(B98:M98,B$1:M$1) -> 0
A99: TOTAL Including FC | Q99: =SUMPRODUCT(B99:M99,B$2:M$2) -> 0 | R99: =SUMPRODUCT(B99:M99,B$1:M$1) -> 0
A100: Scrap | B100: 22.832815 | C100: 20.516916 | D100: 11.691481 | E100: 19.811558 | F100: 18.0162 | G100: 27.274526 | H100: 20.768675 | I100: 19.517551 | J100: 27.066838 | K100: 25.006486 | L100: 25.991371 | M100: 21.113985 | N100: =SUM(B100:M100) -> 259.6084 | Q100: =SUMPRODUCT(B100:M100,B$2:M$2) -> 19.811558 | R100: =SUMPRODUCT(B100:M100,B$1:M$1) -> 259.6084
A101: Scrap Reselling | B101: -56.297268 | C101: -50.701757 | D101: -29.029938 | E101: -48.888273 | F101: -44.28 | G101: -67.035001 | H101: -51.045 | I101: -47.970001 | J101: -66.52455 | K101: -61.46064 | L101: -63.88128 | M101: -51.8937 | N101: =SUM(B101:M101) -> -639.00741 | Q101: =SUMPRODUCT(B101:M101,B$2:M$2) -> -48.888273 | R101: =SUMPRODUCT(B101:M101,B$1:M$1) -> -639.00741
A102: Other Variable (Inventory Adj) | N102: =SUM(B102:M102) -> 0 | Q102: =SUMPRODUCT(B102:M102,B$2:M$2) -> 0 | R102: =SUMPRODUCT(B102:M102,B$1:M$1) -> 0
A103: Obsolete | N103: =SUM(B103:M103) -> 0 | Q103: =SUMPRODUCT(B103:M103,B$2:M$2) -> 0 | R103: =SUMPRODUCT(B103:M103,B$1:M$1) -> 0
A104: Asset Sales | N104: =SUM(B104:M104) -> 0 | Q104: =SUMPRODUCT(B104:M104,B$2:M$2) -> 0 | R104: =SUMPRODUCT(B104:M104,B$1:M$1) -> 0
A105: TOTAL OTHERS | B105: =SUM(B100:B104) -> -33.464453 | C105: =SUM(C100:C104) -> -30.184841 | D105: =SUM(D100:D104) -> -17.338457 | E105: =SUM(E100:E104) -> -29.076715 | F105: =SUM(F100:F104) -> -26.2638 | G105: =SUM(G100:G104) -> -39.760476 | H105: =SUM(H100:H104) -> -30.276325 | I105: =SUM(I100:I104) -> -28.452451 | ... M105: =SUM(M100:M104) -> -30.779714 | N105: =SUM(B105:M105) -> -379.39901 | Q105: =SUMPRODUCT(B105:M105,B$2:M$2) -> -29.076715 | R105: =SUMPRODUCT(B105:M105,B$1:M$1) -> -379.39901
A106: IT GLOBAL | B106: =+B108*('Budget assumption'!B233/'Budget assumption'!B235) -> 74.699583 | C106: 67.140322 | D106: 38.439465 | E106: 64.814167 | F106: 57.587918 | G106: 87.18171 | H106: 66.386072 | I106: 62.386912 | J106: 86.517848 | K106: 79.93203 | L106: 83.080169 | M106: 67.48984 | N106: =SUM(B106:M106) -> 835.65604 | Q106: =SUMPRODUCT(B106:M106,B$2:M$2) -> 64.814167 | R106: =SUMPRODUCT(B106:M106,B$1:M$1) -> 835.65604
A107: G&A(Insurance included) | B107: =+B108*('Budget assumption'!B234/'Budget assumption'!B235) -> 77.857964 | C107: 69.97909 | D107: 40.064728 | E107: 67.554582 | F107: 60.022799 | G107: 90.86785 | H107: 69.192949 | I107: 65.024701 | J107: 90.175919 | K107: 83.311645 | L107: 86.592891 | M107: 70.343386 | N107: =SUM(B107:M107) -> 870.9885 | Q107: =SUMPRODUCT(B107:M107,B$2:M$2) -> 67.554582 | R107: =SUMPRODUCT(B107:M107,B$1:M$1) -> 870.9885
A108: TOTAL OVERHEAD | B108: 152.55755 | C108: =SUM(C106:C107) -> 137.11941 | D108: =SUM(D106:D107) -> 78.504194 | E108: =SUM(E106:E107) -> 132.36875 | F108: =SUM(F106:F107) -> 117.61072 | G108: =SUM(G106:G107) -> 178.04956 | H108: =SUM(H106:H107) -> 135.57902 | I108: =SUM(I106:I107) -> 127.41161 | J108: =SUM(J106:J107) -> 176.69377 | ... N108: =SUM(N106:N107) -> 1706.6445 | Q108: =SUMPRODUCT(B108:M108,B$2:M$2) -> 132.36875 | R108: =SUMPRODUCT(B108:M108,B$1:M$1) -> 1706.6445
Q109: =SUMPRODUCT(B109:M109,B$2:M$2) -> 0 | R109: =SUMPRODUCT(B109:M109,B$1:M$1) -> 0
A110: TOTAL ALL | B110: =+B95+B105+B108 -> 1673.9416 | C110: =+C95+C105+C108 -> 1505.0727 | D110: =+D95+D105+D108 -> 855.90933 | E110: =+E95+E105+E108 -> 1451.6879 | F110: =+F95+F105+F108 -> 1275.7497 | G110: =+G95+G105+G108 -> 1931.3433 | H110: =+H95+H105+H108 -> 1470.6559 | I110: =+I95+I105+I108 -> 1382.0622 | ... N110: =+N95+N105+N108 -> 18569.389 | Q110: =SUMPRODUCT(B110:M110,B$2:M$2) -> 1451.6879 | R110: =SUMPRODUCT(B110:M110,B$1:M$1) -> 18569.389
A111: CHECK
A112: 3+9 | F112: 53.588433 | G112: 54.811 | H112: 55.699667 | I112: 56.588333 | J112: 57.477 | K112: 58.334 | L112: 59.191 | M112: 60.048 | O112: 1000
A113: 4+8 | F113: 52.927767 | G113: 53.82 | H113: 54.721667 | I113: 55.623333 | J113: 56.525 | K113: 57.283333 | L113: 58.041667 | M113: 58.8
...

Sheet SAP Actual extraction
H2: *** revise the formulas for previous month | M2: =M4-36000 -> 376577.93 | N2: =N4+36000 -> 370421.9
B3: SUMMARY | C3: MTD | I3: SUMMARY | J3: YTD | K3: Jan | L3: Feb | M3: March | N3: April | O3: May | P3: June | Q3: July | R3: August | S3: Sept | T3: Oct | U3: Nov | V3: Dec | W3: TOTAL | X3: Check
B4: * CS_Depreciation | C4: =SUMIF($B$29:$B$265,$B4,$C$29:$C$265) -> 425496.57 | H4: Depreciation | I4: * CS_Depreciation | J4: =SUMIF($P$29:$P$265,$I4,$Q$29:$Q$265) -> 4619880.9 | K4: 375963.08 | L4: 346086.07 | M4: 412577.93 | N4: 334421.9 | O4: 403917.55 | P4: 395811.35 | Q4: 401611.09 | R4: 401425.45 | S4: 392242.53 | T4: 342008.27 | U4: 388319.08 | V4: =C4 -> 425496.57 | W4: =SUM(K4:V4) -> 4619880.9 | X4: =W4-J4 -> 0
B5: * CS_Direct Labour | C5: =SUMIF($B$29:$B$265,$B5,$C$29:$C$265) -> 761873.35 | H5: Direct Labor | I5: * CS_Direct Labour | J5: =SUMIF($P$29:$P$265,$I5,$Q$29:$Q$265) -> 7159466.5 | K5: 751784.6 | L5: 351146.64 | M5: 504814.36 | N5: 447695.15 | O5: 481373 | P5: 325889.24 | Q5: 481125.28 | R5: 562670.21 | S5: 812328.16 | T5: 961837.48 | U5: 716928.98 | V5: =C5 -> 761873.35 | W5: =SUM(K5:V5) -> 7159466.5 | X5: =W5-J5 -> 0
B6: * CS_SCRAP_VARIABLE | C6: =SUMIF($B$29:$B$265,$B6,$C$29:$C$265) -> 25658.44 | H6: Scrap | I6: * CS_SCRAP_VARIABLE | J6: =SUMIF($P$29:$P$265,$I6,$Q$29:$Q$265) -> 325569.2 | K6: 32834.38 | L6: 19979.83 | M6: 21245.64 | N6: 27696.57 | O6: 19102.93 | P6: 2066.97 | Q6: 23466.75 | R6: 26892.59 | S6: 29389.62 | T6: 43395.48 | U6: 41727.86 | V6: =C6 -> 25658.44 | W6: =SUM(K6:V6) -> 313457.06 | X6: =W6-J6 -> -12112.14
B7: * CS_Fix Cost | C7: =SUMIF($B$29:$B$265,$B7,$C$29:$C$265)-SUMIF($B$29:$B$265,$D$7,$C$29:$C$265) -> -39181.53 | D7: 6666050312 Inventory count different- Semifinished | H7: Fixed Cost | I7: * CS_Fix Cost | J7: =SUMIF($P$29:$P$265,$I7,$Q$29:$Q$265)-SUMIF($P$29:$P$265,$D$7,$Q$29:$Q$265) -> 642922.42 | K7: 61839.48 | L7: 65350.86 | M7: 68629.34 | N7: 67421.69 | O7: 75825 | P7: 58807.19 | Q7: 61424.56 | R7: 50182.71 | S7: 52085.46 | T7: 63695.24 | U7: 56842.42 | V7: =C7 -> -39181.53 | W7: =SUM(K7:V7) -> 642922.42 | X7: =W7-J7 -> 0
B8: * CS_Variable Cost | C8: =SUMIF($B$29:$B$265,$B8,$C$29:$C$265)+SUMIF($B$29:$B$265,$D$7,$C$29:$C$265) -> -139062.89 | H8: Other Variable (Production Consumable, Inventory ADJ) | I8: * CS_Variable Cost | J8: =SUMIF($P$29:$P$265,$I8,$Q$29:$Q$265)+SUMIF($P$29:$P$265,$D$7,$Q$29:$Q$265) -> -10833.72 | K8: 9381.74 | L8: 14433.91 | M8: 8302.39 | N8: 7490.26 | O8: 41244.88 | P8: -61537.73 | Q8: 11031.76 | R8: 19370.21 | S8: 10808.11 | T8: 53077.35 | U8: 14626.29 | V8: =C8 -> -139062.89 | W8: =SUM(K8:V8) -> -10833.72 | X8: =W8-J8 -> 4.3655746e-11
B9: * CS_Obsolescence | C9: =SUMIF($B$29:$B$265,$B9,$C$29:$C$265) -> 114586.24 | H9: Obsolete | I9: * CS_Obsolescence | J9: =SUMIF($P$29:$P$265,$I9,$Q$29:$Q$265) -> 264585.31 | K9: 27874.31 | L9: 25000 | M9: 25000 | N9: 25000 | O9: 25000 | P9: 31056.07 | Q9: 25000 | R9: -25000 | S9: -36819.17 | T9: 25000 | U9: 15000 | V9: =C9 -> 114586.24 | W9: =SUM(K9:V9) -> 276697.45 | X9: =W9-J9 -> 12112.14
B10: * CS_Reselling | C10: =SUMIF($B$29:$B$265,$B10,$C$29:$C$265) -> -112054.34 | H10: Scrap Reselling | I10: * CS_Reselling | J10: =SUMIF($P$29:$P$265,$I10,$Q$29:$Q$265) -> -1094625.3 | K10: -112278.32 | L10: -85893.39 | M10: -67927.73 | N10: -72652.89 | O10: -73397.41 | P10: -41000.62 | Q10: -68022.12 | R10: -112161.92 | S10: -118823.18 | T10: -128119.05 | U10: -102294.37 | V10: =C10 -> -112054.34 | W10: =SUM(K10:V10) -> -1094625.3 | X10: =W10-J10 -> 0
B11: * CS_Fix Utilities | C11: =SUMIF($B$29:$B$265,$B11,$C$29:$C$265) -> 8548.05 | H11: Fixed utilities | I11: * CS_Fix Utilities | J11: =SUMIF($P$29:$P$265,$I11,$Q$29:$Q$265) -> 58547.42 | K11: 2921.76 | L11: 5863.85 | M11: 4120.75 | N11: 3334.89 | O11: 4336.07 | P11: 1059.71 | Q11: 3511.44 | R11: 5318.79 | S11: 6496.8 | T11: 4030.94 | U11: 9004.37 | V11: =C11 -> 8548.05 | W11: =SUM(K11:V11) -> 58547.42 | X11: =W11-J11 -> 0
B12: * CS_Variable Utilities | C12: =SUMIF($B$29:$B$265,$B12,$C$29:$C$265) -> 34153.77 | H12: Variable Utilities | I12: * CS_Variable Utilities | J12: =SUMIF($P$29:$P$265,$I12,$Q$29:$Q$265) -> 550099.01 | K12: 58426.78 | L12: 44301.28 | M12: 43208.99 | N12: 25781.84 | O12: 39352.91 | P12: 22841.97 | Q12: 41803.6 | R12: 64419.74 | S12: 50371.85 | T12: 63356.64 | U12: 62079.64 | V12: =C12 -> 34153.77 | W12: =SUM(K12:V12) -> 550099.01 | X12: =W12-J12 -> 0
B13: * CS_Indirect Labour | C13: =SUMIF($B$29:$B$265,$B13,$C$29:$C$265) -> 331422.28 | H13: Indirect Labour | I13: * CS_Indirect Labour | J13: =SUMIF($P$29:$P$265,$I13,$Q$29:$Q$265) -> 3474698.4 | K13: 321977.39 | L13: 198443.41 | M13: 285535.62 | N13: 225529.23 | O13: 213264.63 | P13: 236216.63 | Q13: 288816.19 | R13: 269213.85 | S13: 348394.52 | T13: 409578.62 | U13: 346306.02 | V13: =C13 -> 331422.28 | W13: =SUM(K13:V13) -> 3474698.4 | X13: =W13-J13 -> 0
B14: * CS_Fixed Labour | C14: =SUMIF($B$29:$B$265,$B14,$C$29:$C$265) -> 108584.05 | H14: Fixed Labour | I14: * CS_Fixed Labour | J14: =SUMIF($P$29:$P$265,$I14,$Q$29:$Q$265) -> 1420340.9 | K14: 140072.02 | L14: 154529.79 | M14: 123496 | N14: 87980.42 | O14: 133242.53 | P14: 130965.49 | Q14: 109540.08 | R14: 113113.51 | S14: 107933.55 | T14: 105670.01 | U14: 105213.48 | V14: =C14 -> 108584.05 | W14: =SUM(K14:V14) -> 1420340.9 | X14: =W14-J14 -> 0
B15: * CS_Semifix | C15: =SUMIF($B$29:$B$265,$B15,$C$29:$C$265) -> 149924.34 | H15: Semifixed | I15: * CS_Semifix | J15: =SUMIF($P$29:$P$265,$I15,$Q$29:$Q$265) -> 1907628.7 | K15: 211060.15 | L15: 182080.4 | M15: 163505.71 | N15: 137378.03 | O15: 133422.29 | P15: 110913.8 | Q15: 110802.11 | R15: 146197.63 | S15: 219780.68 | T15: 191796.25 | U15: 150767.28 | V15: =C15 -> 149924.34 | W15: =SUM(K15:V15) -> 1907628.7 | X15: =W15-J15 -> 0
B16: * CS_OVH_ADM | C16: =SUMIF($B$29:$B$265,$B16,$C$29:$C$265) -> -135958.59 | H16: Shares & Out of Perimeter | I16: * CS_OVH_ADM | J16: =SUMIF($P$29:$P$265,$I16,$Q$29:$Q$265) -> 3113518.9 | K16: 289689.19 | L16: 355134.83 | M16: 297322.5 | N16: 264191.68 | O16: 298717.94 | P16: 281687.49 | Q16: 284409.78 | R16: 269045.75 | S16: 313719.86 | T16: 311760.45 | U16: 283797.98 | V16: =C16 -> -135958.59 | W16: =SUM(K16:V16) -> 3113518.9 | X16: =W16-J16 -> 0
B17: TOTAL | C17: =SUM(C4:C16) -> 1533989.7 | I17: TOTAL | J17: =SUM(J4:J16) -> 22431798 | K17: =SUM(K4:K16) -> 2171546.6 | L17: =SUM(L4:L16) -> 1676457.5 | M17: =SUM(M4:M16) -> 1889831.5 | N17: =SUM(N4:N16) -> 1581268.8 | O17: =SUM(O4:O16) -> 1795402.3 | P17: =SUM(P4:P16) -> 1494777.6 | Q17: =SUM(Q4:Q16) -> 1774520.5 | R17: 1790688.5 | S17: =SUM(S4:S16) -> 2187908.8 | T17: =SUM(T4:T16) -> 2447087.7 | U17: =SUM(U4:U16) -> 2088319 | V17: =SUM(V4:V16) -> 1533989.7 | W17: =SUM(K17:V17) -> 22431798 | X17: =W17-J17 -> 0
B19: Check | C19: =C17-C256 -> 0 | I19: Check | J19: =J17-Q256 -> 0
B21: 6666050312 Inventory count different- Semifinished | C21: * CS_Fix Cost | D21: * CS_Variable Cost
B25: MTD | P25: YTD
