Workbook
Name \0: #REF!
Name \0: #REF!
Name \0: #REF!
Name \0: #REF!
Name \0: #REF!
Name \0: #REF!
Name \0: #REF!
Name \0: #REF!
Name \0: #REF!
Name \0: #REF!
Name \2: #REF!
Name \2: #REF!
Name \2: #REF!
Name \2: #REF!
Name \2: #REF!
Name \2: #REF!
Name \2: #REF!
Name \2: #REF!
Name \2: #REF!
Name \2: #REF!
Name \a: '[1]FA-LISTING'!#REF!
Name \a: '[1]FA-LISTING'!#REF!
Name \a: '[1]FA-LISTING'!#REF!
Name \a: #REF!
Name \a: #REF!
Name \a: #REF!
Name \a: #REF!
Name \a: #REF!
Name \a: #REF!
Name \a: #REF!
Name \B: '[1]FA-LISTING'!#REF!
Name \B: '[1]FA-LISTING'!#REF!
Name \B: '[1]FA-LISTING'!#REF!
Name \b: #REF!
Name \b: #REF!
Name \b: #REF!
Name \b: #REF!
Name \b: #REF!
Name \b: #REF!
Name \b: #REF!
Name \b1: #REF!
Name \b1: #REF!
Name \b1: #REF!
Name \b1: #REF!
Name \b1: #REF!
Name \b1: #REF!
Name \b1: #REF!
Name \b1: #REF!
Name \b1: #REF!
Name \b1: #REF!
Name \m: #REF!
Name \m: #REF!
Name \m: #REF!
Name \m: #REF!
Name \m: #REF!
Name \m: #REF!
Name \m: #REF!
Name \m: #REF!
Name \m: #REF!
Name \m: #REF!

Sheet DW  2026
A1: 1月费用总结： ①单：1月同期35欧元/台，订单量4.86万台，预测单台费用36.4欧元/台，较同期↑3.9%；实际37.48欧元/台，较同期↑6% 共梳理出8个问题
A2: KPI | B2: ACT 2025 | C2: Budget | D2: Budget-ACT VARIANCE | E2: Act | F2: CPU-Y0Y | G2: Analysis
A4: QTY | B4: 478100 | C4: 565020 | D4: =C4-B4 -> 86920
A5: Work days | B5: 237 | C5: 220 | D5: =C5-B5 -> -17
A6: Direct Labour | B6: 2372 | C6: 2969 | D6: =C6-B6 -> 597
A7: Direct Labour avrerage salary | B7: =0.114397955970597*1000 -> 114.39796 | C7: =0.113723208386452*1000 -> 113.72321 | D7: =C7-B7 -> -0.67474758 | G7: Direct Labour crease，Why decrease？ 人数上涨，工资下降
A8: indirect Labour | B8: 1000 | C8: 1020 | D8: =C8-B8 -> 20
A9: indirect Labour avrerage salary | B9: =2575/B8*1000 -> 2575 | C9: =2701/C8*1000 -> 2648.0392 | D9: =C9-B9 -> 73.039216
A10: Fixed Labour | B10: 293 | C10: 323 | D10: =C10-B10 -> 30
A11: Fixed avrerage salary | B11: =1047/B10*1000 -> 3573.3788 | C11: =1249/C10*1000 -> 3866.8731 | D11: =C11-B11 -> 293.49423 | G11: Why crease 上涨293万
A12: UPH | B12: 10.3048 | C12: 10.400748 | D12: =C12-B12 -> 0.095948021
A13: CPU | B13: =SUM(B14:B26) -> 42.496033 | C13: =SUM(C14:C26) -> 39.975046 | D13: =C13-B13 -> -2.5209874
A14: CS_Depreciation | B14: 13.955205 | C14: 12.395924 | D14: =C14-B14 -> -1.5592803
A15: CS_Fix Cost | B15: 1.0082632 | C15: 1.1921554 | D15: =C15-B15 -> 0.18389221 | G15: Why crease？ 固定人工预测上涨0.18
A16: CS_Obsolescence | B16: 0.50954071 | C16: 0.17698546 | D16: =C16-B16 -> -0.33255524
A17: CS_Fix Utilities | B17: 0.15380524 | C17: 0.11597097 | D17: =C17-B17 -> -0.037834271
A18: Indirect Labour | B18: 5.5151107 | C18: 4.7809268 | D18: =C18-B18 -> -0.73418393
A19: Fixed Labour | B19: 2.2433178 | C19: 2.2112842 | D19: =C19-B19 -> -0.0320336
A20: CS_Semifix | B20: 3.325059 | C20: 3.8154444 | D20: =C20-B20 -> 0.49038533 | G20: Why crease？ 半固定单台上涨0.49
A21: CS_Direct Labour | B21: 11.095745 | C21: 10.755978 | D21: =C21-B21 -> -0.3397671
A22: CS_SCRAP_VARIABLE | B22: 0.58196637 | C22: 0.44001178 | D22: =C22-B22 -> -0.14195459
A23: CS_Variable Cost | B23: 0.2931156 | C23: 0.32747707 | D23: =C23-B23 -> 0.034361472
A24: CS_Reselling | B24: -1.3629003 | C24: -1.0365156 | D24: =C24-B24 -> 0.32638466
A25: CS_Variable Utilities | B25: 0.64202061 | C25: 0.71735626 | D25: =C25-B25 -> 0.075335649
A26: GMA | B26: 4.535785 | C26: 4.0820473 | D26: =C26-B26 -> -0.45373768
A27: IT Expense-Internal Charge Out | B27: 2.0598917 | C27: 1.7973014 | D27: -0.1274777 | F27: =(E27/B27)-1 -> -1
A28: Association dues | B28: 0.10364806 | C28: 0.12931195 | D28: 0.24760611 | F28: =(E28/B28)-1 -> -1
A29: G&A | B29: 1.4372934 | C29: 1.8673518 | D29: 0.299214 | F29: =(E29/B29)-1 -> -1
A30: 类型 | B30: CODE | C30: Description | D30: Description(CN) | E30: K€ | F30: QTY-2025 | G30: 478100 | H30: Budget-QTY | I30: 565020 | J30: ACT-QTY
E31: MFG-2025 | F31: CPU-2025 | G31: Budget-2026 | H31: Budget-CPU-2026 | I31: ACT-2026 | J31: ACT-CPU-2026 | K31: CPU-Y0Y | L31: Budget-ACT VARIANCE | M31: CPU-Y0Y Analysis | N31: Budget-ACT VARIANCE Analysis
A32: 折旧 | B32: 6666110101 | C32: 6666110101 Depreciation of buildings | D32: 建筑物折旧 | E32: 364.2985 | F32: 0.76197134 | G32: 383.10318 | H32: 0.67803473 | L32: =H32-F32 -> -0.083936614
B33: 6666110106 | C33: 6666110106 Depreciation of R&D facilities | D33: 研发设施折旧 | E33: 0 | F33: 0 | G33: 0 | H33: 0 | L33: =H33-F33 -> 0
B34: 6666110107 | C34: 6666110107 Depreciation of mold | D34: 模具折旧 | E34: 2576.6794 | F34: 5.3894151 | G34: 2795.0328 | H34: 4.9467857 | L34: =H34-F34 -> -0.44262943
B35: 6666110110 | C35: 6666110110 Depreciation-Plant & Machinery | D35: 厂房及机械折旧 | E35: 3385.4586 | F35: 7.081068 | G35: 3606.3598 | H35: 6.3827118 | L35: =H35-F35 -> -0.69835619
B36: 6666110112 | C36: 6666110112 Depreciation of Furniture & Fixture | D36: 家具及装置折旧 | E36: 116.10877 | F36: 0.24285457 | G36: 175.22479 | H36: 0.31012139 | L36: =H36-F36 -> 0.067266822
B37: 6666110204 | C37: 6666110204 Amortization of license, trademarks and | D37: 许可证、商标及摊销 | E37: 2.8363716 | F37: 0.0059325907 | G37: 3.0302 | H37: 0.005362996 | L37: =H37-F37 -> -0.00056959475
B38: 6666110207 | C38: 6666110207 Amortization of Software | D38: 软件摊销 | E38: 60.971559 | F38: 0.12752888 | G38: 41.219178 | H38: 0.072951715 | L38: =H38-F38 -> -0.054577168
B39: 6666110506 | C39: 6666110506 Amortization-Leasehold Improvement | D39: 租赁改良摊销 | E39: 7.5633708 | F39: 0.015819642 | G39: 0 | H39: 0 | L39: =H39-F39 -> -0.015819642
B40: 6666110206 | C40: 6666110206 Amortization of Patents | D40: 专利摊销 | F40: 0 | G40: 0 | H40: 0 | L40: =H40-F40 -> 0
B41: FIX | C41: * CS_Depreciation | D41: * CS_折旧 | E41: 6513.9165 | F41: 13.62459 | G41: 7003.97 | H41: 12.395968 | L41: =H41-F41 -> -1.2286218
A42: 直接人工 | B42: 5001010205 | C42: 5001010205 Unemployment Insurance -blue collar-Dire | D42: 失业保险-蓝领-直接 | E42: 82.58064 | F42: 0.17272671 | G42: 110.38167 | H42: 0.19535887 | L42: =H42-F42 -> 0.022632162
B43: 6666010380 | C43: 6666010380 Incentive | D43: 激励 | E43: 6.35019 | F43: 0.013282138 | G43: -287.17262 | H43: -0.50825213 | L43: =H43-F43 -> -0.52153427 | N43: 在2025年，社会安全额外支付了21千欧元。然而，为了详细解释差异，我们需要人力资源部门。因为劳动成本的计算是由他们完成的。
B44: 6666010019 | C44: 6666010019 Payroll Taxes - Blue Collar Direct | E44: 659.07762 | F44: 1.3785351 | G44: 1145.2098 | H44: 2.0268483 | L44: =H44-F44 -> 0.64831322 | N44: 这个账户与直接劳动工资税有关。由于工资金额和人力成本的增加（2025法案218至2026预算247），该账户有所增加。然而，为了详细解释差异，我们需要人力资源部门。因为劳动成本的计算是由他们完成的。
B45: 6666010183 | C45: 6666010183 Overtime-Blue Collar-Direct | D45: 蓝领加班费-直接 | E45: 317.14723 | F45: 0.66334915 | G45: 0 | H45: 0 | L45: =H45-F45 -> -0.66334915
B46: 6666010229 | C46: 6666010229 Staff Leaving Indemnity - Blue Collar Di | D46: 蓝领离职赔偿-直接 | E46: 108.11015 | F46: 0.22612456 | G46: 101.51214 | H46: 0.17966115 | L46: =H46-F46 -> -0.046463402
B47: 6666010188 | C47: 6666010188 Salary - Blue collar direct employees | D47: 蓝领直接员工工资 | E47: 4063.1788 | F47: 8.4985962 | G47: 5007.4329 | H47: 8.8623994 | L47: =H47-F47 -> 0.3638032
B48: 5102040406 | C48: 5102040406 Other revenue-Service/Secondment agreeme | D48: 其他收入-服务/派遣协议 | E48: 0 | F48: 0 | G48: 0 | H48: 0 | L48: =H48-F48 -> 0
B49: 6666010115 | C49: 6666010115 Salary-Blue collar direct employees-Accr | D49: 蓝领直接员工工资-应计 | E49: -55.43767 | F49: -0.11595413 | G49: 0 | H49: 0 | L49: =H49-F49 -> 0.11595413
B50: VAR | C50: * CS_Direct Labour | D50: * CS_直接劳动 | E50: 5181.007 | F50: 10.83666 | G50: 6077.3639 | H50: 10.756016 | L50: =H50-F50 -> -0.080644114
A51: 可回收废料 | B51: 8701530201 | C51: 8701530201 Scrap-Raw Material - Managerial | D51: 废料-原材料-管理 | E51: 0 | F51: 0 | G51: 0 | H51: 0 | L51: =H51-F51 -> 0
B52: 6666050309 | C52: 6666050309 SFG scrap | D52: SFG废料 | E52: 124.32366 | F52: 0.26003694 | G52: 248.61634 | H52: 0.44001334 | L52: =H52-F52 -> 0.1799764
B53: 6666050308 | C53: 6666050308 Raw material scrap | D53: 原材料废料 | E53: 145.2031 | F53: 0.30370864 | G53: 0 | H53: 0 | L53: =H53-F53 -> -0.30370864 | N53: 我们应该考虑废料的总金额以便进行比较。2025年实际废料成本包括原材料、半成品和成品废料。然而在预算中，我们将总废料金额计入一个账户，因为我们不知道账户之间的分配。
B54: 6666050306 | C54: 6666050306 Finished goods scrap | D54: 成品废料 | E54: 2.86061 | F54: 0.005983288 | G54: 0 | H54: 0 | L54: =H54-F54 -> -0.005983288
B55: VAR | C55: * CS_SCRAP_VARIABLE | D55: * CS_废料变量 | E55: 272.38737 | F55: 0.56972886 | G55: 248.61634 | H55: 0.44001334 | L55: =H55-F55 -> -0.12971553
A56: 组织运营 | B56: 5102010151 | C56: 5102010151 Other Rev.-Interco-Epidemic problem comp | D56: 其他收入-内部公司-疫情问题补偿 | E56: 0 | F56: 0 | G56: 0 | H56: 0 | L56: =H56-F56 -> 0
B57: 5001010200 | C57: 5001010200 Cost of Manufacture - Raw Material | D57: 制造成本-原材料 | E57: 0.22851 | F57: 0.0004779544 | G57: 0 | H57: 0 | L57: =H57-F57 -> -0.0004779544
B58: 5001010201 | C58: 5001010201 Cost of Manufacture - Raw Material-Freig | D58: 制造成本-原材料-运费 | E58: 0.18324 | F58: 0.0003832671 | G58: 0 | H58: 0 | L58: =H58-F58 -> -0.0003832671
B59: 5207000011 | C59: 5207000011 Gain of tangible asset disposal | D59: 有形资产处置收益 | E59: 0 | F59: 0 | G59: 0 | H59: 0 | L59: =H59-F59 -> 0
B60: 5207000012 | C60: 5207000012 Loss of tangible asset sold | D60: 出售有形资产损失 | E60: 0 | F60: 0 | G60: 0 | H60: 0 | L60: =H60-F60 -> 0
B61: 5207000022 | C61: 5207000022 Loss of intangible asset disposal | D61: 无形资产处置损失 | E61: 0 | F61: 0 | G61: 0 | H61: 0 | L61: =H61-F61 -> 0
B62: 5301060000 | C62: 5301060000 Other Income-Subsidy income | D62: 其他收入-补贴收入 | E62: 0 | F62: 0 | G62: 0 | H62: 0 | L62: =H62-F62 -> 0
B63: 5301999999 | C63: 5301999999 Non-operation revenue-Other | D63: 非经营收入-其他 | E63: -0.06594 | F63: -0.00013792094 | G63: 0 | H63: 0 | L63: =H63-F63 -> 0.00013792094
B64: 5405030000 | C64: 5405030000 Other cost-others | D64: 其他成本-其他 | E64: 1.47277 | F64: 0.0030804643 | G64: 0 | H64: 0 | L64: =H64-F64 -> -0.0030804643
B65: 5601050000 | C65: 5601050000 Non-Operating Expense - Penalty | D65: 非经营费用-罚款 | E65: 0.06526 | F65: 0.00013649864 | G65: 0 | H65: 0 | L65: =H65-F65 -> -0.00013649864
B66: 5601050100 | C66: 5601050100 Non-operation Expense-Others | D66: 非经营费用-其他 | E66: 0.05161 | F66: 0.00010794813 | G66: 0 | H66: 0 | L66: =H66-F66 -> -0.00010794813
B67: 5102040893 | C67: 5102040893 Other revenue-Charge out-Test Expense | D67: 其他收入-费用支出-测试费用 | E67: 0 | F67: 0 | G67: 0 | H67: 0 | L67: =H67-F67 -> 0
B68: 5801000041 | C68: 5801000041 Previous year Sundry cost | D68: 去年杂项成本 | E68: 0 | F68: 0 | G68: 0 | H68: 0 | L68: =H68-F68 -> 0
B69: 6666010322 | C69: 6666010322 fuel allowance | D69: 燃料津贴 | E69: 16.08902 | F69: 0.033651997 | G69: 22.452132 | H69: 0.03973688 | L69: =H69-F69 -> 0.006084883
B70: 6666020101 | C70: 6666020101 Entertainment | D70: 娱乐 | E70: -7.82509 | F70: -0.016367057 | G70: 52.110409 | H70: 0.092227548 | L70: =H70-F70 -> 0.10859461 | N70: 这个账户中有一些与工会协议相关的费用（野餐、早餐等）。在2025年我们没有使用这笔预算。然而，我们必须为这个账户做预算，以防工会要求支出。
B71: 6666020201 | C71: 6666020201 Domestic business travel | D71: 国内商务旅行 | E71: 9.49769 | F71: 0.019865488 | G71: 28.307139 | H71: 0.050099357 | L71: =H71-F71 -> 0.030233868 | N71: 2026年为总部同事增加19千欧元的额外预算
B72: 6666020202 | C72: 6666020202 Overseas business travel | D72: 海外商务旅行 | E72: 1.38056 | F72: 0.0028875967 | G72: 0 | H72: 0 | L72: =H72-F72 -> -0.0028875967
B73: 6666020204 | C73: 6666020204 Travel expense pay to agency | D73: 支付给代理的旅行费用 | E73: 4.52682 | F73: 0.0094683539 | G73: 0 | H73: 0 | L73: =H73-F73 -> -0.0094683539
B74: 6666020205 | C74: 6666020205 Business travel-other | D74: 商务旅行-其他 | E74: -0.18314 | F74: -0.00038305794 | G74: 0 | H74: 0 | L74: =H74-F74 -> 0.00038305794
B75: 6666020301 | C75: 6666020301 Staff communic | D75: 员工通讯 | E75: 4.75334 | F75: 0.009942146 | G75: 4.1958777 | H75: 0.0074260693 | L75: =H75-F75 -> -0.0025160767
B76: 6666020302 | C76: 6666020302 Communication Expenses | D76: 通讯费用 | E76: 0 | F76: 0 | G76: 0.4785095 | H76: 0.00084688948 | L76: =H76-F76 -> 0.00084688948
B77: 6666020403 | C77: 6666020403 Company car expense | D77: 公司车辆费用 | F77: 0 | G77: 0 | H77: 0 | L77: =H77-F77 -> 0
B78: 6666020405 | C78: 6666020405 Company car expense - maintenance fees | D78: 公司车辆费用-维护费 | E78: 0 | F78: 0 | G78: 0 | H78: 0 | L78: =H78-F78 -> 0
B79: 6666020495 | C79: 6666020495 Non-deductible expense-travel. | D79: 不可扣除费用-旅行 | E79: 3.21211 | F79: 0.0067184899 | G79: 0 | H79: 0 | L79: =H79-F79 -> -0.0067184899
B80: 6666020504 | C80: 6666020504 Newspaper and Periodicals expenditure | D80: 报纸和期刊支出 | E80: 0.29938 | F80: 0.00062618699 | G80: 0.59403638 | H80: 0.0010513546 | L80: =H80-F80 -> 0.00042516761
B81: 6666020508 | C81: 6666020508 Postage | D81: 邮资 | E81: 0.04867 | F81: 0.00010179879 | G81: 4.865322 | H81: 0.0086108845 | L81: =H81-F81 -> 0.0085090857
B82: 6666020602 | C82: 6666020602 Training costs Outside the group | D82: 集团外培训费用 | E82: 4.70704 | F82: 0.0098453043 | G82: 22.162305 | H82: 0.03922393 | L82: =H82-F82 -> 0.029378626 | N82: 5千欧元的设备许可费加上2026年生产需求的10千欧元额外预算
B83: 6666020701 | C83: 6666020701 Enterprise Property Insurance | D83: 企业财产保险 | E83: 0 | F83: 0 | G83: 0 | H83: 0 | L83: =H83-F83 -> 0
B84: 6666020802 | C84: 6666020802 Equipment rental cost | D84: 设备租赁成本 | E84: 133.42406 | F84: 0.27907145 | G84: 156.396 | H84: 0.27679728 | L84: =H84-F84 -> -0.002274168
B85: 6666020803 | C85: 6666020803 Car rental cost | D85: 汽车租赁成本 | E85: 50.53832 | F85: 0.10570659 | G85: 43.217511 | H85: 0.076488462 | L85: =H85-F85 -> -0.029218127
B86: 6666021100 | C86: 6666021100 Consulting fees | D86: 咨询费 | E86: 72.90402 | F86: 0.15248697 | G86: 65.375779 | H86: 0.11570525 | L86: =H86-F86 -> -0.036781721
B87: 6666021104 | C87: 6666021104 Consulting expense-Technical | D87: 技术咨询费用 | E87: -0.03701 | F87: -7.7410584e-05 | G87: 0 | H87: 0 | L87: =H87-F87 -> 7.7410584e-05
B88: 6666021902 | C88: 6666021902 Cleaning fees | D88: 清洁费 | E88: 83.46437 | F88: 0.17457513 | G88: 90.463072 | H88: 0.16010596 | L88: =H88-F88 -> -0.014469167
B89: 6666022100 | C89: 6666022100 Security | D89: 保安 | E89: 13.81918 | F89: 0.028904371 | G89: 16.753287 | H89: 0.029650786 | L89: =H89-F89 -> 0.00074641454
B90: 6666022300 | C90: 6666022300 Association dues | D90: 会费 | E90: 0 | F90: 0 | G90: 0 | H90: 0 | L90: =H90-F90 -> 0
B91: 6666029700 | C91: 6666029700 Service fee recharge | D91: 服务费回收费 | E91: 0 | F91: 0 | G91: 0 | H91: 0 | L91: =H91-F91 -> 0
B92: 6666029900 | C92: 6666029900 Sundry Expenses | D92: 杂项费用 | E92: 0.07586 | F92: 0.00015866973 | G92: 0 | H92: 0 | L92: =H92-F92 -> -0.00015866973
B93: 6666029996 | C93: 6666029996 Non-deductible expense-travel. | D93: 不可扣除费用-旅行 | E93: 0.17373 | F93: 0.00036337586 | G93: 0 | H93: 0 | L93: =H93-F93 -> -0.00036337586
B94: 6666029997 | C94: 6666029997 restructure cost | D94: 重组成本 | E94: 14.93904 | F94: 0.031246685 | G94: 8.251956 | H94: 0.014604715 | L94: =H94-F94 -> -0.01664197
... B99: 6666070300 | C99: 6666070300 Software maintenance fees | D99: 软件维护费 | E99: 0 | F99: 0 | G99: 0 | H99: 0 | L99: =H99-F99 -> 0
B100: 6666070400 | C100: 6666070400 IT maint. & repairs hardware | D100: IT维护及硬件修理 | E100: 62.40957 | F100: 0.13053665 | G100: 145.01519 | H100: 0.25665496 | L100: =H100-F100 -> 0.12611831 | N100: 我有一个25预算与26预算的比较。请查看黄色表格。如果您需要更多细节，我需要与IT团队沟通。
B101: 5401050201 | C101: 5401050201 COGS-Special a | D101: 销售成本-特殊项目 | E101: 0.02369 | F101: 4.9550303e-05 | G101: 0 | H101: 0 | L101: =H101-F101 -> -4.9550303e-05
B102: 5401020212 | C102: 5401020212 Local Transpor | D102: 本地运输 | E102: -0.14776 | F102: -0.00030905668 | G102: 0 | H102: 0 | L102: =H102-F102 -> 0.00030905668
B103: 6666020801 | C103: 6666020801 - HOUSING RENTAL COST | D103: 6666020801 - 住房租赁成本 | F103: 0 | G103: 12.955488 | H103: 0.022929256 | L103: =H103-F103 -> 0.022929256
A104: 生产耗用 | B104: FIX | C104: * CS_Fix Cost | D104: * CS_固定成本 | E104: 470.02002 | F104: 0.98309981 | G104: 673.59401 | H104: 1.1921596 | L104: =H104-F104 -> 0.20905977
B105: 6666110203 | C105: 6666110203 Low value consumables | D105: 低值易耗品 | E105: 145.49291 | F105: 0.30431481 | G105: 185.03175 | H105: 0.32747823 | L105: =H105-F105 -> 0.023163422
...

Sheet 厨电成本数据
A1: 分类 | B1: 指标 | C1: / | D1: 1月份 | E1: 2月份 | F1: 3月份 | G1: 4月份 | H1: 5月份 | I1: 6月份 | J1: 7月份 | K1: 8月份 | L1: 9月份 | M1: 10月份 | N1: 11月份 | O1: 12月份 | P1: 年度
A2: 厨电定单量 | B2: 厨电定单量 | C2: 同期 | D2: 79712 | E2: 82105 | F2: 92657 | G2: 98687 | H2: 93353 | I2: 75092 | J2: 77799 | K2: 58812 | L2: 90826 | M2: 111572 | N2: 111625 | O2: 75554 | P2: 1047794
B3: 厨电定单量 | C3: 目标 | D3: 116704 | E3: 116204 | F3: 106704 | G3: 104704 | H3: 71805 | I3: 110105 | J3: 86206 | K3: 81605 | L3: 117305 | M3: 121005 | N3: 130155 | O3: 91305 | P3: 1253807
B4: 厨电定单量 | C4: 26年 | D4: 97611 | E4: 106294 | F4: =厨电3月!L28 -> 107376 | G4: ='26年厨电费用指标到月测算汇总表 '!G50 -> 110370 | H4: ='厨电5月 '!L27 -> 67531 | I4: 111312 | J4: 86967 | K4: 81560.001 | L4: 117158 | M4: 117404 | N4: 113634 | O4: 76893 | P4: =SUM(D4:O4) -> 1194110
A5: 厨电定单量（累计） | B5: 厨电定单量（累计） | C5: 同期 | D5: =D2 -> 79712 | E5: =D5+E2 -> 161817 | F5: =E5+F2 -> 254474 | G5: =F5+G2 -> 353161 | H5: =G5+H2 -> 446514 | I5: =H5+I2 -> 521606 | J5: =I5+J2 -> 599405 | K5: =J5+K2 -> 658217 | L5: =K5+L2 -> 749043 | ... O5: =N5+O2 -> 1047794 | P5: =O5 -> 1047794
B6: 厨电定单量（累计） | C6: 目标 | D6: =D3 -> 116704 | E6: =D6+E3 -> 232908 | F6: =E6+F3 -> 339612 | G6: =F6+G3 -> 444316 | H6: =G6+H3 -> 516121 | I6: =H6+I3 -> 626226 | J6: =I6+J3 -> 712432 | K6: =J6+K3 -> 794037 | L6: =K6+L3 -> 911342 | ... O6: =N6+O3 -> 1253807 | P6: =O6 -> 1253807
B7: 厨电定单量（累计） | C7: 26年 | D7: =D4 -> 97611 | E7: =D7+E4 -> 203905 | F7: =E7+F4 -> 311281 | G7: =F7+G4 -> 421651 | H7: =G7+H4 -> 489182 | I7: =H7+I4 -> 600494 | J7: =I7+J4 -> 687461 | K7: =J7+K4 -> 769021 | L7: =K7+L4 -> 886179 | ... O7: =N7+O4 -> 1194110 | P7: =O7 -> 1194110
A8: 厨电费用金额 | B8: 厨电费用金额 | C8: 同期 | D8: 2786.3724 | E8: 2692.3078 | F8: 2979.4464 | G8: 2556.6921 | H8: 2816.0883 | I8: 2742.9449 | J8: 2368.5937 | K8: 2153.779 | L8: 1237.7853 | M8: 2317.4637 | N8: 2618.4649 | O8: 1590.4388 | P8: 28860.377
B9: 厨电费用金额 | C9: 目标 | D9: 2628.6417 | E9: 2650.3787 | F9: 2640.9033 | G9: 2463.9881 | H9: 2562.0587 | I9: 2548.9769 | J9: 2516.4942 | K9: 2516.238 | L9: 2799.5329 | M9: 2751.3699 | N9: 2807.1181 | O9: 2894.1929 | P9: 31779.893
B10: 厨电费用金额 | C10: 26年 | D10: 2493.4106 | E10: 2350.455 | F10: =厨电3月!J238 -> 2592.0249 | G10: ='26年厨电费用指标到月测算汇总表 '!G39 -> 2091.3038 | H10: ='厨电5月 '!J245 -> 2105.3224 | I10: 2408.2532 | J10: 2322.2299 | K10: 2326.7122 | L10: 2612.4902 | M10: 2584.0024 | N10: 2628.5695 | O10: 2703.5436 | P10: =SUM(D10:O10) -> 29218.318
A11: 厨电费用金额（累计） | B11: 厨电费用金额（累计） | C11: 同期 | D11: =D8 -> 2786.3724 | E11: =D11+E8 -> 5478.6802 | F11: =E11+F8 -> 8458.1266 | G11: =F11+G8 -> 11014.819 | H11: =G11+H8 -> 13830.907 | I11: =H11+I8 -> 16573.852 | J11: =I11+J8 -> 18942.446 | K11: =J11+K8 -> 21096.225 | L11: =K11+L8 -> 22334.01 | ... O11: =N11+O8 -> 28860.377 | P11: =O11 -> 28860.377
B12: 厨电费用金额（累计） | C12: 目标 | D12: =D9 -> 2628.6417 | E12: =D12+E9 -> 5279.0204 | F12: =E12+F9 -> 7919.9237 | G12: =F12+G9 -> 10383.912 | H12: =G12+H9 -> 12945.97 | I12: =H12+I9 -> 15494.947 | J12: =I12+J9 -> 18011.442 | K12: =J12+K9 -> 20527.679 | L12: =K12+L9 -> 23327.212 | ... O12: =N12+O9 -> 31779.893 | P12: =O12 -> 31779.893
B13: 厨电费用金额（累计） | C13: 26年 | D13: =D10 -> 2493.4106 | E13: =D13+E10 -> 4843.8656 | F13: =E13+F10 -> 7435.8905 | G13: =F13+G10 -> 9527.1943 | H13: =G13+H10 -> 11632.517 | I13: =H13+I10 -> 14040.77 | J13: =I13+J10 -> 16363 | K13: =J13+K10 -> 18689.712 | L13: =K13+L10 -> 21302.202 | ... O13: =N13+O10 -> 29218.318 | P13: =O13 -> 29218.318
A14: 厨电单台 | B14: 厨电单台 | C14: 同期 | D14: 34.955495 | E14: 32.791034 | F14: 32.155654 | G14: 25.907081 | H14: 30.166018 | I14: 36.527791 | J14: 30.44504 | K14: 36.62142 | L14: 13.628094 | M14: 20.771015 | N14: 23.468835 | O14: 14.25482 | P14: 27.543942
B15: 厨电单台 | C15: 目标 | D15: 22.524007 | E15: 22.807982 | F15: 24.749806 | G15: 23.532894 | H15: 35.680784 | I15: 23.150419 | J15: 29.191636 | K15: 30.83436 | L15: 23.865418 | M15: 22.737655 | N15: 21.567501 | O15: 31.698077 | P15: 25.346719
B16: 厨电单台 | C16: 26年 | D16: 25.548148 | E16: 22.115933 | F16: =F10/F4*1000 -> 24.139704 | G16: =G10/G4*1000 -> 18.948118 | H16: =H10/H4*1000 -> 31.175643 | I16: =I10/I4*1000 -> 21.635163 | J16: =J10/J4*1000 -> 26.702427 | K16: =K10/K4*1000 -> 28.527613 | L16: =L10/L4*1000 -> 22.298863 | M16: =M10/M4*1000 -> 22.009492 | ... P16: =P10/P4*1000 -> 24.468699
B17: 厨电单台 | C17: 同期差额 | D17: =(D16-D14)*D4 -> -918260.59 | E17: =(E16-E14)*E4 -> -1134699.1 | F17: =(F16-F14)*F4 -> -860720.59 | G17: =(G16-G14)*G4 -> -768060.73 | H17: =(H16-H14)*H4 -> 68181.024 | I17: =(I16-I14)*I4 -> -1657728.2 | J17: =(J16-J14)*J4 -> -325483.89 | K17: =(K16-K14)*K4 -> -660130.93 | ... P17: =(P16-P14)*P4 -> -3672178.8
B18: 厨电单台 | C18: 当月单台目标完成率 | D18: =2-D16/D15 -> 0.86573699 | E18: =2-E16/E15 -> 1.0303424 | F18: =2-F16/F15 -> 1.0246508 | G18: =2-G16/G15 -> 1.1948241 | H18: =2-H16/H15 -> 1.1262624 | I18: =2-I16/I15 -> 1.0654526 | J18: =2-J16/J15 -> 1.0852713 | K18: =2-K16/K15 -> 1.0748109 | ... P18: =2-P16/P15 -> 1.0346404
B19: 厨电单台 | C19: 单台同期优化 | D19: =(D14-D16)/D14 -> 0.26912356 | E19: =(E14-E16)/E14 -> 0.32554938 | F19: =(F14-F16)/F14 -> 0.24928585 | G19: =(G14-G16)/G14 -> 0.26861238 | H19: =(H14-H16)/H14 -> -0.033468971 | I19: =(I14-I16)/I14 -> 0.40770678 | J19: =(J14-J16)/J14 -> 0.12293016 | K19: =(K14-K16)/K14 -> 0.22101293 | ... P19: =(P14-P16)/P14 -> 0.11164863
A20: 厨电单台（累计） | B20: 厨电单台（累计） | C20: 同期 | D20: =D11/D5*1000 -> 34.955495 | E20: =E11/E5*1000 -> 33.85726 | F20: =F11/F5*1000 -> 33.237685 | G20: =G11/G5*1000 -> 31.189227 | H20: =H11/H5*1000 -> 30.975304 | I20: =I11/I5*1000 -> 31.774657 | J20: =J11/J5*1000 -> 31.602081 | K20: =K11/K5*1000 -> 32.050562 | ... P20: =P11/P5*1000 -> 27.543942
B21: 厨电单台（累计） | C21: 目标 | D21: =D12/D6*1000 -> 22.524007 | E21: =E12/E6*1000 -> 22.665689 | F21: =F12/F6*1000 -> 23.320506 | G21: =G12/G6*1000 -> 23.370556 | H21: =H12/H6*1000 -> 25.083208 | I21: =I12/I6*1000 -> 24.743379 | J21: =J12/J6*1000 -> 25.281629 | K21: =K12/K6*1000 -> 25.852296 | ... P21: =P12/P6*1000 -> 25.346719
B22: 厨电单台（累计） | C22: 26年 | D22: =D13/D7*1000 -> 25.544361 | E22: =E13/E7*1000 -> 23.755502 | F22: =F13/F7*1000 -> 23.888032 | G22: =G13/G7*1000 -> 22.594976 | H22: =H13/H7*1000 -> 23.779527 | I22: =I13/I7*1000 -> 23.382032 | J22: =J13/J7*1000 -> 23.802077 | K22: =K13/K7*1000 -> 24.303253 | ... P22: =P13/P7*1000 -> 24.468699
B23: 厨电单台（累计） | C23: 同期差额 | D23: =(D22-D20)*D7 -> -918630.23 | E23: =(E22-E20)*E7 -> -2059799 | F23: =(F22-F20)*F7 -> -2910369.3 | G23: =(G22-G20)*G7 -> -3623774.6 | H23: =(H22-H20)*H7 -> -3520044.6 | I23: =(I22-I20)*I7 -> -5039721.1 | J23: =(J22-J20)*J7 -> -5362198.6 | K23: =(K22-K20)*K7 -> -5957843 | ... P23: =(P22-P20)*P7 -> -3672178.8
B24: 厨电单台（累计） | C24: 当月单台目标完成率 | D24: =2-D22/D21 -> 0.86590512 | E24: =2-E22/E21 -> 0.95191797 | F24: =2-F22/F21 -> 0.97566408 | G24: =2-G22/G21 -> 1.0331862 | H24: =2-H22/H21 -> 1.0519743 | I24: =2-I22/I21 -> 1.0550186 | J24: =2-J22/J21 -> 1.0585228 | K24: =2-K22/K21 -> 1.059919 | ... P24: =2-P22/P21 -> 1.0346404
B25: 厨电单台（累计） | C25: 累计单台同期优化 | D25: =(D20-D22)/D20 -> 0.2692319 | E25: =(E20-E22)/E20 -> 0.29836313 | F25: =(F20-F22)/F20 -> 0.28129676 | G25: =(G20-G22)/G20 -> 0.27555191 | H25: =(H20-H22)/H20 -> 0.23230691 | I25: =(I20-I22)/I20 -> 0.26412953 | J25: =(J20-J22)/J20 -> 0.24681931 | K25: =(K20-K22)/K20 -> 0.24172146 | ... P25: =(P20-P22)/P20 -> 0.11164863
A26: 厨电折旧费用 | B26: 厨电折旧费用 | C26: 同期 | D26: 770 | E26: 741 | F26: 764 | G26: 766 | H26: 832 | I26: 824 | J26: 839 | K26: 583 | L26: 793 | M26: 590 | N26: 801 | O26: 816 | P26: =SUM(D26:O26) -> 9119
B27: 厨电折旧费用 | C27: 目标 | D27: 816 | E27: 780 | F27: 827 | G27: 816 | H27: 828 | I27: 822 | J27: 884 | K27: 894 | L27: 882 | M27: 898 | N27: 886 | O27: 897 | P27: =SUM(D27:O27) -> 10230
B28: 厨电折旧费用 | C28: 26年 | D28: 818 | E28: =363+250 -> 613 | F28: =厨电3月!J39 -> 798.62406 | G28: =厨电4月!I37 -> 466.69395 | H28: ='厨电5月 '!J38 -> 254.33901 | I28: 597.36367 | J28: 657.3779 | K28: 667.43613 | L28: 659.22372 | M28: 671.7118 | N28: 662.56808 | O28: 669.68611 | P28: =SUM(D28:O28) -> 7536.0244
A29: 厨电折旧费用累计 | B29: 厨电折旧费用累计 | C29: 同期 | D29: =D26 -> 770 | E29: =D29+E26 -> 1511 | F29: =E29+F26 -> 2275 | G29: =F29+G26 -> 3041 | H29: =G29+H26 -> 3873 | I29: =H29+I26 -> 4697 | J29: =I29+J26 -> 5536 | K29: =J29+K26 -> 6119 | L29: =K29+L26 -> 6912 | ... O29: =N29+O26 -> 9119 | P29: =O29 -> 9119
B30: 厨电折旧费用累计 | C30: 目标 | D30: =D27 -> 816 | E30: =D30+E27 -> 1596 | F30: =E30+F27 -> 2423 | G30: =F30+G27 -> 3239 | H30: =G30+H27 -> 4067 | I30: =H30+I27 -> 4889 | J30: =I30+J27 -> 5773 | K30: =J30+K27 -> 6667 | L30: =K30+L27 -> 7549 | ... O30: =N30+O27 -> 10230 | P30: =O30 -> 10230
B31: 厨电折旧费用累计 | C31: 26年 | D31: =D28 -> 818 | E31: =D31+E28 -> 1431 | F31: =E31+F28 -> 2229.6241 | G31: =F31+G28 -> 2696.318 | H31: =G31+H28 -> 2950.657 | I31: =H31+I28 -> 3548.0207 | J31: =I31+J28 -> 4205.3986 | K31: =J31+K28 -> 4872.8347 | L31: =K31+L28 -> 5532.0584 | ... O31: =N31+O28 -> 7536.0244 | P31: =O31 -> 7536.0244
A32: 厨电折旧单台 | B32: 厨电折旧单台 | C32: 同期 | D32: =D26/D2*1000 -> 9.6597752 | E32: =E26/E2*1000 -> 9.0250289 | F32: =F26/F2*1000 -> 8.2454645 | G32: =G26/G2*1000 -> 7.7619139 | H32: =H26/H2*1000 -> 8.9124077 | I32: =I26/I2*1000 -> 10.973206 | J32: =J26/J2*1000 -> 10.7842 | K32: =K26/K2*1000 -> 9.9129429 | ... O32: =O26/O2*1000 -> 10.800222 | P32: =P29/P2*1000 -> 8.7030466
B33: 厨电折旧单台 | C33: 目标 | D33: =D27/D3*1000 -> 6.9920483 | E33: =E27/E3*1000 -> 6.7123335 | F33: =F27/F3*1000 -> 7.7504124 | G33: =G27/G3*1000 -> 7.7933985 | H33: =H27/H3*1000 -> 11.53123 | I33: =I27/I3*1000 -> 7.465601 | J33: =J27/J3*1000 -> 10.254507 | K33: =K27/K3*1000 -> 10.955211 | ... O33: =O27/O3*1000 -> 9.8242155 | P33: =P30/P3*1000 -> 8.1591505
B34: 厨电折旧单台 | C34: 26年 | D34: =D28/D4*1000 -> 8.3802031 | E34: =E28/E4*1000 -> 5.7670235 | F34: =F28/F4*1000 -> 7.4376403 | G34: =G28/G4*1000 -> 4.2284493 | H34: =H28/H4*1000 -> 3.7662556 | I34: =I28/I4*1000 -> 5.3665703 | J34: =J28/J4*1000 -> 7.558935 | K34: =K28/K4*1000 -> 8.1833757 | ... O34: =O28/O4*1000 -> 8.7093248 | P34: =P31/P4*1000 -> 6.3109968
B35: 厨电折旧单台 | C35: 同期差额 | D35: =(D34-D32)*D4 -> -124900.32 | E35: =(E34-E32)*E4 -> -346306.42 | F35: =(F34-F32)*F4 -> -86740.931 | G35: =(G34-G32)*G4 -> -389988.49 | H35: =(H34-H32)*H4 -> -347524.8 | I35: =(I34-I32)*I4 -> -624085.86 | J35: =(J34-J32)*J4 -> -280491.65 | K35: =(K34-K32)*K4 -> -141063.5 | ... P35: =(P34-P32)*P4 -> -2856370.5
A36: 厨电变动费用 | B36: 厨电变动费用 | C36: 同期 | D36: =D8-D26 -> 2016.3724 | E36: =E8-E26 -> 1951.3078 | F36: =F8-F26 -> 2215.4464 | G36: =G8-G26 -> 1790.6921 | H36: =H8-H26 -> 1984.0883 | I36: =I8-I26 -> 1918.9449 | J36: =J8-J26 -> 1529.5937 | K36: =K8-K26 -> 1570.779 | ... P36: =P8-P26 -> 19741.377
B37: 厨电变动费用 | C37: 目标 | D37: =D9-D27 -> 1812.6417 | E37: =E9-E27 -> 1870.3787 | F37: =F9-F27 -> 1813.9033 | G37: =G9-G27 -> 1647.9881 | H37: =H9-H27 -> 1734.0587 | I37: =I9-I27 -> 1726.9769 | J37: =J9-J27 -> 1632.4942 | K37: =K9-K27 -> 1622.238 | ... P37: =P9-P27 -> 21549.893
B38: 厨电变动费用 | C38: 26年 | D38: =D10-D28 -> 1675.4106 | E38: =E10-E28 -> 1737.455 | F38: =F10-F28 -> 1793.4008 | G38: =G10-G28 -> 1624.6099 | H38: =H10-H28 -> 1850.9834 | I38: =I10-I28 -> 1810.8896 | J38: =J10-J28 -> 1664.852 | K38: =K10-K28 -> 1659.276 | ... P38: =P10-P28 -> 21682.293
A39: 厨电变动费用累计 | B39: 厨电变动费用累计 | C39: 同期 | D39: =D36 -> 2016.3724 | E39: =D39+E36 -> 3967.6802 | F39: =E39+F36 -> 6183.1266 | G39: =F39+G36 -> 7973.8188 | H39: =G39+H36 -> 9957.907 | I39: =H39+I36 -> 11876.852 | J39: =I39+J36 -> 13406.446 | K39: =J39+K36 -> 14977.225 | L39: =K39+L36 -> 15422.01 | ... O39: =N39+O36 -> 19741.377 | P39: =O39 -> 19741.377
B40: 厨电变动费用累计 | C40: 目标 | D40: =D37 -> 1812.6417 | E40: =D40+E37 -> 3683.0204 | F40: =E40+F37 -> 5496.9237 | G40: =F40+G37 -> 7144.9118 | H40: =G40+H37 -> 8878.9705 | I40: =H40+I37 -> 10605.947 | J40: =I40+J37 -> 12238.442 | K40: =J40+K37 -> 13860.679 | L40: =K40+L37 -> 15778.212 | ... O40: =N40+O37 -> 21549.893 | P40: =O40 -> 21549.893
B41: 厨电变动费用累计 | C41: 26年 | D41: =D38 -> 1675.4106 | E41: =D41+E38 -> 3412.8656 | F41: =E41+F38 -> 5206.2664 | G41: =F41+G38 -> 6830.8763 | H41: =G41+H38 -> 8681.8597 | I41: =H41+I38 -> 10492.749 | J41: =I41+J38 -> 12157.601 | K41: =J41+K38 -> 13816.877 | L41: =K41+L38 -> 15770.144 | ... O41: =N41+O38 -> 21682.293 | P41: =O41 -> 21682.293
A42: 厨电变动单台 | B42: 厨电变动单台 | C42: 同期 | D42: =D36/D2*1000 -> 25.29572 | E42: =E36/E2*1000 -> 23.766005 | F42: =F36/F2*1000 -> 23.910189 | G42: =G36/G2*1000 -> 18.145167 | H42: =H36/H2*1000 -> 21.25361 | I42: =I36/I2*1000 -> 25.554585 | J42: =J36/J2*1000 -> 19.66084 | K42: =K36/K2*1000 -> 26.708478 | ... P42: =P36/P2*1000 -> 18.840895
B43: 厨电变动单台 | C43: 目标 | D43: =D37/D3*1000 -> 15.531959 | E43: =E37/E3*1000 -> 16.095648 | F43: =F37/F3*1000 -> 16.999393 | G43: =G37/G3*1000 -> 15.739495 | H43: =H37/H3*1000 -> 24.149553 | I43: =I37/I3*1000 -> 15.684818 | J43: =J37/J3*1000 -> 18.937129 | K43: =K37/K3*1000 -> 19.879149 | ... P43: =P37/P3*1000 -> 17.187568
B44: 厨电变动单台 | C44: 26年 | D44: =D38/D4*1000 -> 17.164158 | E44: =E38/E4*1000 -> 16.345748 | F44: =F38/F4*1000 -> 16.702064 | G44: =G38/G4*1000 -> 14.719669 | H44: =H38/H4*1000 -> 27.409388 | I44: =I38/I4*1000 -> 16.268593 | J44: =J38/J4*1000 -> 19.143492 | K44: =K38/K4*1000 -> 20.344237 | ... P44: =P38/P4*1000 -> 18.157702
B45: 厨电变动单台 | C45: 同期差额 | D45: =D44-D42 -> -8.1315621 | E45: =E44-E42 -> -7.4202561 | F45: =F44-F42 -> -7.2081252 | G45: =G44-G42 -> -3.4254982 | H45: =H44-H42 -> 6.1557777 | I45: =I44-I42 -> -9.2859919 | J45: =J44-J42 -> -0.51734838 | K45: =K44-K42 -> -6.3642401 | ... P45: =P44-P42 -> -0.68319358
A46: 厨电变动单台（累计） | B46: 厨电变动单台（累计） | C46: 同期 | D46: =D39/D5*1000 -> 25.29572 | E46: =E39/E5*1000 -> 24.519551 | F46: =F39/F5*1000 -> 24.297675 | G46: =G39/G5*1000 -> 22.578424 | H46: =H39/H5*1000 -> 22.301444 | I46: =I39/I5*1000 -> 22.769776 | J46: =J39/J5*1000 -> 22.366256 | K46: =K39/K5*1000 -> 22.754235 | ... P46: =P39/P5*1000 -> 18.840895
B47: 厨电变动单台（累计） | C47: 目标 | D47: =D40/D6*1000 -> 15.531959 | E47: =E40/E6*1000 -> 15.813198 | F47: =F40/F6*1000 -> 16.185894 | G47: =G40/G6*1000 -> 16.080699 | H47: =H40/H6*1000 -> 17.203273 | I47: =I40/I6*1000 -> 16.936294 | J47: =J40/J6*1000 -> 17.1784 | K47: =K40/K6*1000 -> 17.455962 | ... P47: =P40/P6*1000 -> 17.187568
B48: 厨电变动单台（累计） | C48: 26年 | D48: =D41/D7*1000 -> 17.164158 | E48: =E41/E7*1000 -> 16.737528 | F48: =F41/F7*1000 -> 16.725295 | G48: =G41/G7*1000 -> 16.200309 | H48: =H41/H7*1000 -> 17.747709 | I48: =I41/I7*1000 -> 17.473529 | J48: =J41/J7*1000 -> 17.684787 | K48: =K41/K7*1000 -> 17.96684 | ... P48: =P41/P7*1000 -> 18.157702
B49: 厨电变动单台（累计） | C49: 同期差额 | D49: =D48-D46 -> -8.1315621 | E49: =E48-E46 -> -7.7820236 | F49: =F48-F46 -> -7.5723808 | G49: =G48-G46 -> -6.3781154 | H49: =H48-H46 -> -4.5537354 | I49: =I48-I46 -> -5.2962474 | J49: =J48-J46 -> -4.681469 | K49: =K48-K46 -> -4.7873954 | ... P49: =P48-P46 -> -0.68319358
B50: 厨电变动单台（累计） | C50: 当月单台目标完成率 | D50: =2-D48/D47 -> 0.89491349 | E50: =2-E48/E47 -> 0.94154697 | F50: =2-F48/F47 -> 0.96667462 | G50: =2-G48/G47 -> 0.99256191 | H50: =2-H48/H47 -> 0.96835278 | I50: =2-I48/I47 -> 0.96827905 | J50: =2-J48/J47 -> 0.97052185 | K50: =2-K48/K47 -> 0.97073331 | ... P50: =2-P48/P47 -> 0.94355608
B51: 厨电变动单台（累计） | C51: 累计单台同期优化 | D51: =(D46-D48)/D46 -> 0.32146 | E51: =(E46-E48)/E46 -> 0.31738034 | F51: =(F46-F48)/F46 -> 0.31165042 | G51: =(G46-G48)/G46 -> 0.28248718 | H51: =(H46-H48)/H46 -> 0.20419016 | I51: =(I46-I48)/I46 -> 0.23259989 | J51: =(J46-J48)/J46 -> 0.20930946 | K51: =(K46-K48)/K46 -> 0.21039579 | ... P51: =(P46-P48)/P46 -> 0.036261206
A52: 厨电制造费率 | B52: 厨电收入 | C52: 同期 | D52: 10544378 | E52: 10387950 | F52: 11538095 | G52: 12383605 | H52: 11202173 | I52: 8802515.5 | J52: 8308933.2 | K52: 7184333.1 | L52: 10320823 | M52: 13320749 | N52: 13370725 | O52: 9406887.7 | P52: 1.2680934e+08
B53: 厨电收入 | C53: 目标 | D53: 14121184 | E53: 14060684 | F53: 12911184 | G53: 12669184 | H53: 8688405 | I53: 13322705 | J53: 10430926 | K53: 9874205 | L53: 14193905 | M53: 14641605 | N53: 15748755 | O53: 11047905 | P53: 151710647
B54: 厨电收入 | C54: 26年 | D54: 12201375 | E54: 12330104 | F54: =117*F4 -> 12562992 | G54: 12754771
B55: 厨电收入（累计） | C55: 同期 | D55: =D52 -> 10544378 | E55: =D55+E52 -> 20932327 | F55: =E55+F52 -> 32470423 | G55: =F55+G52 -> 44854028 | H55: =G55+H52 -> 56056201 | I55: =H55+I52 -> 64858717 | J55: =I55+J52 -> 73167650 | K55: =J55+K52 -> 80351983 | L55: =K55+L52 -> 90672806 | ... O55: =N55+O52 -> 1.2677117e+08 | P55: =O55 -> 1.2677117e+08
B56: 厨电收入（累计） | C56: 目标 | D56: =D53 -> 14121184 | E56: =D56+E53 -> 28181868 | F56: =E56+F53 -> 41093052 | G56: =F56+G53 -> 53762236 | H56: =G56+H53 -> 62450641 | I56: =H56+I53 -> 75773346 | J56: =I56+J53 -> 86204272 | K56: =J56+K53 -> 96078477 | L56: =K56+L53 -> 110272382 | ... O56: =N56+O53 -> 151710647 | P56: =O56 -> 151710647
B57: 厨电收入（累计） | C57: 26年 | D57: =D54 -> 12201375 | E57: =D57+E54 -> 24531479 | F57: =E57+F54 -> 37094471 | G57: =F57+G54 -> 49849242 | H57: =G57+H54 -> 49849242
B58: 厨电制造费率 | C58: 同期 | D58: =D8/D52*1000 -> 0.26425195 | E58: =E8/E52*1000 -> 0.25917606 | F58: =F8/F52*1000 -> 0.25822688 | G58: =G8/G52*1000 -> 0.20645782 | H58: =H8/H52*1000 -> 0.25138768 | I58: =I8/I52*1000 -> 0.3116092 | J58: =J8/J52*1000 -> 0.28506592 | K58: =K8/K52*1000 -> 0.2997883 | ... P58: =P8/P52*1000 -> 0.22758873
B59: 厨电制造费率 | C59: 目标 | D59: =D9/D53*1000 -> 0.18614882 | E59: =E9/E53*1000 -> 0.18849572 | F59: =F9/F53*1000 -> 0.20454385 | G59: =G9/G53*1000 -> 0.19448673 | H59: =H9/H53*1000 -> 0.29488251 | I59: =I9/I53*1000 -> 0.19132578 | J59: =J9/J53*1000 -> 0.24125319 | K59: =K9/K53*1000 -> 0.25482942 | ... P59: =P9/P53*1000 -> 0.20947701
B60: 厨电制造费率 | C60: 26年 | D60: =D10/D54*1000 -> 0.20435489 | E60: =E10/E54*1000 -> 0.19062735 | F60: =F10/F54*1000 -> 0.20632226 | G60: =G10/G54*1000 -> 0.16396248
B61: 厨电制造费率（累计） | C61: 同期 | D61: =D11/D55*1000 -> 0.26425195 | E61: =E11/E55*1000 -> 0.26173297 | F61: =F11/F55*1000 -> 0.26048711 | G61: =G11/G55*1000 -> 0.24557034 | H61: =H11/H55*1000 -> 0.24673286 | I61: =I11/I55*1000 -> 0.25553777 | J61: =J11/J55*1000 -> 0.25889099 | K61: =K11/K55*1000 -> 0.26254765 | ... P61: =P11/P55*1000 -> 0.22765727
B62: 厨电制造费率（累计） | C62: 目标 | D62: =D12/D56*1000 -> 0.18614882 | E62: =E12/E56*1000 -> 0.18731975 | F62: =F12/F56*1000 -> 0.19273145 | G62: =G12/G56*1000 -> 0.19314509 | H62: =H12/H56*1000 -> 0.20729924 | I62: =I12/I56*1000 -> 0.20449074 | J62: =J12/J56*1000 -> 0.20893908 | K62: =K12/K56*1000 -> 0.21365534 | ... P62: =P12/P56*1000 -> 0.20947701
B63: 厨电制造费率（累计） | C63: 26年 | D63: =D13/D57*1000 -> 0.20435489 | E63: =E13/E57*1000 -> 0.1974551 | F63: =F13/F57*1000 -> 0.20045819 | G63: =G13/G57*1000 -> 0.19112014 | H63: =H13/H57*1000 -> 0.23335393
A64: 洗碗机定单量 | B64: 洗碗机定单量 | C64: 同期 | D64: 48570 | E64: 46039 | F64: 46330 | G64: 49360 | H64: 53704 | I64: 29664 | J64: 41857 | K64: 31977 | L64: 28268 | M64: 26211 | N64: 34024 | O64: 42093 | P64: 478097
B65: 洗碗机定单量 | C65: 目标 | D65: 50463 | E65: 50450 | F65: 50440 | G65: 48050 | H65: 36788 | I65: 53265 | J65: 42049 | K65: 39150 | L65: 53732 | M65: 48548 | N65: 51408 | O65: 40676 | P65: 565019
B66: 洗碗机定单量 | C66: 26年 | D66: 47360 | E66: 42593 | F66: 23002 | G66: 40893 | H66: 36000 | I66: 54500.001 | J66: 41500 | K66: 39000.001 | L66: 54085 | M66: 49968 | N66: 51936 | O66: 42190 | P66: 523027
A67: 洗碗机定单量（累计） | B67: 洗碗机定单量（累计） | C67: 同期 | D67: 48570 | E67: 94609 | F67: 140939 | G67: 190299 | H67: 244003 | I67: 273667 | J67: 315524 | K67: 347501 | L67: 375769 | M67: 401980 | N67: 436004 | O67: 478097 | P67: 478097
B68: 洗碗机定单量（累计） | C68: 目标 | D68: 50463 | E68: 100913 | F68: 151353 | G68: 199403 | H68: 236191 | I68: 289456 | J68: 331505 | K68: 370655 | L68: 424387 | M68: 472935 | N68: 524343 | O68: 565019 | P68: 565019
B69: 洗碗机定单量（累计） | C69: 26年 | D69: 47360 | E69: 89953 | F69: 112955 | G69: 153848 | H69: 189848 | I69: 244348 | J69: 285848 | K69: 324848 | L69: 378933 | M69: 428901 | N69: 480837 | O69: 523027 | P69: 523027
A70: 洗碗机费用金额 | B70: 洗碗机费用金额 | C70: 同期 | D70: 1702.4888 | E70: 1623.6996 | F70: 1825.8462 | G70: 1591.5968 | H70: 1866.987 | I70: 1737.9 | J70: 1637.4123 | K70: 1533.5455 | L70: 1597.8553 | M70: 1443.0898 | N70: 1758.5061 | O70: 1502.3028 | P70: 19821.23
B71: 洗碗机费用金额 | C71: 目标 | D71: 1838.2556 | E71: 1852.3924 | F71: 1892.6678 | G71: 1849.6673 | H71: 1928.8688 | I71: 1870.4326 | J71: 1859.2351 | K71: 1842.1673 | L71: 1948.6868 | M71: 1894.9246 | N71: 1861.9628 | O71: 1947.1505 | P71: 22586.412
B72: 洗碗机费用金额 | C72: 26年 | D72: 1778.218 | E72: 1749.5522 | F72: 1713 | G72: 900.77836 | H72: 1693.9655 | I72: 1693.2497 | J72: 1663.9548 | K72: 1652.6359 | L72: 1816.2017 | M72: 1764.1942 | N72: 1739.899 | O72: 1797.8953 | P72: 19963.545
A73: 洗碗机费用金额（累计） | B73: 洗碗机费用金额（累计） | C73: 同期 | D73: 1702.4888 | E73: 3326.1883 | F73: 5152.0345 | G73: 6743.6313 | H73: 8610.6183 | I73: 10348.518 | J73: 11985.931 | K73: 13519.476 | L73: 15117.331 | M73: 16560.421 | N73: 18318.927 | O73: 19821.23 | P73: 19821.23
B74: 洗碗机费用金额（累计） | C74: 目标 | D74: 1838.2556 | E74: 3690.648 | F74: 5583.3158 | G74: 7432.9831 | H74: 9361.8519 | I74: 11232.284 | J74: 13091.52 | K74: 14933.687 | L74: 16882.374 | M74: 18777.298 | N74: 20639.261 | O74: 22586.412 | P74: 22586.412
B75: 洗碗机费用金额（累计） | C75: 26年 | D75: 1778.218 | E75: 3527.7702 | F75: 5240.7702 | G75: 6141.5486 | H75: 7835.5141 | I75: 9528.7637 | J75: 11192.719 | K75: 12845.354 | L75: 14661.556 | M75: 16425.75 | N75: 18165.649 | O75: 19963.545 | P75: 19963.545
A76: 洗碗机单台 | B76: 洗碗机单台 | C76: 同期 | D76: 35.046041 | E76: 35.45 | F76: 39.407954 | G76: 32.242707 | H76: 34.764394 | I76: 58.586165 | J76: 39.119199 | K76: 47.957767 | L76: 56.525234 | M76: 55.056648 | N76: 51.684284 | O76: 35.690087 | P76: 41.458596
B77: 洗碗机单台 | C77: 目标 | D77: 36.427791 | E77: 36.72 | F77: 37.525254 | G77: 38.494637 | H77: 52.432012 | I77: 35.115602 | J77: 44.215917 | K77: 47.054083 | L77: 36.266783 | M77: 39.031981 | N77: 36.219319 | O77: 47.869763 | P77: 39.974605
B78: 洗碗机单台 | C78: 26年 | D78: 37.546833 | E78: 41.11 | F78: 74.476709 | G78: 22.053802 | H78: 47.054596 | I78: 31.068801 | J78: 40.095297 | K78: 42.375277 | L78: 33.580508 | M78: 35.306481 | N78: 33.500829 | O78: 42.614252 | P78: 38.169243
B79: 洗碗机单台 | C79: 当月单台目标完成率 | D79: 0.96928055 | E79: 0.88044662 | F79: 0.015291021 | G79: 1.4270942 | H79: 1.1025598 | I79: 1.1152423 | J79: 1.0931931 | K79: 1.0994346 | L79: 1.0740699 | M79: 1.0954474 | N79: 1.0750564 | O79: 1.1097877 | P79: 1.0451627
B80: 洗碗机单台 | C80: 单台同期优化 | D80: -0.071357321 | E80: -0.1596615 | F80: -0.88989028 | G80: 0.3160065 | H80: -0.35352846 | I80: 0.46969049 | J80: -0.024951897 | K80: 0.1164043 | L80: 0.40592006 | M80: 0.35872447 | N80: 0.35181788 | O80: -0.19400807 | P80: 0.079340665
B81: 洗碗机制造费差额 | C81: 差额 | D81: 118437.49 | E81: 241076.38 | F81: 806651.51 | G81: -416654.9 | H81: 442447.29 | I81: -1499696.4 | J81: 40508.076 | K81: -217717.12 | L81: -1240965.5 | M81: -986876.35 | N81: -944375.93 | O81: 292130.52 | P81: -1720420.2
A82: 洗碗机单台（累计） | B82: 洗碗机单台（累计） | C82: 同期 | D82: 35.052271 | E82: 35.157209 | F82: 36.555067 | G82: 35.43703 | H82: 35.288985 | I82: 37.814272 | J82: 37.987382 | K82: 38.904855 | L82: 40.230385 | M82: 41.197127 | N82: 42.015503 | O82: 41.458596 | P82: 41.458596
B83: 洗碗机单台（累计） | C83: 目标 | D83: 36.427791 | E83: 36.572572 | F83: 36.889363 | G83: 37.276185 | H83: 39.636785 | I83: 38.804808 | J83: 39.491168 | K83: 40.289992 | L83: 39.78061 | M83: 39.703761 | N83: 39.362137 | O83: 39.974605 | P83: 39.974605
B84: 洗碗机单台（累计） | C84: 26年 | D84: 37.546833 | E84: 39.217927 | F84: 46.396974 | G84: 39.919587 | H84: 41.272566 | I84: 38.996692 | J84: 39.15619 | K84: 39.542661 | L84: 38.691685 | M84: 38.2973 | N84: 37.779225 | O84: 38.169243 | P84: 38.169243
B85: 洗碗机单台（累计） | C85: 当月单台目标完成率 | D85: 0.96928055 | E85: 0.92766833 | F85: 0.74226687 | G85: 0.92908604 | H85: 0.95873075 | I85: 0.99505515 | J85: 1.0084824 | K85: 1.0185488 | L85: 1.0273733 | M85: 1.0354239 | N85: 1.0402141 | O85: 1.0451627 | P85: 1.0451627
B86: 洗碗机单台（累计） | C86: 累计单台同期优化 | D86: -0.071166926 | E86: -0.11550174 | F86: -0.26923512 | G86: -0.1264936 | H86: -0.16955944 | I86: -0.031269154 | J86: -0.030768325 | K86: -0.016393986 | L86: 0.038247217 | M86: 0.070389063 | N86: 0.10082654 | O86: 0.079340665 | P86: 0.079340665
B87: 洗碗机制造费累计差额 | C87: 累计差额 | D87: 118142.47 | E87: 365273.85 | F87: 1111692.7 | G87: 689632.47 | H87: 1135970.8 | I87: 288922.03 | J87: 334101.46 | K87: 207189.9 | L87: -583064.3 | M87: -1243738.8 | N87: -2036959 | O87: -1720420.2 | P87: -1720420.2
A88: 洗碗机折旧费用 | B88: 洗碗机折旧费用 | C88: 同期 | D88: 547 | E88: 512 | F88: 562 | G88: 551 | H88: 580 | I88: 564 | J88: 579 | K88: 577 | L88: 565 | M88: 370 | N88: 546 | O88: 562 | P88: 6515
B89: 洗碗机折旧费用 | C89: 目标 | D89: 577 | E89: 536 | F89: 582 | G89: 568 | H89: 580 | I89: 569 | J89: 599 | K89: 600 | L89: 586 | M89: 601 | N89: 591 | O89: 614 | P89: 7003
B90: 洗碗机折旧费用 | C90: 26年 | D90: 564 | E90: 557 | F90: 565 | G90: 29.8973 | H90: 458.60897 | I90: 452.18701 | J90: 479.85896 | K90: 480.14766 | L90: 469.5718 | M90: 475.19367 | N90: 475.19367 | O90: 494.2163 | P90: 5500.8753
A91: 洗碗机折旧费用累计 | B91: 洗碗机折旧费用累计 | C91: 同期 | D91: 547 | E91: 1059 | F91: 1621 | G91: 2172 | H91: 2752 | I91: 3316 | J91: 3895 | K91: 4472 | L91: 5037 | M91: 5407 | N91: 5953 | O91: 6515 | P91: 6515
B92: 洗碗机折旧费用累计 | C92: 目标 | D92: 577 | E92: 1113 | F92: 1695 | G92: 2263 | H92: 2843 | I92: 3412 | J92: 4011 | K92: 4611 | L92: 5197 | M92: 5798 | N92: 6389 | O92: 7003 | P92: 7003
B93: 洗碗机折旧费用累计 | C93: 26年 | D93: 564 | E93: 1121 | F93: 1686 | G93: 1715.8973 | H93: 2174.5063 | I93: 2626.6933 | J93: 3106.5522 | K93: 3586.6999 | L93: 4056.2717 | M93: 4531.4654 | N93: 5006.659 | O93: 5500.8753 | P93: 5500.8753
A94: 洗碗机折旧单台 | B94: 洗碗机折旧单台 | C94: 同期 | D94: 11.262096 | E94: 11.121006 | F94: 12.130369 | G94: 11.162885 | H94: 10.79994 | I94: 19.012945 | J94: 13.832812 | K94: 18.044219 | L94: 19.987265 | M94: 14.116211 | N94: 16.047496 | O94: 13.351389 | P94: 13.626942
B95: 洗碗机折旧单台 | C95: 目标 | D95: 11.43412 | E95: 10.624381 | F95: 11.538462 | G95: 11.82102 | H95: 15.766011 | I95: 10.682437 | J95: 14.245285 | K95: 15.32567 | L95: 10.905978 | M95: 12.379501 | N95: 11.496265 | O95: 15.094896 | P95: 12.394273
B96: 洗碗机折旧单台 | C96: 26年 | D96: 11.908784 | E96: 13.077266 | F96: 24.563081 | G96: 0.73111046 | H96: 12.739138 | I96: 8.2970092 | J96: 11.562866 | K96: 12.311478 | L96: 8.6821078 | M96: 9.5099597 | N96: 9.1496008 | O96: 11.714063 | P96: 10.517383
B97: 洗碗机折旧差额 | C97: 差额 | D97: 8147.0616 | E97: -21152.771 | F97: -13615.058 | G97: 26913.108 | H97: 178778.53 | I97: -454012.7 | J97: 17117.652 | K97: -106023.41 | L97: -491161.4 | M97: -86779.928 | N97: -236372.72 | O97: 73558.588 | P97: -644718.83
A98: 洗碗机折旧单台（累计） | B98: 洗碗机折旧单台累计 | C98: 同期 | D98: 11.262096 | E98: 11.193438 | F98: 11.50143 | G98: 11.413618 | H98: 11.27855 | I98: 12.116916 | J98: 12.344544 | K98: 12.869028 | L98: 13.404512 | M98: 13.450918 | N98: 13.653544 | O98: 13.626942 | P98: 13.626942
B99: 洗碗机折旧单台累计 | C99: 目标 | D99: 11.43412 | E99: 11.029302 | F99: 11.198985 | G99: 11.348876 | H99: 12.036868 | I99: 11.787629 | J99: 12.099365 | K99: 12.44014 | L99: 12.245898 | M99: 12.259613 | N99: 12.184772 | O99: 12.394273 | P99: 12.394273
B100: 洗碗机折旧单台累计 | C100: 26年 | D100: 11.908784 | E100: 12.462064 | F100: 14.926298 | G100: 11.153199 | H100: 11.453933 | I100: 10.749805 | J100: 10.867847 | K100: 11.041163 | L100: 10.704456 | M100: 10.565294 | N100: 10.412383 | O100: 10.517383 | P100: 10.517383
...

Sheet 26年厨电费用指标到月测算汇总表 
B1: 土耳其厨电费用指标统计
B2: 一、年度预测： 产量预测：年度预算125.4万台↑20%，实际5月累计48.91万台 ↑19% 单台预测：25年单台达成27.54欧，26年目标25.35欧，预测达成24.47欧，同比↓12%；额收益397万 三、5月达成实际： 单台实际：5月同期30.17欧，实际单台费用31.2欧，较同期↑3.3%； 5月累计单台：5月同期31.19欧，4月实际23.78欧，累计单台↓7.41欧，额收益352万欧
A3: 费 | B3: 序号 | C3: / | D3: 1月份 | E3: 2月份 | F3: 3月份 | G3: 4月份 | H3: 5月份 | I3: 6月份 | J3: 7月份 | K3: 8月份 | L3: 9月份 | M3: 10月份 | N3: 11月份 | O3: 12月份 | P3: 年度
B4: 费率 | C4: 销售收入（26年预测） | D4: 11387.793 | E4: 11383.957 | F4: 11384.182 | G4: 10843.261 | H4: 8301.8079 | I4: 12020.11 | J4: 9489.0377 | K4: 8834.8314 | L4: 12125.496 | M4: 10955.642 | N4: 11601.048 | O4: 9179.1981 | P4: 127506.36
C5: 销售收入（25年实际） | D5: 11599.19 | E5: 10318.459 | F5: 10279.816 | G5: 10804.991 | H5: 11868.184 | I5: 6637.8974 | J5: 9550.8211 | K5: 7188.5794 | L5: 5817.7726 | M5: 5854.6235 | N5: 7485.28 | O5: 8923.716 | P5: 106138.64
C6: 单价（同期） | D6: 238.80897 | E6: 224.15352 | F6: 221.84897 | G6: 218.88846 | H6: 220.99255 | I6: 223.76947 | J6: 228.17739 | K6: 224.80468 | L6: 205.80772 | M6: 223.36513 | N6: 220 | O6: 212 | P6: 222
C7: 单价（实际） | D7: 225.66619 | E7: 225.66619 | F7: 225.66619 | G7: 225.66619 | H7: 225.66619 | I7: 225.66619 | J7: 225.66619 | K7: 225.66619 | L7: 225.66619 | M7: 225.66619 | N7: 225.66619 | O7: 225.66619 | P7: 225.66619
C8: 制造费用（26年预测） | D8: 1838.2556 | E8: 1852.3924 | F8: 1893.0365 | G8: 1849.6673 | H8: 1928.8688 | I8: 1870.4326 | J8: 1859.2351 | K8: 1842.1673 | L8: 1948.6868 | M8: 1894.9246 | N8: 1861.9628 | O8: 1947.1505 | P8: 22586.78
C9: 制造费用（25年实际） | D9: 1702.2213 | E9: 1632.2334 | F9: 1827.8999 | G9: 1591.5968 | H9: 1866.987 | I9: 1737.9 | J9: 1637.4123 | K9: 1533.5455 | L9: 1597.8553 | M9: 1443.0898 | N9: 1758.5061 | O9: 1502.3028 | P9: 19831.55
C10: 同期 | D10: 0.14675346 | E10: 0.15818577 | F10: 0.17781446 | G10: 0.147302 | H10: 0.15731025 | I10: 0.26181483 | J10: 0.17144205 | K10: 0.21333082 | L10: 0.2746507 | M10: 0.24648721 | N10: 0.23492856 | O10: 0.16834947 | P10: 0.18684571
C11: 目标 | D11: 0.16142334 | E11: 0.16271955 | F11: 0.16628656 | G11: 0.17058221 | H11: 0.23234323 | I11: 0.15560861 | J11: 0.19593505 | K11: 0.20851188 | L11: 0.16070986 | M11: 0.17296335 | N11: 0.16049954 | O11: 0.21212643 | P11: 0.17714238
C12: 26年 | D12: =D8/D4 -> 0.16142334 | E12: =E8/E4 -> 0.16271955 | F12: =F8/F4 -> 0.16628656 | G12: =G8/G4 -> 0.17058221 | H12: =H8/H4 -> 0.23234323 | I12: =I8/I4 -> 0.15560861 | J12: =J8/J4 -> 0.19593505 | K12: =K8/K4 -> 0.20851188 | ... P12: =P8/P4 -> 0.17714238
B13: 降幅 | D13: =(D10-D12)/D10 -> -0.09996281 | E13: =(E10-E12)/E10 -> -0.028661121 | F13: =(F10-F12)/F10 -> 0.064831052 | G13: =(G10-G12)/G10 -> -0.15804409 | H13: =(H10-H12)/H10 -> -0.47697446 | I13: =(I10-I12)/I10 -> 0.40565396 | J13: =(J10-J12)/J10 -> -0.14286464 | K13: =(K10-K12)/K10 -> 0.022589029 | ... P13: =(P10-P12)/P10 -> 0.051932324
B14: 完成率 | D14: =2-D12/D11 -> 1 | E14: =2-E12/E11 -> 1 | F14: =2-F12/F11 -> 1 | G14: =2-G12/G11 -> 1 | H14: =2-H12/H11 -> 1 | I14: =2-I12/I11 -> 1 | J14: =2-J12/J11 -> 1 | K14: =2-K12/K11 -> 1 | ... O14: =2-O12/O11 -> 1
B15: 费率（累计） | C15: 累计销售收入（26年预测） | D15: =D4 -> 11387.793 | E15: =D15+E4 -> 22771.75 | F15: =E15+F4 -> 34155.932 | G15: =F15+G4 -> 44999.193 | H15: =G15+H4 -> 53301.001 | I15: =H15+I4 -> 65321.11 | J15: =I15+J4 -> 74810.148 | K15: =J15+K4 -> 83644.98 | L15: =K15+L4 -> 95770.476 | ... O15: =N15+O4 -> 127506.36 | P15: =O15 -> 127506.36
C16: 累计销售收入（25年实际） | D16: =D5 -> 11599.19 | E16: =D16+E5 -> 21917.65 | F16: =E16+F5 -> 32197.465 | G16: =F16+G5 -> 43002.456 | H16: =G16+H5 -> 54870.64 | I16: =H16+I5 -> 61508.538 | J16: =I16+J5 -> 71059.359 | K16: =J16+K5 -> 78247.938 | L16: =K16+L5 -> 84065.711 | ... O16: =N16+O5 -> 106329.33 | P16: =O16 -> 106329.33
C17: 累计制造费用（26年预测） | D17: =D8 -> 1838.2556 | E17: =D17+E8 -> 3690.648 | F17: =E17+F8 -> 5583.6845 | G17: =F17+G8 -> 7433.3518 | H17: =G17+H8 -> 9362.2206 | I17: =H17+I8 -> 11232.653 | J17: =I17+J8 -> 13091.888 | K17: =J17+K8 -> 14934.056 | L17: =K17+L8 -> 16882.742 | ... O17: =N17+O8 -> 22586.78 | P17: =O17 -> 22586.78
C18: 累计制造费用（25年实际） | D18: =D9 -> 1702.2213 | E18: =D18+E9 -> 3334.4547 | F18: =E18+F9 -> 5162.3545 | G18: =F18+G9 -> 6753.9513 | H18: =G18+H9 -> 8620.9383 | I18: =H18+I9 -> 10358.838 | J18: =I18+J9 -> 11996.251 | K18: =J18+K9 -> 13529.796 | L18: =K18+L9 -> 15127.651 | ... O18: =N18+O9 -> 19831.55 | P18: =O18 -> 19831.55
C19: 同期 | D19: =D18/D16 -> 0.14675346 | E19: =E18/E16 -> 0.1521356 | F19: =F18/F16 -> 0.16033419 | G19: =G18/G16 -> 0.15705966 | H19: =H18/H16 -> 0.15711386 | I19: =I18/I16 -> 0.16841302 | J19: =J18/J16 -> 0.16882014 | K19: =K18/K16 -> 0.1729093 | ... P19: =P18/P16 -> 0.18651063
C20: 目标 | D20: 0.16142334 | E20: 0.16207134 | F20: 0.16347627 | G20: 0.16518856 | H20: 0.17564812 | I20: 0.17196054 | J20: 0.1750015 | K20: 0.17854097 | L20: 0.17628337 | M20: 0.17594257 | N20: 0.1744285 | O20: 0.17714238 | P20: 0.17714238
C21: 26年 | D21: =D17/D15 -> 0.16142334 | E21: =E17/E15 -> 0.16207134 | F21: =F17/F15 -> 0.16347627 | G21: =G17/G15 -> 0.16518856 | H21: =H17/H15 -> 0.17564812 | I21: =I17/I15 -> 0.17196054 | J21: =J17/J15 -> 0.1750015 | K21: =K17/K15 -> 0.17854097 | ... P21: =P17/P15 -> 0.17714238
B22: 降幅 | D22: =(D19-D21)/D19 -> -0.09996281 | E22: =(E19-E21)/E19 -> -0.065308465 | F22: =(F19-F21)/F19 -> -0.019597081 | G22: =(G19-G21)/G19 -> -0.05175674 | H22: =(H19-H21)/H19 -> -0.11796704 | I22: =(I19-I21)/I19 -> -0.021064411 | J22: =(J19-J21)/J19 -> -0.036615098 | K22: =(K19-K21)/K19 -> -0.032570075 | ... O22: =(O19-O21)/O19 -> 0.050229047
B23: 完成率 | D23: =2-D21/D20 -> 1 | E23: =2-E21/E20 -> 1 | F23: =2-F21/F20 -> 1 | G23: =2-G21/G20 -> 1 | H23: =2-H21/H20 -> 1 | I23: =2-I21/I20 -> 1 | J23: =2-J21/J20 -> 1 | K23: 0.06 | L23: =2-L21/L20 -> 1 | M23: =2-M21/M20 -> 1 | N23: =2-N21/N20 -> 1 | O23: =2-O21/O20 -> 1 | P23: =2-P21/P20 -> 1
B24: 单台 | C24: 同期 | D24: 34.955495 | E24: 32.791034 | F24: 32.155654 | G24: 25.907081 | H24: 30.166018 | I24: 36.527791 | J24: 30.44504 | K24: 36.62142 | L24: 13.628094 | M24: 20.771015 | N24: 23.468835 | O24: 14.25482 | P24: 27.543942
C25: 目标 | D25: 22.524007 | E25: 22.807982 | F25: 24.749806 | G25: 23.532894 | H25: 35.680784 | I25: 23.150419 | J25: 29.191636 | K25: 30.83436 | L25: 23.865418 | M25: 22.737655 | N25: 21.567501 | O25: 31.698077 | P25: 25.346719
C26: 26年 | D26: ='厨电1月 '!E11 -> 25.548148 | E26: ='厨电2月 '!E12 -> 22.115933 | F26: =厨电3月!F11 -> 24.139704 | G26: =厨电4月!E12 -> 18.948118 | H26: ='厨电5月 '!K245 -> 31.175643 | I26: 21.635163 | J26: 26.702427 | K26: 28.527613 | L26: 22.298863 | M26: 22.009492 | N26: 23.131893 | O26: 35.159814 | P26: 24.23174
B27: 当月单台完成率 | D27: =2-D26/D25 -> 0.86573699 | E27: =2-E26/E25 -> 1.0303424 | F27: =2-F26/F25 -> 1.0246508 | G27: =2-G26/G25 -> 1.1948241 | H27: =2-H26/H25 -> 1.1262624 | I27: =2-I26/I25 -> 1.0654526 | J27: =2-J26/J25 -> 1.0852713 | K27: =2-K26/K25 -> 1.0748109 | ... P27: =2-P26/P25 -> 1.0439891
B28: 目标同期优化率 | D28: =D25/D24-1 -> -0.3556376 | E28: =E25/E24-1 -> -0.30444456 | F28: =F25/F24-1 -> -0.23031246 | G28: =G25/G24-1 -> -0.091642405 | H28: =H25/H24-1 -> 0.18281385 | I28: =I25/I24-1 -> -0.3662245 | J28: =J25/J24-1 -> -0.041169416 | K28: =K25/K24-1 -> -0.15802392 | ... O28: =O25/O24-1 -> 1.2236742
B29: 当月单台同期优化率 | D29: =(D24-D26)/D24 -> 0.26912356 | E29: =(E24-E26)/E24 -> 0.32554938 | F29: =(F24-F26)/F24 -> 0.24928585 | G29: =(G24-G26)/G24 -> 0.26861238 | H29: =(H24-H26)/H24 -> -0.033468971 | I29: =(I24-I26)/I24 -> 0.40770678 | J29: =(J24-J26)/J24 -> 0.12293016 | K29: =(K24-K26)/K24 -> 0.22101293 | ... P29: =(P24-P26)/P24 -> 0.12025157
B30: 当月费用额
B31: 单台（累计） | C31: 同期 | D31: =D40/D60*1000 -> 34.955495 | E31: =E40/E60*1000 -> 33.85726 | F31: =F40/F60*1000 -> 33.237685 | G31: =G40/G60*1000 -> 31.189227 | H31: =H40/H60*1000 -> 30.975304 | I31: =I40/I60*1000 -> 31.774657 | J31: =J40/J60*1000 -> 31.602081 | K31: =K40/K60*1000 -> 32.050562 | ... P31: =P40/P60*1000 -> 27.543942
C32: 目标 | D32: =D41/D61*1000 -> 22.524007 | E32: =E41/E61*1000 -> 22.665689 | F32: =F41/F61*1000 -> 23.320506 | G32: =G41/G61*1000 -> 23.370556 | H32: =H41/H61*1000 -> 25.083208 | I32: =I41/I61*1000 -> 24.743379 | J32: =J41/J61*1000 -> 25.281629 | K32: =K41/K61*1000 -> 25.852296 | ... P32: =P41/P61*1000 -> 25.346719 | R32: =31.19-23.78 -> 7.41
C33: 26年 | D33: =D42/D62*1000 -> 25.544361 | E33: =E42/E62*1000 -> 23.755502 | F33: =F42/F62*1000 -> 23.888032 | G33: =G42/G62*1000 -> 22.594976 | H33: =H42/H62*1000 -> 23.779527 | I33: =I42/I62*1000 -> 23.382032 | J33: =J42/J62*1000 -> 23.802077 | K33: =K42/K62*1000 -> 24.303253 | ... P33: =P42/P62*1000 -> 24.468699
B34: 累计单台完成率 | D34: =2-D33/D32 -> 0.86590512 | E34: =2-E33/E32 -> 0.95191797 | F34: =2-F33/F32 -> 0.97566408 | G34: =2-G33/G32 -> 1.0331862 | H34: =2-H33/H32 -> 1.0519743 | I34: =2-I33/I32 -> 1.0550186 | J34: =2-J33/J32 -> 1.0585228 | K34: =2-K33/K32 -> 1.059919 | ... O34: =2-O33/O32 -> 1.0346404 | P34: =O34 -> 1.0346404
B35: 累计单台同期优化率 | D35: =(D31-D33)/D31 -> 0.2692319 | E35: =(E31-E33)/E31 -> 0.29836313 | F35: =(F31-F33)/F31 -> 0.28129676 | G35: =(G31-G33)/G31 -> 0.27555191 | H35: =(H31-H33)/H31 -> 0.23230691 | I35: =(I31-I33)/I31 -> 0.26412953 | J35: =(J31-J33)/J31 -> 0.24681931 | K35: =(K31-K33)/K31 -> 0.24172146 | ... O35: =(O31-O33)/O31 -> 0.11164863 | P35: =O35 -> 0.11164863
B36: 累计费用额 | D36: =D42 -> 2493.4106 | E36: =E42 -> 4843.8656 | F36: =F42 -> 7435.8905 | G36: =G42 -> 9527.1943 | H36: =H42 -> 11632.517 | I36: =I42 -> 14040.77 | J36: =J42 -> 16363 | K36: =K42 -> 18689.712 | ... O36: =O42 -> 29218.318
B37: 费用金额 | C37: 同期 | D37: 2786.3724 | E37: 2692.3078 | F37: 2979.4464 | G37: 2556.6921 | H37: 2816.0883 | I37: 2742.9449 | J37: 2368.5937 | K37: 2153.779 | L37: 1237.7853 | M37: 2317.4637 | N37: 2618.4649 | O37: 1590.4388 | P37: 28860.377
C38: 目标 | D38: 2628.6417 | E38: 2650.3787 | F38: 2640.9033 | G38: 2463.9881 | H38: 2562.0587 | I38: 2548.9769 | J38: 2516.4942 | K38: 2516.238 | L38: 2799.5329 | M38: 2751.3699 | N38: 2807.1181 | O38: 2894.1929 | P38: 31779.893
C39: 26年 | D39: 2493.4106 | E39: 2350.455 | F39: =厨电3月!J238 -> 2592.0249 | G39: =厨电4月!I235 -> 2091.3038 | H39: ='厨电5月 '!J245 -> 2105.3224 | I39: 2408.2532 | J39: 2322.2299 | K39: 2326.7122 | L39: 2612.4902 | M39: 2584.0024 | N39: 2628.5695 | O39: 2703.5436 | P39: 29058.509
B40: 费用金额（累计） | C40: 同期 | D40: =D37 -> 2786.3724 | E40: =D40+E37 -> 5478.6802 | F40: =E40+F37 -> 8458.1266 | G40: =F40+G37 -> 11014.819 | H40: =G40+H37 -> 13830.907 | I40: =H40+I37 -> 16573.852 | J40: =I40+J37 -> 18942.446 | K40: =J40+K37 -> 21096.225 | L40: =K40+L37 -> 22334.01 | ... O40: =N40+O37 -> 28860.377 | P40: =O40 -> 28860.377
C41: 目标 | D41: =D38 -> 2628.6417 | E41: =D41+E38 -> 5279.0204 | F41: =E41+F38 -> 7919.9237 | G41: =F41+G38 -> 10383.912 | H41: =G41+H38 -> 12945.97 | I41: =H41+I38 -> 15494.947 | J41: =I41+J38 -> 18011.442 | K41: =J41+K38 -> 20527.679 | L41: =K41+L38 -> 23327.212 | ... O41: =N41+O38 -> 31779.893 | P41: =O41 -> 31779.893
C42: 26年 | D42: =D39 -> 2493.4106 | E42: =D42+E39 -> 4843.8656 | F42: =E42+F39 -> 7435.8905 | G42: =F42+G39 -> 9527.1943 | H42: =G42+H39 -> 11632.517 | I42: =H42+I39 -> 14040.77 | J42: =I42+J39 -> 16363 | K42: =J42+K39 -> 18689.712 | L42: =K42+L39 -> 21302.202 | ... O42: =N42+O39 -> 29218.318 | P42: =O42 -> 29218.318
B43: 上涨因素 | C43: 项目 | D43: ①投资类折旧上涨3.38万； ②大件上涨111万元，玻璃二期100.4万元、叶轮自制5.73万元、消毒柜内胆2.63万元、烟机加强梁3.02万元 | E43: ①投资类折旧上涨3.38万； ②大件上涨111万元，玻璃二期100.4万元、叶轮自制5.73万元、消毒柜内胆2.63万元、烟机加强梁3.02万元 | F43: ①投资类折旧上涨3.38万； ②大件上涨111万元，玻璃二期100.4万元、叶轮自制5.73万元、消毒柜内胆2.63万元、烟机加强梁3.02万元 | G43: ①投资类折旧上涨6.94万 ②大件上涨48万元，玻璃二期18.83万元、叶轮自制13.91万元、消毒柜内胆12.63万元、烟机加强梁3.02万元 | H43: 投资类折旧上涨9.21万 ②大件上涨48万元，玻璃二期18.83万元、叶轮自制13.91万元、消毒柜内胆12.63万元、烟机加强梁3.02万元 | I43: ①投资类折旧上涨11.17万 ②大件上涨48万元，玻璃二期18.83万元、叶轮自制13.91万元、消毒柜内胆12.63万元、烟机加强梁3.02万元 | J43: ①投资类折旧上涨17.86万 ②大件上涨45万元，玻璃二期18.83万元、叶轮自制13.91万元、消毒柜内胆12.63万元 | K43: ①投资类折旧上涨20.65万 ②大件上涨45万元，玻璃二期18.83万元、叶轮自制13.91万元、消毒柜内胆12.63万元 | L43: ①投资类折旧上涨20.65万 ②大件上涨51万元，玻璃二期18.83万元、叶轮自制13.91万元、倒角玻璃6.38万元； | M43: ①投资类折旧上涨20.65万 ②大件上涨77万元，玻璃二期18.83万元、叶轮自制13.91万元、倒角玻璃6.38万元、低温丝印玻璃25.53万元 | N43: ①投资类折旧上涨20.65万 ②大件上涨77万元，玻璃二期18.83万元、叶轮自制13.91万元、倒角玻璃6.38万元、低温丝印玻璃25.53万元 | O43: ①投资类折旧上涨19.7万； ②大件上涨77万元，玻璃二期18.83万元、叶轮自制13.91万元、倒角玻璃6.38万元、低温丝印玻璃25.53万元 | P43: /
C44: 金额 | D44: 115.15272 | E44: 115.15272 | F44: 115.15272 | G44: 55.328649 | H44: 57.599119 | I44: 59.558535 | J44: 63.232502 | K44: 66.02085 | L44: 72.39585 | M44: 97.929184 | N44: 97.929184 | O44: 88.626362 | P44: =SUM(D44:O44) -> 1004.0784
B45: 下降因素 | C45: 项目 | D45: 1.人工降28万元：新增省人11人降10.83万：DFX2人、自动化8人、组织架构1人； 2.修理降5.82万元：新增1个项目钻磨线替代水刀降1.6万元； 3.其他降费13万元：新增9个项目降13万元 | E45: 1.人工降33万元：新增省人3人降5万：DFX1人；自动化2人；提效收益3万 2.能源降2.5万元：玻璃厂新增3条降费措施降2.5万元； 3.修理降5.82万元 4.其他降费13万元 | F45: 1.人工降26万元：新增省人3人降2.5万：DFX1人；简易自动化2人 2.能源降8万元：新增光伏项目降费5万元 3.修理降5.82万元 4..其他降费13万元 | G45: 1.人工降35万元：新增省人3人降2.5万：自动化3人； 2.能源降20万元：新增玻璃厂集中钢化项目降费9.5万元，前工序双拉伸降3.4万元； 3.修理降6.95万元：新增玻璃厂老员工代替实习生网板降费1.2万元； 4..其他降费13万元 | H45: 1.人工降36万元：新增省人4人降3.3万：DFX1人、精益1人、拉通模具2人； 2.能源降21万元：新增前处理二合一加工费项目 3.修理降4.6万元 4..其他降费13万元 | I45: 1.人工降44万元：新增省人4人降3.3万：简易自动化1人、自动化3人； 2.能源降27万元：新增前工序及玻璃厂提效减班次项目降6万元 3.修理降5.78万元,：新增激光切割替代水刀降费3.5万元 4..其他降费13万元 | J45: 1.人工降49万元：新增省人2人降1.6万：自动化2人 2.能源降28万元：新增激光切割降水费月降0.2万元； 3.修理降5.78万元, 4.其他降费13万元 | K45: 1.人工降57万元：新增省人3人降8.3万：DFX1人、精益2人、自动化10人 2.能源降28万元 3.修理降5.25万元 4.其他降费13万元 | L45: 1.人工降60万元：新增省人9人降5.8万：自动化7人、拉通模具2人 2.能源降28万元 3.修理降8.5万元：新增备件降费3.25万元； 4..其他降费19万元：新增公寓班车降费6.25万元 | M45: 1.人工降60万元 2.能源降28万元 3.修理降8.5万元： 4..其他降费19万元 | N45: 1.人工降60万元 2.能源降28万元 3.修理降8.5万元： 4..其他降费19万元 | O45: 1.人工降60万元 2.能源降28万元 3.修理降11.5万元：新增网板切换降费2万元； 4..其他降费19万元 | P45: /
C46: 金额 | D46: =#REF! -> #REF! | E46: =#REF! -> #REF! | F46: =#REF! -> #REF! | G46: =#REF! -> #REF! | H46: =#REF! -> #REF! | I46: =#REF! -> #REF! | J46: =#REF! -> #REF! | K46: =#REF! -> #REF! | ... O46: =#REF! -> #REF! | P46: =SUM(D46:O46) -> #REF!
A47: 单 | B47: 定单量 | C47: 同期 | D47: 79712 | E47: 82105 | F47: 92657 | G47: 98687 | H47: 93353 | I47: 75092 | J47: 77799 | K47: 58812 | L47: 90826 | M47: 111572 | N47: 111625 | O47: 75554 | P47: 1047794
C48: 目标 | D48: 116704 | E48: 116204 | F48: 106704 | G48: 104704 | H48: 71805 | I48: 110105 | J48: 86206 | K48: 81605 | L48: 117305 | M48: 121005 | N48: 130155 | O48: 91305 | P48: 1253807
D49: =D48-D50 -> 19093 | E49: =D49/D50 -> 0.19560295
C50: 26年 | D50: 97611 | E50: 106294 | F50: =厨电3月!L28 -> 107376 | G50: =厨电4月!K26 -> 110370 | H50: ='厨电5月 '!L27 -> 67531 | I50: 111312 | J50: 86967 | K50: 81560.001 | L50: 117158 | M50: 117404 | N50: 113634 | O50: 76893 | P50: 1199192
C51: 增幅 | D51: =(D50-D47)/D47 -> 0.22454587 | E51: =(E50-E47)/E47 -> 0.29461056 | F51: =(F50-F47)/F47 -> 0.1588547 | G51: =(G50-G47)/G47 -> 0.11838439 | H51: =(H50-H47)/H47 -> -0.276606 | I51: =(I50-I47)/I47 -> 0.48234166 | J51: =(J50-J47)/J47 -> 0.11784213 | K51: =(K50-K47)/K47 -> 0.38679183 | ... P51: =(P50-P47)/P47 -> 0.14449214
B52: 标准台 | C52: 同期 | D52: 79712 | E52: 82105 | F52: 92657 | G52: 98687 | H52: 93353 | I52: 75092 | J52: 77799 | K52: 58812 | L52: 90826 | M52: 111572 | N52: 111625 | O52: 75554 | P52: =SUM(D52:O52) -> 1047794
C53: 目标 | D53: 116704 | E53: 116204 | F53: 106704 | G53: 104704 | H53: 71805 | I53: 110105 | J53: 86206 | K53: 81605 | L53: 117305 | M53: 121005 | N53: 130155 | O53: 91305 | P53: =SUM(D53:O53) -> 1253807
C54: 26年 | D54: 97611 | E54: 106294 | F54: 105459 | G54: =G53 -> 104704 | H54: =H53 -> 71805 | I54: =I53 -> 110105 | J54: =J53 -> 86206 | K54: =K53 -> 81605 | L54: =L53 -> 117305 | M54: =M53 -> 121005 | N54: =N53 -> 130155 | ... P54: =P53 -> 1253807
C55: 增幅 | D55: =(D54-D52)/D52 -> 0.22454587 | E55: =(E54-E52)/E52 -> 0.29461056 | F55: =(F54-F52)/F52 -> 0.13816549 | G55: =(G54-G52)/G52 -> 0.060970543 | H55: =(H54-H52)/H52 -> -0.23082279 | I55: =(I54-I52)/I52 -> 0.46626804 | J55: =(J54-J52)/J52 -> 0.10806051 | K55: =(K54-K52)/K52 -> 0.38755696 | ... P55: =(P54-P52)/P52 -> 0.19661594
B56: 标准台系数 | C56: 同期 | D56: 1 | E56: 1 | F56: 1 | G56: 1 | H56: 1 | I56: 1 | J56: 1 | K56: 1 | L56: 1 | M56: 1 | N56: 1 | O56: 1 | P56: 1
C57: 目标 | D57: 1 | E57: 1 | F57: 1 | G57: 1 | H57: 1 | I57: 1 | J57: 1 | K57: 1 | L57: 1 | M57: 1 | N57: 1 | O57: 1 | P57: 1
C58: 实际 | D58: 1 | E58: 1 | F58: 1 | G58: 1 | H58: 1 | I58: 1 | J58: 1 | K58: 1 | L58: 1 | M58: 1 | N58: 1 | O58: 1 | P58: 1
C59: 降幅 | D59: =(D58-D56)/D56 -> 0 | E59: =(E58-E56)/E56 -> 0 | F59: =(F58-F56)/F56 -> 0 | G59: =(G58-G56)/G56 -> 0 | H59: =(H58-H56)/H56 -> 0 | I59: =(I58-I56)/I56 -> 0 | J59: =(J58-J56)/J56 -> 0 | K59: =(K58-K56)/K56 -> 0 | ... P59: =(P58-P56)/P56 -> 0
B60: 定单量（累计） | C60: 同期 | D60: =D47 -> 79712 | E60: =D60+E47 -> 161817 | F60: =E60+F47 -> 254474 | G60: =F60+G47 -> 353161 | H60: =G60+H47 -> 446514 | I60: =H60+I47 -> 521606 | J60: =I60+J47 -> 599405 | K60: =J60+K47 -> 658217 | L60: =K60+L47 -> 749043 | ... O60: =N60+O47 -> 1047794 | P60: =O60 -> 1047794
C61: 目标 | D61: =D48 -> 116704 | E61: =D61+E48 -> 232908 | F61: =E61+F48 -> 339612 | G61: =F61+G48 -> 444316 | H61: =G61+H48 -> 516121 | I61: =H61+I48 -> 626226 | J61: =I61+J48 -> 712432 | K61: =J61+K48 -> 794037 | L61: =K61+L48 -> 911342 | ... O61: =N61+O48 -> 1253807 | P61: =O61 -> 1253807
C62: 26年 | D62: =D50 -> 97611 | E62: =D62+E50 -> 203905 | F62: =E62+F50 -> 311281 | G62: =F62+G50 -> 421651 | H62: =G62+H50 -> 489182 | I62: =H62+I50 -> 600494 | J62: =I62+J50 -> 687461 | K62: =J62+K50 -> 769021 | L62: =K62+L50 -> 886179 | ... O62: =N62+O50 -> 1194110 | P62: =O62 -> 1194110 | Q62: 0
C63: 增幅 | D63: =(D62-D60)/D60 -> 0.22454587 | E63: =(E62-E60)/E60 -> 0.26009628 | F63: =(F62-F60)/F60 -> 0.22323302 | G63: =(G62-G60)/G60 -> 0.19393421 | H63: =(H62-H60)/H60 -> 0.095558034 | I63: =(I62-I60)/I60 -> 0.15124059 | J63: =(J62-J60)/J60 -> 0.14690568 | K63: =(K62-K60)/K60 -> 0.16833962 | ... P63: =(P62-P60)/P60 -> 0.13964195
B64: 标准台（累计） | C64: 同期 | D64: =D52 -> 79712 | E64: =D64+E52 -> 161817 | F64: =E64+F52 -> 254474 | G64: =F64+G52 -> 353161 | H64: =G64+H52 -> 446514 | I64: =H64+I52 -> 521606 | J64: =I64+J52 -> 599405 | K64: =J64+K52 -> 658217 | L64: =K64+L52 -> 749043 | ... O64: =N64+O52 -> 1047794 | P64: =O64 -> 1047794
C65: 目标 | D65: =D53 -> 116704 | E65: =D65+E53 -> 232908 | F65: =E65+F53 -> 339612 | G65: =F65+G53 -> 444316 | H65: =G65+H53 -> 516121 | I65: =H65+I53 -> 626226 | J65: =I65+J53 -> 712432 | K65: =J65+K53 -> 794037 | L65: =K65+L53 -> 911342 | ... O65: =N65+O53 -> 1253807 | P65: =O65 -> 1253807
C66: 26年 | D66: =D54 -> 97611 | E66: =D66+E54 -> 203905 | F66: =E66+F54 -> 309364 | G66: =F66+G54 -> 414068 | H66: =G66+H54 -> 485873 | I66: =H66+I54 -> 595978 | J66: =I66+J54 -> 682184 | K66: =J66+K54 -> 763789 | L66: =K66+L54 -> 881094 | ... O66: =N66+O54 -> 1223559 | P66: =O66 -> 1223559
C67: 增幅 | D67: =(D66-D64)/D64 -> 0.22454587 | E67: =(E66-E64)/E64 -> 0.26009628 | F67: =(F66-F64)/F64 -> 0.21569984 | G67: =(G66-G64)/G64 -> 0.17246242 | H67: =(H66-H64)/H64 -> 0.088147292 | I67: =(I66-I64)/I64 -> 0.14258272 | J67: =(J66-J64)/J64 -> 0.13810195 | K67: =(K66-K64)/K64 -> 0.16039087 | ... P67: =(P66-P64)/P64 -> 0.16774767
A68: 工作日 | C68: 同期 | D68: 20 | E68: 20 | F68: 20 | G68: 20 | H68: 20 | I68: 18 | J68: 18 | K68: 15 | L68: 22 | M68: 24 | N68: 24 | O68: 15 | P68: =SUM(D68:O68) -> 236
C69: 26年 | D69: 20 | E69: 20 | F69: 23 | G69: 21 | H69: 14 | I69: 22 | J69: 17 | K69: 16 | L69: 22 | M69: 20 | N69: 21 | O69: 14 | P69: =SUM(D69:O69) -> 230
A70: 用人 | C70: 同期 | D70: 507 | E70: 535 | F70: 528.5 | G70: 532.5 | H70: 524 | I70: 446.29 | J70: 407.96 | K70: 404.33333 | L70: 401 | M70: 473 | N70: 475 | O70: 444 | P70: =AVERAGE(D70:O70) -> 473.21528
C71: 规划用人
C72: （含回移）-减去省人
C73: 同比新增回移自制人数
C74: （不含回移）-减去省人
C75: 省人数
C76: 26年 | D76: 452 | E76: 452 | F76: =厨电3月!F4+厨电3月!F6+厨电3月!F8 -> 452 | G76: =厨电4月!E5+厨电4月!E7+厨电4月!E9 -> 419 | H76: 452 | I76: 406 | J76: 412 | K76: 411 | L76: 411 | M76: 411 | N76: 430 | O76: 430 | P76: 430
A77: 人效（自然台） | C77: 同期 | D77: =D47/D68/D70 -> 7.861144 | E77: =E47/E68/E70 -> 7.6733645 | F77: =F47/F68/F70 -> 8.766036 | G77: =G47/G68/G70 -> 9.266385 | H77: =H47/H68/H70 -> 8.907729 | I77: =I47/I68/I70 -> 9.3476837 | J77: =J47/J68/J70 -> 10.594584 | K77: =K47/K68/K70 -> 9.6969497 | ... P77: =P47/P68/P70 -> 9.3822099
C78: 26年 | D78: =D50/D69/D76 -> 10.797677 | E78: =E50/E69/E76 -> 11.758186 | F78: =F50/F69/F76 -> 10.328588 | G78: =G50/G69/G76 -> 12.543471 | H78: =H50/H69/H76 -> 10.671776 | I78: =I50/I69/I76 -> 12.462159 | J78: =J50/J69/J76 -> 12.416762 | K78: =K50/K69/K76 -> 12.402677 | ... P78: =P50/P69/P76 -> 12.125298
C79: 增幅 | D79: =(D78/D77)-1 -> 0.37355034 | E79: =(E78/E77)-1 -> 0.53233772 | F79: =(F78/F77)-1 -> 0.17825069 | G79: =(G78/G77)-1 -> 0.35365311 | H79: =(H78/H77)-1 -> 0.19803557 | I79: =(I78/I77)-1 -> 0.33318145 | J79: =(J78/J77)-1 -> 0.1719914 | K79: =(K78/K77)-1 -> 0.27902866 | ... P79: =(P78/P77)-1 -> 0.29237124
A80: 当月单台差异 | D80: =D25-D26 -> -3.024141 | E80: =E25-E26 -> 0.69204871 | F80: =F25-F26 -> 0.61010162 | G80: =G25-G26 -> 4.5847756 | H80: =H25-H26 -> 4.5051403 | I80: =I25-I26 -> 1.5152561 | J80: =J25-J26 -> 2.4892092 | K80: =K25-K26 -> 2.3067469 | ... O80: =O25-O26 -> -3.4617372
A81: 当月差异金额 | D81: =D80*D54 -> -295189.42 | E81: =E80*E54 -> 73560.626 | F81: =F80*F54 -> 64340.706 | G81: =G80*G54 -> 480044.35 | H81: =H80*H54 -> 323491.6 | I81: =I80*I54 -> 166837.27 | J81: =J80*J54 -> 214584.77 | K81: =K80*K54 -> 188242.08 | ... O81: =O80*O54 -> -316073.92
A82: 累计单台差异 | D82: =D32-D33 -> -3.0203541 | E82: =E32-E33 -> -1.0898124 | F82: =F32-F33 -> -0.56752597 | G82: =G32-G33 -> 0.77557949 | H82: =H32-H33 -> 1.303681 | I82: =I32-I33 -> 1.3613472 | J82: =J32-J33 -> 1.4795517 | K82: =K32-K33 -> 1.5490428 | ... O82: =O32-O33 -> 0.87801992
A83: 累计差异金额 | D83: =D82*D66 -> -294819.78 | E83: =E82*E66 -> -222218.19 | F83: =F82*F66 -> -175572.1 | G83: =G82*G66 -> 321142.65 | H83: =H82*H66 -> 633423.39 | I83: =I82*I66 -> 811332.97 | J83: =J82*J66 -> 1009326.5 | K83: =K82*K66 -> 1183141.9 | ... O83: =O82*O66 -> 1074309.2
A84: 折旧 | C84: 同期 | D84: 770.36882 | E84: 741.42854 | F84: 763.50516 | G84: 766.01624 | H84: 831.68695 | I84: 824.01968 | J84: 839.2091 | K84: 583.2903 | L84: 793.0073 | M84: 589.92044 | N84: 801.39809 | O84: 815.91192 | P84: =SUM(D84:O84) -> 9119.7625
C85: 26年 | D85: 818.33241 | E85: 613.15617 | F85: 735
C86: 新增投资折旧 | D86: =D85-D84 -> 47.96359 | E86: =E85-E84 -> -128.27237 | F86: =F85-F84 -> -28.50516 | G86: =G85-G84 -> -766.01624 | H86: =H85-H84 -> -831.68695 | I86: =I85-I84 -> -824.01968 | J86: =J85-J84 -> -839.2091 | K86: =K85-K84 -> -583.2903 | ... O86: =O85-O84 -> -815.91192 | P86: =SUM(D86:O86) -> -6953.274
A87: 日均排产 | C87: 同期 | D87: =D47/D68 -> 3985.6 | E87: =E47/E68 -> 4105.25 | F87: =F47/F68 -> 4632.85 | G87: =G47/G68 -> 4934.35 | H87: =H47/H68 -> 4667.65 | I87: =I47/I68 -> 4171.7778 | J87: =J47/J68 -> 4322.1667 | K87: =K47/K68 -> 3920.8 | ... P87: =P47/P68 -> 4439.8051
C88: 26年 | D88: =D50/D69 -> 4880.55 | E88: =E50/E69 -> 5314.7 | F88: =F50/F69 -> 4668.5217 | G88: =G50/G69 -> 5255.7143 | H88: =H50/H69 -> 4823.6429 | I88: =I50/I69 -> 5059.6364 | J88: =J50/J69 -> 5115.7059 | K88: =K50/K69 -> 5097.5001 | ... P88: =P50/P69 -> 5213.8783

Sheet 25年厨电费用指标到月测算汇总表  (2)
B1: 土耳其厨电费用指标统计
B2: 一、年度预测： 产量预测：年度预算125.4万台↑20%，实际Q1 30.9万台 ↑22% 单台预测：25年单台达成31.88欧，26年目标25.3欧，预测达成25.6欧，同比↓19.7%； 二、Q1达成预测： 单台预测：Q1单台预测:23.89欧，同期单台33.24欧，同比28.1%； 三、3月达成实际： 单台预测：3月同期32.16欧，实际单台费用24.1欧，较同期↓24.9%； 四、4月达成预测： 单台预测：4月同期25.91欧，预测单台费用23.5欧，较同期↓9.2%；
A3: 费 | B3: 序号 | C3: / | D3: 1月份 | E3: 2月份 | F3: 3月份 | G3: 4月份 | H3: 5月份 | I3: 6月份 | J3: 7月份 | K3: 8月份 | L3: 9月份 | M3: 10月份 | N3: 11月份 | O3: 12月份 | P3: 年度
B4: 费率 | C4: 销售收入（25年预测） | D4: 11387.793 | E4: 11383.957 | F4: 11384.182 | G4: 10843.261 | H4: 8301.8079 | I4: 12020.11 | J4: 9489.0377 | K4: 8834.8314 | L4: 12125.496 | M4: 10955.642 | N4: 11601.048 | O4: 9179.1981 | P4: 127506.36
C5: 销售收入（25年实际） | D5: 11599.19 | E5: 10318.459 | F5: 10279.816 | G5: 10804.991 | H5: 11868.184 | I5: 6637.8974 | J5: 9550.8211 | K5: 7188.5794 | L5: 5817.7726 | M5: 5854.6235 | N5: 7485.28 | O5: 8923.716 | P5: 106138.64
C6: 单价（同期） | D6: 238.80897 | E6: 224.15352 | F6: 221.84897 | G6: 218.88846 | H6: 220.99255 | I6: 223.76947 | J6: 228.17739 | K6: 224.80468 | L6: 205.80772 | M6: 223.36513 | N6: 220 | O6: 212 | P6: 222
C7: 单价（实际） | D7: 225.66619 | E7: 225.66619 | F7: 225.66619 | G7: 225.66619 | H7: 225.66619 | I7: 225.66619 | J7: 225.66619 | K7: 225.66619 | L7: 225.66619 | M7: 225.66619 | N7: 225.66619 | O7: 225.66619 | P7: 225.66619
C8: 制造费用（25年预测） | D8: 1838.2556 | E8: 1852.3924 | F8: 1893.0365 | G8: 1849.6673 | H8: 1928.8688 | I8: 1870.4326 | J8: 1859.2351 | K8: 1842.1673 | L8: 1948.6868 | M8: 1894.9246 | N8: 1861.9628 | O8: 1947.1505 | P8: 22586.78
C9: 制造费用（25年实际） | D9: 1702.2213 | E9: 1632.2334 | F9: 1827.8999 | G9: 1591.5968 | H9: 1866.987 | I9: 1737.9 | J9: 1637.4123 | K9: 1533.5455 | L9: 1597.8553 | M9: 1443.0898 | N9: 1758.5061 | O9: 1502.3028 | P9: 19831.55
C10: 同期 | D10: 0.14675346 | E10: 0.15818577 | F10: 0.17781446 | G10: 0.147302 | H10: 0.15731025 | I10: 0.26181483 | J10: 0.17144205 | K10: 0.21333082 | L10: 0.2746507 | M10: 0.24648721 | N10: 0.23492856 | O10: 0.16834947 | P10: 0.18684571
C11: 目标 | D11: 0.16142334 | E11: 0.16271955 | F11: 0.16628656 | G11: 0.17058221 | H11: 0.23234323 | I11: 0.15560861 | J11: 0.19593505 | K11: 0.20851188 | L11: 0.16070986 | M11: 0.17296335 | N11: 0.16049954 | O11: 0.21212643 | P11: 0.17714238
C12: 25年 | D12: =D8/D4 -> 0.16142334 | E12: =E8/E4 -> 0.16271955 | F12: =F8/F4 -> 0.16628656 | G12: =G8/G4 -> 0.17058221 | H12: =H8/H4 -> 0.23234323 | I12: =I8/I4 -> 0.15560861 | J12: =J8/J4 -> 0.19593505 | K12: =K8/K4 -> 0.20851188 | ... P12: =P8/P4 -> 0.17714238
B13: 降幅 | D13: =(D10-D12)/D10 -> -0.09996281 | E13: =(E10-E12)/E10 -> -0.028661121 | F13: =(F10-F12)/F10 -> 0.064831052 | G13: =(G10-G12)/G10 -> -0.15804409 | H13: =(H10-H12)/H10 -> -0.47697446 | I13: =(I10-I12)/I10 -> 0.40565396 | J13: =(J10-J12)/J10 -> -0.14286464 | K13: =(K10-K12)/K10 -> 0.022589029 | ... P13: =(P10-P12)/P10 -> 0.051932324
B14: 完成率 | D14: =2-D12/D11 -> 1 | E14: =2-E12/E11 -> 1 | F14: =2-F12/F11 -> 1 | G14: =2-G12/G11 -> 1 | H14: =2-H12/H11 -> 1 | I14: =2-I12/I11 -> 1 | J14: =2-J12/J11 -> 1 | K14: =2-K12/K11 -> 1 | ... O14: =2-O12/O11 -> 1
B15: 费率（累计） | C15: 累计销售收入（25年预测） | D15: =D4 -> 11387.793 | E15: =D15+E4 -> 22771.75 | F15: =E15+F4 -> 34155.932 | G15: =F15+G4 -> 44999.193 | H15: =G15+H4 -> 53301.001 | I15: =H15+I4 -> 65321.11 | J15: =I15+J4 -> 74810.148 | K15: =J15+K4 -> 83644.98 | L15: =K15+L4 -> 95770.476 | ... O15: =N15+O4 -> 127506.36 | P15: =O15 -> 127506.36
C16: 累计销售收入（25年实际） | D16: =D5 -> 11599.19 | E16: =D16+E5 -> 21917.65 | F16: =E16+F5 -> 32197.465 | G16: =F16+G5 -> 43002.456 | H16: =G16+H5 -> 54870.64 | I16: =H16+I5 -> 61508.538 | J16: =I16+J5 -> 71059.359 | K16: =J16+K5 -> 78247.938 | L16: =K16+L5 -> 84065.711 | ... O16: =N16+O5 -> 106329.33 | P16: =O16 -> 106329.33
C17: 累计制造费用（25年预测） | D17: =D8 -> 1838.2556 | E17: =D17+E8 -> 3690.648 | F17: =E17+F8 -> 5583.6845 | G17: =F17+G8 -> 7433.3518 | H17: =G17+H8 -> 9362.2206 | I17: =H17+I8 -> 11232.653 | J17: =I17+J8 -> 13091.888 | K17: =J17+K8 -> 14934.056 | L17: =K17+L8 -> 16882.742 | ... O17: =N17+O8 -> 22586.78 | P17: =O17 -> 22586.78
C18: 累计制造费用（25年实际） | D18: =D9 -> 1702.2213 | E18: =D18+E9 -> 3334.4547 | F18: =E18+F9 -> 5162.3545 | G18: =F18+G9 -> 6753.9513 | H18: =G18+H9 -> 8620.9383 | I18: =H18+I9 -> 10358.838 | J18: =I18+J9 -> 11996.251 | K18: =J18+K9 -> 13529.796 | L18: =K18+L9 -> 15127.651 | ... O18: =N18+O9 -> 19831.55 | P18: =O18 -> 19831.55
C19: 同期 | D19: =D18/D16 -> 0.14675346 | E19: =E18/E16 -> 0.1521356 | F19: =F18/F16 -> 0.16033419 | G19: =G18/G16 -> 0.15705966 | H19: =H18/H16 -> 0.15711386 | I19: =I18/I16 -> 0.16841302 | J19: =J18/J16 -> 0.16882014 | K19: =K18/K16 -> 0.1729093 | ... P19: =P18/P16 -> 0.18651063
C20: 目标 | D20: 0.16142334 | E20: 0.16207134 | F20: 0.16347627 | G20: 0.16518856 | H20: 0.17564812 | I20: 0.17196054 | J20: 0.1750015 | K20: 0.17854097 | L20: 0.17628337 | M20: 0.17594257 | N20: 0.1744285 | O20: 0.17714238 | P20: 0.17714238
C21: 25年 | D21: =D17/D15 -> 0.16142334 | E21: =E17/E15 -> 0.16207134 | F21: =F17/F15 -> 0.16347627 | G21: =G17/G15 -> 0.16518856 | H21: =H17/H15 -> 0.17564812 | I21: =I17/I15 -> 0.17196054 | J21: =J17/J15 -> 0.1750015 | K21: =K17/K15 -> 0.17854097 | ... P21: =P17/P15 -> 0.17714238
B22: 降幅 | D22: =(D19-D21)/D19 -> -0.09996281 | E22: =(E19-E21)/E19 -> -0.065308465 | F22: =(F19-F21)/F19 -> -0.019597081 | G22: =(G19-G21)/G19 -> -0.05175674 | H22: =(H19-H21)/H19 -> -0.11796704 | I22: =(I19-I21)/I19 -> -0.021064411 | J22: =(J19-J21)/J19 -> -0.036615098 | K22: =(K19-K21)/K19 -> -0.032570075 | ... O22: =(O19-O21)/O19 -> 0.050229047
B23: 完成率 | D23: =2-D21/D20 -> 1 | E23: =2-E21/E20 -> 1 | F23: =2-F21/F20 -> 1 | G23: =2-G21/G20 -> 1 | H23: =2-H21/H20 -> 1 | I23: =2-I21/I20 -> 1 | J23: =2-J21/J20 -> 1 | K23: 0.06 | L23: =2-L21/L20 -> 1 | M23: =2-M21/M20 -> 1 | N23: =2-N21/N20 -> 1 | O23: =2-O21/O20 -> 1 | P23: =2-P21/P20 -> 1
B24: 单台 | C24: 同期 | D24: 29.694717 | E24: 27.682021 | F24: 29.102664 | G24: 31.122967 | H24: 23.033408 | I24: 30.245796 | J24: 31.123389 | K24: 66.79137 | L24: 34.287464 | M24: 34.79144 | N24: 37.649627 | O24: 48.840682 | P24: 33.260307
C25: 目标 | D25: 40.044992 | E25: 37.996493 | F25: 32.697817 | G25: 28.580161 | H25: 32.622575 | I25: 27.648112 | J25: 26.507382 | K25: 34.668329 | L25: 22.833595 | M25: 28.518712 | N25: 30.947958 | O25: 33.592314 | P25: 30.719784
C26: 25年 | D26: 34.955495 | E26: 32.791031 | F26: 32.155654 | G26: 25.907081 | H26: 30.165326 | I26: 36.527791 | J26: 30.44504 | K26: 36.62142 | L26: 13.628744 | M26: 20.771015 | N26: 23.458034 | O26: 21.050359 | P26: 27.543973
B27: 当月单台完成率 | D27: =2-D26/D25 -> 1.1270945 | E27: =2-E26/E25 -> 1.1369985 | F27: =2-F26/F25 -> 1.016581 | G27: =2-G26/G25 -> 1.0935292 | H27: =2-H26/H25 -> 1.0753236 | I27: =2-I26/I25 -> 0.67883237 | J27: =2-J26/J25 -> 0.8514505 | K27: =2-K26/K25 -> 0.94366353 | ... P27: =2-P26/P25 -> 1.10338
B28: 目标同期优化率 | D28: =D25/D24-1 -> 0.34855609 | E28: =E25/E24-1 -> 0.37260549 | F28: =F25/F24-1 -> 0.12353347 | G28: =G25/G24-1 -> -0.081701912 | H28: =H25/H24-1 -> 0.41631559 | I28: =I25/I24-1 -> -0.085885797 | J28: =J25/J24-1 -> -0.14831311 | K28: =K25/K24-1 -> -0.48094597 | ... O28: =O25/O24-1 -> -0.31220629
B29: 当月单台同期优化率 | D29: =(D24-D26)/D24 -> -0.17716208 | E29: =(E24-E26)/E24 -> -0.18456058 | F29: =(F24-F26)/F24 -> -0.10490414 | G29: =(G24-G26)/G24 -> 0.1675896 | H29: =(H24-H26)/H24 -> -0.30963362 | I29: =(I24-I26)/I24 -> -0.2076981 | J29: =(J24-J26)/J24 -> 0.021795455 | K29: =(K24-K26)/K24 -> 0.4517043 | ... P29: =(P24-P26)/P24 -> 0.17186654
B30: 当月费用额
B31: 单台（累计） | C31: 同期 | D31: =D40/D59*1000 -> 29.694717 | E31: =E40/E59*1000 -> 28.57184 | F31: =F40/F59*1000 -> 28.765671 | G31: =G40/G59*1000 -> 29.379754 | H31: =H40/H59*1000 -> 27.679999 | I31: =I40/I59*1000 -> 28.12694 | J31: =J40/J59*1000 -> 28.593526 | K31: =K40/K59*1000 -> 31.118641 | ... P31: =P40/P59*1000 -> 33.260307
C32: 目标 | D32: =D41/D60*1000 -> 40.544617 | E32: =E41/E60*1000 -> 79.658846 | F32: =F41/F60*1000 -> 94.425972 | G32: =G41/G60*1000 -> 115.15805 | H32: =H41/H60*1000 -> 164.17325 | I32: =I41/I60*1000 -> 176.23716 | J32: =J41/J60*1000 -> 204.36599 | K32: =K41/K60*1000 -> 300.0071 | ... P32: =P41/P60*1000 -> 30.470192
C33: 25年 | D33: =D42/D61*1000 -> 39.554295 | E33: =E42/E61*1000 -> 75.173442 | F33: =F42/F61*1000 -> 103.28811 | G33: =G42/G61*1000 -> 126.51068 | H33: =H42/H61*1000 -> 167.7567 | I33: =I42/I61*1000 -> 252.85709 | J33: =J42/J61*1000 -> 279.54817 | K33: =K42/K61*1000 -> 413.32275 | ... P33: =P42/P61*1000 -> 32.080891
B34: 累计单台完成率 | D34: =2-D33/D32 -> 1.0244255 | E34: =2-E33/E32 -> 1.0563077 | F34: =2-F33/F32 -> 0.90614726 | G34: =2-G33/G32 -> 0.90141703 | H34: =2-H33/H32 -> 0.97817279 | I34: =2-I33/I32 -> 0.56524526 | J34: =2-J33/J32 -> 0.63211992 | K34: =2-K33/K32 -> 0.62229011 | ... O34: =2-O33/O32 -> 0.82757831 | P34: =O34 -> 0.82757831
B35: 累计单台同期优化率 | D35: =(D31-D33)/D31 -> -0.33203136 | E35: =(E31-E33)/E31 -> -1.6310326 | F35: =(F31-F33)/F31 -> -2.5906727 | G35: =(G31-G33)/G31 -> -3.3060495 | H35: =(H31-H33)/H31 -> -5.0605745 | I35: =(I31-I33)/I31 -> -7.9898543 | J35: =(J31-J33)/J31 -> -8.7766246 | K35: =(K31-K33)/K31 -> -12.282159 | ... O35: =(O31-O33)/O31 -> -12.37638 | P35: =O35 -> -12.37638
B36: 累计费用额 | D36: =D42 -> 3152.9519 | E36: =E42 -> 6172.1155 | F36: =F42 -> 9570.3663 | G36: =G42 -> 12484.959 | H36: =H42 -> 15660.591 | I36: =I42 -> 18987.545 | J36: =J42 -> 21748.568 | K36: =K42 -> 24308.338 | ... O36: =O42 -> 33614.165
B37: 费用金额 | C37: 同期 | D37: 2593.4475 | E37: 3050.8909 | F37: 3306.8193 | G37: 3411.6374 | H37: 3545.5095 | I37: 3666.6677 | J37: 3994.8426 | K37: 3897.2096 | L37: 3768.4323 | M37: 4039.4601 | N37: 3990.0321 | O37: 3556.4319 | P37: 42821.381
C38: 目标 | D38: 3085.8508 | E38: 2924.0109 | F38: 3243.6004 | G38: 3113.4765 | H38: 3114.5993 | I38: 2879.0254 | J38: 2712.4316 | K38: 2722.6683 | L38: 2938.9074 | M38: 2864.1988 | N38: 2851.7672 | O38: 2848.0531 | P38: 35298.59
C39: 25年 | D39: 3152.9519 | E39: 3019.1635 | F39: 3398.2508 | G39: 2914.5928 | H39: 3175.6318 | I39: 3326.954 | J39: 2761.0229 | K39: 2559.7697 | L39: 1617.1885 | M39: 2702.8444 | N39: 2999.4201 | O39: 1986.374 | P39: 33614.307
B40: 费用金额（累计） | C40: 同期 | D40: =D37 -> 2593.4475 | E40: =D40+E37 -> 5644.3384 | F40: =E40+F37 -> 8951.1577 | G40: =F40+G37 -> 12362.795 | H40: =G40+H37 -> 15908.305 | I40: =H40+I37 -> 19574.972 | J40: =I40+J37 -> 23569.815 | K40: =J40+K37 -> 27467.024 | L40: =K40+L37 -> 31235.457 | ... O40: =N40+O37 -> 42821.381 | P40: =O40 -> 42821.381
C41: 目标 | D41: =D38 -> 3085.8508 | E41: =D41+E38 -> 6009.8616 | F41: =E41+F38 -> 9253.462 | G41: =F41+G38 -> 12366.939 | H41: =G41+H38 -> 15481.538 | I41: =H41+I38 -> 18360.563 | J41: =I41+J38 -> 21072.995 | K41: =J41+K38 -> 23795.663 | L41: =K41+L38 -> 26734.571 | ... O41: =N41+O38 -> 35298.59 | P41: =O41 -> 35298.59
C42: 25年 | D42: =D39 -> 3152.9519 | E42: =D42+E39 -> 6172.1155 | F42: =E42+F39 -> 9570.3663 | G42: =F42+G39 -> 12484.959 | H42: =G42+H39 -> 15660.591 | I42: =H42+I39 -> 18987.545 | J42: =I42+J39 -> 21748.568 | K42: =J42+K39 -> 24308.338 | L42: =K42+L39 -> 25925.526 | ... O42: =N42+O39 -> 33614.165 | P42: =O42 -> 33614.165
B43: 上涨因素 | C43: 项目 | D43: ①投资类折旧上涨3.38万； ②大件上涨111万元，玻璃二期100.4万元、叶轮自制5.73万元、消毒柜内胆2.63万元、烟机加强梁3.02万元 | E43: ①投资类折旧上涨3.38万； ②大件上涨111万元，玻璃二期100.4万元、叶轮自制5.73万元、消毒柜内胆2.63万元、烟机加强梁3.02万元 | F43: ①投资类折旧上涨3.38万； ②大件上涨111万元，玻璃二期100.4万元、叶轮自制5.73万元、消毒柜内胆2.63万元、烟机加强梁3.02万元 | G43: ①投资类折旧上涨6.94万 ②大件上涨48万元，玻璃二期18.83万元、叶轮自制13.91万元、消毒柜内胆12.63万元、烟机加强梁3.02万元 | H43: 投资类折旧上涨9.21万 ②大件上涨48万元，玻璃二期18.83万元、叶轮自制13.91万元、消毒柜内胆12.63万元、烟机加强梁3.02万元 | I43: ①投资类折旧上涨11.17万 ②大件上涨48万元，玻璃二期18.83万元、叶轮自制13.91万元、消毒柜内胆12.63万元、烟机加强梁3.02万元 | J43: ①投资类折旧上涨17.86万 ②大件上涨45万元，玻璃二期18.83万元、叶轮自制13.91万元、消毒柜内胆12.63万元 | K43: ①投资类折旧上涨20.65万 ②大件上涨45万元，玻璃二期18.83万元、叶轮自制13.91万元、消毒柜内胆12.63万元 | L43: ①投资类折旧上涨20.65万 ②大件上涨51万元，玻璃二期18.83万元、叶轮自制13.91万元、倒角玻璃6.38万元； | M43: ①投资类折旧上涨20.65万 ②大件上涨77万元，玻璃二期18.83万元、叶轮自制13.91万元、倒角玻璃6.38万元、低温丝印玻璃25.53万元 | N43: ①投资类折旧上涨20.65万 ②大件上涨77万元，玻璃二期18.83万元、叶轮自制13.91万元、倒角玻璃6.38万元、低温丝印玻璃25.53万元 | O43: ①投资类折旧上涨19.7万； ②大件上涨77万元，玻璃二期18.83万元、叶轮自制13.91万元、倒角玻璃6.38万元、低温丝印玻璃25.53万元 | P43: /
C44: 金额 | D44: 115.15272 | E44: 115.15272 | F44: 115.15272 | G44: 55.328649 | H44: 57.599119 | I44: 59.558535 | J44: 63.232502 | K44: 66.02085 | L44: 72.39585 | M44: 97.929184 | N44: 97.929184 | O44: 88.626362 | P44: =SUM(D44:O44) -> 1004.0784
B45: 下降因素 | C45: 项目 | D45: 1.人工降28万元：新增省人11人降10.83万：DFX2人、自动化8人、组织架构1人； 2.修理降5.82万元：新增1个项目钻磨线替代水刀降1.6万元； 3.其他降费13万元：新增9个项目降13万元 | E45: 1.人工降33万元：新增省人3人降5万：DFX1人；自动化2人；提效收益3万 2.能源降2.5万元：玻璃厂新增3条降费措施降2.5万元； 3.修理降5.82万元 4.其他降费13万元 | F45: 1.人工降26万元：新增省人3人降2.5万：DFX1人；简易自动化2人 2.能源降8万元：新增光伏项目降费5万元 3.修理降5.82万元 4..其他降费13万元 | G45: 1.人工降35万元：新增省人3人降2.5万：自动化3人； 2.能源降20万元：新增玻璃厂集中钢化项目降费9.5万元，前工序双拉伸降3.4万元； 3.修理降6.95万元：新增玻璃厂老员工代替实习生网板降费1.2万元； 4..其他降费13万元 | H45: 1.人工降36万元：新增省人4人降3.3万：DFX1人、精益1人、拉通模具2人； 2.能源降21万元：新增前处理二合一加工费项目 3.修理降4.6万元 4..其他降费13万元 | I45: 1.人工降44万元：新增省人4人降3.3万：简易自动化1人、自动化3人； 2.能源降27万元：新增前工序及玻璃厂提效减班次项目降6万元 3.修理降5.78万元,：新增激光切割替代水刀降费3.5万元 4..其他降费13万元 | J45: 1.人工降49万元：新增省人2人降1.6万：自动化2人 2.能源降28万元：新增激光切割降水费月降0.2万元； 3.修理降5.78万元, 4.其他降费13万元 | K45: 1.人工降57万元：新增省人3人降8.3万：DFX1人、精益2人、自动化10人 2.能源降28万元 3.修理降5.25万元 4.其他降费13万元 | L45: 1.人工降60万元：新增省人9人降5.8万：自动化7人、拉通模具2人 2.能源降28万元 3.修理降8.5万元：新增备件降费3.25万元； 4..其他降费19万元：新增公寓班车降费6.25万元 | M45: 1.人工降60万元 2.能源降28万元 3.修理降8.5万元： 4..其他降费19万元 | N45: 1.人工降60万元 2.能源降28万元 3.修理降8.5万元： 4..其他降费19万元 | O45: 1.人工降60万元 2.能源降28万元 3.修理降11.5万元：新增网板切换降费2万元； 4..其他降费19万元 | P45: /
C46: 金额 | D46: =#REF! -> #REF! | E46: =#REF! -> #REF! | F46: =#REF! -> #REF! | G46: =#REF! -> #REF! | H46: =#REF! -> #REF! | I46: =#REF! -> #REF! | J46: =#REF! -> #REF! | K46: =#REF! -> #REF! | ... O46: =#REF! -> #REF! | P46: =SUM(D46:O46) -> #REF!
A47: 单 | B47: 定单量 | C47: 同期 | D47: 87337 | E47: 110212 | F47: 113626 | G47: 109618 | H47: 153929 | I47: 121229 | J47: 128355 | K47: 58349 | L47: 109907 | M47: 116105 | N47: 105978 | O47: 72817 | P47: 1287462
C48: 目标 | D48: 116704 | E48: 116204 | F48: 106704 | G48: 104704 | H48: 71805 | I48: 110105 | J48: 86206 | K48: 81605 | L48: 117305 | M48: 121005 | N48: 130155 | O48: 91305 | P48: 1253807
C49: 25年 | D49: 97611 | E49: 106294 | F49: =厨电3月!L28 -> 107376 | G49: 106859 | H49: 67759 | I49: 105659 | J49: 82859 | K49: 77945 | L49: 112964 | M49: 115460 | N49: 112944 | O49: 77504 | P49: 1168817
C50: 增幅 | D50: =(D49-D47)/D47 -> 0.11763628 | E50: =(E49-E47)/E47 -> -0.035549668 | F50: =(F49-F47)/F47 -> -0.055005016 | G50: =(G49-G47)/G47 -> -0.025169224 | H50: =(H49-H47)/H47 -> -0.55980355 | I50: =(I49-I47)/I47 -> -0.12843462 | J50: =(J49-J47)/J47 -> -0.35445444 | K50: =(K49-K47)/K47 -> 0.33584123 | ... P50: =(P49-P47)/P47 -> -0.092154176
B51: 标准台 | C51: 同期 | D51: 79712 | E51: 82105 | F51: 92657 | G51: 98687 | H51: 93353 | I51: 75092 | J51: 77799 | K51: 58812 | L51: 90826 | M51: 111572 | N51: 111625 | O51: 75554 | P51: =SUM(D51:O51) -> 1047794
C52: 目标 | D52: 116704 | E52: 116204 | F52: 106704 | G52: 104704 | H52: 71805 | I52: 110105 | J52: 86206 | K52: 81605 | L52: 117305 | M52: 121005 | N52: 130155 | O52: 91305 | P52: =SUM(D52:O52) -> 1253807
C53: 25年 | D53: 97611 | E53: 106294 | F53: 105459 | G53: =G52 -> 104704 | H53: =H52 -> 71805 | I53: =I52 -> 110105 | J53: =J52 -> 86206 | K53: =K52 -> 81605 | L53: =L52 -> 117305 | M53: =M52 -> 121005 | N53: =N52 -> 130155 | ... P53: =P52 -> 1253807
C54: 增幅 | D54: =(D53-D51)/D51 -> 0.22454587 | E54: =(E53-E51)/E51 -> 0.29461056 | F54: =(F53-F51)/F51 -> 0.13816549 | G54: =(G53-G51)/G51 -> 0.060970543 | H54: =(H53-H51)/H51 -> -0.23082279 | I54: =(I53-I51)/I51 -> 0.46626804 | J54: =(J53-J51)/J51 -> 0.10806051 | K54: =(K53-K51)/K51 -> 0.38755696 | ... P54: =(P53-P51)/P51 -> 0.19661594
B55: 标准台系数 | C55: 同期 | D55: 1 | E55: 1 | F55: 1 | G55: 1 | H55: 1 | I55: 1 | J55: 1 | K55: 1 | L55: 1 | M55: 1 | N55: 1 | O55: 1 | P55: 1
C56: 目标 | D56: 1 | E56: 1 | F56: 1 | G56: 1 | H56: 1 | I56: 1 | J56: 1 | K56: 1 | L56: 1 | M56: 1 | N56: 1 | O56: 1 | P56: 1
C57: 实际 | D57: 1 | E57: 1 | F57: 1 | G57: 1 | H57: 1 | I57: 1 | J57: 1 | K57: 1 | L57: 1 | M57: 1 | N57: 1 | O57: 1 | P57: 1
C58: 降幅 | D58: =(D57-D55)/D55 -> 0 | E58: =(E57-E55)/E55 -> 0 | F58: =(F57-F55)/F55 -> 0 | G58: =(G57-G55)/G55 -> 0 | H58: =(H57-H55)/H55 -> 0 | I58: =(I57-I55)/I55 -> 0 | J58: =(J57-J55)/J55 -> 0 | K58: =(K57-K55)/K55 -> 0 | ... P58: =(P57-P55)/P55 -> 0
B59: 定单量（累计） | C59: 同期 | D59: =D47 -> 87337 | E59: =D59+E47 -> 197549 | F59: =E59+F47 -> 311175 | G59: =F59+G47 -> 420793 | H59: =G59+H47 -> 574722 | I59: =H59+I47 -> 695951 | J59: =I59+J47 -> 824306 | K59: =J59+K47 -> 882655 | L59: =K59+L47 -> 992562 | ... O59: =N59+O47 -> 1287462 | P59: =O59 -> 1287462
C60: 目标 | D60: 76110 | E60: 75445 | F60: 97997 | G60: 107391 | H60: 94300 | I60: 104181 | J60: 103114 | K60: 79317 | L60: 129648 | M60: 103320 | N60: 94620 | O60: 93020 | P60: 1158463
C61: 25年 | D61: 79712 | E61: 82105 | F61: 92657 | G61: 98687 | H61: 93353 | I61: 75092 | J61: 77799 | K61: 58812 | L61: 90826 | M61: 111572 | N61: 111625 | O61: 75554 | P61: 1047794 | Q61: 0
C62: 增幅 | D62: =(D61-D59)/D59 -> -0.087305495 | E62: =(E61-E59)/E59 -> -0.5843816 | F62: =(F61-F59)/F59 -> -0.70223508 | G62: =(G61-G59)/G59 -> -0.76547376 | H62: =(H61-H59)/H59 -> -0.83756842 | I62: =(I61-I59)/I59 -> -0.8921016 | J62: =(J61-J59)/J59 -> -0.90561879 | K62: =(K61-K59)/K59 -> -0.93336921 | ... P62: =(P61-P59)/P59 -> -0.1861554
B63: 标准台（累计） | C63: 同期 | D63: =D51 -> 79712 | E63: =D63+E51 -> 161817 | F63: =E63+F51 -> 254474 | G63: =F63+G51 -> 353161 | H63: =G63+H51 -> 446514 | I63: =H63+I51 -> 521606 | J63: =I63+J51 -> 599405 | K63: =J63+K51 -> 658217 | L63: =K63+L51 -> 749043 | ... O63: =N63+O51 -> 1047794 | P63: =O63 -> 1047794
C64: 目标 | D64: =D52 -> 116704 | E64: =D64+E52 -> 232908 | F64: =E64+F52 -> 339612 | G64: =F64+G52 -> 444316 | H64: =G64+H52 -> 516121 | I64: =H64+I52 -> 626226 | J64: =I64+J52 -> 712432 | K64: =J64+K52 -> 794037 | L64: =K64+L52 -> 911342 | ... O64: =N64+O52 -> 1253807 | P64: =O64 -> 1253807
C65: 25年 | D65: =D53 -> 97611 | E65: =D65+E53 -> 203905 | F65: =E65+F53 -> 309364 | G65: =F65+G53 -> 414068 | H65: =G65+H53 -> 485873 | I65: =H65+I53 -> 595978 | J65: =I65+J53 -> 682184 | K65: =J65+K53 -> 763789 | L65: =K65+L53 -> 881094 | ... O65: =N65+O53 -> 1223559 | P65: =O65 -> 1223559
C66: 增幅 | D66: =(D65-D63)/D63 -> 0.22454587 | E66: =(E65-E63)/E63 -> 0.26009628 | F66: =(F65-F63)/F63 -> 0.21569984 | G66: =(G65-G63)/G63 -> 0.17246242 | H66: =(H65-H63)/H63 -> 0.088147292 | I66: =(I65-I63)/I63 -> 0.14258272 | J66: =(J65-J63)/J63 -> 0.13810195 | K66: =(K65-K63)/K63 -> 0.16039087 | ... P66: =(P65-P63)/P63 -> 0.16774767
A67: 工作日 | C67: 同期 | D67: 20 | E67: 20 | F67: 20 | G67: 20 | H67: 20 | I67: 18 | J67: 18 | K67: 15 | L67: 22 | M67: 24 | N67: 24 | O67: 15 | P67: =SUM(D67:O67) -> 236
C68: 25年 | D68: 20 | E68: 20 | F68: 23 | G68: 21 | H68: 14 | I68: 22 | J68: 17 | K68: 16 | L68: 22 | M68: 20 | N68: 21 | O68: 14 | P68: =SUM(D68:O68) -> 230
A69: 用人 | C69: 同期 | D69: 544.38 | E69: 547 | F69: 601 | G69: 743 | H69: 737 | I69: 727 | J69: 716.5 | K69: 684 | L69: 595 | M69: 595.5 | N69: 577.5 | O69: 543.5 | P69: =AVERAGE(D69:O69) -> 634.28167
C70: 规划用人
C71: （含回移）-减去省人
C72: 同比新增回移自制人数
C73: （不含回移）-减去省人
C74: 省人数
C75: 25年 | D75: 507 | E75: 535 | F75: 528.5 | G75: 532.75 | H75: 525 | I75: 460 | J75: 408 | K75: 404 | L75: 401 | M75: 474 | N75: 475 | O75: 444 | P75: 452
A76: 人效（自然台） | C76: 同期 | D76: =D47/D67/D69 -> 8.0216944 | E76: =E47/E67/E69 -> 10.074223 | F76: =F47/F67/F69 -> 9.4530782 | G76: =G47/G67/G69 -> 7.376716 | H76: =H47/H67/H69 -> 10.442944 | I76: =I47/I67/I69 -> 9.2640226 | J76: =J47/J67/J69 -> 9.9523145 | K76: =K47/K67/K69 -> 5.687037 | ... P76: =P47/P67/P69 -> 8.6008279
C77: 25年 | D77: =D49/D68/D75 -> 9.6263314 | E77: =E49/E68/E75 -> 9.9340187 | F77: =F49/F68/F75 -> 8.8335321 | G77: =G49/G68/G75 -> 9.551429 | H77: =H49/H68/H75 -> 9.2189116 | I77: =I49/I68/I75 -> 10.440613 | J77: =J49/J68/J75 -> 11.946223 | K77: =K49/K68/K75 -> 12.058323 | ... P77: =P49/P68/P75 -> 11.242949
C78: 增幅 | D78: =(D77/D76)-1 -> 0.20003716 | E78: =(E77/E76)-1 -> -0.013917137 | F78: =(F77/F76)-1 -> -0.065539081 | G78: =(G77/G76)-1 -> 0.29480774 | H78: =(H77/H76)-1 -> -0.11721146 | I78: =(I77/I76)-1 -> 0.12700639 | J78: =(J77/J76)-1 -> 0.20034617 | K78: =(K77/K76)-1 -> 1.1203173 | ... P78: =(P77/P76)-1 -> 0.30719383
A79: 当月单台差异 | D79: =D25-D26 -> 5.0894969 | E79: =E25-E26 -> 5.2054629 | F79: =F25-F26 -> 0.54216311 | G79: =G25-G26 -> 2.6730797 | H79: =H25-H26 -> 2.4572496 | I79: =I25-I26 -> -8.8796786 | J79: =J25-J26 -> -3.9376583 | K79: =K25-K26 -> -1.9530912 | ... O79: =O25-O26 -> 12.541955
A80: 当月差异金额 | D80: =D79*D53 -> 496790.88 | E80: =E79*E53 -> 553309.47 | F80: =F79*F53 -> 57175.98 | G80: =G79*G53 -> 279882.13 | H80: =H79*H53 -> 176442.8 | I80: =I79*I53 -> -977697.02 | J80: =J79*J53 -> -339449.77 | K80: =K79*K53 -> -159382.01 | ... O80: =O79*O53 -> 1145143.2
A81: 累计单台差异 | D81: =D32-D33 -> 0.99032193 | E81: =E32-E33 -> 4.485404 | F81: =F32-F33 -> -8.8621362 | G81: =G32-G33 -> -11.352623 | H81: =H32-H33 -> -3.5834436 | I81: =I32-I33 -> -76.619938 | J81: =J32-J33 -> -75.182176 | K81: =K32-K33 -> -113.31565 | ... O81: =O32-O33 -> -65.429395
A82: 累计差异金额 | D82: =D81*D65 -> 96666.314 | E82: =E81*E65 -> 914596.3 | F82: =F81*F65 -> -2741625.9 | G82: =G81*G65 -> -4700757.8 | H82: =H81*H65 -> -1741098.5 | I82: =I81*I65 -> -45663798 | J82: =J81*J65 -> -51288078 | K82: =K81*K65 -> -86549247 | ... O82: =O81*O65 -> -80056726
A83: 折旧 | C83: 同期 | D83: 770.36882 | E83: 741.42854 | F83: 763.50516 | G83: 766.01624 | H83: 831.68695 | I83: 824.01968 | J83: 839.2091 | K83: 583.2903 | L83: 793.0073 | M83: 589.92044 | N83: 801.39809 | O83: 815.91192 | P83: =SUM(D83:O83) -> 9119.7625
C84: 25年 | D84: 818.33241 | E84: 613.15617 | F84: 735
C85: 新增投资折旧 | D85: =D84-D83 -> 47.96359 | E85: =E84-E83 -> -128.27237 | F85: =F84-F83 -> -28.50516 | G85: =G84-G83 -> -766.01624 | H85: =H84-H83 -> -831.68695 | I85: =I84-I83 -> -824.01968 | J85: =J84-J83 -> -839.2091 | K85: =K84-K83 -> -583.2903 | ... O85: =O84-O83 -> -815.91192 | P85: =SUM(D85:O85) -> -6953.274
A86: 日均排产 | C86: 同期 | D86: =D47/D67 -> 4366.85 | E86: =E47/E67 -> 5510.6 | F86: =F47/F67 -> 5681.3 | G86: =G47/G67 -> 5480.9 | H86: =H47/H67 -> 7696.45 | I86: =I47/I67 -> 6734.9444 | J86: =J47/J67 -> 7130.8333 | K86: =K47/K67 -> 3889.9333 | ... P86: =P47/P67 -> 5455.3475
C87: 25年 | D87: =D49/D68 -> 4880.55 | E87: =E49/E68 -> 5314.7 | F87: =F49/F68 -> 4668.5217 | G87: =G49/G68 -> 5088.5238 | H87: =H49/H68 -> 4839.9286 | I87: =I49/I68 -> 4802.6818 | J87: =J49/J68 -> 4874.0588 | K87: =K49/K68 -> 4871.5625 | ... P87: =P49/P68 -> 5081.813

Sheet 25年厨电费用指标到月测算汇总表
B1: 土耳其厨电费用指标统计
A3: 费 | B3: 序号 | C3: / | D3: 1月份 | E3: 2月份 | F3: 3月份 | G3: 4月份 | H3: 5月份 | I3: 6月份 | J3: 7月份 | K3: 8月份 | L3: 9月份 | M3: 10月份 | N3: 11月份 | O3: 12月份 | P3: 年度
B4: 费率 | C4: 销售收入（25年预测） | D4: 11387.793 | E4: 11383.957 | F4: 11384.182 | G4: 10843.261 | H4: 8301.8079 | I4: 12020.11 | J4: 9489.0377 | K4: 8834.8314 | L4: 12125.496 | M4: 10955.642 | N4: 11601.048 | O4: 9179.1981 | P4: 127506.36
C5: 销售收入（25年实际） | D5: 11599.19 | E5: 10318.459 | F5: 10279.816 | G5: 10804.991 | H5: 11868.184 | I5: 6637.8974 | J5: 9550.8211 | K5: 7188.5794 | L5: 5817.7726 | M5: 5854.6235 | N5: 7485.28 | O5: 8923.716 | P5: 106138.64
C6: 单价（同期） | D6: 238.80897 | E6: 224.15352 | F6: 221.84897 | G6: 218.88846 | H6: 220.99255 | I6: 223.76947 | J6: 228.17739 | K6: 224.80468 | L6: 205.80772 | M6: 223.36513 | N6: 220 | O6: 212 | P6: 222
C7: 单价（实际） | D7: 225.66619 | E7: 225.66619 | F7: 225.66619 | G7: 225.66619 | H7: 225.66619 | I7: 225.66619 | J7: 225.66619 | K7: 225.66619 | L7: 225.66619 | M7: 225.66619 | N7: 225.66619 | O7: 225.66619 | P7: 225.66619
C8: 制造费用（25年预测） | D8: 1838.2556 | E8: 1852.3924 | F8: 1893.0365 | G8: 1849.6673 | H8: 1928.8688 | I8: 1870.4326 | J8: 1859.2351 | K8: 1842.1673 | L8: 1948.6868 | M8: 1894.9246 | N8: 1861.9628 | O8: 1947.1505 | P8: 22586.78
C9: 制造费用（25年实际） | D9: 1702.2213 | E9: 1632.2334 | F9: 1827.8999 | G9: 1591.5968 | H9: 1866.987 | I9: 1737.9 | J9: 1637.4123 | K9: 1533.5455 | L9: 1597.8553 | M9: 1443.0898 | N9: 1758.5061 | O9: 1502.3028 | P9: 19831.55
C10: 同期 | D10: 0.14675346 | E10: 0.15818577 | F10: 0.17781446 | G10: 0.147302 | H10: 0.15731025 | I10: 0.26181483 | J10: 0.17144205 | K10: 0.21333082 | L10: 0.2746507 | M10: 0.24648721 | N10: 0.23492856 | O10: 0.16834947 | P10: 0.18684571
C11: 目标 | D11: 0.16142334 | E11: 0.16271955 | F11: 0.16628656 | G11: 0.17058221 | H11: 0.23234323 | I11: 0.15560861 | J11: 0.19593505 | K11: 0.20851188 | L11: 0.16070986 | M11: 0.17296335 | N11: 0.16049954 | O11: 0.21212643 | P11: 0.17714238
C12: 25年 | D12: =D8/D4 -> 0.16142334 | E12: =E8/E4 -> 0.16271955 | F12: =F8/F4 -> 0.16628656 | G12: =G8/G4 -> 0.17058221 | H12: =H8/H4 -> 0.23234323 | I12: =I8/I4 -> 0.15560861 | J12: =J8/J4 -> 0.19593505 | K12: =K8/K4 -> 0.20851188 | ... P12: =P8/P4 -> 0.17714238
B13: 降幅 | D13: =(D10-D12)/D10 -> -0.09996281 | E13: =(E10-E12)/E10 -> -0.028661121 | F13: =(F10-F12)/F10 -> 0.064831052 | G13: =(G10-G12)/G10 -> -0.15804409 | H13: =(H10-H12)/H10 -> -0.47697446 | I13: =(I10-I12)/I10 -> 0.40565396 | J13: =(J10-J12)/J10 -> -0.14286464 | K13: =(K10-K12)/K10 -> 0.022589029 | ... P13: =(P10-P12)/P10 -> 0.051932324
B14: 完成率 | D14: =2-D12/D11 -> 1 | E14: =2-E12/E11 -> 1 | F14: =2-F12/F11 -> 1 | G14: =2-G12/G11 -> 1 | H14: =2-H12/H11 -> 1 | I14: =2-I12/I11 -> 1 | J14: =2-J12/J11 -> 1 | K14: =2-K12/K11 -> 1 | ... O14: =2-O12/O11 -> 1
B15: 费率（累计） | C15: 累计销售收入（25年预测） | D15: =D4 -> 11387.793 | E15: =D15+E4 -> 22771.75 | F15: =E15+F4 -> 34155.932 | G15: =F15+G4 -> 44999.193 | H15: =G15+H4 -> 53301.001 | I15: =H15+I4 -> 65321.11 | J15: =I15+J4 -> 74810.148 | K15: =J15+K4 -> 83644.98 | L15: =K15+L4 -> 95770.476 | ... O15: =N15+O4 -> 127506.36 | P15: =O15 -> 127506.36
C16: 累计销售收入（25年实际） | D16: =D5 -> 11599.19 | E16: =D16+E5 -> 21917.65 | F16: =E16+F5 -> 32197.465 | G16: =F16+G5 -> 43002.456 | H16: =G16+H5 -> 54870.64 | I16: =H16+I5 -> 61508.538 | J16: =I16+J5 -> 71059.359 | K16: =J16+K5 -> 78247.938 | L16: =K16+L5 -> 84065.711 | ... O16: =N16+O5 -> 106329.33 | P16: =O16 -> 106329.33
C17: 累计制造费用（25年预测） | D17: =D8 -> 1838.2556 | E17: =D17+E8 -> 3690.648 | F17: =E17+F8 -> 5583.6845 | G17: =F17+G8 -> 7433.3518 | H17: =G17+H8 -> 9362.2206 | I17: =H17+I8 -> 11232.653 | J17: =I17+J8 -> 13091.888 | K17: =J17+K8 -> 14934.056 | L17: =K17+L8 -> 16882.742 | ... O17: =N17+O8 -> 22586.78 | P17: =O17 -> 22586.78
C18: 累计制造费用（25年实际） | D18: =D9 -> 1702.2213 | E18: =D18+E9 -> 3334.4547 | F18: =E18+F9 -> 5162.3545 | G18: =F18+G9 -> 6753.9513 | H18: =G18+H9 -> 8620.9383 | I18: =H18+I9 -> 10358.838 | J18: =I18+J9 -> 11996.251 | K18: =J18+K9 -> 13529.796 | L18: =K18+L9 -> 15127.651 | ... O18: =N18+O9 -> 19831.55 | P18: =O18 -> 19831.55
C19: 同期 | D19: =D18/D16 -> 0.14675346 | E19: =E18/E16 -> 0.1521356 | F19: =F18/F16 -> 0.16033419 | G19: =G18/G16 -> 0.15705966 | H19: =H18/H16 -> 0.15711386 | I19: =I18/I16 -> 0.16841302 | J19: =J18/J16 -> 0.16882014 | K19: =K18/K16 -> 0.1729093 | ... P19: =P18/P16 -> 0.18651063
C20: 目标 | D20: 0.16142334 | E20: 0.16207134 | F20: 0.16347627 | G20: 0.16518856 | H20: 0.17564812 | I20: 0.17196054 | J20: 0.1750015 | K20: 0.17854097 | L20: 0.17628337 | M20: 0.17594257 | N20: 0.1744285 | O20: 0.17714238 | P20: 0.17714238
C21: 25年 | D21: =D17/D15 -> 0.16142334 | E21: =E17/E15 -> 0.16207134 | F21: =F17/F15 -> 0.16347627 | G21: =G17/G15 -> 0.16518856 | H21: =H17/H15 -> 0.17564812 | I21: =I17/I15 -> 0.17196054 | J21: =J17/J15 -> 0.1750015 | K21: =K17/K15 -> 0.17854097 | ... P21: =P17/P15 -> 0.17714238
B22: 降幅 | D22: =(D19-D21)/D19 -> -0.09996281 | E22: =(E19-E21)/E19 -> -0.065308465 | F22: =(F19-F21)/F19 -> -0.019597081 | G22: =(G19-G21)/G19 -> -0.05175674 | H22: =(H19-H21)/H19 -> -0.11796704 | I22: =(I19-I21)/I19 -> -0.021064411 | J22: =(J19-J21)/J19 -> -0.036615098 | K22: =(K19-K21)/K19 -> -0.032570075 | ... O22: =(O19-O21)/O19 -> 0.050229047
B23: 完成率 | D23: =2-D21/D20 -> 1 | E23: =2-E21/E20 -> 1 | F23: =2-F21/F20 -> 1 | G23: =2-G21/G20 -> 1 | H23: =2-H21/H20 -> 1 | I23: =2-I21/I20 -> 1 | J23: =2-J21/J20 -> 1 | K23: 0.06 | L23: =2-L21/L20 -> 1 | M23: =2-M21/M20 -> 1 | N23: =2-N21/N20 -> 1 | O23: =2-O21/O20 -> 1 | P23: =2-P21/P20 -> 1
B24: 单台 | C24: 同期 | D24: 29.694717 | E24: 27.682021 | F24: 29.102664 | G24: 31.122967 | H24: 23.033408 | I24: 30.245796 | J24: 31.123389 | K24: 66.79137 | L24: 34.287464 | M24: 34.79144 | N24: 37.649627 | O24: 48.840682 | P24: 33.260307
C25: 目标 | D25: 40.044992 | E25: 37.996493 | F25: 32.697817 | G25: 28.580161 | H25: 32.622575 | I25: 27.648112 | J25: 26.507382 | K25: 34.668329 | L25: 22.833595 | M25: 28.518712 | N25: 30.947958 | O25: 33.592314 | P25: 30.719784
C26: 25年 | D26: 34.955495 | E26: 32.791031 | F26: 32.155654 | G26: 25.907081 | H26: 30.165326 | I26: 36.527791 | J26: 30.44504 | K26: 36.62142 | L26: 13.628744 | M26: 20.771015 | N26: 23.458034 | O26: 21.050359 | P26: 27.543973
B27: 当月单台完成率 | D27: =2-D26/D25 -> 1.1270945 | E27: =2-E26/E25 -> 1.1369985 | F27: =2-F26/F25 -> 1.016581 | G27: =2-G26/G25 -> 1.0935292 | H27: =2-H26/H25 -> 1.0753236 | I27: =2-I26/I25 -> 0.67883237 | J27: =2-J26/J25 -> 0.8514505 | K27: =2-K26/K25 -> 0.94366353 | ... P27: =2-P26/P25 -> 1.10338
B28: 目标同期优化率 | D28: =D25/D24-1 -> 0.34855609 | E28: =E25/E24-1 -> 0.37260549 | F28: =F25/F24-1 -> 0.12353347 | G28: =G25/G24-1 -> -0.081701912 | H28: =H25/H24-1 -> 0.41631559 | I28: =I25/I24-1 -> -0.085885797 | J28: =J25/J24-1 -> -0.14831311 | K28: =K25/K24-1 -> -0.48094597 | ... O28: =O25/O24-1 -> -0.31220629
B29: 当月单台同期优化率 | D29: =(D24-D26)/D24 -> -0.17716208 | E29: =(E24-E26)/E24 -> -0.18456058 | F29: =(F24-F26)/F24 -> -0.10490414 | G29: =(G24-G26)/G24 -> 0.1675896 | H29: =(H24-H26)/H24 -> -0.30963362 | I29: =(I24-I26)/I24 -> -0.2076981 | J29: =(J24-J26)/J24 -> 0.021795455 | K29: =(K24-K26)/K24 -> 0.4517043 | ... P29: =(P24-P26)/P24 -> 0.17186654
B30: 当月费用额
B31: 单台（累计） | C31: 同期
C32: 目标
C33: 25年
B34: 累计单台完成率 | D34: =2-D33/D32 -> #DIV/0! | E34: =2-E33/E32 -> #DIV/0! | F34: =2-F33/F32 -> #DIV/0! | G34: =2-G33/G32 -> #DIV/0! | H34: =2-H33/H32 -> #DIV/0! | I34: =2-I33/I32 -> #DIV/0! | J34: =2-J33/J32 -> #DIV/0! | K34: =2-K33/K32 -> #DIV/0! | ... O34: =2-O33/O32 -> #DIV/0! | P34: =O34 -> #DIV/0!
B35: 累计单台同期优化率 | D35: =(D31-D33)/D31 -> #DIV/0! | E35: =(E31-E33)/E31 -> #DIV/0! | F35: =(F31-F33)/F31 -> #DIV/0! | G35: =(G31-G33)/G31 -> #DIV/0! | H35: =(H31-H33)/H31 -> #DIV/0! | I35: =(I31-I33)/I31 -> #DIV/0! | J35: =(J31-J33)/J31 -> #DIV/0! | K35: =(K31-K33)/K31 -> #DIV/0! | ... O35: =(O31-O33)/O31 -> #DIV/0! | P35: =O35 -> #DIV/0!
B36: 累计费用额 | D36: =D42 -> 0 | E36: =E42 -> 0 | F36: =F42 -> 0 | G36: =G42 -> 0 | H36: =H42 -> 0 | I36: =I42 -> 0 | J36: =J42 -> 0 | K36: =K42 -> 0 | ... O36: =O42 -> 0
B37: 费用金额 | C37: 同期
C38: 目标
C39: 25年
B40: 费用金额（累计） | C40: 同期 | D40: =D37 -> 0 | E40: =D40+E37 -> 0 | F40: =E40+F37 -> 0 | G40: =F40+G37 -> 0 | H40: =G40+H37 -> 0 | I40: =H40+I37 -> 0 | J40: =I40+J37 -> 0 | K40: =J40+K37 -> 0 | L40: =K40+L37 -> 0 | ... O40: =N40+O37 -> 0 | P40: =O40 -> 0
C41: 目标 | D41: =D38 -> 0 | E41: =D41+E38 -> 0 | F41: =E41+F38 -> 0 | G41: =F41+G38 -> 0 | H41: =G41+H38 -> 0 | I41: =H41+I38 -> 0 | J41: =I41+J38 -> 0 | K41: =J41+K38 -> 0 | L41: =K41+L38 -> 0 | ... O41: =N41+O38 -> 0 | P41: =O41 -> 0
C42: 25年 | D42: =D39 -> 0 | E42: =D42+E39 -> 0 | F42: =E42+F39 -> 0 | G42: =F42+G39 -> 0 | H42: =G42+H39 -> 0 | I42: =H42+I39 -> 0 | J42: =I42+J39 -> 0 | K42: =J42+K39 -> 0 | L42: =K42+L39 -> 0 | ... O42: =N42+O39 -> 0 | P42: =O42 -> 0
B43: 上涨因素 | C43: 项目 | D43: ①投资类折旧上涨3.38万； ②大件上涨111万元，玻璃二期100.4万元、叶轮自制5.73万元、消毒柜内胆2.63万元、烟机加强梁3.02万元 | E43: ①投资类折旧上涨3.38万； ②大件上涨111万元，玻璃二期100.4万元、叶轮自制5.73万元、消毒柜内胆2.63万元、烟机加强梁3.02万元 | F43: ①投资类折旧上涨3.38万； ②大件上涨111万元，玻璃二期100.4万元、叶轮自制5.73万元、消毒柜内胆2.63万元、烟机加强梁3.02万元 | G43: ①投资类折旧上涨6.94万 ②大件上涨48万元，玻璃二期18.83万元、叶轮自制13.91万元、消毒柜内胆12.63万元、烟机加强梁3.02万元 | H43: 投资类折旧上涨9.21万 ②大件上涨48万元，玻璃二期18.83万元、叶轮自制13.91万元、消毒柜内胆12.63万元、烟机加强梁3.02万元 | I43: ①投资类折旧上涨11.17万 ②大件上涨48万元，玻璃二期18.83万元、叶轮自制13.91万元、消毒柜内胆12.63万元、烟机加强梁3.02万元 | J43: ①投资类折旧上涨17.86万 ②大件上涨45万元，玻璃二期18.83万元、叶轮自制13.91万元、消毒柜内胆12.63万元 | K43: ①投资类折旧上涨20.65万 ②大件上涨45万元，玻璃二期18.83万元、叶轮自制13.91万元、消毒柜内胆12.63万元 | L43: ①投资类折旧上涨20.65万 ②大件上涨51万元，玻璃二期18.83万元、叶轮自制13.91万元、倒角玻璃6.38万元； | M43: ①投资类折旧上涨20.65万 ②大件上涨77万元，玻璃二期18.83万元、叶轮自制13.91万元、倒角玻璃6.38万元、低温丝印玻璃25.53万元 | N43: ①投资类折旧上涨20.65万 ②大件上涨77万元，玻璃二期18.83万元、叶轮自制13.91万元、倒角玻璃6.38万元、低温丝印玻璃25.53万元 | O43: ①投资类折旧上涨19.7万； ②大件上涨77万元，玻璃二期18.83万元、叶轮自制13.91万元、倒角玻璃6.38万元、低温丝印玻璃25.53万元 | P43: /
C44: 金额 | D44: 115.15272 | E44: 115.15272 | F44: 115.15272 | G44: 55.328649 | H44: 57.599119 | I44: 59.558535 | J44: 63.232502 | K44: 66.02085 | L44: 72.39585 | M44: 97.929184 | N44: 97.929184 | O44: 88.626362 | P44: =SUM(D44:O44) -> 1004.0784
B45: 下降因素 | C45: 项目 | D45: 1.人工降28万元：新增省人11人降10.83万：DFX2人、自动化8人、组织架构1人； 2.修理降5.82万元：新增1个项目钻磨线替代水刀降1.6万元； 3.其他降费13万元：新增9个项目降13万元 | E45: 1.人工降33万元：新增省人3人降5万：DFX1人；自动化2人；提效收益3万 2.能源降2.5万元：玻璃厂新增3条降费措施降2.5万元； 3.修理降5.82万元 4.其他降费13万元 | F45: 1.人工降26万元：新增省人3人降2.5万：DFX1人；简易自动化2人 2.能源降8万元：新增光伏项目降费5万元 3.修理降5.82万元 4..其他降费13万元 | G45: 1.人工降35万元：新增省人3人降2.5万：自动化3人； 2.能源降20万元：新增玻璃厂集中钢化项目降费9.5万元，前工序双拉伸降3.4万元； 3.修理降6.95万元：新增玻璃厂老员工代替实习生网板降费1.2万元； 4..其他降费13万元 | H45: 1.人工降36万元：新增省人4人降3.3万：DFX1人、精益1人、拉通模具2人； 2.能源降21万元：新增前处理二合一加工费项目 3.修理降4.6万元 4..其他降费13万元 | I45: 1.人工降44万元：新增省人4人降3.3万：简易自动化1人、自动化3人； 2.能源降27万元：新增前工序及玻璃厂提效减班次项目降6万元 3.修理降5.78万元,：新增激光切割替代水刀降费3.5万元 4..其他降费13万元 | J45: 1.人工降49万元：新增省人2人降1.6万：自动化2人 2.能源降28万元：新增激光切割降水费月降0.2万元； 3.修理降5.78万元, 4.其他降费13万元 | K45: 1.人工降57万元：新增省人3人降8.3万：DFX1人、精益2人、自动化10人 2.能源降28万元 3.修理降5.25万元 4.其他降费13万元 | L45: 1.人工降60万元：新增省人9人降5.8万：自动化7人、拉通模具2人 2.能源降28万元 3.修理降8.5万元：新增备件降费3.25万元； 4..其他降费19万元：新增公寓班车降费6.25万元 | M45: 1.人工降60万元 2.能源降28万元 3.修理降8.5万元： 4..其他降费19万元 | N45: 1.人工降60万元 2.能源降28万元 3.修理降8.5万元： 4..其他降费19万元 | O45: 1.人工降60万元 2.能源降28万元 3.修理降11.5万元：新增网板切换降费2万元； 4..其他降费19万元 | P45: /
C46: 金额 | D46: =#REF! -> #REF! | E46: =#REF! -> #REF! | F46: =#REF! -> #REF! | G46: =#REF! -> #REF! | H46: =#REF! -> #REF! | I46: =#REF! -> #REF! | J46: =#REF! -> #REF! | K46: =#REF! -> #REF! | ... O46: =#REF! -> #REF! | P46: =SUM(D46:O46) -> #REF!
A47: 单 | B47: 定单量 | C47: 同期
C48: 目标
C49: 25年
C50: 增幅 | D50: =(D49-D47)/D47 -> #DIV/0! | E50: =(E49-E47)/E47 -> #DIV/0! | F50: =(F49-F47)/F47 -> #DIV/0! | G50: =(G49-G47)/G47 -> #DIV/0! | H50: =(H49-H47)/H47 -> #DIV/0! | I50: =(I49-I47)/I47 -> #DIV/0! | J50: =(J49-J47)/J47 -> #DIV/0! | K50: =(K49-K47)/K47 -> #DIV/0! | ... P50: =(P49-P47)/P47 -> #DIV/0!
B51: 标准台 | C51: 同期 | D51: 79712 | E51: 82105 | F51: 92657 | G51: 98687 | H51: 93353 | I51: 75092 | J51: 77799 | K51: 58812 | L51: 90826 | M51: 111572 | N51: 111625 | O51: 75554 | P51: =SUM(D51:O51) -> 1047794
C52: 目标 | D52: 116704 | E52: 116204 | F52: 106704 | G52: 104704 | H52: 71805 | I52: 110105 | J52: 86206 | K52: 81605 | L52: 117305 | M52: 121005 | N52: 130155 | O52: 91305 | P52: =SUM(D52:O52) -> 1253807
C53: 25年 | D53: 97611 | E53: 106294 | F53: 105459 | G53: =G52 -> 104704 | H53: =H52 -> 71805 | I53: =I52 -> 110105 | J53: =J52 -> 86206 | K53: =K52 -> 81605 | L53: =L52 -> 117305 | M53: =M52 -> 121005 | N53: =N52 -> 130155 | ... P53: =P52 -> 1253807
C54: 增幅 | D54: =(D53-D51)/D51 -> 0.22454587 | E54: =(E53-E51)/E51 -> 0.29461056 | F54: =(F53-F51)/F51 -> 0.13816549 | G54: =(G53-G51)/G51 -> 0.060970543 | H54: =(H53-H51)/H51 -> -0.23082279 | I54: =(I53-I51)/I51 -> 0.46626804 | J54: =(J53-J51)/J51 -> 0.10806051 | K54: =(K53-K51)/K51 -> 0.38755696 | ... P54: =(P53-P51)/P51 -> 0.19661594
B55: 标准台系数 | C55: 同期 | D55: 1 | E55: 1 | F55: 1 | G55: 1 | H55: 1 | I55: 1 | J55: 1 | K55: 1 | L55: 1 | M55: 1 | N55: 1 | O55: 1 | P55: 1
C56: 目标 | D56: 1 | E56: 1 | F56: 1 | G56: 1 | H56: 1 | I56: 1 | J56: 1 | K56: 1 | L56: 1 | M56: 1 | N56: 1 | O56: 1 | P56: 1
C57: 实际 | D57: 1 | E57: 1 | F57: 1 | G57: 1 | H57: 1 | I57: 1 | J57: 1 | K57: 1 | L57: 1 | M57: 1 | N57: 1 | O57: 1 | P57: 1
C58: 降幅 | D58: =(D57-D55)/D55 -> 0 | E58: =(E57-E55)/E55 -> 0 | F58: =(F57-F55)/F55 -> 0 | G58: =(G57-G55)/G55 -> 0 | H58: =(H57-H55)/H55 -> 0 | I58: =(I57-I55)/I55 -> 0 | J58: =(J57-J55)/J55 -> 0 | K58: =(K57-K55)/K55 -> 0 | ... P58: =(P57-P55)/P55 -> 0
B59: 定单量（累计） | C59: 同期 | D59: =D47 -> 0 | E59: =D59+E47 -> 0 | F59: =E59+F47 -> 0 | G59: =F59+G47 -> 0 | H59: =G59+H47 -> 0 | I59: =H59+I47 -> 0 | J59: =I59+J47 -> 0 | K59: =J59+K47 -> 0 | L59: =K59+L47 -> 0 | ... O59: =N59+O47 -> 0 | P59: =O59 -> 0
C60: 目标 | D60: =D48 -> 0 | E60: =D60+E48 -> 0 | F60: =E60+F48 -> 0 | G60: =F60+G48 -> 0 | H60: =G60+H48 -> 0 | I60: =H60+I48 -> 0 | J60: =I60+J48 -> 0 | K60: =J60+K48 -> 0 | L60: =K60+L48 -> 0 | ... O60: =N60+O48 -> 0 | P60: =O60 -> 0
C61: 25年 | D61: =D49 -> 0 | E61: =D61+E49 -> 0 | F61: =E61+F49 -> 0 | G61: =F61+G49 -> 0 | H61: =G61+H49 -> 0 | I61: =H61+I49 -> 0 | J61: =I61+J49 -> 0 | K61: =J61+K49 -> 0 | L61: =K61+L49 -> 0 | ... O61: =N61+O49 -> 0 | P61: =O61 -> 0 | Q61: 0
C62: 增幅 | D62: =(D61-D59)/D59 -> #DIV/0! | E62: =(E61-E59)/E59 -> #DIV/0! | F62: =(F61-F59)/F59 -> #DIV/0! | G62: =(G61-G59)/G59 -> #DIV/0! | H62: =(H61-H59)/H59 -> #DIV/0! | I62: =(I61-I59)/I59 -> #DIV/0! | J62: =(J61-J59)/J59 -> #DIV/0! | K62: =(K61-K59)/K59 -> #DIV/0! | ... P62: =(P61-P59)/P59 -> #DIV/0!
B63: 标准台（累计） | C63: 同期 | D63: =D51 -> 79712 | E63: =D63+E51 -> 161817 | F63: =E63+F51 -> 254474 | G63: =F63+G51 -> 353161 | H63: =G63+H51 -> 446514 | I63: =H63+I51 -> 521606 | J63: =I63+J51 -> 599405 | K63: =J63+K51 -> 658217 | L63: =K63+L51 -> 749043 | ... O63: =N63+O51 -> 1047794 | P63: =O63 -> 1047794
C64: 目标 | D64: =D52 -> 116704 | E64: =D64+E52 -> 232908 | F64: =E64+F52 -> 339612 | G64: =F64+G52 -> 444316 | H64: =G64+H52 -> 516121 | I64: =H64+I52 -> 626226 | J64: =I64+J52 -> 712432 | K64: =J64+K52 -> 794037 | L64: =K64+L52 -> 911342 | ... O64: =N64+O52 -> 1253807 | P64: =O64 -> 1253807
C65: 25年 | D65: =D53 -> 97611 | E65: =D65+E53 -> 203905 | F65: =E65+F53 -> 309364 | G65: =F65+G53 -> 414068 | H65: =G65+H53 -> 485873 | I65: =H65+I53 -> 595978 | J65: =I65+J53 -> 682184 | K65: =J65+K53 -> 763789 | L65: =K65+L53 -> 881094 | ... O65: =N65+O53 -> 1223559 | P65: =O65 -> 1223559
C66: 增幅 | D66: =(D65-D63)/D63 -> 0.22454587 | E66: =(E65-E63)/E63 -> 0.26009628 | F66: =(F65-F63)/F63 -> 0.21569984 | G66: =(G65-G63)/G63 -> 0.17246242 | H66: =(H65-H63)/H63 -> 0.088147292 | I66: =(I65-I63)/I63 -> 0.14258272 | J66: =(J65-J63)/J63 -> 0.13810195 | K66: =(K65-K63)/K63 -> 0.16039087 | ... P66: =(P65-P63)/P63 -> 0.16774767
A67: 工作日 | C67: 同期 | D67: 20 | E67: 20 | F67: 20 | G67: 20 | H67: 20 | I67: 18 | J67: 18 | K67: 15 | L67: 22 | M67: 24 | N67: 24 | O67: 15 | P67: =SUM(D67:O67) -> 236
C68: 25年 | D68: 20 | E68: 20 | F68: 23 | G68: 21 | H68: 14 | I68: 22 | J68: 17 | K68: 16 | L68: 22 | M68: 20 | N68: 21 | O68: 14 | P68: =SUM(D68:O68) -> 230
A69: 用人 | C69: 同期 | D69: 507 | E69: 535 | F69: 528.5 | G69: 532.5 | H69: 524 | I69: 446.29 | J69: 407.96 | K69: 404.33333 | L69: 401 | M69: 473 | N69: 475 | O69: 444 | P69: =AVERAGE(D69:O69) -> 473.21528
C70: 规划用人
C71: （含回移）-减去省人
C72: 同比新增回移自制人数
C73: （不含回移）-减去省人
C74: 省人数
C75: 25年 | D75: 452 | E75: 452 | F75: =厨电3月!F4+厨电3月!F6+厨电3月!F8 -> 452 | G75: 452 | H75: 452 | I75: 452 | J75: 452 | K75: 452 | L75: 452 | M75: 452 | N75: 452 | O75: 452 | P75: 452
A76: 人效（自然台） | C76: 同期
C77: 25年
C78: 增幅 | D78: =(D77/D76)-1 -> #DIV/0! | E78: =(E77/E76)-1 -> #DIV/0! | F78: =(F77/F76)-1 -> #DIV/0! | G78: =(G77/G76)-1 -> #DIV/0! | H78: =(H77/H76)-1 -> #DIV/0! | I78: =(I77/I76)-1 -> #DIV/0! | J78: =(J77/J76)-1 -> #DIV/0! | K78: =(K77/K76)-1 -> #DIV/0! | ... P78: =(P77/P76)-1 -> #DIV/0!
A79: 当月单台差异 | D79: =D25-D26 -> 5.0894969 | E79: =E25-E26 -> 5.2054629 | F79: =F25-F26 -> 0.54216311 | G79: =G25-G26 -> 2.6730797 | H79: =H25-H26 -> 2.4572496 | I79: =I25-I26 -> -8.8796786 | J79: =J25-J26 -> -3.9376583 | K79: =K25-K26 -> -1.9530912 | ... O79: =O25-O26 -> 12.541955
A80: 当月差异金额 | D80: =D79*D53 -> 496790.88 | E80: =E79*E53 -> 553309.47 | F80: =F79*F53 -> 57175.98 | G80: =G79*G53 -> 279882.13 | H80: =H79*H53 -> 176442.8 | I80: =I79*I53 -> -977697.02 | J80: =J79*J53 -> -339449.77 | K80: =K79*K53 -> -159382.01 | ... O80: =O79*O53 -> 1145143.2
A81: 累计单台差异 | D81: =D32-D33 -> 0 | E81: =E32-E33 -> 0 | F81: =F32-F33 -> 0 | G81: =G32-G33 -> 0 | H81: =H32-H33 -> 0 | I81: =I32-I33 -> 0 | J81: =J32-J33 -> 0 | K81: =K32-K33 -> 0 | ... O81: =O32-O33 -> 0
A82: 累计差异金额 | D82: =D81*D65 -> 0 | E82: =E81*E65 -> 0 | F82: =F81*F65 -> 0 | G82: =G81*G65 -> 0 | H82: =H81*H65 -> 0 | I82: =I81*I65 -> 0 | J82: =J81*J65 -> 0 | K82: =K81*K65 -> 0 | ... O82: =O81*O65 -> 0
A83: 折旧 | C83: 同期 | D83: 770.36882 | E83: 741.42854 | F83: 763.50516 | G83: 766.01624 | H83: 831.68695 | I83: 824.01968 | J83: 839.2091 | K83: 583.2903 | L83: 793.0073 | M83: 589.92044 | N83: 801.39809 | O83: 815.91192 | P83: =SUM(D83:O83) -> 9119.7625
C84: 25年 | D84: 818.33241 | E84: 613.15617 | F84: 735
C85: 新增投资折旧 | D85: =D84-D83 -> 47.96359 | E85: =E84-E83 -> -128.27237 | F85: =F84-F83 -> -28.50516 | G85: =G84-G83 -> -766.01624 | H85: =H84-H83 -> -831.68695 | I85: =I84-I83 -> -824.01968 | J85: =J84-J83 -> -839.2091 | K85: =K84-K83 -> -583.2903 | ... O85: =O84-O83 -> -815.91192 | P85: =SUM(D85:O85) -> -6953.274
A86: 日均排产 | C86: 同期 | D86: =D47/D67 -> 0 | E86: =E47/E67 -> 0 | F86: =F47/F67 -> 0 | G86: =G47/G67 -> 0 | H86: =H47/H67 -> 0 | I86: =I47/I67 -> 0 | J86: =J47/J67 -> 0 | K86: =K47/K67 -> 0 | ... P86: =P47/P67 -> 0
C87: 25年 | D87: =D49/D68 -> 0 | E87: =E49/E68 -> 0 | F87: =F49/F68 -> 0 | G87: =G49/G68 -> 0 | H87: =H49/H68 -> 0 | I87: =I49/I68 -> 0 | J87: =J49/J68 -> 0 | K87: =K49/K68 -> 0 | ... P87: =P49/P68 -> 0

Sheet 厨电1月 
A1: 维度 | B1: KPI | C1: 25年实际 | D1: 26年预算 | E1: 26年实际 | F1: 预算差异 | G1: 实际比同期差异 | H1: 制造费差额 | I1: 差异原因
A2: 单 | B2: 产量 | C2: 79712 | D2: 116704 | E2: 97611 | F2: =E2-D2 -> -19093 | G2: =E2-C2 -> 17899 | H2: /
A3: 时 | B3: 工作天数 | C3: 20 | D3: 25 | E3: 20 | F3: =E3-D3 -> -5 | G3: =E3-C3 -> 0
A4: 人 | B4: 人工 | C4: 279 | D4: 286 | E4: 294 | F4: =E4-D4 -> 8 | G4: =E4-C4 -> 15
B5: 人工工资 | C5: =E48*1000/C4 -> 1950.3887 | D5: 2117.668 | E5: 2008.2043 | F5: =E5-D5 -> -109.46368 | G5: =E5-C5 -> 57.815646
B6: 间接人工 | C6: 170 | D6: 133 | E6: 127 | F6: =E6-D6 -> -6 | G6: =E6-C6 -> -43
B7: 间接人工工资 | C7: =E133*1000/C6 -> 2269.8431 | D7: =G133*1000/D6 -> 2373.6641 | E7: =I133*1000/E6 -> 2579.7282 | F7: =E7-D7 -> 206.06412 | G7: =E7-C7 -> 309.88507
B8: 白领人数 | C8: 58 | D8: 34 | E8: 31 | F8: =E8-D8 -> -3 | G8: =E8-C8 -> -27
B9: 白领人工工资 | C9: =E141*1000/C8 -> 4761.5476 | D9: =G141*1000/D8 -> 4538.8768 | E9: =I141*1000/E8 -> 5496.6681 | F9: =E9-D9 -> 957.79131 | G9: =E9-C9 -> 735.12048
A10: 效 | B10: UPPH | C10: =C2/C3/C4 -> 14.285305 | D10: =D2/D3/D4 -> 16.322238 | E10: =E2/E3/E4 -> 16.60051 | F10: =E10-D10 -> 0.27827244 | G10: =E10-C10 -> 2.3152055
A11: 费 | B11: 单台制造费 | C11: =SUM(C12:C24) -> 34.951093 | D11: =SUM(D12:D24) -> 22.524007 | E11: =SUM(E12:E24) -> 25.548148 | F11: =E11-D11 -> 3.024141 | G11: =E11-C11 -> -9.4029453 | H11: =G11*$E$2 -> -917830.89
B12: 折旧 | C12: 9.66 | D12: 6.9891943 | E12: 8.3836085 | F12: =E12-D12 -> 1.3944142 | G12: =E12-C12 -> -1.2763915 | H12: =G12*$E$2 -> -124589.85
B13: 运营费 | C13: 1.2015967 | D13: 0.83683288 | E13: 0.73678274 | F13: =E13-D13 -> -0.10005014 | G13: =E13-C13 -> -0.46481401 | H13: =G13*$E$2 -> -45370.96
B14: 存货跌价准备 | C14: 0.437119 | D14: 0.10710858 | E14: 0.12805934 | F14: =E14-D14 -> 0.020950755 | G14: =E14-C14 -> -0.30905967 | H14: =G14*$E$2 -> -30167.623
B15: 固定能源费 | C15: 0.59142187 | D15: 0.28191353 | E15: 0.35446702 | F15: =E15-D15 -> 0.072553489 | G15: =E15-C15 -> -0.23695485 | H15: =G15*$E$2 -> -23129.4
B16: 间接人工成本-辅助人员 | C16: 4.8408437 | D16: 2.7051114 | E16: 3.3564402 | F16: =E16-D16 -> 0.65132875 | G16: =E16-C16 -> -1.4844035 | H16: =G16*$E$2 -> -144894.11
B17: 固定人工-白领 | C17: 3.4645945 | D17: 1.3223352 | E17: 1.7456712 | F17: =E17-D17 -> 0.42333596 | G17: =E17-C17 -> -1.7189234 | H17: =G17*$E$2 -> -167785.83
B18: 半固定-班车/工作服 | C18: 2.7563919 | D18: 2.772445 | E18: 1.6519728 | F18: =E18-D18 -> -1.1204721 | G18: =E18-C18 -> -1.1044191 | H18: =G18*$E$2 -> -107803.45
B19: 直接人工 | C19: 6.8265561 | D19: 4.950356 | E19: 6.0486223 | F19: =E19-D19 -> 1.0982663 | G19: =E19-C19 -> -0.77793382 | H19: =G19*$E$2 -> -75934.898
B20: 可回收废料 | C20: 0.37641911 | D20: 0.4945089 | E20: 0.48670396 | F20: =E20-D20 -> -0.0078049397 | G20: =E20-C20 -> 0.11028485 | H20: =G20*$E$2 -> 10765.014
B21: 生产耗用品 | C21: -0.077533746 | D21: 0.35303919 | E21: 0.092804807 | F21: =E21-D21 -> -0.26023438 | G21: =E21-C21 -> 0.17033855 | H21: =G21*$E$2 -> 16626.917
B22: 废品回收 | C22: -0.45678217 | D22: -0.74328409 | E22: -0.67364313 | F22: =E22-D22 -> 0.069640954 | G22: =E22-C22 -> -0.21686097 | H22: =G22*$E$2 -> -21168.016
B23: 变动能源费 | C23: 0.3388057 | D23: 0.61137691 | E23: 0.39488972 | F23: =E23-D23 -> -0.2164872 | G23: =E23-C23 -> 0.056084015 | H23: =G23*$E$2 -> 5474.4168
B24: 园区分摊费用 | C24: 4.9916604 | D24: 1.843069 | E24: 2.8417683 | F24: =E24-D24 -> 0.99869936 | G24: =E24-C24 -> -2.149892 | H24: =G24*$E$2 -> -209853.11
B25: IT Expense-Internal Charge Out | C25: 3.1717704 | D25: 0.81376731 | E25: 0.96941113 | F25: 0.15564382 | G25: -2.2023592
B26: Association dues | C26: 0.1065285 | D26: 0.054769786 | E26: 0.050926842 | F26: -0.0038429439 | G26: -0.05560166
B27: G&A | C27: 1.7133615 | D27: 0.97453189 | E27: 1.8203277 | F27: 0.84579584 | G27: 0.10696625 | H27: Analysis required
A28: Type 类型 | B28: Code 编码 | C28: Description(EN) 描述 | D28: Description(CN) 描述 | E28: 单位千欧 | F28: 同期台数 | G28: 79712 | H28: 预算台数 | I28: 116704.08 | J28: 实际台数 | K28: 97611
E29: MFG 2025 同期制造费 | F29: CPU 2025 同期单台 | G29: Budget 2026 预算 | H29: Budget-CPU 2026 单台预算 | I29: ACT 2026 实际 | J29: ACT-CPU 2026 单台实际 | K29: CPU-Y0Y 单台同期 | L29: Budget-ACT VARIANCE 实际-预算 | M29: CPU-Y0Y Analysis 单台同期分析 | N29: Budget-ACT VARIANCE Analysis 预算实际分析
A30: 折旧 | B30: 6666110101 | C30: 6666110101 Depreciation of buildings | D30: 建筑物折旧 | E30: 73.06366 | F30: =E30*1000/$G$28 -> 0.91659549 | G30: 73.437796 | H30: 0.62926501 | I30: 75.41415 | J30: 0.77259889 | K30: =J30-F30 -> -0.14399661 | L30: 0.14333388
B31: 6666110106 | C31: 6666110106 Depreciation of R&D facilities | D31: 研发设施折旧 | E31: 0 | F31: =E31*1000/$G$28 -> 0 | G31: 0 | H31: 0 | I31: 0 | J31: 0 | K31: =J31-F31 -> 0 | L31: 0
B32: 6666110107 | C32: 6666110107 Depreciation of mold | D32: 模具折旧 | E32: 211.90984 | F32: =E32*1000/$G$28 -> 2.6584434 | G32: 204.71583 | H32: 1.7541446 | I32: 204.24196 | J32: 2.0924072 | K32: =J32-F32 -> -0.56603619 | L32: 0.33826263
B33: 6666110110 | C33: 6666110110 Depreciation-Plant & Machinery | D33: 6666110110 折旧-厂房及机械 | E33: 407.33455 | F33: =E33*1000/$G$28 -> 5.1100782 | G33: 446.50044 | H33: 3.8259196 | I33: 447.68976 | J33: 4.5864683 | K33: =J33-F33 -> -0.52360983 | L33: 0.76054872 | N33: 单台上涨0.76，费用持平
B34: 6666110112 | C34: 6666110112 Depreciation of Furniture & Fixture | D34: 6666110112 家具及装置折旧 | E34: 36.9678 | F34: =E34*1000/$G$28 -> 0.46376706 | G34: 58.855828 | H34: 0.50431679 | I34: 58.82951 | J34: 0.60269345 | K34: =J34-F34 -> 0.13892639 | L34: 0.098376658
B35: 6666110204 | C35: 6666110204 Amortization of license, trademarks and | D35: 6666110204 许可证、商标及摊销 | E35: 2.81415 | F35: =E35*1000/$G$28 -> 0.035303969 | G35: 32.15703 | H35: 0.27554332 | I35: 2.81415 | J35: 0.028830255 | K35: =J35-F35 -> -0.0064737145 | L35: -0.24671306
B36: 6666110207 | C36: 6666110207 Amortization of Software | D36: 6666110207 软件摊销 | E36: 35.04763 | F36: =E36*1000/$G$28 -> 0.43967822 | G36: 0 | H36: 0 | I36: 26.11824 | J36: 0.26757476 | K36: =J36-F36 -> -0.17210346 | L36: 0.26757476
B37: 6666110506 | C37: 6666110506 Amortization-Leasehold Improvement | D37: 6666110506 租赁改良摊销 | E37: 3.15121 | F37: =E37*1000/$G$28 -> 0.039532442 | G37: 0 | H37: 0 | I37: 3.08533 | J37: 0.031608425 | K37: =J37-F37 -> -0.0079240165 | L37: 0.031608425
B38: 6666110206 | C38: 6666110206 Amortization of Patents | D38: 6666110206 专利摊销 | E38: 0.07998 | F38: =E38*1000/$G$28 -> 0.0010033621 | G38: 0 | H38: 0 | I38: 0.13931 | J38: 0.0014271957 | K38: =J38-F38 -> 0.0004238336 | L38: 0.0014271957
B39: FIX | C39: * CS_Depreciation | D39: * CS_折旧 | E39: =SUM(E30:E38) -> 770.36882 | F39: =SUM(F30:F38) -> 9.6644021 | G39: 815.66693 | H39: 6.9891893 | I39: 818.33241 | J39: 8.3836085 | K39: =J39-F39 -> -1.2807936 | L39: 1.3944192
A40: 直接人工 | B40: 5001010205 | C40: 5001010205 Unemployment Insurance -blue collar-Dire | D40: 5001010205 失业保险-蓝领-直接 | E40: 8.97535 | F40: 0.11259723 | G40: 9.3776031 | H40: 0.080353684 | I40: 9.61211 | J40: 0.098473635 | K40: =J40-F40 -> -0.01412359 | L40: 0.018119951
B41: 6666010380 | C41: 6666010380 Incentive | D41: 6666010380 激励 | E41: -1.30793 | F41: -0.016408195 | G41: -24.916935 | H41: -0.21350525 | I41: -2.29638 | J41: -0.023525832 | K41: =J41-F41 -> -0.0071176376 | L41: 0.18997942
B42: 6666010019 | C42: 6666010019 Payroll Taxes - Blue Collar Direct | D42: 6666010019 工资税-蓝领直接 | E42: 72.82026 | F42: 0.913542 | G42: 97.292632 | H42: 0.83366947 | I42: 82.346 | J42: 0.84361394 | K42: =J42-F42 -> -0.069928064 | L42: 0.0099444634
B43: 6666010183 | C43: 6666010183 Overtime-Blue Collar-Direct | D43: 6666010183 加班费-蓝领-直接 | E43: 2.7937 | F43: 0.035047421 | G43: 0 | H43: 0 | I43: 13.27255 | J43: 0.13597392 | K43: =J43-F43 -> 0.1009265 | L43: 0.13597392
B44: 6666010229 | C44: 6666010229 Staff Leaving Indemnity - Blue Collar Di | D44: 6666010229 蓝领离职赔偿-直接 | E44: 42.73546 | F44: 0.53612329 | G44: 18.354393 | H44: 0.15727293 | I44: 23.0706 | J44: 0.23635246 | K44: =J44-F44 -> -0.29977083 | L44: 0.079079531
B45: 6666010188 | C45: 6666010188 Salary - Blue collar direct employees | D45: 6666010188 蓝领直接员工工资 | E45: 420.61737 | F45: 5.2767133 | G45: 477.61866 | H45: 4.0925616 | I45: 465.92913 | J45: 4.7733261 | K45: =J45-F45 -> -0.50338723 | L45: 0.68076441 | N45: 单台上涨0.68，费用下降1万欧
B46: 5102040406 | C46: 5102040406 Other revenue-Service/Secondment agreeme | D46: 5102040406 其他收入-服务/派遣协议 | E46: 0 | F46: 0 | G46: 0 | H46: 0 | I46: 0 | J46: 0 | K46: =J46-F46 -> 0 | L46: 0
B47: 6666010115 | C47: 6666010115 Salary-Blue collar direct employees-Accr | D47: 6666010115 蓝领直接员工工资-计提 | E47: -2.47577 | F47: -0.031058937 | G47: 0 | H47: 0 | I47: -1.52194 | J47: -0.01559189 | K47: =J47-F47 -> 0.015467047 | L47: -0.01559189
B48: VAR | C48: * CS_Direct Labour | D48: * CS_直接劳动 | E48: 544.15844 | F48: 6.8265561 | G48: 577.72635 | H48: 4.9503525 | I48: 590.41207 | J48: 6.0486223 | K48: =J48-F48 -> -0.77793382 | L48: 1.0982698
A49: 可回收废料 | B49: 8701530201 | C49: 8701530201 Scrap-Raw Material - Managerial | D49: 8701530201 废料-原材料-管理 | E49: 0 | F49: 0 | G49: 0 | H49: 0 | I49: 0 | J49: 0 | K49: =J49-F49 -> 0 | L49: 0
B50: 6666050309 | C50: 6666050309 SFG scrap | D50: 6666050309 SFG废料 | E50: 22.80459 | F50: 0.28608729 | G50: 0 | H50: 0 | I50: 39.44239 | J50: 0.40407731 | K50: =J50-F50 -> 0.11799002 | L50: 0.40407731
B51: 6666050308 | C51: 6666050308 Raw material scrap | D51: 6666050308 原材料废料 | E51: 7.00864 | F51: 0.087924528 | G51: 57.711166 | H51: 0.49450854 | I51: 7.41281 | J51: 0.075942363 | K51: =J51-F51 -> -0.011982165 | L51: -0.41856618
B52: 6666050306 | C52: 6666050306 Finished goods scrap | D52: 6666050306 完工产品废料 | E52: 0.19189 | F52: 0.0024072912 | G52: 0 | H52: 0 | I52: 0.65246 | J52: 0.0066842876 | K52: =J52-F52 -> 0.0042769964 | L52: 0.0066842876
B53: VAR | C53: * CS_SCRAP_VARIABLE | D53: * CS_ 废料_VARIABLE | E53: 30.00512 | F53: 0.37641911 | G53: 57.711166 | H53: 0.49450854 | I53: 47.50766 | J53: 0.48670396 | K53: =J53-F53 -> 0.11028485 | L53: -0.0078045866
A54: 组织运营 | B54: 5102010151 | C54: 5102010151 Other Rev.-Interco-Epidemic problem comp | D54: 5102010151 其他收入-集团间-疫情问题补偿 | E54: -8.9625 | F54: -0.11243602 | G54: 0 | H54: 0 | I54: 0 | J54: 0 | K54: =J54-F54 -> 0.11243602 | L54: 0
B55: 5001010200 | C55: 5001010200 Cost of Manufacture - Raw Material | D55: 5001010200 制造成本-原材料 | E55: 0.36849 | F55: 0.004622767 | G55: 0 | H55: 0 | I55: 0 | J55: 0 | K55: =J55-F55 -> -0.004622767 | L55: 0
B56: 5001010201 | C56: 5001010201 Cost of Manufacture - Raw Material-Freig | D56: 5001010201 制造成本-原材料-运费 | E56: 0.0012 | F56: 1.5054195e-05 | G56: 0 | H56: 0 | I56: 0 | J56: 0 | K56: =J56-F56 -> -1.5054195e-05 | L56: 0
B57: 5207000011 | C57: 5207000011 Gain of tangible asset disposal | D57: 5207000011 有形资产处置收益 | E57: 0 | F57: 0 | G57: 0 | H57: 0 | I57: 0 | J57: 0 | K57: =J57-F57 -> 0 | L57: 0
B58: 5207000012 | C58: 5207000012 Loss of tangible asset sold | D58: 5207000012 出售有形资产损失 | E58: 0 | F58: 0 | G58: 0 | H58: 0 | I58: 0 | J58: 0 | K58: =J58-F58 -> 0 | L58: 0
B59: 5207000022 | C59: 5207000022 Loss of intangible asset disposal | D59: 5207000022 无形资产处置损失 | E59: 0 | F59: 0 | G59: 0 | H59: 0 | I59: 0 | J59: 0 | K59: =J59-F59 -> 0 | L59: 0
B60: 5301060000 | C60: 5301060000 Other Income-Subsidy income | D60: 5301060000 其他收入-补贴收入 | E60: -1.44101 | F60: -0.018077705 | G60: 0 | H60: 0 | I60: -2.60045 | J60: -0.026640952 | K60: =J60-F60 -> -0.0085632476 | L60: -0.026640952
B61: 5301999999 | C61: 5301999999 Non-operation revenue-Other | D61: 5301999999 非经营收入-其他 | E61: 0 | F61: 0 | G61: 0 | H61: 0 | I61: 0 | J61: 0 | K61: =J61-F61 -> 0 | L61: 0
B62: 5405030000 | C62: 5405030000 Other cost-others | D62: 5405030000 其他成本-其他 | E62: 0.04414 | F62: 0.00055374348 | G62: 0 | H62: 0 | I62: 0.00022 | J62: 2.2538443e-06 | K62: =J62-F62 -> -0.00055148963 | L62: 2.2538443e-06
B63: 5601050000 | C63: 5601050000 Non-Operating Expense - Penalty | D63: 5601050000 非经营费用-罚款 | E63: 0 | F63: 0 | G63: 0 | H63: 0 | I63: 0 | J63: 0 | K63: =J63-F63 -> 0 | L63: 0
B64: 5601050100 | C64: 5601050100 Non-operation Expense-Others | D64: 5601050100 非经营费用-其他 | E64: 0.03604 | F64: 0.00045212766 | G64: 0 | H64: 0 | I64: 0 | J64: 0 | K64: =J64-F64 -> -0.00045212766 | L64: 0
B65: 5102040893 | C65: 5102040893 Other revenue-Charge out-Test Expense | D65: 5102040893 其他收入-费用支出-测试费用 | E65: 0 | F65: 0 | G65: 0 | H65: 0 | I65: 0 | J65: 0 | K65: =J65-F65 -> 0 | L65: 0
B66: 5801000041 | C66: 5801000041 Previous year Sundry cost | D66: 5801000041 前一年杂项成本 | E66: 0 | F66: 0 | G66: 0 | H66: 0 | I66: 0 | J66: 0 | K66: =J66-F66 -> 0 | L66: 0
... B74: 6666020302 | C74: 6666020302 Communication Expenses | D74: 6666020302 通讯费用 | E74: 0 | F74: 0 | G74: 1.2307179 | H74: 0.010545628 | I74: 0 | J74: 0 | K74: =J74-F74 -> 0 | L74: -0.010545628
B75: 6666020403 | C75: 6666020403 Company car expense | D75: 6666020403 公司车辆费用 | E75: 0 | F75: 0 | G75: 0 | H75: 0 | I75: 0 | J75: 0 | K75: =J75-F75 -> 0 | L75: 0
B76: 6666020405 | C76: 6666020405 Company car expense - maintenance fees | D76: 6666020405 公司车辆费用-维护费 | E76: 0 | F76: 0 | G76: 0 | H76: 0 | I76: 0 | J76: 0 | K76: =J76-F76 -> 0 | L76: 0
B77: 6666020495 | C77: 6666020495 Non-deductible expense-travel. | D77: 6666020495 不可抵扣费用-旅行 | E77: 0.07849 | F77: 0.00098466981 | G77: 0 | H77: 0 | I77: 0.14395 | J77: 0.0014747313 | K77: =J77-F77 -> 0.00049006152 | L77: 0.0014747313
B78: 6666020504 | C78: 6666020504 Newspaper and Periodicals expenditure | D78: 6666020504 报纸和期刊支出 | E78: 0 | F78: 0 | G78: 0 | H78: 0 | I78: 0 | J78: 0 | K78: =J78-F78 -> 0 | L78: 0
B79: 6666020508 | C79: 6666020508 Postage | D79: 6666020508 邮资 | E79: 0 | F79: 0 | G79: 0 | H79: 0 | I79: 0 | J79: 0 | K79: =J79-F79 -> 0 | L79: 0
B80: 6666020602 | C80: 6666020602 Training costs Outside the group | D80: 6666020602 集团外培训费用 | E80: 0 | F80: 0 | G80: 0.40272949 | H80: 0.0034508603 | I80: 0 | J80: 0 | K80: =J80-F80 -> 0 | L80: -0.0034508603
B81: 6666020701 | C81: 6666020701 Enterprise Property Insurance | D81: 6666020701 企业财产保险 | E81: 0 | F81: 0 | G81: 0 | H81: 0 | I81: 0 | J81: 0 | K81: =J81-F81 -> 0 | L81: 0
B82: 6666020802 | C82: 6666020802 Equipment rental cost | D82: 6666020802 设备租赁费用 | E82: 23.481 | F82: 0.29457296 | G82: 20.409 | H82: 0.1748782 | I82: 21.109 | J82: 0.21625636 | K82: =J82-F82 -> -0.078316598 | L82: 0.041378165
B83: 6666020803 | C83: 6666020803 Car rental cost | D83: 6666020803 汽车租赁费用 | E83: 9.5524 | F83: 0.11983641 | G83: 3.4624602 | H83: 0.029668715 | I83: 6.59518 | J83: 0.067565951 | K83: =J83-F83 -> -0.052270461 | L83: 0.037897235
B84: 6666021100 | C84: 6666021100 Consulting fees | D84: 6666021100 咨询费 | E84: 18.85796 | F84: 0.23657617 | G84: 17.686151 | H84: 0.15154698 | I84: 7.22893 | J84: 0.074058559 | K84: =J84-F84 -> -0.16251762 | L84: -0.077488418
B85: 6666021104 | C85: 6666021104 Consulting expense-Technical | D85: 6666021104 咨询费用-技术 | E85: 0 | F85: 0 | G85: 0 | H85: 0 | I85: 0 | J85: 0 | K85: =J85-F85 -> 0 | L85: 0
B86: 6666021902 | C86: 6666021902 Cleaning fees | D86: 6666021902 清洁费 | E86: 17.23454 | F86: 0.21621011 | G86: 10.882541 | H86: 0.093249013 | I86: 7.84995 | J86: 0.080420752 | K86: =J86-F86 -> -0.13578935 | L86: -0.012828261
B87: 6666022100 | C87: 6666022100 Security | D87: 6666022100 安全 | E87: 15.40124 | F87: 0.19321106 | G87: 13.76681 | H87: 0.1179634 | I87: 14.06269 | J87: 0.1440687 | K87: =J87-F87 -> -0.049142359 | L87: 0.026105305
... B100: 5401020212 | C100: 5401020212 Local Transpor | D100: 5401020212 本地运输 | E100: 0 | F100: 0 | G100: 0 | H100: 0 | I100: 0 | J100: 0 | K100: =J100-F100 -> 0 | L100: 0
B101: 6666050320 | C101: 6666050320 Reworking costs | D101: 6666050320 再加工成本 | E101: -0.03197 | G101: 0 | I101: 0 | J101: 0 | K101: =J101-F101 -> 0 | L101: 0
B102: 6666093800 | C102: 6666093800 Other Taxes-CIT Deductible | D102: 6666093800 其他税项-可抵扣公司税 | E102: 0 | G102: 0 | I102: 0 | J102: 0 | K102: =J102-F102 -> 0 | L102: 0
B103: 5601080000 | C103: 5601080000 Non-operating expense-VAT non-deductible | D103: 5601080000 非经营性支出-不可抵扣增值税 | E103: 0 | G103: 0 | I103: 0 | J103: 0 | K103: =J103-F103 -> 0 | L103: 0
B104: 6666040215 | C104: 6666040215 Product sample fee | D104: 6666040215 产品样品费用 | E104: 0 | G104: 0 | I104: 0 | J104: 0 | K104: =J104-F104 -> 0 | L104: 0
B105: 6666020403 | C105: 6666020403 Company car expense | D105: 6666020403 公司车辆费用 | E105: 0 | G105: 0 | I105: 0 | J105: 0 | K105: =J105-F105 -> 0 | L105: 0
B106: 6666021200 | C106: 6666021200 Audit fee | D106: 6666021200 审计费用 | E106: 0 | G106: 0 | I106: 0 | J106: 0 | K106: =J106-F106 -> 0 | L106: 0
B107: 6666050202 | C107: 6666050202 Custom clearance charge | D107: 6666050202 海关清关费用 | E107: 0 | G107: 0 | I107: 0 | J107: 0 | K107: =J107-F107 -> 0 | L107: 0
B108: 5401050201 | C108: 5401050201 COGS-Freight out-Special and sporadic fr | D108: 5401050201 COGS-特殊和零星运费 | E108: 0 | G108: 0 | I108: 0 | J108: 0 | K108: =J108-F108 -> 0 | L108: 0
B109: 6666020801 | C109: 6666020801 Housing rental cost | D109: 6666020801 房屋租赁成本 | I109: 1 | J109: 0.010244747 | K109: =J109-F109 -> 0.010244747 | L109: 0.010244747
B110: FIX | C110: * CS_Fix Cost | D110: * CS_Fix Cost | E110: 95.78168 | F110: 1.2015967 | G110: 97.661745 | H110: 0.83683229 | I110: 71.65609 | J110: 0.73409851 | K110: =J110-F110 -> -0.46749823 | L110: -0.10273377 | M110: =E110-I110 -> 24.12559
A111: 生产耗用 | B111: 6666110203 | C111: 6666110203 Low value consumables | D111: 6666110203 低值易耗品 | E111: -3.03086 | F111: -0.038022631 | G111: 41.201085 | H111: 0.35303894 | I111: 17.84576 | J111: 0.1828253 | K111: =J111-F111 -> 0.22084793 | L111: -0.17021364
B112: 5102040000 | C112: 5102040000 Other Revenue - Other | D112: 5102040000 其他收入-其他 | E112: 0 | F112: 0 | G112: 0 | H112: 0 | I112: 0 | J112: 0 | K112: =J112-F112 -> 0 | L112: 0
B113: 6666050307 | C113: 6666050307 Inventory count different-raw material | D113: 6666050307 存货盘点差异-原材料 | E113: -5.93365 | F113: -0.074438604 | G113: 0 | H113: 0 | I113: -10.07647 | J113: -0.10323089 | K113: =J113-F113 -> -0.028792282 | L113: -0.10323089
B114: 6666050312 | C114: 6666050312 Inventory count different- Semifinished | D114: 6666050312 存货盘点差异-半成品 | E114: 2.78414 | F114: 0.034927489 | G114: 0 | H114: 0 | I114: 1.28948 | J114: 0.013210396 | K114: =J114-F114 -> -0.021717093 | L114: 0.013210396
B115: VAR | C115: * CS_Variable Cost | D115: * CS_Variable Cost | E115: -6.18037 | F115: -0.077533746 | G115: 41.201085 | H115: 0.35303894 | I115: 9.05877 | J115: 0.092804807 | K115: =J115-F115 -> 0.17033855 | L115: -0.26023413
A116: 存货跌价准备 | B116: 6666100203 | C116: 6666100203 Provision for inventory devaluation - RM | D116: 6666100203 存货减值准备-原材料 | E116: 34.84363 | F116: 0.437119 | G116: 12.5 | H116: 0.10710851 | I116: 12.5 | J116: 0.12805934 | K116: =J116-F116 -> -0.30905967 | L116: 0.020950832
B117: FIX | C117: * CS_Obsolescence | D117: * CS_Obsolescence | E117: 34.84363 | F117: 0.437119 | G117: 12.5 | H117: 0.10710851 | I117: 12.5 | J117: 0.12805934 | K117: =J117-F117 -> -0.30905967 | L117: 0.020950832
A118: 废品回收 | B118: 5301070000 | C118: 5301070000 Non-operation revenue-sales of scrapped | D118: 5301070000 非经营收入-废品销售 | E118: -36.41102 | F118: -0.45678217 | G118: -86.744226 | H118: -0.74328356 | I118: -65.75498 | J118: -0.67364313 | K118: =J118-F118 -> -0.21686097 | L118: 0.069640423
B119: VAR | C119: * CS_Reselling | D119: * CS_Reselling | E119: -36.41102 | F119: -0.45678217 | G119: -86.744226 | H119: -0.74328356 | I119: -65.75498 | J119: -0.67364313 | K119: =J119-F119 -> -0.21686097 | L119: 0.069640423
...

Sheet 厨电2月 
A1: 总结： 2月同期36.8欧元/台，实际单台费用22.1元/台，较同期↓39.8%；降费155.7万欧 变动： 直接人工离职补偿30人费用合计，单台影响0.94欧 福利费用差异11.2万欧，为6.1万欧工会福利费谈判后上涨，其中5.1万欧为释放预提
A2: 维度 | B2: KPI | C2: 25年实际 | D2: 26年预算 | E2: 26年实际 | F2: 预算差异 | G2: 实际比同期差异 | H2: 制造费差额 | I2: 差异原因
A3: 单 | B3: 产量 | C3: 79712 | D3: 116204 | E3: 106294 | F3: =E3-D3 -> -9910 | G3: =E3-C3 -> 26582 | H3: / | J3: =(E3-D3)/D3 -> -0.085281057
A4: 时 | B4: 工作天数 | C4: 20 | D4: 20 | E4: 20 | F4: =E4-D4 -> 0 | G4: =E4-C4 -> 0
A5: 人 | B5: 直接人工 | C5: 296 | D5: 317 | E5: 294 | F5: =E5-D5 -> -23 | G5: =E5-C5 -> -2
B6: 人工工资 | C6: =F49*1000/C5 -> 1584.5274 | D6: =H49*1000/D5 -> 2122.1951 | E6: =618/E5*1000 -> 2102.0408 | F6: =E6-D6 -> -20.154298 | G6: =E6-C6 -> 517.51342
B7: 间接人工 | C7: 181 | D7: 136 | E7: 127 | F7: =E7-D7 -> -9 | G7: =E7-C7 -> -54
B8: 间接人工工资 | C8: =F134*1000/C7 -> 1979.0352 | D8: =H134*1000/D7 -> 2493.3963 | E8: =J134*1000/E7 -> 2437.8975 | F8: =E8-D8 -> -55.498823 | G8: =E8-C8 -> 458.86229
B9: 白领人数 | C9: 58 | D9: 34 | E9: 31 | F9: =E9-D9 -> -3 | G9: =E9-C9 -> -27
B10: 白领人工工资 | C10: =F142*1000/C9 -> 3333.6203 | D10: =H142*1000/D9 -> 4782.8924 | E10: =J142*1000/E9 -> 5013.6442 | F10: =E10-D10 -> 230.75179 | G10: =E10-C10 -> 1680.0238
A11: 效 | B11: UPPH | C11: =C3/C4/C5 -> 13.464865 | D11: =D3/D4/D5 -> 18.328707 | E11: =E3/E4/E5 -> 18.077211 | F11: =E11-D11 -> -0.25149574 | G11: =E11-C11 -> 4.612346
A12: 费 | B12: 单台制造费 | C12: =SUM(C13:C25) -> 32.790782 | D12: =SUM(D13:D25) -> 22.807982 | E12: =SUM(E13:E25) -> 22.115933 | F12: =E12-D12 -> -0.69204871 | G12: =E12-C12 -> -10.674849 | H12: =G12*E3 -> -1134672.4
B13: 折旧 | C13: 9.03 | D13: 6.7092041 | E13: 5.7670235 | F13: =E13-D13 -> -0.94218056 | G13: =E13-C13 -> -3.2629765 | H13: =G13*$E$3 -> -346834.82
B14: 运营费 | C14: 1.3241945 | D14: 0.9895902 | E14: 0.95019474 | F14: =E14-D14 -> -0.039395454 | G14: =E14-C14 -> -0.37399976 | H14: =G14*$E$3 -> -39753.931
B15: 存货跌价准备 | C15: 0.35143755 | D15: 0.10756945 | E15: 0 | F15: =E15-D15 -> -0.10756945 | G15: =E15-C15 -> -0.35143755 | H15: =G15*$E$3 -> -37355.703
B16: 固定能源费 | C16: 0.4284247 | D16: 0.28057364 | E16: 0.25401246 | F16: =E16-D16 -> -0.026561182 | G16: =E16-C16 -> -0.17441224 | H16: =G16*$E$3 -> -18538.975
B17: 间接人工成本-辅助人员 | C17: 4.3627717 | D17: 2.9181603 | E17: 2.9127983 | F17: =E17-D17 -> -0.0053620045 | G17: =E17-C17 -> -1.4499734 | H17: =G17*$E$3 -> -154123.47
B18: 固定人工-白领 | C18: 2.3549112 | D18: 1.3994212 | E18: 1.4621989 | F18: =E18-D18 -> 0.062777697 | G18: =E18-C18 -> -0.89271225 | H18: =G18*$E$3 -> -94889.956
B19: 半固定-班车/工作服 | C19: 2.6847029 | D19: 1.8786839 | E19: 2.8491931 | F19: =E19-D19 -> 0.97050922 | G19: =E19-C19 -> 0.16449021 | H19: =G19*$E$3 -> 17484.322
B20: 直接人工 | C20: 5.7124427 | D20: 5.7892659 | E20: 5.8140629 | F20: =E20-D20 -> 0.024797012 | G20: =E20-C20 -> 0.10162016 | H20: =G20*$E$3 -> 10801.613
B21: 可回收废料 | C21: 0.39080799 | D21: 0.60667009 | E21: 0.49861704 | F21: =E21-D21 -> -0.10805304 | G21: =E21-C21 -> 0.10780905 | H21: =G21*$E$3 -> 11459.456
B22: 生产耗用品 | C22: -0.066185738 | D22: 0.27739662 | E22: 0.25401246 | F22: =E22-D22 -> -0.023384168 | G22: =E22-C22 -> 0.32019819 | H22: =G22*$E$3 -> 34035.147
B23: 废品回收 | C23: -0.46684611 | D23: -0.7495329 | E23: -0.80907671 | F23: =E23-D23 -> -0.05954381 | G23: =E23-C23 -> -0.3422306 | H23: =G23*$E$3 -> -36377.059
B24: 变动能源费 | C24: 0.50243676 | D24: 0.74894869 | E24: 0.43150733 | F24: =E24-D24 -> -0.31744137 | G24: =E24-C24 -> -0.070929429 | H24: =G24*$E$3 -> -7539.3727
B25: 园区分摊费用 | C25: 6.1816841 | D25: 1.8520307 | E25: 1.7313891 | F25: =E25-D25 -> -0.12064161 | G25: =E25-C25 -> -4.450295 | H25: =G25*$E$3 -> -473039.66
B26: IT Expense-Internal Charge Out | C26: 3.0793272 | D26: 0.81726877 | E26: 0.89547698 | F26: =E26-D26 -> 0.07820821 | G26: =E26-C26 -> -2.1838502
B27: Association dues | C27: 0.10600402 | D27: 0.055005448 | E27: 0.022996406 | F27: -0.032009042 | G27: -0.083007613
B28: G&A | C28: 2.9963528 | D28: 0.97975646 | E28: 0.81291569 | F28: -0.16684078 | G28: -2.1834372
B29: Type 类型 | C29: Code 编码 | D29: Description(EN) 描述 | E29: Description(CN) 描述 | F29: 单位千欧 | G29: 同期台数 | H29: 82105 | I29: 预算台数 | J29: 116204 | K29: 实际台数 | L29: 106294
F30: MFG 2025 同期制造费 | G30: CPU 2025 同期单台 | H30: Budget 2026 预算 | I30: Budget-CPU 2026 单台预算 | J30: ACT 2026 实际 | K30: ACT-CPU 2026 单台实际 | L30: CPU-Y0Y 单台同期 | M30: Budget-ACT VARIANCE 预算同比 | N30: CPU-Y0Y Analysis 单台同期分析 | O30: Budget-ACT VARIANCE Analysis 预算实际分析
B31: 折旧 | C31: 6666110101 | D31: 6666110101 Depreciation of buildings | E31: 建筑物折旧 | F31: 66.46563 | G31: =F31*1000/$H$29 -> 0.80951988 | H31: 67.063126 | I31: 0.57711547 | J31: 61.69588 | K31: 0.58042674 | L31: =K31-G31 -> -0.22909314 | M31: 0.0033112752
C32: 6666110106 | D32: 6666110106 Depreciation of R&D facilities | E32: 研发设施折旧 | F32: 0 | G32: =F32*1000/$H$29 -> 0 | H32: 0 | I32: 0 | J32: 0 | K32: 0 | L32: =K32-G32 -> 0 | M32: 0
C33: 6666110107 | D33: 6666110107 Depreciation of mold | E33: 模具折旧 | F33: 205.33288 | G33: =F33*1000/$H$29 -> 2.5008572 | H33: 200.43546 | I33: 1.7248586 | J33: 138.62046 | K33: 1.3041231 | L33: =K33-G33 -> -1.1967341 | M33: -0.42073547
C34: 6666110110 | D34: 6666110110 Depreciation-Plant & Machinery | E34: 6666110110 折旧-厂房及机械 | F34: 392.86982 | G34: =F34*1000/$H$29 -> 4.7849683 | H34: 423.32463 | I34: 3.6429437 | J34: 331.39545 | K34: 3.1177249 | L34: =K34-G34 -> -1.6672434 | M34: -0.52521884 | O34: 单台下降0.53，费用下降9万欧
C35: 6666110112 | D35: 6666110112 Depreciation of Furniture & Fixture | E35: 6666110112 家具及装置折旧 | F35: 37.32028 | G35: =F35*1000/$H$29 -> 0.45454333 | H35: 57.029978 | I35: 0.49077466 | J35: 53.90234 | K35: 0.50710614 | L35: =K35-G35 -> 0.052562811 | M35: 0.016331481
C36: 6666110204 | D36: 6666110204 Amortization of license, trademarks and | E36: 6666110204 许可证、商标及摊销 | F36: 2.81412 | G36: =F36*1000/$H$29 -> 0.034274648 | H36: 31.78315 | I36: 0.27351167 | J36: 2.81412 | K36: 0.026474872 | L36: =K36-G36 -> -0.0077997767 | M36: -0.2470368
C37: 6666110207 | D37: 6666110207 Amortization of Software | E37: 6666110207 软件摊销 | F37: 33.76611 | G37: =F37*1000/$H$29 -> 0.41125522 | H37: 0 | I37: 0 | J37: 27.8339 | K37: 0.26185768 | L37: =K37-G37 -> -0.14939754 | M37: 0.26185768
C38: 6666110506 | D38: 6666110506 Amortization-Leasehold Improvement | E38: 6666110506 租赁改良摊销 | F38: 2.8597 | G38: =F38*1000/$H$29 -> 0.034829791 | H38: 0 | I38: 0 | J38: -3.08533 | K38: -0.02902638 | L38: =K38-G38 -> -0.063856171 | M38: -0.02902638
C39: 6666110206 | D39: 6666110206 Amortization of Patents | E39: 6666110206 专利摊销 | G39: =F39*1000/$H$29 -> 0 | H39: 0 | I39: 0 | J39: -0.02065 | K39: -0.00019427249 | L39: =K39-G39 -> -0.00019427249 | M39: -0.00019427249
C40: FIX | D40: * CS_Depreciation | E40: * CS_折旧 | F40: =SUM(F31:F39) -> 741.42854 | G40: =SUM(G31:G39) -> 9.0302483 | H40: 779.63635 | I40: 6.7092041 | J40: 613.15617 | K40: 5.7684928 | L40: =K40-G40 -> -3.2617556 | M40: -0.94071133
B41: 直接人工 | C41: 5001010205 | D41: 5001010205 Unemployment Insurance -blue collar-Dire | E41: 5001010205 失业保险-蓝领-直接 | F41: 9.03413 | G41: 0.11003142 | H41: 10.984805 | I41: 0.094530348 | J41: 8.93104 | K41: 0.084022052 | L41: =K41-G41 -> -0.026009371 | M41: -0.010508296
C42: 6666010380 | D42: 6666010380 Incentive | E42: 6666010380 激励 | F42: -1.74248 | G42: -0.021222581 | H42: -28.871917 | I42: -0.24845889 | J42: -2.19199 | K42: -0.020621954 | L42: =K42-G42 -> 0.00060062664 | M42: 0.22783693
C43: 6666010019 | D43: 6666010019 Payroll Taxes - Blue Collar Direct | E43: 6666010019 工资税-蓝领直接 | F43: 73.09674 | G43: 0.89028366 | H43: 113.96735 | I43: 0.98075236 | J43: 76.79845 | K43: 0.72250974 | L43: =K43-G43 -> -0.16777392 | M43: -0.25824263
C44: 6666010183 | D44: 6666010183 Overtime-Blue Collar-Direct | E44: 6666010183 加班费-蓝领-直接 | F44: 5.75887 | G44: 0.070140308 | H44: 0 | I44: 0 | J44: 22.61471 | K44: 0.21275622 | L44: =K44-G44 -> 0.14261592 | M44: 0.21275622
C45: 6666010229 | D45: 6666010229 Staff Leaving Indemnity - Blue Collar Di | E45: 6666010229 蓝领离职赔偿-直接 | F45: -48.92735 | G45: -0.59591194 | H45: 18.012162 | I45: 0.15500466 | J45: 116.24877 | K45: 1.0936532 | L45: =K45-G45 -> 1.6895651 | M45: 0.93864851 | N45: 离职赔偿30人 | O45: 单台上涨0.94欧，费用上涨10万欧
C46: 6666010188 | D46: 6666010188 Salary - Blue collar direct employees | E46: 6666010188 蓝领直接员工工资 | F46: 432.01008 | G46: 5.2616781 | H46: 558.64345 | I46: 4.8074374 | J46: 395.30928 | K46: 3.7190178 | L46: =K46-G46 -> -1.5426603 | M46: -1.0884196 | O46: 单台下降1.09，费用下降16万欧
C47: 5102040406 | D47: 5102040406 Other revenue-Service/Secondment agreeme | E47: 5102040406 其他收入-服务/派遣协议 | F47: 0 | G47: 0 | H47: 0 | I47: 0 | J47: 0 | K47: 0 | L47: =K47-G47 -> 0 | M47: 0
C48: 6666010115 | D48: 6666010115 Salary-Blue collar direct employees-Accr | E48: 6666010115 蓝领直接员工工资-计提 | F48: -0.20988 | G48: -0.002556239 | H48: 0 | I48: 0 | J48: 0.18412 | K48: 0.0017321768 | L48: =K48-G48 -> 0.0042884158 | M48: 0.0017321768
C49: VAR | D49: * CS_Direct Labour | E49: * CS_直接劳动 | F49: 469.02011 | G49: 5.7124427 | H49: 672.73585 | I49: 5.7892659 | J49: 617.89438 | K49: 5.8130692 | L49: =K49-G49 -> 0.1006265 | M49: 0.023803353
B50: 可回收废料 | C50: 8701530201 | D50: 8701530201 Scrap-Raw Material - Managerial | E50: 8701530201 废料-原材料-管理 | F50: 0 | G50: 0 | H50: 0 | I50: 0 | J50: 0 | K50: 0 | L50: =K50-G50 -> 0 | M50: 0
C51: 6666050309 | D51: 6666050309 SFG scrap | E51: 6666050309 SFG废料 | F51: 20.0357 | G51: 0.24402533 | H51: 0 | I51: 0 | J51: 36.98318 | K51: 0.3479329 | L51: =K51-G51 -> 0.10390757 | M51: 0.3479329
C52: 6666050308 | D52: 6666050308 Raw material scrap | E52: 6666050308 原材料废料 | F52: 11.07537 | G52: 0.13489276 | H52: 70.497491 | I52: 0.60667009 | J52: 16.07373 | K52: 0.15121954 | L52: =K52-G52 -> 0.016326783 | M52: -0.45545054
C53: 6666050306 | D53: 6666050306 Finished goods scrap | E53: 6666050306 完工产品废料 | F53: 0.97622 | G53: 0.011889897 | H53: 0 | I53: 0 | J53: 0.08533 | K53: 0.00080277344 | L53: =K53-G53 -> -0.011087124 | M53: 0.00080277344
C54: VAR | D54: * CS_SCRAP_VARIABLE | E54: * CS_ 废料_VARIABLE | F54: 32.08729 | G54: 0.39080799 | H54: 70.497491 | I54: 0.60667009 | J54: 53.14224 | K54: 0.49995522 | L54: =K54-G54 -> 0.10914723 | M54: -0.10671487
B55: 组织运营 | C55: 5102010151 | D55: 5102010151 Other Rev.-Interco-Epidemic problem comp | E55: 5102010151 其他收入-集团间-疫情问题补偿 | F55: 0 | G55: 0 | H55: 0 | I55: 0 | J55: 0 | K55: 0 | L55: =K55-G55 -> 0 | M55: 0
C56: 5001010200 | D56: 5001010200 Cost of Manufacture - Raw Material | E56: 5001010200 制造成本-原材料 | F56: 1.02854 | G56: 0.01252713 | H56: 0 | I56: 0 | J56: 0 | K56: 0 | L56: =K56-G56 -> -0.01252713 | M56: 0
C57: 5001010201 | D57: 5001010201 Cost of Manufacture - Raw Material-Freig | E57: 5001010201 制造成本-原材料-运费 | F57: 0 | G57: 0 | H57: 0 | I57: 0 | J57: 0 | K57: 0 | L57: =K57-G57 -> 0 | M57: 0
C58: 5207000011 | D58: 5207000011 Gain of tangible asset disposal | E58: 5207000011 有形资产处置收益 | F58: 0 | G58: 0 | H58: 0 | I58: 0 | J58: 0 | K58: 0 | L58: =K58-G58 -> 0 | M58: 0
C59: 5207000012 | D59: 5207000012 Loss of tangible asset sold | E59: 5207000012 出售有形资产损失 | F59: 0 | G59: 0 | H59: 0 | I59: 0 | J59: 0 | K59: 0 | L59: =K59-G59 -> 0 | M59: 0
C60: 5207000022 | D60: 5207000022 Loss of intangible asset disposal | E60: 5207000022 无形资产处置损失 | F60: 0 | G60: 0 | H60: 0 | I60: 0 | J60: 0 | K60: 0 | L60: =K60-G60 -> 0 | M60: 0
C61: 5301060000 | D61: 5301060000 Other Income-Subsidy income | E61: 5301060000 其他收入-补贴收入 | F61: 0 | G61: 0 | H61: 0 | I61: 0 | J61: 0 | K61: 0 | L61: =K61-G61 -> 0 | M61: 0
C62: 5301999999 | D62: 5301999999 Non-operation revenue-Other | E62: 5301999999 非经营收入-其他 | F62: 0 | G62: 0 | H62: 0 | I62: 0 | J62: -0.44035 | K62: -0.004142755 | L62: =K62-G62 -> -0.004142755 | M62: -0.004142755
C63: 5405030000 | D63: 5405030000 Other cost-others | E63: 5405030000 其他成本-其他 | F63: 2e-05 | G63: 2.4359052e-07 | H63: 0 | I63: 0 | J63: -0.00022 | K63: -2.0697311e-06 | L63: =K63-G63 -> -2.3133216e-06 | M63: -2.0697311e-06
C64: 5601050000 | D64: 5601050000 Non-Operating Expense - Penalty | E64: 5601050000 非经营费用-罚款 | F64: 0 | G64: 0 | H64: 0 | I64: 0 | J64: 0 | K64: 0 | L64: =K64-G64 -> 0 | M64: 0
C65: 5601050100 | D65: 5601050100 Non-operation Expense-Others | E65: 5601050100 非经营费用-其他 | F65: 0 | G65: 0 | H65: 0 | I65: 0 | J65: 0 | K65: 0 | L65: =K65-G65 -> 0 | M65: 0
C66: 5102040893 | D66: 5102040893 Other revenue-Charge out-Test Expense | E66: 5102040893 其他收入-费用支出-测试费用 | F66: 0 | G66: 0 | H66: 0 | I66: 0 | J66: 0 | K66: 0 | L66: =K66-G66 -> 0 | M66: 0
C67: 5801000041 | D67: 5801000041 Previous year Sundry cost | E67: 5801000041 前一年杂项成本 | F67: 0 | G67: 0 | H67: 0 | I67: 0 | J67: 0 | K67: 0 | L67: =K67-G67 -> 0 | M67: 0
... C75: 6666020302 | D75: 6666020302 Communication Expenses | E75: 6666020302 通讯费用 | F75: 0 | G75: 0 | H75: 1.2077702 | I75: 0.010393534 | J75: 1.22327 | K75: 0.011508364 | L75: =K75-G75 -> 0.011508364 | M75: 0.0011148296
C76: 6666020403 | D76: 6666020403 Company car expense | E76: 6666020403 公司车辆费用 | F76: 0 | G76: 0 | H76: 0 | I76: 0 | J76: 0 | K76: 0 | L76: =K76-G76 -> 0 | M76: 0
C77: 6666020405 | D77: 6666020405 Company car expense - maintenance fees | E77: 6666020405 公司车辆费用-维护费 | F77: 0 | G77: 0 | H77: 0 | I77: 0 | J77: 0 | K77: 0 | L77: =K77-G77 -> 0 | M77: 0
C78: 6666020495 | D78: 6666020495 Non-deductible expense-travel. | E78: 6666020495 不可抵扣费用-旅行 | F78: 0.12338 | G78: 0.0015027099 | H78: 0 | I78: 0 | J78: 0.09931 | K78: 0.00093429544 | L78: =K78-G78 -> -0.0005684145 | M78: 0.00093429544
C79: 6666020504 | D79: 6666020504 Newspaper and Periodicals expenditure | E79: 6666020504 报纸和期刊支出 | F79: 0 | G79: 0 | H79: 0 | I79: 0 | J79: 0 | K79: 0 | L79: =K79-G79 -> 0 | M79: 0
C80: 6666020508 | D80: 6666020508 Postage | E80: 6666020508 邮资 | F80: 0 | G80: 0 | H80: 0 | I80: 0 | J80: 0.01908 | K80: 0.00017950214 | L80: =K80-G80 -> 0.00017950214 | M80: 0.00017950214
C81: 6666020602 | D81: 6666020602 Training costs Outside the group | E81: 6666020602 集团外培训费用 | F81: 0 | G81: 0 | H81: 0.39522031 | I81: 0.0034010904 | J81: 0.10889 | K81: 0.0010244228 | L81: =K81-G81 -> 0.0010244228 | M81: -0.0023766675
C82: 6666020701 | D82: 6666020701 Enterprise Property Insurance | E82: 6666020701 企业财产保险 | F82: 0 | G82: 0 | H82: 0 | I82: 0 | J82: 0 | K82: 0 | L82: =K82-G82 -> 0 | M82: 0
C83: 6666020802 | D83: 6666020802 Equipment rental cost | E83: 6666020802 设备租赁费用 | F83: 23.481 | G83: 0.28598746 | H83: 20.409 | I83: 0.17563079 | J83: 20.409 | K83: 0.19200519 | L83: =K83-G83 -> -0.093982262 | M83: 0.016374406
C84: 6666020803 | D84: 6666020803 Car rental cost | E84: 6666020803 汽车租赁费用 | F84: 8.84227 | G84: 0.10769466 | H84: 3.3979001 | I84: 0.029240819 | J84: 4.40212 | K84: 0.041414567 | L84: =K84-G84 -> -0.066280092 | M84: 0.012173748
C85: 6666021100 | D85: 6666021100 Consulting fees | E85: 6666021100 咨询费 | F85: 10.97186 | G85: 0.13363206 | H85: 17.35638 | I85: 0.14936129 | J85: 16.15981 | K85: 0.15202937 | L85: =K85-G85 -> 0.018397315 | M85: 0.0026680773
C86: 6666021104 | D86: 6666021104 Consulting expense-Technical | E86: 6666021104 咨询费用-技术 | F86: 0 | G86: 0 | H86: 0 | I86: 0 | J86: 0 | K86: 0 | L86: =K86-G86 -> 0 | M86: 0
C87: 6666021902 | D87: 6666021902 Cleaning fees | E87: 6666021902 清洁费 | F87: 15.39197 | G87: 0.1874669 | H87: 10.679628 | I87: 0.091904131 | J87: 11.28762 | K87: 0.10619245 | L87: =K87-G87 -> -0.081274455 | M87: 0.014288317
C88: 6666022100 | D88: 6666022100 Security | E88: 6666022100 安全 | F88: 17.93764 | G88: 0.21847196 | H88: 13.510118 | I88: 0.11626207 | J88: 12.28846 | K88: 0.11560822 | L88: =K88-G88 -> -0.10286374 | M88: -0.00065385347
... C101: 5401020212 | D101: 5401020212 Local Transpor | E101: 5401020212 本地运输 | F101: 0 | G101: 0 | H101: 0 | I101: 0 | J101: 0 | K101: 0 | L101: =K101-G101 -> 0 | M101: 0
C102: 6666050320 | D102: 6666050320 Reworking costs | E102: 6666050320 再加工成本 | F102: -0.04453 | H102: 0 | J102: 0 | K102: 0 | L102: =K102-G102 -> 0 | M102: 0
C103: 6666093800 | D103: 6666093800 Other Taxes-CIT Deductible | E103: 6666093800 其他税项-可抵扣公司税 | F103: 0 | H103: 0 | J103: 0 | K103: 0 | L103: =K103-G103 -> 0 | M103: 0
C104: 5601080000 | D104: 5601080000 Non-operating expense-VAT non-deductible | E104: 5601080000 非经营性支出-不可抵扣增值税 | F104: 0 | H104: 0 | J104: 0 | K104: 0 | L104: =K104-G104 -> 0 | M104: 0
C105: 6666040215 | D105: 6666040215 Product sample fee | E105: 6666040215 产品样品费用 | F105: 0 | H105: 0 | J105: 0 | K105: 0 | L105: =K105-G105 -> 0 | M105: 0
C106: 6666020403 | D106: 6666020403 Company car expense | E106: 6666020403 公司车辆费用 | F106: 0 | H106: 0 | J106: 0 | K106: 0 | L106: =K106-G106 -> 0 | M106: 0
C107: 6666021200 | D107: 6666021200 Audit fee | E107: 6666021200 审计费用 | F107: 0 | H107: 0 | J107: 0 | K107: 0 | L107: =K107-G107 -> 0 | M107: 0
C108: 6666050202 | D108: 6666050202 Custom clearance charge | E108: 6666050202 海关清关费用 | F108: 0 | H108: 0 | J108: 0.5999 | K108: 0.0056437805 | L108: =K108-G108 -> 0.0056437805 | M108: 0.0056437805
C109: 5401050201 | D109: 5401050201 COGS-Freight out-Special and sporadic fr | E109: 5401050201 COGS-特殊和零星运费 | F109: 0 | H109: 0 | J109: 0 | K109: 0 | L109: =K109-G109 -> 0 | M109: 0
C110: 6666020801 | D110: 6666020801 Housing rental cost | E110: 6666020801 住房租赁成本 | J110: 1.56888 | L110: =K110-G110 -> 0 | M110: 0
C111: FIX | D111: * CS_Fix Cost | E111: * CS_Fix Cost | F111: 108.72299 | G111: 1.3241945 | H111: 114.99434 | I111: 0.9895902 | J111: 101.48011 | K111: 0.95471155 | L111: =K111-G111 -> -0.36948295 | M111: -0.034878642 | N111: =F111-J111 -> 7.24288
B112: 生产耗用 | C112: 6666110203 | D112: 6666110203 Low value consumables | E112: 6666110203 低值易耗品 | F112: 1.93814 | G112: 0.023605627 | H112: 32.234597 | I112: 0.27739662 | J112: 35.95345 | K112: 0.33824534 | L112: =K112-G112 -> 0.31463971 | M112: 0.060848715
C113: 5102040000 | D113: 5102040000 Other Revenue - Other | E113: 5102040000 其他收入-其他 | F113: 0 | G113: 0 | H113: 0 | I113: 0 | J113: 0 | K113: 0 | L113: =K113-G113 -> 0 | M113: 0
C114: 6666050307 | D114: 6666050307 Inventory count different-raw material | E114: 6666050307 存货盘点差异-原材料 | F114: -9.51008 | G114: -0.11582827 | H114: 0 | I114: 0 | J114: -9.13867 | K114: -0.085975408 | L114: =K114-G114 -> 0.029852861 | M114: -0.085975408
C115: 6666050312 | D115: 6666050312 Inventory count different- Semifinished | E115: 6666050312 存货盘点差异-半成品 | F115: 2.13776 | G115: 0.026036904 | H115: 0 | I115: 0 | J115: 0 | K115: 0 | L115: =K115-G115 -> -0.026036904 | M115: 0
C116: VAR | D116: * CS_Variable Cost | E116: * CS_Variable Cost | F116: -5.43418 | G116: -0.066185738 | H116: 32.234597 | I116: 0.27739662 | J116: 26.81478 | K116: 0.25226993 | L116: =K116-G116 -> 0.31845567 | M116: -0.025126693
B117: 存货跌价准备 | C117: 6666100203 | D117: 6666100203 Provision for inventory devaluation - RM | E117: 6666100203 存货减值准备-原材料 | F117: 28.85478 | G117: 0.35143755 | H117: 12.5 | I117: 0.10756945 | J117: 0 | K117: 0 | L117: =K117-G117 -> -0.35143755 | M117: -0.10756945
C118: FIX | D118: * CS_Obsolescence | E118: * CS_Obsolescence | F118: 28.85478 | G118: 0.35143755 | H118: 12.5 | I118: 0.10756945 | J118: 0 | K118: 0 | L118: =K118-G118 -> -0.35143755 | M118: -0.10756945
B119: 废品回收 | C119: 5301070000 | D119: 5301070000 Non-operation revenue-sales of scrapped | E119: 5301070000 非经营收入-废品销售 | F119: -38.3304 | G119: -0.46684611 | H119: -87.098721 | I119: -0.7495329 | J119: -85.73821 | K119: -0.80661383 | L119: =K119-G119 -> -0.33976771 | M119: -0.057080924
...

Sheet 厨电3月
A1: 维度 | B1: KPI | C1: 25年实际 | E1: 26年预算 | F1: 26年实际 | G1: 预算差异 | H1: 实际比同期差异 | I1: 制造费差额 | J1: 差异原因
A2: 单 | B2: 产量 | C2: 92657 | E2: 116204.08 | F2: =L28 -> 107376 | G2: =F2-E2 -> -8828.0833 | H2: =F2-C2 -> 14719 | I2: /
A3: 时 | B3: 工作天数 | C3: 20 | E3: 20 | F3: 23 | G3: - | H3: =F3-C3 -> 3
A4: 人 | B4: 直接人工 | C4: 279 | E4: 293 | F4: 299 | G4: =F4-E4 -> 6 | H4: =F4-C4 -> 20
B5: 人工工资 | C5: =F48*1000/C4 -> 2469.9063 | E5: =H48*1000/E4 -> 2291.4976 | F5: =J45/F4*1000 -> 3219.5397 | G5: =F5-E5 -> 928.04214 | H5: =F5-C5 -> 749.63335
B6: 间接人工 | C6: 170 | E6: 127 | F6: 122 | G6: =F6-E6 -> -5 | H6: =F6-C6 -> -48
B7: 间接人工工资 | C7: =F132*1000/C6 -> 2892.9495 | E7: =H132*1000/E6 -> 2737.783 | F7: =(J128+J131)/F6*1000 -> 3218.1175 | G7: =F7-E7 -> 480.33448 | H7: =F7-C7 -> 325.16799
B8: 白领人数 | C8: 58 | E8: 31 | F8: 31 | G8: =F8-E8 -> 0 | H8: =F8-C8 -> -27
B9: 白领人工工资 | C9: =F140*1000/C8 -> 4367.3414 | E9: =H140*1000/E8 -> 4794.2121 | F9: =(J134+J135)/F8*1000 -> 4345.5265 | G9: =F9-E9 -> -448.68567 | H9: =F9-C9 -> -21.814928
A10: 效 | B10: UPPH | C10: =C2/C3/C4 -> 16.605197 | E10: =E2/E3/E4 -> 19.830048 | F10: =F2/F3/F4 -> 15.613785 | G10: =F10-E10 -> -4.2162633 | H10: =F10-C10 -> -0.99141205
A11: 费 | B11: 单台制造费 | C11: =SUM(C12:C24) -> 32.162181 | E11: =SUM(E12:E24) -> 22.52 | F11: =SUM(F12:F24) -> 24.139704 | G11: =F11-E11 -> 1.6197042 | H11: =F11-C11 -> -8.0224766 | I11: =H11*$F$2 -> -861421.45
B12: 折旧（含FC） | C12: =G39 -> 8.2401239 | D12: =C12*$C$2 -> 763505.16 | E12: 7.12 | F12: =K39 -> 7.4376403 | G12: =F12-E12 -> 0.31764025 | H12: =F12-C12 -> -0.80248364 | I12: =H12*$F$2 -> -86167.484
B13: 运营费 | C13: 2.02 | D13: =C13*$C$2 -> 187167.14 | E13: 0.97 | F13: =K109 -> 0.38916732 | G13: =F13-E13 -> -0.58083268 | H13: =F13-C13 -> -1.6308327 | I13: =H13*$F$2 -> -175112.29
B14: 存货跌价准备 | C14: 0.311415 | D14: =C14*$C$2 -> 28854.78 | E14: 0.11 | F14: =K116 -> 0.11641335 | G14: =F14-E14 -> 0.0064133512 | H14: =F14-C14 -> -0.19500165 | I14: =H14*$F$2 -> -20938.497
B15: 固定能源费 | C15: 0.51284102 | D15: =C15*$C$2 -> 47518.31 | E15: 0.28 | F15: =K120 -> 0.30656404 | G15: =F15-E15 -> 0.026564037 | H15: =F15-C15 -> -0.20627698 | I15: =H15*$F$2 -> -22149.197
B16: 间接人工成本-辅助人员 | C16: 5.3077631 | D16: =C16*$C$2 -> 491801.41 | E16: 2.99 | F16: =K132 -> 3.3799955 | G16: =F16-E16 -> 0.38999553 | H16: =F16-C16 -> -1.9277676 | I16: =H16*$F$2 -> -206995.98
B17: 固定人工-白领 | C17: 2.733801 | D17: =C17*$C$2 -> 253305.8 | E17: 1.28 | F17: =K140 -> 1.4767593 | G17: =F17-E17 -> 0.19675933 | H17: =F17-C17 -> -1.2570417 | I17: =H17*$F$2 -> -134976.11
B18: 半固定-班车/工作服 | C18: 1.7 | D18: =C18*$C$2 -> 157516.9 | E18: 1.7 | F18: =K156 -> 1.1454646 | G18: =F18-E18 -> -0.55453537 | H18: =F18-C18 -> -0.55453537 | I18: =H18*$F$2 -> -59543.79
B19: 直接人工 | C19: 7.4371485 | D19: =C19*$C$2 -> 689103.87 | E19: 5.78 | F19: =K48 -> 7.5481307 | G19: =F19-E19 -> 1.7681307 | H19: =F19-C19 -> 0.11098217 | I19: =H19*$F$2 -> 11916.821
B20: 可回收废料 | C20: 0.36 | D20: =C20*$C$2 -> 33356.52 | E20: 0.54 | F20: =K53 -> 0.50969295 | G20: =F20-E20 -> -0.030307052 | H20: =F20-C20 -> 0.14969295 | I20: =H20*$F$2 -> 16073.43
B21: 生产耗用品 | C21: -0.05 | D21: =C21*$C$2 -> -4632.85 | E21: 0.29 | F21: =K114 -> 0.042418604 | G21: =F21-E21 -> -0.2475814 | H21: =F21-C21 -> 0.092418604 | I21: =H21*$F$2 -> 9923.54
B22: 废品回收 | C22: -0.94773606 | D22: =C22*$C$2 -> -87814.38 | E22: -0.68 | F22: =K118 -> -0.72368416 | G22: =F22-E22 -> -0.043684157 | H22: =F22-C22 -> 0.2240519 | I22: =H22*$F$2 -> 24057.797
B23: 变动能源费 | C23: 0.46779358 | D23: =C23*$C$2 -> 43344.35 | E23: 0.29 | F23: =K124 -> 0.24392862 | G23: =F23-E23 -> -0.046071375 | H23: =F23-C23 -> -0.22386496 | I23: =H23*$F$2 -> -24037.724
B24: 园区分摊费用 | C24: 4.0690307 | D24: =C24*$C$2 -> 377024.18 | E24: 1.85 | F24: =K236 -> 2.2672131 | G24: =F24-E24 -> 0.41721306 | H24: =F24-C24 -> -1.8018177 | I24: =H24*$F$2 -> -193471.97
B25: IT Expense-Internal Charge Out | E25: 2.7282082
B26: Association dues | E26: 0.098093398
B27: G&A | E27: 1.2427291
A28: Type 类型 | B28: Code 编码 | C28: Description(EN) 描述 | E28: Description(CN) 描述 | F28: 单位-千欧 | G28: 同期订单量 | H28: 92657 | I28: 预测订单量 | J28: 106704 | K28: 实际台数 | L28: 107376
F29: MFG 2025 同期制造费 | G29: CPU 2025 同期单台 | H29: Budget 2026 预算 | I29: Budget-CPU 2026 单台预算 | J29: ACT 2026 实际 | K29: ACT-CPU 2026 单台实际 | L29: CPU-Y0Y 单台同期 | M29: Budget-ACT VARIANCE 预算同比 | N29: CPU-Y0Y Analysis 单台同期分析 | O29: Budget-ACT VARIANCE Analysis 预算实际分析
A30: 折旧 | B30: 6666110101 | C30: 6666110101 Depreciation of buildings | E30: 建筑物折旧 | F30: 73.6323 | G30: =F30*1000/$H$28 -> 0.79467606 | H30: 73.934342 | I30: =H30*1000/$J$28 -> 0.69289194 | J30: 72.20683 | K30: =J30*1000/$L$28 -> 0.67246712 | L30: =K30-G30 -> -0.12220894 | M30: =K30-I30 -> -0.020424818
B31: 6666110106 | C31: 6666110106 Depreciation of R&D facilities | E31: 研发设施折旧 | F31: 0 | G31: =F31*1000/$H$28 -> 0 | H31: 0 | I31: =H31*1000/$J$28 -> 0 | J31: 0 | K31: =J31*1000/$L$28 -> 0 | L31: =K31-G31 -> 0 | M31: =K31-I31 -> 0
B32: 6666110107 | C32: 6666110107 Depreciation of mold | E32: 模具折旧 | F32: 209.08411 | G32: =F32*1000/$H$28 -> 2.2565387 | H32: 208.70125 | I32: =H32*1000/$J$28 -> 1.9558897 | J32: 165.27585 | K32: =J32*1000/$L$28 -> 1.5392252 | L32: =K32-G32 -> -0.71731349 | M32: =K32-I32 -> -0.41666443
B33: 6666110110 | C33: 6666110110 Depreciation-Plant & Machinery | E33: 6666110110 折旧-厂房及机械 | F33: 416.22698 | G33: =F33*1000/$H$28 -> 4.4921267 | H33: 451.36673 | I33: =H33*1000/$J$28 -> 4.2300825 | J33: 471.04914 | K33: =J33*1000/$L$28 -> 4.3869127 | L33: =K33-G33 -> -0.10521394 | M33: =K33-I33 -> 0.15683019
B34: 6666110112 | C34: 6666110112 Depreciation of Furniture & Fixture | E34: 6666110112 家具及装置折旧 | F34: 39.82187 | G34: =F34*1000/$H$28 -> 0.42977724 | H34: 60.932952 | I34: =H34*1000/$J$28 -> 0.57104656 | J34: 58.92395 | K34: =J34*1000/$L$28 -> 0.54876276 | L34: =K34-G34 -> 0.11898552 | M34: =K34-I34 -> -0.022283801
B35: 6666110204 | C35: 6666110204 Amortization of license, trademarks and | E35: 6666110204 许可证、商标及摊销 | F35: 2.81415 | G35: =F35*1000/$H$28 -> 0.030371693 | H35: 32.315355 | I35: =H35*1000/$J$28 -> 0.30285045 | J35: 2.81415 | K35: =J35*1000/$L$28 -> 0.026208371 | L35: =K35-G35 -> -0.0041633229 | M35: =K35-I35 -> -0.27664208
B36: 6666110207 | C36: 6666110207 Amortization of Software | E36: 6666110207 软件摊销 | F36: 18.69461 | G36: =F36*1000/$H$28 -> 0.20176144 | H36: 0 | I36: =H36*1000/$J$28 -> 0 | J36: 28.29481 | K36: =J36*1000/$L$28 -> 0.26351149 | L36: =K36-G36 -> 0.06175005 | M36: =K36-I36 -> 0.26351149
B37: 6666110506 | C37: 6666110506 Amortization-Leasehold Improvement | E37: 6666110506 租赁改良摊销 | F37: 3.15116 | G37: =F37*1000/$H$28 -> 0.034008871 | H37: 0 | I37: =H37*1000/$J$28 -> 0 | J37: 0 | K37: =J37*1000/$L$28 -> 0 | L37: =K37-G37 -> -0.034008871 | M37: =K37-I37 -> 0
B38: 6666110206 | C38: 6666110206 Amortization of Patents | E38: 6666110206 专利摊销 | F38: 0.07998 | G38: =F38*1000/$H$28 -> 0.00086318357 | H38: 0 | I38: =H38*1000/$J$28 -> 0 | J38: 0.05933 | K38: =J38*1000/$L$28 -> 0.00055254433 | L38: =K38-G38 -> -0.00031063924 | M38: =K38-I38 -> 0.00055254433
B39: FIX | C39: * CS_Depreciation | E39: * CS_折旧 | F39: =SUM(F30:F38) -> 763.50516 | G39: =F39*1000/$H$28 -> 8.2401239 | H39: 827.25063 | I39: =SUM(I30:I38) -> 7.7527612 | J39: =SUM(J30:J38) -> 798.62406 | K39: =J39*1000/$L$28 -> 7.4376403 | L39: =K39-G39 -> -0.80248364 | M39: =K39-I39 -> -0.31512091
A40: 直接人工 | B40: 5001010205 | C40: 5001010205 Unemployment Insurance -blue collar-Dire | E40: 5001010205 失业保险-蓝领-直接 | F40: 11.19577 | G40: =F40/$H$28*1000 -> 0.12083027 | H40: 10.970392 | I40: =H40*1000/$J$28 -> 0.10281144 | J40: 14.73509 | K40: =J40*1000/$L$28 -> 0.1372289 | L40: =K40-G40 -> 0.01639863 | M40: =K40-I40 -> 0.034417455
B41: 6666010380 | C41: 6666010380 Incentive | E41: 6666010380 激励 | F41: -1.73083 | G41: =F41/$H$28*1000 -> -0.01867997 | H41: -28.803235 | I41: =H41*1000/$J$28 -> -0.26993585 | J41: -2.27971 | K41: =J41*1000/$L$28 -> -0.021231094 | L41: =K41-G41 -> -0.0025511243 | M41: =K41-I41 -> 0.24870476
B42: 6666010019 | C42: 6666010019 Payroll Taxes - Blue Collar Direct | E42: 6666010019 工资税-蓝领直接 | F42: 90.64247 | G42: =F42/$H$28*1000 -> 0.9782582 | H42: 113.81782 | I42: =H42*1000/$J$28 -> 1.0666687 | J42: 126.36555 | K42: =J42*1000/$L$28 -> 1.176851 | L42: =K42-G42 -> 0.19859277 | M42: =K42-I42 -> 0.11018226
B43: 6666010183 | C43: 6666010183 Overtime-Blue Collar-Direct | E43: 6666010183 加班费-蓝领-直接 | F43: 7.31958 | G43: =F43/$H$28*1000 -> 0.078996514 | H43: 0 | I43: =H43*1000/$J$28 -> 0 | J43: 8.33574 | K43: =J43*1000/$L$28 -> 0.077631314 | L43: =K43-G43 -> -0.0013651998 | M43: =K43-I43 -> 0.077631314
B44: 6666010229 | C44: 6666010229 Staff Leaving Indemnity - Blue Collar Di | E44: 6666010229 蓝领离职赔偿-直接 | F44: 20.16124 | G44: =F44/$H$28*1000 -> 0.21759004 | H44: 17.676312 | I44: =H44*1000/$J$28 -> 0.16565744 | J44: -306.31482 | K44: =J44*1000/$L$28 -> -2.8527308 | L44: =K44-G44 -> -3.0703208 | M44: =K44-I44 -> -3.0183882 | O44: 单台下降3.02欧，费用下降29万欧
B45: 6666010188 | C45: 6666010188 Salary - Blue collar direct employees | E45: 6666010188 蓝领直接员工工资 | F45: 556.2437 | G45: =F45/$H$28*1000 -> 6.0032561 | H45: 557.7475 | I45: =H45*1000/$J$28 -> 5.2270533 | J45: 962.64237 | K45: =J45*1000/$L$28 -> 8.9651539 | L45: =K45-G45 -> 2.9618978 | M45: =K45-I45 -> 3.7381006 | O45: 单台上涨3.74欧，费用上涨40万欧
B46: 5102040406 | C46: 5102040406 Other revenue-Service/Secondment agreeme | E46: 5102040406 其他收入-服务/派遣协议 | F46: 0 | G46: =F46/$H$28*1000 -> 0 | H46: 0 | I46: =H46*1000/$J$28 -> 0 | J46: 0 | K46: =J46*1000/$L$28 -> 0 | L46: =K46-G46 -> 0 | M46: =K46-I46 -> 0
B47: 6666010115 | C47: 6666010115 Salary-Blue collar direct employees-Accr | E47: 6666010115 蓝领直接员工工资-计提 | F47: 5.27194 | G47: =F47/$H$28*1000 -> 0.056897374 | H47: 0 | I47: =H47*1000/$J$28 -> 0 | J47: 7.00386 | K47: =J47*1000/$L$28 -> 0.065227425 | L47: =K47-G47 -> 0.0083300509 | M47: =K47-I47 -> 0.065227425
B48: VAR | C48: * CS_Direct Labour | E48: * CS_直接劳动 | F48: 689.10387 | G48: =SUM(G40:G47) -> 7.4371485 | H48: 671.40878 | I48: =SUM(I40:I47) -> 6.2922551 | J48: =SUM(J40:J47) -> 810.48808 | K48: =J48*1000/$L$28 -> 7.5481307 | L48: =K48-G48 -> 0.11098217 | M48: =K48-I48 -> 1.2558756
A49: 可回收废料 | B49: 8701530201 | C49: 8701530201 Scrap-Raw Material - Managerial | E49: 8701530201 废料-原材料-管理 | F49: 0 | G49: =F49/$H$28*1000 -> 0 | H49: 0 | I49: =H49*1000/$J$28 -> 0 | J49: 0 | K49: =J49*1000/$L$28 -> 0 | L49: =K49-G49 -> 0 | M49: =K49-I49 -> 0
B50: 6666050309 | C50: 6666050309 SFG scrap | E50: 6666050309 SFG废料 | F50: 18.94494 | G50: =F50/$H$28*1000 -> 0.20446313 | H50: 0 | I50: =H50*1000/$J$28 -> 0 | J50: 41.5444 | K50: =J50*1000/$L$28 -> 0.38690583 | L50: =K50-G50 -> 0.1824427 | M50: =K50-I50 -> 0.38690583
B51: 6666050308 | C51: 6666050308 Raw material scrap | E51: 6666050308 原材料废料 | F51: 13.39109 | G51: =F51/$H$28*1000 -> 0.14452324 | H51: 62.46102 | I51: =H51*1000/$J$28 -> 0.58536718 | J51: 12.28569 | K51: =J51*1000/$L$28 -> 0.11441747 | L51: =K51-G51 -> -0.030105774 | M51: =K51-I51 -> -0.47094971
B52: 6666050306 | C52: 6666050306 Finished goods scrap | E52: 6666050306 完工产品废料 | F52: 1.00536 | G52: =F52/$H$28*1000 -> 0.010850341 | H52: 0 | I52: =H52*1000/$J$28 -> 0 | J52: 0.8987 | K52: =J52*1000/$L$28 -> 0.0083696543 | L52: =K52-G52 -> -0.0024806862 | M52: =K52-I52 -> 0.0083696543
B53: VAR | C53: * CS_SCRAP_VARIABLE | E53: * CS_ 废料_VARIABLE | F53: 33.34139 | G53: =SUM(G49:G52) -> 0.35983671 | H53: 62.46102 | I53: =SUM(I49:I52) -> 0.58536718 | J53: =SUM(J49:J52) -> 54.72879 | K53: =J53*1000/$L$28 -> 0.50969295 | L53: =K53-G53 -> 0.14985624 | M53: =K53-I53 -> -0.075674233
A54: 组织运营 | B54: 5102010151 | C54: 5102010151 Other Rev.-Interco-Epidemic problem comp | E54: 5102010151 其他收入-集团间-疫情问题补偿 | F54: 0 | G54: =F54/$H$28*1000 -> 0 | H54: 0 | I54: =H54*1000/$J$28 -> 0 | J54: 0 | K54: =J54*1000/$L$28 -> 0 | L54: =K54-G54 -> 0 | M54: =K54-I54 -> 0
B55: 5001010200 | C55: 5001010200 Cost of Manufacture - Raw Material | E55: 5001010200 制造成本-原材料 | F55: 2.94096 | G55: =F55/$H$28*1000 -> 0.031740289 | H55: 0 | I55: =H55*1000/$J$28 -> 0 | J55: 0 | K55: =J55*1000/$L$28 -> 0 | L55: =K55-G55 -> -0.031740289 | M55: =K55-I55 -> 0
B56: 5001010201 | C56: 5001010201 Cost of Manufacture - Raw Material-Freig | E56: 5001010201 制造成本-原材料-运费 | F56: 0 | G56: =F56/$H$28*1000 -> 0 | H56: 0 | I56: =H56*1000/$J$28 -> 0 | J56: 0 | K56: =J56*1000/$L$28 -> 0 | L56: =K56-G56 -> 0 | M56: =K56-I56 -> 0
B57: 5207000011 | C57: 5207000011 Gain of tangible asset disposal | E57: 5207000011 有形资产处置收益 | F57: -4.25402 | G57: =F57/$H$28*1000 -> -0.04591148 | H57: 0 | I57: =H57*1000/$J$28 -> 0 | J57: 0 | K57: =J57*1000/$L$28 -> 0 | L57: =K57-G57 -> 0.04591148 | M57: =K57-I57 -> 0
B58: 5207000012 | C58: 5207000012 Loss of tangible asset sold | E58: 5207000012 出售有形资产损失 | F58: 95.99121 | G58: =F58/$H$28*1000 -> 1.0359844 | H58: 0 | I58: =H58*1000/$J$28 -> 0 | J58: 0 | K58: =J58*1000/$L$28 -> 0 | L58: =K58-G58 -> -1.0359844 | M58: =K58-I58 -> 0
B59: 5207000022 | C59: 5207000022 Loss of intangible asset disposal | E59: 5207000022 无形资产处置损失 | F59: 0 | G59: =F59/$H$28*1000 -> 0 | H59: 0 | I59: =H59*1000/$J$28 -> 0 | J59: 0 | K59: =J59*1000/$L$28 -> 0 | L59: =K59-G59 -> 0 | M59: =K59-I59 -> 0
B60: 5301060000 | C60: 5301060000 Other Income-Subsidy income | E60: 5301060000 其他收入-补贴收入 | F60: 0 | G60: =F60/$H$28*1000 -> 0 | H60: 0 | I60: =H60*1000/$J$28 -> 0 | J60: -7.37667 | K60: =J60*1000/$L$28 -> -0.06869943 | L60: =K60-G60 -> -0.06869943 | M60: =K60-I60 -> -0.06869943
B61: 5301999999 | C61: 5301999999 Non-operation revenue-Other | E61: 5301999999 非经营收入-其他 | F61: 0 | G61: =F61/$H$28*1000 -> 0 | H61: 0 | I61: =H61*1000/$J$28 -> 0 | J61: -4.57169 | K61: =J61*1000/$L$28 -> -0.04257646 | L61: =K61-G61 -> -0.04257646 | M61: =K61-I61 -> -0.04257646
B62: 5405030000 | C62: 5405030000 Other cost-others | E62: 5405030000 其他成本-其他 | F62: 6.83254 | G62: =F62/$H$28*1000 -> 0.073740138 | H62: 0 | I62: =H62*1000/$J$28 -> 0 | J62: -1e-05 | K62: =J62*1000/$L$28 -> -9.3130681e-08 | L62: =K62-G62 -> -0.073740231 | M62: =K62-I62 -> -9.3130681e-08
B63: 5601050000 | C63: 5601050000 Non-Operating Expense - Penalty | E63: 5601050000 非经营费用-罚款 | F63: 0 | G63: =F63/$H$28*1000 -> 0 | H63: 0 | I63: =H63*1000/$J$28 -> 0 | J63: 0 | K63: =J63*1000/$L$28 -> 0 | L63: =K63-G63 -> 0 | M63: =K63-I63 -> 0
B64: 5601050100 | C64: 5601050100 Non-operation Expense-Others | E64: 5601050100 非经营费用-其他 | F64: 0 | G64: =F64/$H$28*1000 -> 0 | H64: 0 | I64: =H64*1000/$J$28 -> 0 | J64: 0 | K64: =J64*1000/$L$28 -> 0 | L64: =K64-G64 -> 0 | M64: =K64-I64 -> 0
B65: 5102040893 | C65: 5102040893 Other revenue-Charge out-Test Expense | E65: 5102040893 其他收入-费用支出-测试费用 | F65: 0 | G65: =F65/$H$28*1000 -> 0 | H65: 0 | I65: =H65*1000/$J$28 -> 0 | J65: 0 | K65: =J65*1000/$L$28 -> 0 | L65: =K65-G65 -> 0 | M65: =K65-I65 -> 0
B66: 5801000041 | C66: 5801000041 Previous year Sundry cost | E66: 5801000041 前一年杂项成本 | F66: 0 | G66: =F66/$H$28*1000 -> 0 | H66: 0 | I66: =H66*1000/$J$28 -> 0 | J66: 0 | K66: =J66*1000/$L$28 -> 0 | L66: =K66-G66 -> 0 | M66: =K66-I66 -> 0
... B74: 6666020302 | C74: 6666020302 Communication Expenses | E74: 6666020302 通讯费用 | F74: 0 | G74: =F74/$H$28*1000 -> 0 | H74: 1.1852505 | I74: =H74*1000/$J$28 -> 0.011107835 | J74: -0.09788 | K74: =J74*1000/$L$28 -> -0.00091156311 | L74: =K74-G74 -> -0.00091156311 | M74: =K74-I74 -> -0.012019398
B75: 6666020403 | C75: 6666020403 Company car expense | E75: 6666020403 公司车辆费用 | F75: 0 | G75: =F75/$H$28*1000 -> 0 | H75: 0 | I75: =H75*1000/$J$28 -> 0 | J75: 0 | K75: =J75*1000/$L$28 -> 0 | L75: =K75-G75 -> 0 | M75: =K75-I75 -> 0
B76: 6666020405 | C76: 6666020405 Company car expense - maintenance fees | E76: 6666020405 公司车辆费用-维护费 | F76: 0 | G76: =F76/$H$28*1000 -> 0 | H76: 0 | I76: =H76*1000/$J$28 -> 0 | J76: 0 | K76: =J76*1000/$L$28 -> 0 | L76: =K76-G76 -> 0 | M76: =K76-I76 -> 0
B77: 6666020495 | C77: 6666020495 Non-deductible expense-travel. | E77: 6666020495 不可抵扣费用-旅行 | F77: 0.36614 | G77: =F77/$H$28*1000 -> 0.0039515633 | H77: 0 | I77: =H77*1000/$J$28 -> 0 | J77: 0.48269 | K77: =J77*1000/$L$28 -> 0.0044953248 | L77: =K77-G77 -> 0.00054376155 | M77: =K77-I77 -> 0.0044953248
B78: 6666020504 | C78: 6666020504 Newspaper and Periodicals expenditure | E78: 6666020504 报纸和期刊支出 | F78: 0 | G78: =F78/$H$28*1000 -> 0 | H78: 0 | I78: =H78*1000/$J$28 -> 0 | J78: 0 | K78: =J78*1000/$L$28 -> 0 | L78: =K78-G78 -> 0 | M78: =K78-I78 -> 0
B79: 6666020508 | C79: 6666020508 Postage | E79: 6666020508 邮资 | F79: 0 | G79: =F79/$H$28*1000 -> 0 | H79: 0 | I79: =H79*1000/$J$28 -> 0 | J79: -4e-05 | K79: =J79*1000/$L$28 -> -3.7252272e-07 | L79: =K79-G79 -> -3.7252272e-07 | M79: =K79-I79 -> -3.7252272e-07
B80: 6666020602 | C80: 6666020602 Training costs Outside the group | E80: 6666020602 集团外培训费用 | F80: 0.42307 | G80: =F80/$H$28*1000 -> 0.0045659799 | H80: 0.38785113 | I80: =H80*1000/$J$28 -> 0.0036348322 | J80: 0 | K80: =J80*1000/$L$28 -> 0 | L80: =K80-G80 -> -0.0045659799 | M80: =K80-I80 -> -0.0036348322
B81: 6666020701 | C81: 6666020701 Enterprise Property Insurance | E81: 6666020701 企业财产保险 | F81: 0 | G81: =F81/$H$28*1000 -> 0 | H81: 0 | I81: =H81*1000/$J$28 -> 0 | J81: 0 | K81: =J81*1000/$L$28 -> 0 | L81: =K81-G81 -> 0 | M81: =K81-I81 -> 0
B82: 6666020802 | C82: 6666020802 Equipment rental cost | E82: 6666020802 设备租赁费用 | F82: 23.481 | G82: =F82/$H$28*1000 -> 0.25341852 | H82: 20.409 | I82: =H82*1000/$J$28 -> 0.19126743 | J82: 20.409 | K82: =J82*1000/$L$28 -> 0.19007041 | L82: =K82-G82 -> -0.063348115 | M82: =K82-I82 -> -0.0011970246
B83: 6666020803 | C83: 6666020803 Car rental cost | E83: 6666020803 汽车租赁费用 | F83: 8.98448 | G83: =F83/$H$28*1000 -> 0.096964935 | H83: 3.3345438 | I83: =H83*1000/$J$28 -> 0.03125041 | J83: 4.19036 | K83: =J83*1000/$L$28 -> 0.039025108 | L83: =K83-G83 -> -0.057939827 | M83: =K83-I83 -> 0.0077746979
B84: 6666021100 | C84: 6666021100 Consulting fees | E84: 6666021100 咨询费 | F84: 9.52529 | G84: =F84/$H$28*1000 -> 0.10280162 | H84: 17.032757 | I84: =H84*1000/$J$28 -> 0.15962623 | J84: 22.21719 | K84: =J84*1000/$L$28 -> 0.2069102 | L84: =K84-G84 -> 0.10410858 | M84: =K84-I84 -> 0.047283972
B85: 6666021104 | C85: 6666021104 Consulting expense-Technical | E85: 6666021104 咨询费用-技术 | F85: 0 | G85: =F85/$H$28*1000 -> 0 | H85: 0 | I85: =H85*1000/$J$28 -> 0 | J85: 0 | K85: =J85*1000/$L$28 -> 0 | L85: =K85-G85 -> 0 | M85: =K85-I85 -> 0
B86: 6666021902 | C86: 6666021902 Cleaning fees | E86: 6666021902 清洁费 | F86: 16.9796 | G86: =F86/$H$28*1000 -> 0.18325221 | H86: 10.480498 | I86: =H86*1000/$J$28 -> 0.098220293 | J86: 4.73683 | K86: =J86*1000/$L$28 -> 0.04411442 | L86: =K86-G86 -> -0.13913779 | M86: =K86-I86 -> -0.054105873
B87: 6666022100 | C87: 6666022100 Security | E87: 6666022100 安全 | F87: 13.05481 | G87: =F87/$H$28*1000 -> 0.14089394 | H87: 13.258212 | I87: =H87*1000/$J$28 -> 0.12425225 | J87: 13.94601 | K87: =J87*1000/$L$28 -> 0.12988014 | L87: =K87-G87 -> -0.011013801 | M87: =K87-I87 -> 0.0056278934
... B100: 5401020212 | C100: 5401020212 Local Transpor | E100: 5401020212 本地运输 | F100: 0 | G100: =F100/$H$28*1000 -> 0 | H100: 0 | I100: =H100*1000/$J$28 -> 0 | J100: 0 | K100: =J100*1000/$L$28 -> 0 | L100: =K100-G100 -> 0 | M100: =K100-I100 -> 0
B101: 6666050320 | C101: 6666050320 Reworking costs | E101: 6666050320 再加工成本 | F101: 0 | G101: =F101/$H$28*1000 -> 0 | H101: 0 | I101: =H101*1000/$J$28 -> 0 | J101: 0 | K101: =J101*1000/$L$28 -> 0 | L101: =K101-G101 -> 0 | M101: =K101-I101 -> 0
B102: 6666093800 | C102: 6666093800 Other Taxes-CIT Deductible | E102: 6666093800 其他税项-可抵扣公司税 | F102: 0 | G102: =F102/$H$28*1000 -> 0 | H102: 0 | I102: =H102*1000/$J$28 -> 0 | J102: 0 | K102: =J102*1000/$L$28 -> 0 | L102: =K102-G102 -> 0 | M102: =K102-I102 -> 0
B103: 5601080000 | C103: 5601080000 Non-operating expense-VAT non-deductible | E103: 5601080000 非经营性支出-不可抵扣增值税 | F103: 0 | G103: =F103/$H$28*1000 -> 0 | H103: 0 | I103: =H103*1000/$J$28 -> 0 | J103: 0 | K103: =J103*1000/$L$28 -> 0 | L103: =K103-G103 -> 0 | M103: =K103-I103 -> 0
B104: 6666040215 | C104: 6666040215 Product sample fee | E104: 6666040215 产品样品费用 | F104: 0 | G104: =F104/$H$28*1000 -> 0 | H104: 0 | I104: =H104*1000/$J$28 -> 0 | J104: 0 | K104: =J104*1000/$L$28 -> 0 | L104: =K104-G104 -> 0 | M104: =K104-I104 -> 0
B105: 6666020403 | C105: 6666020403 Company car expense | E105: 6666020403 公司车辆费用 | F105: 0 | G105: =F105/$H$28*1000 -> 0 | H105: 0 | I105: =H105*1000/$J$28 -> 0 | J105: 0 | K105: =J105*1000/$L$28 -> 0 | L105: =K105-G105 -> 0 | M105: =K105-I105 -> 0
B106: 6666021200 | C106: 6666021200 Audit fee | E106: 6666021200 审计费用 | F106: 0 | G106: =F106/$H$28*1000 -> 0 | H106: 0 | I106: =H106*1000/$J$28 -> 0 | J106: 0 | K106: =J106*1000/$L$28 -> 0 | L106: =K106-G106 -> 0 | M106: =K106-I106 -> 0
B107: 6666050202 | C107: 6666050202 Custom clearance charge | E107: 6666050202 海关清关费用 | F107: 0 | G107: =F107/$H$28*1000 -> 0 | H107: 0 | I107: =H107*1000/$J$28 -> 0 | J107: 0.58944 | K107: =J107*1000/$L$28 -> 0.0054894949 | L107: =K107-G107 -> 0.0054894949 | M107: =K107-I107 -> 0.0054894949
B108: 5401050201 | C108: 5401050201 COGS-Freight out-Special and sporadic fr | E108: 5401050201 COGS-特殊和零星运费 | F108: 0 | G108: =F108/$H$28*1000 -> 0 | H108: 0 | I108: =H108*1000/$J$28 -> 0 | J108: 0 | K108: =J108*1000/$L$28 -> 0 | L108: =K108-G108 -> 0 | M108: =K108-I108 -> 0
B109: FIX | C109: * CS_Fix Cost | E109: * CS_Fix Cost | F109: 186.94885 | G109: =SUM(G54:G108) -> 2.0176441 | H109: 92.358197 | I109: 0.79479305 | J109: =SUM(J54:J108) -> 41.78723 | K109: =J109*1000/$L$28 -> 0.38916732 | L109: =K109-G109 -> -1.6284768 | M109: =K109-I109 -> -0.40562573
A110: 生产耗用 | B110: 6666110203 | C110: 6666110203 Low value consumables | E110: 6666110203 低值易耗品 | F110: 7.80146 | G110: =F110/$H$28*1000 -> 0.0841972 | H110: 33.617705 | I110: =H110*1000/$J$28 -> 0.31505572 | J110: 23.86612 | K110: =J110*1000/$L$28 -> 0.2222668 | L110: =K110-G110 -> 0.1380696 | M110: =K110-I110 -> -0.092788919
B111: 5102040000 | C111: 5102040000 Other Revenue - Other | E111: 5102040000 其他收入-其他 | F111: 0 | G111: =F111/$H$28*1000 -> 0 | H111: 0 | I111: =H111*1000/$J$28 -> 0 | J111: -0.0402 | K111: =J111*1000/$L$28 -> -0.00037438534 | L111: =K111-G111 -> -0.00037438534 | M111: =K111-I111 -> -0.00037438534
B112: 6666050307 | C112: 6666050307 Inventory count different-raw material | E112: 6666050307 存货盘点差异-原材料 | F112: -46.7357 | G112: =F112/$H$28*1000 -> -0.5043947 | H112: 0 | I112: =H112*1000/$J$28 -> 0 | J112: -19.27118 | K112: =J112*1000/$L$28 -> -0.17947381 | L112: =K112-G112 -> 0.32492089 | M112: =K112-I112 -> -0.17947381
B113: 6666050312 | C113: 6666050312 Inventory count different- Semifinished | E113: 6666050312 存货盘点差异-半成品 | F113: 34.08546 | G113: =F113/$H$28*1000 -> 0.36786708 | H113: 0 | I113: =H113*1000/$J$28 -> 0 | J113: 0 | K113: =J113*1000/$L$28 -> 0 | L113: =K113-G113 -> -0.36786708 | M113: =K113-I113 -> 0
B114: VAR | C114: * CS_Variable Cost | E114: * CS_Variable Cost | F114: -4.84878 | G114: =SUM(G110:G113) -> -0.052330423 | H114: 33.617705 | I114: 0.28929883 | J114: =SUM(J110:J113) -> 4.55474 | K114: =J114*1000/$L$28 -> 0.042418604 | L114: =K114-G114 -> 0.094749027 | M114: =K114-I114 -> -0.24688023
A115: 存货跌价准备 | B115: 6666100203 | C115: 6666100203 Provision for inventory devaluation - RM | E115: 6666100203 存货减值准备-原材料 | F115: 28.85478 | G115: =F115/$H$28*1000 -> 0.311415 | H115: 12.5 | I115: =H115*1000/$J$28 -> 0.1171465 | J115: 12.5 | K115: =J115*1000/$L$28 -> 0.11641335 | L115: =K115-G115 -> -0.19500165 | M115: =K115-I115 -> -0.00073314751
B116: FIX | C116: * CS_Obsolescence | E116: * CS_Obsolescence | F116: 28.85478 | G116: =G115 -> 0.311415 | H116: 12.5 | I116: 0.10756937 | J116: =J115 -> 12.5 | K116: =J116*1000/$L$28 -> 0.11641335 | L116: =K116-G116 -> -0.19500165 | M116: =K116-I116 -> 0.0088439815
A117: 废品回收 | B117: 5301070000 | C117: 5301070000 Non-operation revenue-sales of scrapped | E117: 5301070000 非经营收入-废品销售 | F117: -87.81438 | G117: =F117/$H$28*1000 -> -0.94773606 | H117: -78.973518 | I117: =H117*1000/$J$28 -> -0.74011769 | J117: -77.70631 | K117: =J117*1000/$L$28 -> -0.72368416 | L117: =K117-G117 -> 0.2240519 | M117: =K117-I117 -> 0.016433531
B118: VAR | C118: * CS_Reselling | E118: * CS_Reselling | F118: -87.81438 | G118: =G117 -> -0.94773606 | H118: -78.973518 | I118: -0.67961052 | J118: =J117 -> -77.70631 | K118: =J118*1000/$L$28 -> -0.72368416 | L118: =K118-G118 -> 0.2240519 | M118: =K118-I118 -> -0.044073635
A119: 固定能源 | B119: 6666021602 | C119: 6666021602 Electricity | E119: 6666021602 电费 | F119: 47.51831 | G119: =F119/$H$28*1000 -> 0.51284102 | H119: 32.161075 | I119: =H119*1000/$J$28 -> 0.30140458 | J119: 32.91762 | K119: =J119*1000/$L$28 -> 0.30656404 | L119: =K119-G119 -> -0.20627698 | M119: =K119-I119 -> 0.0051594533
...

Sheet 厨电4月
A1: 总结：4月厨电单台下降6.96欧；降费76万欧 上涨因素：13万（人工、通胀影响13万欧），下降因素258万（规模增加正影响11万欧，园区分摊降费20），68万降费项目_x000b_固定：厨电4月折旧期限延长降费36万欧，订单量上升1.1万，降费3万欧_x000b_变动：厨电4月下降3.4欧，降费37万欧 园区分摊单台↓2.65欧，额优化30万欧 其他变动单台↓0.62欧，额优化7万欧
A2: 维度 | B2: KPI | C2: 同期 | D2: 预测 | E2: 26年实际 | F2: 预算差异 | G2: 实际比同期差异 | H2: 制造费差额 | I2: 差异原因
A3: 单 | B3: 产量 | C3: 98687 | D3: 104704 | E3: =K26 -> 110370 | F3: =E3-D3 -> 5666 | G3: =E3-C3 -> 11683 | H3: =G3/C3 -> 0.11838439
A4: 时 | B4: 工作天数 | C4: 20 | D4: 21 | E4: 21 | F4: =E4-D4 -> 0 | G4: =E4-C4 -> 1
A5: 人 | B5: 人工 | C5: 296 | D5: 258 | E5: 277 | F5: =E5-D5 -> 19 | G5: =E5-C5 -> -19
B6: 人工工资 | C6: =E43/C5*1000 -> 1532.6765 | D6: =G43*1000/D5 -> 1819.634 | E6: =(I43+I45)*1000/E5 -> 1874.6192 | F6: =E6-D6 -> 54.985158 | G6: =E6-C6 -> 341.94271
B7: 间接人工 | C7: 182 | D7: 127 | E7: 113 | F7: =E7-D7 -> -14 | G7: =E7-C7 -> -69
B8: 间接人工工资 | C8: =E130*1000/C7 -> 2214.707 | D8: =G130/D7*1000 -> 2547.4688 | E8: =(I129)*1000/E7 -> 2329.6192 | F8: =E8-D8 -> -217.84955 | G8: =E8-C8 -> 114.91218
B9: 白领人数 | C9: 55 | D9: 34 | E9: 29 | F9: =E9-D9 -> -5 | G9: =E9-C9 -> -26
B10: 白领人工工资 | C10: =E138*1000/C9 -> 2713.6851 | D10: =G138*1000/D9 -> 4419.7838 | E10: =(I132+I133)*1000/E9 -> 2011.6007 | F10: =E10-D10 -> -2408.1831 | G10: =E10-C10 -> -702.0844
A11: 效 | B11: UPPH | C11: =C3/C4/C5/7.5 -> 2.2226802 | D11: =D3/D4/D5/7.5 -> 2.576695 | E11: =E3/E4/E5/7.5 -> 2.5298264 | F11: =E11-D11 -> -0.046868596 | G11: =E11-C11 -> 0.30714619
A12: 费 | B12: 单台制造费 | C12: =SUM(C13:C25) -> 25.907081 | D12: =SUM(D13:D25) -> 23.532894 | E12: =J235 -> 18.948118 | F12: =E12-D12 -> -4.5847756 | G12: =E12-C12 -> -6.9589628 | H12: =G12*$E$3 -> -768060.73 | I12: =F12/C12 -> -0.17696998
B13: 折旧（含FC） | C13: =F37 -> 7.7620785 | D13: 7.7932125 | E13: =J37 -> 4.2284493 | F13: =E13-D13 -> -3.5647632 | G13: =E13-C13 -> -3.5336292 | H13: =G13*$E$3 -> -390006.65
B14: 运营费 | C14: 0.12322991 | D14: 0.88316369 | E14: =J107 -> 0.74906107 | F14: =E14-D14 -> -0.13410262 | G14: =E14-C14 -> 0.62583116 | H14: =G14*$E$3 -> 69072.985
B15: 存货跌价准备 | C15: 0.29238684 | D15: 0.11938417 | E15: =J114 -> 0.11325541 | F15: =E15-D15 -> -0.0061287551 | G15: =E15-C15 -> -0.17913143 | H15: =G15*$E$3 -> -19770.735
B16: 固定能源费 | C16: 0.051572852 | D16: 0.27218766 | E16: =J118 -> 0.25860243 | F16: =E16-D16 -> -0.013585228 | G16: =E16-C16 -> 0.20702958 | H16: =G16*$E$3 -> 22849.854
B17: 间接人工成本-辅助人员 | C17: 4.0843949 | D17: 3.0899348 | E17: =J130 -> 3.0669033 | F17: =E17-D17 -> -0.023031479 | G17: =E17-C17 -> -1.0174916 | H17: =G17*$E$3 -> -112300.55
B18: 固定人工-白领 | C18: 1.5123844 | D18: 1.435214 | E18: =J138 -> 0.72253638 | F18: =E18-D18 -> -0.71267765 | G18: =E18-C18 -> -0.78984803 | H18: =G18*$E$3 -> -87175.527
B19: 半固定-班车/工作服 | C19: 1.49553 | D19: 1.4907828 | E19: =J153 -> 1.8458532 | F19: =E19-D19 -> 0.35507043 | G19: =E19-C19 -> 0.35032321 | H19: =G19*$E$3 -> 38665.173 | I19: 同期出售有形资产会冲10万欧
B20: 直接人工 | C20: 5.8066935 | D20: 5.4271697 | E20: =J46 -> 6.0041188 | F20: =E20-D20 -> 0.57694907 | G20: =E20-C20 -> 0.19742531 | H20: =G20*$E$3 -> 21789.831
B21: 可回收废料 | C21: 0.38762542 | D21: 0.56838499 | E21: =J51 -> 0.53578518 | F21: =E21-D21 -> -0.032599815 | G21: =E21-C21 -> 0.14815976 | H21: =G21*$E$3 -> 16352.392
B22: 生产耗用品 | C22: -0.10165007 | D22: 0.3114159 | E22: =J112 -> 0.10809033 | F22: =E22-D22 -> -0.20332556 | G22: =E22-C22 -> 0.2097404 | H22: =G22*$E$3 -> 23149.048
B23: 废品回收 | C23: -0.85710945 | D23: -0.66902141 | E23: =J116 -> -0.76342865 | F23: =E23-D23 -> -0.094407238 | G23: =E23-C23 -> 0.093680798 | H23: =G23*$E$3 -> 10339.55
B24: 变动能源费 | C24: 0.74235218 | D24: 0.75561954 | E24: =J122 -> 0.31143073 | F24: =E24-D24 -> -0.44418881 | G24: =E24-C24 -> -0.43092145 | H24: =G24*$E$3 -> -47560.801
B25: 分摊费用 | C25: 4.6075922 | D25: 2.0554456 | E25: =J233 -> 1.7674608 | F25: =E25-D25 -> -0.28798476 | G25: =E25-C25 -> -2.8401314 | H25: =G25*$E$3 -> -313465.3
A26: Type 类型 | B26: Code 编码 | C26: Description(EN) 描述 | D26: Description(CN) 描述 | E26: 单位-千欧 | F26: 同期订单量 | G26: 98687 | H26: 预测订单量 | I26: 104704.08 | J26: 实际订单量 | K26: 110370
E27: MFG 2025 同期制造费 | F27: CPU 2025 同期单台 | G27: Budget 2026 预算 | H27: Budget-CPU 2026 单台预算 | I27: ACT 2026 实际 | J27: ACT-CPU 2026 单台实际 | K27: CPU-Y0Y 单台同期 | L27: Budget-ACT VARIANCE 预算同比 | M27: CPU-Y0Y Analysis 单台同期分析 | N27: Budget-ACT VARIANCE Analysis 预算实际分析
A28: 折旧 | B28: 6666110101 | C28: 6666110101 Depreciation of buildings | D28: 建筑物折旧 | E28: 71.56655 | F28: =E28/$G$26*1000 -> 0.72518721 | G28: 71.809392 | H28: =G28/$I$26*1000 -> 0.68583182 | I28: 70.89159 | J28: =I28/$K$26*1000 -> 0.64230851 | K28: =J28-F28 -> -0.0828787 | L28: =K28-H28 -> -0.76871052
B29: 6666110106 | C29: 6666110106 Depreciation of R&D facilities | D29: 研发设施折旧 | E29: 0 | F29: =E29/$G$26*1000 -> 0 | G29: 0 | H29: =G29/$I$26*1000 -> 0 | I29: 0 | J29: =I29/$K$26*1000 -> 0 | K29: =J29-F29 -> 0 | L29: =K29-H29 -> 0
B30: 6666110107 | C30: 6666110107 Depreciation of mold | D30: 模具折旧 | E30: 209.39447 | F30: =E30/$G$26*1000 -> 2.121804 | G30: 207.27444 | H30: =G30/$I$26*1000 -> 1.9796214 | I30: 164.91769 | J30: =I30/$K$26*1000 -> 1.4942257 | K30: =J30-F30 -> -0.62757829 | L30: =K30-H30 -> -2.6071997
B31: 6666110110 | C31: 6666110110 Depreciation-Plant & Machinery | D31: 6666110110 折旧-厂房及机械 | E31: 408.33684 | F31: =E31/$G$26*1000 -> 4.1376964 | G31: 444.21031 | H31: =G31/$I$26*1000 -> 4.2425309 | I31: 154.5351 | J31: =I31/$K$26*1000 -> 1.4001549 | K31: =J31-F31 -> -2.7375414 | L31: =K31-H31 -> -6.9800723
B32: 6666110112 | C32: 6666110112 Depreciation of Furniture & Fixture | D32: 6666110112 家具及装置折旧 | E32: 41.67962 | F32: =E32/$G$26*1000 -> 0.42234154 | G32: 60.495615 | H32: =G32/$I$26*1000 -> 0.57777704 | I32: 43.61875 | J32: =I32/$K$26*1000 -> 0.39520477 | K32: =J32-F32 -> -0.027136779 | L32: =K32-H32 -> -0.60491382
B33: 6666110204 | C33: 6666110204 Amortization of license, trademarks and | D33: 6666110204 许可证、商标及摊销 | E33: 2.81414 | F33: =E33/$G$26*1000 -> 0.028515813 | G33: 32.190765 | H33: =G33/$I$26*1000 -> 0.30744517 | I33: 2.81414 | J33: =I33/$K$26*1000 -> 0.025497327 | K33: =J33-F33 -> -0.0030184854 | L33: =K33-H33 -> -0.31046366
B34: 6666110207 | C34: 6666110207 Amortization of Software | D34: 6666110207 软件摊销 | E34: 29.03388 | F34: =E34/$G$26*1000 -> 0.29420167 | G34: 0 | H34: =G34/$I$26*1000 -> 0 | I34: 29.85735 | J34: =I34/$K$26*1000 -> 0.27052052 | K34: =J34-F34 -> -0.023681146 | L34: =K34-H34 -> -0.023681146
B35: 6666110506 | C35: 6666110506 Amortization-Leasehold Improvement | D35: 6666110506 租赁改良摊销 | E35: 3.05401 | F35: =E35/$G$26*1000 -> 0.030946427 | G35: 0 | H35: =G35/$I$26*1000 -> 0 | I35: 0 | J35: =I35/$K$26*1000 -> 0 | K35: =J35-F35 -> -0.030946427 | L35: =K35-H35 -> -0.030946427
B36: 6666110206 | C36: 6666110206 Amortization of Patents | D36: 6666110206 专利摊销 | E36: 0.13673 | F36: =E36/$G$26*1000 -> 0.0013854915 | G36: 0 | H36: =G36/$I$26*1000 -> 0 | I36: 0.05933 | J36: =I36/$K$26*1000 -> 0.0005375555 | K36: =J36-F36 -> -0.00084793601 | L36: =K36-H36 -> -0.00084793601
B37: FIX | C37: * CS_Depreciation | D37: * CS_折旧 | E37: 766.01624 | F37: =E37/$G$26*1000 -> 7.7620785 | G37: =SUM(G28:G36) -> 815.98052 | H37: =G37/$I$26*1000 -> 7.7932063 | I37: =SUM(I28:I36) -> 466.69395 | J37: =I37/$K$26*1000 -> 4.2284493 | K37: =J37-F37 -> -3.5336292 | L37: =K37-H37 -> -11.326836
A38: 直接人工 | B38: 5001010205 | C38: 5001010205 Unemployment Insurance -blue collar-Dire | D38: 5001010205 失业保险-蓝领-直接 | E38: 9.43698 | F38: =E38/$G$26*1000 -> 0.095625361 | G38: 9.2379411 | H38: =G38/$I$26*1000 -> 0.088229043 | I38: 11.428825 | J38: =I38/$K$26*1000 -> 0.10355011 | K38: =J38-F38 -> 0.0079247468 | L38: =K38-H38 -> -0.080304296
B39: 6666010380 | C39: 6666010380 Incentive | D39: 6666010380 激励 | E39: -1.59333 | F39: =E39/$G$26*1000 -> -0.016145288 | G39: -23.715861 | H39: =G39/$I$26*1000 -> -0.22650369 | I39: -2.39392 | J39: =I39/$K$26*1000 -> -0.021689952 | K39: =J39-F39 -> -0.0055446644 | L39: =K39-H39 -> 0.22095903
B40: 6666010019 | C40: 6666010019 Payroll Taxes - Blue Collar Direct | D40: 6666010019 工资税-蓝领直接 | E40: 76.40214 | F40: =E40/$G$26*1000 -> 0.77418647 | G40: 95.843639 | H40: =G40/$I$26*1000 -> 0.91537632 | I40: 91.996676 | J40: =I40/$K$26*1000 -> 0.83352973 | K40: =J40-F40 -> 0.05934326 | L40: =K40-H40 -> -0.85603306
B41: 6666010183 | C41: 6666010183 Overtime-Blue Collar-Direct | D41: 6666010183 加班费-蓝领-直接 | E41: 13.90994 | F41: =E41/$G$26*1000 -> 0.14095007 | G41: 0 | H41: =G41/$I$26*1000 -> 0 | I41: 22.83766 | J41: =I41/$K$26*1000 -> 0.20691909 | K41: =J41-F41 -> 0.06596902 | L41: =K41-H41 -> 0.06596902
B42: 6666010229 | C42: 6666010229 Staff Leaving Indemnity - Blue Collar Di | D42: 6666010229 蓝领离职赔偿-直接 | E42: 19.48446 | F42: =E42/$G$26*1000 -> 0.19743695 | G42: 17.415086 | H42: =G42/$I$26*1000 -> 0.16632671 | I42: 19.53584 | J42: =I42/$K$26*1000 -> 0.17700317 | K42: =J42-F42 -> -0.020433776 | L42: =K42-H42 -> -0.18676049
B43: 6666010188 | C43: 6666010188 Salary - Blue collar direct employees | D43: 6666010188 蓝领直接员工工资 | E43: 453.67223 | F43: =E43/$G$26*1000 -> 4.597082 | G43: 469.46557 | H43: =G43/$I$26*1000 -> 4.483737 | I43: 514.7873 | J43: =I43/$K$26*1000 -> 4.6641959 | K43: =J43-F43 -> 0.067113894 | L43: =K43-H43 -> -4.4166231
B44: 5102040406 | C44: 5102040406 Other revenue-Service/Secondment agreeme | D44: 5102040406 其他收入-服务/派遣协议 | E44: 0 | F44: =E44/$G$26*1000 -> 0 | G44: 0 | H44: =G44/$I$26*1000 -> 0 | I44: 0 | J44: =I44/$K$26*1000 -> 0 | K44: =J44-F44 -> 0 | L44: =K44-H44 -> 0
B45: 6666010115 | C45: 6666010115 Salary-Blue collar direct employees-Accr | D45: 6666010115 蓝领直接员工工资-计提 | E45: 1.73274 | F45: =E45/$G$26*1000 -> 0.017557936 | G45: 0 | H45: =G45/$I$26*1000 -> 0 | I45: 4.48221 | J45: =I45/$K$26*1000 -> 0.040610764 | K45: =J45-F45 -> 0.023052828 | L45: =K45-H45 -> 0.023052828
B46: VAR | C46: * CS_Direct Labour | D46: * CS_直接劳动 | E46: =SUM(E38:E45) -> 573.04516 | F46: =E46/$G$26*1000 -> 5.8066935 | G46: =SUM(G38:G45) -> 568.24638 | H46: =G46/$I$26*1000 -> 5.4271654 | I46: =SUM(I38:I45) -> 662.67459 | J46: =I46/$K$26*1000 -> 6.0041188 | K46: =J46-F46 -> 0.19742531 | L46: =K46-H46 -> -5.2297401
A47: 可回收废料 | B47: 8701530201 | C47: 8701530201 Scrap-Raw Material - Managerial | D47: 8701530201 废料-原材料-管理 | E47: 0 | F47: =E47/$G$26*1000 -> 0 | G47: 0 | H47: =G47/$I$26*1000 -> 0 | I47: 0 | J47: =I47/$K$26*1000 -> 0 | K47: =J47-F47 -> 0 | L47: =K47-H47 -> 0
B48: 6666050309 | C48: 6666050309 SFG scrap | D48: 6666050309 SFG废料 | E48: 33.41447 | F48: =E48/$G$26*1000 -> 0.33859039 | G48: 0 | H48: =G48/$I$26*1000 -> 0 | I48: 48.09227 | J48: =I48/$K$26*1000 -> 0.43573679 | K48: =J48-F48 -> 0.097146403 | L48: =K48-H48 -> 0.097146403
B49: 6666050308 | C49: 6666050308 Raw material scrap | D49: 6666050308 原材料废料 | E49: 4.83912 | F49: =E49/$G$26*1000 -> 0.04903503 | G49: 59.512182 | H49: =G49/$I$26*1000 -> 0.56838454 | I49: 10.61223 | J49: =I49/$K$26*1000 -> 0.0961514 | K49: =J49-F49 -> 0.04711637 | L49: =K49-H49 -> -0.52126817
B50: 6666050306 | C50: 6666050306 Finished goods scrap | D50: 6666050306 完工产品废料 | E50: 0 | F50: =E50/$G$26*1000 -> 0 | G50: 0 | H50: =G50/$I$26*1000 -> 0 | I50: 0.43011 | J50: =I50/$K$26*1000 -> 0.0038969829 | K50: =J50-F50 -> 0.0038969829 | L50: =K50-H50 -> 0.0038969829
B51: VAR | C51: * CS_SCRAP_VARIABLE | D51: * CS_ 废料_VARIABLE | E51: =SUM(E47:E50) -> 38.25359 | F51: =E51/$G$26*1000 -> 0.38762542 | G51: =SUM(G47:G50) -> 59.512182 | H51: =G51/$I$26*1000 -> 0.56838454 | I51: =SUM(I47:I50) -> 59.13461 | J51: =I51/$K$26*1000 -> 0.53578518 | K51: =J51-F51 -> 0.14815976 | L51: =K51-H51 -> -0.42022478
A52: 组织运营 | B52: 5102010151 | C52: 5102010151 Other Rev.-Interco-Epidemic problem comp | D52: 5102010151 其他收入-集团间-疫情问题补偿 | E52: 0 | F52: =E52/$G$26*1000 -> 0 | G52: 0 | H52: =G52/$I$26*1000 -> 0 | I52: 0 | J52: =I52/$K$26*1000 -> 0 | K52: =J52-F52 -> 0 | L52: =K52-H52 -> 0
B53: 5001010200 | C53: 5001010200 Cost of Manufacture - Raw Material | D53: 5001010200 制造成本-原材料 | E53: 6.86069 | F53: =E53/$G$26*1000 -> 0.069519694 | G53: 0 | H53: =G53/$I$26*1000 -> 0 | I53: 0 | J53: =I53/$K$26*1000 -> 0 | K53: =J53-F53 -> -0.069519694 | L53: =K53-H53 -> -0.069519694
B54: 5001010201 | C54: 5001010201 Cost of Manufacture - Raw Material-Freig | D54: 5001010201 制造成本-原材料-运费 | E54: 0 | F54: =E54/$G$26*1000 -> 0 | G54: 0 | H54: =G54/$I$26*1000 -> 0 | I54: 0 | J54: =I54/$K$26*1000 -> 0 | K54: =J54-F54 -> 0 | L54: =K54-H54 -> 0
B55: 5207000011 | C55: 5207000011 Gain of tangible asset disposal | D55: 5207000011 有形资产处置收益 | E55: 4.25402 | F55: =E55/$G$26*1000 -> 0.043106184 | G55: 0 | H55: =G55/$I$26*1000 -> 0 | I55: -0.15632 | J55: =I55/$K$26*1000 -> -0.0014163269 | K55: =J55-F55 -> -0.044522511 | L55: =K55-H55 -> -0.044522511
B56: 5207000012 | C56: 5207000012 Loss of tangible asset sold | D56: 5207000012 出售有形资产损失 | E56: -95.99121 | F56: =E56/$G$26*1000 -> -0.97268343 | G56: 0 | H56: =G56/$I$26*1000 -> 0 | I56: 0 | J56: =I56/$K$26*1000 -> 0 | K56: =J56-F56 -> 0.97268343 | L56: =K56-H56 -> 0.97268343
B57: 5207000022 | C57: 5207000022 Loss of intangible asset disposal | D57: 5207000022 无形资产处置损失 | E57: 0 | F57: =E57/$G$26*1000 -> 0 | G57: 0 | H57: =G57/$I$26*1000 -> 0 | I57: 0 | J57: =I57/$K$26*1000 -> 0 | K57: =J57-F57 -> 0 | L57: =K57-H57 -> 0
B58: 5301060000 | C58: 5301060000 Other Income-Subsidy income | D58: 5301060000 其他收入-补贴收入 | E58: -1.96387 | F58: =E58/$G$26*1000 -> -0.019899987 | G58: 0 | H58: =G58/$I$26*1000 -> 0 | I58: -3.09566 | J58: =I58/$K$26*1000 -> -0.02804802 | K58: =J58-F58 -> -0.0081480335 | L58: =K58-H58 -> -0.0081480335
B59: 5301999999 | C59: 5301999999 Non-operation revenue-Other | D59: 5301999999 非经营收入-其他 | E59: 0 | F59: =E59/$G$26*1000 -> 0 | G59: 0 | H59: =G59/$I$26*1000 -> 0 | I59: -0.30976 | J59: =I59/$K$26*1000 -> -0.0028065598 | K59: =J59-F59 -> -0.0028065598 | L59: =K59-H59 -> -0.0028065598
B60: 5405030000 | C60: 5405030000 Other cost-others | D60: 5405030000 其他成本-其他 | E60: -1.42682 | F60: =E60/$G$26*1000 -> -0.014458034 | G60: 0 | H60: =G60/$I$26*1000 -> 0 | I60: -1.8900437e-15 | J60: =I60/$K$26*1000 -> -1.7124614e-17 | K60: =J60-F60 -> 0.014458034 | L60: =K60-H60 -> 0.014458034
B61: 5601050000 | C61: 5601050000 Non-Operating Expense - Penalty | D61: 5601050000 非经营费用-罚款 | E61: 0 | F61: =E61/$G$26*1000 -> 0 | G61: 0 | H61: =G61/$I$26*1000 -> 0 | I61: 0 | J61: =I61/$K$26*1000 -> 0 | K61: =J61-F61 -> 0 | L61: =K61-H61 -> 0
B62: 5601050100 | C62: 5601050100 Non-operation Expense-Others | D62: 5601050100 非经营费用-其他 | E62: 0.00052 | F62: =E62/$G$26*1000 -> 5.2691844e-06 | G62: 0 | H62: =G62/$I$26*1000 -> 0 | I62: 0 | J62: =I62/$K$26*1000 -> 0 | K62: =J62-F62 -> -5.2691844e-06 | L62: =K62-H62 -> -5.2691844e-06
B63: 5102040893 | C63: 5102040893 Other revenue-Charge out-Test Expense | D63: 5102040893 其他收入-费用支出-测试费用 | E63: 0 | F63: =E63/$G$26*1000 -> 0 | G63: 0 | H63: =G63/$I$26*1000 -> 0 | I63: 0 | J63: =I63/$K$26*1000 -> 0 | K63: =J63-F63 -> 0 | L63: =K63-H63 -> 0
B64: 5801000041 | C64: 5801000041 Previous year Sundry cost | D64: 5801000041 前一年杂项成本 | E64: 0 | F64: =E64/$G$26*1000 -> 0 | G64: 0 | H64: =G64/$I$26*1000 -> 0 | I64: 0 | J64: =I64/$K$26*1000 -> 0 | K64: =J64-F64 -> 0 | L64: =K64-H64 -> 0
... B72: 6666020302 | C72: 6666020302 Communication Expenses | D72: 6666020302 通讯费用 | E72: 0 | F72: =E72/$G$26*1000 -> 0 | G72: 1.1677344 | H72: =G72/$I$26*1000 -> 0.011152712 | I72: 0 | J72: =I72/$K$26*1000 -> 0 | K72: =J72-F72 -> 0 | L72: =K72-H72 -> -0.011152712
B73: 6666020403 | C73: 6666020403 Company car expense | D73: 6666020403 公司车辆费用 | E73: 0 | F73: =E73/$G$26*1000 -> 0 | G73: 0 | H73: =G73/$I$26*1000 -> 0 | I73: 0 | J73: =I73/$K$26*1000 -> 0 | K73: =J73-F73 -> 0 | L73: =K73-H73 -> 0
B74: 6666020405 | C74: 6666020405 Company car expense - maintenance fees | D74: 6666020405 公司车辆费用-维护费 | E74: 0 | F74: =E74/$G$26*1000 -> 0 | G74: 0 | H74: =G74/$I$26*1000 -> 0 | I74: 0 | J74: =I74/$K$26*1000 -> 0 | K74: =J74-F74 -> 0 | L74: =K74-H74 -> 0
B75: 6666020495 | C75: 6666020495 Non-deductible expense-travel. | D75: 6666020495 不可抵扣费用-旅行 | E75: 0.44353 | F75: =E75/$G$26*1000 -> 0.0044943103 | G75: 0 | H75: =G75/$I$26*1000 -> 0 | I75: 0.25046 | J75: =I75/$K$26*1000 -> 0.0022692761 | K75: =J75-F75 -> -0.0022250342 | L75: =K75-H75 -> -0.0022250342
B76: 6666020504 | C76: 6666020504 Newspaper and Periodicals expenditure | D76: 6666020504 报纸和期刊支出 | E76: 0 | F76: =E76/$G$26*1000 -> 0 | G76: 0 | H76: =G76/$I$26*1000 -> 0 | I76: 0 | J76: =I76/$K$26*1000 -> 0 | K76: =J76-F76 -> 0 | L76: =K76-H76 -> 0
B77: 6666020508 | C77: 6666020508 Postage | D77: 6666020508 邮资 | E77: 0 | F77: =E77/$G$26*1000 -> 0 | G77: 0 | H77: =G77/$I$26*1000 -> 0 | I77: 0.00139 | J77: =I77/$K$26*1000 -> 1.2594002e-05 | K77: =J77-F77 -> 1.2594002e-05 | L77: =K77-H77 -> 1.2594002e-05
B78: 6666020602 | C78: 6666020602 Training costs Outside the group | D78: 6666020602 集团外培训费用 | E78: 2.05633 | F78: =E78/$G$26*1000 -> 0.020836888 | G78: 0.38211934 | H78: =G78/$I$26*1000 -> 0.0036495171 | I78: 0 | J78: =I78/$K$26*1000 -> 0 | K78: =J78-F78 -> -0.020836888 | L78: =K78-H78 -> -0.024486405
B79: 6666020701 | C79: 6666020701 Enterprise Property Insurance | D79: 6666020701 企业财产保险 | E79: 0 | F79: =E79/$G$26*1000 -> 0 | G79: 0 | H79: =G79/$I$26*1000 -> 0 | I79: 0 | J79: =I79/$K$26*1000 -> 0 | K79: =J79-F79 -> 0 | L79: =K79-H79 -> 0
B80: 6666020802 | C80: 6666020802 Equipment rental cost | D80: 6666020802 设备租赁费用 | E80: 23.699 | F80: =E80/$G$26*1000 -> 0.24014308 | G80: 20.409 | H80: =G80/$I$26*1000 -> 0.19492076 | I80: 20.41218 | J80: =I80/$K$26*1000 -> 0.18494319 | K80: =J80-F80 -> -0.055199888 | L80: =K80-H80 -> -0.25012065 | M80: 这个和叉车减少有关系吗
B81: 6666020803 | C81: 6666020803 Car rental cost | D81: 6666020803 汽车租赁费用 | E81: 7.13547 | F81: =E81/$G$26*1000 -> 0.072304052 | G81: 3.2852648 | H81: =G81/$I$26*1000 -> 0.031376664 | I81: 4.45253 | J81: =I81/$K$26*1000 -> 0.04034185 | K81: =J81-F81 -> -0.031962202 | L81: =K81-H81 -> -0.063338866
B82: 6666021100 | C82: 6666021100 Consulting fees | D82: 6666021100 咨询费 | E82: 8.48654 | F82: =E82/$G$26*1000 -> 0.085994508 | G82: 16.781042 | H82: =G82/$I$26*1000 -> 0.16027113 | I82: 16.83585 | J82: =I82/$K$26*1000 -> 0.15254009 | K82: =J82-F82 -> 0.066545585 | L82: =K82-H82 -> -0.093725546 | M82: 这个为什么
B83: 6666021104 | C83: 6666021104 Consulting expense-Technical | D83: 6666021104 咨询费用-技术 | E83: 0 | F83: =E83/$G$26*1000 -> 0 | G83: 0 | H83: =G83/$I$26*1000 -> 0 | I83: 0 | J83: =I83/$K$26*1000 -> 0 | K83: =J83-F83 -> 0 | L83: =K83-H83 -> 0
B84: 6666021902 | C84: 6666021902 Cleaning fees | D84: 6666021902 清洁费 | E84: 16.72079 | F84: =E84/$G$26*1000 -> 0.16943255 | G84: 10.325614 | H84: =G84/$I$26*1000 -> 0.098617108 | I84: 11.66625 | J84: =I84/$K$26*1000 -> 0.10570128 | K84: =J84-F84 -> -0.063731272 | L84: =K84-H84 -> -0.16234838 | M84: 这个为什么，有什么降费项目吗
B85: 6666022100 | C85: 6666022100 Security | D85: 6666022100 安全 | E85: 15.04888 | F85: =E85/$G$26*1000 -> 0.15249101 | G85: 13.062278 | H85: =G85/$I$26*1000 -> 0.12475423 | I85: 13.37186 | J85: =I85/$K$26*1000 -> 0.12115484 | K85: =J85-F85 -> -0.031336164 | L85: =K85-H85 -> -0.1560904
B86: 6666022300 | C86: 6666022300 Association dues | D86: 6666022300 协会会费 | E86: 0 | F86: =E86/$G$26*1000 -> 0 | G86: 0 | H86: =G86/$I$26*1000 -> 0 | I86: 0 | J86: =I86/$K$26*1000 -> 0 | K86: =J86-F86 -> 0 | L86: =K86-H86 -> 0
B87: 6666029700 | C87: 6666029700 Service fee recharge | D87: 6666029700 服务费充值 | E87: 0 | F87: =E87/$G$26*1000 -> 0 | G87: 0 | H87: =G87/$I$26*1000 -> 0 | I87: 0 | J87: =I87/$K$26*1000 -> 0 | K87: =J87-F87 -> 0 | L87: =K87-H87 -> 0
B88: 6666029900 | C88: 6666029900 Sundry Expenses | D88: 6666029900 杂项费用 | E88: 0.00385 | F88: =E88/$G$26*1000 -> 3.9012231e-05 | G88: 0 | H88: =G88/$I$26*1000 -> 0 | I88: -0.01671 | J88: =I88/$K$26*1000 -> -0.00015139984 | K88: =J88-F88 -> -0.00019041207 | L88: =K88-H88 -> -0.00019041207
B89: 6666029996 | C89: 6666029996 Non-deductible expense-travel. | D89: 6666029996 不可抵扣费用-旅行 | E89: 0.18828 | F89: =E89/$G$26*1000 -> 0.0019078501 | G89: 0 | H89: =G89/$I$26*1000 -> 0 | I89: 0.0471 | J89: =I89/$K$26*1000 -> 0.0004267464 | K89: =J89-F89 -> -0.0014811037 | L89: =K89-H89 -> -0.0014811037
B90: 6666029997 | C90: 6666029997 restructure cost | D90: 6666029997 重组成本 | E90: 0 | F90: =E90/$G$26*1000 -> 0 | G90: 0 | H90: =G90/$I$26*1000 -> 0 | I90: 6.84197 | J90: =I90/$K$26*1000 -> 0.061991211 | K90: =J90-F90 -> 0.061991211 | L90: =K90-H90 -> 0.061991211
B91: 6666030702 | C91: 6666030702 R&D prototype purchased | D91: 6666030702 研发原型采购 | E91: 0 | F91: =E91/$G$26*1000 -> 0 | G91: 0 | H91: =G91/$I$26*1000 -> 0 | I91: 0 | J91: =I91/$K$26*1000 -> 0 | K91: =J91-F91 -> 0 | L91: =K91-H91 -> 0
B92: 6666031200 | C92: 6666031200 Instrument fee | D92: 6666031200 仪器费用 | E92: 0 | F92: =E92/$G$26*1000 -> 0 | G92: 0 | H92: =G92/$I$26*1000 -> 0 | I92: 0 | J92: =I92/$K$26*1000 -> 0 | K92: =J92-F92 -> 0 | L92: =K92-H92 -> 0
B93: 6666050107 | C93: 6666050107 Special distribution costs | D93: 6666050107 特殊分配成本 | E93: 0 | F93: =E93/$G$26*1000 -> 0 | G93: 0 | H93: =G93/$I$26*1000 -> 0 | I93: 0 | J93: =I93/$K$26*1000 -> 0 | K93: =J93-F93 -> 0 | L93: =K93-H93 -> 0
B94: 6666070100 | C94: 6666070100 Software purchase, development and imple | D94: 6666070100 软件购买、开发及实施 | E94: 0 | F94: =E94/$G$26*1000 -> 0 | G94: 0 | H94: =G94/$I$26*1000 -> 0 | I94: 0 | J94: =I94/$K$26*1000 -> 0 | K94: =J94-F94 -> 0 | L94: =K94-H94 -> 0
B95: 6666070300 | C95: 6666070300 Software maintenance fees | D95: 6666070300 软件维护费 | E95: 0 | F95: =E95/$G$26*1000 -> 0 | G95: 0 | H95: =G95/$I$26*1000 -> 0 | I95: 0 | J95: =I95/$K$26*1000 -> 0 | K95: =J95-F95 -> 0 | L95: =K95-H95 -> 0
B96: 6666070400 | C96: 6666070400 IT maint. & repairs hardware | D96: 6666070400 IT维护与硬件修理 | E96: 16.89738 | F96: =E96/$G$26*1000 -> 0.17122194 | G96: 12.9 | H96: =G96/$I$26*1000 -> 0.12320436 | I96: 4.97443 | J96: =I96/$K$26*1000 -> 0.04507049 | K96: =J96-F96 -> -0.12615145 | L96: =K96-H96 -> -0.24935582 | M96: 没有费用为什么
B97: 5401050201 | C97: 5401050201 COGS-Special a | D97: 5401050201 COGS-特殊a | E97: 0 | F97: =E97/$G$26*1000 -> 0 | G97: 0 | H97: =G97/$I$26*1000 -> 0 | I97: 0 | J97: =I97/$K$26*1000 -> 0 | K97: =J97-F97 -> 0 | L97: =K97-H97 -> 0
B98: 5401020212 | C98: 5401020212 Local Transpor | D98: 5401020212 本地运输 | E98: 0 | F98: =E98/$G$26*1000 -> 0 | G98: 0 | H98: =G98/$I$26*1000 -> 0 | I98: 0 | J98: =I98/$K$26*1000 -> 0 | K98: =J98-F98 -> 0 | L98: =K98-H98 -> 0
B99: 6666050320 | C99: 6666050320 Reworking costs | D99: 6666050320 再加工成本 | E99: 0.0765 | G99: 0 | I99: 0 | J99: =I99/$K$26*1000 -> 0 | K99: =J99-F99 -> 0 | L99: =K99-H99 -> 0
B100: 6666093800 | C100: 6666093800 Other Taxes-CIT Deductible | D100: 6666093800 其他税项-可抵扣公司税 | E100: 0 | G100: 0 | I100: 0 | J100: =I100/$K$26*1000 -> 0 | K100: =J100-F100 -> 0 | L100: =K100-H100 -> 0
B101: 5601080000 | C101: 5601080000 Non-operating expense-VAT non-deductible | D101: 5601080000 非经营性支出-不可抵扣增值税 | E101: 3.03288 | G101: 0 | I101: 0 | J101: =I101/$K$26*1000 -> 0 | K101: =J101-F101 -> 0 | L101: =K101-H101 -> 0
B102: 6666040215 | C102: 6666040215 Product sample fee | D102: 6666040215 产品样品费用 | E102: 0 | G102: 0 | I102: 0 | J102: =I102/$K$26*1000 -> 0 | K102: =J102-F102 -> 0 | L102: =K102-H102 -> 0
B103: 6666020403 | C103: 6666020403 Company car expense | D103: 6666020403 公司车辆费用 | E103: 0 | G103: 0 | I103: 0 | J103: =I103/$K$26*1000 -> 0 | K103: =J103-F103 -> 0 | L103: =K103-H103 -> 0
B104: 6666021200 | C104: 6666021200 Audit fee | D104: 6666021200 审计费用 | E104: 0 | G104: 0 | I104: 0 | J104: =I104/$K$26*1000 -> 0 | K104: =J104-F104 -> 0 | L104: =K104-H104 -> 0
B105: 6666050202 | C105: 6666050202 Custom clearance charge | D105: 6666050202 海关清关费用 | E105: 0 | G105: 0 | I105: -0.04123 | J105: =I105/$K$26*1000 -> -0.00037356166 | K105: =J105-F105 -> -0.00037356166 | L105: =K105-H105 -> -0.00037356166
B106: 5401050201 | C106: 5401050201 COGS-Freight out-Special and sporadic fr | D106: 5401050201 COGS-特殊和零星运费 | E106: 0 | G106: 0 | I106: 0 | J106: =I106/$K$26*1000 -> 0 | K106: =J106-F106 -> 0 | L106: =K106-H106 -> 0
B107: FIX | C107: * CS_Fix Cost | D107: * CS_Fix Cost | E107: =SUM(E52:E106) -> 12.28085 | F107: =E107/$G$26*1000 -> 0.12444243 | G107: =SUM(G52:G106) -> 92.470771 | H107: =G107/$I$26*1000 -> 0.88316299 | I107: =SUM(I52:I106) -> 82.67387 | J107: =I107/$K$26*1000 -> 0.74906107 | K107: =J107-F107 -> 0.62461864 | L107: =K107-H107 -> -0.25854435
...

Sheet 厨电5月 
C1: 5月费用实际：_x000b_①单台：5月实际31.18欧，5月同期30.17欧。较同期↑1欧，恶化7万。_x000b_②主要影响：人工工资上涨及通胀影响约12万欧；_x000b_③扣除影响后：单台↓0.74欧，降费约5万欧 ④变动费用异常：G＆A单台较预测差异8.3万欧，原因：1.汇率更正，本地币发票折算欧元时产生更正-5.7万欧， 2.协会费重复计提,由于计提周期错误导致，本月重复计入下月冲，差异1.3WAN1OU1 2.固定人工-白领差异2.8万欧，原因：白领MBO相关计提本月未冲回,影响约 +28K
A2: 维度 | B2: KPI | C2: 同期 | D2: 预测 | E2: 26年实际 | F2: 预算差异 | G2: 实际比同期差异 | H2: 制造费差额 | I2: 差异原因
A3: 单 | B3: 产量 | C3: =H27 -> 93353 | D3: =J27 -> 71805.083 | E3: =L27 -> 67531 | F3: =E3-D3 -> -4274.0833 | G3: =E3-C3 -> -25822
A4: 时 | B4: 工作天数 | C4: 20 | D4: 14 | E4: 14 | F4: =E4-D4 -> 0 | G4: =E4-C4 -> -6
B5: 人工 | C5: 293 | D5: 257.93476 | E5: 265 | F5: =E5-D5 -> 7.0652446 | G5: =E5-C5 -> -28
B6: 人工工资 | C6: =F44*1000/C5 -> 1741.1506 | D6: =H44*1000/D5 -> 2081.424 | E6: =(J46+J44)*1000/E5 -> 2187.8331 | F6: =E6-D6 -> 106.40906 | G6: =E6-C6 -> 446.68248 | H6: =(E6-C6)/C6 -> 0.25654443
B7: 间接人工 | C7: 178 | D7: 127 | E7: 113 | F7: =E7-D7 -> -14 | G7: =E7-C7 -> -65
B8: 间接人工工资 | C8: =(F130+F133)*1000/C7 -> 2079.3361 | D8: =(H133+H130)*1000/D7 -> 2207.0299 | E8: =J130*1000/E7 -> 0 | F8: =E8-D8 -> -2207.0299 | G8: =E8-C8 -> -2079.3361
B9: 白领人数 | C9: 53 | D9: 34 | E9: 28 | F9: =E9-D9 -> -6 | G9: =E9-C9 -> -25
B10: 白领人工工资 | C10: =(F136+F137)*1000/C9 -> 3184.9262 | D10: =H136*1000/D9 -> 4030.7127 | E10: =(J136+J137)*1000/E9 -> 5460.1136 | F10: =E10-D10 -> 1429.4008 | G10: =E10-C10 -> 2275.1873
A11: 效 | B11: UPPH | C11: =C3/C5/C4/7.5 -> 2.1240728 | D11: =D3/D5/D4/7.5 -> 2.6512826 | E11: =E3/E5/E4/7.5 -> 2.4269901 | F11: =E11-D11 -> -0.22429251 | G11: =E11-C11 -> 0.30291731
A12: 费 | B12: 单台制造费 | C12: =SUM(C13:C25) -> 30.165322 | D12: =SUM(D13:D25) -> 35.680742 | E12: =SUM(E13:E25) -> 31.175643 | F12: =E12-D12 -> -4.5050989 | G12: =E12-C12 -> 1.010322 | H12: =G12*$E$3 -> 68228.052
B13: 折旧（含FC） | C13: =G38 -> 8.9090543 | D13: =I38 -> 11.529895 | E13: =K38 -> 3.7662556 | F13: =E13-D13 -> -7.7636393 | G13: =E13-C13 -> -5.1427987 | H13: =G13*$E$3 -> -347298.34
B14: 运营费 | C14: =G111 -> 0.89697932 | D14: =I111 -> 1.2288016 | E14: =K111 -> 1.146286 | F14: =E14-D14 -> -0.082515639 | G14: =E14-C14 -> 0.24930669 | H14: =G14*$E$3 -> 16835.93
B15: 存货跌价准备 | C15: =G118 -> 0.30909323 | D15: =I118 -> 0.17408238 | E15: =K118 -> 0.23938636 | F15: =E15-D15 -> 0.065303973 | G15: =E15-C15 -> -0.069706871 | H15: =G15*$E$3 -> -4707.3747
B16: 固定能源费 | C16: =G122 -> 0.29473386 | D16: =I122 -> 0.37370656 | E16: =K122 -> 0.42110586 | F16: =E16-D16 -> 0.047399305 | G16: =E16-C16 -> 0.126372 | H16: =G16*$E$3 -> 8534.0277
B17: 间接人工成本-辅助人员 | C17: =G134 -> 4.8437531 | D17: =I134 -> 5.0117726 | E17: =K134 -> 5.4856978 | F17: =E17-D17 -> 0.47392524 | G17: =E17-C17 -> 0.64194476 | H17: =G17*$E$3 -> 43351.172
B18: 固定人工-白领 | C18: =G142 -> 2.1331402 | D18: =I142 -> 2.2099525 | E18: =K142 -> 2.6004268 | F18: =E18-D18 -> 0.39047423 | G18: =E18-C18 -> 0.46728654 | H18: =G18*$E$3 -> 31556.327
B19: 半固定-班车/工作服 | C19: =G158 -> 1.8280617 | D19: =I158 -> 2.0081557 | E19: =K158 -> 2.4795747 | F19: =E19-D19 -> 0.47141906 | G19: =E19-C19 -> 0.65151306 | H19: =G19*$E$3 -> 43997.328
B20: 直接人工 | C20: =G47 -> 6.9098795 | D20: =I47 -> 9.0167143 | E20: =K47 -> 10.749062 | F20: =E20-D20 -> 1.7323476 | G20: =E20-C20 -> 3.8391824 | H20: =G20*$E$3 -> 259263.83
B21: 可回收废料 | C21: =G52 -> 0.41056013 | D21: =I52 -> 0.56383241 | E21: =K52 -> 0.52963217 | F21: =E21-D21 -> -0.034200237 | G21: =E21-C21 -> 0.11907204 | H21: =G21*$E$3 -> 8041.0537
B22: 生产耗用品 | C22: =G116 -> -0.23774747 | D22: =I116 -> 0.47269173 | E22: =K116 -> 0.053795294 | F22: =E22-D22 -> -0.41889644 | G22: =E22-C22 -> 0.29154277 | H22: =G22*$E$3 -> 19688.175
B23: 废品回收 | C23: =G120 -> -0.97244845 | D23: =I120 -> -0.67075017 | E23: =K120 -> -1.0347467 | F23: =E23-D23 -> -0.36399654 | G23: =E23-C23 -> -0.062298261 | H23: =G23*$E$3 -> -4207.0638
B24: 变动能源费 | C24: =G126 -> 0.6753392 | D24: =I126 -> 0.7635213 | E24: =K126 -> 0.23170322 | F24: =E24-D24 -> -0.53181808 | G24: =E24-C24 -> -0.44363598 | H24: =G24*$E$3 -> -29959.181
B25: 分摊费用 | C25: =G243 -> 4.1649229 | D25: =I243 -> 2.9983665 | E25: =K243 -> 4.5074644 | F25: =E25-D25 -> 1.509098 | G25: =E25-C25 -> 0.3425415 | H25: =G25*$E$3 -> 23132.17
B26: 预测和实际的差（不考虑产量因素）： 总费用实际与4＋8预测差异16.0万欧 1,折旧费用：差异2.6万欧 2.变动费用：①直接人工：差异1.万欧 ②固定人工：差异3.5万欧 ③变动能源：差异1.4万欧 ④半固定：差异2.0万欧 ⑤间接人工：差异2.4万欧 3.园区分摊费用：差异8.3万欧
B27: Type 类型 | D27: Description(EN) 描述 | E27: Description(CN) 描述 | F27: 单位-千欧 | G27: 同期订单量 | H27: 93353 | I27: 预测订单量 | J27: 71805.083 | K27: 实际订单量 | L27: 67531
F28: MFG 2025 同期制造费 | G28: CPU 2025 同期单台 | H28: Budget 2026 预算 | I28: Budget-CPU 2026 单台预算 | J28: ACT 2026 实际 | K28: ACT-CPU 2026 单台实际 | L28: CPU-Y0Y 单台同期 | M28: Budget-ACT VARIANCE 预算同比 | N28: CPU-Y0Y Analysis 单台同期分析 | O28: Budget-ACT VARIANCE Analysis 预算实际分析 | P28: 26年预测制造费 | Q28: 26年预测单台 | R28: 费用差 | S28: 预测与实际单台差
B29: 折旧 | C29: 6666110101 | D29: 6666110101 Depreciation of buildings | E29: 建筑物折旧 | F29: 75.57859 | G29: =F29/$H$27*1000 -> 0.80960001 | H29: 73.934282 | I29: =H29/$J$27*1000 -> 1.0296525 | J29: 72.97519 | K29: =J29*1000/$L$27 -> 1.0806176 | L29: =K29-G29 -> 0.27101763 | M29: =K29-I29 -> 0.050965166 | P29: 23.577176 | Q29: 0.32469635
C30: 6666110106 | D30: 6666110106 Depreciation of R&D facilities | E30: 研发设施折旧 | F30: 0 | G30: =F30/$H$27*1000 -> 0 | H30: 0 | I30: =H30/$J$27*1000 -> 0 | J30: 0 | K30: =J30*1000/$L$27 -> 0 | L30: =K30-G30 -> 0 | M30: =K30-I30 -> 0 | P30: 0 | Q30: 0
C31: 6666110107 | D31: 6666110107 Depreciation of mold | E31: 模具折旧 | F31: 213.84525 | G31: =F31/$H$27*1000 -> 2.2907164 | H31: 208.70158 | I31: =H31/$J$27*1000 -> 2.9065015 | J31: -139.58229 | K31: =J31*1000/$L$27 -> -2.0669365 | L31: =K31-G31 -> -4.3576529 | M31: =K31-I31 -> -4.973438 | P31: 54.690127 | Q31: 0.75317267
