Workbook
Name \0: #REF!
Name \0: #REF!
Name \0: #REF!
Name \A: #REF!
Name \A: #REF!
Name \A: #REF!
Name \b: #REF!
Name \B: #REF!
Name \B: #REF!
Name \c: #REF!
Name \C: #REF!
Name \C: #REF!
Name \e: #REF!
Name \e: #REF!
Name \m: #REF!
Name \m: #REF!
Name \P: #REF!
Name \P: #REF!
Name \P: #REF!
Name \Q: #REF!
Name \Q: #REF!
Name \Q: #REF!
Name \R: #REF!
Name \R: #REF!
Name \R: #REF!
Name \s: #REF!
Name \S: #REF!
Name \S: #REF!
Name \t: #REF!
Name \T: #REF!
Name \T: #REF!
Name \v: #N/A
Name \w: #REF!
Name \w: #REF!
Name \x: #REF!
Name \X: #REF!
Name \X: #REF!
Name _: #REF!
Name _: #REF!
Name ___CNQ07: #REF!
Name ___CON1: #REF!
Name ___CON1: #REF!
Name ___CON1: #REF!
Name ___CON2: #REF!
Name ___CON2: #REF!
Name ___CON2: #REF!
Name ___ddn400: #REF!
Name ___ddn400: #REF!
Name ___ddn400: #REF!
Name ___ddn600: #REF!
Name ___ddn600: #REF!
Name ___ddn600: #REF!
Name ___E99999: #REF!
Name ___E99999: #REF!
Name ___E99999: #REF!
Name ___gon4: #REF!
Name ___gon4: #REF!
Name ___IV999999: #REF!
Name ___IV999999: #REF!
Name ___IV999999: #REF!

Sheet Instruction
B1: Actual Reporting
B2: 1. | C2: Please update copertura for the period / data entry - line 53 onwords
B3: 2. | C3: Please update the actual cost for the period / data entry - line 75 onwords
B4: 3. | C4: Update columns "Q" & "R" in the data entry and budget assumption tab
B6: 4. | C6: YTD and MTD variances, as well as the report is populated automatically
B7: 5. | C7: Please provide the rootcauses for the variances YTD and MTD Report (column J-P)
C8: Checkline in column "U" needs to be zero in each line
B9: 6. | C9: SAP extraction actual cost lines as separate sheet
B11: FCST Reporting
B13: 1. | C13: Please fill in the copertura and actuals for the upcoming months _ data entry tab - lines 53-94
B14: 2. | C14: FCST tab is populated automatically , please check the correctness
B15: 3. | C15: Provide root cause split for the upcoming periods variances
B16: 4. | C16: Paste values previous submitted FCST in "FCST25" sheet lines 47-87
B17: 5. | C17: Check variances vs last forecast in "FCST25" sheet lines 91-131
B18: 6. | C18: Update column AE & AF in "FCST CPU"
B19: 7. | C19: Update Material & Freight In part in "FCST CPU"

Sheet Root cause explanations
B2: Budget Cost | C2: Budgeted cost of the period @ Budget FX rate
B4: ACE | C4: Permanent saving, linked to ACE projects. This line needs to give us the deviation versus the budgeted ACE improvements
B6: MFG Efficiency | C6: Saving / Cost in relation with current year standard production process not linked to price , one off or ACE ; e.g delay of hiring , not spending the budget for a specific line or additional consumption due to breakdown etc
B8: S&OP | C8: Increase or decrease of cost due to volume fluctuations; Excess of Manpower, Additional / less vertical closure days impact, Incremental cost increase / decrease on the fixed cost due to volume change
B10: Price / Inflation | C10: Pure Price or Inflation impact
B12: fX translation | C12: fx impact act fx versus budget fx
B14: One off | C14: Extraordinary expense/income not linked to current year standard production process; previous years income/ loss, write off and sale of assets , one time expenses like restructuring program, cost related to opening ceremony, extra ordinary donations etc
B16: Oth Functions | C16: Cost related to claims , which in the past was recharged to R&D, Procurement , Logistics
B18: Actual Cost | C18: Actual cost of the period converted @ actual fx rate

Sheet HC 2026
A1: Headcount 2026 (ACT + FCST)
C3: Jan | D3: Feb | E3: March | F3: April | G3: May | H3: June | I3: July | J3: August | K3: Sept | L3: Oct | M3: Nov | N3: Dec | O3: Total
A4: Direct HC | B4: Production | C4: 236.73 | D4: 215 | E4: 132 | F4: 222 | G4: 261 | H4: =163+98 -> 261 | I4: 264 | J4: 264 | K4: 264 | L4: 242 | M4: 243 | N4: 245 | O4: =AVERAGE(C4:N4) -> 237.4775 | P4: FOR YTG 100 ISKUR HDC untl October
B5: Shared | O5: =AVERAGE(C5:N5) -> #DIV/0!
B6: Total | C6: =C4+C5 -> 236.73 | D6: =D4+D5 -> 215 | E6: =E4+E5 -> 132 | F6: =F4+F5 -> 222 | G6: =G4+G5 -> 261 | H6: =H4+H5 -> 261 | I6: =I4+I5 -> 264 | J6: =J4+J5 -> 264 | ... N6: =N4+N5 -> 245 | O6: =AVERAGE(C6:N6) -> 237.4775
B8: Assigned hours | O8: =AVERAGE(C8:N8) -> #DIV/0!
C10: Jan | D10: Feb | E10: March | F10: April | G10: May | H10: June | I10: July | J10: August | K10: Sept | L10: Oct | M10: Nov | N10: Dec | O10: Total
A11: Indirect HC | B11: Production | C11: 85 | D11: 82 | E11: 69 | F11: 79 | G11: 82 | H11: =81+1 -> 82 | I11: 84 | J11: 84 | K11: 84 | L11: 84 | M11: 84 | N11: 84 | O11: =AVERAGE(C11:N11) -> 81.916667
B12: Shared | O12: =AVERAGE(C12:N12) -> #DIV/0!
B13: Total | C13: =C11+C12 -> 85 | D13: =D11+D12 -> 82 | E13: =E11+E12 -> 69 | F13: =F11+F12 -> 79 | G13: =G11+G12 -> 82 | H13: =H11+H12 -> 82 | I13: =I11+I12 -> 84 | J13: =J11+J12 -> 84 | ... N13: =N11+N12 -> 84 | O13: =AVERAGE(C13:N13) -> 81.916667
C16: Jan | D16: Feb | E16: March | F16: April | G16: May | H16: June | I16: July | J16: August | K16: Sept | L16: Oct | M16: Nov | N16: Dec | O16: Total
A17: Fixed HC | B17: Production | C17: 22 | D17: 22 | E17: 22 | F17: 22 | G17: 22 | H17: 22 | I17: 22 | J17: 23 | K17: 23 | L17: 23 | M17: 23 | N17: 23 | O17: =AVERAGE(C17:N17) -> 22.416667
B18: Shared | C18: 3.5 | D18: 3.5 | E18: 3.5 | F18: 2.7 | G18: 2.7 | H18: 2.7 | I18: 3.5 | J18: 3.5 | K18: 3.5 | L18: 3.5 | M18: 3.5 | N18: 3.5 | O18: =AVERAGE(C18:N18) -> 3.3
B19: Lapro | O19: =AVERAGE(C19:N19) -> #DIV/0!
B20: Total | C20: =C17+C18+C19 -> 25.5 | D20: =D17+D18+D19 -> 25.5 | E20: =E17+E18+E19 -> 25.5 | F20: =F17+F18+F19 -> 24.7 | G20: =G17+G18+G19 -> 24.7 | H20: =H17+H18+H19 -> 24.7 | I20: =I17+I18+I19 -> 25.5 | J20: =J17+J18+J19 -> 26.5 | ... N20: =N17+N18+N19 -> 26.5 | O20: =AVERAGE(C20:N20) -> 25.716667
C22: =SUM(C17:C18) -> 25.5 | D22: =SUM(D17:D18) -> 25.5 | E22: =SUM(E17:E18) -> 25.5 | F22: =SUM(F17:F18) -> 24.7 | G22: =SUM(G17:G18) -> 24.7 | H22: =SUM(H17:H18) -> 24.7 | I22: =SUM(I17:I18) -> 25.5
C24: Jan | D24: Feb | E24: March | F24: April | G24: May | H24: June | I24: July | J24: Aug | K24: Sep | L24: Oct | M24: Nov | N24: Dec | O24: Total
B25: Direct HC | C25: =+C6 -> 236.73 | D25: =+D6 -> 215 | E25: =+E6 -> 132 | F25: =+F6 -> 222 | G25: =+G6 -> 261 | H25: =+H6 -> 261 | I25: =+I6 -> 264 | J25: =+J6 -> 264 | ... N25: =+N6 -> 245 | O25: =O6 -> 237.4775
B26: Indirect HC | C26: =+C13 -> 85 | D26: =+D13 -> 82 | E26: =+E13 -> 69 | F26: =+F13 -> 79 | G26: =+G13 -> 82 | H26: =+H13 -> 82 | I26: =+I13 -> 84 | J26: =+J13 -> 84 | ... N26: =+N13 -> 84 | O26: =O13 -> 81.916667
B27: Total HC | C27: =C25+C26 -> 321.73 | D27: =D25+D26 -> 297 | E27: =E25+E26 -> 201 | F27: =F25+F26 -> 301 | G27: =G25+G26 -> 343 | H27: =H25+H26 -> 343 | I27: =I25+I26 -> 348 | J27: =J25+J26 -> 348 | ... O27: =O25+O26 -> 319.39417
B29: Temporary ratio | C29: =+C26/C27 -> 0.26419669 | D29: =+D26/D27 -> 0.27609428 | E29: =+E26/E27 -> 0.34328358 | F29: =+F26/F27 -> 0.26245847 | G29: =+G26/G27 -> 0.23906706 | H29: =+H26/H27 -> 0.23906706 | I29: =+I26/I27 -> 0.24137931 | J29: =+J26/J27 -> 0.24137931 | ... N29: =+N26/N27 -> 0.25531915
A32: BUDGET | C32: Jan | D32: Feb | E32: March | F32: April | G32: May | H32: June | I32: July | J32: August | K32: Sept | L32: Oct | M32: Nov | N32: Dec | O32: Total
A33: Direct HC | B33: Production | C33: 244 | D33: 244 | E33: 244 | F33: 244 | G33: 247 | H33: 245 | I33: 245 | J33: 251 | K33: 252 | L33: 250 | M33: 251 | N33: 252 | O33: =AVERAGE(C33:N33) -> 247.41667
B34: Shared | O34: =AVERAGE(C34:N34) -> #DIV/0!
B35: Total | C35: =C33+C34 -> 244 | D35: =D33+D34 -> 244 | E35: =E33+E34 -> 244 | F35: =F33+F34 -> 244 | G35: =G33+G34 -> 247 | H35: =H33+H34 -> 245 | I35: =I33+I34 -> 245 | J35: =J33+J34 -> 251 | ... N35: =N33+N34 -> 252 | O35: =AVERAGE(C35:N35) -> 247.41667
B37: Assigned hours | O37: =AVERAGE(C37:N37) -> #DIV/0!
A39: BUDGET | C39: Jan | D39: Feb | E39: March | F39: April | G39: May | H39: June | I39: July | J39: August | K39: Sept | L39: Oct | M39: Nov | N39: Dec | O39: Total
A40: Indirect HC | B40: Production | C40: 85 | D40: 85 | E40: 85 | F40: 85 | G40: 85 | H40: 85 | I40: 85 | J40: 85 | K40: 85 | L40: 85 | M40: 85 | N40: 85 | O40: =AVERAGE(C40:N40) -> 85
B41: Shared | O41: =AVERAGE(C41:N41) -> #DIV/0!
B42: Total | C42: =C40+C41 -> 85 | D42: =D40+D41 -> 85 | E42: =E40+E41 -> 85 | F42: =F40+F41 -> 85 | G42: =G40+G41 -> 85 | H42: =H40+H41 -> 85 | I42: =I40+I41 -> 85 | J42: =J40+J41 -> 85 | ... N42: =N40+N41 -> 85 | O42: =AVERAGE(C42:N42) -> 85
A45: BUDGET | C45: Jan | D45: Feb | E45: March | F45: April | G45: May | H45: June | I45: July | J45: August | K45: Sept | L45: Oct | M45: Nov | N45: Dec | O45: Total
A46: Fixed HC | B46: Production | C46: 22 | D46: 22 | E46: 22 | F46: 22 | G46: 22 | H46: 22 | I46: 22 | J46: 23 | K46: 23 | L46: 23 | M46: 23 | N46: 23 | O46: =AVERAGE(C46:N46) -> 22.416667
B47: Shared | C47: 4.5 | D47: 4.5 | E47: 4.5 | F47: 4.5 | G47: 4.5 | H47: 4.5 | I47: 4.5 | J47: 4.5 | K47: 4.5 | L47: 4.5 | M47: 4.5 | N47: 4.5 | O47: =AVERAGE(C47:N47) -> 4.5 | P47: 1.5 hqd included
B48: Lapro | O48: =AVERAGE(C48:N48) -> #DIV/0!
B49: Total | C49: =C46+C47+C48 -> 26.5 | D49: =D46+D47+D48 -> 26.5 | E49: =E46+E47+E48 -> 26.5 | F49: =F46+F47+F48 -> 26.5 | G49: =G46+G47+G48 -> 26.5 | H49: =H46+H47+H48 -> 26.5 | I49: =I46+I47+I48 -> 26.5 | J49: =J46+J47+J48 -> 27.5 | ... N49: =N46+N47+N48 -> 27.5 | O49: =AVERAGE(C49:N49) -> 26.916667

Sheet G&A _Out of Per_
C2: RENTA | I2: EURASIA | K2: TOTAL
C3: TD | D3: DW | E3: CK | F3: INFRA | G3: TOTAL | I3: TOTAL | M3: Highlights;
B4: Association dues (MESS Payment) | G4: =SUM(C4:F4) -> 0 | K4: =G4+I4 -> 0
B5: G&A Recharge Eurosia - Renta | G5: =SUM(C5:F5) -> 0 | K5: =G5+I5 -> 0
B6: IT Recharge Group | G6: =SUM(C6:F6) -> 0 | K6: =G6+I6 -> 0
B7: Controlling Expenses | G7: =SUM(C7:F7) -> 0 | K7: =G7+I7 -> 0
B8: Enterprice Property Insurance | G8: =SUM(C8:F8) -> 0 | K8: =G8+I8 -> 0
B9: Profit on Asset Sale | G9: =SUM(C9:F9) -> 0 | K9: =G9+I9 -> 0
B10: Loss on Asset Sale | G10: =SUM(C10:F10) -> 0 | K10: =G10+I10 -> 0
B11: Litigation fee | G11: =SUM(C11:F11) -> 0 | K11: =G11+I11 -> 0
B12: INFRA | G12: =SUM(C12:F12) -> 0 | K12: =G12+I12 -> 0
B13: …...... | G13: =SUM(C13:F13) -> 0 | K13: =G13+I13 -> 0
B14: G&A _ Out of Perimeter | C14: =SUM(C4:C13) -> 0 | D14: =SUM(D4:D13) -> 0 | E14: =SUM(E4:E13) -> 0 | F14: =SUM(F4:F13) -> 0 | G14: =SUM(G4:G13) -> 0 | I14: =SUM(I4:I13) -> 0 | K14: =SUM(K4:K13) -> 0

Sheet CC
I2: MFG | J2: PTK4M00WAB
J3: PTK4M00WAC
J4: PTK4M00WAD
J5: PTK4M00WAE
J6: PTK4M00WAF
J7: PTK4M00WAG
J8: PTK4M00WAH
J9: PTK4M00WAI
J10: PTK4M00WAJ
J11: PTK4M00WAK
J12: PTK4M00WYD
I13: Overhead | J13: PTK4Y00WYE

Sheet ACE 2026
A1: YTD | B1: =IF($V$3>=B$2,1,0) -> 1 | C1: =IF($V$3>=C$2,1,0) -> 0 | D1: =IF($V$3>=D$2,1,0) -> 0 | E1: =IF($V$3>=E$2,1,0) -> 0 | F1: =IF($V$3>=F$2,1,0) -> 0 | G1: =IF($V$3>=G$2,1,0) -> 0 | H1: =IF($V$3>=H$2,1,0) -> 0 | I1: =IF($V$3>=I$2,1,0) -> 0 | ... M1: =IF($V$3>=M$2,1,0) -> 0
A2: MTD | B2: 1 | C2: 2 | D2: 3 | E2: 4 | F2: 5 | G2: 6 | H2: 7 | I2: 8 | J2: 9 | K2: 10 | L2: 11 | M2: 12
T3: Month | U3: Jan | V3: =VLOOKUP(U3,List!$C$2:$D$13,2,0) -> 1 | W3: =VLOOKUP(U3,List!$C$2:$E$13,3,0) -> 1
A4: ACE Budget | B4: Jan | C4: Feb | D4: March | E4: April | F4: May | G4: June | H4: July | I4: August | J4: Sept | K4: Oct | L4: Nov | M4: Dec | N4: Total | P4: MTD | Q4: YTD
A5: Direct Labour | B5: 4644.3971 | C5: 5010.6746 | D5: 5057.5234 | E5: 4872.7558 | F5: 15380.89 | G5: 49280.033 | H5: 49328.755 | I5: 49547.308 | J5: 58604.946 | K5: 54442.467 | L5: 52437.071 | M5: 52468.259 | N5: =SUM(B5:M5) -> 401075.08 | P5: =+SUMIFS(B5:M5,$B$2:$M$2,$V$3)/1000 -> 4.6443971 | Q5: =+SUMIFS(B5:M5,$B$1:$M$1,$W$3)/1000 -> 4.6443971
A6: Variable Utilities | B6: 0 | C6: 0 | D6: 0 | E6: 0 | F6: 0 | G6: 0 | H6: 0 | I6: 0 | J6: 0 | K6: 0 | L6: 0 | M6: 0 | N6: =SUM(B6:M6) -> 0 | P6: =+SUMIFS(B6:M6,$B$2:$M$2,$V$3)/1000 -> 0 | Q6: =+SUMIFS(B6:M6,$B$1:$M$1,$W$3)/1000 -> 0
A7: Scrap | B7: 0 | C7: 0 | D7: 0 | E7: 6811.5 | F7: 5019 | G7: 7528.5 | H7: 6094.5 | I7: 5557.5 | J7: 7780.5 | K7: 6669 | L7: 7410 | M7: 5570.25 | N7: =SUM(B7:M7) -> 58440.75 | P7: =+SUMIFS(B7:M7,$B$2:$M$2,$V$3)/1000 -> 0 | Q7: =+SUMIFS(B7:M7,$B$1:$M$1,$W$3)/1000 -> 0
A8: Scrap Reselling | B8: 0 | C8: 0 | D8: 0 | E8: 0 | F8: 0 | G8: 0 | H8: 0 | I8: 0 | J8: 0 | K8: 0 | L8: 0 | M8: 0 | N8: =SUM(B8:M8) -> 0 | P8: =+SUMIFS(B8:M8,$B$2:$M$2,$V$3)/1000 -> 0 | Q8: =+SUMIFS(B8:M8,$B$1:$M$1,$W$3)/1000 -> 0
A9: Variable Costs | B9: 1000 | C9: 1000 | D9: 1000 | E9: 1000 | F9: 1000 | G9: 1000 | H9: 1000 | I9: 1000 | J9: 1000 | K9: 1000 | L9: 1000 | M9: 1000 | N9: =SUM(B9:M9) -> 12000 | P9: =+SUMIFS(B9:M9,$B$2:$M$2,$V$3)/1000 -> 1 | Q9: =+SUMIFS(B9:M9,$B$1:$M$1,$W$3)/1000 -> 1
A10: VARIABLE CONVERSION | B10: =SUM(B5:B9) -> 5644.3971 | C10: =SUM(C5:C9) -> 6010.6746 | D10: =SUM(D5:D9) -> 6057.5234 | E10: =SUM(E5:E9) -> 12684.256 | F10: =SUM(F5:F9) -> 21399.89 | G10: =SUM(G5:G9) -> 57808.533 | H10: =SUM(H5:H9) -> 56423.255 | I10: =SUM(I5:I9) -> 56104.808 | ... M10: =SUM(M5:M9) -> 59038.509 | N10: =SUM(B10:M10) -> 471515.83 | P10: =SUM(P5:P9) -> 5.6443971 | Q10: =SUM(Q5:Q9) -> 5.6443971
A11: Indirect Labour | B11: 0 | C11: 0 | D11: 0 | E11: 0 | F11: 0 | G11: 0 | H11: 0 | I11: 0 | J11: 0 | K11: 0 | L11: 0 | M11: 0 | N11: =SUM(B11:M11) -> 0 | P11: =+SUMIFS(B11:M11,$B$2:$M$2,$V$3)/1000 -> 0 | Q11: =+SUMIFS(B11:M11,$B$1:$M$1,$W$3)/1000 -> 0
A12: Fixed Labour | B12: 0 | C12: 0 | D12: 0 | E12: 0 | F12: 0 | G12: 0 | H12: 0 | I12: 0 | J12: 0 | K12: 0 | L12: 0 | M12: 0 | N12: =SUM(B12:M12) -> 0 | P12: =+SUMIFS(B12:M12,$B$2:$M$2,$V$3)/1000 -> 0 | Q12: =+SUMIFS(B12:M12,$B$1:$M$1,$W$3)/1000 -> 0
A13: Semifixed | B13: 0 | C13: 0 | D13: 0 | E13: 0 | F13: 0 | G13: 0 | H13: 0 | I13: 0 | J13: 0 | K13: 0 | L13: 0 | M13: 0 | N13: =SUM(B13:M13) -> 0 | P13: =+SUMIFS(B13:M13,$B$2:$M$2,$V$3)/1000 -> 0 | Q13: =+SUMIFS(B13:M13,$B$1:$M$1,$W$3)/1000 -> 0
A14: Fixed utilities | B14: 1100 | C14: 1100 | D14: 1100 | E14: 1100 | F14: 1100 | G14: 1100 | H14: 1100 | I14: 1100 | J14: 1100 | K14: 1100 | L14: 1100 | M14: 1100 | N14: =SUM(B14:M14) -> 13200 | P14: =+SUMIFS(B14:M14,$B$2:$M$2,$V$3)/1000 -> 1.1 | Q14: =+SUMIFS(B14:M14,$B$1:$M$1,$W$3)/1000 -> 1.1
A15: Fixed Cost | B15: 0 | C15: 0 | D15: 0 | E15: 0 | F15: 0 | G15: 0 | H15: 0 | I15: 0 | J15: 0 | K15: 0 | L15: 0 | M15: 0 | N15: =SUM(B15:M15) -> 0 | P15: =+SUMIFS(B15:M15,$B$2:$M$2,$V$3)/1000 -> 0 | Q15: =+SUMIFS(B15:M15,$B$1:$M$1,$W$3)/1000 -> 0
A16: Obsolete | N16: =SUM(B16:M16) -> 0 | P16: =+SUMIFS(B16:M16,$B$2:$M$2,$V$3)/1000 -> 0 | Q16: =+SUMIFS(B16:M16,$B$1:$M$1,$W$3)/1000 -> 0
A17: Depreciation | N17: =SUM(B17:M17) -> 0 | P17: =+SUMIFS(B17:M17,$B$2:$M$2,$V$3)/1000 -> 0 | Q17: =+SUMIFS(B17:M17,$B$1:$M$1,$W$3)/1000 -> 0
A18: FIXED CONVERSION | B18: =SUM(B11:B17) -> 1100 | C18: =SUM(C11:C17) -> 1100 | D18: =SUM(D11:D17) -> 1100 | E18: =SUM(E11:E17) -> 1100 | F18: =SUM(F11:F17) -> 1100 | G18: =SUM(G11:G17) -> 1100 | H18: =SUM(H11:H17) -> 1100 | I18: =SUM(I11:I17) -> 1100 | ... M18: =SUM(M11:M17) -> 1100 | N18: =SUM(B18:M18) -> 13200 | P18: =SUM(P11:P17) -> 1.1 | Q18: =SUM(Q11:Q17) -> 1.1
A19: OVH AND OTHERS | B19: 0 | C19: 0 | D19: 0 | E19: 0 | F19: 0 | G19: 0 | H19: 0 | I19: 0 | J19: 0 | K19: 0 | L19: 0 | M19: 0 | N19: =SUM(B19:M19) -> 0 | P19: =+SUMIFS(B19:M19,$B$2:$M$2,$V$3)/1000 -> 0 | Q19: =+SUMIFS(B19:M19,$B$1:$M$1,$W$3)/1000 -> 0
A20: Grand Total | B20: =SUM(B10,B18,B19) -> 6744.3971 | C20: =SUM(C10,C18,C19) -> 7110.6746 | D20: =SUM(D10,D18,D19) -> 7157.5234 | E20: =SUM(E10,E18,E19) -> 13784.256 | F20: =SUM(F10,F18,F19) -> 22499.89 | G20: =SUM(G10,G18,G19) -> 58908.533 | H20: =SUM(H10,H18,H19) -> 57523.255 | I20: =SUM(I10,I18,I19) -> 57204.808 | ... M20: =SUM(M10,M18,M19) -> 60138.509 | N20: =SUM(B20:M20) -> 484715.83 | P20: =P18+P10+P19 -> 6.7443971 | Q20: =Q18+Q10+Q19 -> 6.7443971
A23: F-Matrix Actual | B23: Jan | C23: Feb | D23: March | E23: April | F23: May | G23: June | H23: July | I23: August | J23: Sept | K23: Oct | L23: Nov | M23: Dec | N23: Total | P23: MTD | Q23: YTD
A24: Direct Labour | B24: =+'ACE Details_FULL'!D25-'ACE Details_FULL'!D5+'ACE Details_FULL'!D30+'ACE Details_FULL'!D32 -> 40450.38 | C24: =+SUM('ACE Details_FULL'!E25,'ACE Details_FULL'!E30,'ACE Details_FULL'!E32,'ACE Details_FULL'!E32) -> 48560.941 | D24: =+SUM('ACE Details_FULL'!F25,'ACE Details_FULL'!F30,'ACE Details_FULL'!F32) -> 24543.182 | E24: =+SUM('ACE Details_FULL'!G25,'ACE Details_FULL'!G30,'ACE Details_FULL'!G32) -> 26853.444 | F24: =SUM('ACE Details_FULL'!H25:H32) -> 27917.878 | G24: =SUM('ACE Details_FULL'!I25:I32) -> 31020.665 | H24: =+SUM('ACE Details_FULL'!J25,'ACE Details_FULL'!J30,'ACE Details_FULL'!J32) -> 27265.034 | I24: =+SUM('ACE Details_FULL'!K25,'ACE Details_FULL'!K30,'ACE Details_FULL'!K32) -> 27115.925 | J24: =+SUM('ACE Details_FULL'!L25,'ACE Details_FULL'!L30,'ACE Details_FULL'!L32) -> 29457.764 | K24: =+SUM('ACE Details_FULL'!M25,'ACE Details_FULL'!M30,'ACE Details_FULL'!M32) -> 28696.971 | L24: =+SUM('ACE Details_FULL'!N25,'ACE Details_FULL'!N30,'ACE Details_FULL'!N32) -> 29000.118 | M24: =+SUM('ACE Details_FULL'!O25,'ACE Details_FULL'!O30,'ACE Details_FULL'!O32) -> 27498.863 | N24: =SUM(B24:M24) -> 368381.16 | P24: =+SUMIFS(B24:M24,$B$2:$M$2,$V$3)/1000 -> 40.45038 | Q24: =+SUMIFS(B24:M24,$B$1:$M$1,$W$3)/1000 -> 40.45038
A25: Variable Utilities | N25: =SUM(B25:M25) -> 0 | P25: =+SUMIFS(B25:M25,$B$2:$M$2,$V$3)/1000 -> 0 | Q25: =+SUMIFS(B25:M25,$B$1:$M$1,$W$3)/1000 -> 0
A26: Scrap | B26: =+'ACE Details_FULL'!D42 -> 0 | C26: =+'ACE Details_FULL'!E42 -> 0 | D26: =+'ACE Details_FULL'!F42 -> 0 | E26: =+'ACE Details_FULL'!G42 -> 0 | F26: =SUM('ACE Details_FULL'!H42) -> 0 | G26: =+'ACE Details_FULL'!I42 -> 0 | H26: =+'ACE Details_FULL'!J42 -> 6460.0226 | I26: =+'ACE Details_FULL'!K42 -> 6306.2731 | J26: =+'ACE Details_FULL'!L42 -> 8720.9988 | K26: =+'ACE Details_FULL'!M42 -> 7936.5266 | L26: =+'ACE Details_FULL'!N42 -> 8249.1084 | M26: =+'ACE Details_FULL'!O42 -> 6701.1299 | N26: =SUM(B26:M26) -> 44374.059 | P26: =+SUMIFS(B26:M26,$B$2:$M$2,$V$3)/1000 -> 0 | Q26: =+SUMIFS(B26:M26,$B$1:$M$1,$W$3)/1000 -> 0
A27: Scrap Reselling | N27: =SUM(B27:M27) -> 0 | P27: =+SUMIFS(B27:M27,$B$2:$M$2,$V$3)/1000 -> 0 | Q27: =+SUMIFS(B27:M27,$B$1:$M$1,$W$3)/1000 -> 0
A28: Variable Costs | B28: =+'ACE Details_FULL'!D33 -> 1000 | C28: =+'ACE Details_FULL'!E33 -> 1000 | D28: =+'ACE Details_FULL'!F33 -> 1000 | E28: =+'ACE Details_FULL'!G33 -> 1000 | F28: =SUM('ACE Details_FULL'!H33) -> 1000 | G28: =+'ACE Details_FULL'!I33 -> 1000 | H28: =+'ACE Details_FULL'!J33 -> 1000 | I28: =+'ACE Details_FULL'!K33 -> 1000 | J28: =+'ACE Details_FULL'!L33 -> 1000 | K28: =+'ACE Details_FULL'!M33 -> 1000 | L28: =+'ACE Details_FULL'!N33 -> 1000 | M28: =+'ACE Details_FULL'!O33 -> 1000 | N28: =SUM(B28:M28) -> 12000 | P28: =+SUMIFS(B28:M28,$B$2:$M$2,$V$3)/1000 -> 1 | Q28: =+SUMIFS(B28:M28,$B$1:$M$1,$W$3)/1000 -> 1
A29: VARIABLE CONVERSION | B29: =SUM(B24:B28) -> 41450.38 | C29: =SUM(C24:C28) -> 49560.941 | D29: =SUM(D24:D28) -> 25543.182 | E29: =SUM(E24:E28) -> 27853.444 | F29: =SUM(F24:F28) -> 28917.878 | G29: =SUM(G24:G28) -> 32020.665 | H29: =SUM(H24:H28) -> 34725.056 | I29: =SUM(I24:I28) -> 34422.198 | ... M29: =SUM(M24:M28) -> 35199.993 | N29: =SUM(B29:M29) -> 424755.22 | P29: =SUM(P24:P28) -> 41.45038 | Q29: =SUM(Q24:Q28) -> 41.45038
A30: Indirect Labour | B30: =+'ACE Details_FULL'!D34 -> 0 | C30: =+'ACE Details_FULL'!E34 -> 2240.8813 | D30: =+'ACE Details_FULL'!F34 -> 2240.8813 | E30: =+'ACE Details_FULL'!G34 -> 2240.8813 | F30: =SUM('ACE Details_FULL'!H34,'ACE Details_FULL'!H35) -> 4481.7626 | G30: =SUM('ACE Details_FULL'!I34,'ACE Details_FULL'!I35) -> 4481.7626 | H30: =+'ACE Details_FULL'!J34 -> 2240.8813 | I30: =+'ACE Details_FULL'!K34 -> 2240.8813 | J30: =+'ACE Details_FULL'!L34 -> 2240.8813 | K30: =+'ACE Details_FULL'!M34 -> 2240.8813 | L30: =+'ACE Details_FULL'!N34 -> 2240.8813 | M30: =+'ACE Details_FULL'!O34 -> 2240.8813 | N30: =SUM(B30:M30) -> 29131.457 | P30: =+SUMIFS(B30:M30,$B$2:$M$2,$V$3)/1000 -> 0 | Q30: =+SUMIFS(B30:M30,$B$1:$M$1,$W$3)/1000 -> 0
A31: Fixed Labour | N31: =SUM(B31:M31) -> 0 | P31: =+SUMIFS(B31:M31,$B$2:$M$2,$V$3)/1000 -> 0 | Q31: =+SUMIFS(B31:M31,$B$1:$M$1,$W$3)/1000 -> 0
A32: Semifixed | B32: =+'ACE Details_FULL'!D40+'ACE Details_FULL'!D38 -> 0 | C32: =+'ACE Details_FULL'!E40+'ACE Details_FULL'!E38 -> 211.30421 | D32: =+'ACE Details_FULL'!F40+'ACE Details_FULL'!F38 -> 211.30421 | E32: =+'ACE Details_FULL'!G40+'ACE Details_FULL'!G38 -> 211.30421 | F32: =SUM('ACE Details_FULL'!H38,'ACE Details_FULL'!H39) -> 422.60842 | G32: =SUM('ACE Details_FULL'!I38,'ACE Details_FULL'!I39) -> 422.60842 | H32: =+'ACE Details_FULL'!J40+'ACE Details_FULL'!J38 -> 845.21684 | I32: =+'ACE Details_FULL'!K40+'ACE Details_FULL'!K38 -> 845.21684 | J32: =+'ACE Details_FULL'!L40+'ACE Details_FULL'!L38 -> 845.21684 | K32: =+'ACE Details_FULL'!M40+'ACE Details_FULL'!M38 -> 845.21684 | L32: =+'ACE Details_FULL'!N40+'ACE Details_FULL'!N38 -> 845.21684 | M32: =+'ACE Details_FULL'!O40+'ACE Details_FULL'!O38 -> 845.21684 | N32: =SUM(B32:M32) -> 6550.4305 | P32: =+SUMIFS(B32:M32,$B$2:$M$2,$V$3)/1000 -> 0 | Q32: =+SUMIFS(B32:M32,$B$1:$M$1,$W$3)/1000 -> 0
A33: Fixed utilities | B33: =+'ACE Details_FULL'!D36+'ACE Details_FULL'!D37 -> 0 | C33: =+'ACE Details_FULL'!E36+'ACE Details_FULL'!E37 -> 0 | D33: =+'ACE Details_FULL'!F36+'ACE Details_FULL'!F37 -> 222.8 | E33: =+'ACE Details_FULL'!G36+'ACE Details_FULL'!G37 -> 222.8 | F33: =SUM('ACE Details_FULL'!H36,'ACE Details_FULL'!H37) -> 222.8 | G33: =SUM('ACE Details_FULL'!I36,'ACE Details_FULL'!I37) -> 222.8 | H33: =+'ACE Details_FULL'!J36+'ACE Details_FULL'!J37 -> 922.8 | I33: =+'ACE Details_FULL'!K36+'ACE Details_FULL'!K37 -> 922.8 | J33: =+'ACE Details_FULL'!L36+'ACE Details_FULL'!L37 -> 922.8 | K33: =+'ACE Details_FULL'!M36+'ACE Details_FULL'!M37 -> 922.8 | L33: =+'ACE Details_FULL'!N36+'ACE Details_FULL'!N37 -> 922.8 | M33: =+'ACE Details_FULL'!O36+'ACE Details_FULL'!O37 -> 922.8 | N33: =SUM(B33:M33) -> 6428 | P33: =+SUMIFS(B33:M33,$B$2:$M$2,$V$3)/1000 -> 0 | Q33: =+SUMIFS(B33:M33,$B$1:$M$1,$W$3)/1000 -> 0
A34: Fixed Cost | N34: =SUM(B34:M34) -> 0 | P34: =+SUMIFS(B34:M34,$B$2:$M$2,$V$3)/1000 -> 0 | Q34: =+SUMIFS(B34:M34,$B$1:$M$1,$W$3)/1000 -> 0
A35: Obsolete | N35: =SUM(B35:M35) -> 0 | P35: =+SUMIFS(B35:M35,$B$2:$M$2,$V$3)/1000 -> 0 | Q35: =+SUMIFS(B35:M35,$B$1:$M$1,$W$3)/1000 -> 0
A36: Depreciation | N36: =SUM(B36:M36) -> 0 | P36: =+SUMIFS(B36:M36,$B$2:$M$2,$V$3)/1000 -> 0 | Q36: =+SUMIFS(B36:M36,$B$1:$M$1,$W$3)/1000 -> 0
A37: FIXED CONVERSION | B37: =SUM(B30:B36) -> 0 | C37: =SUM(C30:C36) -> 2452.1855 | D37: =SUM(D30:D36) -> 2674.9855 | E37: =SUM(E30:E36) -> 2674.9855 | F37: =SUM(F30:F36) -> 5127.171 | G37: =SUM(G30:G36) -> 5127.171 | H37: =SUM(H30:H36) -> 4008.8981 | I37: =SUM(I30:I36) -> 4008.8981 | ... M37: =SUM(M30:M36) -> 4008.8981 | N37: =SUM(B37:M37) -> 42109.887 | P37: =SUM(P30:P36) -> 0 | Q37: =SUM(Q30:Q36) -> 0
A38: OVH AND OTHERS | N38: =SUM(B38:M38) -> 0 | P38: =+SUMIFS(B38:M38,$B$2:$M$2,$V$3)/1000 -> 0 | Q38: =+SUMIFS(B38:M38,$B$1:$M$1,$W$3)/1000 -> 0
A39: Grand Total | B39: =B29+B37+B38 -> 41450.38 | C39: =C29+C37+C38 -> 52013.126 | D39: =D29+D37+D38 -> 28218.168 | E39: =E29+E37+E38 -> 30528.429 | F39: =F29+F37+F38 -> 34045.049 | G39: =G29+G37+G38 -> 37147.836 | H39: =H29+H37+H38 -> 38733.954 | I39: =I29+I37+I38 -> 38431.096 | ... M39: =M29+M37+M38 -> 39208.891 | N39: =SUM(B39:M39) -> 466865.11 | P39: =P37+P29+P38 -> 41.45038 | Q39: =Q37+Q29+Q38 -> 41.45038
A42: Over /Underabsorption | B42: Jan | C42: Feb | D42: March | E42: April | F42: May | G42: June | H42: July | I42: August | J42: Sept | K42: Oct | L42: Nov | M42: Dec | N42: Total | P42: MTD | Q42: YTD
A43: Direct Labour | B43: =B24-B5 -> 35805.983 | C43: =C24-C5 -> 43550.266 | D43: =D24-D5 -> 19485.659 | E43: =E24-E5 -> 21980.688 | F43: =F24-F5 -> 12536.988 | G43: =G24-G5 -> -18259.368 | H43: =H24-H5 -> -22063.721 | I43: =I24-I5 -> -22431.383 | ... M43: =M24-M5 -> -24969.396 | N43: =SUM(B43:M43) -> -32693.916 | P43: =+SUMIFS(B43:M43,$B$2:$M$2,$V$3)/1000 -> 35.805983 | Q43: =+SUMIFS(B43:M43,$B$1:$M$1,$W$3)/1000 -> 35.805983
A44: Variable Utilities | B44: =B25-B6 -> 0 | C44: =C25-C6 -> 0 | D44: =D25-D6 -> 0 | E44: =E25-E6 -> 0 | F44: =F25-F6 -> 0 | G44: =G25-G6 -> 0 | H44: =H25-H6 -> 0 | I44: =I25-I6 -> 0 | ... M44: =M25-M6 -> 0 | N44: =SUM(B44:M44) -> 0 | P44: =+SUMIFS(B44:M44,$B$2:$M$2,$V$3)/1000 -> 0 | Q44: =+SUMIFS(B44:M44,$B$1:$M$1,$W$3)/1000 -> 0
A45: Scrap | B45: =B26-B7 -> 0 | C45: =C26-C7 -> 0 | D45: =D26-D7 -> 0 | E45: =E26-E7 -> -6811.5 | F45: =F26-F7 -> -5019 | G45: =G26-G7 -> -7528.5 | H45: =H26-H7 -> 365.52265 | I45: =I26-I7 -> 748.77309 | ... M45: =M26-M7 -> 1130.8799 | N45: =SUM(B45:M45) -> -14066.691 | P45: =+SUMIFS(B45:M45,$B$2:$M$2,$V$3)/1000 -> 0 | Q45: =+SUMIFS(B45:M45,$B$1:$M$1,$W$3)/1000 -> 0
A46: Scrap Reselling | B46: =B27-B8 -> 0 | C46: =C27-C8 -> 0 | D46: =D27-D8 -> 0 | E46: =E27-E8 -> 0 | F46: =F27-F8 -> 0 | G46: =G27-G8 -> 0 | H46: =H27-H8 -> 0 | I46: =I27-I8 -> 0 | ... M46: =M27-M8 -> 0 | N46: =SUM(B46:M46) -> 0 | P46: =+SUMIFS(B46:M46,$B$2:$M$2,$V$3)/1000 -> 0 | Q46: =+SUMIFS(B46:M46,$B$1:$M$1,$W$3)/1000 -> 0
A47: Variable Costs | B47: =B28-B9 -> 0 | C47: =C28-C9 -> 0 | D47: =D28-D9 -> 0 | E47: =E28-E9 -> 0 | F47: =F28-F9 -> 0 | G47: =G28-G9 -> 0 | H47: =H28-H9 -> 0 | I47: =I28-I9 -> 0 | ... M47: =M28-M9 -> 0 | N47: =SUM(B47:M47) -> 0 | P47: =+SUMIFS(B47:M47,$B$2:$M$2,$V$3)/1000 -> 0 | Q47: =+SUMIFS(B47:M47,$B$1:$M$1,$W$3)/1000 -> 0
A48: VARIABLE CONVERSION | B48: =SUM(B43:B47) -> 35805.983 | C48: =SUM(C43:C47) -> 43550.266 | D48: =SUM(D43:D47) -> 19485.659 | E48: =SUM(E43:E47) -> 15169.188 | F48: =SUM(F43:F47) -> 7517.9881 | G48: =SUM(G43:G47) -> -25787.868 | H48: =SUM(H43:H47) -> -21698.199 | I48: =SUM(I43:I47) -> -21682.61 | ... M48: =SUM(M43:M47) -> -23838.516 | N48: =SUM(B48:M48) -> -46760.606 | P48: =SUM(P43:P47) -> 35.805983 | Q48: =SUM(Q43:Q47) -> 35.805983
A49: Indirect Labour | B49: =B30-B11 -> 0 | C49: =C30-C11 -> 2240.8813 | D49: =D30-D11 -> 2240.8813 | E49: =E30-E11 -> 2240.8813 | F49: =F30-F11 -> 4481.7626 | G49: =G30-G11 -> 4481.7626 | H49: =H30-H11 -> 2240.8813 | I49: =I30-I11 -> 2240.8813 | ... M49: =M30-M11 -> 2240.8813 | N49: =SUM(B49:M49) -> 29131.457 | P49: =+SUMIFS(B49:M49,$B$2:$M$2,$V$3)/1000 -> 0 | Q49: =+SUMIFS(B49:M49,$B$1:$M$1,$W$3)/1000 -> 0
A50: Fixed Labour | B50: =B31-B12 -> 0 | C50: =C31-C12 -> 0 | D50: =D31-D12 -> 0 | E50: =E31-E12 -> 0 | F50: =F31-F12 -> 0 | G50: =G31-G12 -> 0 | H50: =H31-H12 -> 0 | I50: =I31-I12 -> 0 | ... M50: =M31-M12 -> 0 | N50: =SUM(B50:M50) -> 0 | P50: =+SUMIFS(B50:M50,$B$2:$M$2,$V$3)/1000 -> 0 | Q50: =+SUMIFS(B50:M50,$B$1:$M$1,$W$3)/1000 -> 0
A51: Semifixed | B51: =B32-B13 -> 0 | C51: =C32-C13 -> 211.30421 | D51: =D32-D13 -> 211.30421 | E51: =E32-E13 -> 211.30421 | F51: =F32-F13 -> 422.60842 | G51: =G32-G13 -> 422.60842 | H51: =H32-H13 -> 845.21684 | I51: =I32-I13 -> 845.21684 | ... M51: =M32-M13 -> 845.21684 | N51: =SUM(B51:M51) -> 6550.4305 | P51: =+SUMIFS(B51:M51,$B$2:$M$2,$V$3)/1000 -> 0 | Q51: =+SUMIFS(B51:M51,$B$1:$M$1,$W$3)/1000 -> 0
A52: Fixed utilities | B52: =B33-B14 -> -1100 | C52: =C33-C14 -> -1100 | D52: =D33-D14 -> -877.2 | E52: =E33-E14 -> -877.2 | F52: =F33-F14 -> -877.2 | G52: =G33-G14 -> -877.2 | H52: =H33-H14 -> -177.2 | I52: =I33-I14 -> -177.2 | ... M52: =M33-M14 -> -177.2 | N52: =SUM(B52:M52) -> -6772 | P52: =+SUMIFS(B52:M52,$B$2:$M$2,$V$3)/1000 -> -1.1 | Q52: =+SUMIFS(B52:M52,$B$1:$M$1,$W$3)/1000 -> -1.1
A53: Fixed Cost | B53: =B34-B15 -> 0 | C53: =C34-C15 -> 0 | D53: =D34-D15 -> 0 | E53: =E34-E15 -> 0 | F53: =F34-F15 -> 0 | G53: =G34-G15 -> 0 | H53: =H34-H15 -> 0 | I53: =I34-I15 -> 0 | ... M53: =M34-M15 -> 0 | N53: =SUM(B53:M53) -> 0 | P53: =+SUMIFS(B53:M53,$B$2:$M$2,$V$3)/1000 -> 0 | Q53: =+SUMIFS(B53:M53,$B$1:$M$1,$W$3)/1000 -> 0
A54: Obsolete | B54: =B35-B16 -> 0 | C54: =C35-C16 -> 0 | D54: =D35-D16 -> 0 | E54: =E35-E16 -> 0 | F54: =F35-F16 -> 0 | G54: =G35-G16 -> 0 | H54: =H35-H16 -> 0 | I54: =I35-I16 -> 0 | ... M54: =M35-M16 -> 0 | N54: =SUM(B54:M54) -> 0 | P54: =+SUMIFS(B54:M54,$B$2:$M$2,$V$3)/1000 -> 0 | Q54: =+SUMIFS(B54:M54,$B$1:$M$1,$W$3)/1000 -> 0
A55: Depreciation | B55: =B36-B17 -> 0 | C55: =C36-C17 -> 0 | D55: =D36-D17 -> 0 | E55: =E36-E17 -> 0 | F55: =F36-F17 -> 0 | G55: =G36-G17 -> 0 | H55: =H36-H17 -> 0 | I55: =I36-I17 -> 0 | ... M55: =M36-M17 -> 0 | N55: =SUM(B55:M55) -> 0 | P55: =+SUMIFS(B55:M55,$B$2:$M$2,$V$3)/1000 -> 0 | Q55: =+SUMIFS(B55:M55,$B$1:$M$1,$W$3)/1000 -> 0
A56: FIXED CONVERSION | B56: =SUM(B49:B55) -> -1100 | C56: =SUM(C49:C55) -> 1352.1855 | D56: =SUM(D49:D55) -> 1574.9855 | E56: =SUM(E49:E55) -> 1574.9855 | F56: =SUM(F49:F55) -> 4027.171 | G56: =SUM(G49:G55) -> 4027.171 | H56: =SUM(H49:H55) -> 2908.8981 | I56: =SUM(I49:I55) -> 2908.8981 | ... M56: =SUM(M49:M55) -> 2908.8981 | N56: =SUM(B56:M56) -> 28909.887 | P56: =SUM(P49:P55) -> -1.1 | Q56: =SUM(Q49:Q55) -> -1.1
A57: OVH AND OTHERS | B57: =B38-B19 -> 0 | C57: =C38-C19 -> 0 | D57: =D38-D19 -> 0 | E57: =E38-E19 -> 0 | F57: =F38-F19 -> 0 | G57: =G38-G19 -> 0 | H57: =H38-H19 -> 0 | I57: =I38-I19 -> 0 | ... M57: =M38-M19 -> 0 | N57: =SUM(B57:M57) -> 0 | P57: =+SUMIFS(B57:M57,$B$2:$M$2,$V$3)/1000 -> 0 | Q57: =+SUMIFS(B57:M57,$B$1:$M$1,$W$3)/1000 -> 0
A58: Grand Total | B58: =B48+B56+B57 -> 34705.983 | C58: =C48+C56+C57 -> 44902.451 | D58: =D48+D56+D57 -> 21060.644 | E58: =E48+E56+E57 -> 16744.174 | F58: =F48+F56+F57 -> 11545.159 | G58: =G48+G56+G57 -> -21760.697 | H58: =H48+H56+H57 -> -18789.3 | I58: =I48+I56+I57 -> -18773.712 | ... M58: =M48+M56+M57 -> -20929.617 | N58: =SUM(B58:M58) -> -17850.719 | P58: =P56+P48+P57 -> 34.705983 | Q58: =Q56+Q48+Q57 -> 34.705983
G59: -142057
G60: =G59+136000 -> -6057

Sheet VOLUME
B2: MTD | C2: Jan | D2: Feb | E2: Mar | F2: Apr | G2: May | H2: Jun | I2: Jul | J2: Aug | K2: Sep | L2: Oct | M2: Nov | N2: Dec | O2: Total
B3: Budget Volume | C3: 50463 | D3: 50446 | E3: 50447 | F3: 48050 | G3: 36788 | H3: 53265 | I3: 42049 | J3: 39150 | K3: 53732 | L3: 48548 | M3: 51408 | N3: 40676 | O3: =SUM(C3:N3) -> 565022
B5: STD Volume | C5: 46000 | D5: 46000 | E5: 46000 | F5: 48300 | G5: 32200 | H5: 71500 | I5: 57750 | J5: 52250 | K5: 71500 | L5: 71500 | M5: 68750 | N5: 62561 | O5: =SUM(C5:N5) -> 674311
B7: Actual Volume | C7: =+C10 -> 47357 | D7: =+D10 -> 42593 | E7: =+E10 -> 23002 | F7: =+F10 -> 40893 | G7: =+G10 -> 33043 | H7: =+H10 -> 53186 | I7: =+I10 -> 41500 | J7: =+J10 -> 39000 | ... N7: =+N10 -> 42190 | O7: =SUM(C7:N7) -> 518285
C8: =C9-C10 -> 0 | D8: =D9-D10 -> 0 | E8: =E9-E10 -> 0 | F8: =F9-F10 -> 0 | G8: =G9-G10 -> 0 | H8: =H9-H10 -> 1714 | I8: =I9-I10 -> 0 | J8: =J9-J10 -> 0 | ... N8: =N9-N10 -> 0
C9: 47357 | D9: 42593 | E9: 23002 | F9: 40893 | G9: 33043 | H9: 54900 | I9: 41500 | J9: 39000 | K9: 54085 | L9: 49500 | M9: 51936 | N9: 42190
B10: DW 2 | C10: =SUM(C11:C13) -> 47357 | D10: =SUM(D11:D13) -> 42593 | E10: =SUM(E11:E13) -> 23002 | F10: =SUM(F11:F13) -> 40893 | G10: =SUM(G11:G13) -> 33043 | H10: =SUM(H11:H13) -> 53186 | I10: =SUM(I11:I13) -> 41500 | J10: =SUM(J11:J13) -> 39000 | ... N10: =SUM(N11:N13) -> 42190 | O10: =SUM(C10:N10) -> 518285
B11: FS | C11: 19805 | D11: 18495 | E11: 10482 | F11: 14837 | G11: 14006 | H11: 24548 | I11: 15800 | J11: 15600 | K11: 20600 | L11: 19800 | M11: 25500 | N11: 20024 | O11: =SUM(C11:N11) -> 219497
B12: BI | C12: 27552 | D12: 24098 | E12: 12520 | F12: 26056 | G12: 19037 | H12: 28638 | I12: 23700 | J12: 23400 | K12: 30900 | L12: 29700 | M12: 25500 | N12: 20024 | O12: =SUM(C12:N12) -> 291125
B13: KIT | H13: 0 | I13: 2000 | J13: 0 | K13: 2585 | L13: 0 | M13: 936 | N13: 2142 | O13: =SUM(C13:N13) -> 7663

Sheet HQD
A1: PERIMETER | B1: HQD REPORTING -EXCLUDED COST ITEMS | C1: IN | D1: OUT
A3: PERIMETER | B3: Direct Labor | C3: X
A4: PERIMETER | B4: Variable Utilities | C4: X
A5: PERIMETER | B5: Scrap | D5: X
A6: PERIMETER | B6: Scrap Reselling | D6: X
A7: PERIMETER | B7: Other Variable (Production Consumable, Inventory ADJ)
A8: PERIMETER | B8: Inventory Adjustment | D8: X
A9: PERIMETER | B9: Production Consummables | C9: X
A10: PERIMETER | B10: Variable Conv.
A11: PERIMETER | B11: Indirect Labour | C11: X
A12: PERIMETER | B12: Fixed Labour | C12: X
A13: PERIMETER | B13: Semifixed | C13: X
A14: PERIMETER | B14: Fixed utilities | C14: X
A15: PERIMETER | B15: Fixed Cost | C15: X
A16: PERIMETER | B16: IT LOCAL | C16: Should be under shares
A17: PERIMETER | B17: Security | C17: Should be under shares
A18: PERIMETER | B18: Obsolete | D18: X
A19: PERIMETER | B19: Depreciation | C19: X
A20: PERIMETER | B20: Fixed Conv.
A21: PERIMETER | B21: TOTAL MFG COST w/o SHARES
A22: PERIMETER | B22: TOTAL SHARES
A23: PERIMETER | B23: Mess Union Fee | C23: X | E23: Target'tan çıkarılırken bütçe değerleri alınabilir.
A24: PERIMETER | B24: IT LOCAL | C24: X | E24: Target'tan çıkarılırken bütçe değerleri alınabilir.
A25: PERIMETER | B25: Security | C25: X | E25: Target'tan çıkarılırken bütçe değerleri alınabilir.
A26: PERIMETER | B26: IT GLOBAL | D26: X
A27: PERIMETER | B27: G&A(Insurance included) | D27: X
A28: PERIMETER | B28: TOTAL MFG COST w/ SHARES
A29: PERIMETER | B29: Functional Currency Impact | C29: X
A32: OTHERS | B32: Scrap
A33: OTHERS | B33: Scrap Reselling
A34: OTHERS | B34: Inventory Adjustment
A35: OTHERS | B35: Obsolete
A36: OTHERS | B36: Asset Sales
A38: OVERHEAD | B38: IT GLOBAL
A39: OVERHEAD | B39: G&A(Insurance included)

Sheet >>>

Sheet MTD Report  (HQD) (deneme)
B2: TD MTD Oct | C2: Actual Cost | I2: GP | M2: TC ALL | N2: TC WO GP | O2: GP TC
M3: 38.12 | N3: 37.43 | O3: 49.19 | P3: =O3/M3-1 -> 0.29039874 | T3: HC | U3: Unit price TRY
C4: ='data entry '!Q115 -> 53186 | I4: 6565 | T4: =(G7+G11+G12) -> 47.196781
B5: - Gain / +Loss | S5: Working meal | T5: =T4 -> 47.196781 | U5: 165.3 | V5: =T5*U5 -> 7801.6279
C6: EUR/000 | D6: €/pc | F6: HC | G6: GP | I6: EUR/000 | J6: €/pc | S6: Transport | T6: =T5 -> 47.196781 | U6: 185.43 | V6: =T6*U6*2 -> 17503.398
A7: MFG PERIMETER | B7: Direct Labor | C7: 961.83748 | D7: 8.5640541 | F7: 447 | G7: 34 | I7: =C7/F7*G7 -> 73.159898 | J7: =I7/$I$4*1000 -> 11.14393 | M7: =J7/D7-1 -> 0.30124465 | V7: =SUM(V4:V6) -> 25305.026
A8: MFG PERIMETER | B8: Variable Utilities | C8: 63.35664 | D8: 0.56411785 | I8: =D8*$I$4/1000 -> 3.7034337 | J8: =I8/$I$4*1000 -> 0.56411785
A9: MFG PERIMETER | B9: Other Variable (Production Consumable) | C9: 41.55311 | D9: 0.36998255 | I9: =D9*$I$4/1000 -> 2.4289354 | J9: =I9/$I$4*1000 -> 0.36998255
A10: MFG PERIMETER | B10: Variable Conv. | C10: 1066.7472 | D10: 9.4981545 | I10: =SUM(I7:I9) -> 79.292267 | J10: =SUM(J7:J9) -> 12.07803
A11: MFG PERIMETER | B11: Indirect Labour | C11: 409.57862 | D11: 3.6468255 | F11: 157 | G11: =9 -> 9 | I11: =C11/F11*G11 -> 23.479029 | J11: =I11/$I$4*1000 -> 3.5763944 | K11: 4 | M11: =C11/F11*K11 -> 10.435124 | N11: =M11*1000/I4 -> 1.5895086 | O11: CKD Impact
A12: MFG PERIMETER | B12: Fixed Labour | C12: 105.67001 | D12: 0.94086964 | F12: 34 | G12: =F12/C4*I4 -> 4.1967811 | I12: =D12*I4/1000 -> 6.1768092 | J12: =I12/$I$4*1000 -> 0.94086964
A13: MFG PERIMETER | B13: Semifixed | C13: 191.79625 | D13: 1.7077245 | I13: =D13*I4/1000 -> 11.211212 | J13: =I13/$I$4*1000 -> 1.7077245
A14: MFG PERIMETER | B14: Fixed utilities | C14: 4.03094 | D14: 0.035890874 | I14: =D14*$I$4/1000 -> 0.23562359 | J14: =I14/$I$4*1000 -> 0.035890874
A15: MFG PERIMETER | B15: Fixed Cost | C15: 52.07714 | D15: 0.46368691 | I15: =D15*$I$4/1000 -> 3.0441045 | J15: =I15/$I$4*1000 -> 0.46368691
A16: MFG PERIMETER | B16: Depreciation | C16: 78.79631 | D16: 0.70159032 | I16: =D16*$I$4/1000 -> 4.6059404 | J16: =I16/$I$4*1000 -> 0.70159032
A17: MFG PERIMETER | B17: Fixed Conv. | C17: 841.94927 | D17: 7.4965878 | I17: =SUM(I11:I16) -> 48.752718 | J17: =SUM(J11:J16) -> 7.4261567
A18: MFG PERIMETER | B18: TOTAL MFG COST w/o SHARES | C18: 1908.6965 | D18: 16.994742 | I18: =I17+I10 -> 128.04499 | J18: =I18/$I$4*1000 -> 19.504187
A19: MFG PERIMETER | B19: TOTAL SHARES | C19: 16.80699 | D19: 0.14964687 | I19: =D19*$I$4/1000 -> 0.98243172 | J19: =I19/$I$4*1000 -> 0.14964687
A20: MFG PERIMETER | B20: TOTAL MFG COST w/ SHARES | C20: 1925.5035 | D20: 17.144389 | I20: =I19+I18 -> 129.02742 | J20: =I20/$I$4*1000 -> 19.653834
A21: MFG PERIMETER | B21: Functional Currency Impact | C21: 263.21196 | D21: 2.3435991 | I21: =D21*$I$4/1000 -> 15.385728 | J21: =I21/$I$4*1000 -> 2.3435991
A22: MFG PERIMETER | B22: TOTAL Including FC | C22: 2188.7155 | D22: 19.487988 | I22: =I21+I20 -> 144.41315 | J22: =I22/$I$4*1000 -> 21.997433 | M22: =J22/D22-1 -> 0.12876878
J23: =I23/$I$4*1000 -> 0
A24: OTHERS | B24: Scrap | C24: 43.39548 | D24: 0.38638673 | J24: =I24/$I$4*1000 -> 0
A25: OTHERS | B25: Scrap Reselling | C25: -128.11905 | D25: -1.1407525 | J25: =I25/$I$4*1000 -> 0
A26: OTHERS | B26: Other Variable (Inventory Adj) | C26: 11.52424 | D26: 0.10261007 | J26: =I26/$I$4*1000 -> 0
A27: OTHERS | B27: Obsolete | C27: 25 | D27: 0.22259618 | J27: =I27/$I$4*1000 -> 0
A28: OTHERS | B28: Asset Sales | C28: 0 | D28: 0 | J28: =I28/$I$4*1000 -> 0
A29: OTHERS | B29: TOTAL OTHERS | C29: -48.19933 | D29: -0.42915948 | J29: =I29/$I$4*1000 -> 0
J30: =I30/$I$4*1000 -> 0
A31: OVERHEAD | B31: IT GLOBAL | C31: 213.47408 | D31: 1.9007406 | J31: =I31/$I$4*1000 -> 0
A32: OVERHEAD | B32: G&A(Insurance included) | C32: 93.09748 | D32: 0.82892575 | J32: =I32/$I$4*1000 -> 0
A33: OVERHEAD | B33: TOTAL OVERHEAD | C33: 306.57156 | D33: 2.7296664 | J33: =I33/$I$4*1000 -> 0
J34: =I34/$I$4*1000 -> 0
A35: ALL | B35: TOTAL ALL | C35: 2447.0877 | D35: 21.788495 | J35: =I35/$I$4*1000 -> 0
A37: Check | C37: 0 | D37: 0

Sheet MTD Report  (HQD)
B2: DW MTD May | C2: Budget26 | F2: Actual Cost | I2: 5+7Forecast | L2: Delta FCST vs ACT
C4: =+'MTD Report(HQD)_variance'!B4 -> 53265 | F4: =+'MTD Report(HQD)_variance'!Q4 -> 53186 | I4: 54900 | L4: =+F4-I4 -> -1714
B5: - Gain / +Loss
C6: EUR/000 | D6: €/pc | F6: EUR/000 | G6: €/pc | I6: EUR/000 | J6: €/pc
A7: MFG PERIMETER | B7: Direct Labor | C7: =+'MTD Report(HQD)_variance'!B7 -> 503 | D7: =+C7*1000/$C$4 -> 9.4433493 | F7: =+'MTD Report(HQD)_variance'!Q7 -> 391.63361 | G7: =+F7*1000/$F$4 -> 7.3634718 | I7: 460.9901 | J7: =+I7*1000/$I$4 -> 8.3969052 | L7: =+F7-I7 -> -69.356488 | M7: -28 k€ ISKUR impact(more efficient than FCST), -16 k€recharges to suppliers&ITCY, -13 k€ more efficienct than FCST, -5 k€ salary mix impact, -5 k€ less ovt than FCST -2k€ annual leave days accrual gain
A8: MFG PERIMETER | B8: Variable Utilities | C8: =+'MTD Report(HQD)_variance'!B8 -> 35.762038 | D8: =+C8*1000/$C$4 -> 0.67139844 | F8: =+'MTD Report(HQD)_variance'!Q8 -> 28.66065 | G8: =+F8*1000/$F$4 -> 0.53887583 | I8: 39.635645 | J8: =+I8*1000/$I$4 -> 0.72196076 | L8: =+F8-I8 -> -10.974995
A9: MFG PERIMETER | B9: Other Variable (Production Consumable) | C9: =+'MTD Report(HQD)_variance'!B9 -> 17.5665 | D9: =+C9*1000/$C$4 -> 0.32979442 | F9: =+'MTD Report(HQD)_variance'!Q9 -> 28.88567 | G9: =+F9*1000/$F$4 -> 0.54310664 | I9: 17.076248 | J9: =+I9*1000/$I$4 -> 0.31104278 | L9: =+F9-I9 -> 11.809422
A10: MFG PERIMETER | B10: Variable Conv. | C10: =+'MTD Report(HQD)_variance'!B10 -> 556.32854 | D10: =+C10*1000/$C$4 -> 10.444542 | F10: =+'MTD Report(HQD)_variance'!Q10 -> 449.17993 | G10: =+F10*1000/$F$4 -> 8.4454543 | I10: 517.70199 | J10: =+I10*1000/$I$4 -> 9.4299088 | L10: =+F10-I10 -> -68.522062
A11: MFG PERIMETER | B11: Indirect Labour | C11: =+'MTD Report(HQD)_variance'!B11 -> 217.31856 | D11: =+C11*1000/$C$4 -> 4.0799504 | F11: =+'MTD Report(HQD)_variance'!Q11 -> 229.24062 | G11: =+F11*1000/$F$4 -> 4.3101685 | I11: 221.9721 | J11: =+I11*1000/$I$4 -> 4.0432076 | L11: =+F11-I11 -> 7.2685249
A12: MFG PERIMETER | B12: Fixed Labour | C12: =+'MTD Report(HQD)_variance'!B12 -> 107.62726 | D12: =+C12*1000/$C$4 -> 2.0206001 | F12: =+'MTD Report(HQD)_variance'!Q12 -> 111.60063 | G12: =+F12*1000/$F$4 -> 2.0983084 | I12: 109.70635 | J12: =+I12*1000/$I$4 -> 1.9982942 | L12: =+F12-I12 -> 1.8942799
A13: MFG PERIMETER | B13: Semifixed | C13: =+'MTD Report(HQD)_variance'!B13 -> 188.37864 | D13: =+C13*1000/$C$4 -> 3.5366307 | F13: =+'MTD Report(HQD)_variance'!Q13 -> 111.35076 | G13: =+F13*1000/$F$4 -> 2.0936103 | I13: 196.44185 | J13: =+I13*1000/$I$4 -> 3.5781758 | L13: =+F13-I13 -> -85.09109 | M13: 56 k€ less expense on mnt
A14: MFG PERIMETER | B14: Fixed utilities | C14: =+'MTD Report(HQD)_variance'!B14 -> 6 | D14: =+C14*1000/$C$4 -> 0.11264433 | F14: =+'MTD Report(HQD)_variance'!Q14 -> 2.00758 | G14: =+F14*1000/$F$4 -> 0.037746399 | I14: 6.731241 | J14: =+I14*1000/$I$4 -> 0.12260913 | L14: =+F14-I14 -> -4.723661
A15: MFG PERIMETER | B15: Fixed Cost | C15: =+'MTD Report(HQD)_variance'!B15 -> 43.825739 | D15: =+C15*1000/$C$4 -> 0.82278681 | F15: =+'MTD Report(HQD)_variance'!Q15 -> 50.4317 | G15: =+F15*1000/$F$4 -> 0.94821382 | I15: 48.289824 | J15: =+I15*1000/$I$4 -> 0.87959606 | L15: =+F15-I15 -> 2.1418763
A16: MFG PERIMETER | B16: Depreciation | C16: =+'MTD Report(HQD)_variance'!B16 -> 152.87378 | D16: =+C16*1000/$C$4 -> 2.8700606 | F16: =+'MTD Report(HQD)_variance'!Q16 -> 132.04277 | G16: =+F16*1000/$F$4 -> 2.4826603 | I16: 140.00134 | J16: =+I16*1000/$I$4 -> 2.5501155 | L16: =+F16-I16 -> -7.9585723
A17: MFG PERIMETER | B17: Fixed Conv. | C17: =+'MTD Report(HQD)_variance'!B17 -> 716.02398 | D17: =+C17*1000/$C$4 -> 13.442673 | F17: =+'MTD Report(HQD)_variance'!Q17 -> 636.67406 | G17: =+F17*1000/$F$4 -> 11.970708 | I17: 723.1427 | J17: =+I17*1000/$I$4 -> 13.171998 | L17: =+F17-I17 -> -86.468642
A18: MFG PERIMETER | B18: TOTAL MFG COST w/o SHARES | C18: =+'MTD Report(HQD)_variance'!B18 -> 1272.3525 | D18: =+C18*1000/$C$4 -> 23.887215 | F18: =+'MTD Report(HQD)_variance'!Q18 -> 1085.854 | G18: =+F18*1000/$F$4 -> 20.416162 | I18: 1240.8447 | J18: =+I18*1000/$I$4 -> 22.601907 | L18: =+F18-I18 -> -154.9907
A19: MFG PERIMETER | B19: TOTAL SHARES | C19: =+'MTD Report(HQD)_variance'!B19 -> 20.474517 | D19: =+C19*1000/$C$4 -> 0.3843897 | F19: =+'MTD Report(HQD)_variance'!Q19 -> 5.0717 | G19: =+F19*1000/$F$4 -> 0.095357801 | I19: 13.453346 | J19: =+I19*1000/$I$4 -> 0.24505184 | L19: =+F19-I19 -> -8.3816461
A20: MFG PERIMETER | B20: TOTAL MFG COST w/ SHARES | C20: =+'MTD Report(HQD)_variance'!B20 -> 1292.827 | D20: =+C20*1000/$C$4 -> 24.271605 | F20: =+'MTD Report(HQD)_variance'!Q20 -> 1090.9257 | G20: =+F20*1000/$F$4 -> 20.51152 | I20: 1254.298 | J20: =+I20*1000/$I$4 -> 22.846959 | L20: =+F20-I20 -> -163.37235
A21: MFG PERIMETER | B21: Functional Currency Impact | C21: =+'MTD Report(HQD)_variance'!B22 -> 416.35266 | D21: =+C21*1000/$C$4 -> 7.8166274 | F21: =+'MTD Report(HQD)_variance'!Q22 -> 301.40709 | G21: =+F21*1000/$F$4 -> 5.6670381 | I21: 304.784 | J21: =+I21*1000/$I$4 -> 5.5516211 | L21: =+F21-I21 -> -3.37691
A22: MFG PERIMETER | B22: TOTAL Including FC | C22: =+C21+C20 -> 1709.1797 | D22: =+C22*1000/$C$4 -> 32.088232 | F22: =+F21+F20 -> 1392.3328 | G22: =+F22*1000/$F$4 -> 26.178558 | I22: 1559.082 | J22: =+I22*1000/$I$4 -> 28.39858 | L22: =+F22-I22 -> -166.74926
A24: OTHERS | B24: Scrap | C24: =+'MTD Report(HQD)_variance'!B25 -> 21 | D24: =+C24*1000/$C$4 -> 0.39425514 | F24: =+'MTD Report(HQD)_variance'!Q25 -> 27.97038 | G24: =+F24*1000/$F$4 -> 0.52589742 | I24: 23.30592 | J24: =+I24*1000/$I$4 -> 0.42451585 | L24: =+F24-I24 -> 4.66446
A25: OTHERS | B25: Scrap Reselling | C25: =+'MTD Report(HQD)_variance'!B26 -> -53 | D25: =+C25*1000/$C$4 -> -0.99502488 | F25: =+'MTD Report(HQD)_variance'!Q26 -> -74.14161 | G25: =+F25*1000/$F$4 -> -1.3940061 | I25: -51.571118 | J25: =+I25*1000/$I$4 -> -0.93936463 | L25: =+F25-I25 -> -22.570492
A26: OTHERS | B26: Other Variable (Inventory Adj) | C26: =+'MTD Report(HQD)_variance'!B27 -> 0 | D26: =+C26*1000/$C$4 -> 0 | F26: =+'MTD Report(HQD)_variance'!Q27 -> -8.91442 | G26: =+F26*1000/$F$4 -> -0.16760839 | I26: 0 | J26: =+I26*1000/$I$4 -> 0 | L26: =+F26-I26 -> -8.91442
A27: OTHERS | B27: Obsolete | C27: =+'MTD Report(HQD)_variance'!B28 -> 8 | D27: =+C27*1000/$C$4 -> 0.15019243 | F27: =+'MTD Report(HQD)_variance'!Q28 -> -30.71528 | G27: =+F27*1000/$F$4 -> -0.57750686 | I27: 14.970477 | J27: =+I27*1000/$I$4 -> 0.27268628 | L27: =+F27-I27 -> -45.685757
A28: OTHERS | B28: Asset Sales | C28: =+'MTD Report(HQD)_variance'!B29 -> 0 | D28: =+C28*1000/$C$4 -> 0 | F28: =+'MTD Report(HQD)_variance'!Q29 -> 0 | G28: =+F28*1000/$F$4 -> 0 | I28: 0 | J28: =+I28*1000/$I$4 -> 0 | L28: =+F28-I28 -> 0 | M28: Aging risk is decreased especially for active materials
A29: OTHERS | B29: TOTAL OTHERS | C29: =+'MTD Report(HQD)_variance'!B30 -> -24 | D29: =+C29*1000/$C$4 -> -0.4505773 | F29: =+'MTD Report(HQD)_variance'!Q30 -> -85.80093 | G29: =+F29*1000/$F$4 -> -1.613224 | I29: -13.294721 | J29: =+I29*1000/$I$4 -> -0.2421625 | L29: =+F29-I29 -> -72.506209
A31: OVERHEAD | B31: IT GLOBAL | C31: =+'MTD Report(HQD)_variance'!B32 -> 90.697223 | D31: =+C31*1000/$C$4 -> 1.7027546 | F31: =+'MTD Report(HQD)_variance'!Q32 -> 89.41512 | G31: =+F31*1000/$F$4 -> 1.6811778 | I31: 90.697222 | J31: =+I31*1000/$I$4 -> 1.6520441 | L31: =+F31-I31 -> -1.2821024
A32: OVERHEAD | B32: G&A(Insurance included) | C32: =+'MTD Report(HQD)_variance'!B33 -> 94.532002 | D32: =+C32*1000/$C$4 -> 1.7747489 | F32: =+'MTD Report(HQD)_variance'!Q33 -> 43.15732 | G32: =+F32*1000/$F$4 -> 0.81144136 | I32: 48.601049 | J32: =+I32*1000/$I$4 -> 0.88526502 | L32: =+F32-I32 -> -5.4437294
A33: OVERHEAD | B33: TOTAL OVERHEAD | C33: =SUM(C31:C32) -> 185.22922 | D33: =+C33*1000/$C$4 -> 3.4775035 | F33: =SUM(F31:F32) -> 132.57244 | G33: =+F33*1000/$F$4 -> 2.4926191 | I33: 139.29827 | J33: =+I33*1000/$I$4 -> 2.5373091 | L33: =+F33-I33 -> -6.7258318
A35: ALL | B35: GRAND TOTAL | C35: =+C33+C29+C22 -> 1870.4089 | D35: =+C35*1000/$C$4 -> 35.115159 | F35: =+F33+F29+F22 -> 1439.1043 | G35: =+F35*1000/$F$4 -> 27.057953 | I35: 1685.0856 | J35: =+I35*1000/$I$4 -> 30.693727 | L35: =+F35-I35 -> -245.9813
A37: Check | C37: =+C35*1000-'MTD Report(HQD)_variance'!B36*1000 -> 0 | F37: =+F35*1000-'MTD Report(HQD)_variance'!Q36*1000 -> 0

Sheet YTD Report  (HQD)
B2: DW YTD MAY | C2: Budget26 | F2: Actual Cost | I2: 5+7 Forecast | L2: Delta FCST vs ACT
C4: =+'YTD Report(HQD)_variance '!B4 -> 289459 | F4: =+'YTD Report(HQD)_variance '!Q4 -> 240074 | I4: 241788 | L4: =+F4-I4 -> -1714
B5: - Gain / +Loss
C6: EUR/000 | D6: €/pc | F6: EUR/000 | G6: €/pc | I6: EUR/000 | J6: €/pc
A7: MFG PERIMETER | B7: Direct Labor | C7: =+'YTD Report(HQD)_variance '!B7 -> 3129 | D7: =+C7*1000/$C$4 -> 10.809821 | F7: =+'YTD Report(HQD)_variance '!Q7 -> 2418.8816 | G7: =+F7*1000/$F$4 -> 10.075567 | I7: 2488.2381 | J7: =+I7*1000/$I$4 -> 10.290991 | L7: =+F7-I7 -> -69.356488
A8: MFG PERIMETER | B8: Variable Utilities | C8: =+'YTD Report(HQD)_variance '!B8 -> 209.56944 | D8: =+C8*1000/$C$4 -> 0.72400387 | F8: =+'YTD Report(HQD)_variance '!Q8 -> 151.60735 | G8: =+F8*1000/$F$4 -> 0.63150258 | I8: 162.58235 | J8: =+I8*1000/$I$4 -> 0.67241693 | L8: =+F8-I8 -> -10.974995
A9: MFG PERIMETER | B9: Other Variable (Production Consumable) | C9: =+'YTD Report(HQD)_variance '!B9 -> 95.361 | D9: =+C9*1000/$C$4 -> 0.32944562 | F9: =+'YTD Report(HQD)_variance '!Q9 -> 113.14721 | G9: =+F9*1000/$F$4 -> 0.47130139 | I9: 101.33779 | J9: =+I9*1000/$I$4 -> 0.41911835 | L9: =+F9-I9 -> 11.809422
A10: MFG PERIMETER | B10: Variable Conv. | C10: =+'YTD Report(HQD)_variance '!B10 -> 3433.9304 | D10: =+C10*1000/$C$4 -> 11.863271 | F10: =+'YTD Report(HQD)_variance '!Q10 -> 2683.6361 | G10: =+F10*1000/$F$4 -> 11.178371 | I10: 2752.1582 | J10: =+I10*1000/$I$4 -> 11.382526 | L10: =+F10-I10 -> -68.522062
A11: MFG PERIMETER | B11: Indirect Labour | C11: =+'YTD Report(HQD)_variance '!B11 -> 1264.7213 | D11: =+C11*1000/$C$4 -> 4.369259 | F11: =+'YTD Report(HQD)_variance '!Q11 -> 1325.2768 | G11: =+F11*1000/$F$4 -> 5.5202847 | I11: 1318.0083 | J11: =+I11*1000/$I$4 -> 5.4510906 | L11: =+F11-I11 -> 7.2685249
A12: MFG PERIMETER | B12: Fixed Labour | C12: =+'YTD Report(HQD)_variance '!B12 -> 644.90809 | D12: =+C12*1000/$C$4 -> 2.2279773 | F12: =+'YTD Report(HQD)_variance '!Q12 -> 636.09685 | G12: =+F12*1000/$F$4 -> 2.6495866 | I12: 634.20257 | J12: =+I12*1000/$I$4 -> 2.6229696 | L12: =+F12-I12 -> 1.8942799
A13: MFG PERIMETER | B13: Semifixed | C13: =+'YTD Report(HQD)_variance '!B13 -> 1060.8528 | D13: =+C13*1000/$C$4 -> 3.66495 | F13: =+'YTD Report(HQD)_variance '!Q13 -> 906.21602 | G13: =+F13*1000/$F$4 -> 3.7747362 | I13: 991.30711 | J13: =+I13*1000/$I$4 -> 4.099902 | L13: =+F13-I13 -> -85.09109
A14: MFG PERIMETER | B14: Fixed utilities | C14: =+'YTD Report(HQD)_variance '!B14 -> 32 | D14: =+C14*1000/$C$4 -> 0.11055106 | F14: =+'YTD Report(HQD)_variance '!Q14 -> 16.25655 | G14: =+F14*1000/$F$4 -> 0.067714746 | I14: 20.980211 | J14: =+I14*1000/$I$4 -> 0.086771101 | L14: =+F14-I14 -> -4.723661
A15: MFG PERIMETER | B15: Fixed Cost | C15: =+'YTD Report(HQD)_variance '!B15 -> 262.61091 | D15: =+C15*1000/$C$4 -> 0.90724733 | F15: =+'YTD Report(HQD)_variance '!Q15 -> 205.53572 | G15: =+F15*1000/$F$4 -> 0.85613486 | I15: 203.39384 | J15: =+I15*1000/$I$4 -> 0.84120735 | L15: =+F15-I15 -> 2.1418763
A16: MFG PERIMETER | B16: Depreciation | C16: =+'YTD Report(HQD)_variance '!B16 -> 935.32923 | D16: =+C16*1000/$C$4 -> 3.2313013 | F16: =+'YTD Report(HQD)_variance '!Q16 -> 748.35691 | G16: =+F16*1000/$F$4 -> 3.1171926 | I16: 756.31548 | J16: =+I16*1000/$I$4 -> 3.1280108 | L16: =+F16-I16 -> -7.9585723
A17: MFG PERIMETER | B17: Fixed Conv. | C17: =+'YTD Report(HQD)_variance '!B17 -> 4200.4223 | D17: =+C17*1000/$C$4 -> 14.511286 | F17: =+'YTD Report(HQD)_variance '!Q17 -> 3837.7389 | G17: =+F17*1000/$F$4 -> 15.98565 | I17: 3924.2075 | J17: =+I17*1000/$I$4 -> 16.229951 | L17: =+F17-I17 -> -86.468642
A18: MFG PERIMETER | B18: TOTAL MFG COST w/o SHARES | C18: =+'YTD Report(HQD)_variance '!B18 -> 7634.3528 | D18: =+C18*1000/$C$4 -> 26.374557 | F18: =+'YTD Report(HQD)_variance '!Q18 -> 6521.375 | G18: =+F18*1000/$F$4 -> 27.16402 | I18: 6676.3657 | J18: =+I18*1000/$I$4 -> 27.612478 | L18: =+F18-I18 -> -154.9907
... A20: MFG PERIMETER | B20: TOTAL MFG COST w/ SHARES | C20: =+'YTD Report(HQD)_variance '!B20 -> 7759.6885 | D20: =+C20*1000/$C$4 -> 26.807557 | F20: =+'YTD Report(HQD)_variance '!Q20 -> 6623.8096 | G20: =+F20*1000/$F$4 -> 27.5907 | I20: 6787.1819 | J20: =+I20*1000/$I$4 -> 28.070797 | L20: =+F20-I20 -> -163.37235
A21: MFG PERIMETER | B21: Functional Currency Impact | C21: =+'YTD Report(HQD)_variance '!B22 -> 2478.1861 | D21: =+C21*1000/$C$4 -> 8.5614407 | F21: =+'YTD Report(HQD)_variance '!Q22 -> 1802.1403 | G21: =+F21*1000/$F$4 -> 7.5066036 | I21: 1805.5173 | J21: =+I21*1000/$I$4 -> 7.4673567 | L21: =+F21-I21 -> -3.37691
A22: MFG PERIMETER | B22: TOTAL Including FC | C22: =+'YTD Report(HQD)_variance '!B23 -> 10237.875 | D22: =+C22*1000/$C$4 -> 35.368997 | F22: =+F21+F20 -> 8425.9499 | G22: =+F22*1000/$F$4 -> 35.097303 | I22: 8592.6992 | J22: =+I22*1000/$I$4 -> 35.538154 | L22: =+F22-I22 -> -166.74926
A24: OTHERS | B24: Scrap | C24: =+'YTD Report(HQD)_variance '!B25 -> 136 | D24: =+C24*1000/$C$4 -> 0.46984202 | F24: =+'YTD Report(HQD)_variance '!Q25 -> 136.63113 | G24: =+F24*1000/$F$4 -> 0.5691209 | I24: 131.96667 | J24: =+I24*1000/$I$4 -> 0.54579495 | L24: =+F24-I24 -> 4.66446
A25: OTHERS | B25: Scrap Reselling | C25: =+'YTD Report(HQD)_variance '!B26 -> -303 | D25: =+C25*1000/$C$4 -> -1.0467804 | F25: =+'YTD Report(HQD)_variance '!Q26 -> -306.81066 | G25: =+F25*1000/$F$4 -> -1.2779837 | I25: -284.24017 | J25: =+I25*1000/$I$4 -> -1.175576 | L25: =+F25-I25 -> -22.570492
A26: OTHERS | B26: Other Variable (Inventory Adj) | C26: =+'YTD Report(HQD)_variance '!B27 -> 0 | D26: =+C26*1000/$C$4 -> 0 | F26: =+'YTD Report(HQD)_variance '!Q27 -> 63.28184 | G26: =+F26*1000/$F$4 -> 0.26359306 | I26: 72.19626 | J26: =+I26*1000/$I$4 -> 0.29859323 | L26: =+F26-I26 -> -8.91442
A27: OTHERS | B27: Obsolete | C27: =+'YTD Report(HQD)_variance '!B28 -> 52 | D27: =+C27*1000/$C$4 -> 0.17964548 | F27: =+'YTD Report(HQD)_variance '!Q28 -> 17.3384 | G27: =+F27*1000/$F$4 -> 0.072221065 | I27: 63.024157 | J27: =+I27*1000/$I$4 -> 0.26065875 | L27: =+F27-I27 -> -45.685757
A28: OTHERS | B28: Asset Sales | C28: =+'YTD Report(HQD)_variance '!B29 -> 0 | D28: =+C28*1000/$C$4 -> 0 | F28: =+'YTD Report(HQD)_variance '!Q29 -> 0 | G28: =+F28*1000/$F$4 -> 0 | I28: 0 | J28: =+I28*1000/$I$4 -> 0 | L28: =+F28-I28 -> 0
A29: OTHERS | B29: TOTAL OTHERS | C29: =+'YTD Report(HQD)_variance '!B30 -> -115 | D29: =+C29*1000/$C$4 -> -0.39729288 | F29: =+'YTD Report(HQD)_variance '!Q30 -> -89.55929 | G29: =+F29*1000/$F$4 -> -0.37304868 | I29: -17.053081 | J29: =+I29*1000/$I$4 -> -0.070529064 | L29: =+F29-I29 -> -72.506209
A31: OVERHEAD | B31: IT GLOBAL | C31: =+'YTD Report(HQD)_variance '!B32 -> 544.18334 | D31: =+C31*1000/$C$4 -> 1.8800014 | F31: =+'YTD Report(HQD)_variance '!Q32 -> 535.96594 | G31: =+F31*1000/$F$4 -> 2.2325031 | I31: 537.24804 | J31: =+I31*1000/$I$4 -> 2.2219798 | L31: =+F31-I31 -> -1.2821024
A32: OVERHEAD | B32: G&A(Insurance included) | C32: =+'YTD Report(HQD)_variance '!B33 -> 567.19201 | D32: =+C32*1000/$C$4 -> 1.95949 | F32: =+'YTD Report(HQD)_variance '!Q33 -> 538.91129 | G32: =+F32*1000/$F$4 -> 2.2447716 | I32: 544.35502 | J32: =+I32*1000/$I$4 -> 2.2513732 | L32: =+F32-I32 -> -5.4437294
A33: OVERHEAD | B33: TOTAL OVERHEAD | C33: =SUM(C31:C32) -> 1111.3753 | D33: =+C33*1000/$C$4 -> 3.8394914 | F33: =SUM(F31:F32) -> 1074.8772 | G33: =+F33*1000/$F$4 -> 4.4772746 | I33: 1081.6031 | J33: =+I33*1000/$I$4 -> 4.4733529 | L33: =+F33-I33 -> -6.7258318
A35: ALL | B35: GRAND TOTAL | C35: =+C33+C29+C22 -> 11234.25 | D35: =+C35*1000/$C$4 -> 38.811196 | F35: =+F33+F29+F22 -> 9411.2679 | G35: =+F35*1000/$F$4 -> 39.201529 | I35: 9657.2492 | J35: =+I35*1000/$I$4 -> 39.940978 | L35: =+F35-I35 -> -245.9813
A37: Check | C37: =+C35*1000-'YTD Report(HQD)_variance '!B36*1000 -> 0 | F37: =+F35*1000-'YTD Report(HQD)_variance '!Q36*1000 -> 0

Sheet MTD VAR 
A1: Volume | B1: =+'Budget assumption'!Q35 -> 71500 | C1: =H1-B1 -> -18235 | H1: ='Budget assumption'!Q66 -> 53265 | I1: ='Budget assumption'!Q321 -> 0 | K1: ='data entry '!Q82 -> 53186 | M1: ='data entry '!Q115 -> 53186 | AA1: EFF | AB1: variable cost | AC1: Actual minus Copertura
B2: EUR | C2: EUR | H2: EUR | I2: EUR | K2: EUR | M2: EUR | Q2: Variances vs Budget | V2: Variances vs STD | AB2: fixed cost | AC2: Actual minus Budget
A3: Cost Elements | B3: STD | C3: Delta Volume | D3: ACE | E3: HW / TW | F3: Price FX | G3: Seasonality | H3: Plan Costs | I3: Budget VAR | K3: Copertura | M3: Act. Costs | O3: Variance vs STD | Q3: EFF | R3: FCA | S3: Total Variance | V3: EFF | W3: FCA | X3: Total Variance
D4: ACE
I5: FCA
A6: Direct Labour | B6: ='Budget assumption'!Q37 -> 813.54709 | C6: ='Budget assumption'!Q70 -> -207.48295 | D6: ='Budget assumption'!Q118 -> -49.280033 | E6: ='Budget assumption'!Q149 -> -38.746752 | F6: ='Budget assumption'!Q180 -> 66.129739 | G6: ='Budget assumption'!Q242+'Budget assumption'!Q273 -> -81.167087 | H6: ='Budget assumption'!Q211 -> 503 | J6: =H6-SUM(B6:G6) -> 0 | K6: ='data entry '!Q84 -> 598.40414 | M6: ='data entry '!Q117 -> 391.63361 | O6: =M6-K6 -> -206.77053 | Q6: =M6-K6-E6-F6-D6-G6 -> -103.7064 | S6: =Q6+R6 -> -103.7064 | V6: =M6-K6 -> -206.77053 | X6: =V6+W6 -> -206.77053
A7: Variable Utilities | B7: ='Budget assumption'!Q38 -> 55.137763 | C7: ='Budget assumption'!Q71 -> -14.062057 | D7: ='Budget assumption'!Q119 -> 0 | E7: ='Budget assumption'!Q150 -> 0 | F7: ='Budget assumption'!Q181 -> -4.1759045 | G7: ='Budget assumption'!Q243+'Budget assumption'!Q274 -> -1.1377628 | H7: ='Budget assumption'!Q212 -> 35.762038 | J7: =H7-SUM(B7:G7) -> 0 | K7: ='data entry '!Q85 -> 39.841032 | M7: ='data entry '!Q118 -> 28.66065 | O7: =M7-K7 -> -11.180382 | Q7: =M7-K7-E7-F7-D7-G7 -> -5.8667146 | S7: =Q7+R7 -> -5.8667146 | V7: =M7-K7 -> -11.180382 | X7: =V7+W7 -> -11.180382
A8: Variable Costs | B8: ='Budget assumption'!Q39 -> 25.133277 | C8: ='Budget assumption'!Q72 -> -6.4098644 | D8: ='Budget assumption'!Q120 -> -1 | E8: ='Budget assumption'!Q151 -> 0 | F8: ='Budget assumption'!Q182 -> -0.15363563 | G8: ='Budget assumption'!Q244+'Budget assumption'!Q275 -> -0.0032767818 | H8: ='Budget assumption'!Q213 -> 17.5665 | J8: =H8-SUM(B8:G8) -> 0 | K8: ='data entry '!Q86 -> 17.021983 | M8: ='data entry '!Q119 -> 28.88567 | O8: =M8-K8 -> 11.863687 | Q8: =M8-K8-E8-F8-D8-G8 -> 13.020599 | S8: =Q8+R8 -> 13.020599 | V8: =M8-K8 -> 11.863687 | X8: =V8+W8 -> 11.863687
A9: VARIABLE CONVERSION | B9: =SUM(B6:B8) -> 893.81813 | C9: =SUM(C6:C8) -> -227.95487 | D9: =SUM(D6:D8) -> -50.280033 | E9: =SUM(E6:E8) -> -38.746752 | F9: =SUM(F6:F8) -> 61.800199 | G9: =SUM(G6:G8) -> -82.308127 | H9: =SUM(H6:H8) -> 556.32854 | I9: =SUM(I6:I8) -> 0 | J9: =H9-SUM(B9:G9) -> 0 | K9: =SUM(K6:K8) -> 655.26716 | M9: =SUM(M6:M8) -> 449.17993 | O9: =SUM(O6:O8) -> -206.08723 | Q9: =SUM(Q6:Q8) -> -96.552512 | R9: =SUM(R6:R8) -> 0 | S9: =SUM(S6:S8) -> -96.552512 | V9: =SUM(V6:V8) -> -206.08723 | W9: =SUM(W6:W8) -> 0 | X9: =SUM(X6:X8) -> -206.08723
A10: Indirect Labour | B10: ='Budget assumption'!Q41 -> 319.09496 | D10: ='Budget assumption'!Q122 -> 0 | E10: ='Budget assumption'!Q153 -> -42 | F10: ='Budget assumption'!Q184 -> -18.861442 | G10: ='Budget assumption'!Q246+'Budget assumption'!Q277 -> -40.914958 | H10: ='Budget assumption'!Q215 -> 217.31856 | I10: ='Budget assumption'!Q323 -> 81.380371 | J10: =H10-SUM(B10:G10) -> 0 | K10: ='data entry '!Q88 -> 236.64471 | M10: ='data entry '!Q121 -> 229.24062 | O10: =M10-K10 -> -7.4040914 | Q10: =M10-H10 -> 11.922062 | R10: =H10-K10-E10-I10-F10-G10-D10 -> 1.0698749 | S10: =Q10+R10 -> 12.991937 | V10: =M10-B10 -> -89.854338 | W10: =B10-K10 -> 82.450246 | X10: =V10+W10 -> -7.4040914
A11: Fixed Labour | B11: ='Budget assumption'!Q42 -> 115.42242 | D11: ='Budget assumption'!Q123 -> 0 | E11: ='Budget assumption'!Q154 -> 7 | F11: ='Budget assumption'!Q185 -> 12.297265 | G11: ='Budget assumption'!Q247+'Budget assumption'!Q278 -> -27.092424 | H11: ='Budget assumption'!Q216 -> 107.62726 | I11: ='Budget assumption'!Q324 -> 29.436754 | J11: =H11-SUM(B11:G11) -> 0 | K11: ='data entry '!Q89 -> 83.695495 | M11: ='data entry '!Q122 -> 111.60063 | O11: =M11-K11 -> 27.905135 | Q11: =M11-H11 -> 3.9733651 | R11: =H11-K11-E11-I11-F11-G11-D11 -> 2.2901751 | S11: =Q11+R11 -> 6.2635402 | V11: =M11-B11 -> -3.8217938 | W11: =B11-K11 -> 31.726929 | X11: =V11+W11 -> 27.905135
A12: Semifixed | B12: ='Budget assumption'!Q43 -> 222.84033 | D12: ='Budget assumption'!Q124 -> 0 | E12: ='Budget assumption'!Q155 -> -13.429082 | F12: ='Budget assumption'!Q186 -> -4.3322822 | G12: ='Budget assumption'!Q248+'Budget assumption'!Q279 -> -16.700329 | H12: ='Budget assumption'!Q217 -> 188.37864 | I12: ='Budget assumption'!Q325 -> 56.832075 | J12: =H12-SUM(B12:G12) -> 0 | K12: ='data entry '!Q90 -> 162.06681 | M12: ='data entry '!Q123 -> 111.35076 | O12: =M12-K12 -> -50.716054 | Q12: =M12-H12 -> -77.027875 | R12: =H12-K12-E12-I12-F12-G12-D12 -> 3.941439 | S12: =Q12+R12 -> -73.086436 | V12: =M12-B12 -> -111.48957 | W12: =B12-K12 -> 60.773514 | X12: =V12+W12 -> -50.716054
A13: Fixed utilities | B13: ='Budget assumption'!Q44 -> 14.176767 | D13: ='Budget assumption'!Q125 -> -1.1 | E13: ='Budget assumption'!Q156 -> -2 | F13: ='Budget assumption'!Q187 -> -5.17 | G13: ='Budget assumption'!Q249+'Budget assumption'!Q280 -> 0.0932329 | H13: ='Budget assumption'!Q218 -> 6 | I13: ='Budget assumption'!Q326 -> 3.6155713 | J13: =H13-SUM(B13:G13) -> 0 | K13: ='data entry '!Q91 -> 8.8590025 | M13: ='data entry '!Q124 -> 2.00758 | O13: =M13-K13 -> -6.8514225 | Q13: =M13-H13 -> -3.99242 | R13: =H13-K13-E13-I13-F13-G13-D13 -> 1.7021933 | S13: =Q13+R13 -> -2.2902267 | V13: =M13-B13 -> -12.169187 | W13: =B13-K13 -> 5.3177646 | X13: =V13+W13 -> -6.8514225
A14: Fixed Cost | B14: ='Budget assumption'!Q45 -> 49.7397 | D14: ='Budget assumption'!Q126 -> 0 | E14: ='Budget assumption'!Q157 -> 0 | F14: ='Budget assumption'!Q188 -> 4.7347992 | G14: ='Budget assumption'!Q250+'Budget assumption'!Q281 -> -10.64876 | H14: ='Budget assumption'!Q219 -> 43.825739 | I14: ='Budget assumption'!Q327 -> 12.685363 | J14: =H14-SUM(B14:G14) -> 0 | K14: ='data entry '!Q92 -> 41.414629 | M14: ='data entry '!Q125 -> 50.4317 | O14: =M14-K14 -> 9.0170707 | Q14: =M14-H14 -> 6.6059608 | R14: =H14-K14-E14-I14-F14-G14-D14 -> -4.3602923 | S14: =Q14+R14 -> 2.2456685 | V14: =M14-B14 -> 0.69200048 | W14: =B14-K14 -> 8.3250702 | X14: =V14+W14 -> 9.0170707
A15: Depreciation | B15: ='Budget assumption'!Q46 -> 194.73892 | D15: ='Budget assumption'!Q127 -> 0 | E15: ='Budget assumption'!Q158 -> 1.1397408 | F15: ='Budget assumption'!Q189 -> -0.0033 | G15: ='Budget assumption'!Q251+'Budget assumption'!Q282 -> -43.001579 | H15: ='Budget assumption'!Q220 -> 152.87378 | I15: ='Budget assumption'!Q329 -> 49.665233 | J15: =H15-SUM(B15:G15) -> 0 | K15: ='data entry '!Q93 -> 543.42574 | M15: ='data entry '!Q126 -> 132.04277 | O15: =M15-K15 -> -411.38297 | Q15: =M15-H15 -> -20.83101 | R15: =H15-K15-E15-I15-F15-G15-D15 -> -398.35205 | S15: =Q15+R15 -> -419.18306 | V15: =M15-B15 -> -62.696148 | W15: =B15-K15 -> -348.68682 | X15: =V15+W15 -> -411.38297
A16: FIXED CONVERSION | B16: =SUM(B10:B15) -> 916.0131 | C16: =SUM(C10:C15) -> 0 | D16: =SUM(D10:D15) -> -1.1 | E16: =SUM(E10:E15) -> -49.289342 | F16: =SUM(F10:F15) -> -11.33496 | G16: =SUM(G10:G15) -> -138.26482 | H16: =SUM(H10:H15) -> 716.02398 | I16: =SUM(I10:I15) -> 233.61537 | J16: =H16-SUM(B16:G16) -> 0 | K16: =SUM(K10:K15) -> 1076.1064 | M16: =SUM(M10:M15) -> 636.67406 | O16: =SUM(O10:O15) -> -439.43233 | Q16: =SUM(Q10:Q15) -> -79.349918 | R16: =SUM(R10:R15) -> -393.70866 | S16: =Q16+R16 -> -473.05858 | V16: =SUM(V10:V15) -> -279.33904 | W16: =SUM(W10:W15) -> -160.09329 | X16: =SUM(X10:X15) -> -439.43233
A17: TOTAL MFG COST w/o SHARES | B17: =B9+B16 -> 1809.8312 | C17: =C9+C16 -> -227.95487 | D17: =D9+D16 -> -51.380033 | E17: =E9+E16 -> -88.036094 | F17: =F9+F16 -> 50.465239 | G17: =G9+G16 -> -220.57294 | H17: =H9+H16 -> 1272.3525 | I17: =I9+I16 -> 233.61537 | J17: =H17-SUM(B17:G17) -> 0 | K17: =K9+K16 -> 1731.3735 | M17: =M9+M16 -> 1085.854 | O17: =M17-K17 -> -645.51956 | Q17: =Q9+Q16 -> -175.90243 | R17: =R9+R16 -> -393.70866 | S17: =Q17+R17 -> -569.61109 | V17: =V9+V16 -> -485.42626 | W17: =W9+W16 -> -160.09329 | X17: =X9+X16 -> -645.51956
A18: TOTAL SHARES | B18: ='Budget assumption'!Q49 -> 12.784403 | D18: ='Budget assumption'!Q130 -> 0 | E18: ='Budget assumption'!Q161 -> 0 | F18: ='Budget assumption'!Q192 -> 0 | G18: ='Budget assumption'!Q254+'Budget assumption'!Q285 -> 7.6901145 | H18: ='Budget assumption'!Q223 -> 20.474517 | I18: ='Budget assumption'!V49 -> 0 | J18: =H18-SUM(B18:G18) -> 0 | K18: ='data entry '!Q96 -> 0 | M18: ='data entry '!Q129 -> 5.0717 | O18: =M18-K18 -> 5.0717 | Q18: =M18-H18 -> -15.402817 | R18: =H18-K18-E18-I18-F18-G18-D18 -> 12.784403 | S18: =Q18+R18 -> -2.6184145 | V18: =M18-B18 -> -7.7127029 | W18: =B18-K18 -> 12.784403 | X18: =V18+W18 -> 5.0717
A19: TOTAL MFG COST w/ SHARES | B19: =B17+B18 -> 1822.6156 | C19: =C17+C18 -> -227.95487 | D19: =D17+D18 -> -51.380033 | E19: =E17+E18 -> -88.036094 | F19: =F17+F18 -> 50.465239 | G19: =G17+G18 -> -212.88283 | H19: =H17+H18 -> 1292.827 | I19: =I17+I18 -> 233.61537 | J19: =H19-SUM(B19:G19) -> 0 | K19: =K17+K18 -> 1731.3735 | M19: =M17+M18 -> 1090.9257 | O19: =O17+O18 -> -640.44786 | Q19: =Q17+Q18 -> -191.30525 | R19: =R17+R18 -> -380.92426 | S19: =Q19+R19 -> -572.22951 | V19: =V17+V18 -> -493.13896 | W19: =W17+W18 -> -147.30889 | X19: =X17+X18 -> -640.44786
A20: Functional Currency Impact | B20: ='Budget assumption'!Q51 -> 535.28082 | D20: ='Budget assumption'!Q132 -> 0 | E20: ='Budget assumption'!Q163 -> 0 | F20: ='Budget assumption'!Q194 -> 0 | G20: ='Budget assumption'!Q256+'Budget assumption'!Q287 -> -118.92816 | H20: ='Budget assumption'!Q225 -> 416.35266 | I20: ='Budget assumption'!Q333 -> 136.51533 | J20: =H20-SUM(B20:G20) -> 0 | K20: ='data entry '!Q98 -> 0 | M20: ='data entry '!Q131 -> 301.40709 | O20: =M20-K20 -> 301.40709 | Q20: =M20-H20 -> -114.94557 | R20: =H20-K20-E20-I20-F20-G20-D20 -> 398.7655 | S20: =Q20+R20 -> 283.81992 | V20: =M20-B20 -> -233.87373 | W20: =B20-K20 -> 535.28082 | X20: =V20+W20 -> 301.40709
A21: TOTAL Including FC | B21: =B19+B20 -> 2357.8964 | C21: =C19+C20 -> -227.95487 | D21: =D19+D20 -> -51.380033 | E21: =E19+E20 -> -88.036094 | F21: =F19+F20 -> 50.465239 | G21: =G19+G20 -> -331.81099 | H21: =H19+H20 -> 1709.1797 | I21: =I19+I20 -> 370.13069 | J21: =H21-SUM(B21:G21) -> 0 | K21: =K19+K20 -> 1731.3735 | M21: =M19+M20 -> 1392.3328 | O21: =M21-K21 -> -339.04077 | Q21: =Q19+Q20 -> -306.25082 | R21: =R19+R20 -> 17.841236 | S21: =Q21+R21 -> -288.40958 | V21: =V19+V20 -> -727.01269 | W21: =W19+W20 -> 387.97193 | X21: =X19+X20 -> -339.04077
A22: Scrap | B22: ='Budget assumption'!Q53 -> 35.781227 | C22: ='Budget assumption'!Q74 -> -9.125464 | D22: ='Budget assumption'!Q134 -> -7.5285 | E22: ='Budget assumption'!Q165 -> 0 | F22: ='Budget assumption'!Q196 -> 1.8727369 | G22: ='Budget assumption'!Q258+'Budget assumption'!Q289 -> 0 | H22: ='Budget assumption'!Q227 -> 21 | J22: =H22-SUM(B22:G22) -> 0 | K22: ='data entry '!Q100 -> 25.432898 | M22: ='data entry '!Q133 -> 27.97038 | O22: =M22-K22 -> 2.5374816 | Q22: =M22-K22-E22-F22-D22-G22 -> 8.1932446 | S22: =Q22+R22 -> 8.1932446 | V22: =M22-K22 -> 2.5374816 | X22: =V22+W22 -> 2.5374816
A23: Scrap Reselling | B23: ='Budget assumption'!Q54 -> -87.945 | C23: ='Budget assumption'!Q75 -> 22.42905 | D23: ='Budget assumption'!Q135 -> 0 | E23: ='Budget assumption'!Q166 -> 0 | F23: ='Budget assumption'!Q197 -> 12.51595 | G23: ='Budget assumption'!Q259+'Budget assumption'!Q290 -> 0 | H23: ='Budget assumption'!Q228 -> -53 | J23: =H23-SUM(B23:G23) -> 0 | K23: ='data entry '!Q101 -> -62.74935 | M23: ='data entry '!Q134 -> -74.14161 | O23: =M23-K23 -> -11.39226 | Q23: =M23-K23-E23-F23-D23-G23 -> -23.90821 | S23: =Q23+R23 -> -23.90821 | V23: =M23-K23 -> -11.39226 | X23: =V23+W23 -> -11.39226
A24: Other Variable (Inventory Adj) | B24: ='Budget assumption'!Q55 -> 0 | C24: ='Budget assumption'!Q76+'Budget assumption'!Q291 -> 0 | D24: ='Budget assumption'!Q136 -> 0 | E24: ='Budget assumption'!Q167 -> 0 | F24: ='Budget assumption'!Q198 -> 0 | G24: ='Budget assumption'!Q260+'Budget assumption'!Q291 -> 0 | H24: ='Budget assumption'!Q229 -> 0 | J24: =H24-SUM(B24:G24) -> 0 | K24: ='data entry '!Q102 -> 0 | M24: ='data entry '!Q135 -> -8.91442 | O24: =M24-K24 -> -8.91442 | Q24: =M24-K24-E24-F24-D24-G24 -> -8.91442 | S24: =Q24+R24 -> -8.91442 | V24: =M24-K24 -> -8.91442 | X24: =V24+W24 -> -8.91442
A25: Obsolete | B25: ='Budget assumption'!Q56 -> 0 | C25: ='Budget assumption'!Q77+'Budget assumption'!Q292 -> 0 | D25: ='Budget assumption'!Q137 -> 0 | E25: ='Budget assumption'!Q168 -> 8.3333333 | F25: ='Budget assumption'!Q199 -> -0.33333333 | G25: ='Budget assumption'!Q261+'Budget assumption'!Q292 -> 0 | H25: ='Budget assumption'!Q230 -> 8 | I25: ='Budget assumption'!Q328 -> 0 | J25: =H25-SUM(B25:G25) -> 0 | K25: ='data entry '!Q103 -> 0 | M25: ='data entry '!Q136 -> -30.71528 | O25: =M25-K25 -> -30.71528 | Q25: =M25-H25 -> -38.71528 | R25: =H25-K25-E25-I25-F25-G25-D25 -> 0 | S25: =Q25+R25 -> -38.71528 | V25: =M25-B25 -> -30.71528 | W25: =B25-K25 -> 0 | X25: =V25+W25 -> -30.71528
A26: Asset Sales | B26: ='Budget assumption'!Q57 -> 0 | C26: ='Budget assumption'!Q78+'Budget assumption'!Q293 -> 0 | D26: ='Budget assumption'!Q138 -> 0 | E26: ='Budget assumption'!Q169 -> 0 | F26: ='Budget assumption'!Q200 -> 0 | G26: ='Budget assumption'!Q262+'Budget assumption'!Q293 -> 0 | H26: ='Budget assumption'!Q231 -> 0 | J26: =H26-SUM(B26:G26) -> 0 | K26: ='data entry '!Q104 -> 0 | M26: ='data entry '!Q137 -> 0 | O26: =M26-K26 -> 0 | Q26: =M26-H26 -> 0 | R26: =H26-K26-E26-I26-F26-G26-D26 -> 0 | S26: =Q26+R26 -> 0 | V26: =M26-B26 -> 0 | W26: =B26-K26 -> 0 | X26: =V26+W26 -> 0
A27: TOTAL OTHERS | B27: =SUM(B22:B26) -> -52.163773 | C27: =SUM(C22:C26) -> 13.303586 | D27: =SUM(D22:D26) -> -7.5285 | E27: =SUM(E22:E26) -> 8.3333333 | F27: =SUM(F22:F26) -> 14.055354 | G27: =SUM(G22:G26) -> 0 | H27: =SUM(H22:H26) -> -24 | I27: =SUM(I22:I26) -> 0 | J27: =H27-SUM(B27:G27) -> 0 | K27: =SUM(K22:K26) -> -37.316452 | M27: =SUM(M22:M26) -> -85.80093 | O27: =M27-K27 -> -48.484478 | Q27: =SUM(Q22:Q26) -> -63.344665 | R27: =SUM(R22:R26) -> 0 | S27: =Q27+R27 -> -63.344665 | V27: =SUM(V22:V26) -> -48.484478 | W27: =SUM(W22:W26) -> 0 | X27: =SUM(X22:X26) -> -48.484478
A28: IT GLOBAL | B28: ='Budget assumption'!Q59 -> 123.62205 | D28: ='Budget assumption'!Q140 -> 0 | E28: ='Budget assumption'!Q171 -> 7.7281599 | F28: ='Budget assumption'!Q202 -> -17.070937 | G28: ='Budget assumption'!Q264+'Budget assumption'!Q295 -> -23.582045 | H28: ='Budget assumption'!Q233 -> 90.697223 | I28: ='Budget assumption'!Q337 -> 58.158777 | J28: =H28-SUM(B28:G28) -> 0 | K28: ='data entry '!Q106 -> 83.314994 | M28: ='data entry '!Q139 -> 89.41512 | O28: =M28-K28 -> 6.1001259 | Q28: =M28-H28 -> -1.2821025 | R28: =H28-K28-E28-I28-F28-G28-D28 -> -17.851725 | S28: =Q28+R28 -> -19.133828 | V28: =M28-B28 -> -34.206925 | W28: =B28-K28 -> 40.307051 | X28: =V28+W28 -> 6.1001259
A29: G&A(Insurance included) | B29: ='Budget assumption'!Q60 -> 104.42032 | D29: ='Budget assumption'!Q141 -> 0 | E29: ='Budget assumption'!Q172 -> 0 | F29: ='Budget assumption'!Q203 -> 14.612002 | G29: ='Budget assumption'!Q265+'Budget assumption'!Q296 -> -24.500319 | H29: ='Budget assumption'!Q234 -> 94.532002 | J29: =H29-SUM(B29:G29) -> 0 | K29: ='data entry '!Q107 -> 86.837645 | M29: ='data entry '!Q140 -> 43.15732 | O29: =M29-K29 -> -43.680325 | Q29: =M29-H29 -> -51.374682 | R29: =H29-K29-E29-I29-F29-G29-D29 -> 17.582675 | S29: =Q29+R29 -> -33.792008 | V29: =M29-B29 -> -61.262999 | X29: =V29+W29 -> -61.262999
A30: TOTAL OVERHEAD | B30: =B28+B29 -> 228.04236 | C30: =C28+C29 -> 0 | D30: =D28+D29 -> 0 | E30: =E28+E29 -> 7.7281599 | F30: =F28+F29 -> -2.4589352 | G30: =G28+G29 -> -48.082365 | H30: =H28+H29 -> 185.22922 | I30: =I28+I29 -> 58.158777 | J30: =H30-SUM(B30:G30) -> 0 | K30: =K28+K29 -> 170.15264 | M30: =M28+M29 -> 132.57244 | O30: =O28+O29 -> -37.580199 | Q30: =Q28+Q29 -> -52.656785 | R30: =R28+R29 -> -0.26905074 | S30: =S28+S29 -> -52.925835 | V30: =V28+V29 -> -95.469925 | W30: =W28+W29 -> 40.307051 | X30: =X28+X29 -> -55.162873
D31: ='Budget assumption'!Q143 -> 0 | G31: ='Budget assumption'!Q267 -> 0 | J31: =H31-SUM(B31:G31) -> 0 | K31: ='data entry '!Q109 -> 0 | M31: ='data entry '!Q142 -> 0 | O31: =M31-K31 -> 0 | Q31: =M31-K31-E31-F31-D31-G31 -> 0 | S31: =Q31+R31 -> 0
A32: TOTAL ALL | B32: =B21+B27+B30 -> 2533.775 | C32: =C21+C27+C30 -> -214.65129 | D32: =D21+D27+D30 -> -58.908533 | E32: =E21+E27+E30 -> -71.974601 | F32: =F21+F27+F30 -> 62.061657 | G32: =G21+G27+G30 -> -379.89335 | H32: =H21+H27+H30 -> 1870.4089 | I32: =I21+I27+I30 -> 428.28947 | J32: =H32-SUM(B32:G32) -> 0 | K32: =K21+K27+K30 -> 1864.2097 | M32: =M21+M27+M30 -> 1439.1043 | O32: =M32-K32 -> -425.10544 | Q32: =Q21+Q27+Q30 -> -422.25227 | R32: =R21+R27+R30 -> 17.572185 | S32: =Q32+R32 -> -404.68008 | V32: =V21+V27+V30 -> -870.9671 | W32: =W21+W27+W30 -> 428.27898 | X32: =X21+X27+X30 -> -442.68812

Sheet Obsolete
A1: Yend Accrual | B1: 197000
N3: 3 Months
B4: 1 | C4: 2 | D4: 3 | E4: 4 | F4: 5 | G4: 6 | H4: 7 | I4: 8 | J4: 9 | K4: 10 | L4: 11 | M4: 12 | N4: YTD
A5: Reversal Accrual | B5: =+B1*-1 -> -197000 | C5: =+B6*-1 -> -171249.56 | D5: =+C6*-1 -> -176343.37 | N5: =SUM(B5:M5) -> -544592.93
A6: Aging Report | B6: 171249.56 | C6: 176343.37 | D6: 343493.9 | N6: =SUM(B6:M6) -> 691086.82
A7: Obsolete Movement | D7: 33023.3
A8: ACT COST | B8: =SUM(B5:B6) -> -25750.443 | C8: =SUM(C5:C6) -> 5093.8126 | D8: =SUM(D5:D7) -> 200173.83 | N8: =SUM(N5:N6) -> 146493.9
A9: BUDGET | B9: 9029.9612 | C9: 8861.591 | D9: 8696.3601 | E9: 8567.8425 | F9: 8441.2241 | G9: 8316.477 | H9: 8250.4732 | I9: 8184.9932 | J9: 8120.033 | K9: 7980.3764 | L9: 7843.1217 | M9: 7708.2278 | N9: =SUM(B9:D9) -> 26587.912
A11: NET DIFF | B11: =+B8-B9 -> -34780.404 | C11: =+C8-C9 -> -3767.7784 | D11: =+D8-D9 -> 191477.47 | E11: =+E8-E9 -> -8567.8425 | F11: =+F8-F9 -> -8441.2241 | G11: =+G8-G9 -> -8316.477 | H11: =+H8-H9 -> -8250.4732 | I11: =+I8-I9 -> -8184.9932 | ... M11: =+M8-M9 -> -7708.2278 | N11: =SUM(B11:D11) -> 152929.28

Sheet YTD VAR
A1: Volume | B1: =+'Budget assumption'!R35 -> 290000 | C1: =H1-B1 -> -541 | H1: =+'Budget assumption'!R66 -> 289459 | I1: ='Budget assumption'!Q321 -> 0 | K1: ='data entry '!R82 -> 240074 | M1: ='data entry '!R115 -> 240074 | AA1: EFF | AB1: variable cost | AC1: Actual minus Copertura
B2: EUR | C2: EUR | H2: EUR | I2: EUR | K2: EUR | M2: EUR | Q2: Variances vs Budget | V2: Variances vs STD | AB2: fixed cost | AC2: Actual minus Budget
A3: Cost Elements | B3: STD | C3: Delta Volume | D3: ACE | E3: HW / TW | F3: Price FX | G3: Seasonality | H3: Plan Costs | I3: Budget VAR | K3: Copertura | M3: Act. Costs | O3: Variance vs STD | Q3: EFF | R3: FCA | S3: Total Variance | V3: EFF | W3: FCA | X3: Total Variance
D4: ACE
I5: FCA
A6: Direct Labour | B6: ='Budget assumption'!R37 -> 3299.7015 | C6: ='Budget assumption'!R70 -> -6.15565 | D6: ='Budget assumption'!R118 -> -84.246274 | E6: ='Budget assumption'!R149 -> -210.56221 | F6: ='Budget assumption'!R180 -> 178.26413 | G6: ='Budget assumption'!R242+'Budget assumption'!R273 -> -48.001473 | H6: ='Budget assumption'!R211 -> 3129 | J6: =H6-SUM(B6:G6) -> 0 | K6: ='data entry '!R84 -> 2737.3598 | M6: ='data entry '!R117 -> 2418.8816 | O6: =M6-K6 -> -318.47822 | Q6: =M6-K6-E6-F6-D6-G6 -> -153.93239 | S6: =Q6+R6 -> -153.93239 | V6: =M6-K6 -> -318.47822 | X6: =V6+W6 -> -318.47822
A7: Variable Utilities | B7: ='Budget assumption'!R38 -> 223.63568 | C7: ='Budget assumption'!R71 -> -0.41719622 | D7: ='Budget assumption'!R119 -> 0 | E7: ='Budget assumption'!R150 -> 0 | F7: ='Budget assumption'!R181 -> -16.013368 | G7: ='Budget assumption'!R243+'Budget assumption'!R274 -> 2.3643185 | H7: ='Budget assumption'!R212 -> 209.56944 | J7: =H7-SUM(B7:G7) -> 0 | K7: ='data entry '!R85 -> 182.02348 | M7: ='data entry '!R118 -> 151.60735 | O7: =M7-K7 -> -30.41613 | Q7: =M7-K7-E7-F7-D7-G7 -> -16.76708 | S7: =Q7+R7 -> -16.76708 | V7: =M7-K7 -> -30.41613 | X7: =V7+W7 -> -30.41613
A8: Variable Costs | B8: ='Budget assumption'!R39 -> 101.93916 | C8: ='Budget assumption'!R72 -> -0.19016927 | D8: ='Budget assumption'!R120 -> -6 | E8: ='Budget assumption'!R151 -> 0 | F8: ='Budget assumption'!R182 -> -0.38883073 | G8: ='Budget assumption'!R244+'Budget assumption'!R275 -> 0.00083543054 | H8: ='Budget assumption'!R213 -> 95.361 | J8: =H8-SUM(B8:G8) -> 0 | K8: ='data entry '!R86 -> 77.826839 | M8: ='data entry '!R119 -> 113.14721 | O8: =M8-K8 -> 35.320371 | Q8: =M8-K8-E8-F8-D8-G8 -> 41.708366 | S8: =Q8+R8 -> 41.708366 | V8: =M8-K8 -> 35.320371 | X8: =V8+W8 -> 35.320371
A9: VARIABLE CONVERSION | B9: =SUM(B6:B8) -> 3625.2763 | C9: =SUM(C6:C8) -> -6.7630155 | D9: =SUM(D6:D8) -> -90.246274 | E9: =SUM(E6:E8) -> -210.56221 | F9: =SUM(F6:F8) -> 161.86194 | G9: =SUM(G6:G8) -> -45.636319 | H9: =SUM(H6:H8) -> 3433.9304 | I9: =SUM(I6:I8) -> 0 | J9: =H9-SUM(B9:G9) -> 0 | K9: =SUM(K6:K8) -> 2997.2101 | M9: =SUM(M6:M8) -> 2683.6361 | O9: =SUM(O6:O8) -> -313.57398 | Q9: =SUM(Q6:Q8) -> -128.99111 | R9: =SUM(R6:R8) -> 0 | S9: =SUM(S6:S8) -> -128.99111 | V9: =SUM(V6:V8) -> -313.57398 | W9: =SUM(W6:W8) -> 0 | X9: =SUM(X6:X8) -> -313.57398
A10: Indirect Labour | B10: ='Budget assumption'!R41 -> 1294.2313 | D10: ='Budget assumption'!R122 -> 0 | E10: ='Budget assumption'!R153 -> -252 | F10: ='Budget assumption'!R184 -> 210.34134 | G10: ='Budget assumption'!R246+'Budget assumption'!R277 -> 12.148703 | H10: ='Budget assumption'!R215 -> 1264.7213 | I10: ='Budget assumption'!R323 -> 2.4144108 | J10: =H10-SUM(B10:G10) -> 0 | K10: ='data entry '!R88 -> 1082.3243 | M10: ='data entry '!R121 -> 1325.2768 | O10: =M10-K10 -> 242.95253 | Q10: =M10-H10 -> 60.555482 | R10: =H10-K10-E10-I10-F10-G10-D10 -> 209.49259 | S10: =Q10+R10 -> 270.04807 | V10: =M10-B10 -> 31.045526 | W10: =B10-K10 -> 211.907 | X10: =V10+W10 -> 242.95253
A11: Fixed Labour | B11: ='Budget assumption'!R42 -> 468.14689 | D11: ='Budget assumption'!R123 -> 0 | E11: ='Budget assumption'!R154 -> 43 | F11: ='Budget assumption'!R185 -> 66.498088 | G11: ='Budget assumption'!R247+'Budget assumption'!R278 -> 67.263106 | H11: ='Budget assumption'!R216 -> 644.90809 | I11: ='Budget assumption'!R324 -> 0.8733361 | J11: =H11-SUM(B11:G11) -> 0 | K11: ='data entry '!R89 -> 382.92251 | M11: ='data entry '!R122 -> 636.09685 | O11: =M11-K11 -> 253.17434 | Q11: =M11-H11 -> -8.8112377 | R11: =H11-K11-E11-I11-F11-G11-D11 -> 84.351048 | S11: =Q11+R11 -> 75.53981 | V11: =M11-B11 -> 167.94996 | W11: =B11-K11 -> 85.224384 | X11: =V11+W11 -> 253.17434
A12: Semifixed | B12: ='Budget assumption'!R43 -> 903.82791 | D12: ='Budget assumption'!R124 -> 0 | E12: ='Budget assumption'!R155 -> -74.444011 | F12: ='Budget assumption'!R186 -> 193.42678 | G12: ='Budget assumption'!R248+'Budget assumption'!R279 -> 38.042093 | H12: ='Budget assumption'!R217 -> 1060.8528 | I12: ='Budget assumption'!R325 -> 1.6861065 | J12: =H12-SUM(B12:G12) -> 0 | K12: ='data entry '!R90 -> 741.73199 | M12: ='data entry '!R123 -> 906.21602 | O12: =M12-K12 -> 164.48403 | Q12: =M12-H12 -> -154.63675 | R12: =H12-K12-E12-I12-F12-G12-D12 -> 160.40981 | S12: =Q12+R12 -> 5.7730617 | V12: =M12-B12 -> 2.3881127 | W12: =B12-K12 -> 162.09592 | X12: =V12+W12 -> 164.48403
A13: Fixed utilities | B13: ='Budget assumption'!R44 -> 57.500174 | D13: ='Budget assumption'!R125 -> -6.6 | E13: ='Budget assumption'!R156 -> -12 | F13: ='Budget assumption'!R187 -> -4.9 | G13: ='Budget assumption'!R249+'Budget assumption'!R280 -> -2.0001743 | H13: ='Budget assumption'!R218 -> 32 | I13: ='Budget assumption'!R326 -> 0.10726757 | J13: =H13-SUM(B13:G13) -> 0 | K13: ='data entry '!R91 -> 40.771032 | M13: ='data entry '!R124 -> 16.25655 | O13: =M13-K13 -> -24.514482 | Q13: =M13-H13 -> -15.74345 | R13: =H13-K13-E13-I13-F13-G13-D13 -> 16.621874 | S13: =Q13+R13 -> 0.87842423 | V13: =M13-B13 -> -41.243624 | W13: =B13-K13 -> 16.729142 | X13: =V13+W13 -> -24.514482
A14: Fixed Cost | B14: ='Budget assumption'!R45 -> 201.74144 | D14: ='Budget assumption'!R126 -> 0 | E14: ='Budget assumption'!R157 -> 0 | F14: ='Budget assumption'!R188 -> 28.065266 | G14: ='Budget assumption'!R250+'Budget assumption'!R281 -> 32.804201 | H14: ='Budget assumption'!R219 -> 262.61091 | I14: ='Budget assumption'!R327 -> 0.37635213 | J14: =H14-SUM(B14:G14) -> 0 | K14: ='data entry '!R92 -> 189.24152 | M14: ='data entry '!R125 -> 205.53572 | O14: =M14-K14 -> 16.294203 | Q14: =M14-H14 -> -57.075186 | R14: =H14-K14-E14-I14-F14-G14-D14 -> 12.123569 | S14: =Q14+R14 -> -44.951617 | V14: =M14-B14 -> 3.7942814 | W14: =B14-K14 -> 12.499922 | X14: =V14+W14 -> 16.294203
A15: Depreciation | B15: ='Budget assumption'!R46 -> 789.85016 | D15: ='Budget assumption'!R127 -> 0 | E15: ='Budget assumption'!R158 -> -15.75592 | F15: ='Budget assumption'!R189 -> 0.0012 | G15: ='Budget assumption'!R251+'Budget assumption'!R282 -> 161.23379 | H15: ='Budget assumption'!R220 -> 935.32923 | I15: ='Budget assumption'!R329 -> 1.4734791 | J15: =H15-SUM(B15:G15) -> 0 | K15: ='data entry '!R93 -> 2491.3283 | M15: ='data entry '!R126 -> 748.35691 | O15: =M15-K15 -> -1742.9714 | Q15: =M15-H15 -> -186.97232 | R15: =H15-K15-E15-I15-F15-G15-D15 -> -1702.9516 | S15: =Q15+R15 -> -1889.924 | V15: =M15-B15 -> -41.493251 | W15: =B15-K15 -> -1701.4782 | X15: =V15+W15 -> -1742.9714
A16: FIXED CONVERSION | B16: =SUM(B10:B15) -> 3715.2979 | C16: =SUM(C10:C15) -> 0 | D16: =SUM(D10:D15) -> -6.6 | E16: =SUM(E10:E15) -> -311.19993 | F16: =SUM(F10:F15) -> 493.43268 | G16: =SUM(G10:G15) -> 309.49172 | H16: =SUM(H10:H15) -> 4200.4223 | I16: =SUM(I10:I15) -> 6.9309522 | J16: =H16-SUM(B16:G16) -> 0 | K16: =SUM(K10:K15) -> 4928.3197 | M16: =SUM(M10:M15) -> 3837.7389 | O16: =M16-K16 -> -1090.5808 | Q16: =SUM(Q10:Q15) -> -362.68346 | R16: =SUM(R10:R15) -> -1219.9527 | S16: =Q16+R16 -> -1582.6362 | V16: =SUM(V10:V15) -> 122.441 | W16: =SUM(W10:W15) -> -1213.0218 | X16: =SUM(X10:X15) -> -1090.5808
A17: TOTAL MFG COST w/o SHARES | B17: =B9+B16 -> 7340.5742 | C17: =C9+C16 -> -6.7630155 | D17: =D9+D16 -> -96.846274 | E17: =E9+E16 -> -521.76214 | F17: =F9+F16 -> 655.29461 | G17: =G9+G16 -> 263.8554 | H17: =H9+H16 -> 7634.3528 | I17: =I9+I16 -> 6.9309522 | J17: =H17-SUM(B17:G17) -> 0 | K17: =K9+K16 -> 7925.5298 | M17: =M9+M16 -> 6521.375 | O17: =M17-K17 -> -1404.1548 | Q17: =Q9+Q16 -> -491.67457 | R17: =R9+R16 -> -1219.9527 | S17: =Q17+R17 -> -1711.6273 | V17: =V9+V16 -> -191.13298 | W17: =W9+W16 -> -1213.0218 | X17: =X9+X16 -> -1404.1548
A18: TOTAL SHARES | B18: ='Budget assumption'!R49 -> 51.852823 | D18: ='Budget assumption'!R130 -> 0 | E18: ='Budget assumption'!R161 -> 0 | F18: ='Budget assumption'!R192 -> 0 | G18: ='Budget assumption'!R254+'Budget assumption'!R285 -> 73.482907 | H18: ='Budget assumption'!R223 -> 125.33573 | I18: =+'Budget assumption'!R331 -> 0.096732335 | J18: =H18-SUM(B18:G18) -> 0 | K18: ='data entry '!R96 -> 0 | M18: ='data entry '!R129 -> 102.43459 | O18: =M18-K18 -> 102.43459 | Q18: =M18-H18 -> -22.90114 | R18: =H18-K18-E18-I18-F18-G18-D18 -> 51.75609 | S18: =Q18+R18 -> 28.854951 | V18: =M18-B18 -> 50.581767 | W18: =B18-K18 -> 51.852823 | X18: =V18+W18 -> 102.43459
A19: TOTAL MFG COST w/ SHARES | B19: =B17+B18 -> 7392.427 | C19: =C17+C18 -> -6.7630155 | D19: =D17+D18 -> -96.846274 | E19: =E17+E18 -> -521.76214 | F19: =F17+F18 -> 655.29461 | G19: =G17+G18 -> 337.33831 | H19: =H17+H18 -> 7759.6885 | I19: =I17+I18 -> 7.0276846 | J19: =H19-SUM(B19:G19) -> 0 | K19: =K17+K18 -> 7925.5298 | M19: =M17+M18 -> 6623.8096 | O19: =O17+O18 -> -1301.7202 | Q19: =Q17+Q18 -> -514.57571 | R19: =R17+R18 -> -1168.1967 | S19: =Q19+R19 -> -1682.7724 | V19: =V17+V18 -> -140.55121 | W19: =W17+W18 -> -1161.169 | X19: =X17+X18 -> -1301.7202
A20: Functional Currency Impact | B20: ='Budget assumption'!R51 -> 2171.0691 | D20: ='Budget assumption'!R132 -> 0 | E20: ='Budget assumption'!R163 -> 0 | F20: ='Budget assumption'!R194 -> 0 | G20: ='Budget assumption'!R256+'Budget assumption'!R287 -> 307.11699 | H20: ='Budget assumption'!R225 -> 2478.1861 | I20: ='Budget assumption'!R333 -> 4.0501668 | J20: =H20-SUM(B20:G20) -> 0 | K20: ='data entry '!R98 -> 0 | M20: ='data entry '!R131 -> 1802.1403 | O20: =M20-K20 -> 1802.1403 | Q20: =M20-H20 -> -676.04571 | R20: =H20-K20-E20-I20-F20-G20-D20 -> 2167.0189 | S20: =Q20+R20 -> 1490.9732 | V20: =M20-B20 -> -368.92872 | W20: =B20-K20 -> 2171.0691 | X20: =V20+W20 -> 1802.1403
A21: TOTAL Including FC | B21: =B19+B20 -> 9563.4961 | C21: =C19+C20 -> -6.7630155 | D21: =D19+D20 -> -96.846274 | E21: =E19+E20 -> -521.76214 | F21: =F19+F20 -> 655.29461 | G21: =G19+G20 -> 644.4553 | H21: =H19+H20 -> 10237.875 | I21: =I19+I20 -> 11.077851 | J21: =H21-SUM(B21:G21) -> 0 | K21: =K19+K20 -> 7925.5298 | M21: =M19+M20 -> 8425.9499 | O21: =M21-K21 -> 500.42016 | Q21: =Q19+Q20 -> -1190.6214 | R21: =R19+R20 -> 998.82224 | S21: =Q21+R21 -> -191.79918 | V21: =V19+V20 -> -509.47993 | W21: =W19+W20 -> 1009.9001 | X21: =X19+X20 -> 500.42016
A22: Scrap | B22: ='Budget assumption'!R53 -> 145.12666 | C22: ='Budget assumption'!R74 -> -0.27073628 | D22: ='Budget assumption'!R134 -> -19.359 | E22: ='Budget assumption'!R165 -> 0 | F22: ='Budget assumption'!R196 -> 10.503081 | G22: ='Budget assumption'!R258+'Budget assumption'!R289 -> 0 | H22: ='Budget assumption'!R227 -> 136 | J22: =H22-SUM(B22:G22) -> 0 | K22: ='data entry '!R100 -> 116.43982 | M22: ='data entry '!R133 -> 136.63113 | O22: =M22-K22 -> 20.191311 | Q22: =M22-K22-E22-F22-D22-G22 -> 29.04723 | S22: =Q22+R22 -> 29.04723 | V22: =M22-K22 -> 20.191311 | X22: =V22+W22 -> 20.191311
A23: Scrap Reselling | B23: ='Budget assumption'!R54 -> -356.7 | C23: ='Budget assumption'!R75 -> 0.66543 | D23: ='Budget assumption'!R135 -> 0 | E23: ='Budget assumption'!R166 -> 0 | F23: ='Budget assumption'!R197 -> 53.03457 | G23: ='Budget assumption'!R259+'Budget assumption'!R290 -> 0 | H23: ='Budget assumption'!R228 -> -303 | J23: =H23-SUM(B23:G23) -> 0 | K23: ='data entry '!R101 -> -287.44793 | M23: ='data entry '!R134 -> -306.81066 | O23: =M23-K23 -> -19.362728 | Q23: =M23-K23-E23-F23-D23-G23 -> -72.397298 | S23: =Q23+R23 -> -72.397298 | V23: =M23-K23 -> -19.362728 | X23: =V23+W23 -> -19.362728
A24: Other Variable (Inventory Adj) | B24: ='Budget assumption'!R55 -> 0 | C24: ='Budget assumption'!R76+'Budget assumption'!R291 -> 0 | D24: ='Budget assumption'!R136 -> 0 | E24: ='Budget assumption'!R167 -> 0 | F24: ='Budget assumption'!R198 -> 0 | G24: ='Budget assumption'!R260+'Budget assumption'!R291 -> 0 | H24: ='Budget assumption'!R229 -> 0 | J24: =H24-SUM(B24:G24) -> 0 | K24: ='data entry '!R102 -> 0 | M24: ='data entry '!R135 -> 63.28184 | O24: =M24-K24 -> 63.28184 | Q24: =M24-K24-E24-F24-D24-G24 -> 63.28184 | S24: =Q24+R24 -> 63.28184 | V24: =M24-K24 -> 63.28184 | X24: =V24+W24 -> 63.28184
A25: Obsolete | B25: ='Budget assumption'!R56 -> 0 | C25: ='Budget assumption'!R77+'Budget assumption'!R292 -> 0 | D25: ='Budget assumption'!R137 -> 0 | E25: ='Budget assumption'!R168 -> 50 | F25: ='Budget assumption'!R199 -> 2 | G25: ='Budget assumption'!R261+'Budget assumption'!R292 -> 0 | H25: ='Budget assumption'!R230 -> 52 | I25: ='Budget assumption'!R328 -> 0 | J25: =H25-SUM(B25:G25) -> 0 | K25: ='data entry '!R103 -> 0 | M25: ='data entry '!R136 -> 17.3384 | O25: =M25-K25 -> 17.3384 | Q25: =M25-H25 -> -34.6616 | R25: =H25-K25-E25-I25-F25-G25-D25 -> -3.5527137e-15 | S25: =Q25+R25 -> -34.6616 | V25: =M25-B25 -> 17.3384 | W25: =B25-K25 -> 0 | X25: =V25+W25 -> 17.3384
A26: Asset Sales | B26: ='Budget assumption'!R57 -> 0 | C26: ='Budget assumption'!R78+'Budget assumption'!R293 -> 0 | D26: ='Budget assumption'!R138 -> 0 | E26: ='Budget assumption'!R169 -> 0 | F26: ='Budget assumption'!R200 -> 0 | G26: ='Budget assumption'!R262+'Budget assumption'!R293 -> 0 | H26: ='Budget assumption'!R231 -> 0 | J26: =H26-SUM(B26:G26) -> 0 | K26: ='data entry '!R104 -> 0 | M26: ='data entry '!R137 -> 0 | O26: =M26-K26 -> 0 | Q26: =M26-H26 -> 0 | R26: =H26-K26-E26-I26-F26-G26-D26 -> 0 | S26: =Q26+R26 -> 0 | V26: =M26-B26 -> 0 | W26: =B26-K26 -> 0 | X26: =V26+W26 -> 0
A27: TOTAL OTHERS | B27: =SUM(B22:B26) -> -211.57334 | C27: =SUM(C22:C26) -> 0.39469372 | D27: =SUM(D22:D26) -> -19.359 | E27: =SUM(E22:E26) -> 50 | F27: =SUM(F22:F26) -> 65.537651 | G27: =SUM(G22:G26) -> 0 | H27: =SUM(H22:H26) -> -115 | I27: =SUM(I22:I26) -> 0 | J27: =H27-SUM(B27:G27) -> 0 | K27: =SUM(K22:K26) -> -171.00811 | M27: =SUM(M22:M26) -> -89.55929 | O27: =M27-K27 -> 81.448823 | Q27: =SUM(Q22:Q26) -> -14.729828 | R27: =SUM(R22:R26) -> -3.5527137e-15 | S27: =Q27+R27 -> -14.729828 | V27: =SUM(V22:V26) -> 81.448823 | W27: =SUM(W22:W26) -> 0 | X27: =SUM(X22:X26) -> 81.448823
A28: IT GLOBAL | B28: ='Budget assumption'!R59 -> 501.4041 | D28: ='Budget assumption'!R140 -> 0 | E28: ='Budget assumption'!R171 -> -28.906649 | F28: ='Budget assumption'!R202 -> -37.780016 | G28: ='Budget assumption'!R264+'Budget assumption'!R295 -> 109.4659 | H28: ='Budget assumption'!R233 -> 544.18334 | I28: ='Budget assumption'!R335 -> 0.93537799 | J28: =H28-SUM(B28:G28) -> 0 | K28: ='data entry '!R106 -> 381.19684 | M28: ='data entry '!R139 -> 535.96594 | O28: =M28-K28 -> 154.7691 | Q28: =M28-H28 -> -8.217395 | R28: =H28-K28-E28-I28-F28-G28-D28 -> 119.27188 | S28: =Q28+R28 -> 111.05448 | V28: =M28-B28 -> 34.56184 | W28: =B28-K28 -> 120.20726 | X28: =V28+W28 -> 154.7691
A29: G&A(Insurance included) | B29: ='Budget assumption'!R60 -> 423.52297 | D29: ='Budget assumption'!R141 -> 0 | E29: ='Budget assumption'!R172 -> 0 | F29: ='Budget assumption'!R203 -> 26.952013 | G29: ='Budget assumption'!R265+'Budget assumption'!R296 -> 116.71703 | H29: ='Budget assumption'!R234 -> 567.19201 | I29: ='Budget assumption'!R336 -> 0.79008941 | J29: =H29-SUM(B29:G29) -> 0 | K29: ='data entry '!R107 -> 397.31427 | M29: ='data entry '!R140 -> 538.91129 | O29: =M29-K29 -> 141.59702 | Q29: =M29-H29 -> -28.280723 | R29: =H29-K29-E29-I29-F29-G29-D29 -> 25.418614 | S29: =Q29+R29 -> -2.8621085 | V29: =M29-B29 -> 115.38832 | X29: =V29+W29 -> 115.38832
A30: TOTAL OVERHEAD | B30: =B28+B29 -> 924.92707 | C30: =C28+C29 -> 0 | D30: =D28+D29 -> 0 | E30: =E28+E29 -> -28.906649 | F30: =F28+F29 -> -10.828003 | G30: =G28+G29 -> 226.18293 | H30: =H28+H29 -> 1111.3753 | I30: =I28+I29 -> 1.7254674 | J30: =H30-SUM(B30:G30) -> 0 | K30: =K28+K29 -> 778.51111 | M30: =M28+M29 -> 1074.8772 | O30: =O28+O29 -> 296.36612 | Q30: =Q28+Q29 -> -36.498118 | R30: =R28+R29 -> 144.69049 | S30: =S28+S29 -> 108.19238 | V30: =V28+V29 -> 149.95016 | W30: =W28+W29 -> 120.20726 | X30: =X28+X29 -> 270.15741
D31: ='Budget assumption'!R143 -> 0 | G31: ='Budget assumption'!R267 -> 0 | J31: =H31-SUM(B31:G31) -> 0 | K31: ='data entry '!R109 -> 0 | M31: ='data entry '!R142 -> 0 | O31: =M31-K31 -> 0 | Q31: =M31-K31-E31-F31-D31-G31 -> 0 | S31: =Q31+R31 -> 0
A32: TOTAL ALL | B32: =B21+B27+B30 -> 10276.85 | C32: =C21+C27+C30 -> -6.3683218 | D32: =D21+D27+D30 -> -116.20527 | E32: =E21+E27+E30 -> -500.66879 | F32: =F21+F27+F30 -> 710.00426 | G32: =G21+G27+G30 -> 870.63822 | H32: =H21+H27+H30 -> 11234.25 | I32: =I21+I27+I30 -> 12.803319 | J32: =H32-SUM(B32:G32) -> 0 | K32: =K21+K27+K30 -> 8533.0328 | M32: =M21+M27+M30 -> 9411.2679 | O32: =M32-K32 -> 878.2351 | Q32: =Q21+Q27+Q30 -> -1241.8494 | R32: =R21+R27+R30 -> 1143.5127 | S32: =Q32+R32 -> -98.336637 | V32: =V21+V27+V30 -> -278.08095 | W32: =W21+W27+W30 -> 1130.1073 | X32: =X21+X27+X30 -> 852.0264

Sheet ACE Details_FULL
C1: DIR HOURLY COST | D1: 11.659574 | E1: 12.579099 | F1: 12.696711 | G1: 12.876694 | H1: 19.860831 | I1: 12.477853 | J1: 13.951558 | K1: 15.780654 | L1: 13.332487 | M1: 14.449788 | N1: 12.525775 | O1: 16.70343
C2: MONTHLY COST | D2: 2063.7447 | E2: 2226.5006 | F2: 2247.3179 | G2: 2165.2162 | H2: 2460.757 | I2: 2319.009 | J2: 2099.0118 | K2: 2094.8818 | L2: 2477.8427 | M2: 2301.8513 | N2: 2217.0623 | O2: 2217.3804
C3: VOLUME | D3: 47800 | E3: 47800 | F3: 47800 | G3: 45410 | H3: 33460 | I3: 50190 | J3: 40630 | K3: 37050 | L3: 51870 | M3: 44460 | N3: 49400 | O3: 37135 | P3: =SUM(D3:O3) -> 533005
A4: DW | B4: Description | C4: Level of P&L | D4: Jan | E4: Feb | F4: Mar | G4: Apr | H4: May | I4: Jun | J4: Jul | K4: Aug | L4: Sep | M4: Oct | N4: Nov | O4: Dec | P4: FY
A5: BUDGET | B5: Line speed 130 to 135 | C5: Direct Labour | D5: =D$1*0.5*D$3/60 -> 4644.3971 | E5: =E$1*0.5*E$3/60 -> 5010.6746 | F5: =F$1*0.5*F$3/60 -> 5057.5234 | G5: =G$1*0.5*G$3/60 -> 4872.7558 | H5: =H$1*0.5*H$3/60 -> 5537.8617 | I5: =I$1*0.5*I$3/60 -> 5218.8621 | J5: =J$1*0.5*J$3/60 -> 4723.7649 | K5: =K$1*0.5*K$3/60 -> 4872.2769 | ... O5: =O$1*0.5*O$3/60 -> 5169.0157 | P5: =SUM(D5:O5) -> 61380.19
A6: BUDGET | B6: Line speed 135 to 140 | C6: Direct Labour | J6: =J$1*0.5*J$3/60 -> 4723.7649 | K6: =K$1*0.5*K$3/60 -> 4872.2769 | L6: =L$1*0.5*L$3/60 -> 5762.9675 | M6: =M$1*0.5*M$3/60 -> 5353.6465 | N6: =N$1*0.5*N$3/60 -> 5156.4442 | O6: =O$1*0.5*O$3/60 -> 5169.0157 | P6: =SUM(D6:O6) -> 31038.116
A7: BUDGET | B7: AGV Replace Operator (Tub transportation)-Chinese Supplier | C7: Direct Labour | I7: =3*I2 -> 6957.0271 | J7: =3*J2 -> 6297.0355 | K7: =3*K2 -> 6284.6454 | L7: =3*L2 -> 7433.5281 | M7: =3*M2 -> 6905.5538 | N7: =3*N2 -> 6651.1868 | O7: =3*O2 -> 6652.1411 | P7: =SUM(D7:O7) -> 47181.118 | Q7: CANCELED
A8: BUDGET | B8: Sump Pre-Assy line NEW Semi Automatic Line - Chinese Supplier | C8: Direct Labour | I8: =6*I2 -> 13914.054 | J8: =6*J2 -> 12594.071 | K8: =6*K2 -> 12569.291 | L8: =6*L2 -> 14867.056 | M8: =6*M2 -> 13811.108 | N8: =6*N2 -> 13302.374 | O8: =6*O2 -> 13304.282 | P8: =SUM(D8:O8) -> 94362.235 | Q8: CANCELED
A9: BUDGET | B9: C/L-Pipe & Heater Auto Assembly and Taping-Chinese Supplier | C9: Direct Labour | I9: =2*I2 -> 4638.018 | J9: =2*J2 -> 4198.0237 | K9: =2*K2 -> 4189.7636 | L9: =2*L2 -> 4955.6854 | M9: =2*M2 -> 4603.7025 | N9: =2*N2 -> 4434.1245 | O9: =2*O2 -> 4434.7608 | P9: =SUM(D9:O9) -> 31454.078 | Q9: CANCELED
A10: BUDGET | B10: Sump and Hub screwing automation-Chinese Supplier | C10: Direct Labour | H10: =2*H2 -> 4921.5139 | I10: =2*I2 -> 4638.018 | J10: =2*J2 -> 4198.0237 | K10: =2*K2 -> 4189.7636 | L10: =2*L2 -> 4955.6854 | M10: =2*M2 -> 4603.7025 | N10: =2*N2 -> 4434.1245 | O10: =2*O2 -> 4434.7608 | P10: =SUM(D10:O10) -> 36375.592 | Q10: CANCELED
A11: BUDGET | B11: User manual pack automation | C11: Direct Labour | H11: =2*H2 -> 4921.5139 | I11: =2*I2 -> 4638.018 | J11: =2*J2 -> 4198.0237 | K11: =2*K2 -> 4189.7636 | L11: =2*L2 -> 4955.6854 | M11: =2*M2 -> 4603.7025 | N11: =2*N2 -> 4434.1245 | O11: =2*O2 -> 4434.7608 | P11: =SUM(D11:O11) -> 36375.592 | Q11: CANCELED
A12: BUDGET | B12: Automatic EPS assembly | C12: Direct Labour | I12: =4*I2 -> 9276.0361 | J12: =4*J2 -> 8396.0474 | K12: =4*K2 -> 8379.5272 | L12: =4*L2 -> 9911.3708 | M12: =4*M2 -> 9207.405 | N12: =4*N2 -> 8868.249 | O12: =4*O2 -> 8869.5215 | P12: =SUM(D12:O12) -> 62908.157 | Q12: CANCELED
A13: BUDGET | B13: AIDA recycled oil usage in Erkekoğlu Press | C13: Variable Costs | D13: 1000 | E13: 1000 | F13: 1000 | G13: 1000 | H13: 1000 | I13: 1000 | J13: 1000 | K13: 1000 | L13: 1000 | M13: 1000 | N13: 1000 | O13: 1000 | P13: =SUM(D13:O13) -> 12000
A14: BUDGET | B14: Factory air conditioning units working optimazation for energy saving | C14: Fixed utilities | D14: 700 | E14: 700 | F14: 700 | G14: 700 | H14: 700 | I14: 700 | J14: 700 | K14: 700 | L14: 700 | M14: 700 | N14: 700 | O14: 700 | P14: =SUM(D14:O14) -> 8400
A15: BUDGET | B15: Factory lightening optimization for energy saving | C15: Fixed utilities | D15: 400 | E15: 400 | F15: 400 | G15: 400 | H15: 400 | I15: 400 | J15: 400 | K15: 400 | L15: 400 | M15: 400 | N15: 400 | O15: 400 | P15: =SUM(D15:O15) -> 4800 | Q15: =15*55 -> 825
A16: BUDGET | B16: Inner door Scrap reduction | C16: Scrap | G16: =0.15*G3 -> 6811.5 | H16: =0.15*H3 -> 5019 | I16: =0.15*I3 -> 7528.5 | J16: =0.15*J3 -> 6094.5 | K16: =0.15*K3 -> 5557.5 | L16: =0.15*L3 -> 7780.5 | M16: =0.15*M3 -> 6669 | N16: =0.15*N3 -> 7410 | O16: =0.15*O3 -> 5570.25 | P16: =SUM(D16:O16) -> 58440.75
D18: =SUM(D5:D16) -> 6744.3971 | E18: =SUM(E5:E16) -> 7110.6746 | F18: =SUM(F5:F16) -> 7157.5234 | G18: =SUM(G5:G16) -> 13784.256 | H18: =SUM(H5:H16) -> 22499.89 | I18: =SUM(I5:I16) -> 58908.533 | J18: =SUM(J5:J16) -> 57523.255 | K18: =SUM(K5:K16) -> 57204.808 | ... P18: =SUM(P5:P16) -> 484715.83
C20: DIR HOURLY COST | D20: 11.659574 | E20: 12.579099 | F20: 12.696711 | G20: 12.876694 | H20: 19.860831 | I20: 12.477853 | J20: 13.951558 | K20: 15.780654 | L20: 13.332487 | M20: 14.449788 | N20: 12.525775 | O20: 16.70343 | P20: =AVERAGE(D20:O20) -> 14.074538 | U20: Canteen(Yearly) | V20: 997.26316
C21: MONTHLY COST | D21: 2063.7447 | E21: 2226.5006 | F21: 2247.3179 | G21: 2165.2162 | H21: 2460.757 | I21: 2319.009 | J21: 2099.0118 | K21: 2094.8818 | L21: 2477.8427 | M21: 2301.8513 | N21: 2217.0623 | O21: 2217.3804 | P21: =AVERAGE(D21:O21) -> 2240.8813 | U21: Uniforms (Yearly) | V21: 461.93474
C22: SEMIFIXED BENEFIT | D22: 211.30421 | U22: Service (Yearly) | V22: 1076.4526
C23: VOLUME | D23: =+VOLUME!C7 -> 47357 | E23: =+VOLUME!D7 -> 42593 | F23: =+VOLUME!E7 -> 23002 | G23: 38000 | H23: =VOLUME!G7 -> 33043 | I23: =VOLUME!H7 -> 53186 | J23: 40672 | K23: 39704 | L23: 54907 | M23: 49968 | N23: 51936 | O23: 42190 | P23: =SUM(D23:O23) -> 516558 | Q23: 1+11Forecast | S23: June Closure
D24: Jan | E24: Feb | F24: Mar | G24: Apr | H24: May | I24: Jun | J24: Jul | K24: Aug | L24: Sep | M24: Oct | N24: Nov | O24: Dec | P24: FY
A25: ACTUAL | B25: Line speed 130 to 135 | C25: Direct Labour | D25: =$P$20*0.6*D$23/60 -> 6665.279 | E25: =$P$20*0.6*E$23/60 -> 5994.768 | F25: =$P$20*0.6*F$23/60 -> 3237.4252 | G25: =$P$20*0.6*G$23/60 -> 5348.3244 | H25: =$P$20*0.6*H$23/60 -> 4650.6496 | I25: =$P$20*0.6*I$23/60 -> 7485.6838 | J25: =$P$20*0.6*J$23/60 -> 5724.3961 | K25: =$P$20*0.6*K$23/60 -> 5588.1546 | ... O25: =$P$20*0.6*O$23/60 -> 5938.0476 | P25: =SUM(D25:O25) -> 72703.152 | Q25: OK | S25: ok
A26: ACTUAL | B26: Line speed 135 to 140 | C26: Direct Labour | J26: =$P$20*0.6*J$23/60 -> 5724.3961 | K26: =$P$20*0.6*K$23/60 -> 5588.1546 | L26: =$P$20*0.6*L$23/60 -> 7727.9066 | M26: =$P$20*0.6*M$23/60 -> 7032.7652 | N26: =$P$20*0.6*N$23/60 -> 7309.7521 | O26: =$P$20*0.6*O$23/60 -> 5938.0476 | P26: =SUM(D26:O26) -> 39321.022 | Q26: Ongoing
A27: ACTUAL | B27: AGV Replace Operator (Tub transportation)-Chinese Supplier | C27: Direct Labour | J27: =3*$P$21 -> 6722.6439 | K27: =3*$P$21 -> 6722.6439 | L27: =3*$P$21 -> 6722.6439 | M27: =3*$P$21 -> 6722.6439 | N27: =3*$P$21 -> 6722.6439 | O27: =3*$P$21 -> 6722.6439 | P27: =SUM(D27:O27) -> 40335.863 | Q27: OK
A28: ADDITION | B28: AGV Replace Operators-( Logistic operators) | C28: Direct Labour | K28: =3*$P$21 -> 6722.6439 | L28: =3*$P$21 -> 6722.6439 | M28: =3*$P$21 -> 6722.6439 | N28: =3*$P$21 -> 6722.6439 | O28: =3*$P$21 -> 6722.6439 | P28: =SUM(D28:O28) -> 33613.219 | Q28: Ongoing
A29: ADDITION | B29: IKEA cartoon bendin&feeding | C29: Direct Labour | E29: =13.85*100000/3600*$P$20*9/12/9*0 -> 0 | F29: =13.85*100000/3600*$P$20*9/12/9*0 -> 0 | G29: =13.85*100000/3600*$P$20*9/12/9*0 -> 0 | H29: =13.85*100000/3600*$P$20*9/12/9*0 -> 0 | I29: 0 | J29: =13.85*100000/3600*$P$20*9/12/9 -> 451.23229 | K29: =13.85*100000/3600*$P$20*9/12/9 -> 451.23229 | L29: =13.85*100000/3600*$P$20*9/12/9 -> 451.23229 | M29: =13.85*100000/3600*$P$20*9/12/9 -> 451.23229 | N29: =13.85*100000/3600*$P$20*9/12/9 -> 451.23229 | O29: =13.85*100000/3600*$P$20*9/12/9 -> 451.23229 | P29: =SUM(D29:O29) -> 2707.3938 | Q29: Ongoing | R29: ok
A30: ADDITION | B30: Injection parts TC improvement(3 sec) | C30: Direct Labour | D30: =D23*0.85*4/3600*$P$20 -> 629.49857 | E30: =E23*0.85*4/3600*$P$20 -> 566.17253 | F30: =F23*0.85*4/3600*$P$20 -> 305.75683 | G30: =G23*0.85*4/3600*$P$20 -> 505.11953 | H30: =H23*0.85*4/3600*$P$20 -> 439.22802 | I30: =I23*0.85*4/3600*$P$20 -> 706.98125 | J30: =J23*0.85*4/3600*$P$20 -> 540.63741 | K30: =K23*0.85*4/3600*$P$20 -> 527.77015 | ... O30: =O23*0.85*4/3600*$P$20 -> 560.81561 | P30: =SUM(D30:O30) -> 6866.4088 | Q30: OK | S30: ok
A31: ADDITION | B31: Packing line speed | C31: Direct Labour | H31: 1828 | I31: 1828 | J31: 1828 | K31: 1828 | L31: 1828 | M31: 1828 | N31: 1828 | O31: 1828 | P31: =SUM(D31:O31) -> 14624 | Q31: OK | S31: ok
A32: ADDITION | B32: Low cost effect std vs act bdg | C32: Direct Labour | D32: =54*(2300-1600) -> 37800 | E32: =30*(2300-1600) -> 21000 | F32: =30*(2300-1600) -> 21000 | G32: =30*(2300-1600) -> 21000 | H32: =30*(2300-1600) -> 21000 | I32: =30*(2300-1600) -> 21000 | J32: =30*(2300-1600) -> 21000 | K32: =30*(2300-1600) -> 21000 | L32: =30*(2300-1600) -> 21000 | ... O32: =30*(2300-1600) -> 21000 | P32: =SUM(D32:O32) -> 268800 | Q32: OK | S32: ok
A33: ACTUAL | B33: AIDA recycled oil usage in Erkekoğlu Press | C33: Variable Costs | D33: 1000 | E33: 1000 | F33: 1000 | G33: 1000 | H33: 1000 | I33: 1000 | J33: 1000 | K33: 1000 | L33: 1000 | M33: 1000 | N33: 1000 | O33: 1000 | P33: =SUM(D33:O33) -> 12000 | Q33: OK | S33: ok
A34: ADDITION | B34: İnternal logistic headcound reduction - 1 operator -New- hinge handling elimination | C34: Indirect Labour | E34: =+$P$21 -> 2240.8813 | F34: =+$P$21 -> 2240.8813 | G34: =+$P$21 -> 2240.8813 | H34: =+$P$21 -> 2240.8813 | I34: =+$P$21 -> 2240.8813 | J34: =+$P$21 -> 2240.8813 | K34: =+$P$21 -> 2240.8813 | L34: =+$P$21 -> 2240.8813 | ... O34: =+$P$21 -> 2240.8813 | P34: =SUM(D34:O34) -> 24649.694 | Q34: OK | S34: ok
A35: ADDITION | B35: Internal logistic headcound reduction - 1 operator - New-internal logistic optimizaiton | C35: Indirect Labour | H35: =+$P$21 -> 2240.8813 | I35: =+$P$21 -> 2240.8813 | J35: =+$P$21 -> 2240.8813 | K35: =+$P$21 -> 2240.8813 | L35: =+$P$21 -> 2240.8813 | M35: =+$P$21 -> 2240.8813 | N35: =+$P$21 -> 2240.8813 | O35: =+$P$21 -> 2240.8813 | P35: =SUM(D35:O35) -> 17927.05 | Q35: OK | S35: ok
A36: ACTUAL | B36: Factory air conditioning units working optimazation for energy saving | C36: Fixed utilities | H36: =700*0 -> 0 | I36: 0 | J36: 700 | K36: 700 | L36: 700 | M36: 700 | N36: 700 | O36: 700 | P36: =SUM(D36:O36) -> 4200 | Q36: Ongoing | R36: ok | S36: 37563
A37: ACTUAL | B37: Factory lightening optimization for energy saving | C37: Fixed utilities | F37: 222.8 | G37: 222.8 | H37: 222.8 | I37: 222.8 | J37: 222.8 | K37: 222.8 | L37: 222.8 | M37: 222.8 | N37: 222.8 | O37: 222.8 | P37: =SUM(D37:O37) -> 2228 | Q37: OK | S37: ok
A38: ADDITION | B38: İnternal logistic headcound reduction - 1 operator - New- hinge handling elimination | C38: Semifixed costs | E38: =1*$D$22 -> 211.30421 | F38: =1*$D$22 -> 211.30421 | G38: =1*$D$22 -> 211.30421 | H38: =1*$D$22 -> 211.30421 | I38: =1*$D$22 -> 211.30421 | J38: =1*$D$22 -> 211.30421 | K38: =1*$D$22 -> 211.30421 | L38: =1*$D$22 -> 211.30421 | ... O38: =1*$D$22 -> 211.30421 | P38: =SUM(D38:O38) -> 2324.3463 | Q38: OK | S38: ok
A39: ADDITION | B39: Internal logistic headcound reduction - 1 operator - New-internal logistic optimizaiton | C39: Semifixed costs | H39: =1*$D$22 -> 211.30421 | I39: =1*$D$22 -> 211.30421 | J39: =1*$D$22 -> 211.30421 | K39: =1*$D$22 -> 211.30421 | L39: =1*$D$22 -> 211.30421 | M39: =1*$D$22 -> 211.30421 | N39: =1*$D$22 -> 211.30421 | O39: =1*$D$22 -> 211.30421 | P39: =SUM(D39:O39) -> 1690.4337 | Q39: OK | S39: ok
A40: ADDITION | B40: AGV Replace Operator (Tub transportation)-Chinese Supplier | C40: Semifixed Costs | J40: =3*$D$22 -> 633.91263 | K40: =3*$D$22 -> 633.91263 | L40: =3*$D$22 -> 633.91263 | M40: =3*$D$22 -> 633.91263 | N40: =3*$D$22 -> 633.91263 | O40: =3*$D$22 -> 633.91263 | P40: =SUM(D40:O40) -> 3803.4758 | Q40: Ongoing
A41: ADDITION | B41: AGV Replace Operators-( Logistic operators) | C41: Semifixed Costs | K41: =3*$D$22 -> 633.91263 | L41: =3*$D$22 -> 633.91263 | M41: =3*$D$22 -> 633.91263 | N41: =3*$D$22 -> 633.91263 | O41: =3*$D$22 -> 633.91263 | P41: =SUM(D41:O41) -> 3169.5632 | Q41: Ongoing
A42: ACTUAL | B42: Inner door Scrap reduction | C42: Scrap | H42: =+$P$42/SUM($H$23:$O$23)*H23*0 -> 0 | I42: 0 | J42: =+$P$42/SUM($H$23:$O$23)*J23 -> 6460.0226 | K42: =+$P$42/SUM($H$23:$O$23)*K23 -> 6306.2731 | L42: =+$P$42/SUM($H$23:$O$23)*L23 -> 8720.9988 | M42: =+$P$42/SUM($H$23:$O$23)*M23 -> 7936.5266 | N42: =+$P$42/SUM($H$23:$O$23)*N23 -> 8249.1084 | O42: =+$P$42/SUM($H$23:$O$23)*O23 -> 6701.1299 | P42: 58070 | Q42: Ongoing | R42: ok
C44: TOTAL | D44: =SUM(D25:D42) -> 46094.778 | E44: =SUM(E25:E42) -> 31013.126 | F44: =SUM(F25:F42) -> 28218.168 | G44: =SUM(G25:G42) -> 30528.429 | H44: =SUM(H25:H42) -> 34045.049 | I44: =SUM(I25:I42) -> 37147.836 | J44: =SUM(J25:J42) -> 55912.412 | K44: =SUM(K25:K42) -> 62829.869 | ... P44: =SUM(P25:P42) -> 609033.62
B48: Temporary Worker Effect | C48: Direct Labour | H48: =100*(2200-1400) -> 80000 | I48: =100*(2200-1400) -> 80000 | J48: =100*(2200-1400) -> 80000 | K48: =100*(2200-1400) -> 80000 | L48: =100*(2200-1400) -> 80000 | M48: =100*(2200-1400) -> 80000 | N48: =100*(2200-1400) -> 80000 | O48: =100*(2200-1400) -> 80000 | P48: 640000 | Q48: Forecaste koyma
B49: Asset Life Extension (Tools & Macine) | C49: Depreciation | P49: 300000 | Q49: Forecaste koyma
A51: CANCELED | B51: Sump Pre-Assy line NEW Semi Automatic Line - Chinese Supplier | C51: Direct Labour | P51: =SUM(D51:O51) -> 0
A52: CANCELED | B52: C/L-Pipe & Heater Auto Assembly and Taping-Chinese Supplier | C52: Direct Labour | P52: =SUM(D52:O52) -> 0
A53: CANCELED | B53: Sump and Hub screwing automation-Chinese Supplier | C53: Direct Labour | P53: =SUM(D53:O53) -> 0
A54: CANCELED | B54: User manual pack automation | C54: Direct Labour | P54: =SUM(D54:O54) -> 0
A55: CANCELED | B55: Automatic EPS assembly | C55: Direct Labour | P55: =SUM(D55:O55) -> 0
D56: =SUM(D25:D55) -> 92189.555 | E56: =SUM(E25:E55) -> 62026.252 | F56: =SUM(F25:F55) -> 56436.335 | G56: =SUM(G25:G55) -> 61056.859 | H56: =SUM(H25:H55) -> 148090.1 | I56: =SUM(I25:I55) -> 154295.67 | J56: =SUM(J25:J55) -> 191824.82 | K56: =SUM(K25:K55) -> 205659.74 | ... P56: =SUM(P25:P55) -> 2158067.2
F60: =F44-F18 -> 21060.644 | G60: =G44-G18 -> 16744.174

Sheet MTD Report(HQD)_variance
A2: DW MTD MAY | B2: Budget26 | E2: Volume Variance | F2: Copertura | G2: HWTW&ACE | H2: Budget FCA | I2: Budget Flex. | J2: ACE | K2: MFG Efficiency | L2: S&OP | M2: Price / Inflation | N2: fX translation | O2: Oth Functions | P2: VARIANCE | Q2: Actual Cost | AC2: BDG FX | AD2: 53.485975
AC3: ACT FX | AD3: 51.632775 | AF3: =2300-1600 -> 700
B4: ='data entry '!Q3 -> 53265 | E4: =Q4-B4 -> -79 | Q4: ='data entry '!Q115 -> 53186 | T4: Δ vs Flex. | U4: FCA | V4: Total Variance | X4: Variance | AA4: COST | AF4: =+AF3*54 -> 37800
A5: - Gain / +Loss | E5: =E4/B4 -> -0.0014831503
B6: EUR/000 | C6: €/pc | E6: EUR/000 | F6: EUR/000 | G6: EUR/000 | H6: EUR/000 | I6: EUR/000 | J6: EUR/000 | K6: EUR/000 | L6: EUR/000 | M6: EUR/000 | N6: EUR/001 | O6: EUR/000 | P6: EUR/000 | Q6: EUR/000 | R6: €/pc | T6: EUR/000 | U6: EUR/000 | V6: EUR/000 | X6: 5+7 | Y6: DIFF | AA6: 5+7 | AB6: DIFF | AD6: MFG | AE6: PRICE&FX | AF6: GROSS
A7: Direct Labor | B7: ='data entry '!Q5 -> 503 | C7: =B7/$B$4*1000 -> 9.4433493 | E7: =I7-B7 -> -7.6599938 | F7: ='data entry '!Q84 -> 598.40414 | G7: ='data entry '!Q39 -> -103.06413 | I7: =F7+G7 -> 495.34001 | J7: =-'ACE 2026'!G43/1000 -> 18.259368 | K7: =(-150+7)+-3.57958180052549 -> -146.57958 | M7: =16.486-36+1.418+16 -> -2.096 | N7: =SAP_ACT_EUR!P20/1000 -> 26.709817 | P7: =SUM(J7:O7) -> -103.7064 | Q7: ='data entry '!Q117 -> 391.63361 | R7: =Q7*1000/$Q$4 -> 7.3634718 | S7: =Q7-SUM(I7:O7) -> 0 | T7: =+Q7-I7 -> -103.7064 | V7: =+T7+U7 -> -103.7064 | X7: -67.706187 | Y7: =+P7-X7 -> -36.000209 | AA7: 460.9901 | AB7: =+Q7-AA7 -> -69.356488 | AD7: =SUM(I7:L7)*1000/$Q$4 -> 6.9006843 | AE7: =+AF7-AD7 -> 0.46278752 | AF7: =R7 -> 7.3634718 | AH7: -28 k€ ISKUR impact(more efficient than FCST), -16 k€recharges to suppliers&ITCY, -13 k€ more efficienct than FCST, -5 k€ salary mix impact, -5 k€ less ovt than FCST -2k€ annual leave days accrual gain
A8: Variable Utilities | B8: ='data entry '!Q6 -> 35.762038 | C8: =B8/$B$4*1000 -> 0.67139844 | E8: =I8-B8 -> -1.2346735 | F8: ='data entry '!Q85 -> 39.841032 | G8: ='data entry '!Q40 -> -5.3136673 | I8: =F8+G8 -> 34.527365 | K8: -5.5114587 | M8: -3 | N8: =SAP_ACT_EUR!P96/1000 -> 2.6447441 | P8: =SUM(J8:O8) -> -5.8667146 | Q8: ='data entry '!Q118 -> 28.66065 | R8: =Q8*1000/$Q$4 -> 0.53887583 | S8: =Q8-SUM(I8:O8) -> 0 | T8: =+Q8-I8 -> -5.8667146 | V8: =+T8+U8 -> -5.8667146 | X8: 2.8968225 | Y8: =+P8-X8 -> -8.7635372 | AA8: 39.635645 | AB8: =+Q8-AA8 -> -10.974995 | AD8: =SUM(I8:L8)*1000/$Q$4 -> 0.54555533 | AE8: =+AF8-AD8 -> -0.0066795007 | AF8: =R8 -> 0.53887583
A9: Other Variable (Production Consumable) | B9: ='data entry '!Q7 -> 17.5665 | C9: =B9/$B$4*1000 -> 0.32979442 | E9: =I9-B9 -> -1.7014291 | F9: ='data entry '!Q86 -> 17.021983 | G9: ='data entry '!Q41 -> -1.1569124 | I9: =F9+G9 -> 15.865071 | J9: =-'ACE 2026'!F47/1000 -> 0 | K9: 11.793103 | N9: =SAP_ACT_EUR!P82/1000 -> 1.2274957 | P9: =SUM(J9:O9) -> 13.020599 | Q9: ='data entry '!Q119 -> 28.88567 | R9: =Q9*1000/$Q$4 -> 0.54310664 | S9: =Q9-SUM(I9:O9) -> 0 | T9: =+Q9-I9 -> 13.020599 | V9: =+T9+U9 -> 13.020599 | X9: 0.34488569 | Y9: =+P9-X9 -> 12.675713 | AA9: 17.076248 | AB9: =+Q9-AA9 -> 11.809422 | AD9: =SUM(I9:L9)*1000/$Q$4 -> 0.52002734 | AE9: =+AF9-AD9 -> 0.0230793 | AF9: =R9 -> 0.54310664
A10: Variable Conv. | B10: =SUM(B7:B9) -> 556.32854 | C10: =B10/$B$4*1000 -> 10.444542 | E10: =SUM(E7:E9) -> -10.596096 | F10: =SUM(F7:F9) -> 655.26716 | G10: =SUM(G7:G9) -> -109.53471 | H10: =SUM(H7:H9) -> 0 | I10: =SUM(I7:I9) -> 545.73244 | J10: =SUM(J7:J9) -> 18.259368 | K10: =SUM(K7:K9) -> -140.29794 | L10: =SUM(L7:L9) -> 0 | ... Q10: =SUM(Q7:Q9) -> 449.17993 | R10: =Q10*1000/$Q$4 -> 8.4454543 | S10: =Q10-SUM(I10:O10) -> 0 | T10: =+Q10-I10 -> -96.552512 | V10: =+T10+U10 -> -96.552512 | X10: -64.464479 | Y10: =+P10-X10 -> -32.088033 | AA10: 517.70199 | AB10: =+Q10-AA10 -> -68.522062 | AD10: =SUM(I10:L10)*1000/$Q$4 -> 7.9662669 | AE10: =+AF10-AD10 -> 0.47918732 | AF10: =R10 -> 8.4454543
A11: Indirect Labour | B11: ='data entry '!Q9 -> 217.31856 | C11: =B11/$B$4*1000 -> 4.0799504 | F11: ='data entry '!Q88 -> 236.64471 | G11: ='data entry '!Q43 -> -101.7764 | H11: ='Budget assumption'!Q323 -> 81.380371 | I11: =B11 -> 217.31856 | J11: =-'ACE 2026'!G49/1000 -> -4.4817626 | K11: =(-6.313-J11+5.211-0.481)+-0.00357509646474341 -> 2.8951875 | M11: =8-9-1.016 -> -2.016 | N11: =SAP_ACT_EUR!P104/1000 -> 15.524637 | P11: =SUM(J11:O11) -> 11.922062 | Q11: ='data entry '!Q121 -> 229.24062 | R11: =Q11*1000/$Q$4 -> 4.3101685 | S11: =Q11-SUM(I11:O11) -> 0 | T11: =+Q11-I11 -> 11.922062 | U11: =+'MTD VAR '!R10 -> 1.0698749 | V11: =+T11+U11 -> 12.991937 | X11: 4.653537 | Y11: =+P11-X11 -> 7.2685249 | AA11: 221.9721 | AB11: =+Q11-AA11 -> 7.2685249 | AD11: =SUM(I11:L11)*1000/$Q$4 -> 4.0561799 | AE11: =+AF11-AD11 -> 0.25398859 | AF11: =R11 -> 4.3101685
A12: Fixed Labour | B12: ='data entry '!Q10 -> 107.62726 | C12: =B12/$B$4*1000 -> 2.0206001 | F12: ='data entry '!Q89 -> 83.695495 | G12: ='data entry '!Q44 -> -7.7951589 | H12: ='Budget assumption'!Q324 -> 29.436754 | I12: =B12 -> 107.62726 | K12: -2.282 | M12: =(-4.137+3.791-0.144)+1.04093542905849 -> 0.55093543 | N12: =SAP_ACT_EUR!P112/1000 -> 5.7044297 | P12: =SUM(J12:O12) -> 3.9733651 | Q12: ='data entry '!Q122 -> 111.60063 | R12: =Q12*1000/$Q$4 -> 2.0983084 | S12: =Q12-SUM(I12:O12) -> 0 | T12: =+Q12-I12 -> 3.9733651 | U12: =+'MTD VAR '!R11 -> 2.2901751 | V12: =+T12+U12 -> 6.2635402 | X12: 2.0790852 | Y12: =+P12-X12 -> 1.8942799 | AA12: 109.70635 | AB12: =+Q12-AA12 -> 1.8942799 | AD12: =SUM(I12:L12)*1000/$Q$4 -> 1.9806954 | AE12: =+AF12-AD12 -> 0.117613 | AF12: =R12 -> 2.0983084
A13: Semifixed | B13: ='data entry '!Q11 -> 188.37864 | C13: =B13/$B$4*1000 -> 3.5366307 | F13: ='data entry '!Q90 -> 162.06681 | G13: ='data entry '!Q45 -> -34.461693 | H13: ='Budget assumption'!Q325 -> 56.832075 | I13: =B13 -> 188.37864 | J13: =-'ACE 2026'!G51/1000 -> -0.42260842 | K13: -86.422155 | M13: =4.668-1.094 -> 3.574 | N13: =SAP_ACT_EUR!P129/1000 -> 6.2428885 | P13: =SUM(J13:O13) -> -77.027875 | Q13: ='data entry '!Q123 -> 111.35076 | R13: =Q13*1000/$Q$4 -> 2.0936103 | S13: =Q13-SUM(I13:O13) -> 0 | T13: =+Q13-I13 -> -77.027875 | U13: =+'MTD VAR '!R12 -> 3.941439 | V13: =+T13+U13 -> -73.086436 | X13: 8.0632146 | Y13: =+P13-X13 -> -85.09109 | AA13: 196.44185 | AB13: =+Q13-AA13 -> -85.09109 | AD13: =SUM(I13:L13)*1000/$Q$4 -> 1.9090338 | AE13: =+AF13-AD13 -> 0.18457655 | AF13: =R13 -> 2.0936103 | AH13: 56 k€ less expense on mnt
A14: Fixed utilities | B14: ='data entry '!Q12 -> 6 | C14: =B14/$B$4*1000 -> 0.11264433 | F14: ='data entry '!Q91 -> 8.8590025 | G14: ='data entry '!Q46 -> -8.1767671 | H14: ='Budget assumption'!Q326 -> 3.6155713 | I14: =B14 -> 6 | J14: =-'ACE 2026'!G52/1000 -> 0.8772 | K14: -4.4758431 | M14: -0.59011826 | N14: =SAP_ACT_EUR!P92/1000 -> 0.19634136 | P14: =SUM(J14:O14) -> -3.99242 | Q14: ='data entry '!Q124 -> 2.00758 | R14: =Q14*1000/$Q$4 -> 0.037746399 | S14: =Q14-SUM(I14:O14) -> 0 | T14: =+Q14-I14 -> -3.99242 | U14: =+'MTD VAR '!R13 -> 1.7021933 | V14: =+T14+U14 -> -2.2902267 | X14: 0.73124103 | Y14: =+P14-X14 -> -4.723661 | AA14: 6.731241 | AB14: =+Q14-AA14 -> -4.723661 | AD14: =SUM(I14:L14)*1000/$Q$4 -> 0.045150169 | AE14: =+AF14-AD14 -> -0.0074037698 | AF14: =R14 -> 0.037746399
A15: Fixed Cost | B15: ='data entry '!Q13 -> 43.825739 | C15: =B15/$B$4*1000 -> 0.82278681 | F15: ='data entry '!Q92 -> 41.414629 | G15: ='data entry '!Q47 -> -5.9139603 | H15: ='Budget assumption'!Q327 -> 12.685363 | I15: =B15 -> 43.825739 | K15: 3.22554 | N15: =SAP_ACT_EUR!P81/1000 -> 3.3804208 | P15: =SUM(J15:O15) -> 6.6059608 | Q15: ='data entry '!Q125 -> 50.4317 | R15: =Q15*1000/$Q$4 -> 0.94821382 | S15: =Q15-SUM(I15:O15) -> 0 | T15: =+Q15-I15 -> 6.6059608 | U15: =+'MTD VAR '!R14 -> -4.3602923 | V15: =+T15+U15 -> 2.2456685 | X15: 4.4640845 | Y15: =+P15-X15 -> 2.1418763 | AA15: 48.289824 | AB15: =+Q15-AA15 -> 2.1418763 | AD15: =SUM(I15:L15)*1000/$Q$4 -> 0.88465535 | AE15: =+AF15-AD15 -> 0.06355847 | AF15: =R15 -> 0.94821382
A16: Depreciation | B16: ='data entry '!Q14 -> 152.87378 | C16: =B16/$B$4*1000 -> 2.8700606 | F16: ='data entry '!Q93 -> 543.42574 | G16: ='data entry '!Q48 -> -41.865138 | H16: ='Budget assumption'!Q329 -> 49.665233 | I16: =B16 -> 152.87378 | K16: -20.83101 | P16: =SUM(J16:O16) -> -20.83101 | Q16: ='data entry '!Q126 -> 132.04277 | R16: =Q16*1000/$Q$4 -> 2.4826603 | S16: =Q16-SUM(I16:O16) -> 0 | T16: =+Q16-I16 -> -20.83101 | U16: =+'MTD VAR '!R15 -> -398.35205 | V16: =+T16+U16 -> -419.18306 | X16: -12.872438 | Y16: =+P16-X16 -> -7.9585723 | AA16: 140.00134 | AB16: =+Q16-AA16 -> -7.9585723 | AD16: =SUM(I16:L16)*1000/$Q$4 -> 2.4826603 | AE16: =+AF16-AD16 -> 0 | AF16: =R16 -> 2.4826603
A17: Fixed Conv. | B17: =SUM(B11:B16) -> 716.02398 | C17: =B17/$B$4*1000 -> 13.442673 | E17: =SUM(E11:E16) -> 0 | F17: =SUM(F11:F16) -> 1076.1064 | G17: =SUM(G11:G16) -> -199.98912 | H17: =SUM(H11:H16) -> 233.61537 | I17: =SUM(I11:I16) -> 716.02398 | J17: =SUM(J11:J16) -> -4.027171 | K17: =SUM(K11:K16) -> -107.89028 | L17: =SUM(L11:L16) -> 0 | ... Q17: =SUM(Q11:Q16) -> 636.67406 | R17: =Q17*1000/$Q$4 -> 11.970708 | S17: =Q17-SUM(I17:O17) -> 0 | T17: =+Q17-I17 -> -79.349918 | U17: =SUM(U11:U16) -> -393.70866 | V17: =+T17+U17 -> -473.05858 | X17: 7.1187246 | Y17: =+P17-X17 -> -86.468642 | AA17: 723.1427 | AB17: =+Q17-AA17 -> -86.468642 | AD17: =SUM(I17:L17)*1000/$Q$4 -> 11.358375 | AE17: =+AF17-AD17 -> 0.61233284 | AF17: =R17 -> 11.970708
A18: TOTAL MFG COST w/o SHARES | B18: =B10+B17 -> 1272.3525 | C18: =B18/$B$4*1000 -> 23.887215 | E18: =E10+E17 -> -10.596096 | F18: =F10+F17 -> 1731.3735 | G18: =G10+G17 -> -309.52383 | H18: =H10+H17 -> 233.61537 | I18: =I10+I17 -> 1261.7564 | J18: =J10+J17 -> 14.232197 | K18: =K10+K17 -> -248.18822 | L18: =L10+L17 -> 0 | ... Q18: =Q10+Q17 -> 1085.854 | R18: =Q18*1000/$Q$4 -> 20.416162 | S18: =Q18-SUM(I18:O18) -> 0 | T18: =+Q18-I18 -> -175.90243 | U18: =+U17 -> -393.70866 | V18: =+T18+U18 -> -569.61109 | X18: -57.345754 | Y18: =+P18-X18 -> -118.55668 | AA18: 1240.8447 | AB18: =+Q18-AA18 -> -154.9907 | AD18: =SUM(I18:L18)*1000/$Q$4 -> 19.324642 | AE18: =+AF18-AD18 -> 1.0915202 | AF18: =R18 -> 20.416162
A19: TOTAL SHARES | B19: ='data entry '!Q17 -> 20.474517 | C19: =B19/$B$4*1000 -> 0.3843897 | F19: ='data entry '!Q96 -> 0 | G19: ='data entry '!Q51 -> 7.6901145 | H19: ='Budget assumption'!Q331 -> 3.2604697 | I19: =B19 -> 20.474517 | K19: -15.779304 | N19: =SUM(SAP_ACT_EUR!P72,SAP_ACT_EUR!P290,SAP_ACT_EUR!P60)/1000 -> 0.37648679 | P19: =SUM(J19:O19) -> -15.402817 | Q19: ='data entry '!Q129 -> 5.0717 | R19: =Q19*1000/$Q$4 -> 0.095357801 | S19: =Q19-SUM(I19:O19) -> 0 | T19: =+Q19-I19 -> -15.402817 | U19: =+'MTD VAR '!R18 -> 12.784403 | V19: =+T19+U19 -> -2.6184145 | X19: -7.0211713 | Y19: =+P19-X19 -> -8.3816461 | AA19: 13.453346 | AB19: =+Q19-AA19 -> -8.3816461 | AD19: =SUM(I19:L19)*1000/$Q$4 -> 0.088279119 | AE19: =+AF19-AD19 -> 0.0070786822 | AF19: =R19 -> 0.095357801
A20: TOTAL MFG COST w/ SHARES | B20: =B18+B19 -> 1292.827 | C20: =B20/$B$4*1000 -> 24.271605 | E20: =E18+E19 -> -10.596096 | F20: =F18+F19 -> 1731.3735 | G20: =G18+G19 -> -301.83372 | H20: =H18+H19 -> 236.87584 | I20: =I18+I19 -> 1282.2309 | J20: =J18+J19 -> 14.232197 | K20: =K18+K19 -> -263.96752 | L20: =L18+L19 -> 0 | ... Q20: =Q18+Q19 -> 1090.9257 | R20: =Q20*1000/$Q$4 -> 20.51152 | S20: =Q20-SUM(I20:O20) -> 0 | T20: =+Q20-I20 -> -191.30525 | U20: =+U19+U18 -> -380.92426 | V20: =+T20+U20 -> -572.22951 | X20: -64.366925 | Y20: =+P20-X20 -> -126.93832 | AA20: 1254.298 | AB20: =+Q20-AA20 -> -163.37235 | AD20: =SUM(I20:L20)*1000/$Q$4 -> 19.412921 | AE20: =+AF20-AD20 -> 1.0985988 | AF20: =R20 -> 20.51152
A22: Functional Currency Impact | B22: ='data entry '!Q19 -> 416.35266 | C22: =B22/$B$4*1000 -> 7.8166274 | F22: ='data entry '!Q98 -> 0 | G22: ='data entry '!Q53 -> -118.92816 | H22: =+'Budget assumption'!Q333 -> 136.51533 | I22: =B22 -> 416.35266 | K22: -114.94557 | P22: =SUM(J22:O22) -> -114.94557 | Q22: ='data entry '!Q131 -> 301.40709 | R22: =Q22*1000/$Q$4 -> 5.6670381 | S22: =Q22-SUM(I22:O22) -> 0 | T22: =+Q22-I22 -> -114.94557 | U22: =+'MTD VAR '!R20 -> 398.7655 | V22: =+T22+U22 -> 283.81992 | X22: -111.56866 | Y22: =+P22-X22 -> -3.37691 | AA22: 304.784 | AB22: =+Q22-AA22 -> -3.37691 | AD22: =SUM(I22:L22)*1000/$Q$4 -> 5.6670381 | AE22: =+AF22-AD22 -> 0 | AF22: =R22 -> 5.6670381
A23: TOTAL Including FC | B23: =+B22+B20 -> 1709.1797 | C23: =B23/$B$4*1000 -> 32.088232 | E23: =+E22+E20 -> -10.596096 | F23: =+F22+F20 -> 1731.3735 | G23: =+G22+G20 -> -420.76188 | H23: =+H22+H20 -> 373.39116 | I23: =+I22+I20 -> 1698.5836 | J23: =+J22+J20 -> 14.232197 | K23: =+K22+K20 -> -378.91309 | L23: =+L22+L20 -> 0 | ... Q23: =+Q22+Q20 -> 1392.3328 | R23: =Q23*1000/$Q$4 -> 26.178558 | S23: =Q23-SUM(I23:O23) -> 0 | T23: =+Q23-I23 -> -306.25082 | U23: =+U22+U20 -> 17.841236 | V23: =+T23+U23 -> -288.40958 | X23: -175.93559 | Y23: =+P23-X23 -> -130.31523 | AA23: 1559.082 | AB23: =+Q23-AA23 -> -166.74926 | AD23: =SUM(I23:L23)*1000/$Q$4 -> 25.079959 | AE23: =+AF23-AD23 -> 1.0985988 | AF23: =R23 -> 26.178558
AF24: =R24 -> 0
A25: Scrap | B25: ='data entry '!Q21 -> 21 | C25: =B25/$B$4*1000 -> 0.39425514 | E25: =I25-B25 -> -1.2228646 | F25: ='data entry '!Q100 -> 25.432898 | G25: ='data entry '!Q55 -> -5.6557631 | I25: =F25+G25 -> 19.777135 | J25: =-'ACE 2026'!G45/1000 -> 7.5285 | K25: =((((0.55-0.48)*53.265)-J25)+2.73972522035599)+0.567749999999997 -> -0.49247478 | M25: =0.56775+0.586 -> 1.15375 | N25: =SAP_ACT_EUR!P25/1000 -> 0.0034694264 | P25: =SUM(J25:O25) -> 8.1932446 | Q25: ='data entry '!Q133 -> 27.97038 | R25: =Q25*1000/$Q$4 -> 0.52589742 | S25: =Q25-SUM(I25:O25) -> 0 | T25: =+Q25-I25 -> 8.1932446 | V25: =+T25+U25 -> 8.1932446 | X25: 2.0421797 | Y25: =+P25-X25 -> 6.1510649 | AA25: 23.30592 | AB25: =+Q25-AA25 -> 4.66446 | AD25: =SUM(I25:L25)*1000/$Q$4 -> 0.50413945 | AE25: =+AF25-AD25 -> 0.021757971 | AF25: =R25 -> 0.52589742
A26: Scrap Reselling | B26: ='data entry '!Q22 -> -53 | C26: =B26/$B$4*1000 -> -0.99502488 | E26: =I26-B26 -> 2.7665998 | F26: ='data entry '!Q101 -> -62.74935 | G26: ='data entry '!Q56 -> 12.51595 | I26: =F26+G26 -> -50.2334 | K26: -4.2145351 | M26: -19 | N26: =SAP_ACT_EUR!P90/1000 -> -0.69367477 | P26: =SUM(J26:O26) -> -23.90821 | Q26: ='data entry '!Q134 -> -74.14161 | R26: =Q26*1000/$Q$4 -> -1.3940061 | S26: =Q26-SUM(I26:O26) -> 0 | T26: =+Q26-I26 -> -23.90821 | V26: =+T26+U26 -> -23.90821 | X26: 2.1883729 | Y26: =+P26-X26 -> -26.096583 | AA26: -51.571118 | AB26: =+Q26-AA26 -> -22.570492 | AD26: =SUM(I26:L26)*1000/$Q$4 -> -1.0237268 | AE26: =+AF26-AD26 -> -0.3702793 | AF26: =R26 -> -1.3940061
A27: Other Variable (Inventory Adj) | B27: ='data entry '!Q23 -> 0 | C27: =B27/$B$4*1000 -> 0 | F27: ='data entry '!Q102 -> 0 | G27: ='data entry '!Q57 -> 0 | I27: =F27+G27 -> 0 | K27: -8.63233 | M27: =-0.41448+0.13239 -> -0.28209 | P27: =SUM(J27:O27) -> -8.91442 | Q27: ='data entry '!Q135 -> -8.91442 | R27: =Q27*1000/$Q$4 -> -0.16760839 | S27: =Q27-SUM(I27:O27) -> 0 | T27: =+Q27-I27 -> -8.91442 | V27: =+T27+U27 -> -8.91442 | X27: 0 | Y27: =+P27-X27 -> -8.91442 | AA27: 0 | AB27: =+Q27-AA27 -> -8.91442 | AD27: =SUM(I27:L27)*1000/$Q$4 -> -0.16230455 | AE27: =+AF27-AD27 -> -0.0053038394 | AF27: =R27 -> -0.16760839
A28: Obsolete | B28: ='data entry '!Q24 -> 8 | C28: =B28/$B$4*1000 -> 0.15019243 | F28: ='data entry '!Q103 -> 0 | G28: ='data entry '!Q58 -> 8 | H28: ='Budget assumption'!Q328 -> 0 | I28: =B28 -> 8 | K28: -38.71528 | P28: =SUM(J28:O28) -> -38.71528 | Q28: ='data entry '!Q136 -> -30.71528 | R28: =Q28*1000/$Q$4 -> -0.57750686 | S28: =Q28-SUM(I28:O28) -> 0 | T28: =+Q28-I28 -> -38.71528 | U28: =+'MTD VAR '!R25 -> 0 | V28: =+T28+U28 -> -38.71528 | X28: 6.970477 | Y28: =+P28-X28 -> -45.685757 | AA28: 14.970477 | AB28: =+Q28-AA28 -> -45.685757 | AD28: =SUM(I28:L28)*1000/$Q$4 -> -0.57750686 | AE28: =+AF28-AD28 -> 0 | AF28: =R28 -> -0.57750686 | AH28: Aging risk is decreased especially for active materials
A29: Asset Sales | B29: ='data entry '!Q25 -> 0 | C29: =B29/$B$4*1000 -> 0 | F29: ='data entry '!Q104 -> 0 | G29: ='data entry '!Q59 -> 0 | I29: =B29 -> 0 | P29: =SUM(J29:O29) -> 0 | Q29: ='data entry '!Q137 -> 0 | R29: =Q29*1000/$Q$4 -> 0 | S29: =Q29-SUM(I29:O29) -> 0 | T29: =+Q29-I29 -> 0 | U29: =+'MTD VAR '!R26 -> 0 | V29: =+T29+U29 -> 0 | X29: 0 | Y29: =+P29-X29 -> 0 | AA29: 0 | AB29: =+Q29-AA29 -> 0 | AD29: =SUM(I29:L29)*1000/$Q$4 -> 0 | AE29: =+AF29-AD29 -> 0 | AF29: =R29 -> 0
A30: TOTAL OTHERS | B30: =SUM(B25:B29) -> -24 | C30: =B30/$B$4*1000 -> -0.4505773 | E30: =SUM(E25:E29) -> 1.5437352 | F30: =SUM(F25:F29) -> -37.316452 | G30: =SUM(G25:G29) -> 14.860187 | H30: =SUM(H25:H29) -> 0 | I30: =SUM(I25:I29) -> -22.456265 | J30: =SUM(J25:J29) -> 7.5285 | K30: =SUM(K25:K29) -> -52.05462 | L30: =SUM(L25:L29) -> 0 | ... Q30: =SUM(Q25:Q29) -> -85.80093 | R30: =Q30*1000/$Q$4 -> -1.613224 | S30: =Q30-SUM(I30:O30) -> 0 | T30: =+Q30-I30 -> -63.344665 | U30: =SUM(U28:U29) -> 0 | V30: =+T30+U30 -> -63.344665 | X30: 11.20103 | Y30: =+P30-X30 -> -74.545695 | AA30: -13.294721 | AB30: =+Q30-AA30 -> -72.506209 | AD30: =SUM(I30:L30)*1000/$Q$4 -> -1.2593988 | AE30: =+AF30-AD30 -> -0.35382517 | AF30: =R30 -> -1.613224
A32: IT GLOBAL | B32: ='data entry '!Q27 -> 90.697223 | C32: =B32/$B$4*1000 -> 1.7027546 | F32: ='data entry '!Q106 -> 83.314994 | G32: ='data entry '!Q61 -> -32.924823 | H32: ='Budget assumption'!Q335 -> 31.527944 | I32: =B32 -> 90.697223 | K32: -1.2821025 | P32: =SUM(J32:O32) -> -1.2821025 | Q32: ='data entry '!Q139 -> 89.41512 | R32: =Q32*1000/$Q$4 -> 1.6811778 | S32: =Q32-SUM(I32:O32) -> 0 | T32: =+Q32-I32 -> -1.2821025 | U32: =+'MTD VAR '!R28 -> -17.851725 | V32: =+T32+U32 -> -19.133828 | X32: -1.3199509e-07 | Y32: =+P32-X32 -> -1.2821024 | AA32: 90.697222 | AB32: =+Q32-AA32 -> -1.2821024 | AD32: =SUM(I32:L32)*1000/$Q$4 -> 1.6811778 | AE32: =+AF32-AD32 -> 0 | AF32: =R32 -> 1.6811778
A33: G&A(Insurance included) | B33: ='data entry '!Q28 -> 94.532002 | C33: =B33/$B$4*1000 -> 1.7747489 | F33: ='data entry '!Q107 -> 86.837645 | G33: ='data entry '!Q62 -> -9.8883173 | H33: ='Budget assumption'!Q336 -> 26.630833 | I33: =B33 -> 94.532002 | M33: -54.592549 | N33: =((SAP_ACT_EUR!P335-SAP_ACT_EUR!P290)/1000) -> 3.2178666 | P33: =SUM(J33:O33) -> -51.374682 | Q33: ='data entry '!Q140 -> 43.15732 | R33: =Q33*1000/$Q$4 -> 0.81144136 | S33: =Q33-SUM(I33:O33) -> 0 | T33: =+Q33-I33 -> -51.374682 | U33: =+'MTD VAR '!R29 -> 17.582675 | V33: =+T33+U33 -> -33.792008 | X33: -45.930953 | Y33: =+P33-X33 -> -5.4437294 | AA33: 48.601049 | AB33: =+Q33-AA33 -> -5.4437294 | AD33: =SUM(I33:L33)*1000/$Q$4 -> 1.7773851 | AE33: =+AF33-AD33 -> -0.96594371 | AF33: =R33 -> 0.81144136
A34: TOTAL OVERHEAD | B34: =B32+B33 -> 185.22922 | C34: =B34/$B$4*1000 -> 3.4775035 | E34: =E32+E33 -> 0 | F34: =F32+F33 -> 170.15264 | G34: =G32+G33 -> -42.81314 | H34: =H32+H33 -> 58.158777 | I34: =I32+I33 -> 185.22922 | J34: =J32+J33 -> 0 | K34: =K32+K33 -> -1.2821025 | L34: =L32+L33 -> 0 | ... Q34: =Q32+Q33 -> 132.57244 | R34: =Q34*1000/$Q$4 -> 2.4926191 | S34: =Q34-SUM(I34:O34) -> 0 | T34: =+Q34-I34 -> -52.656785 | U34: =SUM(U32:U33) -> -0.26905074 | V34: =+T34+U34 -> -52.925835 | X34: -45.930953 | Y34: =+P34-X34 -> -6.7258318 | AA34: 139.29827 | AB34: =+Q34-AA34 -> -6.7258318 | AD34: =SUM(I34:L34)*1000/$Q$4 -> 3.4585628 | AE34: =+AF34-AD34 -> -0.96594371 | AF34: =R34 -> 2.4926191
A36: GRAND TOTAL | B36: =B23+B30+B34 -> 1870.4089 | C36: =B36/$B$4*1000 -> 35.115159 | E36: =E23+E30+E34 -> -9.0523612 | F36: =F23+F30+F34 -> 1864.2097 | G36: =G23+G30+G34 -> -448.71483 | H36: =H23+H30+H34 -> 431.54994 | I36: =I23+I30+I34 -> 1861.3566 | J36: =J23+J30+J34 -> 21.760697 | K36: =K23+K30+K34 -> -432.24982 | L36: =L23+L30+L34 -> 0 | ... Q36: =Q23+Q30+Q34 -> 1439.1043 | R36: =Q36*1000/$Q$4 -> 27.057953 | S36: =Q36-SUM(I36:O36) -> 0 | T36: =+Q36-I36 -> -422.25227 | U36: =+U34+U30+U23 -> 17.572185 | V36: =+T36+U36 -> -404.68008 | W36: =+X36*1000/$X$4 -> #VALUE! | X36: =SUM(X34,X30,X23) -> -210.66551 | Y36: =+P36-X36 -> -211.58676 | AA36: =SUM(AA34,AA30,AA23) -> 1685.0856 | AB36: =+Q36-AA36 -> -245.9813 | AD36: =SUM(I36:L36)*1000/$Q$4 -> 27.279123 | AE36: =+AF36-AD36 -> -0.22117003 | AF36: =R36 -> 27.057953
A38: Highlights;
A41: Direct Labour | B41: Ace | C41: -28 K€ gain --> -21 K€ gain due to 30 HC low salary & -7 K€ gain Line speed 130 to 135 & Injection parts TC improvement(3 sec), 18 k€loss due to ongoing,cancelled ACE projects(related Chinese supplier&EPS&User manual)
B42: MFG | C42: Act 100 % eff vs Bdg 98 %--> -150k€ gain due to ISKUR project. 7 k€loss related with ovt
B43: Price | C43: 16 K€ loss salary increase, -20 K€ social allowace gain
A45: Variable Utilities | B45: MFG
B46: Price
A48: Indirect Labour | B48: MFG | C48: -6 K€ gain 3 HC less than bdg, 5 K€ loss overtime hours
B49: Price | C49: 8 K€ loss salary,-9 k€ low salary mix impact
A52: Fixed Labour | B52: MFG | C52: -3 K€ shared gain
B53: Price | C53: -4K€ gain salary, 4 K€ loss salary mix, 1k€ loss on annual leave days accrual.
A55: Semifixed | B55: MFG | C55: -58k€gain on maintenace expenses -10 K€ gain social aids, -5k€ related with work uniforms, 11 k€gain related with shuttles.
B56: Price | C56: -1 K€ gain meal price, 5 k€loss on shuttle
A58: Fixed Utiliites | B58: MFG
B59: Price
A61: Fixed Cost | B61: MFG
A63: Depreciation | B63: MFG | C63: -135 k€useful life extention project impact
A65: Scrap | B65: MFG | C65: Act 0,55€/box, tgt 0.48 €/box. 1k€ML posting
A67: Scrap Reselling | B67: MFG | C67: 4 k€ more scrap sales vs budget
B68: Price | C68: -1 9 K€ price gain mainly related 430 Steel and galvanize, 10 k€price difference invoice issued this month.
A70: Obsolete | B70: MFG | C70: Aging risk is decreased especially for active materials compared to prev. Month
A72: G&A(Insurance included) | B72: Price | C72: -50 k€ gain related with Insurance policy.

Sheet YTD Report(HQD)_variance 
A2: DW YTD MAY | B2: Budget25 | E2: Volume Variance | F2: Copertura | G2: HWTW&ACE | H2: Budget FCA | I2: Budget Flex. | J2: ACE | K2: MFG Efficiency | L2: S&OP | M2: Price / Inflation | N2: fX translation | O2: Oth Functions | P2: VARIANCE | Q2: Actual Cost
B4: ='data entry '!R3 -> 289459 | E4: =Q4-B4 -> -49385 | Q4: ='data entry '!R115 -> 240074 | T4: Δ vs Flex. | U4: FCA | V4: Total Variance
A5: - Gain / +Loss | E5: =E4/B4 -> -0.17061138 | X5: checkline
B6: EUR/000 | C6: €/pc | E6: EUR/000 | F6: EUR/000 | G6: EUR/000 | H6: EUR/000 | I6: EUR/000 | J6: EUR/000 | K6: EUR/000 | L6: EUR/000 | M6: EUR/000 | N6: EUR/001 | O6: EUR/000 | P6: EUR/000 | Q6: EUR/000 | R6: €/pc | T6: EUR/000 | U6: EUR/000 | V6: EUR/000
A7: Direct Labor | B7: ='data entry '!R5 -> 3129 | C7: =B7/$B$4*1000 -> 10.809821 | E7: =I7-B7 -> -556.18603 | F7: ='data entry '!R84 -> 2737.3598 | G7: ='data entry '!R39 -> -164.54582 | I7: =F7+G7 -> 2572.814 | J7: -99.195845 | K7: -366.19926 | L7: 34.68 | M7: 117.016 | N7: 159.76563 | P7: =SUM(J7:O7) -> -153.93347 | Q7: ='data entry '!R117 -> 2418.8816 | R7: =Q7*1000/$Q$4 -> 10.075567 | S7: =Q7-SUM(I7:O7) -> 0.0010742934 | T7: =+Q7-I7 -> -153.93239 | V7: =+T7+U7 -> -153.93239
A8: Variable Utilities | B8: ='data entry '!R6 -> 209.56944 | C8: =B8/$B$4*1000 -> 0.72400387 | E8: =I8-B8 -> -41.195006 | F8: ='data entry '!R85 -> 182.02348 | G8: ='data entry '!R40 -> -13.649049 | I8: =F8+G8 -> 168.37443 | K8: -4.5848715 | M8: -17.6 | N8: 5.4179462 | P8: =SUM(J8:O8) -> -16.766925 | Q8: ='data entry '!R118 -> 151.60735 | R8: =Q8*1000/$Q$4 -> 0.63150258 | S8: =Q8-SUM(I8:O8) -> -0.00015505225 | T8: =+Q8-I8 -> -16.76708 | V8: =+T8+U8 -> -16.76708
A9: Other Variable (Production Consumable) | B9: ='data entry '!R7 -> 95.361 | C9: =B9/$B$4*1000 -> 0.32944562 | E9: =I9-B9 -> -23.922156 | F9: ='data entry '!R86 -> 77.826839 | G9: ='data entry '!R41 -> -6.3879953 | I9: =F9+G9 -> 71.438844 | J9: -2.77 | K9: 43.013249 | N9: 1.4741963 | P9: =SUM(J9:O9) -> 41.717445 | Q9: ='data entry '!R119 -> 113.14721 | R9: =Q9*1000/$Q$4 -> 0.47130139 | S9: =Q9-SUM(I9:O9) -> -0.0090794913 | T9: =+Q9-I9 -> 41.708366 | V9: =+T9+U9 -> 41.708366
A10: Variable Conv. | B10: =SUM(B7:B9) -> 3433.9304 | C10: =B10/$B$4*1000 -> 11.863271 | E10: =SUM(E7:E9) -> -621.30319 | F10: =SUM(F7:F9) -> 2997.2101 | G10: =SUM(G7:G9) -> -184.58287 | H10: =SUM(H7:H9) -> 0 | I10: =SUM(I7:I9) -> 2812.6272 | J10: =SUM(J7:J9) -> -101.96585 | K10: =SUM(K7:K9) -> -327.77088 | L10: =SUM(L7:L9) -> 34.68 | ... Q10: =SUM(Q7:Q9) -> 2683.6361 | R10: =Q10*1000/$Q$4 -> 11.178371 | S10: =Q10-SUM(I10:O10) -> -0.0081602501 | T10: =+Q10-I10 -> -128.99111 | V10: =+T10+U10 -> -128.99111
A11: Indirect Labour | B11: ='data entry '!R9 -> 1264.7213 | C11: =B11/$B$4*1000 -> 4.369259 | F11: ='data entry '!R88 -> 1082.3243 | G11: ='data entry '!R43 -> -29.509956 | H11: ='Budget assumption'!R323 -> 2.4144108 | I11: =B11 -> 1264.7213 | J11: -15.686169 | K11: -28.150169 | L11: 6 | M11: 52.869924 | N11: 45.523074 | P11: =SUM(J11:O11) -> 60.556661 | Q11: ='data entry '!R121 -> 1325.2768 | R11: =Q11*1000/$Q$4 -> 5.5202847 | S11: =Q11-SUM(I11:O11) -> -0.0011787155 | T11: =+Q11-I11 -> 60.555482 | U11: =+'YTD VAR'!R10 -> 209.49259 | V11: =+T11+U11 -> 270.04807
A12: Fixed Labour | B12: ='data entry '!R10 -> 644.90809 | C12: =B12/$B$4*1000 -> 2.2279773 | F12: ='data entry '!R89 -> 382.92251 | G12: ='data entry '!R44 -> 176.76119 | H12: ='Budget assumption'!R324 -> 0.8733361 | I12: =B12 -> 644.90809 | K12: -25.976929 | M12: 3.3304957 | N12: 13.842376 | P12: =SUM(J12:O12) -> -8.8040567 | Q12: ='data entry '!R122 -> 636.09685 | R12: =Q12*1000/$Q$4 -> 2.6495866 | S12: =Q12-SUM(I12:O12) -> -0.0071809618 | T12: =+Q12-I12 -> -8.8112377 | U12: =+'YTD VAR'!R11 -> 84.351048 | V12: =+T12+U12 -> 75.53981
A13: Semifixed | B13: ='data entry '!R11 -> 1060.8528 | C13: =B13/$B$4*1000 -> 3.66495 | F13: ='data entry '!R90 -> 741.73199 | G13: ='data entry '!R45 -> 157.02486 | H13: ='Budget assumption'!R325 -> 1.6861065 | I13: =B13 -> 1060.8528 | J13: -1.4791295 | K13: -189.4347 | M13: 21.588 | N13: 14.682347 | P13: =SUM(J13:O13) -> -154.64348 | Q13: ='data entry '!R123 -> 906.21602 | R13: =Q13*1000/$Q$4 -> 3.7747362 | S13: =Q13-SUM(I13:O13) -> 0.006733498 | T13: =+Q13-I13 -> -154.63675 | U13: =+'YTD VAR'!R12 -> 160.40981 | V13: =+T13+U13 -> 5.7730617
A14: Fixed utilities | B14: ='data entry '!R12 -> 32 | C14: =B14/$B$4*1000 -> 0.11055106 | F14: ='data entry '!R91 -> 40.771032 | G14: ='data entry '!R46 -> -25.500174 | H14: ='Budget assumption'!R326 -> 0.10726757 | I14: =B14 -> 32 | J14: 2.5 | K14: -12.117611 | M14: -6.0041183 | N14: -0.12288949 | P14: =SUM(J14:O14) -> -15.744619 | Q14: ='data entry '!R124 -> 16.25655 | R14: =Q14*1000/$Q$4 -> 0.067714746 | S14: =Q14-SUM(I14:O14) -> 0.001168825 | T14: =+Q14-I14 -> -15.74345 | U14: =+'YTD VAR'!R13 -> 16.621874 | V14: =+T14+U14 -> 0.87842423
A15: Fixed Cost | B15: ='data entry '!R13 -> 262.61091 | C15: =B15/$B$4*1000 -> 0.90724733 | F15: ='data entry '!R92 -> 189.24152 | G15: ='data entry '!R47 -> 60.869468 | H15: ='Budget assumption'!R327 -> 0.37635213 | I15: =B15 -> 262.61091 | J15: -8.34 | K15: -51.318552 | N15: 2.5780303 | P15: =SUM(J15:O15) -> -57.080522 | Q15: ='data entry '!R125 -> 205.53572 | R15: =Q15*1000/$Q$4 -> 0.85613486 | S15: =Q15-SUM(I15:O15) -> 0.0053354218 | T15: =+Q15-I15 -> -57.075186 | U15: =+'YTD VAR'!R14 -> 12.123569 | V15: =+T15+U15 -> -44.951617
A16: Depreciation | B16: ='data entry '!R14 -> 935.32923 | C16: =B16/$B$4*1000 -> 3.2313013 | F16: ='data entry '!R93 -> 2491.3283 | G16: ='data entry '!R48 -> 145.47907 | H16: ='Budget assumption'!R329 -> 1.4734791 | I16: =B16 -> 935.32923 | K16: -215.64247 | N16: 28.67 | P16: =SUM(J16:O16) -> -186.97247 | Q16: ='data entry '!R126 -> 748.35691 | R16: =Q16*1000/$Q$4 -> 3.1171926 | S16: =Q16-SUM(I16:O16) -> 0.00014536682 | T16: =+Q16-I16 -> -186.97232 | U16: =+'YTD VAR'!R15 -> -1702.9516 | V16: =+T16+U16 -> -1889.924
A17: Fixed Conv. | B17: =SUM(B11:B16) -> 4200.4223 | C17: =B17/$B$4*1000 -> 14.511286 | E17: =SUM(E11:E16) -> 0 | F17: =SUM(F11:F16) -> 4928.3197 | G17: =SUM(G11:G16) -> 485.12446 | H17: =SUM(H11:H16) -> 6.9309522 | I17: =SUM(I11:I16) -> 4200.4223 | J17: =SUM(J11:J16) -> -23.005299 | K17: =SUM(K11:K16) -> -522.64043 | L17: =SUM(L11:L16) -> 6 | ... Q17: =SUM(Q11:Q16) -> 3837.7389 | R17: =Q17*1000/$Q$4 -> 15.98565 | S17: =Q17-SUM(I17:O17) -> 0.0050234344 | T17: =+Q17-I17 -> -362.68346 | U17: =SUM(U11:U16) -> -1219.9527 | V17: =+T17+U17 -> -1582.6362
A18: TOTAL MFG COST w/o SHARES | B18: =B10+B17 -> 7634.3528 | C18: =B18/$B$4*1000 -> 26.374557 | E18: =E10+E17 -> -621.30319 | F18: =F10+F17 -> 7925.5298 | G18: =G10+G17 -> 300.5416 | H18: =H10+H17 -> 6.9309522 | I18: =I10+I17 -> 7013.0496 | J18: =J10+J17 -> -124.97114 | K18: =K10+K17 -> -850.41131 | L18: =L10+L17 -> 40.68 | ... Q18: =Q10+Q17 -> 6521.375 | R18: =Q18*1000/$Q$4 -> 27.16402 | S18: =Q18-SUM(I18:O18) -> -0.0031368157 | T18: =+Q18-I18 -> -491.67457 | U18: =+U17 -> -1219.9527 | V18: =+T18+U18 -> -1711.6273
A19: TOTAL SHARES | B19: ='data entry '!R17 -> 125.33573 | C19: =B19/$B$4*1000 -> 0.43299994 | F19: ='data entry '!R96 -> 0 | G19: ='data entry '!R51 -> 73.482907 | H19: ='Budget assumption'!R331 -> 0.096732335 | I19: =B19 -> 125.33573 | K19: -22.633456 | N19: -0.27245919 | P19: =SUM(J19:O19) -> -22.905915 | Q19: ='data entry '!R129 -> 102.43459 | R19: =Q19*1000/$Q$4 -> 0.42667923 | S19: =Q19-SUM(I19:O19) -> 0.0047752097 | T19: =+Q19-I19 -> -22.90114 | U19: =+'YTD VAR'!R18 -> 51.75609 | V19: =+T19+U19 -> 28.854951
A20: TOTAL MFG COST w/ SHARES | B20: =B18+B19 -> 7759.6885 | C20: =B20/$B$4*1000 -> 26.807557 | E20: =E18+E19 -> -621.30319 | F20: =F18+F19 -> 7925.5298 | G20: =G18+G19 -> 374.0245 | H20: =H18+H19 -> 7.0276846 | I20: =I18+I19 -> 7138.3853 | J20: =J18+J19 -> -124.97114 | K20: =K18+K19 -> -873.04477 | L20: =L18+L19 -> 40.68 | ... Q20: =Q18+Q19 -> 6623.8096 | R20: =Q20*1000/$Q$4 -> 27.5907 | S20: =Q20-SUM(I20:O20) -> 0.001638394 | T20: =+Q20-I20 -> -514.57571 | U20: =+U19+U18 -> -1168.1967 | V20: =+T20+U20 -> -1682.7724
S21: =Q21-SUM(I21:O21) -> 0
A22: Functional Currency Impact | B22: ='data entry '!R19 -> 2478.1861 | C22: =B22/$B$4*1000 -> 8.5614407 | F22: ='data entry '!R98 -> 0 | G22: ='data entry '!R53 -> 307.11699 | I22: =B22 -> 2478.1861 | K22: -114.94557 | N22: -561.10286 | P22: =SUM(J22:O22) -> -676.04843 | Q22: ='data entry '!R131 -> 1802.1403 | R22: =Q22*1000/$Q$4 -> 7.5066036 | S22: =Q22-SUM(I22:O22) -> 0.0027204665 | T22: =+Q22-I22 -> -676.04571 | U22: =+'YTD VAR'!R20 -> 2167.0189 | V22: =+T22+U22 -> 1490.9732
A23: TOTAL Including FC | B23: =+B22+B20 -> 10237.875 | C23: =B23/$B$4*1000 -> 35.368997 | E23: =E22 -> 0 | F23: =F22 -> 0 | G23: =G22 -> 307.11699 | H23: =H22 -> 0 | I23: =+I22+I20 -> 9616.5714 | J23: =+J22+J20 -> -124.97114 | K23: =+K22+K20 -> -987.99034 | L23: =+L22+L20 -> 40.68 | M23: =+M22+M20 -> 171.2003 | N23: =+N22+N20 -> -289.5446 | O23: =O22 -> 0 | P23: =+P22+P20 -> -1190.6258 | Q23: =+Q22+Q20 -> 8425.9499 | R23: =Q23*1000/$Q$4 -> 35.097303 | S23: =Q23-SUM(I23:O23) -> 0.0043588605 | T23: =+Q23-I23 -> -1190.6214 | U23: =+U22+U20 -> 998.82224 | V23: =+T23+U23 -> -191.79918
S24: =Q24-SUM(I24:O24) -> 0
A25: Scrap | B25: ='data entry '!R21 -> 136 | C25: =B25/$B$4*1000 -> 0.46984202 | E25: =I25-B25 -> -28.4161 | F25: ='data entry '!R100 -> 116.43982 | G25: ='data entry '!R55 -> -8.8559189 | I25: =F25+G25 -> 107.5839 | J25: 19.359 | K25: 8.7900408 | M25: -0.38538181 | N25: 1.2881461 | P25: =SUM(J25:O25) -> 29.051805 | Q25: ='data entry '!R133 -> 136.63113 | R25: =Q25*1000/$Q$4 -> 0.5691209 | S25: =Q25-SUM(I25:O25) -> -0.0045750897 | T25: =+Q25-I25 -> 29.04723 | V25: =+T25+U25 -> 29.04723
A26: Scrap Reselling | B26: ='data entry '!R22 -> -303 | C26: =B26/$B$4*1000 -> -1.0467804 | E26: =I26-B26 -> 68.586638 | F26: ='data entry '!R101 -> -287.44793 | G26: ='data entry '!R56 -> 53.03457 | I26: =F26+G26 -> -234.41336 | K26: 2.0630141 | M26: -63.259 | N26: -11.211675 | P26: =SUM(J26:O26) -> -72.407661 | Q26: ='data entry '!R134 -> -306.81066 | R26: =Q26*1000/$Q$4 -> -1.2779837 | S26: =Q26-SUM(I26:O26) -> 0.010362632 | T26: =+Q26-I26 -> -72.397298 | V26: =+T26+U26 -> -72.397298
A27: Other Variable (Inventory Adj) | B27: ='data entry '!R23 -> 0 | C27: =B27/$B$4*1000 -> 0 | F27: ='data entry '!R102 -> 0 | G27: ='data entry '!R57 -> 0 | I27: =F27+G27 -> 0 | K27: 67.54458 | M27: -4.25977 | P27: =SUM(J27:O27) -> 63.28481 | Q27: ='data entry '!R135 -> 63.28184 | R27: =Q27*1000/$Q$4 -> 0.26359306 | S27: =Q27-SUM(I27:O27) -> -0.00297 | T27: =+Q27-I27 -> 63.28184 | V27: =+T27+U27 -> 63.28184
A28: Obsolete | B28: ='data entry '!R24 -> 52 | C28: =B28/$B$4*1000 -> 0.17964548 | F28: ='data entry '!R103 -> 0 | G28: ='data entry '!R58 -> 52 | H28: ='Budget assumption'!R328 -> 0 | I28: =B28 -> 52 | K28: -34.67118 | P28: =SUM(J28:O28) -> -34.67118 | Q28: ='data entry '!R136 -> 17.3384 | R28: =Q28*1000/$Q$4 -> 0.072221065 | S28: =Q28-SUM(I28:O28) -> 0.00958 | T28: =+Q28-I28 -> -34.6616 | U28: =+'YTD VAR'!R25 -> -3.5527137e-15 | V28: =+T28+U28 -> -34.6616
A29: Asset Sales | B29: ='data entry '!R25 -> 0 | C29: =B29/$B$4*1000 -> 0 | F29: ='data entry '!R104 -> 0 | G29: ='data entry '!R59 -> 0 | I29: =B29 -> 0 | P29: =SUM(J29:O29) -> 0 | Q29: ='data entry '!R137 -> 0 | R29: =Q29*1000/$Q$4 -> 0 | S29: =Q29-SUM(I29:O29) -> 0 | T29: =+Q29-I29 -> 0 | U29: =+'YTD VAR'!R26 -> 0 | V29: =+T29+U29 -> 0
A30: TOTAL OTHERS | B30: =SUM(B25:B29) -> -115 | C30: =B30/$B$4*1000 -> -0.39729288 | E30: =SUM(E25:E29) -> 40.170538 | F30: =SUM(F25:F29) -> -171.00811 | G30: =SUM(G25:G29) -> 96.178651 | H30: =SUM(H25:H29) -> 0 | I30: =SUM(I25:I29) -> -74.829462 | J30: =SUM(J25:J29) -> 19.359 | K30: =SUM(K25:K29) -> 43.726455 | L30: =SUM(L25:L29) -> 0 | ... Q30: =SUM(Q25:Q29) -> -89.55929 | R30: =Q30*1000/$Q$4 -> -0.37304868 | S30: =Q30-SUM(I30:O30) -> 0.012397542 | T30: =+Q30-I30 -> -14.729828 | U30: =SUM(U28:U29) -> -3.5527137e-15 | V30: =+T30+U30 -> -14.729828
S31: =Q31-SUM(I31:O31) -> 0
A32: IT GLOBAL | B32: ='data entry '!R27 -> 544.18334 | C32: =B32/$B$4*1000 -> 1.8800014 | F32: ='data entry '!R106 -> 381.19684 | G32: ='data entry '!R61 -> 42.779235 | H32: =+'Budget assumption'!R335 -> 0.93537799 | I32: =B32 -> 544.18334 | K32: -3.8463075 | N32: -4.37 | P32: =SUM(J32:O32) -> -8.2163075 | Q32: ='data entry '!R139 -> 535.96594 | R32: =Q32*1000/$Q$4 -> 2.2325031 | S32: =Q32-SUM(I32:O32) -> -0.0010875 | T32: =+Q32-I32 -> -8.217395 | U32: =+'YTD VAR'!R28 -> 119.27188 | V32: =+T32+U32 -> 111.05448
A33: G&A(Insurance included) | B33: ='data entry '!R28 -> 567.19201 | C33: =B33/$B$4*1000 -> 1.95949 | F33: ='data entry '!R107 -> 397.31427 | G33: ='data entry '!R62 -> 143.66904 | H33: =+'Budget assumption'!R336 -> 0.79008941 | I33: =B33 -> 567.19201 | M33: =((-24.83+74)+-54.5925486914528-55)+26.4995819756332 -> -33.922967 | N33: 5.6408103 | P33: =SUM(J33:O33) -> -28.282156 | Q33: ='data entry '!R140 -> 538.91129 | R33: =Q33*1000/$Q$4 -> 2.2447716 | S33: =Q33-SUM(I33:O33) -> 0.0014335765 | T33: =+Q33-I33 -> -28.280723 | U33: =+'YTD VAR'!R29 -> 25.418614 | V33: =+T33+U33 -> -2.8621085
A34: TOTAL OVERHEAD | B34: =B32+B33 -> 1111.3753 | C34: =B34/$B$4*1000 -> 3.8394914 | E34: =E32+E33 -> 0 | F34: =F32+F33 -> 778.51111 | G34: =G32+G33 -> 186.44827 | H34: =H32+H33 -> 1.7254674 | I34: =I32+I33 -> 1111.3753 | J34: =J32+J33 -> 0 | K34: =K32+K33 -> -3.8463075 | L34: =L32+L33 -> 0 | ... Q34: =Q32+Q33 -> 1074.8772 | R34: =Q34*1000/$Q$4 -> 4.4772746 | S34: =Q34-SUM(I34:O34) -> 0.00034607646 | T34: =+Q34-I34 -> -36.498118 | U34: =SUM(U32:U33) -> 144.69049 | V34: =+T34+U34 -> 108.19238
R35: =Q35*1000/$Q$4 -> 0 | S35: =Q35-SUM(I35:O35) -> 0
A36: GRAND TOTAL | B36: =B23+B30+B34 -> 11234.25 | C36: =B36/$B$4*1000 -> 38.811196 | E36: =E20+E23+E30+E34 -> -581.13265 | F36: =F20+F23+F30+F34 -> 8533.0328 | G36: =G20+G23+G30+G34 -> 963.76842 | H36: =H20+H23+H30+H34 -> 8.753152 | I36: =+I23+I30+I34 -> 10653.117 | J36: =+J23+J30+J34 -> -105.61214 | K36: =+K23+K30+K34 -> -948.11019 | L36: =+L23+L30+L34 -> 40.68 | M36: =+M23+M30+M34 -> 69.373183 | N36: =+N23+N30+N34 -> -298.19732 | O36: =+O23+O30+O34 -> 0 | P36: =P23+P30+P34 -> -1241.8665 | Q36: =Q23+Q30+Q34 -> 9411.2679 | R36: =Q36*1000/$Q$4 -> 39.201529 | S36: =Q36-SUM(I36:O36) -> 0.017102479 | T36: =+Q36-I36 -> -1241.8494 | U36: =+U34+U30+U23 -> 1143.5127 | V36: =+T36+U36 -> -98.336637
A39: Direct Labour | B39: Ace | C39: -145 K€ gain --> -133K€ gain due to 30 HC low salary & -12K€ gain Line speed 130 to 135 & Injection parts TC improvement(3 sec)
B40: MFG | C40: -23 K€ gain due to 10 HC less, -197k€ gain due to ISKUR, 35 k€ loss related ovt -2.45 K€ loss annual leave, -29 K€ gain festivity payment due to 113 HC less than bdg
B41: S&op | C41: 35 K€ loss unefficiency due to volume cut
B42: Price | C42: 77 K€ loss salary,25 K€ loss overtime, -7 K€ gain TIS Accrual social aid reverse, -2 K€ gain indemnity, -63K€ salary mix gain . 72 K€ loss seasonality effect, -9.4 K€ gain festivity payment accrual, -3.72 K€ gain others 30 k€ ISKUr bayram payment
A44: Variable Utilities | B44: MFG
B45: Price | C45: -8 K€ grid price electiricity gain & -2 k€ solar electricity gain, -6 K€ gain seasonality effect
C46: =-83+1.5+9+26+22+3-4-12 -> -37.5
A47: Indirect Labour | B47: MFG | C47: -86 K€ gain less than bdg, 1,5 K€ loss annual leave, 9 K€ loss CK to DW transfer, 26 K€ loss DIR to IND transfer (Union Protest& Inventory Hours),22 K€ loss overtime hours,3 K€ loss trainee, -4 K€ gain gain festivity payment due to 16 HC less than bdg, -12 k€ ISKUR gain
B48: S&op | C48: 6 K€ loss ( Direct HC worked as Indirect because of volume cut-->excess manpower)
B49: Price | C49: 10 K€ loss overtime salary, 41K€ loss salary, -3 K€ gain TIS Accrual social aid reverse,4.44 k€ loss indemnity, '-5 K€ gain festivity payment accrual, -4.5 K€ gain TIS payment, 12 K€ loss others
A51: Fixed Labour | B51: MFG | C51: -29 K€ shared gain, -4,5 delta HDC gain 7K€ loss annual leave
B52: Price | C52: -7 K€ gain salary, 22K€ loss salary mix,-0.29 K€ gain indemnity,-18 K€ MBO, 5.6 K€ loss other
A54: Semifixed | B54: MFG | C54: 10K€ loss social aids(seasonality), -7 K€ gain meal, -176 K€ gain maintenance,-4 K€ gain stationery, -8 K€ gain quality, -5 k€ medical expenses
B55: MFG | C55: 18 K€ loss uniforms winter&summer shoe, trouser, shirt purchase (Bdg HC 380 vs Act HC 515), 20.2 K€ loss uniforms seasonality effect
B56: Price | C56: 13.2 K€ loss social aid price (10 KTL vs 8 KTL)+ 2 K€ tax impact due to amount diff,-4 K€ gain meal,+10 k€loss on shuttle
A58: Fixed Utiliites | B58: MFG | C58: -10 k€ consumption gain
B59: Price | C59: -6 K€ price gain
A61: Fixed Cost | B61: MFG | C61: 5 K€ loss accrual for suitcase, -20k€ entertainment, -2 K€ gain car rent, -2 K€ gain equipment rent, -1.4 K€ gain forklift rent, -5.5 K€ gain training, -5 K€ gain travel,-2.9 K€ gain cleaning, -1 K€ gain fuel
A63: Depreciation | B63: MFG | C63: -865 k€ useful life extention project impact
A65: Scrap Reselling | B65: MFG
B66: Price | C66: -63 k€scrap sales unit price higher than budget especially on steel and galvanize
A68: G&A(Insurance included) | B68: MFG
B69: Price | C69: -50 k€ gain related with Insurance policy.

Sheet List
C2: Jan | D2: 1 | E2: 1
C3: Feb | D3: 2 | E3: 1
C4: March | D4: 3 | E4: 1
C5: April | D5: 4 | E5: 1
C6: May | D6: 5 | E6: 1
C7: June | D7: 6 | E7: 1
C8: July | D8: 7 | E8: 1
C9: August | D9: 8 | E9: 1
C10: Sept | D10: 9 | E10: 1
C11: Oct | D11: 10 | E11: 1
C12: Nov | D12: 11 | E12: 1
C13: Dec | D13: 12 | E13: 1

Sheet data entry 
A1: YTD | B1: =IF($X$3>=B$2,1,0) -> 1 | C1: =IF($X$3>=C$2,1,0) -> 1 | D1: =IF($X$3>=D$2,1,0) -> 1 | E1: =IF($X$3>=E$2,1,0) -> 1 | F1: =IF($X$3>=F$2,1,0) -> 1 | G1: =IF($X$3>=G$2,1,0) -> 1 | H1: =IF($X$3>=H$2,1,0) -> 0 | I1: =IF($X$3>=I$2,1,0) -> 0 | ... M1: =IF($X$3>=M$2,1,0) -> 0
A2: MTD | B2: 1 | C2: 2 | D2: 3 | E2: 4 | F2: 5 | G2: 6 | H2: 7 | I2: 8 | J2: 9 | K2: 10 | L2: 11 | M2: 12
A3: Budget Volume | B3: ='Budget assumption'!B66 -> 50463 | C3: ='Budget assumption'!C66 -> 50446 | D3: ='Budget assumption'!D66 -> 50447 | E3: ='Budget assumption'!E66 -> 48050 | F3: ='Budget assumption'!F66 -> 36788 | G3: ='Budget assumption'!G66 -> 53265 | H3: ='Budget assumption'!H66 -> 42049 | I3: ='Budget assumption'!I66 -> 39150 | ... M3: ='Budget assumption'!M66 -> 40676 | N3: =SUM(B3:M3) -> 565022 | Q3: =SUMIFS(B3:M3,$B$2:$M$2,$X$3) -> 53265 | R3: =SUMIFS(B3:M3,$B$1:$M$1,$Y$3) -> 289459 | V3: Month | W3: June | X3: =VLOOKUP(W3,List!$C$2:$D$13,2,0) -> 6 | Y3: =VLOOKUP(W3,List!$C$2:$E$13,3,0) -> 1
A4: Budget 2025 | B4: Jan | C4: Feb | D4: March | E4: April | F4: May | G4: June | H4: July | I4: August | J4: Sept | K4: Oct | L4: Nov | M4: Dec | N4: Total | Q4: MTD | R4: YTD
A5: Direct Labour | B5: ='Budget assumption'!B211 -> 485 | C5: ='Budget assumption'!C211 -> 524 | D5: ='Budget assumption'!D211 -> 529 | E5: ='Budget assumption'!E211 -> 509 | F5: ='Budget assumption'!F211 -> 579 | G5: ='Budget assumption'!G211 -> 503 | H5: ='Budget assumption'!H211 -> 451 | I5: ='Budget assumption'!I211 -> 460 | ... M5: ='Budget assumption'!M211 -> 492 | N5: =SUM(B5:M5) -> 6077 | Q5: =SUMIFS(B5:M5,$B$2:$M$2,$X$3) -> 503 | R5: =SUMIFS(B5:M5,$B$1:$M$1,$Y$3) -> 3129
A6: Variable Utilities | B6: ='Budget assumption'!B212 -> 38.516777 | C6: ='Budget assumption'!C212 -> 37.591302 | D6: ='Budget assumption'!D212 -> 37.944559 | E6: ='Budget assumption'!E212 -> 35.733562 | F6: ='Budget assumption'!F212 -> 24.021199 | G6: ='Budget assumption'!G212 -> 35.762038 | H6: ='Budget assumption'!H212 -> 29.53027 | I6: ='Budget assumption'!I212 -> 31.209684 | ... M6: ='Budget assumption'!M212 -> 31.787008 | N6: =SUM(B6:M6) -> 405.32207 | Q6: =SUMIFS(B6:M6,$B$2:$M$2,$X$3) -> 35.762038 | R6: =SUMIFS(B6:M6,$B$1:$M$1,$Y$3) -> 209.56944
A7: Variable Costs | B7: ='Budget assumption'!B213 -> 16.73 | C7: ='Budget assumption'!C213 -> 16.73 | D7: ='Budget assumption'!D213 -> 16.73 | E7: ='Budget assumption'!E213 -> 15.8935 | F7: ='Budget assumption'!F213 -> 11.711 | G7: ='Budget assumption'!G213 -> 17.5665 | H7: ='Budget assumption'!H213 -> 14.2205 | I7: ='Budget assumption'!I213 -> 12.9675 | ... M7: ='Budget assumption'!M213 -> 11.47725 | N7: =SUM(B7:M7) -> 185.03175 | Q7: =SUMIFS(B7:M7,$B$2:$M$2,$X$3) -> 17.5665 | R7: =SUMIFS(B7:M7,$B$1:$M$1,$Y$3) -> 95.361
A8: VARIABLE CONVERSION | B8: =SUM(B5:B7) -> 540.24678 | C8: =SUM(C5:C7) -> 578.3213 | D8: =SUM(D5:D7) -> 583.67456 | E8: =SUM(E5:E7) -> 560.62706 | F8: =SUM(F5:F7) -> 614.7322 | G8: =SUM(G5:G7) -> 556.32854 | H8: =SUM(H5:H7) -> 494.75077 | I8: =SUM(I5:I7) -> 504.17718 | ... M8: =SUM(M5:M7) -> 535.26426 | N8: =SUM(B8:M8) -> 6667.3538 | Q8: =SUM(Q5:Q7) -> 556.32854 | R8: =SUM(R5:R7) -> 3433.9304
A9: Indirect Labour | B9: ='Budget assumption'!B215 -> 194.74895 | C9: ='Budget assumption'!C215 -> 207.51639 | D9: ='Budget assumption'!D215 -> 211.95318 | E9: ='Budget assumption'!E215 -> 204.69927 | F9: ='Budget assumption'!F215 -> 228.48499 | G9: ='Budget assumption'!G215 -> 217.31856 | H9: ='Budget assumption'!H215 -> 251.55222 | I9: ='Budget assumption'!I215 -> 229.24655 | ... M9: ='Budget assumption'!M215 -> 288.17726 | N9: =SUM(B9:M9) -> 2701.3288 | Q9: =SUMIFS(B9:M9,$B$2:$M$2,$X$3) -> 217.31856 | R9: =SUMIFS(B9:M9,$B$1:$M$1,$Y$3) -> 1264.7213
A10: Fixed Labour | B10: ='Budget assumption'!B216 -> 106.58 | C10: ='Budget assumption'!C216 -> 112.97149 | D10: ='Budget assumption'!D216 -> 102.64253 | E10: ='Budget assumption'!E216 -> 104.32865 | F10: ='Budget assumption'!F216 -> 110.75817 | G10: ='Budget assumption'!G216 -> 107.62726 | H10: ='Budget assumption'!H216 -> 100.46411 | I10: ='Budget assumption'!I216 -> 101.53527 | ... M10: ='Budget assumption'!M216 -> 96.810882 | N10: =SUM(B10:M10) -> 1249.4242 | Q10: =SUMIFS(B10:M10,$B$2:$M$2,$X$3) -> 107.62726 | R10: =SUMIFS(B10:M10,$B$1:$M$1,$Y$3) -> 644.90809
A11: Semifixed | B11: ='Budget assumption'!B217 -> 183.02969 | C11: ='Budget assumption'!C217 -> 179.83513 | D11: ='Budget assumption'!D217 -> 176.70014 | E11: ='Budget assumption'!E217 -> 177.19911 | F11: ='Budget assumption'!F217 -> 155.71007 | G11: ='Budget assumption'!G217 -> 188.37864 | H11: ='Budget assumption'!H217 -> 178.57404 | I11: ='Budget assumption'!I217 -> 171.83302 | ... M11: ='Budget assumption'!M217 -> 176.72183 | N11: =SUM(B11:M11) -> 2155.81 | Q11: =SUMIFS(B11:M11,$B$2:$M$2,$X$3) -> 188.37864 | R11: =SUMIFS(B11:M11,$B$1:$M$1,$Y$3) -> 1060.8528
A12: Fixed utilities | B12: ='Budget assumption'!B218 -> 5 | C12: ='Budget assumption'!C218 -> 6 | D12: ='Budget assumption'!D218 -> 6 | E12: ='Budget assumption'!E218 -> 5 | F12: ='Budget assumption'!F218 -> 4 | G12: ='Budget assumption'!G218 -> 6 | H12: ='Budget assumption'!H218 -> 5 | I12: ='Budget assumption'!I218 -> 4 | ... M12: ='Budget assumption'!M218 -> 5 | N12: =SUM(B12:M12) -> 66 | Q12: =SUMIFS(B12:M12,$B$2:$M$2,$X$3) -> 6 | R12: =SUMIFS(B12:M12,$B$1:$M$1,$Y$3) -> 32
A13: Fixed Cost | B13: ='Budget assumption'!B219 -> 44.860259 | C13: ='Budget assumption'!C219 -> 44.262155 | D13: ='Budget assumption'!D219 -> 43.675204 | E13: ='Budget assumption'!E219 -> 43.218668 | F13: ='Budget assumption'!F219 -> 42.76888 | G13: ='Budget assumption'!G219 -> 43.825739 | H13: ='Budget assumption'!H219 -> 42.091273 | I13: ='Budget assumption'!I219 -> 41.858668 | ... M13: ='Budget assumption'!M219 -> 43.146735 | N13: =SUM(B13:M13) -> 513.11153 | Q13: =SUMIFS(B13:M13,$B$2:$M$2,$X$3) -> 43.825739 | R13: =SUMIFS(B13:M13,$B$1:$M$1,$Y$3) -> 262.61091
A14: Depreciation | B14: ='Budget assumption'!B220 -> 161.79174 | C14: ='Budget assumption'!C220 -> 149.59309 | D14: ='Budget assumption'!D220 -> 160.35867 | E14: ='Budget assumption'!E220 -> 155.0923 | F14: ='Budget assumption'!F220 -> 155.61965 | G14: ='Budget assumption'!G220 -> 152.87378 | H14: ='Budget assumption'!H220 -> 171.28341 | I14: ='Budget assumption'!I220 -> 170.28855 | ... M14: ='Budget assumption'!M220 -> 176.92268 | N14: =SUM(B14:M14) -> 1955.7778 | Q14: =SUMIFS(B14:M14,$B$2:$M$2,$X$3) -> 152.87378 | R14: =SUMIFS(B14:M14,$B$1:$M$1,$Y$3) -> 935.32923
A15: FIXED CONVERSION | B15: =SUM(B9:B14) -> 696.01064 | C15: =SUM(C9:C14) -> 700.17825 | D15: =SUM(D9:D14) -> 701.32971 | E15: =SUM(E9:E14) -> 689.538 | F15: =SUM(F9:F14) -> 697.34176 | G15: =SUM(G9:G14) -> 716.02398 | H15: =SUM(H9:H14) -> 748.96506 | I15: =SUM(I9:I14) -> 718.76205 | ... M15: =SUM(M9:M14) -> 786.77939 | N15: =SUM(B15:M15) -> 8641.4523 | Q15: =SUM(Q9:Q14) -> 716.02398 | R15: =SUM(R9:R14) -> 4200.4223
A16: TOTAL MFG COST w/o SHARES | B16: =B8+B15 -> 1236.2574 | C16: =C8+C15 -> 1278.4995 | D16: =D8+D15 -> 1285.0043 | E16: =E8+E15 -> 1250.1651 | F16: =F8+F15 -> 1312.074 | G16: =G8+G15 -> 1272.3525 | H16: =H8+H15 -> 1243.7158 | I16: =I8+I15 -> 1222.9392 | ... M16: =M8+M15 -> 1322.0436 | N16: =SUM(B16:M16) -> 15308.806 | Q16: =+Q15+Q8 -> 1272.3525 | R16: =+R15+R8 -> 7634.3528
A17: TOTAL SHARES | B17: ='Budget assumption'!B223 -> 21.133 | C17: ='Budget assumption'!C223 -> 21.209825 | D17: ='Budget assumption'!D223 -> 20.932865 | E17: ='Budget assumption'!E223 -> 20.567044 | F17: ='Budget assumption'!F223 -> 21.018478 | G17: ='Budget assumption'!G223 -> 20.474517 | H17: ='Budget assumption'!H223 -> 20.217401 | I17: ='Budget assumption'!I223 -> 20.03887 | ... M17: ='Budget assumption'!M223 -> 19.789757 | N17: =SUM(B17:M17) -> 245.4643 | Q17: =SUMIFS(B17:M17,$B$2:$M$2,$X$3) -> 20.474517 | R17: =SUMIFS(B17:M17,$B$1:$M$1,$Y$3) -> 125.33573
A18: TOTAL MFG COST w/ SHARES | B18: =B16+B17 -> 1257.3904 | C18: =C16+C17 -> 1299.7094 | D18: =D16+D17 -> 1305.9371 | E18: =E16+E17 -> 1270.7321 | F18: =F16+F17 -> 1333.0924 | G18: =G16+G17 -> 1292.827 | H18: =H16+H17 -> 1263.9332 | I18: =I16+I17 -> 1242.9781 | ... M18: =M16+M17 -> 1341.8334 | N18: =SUM(B18:M18) -> 15554.27 | Q18: =+Q17+Q16 -> 1292.827 | R18: =+R17+R16 -> 7759.6885
A19: Functional Currency Impact | B19: ='Budget assumption'!B225 -> 415.68863 | C19: ='Budget assumption'!C225 -> 386.88891 | D19: ='Budget assumption'!D225 -> 421.50115 | E19: ='Budget assumption'!E225 -> 413.13905 | F19: ='Budget assumption'!F225 -> 424.61564 | G19: ='Budget assumption'!G225 -> 416.35266 | H19: ='Budget assumption'!H225 -> 428.1206 | I19: ='Budget assumption'!I225 -> 429.39435 | ... M19: ='Budget assumption'!M225 -> 436.70918 | N19: =SUM(B19:M19) -> 5048.1922 | Q19: =SUMIFS(B19:M19,$B$2:$M$2,$X$3) -> 416.35266 | R19: =SUMIFS(B19:M19,$B$1:$M$1,$Y$3) -> 2478.1861
A20: TOTAL Including FC | B20: =B18+B19 -> 1673.0791 | C20: =C18+C19 -> 1686.5983 | D20: =D18+D19 -> 1727.4383 | E20: =E18+E19 -> 1683.8712 | F20: =F18+F19 -> 1757.7081 | G20: =G18+G19 -> 1709.1797 | H20: =H18+H19 -> 1692.0538 | I20: =I18+I19 -> 1672.3725 | ... M20: =M18+M19 -> 1778.5426 | N20: =SUM(B20:M20) -> 20602.463 | Q20: =+Q18+Q19 -> 1709.1797 | R20: =+R18+R19 -> 10237.875
A21: Scrap | B21: ='Budget assumption'!B227 -> 27 | C21: ='Budget assumption'!C227 -> 27 | D21: ='Budget assumption'!D227 -> 27 | E21: ='Budget assumption'!E227 -> 19 | F21: ='Budget assumption'!F227 -> 15 | G21: ='Budget assumption'!G227 -> 21 | H21: ='Budget assumption'!H227 -> 17 | I21: ='Budget assumption'!I227 -> 16 | ... M21: ='Budget assumption'!M227 -> 16 | N21: =SUM(B21:M21) -> 247 | Q21: =SUMIFS(B21:M21,$B$2:$M$2,$X$3) -> 21 | R21: =SUMIFS(B21:M21,$B$1:$M$1,$Y$3) -> 136
A22: Scrap Reselling | B22: ='Budget assumption'!B228 -> -55 | C22: ='Budget assumption'!C228 -> -55 | D22: ='Budget assumption'!D228 -> -56 | E22: ='Budget assumption'!E228 -> -48 | F22: ='Budget assumption'!F228 -> -36 | G22: ='Budget assumption'!G228 -> -53 | H22: ='Budget assumption'!H228 -> -44 | I22: ='Budget assumption'!I228 -> -40 | ... M22: ='Budget assumption'!M228 -> -41 | N22: =SUM(B22:M22) -> -585 | O22: 23.011403 | Q22: =SUMIFS(B22:M22,$B$2:$M$2,$X$3) -> -53 | R22: =SUMIFS(B22:M22,$B$1:$M$1,$Y$3) -> -303
A23: Other Variable (Inventory Adj) | B23: ='Budget assumption'!B229 -> 0 | C23: ='Budget assumption'!C229 -> 0 | D23: ='Budget assumption'!D229 -> 0 | E23: ='Budget assumption'!E229 -> 0 | F23: ='Budget assumption'!F229 -> 0 | G23: ='Budget assumption'!G229 -> 0 | H23: ='Budget assumption'!H229 -> 0 | I23: ='Budget assumption'!I229 -> 0 | ... M23: ='Budget assumption'!M229 -> 0 | N23: =SUM(B23:M23) -> 0 | Q23: =SUMIFS(B23:M23,$B$2:$M$2,$X$3) -> 0 | R23: =SUMIFS(B23:M23,$B$1:$M$1,$Y$3) -> 0
A24: Obsolete | B24: ='Budget assumption'!B230 -> 9 | C24: ='Budget assumption'!C230 -> 9 | D24: ='Budget assumption'!D230 -> 9 | E24: ='Budget assumption'!E230 -> 9 | F24: ='Budget assumption'!F230 -> 8 | G24: ='Budget assumption'!G230 -> 8 | H24: ='Budget assumption'!H230 -> 8 | I24: ='Budget assumption'!I230 -> 8 | ... M24: ='Budget assumption'!M230 -> 8 | N24: =SUM(B24:M24) -> 100 | Q24: =SUMIFS(B24:M24,$B$2:$M$2,$X$3) -> 8 | R24: =SUMIFS(B24:M24,$B$1:$M$1,$Y$3) -> 52
A25: Asset Sales | B25: ='Budget assumption'!B231 -> 0 | C25: ='Budget assumption'!C231 -> 0 | D25: ='Budget assumption'!D231 -> 0 | E25: ='Budget assumption'!E231 -> 0 | F25: ='Budget assumption'!F231 -> 0 | G25: ='Budget assumption'!G231 -> 0 | H25: ='Budget assumption'!H231 -> 0 | I25: ='Budget assumption'!I231 -> 0 | ... M25: ='Budget assumption'!M231 -> 0 | N25: =SUM(B25:M25) -> 0 | Q25: =SUMIFS(B25:M25,$B$2:$M$2,$X$3) -> 0 | R25: =SUMIFS(B25:M25,$B$1:$M$1,$Y$3) -> 0
A26: TOTAL OTHERS | B26: =SUM(B21:B25) -> -19 | C26: =SUM(C21:C25) -> -19 | D26: =SUM(D21:D25) -> -20 | E26: =SUM(E21:E25) -> -20 | F26: =SUM(F21:F25) -> -13 | G26: =SUM(G21:G25) -> -24 | H26: =SUM(H21:H25) -> -19 | I26: =SUM(I21:I25) -> -16 | ... M26: =SUM(M21:M25) -> -17 | N26: =SUM(B26:M26) -> -238 | Q26: =SUMIFS(B26:M26,$B$2:$M$2,$X$3) -> -24 | R26: =SUMIFS(B26:M26,$B$1:$M$1,$Y$3) -> -115
A27: IT GLOBAL | B27: ='Budget assumption'!B233 -> 90.697223 | C27: ='Budget assumption'!C233 -> 90.697223 | D27: ='Budget assumption'!D233 -> 90.697223 | E27: ='Budget assumption'!E233 -> 90.697223 | F27: ='Budget assumption'!F233 -> 90.697223 | G27: ='Budget assumption'!G233 -> 90.697223 | H27: ='Budget assumption'!H233 -> 90.697223 | I27: ='Budget assumption'!I233 -> 90.697223 | ... M27: ='Budget assumption'!M233 -> 90.697223 | N27: =SUM(B27:M27) -> 1088.3667 | Q27: =SUMIFS(B27:M27,$B$2:$M$2,$X$3) -> 90.697223 | R27: =SUMIFS(B27:M27,$B$1:$M$1,$Y$3) -> 544.18334
A28: G&A(Insurance included) | B28: ='Budget assumption'!B234 -> 94.532002 | C28: ='Budget assumption'!C234 -> 94.532002 | D28: ='Budget assumption'!D234 -> 94.532002 | E28: ='Budget assumption'!E234 -> 94.532002 | F28: ='Budget assumption'!F234 -> 94.532002 | G28: ='Budget assumption'!G234 -> 94.532002 | H28: ='Budget assumption'!H234 -> 94.532002 | I28: ='Budget assumption'!I234 -> 94.532002 | ... M28: ='Budget assumption'!M234 -> 94.532002 | N28: =SUM(B28:M28) -> 1134.384 | Q28: =SUMIFS(B28:M28,$B$2:$M$2,$X$3) -> 94.532002 | R28: =SUMIFS(B28:M28,$B$1:$M$1,$Y$3) -> 567.19201
A29: TOTAL OVERHEAD | B29: =SUM(B27:B28) -> 185.22922 | C29: =SUM(C27:C28) -> 185.22922 | D29: =SUM(D27:D28) -> 185.22922 | E29: =SUM(E27:E28) -> 185.22922 | F29: =SUM(F27:F28) -> 185.22922 | G29: =SUM(G27:G28) -> 185.22922 | H29: =SUM(H27:H28) -> 185.22922 | I29: =SUM(I27:I28) -> 185.22922 | ... M29: =SUM(M27:M28) -> 185.22922 | N29: =SUM(B29:M29) -> 2222.7507 | Q29: =SUMIFS(B29:M29,$B$2:$M$2,$X$3) -> 185.22922 | R29: =SUMIFS(B29:M29,$B$1:$M$1,$Y$3) -> 1111.3753
N30: =SUM(B30:M30) -> 0 | Q30: =SUMIFS(B30:M30,$B$2:$M$2,$X$3) -> 0 | R30: =SUMIFS(B30:M30,$B$1:$M$1,$Y$3) -> 0
A31: TOTAL ALL | B31: =B20+B26+B29 -> 1839.3083 | C31: =C20+C26+C29 -> 1852.8275 | D31: =D20+D26+D29 -> 1892.6675 | E31: =E20+E26+E29 -> 1849.1004 | F31: =F20+F26+F29 -> 1929.9373 | G31: =G20+G26+G29 -> 1870.4089 | H31: =H20+H26+H29 -> 1858.283 | I31: =I20+I26+I29 -> 1841.6017 | ... M31: =M20+M26+M29 -> 1946.7718 | N31: =SUM(B31:M31) -> 22587.213 | Q31: =SUMIFS(B31:M31,$B$2:$M$2,$X$3) -> 1870.4089 | R31: =SUMIFS(B31:M31,$B$1:$M$1,$Y$3) -> 11234.25
A38: ACE + HWTW+ price +seasonality | B38: Jan | C38: Feb | D38: March | E38: April | F38: May | G38: June | H38: July | I38: August | J38: Sept | K38: Oct | L38: Nov | M38: Dec | N38: Total | Q38: MTD | R38: YTD
A39: Direct Labour | B39: ='Budget assumption'!B118+'Budget assumption'!B149+'Budget assumption'!B180+'Budget assumption'!B242+'Budget assumption'!B273 -> -89.182191 | C39: ='Budget assumption'!C118+'Budget assumption'!C149+'Budget assumption'!C180+'Budget assumption'!C242+'Budget assumption'!C273 -> -49.98876 | D39: ='Budget assumption'!D118+'Budget assumption'!D149+'Budget assumption'!D180+'Budget assumption'!D242+'Budget assumption'!D273 -> -45.000139 | E39: ='Budget assumption'!E118+'Budget assumption'!E149+'Budget assumption'!E180+'Budget assumption'!E242+'Budget assumption'!E273 -> -37.726399 | F39: ='Budget assumption'!F118+'Budget assumption'!F149+'Budget assumption'!F180+'Budget assumption'!F242+'Budget assumption'!F273 -> 160.4158 | G39: ='Budget assumption'!G118+'Budget assumption'!G149+'Budget assumption'!G180+'Budget assumption'!G242+'Budget assumption'!G273 -> -103.06413 | H39: ='Budget assumption'!H118+'Budget assumption'!H149+'Budget assumption'!H180+'Budget assumption'!H242+'Budget assumption'!H273 -> -27.445335 | I39: ='Budget assumption'!I118+'Budget assumption'!I149+'Budget assumption'!I180+'Budget assumption'!I242+'Budget assumption'!I273 -> 14.540301 | ... N39: ='Budget assumption'!N118+'Budget assumption'!N149+'Budget assumption'!N180+'Budget assumption'!N242+'Budget assumption'!N273 -> -351.97905 | Q39: =SUMIFS(B39:M39,$B$2:$M$2,$X$3) -> -103.06413 | R39: =SUMIFS(B39:M39,$B$1:$M$1,$Y$3) -> -164.54582
A40: Variable Utilities | B40: ='Budget assumption'!B119+'Budget assumption'!B150+'Budget assumption'!B181+'Budget assumption'!B243+'Budget assumption'!B274 -> -0.39814539 | C40: ='Budget assumption'!C119+'Budget assumption'!C150+'Budget assumption'!C181+'Budget assumption'!C243+'Budget assumption'!C274 -> -1.3105109 | D40: ='Budget assumption'!D119+'Budget assumption'!D150+'Budget assumption'!D181+'Budget assumption'!D243+'Budget assumption'!D274 -> -0.95802494 | E40: ='Budget assumption'!E119+'Budget assumption'!E150+'Budget assumption'!E181+'Budget assumption'!E243+'Budget assumption'!E274 -> -1.3205572 | F40: ='Budget assumption'!F119+'Budget assumption'!F150+'Budget assumption'!F181+'Budget assumption'!F243+'Budget assumption'!F274 -> -4.3481435 | G40: ='Budget assumption'!G119+'Budget assumption'!G150+'Budget assumption'!G181+'Budget assumption'!G243+'Budget assumption'!G274 -> -5.3136673 | H40: ='Budget assumption'!H119+'Budget assumption'!H150+'Budget assumption'!H181+'Budget assumption'!H243+'Budget assumption'!H274 -> -2.8961328 | I40: ='Budget assumption'!I119+'Budget assumption'!I150+'Budget assumption'!I181+'Budget assumption'!I243+'Budget assumption'!I274 -> 1.0188675 | ... N40: ='Budget assumption'!N119+'Budget assumption'!N150+'Budget assumption'!N181+'Budget assumption'!N243+'Budget assumption'!N274 -> -30.398899 | Q40: =SUMIFS(B40:M40,$B$2:$M$2,$X$3) -> -5.3136673 | R40: =SUMIFS(B40:M40,$B$1:$M$1,$Y$3) -> -13.649049
A41: Variable Costs | B41: ='Budget assumption'!B120+'Budget assumption'!B151+'Budget assumption'!B182+'Budget assumption'!B244+'Budget assumption'!B275 -> -1.0084692 | C41: ='Budget assumption'!C120+'Budget assumption'!C151+'Budget assumption'!C182+'Budget assumption'!C244+'Budget assumption'!C275 -> -1.0024934 | D41: ='Budget assumption'!D120+'Budget assumption'!D151+'Budget assumption'!D182+'Budget assumption'!D244+'Budget assumption'!D275 -> -1.0028449 | E41: ='Budget assumption'!E120+'Budget assumption'!E151+'Budget assumption'!E182+'Budget assumption'!E244+'Budget assumption'!E275 -> -0.99676503 | F41: ='Budget assumption'!F120+'Budget assumption'!F151+'Budget assumption'!F182+'Budget assumption'!F244+'Budget assumption'!F275 -> -1.2205103 | G41: ='Budget assumption'!G120+'Budget assumption'!G151+'Budget assumption'!G182+'Budget assumption'!G244+'Budget assumption'!G275 -> -1.1569124 | H41: ='Budget assumption'!H120+'Budget assumption'!H151+'Budget assumption'!H182+'Budget assumption'!H244+'Budget assumption'!H275 -> -0.56032735 | I41: ='Budget assumption'!I120+'Budget assumption'!I151+'Budget assumption'!I182+'Budget assumption'!I244+'Budget assumption'!I275 -> -0.79428722 | ... N41: ='Budget assumption'!N120+'Budget assumption'!N151+'Budget assumption'!N182+'Budget assumption'!N244+'Budget assumption'!N275 -> -13.581597 | Q41: =SUMIFS(B41:M41,$B$2:$M$2,$X$3) -> -1.1569124 | R41: =SUMIFS(B41:M41,$B$1:$M$1,$Y$3) -> -6.3879953
A42: VARIABLE CONVERSION | B42: =SUM(B39:B41) -> -90.588806 | C42: =SUM(C39:C41) -> -52.301765 | D42: =SUM(D39:D41) -> -46.961009 | E42: =SUM(E39:E41) -> -40.043721 | F42: =SUM(F39:F41) -> 154.84715 | G42: =SUM(G39:G41) -> -109.53471 | H42: =SUM(H39:H41) -> -30.901795 | I42: =SUM(I39:I41) -> 14.764881 | ... N42: =SUM(N39:N41) -> -395.95955 | Q42: =SUMIFS(B42:M42,$B$2:$M$2,$X$3) -> -109.53471 | R42: =SUMIFS(B42:M42,$B$1:$M$1,$Y$3) -> -184.58287
A43: Indirect Labour | B43: ='Budget assumption'!B122+'Budget assumption'!B153+'Budget assumption'!B184+'Budget assumption'!B246+'Budget assumption'!B277 -> -10.542907 | C43: ='Budget assumption'!C122+'Budget assumption'!C153+'Budget assumption'!C184+'Budget assumption'!C246+'Budget assumption'!C277 -> 2.2245259 | D43: ='Budget assumption'!D122+'Budget assumption'!D153+'Budget assumption'!D184+'Budget assumption'!D246+'Budget assumption'!D277 -> 6.6613201 | E43: ='Budget assumption'!E122+'Budget assumption'!E153+'Budget assumption'!E184+'Budget assumption'!E246+'Budget assumption'!E277 -> -10.85718 | F43: ='Budget assumption'!F122+'Budget assumption'!F153+'Budget assumption'!F184+'Budget assumption'!F246+'Budget assumption'!F277 -> 84.780684 | G43: ='Budget assumption'!G122+'Budget assumption'!G153+'Budget assumption'!G184+'Budget assumption'!G246+'Budget assumption'!G277 -> -101.7764 | H43: ='Budget assumption'!H122+'Budget assumption'!H153+'Budget assumption'!H184+'Budget assumption'!H246+'Budget assumption'!H277 -> -6.1783218 | I43: ='Budget assumption'!I122+'Budget assumption'!I153+'Budget assumption'!I184+'Budget assumption'!I246+'Budget assumption'!I277 -> -3.9382299 | ... N43: ='Budget assumption'!N122+'Budget assumption'!N153+'Budget assumption'!N184+'Budget assumption'!N246+'Budget assumption'!N277 -> -308.03119 | Q43: =SUMIFS(B43:M43,$B$2:$M$2,$X$3) -> -101.7764 | R43: =SUMIFS(B43:M43,$B$1:$M$1,$Y$3) -> -29.509956
A44: Fixed Labour | B44: ='Budget assumption'!B123+'Budget assumption'!B154+'Budget assumption'!B185+'Budget assumption'!B247+'Budget assumption'!B278 -> 32.322212 | C44: ='Budget assumption'!C123+'Budget assumption'!C154+'Budget assumption'!C185+'Budget assumption'!C247+'Budget assumption'!C278 -> 38.713702 | D44: ='Budget assumption'!D123+'Budget assumption'!D154+'Budget assumption'!D185+'Budget assumption'!D247+'Budget assumption'!D278 -> 28.384742 | E44: ='Budget assumption'!E123+'Budget assumption'!E154+'Budget assumption'!E185+'Budget assumption'!E247+'Budget assumption'!E278 -> 26.357974 | F44: ='Budget assumption'!F123+'Budget assumption'!F154+'Budget assumption'!F185+'Budget assumption'!F247+'Budget assumption'!F278 -> 58.777722 | G44: ='Budget assumption'!G123+'Budget assumption'!G154+'Budget assumption'!G185+'Budget assumption'!G247+'Budget assumption'!G278 -> -7.7951589 | H44: ='Budget assumption'!H123+'Budget assumption'!H154+'Budget assumption'!H185+'Budget assumption'!H247+'Budget assumption'!H278 -> 7.2383097 | I44: ='Budget assumption'!I123+'Budget assumption'!I154+'Budget assumption'!I185+'Budget assumption'!I247+'Budget assumption'!I278 -> 17.188109 | ... N44: ='Budget assumption'!N123+'Budget assumption'!N154+'Budget assumption'!N185+'Budget assumption'!N247+'Budget assumption'!N278 -> 160.88421 | Q44: =SUMIFS(B44:M44,$B$2:$M$2,$X$3) -> -7.7951589 | R44: =SUMIFS(B44:M44,$B$1:$M$1,$Y$3) -> 176.76119
A45: Semifixed | B45: ='Budget assumption'!B124+'Budget assumption'!B155+'Budget assumption'!B186+'Budget assumption'!B248+'Budget assumption'!B279 -> 39.663885 | C45: ='Budget assumption'!C124+'Budget assumption'!C155+'Budget assumption'!C186+'Budget assumption'!C248+'Budget assumption'!C279 -> 36.46932 | D45: ='Budget assumption'!D124+'Budget assumption'!D155+'Budget assumption'!D186+'Budget assumption'!D248+'Budget assumption'!D279 -> 33.33433 | E45: ='Budget assumption'!E124+'Budget assumption'!E155+'Budget assumption'!E186+'Budget assumption'!E248+'Budget assumption'!E279 -> 26.665011 | F45: ='Budget assumption'!F124+'Budget assumption'!F155+'Budget assumption'!F186+'Budget assumption'!F248+'Budget assumption'!F279 -> 55.35401 | G45: ='Budget assumption'!G124+'Budget assumption'!G155+'Budget assumption'!G186+'Budget assumption'!G248+'Budget assumption'!G279 -> -34.461693 | H45: ='Budget assumption'!H124+'Budget assumption'!H155+'Budget assumption'!H186+'Budget assumption'!H248+'Budget assumption'!H279 -> -1.4123817 | I45: ='Budget assumption'!I124+'Budget assumption'!I155+'Budget assumption'!I186+'Budget assumption'!I248+'Budget assumption'!I279 -> 8.9881641 | ... N45: ='Budget assumption'!N124+'Budget assumption'!N155+'Budget assumption'!N186+'Budget assumption'!N248+'Budget assumption'!N279 -> 54.22 | Q45: =SUMIFS(B45:M45,$B$2:$M$2,$X$3) -> -34.461693 | R45: =SUMIFS(B45:M45,$B$1:$M$1,$Y$3) -> 157.02486
A46: Fixed utilities | B46: ='Budget assumption'!B125+'Budget assumption'!B156+'Budget assumption'!B187+'Budget assumption'!B249+'Budget assumption'!B280 -> -4.1207173 | C46: ='Budget assumption'!C125+'Budget assumption'!C156+'Budget assumption'!C187+'Budget assumption'!C249+'Budget assumption'!C280 -> -3.1207173 | D46: ='Budget assumption'!D125+'Budget assumption'!D156+'Budget assumption'!D187+'Budget assumption'!D249+'Budget assumption'!D280 -> -3.1207173 | E46: ='Budget assumption'!E125+'Budget assumption'!E156+'Budget assumption'!E187+'Budget assumption'!E249+'Budget assumption'!E280 -> -4.5767532 | F46: ='Budget assumption'!F125+'Budget assumption'!F156+'Budget assumption'!F187+'Budget assumption'!F249+'Budget assumption'!F280 -> -2.3845021 | G46: ='Budget assumption'!G125+'Budget assumption'!G156+'Budget assumption'!G187+'Budget assumption'!G249+'Budget assumption'!G280 -> -8.1767671 | H46: ='Budget assumption'!H125+'Budget assumption'!H156+'Budget assumption'!H187+'Budget assumption'!H249+'Budget assumption'!H280 -> -6.4504657 | I46: ='Budget assumption'!I125+'Budget assumption'!I156+'Budget assumption'!I187+'Budget assumption'!I249+'Budget assumption'!I280 -> -6.3599452 | ... N46: ='Budget assumption'!N125+'Budget assumption'!N156+'Budget assumption'!N187+'Budget assumption'!N249+'Budget assumption'!N280 -> -67.7 | Q46: =SUMIFS(B46:M46,$B$2:$M$2,$X$3) -> -8.1767671 | R46: =SUMIFS(B46:M46,$B$1:$M$1,$Y$3) -> -25.500174
A47: Fixed Cost | B47: ='Budget assumption'!B126+'Budget assumption'!B157+'Budget assumption'!B188+'Budget assumption'!B250+'Budget assumption'!B281 -> 12.859893 | C47: ='Budget assumption'!C126+'Budget assumption'!C157+'Budget assumption'!C188+'Budget assumption'!C250+'Budget assumption'!C281 -> 12.261789 | D47: ='Budget assumption'!D126+'Budget assumption'!D157+'Budget assumption'!D188+'Budget assumption'!D250+'Budget assumption'!D281 -> 11.674837 | E47: ='Budget assumption'!E126+'Budget assumption'!E157+'Budget assumption'!E188+'Budget assumption'!E250+'Budget assumption'!E281 -> 9.6182841 | F47: ='Budget assumption'!F126+'Budget assumption'!F157+'Budget assumption'!F188+'Budget assumption'!F250+'Budget assumption'!F281 -> 20.368624 | G47: ='Budget assumption'!G126+'Budget assumption'!G157+'Budget assumption'!G188+'Budget assumption'!G250+'Budget assumption'!G281 -> -5.9139603 | H47: ='Budget assumption'!H126+'Budget assumption'!H157+'Budget assumption'!H188+'Budget assumption'!H250+'Budget assumption'!H281 -> 1.9169003 | I47: ='Budget assumption'!I126+'Budget assumption'!I157+'Budget assumption'!I188+'Budget assumption'!I250+'Budget assumption'!I281 -> 5.5104257 | ... N47: ='Budget assumption'!N126+'Budget assumption'!N157+'Budget assumption'!N188+'Budget assumption'!N250+'Budget assumption'!N281 -> 44.020248 | Q47: =SUMIFS(B47:M47,$B$2:$M$2,$X$3) -> -5.9139603 | R47: =SUMIFS(B47:M47,$B$1:$M$1,$Y$3) -> 60.869468
A48: Depreciation | B48: ='Budget assumption'!B127+'Budget assumption'!B158+'Budget assumption'!B189+'Budget assumption'!B251+'Budget assumption'!B282 -> 36.505165 | C48: ='Budget assumption'!C127+'Budget assumption'!C158+'Budget assumption'!C189+'Budget assumption'!C251+'Budget assumption'!C282 -> 24.306514 | D48: ='Budget assumption'!D127+'Budget assumption'!D158+'Budget assumption'!D189+'Budget assumption'!D251+'Budget assumption'!D282 -> 35.072092 | E48: ='Budget assumption'!E127+'Budget assumption'!E158+'Budget assumption'!E189+'Budget assumption'!E251+'Budget assumption'!E282 -> 23.541396 | F48: ='Budget assumption'!F127+'Budget assumption'!F158+'Budget assumption'!F189+'Budget assumption'!F251+'Budget assumption'!F282 -> 67.919042 | G48: ='Budget assumption'!G127+'Budget assumption'!G158+'Budget assumption'!G189+'Budget assumption'!G251+'Budget assumption'!G282 -> -41.865138 | H48: ='Budget assumption'!H127+'Budget assumption'!H158+'Budget assumption'!H189+'Budget assumption'!H251+'Budget assumption'!H282 -> 13.994285 | I48: ='Budget assumption'!I127+'Budget assumption'!I158+'Budget assumption'!I189+'Budget assumption'!I251+'Budget assumption'!I282 -> 27.979342 | ... N48: ='Budget assumption'!N127+'Budget assumption'!N158+'Budget assumption'!N189+'Budget assumption'!N251+'Budget assumption'!N282 -> 119.21 | Q48: =SUMIFS(B48:M48,$B$2:$M$2,$X$3) -> -41.865138 | R48: =SUMIFS(B48:M48,$B$1:$M$1,$Y$3) -> 145.47907
A49: FIXED CONVERSION | B49: =SUM(B43:B48) -> 106.68753 | C49: =SUM(C43:C48) -> 110.85514 | D49: =SUM(D43:D48) -> 112.0066 | E49: =SUM(E43:E48) -> 70.748731 | F49: =SUM(F43:F48) -> 284.81558 | G49: =SUM(G43:G48) -> -199.98912 | H49: =SUM(H43:H48) -> 9.1083261 | I49: =SUM(I43:I48) -> 49.367866 | ... N49: =SUM(N43:N48) -> 2.6032609 | Q49: =SUMIFS(B49:M49,$B$2:$M$2,$X$3) -> -199.98912 | R49: =SUMIFS(B49:M49,$B$1:$M$1,$Y$3) -> 485.12446
A50: TOTAL MFG COST w/o SHARES | B50: =B42+B49 -> 16.098725 | C50: =C42+C49 -> 58.55337 | D50: =D42+D49 -> 65.045596 | E50: =E42+E49 -> 30.70501 | F50: =F42+F49 -> 439.66273 | G50: =G42+G49 -> -309.52383 | H50: =H42+H49 -> -21.793469 | I50: =I42+I49 -> 64.132748 | ... N50: =N42+N49 -> -393.35629 | Q50: =SUMIFS(B50:M50,$B$2:$M$2,$X$3) -> -309.52383 | R50: =SUMIFS(B50:M50,$B$1:$M$1,$Y$3) -> 300.5416
A51: TOTAL SHARES | B51: ='Budget assumption'!B130+'Budget assumption'!B161+'Budget assumption'!B192+'Budget assumption'!B254+'Budget assumption'!B285 -> 12.908069 | C51: ='Budget assumption'!C130+'Budget assumption'!C161+'Budget assumption'!C192+'Budget assumption'!C254+'Budget assumption'!C285 -> 12.984894 | D51: ='Budget assumption'!D130+'Budget assumption'!D161+'Budget assumption'!D192+'Budget assumption'!D254+'Budget assumption'!D285 -> 12.707935 | E51: ='Budget assumption'!E130+'Budget assumption'!E161+'Budget assumption'!E192+'Budget assumption'!E254+'Budget assumption'!E285 -> 11.930867 | F51: ='Budget assumption'!F130+'Budget assumption'!F161+'Budget assumption'!F192+'Budget assumption'!F254+'Budget assumption'!F285 -> 15.261027 | G51: ='Budget assumption'!G130+'Budget assumption'!G161+'Budget assumption'!G192+'Budget assumption'!G254+'Budget assumption'!G285 -> 7.6901145 | H51: ='Budget assumption'!H130+'Budget assumption'!H161+'Budget assumption'!H192+'Budget assumption'!H254+'Budget assumption'!H285 -> 9.8915375 | I51: ='Budget assumption'!I130+'Budget assumption'!I161+'Budget assumption'!I192+'Budget assumption'!I254+'Budget assumption'!I285 -> 10.696422 | ... N51: ='Budget assumption'!N130+'Budget assumption'!N161+'Budget assumption'!N192+'Budget assumption'!N254+'Budget assumption'!N285 -> 124.89558 | Q51: =SUMIFS(B51:M51,$B$2:$M$2,$X$3) -> 7.6901145 | R51: =SUMIFS(B51:M51,$B$1:$M$1,$Y$3) -> 73.482907
A52: TOTAL MFG COST w/ SHARES | B52: =B50+B51 -> 29.006794 | C52: =C50+C51 -> 71.538265 | D52: =D50+D51 -> 77.753531 | E52: =E50+E51 -> 42.635877 | F52: =F50+F51 -> 454.92375 | G52: =G50+G51 -> -301.83372 | H52: =H50+H51 -> -11.901932 | I52: =I50+I51 -> 74.82917 | ... N52: =N50+N51 -> -268.46071 | Q52: =SUMIFS(B52:M52,$B$2:$M$2,$X$3) -> -301.83372 | R52: =SUMIFS(B52:M52,$B$1:$M$1,$Y$3) -> 374.0245
A53: Functional Currency Impact | B53: ='Budget assumption'!B132+'Budget assumption'!B163+'Budget assumption'!B194+'Budget assumption'!B256+'Budget assumption'!B287 -> 71.312162 | C53: ='Budget assumption'!C132+'Budget assumption'!C163+'Budget assumption'!C194+'Budget assumption'!C256+'Budget assumption'!C287 -> 42.512443 | D53: ='Budget assumption'!D132+'Budget assumption'!D163+'Budget assumption'!D194+'Budget assumption'!D256+'Budget assumption'!D287 -> 77.124682 | E53: ='Budget assumption'!E132+'Budget assumption'!E163+'Budget assumption'!E194+'Budget assumption'!E256+'Budget assumption'!E287 -> 51.543756 | F53: ='Budget assumption'!F132+'Budget assumption'!F163+'Budget assumption'!F194+'Budget assumption'!F256+'Budget assumption'!F287 -> 183.55211 | G53: ='Budget assumption'!G132+'Budget assumption'!G163+'Budget assumption'!G194+'Budget assumption'!G256+'Budget assumption'!G287 -> -118.92816 | H53: ='Budget assumption'!H132+'Budget assumption'!H163+'Budget assumption'!H194+'Budget assumption'!H256+'Budget assumption'!H287 -> -4.2216047 | I53: ='Budget assumption'!I132+'Budget assumption'!I163+'Budget assumption'!I194+'Budget assumption'!I256+'Budget assumption'!I287 -> 38.227599 | ... N53: ='Budget assumption'!N132+'Budget assumption'!N163+'Budget assumption'!N194+'Budget assumption'!N256+'Budget assumption'!N287 -> 9.094947e-13 | Q53: =SUMIFS(B53:M53,$B$2:$M$2,$X$3) -> -118.92816 | R53: =SUMIFS(B53:M53,$B$1:$M$1,$Y$3) -> 307.11699
A54: TOTAL Including FC | B54: =B52+B53 -> 100.31896 | C54: =C52+C53 -> 114.05071 | D54: =D52+D53 -> 154.87821 | E54: =E52+E53 -> 94.179633 | F54: =F52+F53 -> 638.47586 | G54: =G52+G53 -> -420.76188 | H54: =H52+H53 -> -16.123537 | I54: =I52+I53 -> 113.05677 | ... N54: =N52+N53 -> -268.46071 | Q54: =SUMIFS(B54:M54,$B$2:$M$2,$X$3) -> -420.76188 | R54: =SUMIFS(B54:M54,$B$1:$M$1,$Y$3) -> 681.14149
A55: Scrap | B55: ='Budget assumption'!B134+'Budget assumption'!B165+'Budget assumption'!B196+'Budget assumption'!B258+'Budget assumption'!B289 -> 1.7464607 | C55: ='Budget assumption'!C134+'Budget assumption'!C165+'Budget assumption'!C196+'Budget assumption'!C258+'Budget assumption'!C289 -> 1.7549681 | D55: ='Budget assumption'!D134+'Budget assumption'!D165+'Budget assumption'!D196+'Budget assumption'!D258+'Budget assumption'!D289 -> 1.7544677 | E55: ='Budget assumption'!E134+'Budget assumption'!E165+'Budget assumption'!E196+'Budget assumption'!E258+'Budget assumption'!E289 -> -5.0459855 | F55: ='Budget assumption'!F134+'Budget assumption'!F165+'Budget assumption'!F196+'Budget assumption'!F258+'Budget assumption'!F289 -> -3.4100669 | G55: ='Budget assumption'!G134+'Budget assumption'!G165+'Budget assumption'!G196+'Budget assumption'!G258+'Budget assumption'!G289 -> -5.6557631 | H55: ='Budget assumption'!H134+'Budget assumption'!H165+'Budget assumption'!H196+'Budget assumption'!H258+'Budget assumption'!H289 -> -4.0428646 | I55: ='Budget assumption'!I134+'Budget assumption'!I165+'Budget assumption'!I196+'Budget assumption'!I258+'Budget assumption'!I289 -> -3.5920985 | ... N55: ='Budget assumption'!N134+'Budget assumption'!N165+'Budget assumption'!N196+'Budget assumption'!N258+'Budget assumption'!N289 -> -35.757769 | Q55: =SUMIFS(B55:M55,$B$2:$M$2,$X$3) -> -5.6557631 | R55: =SUMIFS(B55:M55,$B$1:$M$1,$Y$3) -> -8.8559189
A56: Scrap Reselling | B56: ='Budget assumption'!B135+'Budget assumption'!B166+'Budget assumption'!B197+'Budget assumption'!B259+'Budget assumption'!B290 -> 7.06949 | C56: ='Budget assumption'!C135+'Budget assumption'!C166+'Budget assumption'!C197+'Budget assumption'!C259+'Budget assumption'!C290 -> 7.04858 | D56: ='Budget assumption'!D135+'Budget assumption'!D166+'Budget assumption'!D197+'Budget assumption'!D259+'Budget assumption'!D290 -> 6.04981 | E56: ='Budget assumption'!E135+'Budget assumption'!E166+'Budget assumption'!E197+'Budget assumption'!E259+'Budget assumption'!E290 -> 11.1015 | F56: ='Budget assumption'!F135+'Budget assumption'!F166+'Budget assumption'!F197+'Budget assumption'!F259+'Budget assumption'!F290 -> 9.24924 | G56: ='Budget assumption'!G135+'Budget assumption'!G166+'Budget assumption'!G197+'Budget assumption'!G259+'Budget assumption'!G290 -> 12.51595 | H56: ='Budget assumption'!H135+'Budget assumption'!H166+'Budget assumption'!H197+'Budget assumption'!H259+'Budget assumption'!H290 -> 7.72027 | I56: ='Budget assumption'!I135+'Budget assumption'!I166+'Budget assumption'!I197+'Budget assumption'!I259+'Budget assumption'!I290 -> 8.1545 | ... N56: ='Budget assumption'!N135+'Budget assumption'!N166+'Budget assumption'!N197+'Budget assumption'!N259+'Budget assumption'!N290 -> 109.97706 | Q56: =SUMIFS(B56:M56,$B$2:$M$2,$X$3) -> 12.51595 | R56: =SUMIFS(B56:M56,$B$1:$M$1,$Y$3) -> 53.03457
A57: Other Variable (Inventory Adj) | B57: ='Budget assumption'!B136+'Budget assumption'!B167+'Budget assumption'!B198+'Budget assumption'!B260+'Budget assumption'!B291 -> 0 | C57: ='Budget assumption'!C136+'Budget assumption'!C167+'Budget assumption'!C198+'Budget assumption'!C260+'Budget assumption'!C291 -> 0 | D57: ='Budget assumption'!D136+'Budget assumption'!D167+'Budget assumption'!D198+'Budget assumption'!D260+'Budget assumption'!D291 -> 0 | E57: ='Budget assumption'!E136+'Budget assumption'!E167+'Budget assumption'!E198+'Budget assumption'!E260+'Budget assumption'!E291 -> 0 | F57: ='Budget assumption'!F136+'Budget assumption'!F167+'Budget assumption'!F198+'Budget assumption'!F260+'Budget assumption'!F291 -> 0 | G57: ='Budget assumption'!G136+'Budget assumption'!G167+'Budget assumption'!G198+'Budget assumption'!G260+'Budget assumption'!G291 -> 0 | H57: ='Budget assumption'!H136+'Budget assumption'!H167+'Budget assumption'!H198+'Budget assumption'!H260+'Budget assumption'!H291 -> 0 | I57: ='Budget assumption'!I136+'Budget assumption'!I167+'Budget assumption'!I198+'Budget assumption'!I260+'Budget assumption'!I291 -> 0 | ... N57: ='Budget assumption'!N136+'Budget assumption'!N167+'Budget assumption'!N198+'Budget assumption'!N260+'Budget assumption'!N291 -> 0 | Q57: =SUMIFS(B57:M57,$B$2:$M$2,$X$3) -> 0 | R57: =SUMIFS(B57:M57,$B$1:$M$1,$Y$3) -> 0
A58: Obsolete | B58: ='Budget assumption'!B137+'Budget assumption'!B168+'Budget assumption'!B199+'Budget assumption'!B261+'Budget assumption'!B292 -> 9 | C58: ='Budget assumption'!C137+'Budget assumption'!C168+'Budget assumption'!C199+'Budget assumption'!C261+'Budget assumption'!C292 -> 9 | D58: ='Budget assumption'!D137+'Budget assumption'!D168+'Budget assumption'!D199+'Budget assumption'!D261+'Budget assumption'!D292 -> 9 | E58: ='Budget assumption'!E137+'Budget assumption'!E168+'Budget assumption'!E199+'Budget assumption'!E261+'Budget assumption'!E292 -> 9 | F58: ='Budget assumption'!F137+'Budget assumption'!F168+'Budget assumption'!F199+'Budget assumption'!F261+'Budget assumption'!F292 -> 8 | G58: ='Budget assumption'!G137+'Budget assumption'!G168+'Budget assumption'!G199+'Budget assumption'!G261+'Budget assumption'!G292 -> 8 | H58: ='Budget assumption'!H137+'Budget assumption'!H168+'Budget assumption'!H199+'Budget assumption'!H261+'Budget assumption'!H292 -> 8 | I58: ='Budget assumption'!I137+'Budget assumption'!I168+'Budget assumption'!I199+'Budget assumption'!I261+'Budget assumption'!I292 -> 8 | ... N58: ='Budget assumption'!N137+'Budget assumption'!N168+'Budget assumption'!N199+'Budget assumption'!N261+'Budget assumption'!N292 -> 100 | Q58: =SUMIFS(B58:M58,$B$2:$M$2,$X$3) -> 8 | R58: =SUMIFS(B58:M58,$B$1:$M$1,$Y$3) -> 52
A59: Asset Sales | B59: ='Budget assumption'!B138+'Budget assumption'!B169+'Budget assumption'!B200+'Budget assumption'!B262+'Budget assumption'!B293 -> 0 | C59: ='Budget assumption'!C138+'Budget assumption'!C169+'Budget assumption'!C200+'Budget assumption'!C262+'Budget assumption'!C293 -> 0 | D59: ='Budget assumption'!D138+'Budget assumption'!D169+'Budget assumption'!D200+'Budget assumption'!D262+'Budget assumption'!D293 -> 0 | E59: ='Budget assumption'!E138+'Budget assumption'!E169+'Budget assumption'!E200+'Budget assumption'!E262+'Budget assumption'!E293 -> 0 | F59: ='Budget assumption'!F138+'Budget assumption'!F169+'Budget assumption'!F200+'Budget assumption'!F262+'Budget assumption'!F293 -> 0 | G59: ='Budget assumption'!G138+'Budget assumption'!G169+'Budget assumption'!G200+'Budget assumption'!G262+'Budget assumption'!G293 -> 0 | H59: ='Budget assumption'!H138+'Budget assumption'!H169+'Budget assumption'!H200+'Budget assumption'!H262+'Budget assumption'!H293 -> 0 | I59: ='Budget assumption'!I138+'Budget assumption'!I169+'Budget assumption'!I200+'Budget assumption'!I262+'Budget assumption'!I293 -> 0 | ... N59: ='Budget assumption'!N138+'Budget assumption'!N169+'Budget assumption'!N200+'Budget assumption'!N262+'Budget assumption'!N293 -> 0 | Q59: =SUMIFS(B59:M59,$B$2:$M$2,$X$3) -> 0 | R59: =SUMIFS(B59:M59,$B$1:$M$1,$Y$3) -> 0
A60: TOTAL OTHERS | B60: =SUM(B55:B59) -> 17.815951 | C60: =SUM(C55:C59) -> 17.803548 | D60: =SUM(D55:D59) -> 16.804278 | E60: =SUM(E55:E59) -> 15.055515 | F60: =SUM(F55:F59) -> 13.839173 | G60: =SUM(G55:G59) -> 14.860187 | H60: =SUM(H55:H59) -> 11.677405 | I60: =SUM(I55:I59) -> 12.562402 | ... N60: =SUM(N55:N59) -> 174.21929 | Q60: =SUMIFS(B60:M60,$B$2:$M$2,$X$3) -> 14.860187 | R60: =SUMIFS(B60:M60,$B$1:$M$1,$Y$3) -> 96.178651
A61: IT GLOBAL | B61: ='Budget assumption'!B140+'Budget assumption'!B171+'Budget assumption'!B202+'Budget assumption'!B264+'Budget assumption'!B295 -> 11.164158 | C61: ='Budget assumption'!C140+'Budget assumption'!C171+'Budget assumption'!C202+'Budget assumption'!C264+'Budget assumption'!C295 -> 11.164158 | D61: ='Budget assumption'!D140+'Budget assumption'!D171+'Budget assumption'!D202+'Budget assumption'!D264+'Budget assumption'!D295 -> 11.164158 | E61: ='Budget assumption'!E140+'Budget assumption'!E171+'Budget assumption'!E202+'Budget assumption'!E264+'Budget assumption'!E295 -> 7.1875052 | F61: ='Budget assumption'!F140+'Budget assumption'!F171+'Budget assumption'!F202+'Budget assumption'!F264+'Budget assumption'!F295 -> 35.024078 | G61: ='Budget assumption'!G140+'Budget assumption'!G171+'Budget assumption'!G202+'Budget assumption'!G264+'Budget assumption'!G295 -> -32.924823 | H61: ='Budget assumption'!H140+'Budget assumption'!H171+'Budget assumption'!H202+'Budget assumption'!H264+'Budget assumption'!H295 -> -9.1513526 | I61: ='Budget assumption'!I140+'Budget assumption'!I171+'Budget assumption'!I202+'Budget assumption'!I264+'Budget assumption'!I295 -> 0.35803554 | ... N61: ='Budget assumption'!N140+'Budget assumption'!N171+'Budget assumption'!N202+'Budget assumption'!N264+'Budget assumption'!N295 -> -77.50333 | Q61: =SUMIFS(B61:M61,$B$2:$M$2,$X$3) -> -32.924823 | R61: =SUMIFS(B61:M61,$B$1:$M$1,$Y$3) -> 42.779235
A62: G&A(Insurance included) | B62: ='Budget assumption'!B141+'Budget assumption'!B172+'Budget assumption'!B203+'Budget assumption'!B265+'Budget assumption'!B296 -> 27.352496 | C62: ='Budget assumption'!C141+'Budget assumption'!C172+'Budget assumption'!C203+'Budget assumption'!C265+'Budget assumption'!C296 -> 27.352496 | D62: ='Budget assumption'!D141+'Budget assumption'!D172+'Budget assumption'!D203+'Budget assumption'!D265+'Budget assumption'!D296 -> 27.352496 | E62: ='Budget assumption'!E141+'Budget assumption'!E172+'Budget assumption'!E203+'Budget assumption'!E265+'Budget assumption'!E296 -> 23.993521 | F62: ='Budget assumption'!F141+'Budget assumption'!F172+'Budget assumption'!F203+'Budget assumption'!F265+'Budget assumption'!F296 -> 47.506348 | G62: ='Budget assumption'!G141+'Budget assumption'!G172+'Budget assumption'!G203+'Budget assumption'!G265+'Budget assumption'!G296 -> -9.8883173 | H62: ='Budget assumption'!H141+'Budget assumption'!H172+'Budget assumption'!H203+'Budget assumption'!H265+'Budget assumption'!H296 -> 10.192513 | I62: ='Budget assumption'!I141+'Budget assumption'!I172+'Budget assumption'!I203+'Budget assumption'!I265+'Budget assumption'!I296 -> 18.224846 | ... N62: ='Budget assumption'!N141+'Budget assumption'!N172+'Budget assumption'!N203+'Budget assumption'!N265+'Budget assumption'!N296 -> 149.60403 | Q62: =SUMIFS(B62:M62,$B$2:$M$2,$X$3) -> -9.8883173 | R62: =SUMIFS(B62:M62,$B$1:$M$1,$Y$3) -> 143.66904
A63: TOTAL OVERHEAD | B63: =SUM(B61:B62) -> 38.516654 | C63: =SUM(C61:C62) -> 38.516654 | D63: =SUM(D61:D62) -> 38.516654 | E63: =SUM(E61:E62) -> 31.181026 | F63: =SUM(F61:F62) -> 82.530425 | G63: =SUM(G61:G62) -> -42.81314 | H63: =SUM(H61:H62) -> 1.0411608 | I63: =SUM(I61:I62) -> 18.582881 | ... N63: =SUM(N61:N62) -> 72.100696 | Q63: =SUMIFS(B63:M63,$B$2:$M$2,$X$3) -> -42.81314 | R63: =SUMIFS(B63:M63,$B$1:$M$1,$Y$3) -> 186.44827
Q64: =SUMIFS(B64:M64,$B$2:$M$2,$X$3) -> 0 | R64: =SUMIFS(B64:M64,$B$1:$M$1,$Y$3) -> 0
A65: TOTAL ALL | B65: =B54+B60+B63 -> 156.65156 | C65: =C54+C60+C63 -> 170.37091 | D65: =D54+D60+D63 -> 210.19915 | E65: =E54+E60+E63 -> 140.41617 | F65: =F54+F60+F63 -> 734.84546 | G65: =G54+G60+G63 -> -448.71483 | H65: =H54+H60+H63 -> -3.4049703 | I65: =I54+I60+I63 -> 144.20205 | ... N65: =N54+N60+N63 -> -22.14072 | Q65: =SUMIFS(B65:M65,$B$2:$M$2,$X$3) -> -448.71483 | R65: =SUMIFS(B65:M65,$B$1:$M$1,$Y$3) -> 963.76842
A71: Budget Variances | B71: Jan | C71: Feb | D71: March | E71: April | F71: May | G71: June | H71: July | I71: August | J71: Sept | K71: Oct | L71: Nov | M71: Dec | N71: Total
A72: ='Budget assumption'!A316 -> mfg vs upload | B72: ='Budget assumption'!B316 -> 0 | C72: ='Budget assumption'!C316 -> 0 | D72: ='Budget assumption'!D316 -> 0 | E72: ='Budget assumption'!E316 -> 0 | F72: ='Budget assumption'!F316 -> 0 | G72: ='Budget assumption'!G316 -> 0 | H72: ='Budget assumption'!H316 -> 0 | ... N72: ='Budget assumption'!N316 -> 0 | Q72: =SUMIFS(B72:M72,$B$2:$M$2,$X$3) -> 0 | R72: =SUMIFS(B72:M72,$B$1:$M$1,$Y$3) -> 0
A73: ACE | B73: ='Budget assumption'!B306 -> -6.7443971 | C73: ='Budget assumption'!C306 -> -7.1106746 | D73: ='Budget assumption'!D306 -> -7.1575234 | E73: ='Budget assumption'!E306 -> -13.784256 | F73: ='Budget assumption'!F306 -> -22.49989 | G73: ='Budget assumption'!G306 -> -58.908533 | H73: ='Budget assumption'!H306 -> -57.523255 | I73: ='Budget assumption'!I306 -> -57.204808 | ... N73: ='Budget assumption'!N306 -> -484 | Q73: =SUMIFS(B73:M73,$B$2:$M$2,$X$3) -> -58.908533 | R73: =SUMIFS(B73:M73,$B$1:$M$1,$Y$3) -> -116.20527
A74: HWTW | B74: ='Budget assumption'!B308 -> -67.734714 | C74: ='Budget assumption'!C308 -> -136.5981 | D74: ='Budget assumption'!D308 -> -106.87028 | E74: ='Budget assumption'!E308 -> -47.120574 | F74: ='Budget assumption'!F308 -> -70.370518 | G74: ='Budget assumption'!G308 -> -71.974601 | H74: ='Budget assumption'!H308 -> -11.001751 | I74: ='Budget assumption'!I308 -> -7.4535707 | ... N74: ='Budget assumption'!N308 -> -605.66 | Q74: =SUMIFS(B74:M74,$B$2:$M$2,$X$3) -> -71.974601 | R74: =SUMIFS(B74:M74,$B$1:$M$1,$Y$3) -> -500.66879
A75: Price & FX | B75: ='Budget assumption'!B307 -> 97.042645 | C75: ='Budget assumption'!C307 -> 95.204836 | D75: ='Budget assumption'!D307 -> 141.08906 | E75: ='Budget assumption'!E307 -> 167.09298 | F75: ='Budget assumption'!F307 -> 147.51309 | G75: ='Budget assumption'!G307 -> 62.061657 | H75: ='Budget assumption'!H307 -> -45.22542 | I75: ='Budget assumption'!I307 -> -65.234865 | ... N75: ='Budget assumption'!N307 -> 944.58031 | Q75: =SUMIFS(B75:M75,$B$2:$M$2,$X$3) -> 62.061657 | R75: =SUMIFS(B75:M75,$B$1:$M$1,$Y$3) -> 710.00426
A76: FCA | B76: ='Budget assumption'!B310 -> -105.62146 | C76: ='Budget assumption'!C310 -> -105.21914 | D76: ='Budget assumption'!D310 -> -105.24281 | E76: ='Budget assumption'!E310 -> 5.9165059 | F76: ='Budget assumption'!F310 -> -108.57972 | G76: ='Budget assumption'!G310 -> 431.54994 | H76: ='Budget assumption'!H310 -> 371.58024 | I76: ='Budget assumption'!I310 -> 310.02491 | ... N76: ='Budget assumption'!N310 -> 2586.436 | Q76: =SUMIFS(B76:M76,$B$2:$M$2,$X$3) -> 431.54994 | R76: =SUMIFS(B76:M76,$B$1:$M$1,$Y$3) -> 12.803319
A77: seasonlaity | B77: ='Budget assumption'!B309 -> 134.08803 | C77: ='Budget assumption'!C309 -> 218.87485 | D77: ='Budget assumption'!D309 -> 183.13789 | E77: ='Budget assumption'!E309 -> 34.228026 | F77: ='Budget assumption'!F309 -> 680.20278 | G77: ='Budget assumption'!G309 -> -379.89335 | H77: ='Budget assumption'!H309 -> 110.34546 | I77: ='Budget assumption'!I309 -> 274.0953 | ... N77: ='Budget assumption'!N309 -> 122.93897 | Q77: =SUMIFS(B77:M77,$B$2:$M$2,$X$3) -> -379.89335 | R77: =SUMIFS(B77:M77,$B$1:$M$1,$Y$3) -> 870.63822
A78: round 2 var | B78: =SUM(B72:B77) -> 51.030098 | C78: =SUM(C72:C77) -> 65.151769 | D78: =SUM(D72:D77) -> 104.95634 | E78: =SUM(E72:E77) -> 146.33268 | F78: =SUM(F72:F77) -> 626.26574 | G78: =SUM(G72:G77) -> -17.164891 | H78: =SUM(H72:H77) -> 368.17527 | I78: =SUM(I72:I77) -> 454.22696 | ... N78: =SUM(N72:N77) -> 2564.2953 | Q78: =SUMIFS(B78:M78,$B$2:$M$2,$X$3) -> -17.164891 | R78: =SUMIFS(B78:M78,$B$1:$M$1,$Y$3) -> 976.57174
D81: 5 | E81: 6 | F81: 7 | G81: 8 | H81: 9 | I81: 10 | J81: 11 | K81: 12 | L81: 13 | M81: 14
A82: Volume | B82: =+VOLUME!C7 -> 47357 | C82: =+VOLUME!D7 -> 42593 | D82: =+VOLUME!E7 -> 23002 | E82: =+VOLUME!F7 -> 40893 | F82: =+VOLUME!G7 -> 33043 | G82: =+VOLUME!H7 -> 53186 | H82: =+VOLUME!I7 -> 41500 | I82: =+VOLUME!J7 -> 39000 | ... N82: =+VOLUME!O7 -> 518285 | Q82: =SUMIFS(B82:M82,$B$2:$M$2,$X$3) -> 53186 | R82: =SUMIFS(B82:M82,$B$1:$M$1,$Y$3) -> 240074
A83: Copertura | B83: Jan | C83: Feb | D83: March | E83: April | F83: May | G83: June | H83: July | I83: August | J83: Sept | K83: Oct | L83: Nov | M83: Dec | N83: Total | Q83: MTD | R83: YTD
A84: Direct Labour | B84: 536.4458 | C84: 482.03678 | D84: 276.12312 | E84: 465.28736 | F84: 379.06259 | G84: 598.40414 | H84: 475.70902 | I84: 446.96376 | J84: 619.9682 | K84: 567.30016 | L84: 597.65226 | M84: 485.5004 | N84: =SUM(B84:M84) -> 5930.4536 | Q84: =SUMIFS(B84:M84,$B$2:$M$2,$X$3) -> 598.40414 | R84: =SUMIFS(B84:M84,$B$1:$M$1,$Y$3) -> 2737.3598
A85: Variable Utilities | B85: 35.686211 | C85: 32.002356 | D85: 18.351187 | E85: 30.915274 | F85: 25.227419 | G85: 39.841032 | H85: 31.658026 | I85: 29.744716 | J85: 41.258346 | K85: 37.752909 | L85: 39.782115 | M85: 32.316841 | N85: =SUM(B85:M85) -> 394.53643 | Q85: =SUMIFS(B85:M85,$B$2:$M$2,$X$3) -> 39.841032 | R85: =SUMIFS(B85:M85,$B$1:$M$1,$Y$3) -> 182.02348
A86: Variable Costs | B86: 15.1712 | C86: 13.746193 | D86: 7.8790032 | E86: 13.272976 | F86: 10.735484 | G86: 17.021983 | H86: 13.473359 | I86: 12.659391 | J86: 17.559169 | K86: 16.067689 | L86: 16.922504 | M86: 13.746928 | N86: =SUM(B86:M86) -> 168.25588 | Q86: =SUMIFS(B86:M86,$B$2:$M$2,$X$3) -> 17.021983 | R86: =SUMIFS(B86:M86,$B$1:$M$1,$Y$3) -> 77.826839
A87: VARIABLE CONVERSION | B87: =SUM(B84:B86) -> 587.30321 | C87: =SUM(C84:C86) -> 527.78533 | D87: =SUM(D84:D86) -> 302.35331 | E87: =SUM(E84:E86) -> 509.47561 | F87: =SUM(F84:F86) -> 415.0255 | G87: =SUM(G84:G86) -> 655.26716 | H87: =SUM(H84:H86) -> 520.8404 | I87: =SUM(I84:I86) -> 489.36787 | ... N87: =SUM(N84:N86) -> 6493.2459 | Q87: =SUMIFS(B87:M87,$B$2:$M$2,$X$3) -> 655.26716 | R87: =SUMIFS(B87:M87,$B$1:$M$1,$Y$3) -> 2997.2101
A88: Indirect Labour | B88: 212.14049 | C88: 190.5489 | D88: 109.11422 | E88: 184.03658 | F88: 149.8394 | G88: 236.64471 | H88: 188.03323 | I88: 176.66886 | J88: 245.05445 | K88: 224.23355 | L88: 236.29289 | M88: 191.95158 | N88: =SUM(B88:M88) -> 2344.5588 | Q88: =SUMIFS(B88:M88,$B$2:$M$2,$X$3) -> 236.64471 | R88: =SUMIFS(B88:M88,$B$1:$M$1,$Y$3) -> 1082.3243
A89: Fixed Labour | B89: 74.965892 | C89: 67.454868 | D89: 38.698586 | E89: 65.067655 | F89: 53.040013 | G89: 83.695495 | H89: 66.553724 | I89: 62.52989 | J89: 86.736175 | K89: 79.364861 | L89: 83.673278 | M89: 67.97165 | N89: =SUM(B89:M89) -> 829.75209 | Q89: =SUMIFS(B89:M89,$B$2:$M$2,$X$3) -> 83.695495 | R89: =SUMIFS(B89:M89,$B$1:$M$1,$Y$3) -> 382.92251
A90: Semifixed | B90: 145.37437 | C90: 130.62199 | D90: 74.809423 | E90: 126.16662 | F90: 102.69277 | G90: 162.06681 | H90: 128.88785 | I90: 121.1026 | J90: 167.97324 | K90: 153.70715 | L90: 161.84962 | M90: 131.47788 | N90: =SUM(B90:M90) -> 1606.7303 | Q90: =SUMIFS(B90:M90,$B$2:$M$2,$X$3) -> 162.06681 | R90: =SUMIFS(B90:M90,$B$1:$M$1,$Y$3) -> 741.73199
A91: Fixed utilities | B91: 7.9978 | C91: 7.23397 | D91: 4.08225 | E91: 6.95061 | F91: 5.6474 | G91: 8.8590025 | H91: 7.0880853 | I91: 6.6599736 | J91: 9.2375557 | K91: 8.4530434 | L91: 8.8999463 | M91: 7.2298355 | N91: =SUM(B91:M91) -> 88.339472 | Q91: =SUMIFS(B91:M91,$B$2:$M$2,$X$3) -> 8.8590025 | R91: =SUMIFS(B91:M91,$B$1:$M$1,$Y$3) -> 40.771032
A92: Fixed Cost | B92: 37.110271 | C92: 33.289206 | D92: 19.053177 | E92: 32.152644 | F92: 26.221589 | G92: 41.414629 | H92: 32.906571 | I92: 30.918031 | J92: 42.885517 | K92: 39.242117 | L92: 41.345079 | M92: 33.586508 | N92: =SUM(B92:M92) -> 410.12534 | Q92: =SUMIFS(B92:M92,$B$2:$M$2,$X$3) -> 41.414629 | R92: =SUMIFS(B92:M92,$B$1:$M$1,$Y$3) -> 189.24152
A93: Depreciation | B93: 489.95651 | C93: 441.20391 | D93: 246.63262 | E93: 424.54616 | F93: 345.56338 | G93: 543.42574 | H93: 433.93082 | I93: 407.77239 | J93: 565.52144 | K93: 517.55727 | L93: 543.52514 | M93: 441.53046 | N93: =SUM(B93:M93) -> 5401.1658 | Q93: =SUMIFS(B93:M93,$B$2:$M$2,$X$3) -> 543.42574 | R93: =SUMIFS(B93:M93,$B$1:$M$1,$Y$3) -> 2491.3283
A94: FIXED CONVERSION | B94: =SUM(B88:B93) -> 967.54534 | C94: =SUM(C88:C93) -> 870.35285 | D94: =SUM(D88:D93) -> 492.39028 | E94: =SUM(E88:E93) -> 838.92027 | F94: =SUM(F88:F93) -> 683.00455 | G94: =SUM(G88:G93) -> 1076.1064 | H94: =SUM(H88:H93) -> 857.40028 | I94: =SUM(I88:I93) -> 805.65174 | ... N94: =SUM(N88:N93) -> 10680.672 | Q94: =SUMIFS(B94:M94,$B$2:$M$2,$X$3) -> 1076.1064 | R94: =SUMIFS(B94:M94,$B$1:$M$1,$Y$3) -> 4928.3197
A95: TOTAL MFG COST w/o SHARES | B95: =B87+B94 -> 1554.8485 | C95: =C87+C94 -> 1398.1382 | D95: =D87+D94 -> 794.74359 | E95: =E87+E94 -> 1348.3959 | F95: =F87+F94 -> 1098.03 | G95: =G87+G94 -> 1731.3735 | H95: =H87+H94 -> 1378.2407 | I95: =I87+I94 -> 1295.0196 | ... N95: =N87+N94 -> 17173.918 | Q95: =SUMIFS(B95:M95,$B$2:$M$2,$X$3) -> 1731.3735 | R95: =SUMIFS(B95:M95,$B$1:$M$1,$Y$3) -> 7925.5298
A96: TOTAL SHARES | N96: =SUM(B96:M96) -> 0 | Q96: =SUMIFS(B96:M96,$B$2:$M$2,$X$3) -> 0 | R96: =SUMIFS(B96:M96,$B$1:$M$1,$Y$3) -> 0
A97: TOTAL MFG COST w/ SHARES | N97: =SUM(N95,N96) -> 17173.918 | Q97: =SUMIFS(B97:M97,$B$2:$M$2,$X$3) -> 0 | R97: =SUMIFS(B97:M97,$B$1:$M$1,$Y$3) -> 0
A98: Functional Currency Impact | N98: =SUM(B98:M98) -> 0 | P98: 1000 | Q98: =SUMIFS(B98:M98,$B$2:$M$2,$X$3) -> 0 | R98: =SUMIFS(B98:M98,$B$1:$M$1,$Y$3) -> 0
A99: TOTAL Including FC | N99: =SUM(N97,N98) -> 17173.918 | Q99: =SUMIFS(B99:M99,$B$2:$M$2,$X$3) -> 0 | R99: =SUMIFS(B99:M99,$B$1:$M$1,$Y$3) -> 0
A100: Scrap | B100: 22.832815 | C100: 20.516916 | D100: 11.691481 | E100: 19.811558 | F100: 16.154151 | G100: 25.432898 | H100: 20.273526 | I100: 19.048639 | J100: 26.421493 | K100: 24.177119 | L100: 25.466144 | M100: 20.68732 | N100: =SUM(B100:M100) -> 252.51406 | Q100: =SUMIFS(B100:M100,$B$2:$M$2,$X$3) -> 25.432898 | R100: =SUMIFS(B100:M100,$B$1:$M$1,$Y$3) -> 116.43982
A101: Scrap Reselling | B101: -56.297268 | C101: -50.701757 | D101: -29.029938 | E101: -48.888273 | F101: -39.781346 | G101: -62.74935 | H101: -49.928925 | I101: -46.913069 | J101: -65.069929 | K101: -59.543511 | L101: -62.697292 | M101: -50.931892 | N101: =SUM(B101:M101) -> -622.53255 | Q101: =SUMIFS(B101:M101,$B$2:$M$2,$X$3) -> -62.74935 | R101: =SUMIFS(B101:M101,$B$1:$M$1,$Y$3) -> -287.44793
A102: Other Variable (Inventory Adj) | N102: =SUM(B102:M102) -> 0 | Q102: =SUMIFS(B102:M102,$B$2:$M$2,$X$3) -> 0 | R102: =SUMIFS(B102:M102,$B$1:$M$1,$Y$3) -> 0
A103: Obsolete | N103: =SUM(B103:M103) -> 0 | Q103: =SUMIFS(B103:M103,$B$2:$M$2,$X$3) -> 0 | R103: =SUMIFS(B103:M103,$B$1:$M$1,$Y$3) -> 0
A104: Asset Sales | N104: =SUM(B104:M104) -> 0 | Q104: =SUMIFS(B104:M104,$B$2:$M$2,$X$3) -> 0 | R104: =SUMIFS(B104:M104,$B$1:$M$1,$Y$3) -> 0
A105: TOTAL OTHERS | B105: =SUM(B100:B104) -> -33.464453 | C105: =SUM(C100:C104) -> -30.184841 | D105: =SUM(D100:D104) -> -17.338457 | E105: =SUM(E100:E104) -> -29.076715 | F105: =SUM(F100:F104) -> -23.627196 | G105: =SUM(G100:G104) -> -37.316452 | H105: =SUM(H100:H104) -> -29.655398 | I105: =SUM(I100:I104) -> -27.86443 | ... N105: =SUM(N100:N104) -> -370.01849 | Q105: =SUMIFS(B105:M105,$B$2:$M$2,$X$3) -> -37.316452 | R105: =SUMIFS(B105:M105,$B$1:$M$1,$Y$3) -> -171.00811
A106: IT GLOBAL | B106: =+B108*('Budget assumption'!B233/'Budget assumption'!B235) -> 74.699583 | C106: =+C108*('Budget assumption'!C233/'Budget assumption'!C235) -> 67.140322 | D106: =+D108*('Budget assumption'!D233/'Budget assumption'!D235) -> 38.439465 | E106: =+E108*('Budget assumption'!E233/'Budget assumption'!E235) -> 64.814167 | F106: =+F108*('Budget assumption'!F233/'Budget assumption'!F235) -> 52.788312 | G106: =+G108*('Budget assumption'!G233/'Budget assumption'!G235) -> 83.314994 | H106: =+H108*('Budget assumption'!H233/'Budget assumption'!H235) -> 66.24904 | I106: =+I108*('Budget assumption'!I233/'Budget assumption'!I235) -> 62.246279 | ... M106: =+M108*('Budget assumption'!M233/'Budget assumption'!M235) -> 67.603814 | N106: =SUM(B106:M106) -> 825.86047 | Q106: =SUMIFS(B106:M106,$B$2:$M$2,$X$3) -> 83.314994 | R106: =SUMIFS(B106:M106,$B$1:$M$1,$Y$3) -> 381.19684
A107: G&A(Insurance included) | B107: =+B108*('Budget assumption'!B234/'Budget assumption'!B235) -> 77.857964 | C107: =+C108*('Budget assumption'!C234/'Budget assumption'!C235) -> 69.97909 | D107: =+D108*('Budget assumption'!D234/'Budget assumption'!D235) -> 40.064728 | E107: =+E108*('Budget assumption'!E234/'Budget assumption'!E235) -> 67.554582 | F107: =+F108*('Budget assumption'!F234/'Budget assumption'!F235) -> 55.02026 | G107: =+G108*('Budget assumption'!G234/'Budget assumption'!G235) -> 86.837645 | H107: =+H108*('Budget assumption'!H234/'Budget assumption'!H235) -> 69.050123 | I107: =+I108*('Budget assumption'!I234/'Budget assumption'!I235) -> 64.878121 | ... M107: =+M108*('Budget assumption'!M234/'Budget assumption'!M235) -> 70.462178 | N107: =SUM(B107:M107) -> 860.77877 | Q107: =SUMIFS(B107:M107,$B$2:$M$2,$X$3) -> 86.837645 | R107: =SUMIFS(B107:M107,$B$1:$M$1,$Y$3) -> 397.31427
A108: TOTAL OVERHEAD | B108: 152.55755 | C108: 137.11941 | D108: 78.504194 | E108: 132.36875 | F108: 107.80857 | G108: 170.15264 | H108: 135.29916 | I108: 127.1244 | J108: 176.32877 | K108: 161.3502 | L108: 169.9596 | M108: 138.06599 | N108: =SUM(N106:N107) -> 1686.6392 | Q108: =SUMIFS(B108:M108,$B$2:$M$2,$X$3) -> 170.15264 | R108: =SUMIFS(B108:M108,$B$1:$M$1,$Y$3) -> 778.51111
Q109: =SUMIFS(B109:M109,$B$2:$M$2,$X$3) -> 0 | R109: =SUMIFS(B109:M109,$B$1:$M$1,$Y$3) -> 0
