Workbook
Name \1: #REF!
Name \1: #REF!
Name \2: #REF!
Name \2: #REF!
Name \3: #REF!
Name \3: #REF!
Name \4: #REF!
Name \4: #REF!
Name \A: #REF!
Name \A: #REF!
Name \B: #REF!
Name \B: #REF!
Name \C: #REF!
Name \C: #REF!
Name \P: #REF!
Name \P: #REF!
Name \Q: #REF!
Name \Q: #REF!
Name \R: #REF!
Name \R: #REF!
Name \S: #REF!
Name \S: #REF!
Name \T: #REF!
Name \T: #REF!
Name \X: #REF!
Name \X: #REF!
Name ___CON1: #REF!
Name ___CON1: #REF!
Name ___CON2: #REF!
Name ___CON2: #REF!
Name ___ddn400: #REF!
Name ___ddn400: #REF!
Name ___ddn600: #REF!
Name ___ddn600: #REF!
Name ___E99999: #REF!
Name ___E99999: #REF!
Name ___ETI2: #REF!
Name ___ETI2: #REF!
Name ___gon4: #REF!
Name ___gon4: #REF!
Name ___IV999999: #REF!
Name ___IV999999: #REF!
Name ___IZ53: #REF!
Name ___IZ53: #REF!
Name ___JZ123: #REF!
Name ___JZ123: #REF!
Name ___lap1: #REF!
Name ___lap1: #REF!
Name ___lap2: #REF!
Name ___lap2: #REF!
Name ___LI1: OFFSET(#REF!,4,0,COUNTA(#REF!)-1,1)
Name ___LI1: OFFSET(#REF!,4,0,COUNTA(#REF!)-1,1)
Name ___LI10: OFFSET(#REF!,4,0,COUNTA(#REF!)-1,1)
Name ___LI10: OFFSET(#REF!,4,0,COUNTA(#REF!)-1,1)
Name ___LI11: OFFSET(#REF!,4,0,COUNTA(#REF!)-1,1)
Name ___LI11: OFFSET(#REF!,4,0,COUNTA(#REF!)-1,1)
Name ___LI12: OFFSET(#REF!,4,0,COUNTA(#REF!)-1,1)
Name ___LI12: OFFSET(#REF!,4,0,COUNTA(#REF!)-1,1)
Name ___LI13: OFFSET(#REF!,4,0,COUNTA(#REF!)-1,1)
Name ___LI13: OFFSET(#REF!,4,0,COUNTA(#REF!)-1,1)

Sheet 大厨电
C2: 24年实际
B3: 千欧 | C3: 科目 | D3: 24年1月 | E3: 24年2月 | F3: 24年3月 | G3: 24年4月 | H3: 24年5月 | I3: 24年6月 | J3: 24年7月 | K3: 24年8月 | L3: 24年9月 | M3: 24年10月 | N3: 24年11月 | O3: 24年12月 | P3: 合计 | Q3: 单台 | R3: 占比 | S3: 费率 | T3: 同比
B4: 平均单价 | P4: =AVERAGE(D4:O4) -> #DIV/0!
B5: 产量 | D5: =厨电!D5+洗碗机!D5 -> 103382 | E5: =厨电!E5+洗碗机!E5 -> 129964 | F5: =厨电!F5+洗碗机!F5 -> 133663 | G5: =厨电!G5+洗碗机!G5 -> 137661 | H5: =厨电!H5+洗碗机!H5 -> 194723 | I5: =厨电!I5+洗碗机!I5 -> 152205 | J5: =厨电!J5+洗碗机!J5 -> 162832 | K5: =厨电!K5+洗碗机!K5 -> 83927 | ... O5: =厨电!O5+洗碗机!O5 -> 98970 | P5: =SUM(D5:O5) -> 1653718
B6: 固定制造 | C6: 折旧-不含FC | D6: =厨电!D6+洗碗机!D6 -> 779.26812 | E6: =厨电!E6+洗碗机!E6 -> 1069.3452 | F6: =厨电!F6+洗碗机!F6 -> 1075.7581 | G6: =厨电!G6+洗碗机!G6 -> 1083.3709 | H6: =厨电!H6+洗碗机!H6 -> 1146.8274 | I6: =厨电!I6+洗碗机!I6 -> 1276.0461 | J6: =厨电!J6+洗碗机!J6 -> 1185.7026 | K6: =厨电!K6+洗碗机!K6 -> 1171.6177 | ... O6: =厨电!O6+洗碗机!O6 -> 1241.6148 | P6: =SUM(D6:O6) -> 13446.54 | Q6: =P6/$P$5*1000 -> 8.1310964 | R6: =P6/$P$22 -> 0.23367425 | S6: =Q6/$P$4 -> #DIV/0!
C7: 运营费 | D7: =厨电!D7+洗碗机!D7 -> 120.9141 | E7: =厨电!E7+洗碗机!E7 -> 154.9804 | F7: =厨电!F7+洗碗机!F7 -> 196.5469 | G7: =厨电!G7+洗碗机!G7 -> 91.549433 | H7: =厨电!H7+洗碗机!H7 -> 153.18612 | I7: =厨电!I7+洗碗机!I7 -> 147.42758 | J7: =厨电!J7+洗碗机!J7 -> 284.03263 | K7: =厨电!K7+洗碗机!K7 -> -4.2988168 | ... O7: =厨电!O7+洗碗机!O7 -> 134.3931 | P7: =SUM(D7:O7) -> 1728.309 | Q7: =P7/$P$5*1000 -> 1.045105 | R7: =P7/$P$22 -> 0.030034588 | S7: =Q7/$P$4 -> #DIV/0!
C8: 存货跌价准备 | D8: =厨电!D8+洗碗机!D8 -> 28.412404 | E8: =厨电!E8+洗碗机!E8 -> 28.379922 | F8: =厨电!F8+洗碗机!F8 -> 14.473723 | G8: =厨电!G8+洗碗机!G8 -> 28.281947 | H8: =厨电!H8+洗碗机!H8 -> 28.270956 | I8: =厨电!I8+洗碗机!I8 -> 28.257603 | J8: =厨电!J8+洗碗机!J8 -> 397.95655 | K8: =厨电!K8+洗碗机!K8 -> 397.02774 | ... O8: =厨电!O8+洗碗机!O8 -> 436.53859 | P8: =SUM(D8:O8) -> 2813.6902 | Q8: =P8/$P$5*1000 -> 1.7014329 | R8: =P8/$P$22 -> 0.048896365 | S8: =Q8/$P$4 -> #DIV/0!
C9: 固定能源费 | D9: =厨电!D9+洗碗机!D9 -> 28.253599 | E9: =厨电!E9+洗碗机!E9 -> 1.7394932 | F9: =厨电!F9+洗碗机!F9 -> 29.04951 | G9: =厨电!G9+洗碗机!G9 -> 20.763787 | H9: =厨电!H9+洗碗机!H9 -> 6.5275961 | I9: =厨电!I9+洗碗机!I9 -> 4.6551348 | J9: =厨电!J9+洗碗机!J9 -> 5.0573918 | K9: =厨电!K9+洗碗机!K9 -> 8.6256962 | ... O9: =厨电!O9+洗碗机!O9 -> 19.670155 | P9: =SUM(D9:O9) -> 152.86065 | Q9: =P9/$P$5*1000 -> 0.092434531 | R9: =P9/$P$22 -> 0.0026564154 | S9: =Q9/$P$4 -> #DIV/0!
C10: 间接人工成本-辅助人员 | D10: =厨电!D10+洗碗机!D10 -> 365.56135 | E10: =厨电!E10+洗碗机!E10 -> 577.61784 | F10: =厨电!F10+洗碗机!F10 -> 689.72849 | G10: =厨电!G10+洗碗机!G10 -> 633.9929 | H10: =厨电!H10+洗碗机!H10 -> 656.31253 | I10: =厨电!I10+洗碗机!I10 -> 671.49986 | J10: =厨电!J10+洗碗机!J10 -> 627.03387 | K10: =厨电!K10+洗碗机!K10 -> 578.51089 | ... O10: =厨电!O10+洗碗机!O10 -> 700.26856 | P10: =SUM(D10:O10) -> 7496.4209 | Q10: =P10/$P$5*1000 -> 4.5330708 | R10: =P10/$P$22 -> 0.13027295 | S10: =Q10/$P$4 -> #DIV/0!
C11: 固定人工-白领 | D11: =厨电!D11+洗碗机!D11 -> 229.5068 | E11: =厨电!E11+洗碗机!E11 -> 162.78929 | F11: =厨电!F11+洗碗机!F11 -> 260.26961 | G11: =厨电!G11+洗碗机!G11 -> 240.19025 | H11: =厨电!H11+洗碗机!H11 -> 271.3336 | I11: =厨电!I11+洗碗机!I11 -> 288.59303 | J11: =厨电!J11+洗碗机!J11 -> 342.81746 | K11: =厨电!K11+洗碗机!K11 -> 328.95984 | ... O11: =厨电!O11+洗碗机!O11 -> 258.17259 | P11: =SUM(D11:O11) -> 3181.6033 | Q11: =P11/$P$5*1000 -> 1.9239092 | R11: =P11/$P$22 -> 0.055289967 | S11: =Q11/$P$4 -> #DIV/0!
C12: 半固定-班车/工作服 | D12: =厨电!D12+洗碗机!D12 -> 254.91522 | E12: =厨电!E12+洗碗机!E12 -> 299.62616 | F12: =厨电!F12+洗碗机!F12 -> 409.17661 | G12: =厨电!G12+洗碗机!G12 -> 376.82461 | H12: =厨电!H12+洗碗机!H12 -> 362.67674 | I12: =厨电!I12+洗碗机!I12 -> 425.16019 | J12: =厨电!J12+洗碗机!J12 -> 380.33989 | K12: =厨电!K12+洗碗机!K12 -> 252.23967 | ... O12: =厨电!O12+洗碗机!O12 -> 253.73661 | P12: =SUM(D12:O12) -> 4070.7214 | Q12: =P12/$P$5*1000 -> 2.4615571 | R12: =P12/$P$22 -> 0.070741078 | S12: =Q12/$P$4 -> #DIV/0!
B13: 变动制造 | C13: 直接人工 | D13: =厨电!D13+洗碗机!D13 -> 597.46818 | E13: =厨电!E13+洗碗机!E13 -> 739.37611 | F13: =厨电!F13+洗碗机!F13 -> 583.51977 | G13: =厨电!G13+洗碗机!G13 -> 994.38489 | H13: =厨电!H13+洗碗机!H13 -> 1014.6894 | I13: =厨电!I13+洗碗机!I13 -> 1059.6095 | J13: =厨电!J13+洗碗机!J13 -> 955.26573 | K13: =厨电!K13+洗碗机!K13 -> 883.51069 | ... O13: =厨电!O13+洗碗机!O13 -> 819.0595 | P13: =SUM(D13:O13) -> 10721.197 | Q13: =P13/$P$5*1000 -> 6.4830863 | R13: =P13/$P$22 -> 0.18631317 | S13: =Q13/$P$4 -> #DIV/0!
C14: 废料 | D14: =厨电!D14+洗碗机!D14 -> 26.324516 | E14: =厨电!E14+洗碗机!E14 -> 62.322607 | F14: =厨电!F14+洗碗机!F14 -> 46.877662 | G14: =厨电!G14+洗碗机!G14 -> 73.192417 | H14: =厨电!H14+洗碗机!H14 -> 111.71128 | I14: =厨电!I14+洗碗机!I14 -> 78.031684 | J14: =厨电!J14+洗碗机!J14 -> 83.166879 | K14: =厨电!K14+洗碗机!K14 -> 47.645265 | ... O14: =厨电!O14+洗碗机!O14 -> 81.862185 | P14: =SUM(D14:O14) -> 785.65563 | Q14: =P14/$P$5*1000 -> 0.4750844 | R14: =P14/$P$22 -> 0.013653139 | S14: =Q14/$P$4 -> #DIV/0!
C15: 生产耗用品 | D15: =厨电!D15+洗碗机!D15 -> -2.2935624 | E15: =厨电!E15+洗碗机!E15 -> 2.6206302 | F15: =厨电!F15+洗碗机!F15 -> 26.963748 | G15: =厨电!G15+洗碗机!G15 -> 61.216313 | H15: =厨电!H15+洗碗机!H15 -> 63.885472 | I15: =厨电!I15+洗碗机!I15 -> 44.476742 | J15: =厨电!J15+洗碗机!J15 -> -3.0117491 | K15: =厨电!K15+洗碗机!K15 -> 74.110438 | ... O15: =厨电!O15+洗碗机!O15 -> 75.801337 | P15: =SUM(D15:O15) -> 480.46717 | Q15: =P15/$P$5*1000 -> 0.29053755 | R15: =P15/$P$22 -> 0.0083495682 | S15: =Q15/$P$4 -> #DIV/0!
C16: 废品收入 | D16: =厨电!D16+洗碗机!D16 -> -78.443595 | E16: =厨电!E16+洗碗机!E16 -> -106.8524 | F16: =厨电!F16+洗碗机!F16 -> -125.44641 | G16: =厨电!G16+洗碗机!G16 -> -131.92906 | H16: =厨电!H16+洗碗机!H16 -> -180.5009 | I16: =厨电!I16+洗碗机!I16 -> -137.85001 | J16: =厨电!J16+洗碗机!J16 -> -159.74739 | K16: =厨电!K16+洗碗机!K16 -> -107.52558 | ... O16: =厨电!O16+洗碗机!O16 -> -103.50766 | P16: =SUM(D16:O16) -> -1580.9556 | Q16: =P16/$P$5*1000 -> -0.95600071 | R16: =P16/$P$22 -> -0.027473878 | S16: =Q16/$P$4 -> #DIV/0!
C17: 变动能源费 | D17: =厨电!D17+洗碗机!D17 -> 144.17801 | E17: =厨电!E17+洗碗机!E17 -> 30.240509 | F17: =厨电!F17+洗碗机!F17 -> 105.79044 | G17: =厨电!G17+洗碗机!G17 -> 133.97283 | H17: =厨电!H17+洗碗机!H17 -> 131.14769 | I17: =厨电!I17+洗碗机!I17 -> 97.475812 | J17: =厨电!J17+洗碗机!J17 -> 95.205029 | K17: =厨电!K17+洗碗机!K17 -> 99.804389 | ... O17: =厨电!O17+洗碗机!O17 -> 94.785612 | P17: =SUM(D17:O17) -> 1264.3049 | Q17: =P17/$P$5*1000 -> 0.76452269 | R17: =P17/$P$22 -> 0.021971117 | S17: =Q17/$P$4 -> #DIV/0!
B18: 分摊 | C18: 分摊费用 | D18: =厨电!D18+洗碗机!D18 -> 549.35903 | E18: =厨电!E18+洗碗机!E18 -> 491.27192 | F18: =厨电!F18+洗碗机!F18 -> 567.26019 | G18: =厨电!G18+洗碗机!G18 -> 592.2887 | H18: =厨电!H18+洗碗机!H18 -> 531.88513 | I18: =厨电!I18+洗碗机!I18 -> 520.11704 | J18: =厨电!J18+洗碗机!J18 -> 606.26397 | K18: =厨电!K18+洗碗机!K18 -> 802.30109 | ... O18: =厨电!O18+洗碗机!O18 -> 380.24112 | P18: =SUM(D18:O18) -> 6792.3339 | Q18: =P18/$P$5*1000 -> 4.1073109 | R18: =P18/$P$22 -> 0.11803732 | S18: =Q18/$P$4 -> #DIV/0!
C19: IT Expense-Internal Charge Out | D19: =厨电!D19+洗碗机!D19 -> 314.52539 | E19: =厨电!E19+洗碗机!E19 -> 440.27359 | F19: =厨电!F19+洗碗机!F19 -> 494.49209 | G19: =厨电!G19+洗碗机!G19 -> 452.18563 | H19: =厨电!H19+洗碗机!H19 -> 469.34009 | I19: =厨电!I19+洗碗机!I19 -> 451.8314 | J19: =厨电!J19+洗碗机!J19 -> 523.08639 | K19: =厨电!K19+洗碗机!K19 -> 509.3 | ... O19: =厨电!O19+洗碗机!O19 -> 360.25711 | P19: =SUM(D19:O19) -> 5554.8871 | Q19: =P19/$P$5*1000 -> 3.3590292 | S19: =Q19/$P$4 -> #DIV/0!
C20: Association dues | D20: =厨电!D20+洗碗机!D20 -> 3.3545015 | E20: =厨电!E20+洗碗机!E20 -> 9.5692914 | F20: =厨电!F20+洗碗机!F20 -> 2.0080192 | G20: =厨电!G20+洗碗机!G20 -> 13.615264 | H20: =厨电!H20+洗碗机!H20 -> 13.123118 | I20: =厨电!I20+洗碗机!I20 -> 13.368661 | J20: =厨电!J20+洗碗机!J20 -> 12.646808 | K20: =厨电!K20+洗碗机!K20 -> 11.888594 | ... O20: =厨电!O20+洗碗机!O20 -> 11.96886 | P20: =SUM(D20:O20) -> 125.76025 | Q20: =P20/$P$5*1000 -> 0.076046972 | S20: =Q20/$P$4 -> #DIV/0!
C21: G&A | D21: =厨电!D21+洗碗机!D21 -> 231.47914 | E21: =厨电!E21+洗碗机!E21 -> 41.429036 | F21: =厨电!F21+洗碗机!F21 -> 70.760072 | G21: =厨电!G21+洗碗机!G21 -> 126.48781 | H21: =厨电!H21+洗碗机!H21 -> 49.421912 | I21: =厨电!I21+洗碗机!I21 -> 54.916982 | J21: =厨电!J21+洗碗机!J21 -> 70.530774 | K21: =厨电!K21+洗碗机!K21 -> 281.1125 | ... O21: =厨电!O21+洗碗机!O21 -> 8.0151415 | P21: =SUM(D21:O21) -> 1111.6866 | Q21: =P21/$P$5*1000 -> 0.6722347 | S21: =Q21/$P$4 -> #DIV/0!
B22: 合计 | D22: =厨电!D22+洗碗机!D22 -> 3572.3056 | E22: =厨电!E22+洗碗机!E22 -> 4042.3391 | F22: =厨电!F22+洗碗机!F22 -> 4408.8497 | G22: =厨电!G22+洗碗机!G22 -> 4726.9814 | H22: =厨电!H22+洗碗机!H22 -> 4826.8344 | I22: =厨电!I22+洗碗机!I22 -> 5032.3817 | J22: =厨电!J22+洗碗机!J22 -> 5328.9643 | K22: =厨电!K22+洗碗机!K22 -> 5061.4104 | ... O22: =厨电!O22+洗碗机!O22 -> 4765.7466 | P22: =SUM(D22:O22) -> 57543.954
B23: 单台 | D23: =D22/D5*1000 -> 34.554425 | E23: =E22/E5*1000 -> 31.103529 | F23: =F22/F5*1000 -> 32.984818 | G23: =G22/G5*1000 -> 34.33784 | H23: =H22/H5*1000 -> 24.788209 | I23: =I22/I5*1000 -> 33.063183 | J23: =J22/J5*1000 -> 32.726763 | K23: =K22/K5*1000 -> 60.307296 | ... P23: =P22/P5*1000 -> 34.796715 | Q23: =P23 -> 34.796715 | S23: =Q23/$P$4 -> #DIV/0!
B25: 青岛不包含科目 | D25: =('24年CK1'!D158+'24年CK2'!D150)/1000 -> 341.802 | E25: =('24年CK1'!E158+'24年CK2'!E150)/1000 -> 327.68597 | F25: =('24年CK1'!F158+'24年CK2'!F150)/1000 -> 365.93252 | G25: =('24年CK1'!G158+'24年CK2'!G150)/1000 -> 383.45643 | H25: =('24年CK1'!H158+'24年CK2'!H150)/1000 -> 419.76833 | I25: =('24年CK1'!I158+'24年CK2'!I150)/1000 -> 551.74142 | J25: =('24年CK1'!J158+'24年CK2'!J150)/1000 -> 906.90377 | K25: =('24年CK1'!K158+'24年CK2'!K150)/1000 -> 986.05575 | ... O25: =('24年CK1'!O158+'24年CK2'!O150)/1000 -> 910.23683 | P25: =SUM(D25:O25) -> 7984.5405
B26: functional currency | D26: =厨电!D26+洗碗机!D26 -> 1094.4907 | E26: =厨电!E26+洗碗机!E26 -> 1094.4907 | F26: =厨电!F26+洗碗机!F26 -> 1094.4907 | G26: =厨电!G26+洗碗机!G26 -> 1094.4907 | H26: =厨电!H26+洗碗机!H26 -> 1094.4907 | I26: =厨电!I26+洗碗机!I26 -> 1094.4907 | J26: =厨电!J26+洗碗机!J26 -> 1094.4907 | K26: =厨电!K26+洗碗机!K26 -> 1094.4907 | ... O26: =厨电!O26+洗碗机!O26 -> 856.04029 | P26: =SUM(D26:O26) -> 12895.438 | Q26: =P26/$P$5*1000 -> 7.7978461
Q27: =Q23+Q26 -> 42.594561 | S27: =Q23/P4 -> #DIV/0!
C28: 大厨电25年实际
A29: 年累 | C29: 科目 | D29: 25年1月 | E29: 25年2月 | F29: 25年3月 | G29: 25年4月 | H29: 25年5月 | I29: 25年6月 | J29: 25年7月 | K29: 25年8月 | L29: 25年9月 | M29: 25年10月 | N29: 25年11月 | O29: 25年12月 | P29: 合计 | Q29: 单台 | R29: 占比 | S29: 费率 | T29: 同比
A30: 125 | B30: 平均单价（自制） | D30: 162.48841 | E30: 160.90377 | F30: 156.89927 | G30: 161.78509 | H30: 154.82189 | I30: 155.33307 | J30: 147.70531 | K30: 157.18622 | L30: 144.0859 | M30: 146.91137 | N30: 147.83429 | O30: 157.09858 | P30: =AVERAGE(D30:O30) -> 154.4211 | Q30: =AVERAGE(D30:O30) -> 154.4211
A31: =SUM(D31:F31) -> 395415 | C31: 产量 | D31: =厨电!D31+洗碗机!D31 -> 128283 | E31: =厨电!E31+洗碗机!E31 -> 128138 | F31: =厨电!F31+洗碗机!F31 -> 138994 | G31: =厨电!G31+洗碗机!G31 -> 148050 | H31: =厨电!H31+洗碗机!H31 -> 147057 | I31: =厨电!I31+洗碗机!I31 -> 104756 | J31: =厨电!J31+洗碗机!J31 -> 119656 | K31: =厨电!K31+洗碗机!K31 -> 90789 | ... O31: =厨电!O31+洗碗机!O31 -> 117647 | P31: =SUM(D31:O31) -> 1525896
A32: =SUM(D32:F32) -> 3895.9228 | B32: 固定制造 | C32: 折旧 | D32: =厨电!D32+洗碗机!D32 -> 1317.1753 | E32: =厨电!E32+洗碗机!E32 -> 1253.7334 | F32: =厨电!F32+洗碗机!F32 -> 1325.0141 | G32: =厨电!G32+洗碗机!G32 -> 1316.6541 | H32: =厨电!H32+洗碗机!H32 -> 1411.2359 | I32: =厨电!I32+洗碗机!I32 -> 1388.0214 | J32: =厨电!J32+洗碗机!J32 -> 1418.1628 | K32: =厨电!K32+洗碗机!K32 -> 1160.6474 | ... O32: =厨电!O32+洗碗机!O32 -> 1377.9119 | P32: =SUM(D32:O32) -> 15634.26 | Q32: =P32/$P$31*1000 -> 10.245954 | R32: =P32/$P$48 -> 0.32108504 | S32: =Q32/$P$30 -> 0.066350738
A33: =SUM(D33:F33) -> 555.07614 | C33: 运营费 | D33: =厨电!D33+洗碗机!D33 -> 143.31599 | E33: =厨电!E33+洗碗机!E33 -> 164.6474 | F33: =厨电!F33+洗碗机!F33 -> 247.11275 | G33: =厨电!G33+洗碗机!G33 -> 52.76386 | H33: =厨电!H33+洗碗机!H33 -> 121.69989 | I33: =厨电!I33+洗碗机!I33 -> 118.21183 | J33: =厨电!J33+洗碗机!J33 -> 113.72722 | K33: =厨电!K33+洗碗机!K33 -> 124.99486 | ... O33: =厨电!O33+洗碗机!O33 -> 61.40762 | P33: =SUM(D33:O33) -> 1567.3922 | Q33: =P33/$P$31*1000 -> 1.0271946 | R33: =P33/$P$48 -> 0.032189959 | S33: =Q33/$P$30 -> 0.006651906
A34: =SUM(D34:F34) -> 99.23558 | C34: 存货跌价准备 | D34: =厨电!D34+洗碗机!D34 -> 37.35936 | E34: =厨电!E34+洗碗机!E34 -> 30.93811 | F34: =厨电!F34+洗碗机!F34 -> 30.93811 | G34: =厨电!G34+洗碗机!G34 -> 30.93811 | H34: =厨电!H34+洗碗机!H34 -> 30.93811 | I34: =厨电!I34+洗碗机!I34 -> 290.7142 | J34: =厨电!J34+洗碗机!J34 -> 8.85478 | K34: =厨电!K34+洗碗机!K34 -> 8.855 | ... O34: =厨电!O34+洗碗机!O34 -> -283.32317 | P34: =SUM(D34:O34) -> -1027.686 | Q34: =P34/$P$31*1000 -> -0.67349675 | R34: =P34/$P$48 -> -0.021105866 | S34: =Q34/$P$30 -> -0.0043614296
A35: =SUM(D35:F35) -> 159.29147 | C35: 固定能源费 | D35: =厨电!D35+洗碗机!D35 -> 54.19819 | E35: =厨电!E35+洗碗机!E35 -> 46.66486 | F35: =厨电!F35+洗碗机!F35 -> 58.42842 | G35: =厨电!G35+洗碗机!G35 -> 10.602999 | H35: =厨电!H35+洗碗机!H35 -> 34.21968 | I35: =厨电!I35+洗碗机!I35 -> 19.02607 | J35: =厨电!J35+洗碗机!J35 -> 24.56847 | K35: =厨电!K35+洗碗机!K35 -> 36.77566 | ... O35: =厨电!O35+洗碗机!O35 -> 39.69396 | P35: =SUM(D35:O35) -> 431.18694 | Q35: =P35/$P$31*1000 -> 0.28257951 | R35: =P35/$P$48 -> 0.0088554033 | S35: =Q35/$P$30 -> 0.0018299281
A36: =SUM(D36:F36) -> 1850.9144 | C36: 间接人工成本-辅助人员 | D36: =厨电!D36+洗碗机!D36 -> 593.9138 | E36: =厨电!E36+洗碗机!E36 -> 519.57438 | F36: =厨电!F36+洗碗机!F36 -> 737.42617 | G36: =厨电!G36+洗碗机!G36 -> 613.43502 | H36: =厨电!H36+洗碗机!H36 -> 693.47583 | I36: =厨电!I36+洗碗机!I36 -> 598.46574 | J36: =厨电!J36+洗碗机!J36 -> 487.85191 | K36: =厨电!K36+洗碗机!K36 -> 473.02536 | ... O36: =厨电!O36+洗碗机!O36 -> 692.89474 | P36: =SUM(D36:O36) -> 7126.7577 | Q36: =P36/$P$31*1000 -> 4.6705396 | R36: =P36/$P$48 -> 0.14636416 | S36: =Q36/$P$30 -> 0.030245476
A37: =SUM(D37:F37) -> 1015.4306 | C37: 固定人工-白领 | D37: =厨电!D37+洗碗机!D37 -> 410.48672 | E37: =厨电!E37+洗碗机!E37 -> 316.5566 | F37: =厨电!F37+洗碗机!F37 -> 288.38723 | G37: =厨电!G37+洗碗机!G37 -> 205.71739 | H37: =厨电!H37+洗碗机!H37 -> 280.41396 | I37: =厨电!I37+洗碗机!I37 -> 258.39155 | J37: =厨电!J37+洗碗机!J37 -> 231.49671 | K37: =厨电!K37+洗碗机!K37 -> 227.51409 | ... O37: =厨电!O37+洗碗机!O37 -> 187.23786 | P37: =SUM(D37:O37) -> 2984.8065 | Q37: =P37/$P$31*1000 -> 1.9561009 | R37: =P37/$P$48 -> 0.061299781 | S37: =Q37/$P$30 -> 0.012667316
A38: =SUM(D38:F38) -> 1002.4131 | C38: 半固定-班车/工作服 | D38: =厨电!D38+洗碗机!D38 -> 326.27796 | E38: =厨电!E38+洗碗机!E38 -> 374.3963 | F38: =厨电!F38+洗碗机!F38 -> 301.73887 | G38: =厨电!G38+洗碗机!G38 -> 273.98815 | H38: =厨电!H38+洗碗机!H38 -> 305.50347 | I38: =厨电!I38+洗碗机!I38 -> 248.03449 | J38: =厨电!J38+洗碗机!J38 -> 253.39644 | K38: =厨电!K38+洗碗机!K38 -> 218.02976 | ... O38: =厨电!O38+洗碗机!O38 -> 309.08275 | P38: =SUM(D38:O38) -> 3464.0048 | Q38: =P38/$P$31*1000 -> 2.2701448 | R38: =P38/$P$48 -> 0.071141207 | S38: =Q38/$P$30 -> 0.014701001
A39: =SUM(D39:F39) -> 3034.8452 | B39: 变动制造 | C39: 直接人工 | D39: =厨电!D39+洗碗机!D39 -> 1016.1174 | E39: =厨电!E39+洗碗机!E39 -> 812.4108 | F39: =厨电!F39+洗碗机!F39 -> 1206.3169 | G39: =厨电!G39+洗碗机!G39 -> 1042.1462 | H39: =厨电!H39+洗碗机!H39 -> 1208.068 | I39: =厨电!I39+洗碗机!I39 -> 978.48413 | J39: =厨电!J39+洗碗机!J39 -> 969.54525 | K39: =厨电!K39+洗碗机!K39 -> 784.28839 | ... O39: =厨电!O39+洗碗机!O39 -> 983.23408 | P39: =SUM(D39:O39) -> 11924.424 | Q39: =P39/$P$31*1000 -> 7.8147029 | R39: =P39/$P$48 -> 0.24489513 | S39: =Q39/$P$30 -> 0.050606446
A40: =SUM(D40:F40) -> 164.12315 | C40: 废料 | D40: =厨电!D40+洗碗机!D40 -> 53.20349 | E40: =厨电!E40+洗碗机!E40 -> 54.68028 | F40: =厨电!F40+洗碗机!F40 -> 56.23938 | G40: =厨电!G40+洗碗机!G40 -> 60.85428 | H40: =厨电!H40+洗碗机!H40 -> 66.56418 | I40: =厨电!I40+洗碗机!I40 -> 60.09286 | J40: =厨电!J40+洗碗机!J40 -> 52.11769 | K40: =厨电!K40+洗碗机!K40 -> 50.89797 | ... O40: =厨电!O40+洗碗机!O40 -> 97.6763 | P40: =SUM(D40:O40) -> 733.57 | Q40: =P40/$P$31*1000 -> 0.48074705 | R40: =P40/$P$48 -> 0.015065526 | S40: =Q40/$P$30 -> 0.0031132213
A41: =SUM(D41:F41) -> 63.87373 | C41: 生产耗用品 | D41: =厨电!D41+洗碗机!D41 -> 6.03099 | E41: =厨电!E41+洗碗机!E41 -> 26.94665 | F41: =厨电!F41+洗碗机!F41 -> 30.89609 | G41: =厨电!G41+洗碗机!G41 -> -15.84372 | H41: =厨电!H41+洗碗机!H41 -> -4.43767 | I41: =厨电!I41+洗碗机!I41 -> 25.46166 | J41: =厨电!J41+洗碗机!J41 -> -88.20429 | K41: =厨电!K41+洗碗机!K41 -> 88.19468 | ... O41: =厨电!O41+洗碗机!O41 -> -53.65688 | P41: =SUM(D41:O41) -> 78.83959 | Q41: =P41/$P$31*1000 -> 0.051667735 | R41: =P41/$P$48 -> 0.0016191501 | S41: =Q41/$P$30 -> 0.00033458987
A42: =SUM(D42:F42) -> -332.20269 | C42: 废品收入 | D42: =厨电!D42+洗碗机!D42 -> -94.64742 | E42: =厨电!E42+洗碗机!E42 -> -91.95947 | F42: =厨电!F42+洗碗机!F42 -> -145.5958 | G42: =厨电!G42+洗碗机!G42 -> -159.63492 | H42: =厨电!H42+洗碗机!H42 -> -153.25855 | I42: =厨电!I42+洗碗机!I42 -> -151.92839 | J42: =厨电!J42+洗碗机!J42 -> -128.04073 | K42: =厨电!K42+洗碗机!K42 -> -98.08811 | ... O42: =厨电!O42+洗碗机!O42 -> -123.5865 | P42: =SUM(D42:O42) -> -1517.447 | Q42: =P42/$P$31*1000 -> -0.99446293 | R42: =P42/$P$48 -> -0.031164221 | S42: =Q42/$P$30 -> -0.0064399421
A43: =SUM(D43:F43) -> 191.08258 | C43: 变动能源费 | D43: =厨电!D43+洗碗机!D43 -> 52.37062 | E43: =厨电!E43+洗碗机!E43 -> 64.60598 | F43: =厨电!F43+洗碗机!F43 -> 74.10598 | G43: =厨电!G43+洗碗机!G43 -> 100.69488 | H43: =厨电!H43+洗碗机!H43 -> 102.89451 | I43: =厨电!I43+洗碗机!I43 -> 67.17979 | J43: =厨电!J43+洗碗机!J43 -> 74.21017 | K43: =厨电!K43+洗碗机!K43 -> 54.709 | ... O43: =厨电!O43+洗碗机!O43 -> 52.58832 | P43: =SUM(D43:O43) -> 861.65756 | Q43: =P43/$P$31*1000 -> 0.56468957 | R43: =P43/$P$48 -> 0.017696095 | S43: =Q43/$P$30 -> 0.0036568162
A44: =SUM(D44:F44) -> 1920.475 | B44: 分摊 | C44: 分摊费用 | D44: =厨电!D44+洗碗机!D44 -> 572.7913 | E44: =厨电!E44+洗碗机!E44 -> 751.34568 | F44: =厨电!F44+洗碗机!F44 -> 596.33797 | G44: =厨电!G44+洗碗机!G44 -> 615.97256 | H44: =厨电!H44+洗碗机!H44 -> 585.69329 | I44: =厨电!I44+洗碗机!I44 -> 580.68951 | J44: =厨电!J44+洗碗机!J44 -> 588.31954 | K44: =厨电!K44+洗碗机!K44 -> 557.4804 | ... O44: =厨电!O44+洗碗机!O44 -> -248.41934 | P44: =SUM(D44:O44) -> 6430.1935 | Q44: =P44/$P$31*1000 -> 4.2140444 | R44: =P44/$P$48 -> 0.13205863 | S44: =Q44/$P$30 -> 0.027289305
A45: =SUM(D45:F45) -> 1059.2085 | C45: IT Expense-Internal Charge Out | D45: =厨电!D45+洗碗机!D45 -> 352.87916 | E45: =厨电!E45+洗碗机!E45 -> 353.5153 | F45: =厨电!F45+洗碗机!F45 -> 352.81409 | G45: =厨电!G45+洗碗机!G45 -> 352.85747 | H45: =厨电!H45+洗碗机!H45 -> 388.03079 | I45: =厨电!I45+洗碗机!I45 -> 352.85747 | J45: =厨电!J45+洗碗机!J45 -> 377.75583 | K45: =厨电!K45+洗碗机!K45 -> 352.84283 | ... O45: =厨电!O45+洗碗机!O45 -> -419.6708 | P45: =SUM(D45:O45) -> 3592.8012 | Q45: =P45/$P$31*1000 -> 2.3545518 | S45: =Q45/$P$30 -> 0.015247604
A46: =SUM(D46:F46) -> 41.32335 | C46: Association dues | D46: =厨电!D46+洗碗机!D46 -> 13.52589 | E46: =厨电!E46+洗碗机!E46 -> 13.69713 | F46: =厨电!F46+洗碗机!F46 -> 14.10033 | G46: =厨电!G46+洗碗机!G46 -> 13.7227 | H46: =厨电!H46+洗碗机!H46 -> 13.6007 | I46: =厨电!I46+洗碗机!I46 -> 11.14706 | J46: =厨电!J46+洗碗机!J46 -> 14.57156 | K46: =厨电!K46+洗碗机!K46 -> 11.25921 | ... O46: =厨电!O46+洗碗机!O46 -> 12.09843 | P46: =SUM(D46:O46) -> 151.26908 | Q46: =P46/$P$31*1000 -> 0.099134594 | S46: =Q46/$P$30 -> 0.00064197571
A47: =SUM(D47:F47) -> 819.94305 | C47: G&A | D47: =厨电!D47+洗碗机!D47 -> 206.38625 | E47: =厨电!E47+洗碗机!E47 -> 384.13325 | F47: =厨电!F47+洗碗机!F47 -> 229.42355 | G47: =厨电!G47+洗碗机!G47 -> 249.39239 | H47: =厨电!H47+洗碗机!H47 -> 184.0618 | I47: =厨电!I47+洗碗机!I47 -> 216.68498 | J47: =厨电!J47+洗碗机!J47 -> 195.99215 | K47: =厨电!K47+洗碗机!K47 -> 193.58594 | ... O47: =厨电!O47+洗碗机!O47 -> 159.15303 | P47: =SUM(D47:O47) -> 2686.3308 | Q47: =P47/$P$31*1000 -> 1.760494 | S47: =Q47/$P$30 -> 0.011400606
A48: =SUM(D48:F48) -> 13620.481 | B48: 合计 | D48: =厨电!D48+洗碗机!D48 -> 4488.5937 | E48: =厨电!E48+洗碗机!E48 -> 4324.541 | F48: =厨电!F48+洗碗机!F48 -> 4807.3463 | G48: =厨电!G48+洗碗机!G48 -> 4148.2889 | H48: =厨电!H48+洗碗机!H48 -> 4683.0107 | I48: =厨电!I48+洗碗机!I48 -> 4480.8449 | J48: =厨电!J48+洗碗机!J48 -> 4006.006 | K48: =厨电!K48+洗碗机!K48 -> 3687.3245 | ... O48: =厨电!O48+洗碗机!O48 -> 3092.7417 | P48: =SUM(P32:P44) -> 48691.96 | Q48: =P49/P30 -> 0.20664537 | S48: =Q48/$P$30 -> 0.0013381939
A49: =A48/A31*1000 -> 34.44604 | B49: 单台 | D49: =D48/D31*1000 -> 34.989778 | E49: =E48/E31*1000 -> 33.749091 | F49: =F48/F31*1000 -> 34.586718 | G49: =G48/G31*1000 -> 28.019513 | H49: =H48/H31*1000 -> 31.844867 | I49: =I48/I31*1000 -> 42.774112 | J49: =J48/J31*1000 -> 33.479357 | K49: =K48/K31*1000 -> 40.614221 | L49: =L48*1000/L31 -> 23.8106 | M49: 20.771015 | N49: =N48/N31*1000 -> 30.051762 | O49: =O48/O31*1000 -> 26.288317 | P49: =P48/P31*1000 -> 31.910405 | Q49: =P49 -> 31.910405 | S49: =Q49/$P$30 -> 0.20664537
A50: =SUM(D50:F50) -> 2091.5783 | B50: functional currency | D50: =厨电!D50+洗碗机!D50 -> 743.70743 | E50: =厨电!E50+洗碗机!E50 -> 661.06836 | F50: =厨电!F50+洗碗机!F50 -> 686.80255 | G50: =厨电!G50+洗碗机!G50 -> 719.671 | H50: =厨电!H50+洗碗机!H50 -> 745.10541 | I50: =厨电!I50+洗碗机!I50 -> 750.77777 | J50: =厨电!J50+洗碗机!J50 -> 788.4 | K50: =厨电!K50+洗碗机!K50 -> 804.05537 | ... O50: =厨电!O50+洗碗机!O50 -> 786.18807 | P50: =SUM(D50:O50) -> 8837.9289 | Q50: =P50/$P$31*1000 -> 5.7919602 | R50: =P49-Q50-Q44 -> 21.904401 | S50: =Q50/$P$30 -> 0.03750757
C51: 大厨电25年预算 | Q51: =P49/P30 -> 0.20664537
C52: 科目 | D52: 25年1月 | E52: 25年2月 | F52: 25年3月 | G52: 25年4月 | H52: 25年5月 | I52: 25年6月 | J52: 25年7月 | K52: 25年8月 | L52: 25年9月 | M52: 25年10月 | N52: 25年11月 | O52: 25年12月 | P52: 合计 | Q52: 单台 | R52: 占比 | S52: 费率 | T52: 同比
B53: 平均单价 | D53: =(厨电!D53*厨电!D54+洗碗机!D53*洗碗机!D54)/(洗碗机!D54+厨电!D54) -> 166.68032 | E53: =(厨电!E53*厨电!E54+洗碗机!E53*洗碗机!E54)/(洗碗机!E54+厨电!E54) -> 161.7245 | F53: =(厨电!F53*厨电!F54+洗碗机!F53*洗碗机!F54)/(洗碗机!F54+厨电!F54) -> 154.62056 | G53: =(厨电!G53*厨电!G54+洗碗机!G53*洗碗机!G54)/(洗碗机!G54+厨电!G54) -> 154.00716 | H53: =(厨电!H53*厨电!H54+洗碗机!H53*洗碗机!H54)/(洗碗机!H54+厨电!H54) -> 157.38206 | I53: =(厨电!I53*厨电!I54+洗碗机!I53*洗碗机!I54)/(洗碗机!I54+厨电!I54) -> 137.627 | J53: =(厨电!J53*厨电!J54+洗碗机!J53*洗碗机!J54)/(洗碗机!J54+厨电!J54) -> 157.02136 | K53: =(厨电!K53*厨电!K54+洗碗机!K53*洗碗机!K54)/(洗碗机!K54+厨电!K54) -> 161.04059 | ... P53: =(厨电!P53*厨电!P54+洗碗机!P53*洗碗机!P54)/(洗碗机!P54+厨电!P54) -> 155.6419
C54: 产量 | D54: =厨电!D54+洗碗机!D54 -> 122838 | E54: =厨电!E54+洗碗机!E54 -> 121465 | F54: =厨电!F54+洗碗机!F54 -> 144017 | G54: =厨电!G54+洗碗机!G54 -> 155712 | H54: =厨电!H54+洗碗机!H54 -> 142621 | I54: =厨电!I54+洗碗机!I54 -> 122589 | J54: =厨电!J54+洗碗机!J54 -> 156037 | K54: =厨电!K54+洗碗机!K54 -> 127638 | ... O54: =厨电!O54+洗碗机!O54 -> 138393 | P54: =SUM(D54:O54) -> 1708463
B55: 固定制造 | C55: 折旧 | D55: =厨电!D55+洗碗机!D55 -> 637.68476 | E55: =厨电!E55+洗碗机!E55 -> 618.34576 | F55: =厨电!F55+洗碗机!F55 -> 636.39876 | G55: =厨电!G55+洗碗机!G55 -> 631.48676 | H55: =厨电!H55+洗碗机!H55 -> 637.42076 | I55: =厨电!I55+洗碗机!I55 -> 677.09376 | J55: =厨电!J55+洗碗机!J55 -> 696.56176 | K55: =厨电!K55+洗碗机!K55 -> 702.83076 | ... O55: =厨电!O55+洗碗机!O55 -> 796.64376 | P55: =SUM(D55:O55) -> 8241.9061 | Q55: =P55/$P$54*1000 -> 4.8241642 | R55: =P55/$P$71 -> 0.193995
C56: 运营费 | D56: =厨电!D56+洗碗机!D56 -> 148.13047 | E56: =厨电!E56+洗碗机!E56 -> 148.13047 | F56: =厨电!F56+洗碗机!F56 -> 148.10577 | G56: =厨电!G56+洗碗机!G56 -> 148.10577 | H56: =厨电!H56+洗碗机!H56 -> 148.08106 | I56: =厨电!I56+洗碗机!I56 -> 119.65731 | J56: =厨电!J56+洗碗机!J56 -> 108.32186 | K56: =厨电!K56+洗碗机!K56 -> 108.32186 | ... O56: =厨电!O56+洗碗机!O56 -> 108.32186 | P56: =SUM(D56:O56) -> 1510.142 | Q56: =P56/$P$54*1000 -> 0.88391845 | R56: =P56/$P$71 -> 0.035545175
C57: 存货跌价准备 | D57: =厨电!D57+洗碗机!D57 -> 37.648939 | E57: =厨电!E57+洗碗机!E57 -> 37.648939 | F57: =厨电!F57+洗碗机!F57 -> 37.648939 | G57: =厨电!G57+洗碗机!G57 -> 37.648939 | H57: =厨电!H57+洗碗机!H57 -> 37.648939 | I57: =厨电!I57+洗碗机!I57 -> 17.648939 | J57: =厨电!J57+洗碗机!J57 -> 17.648939 | K57: =厨电!K57+洗碗机!K57 -> 17.648939 | ... O57: =厨电!O57+洗碗机!O57 -> 17.648939 | P57: =SUM(D57:O57) -> 311.78726 | Q57: =P57/$P$54*1000 -> 0.18249577 | R57: =P57/$P$71 -> 0.0073387358
C58: 固定能源费 | D58: =厨电!D58+洗碗机!D58 -> 52.695528 | E58: =厨电!E58+洗碗机!E58 -> 52.017403 | F58: =厨电!F58+洗碗机!F58 -> 53.462942 | G58: =厨电!G58+洗碗机!G58 -> 48.30733 | H58: =厨电!H58+洗碗机!H58 -> 37.61794 | I58: =厨电!I58+洗碗机!I58 -> 23.576349 | J58: =厨电!J58+洗碗机!J58 -> 29.215644 | K58: =厨电!K58+洗碗机!K58 -> 29.250451 | ... O58: =厨电!O58+洗碗机!O58 -> 45.076179 | P58: =SUM(D58:O58) -> 486.83098 | Q58: =P58/$P$54*1000 -> 0.28495261 | R58: =P58/$P$71 -> 0.011458852
C59: 间接人工成本-辅助人员 | D59: =厨电!D59+洗碗机!D59 -> 608.74079 | E59: =厨电!E59+洗碗机!E59 -> 460.18304 | F59: =厨电!F59+洗碗机!F59 -> 564.98353 | G59: =厨电!G59+洗碗机!G59 -> 514.22063 | H59: =厨电!H59+洗碗机!H59 -> 519.10811 | I59: =厨电!I59+洗碗机!I59 -> 491.63491 | J59: =厨电!J59+洗碗机!J59 -> 429.24075 | K59: =厨电!K59+洗碗机!K59 -> 478.81308 | ... O59: =厨电!O59+洗碗机!O59 -> 558.65352 | P59: =SUM(D59:O59) -> 6080.6529 | Q59: =P59/$P$54*1000 -> 3.5591364 | R59: =P59/$P$71 -> 0.14312421
C60: 固定人工-白领 | D60: =厨电!D60+洗碗机!D60 -> 269.4856 | E60: =厨电!E60+洗碗机!E60 -> 266.20653 | F60: =厨电!F60+洗碗机!F60 -> 274.07875 | G60: =厨电!G60+洗碗机!G60 -> 283.30748 | H60: =厨电!H60+洗碗机!H60 -> 278.55197 | I60: =厨电!I60+洗碗机!I60 -> 256.14562 | J60: =厨电!J60+洗碗机!J60 -> 237.26351 | K60: =厨电!K60+洗碗机!K60 -> 237.26351 | ... O60: =厨电!O60+洗碗机!O60 -> 238.88772 | P60: =SUM(D60:O60) -> 3064.3627 | Q60: =P60/$P$54*1000 -> 1.7936371 | R60: =P60/$P$71 -> 0.072127859
C61: 半固定-班车/工作服 | D61: =厨电!D61+洗碗机!D61 -> 393.96539 | E61: =厨电!E61+洗碗机!E61 -> 397.31816 | F61: =厨电!F61+洗碗机!F61 -> 399.7248 | G61: =厨电!G61+洗碗机!G61 -> 392.76968 | H61: =厨电!H61+洗碗机!H61 -> 392.15926 | I61: =厨电!I61+洗碗机!I61 -> 324.27481 | J61: =厨电!J61+洗碗机!J61 -> 324.07609 | K61: =厨电!K61+洗碗机!K61 -> 279.91689 | ... O61: =厨电!O61+洗碗机!O61 -> 330.4102 | P61: =SUM(D61:O61) -> 4200.238 | Q61: =P61/$P$54*1000 -> 2.4584893 | R61: =P61/$P$71 -> 0.098863682
B62: 变动制造 | C62: 直接人工 | D62: =厨电!D62+洗碗机!D62 -> 827.8346 | E62: =厨电!E62+洗碗机!E62 -> 840.89374 | F62: =厨电!F62+洗碗机!F62 -> 1002.2044 | G62: =厨电!G62+洗碗机!G62 -> 939.99062 | H62: =厨电!H62+洗碗机!H62 -> 937.59328 | I62: =厨电!I62+洗碗机!I62 -> 723.78287 | J62: =厨电!J62+洗碗机!J62 -> 892.53203 | K62: =厨电!K62+洗碗机!K62 -> 863.52948 | ... O62: =厨电!O62+洗碗机!O62 -> 863.32272 | P62: =SUM(D62:O62) -> 10678.655 | Q62: =P62/$P$54*1000 -> 6.2504456 | R62: =P62/$P$71 -> 0.25135032
C63: 废料 | D63: =厨电!D63+洗碗机!D63 -> 57.252959 | E63: =厨电!E63+洗碗机!E63 -> 57.002864 | F63: =厨电!F63+洗碗机!F63 -> 64.879203 | G63: =厨电!G63+洗碗机!G63 -> 70.662274 | H63: =厨电!H63+洗碗机!H63 -> 69.489455 | I63: =厨电!I63+洗碗机!I63 -> 53.384992 | J63: =厨电!J63+洗碗机!J63 -> 71.178082 | K63: =厨电!K63+洗碗机!K63 -> 59.275404 | ... O63: =厨电!O63+洗碗机!O63 -> 65.575105 | P63: =SUM(D63:O63) -> 789.84571 | Q63: =P63/$P$54*1000 -> 0.46231362 | R63: =P63/$P$71 -> 0.018591103
C64: 生产耗用品 | D64: =厨电!D64+洗碗机!D64 -> 53.0242 | E64: =厨电!E64+洗碗机!E64 -> 36.116884 | F64: =厨电!F64+洗碗机!F64 -> 42.714329 | G64: =厨电!G64+洗碗机!G64 -> 47.422348 | H64: =厨电!H64+洗碗机!H64 -> 51.318559 | I64: =厨电!I64+洗碗机!I64 -> 39.89529 | J64: =厨电!J64+洗碗机!J64 -> 46.842037 | K64: =厨电!K64+洗碗机!K64 -> 42.289164 | ... O64: =厨电!O64+洗碗机!O64 -> 42.278668 | P64: =SUM(D64:O64) -> 531.69901 | Q64: =P64/$P$54*1000 -> 0.31121482 | R64: =P64/$P$71 -> 0.012514939
C65: 废品收入 | D65: =厨电!D65+洗碗机!D65 -> -103.564 | E65: =厨电!E65+洗碗机!E65 -> -102.18037 | F65: =厨电!F65+洗碗机!F65 -> -117.45292 | G65: =厨电!G65+洗碗机!G65 -> -128.53315 | H65: =厨电!H65+洗碗机!H65 -> -129.77034 | I65: =厨电!I65+洗碗机!I65 -> -98.458458 | J65: =厨电!J65+洗碗机!J65 -> -135.00403 | K65: =厨电!K65+洗碗机!K65 -> -114.14718 | ... O65: =厨电!O65+洗碗机!O65 -> -127.96095 | P65: =SUM(D65:O65) -> -1481.5863 | Q65: =P65/$P$54*1000 -> -0.86720421 | R65: =P65/$P$71 -> -0.034873042
C66: 变动能源费 | D66: =厨电!D66+洗碗机!D66 -> 70.389509 | E66: =厨电!E66+洗碗机!E66 -> 69.881588 | F66: =厨电!F66+洗碗机!F66 -> 83.956884 | G66: =厨电!G66+洗碗机!G66 -> 93.088298 | H66: =厨电!H66+洗碗机!H66 -> 99.310613 | I66: =厨电!I66+洗碗机!I66 -> 79.416529 | J66: =厨电!J66+洗碗机!J66 -> 107.19592 | K66: =厨电!K66+洗碗机!K66 -> 91.025228 | ... O66: =厨电!O66+洗碗机!O66 -> 114.91559 | P66: =SUM(D66:O66) -> 1174.1003 | Q66: =P66/$P$54*1000 -> 0.68722604 | R66: =P66/$P$71 -> 0.027635547
B67: 分摊 | C67: 分摊费用 | D67: =厨电!D67+洗碗机!D67 -> 646.83942 | E67: =厨电!E67+洗碗机!E67 -> 646.03533 | F67: =厨电!F67+洗碗机!F67 -> 647.8578 | G67: =厨电!G67+洗碗机!G67 -> 647.00655 | H67: =厨电!H67+洗碗机!H67 -> 647.02013 | I67: =厨电!I67+洗碗机!I67 -> 523.50598 | J67: =厨电!J67+洗碗机!J67 -> 522.40609 | K67: =厨电!K67+洗碗机!K67 -> 522.79092 | ... O67: =厨电!O67+洗碗机!O67 -> 523.48304 | P67: =SUM(D67:O67) -> 6896.5127 | Q67: =P67/$P$54*1000 -> 4.0366766 | R67: =P67/$P$71 -> 0.16232762
C68: IT Expense-Internal Charge Out | D68: =厨电!D68+洗碗机!D68 -> 0 | E68: =厨电!E68+洗碗机!E68 -> 0 | F68: =厨电!F68+洗碗机!F68 -> 0 | G68: =厨电!G68+洗碗机!G68 -> 0 | H68: =厨电!H68+洗碗机!H68 -> 0 | I68: =厨电!I68+洗碗机!I68 -> 0 | J68: =厨电!J68+洗碗机!J68 -> 0 | K68: =厨电!K68+洗碗机!K68 -> 0 | ... O68: =厨电!O68+洗碗机!O68 -> 0 | P68: =SUM(D68:O68) -> 0
C69: Association dues | D69: =厨电!D69+洗碗机!D69 -> 0 | E69: =厨电!E69+洗碗机!E69 -> 0 | F69: =厨电!F69+洗碗机!F69 -> 0 | G69: =厨电!G69+洗碗机!G69 -> 0 | H69: =厨电!H69+洗碗机!H69 -> 0 | I69: =厨电!I69+洗碗机!I69 -> 0 | J69: =厨电!J69+洗碗机!J69 -> 0 | K69: =厨电!K69+洗碗机!K69 -> 0 | ... O69: =厨电!O69+洗碗机!O69 -> 0 | P69: =SUM(D69:O69) -> 0
C70: G&A | D70: =厨电!D70+洗碗机!D70 -> 0 | E70: =厨电!E70+洗碗机!E70 -> 0 | F70: =厨电!F70+洗碗机!F70 -> 0 | G70: =厨电!G70+洗碗机!G70 -> 0 | H70: =厨电!H70+洗碗机!H70 -> 0 | I70: =厨电!I70+洗碗机!I70 -> 0 | J70: =厨电!J70+洗碗机!J70 -> 0 | K70: =厨电!K70+洗碗机!K70 -> 0 | ... O70: =厨电!O70+洗碗机!O70 -> 0 | P70: =SUM(D70:O70) -> 0
B71: 合计 | D71: =厨电!D71+洗碗机!D71 -> 3700.1282 | E71: =厨电!E71+洗碗机!E71 -> 3527.6003 | F71: =厨电!F71+洗碗机!F71 -> 3838.5631 | G71: =厨电!G71+洗碗机!G71 -> 3725.4835 | H71: =厨电!H71+洗碗机!H71 -> 3725.5497 | I71: =厨电!I71+洗碗机!I71 -> 3231.5589 | J71: =厨电!J71+洗碗机!J71 -> 3347.4787 | K71: =厨电!K71+洗碗机!K71 -> 3318.8085 | ... O71: =厨电!O71+洗碗机!O71 -> 3577.2563 | P71: =SUM(P55:P67) -> 42485.146
B72: 单台 | D72: =D71/D54*1000 -> 30.122016 | E72: =E71/E54*1000 -> 29.042114 | F72: =F71/F54*1000 -> 26.653542 | G72: =G71/G54*1000 -> 23.925475 | H72: =H71/H54*1000 -> 26.122028 | I72: =I71/I54*1000 -> 26.360921 | J72: =J71/J54*1000 -> 21.453108 | K72: =K71/K54*1000 -> 26.001728 | ... P72: =P71/P54*1000 -> 24.867466
B73: functional currency | D73: =厨电!D73+洗碗机!D73 -> 906.00886 | E73: =厨电!E73+洗碗机!E73 -> 863.09379 | F73: =厨电!F73+洗碗机!F73 -> 904.68398 | G73: =厨电!G73+洗碗机!G73 -> 890.55243 | H73: =厨电!H73+洗碗机!H73 -> 913.98684 | I73: =厨电!I73+洗碗机!I73 -> 909.6592 | J73: =厨电!J73+洗碗机!J73 -> 924.88143 | K73: =厨电!K73+洗碗机!K73 -> 926.9458 | ... O73: =厨电!O73+洗碗机!O73 -> 738.16084 | P73: =SUM(D73:O73) -> 10571.415 | Q73: =P73/$P$54*1000 -> 6.1876758
D74: =D72/D53 -> 0.18071729 | E74: =E72/E53 -> 0.1795777 | F74: =F72/F53 -> 0.17238033 | G74: =G72/G53 -> 0.155353 | H74: =H72/H53 -> 0.16597844 | I74: =I72/I53 -> 0.19153888 | J74: =J72/J53 -> 0.13662541 | K74: =K72/K53 -> 0.1614607 | ... P74: =P72/P53 -> 0.1597736
C76: 厨电26年实际 | Q76: =P75/P57 -> 0
A77: 年累 | C77: 科目 | D77: 25年1月 | E77: 25年2月 | F77: 25年3月 | G77: 25年4月 | H77: 25年5月 | I77: 25年6月 | J77: 25年7月 | K77: 25年8月 | L77: 25年9月 | M77: 25年10月 | N77: 25年11月 | O77: 25年12月 | P77: 合计 | Q77: 单台 | R77: 占比 | S77: 费率 | T77: 同比
A78: 125 | B78: 平均单价 | D78: 154.60918 | E78: 146.74311 | F78: 145.28535 | G78: 146.74311
A79: =SUM(D79:F79) -> 424233 | C79: 产量 | D79: =厨电!D79+洗碗机!D79 -> 144968 | E79: =厨电!E79+洗碗机!E79 -> 148887 | F79: =厨电!F79+洗碗机!F79 -> 130378 | G79: =厨电!G79+洗碗机!G79 -> 151260 | H79: =厨电!H79+洗碗机!H79 -> 100574 | I79: =厨电!I79+洗碗机!I79 -> 0 | J79: =厨电!J79+洗碗机!J79 -> 0 | K79: =厨电!K79+洗碗机!K79 -> 0 | ... O79: =厨电!O79+洗碗机!O79 -> 0 | P79: =SUM(D79:O79) -> 676067
A80: =SUM(D80:F80) -> 3883.9477 | B80: 固定制造 | C80: 折旧（含FC) | D80: =厨电!D80+洗碗机!D80 -> 1382.5836 | E80: =厨电!E80+洗碗机!E80 -> 1137.5572 | F80: =厨电!F80+洗碗机!F80 -> 1363.8069 | G80: =厨电!G80+洗碗机!G80 -> 496.59125 | H80: =厨电!H80+洗碗机!H80 -> 687.31502 | I80: =厨电!I80+洗碗机!I80 -> 0 | J80: =厨电!J80+洗碗机!J80 -> 0 | K80: =厨电!K80+洗碗机!K80 -> 0 | ... O80: =厨电!O80+洗碗机!O80 -> 0 | P80: =SUM(D80:O80) -> 5067.854 | Q80: =P80/$P$79*1000 -> 7.4960825 | R80: =P80/$P$71 -> 0.11928531 | T80: =Q80-Q32 -> -2.7498714
A81: =SUM(D81:F81) -> 388.9619 | C81: 运营费 | D81: =厨电!D81+洗碗机!D81 -> 131.60955 | E81: =厨电!E81+洗碗机!E81 -> 150.79809 | F81: =厨电!F81+洗碗机!F81 -> 106.55426 | G81: =厨电!G81+洗碗机!G81 -> 80.08298 | H81: =厨电!H81+洗碗机!H81 -> 117.05034 | I81: =厨电!I81+洗碗机!I81 -> 0 | J81: =厨电!J81+洗碗机!J81 -> 0 | K81: =厨电!K81+洗碗机!K81 -> 0 | ... O81: =厨电!O81+洗碗机!O81 -> 0 | P81: =SUM(D81:O81) -> 586.09522 | Q81: =P81/$P$79*1000 -> 0.86691884 | R81: =P81/$P$71 -> 0.013795297 | T81: =Q81-Q33 -> -0.16027579
A82: =SUM(D82:F82) -> 204.19958 | C82: 存货跌价准备 | D82: =厨电!D82+洗碗机!D82 -> -13.56806 | E82: =厨电!E82+洗碗机!E82 -> 5.09381 | F82: =厨电!F82+洗碗机!F82 -> 212.67383 | G82: =厨电!G82+洗碗机!G82 -> -164.6679 | H82: =厨电!H82+洗碗机!H82 -> 62.188 | I82: =厨电!I82+洗碗机!I82 -> 0 | J82: =厨电!J82+洗碗机!J82 -> 0 | K82: =厨电!K82+洗碗机!K82 -> 0 | ... O82: =厨电!O82+洗碗机!O82 -> 0 | P82: =SUM(D82:O82) -> 101.71968 | Q82: =P82/$P$79*1000 -> 0.15045799 | R82: =P82/$P$71 -> 0.002394241 | T82: =Q82-Q34 -> 0.82395473
A83: =SUM(D83:F83) -> 106.62743 | C83: 固定能源费 | D83: =厨电!D83+洗碗机!D83 -> 38.88392 | E83: =厨电!E83+洗碗机!E83 -> 31.28362 | F83: =厨电!F83+洗碗机!F83 -> 36.45989 | G83: =厨电!G83+洗碗机!G83 -> 32.34728 | H83: =厨电!H83+洗碗机!H83 -> 29.89808 | I83: =厨电!I83+洗碗机!I83 -> 0 | J83: =厨电!J83+洗碗机!J83 -> 0 | K83: =厨电!K83+洗碗机!K83 -> 0 | ... O83: =厨电!O83+洗碗机!O83 -> 0 | P83: =SUM(D83:O83) -> 168.87279 | Q83: =P83/$P$79*1000 -> 0.24978706 | R83: =P83/$P$71 -> 0.0039748666 | T83: =Q83-Q35 -> -0.032792445
A84: =SUM(D84:F84) -> 1636.5044 | C84: 间接人工成本-辅助人员 | D84: =厨电!D84+洗碗机!D84 -> 564.1426 | E84: =厨电!E84+洗碗机!E84 -> 519.94344 | F84: =厨电!F84+洗碗机!F84 -> 552.4184 | G84: =厨电!G84+洗碗机!G84 -> 550.41413 | H84: =厨电!H84+洗碗机!H84 -> 618.23528 | I84: =厨电!I84+洗碗机!I84 -> 0 | J84: =厨电!J84+洗碗机!J84 -> 0 | K84: =厨电!K84+洗碗机!K84 -> 0 | ... O84: =厨电!O84+洗碗机!O84 -> 0 | P84: =SUM(D84:O84) -> 2805.1538 | Q84: =P84/$P$79*1000 -> 4.1492246 | R84: =P84/$P$71 -> 0.066026696 | T84: =Q84-Q36 -> -0.52131499
A85: =SUM(D85:F85) -> 815.04894 | C85: 固定人工-白领 | D85: =厨电!D85+洗碗机!D85 -> 285.5666 | E85: =厨电!E85+洗碗机!E85 -> 266.4755 | F85: =厨电!F85+洗碗机!F85 -> 263.00684 | G85: =厨电!G85+洗碗机!G85 -> 166.01058 | H85: =厨电!H85+洗碗机!H85 -> 283.18065 | I85: =厨电!I85+洗碗机!I85 -> 0 | J85: =厨电!J85+洗碗机!J85 -> 0 | K85: =厨电!K85+洗碗机!K85 -> 0 | ... O85: =厨电!O85+洗碗机!O85 -> 0 | P85: =SUM(D85:O85) -> 1264.2402 | Q85: =P85/$P$79*1000 -> 1.8699924 | R85: =P85/$P$71 -> 0.029757228 | T85: =Q85-Q37 -> -0.086108428
A86: =SUM(D86:F86) -> 1128.1281 | C86: 半固定-班车/工作服 | D86: =厨电!D86+洗碗机!D86 -> 325.35164 | E86: =厨电!E86+洗碗机!E86 -> 550.19837 | F86: =厨电!F86+洗碗机!F86 -> 252.5781 | G86: =厨电!G86+洗碗机!G86 -> 290.93984 | H86: =厨电!H86+洗碗机!H86 -> 334.64789 | I86: =厨电!I86+洗碗机!I86 -> 0 | J86: =厨电!J86+洗碗机!J86 -> 0 | K86: =厨电!K86+洗碗机!K86 -> 0 | ... O86: =厨电!O86+洗碗机!O86 -> 0 | P86: =SUM(D86:O86) -> 1753.7158 | Q86: =P86/$P$79*1000 -> 2.5939971 | R86: =P86/$P$71 -> 0.041278329 | T86: =Q86-Q38 -> 0.32385235
A87: =SUM(D87:F87) -> 3203.6602 | B87: 变动制造 | C87: 直接人工 | D87: =厨电!D87+洗碗机!D87 -> 1041.5263 | E87: =厨电!E87+洗碗机!E87 -> 1075.6812 | F87: =厨电!F87+洗碗机!F87 -> 1086.4527 | G87: =厨电!G87+洗碗机!G87 -> 1026.409 | H87: =厨电!H87+洗碗机!H87 -> 1204.5428 | I87: =厨电!I87+洗碗机!I87 -> 0 | J87: =厨电!J87+洗碗机!J87 -> 0 | K87: =厨电!K87+洗碗机!K87 -> 0 | ... O87: =厨电!O87+洗碗机!O87 -> 0 | P87: =SUM(D87:O87) -> 5434.612 | Q87: =P87/$P$79*1000 -> 8.0385701 | R87: =P87/$P$71 -> 0.12791793 | T87: =Q87-Q39 -> 0.2238672
A88: =SUM(D88:F88) -> 197.49683 | C88: 可回收废料 | D88: =厨电!D88+洗碗机!D88 -> 65.73331 | E88: =厨电!E88+洗碗机!E88 -> 67.47993 | F88: =厨电!F88+洗碗机!F88 -> 64.28359 | G88: =厨电!G88+洗碗机!G88 -> 109.59202 | H88: =厨电!H88+洗碗机!H88 -> 51.85179 | I88: =厨电!I88+洗碗机!I88 -> 0 | J88: =厨电!J88+洗碗机!J88 -> 0 | K88: =厨电!K88+洗碗机!K88 -> 0 | ... O88: =厨电!O88+洗碗机!O88 -> 0 | P88: =SUM(D88:O88) -> 358.94064 | Q88: =P88/$P$79*1000 -> 0.53092466 | R88: =P88/$P$71 -> 0.0084486149 | T88: =Q88-Q40 -> 0.050177607
A89: =SUM(D89:F89) -> 69.00406 | C89: 生产耗用品 | D89: =厨电!D89+洗碗机!D89 -> 18.65267 | E89: =厨电!E89+洗碗机!E89 -> 37.63015 | F89: =厨电!F89+洗碗机!F89 -> 12.72124 | G89: =厨电!G89+洗碗机!G89 -> 115.70389 | H89: =厨电!H89+洗碗机!H89 -> 27.74172 | I89: =厨电!I89+洗碗机!I89 -> 0 | J89: =厨电!J89+洗碗机!J89 -> 0 | K89: =厨电!K89+洗碗机!K89 -> 0 | ... O89: =厨电!O89+洗碗机!O89 -> 0 | P89: =SUM(D89:O89) -> 212.44967 | Q89: =P89/$P$79*1000 -> 0.31424351 | R89: =P89/$P$71 -> 0.0050005635 | T89: =Q89-Q41 -> 0.26257578
A90: =SUM(D90:F90) -> -371.87022 | C90: 废品回收 | D90: =厨电!D90+洗碗机!D90 -> -122.11046 | E90: =厨电!E90+洗碗机!E90 -> -141.68703 | F90: =厨电!F90+洗碗机!F90 -> -108.07273 | G90: =厨电!G90+洗碗机!G90 -> -138.1531 | H90: =厨电!H90+洗碗机!H90 -> -105.98233 | I90: =厨电!I90+洗碗机!I90 -> 0 | J90: =厨电!J90+洗碗机!J90 -> 0 | K90: =厨电!K90+洗碗机!K90 -> 0 | ... O90: =厨电!O90+洗碗机!O90 -> 0 | P90: =SUM(D90:O90) -> -616.00565 | Q90: =P90/$P$79*1000 -> -0.91116065 | R90: =P90/$P$71 -> -0.014499318 | T90: =Q90-Q42 -> 0.083302271
A91: =SUM(D91:F91) -> 173.84496 | C91: 变动能源费 | D91: =厨电!D91+洗碗机!D91 -> 63.88775 | E91: =厨电!E91+洗碗机!E91 -> 62.01218 | F91: =厨电!F91+洗碗机!F91 -> 47.94503 | G91: =厨电!G91+洗碗机!G91 -> 62.44103 | H91: =厨电!H91+洗碗机!H91 -> 47.28477 | I91: =厨电!I91+洗碗机!I91 -> 0 | J91: =厨电!J91+洗碗机!J91 -> 0 | K91: =厨电!K91+洗碗机!K91 -> 0 | ... O91: =厨电!O91+洗碗机!O91 -> 0 | P91: =SUM(D91:O91) -> 283.57076 | Q91: =P91/$P$79*1000 -> 0.4194418 | R91: =P91/$P$71 -> 0.0066745859 | T91: =Q91-Q43 -> -0.14524777
A92: =SUM(D92:F92) -> 1244.9819 | B92: 分摊 | C92: 分摊费用 | D92: =厨电!D92+洗碗机!D92 -> 489.86078 | E92: =厨电!E92+洗碗机!E92 -> 340.4507 | F92: =厨电!F92+洗碗机!F92 -> 414.67041 | G92: =厨电!G92+洗碗机!G92 -> 363.96881 | H92: =厨电!H92+洗碗机!H92 -> 574.13819 | I92: =厨电!I92+洗碗机!I92 -> 0 | J92: =厨电!J92+洗碗机!J92 -> 0 | K92: =厨电!K92+洗碗机!K92 -> 0 | ... O92: =厨电!O92+洗碗机!O92 -> 0 | P92: =SUM(D92:O92) -> 2183.0889 | Q92: =P92/$P$79*1000 -> 3.2291014 | R92: =P92/$P$71 -> 0.051384756 | T92: =Q92-Q44 -> -0.98494302
A93: =SUM(D93:F93) -> 552.71343 | C93: IT Expense-Internal Charge Out | D93: =厨电!D93+洗碗机!D93 -> 183.51553 | E93: =厨电!E93+洗碗机!E93 -> 184.59895 | F93: =厨电!F93+洗碗机!F93 -> 184.59895 | G93: =厨电!G93+洗碗机!G93 -> 184.59895 | H93: =厨电!H93+洗碗机!H93 -> 184.59895 | I93: =厨电!I93+洗碗机!I93 -> 0 | J93: =厨电!J93+洗碗机!J93 -> 0 | K93: =厨电!K93+洗碗机!K93 -> 0 | ... O93: =厨电!O93+洗碗机!O93 -> 0 | P93: =SUM(D93:O93) -> 921.91133
A94: =SUM(D94:F94) -> 21.23472 | C94: Association dues | D94: =厨电!D94+洗碗机!D94 -> 9.64076 | E94: =厨电!E94+洗碗机!E94 -> 4.74062 | F94: =厨电!F94+洗碗机!F94 -> 6.85334 | G94: =厨电!G94+洗碗机!G94 -> 21.44317 | H94: =厨电!H94+洗碗机!H94 -> 26.29239 | I94: =厨电!I94+洗碗机!I94 -> 0 | J94: =厨电!J94+洗碗机!J94 -> 0 | K94: =厨电!K94+洗碗机!K94 -> 0 | ... O94: =厨电!O94+洗碗机!O94 -> 0 | P94: =SUM(D94:O94) -> 68.97028
A95: =SUM(D95:F95) -> 645.77263 | C95: G&A | D95: =厨电!D95+洗碗机!D95 -> 296.70449 | E95: =厨电!E95+洗碗机!E95 -> 125.85002 | F95: =厨电!F95+洗碗机!F95 -> 223.21812 | G95: =厨电!G95+洗碗机!G95 -> 157.92669 | H95: =厨电!H95+洗碗机!H95 -> 363.24685 | I95: =厨电!I95+洗碗机!I95 -> 0 | J95: =厨电!J95+洗碗机!J95 -> 0 | K95: =厨电!K95+洗碗机!K95 -> 0 | ... O95: =厨电!O95+洗碗机!O95 -> 0 | P95: =SUM(D95:O95) -> 1166.9462
A96: =SUM(D96:F96) -> 12680.536 | B96: 合计 | D96: =厨电!D96+洗碗机!D96 -> 4272.1202 | E96: =厨电!E96+洗碗机!E96 -> 4102.9172 | F96: =厨电!F96+洗碗机!F96 -> 4305.4984 | G96: =厨电!G96+洗碗机!G96 -> 2991.6798 | H96: =厨电!H96+洗碗机!H96 -> 3932.0922 | I96: =厨电!I96+洗碗机!I96 -> 0 | J96: =厨电!J96+洗碗机!J96 -> 0 | K96: =厨电!K96+洗碗机!K96 -> 0 | ... O96: =厨电!O96+洗碗机!O96 -> 0 | P96: =SUM(P80:P92) -> 19604.308
A97: =A96/A79*1000 -> 29.890498 | B97: 单台 | D97: =D96/D79*1000 -> 29.469402 | E97: =E96/E79*1000 -> 27.557256 | F97: =F96/F79*1000 -> 33.023197 | G97: =G96/G79*1000 -> 19.778394 | H97: =H96/H79*1000 -> 39.096508 | I97: =I96/I79*1000 -> #DIV/0! | J97: =J96/J79*1000 -> #DIV/0! | K97: =K96/K79*1000 -> #DIV/0! | ... P97: =P96/P79*1000 -> 28.997581
A98: =SUM(D98:F98) -> 2195.8932 | B98: functional currency | D98: =厨电!D98+洗碗机!D98 -> 795.757 | E98: =厨电!E98+洗碗机!E98 -> 616.84592 | F98: =厨电!F98+洗碗机!F98 -> 783.29026 | G98: =厨电!G98+洗碗机!G98 -> 269.96062 | H98: =厨电!H98+洗碗机!H98 -> 462.75307 | I98: =厨电!I98+洗碗机!I98 -> 0 | J98: =厨电!J98+洗碗机!J98 -> 0 | K98: =厨电!K98+洗碗机!K98 -> 0 | ... O98: =厨电!O98+洗碗机!O98 -> 0 | Q98: =P98/$P$54*1000 -> 0
A99: =A97/A78 -> 0.23912399 | C99: 制造费率 | D99: =D97/D78 -> 0.19060577 | E99: =E97/E78 -> 0.1877925 | F99: =F97/F78 -> 0.22729888 | G99: =G97/G78 -> 0.13478243 | H99: =H97/H78 -> #DIV/0! | I99: =I97/I78 -> #DIV/0! | J99: =J97/J78 -> #DIV/0! | K99: =K97/K78 -> #DIV/0! | ... P99: =P97/P78 -> #DIV/0!
C101: 厨电26年预算 | Q101: =P99/P80 -> #DIV/0!
A102: 年累 | C102: 科目 | D102: 25年1月 | E102: 25年2月 | F102: 25年3月 | G102: 25年4月 | H102: 25年5月 | I102: 25年6月 | J102: 25年7月 | K102: 25年8月 | L102: 25年9月 | M102: 25年10月 | N102: 25年11月 | O102: 25年12月 | P102: 合计 | Q102: 单台 | R102: 占比 | S102: 费率 | T102: 同比
A103: 125 | B103: 平均单价 | D103: =(厨电!D103*厨电!D104+洗碗机!D103*洗碗机!D104)/(洗碗机!D104+厨电!D104) -> 151.48905 | E103: =(厨电!E103*厨电!E104+洗碗机!E103*洗碗机!E104)/(洗碗机!E104+厨电!E104) -> 151.57333 | F103: =(厨电!F103*厨电!F104+洗碗机!F103*洗碗机!F104)/(洗碗机!F104+厨电!F104) -> 153.42198 | G103: =(厨电!G103*厨电!G104+洗碗机!G103*洗碗机!G104)/(洗碗机!G104+厨电!G104) -> 152.77036 | H103: =(厨电!H103*厨电!H104+洗碗机!H103*洗碗机!H104)/(洗碗机!H104+厨电!H104) -> 155.21572 | I103: =(厨电!I103*厨电!I104+洗碗机!I103*洗碗机!I104)/(洗碗机!I104+厨电!I104) -> 153.92994 | J103: =(厨电!J103*厨电!J104+洗碗机!J103*洗碗机!J104)/(洗碗机!J104+厨电!J104) -> 154.11332 | K103: =(厨电!K103*厨电!K104+洗碗机!K103*洗碗机!K104)/(洗碗机!K104+厨电!K104) -> 153.74523 | ... P103: =(厨电!P103*厨电!P104+洗碗机!P103*洗碗机!P104)/(洗碗机!P104+厨电!P104) -> 152.3758 | Q103: =P103 -> 152.3758
A104: =SUM(D104:F104) -> 490968 | C104: 产量 | D104: =厨电!D104+洗碗机!D104 -> 167167 | E104: =厨电!E104+洗碗机!E104 -> 166650 | F104: =厨电!F104+洗碗机!F104 -> 157151 | G104: =厨电!G104+洗碗机!G104 -> 152754 | H104: =厨电!H104+洗碗机!H104 -> 108593 | I104: =厨电!I104+洗碗机!I104 -> 163370 | J104: =厨电!J104+洗碗机!J104 -> 128255 | K104: =厨电!K104+洗碗机!K104 -> 120755 | ... O104: =厨电!O104+洗碗机!O104 -> 131981 | P104: =SUM(D104:O104) -> 1818829 | Q104: =P104/12 -> 151569.08
...

Sheet 厨电
C2: 24年实际 | V2: 额 | AH2: 单台 | AT2: 费率
B3: 千欧 | C3: 科目 | D3: 24年1月 | E3: 24年2月 | F3: 24年3月 | G3: 24年4月 | H3: 24年5月 | I3: 24年6月 | J3: 24年7月 | K3: 24年8月 | L3: 24年9月 | M3: 24年10月 | N3: 24年11月 | O3: 24年12月 | P3: 合计 | Q3: 单台 | R3: 占比 | S3: 费率 | T3: 同比 | U3: 备注 | V3: 2月年累 | W3: 3月年累 | X3: 4月年累 | Y3: 5月年累 | Z3: 6月年累 | AA3: 7月年累 | AB3: 8月年累 | AC3: 9月年累 | AD3: 10月年累 | AE3: 11月年累 | AF3: 12月年累 | AH3: 2月年累 | AI3: 3月年累 | AJ3: 4月年累 | AK3: 5月年累 | AL3: 6月年累 | AM3: 7月年累 | AN3: 8月年累 | AO3: 9月年累 | AP3: 10月年累 | AQ3: 11月年累 | AR3: 12月年累 | AT3: 2月年累 | AU3: 3月年累 | AV3: 4月年累 | AW3: 5月年累 | AX3: 6月年累 | AY3: 7月年累 | AZ3: 8月年累 | BA3: 9月年累 | BB3: 10月年累 | BC3: 11月年累 | BD3: 12月年累
B4: 平均单价 | D4: 132.50001 | E4: 125.23284 | F4: 123.16608 | G4: 121.99032 | H4: 122.66935 | I4: 119.61187 | J4: 122.49963 | K4: 123.97736 | L4: 116.13849 | M4: 123.19497 | N4: 117.49913 | O4: 120.2801 | P4: =AVERAGE(D4:O4) -> 122.39668 | AT4: =$P$4 -> 122.39668 | AU4: =$P$4 -> 122.39668 | AV4: =$P$4 -> 122.39668 | AW4: =$P$4 -> 122.39668 | AX4: =$P$4 -> 122.39668 | AY4: =$P$4 -> 122.39668 | AZ4: =$P$4 -> 122.39668 | BA4: =$P$4 -> 122.39668 | ... BD4: =$P$4 -> 122.39668
B5: 产量 | D5: ='24年CK1'!D1+'24年CK2'!D1 -> 87337 | E5: ='24年CK1'!E1+'24年CK2'!E1 -> 110212 | F5: ='24年CK1'!F1+'24年CK2'!F1 -> 113626 | G5: ='24年CK1'!G1+'24年CK2'!G1 -> 109618 | H5: ='24年CK1'!H1+'24年CK2'!H1 -> 153929 | I5: ='24年CK1'!I1+'24年CK2'!I1 -> 121229 | J5: ='24年CK1'!J1+'24年CK2'!J1 -> 128355 | K5: ='24年CK1'!K1+'24年CK2'!K1 -> 58349 | ... O5: ='24年CK1'!O1+'24年CK2'!O1 -> 72817 | P5: =SUM(D5:O5) -> 1287462 | V5: =D5+E5 -> 197549 | W5: =V5+F5 -> 311175 | X5: =W5+G5 -> 420793 | Y5: =X5+H5 -> 574722 | Z5: =Y5+I5 -> 695951 | AA5: =Z5+J5 -> 824306 | AB5: =AA5+K5 -> 882655 | AC5: =AB5+L5 -> 992562 | AD5: =AC5+M5 -> 1108667 | ... AF5: =AE5+O5 -> 1287462
B6: 固定制造 | C6: 折旧-不含FC | D6: =('24年CK1'!D144+'24年CK2'!D136)/1000 -> 85.774829 | E6: =('24年CK1'!E144+'24年CK2'!E136)/1000 -> 351.93788 | F6: =('24年CK1'!F144+'24年CK2'!F136)/1000 -> 352.07193 | G6: =('24年CK1'!G144+'24年CK2'!G136)/1000 -> 339.96967 | H6: =('24年CK1'!H144+'24年CK2'!H136)/1000 -> 403.5684 | I6: =('24年CK1'!I144+'24年CK2'!I136)/1000 -> 524.02594 | J6: =('24年CK1'!J144+'24年CK2'!J136)/1000 -> 431.48432 | K6: =('24年CK1'!K144+'24年CK2'!K136)/1000 -> 417.90218 | ... O6: =('24年CK1'!O144+'24年CK2'!O136)/1000 -> 471.31418 | P6: =SUM(D6:O6) -> 4549.6106 | Q6: =P6/$P$5*1000 -> 3.5337824 | R6: =P6/$P$22 -> 0.12420254 | S6: =Q6/$P$4 -> 0.028871554 | V6: =D6+E6 -> 437.71271 | W6: =V6+F6 -> 789.78464 | X6: =W6+G6 -> 1129.7543 | Y6: =X6+H6 -> 1533.3227 | Z6: =Y6+I6 -> 2057.3487 | AA6: =Z6+J6 -> 2488.833 | AB6: =AA6+K6 -> 2906.7352 | AC6: =AB6+L6 -> 3167.3488 | AD6: =AC6+M6 -> 3614.9724 | ... AF6: =AE6+O6 -> 4549.6106 | AH6: =V6/V$5*1000 -> 2.2157172 | AI6: =W6/W$5*1000 -> 2.5380723 | AJ6: =X6/X$5*1000 -> 2.684822 | AK6: =Y6/Y$5*1000 -> 2.6679381 | AL6: =Z6/Z$5*1000 -> 2.9561688 | AM6: =AA6/AA$5*1000 -> 3.0193071 | AN6: =AB6/AB$5*1000 -> 3.2931725 | AO6: =AC6/AC$5*1000 -> 3.1910841 | ... AR6: =AF6/AF$5*1000 -> 3.5337824 | AT6: =AH6/AT$4 -> 0.018102755 | AU6: =AI6/AU$4 -> 0.020736447 | AV6: =AJ6/AV$4 -> 0.021935415 | AW6: =AK6/AW$4 -> 0.021797471 | AX6: =AL6/AX$4 -> 0.024152361 | AY6: =AM6/AY$4 -> 0.024668211 | AZ6: =AN6/AZ$4 -> 0.026905734 | BA6: =AO6/BA$4 -> 0.026071656 | ... BD6: =AR6/BD$4 -> 0.028871554
C7: 运营费 | D7: =('24年CK1'!D145+'24年CK2'!D137)/1000 -> 79.235716 | E7: =('24年CK1'!E145+'24年CK2'!E137)/1000 -> 99.823853 | F7: =('24年CK1'!F145+'24年CK2'!F137)/1000 -> 148.24952 | G7: =('24年CK1'!G145+'24年CK2'!G137)/1000 -> 39.559414 | H7: =('24年CK1'!H145+'24年CK2'!H137)/1000 -> 105.48256 | I7: =('24年CK1'!I145+'24年CK2'!I137)/1000 -> 101.51889 | J7: =('24年CK1'!J145+'24年CK2'!J137)/1000 -> 236.5676 | K7: =('24年CK1'!K145+'24年CK2'!K137)/1000 -> -51.40182 | ... O7: =('24年CK1'!O145+'24年CK2'!O137)/1000 -> 163.94473 | P7: =SUM(D7:O7) -> 1286.7491 | Q7: =P7/$P$5*1000 -> 0.9994463 | R7: =P7/$P$22 -> 0.035127735 | S7: =Q7/$P$4 -> 0.0081656324 | V7: =D7+E7 -> 179.05957 | W7: =V7+F7 -> 327.30909 | X7: =W7+G7 -> 366.8685 | Y7: =X7+H7 -> 472.35107 | Z7: =Y7+I7 -> 573.86995 | AA7: =Z7+J7 -> 810.43755 | AB7: =AA7+K7 -> 759.03573 | AC7: =AB7+L7 -> 907.11574 | AD7: =AC7+M7 -> 1011.2655 | ... AF7: =AE7+O7 -> 1286.7491 | AH7: =V7/V$5*1000 -> 0.90640585 | AI7: =W7/W$5*1000 -> 1.0518489 | AJ7: =X7/X$5*1000 -> 0.8718503 | AK7: =Y7/Y$5*1000 -> 0.82187747 | AL7: =Z7/Z$5*1000 -> 0.82458385 | AM7: =AA7/AA$5*1000 -> 0.98317561 | AN7: =AB7/AB$5*1000 -> 0.85994611 | AO7: =AC7/AC$5*1000 -> 0.91391343 | ... AR7: =AF7/AF$5*1000 -> 0.9994463 | AT7: =AH7/AT$4 -> 0.0074054774 | AU7: =AI7/AU$4 -> 0.00859377 | AV7: =AJ7/AV$4 -> 0.0071231532 | AW7: =AK7/AW$4 -> 0.0067148674 | AX7: =AL7/AX$4 -> 0.0067369789 | AY7: =AM7/AY$4 -> 0.0080326983 | AZ7: =AN7/AZ$4 -> 0.0070258941 | BA7: =AO7/BA$4 -> 0.0074668155 | ... BD7: =AR7/BD$4 -> 0.0081656324
C8: 存货跌价准备 | D8: =('24年CK1'!D146+'24年CK2'!D138)/1000 -> 26 | E8: =('24年CK1'!E146+'24年CK2'!E138)/1000 -> 26 | F8: =('24年CK1'!F146+'24年CK2'!F138)/1000 -> 12.200314 | G8: =('24年CK1'!G146+'24年CK2'!G138)/1000 -> 26 | H8: =('24年CK1'!H146+'24年CK2'!H138)/1000 -> 26 | I8: =('24年CK1'!I146+'24年CK2'!I138)/1000 -> 26 | J8: =('24年CK1'!J146+'24年CK2'!J138)/1000 -> 373.56136 | K8: =('24年CK1'!K146+'24年CK2'!K138)/1000 -> 373.56136 | ... O8: =('24年CK1'!O146+'24年CK2'!O138)/1000 -> 506.99463 | P8: =SUM(D8:O8) -> 2787.7922 | Q8: =P8/$P$5*1000 -> 2.1653394 | R8: =P8/$P$22 -> 0.076105607 | S8: =Q8/$P$4 -> 0.017691161 | V8: =D8+E8 -> 52 | W8: =V8+F8 -> 64.200314 | X8: =W8+G8 -> 90.200314 | Y8: =X8+H8 -> 116.20031 | Z8: =Y8+I8 -> 142.20031 | AA8: =Z8+J8 -> 515.76167 | AB8: =AA8+K8 -> 889.32303 | AC8: =AB8+L8 -> 1291.9923 | AD8: =AC8+M8 -> 1786.3282 | ... AF8: =AE8+O8 -> 2787.7922 | AH8: =V8/V$5*1000 -> 0.26322583 | AI8: =W8/W$5*1000 -> 0.20631578 | AJ8: =X8/X$5*1000 -> 0.21435792 | AK8: =Y8/Y$5*1000 -> 0.20218526 | AL8: =Z8/Z$5*1000 -> 0.20432518 | AM8: =AA8/AA$5*1000 -> 0.62569201 | AN8: =AB8/AB$5*1000 -> 1.0075545 | AO8: =AC8/AC$5*1000 -> 1.3016741 | ... AR8: =AF8/AF$5*1000 -> 2.1653394 | AT8: =AH8/AT$4 -> 0.0021505962 | AU8: =AI8/AU$4 -> 0.0016856322 | AV8: =AJ8/AV$4 -> 0.0017513377 | AW8: =AK8/AW$4 -> 0.0016518851 | AX8: =AL8/AX$4 -> 0.0016693687 | AY8: =AM8/AY$4 -> 0.0051120014 | AZ8: =AN8/AZ$4 -> 0.0082318778 | BA8: =AO8/BA$4 -> 0.010634881 | ... BD8: =AR8/BD$4 -> 0.017691161
C9: 固定能源费 | D9: =('24年CK1'!D147+'24年CK2'!D139)/1000 -> 12.400184 | E9: =('24年CK1'!E147+'24年CK2'!E139)/1000 -> -1.0670255 | F9: =('24年CK1'!F147+'24年CK2'!F139)/1000 -> 16.256636 | G9: =('24年CK1'!G147+'24年CK2'!G139)/1000 -> 6.0209282 | H9: =('24年CK1'!H147+'24年CK2'!H139)/1000 -> 6.1583453 | I9: =('24年CK1'!I147+'24年CK2'!I139)/1000 -> 5.5907489 | J9: =('24年CK1'!J147+'24年CK2'!J139)/1000 -> 5.5766195 | K9: =('24年CK1'!K147+'24年CK2'!K139)/1000 -> 6.6059645 | ... O9: =('24年CK1'!O147+'24年CK2'!O139)/1000 -> 7.49769 | P9: =SUM(D9:O9) -> 81.060862 | Q9: =P9/$P$5*1000 -> 0.062961751 | R9: =P9/$P$22 -> 0.002212929 | S9: =Q9/$P$4 -> 0.00051440735 | V9: =D9+E9 -> 11.333159 | W9: =V9+F9 -> 27.589794 | X9: =W9+G9 -> 33.610723 | Y9: =X9+H9 -> 39.769068 | Z9: =Y9+I9 -> 45.359817 | AA9: =Z9+J9 -> 50.936436 | AB9: =AA9+K9 -> 57.542401 | AC9: =AB9+L9 -> 63.417406 | AD9: =AC9+M9 -> 69.850742 | ... AF9: =AE9+O9 -> 81.060862 | AH9: =V9/V$5*1000 -> 0.057368849 | AI9: =W9/W$5*1000 -> 0.088663275 | AJ9: =X9/X$5*1000 -> 0.079874719 | AK9: =Y9/Y$5*1000 -> 0.069197052 | AL9: =Z9/Z$5*1000 -> 0.065176739 | AM9: =AA9/AA$5*1000 -> 0.061793116 | AN9: =AB9/AB$5*1000 -> 0.065192403 | AO9: =AC9/AC$5*1000 -> 0.06389264 | ... AR9: =AF9/AF$5*1000 -> 0.062961751 | AT9: =AH9/AT$4 -> 0.00046871246 | AU9: =AI9/AU$4 -> 0.00072439281 | AV9: =AJ9/AV$4 -> 0.00065258893 | AW9: =AK9/AW$4 -> 0.00056535072 | AX9: =AL9/AX$4 -> 0.00053250414 | AY9: =AM9/AY$4 -> 0.00050485941 | AZ9: =AN9/AZ$4 -> 0.00053263212 | BA9: =AO9/BA$4 -> 0.00052201285 | ... BD9: =AR9/BD$4 -> 0.00051440735
C10: 间接人工成本-辅助人员 | D10: =('24年CK1'!D148+'24年CK2'!D140)/1000 -> 224.16848 | E10: =('24年CK1'!E148+'24年CK2'!E140)/1000 -> 414.34793 | F10: =('24年CK1'!F148+'24年CK2'!F140)/1000 -> 456.9152 | G10: =('24年CK1'!G148+'24年CK2'!G140)/1000 -> 424.5319 | H10: =('24年CK1'!H148+'24年CK2'!H140)/1000 -> 449.10915 | I10: =('24年CK1'!I148+'24年CK2'!I140)/1000 -> 453.03789 | J10: =('24年CK1'!J148+'24年CK2'!J140)/1000 -> 415.64357 | K10: =('24年CK1'!K148+'24年CK2'!K140)/1000 -> 394.26511 | ... O10: =('24年CK1'!O148+'24年CK2'!O140)/1000 -> 473.50299 | P10: =SUM(D10:O10) -> 5078.6667 | Q10: =P10/$P$5*1000 -> 3.9447119 | R10: =P10/$P$22 -> 0.13864556 | S10: =Q10/$P$4 -> 0.032228913 | V10: =D10+E10 -> 638.5164 | W10: =V10+F10 -> 1095.4316 | X10: =W10+G10 -> 1519.9635 | Y10: =X10+H10 -> 1969.0726 | Z10: =Y10+I10 -> 2422.1105 | AA10: =Z10+J10 -> 2837.7541 | AB10: =AA10+K10 -> 3232.0192 | AC10: =AB10+L10 -> 3702.2507 | AD10: =AC10+M10 -> 4178.6777 | ... AF10: =AE10+O10 -> 5078.6667 | AH10: =V10/V$5*1000 -> 3.2321925 | AI10: =W10/W$5*1000 -> 3.5203072 | AJ10: =X10/X$5*1000 -> 3.6121407 | AK10: =Y10/Y$5*1000 -> 3.4261306 | AL10: =Z10/Z$5*1000 -> 3.4802889 | AM10: =AA10/AA$5*1000 -> 3.4425979 | AN10: =AB10/AB$5*1000 -> 3.6617016 | AO10: =AC10/AC$5*1000 -> 3.7299944 | ... AR10: =AF10/AF$5*1000 -> 3.9447119 | AT10: =AH10/AT$4 -> 0.026407518 | AU10: =AI10/AU$4 -> 0.02876146 | AV10: =AJ10/AV$4 -> 0.029511753 | AW10: =AK10/AW$4 -> 0.027992023 | AX10: =AL10/AX$4 -> 0.028434504 | AY10: =AM10/AY$4 -> 0.028126563 | AZ10: =AN10/AZ$4 -> 0.029916674 | BA10: =AO10/BA$4 -> 0.030474637 | ... BD10: =AR10/BD$4 -> 0.032228913
C11: 固定人工-白领 | D11: =('24年CK1'!D149+'24年CK2'!D141)/1000 -> 122.23615 | E11: =('24年CK1'!E149+'24年CK2'!E141)/1000 -> 84.280247 | F11: =('24年CK1'!F149+'24年CK2'!F141)/1000 -> 158.11684 | G11: =('24年CK1'!G149+'24年CK2'!G141)/1000 -> 163.96534 | H11: =('24年CK1'!H149+'24年CK2'!H141)/1000 -> 195.26381 | I11: =('24年CK1'!I149+'24年CK2'!I141)/1000 -> 201.13422 | J11: =('24年CK1'!J149+'24年CK2'!J141)/1000 -> 244.86138 | K11: =('24年CK1'!K149+'24年CK2'!K141)/1000 -> 223.19253 | ... O11: =('24年CK1'!O149+'24年CK2'!O141)/1000 -> 184.89072 | P11: =SUM(D11:O11) -> 2090.5711 | Q11: =P11/$P$5*1000 -> 1.6237925 | R11: =P11/$P$22 -> 0.057071753 | S11: =Q11/$P$4 -> 0.013266638 | V11: =D11+E11 -> 206.5164 | W11: =V11+F11 -> 364.63324 | X11: =W11+G11 -> 528.59858 | Y11: =X11+H11 -> 723.86239 | Z11: =Y11+I11 -> 924.99662 | AA11: =Z11+J11 -> 1169.858 | AB11: =AA11+K11 -> 1393.0505 | AC11: =AB11+L11 -> 1594.5213 | AD11: =AC11+M11 -> 1687.354 | ... AF11: =AE11+O11 -> 2090.5711 | AH11: =V11/V$5*1000 -> 1.0453933 | AI11: =W11/W$5*1000 -> 1.1717948 | AJ11: =X11/X$5*1000 -> 1.2561962 | AK11: =Y11/Y$5*1000 -> 1.2595001 | AL11: =Z11/Z$5*1000 -> 1.3291117 | AM11: =AA11/AA$5*1000 -> 1.4192035 | AN11: =AB11/AB$5*1000 -> 1.5782503 | AO11: =AC11/AC$5*1000 -> 1.6064702 | ... AR11: =AF11/AF$5*1000 -> 1.6237925 | AT11: =AH11/AT$4 -> 0.0085410266 | AU11: =AI11/AU$4 -> 0.0095737464 | AV11: =AJ11/AV$4 -> 0.010263319 | AW11: =AK11/AW$4 -> 0.010290312 | AX11: =AL11/AX$4 -> 0.01085905 | AY11: =AM11/AY$4 -> 0.011595115 | AZ11: =AN11/AZ$4 -> 0.012894552 | BA11: =AO11/BA$4 -> 0.013125112 | ... BD11: =AR11/BD$4 -> 0.013266638
C12: 半固定-班车/工作服 | D12: =('24年CK1'!D150+'24年CK2'!D142)/1000 -> 142.51708 | E12: =('24年CK1'!E150+'24年CK2'!E142)/1000 -> 171.20656 | F12: =('24年CK1'!F150+'24年CK2'!F142)/1000 -> 283.62613 | G12: =('24年CK1'!G150+'24年CK2'!G142)/1000 -> 231.25393 | H12: =('24年CK1'!H150+'24年CK2'!H142)/1000 -> 215.49158 | I12: =('24年CK1'!I150+'24年CK2'!I142)/1000 -> 249.63048 | J12: =('24年CK1'!J150+'24年CK2'!J142)/1000 -> 228.76015 | K12: =('24年CK1'!K150+'24年CK2'!K142)/1000 -> 189.02819 | ... O12: =('24年CK1'!O150+'24年CK2'!O142)/1000 -> 172.45257 | P12: =SUM(D12:O12) -> 2548.2886 | Q12: =P12/$P$5*1000 -> 1.9793117 | R12: =P12/$P$22 -> 0.069567257 | S12: =Q12/$P$4 -> 0.016171286 | V12: =D12+E12 -> 313.72364 | W12: =V12+F12 -> 597.34977 | X12: =W12+G12 -> 828.60369 | Y12: =X12+H12 -> 1044.0953 | Z12: =Y12+I12 -> 1293.7258 | AA12: =Z12+J12 -> 1522.4859 | AB12: =AA12+K12 -> 1711.5141 | AC12: =AB12+L12 -> 1900.2893 | AD12: =AC12+M12 -> 2216.2574 | ... AF12: =AE12+O12 -> 2548.2886 | AH12: =V12/V$5*1000 -> 1.5880801 | AI12: =W12/W$5*1000 -> 1.9196586 | AJ12: =X12/X$5*1000 -> 1.969148 | AK12: =Y12/Y$5*1000 -> 1.8166962 | AL12: =Z12/Z$5*1000 -> 1.8589322 | AM12: =AA12/AA$5*1000 -> 1.8469912 | AN12: =AB12/AB$5*1000 -> 1.9390522 | AO12: =AC12/AC$5*1000 -> 1.9145296 | ... AR12: =AF12/AF$5*1000 -> 1.9793117 | AT12: =AH12/AT$4 -> 0.012974863 | AU12: =AI12/AU$4 -> 0.015683911 | AV12: =AJ12/AV$4 -> 0.016088247 | AW12: =AK12/AW$4 -> 0.014842692 | AX12: =AL12/AX$4 -> 0.015187767 | AY12: =AM12/AY$4 -> 0.015090206 | AZ12: =AN12/AZ$4 -> 0.015842359 | BA12: =AO12/BA$4 -> 0.015642006 | ... BD12: =AR12/BD$4 -> 0.016171286
B13: 变动制造 | C13: 直接人工 | D13: =('24年CK1'!D151+'24年CK2'!D143)/1000 -> 421.24519 | E13: =('24年CK1'!E151+'24年CK2'!E143)/1000 -> 551.94817 | F13: =('24年CK1'!F151+'24年CK2'!F143)/1000 -> 421.62088 | G13: =('24年CK1'!G151+'24年CK2'!G143)/1000 -> 612.54001 | H13: =('24年CK1'!H151+'24年CK2'!H143)/1000 -> 635.19802 | I13: =('24年CK1'!I151+'24年CK2'!I143)/1000 -> 679.02858 | J13: =('24年CK1'!J151+'24年CK2'!J143)/1000 -> 619.58928 | K13: =('24年CK1'!K151+'24年CK2'!K143)/1000 -> 534.65847 | ... O13: =('24年CK1'!O151+'24年CK2'!O143)/1000 -> 456.13529 | P13: =SUM(D13:O13) -> 6732.5969 | Q13: =P13/$P$5*1000 -> 5.2293558 | R13: =P13/$P$22 -> 0.18379719 | S13: =Q13/$P$4 -> 0.042724654 | V13: =D13+E13 -> 973.19336 | W13: =V13+F13 -> 1394.8142 | X13: =W13+G13 -> 2007.3542 | Y13: =X13+H13 -> 2642.5523 | Z13: =Y13+I13 -> 3321.5808 | AA13: =Z13+J13 -> 3941.1701 | AB13: =AA13+K13 -> 4475.8286 | AC13: =AB13+L13 -> 5091.447 | AD13: =AC13+M13 -> 5705.6343 | ... AF13: =AE13+O13 -> 6732.5969 | AH13: =V13/V$5*1000 -> 4.9263391 | AI13: =W13/W$5*1000 -> 4.482411 | AJ13: =X13/X$5*1000 -> 4.7704079 | AK13: =Y13/Y$5*1000 -> 4.5979661 | AL13: =Z13/Z$5*1000 -> 4.7727223 | AM13: =AA13/AA$5*1000 -> 4.7811979 | AN13: =AB13/AB$5*1000 -> 5.0708698 | AO13: =AC13/AC$5*1000 -> 5.129601 | ... AR13: =AF13/AF$5*1000 -> 5.2293558 | AT13: =AH13/AT$4 -> 0.04024896 | AU13: =AI13/AU$4 -> 0.036621998 | AV13: =AJ13/AV$4 -> 0.038974978 | AW13: =AK13/AW$4 -> 0.037566101 | AX13: =AL13/AX$4 -> 0.038993887 | AY13: =AM13/AY$4 -> 0.039063134 | AZ13: =AN13/AZ$4 -> 0.041429799 | BA13: =AO13/BA$4 -> 0.041909642 | ... BD13: =AR13/BD$4 -> 0.042724654
C14: 废料 | D14: =('24年CK1'!D152+'24年CK2'!D144)/1000 -> 20.146721 | E14: =('24年CK1'!E152+'24年CK2'!E144)/1000 -> 53.452345 | F14: =('24年CK1'!F152+'24年CK2'!F144)/1000 -> 38.048936 | G14: =('24年CK1'!G152+'24年CK2'!G144)/1000 -> 61.072459 | H14: =('24年CK1'!H152+'24年CK2'!H144)/1000 -> 94.598057 | I14: =('24年CK1'!I152+'24年CK2'!I144)/1000 -> 50.382744 | J14: =('24年CK1'!J152+'24年CK2'!J144)/1000 -> 63.028552 | K14: =('24年CK1'!K152+'24年CK2'!K144)/1000 -> 32.375367 | ... O14: =('24年CK1'!O152+'24年CK2'!O144)/1000 -> 52.074158 | P14: =SUM(D14:O14) -> 579.12434 | Q14: =P14/$P$5*1000 -> 0.44981859 | R14: =P14/$P$22 -> 0.015809862 | S14: =Q14/$P$4 -> 0.0036750881 | V14: =D14+E14 -> 73.599065 | W14: =V14+F14 -> 111.648 | X14: =W14+G14 -> 172.72046 | Y14: =X14+H14 -> 267.31852 | Z14: =Y14+I14 -> 317.70126 | AA14: =Z14+J14 -> 380.72981 | AB14: =AA14+K14 -> 413.10518 | AC14: =AB14+L14 -> 450.34704 | AD14: =AC14+M14 -> 496.81843 | ... AF14: =AE14+O14 -> 579.12434 | AH14: =V14/V$5*1000 -> 0.37256106 | AI14: =W14/W$5*1000 -> 0.35879489 | AJ14: =X14/X$5*1000 -> 0.41046419 | AK14: =Y14/Y$5*1000 -> 0.46512665 | AL14: =Z14/Z$5*1000 -> 0.45649947 | AM14: =AA14/AA$5*1000 -> 0.46187922 | AN14: =AB14/AB$5*1000 -> 0.46802565 | AO14: =AC14/AC$5*1000 -> 0.45372183 | ... AR14: =AF14/AF$5*1000 -> 0.44981859 | AT14: =AH14/AT$4 -> 0.0030438821 | AU14: =AI14/AU$4 -> 0.0029314103 | AV14: =AJ14/AV$4 -> 0.0033535566 | AW14: =AK14/AW$4 -> 0.0038001574 | AX14: =AL14/AX$4 -> 0.003729672 | AY14: =AM14/AY$4 -> 0.0037736254 | AZ14: =AN14/AZ$4 -> 0.0038238427 | BA14: =AO14/BA$4 -> 0.0037069782 | ... BD14: =AR14/BD$4 -> 0.0036750881
C15: 生产耗用品 | D15: =('24年CK1'!D153+'24年CK2'!D145)/1000 -> -5.3140542 | E15: =('24年CK1'!E153+'24年CK2'!E145)/1000 -> 2.6393653 | F15: =('24年CK1'!F153+'24年CK2'!F145)/1000 -> 15.297229 | G15: =('24年CK1'!G153+'24年CK2'!G145)/1000 -> 47.314716 | H15: =('24年CK1'!H153+'24年CK2'!H145)/1000 -> 36.021673 | I15: =('24年CK1'!I153+'24年CK2'!I145)/1000 -> 24.306903 | J15: =('24年CK1'!J153+'24年CK2'!J145)/1000 -> -22.42083 | K15: =('24年CK1'!K153+'24年CK2'!K145)/1000 -> 117.45385 | ... O15: =('24年CK1'!O153+'24年CK2'!O145)/1000 -> 61.90531 | P15: =SUM(D15:O15) -> 386.72453 | Q15: =P15/$P$5*1000 -> 0.30037743 | R15: =P15/$P$22 -> 0.010557424 | S15: =Q15/$P$4 -> 0.0024541305 | V15: =D15+E15 -> -2.6746889 | W15: =V15+F15 -> 12.62254 | X15: =W15+G15 -> 59.937256 | Y15: =X15+H15 -> 95.958929 | Z15: =Y15+I15 -> 120.26583 | AA15: =Z15+J15 -> 97.845002 | AB15: =AA15+K15 -> 215.29885 | AC15: =AB15+L15 -> 258.07749 | AD15: =AC15+M15 -> 286.69124 | ... AF15: =AE15+O15 -> 386.72453 | AH15: =V15/V$5*1000 -> -0.01353937 | AI15: =W15/W$5*1000 -> 0.04056412 | AJ15: =X15/X$5*1000 -> 0.14243881 | AK15: =Y15/Y$5*1000 -> 0.16696582 | AL15: =Z15/Z$5*1000 -> 0.1728079 | AM15: =AA15/AA$5*1000 -> 0.11869985 | AN15: =AB15/AB$5*1000 -> 0.24392186 | AO15: =AC15/AC$5*1000 -> 0.26001145 | ... AR15: =AF15/AF$5*1000 -> 0.30037743 | AT15: =AH15/AT$4 -> -0.00011061877 | AU15: =AI15/AU$4 -> 0.0003314152 | AV15: =AJ15/AV$4 -> 0.0011637474 | AW15: =AK15/AW$4 -> 0.0013641368 | AX15: =AL15/AX$4 -> 0.0014118676 | AY15: =AM15/AY$4 -> 0.00096979635 | AZ15: =AN15/AZ$4 -> 0.0019928797 | BA15: =AO15/BA$4 -> 0.0021243342 | ... BD15: =AR15/BD$4 -> 0.0024541305
C16: 废品收入 | D16: =('24年CK1'!D154+'24年CK2'!D146)/1000 -> -64.159226 | E16: =('24年CK1'!E154+'24年CK2'!E146)/1000 -> -81.22218 | F16: =('24年CK1'!F154+'24年CK2'!F146)/1000 -> -93.278408 | G16: =('24年CK1'!G154+'24年CK2'!G146)/1000 -> -96.845092 | H16: =('24年CK1'!H154+'24年CK2'!H146)/1000 -> -132.97674 | I16: =('24年CK1'!I154+'24年CK2'!I146)/1000 -> -100.33 | J16: =('24年CK1'!J154+'24年CK2'!J146)/1000 -> -115.20764 | K16: =('24年CK1'!K154+'24年CK2'!K146)/1000 -> -77.008382 | ... O16: =('24年CK1'!O154+'24年CK2'!O146)/1000 -> -68.619842 | P16: =SUM(D16:O16) -> -1123.5815 | Q16: =P16/$P$5*1000 -> -0.87271045 | R16: =P16/$P$22 -> -0.030673325 | S16: =Q16/$P$4 -> -0.0071301807 | V16: =D16+E16 -> -145.38141 | W16: =V16+F16 -> -238.65981 | X16: =W16+G16 -> -335.50491 | Y16: =X16+H16 -> -468.48164 | Z16: =Y16+I16 -> -568.81164 | AA16: =Z16+J16 -> -684.01929 | AB16: =AA16+K16 -> -761.02767 | AC16: =AB16+L16 -> -847.18663 | AD16: =AC16+M16 -> -946.67481 | ... AF16: =AE16+O16 -> -1123.5815 | AH16: =V16/V$5*1000 -> -0.7359258 | AI16: =W16/W$5*1000 -> -0.76696333 | AJ16: =X16/X$5*1000 -> -0.7973158 | AK16: =Y16/Y$5*1000 -> -0.81514479 | AL16: =Z16/Z$5*1000 -> -0.81731565 | AM16: =AA16/AA$5*1000 -> -0.82981234 | AN16: =AB16/AB$5*1000 -> -0.86220286 | AO16: =AC16/AC$5*1000 -> -0.85353523 | ... AR16: =AF16/AF$5*1000 -> -0.87271045 | AT16: =AH16/AT$4 -> -0.0060126288 | AU16: =AI16/AU$4 -> -0.0062662102 | AV16: =AJ16/AV$4 -> -0.0065141946 | AW16: =AK16/AW$4 -> -0.0066598603 | AX16: =AL16/AX$4 -> -0.0066775965 | AY16: =AM16/AY$4 -> -0.0067796964 | AZ16: =AN16/AZ$4 -> -0.0070443321 | BA16: =AO16/BA$4 -> -0.0069735161 | ... BD16: =AR16/BD$4 -> -0.0071301807
C17: 变动能源费 | D17: =('24年CK1'!D155+'24年CK2'!D147)/1000 -> 128.91707 | E17: =('24年CK1'!E155+'24年CK2'!E147)/1000 -> 13.511551 | F17: =('24年CK1'!F155+'24年CK2'!F147)/1000 -> 76.888153 | G17: =('24年CK1'!G155+'24年CK2'!G147)/1000 -> 91.758476 | H17: =('24年CK1'!H155+'24年CK2'!H147)/1000 -> 105.74127 | I17: =('24年CK1'!I155+'24年CK2'!I147)/1000 -> 74.111514 | J17: =('24年CK1'!J155+'24年CK2'!J147)/1000 -> 59.160388 | K17: =('24年CK1'!K155+'24年CK2'!K147)/1000 -> 78.859311 | ... O17: =('24年CK1'!O155+'24年CK2'!O147)/1000 -> 76.976366 | P17: =SUM(D17:O17) -> 964.90888 | Q17: =P17/$P$5*1000 -> 0.74946591 | R17: =P17/$P$22 -> 0.026341625 | S17: =Q17/$P$4 -> 0.0061232536 | V17: =D17+E17 -> 142.42863 | W17: =V17+F17 -> 219.31678 | X17: =W17+G17 -> 311.07525 | Y17: =X17+H17 -> 416.81652 | Z17: =Y17+I17 -> 490.92804 | AA17: =Z17+J17 -> 550.08843 | AB17: =AA17+K17 -> 628.94774 | AC17: =AB17+L17 -> 707.51845 | AD17: =AC17+M17 -> 789.57736 | ... AF17: =AE17+O17 -> 964.90888 | AH17: =V17/V$5*1000 -> 0.72097872 | AI17: =W17/W$5*1000 -> 0.70480205 | AJ17: =X17/X$5*1000 -> 0.73925958 | AK17: =Y17/Y$5*1000 -> 0.72524894 | AL17: =Z17/Z$5*1000 -> 0.70540604 | AM17: =AA17/AA$5*1000 -> 0.66733522 | AN17: =AB17/AB$5*1000 -> 0.7125635 | AO17: =AC17/AC$5*1000 -> 0.71282041 | ... AR17: =AF17/AF$5*1000 -> 0.74946591 | AT17: =AH17/AT$4 -> 0.0058905088 | AU17: =AI17/AU$4 -> 0.0057583429 | AV17: =AJ17/AV$4 -> 0.0060398662 | AW17: =AK17/AW$4 -> 0.0059253972 | AX17: =AL17/AX$4 -> 0.0057632775 | AY17: =AM17/AY$4 -> 0.005452233 | AZ17: =AN17/AZ$4 -> 0.0058217551 | BA17: =AO17/BA$4 -> 0.0058238541 | ... BD17: =AR17/BD$4 -> 0.0061232536
B18: 分摊 | C18: 分摊费用 | D18: =('24年CK1'!D156+'24年CK2'!D148)/1000 -> 342.51653 | E18: =('24年CK1'!E156+'24年CK2'!E148)/1000 -> 306.2693 | F18: =('24年CK1'!F156+'24年CK2'!F148)/1000 -> 363.04306 | G18: =('24年CK1'!G156+'24年CK2'!G148)/1000 -> 406.73276 | H18: =('24年CK1'!H156+'24年CK2'!H148)/1000 -> 348.09051 | I18: =('24年CK1'!I156+'24年CK2'!I148)/1000 -> 320.46688 | J18: =('24年CK1'!J156+'24年CK2'!J148)/1000 -> 396.47497 | K18: =('24年CK1'!K156+'24年CK2'!K148)/1000 -> 599.95462 | ... O18: =('24年CK1'!O156+'24年CK2'!O148)/1000 -> 251.14301 | P18: =SUM(D18:O18) -> 4477.257 | Q18: =P18/$P$5*1000 -> 3.4775838 | R18: =P18/$P$22 -> 0.12222732 | S18: =Q18/$P$4 -> 0.028412403 | V18: =D18+E18 -> 648.78583 | W18: =V18+F18 -> 1011.8289 | X18: =W18+G18 -> 1418.5616 | Y18: =X18+H18 -> 1766.6522 | Z18: =Y18+I18 -> 2087.119 | AA18: =Z18+J18 -> 2483.594 | AB18: =AA18+K18 -> 3083.5486 | AC18: =AB18+L18 -> 3428.452 | AD18: =AC18+M18 -> 3800.5357 | ... AF18: =AE18+O18 -> 4477.257 | AH18: =V18/V$5*1000 -> 3.2841768 | AI18: =W18/W$5*1000 -> 3.2516394 | AJ18: =X18/X$5*1000 -> 3.3711627 | AK18: =Y18/Y$5*1000 -> 3.0739247 | AL18: =Z18/Z$5*1000 -> 2.9989454 | AM18: =AA18/AA$5*1000 -> 3.0129515 | AN18: =AB18/AB$5*1000 -> 3.4934925 | AO18: =AC18/AC$5*1000 -> 3.454144 | ... AR18: =AF18/AF$5*1000 -> 3.4775838 | AT18: =AH18/AT$4 -> 0.026832237 | AU18: =AI18/AU$4 -> 0.026566402 | AV18: =AJ18/AV$4 -> 0.027542926 | AW18: =AK18/AW$4 -> 0.025114445 | AX18: =AL18/AX$4 -> 0.024501852 | AY18: =AM18/AY$4 -> 0.024616285 | AZ18: =AN18/AZ$4 -> 0.02854238 | BA18: =AO18/BA$4 -> 0.028220896 | ... BD18: =AR18/BD$4 -> 0.028412403
C19: IT Expense-Internal Charge Out | D19: =('24年CK1'!D115+'24年CK2'!D107)/38/1000 -> 182.09794 | E19: =('24年CK1'!E115+'24年CK2'!E107)/38/1000 -> 304.45861 | F19: =('24年CK1'!F115+'24年CK2'!F107)/38/1000 -> 362.88386 | G19: =('24年CK1'!G115+'24年CK2'!G107)/38/1000 -> 320.66614 | H19: =('24年CK1'!H115+'24年CK2'!H107)/38/1000 -> 319.7274 | I19: =('24年CK1'!I115+'24年CK2'!I107)/38/1000 -> 319.91356 | J19: =('24年CK1'!J115+'24年CK2'!J107)/38/1000 -> 372.5827 | K19: =('24年CK1'!K115+'24年CK2'!K107)/38/1000 -> 375.61781 | ... O19: =('24年CK1'!O115+'24年CK2'!O107)/38/1000 -> 228.26902 | P19: =SUM(D19:O19) -> 3918.9001 | Q19: =P19/$P$5*1000 -> 3.0438958 | S19: =Q19/$P$4 -> 0.024869104 | V19: =D19+E19 -> 486.55656 | W19: =V19+F19 -> 849.44042 | X19: =W19+G19 -> 1170.1066 | Y19: =X19+H19 -> 1489.834 | Z19: =Y19+I19 -> 1809.7475 | AA19: =Z19+J19 -> 2182.3302 | AB19: =AA19+K19 -> 2557.948 | AC19: =AB19+L19 -> 2910.952 | AD19: =AC19+M19 -> 3287.7228 | ... AF19: =AE19+O19 -> 3918.9001 | AH19: =V19/V$5*1000 -> 2.4629664 | AI19: =W19/W$5*1000 -> 2.7297836 | AJ19: =X19/X$5*1000 -> 2.7807177 | AK19: =Y19/Y$5*1000 -> 2.5922689 | AL19: =Z19/Z$5*1000 -> 2.600395 | AM19: =AA19/AA$5*1000 -> 2.6474758 | AN19: =AB19/AB$5*1000 -> 2.8980157 | AO19: =AC19/AC$5*1000 -> 2.9327659 | ... AR19: =AF19/AF$5*1000 -> 3.0438958 | AT19: =AH19/AT$4 -> 0.020122821 | AU19: =AI19/AU$4 -> 0.022302759 | AV19: =AJ19/AV$4 -> 0.022718898 | AW19: =AK19/AW$4 -> 0.021179242 | AX19: =AL19/AX$4 -> 0.021245634 | AY19: =AM19/AY$4 -> 0.021630291 | AZ19: =AN19/AZ$4 -> 0.023677241 | BA19: =AO19/BA$4 -> 0.023961156 | ... BD19: =AR19/BD$4 -> 0.024869104
C20: Association dues | D20: =('24年CK1'!D114+'24年CK2'!D106)/38/1000 -> 0 | E20: =('24年CK1'!E114+'24年CK2'!E106)/38/1000 -> 1.8106924 | F20: =('24年CK1'!F114+'24年CK2'!F106)/38/1000 -> 0.15919132 | G20: =('24年CK1'!G114+'24年CK2'!G106)/38/1000 -> 9.5572245 | H20: =('24年CK1'!H114+'24年CK2'!H106)/38/1000 -> 8.6376266 | I20: =('24年CK1'!I114+'24年CK2'!I106)/38/1000 -> 8.7279321 | J20: =('24年CK1'!J114+'24年CK2'!J106)/38/1000 -> 8.4154321 | K20: =('24年CK1'!K114+'24年CK2'!K106)/38/1000 -> 7.8008282 | ... O20: =('24年CK1'!O114+'24年CK2'!O106)/38/1000 -> 7.3971439 | P20: =SUM(D20:O20) -> 75.02988 | Q20: =P20/$P$5*1000 -> 0.058277355 | S20: =Q20/$P$4 -> 0.00047613509 | V20: =D20+E20 -> 1.8106924 | W20: =V20+F20 -> 1.9698837 | X20: =W20+G20 -> 11.527108 | Y20: =X20+H20 -> 20.164735 | Z20: =Y20+I20 -> 28.892667 | AA20: =Z20+J20 -> 37.308099 | AB20: =AA20+K20 -> 45.108927 | AC20: =AB20+L20 -> 53.110412 | AD20: =AC20+M20 -> 60.273355 | ... AF20: =AE20+O20 -> 75.02988 | AH20: =V20/V$5*1000 -> 0.0091657886 | AI20: =W20/W$5*1000 -> 0.006330469 | AJ20: =X20/X$5*1000 -> 0.027393774 | AK20: =Y20/Y$5*1000 -> 0.035086067 | AL20: =Z20/Z$5*1000 -> 0.041515375 | AM20: =AA20/AA$5*1000 -> 0.045260011 | AN20: =AB20/AB$5*1000 -> 0.051105955 | AO20: =AC20/AC$5*1000 -> 0.053508408 | ... AR20: =AF20/AF$5*1000 -> 0.058277355 | AT20: =AH20/AT$4 -> 7.4885925e-05 | AU20: =AI20/AU$4 -> 5.1720921e-05 | AV20: =AJ20/AV$4 -> 0.00022381141 | AW20: =AK20/AW$4 -> 0.00028665865 | AX20: =AL20/AX$4 -> 0.0003391871 | AY20: =AM20/AY$4 -> 0.00036978136 | AZ20: =AN20/AZ$4 -> 0.00041754364 | BA20: =AO20/BA$4 -> 0.00043717205 | ... BD20: =AR20/BD$4 -> 0.00047613509
C21: G&A | D21: =D18-D19-D20 -> 160.41859 | E21: =E18-E19-E20 -> -2.2426505e-14 | F21: =F18-F19-F20 -> 1.1407542e-14 | G21: =G18-G19-G20 -> 76.509399 | H21: =H18-H19-H20 -> 19.725482 | I21: =I18-I19-I20 -> -8.1746113 | J21: =J18-J19-J20 -> 15.476841 | K21: =K18-K19-K20 -> 216.53599 | ... O21: =O18-O19-O20 -> 15.476841 | P21: =SUM(D21:O21) -> 483.32696 | Q21: =P21/$P$5*1000 -> 0.37541066 | S21: =Q21/$P$4 -> 0.0030671637 | V21: =D21+E21 -> 160.41859 | W21: =V21+F21 -> 160.41859 | X21: =W21+G21 -> 236.92799 | Y21: =X21+H21 -> 256.65347 | Z21: =Y21+I21 -> 248.47886 | AA21: =Z21+J21 -> 263.9557 | AB21: =AA21+K21 -> 480.49168 | AC21: =AB21+L21 -> 464.38958 | AD21: =AC21+M21 -> 452.53955 | ... AF21: =AE21+O21 -> 483.32696 | AH21: =V21/V$5*1000 -> 0.81204454 | AI21: =W21/W$5*1000 -> 0.5155253 | AJ21: =X21/X$5*1000 -> 0.56305116 | AK21: =Y21/Y$5*1000 -> 0.44656976 | AL21: =Z21/Z$5*1000 -> 0.35703499 | AM21: =AA21/AA$5*1000 -> 0.32021567 | AN21: =AB21/AB$5*1000 -> 0.54437088 | AO21: =AC21/AC$5*1000 -> 0.4678696 | ... AR21: =AF21/AF$5*1000 -> 0.37541066 | AT21: =AH21/AT$4 -> 0.0066345307 | AU21: =AI21/AU$4 -> 0.0042119223 | AV21: =AJ21/AV$4 -> 0.0046002159 | AW21: =AK21/AW$4 -> 0.0036485447 | AX21: =AL21/AX$4 -> 0.0029170316 | AY21: =AM21/AY$4 -> 0.002616212 | AZ21: =AN21/AZ$4 -> 0.0044475952 | BA21: =AO21/BA$4 -> 0.0038225677 | ... BD21: =AR21/BD$4 -> 0.0030671637
B22: 合计 | D22: =SUM(D6:D18,D26) -> 2064.5661 | E22: =SUM(E6:E18,E26) -> 2522.0094 | F22: =SUM(F6:F18,F26) -> 2777.9378 | G22: =SUM(G6:G18,G26) -> 2882.7559 | H22: =SUM(H6:H18,H26) -> 3016.6281 | I22: =SUM(I6:I18,I26) -> 3137.7862 | J22: =SUM(J6:J18,J26) -> 3465.9611 | K22: =SUM(K6:K18,K26) -> 3368.3282 | ... O22: =SUM(O6:O18,O26) -> 3183.3219 | P22: =SUM(D22:O22) -> 36630.575 | V22: =SUM(V6:V18) -> 3528.8127 | W22: =SUM(W6:W18) -> 5777.8691 | X22: =SUM(X6:X18) -> 8131.7436 | Y22: =SUM(Y6:Y18) -> 10619.49 | Z22: =SUM(Z6:Z18) -> 13228.395 | AA22: =SUM(AA6:AA18) -> 16165.475 | AB22: =SUM(AB6:AB18) -> 19004.921 | AC22: =SUM(AC6:AC18) -> 21715.591 | ... AF22: =SUM(AF6:AF18) -> 30439.769 | AH22: =V22/V$5*1000 -> 17.862974 | AI22: =W22/W$5*1000 -> 18.567909 | AJ22: =X22/X$5*1000 -> 19.324807 | AK22: =Y22/Y$5*1000 -> 18.477612 | AL22: =Z22/Z$5*1000 -> 19.007653 | AM22: =AA22/AA$5*1000 -> 19.611012 | AN22: =AB22/AB$5*1000 -> 21.53154 | AO22: =AC22/AC$5*1000 -> 21.878322 | ... AR22: =AF22/AF$5*1000 -> 23.643237 | AT22: =AH22/AT$4 -> 0.14594329 | AU22: =AI22/AU$4 -> 0.15170272 | AV22: =AJ22/AV$4 -> 0.15788669 | AW22: =AK22/AW$4 -> 0.15096498 | AX22: =AL22/AX$4 -> 0.15529549 | AY22: =AM22/AY$4 -> 0.16022503 | AZ22: =AN22/AZ$4 -> 0.17591605 | BA22: =AO22/BA$4 -> 0.17874931 | ... BD22: =AR22/BD$4 -> 0.19316894
B23: 单台 | D23: =D22/D5*1000 -> 23.639077 | E23: =E22/E5*1000 -> 22.883256 | F23: =F22/F5*1000 -> 24.448083 | G23: =G22/G5*1000 -> 26.298199 | H23: =H22/H5*1000 -> 19.597529 | I23: =I22/I5*1000 -> 25.883132 | J23: =J22/J5*1000 -> 27.002931 | K23: =K22/K5*1000 -> 57.727265 | ... P23: =P22/P5*1000 -> 28.451772 | Q23: =P23 -> 28.451772 | S23: =Q23/$P$4 -> 0.23245542 | V23: =V22/V5*1000 -> 17.862974 | W23: =W22/W5*1000 -> 18.567909 | X23: =X22/X5*1000 -> 19.324807 | Y23: =Y22/Y5*1000 -> 18.477612 | Z23: =Z22/Z5*1000 -> 19.007653 | AA23: =AA22/AA5*1000 -> 19.611012 | AB23: =AB22/AB5*1000 -> 21.53154 | AC23: =AC22/AC5*1000 -> 21.878322 | ... AF23: =AF22/AF5*1000 -> 23.643237
B25: 青岛不包含科目 | D25: =('24年CK1'!D158+'24年CK2'!D150)/1000 -> 341.802 | E25: =('24年CK1'!E158+'24年CK2'!E150)/1000 -> 327.68597 | F25: =('24年CK1'!F158+'24年CK2'!F150)/1000 -> 365.93252 | G25: =('24年CK1'!G158+'24年CK2'!G150)/1000 -> 383.45643 | H25: =('24年CK1'!H158+'24年CK2'!H150)/1000 -> 419.76833 | I25: =('24年CK1'!I158+'24年CK2'!I150)/1000 -> 551.74142 | J25: =('24年CK1'!J158+'24年CK2'!J150)/1000 -> 906.90377 | K25: =('24年CK1'!K158+'24年CK2'!K150)/1000 -> 986.05575 | ... O25: =('24年CK1'!O158+'24年CK2'!O150)/1000 -> 910.23683 | P25: =SUM(D25:O25) -> 7984.5405
B26: functional currency | D26: 528.88143 | E26: 528.88143 | F26: 528.88143 | G26: 528.88143 | H26: 528.88143 | I26: 528.88143 | J26: 528.88143 | K26: 528.88143 | L26: 528.88143 | M26: 528.88143 | N26: 528.88143 | O26: 373.11006 | P26: =SUM(D26:O26) -> 6190.8058 | Q26: =P26/$P$5*1000 -> 4.8085348
Q27: =Q23+Q26 -> 33.260307 | S27: =Q23/P4 -> 0.23245542
C28: 厨电25年实际
A29: 年累 | C29: 科目 | D29: 25年1月 | E29: 25年2月 | F29: 25年3月 | G29: 25年4月 | H29: 25年5月 | I29: 25年6月 | J29: 25年7月 | K29: 25年8月 | L29: 25年9月 | M29: 25年10月 | N29: 25年11月 | O29: 25年12月 | P29: 合计 | Q29: 单台 | R29: 占比 | S29: 费率 | T29: 同比
A30: 125 | B30: 平均单价（自制） | D30: 132.28094 | E30: 126.5203 | F30: 124.52481 | G30: 125.48365 | H30: 119.998 | I30: 117.22308 | J30: 106.8 | K30: 122.15761 | L30: 113.63291 | M30: 119.3915 | N30: 119.78253 | O30: 124.50549 | P30: =AVERAGE(D30:O30) -> 121.02507 | Q30: =AVERAGE(D30:O30) -> 121.02507 | AT30: =$P$30 -> 121.02507 | AU30: =$P$30 -> 121.02507 | AV30: =$P$30 -> 121.02507 | AW30: =$P$30 -> 121.02507 | AX30: =$P$30 -> 121.02507 | AY30: =$P$30 -> 121.02507 | AZ30: =$P$30 -> 121.02507 | BA30: =$P$30 -> 121.02507 | ... BD30: =$P$30 -> 121.02507
A31: =SUM(D31:F31) -> 254474 | C31: 产量 | D31: 79712 | E31: 82105 | F31: 92657 | G31: 98687 | H31: 93353 | I31: 75092 | J31: 77799 | K31: 58812 | L31: 90826 | M31: 111572 | N31: 111625 | O31: 75554 | P31: =SUM(D31:O31) -> 1047794 | U31: 1171 | V31: =D31+E31 -> 161817 | W31: =V31+F31 -> 254474 | X31: =W31+G31 -> 353161 | Y31: =X31+H31 -> 446514 | Z31: =Y31+I31 -> 521606 | AA31: =Z31+J31 -> 599405 | AB31: =AA31+K31 -> 658217 | AC31: =AB31+L31 -> 749043 | AD31: =AC31+M31 -> 860615 | ... AF31: =AE31+O31 -> 1047794
A32: =SUM(D32:F32) -> 2275.3025 | B32: 固定制造 | C32: 折旧 | D32: 770.36882 | E32: 741.42854 | F32: 763.50516 | G32: 766.01624 | H32: 831.68695 | I32: 824.01968 | J32: 839.2091 | K32: 583.2903 | L32: 793.0073 | M32: 589.92044 | N32: 801.39809 | O32: 815.91192 | P32: =SUM(D32:O32) -> 9119.7625 | Q32: =P32/$P$31*1000 -> 8.7037743 | R32: =P32/$P$48 -> 0.3159956 | S32: =Q32/$P$30 -> 0.07191712 | U32: 含FC | V32: =D32+E32 -> 1511.7974 | W32: =V32+F32 -> 2275.3025 | X32: =W32+G32 -> 3041.3188 | Y32: =X32+H32 -> 3873.0057 | Z32: =Y32+I32 -> 4697.0254 | AA32: =Z32+J32 -> 5536.2345 | AB32: =AA32+K32 -> 6119.5248 | AC32: =AB32+L32 -> 6912.5321 | AD32: =AC32+M32 -> 7502.4525 | ... AF32: =AE32+O32 -> 9119.7625 | AH32: =V32/V$31*1000 -> 9.3426362 | AI32: =W32/W$31*1000 -> 8.9411984 | AJ32: =X32/X$31*1000 -> 8.6117062 | AK32: =Y32/Y$31*1000 -> 8.673873 | AL32: =Z32/Z$31*1000 -> 9.0049298 | AM32: =AA32/AA$31*1000 -> 9.2362167 | AN32: =AB32/AB$31*1000 -> 9.2971236 | AO32: =AC32/AC$31*1000 -> 9.228485 | ... AR32: =AF32/AF$31*1000 -> 8.7037743 | AT32: =AH32/AT$30 -> 0.077195877 | AU32: =AI32/AU$30 -> 0.073878896 | AV32: =AJ32/AV$30 -> 0.071156384 | AW32: =AK32/AW$30 -> 0.071670053 | AX32: =AL32/AX$30 -> 0.074405492 | AY32: =AM32/AY$30 -> 0.076316559 | AZ32: =AN32/AZ$30 -> 0.076819817 | BA32: =AO32/BA$30 -> 0.076252674 | ... BD32: =AR32/BD$30 -> 0.07191712
A33: =SUM(D33:F33) -> 407.82934 | C33: 运营费 | D33: 95.78168 | E33: 108.72299 | F33: 203.32467 | G33: 12.16119 | H33: 83.73571 | I33: 82.17874 | J33: 72.26606 | K33: 71.16146 | L33: 85.19357 | M33: 87.58382 | N33: 120.34261 | O33: 75.7403 | P33: =SUM(D33:O33) -> 1098.1928 | Q33: =P33/$P$31*1000 -> 1.0480999 | R33: =P33/$P$48 -> 0.038051879 | S33: =Q33/$P$30 -> 0.0086601886 | V33: =D33+E33 -> 204.50467 | W33: =V33+F33 -> 407.82934 | X33: =W33+G33 -> 419.99053 | Y33: =X33+H33 -> 503.72624 | Z33: =Y33+I33 -> 585.90498 | AA33: =Z33+J33 -> 658.17104 | AB33: =AA33+K33 -> 729.3325 | AC33: =AB33+L33 -> 814.52607 | AD33: =AC33+M33 -> 902.10989 | ... AF33: =AE33+O33 -> 1098.1928 | AH33: =V33/V$31*1000 -> 1.2638021 | AI33: =W33/W$31*1000 -> 1.6026366 | AJ33: =X33/X$31*1000 -> 1.1892325 | AK33: =Y33/Y$31*1000 -> 1.1281309 | AL33: =Z33/Z$31*1000 -> 1.1232712 | AM33: =AA33/AA$31*1000 -> 1.0980406 | AN33: =AB33/AB$31*1000 -> 1.1080426 | AO33: =AC33/AC$31*1000 -> 1.0874223 | ... AR33: =AF33/AF$31*1000 -> 1.0480999 | AT33: =AH33/AT$30 -> 0.010442482 | AU33: =AI33/AU$30 -> 0.013242187 | AV33: =AJ33/AV$30 -> 0.0098263318 | AW33: =AK33/AW$30 -> 0.0093214647 | AX33: =AL33/AX$30 -> 0.00928131 | AY33: =AM33/AY$30 -> 0.0090728363 | AZ33: =AN33/AZ$30 -> 0.0091554804 | BA33: =AO33/BA$30 -> 0.0089850998 | ... BD33: =AR33/BD$30 -> 0.0086601886
A34: =SUM(D34:F34) -> 92.55319 | C34: 存货跌价准备 | D34: 34.84363 | E34: 28.85478 | F34: 28.85478 | G34: 28.85478 | H34: 28.85478 | I34: 222.48895 | J34: 8.85478 | K34: 8.855 | L34: -1281.6854 | M34: 0 | N34: 0 | O34: -375.25241 | P34: =SUM(D34:O34) -> -1266.4763 | Q34: =P34/$P$31*1000 -> -1.2087074 | R34: =P34/$P$48 -> -0.043882826 | S34: =Q34/$P$30 -> -0.009987248 | V34: =D34+E34 -> 63.69841 | W34: =V34+F34 -> 92.55319 | X34: =W34+G34 -> 121.40797 | Y34: =X34+H34 -> 150.26275 | Z34: =Y34+I34 -> 372.7517 | AA34: =Z34+J34 -> 381.60648 | AB34: =AA34+K34 -> 390.46148 | AC34: =AB34+L34 -> -891.22391 | AD34: =AC34+[1]Sheet1!L57 -> -891.10397 | AE34: =AD34+N34 -> -891.10397 | AF34: =AE34+O34 -> -1266.3564 | AH34: =V34/V$31*1000 -> 0.39364473 | AI34: =W34/W$31*1000 -> 0.36370391 | AJ34: =X34/X$31*1000 -> 0.34377513 | AK34: =Y34/Y$31*1000 -> 0.33652416 | AL34: =Z34/Z$31*1000 -> 0.71462311 | AM34: =AA34/AA$31*1000 -> 0.63664214 | AN34: =AB34/AB$31*1000 -> 0.59321087 | AO34: =AC34/AC$31*1000 -> -1.1898168 | ... AR34: =AF34/AF$31*1000 -> -1.2085929 | AT34: =AH34/AT$30 -> 0.0032525884 | AU34: =AI34/AU$30 -> 0.0030051949 | AV34: =AJ34/AV$30 -> 0.0028405283 | AW34: =AK34/AW$30 -> 0.0027806154 | AX34: =AL34/AX$30 -> 0.0059047528 | AY34: =AM34/AY$30 -> 0.0052604155 | AZ34: =AN34/AZ$30 -> 0.0049015537 | BA34: =AO34/BA$30 -> -0.0098311596 | ... BD34: =AR34/BD$30 -> -0.0099863022
A35: =SUM(D35:F35) -> 129.83754 | C35: 固定能源费 | D35: 47.14342 | E35: 35.17581 | F35: 47.51831 | G35: 5.08957 | H35: 27.51429 | I35: 20.25036 | J35: 22.36867 | K35: 29.97052 | L35: 29.52934 | M35: 33.0999 | N35: 27.76599 | O35: 33.87562 | P35: =SUM(D35:O35) -> 359.3018 | Q35: =P35/$P$31*1000 -> 0.34291263 | R35: =P35/$P$48 -> 0.012449643 | S35: =Q35/$P$30 -> 0.0028334017 | V35: =D35+E35 -> 82.31923 | W35: =V35+F35 -> 129.83754 | X35: =W35+G35 -> 134.92711 | Y35: =X35+H35 -> 162.4414 | Z35: =Y35+I35 -> 182.69176 | AA35: =Z35+J35 -> 205.06043 | AB35: =AA35+K35 -> 235.03095 | AC35: =AB35+L35 -> 264.56029 | AD35: =AC35+M35 -> 297.66019 | ... AF35: =AE35+O35 -> 359.3018 | AH35: =V35/V$31*1000 -> 0.50871806 | AI35: =W35/W$31*1000 -> 0.51021928 | AJ35: =X35/X$31*1000 -> 0.38205552 | AK35: =Y35/Y$31*1000 -> 0.36379912 | AL35: =Z35/Z$31*1000 -> 0.35024858 | AM35: =AA35/AA$31*1000 -> 0.34210664 | AN35: =AB35/AB$31*1000 -> 0.35707214 | AO35: =AC35/AC$31*1000 -> 0.35319773 | ... AR35: =AF35/AF$31*1000 -> 0.34291263 | AT35: =AH35/AT$30 -> 0.0042034106 | AU35: =AI35/AU$30 -> 0.0042158148 | AV35: =AJ35/AV$30 -> 0.0031568296 | AW35: =AK35/AW$30 -> 0.0030059815 | AX35: =AL35/AX$30 -> 0.0028940168 | AY35: =AM35/AY$30 -> 0.002826742 | AZ35: =AN35/AZ$30 -> 0.0029503981 | BA35: =AO35/BA$30 -> 0.0029183849 | ... BD35: =AR35/BD$30 -> 0.0028334017
A36: =SUM(D36:F36) -> 1235.8801 | C36: 间接人工成本-辅助人员 | D36: 385.87333 | E36: 358.20537 | F36: 491.80141 | G36: 403.07668 | H36: 452.17888 | I36: 332.25239 | J36: 332.16484 | K36: 279.86157 | L36: 317.01562 | M36: 415.08803 | N36: 361.68076 | O36: 422.62091 | P36: =SUM(D36:O36) -> 4551.8198 | Q36: =P36/$P$31*1000 -> 4.3441934 | R36: =P36/$P$48 -> 0.15771848 | S36: =Q36/$P$30 -> 0.035894988 | U36: 25年3月/9月各涨18% | V36: =D36+E36 -> 744.0787 | W36: =V36+F36 -> 1235.8801 | X36: =W36+G36 -> 1638.9568 | Y36: =X36+H36 -> 2091.1357 | Z36: =Y36+I36 -> 2423.3881 | AA36: =Z36+J36 -> 2755.5529 | AB36: =AA36+K36 -> 3035.4145 | AC36: =AB36+L36 -> 3352.4301 | AD36: =AC36+M36 -> 3767.5181 | ... AF36: =AE36+O36 -> 4551.8198 | AH36: =V36/V$31*1000 -> 4.5982727 | AI36: =W36/W$31*1000 -> 4.8566066 | AJ36: =X36/X$31*1000 -> 4.6408204 | AK36: =Y36/Y$31*1000 -> 4.6832477 | AL36: =Z36/Z$31*1000 -> 4.6460126 | AM36: =AA36/AA$31*1000 -> 4.597147 | AN36: =AB36/AB$31*1000 -> 4.6115711 | AO36: =AC36/AC$31*1000 -> 4.4756177 | ... AR36: =AF36/AF$31*1000 -> 4.3441934 | AT36: =AH36/AT$30 -> 0.037994383 | AU36: =AI36/AU$30 -> 0.040128931 | AV36: =AJ36/AV$30 -> 0.038345944 | AW36: =AK36/AW$30 -> 0.03869651 | AX36: =AL36/AX$30 -> 0.038388845 | AY36: =AM36/AY$30 -> 0.037985081 | AZ36: =AN36/AZ$30 -> 0.038104263 | BA36: =AO36/BA$30 -> 0.036980914 | ... BD36: =AR36/BD$30 -> 0.035894988
A37: =SUM(D37:F37) -> 722.82554 | C37: 固定人工-白领 | D37: 276.16976 | E37: 193.34998 | F37: 253.3058 | G37: 149.25268 | H37: 199.13504 | I37: 153.80926 | J37: 132.57406 | K37: 141.30123 | L37: 119.39319 | M37: 103.52545 | N37: 110.0848 | O37: 106.23428 | P37: =SUM(D37:O37) -> 1938.1355 | Q37: =P37/$P$31*1000 -> 1.8497296 | R37: =P37/$P$48 -> 0.06715551 | S37: =Q37/$P$30 -> 0.015283855 | V37: =D37+E37 -> 469.51974 | W37: =V37+F37 -> 722.82554 | X37: =W37+G37 -> 872.07822 | Y37: =X37+H37 -> 1071.2133 | Z37: =Y37+I37 -> 1225.0225 | AA37: =Z37+J37 -> 1357.5966 | AB37: =AA37+K37 -> 1498.8978 | AC37: =AB37+L37 -> 1618.291 | AD37: =AC37+M37 -> 1721.8164 | ... AF37: =AE37+O37 -> 1938.1355 | AH37: =V37/V$31*1000 -> 2.9015477 | AI37: =W37/W$31*1000 -> 2.8404691 | AJ37: =X37/X$31*1000 -> 2.4693503 | AK37: =Y37/Y$31*1000 -> 2.3990586 | AL37: =Z37/Z$31*1000 -> 2.3485591 | AM37: =AA37/AA$31*1000 -> 2.264907 | AN37: =AB37/AB$31*1000 -> 2.2772092 | AO37: =AC37/AC$31*1000 -> 2.1604781 | ... AR37: =AF37/AF$31*1000 -> 1.8497296 | AT37: =AH37/AT$30 -> 0.023974766 | AU37: =AI37/AU$30 -> 0.023470089 | AV37: =AJ37/AV$30 -> 0.020403627 | AW37: =AK37/AW$30 -> 0.019822824 | AX37: =AL37/AX$30 -> 0.019405559 | AY37: =AM37/AY$30 -> 0.018714363 | AZ37: =AN37/AZ$30 -> 0.018816013 | BA37: =AO37/BA$30 -> 0.017851493 | ... BD37: =AR37/BD$30 -> 0.015283855
A38: =SUM(D38:F38) -> 581.13068 | C38: 半固定-班车/工作服 | D38: 219.71751 | E38: 220.42753 | F38: 140.98564 | G38: 147.58937 | H38: 170.65504 | I38: 126.29138 | J38: 128.75935 | K38: 134.41711 | L38: 147.22651 | M38: 149.29277 | N38: 157.73939 | O38: 168.50673 | P38: =SUM(D38:O38) -> 1911.6083 | Q38: =P38/$P$31*1000 -> 1.8244124 | R38: =P38/$P$48 -> 0.066236355 | S38: =Q38/$P$30 -> 0.015074665 | V38: =D38+E38 -> 440.14504 | W38: =V38+F38 -> 581.13068 | X38: =W38+G38 -> 728.72005 | Y38: =X38+H38 -> 899.37509 | Z38: =Y38+I38 -> 1025.6665 | AA38: =Z38+J38 -> 1154.4258 | AB38: =AA38+K38 -> 1288.8429 | AC38: =AB38+L38 -> 1436.0694 | AD38: =AC38+M38 -> 1585.3622 | ... AF38: =AE38+O38 -> 1911.6083 | AH38: =V38/V$31*1000 -> 2.7200173 | AI38: =W38/W$31*1000 -> 2.2836544 | AJ38: =X38/X$31*1000 -> 2.0634216 | AK38: =Y38/Y$31*1000 -> 2.0142148 | AL38: =Z38/Z$31*1000 -> 1.9663625 | AM38: =AA38/AA$31*1000 -> 1.9259529 | AN38: =AB38/AB$31*1000 -> 1.9580821 | AO38: =AC38/AC$31*1000 -> 1.9172056 | ... AR38: =AF38/AF$31*1000 -> 1.8244124 | AT38: =AH38/AT$30 -> 0.022474826 | AU38: =AI38/AU$30 -> 0.018869268 | AV38: =AJ38/AV$30 -> 0.017049539 | AW38: =AK38/AW$30 -> 0.016642955 | AX38: =AL38/AX$30 -> 0.016247564 | AY38: =AM38/AY$30 -> 0.01591367 | AZ38: =AN38/AZ$30 -> 0.016179145 | BA38: =AO38/BA$30 -> 0.015841393 | ... BD38: =AR38/BD$30 -> 0.015074665
A39: =SUM(D39:F39) -> 1702.2824 | B39: 变动制造 | C39: 直接人工 | D39: 544.15844 | E39: 469.02011 | F39: 689.10387 | G39: 573.04516 | H39: 645.05798 | I39: 596.42251 | J39: 524.39303 | K39: 432.51216 | L39: 570.86096 | M39: 501.28108 | N39: 640.25558 | O39: 557.30606 | P39: =SUM(D39:O39) -> 6743.4169 | Q39: =P39/$P$31*1000 -> 6.4358232 | R39: =P39/$P$48 -> 0.23365632 | S39: =Q39/$P$30 -> 0.053177605 | U39: 25年3月/9月各涨18% | V39: =D39+E39 -> 1013.1786 | W39: =V39+F39 -> 1702.2824 | X39: =W39+G39 -> 2275.3276 | Y39: =X39+H39 -> 2920.3856 | Z39: =Y39+I39 -> 3516.8081 | AA39: =Z39+J39 -> 4041.2011 | AB39: =AA39+K39 -> 4473.7133 | AC39: =AB39+L39 -> 5044.5742 | AD39: =AC39+M39 -> 5545.8553 | ... AF39: =AE39+O39 -> 6743.4169 | AH39: =V39/V$31*1000 -> 6.2612615 | AI39: =W39/W$31*1000 -> 6.6894159 | AJ39: =X39/X$31*1000 -> 6.4427487 | AK39: =Y39/Y$31*1000 -> 6.5404121 | AL39: =Z39/Z$31*1000 -> 6.7422692 | AM39: =AA39/AA$31*1000 -> 6.742021 | AN39: =AB39/AB$31*1000 -> 6.7967149 | AO39: =AC39/AC$31*1000 -> 6.7346924 | ... AR39: =AF39/AF$31*1000 -> 6.4358232 | AT39: =AH39/AT$30 -> 0.051735245 | AU39: =AI39/AU$30 -> 0.055272978 | AV39: =AJ39/AV$30 -> 0.053234828 | AW39: =AK39/AW$30 -> 0.054041797 | AX39: =AL39/AX$30 -> 0.055709692 | AY39: =AM39/AY$30 -> 0.055707641 | AZ39: =AN39/AZ$30 -> 0.056159562 | BA39: =AO39/BA$30 -> 0.055647087 | ... BD39: =AR39/BD$30 -> 0.053177605
A40: =SUM(D40:F40) -> 95.4338 | C40: 废料 | D40: 30.00512 | E40: 32.08729 | F40: 33.34139 | G40: 38.25359 | H40: 38.32702 | I40: 39.72992 | J40: 34.70272 | K40: 33.87479 | L40: 43.88856 | M40: 42.01354 | N40: 43.6391 | O40: 51.31959 | P40: =SUM(D40:O40) -> 461.18263 | Q40: =P40/$P$31*1000 -> 0.44014628 | R40: =P40/$P$48 -> 0.015979767 | S40: =Q40/$P$30 -> 0.0036368191 | V40: =D40+E40 -> 62.09241 | W40: =V40+F40 -> 95.4338 | X40: =W40+G40 -> 133.68739 | Y40: =X40+H40 -> 172.01441 | Z40: =Y40+I40 -> 211.74433 | AA40: =Z40+J40 -> 246.44705 | AB40: =AA40+K40 -> 280.32184 | AC40: =AB40+L40 -> 324.2104 | AD40: =AC40+M40 -> 366.22394 | ... AF40: =AE40+O40 -> 461.18263 | AH40: =V40/V$31*1000 -> 0.38371994 | AI40: =W40/W$31*1000 -> 0.37502377 | AJ40: =X40/X$31*1000 -> 0.37854517 | AK40: =Y40/Y$31*1000 -> 0.38523856 | AL40: =Z40/Z$31*1000 -> 0.40594688 | AM40: =AA40/AA$31*1000 -> 0.41115281 | AN40: =AB40/AB$31*1000 -> 0.42588058 | AO40: =AC40/AC$31*1000 -> 0.43283283 | ... AR40: =AF40/AF$31*1000 -> 0.44014628 | AT40: =AH40/AT$30 -> 0.0031705823 | AU40: =AI40/AU$30 -> 0.0030987281 | AV40: =AJ40/AV$30 -> 0.0031278245 | AW40: =AK40/AW$30 -> 0.0031831303 | AX40: =AL40/AX$30 -> 0.003354238 | AY40: =AM40/AY$30 -> 0.0033972533 | AZ40: =AN40/AZ$30 -> 0.0035189452 | BA40: =AO40/BA$30 -> 0.0035763899 | ... BD40: =AR40/BD$30 -> 0.0036368191
A41: =SUM(D41:F41) -> -16.46333 | C41: 生产耗用品 | D41: -6.18037 | E41: -5.43418 | F41: -4.84878 | G41: -10.03154 | H41: -22.19444 | I41: 4.14348 | J41: -89.60533 | K41: 70.59169 | L41: 9.30265 | M41: 6.55931 | N41: 5.24204 | O41: -14.07716 | P41: =SUM(D41:O41) -> -56.53263 | Q41: =P41/$P$31*1000 -> -0.053953955 | R41: =P41/$P$48 -> -0.0019588298 | S41: =Q41/$P$30 -> -0.00044580809 | V41: =D41+E41 -> -11.61455 | W41: =V41+F41 -> -16.46333 | X41: =W41+G41 -> -26.49487 | Y41: =X41+H41 -> -48.68931 | Z41: =Y41+I41 -> -44.54583 | AA41: =Z41+J41 -> -134.15116 | AB41: =AA41+K41 -> -63.55947 | AC41: =AB41+L41 -> -54.25682 | AD41: =AC41+M41 -> -47.69751 | ... AF41: =AE41+O41 -> -56.53263 | AH41: =V41/V$31*1000 -> -0.071775833 | AI41: =W41/W$31*1000 -> -0.064695529 | AJ41: =X41/X$31*1000 -> -0.075022072 | AK41: =Y41/Y$31*1000 -> -0.10904319 | AL41: =Z41/Z$31*1000 -> -0.085401299 | AM41: =AA41/AA$31*1000 -> -0.22380721 | AN41: =AB41/AB$31*1000 -> -0.096563094 | AO41: =AC41/AC$31*1000 -> -0.072434854 | ... AR41: =AF41/AF$31*1000 -> -0.053953955 | AT41: =AH41/AT$30 -> -0.00059306584 | AU41: =AI41/AU$30 -> -0.00053456305 | AV41: =AJ41/AV$30 -> -0.0006198887 | AW41: =AK41/AW$30 -> -0.00090099671 | AX41: =AL41/AX$30 -> -0.00070564967 | AY41: =AM41/AY$30 -> -0.0018492632 | AZ41: =AN41/AZ$30 -> -0.0007978768 | BA41: =AO41/BA$30 -> -0.00059851116 | ... BD41: =AR41/BD$30 -> -0.00044580809
A42: =SUM(D42:F42) -> -162.5558 | C42: 废品收入 | D42: -36.41102 | E42: -38.3304 | F42: -87.81438 | G42: -84.58556 | H42: -90.78098 | I42: -97.37103 | J42: -81.74893 | K42: -45.93377 | L42: -76.47944 | M42: -78.08778 | N42: -95.42989 | O42: -67.8956 | P42: =SUM(D42:O42) -> -880.86878 | Q42: =P42/$P$31*1000 -> -0.84068889 | R42: =P42/$P$48 -> -0.030521701 | S42: =Q42/$P$30 -> -0.006946403 | V42: =D42+E42 -> -74.74142 | W42: =V42+F42 -> -162.5558 | X42: =W42+G42 -> -247.14136 | Y42: =X42+H42 -> -337.92234 | Z42: =Y42+I42 -> -435.29337 | AA42: =Z42+J42 -> -517.0423 | AB42: =AA42+K42 -> -562.97607 | AC42: =AB42+L42 -> -639.45551 | AD42: =AC42+M42 -> -717.54329 | ... AF42: =AE42+O42 -> -880.86878 | AH42: =V42/V$31*1000 -> -0.46188855 | AI42: =W42/W$31*1000 -> -0.63879139 | AJ42: =X42/X$31*1000 -> -0.699798 | AK42: =Y42/Y$31*1000 -> -0.75680122 | AL42: =Z42/Z$31*1000 -> -0.83452524 | AM42: =AA42/AA$31*1000 -> -0.86259257 | AN42: =AB42/AB$31*1000 -> -0.85530466 | AO42: =AC42/AC$31*1000 -> -0.85369666 | ... AR42: =AF42/AF$31*1000 -> -0.84068889 | AT42: =AH42/AT$30 -> -0.0038164701 | AU42: =AI42/AU$30 -> -0.0052781742 | AV42: =AJ42/AV$30 -> -0.0057822566 | AW42: =AK42/AW$30 -> -0.00625326 | AX42: =AL42/AX$30 -> -0.0068954742 | AY42: =AM42/AY$30 -> -0.0071273876 | AZ42: =AN42/AZ$30 -> -0.0070671695 | BA42: =AO42/BA$30 -> -0.007053883 | ... BD42: =AR42/BD$30 -> -0.006946403
A43: =SUM(D43:F43) -> 111.6038 | C43: 变动能源费 | D43: 27.00688 | E43: 41.25257 | F43: 43.34435 | G43: 73.26051 | H43: 63.04494 | I43: 42.06939 | J43: 44.6181 | K43: 33.37998 | L43: 43.418 | M43: 58.75728 | N43: 60.06815 | O43: 31.5877 | P43: =SUM(D43:O43) -> 561.80785 | Q43: =P43/$P$31*1000 -> 0.53618159 | R43: =P43/$P$48 -> 0.019466385 | S43: =Q43/$P$30 -> 0.0044303349 | V43: =D43+E43 -> 68.25945 | W43: =V43+F43 -> 111.6038 | X43: =W43+G43 -> 184.86431 | Y43: =X43+H43 -> 247.90925 | Z43: =Y43+I43 -> 289.97864 | AA43: =Z43+J43 -> 334.59674 | AB43: =AA43+K43 -> 367.97672 | AC43: =AB43+L43 -> 411.39472 | AD43: =AC43+M43 -> 470.152 | ... AF43: =AE43+O43 -> 561.80785 | AH43: =V43/V$31*1000 -> 0.42183114 | AI43: =W43/W$31*1000 -> 0.43856661 | AJ43: =X43/X$31*1000 -> 0.52345619 | AK43: =Y43/Y$31*1000 -> 0.55521047 | AL43: =Z43/Z$31*1000 -> 0.55593425 | AM43: =AA43/AA$31*1000 -> 0.5582148 | AN43: =AB43/AB$31*1000 -> 0.55905077 | AO43: =AC43/AC$31*1000 -> 0.54922711 | ... AR43: =AF43/AF$31*1000 -> 0.53618159 | AT43: =AH43/AT$30 -> 0.0034854857 | AU43: =AI43/AU$30 -> 0.0036237667 | AV43: =AJ43/AV$30 -> 0.0043251881 | AW43: =AK43/AW$30 -> 0.0045875659 | AX43: =AL43/AX$30 -> 0.0045935463 | AY43: =AM43/AY$30 -> 0.0046123899 | AZ43: =AN43/AZ$30 -> 0.0046192973 | BA43: =AO43/BA$30 -> 0.0045381268 | ... BD43: =AR43/BD$30 -> 0.0044303349
A44: =SUM(D44:F44) -> 1282.4666 | B44: 分摊 | C44: 分摊费用 | D44: 397.89523 | E44: 507.54717 | F44: 377.02418 | G44: 454.70945 | H44: 388.80844 | I44: 396.65983 | J44: 400.03725 | K44: 380.49694 | L44: 437.17342 | M44: 408.42982 | N44: 385.71638 | O44: -215.43912 | P44: =SUM(D44:O44) -> 4319.059 | Q44: =P44/$P$31*1000 -> 4.1220497 | R44: =P44/$P$48 -> 0.14965342 | S44: =Q44/$P$30 -> 0.034059471 | U44: =P44/8*12 -> 6478.5885 | V44: =D44+E44 -> 905.4424 | W44: =V44+F44 -> 1282.4666 | X44: =W44+G44 -> 1737.176 | Y44: =X44+H44 -> 2125.9845 | Z44: =Y44+I44 -> 2522.6443 | AA44: =Z44+J44 -> 2922.6815 | AB44: =AA44+K44 -> 3303.1785 | AC44: =AB44+L44 -> 3740.3519 | AD44: =AC44+M44 -> 4148.7817 | ... AF44: =AE44+O44 -> 4319.059 | AH44: =V44/V$31*1000 -> 5.5954714 | AI44: =W44/W$31*1000 -> 5.0396763 | AJ44: =X44/X$31*1000 -> 4.9189351 | AK44: =Y44/Y$31*1000 -> 4.7612941 | AL44: =Z44/Z$31*1000 -> 4.8363023 | AM44: =AA44/AA$31*1000 -> 4.8759713 | AN44: =AB44/AB$31*1000 -> 5.0183731 | AO44: =AC44/AC$31*1000 -> 4.9935076 | ... AR44: =AF44/AF$31*1000 -> 4.1220497 | AT44: =AH44/AT$30 -> 0.046233987 | AU44: =AI44/AU$30 -> 0.04164159 | AV44: =AJ44/AV$30 -> 0.040643936 | AW44: =AK44/AW$30 -> 0.039341388 | AX44: =AL44/AX$30 -> 0.039961162 | AY44: =AM44/AY$30 -> 0.040288936 | AZ44: =AN44/AZ$30 -> 0.041465567 | BA44: =AO44/BA$30 -> 0.04126011 | ... BD44: =AR44/BD$30 -> 0.034059471
A45: =SUM(D45:F45) -> 758.44391 | C45: IT Expense-Internal Charge Out | D45: 252.82816 | E45: 252.82816 | F45: 252.78759 | G45: 252.81464 | H45: 278.01555 | I45: 252.81464 | J45: 277.713 | K45: 252.8 | L45: 278.01555 | M45: 278.01555 | N45: 252.81464 | O45: -300.68492 | P45: =SUM(D45:O45) -> 2580.7626 | Q45: =P45/$P$31*1000 -> 2.4630438 | S45: =Q45/$P$30 -> 0.020351518 | V45: =D45+E45 -> 505.65632 | W45: =V45+F45 -> 758.44391 | X45: =W45+G45 -> 1011.2586 | Y45: =X45+H45 -> 1289.2741 | Z45: =Y45+I45 -> 1542.0887 | AA45: =Z45+J45 -> 1819.8017 | AB45: =AA45+K45 -> 2072.6017 | AC45: =AB45+L45 -> 2350.6173 | AD45: =AC45+M45 -> 2628.6328 | ... AF45: =AE45+O45 -> 2580.7626 | AH45: =V45/V$31*1000 -> 3.1248652 | AI45: =W45/W$31*1000 -> 2.9804377 | AJ45: =X45/X$31*1000 -> 2.8634491 | AK45: =Y45/Y$31*1000 -> 2.8874214 | AL45: =Z45/Z$31*1000 -> 2.9564245 | AM45: =AA45/AA$31*1000 -> 3.0360136 | AN45: =AB45/AB$31*1000 -> 3.1488122 | AO45: =AC45/AC$31*1000 -> 3.1381607 | ... AR45: =AF45/AF$31*1000 -> 2.4630438 | AT45: =AH45/AT$30 -> 0.025819983 | AU45: =AI45/AU$30 -> 0.024626615 | AV45: =AJ45/AV$30 -> 0.023659967 | AW45: =AK45/AW$30 -> 0.023858044 | AX45: =AL45/AX$30 -> 0.024428199 | AY45: =AM45/AY$30 -> 0.025085825 | AZ45: =AN45/AZ$30 -> 0.026017851 | BA45: =AO45/BA$30 -> 0.02592984 | ... BD45: =AR45/BD$30 -> 0.020351518
A46: =SUM(D46:F46) -> 26.2841 | C46: Association dues | D46: 8.4916 | E46: 8.70346 | F46: 9.08904 | G46: 8.71558 | H46: 8.6381 | I46: 7.07974 | J46: 9.466 | K46: 7.111 | L46: 6.994 | M46: 8.07241 | N46: 5.47521 | O46: 8.44809 | P46: =SUM(D46:O46) -> 96.28423 | Q46: =P46/$P$31*1000 -> 0.091892328 | S46: =Q46/$P$30 -> 0.00075928343 | V46: =D46+E46 -> 17.19506 | W46: =V46+F46 -> 26.2841 | X46: =W46+G46 -> 34.99968 | Y46: =X46+H46 -> 43.63778 | Z46: =Y46+I46 -> 50.71752 | AA46: =Z46+J46 -> 60.18352 | AB46: =AA46+K46 -> 67.29452 | AC46: =AB46+L46 -> 74.28852 | AD46: =AC46+M46 -> 82.36093 | ... AF46: =AE46+O46 -> 96.28423 | AH46: =V46/V$31*1000 -> 0.10626238 | AI46: =W46/W$31*1000 -> 0.10328796 | AJ46: =X46/X$31*1000 -> 0.099104035 | AK46: =Y46/Y$31*1000 -> 0.097729926 | AL46: =Z46/Z$31*1000 -> 0.097233391 | AM46: =AA46/AA$31*1000 -> 0.10040544 | AN46: =AB46/AB$31*1000 -> 0.10223759 | AO46: =AC46/AC$31*1000 -> 0.099177911 | ... AR46: =AF46/AF$31*1000 -> 0.091892328 | AT46: =AH46/AT$30 -> 0.00087801961 | AU46: =AI46/AU$30 -> 0.00085344268 | AV46: =AJ46/AV$30 -> 0.00081887196 | AW46: =AK46/AW$30 -> 0.00080751804 | AX46: =AL46/AX$30 -> 0.0008034153 | AY46: =AM46/AY$30 -> 0.00082962511 | AZ46: =AN46/AZ$30 -> 0.00084476375 | BA46: =AO46/BA$30 -> 0.00081948238 | ... BD46: =AR46/BD$30 -> 0.00075928343
A47: =SUM(D47:F47) -> 497.73857 | C47: G&A | D47: 136.57547 | E47: 246.01555 | F47: 115.14755 | G47: 193.17923 | H47: 102.15479 | I47: 136.76545 | J47: 112.85825 | K47: 120.58594 | L47: =L44-L45-L46 -> 152.16387 | M47: 122.34186 | N47: 127.42653 | O47: 76.79771 | P47: =SUM(D47:O47) -> 1642.0122 | Q47: =P47/$P$31*1000 -> 1.5671136 | S47: =Q47/$P$30 -> 0.012948669 | V47: =D47+E47 -> 382.59102 | W47: =V47+F47 -> 497.73857 | X47: =W47+G47 -> 690.9178 | Y47: =X47+H47 -> 793.07259 | Z47: =Y47+I47 -> 929.83804 | AA47: =Z47+J47 -> 1042.6963 | AB47: =AA47+K47 -> 1163.2822 | AC47: =AB47+L47 -> 1315.4461 | AD47: =AC47+M47 -> 1437.788 | ... AF47: =AE47+O47 -> 1642.0122 | AH47: =V47/V$31*1000 -> 2.3643438 | AI47: =W47/W$31*1000 -> 1.9559506 | AJ47: =X47/X$31*1000 -> 1.9563819 | AK47: =Y47/Y$31*1000 -> 1.7761427 | AL47: =Z47/Z$31*1000 -> 1.7826444 | AM47: =AA47/AA$31*1000 -> 1.7395522 | AN47: =AB47/AB$31*1000 -> 1.7673233 | AO47: =AC47/AC$31*1000 -> 1.756169 | ... AR47: =AF47/AF$31*1000 -> 1.5671136 | AT47: =AH47/AT$30 -> 0.019535984 | AU47: =AI47/AU$30 -> 0.016161533 | AV47: =AJ47/AV$30 -> 0.016165097 | AW47: =AK47/AW$30 -> 0.014675825 | AX47: =AL47/AX$30 -> 0.014729547 | AY47: =AM47/AY$30 -> 0.014373487 | AZ47: =AN47/AZ$30 -> 0.014602952 | BA47: =AO47/BA$30 -> 0.014510787 | ... BD47: =AR47/BD$30 -> 0.012948669
A48: =SUM(D48:F48) -> 8458.1264 | B48: 合计 | D48: =SUM(D32:D44) -> 2786.3724 | E48: =SUM(E32:E44) -> 2692.3076 | F48: =SUM(F32:F44) -> 2979.4464 | G48: =SUM(G32:G44) -> 2556.6921 | H48: =SUM(H32:H44) -> 2816.0237 | I48: =SUM(I32:I44) -> 2742.9449 | J48: =SUM(J32:J44) -> 2368.5937 | K48: =SUM(K32:K44) -> 2153.779 | L48: 1237.8443 | M48: 2317.4637 | N48: =SUM(N32:N44) -> 2618.503 | O48: =SUM(O32:O44) -> 1590.4388 | P48: =SUM(P32:P44) -> 28860.409 | Q48: =P49/P30 -> 0.22758899 | S48: =Q48/$P$30 -> 0.0018805112 | V48: =SUM(V32:V44) -> 5478.68 | W48: =SUM(W32:W44) -> 8458.1264 | X48: =SUM(X32:X44) -> 11014.819 | Y48: =SUM(Y32:Y44) -> 13830.842 | Z48: =SUM(Z32:Z44) -> 16573.787 | AA48: =SUM(AA32:AA44) -> 18942.381 | AB48: =SUM(AB32:AB44) -> 21096.16 | AC48: =SUM(AC32:AC44) -> 22334.004 | ... AF48: =SUM(AF32:AF44) -> 28860.529 | AH48: =V48/V$31*1000 -> 33.857258 | AI48: =W48/W$31*1000 -> 33.237684 | AJ48: =X48/X$31*1000 -> 31.189227 | AK48: =Y48/Y$31*1000 -> 30.975159 | AL48: =Z48/Z$31*1000 -> 31.774533 | AM48: =AA48/AA$31*1000 -> 31.601973 | AN48: =AB48/AB$31*1000 -> 32.050463 | AO48: =AC48/AC$31*1000 -> 29.816718 | ... AR48: =AF48/AF$31*1000 -> 27.544087 | AT48: =AH48/AT$30 -> 0.2797541 | AU48: =AI48/AU$30 -> 0.27463471 | AV48: =AJ48/AV$30 -> 0.25770881 | AW48: =AK48/AW$30 -> 0.25594003 | AX48: =AL48/AX$30 -> 0.26254505 | AY48: =AM48/AY$30 -> 0.26111924 | AZ48: =AN48/AZ$30 -> 0.264825 | BA48: =AO48/BA$30 -> 0.24636812 | ... BD48: =AR48/BD$30 -> 0.22758994
A49: =A48/A31*1000 -> 33.237684 | B49: 单台 | D49: =D48/D31*1000 -> 34.955495 | E49: =E48/E31*1000 -> 32.791031 | F49: =F48/F31*1000 -> 32.155654 | G49: =G48/G31*1000 -> 25.907081 | H49: =H48/H31*1000 -> 30.165326 | I49: =I48/I31*1000 -> 36.527791 | J49: =J48/J31*1000 -> 30.44504 | K49: =K48/K31*1000 -> 36.62142 | L49: =L48*1000/L31 -> 13.628744 | M49: 20.771015 | N49: =N48/N31*1000 -> 23.458034 | O49: =O48/O31*1000 -> 21.050359 | P49: =P48/P31*1000 -> 27.543973 | Q49: =P49 -> 27.543973 | S49: =Q49/$P$30 -> 0.22758899 | V49: =V48/V31*1000 -> 33.857258 | W49: =W48/W31*1000 -> 33.237684 | X49: =X48/X31*1000 -> 31.189227 | Y49: =Y48/Y31*1000 -> 30.975159 | Z49: =Z48/Z31*1000 -> 31.774533 | AA49: =AA48/AA31*1000 -> 31.601973 | AB49: =AB48/AB31*1000 -> 32.050463 | AC49: =AC48/AC31*1000 -> 29.816718 | ... AF49: =AF48/AF31*1000 -> 27.544087
A50: =SUM(D50:F50) -> 1004.436 | B50: functional currency | D50: 366.58 | E50: 326.856 | F50: 311 | G50: 358 | H50: 360 | I50: 370 | J50: 392.4 | K50: 405.991 | L50: 379.4 | M50: 385 | N50: 380.95522 | O50: 395.9352 | P50: =SUM(D50:O50) -> 4432.1174 | Q50: =P50/$P$31*1000 -> 4.2299511 | R50: =P49-Q50-Q44 -> 19.191972 | S50: =Q50/$P$30 -> 0.034951033 | U50: =28/104 -> 0.26923077
C51: 厨电25年预算 | Q51: =P49/P30 -> 0.22758899
C52: 科目 | D52: 25年1月 | E52: 25年2月 | F52: 25年3月 | G52: 25年4月 | H52: 25年5月 | I52: 25年6月 | J52: 25年7月 | K52: 25年8月 | L52: 25年9月 | M52: 25年10月 | N52: 25年11月 | O52: 25年12月 | P52: 合计 | Q52: 单台 | R52: 占比 | S52: 费率 | T52: 同比
B53: 平均单价 | D53: 122.39668 | E53: 122.39668 | F53: 122.39668 | G53: 122.39668 | H53: 122.39668 | I53: 122.39668 | J53: 122.39668 | K53: 122.39668 | L53: 122.39668 | M53: 122.39668 | N53: 122.39668 | O53: 122.39668 | P53: =P4 -> 122.39668 | AT53: =$P$53 -> 122.39668 | AU53: =$P$53 -> 122.39668 | AV53: =$P$53 -> 122.39668 | AW53: =$P$53 -> 122.39668 | AX53: =$P$53 -> 122.39668 | AY53: =$P$53 -> 122.39668 | AZ53: =$P$53 -> 122.39668 | BA53: =$P$53 -> 122.39668 | ... BD53: =$P$53 -> 122.39668
C54: 产量 | D54: 76110 | E54: 75445 | F54: 97997 | G54: 107391 | H54: 94300 | I54: 104181 | J54: 103114 | K54: 79317 | L54: 129648 | M54: 103320 | N54: 94620 | O54: 93020 | P54: =SUM(D54:O54) -> 1158463 | V54: =D54+E54 -> 151555 | W54: =V54+F54 -> 249552 | X54: =W54+G54 -> 356943 | Y54: =X54+H54 -> 451243 | Z54: =Y54+I54 -> 555424 | AA54: =Z54+J54 -> 658538 | AB54: =AA54+K54 -> 737855 | AC54: =AB54+L54 -> 867503 | AD54: =AC54+M54 -> 970823 | ... AF54: =AE54+O54 -> 1158463
B55: 固定制造 | C55: 折旧 | D55: 490.855 | E55: 471.516 | F55: 489.569 | G55: 484.657 | H55: 490.591 | I55: 530.264 | J55: 549.732 | K55: 556.001 | L55: 550.304 | M55: 611.236 | N55: 605.41 | O55: 649.814 | P55: =SUM(D55:O55) -> 6479.949 | Q55: =P55/$P$54*1000 -> 5.5935744 | R55: =P55/$P$71 -> 0.22261911 | V55: =D55+E55 -> 962.371 | W55: =V55+F55 -> 1451.94 | X55: =W55+G55 -> 1936.597 | Y55: =X55+H55 -> 2427.188 | Z55: =Y55+I55 -> 2957.452 | AA55: =Z55+J55 -> 3507.184 | AB55: =AA55+K55 -> 4063.185 | AC55: =AB55+L55 -> 4613.489 | AD55: =AC55+M55 -> 5224.725 | ... AF55: =AE55+O55 -> 6479.949 | AH55: =V55/V$54*1000 -> 6.3499786 | AI55: =W55/W$54*1000 -> 5.8181862 | AJ55: =X55/X$54*1000 -> 5.4255077 | AK55: =Y55/Y$54*1000 -> 5.3788934 | AL55: =Z55/Z$54*1000 -> 5.3246745 | AM55: =AA55/AA$54*1000 -> 5.3257124 | AN55: =AB55/AB$54*1000 -> 5.5067527 | AO55: =AC55/AC$54*1000 -> 5.3181245 | ... AR55: =AF55/AF$54*1000 -> 5.5935744 | AT55: =AH55/AT$53 -> 0.051880317 | AU55: =AI55/AU$53 -> 0.04753549 | AV55: =AJ55/AV$53 -> 0.044327246 | AW55: =AK55/AW$53 -> 0.0439464 | AX55: =AL55/AX$53 -> 0.043503422 | AY55: =AM55/AY$53 -> 0.043511902 | AZ55: =AN55/AZ$53 -> 0.04499103 | BA55: =AO55/BA$53 -> 0.043449908 | ... BD55: =AR55/BD$53 -> 0.045700377
C56: 运营费 | D56: 117.69741 | E56: 117.69741 | F56: 117.67271 | G56: 117.67271 | H56: 117.648 | I56: 89.22425 | J56: 77.888795 | K56: 77.888795 | L56: 77.888795 | M56: 77.888795 | N56: 77.888795 | O56: 77.888795 | P56: =SUM(D56:O56) -> 1144.9453 | Q56: =P56/$P$54*1000 -> 0.98833131 | R56: =P56/$P$71 -> 0.039334676 | V56: =D56+E56 -> 235.39482 | W56: =V56+F56 -> 353.06752 | X56: =W56+G56 -> 470.74023 | Y56: =X56+H56 -> 588.38823 | Z56: =Y56+I56 -> 677.61248 | AA56: =Z56+J56 -> 755.50128 | AB56: =AA56+K56 -> 833.39007 | AC56: =AB56+L56 -> 911.27887 | AD56: =AC56+M56 -> 989.16766 | ... AF56: =AE56+O56 -> 1144.9453 | AH56: =V56/V$54*1000 -> 1.5531973 | AI56: =W56/W$54*1000 -> 1.4148054 | AJ56: =X56/X$54*1000 -> 1.3188106 | AK56: =Y56/Y$54*1000 -> 1.3039277 | AL56: =Z56/Z$54*1000 -> 1.2199914 | AM56: =AA56/AA$54*1000 -> 1.1472402 | AN56: =AB56/AB$54*1000 -> 1.1294768 | AO56: =AC56/AC$54*1000 -> 1.0504619 | ... AR56: =AF56/AF$54*1000 -> 0.98833131 | AT56: =AH56/AT$53 -> 0.012689865 | AU56: =AI56/AU$53 -> 0.011559181 | AV56: =AJ56/AV$53 -> 0.010774889 | AW56: =AK56/AW$53 -> 0.010653293 | AX56: =AL56/AX$53 -> 0.00996752 | AY56: =AM56/AY$53 -> 0.0093731318 | AZ56: =AN56/AZ$53 -> 0.0092280016 | BA56: =AO56/BA$53 -> 0.008582438 | ... BD56: =AR56/BD$53 -> 0.0080748212
C57: 存货跌价准备 | D57: 28.854448 | E57: 28.854448 | F57: 28.854448 | G57: 28.854448 | H57: 28.854448 | I57: 8.8544478 | J57: 8.8544478 | K57: 8.8544478 | L57: 8.8544478 | M57: 8.8544478 | N57: 8.8544478 | O57: 8.8544478 | P57: =SUM(D57:O57) -> 206.25337 | Q57: =P57/$P$54*1000 -> 0.17804054 | R57: =P57/$P$71 -> 0.0070858494 | V57: =D57+E57 -> 57.708896 | W57: =V57+F57 -> 86.563343 | X57: =W57+G57 -> 115.41779 | Y57: =X57+H57 -> 144.27224 | Z57: =Y57+I57 -> 153.12669 | AA57: =Z57+J57 -> 161.98113 | AB57: =AA57+K57 -> 170.83558 | AC57: =AB57+L57 -> 179.69003 | AD57: =AC57+M57 -> 188.54448 | ... AF57: =AE57+O57 -> 206.25337 | AH57: =V57/V$54*1000 -> 0.38077857 | AI57: =W57/W$54*1000 -> 0.34687497 | AJ57: =X57/X$54*1000 -> 0.32335076 | AK57: =Y57/Y$54*1000 -> 0.31972183 | AL57: =Z57/Z$54*1000 -> 0.27569332 | AM57: =AA57/AA$54*1000 -> 0.24597082 | AN57: =AB57/AB$54*1000 -> 0.23153002 | AO57: =AC57/AC$54*1000 -> 0.20713476 | ... AR57: =AF57/AF$54*1000 -> 0.17804054 | AT57: =AH57/AT$53 -> 0.0031110204 | AU57: =AI57/AU$53 -> 0.0028340227 | AV57: =AJ57/AV$53 -> 0.0026418262 | AW57: =AK57/AW$53 -> 0.0026121773 | AX57: =AL57/AX$53 -> 0.0022524575 | AY57: =AM57/AY$53 -> 0.0020096201 | AZ57: =AN57/AZ$53 -> 0.0018916364 | BA57: =AO57/BA$53 -> 0.0016923234 | ... BD57: =AR57/BD$53 -> 0.001454619
C58: 固定能源费 | D58: 40.246479 | E58: 40.572571 | F58: 42.859853 | G58: 40.18962 | H58: 30.556814 | I58: 21.046617 | J58: 21.672925 | K58: 21.560251 | L58: 23.956361 | M58: 27.447749 | N58: 30.75589 | O58: 35.078243 | P58: =SUM(D58:O58) -> 375.94337 | Q58: =P58/$P$54*1000 -> 0.3245191 | R58: =P58/$P$71 -> 0.012915562 | V58: =D58+E58 -> 80.81905 | W58: =V58+F58 -> 123.6789 | X58: =W58+G58 -> 163.86852 | Y58: =X58+H58 -> 194.42534 | Z58: =Y58+I58 -> 215.47195 | AA58: =Z58+J58 -> 237.14488 | AB58: =AA58+K58 -> 258.70513 | AC58: =AB58+L58 -> 282.66149 | AD58: =AC58+M58 -> 310.10924 | ... AF58: =AE58+O58 -> 375.94337 | AH58: =V58/V$54*1000 -> 0.53326548 | AI58: =W58/W$54*1000 -> 0.49560373 | AJ58: =X58/X$54*1000 -> 0.45908877 | AK58: =Y58/Y$54*1000 -> 0.43086615 | AL58: =Z58/Z$54*1000 -> 0.38794138 | AM58: =AA58/AA$54*1000 -> 0.36010812 | AN58: =AB58/AB$54*1000 -> 0.35061784 | AO58: =AC58/AC$54*1000 -> 0.32583344 | ... AR58: =AF58/AF$54*1000 -> 0.3245191 | AT58: =AH58/AT$53 -> 0.0043568623 | AU58: =AI58/AU$53 -> 0.0040491599 | AV58: =AJ58/AV$53 -> 0.003750827 | AW58: =AK58/AW$53 -> 0.0035202438 | AX58: =AL58/AX$53 -> 0.0031695417 | AY58: =AM58/AY$53 -> 0.0029421396 | AZ58: =AN58/AZ$53 -> 0.0028646026 | BA58: =AO58/BA$53 -> 0.0026621101 | ... BD58: =AR58/BD$53 -> 0.0026513718
C59: 间接人工成本-辅助人员 | D59: 443.29154 | E59: 294.73379 | F59: 401.38634 | G59: 350.62344 | H59: 355.51091 | I59: 328.03771 | J59: 271.1997 | K59: 320.76703 | L59: 345.9535 | M59: 321.36867 | N59: 313.62922 | O59: 400.61247 | P59: =SUM(D59:O59) -> 4147.1143 | Q59: =P59/$P$54*1000 -> 3.5798418 | R59: =P59/$P$71 -> 0.14247441 | V59: =D59+E59 -> 738.02534 | W59: =V59+F59 -> 1139.4117 | X59: =W59+G59 -> 1490.0351 | Y59: =X59+H59 -> 1845.546 | Z59: =Y59+I59 -> 2173.5837 | AA59: =Z59+J59 -> 2444.7834 | AB59: =AA59+K59 -> 2765.5505 | AC59: =AB59+L59 -> 3111.504 | AD59: =AC59+M59 -> 3432.8726 | ... AF59: =AE59+O59 -> 4147.1143 | AH59: =V59/V$54*1000 -> 4.8696865 | AI59: =W59/W$54*1000 -> 4.5658287 | AJ59: =X59/X$54*1000 -> 4.1744343 | AK59: =Y59/Y$54*1000 -> 4.0899161 | AL59: =Z59/Z$54*1000 -> 3.9133774 | AM59: =AA59/AA$54*1000 -> 3.7124409 | AN59: =AB59/AB$54*1000 -> 3.7480948 | AO59: =AC59/AC$54*1000 -> 3.5867357 | ... AR59: =AF59/AF$54*1000 -> 3.5798418 | AT59: =AH59/AT$53 -> 0.0397861 | AU59: =AI59/AU$53 -> 0.037303533 | AV59: =AJ59/AV$53 -> 0.034105781 | AW59: =AK59/AW$53 -> 0.033415254 | AX59: =AL59/AX$53 -> 0.031972905 | AY59: =AM59/AY$53 -> 0.030331223 | AZ59: =AN59/AZ$53 -> 0.03062252 | BA59: =AO59/BA$53 -> 0.029304191 | ... BD59: =AR59/BD$53 -> 0.029247867
C60: 固定人工-白领 | D60: 184.50388 | E60: 184.50388 | F60: 192.3761 | G60: 201.60483 | H60: 196.84932 | I60: 174.44297 | J60: 155.56086 | K60: 155.56086 | L60: 163.71387 | M60: 157.17507 | N60: 157.17507 | O60: 157.17507 | P60: =SUM(D60:O60) -> 2080.6418 | Q60: =P60/$P$54*1000 -> 1.7960365 | R60: =P60/$P$71 -> 0.071480598 | V60: =D60+E60 -> 369.00776 | W60: =V60+F60 -> 561.38387 | X60: =W60+G60 -> 762.9887 | Y60: =X60+H60 -> 959.83802 | Z60: =Y60+I60 -> 1134.281 | AA60: =Z60+J60 -> 1289.8418 | AB60: =AA60+K60 -> 1445.4027 | AC60: =AB60+L60 -> 1609.1166 | AD60: =AC60+M60 -> 1766.2917 | ... AF60: =AE60+O60 -> 2080.6418 | AH60: =V60/V$54*1000 -> 2.4348109 | AI60: =W60/W$54*1000 -> 2.2495667 | AJ60: =X60/X$54*1000 -> 2.1375645 | AK60: =Y60/Y$54*1000 -> 2.1270979 | AL60: =Z60/Z$54*1000 -> 2.0421894 | AM60: =AA60/AA$54*1000 -> 1.9586445 | AN60: =AB60/AB$54*1000 -> 1.9589251 | AO60: =AC60/AC$54*1000 -> 1.854883 | ... AR60: =AF60/AF$54*1000 -> 1.7960365 | AT60: =AH60/AT$53 -> 0.019892785 | AU60: =AI60/AU$53 -> 0.018379311 | AV60: =AJ60/AV$53 -> 0.017464236 | AW60: =AK60/AW$53 -> 0.017378722 | AX60: =AL60/AX$53 -> 0.016685006 | AY60: =AM60/AY$53 -> 0.016002432 | AZ60: =AN60/AZ$53 -> 0.016004724 | BA60: =AO60/BA$53 -> 0.015154684 | ... BD60: =AR60/BD$53 -> 0.014673899
C61: 半固定-班车/工作服 | D61: 263.4415 | E61: 267.1898 | F61: 275.52934 | G61: 268.57422 | H61: 267.9638 | I61: 200.07935 | J61: 209.7688 | K61: 165.60961 | L61: 207.80534 | M61: 201.26577 | N61: 213.62978 | O61: 216.10291 | P61: =SUM(D61:O61) -> 2756.9602 | Q61: =P61/$P$54*1000 -> 2.3798432 | R61: =P61/$P$71 -> 0.094715567 | V61: =D61+E61 -> 530.6313 | W61: =V61+F61 -> 806.16064 | X61: =W61+G61 -> 1074.7349 | Y61: =X61+H61 -> 1342.6987 | Z61: =Y61+I61 -> 1542.778 | AA61: =Z61+J61 -> 1752.5468 | AB61: =AA61+K61 -> 1918.1564 | AC61: =AB61+L61 -> 2125.9618 | AD61: =AC61+M61 -> 2327.2275 | ... AF61: =AE61+O61 -> 2756.9602 | AH61: =V61/V$54*1000 -> 3.5012458 | AI61: =W61/W$54*1000 -> 3.2304315 | AJ61: =X61/X$54*1000 -> 3.0109425 | AK61: =Y61/Y$54*1000 -> 2.9755557 | AL61: =Z61/Z$54*1000 -> 2.7776582 | AM61: =AA61/AA$54*1000 -> 2.6612691 | AN61: =AB61/AB$54*1000 -> 2.5996387 | AO61: =AC61/AC$54*1000 -> 2.4506679 | ... AR61: =AF61/AF$54*1000 -> 2.3798432 | AT61: =AH61/AT$53 -> 0.028605725 | AU61: =AI61/AU$53 -> 0.02639313 | AV61: =AJ61/AV$53 -> 0.024599871 | AW61: =AK61/AW$53 -> 0.024310755 | AX61: =AL61/AX$53 -> 0.022693901 | AY61: =AM61/AY$53 -> 0.021742984 | AZ61: =AN61/AZ$53 -> 0.021239455 | BA61: =AO61/BA$53 -> 0.02002234 | ... BD61: =AR61/BD$53 -> 0.01944369
B62: 变动制造 | C62: 直接人工 | D62: 454.20494 | E62: 472.92513 | F62: 634.23575 | G62: 553.62358 | H62: 551.22624 | I62: 576.59543 | J62: 469.36813 | K62: 477.16244 | L62: 601.77073 | M62: 499.57137 | N62: 489.73128 | O62: 500.52742 | P62: =SUM(D62:O62) -> 6280.9424 | Q62: =P62/$P$54*1000 -> 5.4217894 | R62: =P62/$P$71 -> 0.21578223 | V62: =D62+E62 -> 927.13007 | W62: =V62+F62 -> 1561.3658 | X62: =W62+G62 -> 2114.9894 | Y62: =X62+H62 -> 2666.2156 | Z62: =Y62+I62 -> 3242.8111 | AA62: =Z62+J62 -> 3712.1792 | AB62: =AA62+K62 -> 4189.3416 | AC62: =AB62+L62 -> 4791.1124 | AD62: =AC62+M62 -> 5290.6837 | ... AF62: =AE62+O62 -> 6280.9424 | AH62: =V62/V$54*1000 -> 6.1174496 | AI62: =W62/W$54*1000 -> 6.2566752 | AJ62: =X62/X$54*1000 -> 5.9252861 | AK62: =Y62/Y$54*1000 -> 5.9086028 | AL62: =Z62/Z$54*1000 -> 5.8384425 | AM62: =AA62/AA$54*1000 -> 5.6370007 | AN62: =AB62/AB$54*1000 -> 5.6777302 | AO62: =AC62/AC$54*1000 -> 5.522877 | ... AR62: =AF62/AF$54*1000 -> 5.4217894 | AT62: =AH62/AT$53 -> 0.049980519 | AU62: =AI62/AU$53 -> 0.051118014 | AV62: =AJ62/AV$53 -> 0.048410513 | AW62: =AK62/AW$53 -> 0.048274208 | AX62: =AL62/AX$53 -> 0.047700987 | AY62: =AM62/AY$53 -> 0.046055177 | AZ62: =AN62/AZ$53 -> 0.046387943 | BA62: =AO62/BA$53 -> 0.045122768 | ... BD62: =AR62/BD$53 -> 0.044296867
C63: 废料 | D63: 34.252811 | E63: 34.351203 | F63: 42.227543 | G63: 46.87803 | H63: 45.705211 | I63: 44.324327 | J63: 45.128673 | K63: 35.491161 | L63: 55.118595 | M63: 48.777227 | N63: 43.631656 | O63: 43.241906 | P63: =SUM(D63:O63) -> 519.12834 | Q63: =P63/$P$54*1000 -> 0.44811819 | R63: =P63/$P$71 -> 0.017834691 | V63: =D63+E63 -> 68.604014 | W63: =V63+F63 -> 110.83156 | X63: =W63+G63 -> 157.70959 | Y63: =X63+H63 -> 203.4148 | Z63: =Y63+I63 -> 247.73913 | AA63: =Z63+J63 -> 292.8678 | AB63: =AA63+K63 -> 328.35896 | AC63: =AB63+L63 -> 383.47755 | AD63: =AC63+M63 -> 432.25478 | ... AF63: =AE63+O63 -> 519.12834 | AH63: =V63/V$54*1000 -> 0.45266744 | AI63: =W63/W$54*1000 -> 0.44412209 | AJ63: =X63/X$54*1000 -> 0.44183409 | AK63: =Y63/Y$54*1000 -> 0.45078771 | AL63: =Z63/Z$54*1000 -> 0.44603605 | AM63: =AA63/AA$54*1000 -> 0.44472422 | AN63: =AB63/AB$54*1000 -> 0.44501827 | AO63: =AC63/AC$54*1000 -> 0.44204753 | ... AR63: =AF63/AF$54*1000 -> 0.44811819 | AT63: =AH63/AT$53 -> 0.0036983637 | AU63: =AI63/AU$53 -> 0.0036285469 | AV63: =AJ63/AV$53 -> 0.0036098536 | AW63: =AK63/AW$53 -> 0.003683006 | AX63: =AL63/AX$53 -> 0.0036441842 | AY63: =AM63/AY$53 -> 0.0036334664 | AZ63: =AN63/AZ$53 -> 0.0036358688 | BA63: =AO63/BA$53 -> 0.0036115973 | ... BD63: =AR63/BD$53 -> 0.0036611956
C64: 生产耗用品 | D64: 38.300139 | E64: 21.615915 | F64: 28.21336 | G64: 32.19633 | H64: 36.092541 | I64: 34.094902 | J64: 30.165923 | K64: 27.063147 | L64: 28.429658 | M64: 27.074839 | N64: 27.164884 | O64: 27.98157 | P64: =SUM(D64:O64) -> 358.39321 | Q64: =P64/$P$54*1000 -> 0.30936958 | R64: =P64/$P$71 -> 0.012312624 | V64: =D64+E64 -> 59.916054 | W64: =V64+F64 -> 88.129414 | X64: =W64+G64 -> 120.32574 | Y64: =X64+H64 -> 156.41829 | Z64: =Y64+I64 -> 190.51319 | AA64: =Z64+J64 -> 220.67911 | AB64: =AA64+K64 -> 247.74226 | AC64: =AB64+L64 -> 276.17192 | AD64: =AC64+M64 -> 303.24676 | ... AF64: =AE64+O64 -> 358.39321 | AH64: =V64/V$54*1000 -> 0.39534198 | AI64: =W64/W$54*1000 -> 0.3531505 | AJ64: =X64/X$54*1000 -> 0.33710073 | AK64: =Y64/Y$54*1000 -> 0.3466387 | AL64: =Z64/Z$54*1000 -> 0.34300496 | AM64: =AA64/AA$54*1000 -> 0.3351046 | AN64: =AB64/AB$54*1000 -> 0.33576009 | AO64: =AC64/AC$54*1000 -> 0.31835269 | ... AR64: =AF64/AF$54*1000 -> 0.30936958 | AT64: =AH64/AT$53 -> 0.0032300058 | AU64: =AI64/AU$53 -> 0.0028852948 | AV64: =AJ64/AV$53 -> 0.0027541656 | AW64: =AK64/AW$53 -> 0.0028320923 | AX64: =AL64/AX$53 -> 0.0028024041 | AY64: =AM64/AY$53 -> 0.0027378569 | AZ64: =AN64/AZ$53 -> 0.0027432124 | BA64: =AO64/BA$53 -> 0.0026009912 | ... BD64: =AR64/BD$53 -> 0.0025275978
C65: 废品收入 | D65: -57.770557 | E65: -57.080766 | F65: -72.353323 | G65: -81.178566 | H65: -82.41576 | I65: -80.418618 | J65: -83.139492 | K65: -66.792604 | L65: -101.45817 | M65: -93.015084 | N65: -83.467961 | O65: -83.495412 | P65: =SUM(D65:O65) -> -942.58631 | Q65: =P65/$P$54*1000 -> -0.8136525 | R65: =P65/$P$71 -> -0.03238262 | V65: =D65+E65 -> -114.85132 | W65: =V65+F65 -> -187.20465 | X65: =W65+G65 -> -268.38321 | Y65: =X65+H65 -> -350.79897 | Z65: =Y65+I65 -> -431.21759 | AA65: =Z65+J65 -> -514.35708 | AB65: =AA65+K65 -> -581.14969 | AC65: =AB65+L65 -> -682.60786 | AD65: =AC65+M65 -> -775.62294 | ... AF65: =AE65+O65 -> -942.58631 | AH65: =V65/V$54*1000 -> -0.75781943 | AI65: =W65/W$54*1000 -> -0.75016288 | AJ65: =X65/X$54*1000 -> -0.75189376 | AK65: =Y65/Y$54*1000 -> -0.77740591 | AL65: =Z65/Z$54*1000 -> -0.77637551 | AM65: =AA65/AA$54*1000 -> -0.78105908 | AN65: =AB65/AB$54*1000 -> -0.78762045 | AO65: =AC65/AC$54*1000 -> -0.78686512 | ... AR65: =AF65/AF$54*1000 -> -0.8136525 | AT65: =AH65/AT$53 -> -0.0061915031 | AU65: =AI65/AU$53 -> -0.0061289479 | AV65: =AJ65/AV$53 -> -0.0061430895 | AW65: =AK65/AW$53 -> -0.0063515277 | AX65: =AL65/AX$53 -> -0.0063431092 | AY65: =AM65/AY$53 -> -0.0063813747 | AZ65: =AN65/AZ$53 -> -0.0064349821 | BA65: =AO65/BA$53 -> -0.006428811 | ... BD65: =AR65/BD$53 -> -0.006647668
C66: 变动能源费 | D66: 39.347651 | E66: 39.310062 | F66: 53.385357 | G66: 60.988195 | H66: 67.21051 | I66: 67.187918 | J66: 72.038665 | K66: 58.925125 | L66: 90.98909 | M66: 91.822776 | N66: 82.750763 | O66: 84.773873 | P66: =SUM(D66:O66) -> 808.72999 | Q66: =P66/$P$54*1000 -> 0.69810601 | R66: =P66/$P$71 -> 0.027783977 | V66: =D66+E66 -> 78.657713 | W66: =V66+F66 -> 132.04307 | X66: =W66+G66 -> 193.03126 | Y66: =X66+H66 -> 260.24177 | Z66: =Y66+I66 -> 327.42969 | AA66: =Z66+J66 -> 399.46836 | AB66: =AA66+K66 -> 458.39348 | AC66: =AB66+L66 -> 549.38257 | AD66: =AC66+M66 -> 641.20535 | ... AF66: =AE66+O66 -> 808.72999 | AH66: =V66/V$54*1000 -> 0.5190044 | AI66: =W66/W$54*1000 -> 0.52912046 | AJ66: =X66/X$54*1000 -> 0.54079017 | AK66: =Y66/Y$54*1000 -> 0.57672202 | AL66: =Z66/Z$54*1000 -> 0.58951304 | AM66: =AA66/AA$54*1000 -> 0.6065988 | AN66: =AB66/AB$54*1000 -> 0.62125144 | AO66: =AC66/AC$54*1000 -> 0.63329184 | ... AR66: =AF66/AF$54*1000 -> 0.69810601 | AT66: =AH66/AT$53 -> 0.0042403471 | AU66: =AI66/AU$53 -> 0.0043229968 | AV66: =AJ66/AV$53 -> 0.0044183401 | AW66: =AK66/AW$53 -> 0.004711909 | AX66: =AL66/AX$53 -> 0.0048164137 | AY66: =AM66/AY$53 -> 0.0049560069 | AZ66: =AN66/AZ$53 -> 0.0050757213 | BA66: =AO66/BA$53 -> 0.0051740933 | ... BD66: =AR66/BD$53 -> 0.0057036352
B67: 分摊 | C67: 分摊费用 | D67: 479.74409 | E67: 478.94 | F67: 480.76248 | G67: 479.91122 | H67: 479.9248 | I67: 356.41066 | J67: 355.31077 | K67: 355.6956 | L67: 356.69976 | M67: 355.84971 | N67: 355.73197 | O67: 356.38771 | P67: =SUM(D67:O67) -> 4891.3688 | Q67: =P67/$P$54*1000 -> 4.2222918 | R67: =P67/$P$71 -> 0.16804333 | V67: =D67+E67 -> 958.6841 | W67: =V67+F67 -> 1439.4466 | X67: =W67+G67 -> 1919.3578 | Y67: =X67+H67 -> 2399.2826 | Z67: =Y67+I67 -> 2755.6933 | AA67: =Z67+J67 -> 3111.004 | AB67: =AA67+K67 -> 3466.6996 | AC67: =AB67+L67 -> 3823.3994 | AD67: =AC67+M67 -> 4179.2491 | ... AF67: =AE67+O67 -> 4891.3688 | AH67: =V67/V$54*1000 -> 6.3256514 | AI67: =W67/W$54*1000 -> 5.7681228 | AJ67: =X67/X$54*1000 -> 5.3772109 | AK67: =Y67/Y$54*1000 -> 5.3170522 | AL67: =Z67/Z$54*1000 -> 4.9614227 | AM67: =AA67/AA$54*1000 -> 4.7241071 | AN67: =AB67/AB$54*1000 -> 4.6983481 | AO67: =AC67/AC$54*1000 -> 4.4073616 | ... AR67: =AF67/AF$54*1000 -> 4.2222918 | AT67: =AH67/AT$53 -> 0.05168156 | AU67: =AI67/AU$53 -> 0.047126464 | AV67: =AJ67/AV$53 -> 0.043932653 | AW67: =AK67/AW$53 -> 0.043441147 | AX67: =AL67/AX$53 -> 0.040535599 | AY67: =AM67/AY$53 -> 0.038596693 | AZ67: =AN67/AZ$53 -> 0.038386238 | BA67: =AO67/BA$53 -> 0.036008833 | ... BD67: =AR67/BD$53 -> 0.034496783
C68: IT Expense-Internal Charge Out | P68: =SUM(D68:O68) -> 0 | V68: =D68+E68 -> 0 | W68: =V68+F68 -> 0 | X68: =W68+G68 -> 0 | Y68: =X68+H68 -> 0 | Z68: =Y68+I68 -> 0 | AA68: =Z68+J68 -> 0 | AB68: =AA68+K68 -> 0 | AC68: =AB68+L68 -> 0 | AD68: =AC68+M68 -> 0 | ... AF68: =AE68+O68 -> 0 | AH68: =V68/V$54*1000 -> 0 | AI68: =W68/W$54*1000 -> 0 | AJ68: =X68/X$54*1000 -> 0 | AK68: =Y68/Y$54*1000 -> 0 | AL68: =Z68/Z$54*1000 -> 0 | AM68: =AA68/AA$54*1000 -> 0 | AN68: =AB68/AB$54*1000 -> 0 | AO68: =AC68/AC$54*1000 -> 0 | ... AR68: =AF68/AF$54*1000 -> 0 | AT68: =AH68/AT$53 -> 0 | AU68: =AI68/AU$53 -> 0 | AV68: =AJ68/AV$53 -> 0 | AW68: =AK68/AW$53 -> 0 | AX68: =AL68/AX$53 -> 0 | AY68: =AM68/AY$53 -> 0 | AZ68: =AN68/AZ$53 -> 0 | BA68: =AO68/BA$53 -> 0 | ... BD68: =AR68/BD$53 -> 0
C69: Association dues | P69: =SUM(D69:O69) -> 0 | V69: =D69+E69 -> 0 | W69: =V69+F69 -> 0 | X69: =W69+G69 -> 0 | Y69: =X69+H69 -> 0 | Z69: =Y69+I69 -> 0 | AA69: =Z69+J69 -> 0 | AB69: =AA69+K69 -> 0 | AC69: =AB69+L69 -> 0 | AD69: =AC69+M69 -> 0 | ... AF69: =AE69+O69 -> 0 | AH69: =V69/V$54*1000 -> 0 | AI69: =W69/W$54*1000 -> 0 | AJ69: =X69/X$54*1000 -> 0 | AK69: =Y69/Y$54*1000 -> 0 | AL69: =Z69/Z$54*1000 -> 0 | AM69: =AA69/AA$54*1000 -> 0 | AN69: =AB69/AB$54*1000 -> 0 | AO69: =AC69/AC$54*1000 -> 0 | ... AR69: =AF69/AF$54*1000 -> 0 | AT69: =AH69/AT$53 -> 0 | AU69: =AI69/AU$53 -> 0 | AV69: =AJ69/AV$53 -> 0 | AW69: =AK69/AW$53 -> 0 | AX69: =AL69/AX$53 -> 0 | AY69: =AM69/AY$53 -> 0 | AZ69: =AN69/AZ$53 -> 0 | BA69: =AO69/BA$53 -> 0 | ... BD69: =AR69/BD$53 -> 0
C70: G&A | P70: =SUM(D70:O70) -> 0 | V70: =D70+E70 -> 0 | W70: =V70+F70 -> 0 | X70: =W70+G70 -> 0 | Y70: =X70+H70 -> 0 | Z70: =Y70+I70 -> 0 | AA70: =Z70+J70 -> 0 | AB70: =AA70+K70 -> 0 | AC70: =AB70+L70 -> 0 | AD70: =AC70+M70 -> 0 | ... AF70: =AE70+O70 -> 0 | AH70: =V70/V$54*1000 -> 0 | AI70: =W70/W$54*1000 -> 0 | AJ70: =X70/X$54*1000 -> 0 | AK70: =Y70/Y$54*1000 -> 0 | AL70: =Z70/Z$54*1000 -> 0 | AM70: =AA70/AA$54*1000 -> 0 | AN70: =AB70/AB$54*1000 -> 0 | AO70: =AC70/AC$54*1000 -> 0 | ... AR70: =AF70/AF$54*1000 -> 0 | AT70: =AH70/AT$53 -> 0 | AU70: =AI70/AU$53 -> 0 | AV70: =AJ70/AV$53 -> 0 | AW70: =AK70/AW$53 -> 0 | AX70: =AL70/AX$53 -> 0 | AY70: =AM70/AY$53 -> 0 | AZ70: =AN70/AZ$53 -> 0 | BA70: =AO70/BA$53 -> 0 | ... BD70: =AR70/BD$53 -> 0
B71: 合计 | D71: =SUM(D55:D67) -> 2556.9693 | E71: =SUM(E55:E67) -> 2395.1294 | F71: =SUM(F55:F67) -> 2714.7189 | G71: =SUM(G55:G67) -> 2584.5951 | H71: =SUM(H55:H67) -> 2585.7178 | I71: =SUM(I55:I67) -> 2350.144 | J71: =SUM(J55:J67) -> 2183.5502 | K71: =SUM(K55:K67) -> 2193.7869 | ... P71: =SUM(P55:P67) -> 29107.784 | V71: =SUM(V55:V67) -> 4952.0988 | W71: =SUM(W55:W67) -> 7666.8177 | X71: =SUM(X55:X67) -> 10251.413 | Y71: =SUM(Y55:Y67) -> 12837.131 | Z71: =SUM(Z55:Z67) -> 15187.275 | AA71: =SUM(AA55:AA67) -> 17370.825 | AB71: =SUM(AB55:AB67) -> 19564.612 | AC71: =SUM(AC55:AC67) -> 21974.638 | ... AF71: =SUM(AF55:AF67) -> 29107.784 | AH71: =V71/V$54*1000 -> 32.675258 | AI71: =W71/W$54*1000 -> 30.722325 | AJ71: =X71/X$54*1000 -> 28.720028 | AK71: =Y71/Y$54*1000 -> 28.448376 | AL71: =Z71/Z$54*1000 -> 27.343569 | AM71: =AA71/AA$54*1000 -> 26.377862 | AN71: =AB71/AB$54*1000 -> 26.515524 | AO71: =AC71/AC$54*1000 -> 25.330907 | ... AR71: =AF71/AF$54*1000 -> 25.126209 | AT71: =AH71/AT$53 -> 0.26696197 | AU71: =AI71/AU$53 -> 0.2510062 | AV71: =AJ71/AV$53 -> 0.23464711 | AW71: =AK71/AW$53 -> 0.23242768 | AX71: =AL71/AX$53 -> 0.22340123 | AY71: =AM71/AY$53 -> 0.21551126 | AZ71: =AN71/AZ$53 -> 0.21663597 | BA71: =AO71/BA$53 -> 0.20695747 | ... BD71: =AR71/BD$53 -> 0.20528506
B72: 单台 | D72: =D71/D54*1000 -> 33.595708 | E72: =E71/E54*1000 -> 31.746696 | F72: =F71/F54*1000 -> 27.702062 | G72: =G71/G54*1000 -> 24.067148 | H72: =H71/H54*1000 -> 27.420126 | I72: =I71/I54*1000 -> 22.558278 | J72: =J71/J54*1000 -> 21.176079 | K72: =K71/K54*1000 -> 27.65847 | ... P72: =P71/P54*1000 -> 25.126209 | V72: =V71/V54*1000 -> 32.675258 | W72: =W71/W54*1000 -> 30.722325 | X72: =X71/X54*1000 -> 28.720028 | Y72: =Y71/Y54*1000 -> 28.448376 | Z72: =Z71/Z54*1000 -> 27.343569 | AA72: =AA71/AA54*1000 -> 26.377862 | AB72: =AB71/AB54*1000 -> 26.515524 | AC72: =AC71/AC54*1000 -> 25.330907 | ... AF72: =AF71/AF54*1000 -> 25.126209 | AZ72: =AZ48-AZ71 -> 0.048189026
B73: functional currency | D73: 528.88143 | E73: 528.88143 | F73: 528.88143 | G73: 528.88143 | H73: 528.88143 | I73: 528.88143 | J73: 528.88143 | K73: 528.88143 | L73: 528.88143 | M73: 528.88143 | N73: 528.88143 | O73: 373.11006 | P73: =SUM(D73:O73) -> 6190.8058 | Q73: =P73/$P$54*1000 -> 5.3439823 | V73: =D73+E73 -> 1057.7629 | W73: =V73+F73 -> 1586.6443 | X73: =W73+G73 -> 2115.5257 | Y73: =X73+H73 -> 2644.4072 | Z73: =Y73+I73 -> 3173.2886 | AA73: =Z73+J73 -> 3702.17 | AB73: =AA73+K73 -> 4231.0514 | AC73: =AB73+L73 -> 4759.9329 | AD73: =AC73+M73 -> 5288.8143 | ... AF73: =AE73+O73 -> 6190.8058 | AH73: =V73/V$54*1000 -> 6.9793993 | AI73: =W73/W$54*1000 -> 6.3579706 | AJ73: =X73/X$54*1000 -> 5.9267886 | AK73: =Y73/Y$54*1000 -> 5.860273 | AL73: =Z73/Z$54*1000 -> 5.7132723 | AM73: =AA73/AA$54*1000 -> 5.6218016 | AN73: =AB73/AB$54*1000 -> 5.7342587 | AO73: =AC73/AC$54*1000 -> 5.4869353 | ... AR73: =AF73/AF$54*1000 -> 5.3439823
D74: =D72/D53 -> 0.27448218 | E74: =E72/E53 -> 0.25937546 | F74: =F72/F53 -> 0.22633017 | G74: =G72/G53 -> 0.19663236 | H74: =H72/H53 -> 0.22402671 | I74: =I72/I53 -> 0.18430466 | J74: =J72/J53 -> 0.17301187 | K74: =K72/K53 -> 0.22597402 | ... P74: =P72/P53 -> 0.20528506
C76: 厨电26年实际 | Q76: =P75/P57 -> 0
A77: 年累 | C77: 科目 | D77: 25年1月 | E77: 25年2月 | F77: 25年3月 | G77: 25年4月 | H77: 25年5月 | I77: 25年6月 | J77: 25年7月 | K77: 25年8月 | L77: 25年9月 | M77: 25年10月 | N77: 25年11月 | O77: 25年12月 | P77: 合计 | Q77: 单台 | R77: 占比 | S77: 费率 | T77: 同比
A78: 125 | B78: 平均单价 | D78: 125 | E78: 116 | F78: 117 | G78: 115.56375 | H78: 117.21207 | P78: =SUMPRODUCT(D79:G79,D78:G78)/P79 -> 101.90326 | AT78: =$P$78 -> 101.90326 | AU78: =$P$78 -> 101.90326 | AV78: =$P$78 -> 101.90326 | AW78: =$P$78 -> 101.90326 | AX78: =$P$78 -> 101.90326 | AY78: =$P$78 -> 101.90326 | AZ78: =$P$78 -> 101.90326 | BA78: =$P$78 -> 101.90326 | ... BD78: =$P$78 -> 101.90326
A79: =SUM(D79:F79) -> 311281 | C79: 产量 | D79: 97611 | E79: 106294 | F79: 107376 | G79: 110370 | H79: 67531 | P79: =SUM(D79:O79) -> 489182 | V79: =D79+E79 -> 203905 | W79: =V79+F79 -> 311281 | X79: =W79+G79 -> 421651 | Y79: =X79+H79 -> 489182 | Z79: =Y79+I79 -> 489182 | AA79: =Z79+J79 -> 489182 | AB79: =AA79+K79 -> 489182 | AC79: =AB79+L79 -> 489182 | AD79: =AC79+M79 -> 489182 | ... AF79: =AE79+O79 -> 489182
A80: =SUM(D80:F80) -> 2230.1126 | B80: 固定制造 | C80: 折旧（含FC) | D80: =415.478390812441+D98 -> 818.33241 | E80: =362.675055365863+E98 -> 613.15617 | F80: =409.48744019919+F98 -> 798.62406 | G80: 466.69395 | H80: 254 | P80: =SUM(D80:O80) -> 2950.8066 | Q80: =P80/$P$79*1000 -> 6.0321242 | R80: =P80/$P$71 -> 0.10137517 | T80: =Q80-Q32 -> -2.6716501 | V80: =D80+E80 -> 1431.4886 | W80: =V80+F80 -> 2230.1126 | X80: =W80+G80 -> 2696.8066 | Y80: =X80+H80 -> 2950.8066 | Z80: =Y80+I80 -> 2950.8066 | AA80: =Z80+J80 -> 2950.8066 | AB80: =AA80+K80 -> 2950.8066 | AC80: =AB80+L80 -> 2950.8066 | AD80: =AC80+M80 -> 2950.8066 | ... AF80: =AE80+O80 -> 2950.8066 | AH80: =V80/V$79*1000 -> 7.0203702 | AI80: =W80/W$79*1000 -> 7.164307 | AJ80: =X80/X$79*1000 -> 6.3958264 | AK80: =Y80/Y$79*1000 -> 6.0321242 | AL80: =Z80/Z$79*1000 -> 6.0321242 | AM80: =AA80/AA$79*1000 -> 6.0321242 | AN80: =AB80/AB$79*1000 -> 6.0321242 | AO80: =AC80/AC$79*1000 -> 6.0321242 | ... AR80: =AF80/AF$79*1000 -> 6.0321242 | AT80: =AH80/AT$78 -> 0.068892497 | AU80: =AI80/AU$78 -> 0.070304981 | AV80: =AJ80/AV$78 -> 0.062763706 | AW80: =AK80/AW$78 -> 0.059194613 | AX80: =AL80/AX$78 -> 0.059194613 | AY80: =AM80/AY$78 -> 0.059194613 | AZ80: =AN80/AZ$78 -> 0.059194613 | BA80: =AO80/BA$78 -> 0.059194613 | ... BD80: =AR80/BD$78 -> 0.059194613
A81: =SUM(D81:F81) -> 216.13543 | C81: 运营费 | D81: 71.9181 | E81: 101.48011 | F81: 42.73722 | G81: 80.12026 | H81: 77.70732 | P81: =SUM(D81:O81) -> 373.96301 | Q81: =P81/$P$79*1000 -> 0.76446601 | R81: =P81/$P$71 -> 0.012847526 | T81: =Q81-Q33 -> -0.28363391 | V81: =D81+E81 -> 173.39821 | W81: =V81+F81 -> 216.13543 | X81: =W81+G81 -> 296.25569 | Y81: =X81+H81 -> 373.96301 | Z81: =Y81+I81 -> 373.96301 | AA81: =Z81+J81 -> 373.96301 | AB81: =AA81+K81 -> 373.96301 | AC81: =AB81+L81 -> 373.96301 | AD81: =AC81+M81 -> 373.96301 | ... AF81: =AE81+O81 -> 373.96301 | AH81: =V81/V$79*1000 -> 0.85038724 | AI81: =W81/W$79*1000 -> 0.69434186 | AJ81: =X81/X$79*1000 -> 0.70260877 | AK81: =Y81/Y$79*1000 -> 0.76446601 | AL81: =Z81/Z$79*1000 -> 0.76446601 | AM81: =AA81/AA$79*1000 -> 0.76446601 | AN81: =AB81/AB$79*1000 -> 0.76446601 | AO81: =AC81/AC$79*1000 -> 0.76446601 | ... AR81: =AF81/AF$79*1000 -> 0.76446601 | AT81: =AH81/AT$78 -> 0.0083450443 | AU81: =AI81/AU$78 -> 0.0068137354 | AV81: =AJ81/AV$78 -> 0.0068948604 | AW81: =AK81/AW$78 -> 0.0075018796 | AX81: =AL81/AX$78 -> 0.0075018796 | AY81: =AM81/AY$78 -> 0.0075018796 | AZ81: =AN81/AZ$78 -> 0.0075018796 | BA81: =AO81/BA$78 -> 0.0075018796 | ... BD81: =AR81/BD$78 -> 0.0075018796
A82: =SUM(D82:F82) -> 25 | C82: 存货跌价准备 | D82: 12.5 | E82: 0 | F82: 12.5 | G82: 12.5 | H82: 16.166 | P82: =SUM(D82:O82) -> 53.666 | Q82: =P82/$P$79*1000 -> 0.10970559 | R82: =P82/$P$71 -> 0.0018436993 | T82: =Q82-Q34 -> 1.318413 | V82: =D82+E82 -> 12.5 | W82: =V82+F82 -> 25 | X82: =W82+G82 -> 37.5 | Y82: =X82+H82 -> 53.666 | Z82: =Y82+I82 -> 53.666 | AA82: =Z82+J82 -> 53.666 | AB82: =AA82+K82 -> 53.666 | AC82: =AB82+L82 -> 53.666 | AD82: =AC82+M82 -> 53.666 | ... AF82: =AE82+O82 -> 53.666 | AH82: =V82/V$79*1000 -> 0.061303058 | AI82: =W82/W$79*1000 -> 0.080313286 | AJ82: =X82/X$79*1000 -> 0.088936111 | AK82: =Y82/Y$79*1000 -> 0.10970559 | AL82: =Z82/Z$79*1000 -> 0.10970559 | AM82: =AA82/AA$79*1000 -> 0.10970559 | AN82: =AB82/AB$79*1000 -> 0.10970559 | AO82: =AC82/AC$79*1000 -> 0.10970559 | ... AR82: =AF82/AF$79*1000 -> 0.10970559 | AT82: =AH82/AT$78 -> 0.00060158091 | AU82: =AI82/AU$78 -> 0.00078813263 | AV82: =AJ82/AV$78 -> 0.00087275037 | AW82: =AK82/AW$78 -> 0.001076566 | AX82: =AL82/AX$78 -> 0.001076566 | AY82: =AM82/AY$78 -> 0.001076566 | AZ82: =AN82/AZ$78 -> 0.001076566 | BA82: =AO82/BA$78 -> 0.001076566 | ... BD82: =AR82/BD$78 -> 0.001076566
A83: =SUM(D83:F83) -> 94.72341 | C83: 固定能源费 | D83: 34.59988 | E83: 27.20591 | F83: 32.91762 | G83: 28.54195 | H83: 28.4377 | P83: =SUM(D83:O83) -> 151.70306 | Q83: =P83/$P$79*1000 -> 0.31011579 | R83: =P83/$P$71 -> 0.0052117695 | T83: =Q83-Q35 -> -0.032796848 | V83: =D83+E83 -> 61.80579 | W83: =V83+F83 -> 94.72341 | X83: =W83+G83 -> 123.26536 | Y83: =X83+H83 -> 151.70306 | Z83: =Y83+I83 -> 151.70306 | AA83: =Z83+J83 -> 151.70306 | AB83: =AA83+K83 -> 151.70306 | AC83: =AB83+L83 -> 151.70306 | AD83: =AC83+M83 -> 151.70306 | ... AF83: =AE83+O83 -> 151.70306 | AH83: =V83/V$79*1000 -> 0.30311071 | AI83: =W83/W$79*1000 -> 0.30430193 | AJ83: =X83/X$79*1000 -> 0.29233978 | AK83: =Y83/Y$79*1000 -> 0.31011579 | AL83: =Z83/Z$79*1000 -> 0.31011579 | AM83: =AA83/AA$79*1000 -> 0.31011579 | AN83: =AB83/AB$79*1000 -> 0.31011579 | AO83: =AC83/AC$79*1000 -> 0.31011579 | ... AR83: =AF83/AF$79*1000 -> 0.31011579 | AT83: =AH83/AT$78 -> 0.0029744947 | AU83: =AI83/AU$78 -> 0.0029861844 | AV83: =AJ83/AV$78 -> 0.002868797 | AW83: =AK83/AW$78 -> 0.0030432371 | AX83: =AL83/AX$78 -> 0.0030432371 | AY83: =AM83/AY$78 -> 0.0030432371 | AZ83: =AN83/AZ$78 -> 0.0030432371 | BA83: =AO83/BA$78 -> 0.0030432371 | ... BD83: =AR83/BD$78 -> 0.0030432371
A84: =SUM(D84:F84) -> 1000.1689 | C84: 间接人工成本-辅助人员 | D84: 327.62548 | E84: 309.61298 | F84: 362.9304 | G84: 338.49412 | H84: 370.45466 | P84: =SUM(D84:O84) -> 1709.1176 | Q84: =P84/$P$79*1000 -> 3.4938277 | R84: =P84/$P$71 -> 0.058716859 | T84: =Q84-Q36 -> -0.85036568 | V84: =D84+E84 -> 637.23846 | W84: =V84+F84 -> 1000.1689 | X84: =W84+G84 -> 1338.663 | Y84: =X84+H84 -> 1709.1176 | Z84: =Y84+I84 -> 1709.1176 | AA84: =Z84+J84 -> 1709.1176 | AB84: =AA84+K84 -> 1709.1176 | AC84: =AB84+L84 -> 1709.1176 | AD84: =AC84+M84 -> 1709.1176 | ... AF84: =AE84+O84 -> 1709.1176 | AH84: =V84/V$79*1000 -> 3.1251733 | AI84: =W84/W$79*1000 -> 3.2130739 | AJ84: =X84/X$79*1000 -> 3.1748128 | AK84: =Y84/Y$79*1000 -> 3.4938277 | AL84: =Z84/Z$79*1000 -> 3.4938277 | AM84: =AA84/AA$79*1000 -> 3.4938277 | AN84: =AB84/AB$79*1000 -> 3.4938277 | AO84: =AC84/AC$79*1000 -> 3.4938277 | ... AR84: =AF84/AF$79*1000 -> 3.4938277 | AT84: =AH84/AT$78 -> 0.03066804 | AU84: =AI84/AU$78 -> 0.031530628 | AV84: =AJ84/AV$78 -> 0.031155163 | AW84: =AK84/AW$78 -> 0.03428573 | AX84: =AL84/AX$78 -> 0.03428573 | AY84: =AM84/AY$78 -> 0.03428573 | AZ84: =AN84/AZ$78 -> 0.03428573 | BA84: =AO84/BA$78 -> 0.03428573 | ... BD84: =AR84/BD$78 -> 0.03428573
A85: =SUM(D85:F85) -> 484.38819 | C85: 固定人工-白领 | D85: 170.39671 | E85: 155.42297 | F85: 158.56851 | G85: 79.74634 | H85: 175.60942 | P85: =SUM(D85:O85) -> 739.74395 | Q85: =P85/$P$79*1000 -> 1.512206 | R85: =P85/$P$71 -> 0.025413956 | T85: =Q85-Q37 -> -0.33752357 | V85: =D85+E85 -> 325.81968 | W85: =V85+F85 -> 484.38819 | X85: =W85+G85 -> 564.13453 | Y85: =X85+H85 -> 739.74395 | Z85: =Y85+I85 -> 739.74395 | AA85: =Z85+J85 -> 739.74395 | AB85: =AA85+K85 -> 739.74395 | AC85: =AB85+L85 -> 739.74395 | AD85: =AC85+M85 -> 739.74395 | ... AF85: =AE85+O85 -> 739.74395 | AH85: =V85/V$79*1000 -> 1.5978994 | AI85: =W85/W$79*1000 -> 1.5561123 | AJ85: =X85/X$79*1000 -> 1.3379182 | AK85: =Y85/Y$79*1000 -> 1.512206 | AL85: =Z85/Z$79*1000 -> 1.512206 | AM85: =AA85/AA$79*1000 -> 1.512206 | AN85: =AB85/AB$79*1000 -> 1.512206 | AO85: =AC85/AC$79*1000 -> 1.512206 | ... AR85: =AF85/AF$79*1000 -> 1.512206 | AT85: =AH85/AT$78 -> 0.015680552 | AU85: =AI85/AU$78 -> 0.015270485 | AV85: =AJ85/AV$78 -> 0.013129297 | AW85: =AK85/AW$78 -> 0.014839623 | AX85: =AL85/AX$78 -> 0.014839623 | AY85: =AM85/AY$78 -> 0.014839623 | AZ85: =AN85/AZ$78 -> 0.014839623 | BA85: =AO85/BA$78 -> 0.014839623 | ... BD85: =AR85/BD$78 -> 0.014839623
A86: =SUM(D86:F86) -> 586.70041 | C86: 半固定-班车/工作服 | D86: 161.25072 | E86: 302.85213 | F86: 122.59756 | G86: 204.70201 | H86: 167.44816 | P86: =SUM(D86:O86) -> 958.85058 | Q86: =P86/$P$79*1000 -> 1.9601101 | R86: =P86/$P$71 -> 0.03294138 | T86: =Q86-Q38 -> 0.13569774 | V86: =D86+E86 -> 464.10285 | W86: =V86+F86 -> 586.70041 | X86: =W86+G86 -> 791.40242 | Y86: =X86+H86 -> 958.85058 | Z86: =Y86+I86 -> 958.85058 | AA86: =Z86+J86 -> 958.85058 | AB86: =AA86+K86 -> 958.85058 | AC86: =AB86+L86 -> 958.85058 | AD86: =AC86+M86 -> 958.85058 | ... AF86: =AE86+O86 -> 958.85058 | AH86: =V86/V$79*1000 -> 2.2760739 | AI86: =W86/W$79*1000 -> 1.8847935 | AJ86: =X86/X$79*1000 -> 1.8769134 | AK86: =Y86/Y$79*1000 -> 1.9601101 | AL86: =Z86/Z$79*1000 -> 1.9601101 | AM86: =AA86/AA$79*1000 -> 1.9601101 | AN86: =AB86/AB$79*1000 -> 1.9601101 | AO86: =AC86/AC$79*1000 -> 1.9601101 | ... AR86: =AF86/AF$79*1000 -> 1.9601101 | AT86: =AH86/AT$78 -> 0.022335633 | AU86: =AI86/AU$78 -> 0.018495909 | AV86: =AJ86/AV$78 -> 0.01841858 | AW86: =AK86/AW$78 -> 0.019235008 | AX86: =AL86/AX$78 -> 0.019235008 | AY86: =AM86/AY$78 -> 0.019235008 | AZ86: =AN86/AZ$78 -> 0.019235008 | BA86: =AO86/BA$78 -> 0.019235008 | ... BD86: =AR86/BD$78 -> 0.019235008
A87: =SUM(D87:F87) -> 2018.7945 | B87: 变动制造 | C87: 直接人工 | D87: 590.41207 | E87: 617.89438 | F87: 810.48808 | G87: 662.67459 | H87: 725.8949 | P87: =SUM(D87:O87) -> 3407.364 | Q87: =P87/$P$79*1000 -> 6.9654321 | R87: =P87/$P$71 -> 0.11706024 | T87: =Q87-Q39 -> 0.52960893 | V87: =D87+E87 -> 1208.3065 | W87: =V87+F87 -> 2018.7945 | X87: =W87+G87 -> 2681.4691 | Y87: =X87+H87 -> 3407.364 | Z87: =Y87+I87 -> 3407.364 | AA87: =Z87+J87 -> 3407.364 | AB87: =AA87+K87 -> 3407.364 | AC87: =AB87+L87 -> 3407.364 | AD87: =AC87+M87 -> 3407.364 | ... AF87: =AE87+O87 -> 3407.364 | AH87: =V87/V$79*1000 -> 5.9258304 | AI87: =W87/W$79*1000 -> 6.4854409 | AJ87: =X87/X$79*1000 -> 6.3594516 | AK87: =Y87/Y$79*1000 -> 6.9654321 | AL87: =Z87/Z$79*1000 -> 6.9654321 | AM87: =AA87/AA$79*1000 -> 6.9654321 | AN87: =AB87/AB$79*1000 -> 6.9654321 | AO87: =AC87/AC$79*1000 -> 6.9654321 | ... AR87: =AF87/AF$79*1000 -> 6.9654321 | AT87: =AH87/AT$78 -> 0.058151528 | AU87: =AI87/AU$78 -> 0.063643113 | AV87: =AJ87/AV$78 -> 0.062406751 | AW87: =AK87/AW$78 -> 0.068353377 | AX87: =AL87/AX$78 -> 0.068353377 | AY87: =AM87/AY$78 -> 0.068353377 | AZ87: =AN87/AZ$78 -> 0.068353377 | BA87: =AO87/BA$78 -> 0.068353377 | ... BD87: =AR87/BD$78 -> 0.068353377
A88: =SUM(D88:F88) -> 155.37869 | C88: 可回收废料 | D88: 47.50766 | E88: 53.14224 | F88: 54.72879 | G88: 59.13461 | H88: 35.76659 | P88: =SUM(D88:O88) -> 250.27989 | Q88: =P88/$P$79*1000 -> 0.51162939 | R88: =P88/$P$71 -> 0.0085983836 | T88: =Q88-Q40 -> 0.071483115 | V88: =D88+E88 -> 100.6499 | W88: =V88+F88 -> 155.37869 | X88: =W88+G88 -> 214.5133 | Y88: =X88+H88 -> 250.27989 | Z88: =Y88+I88 -> 250.27989 | AA88: =Z88+J88 -> 250.27989 | AB88: =AA88+K88 -> 250.27989 | AC88: =AB88+L88 -> 250.27989 | AD88: =AC88+M88 -> 250.27989 | ... AF88: =AE88+O88 -> 250.27989 | AH88: =V88/V$79*1000 -> 0.49361173 | AI88: =W88/W$79*1000 -> 0.49915893 | AJ88: =X88/X$79*1000 -> 0.5087461 | AK88: =Y88/Y$79*1000 -> 0.51162939 | AL88: =Z88/Z$79*1000 -> 0.51162939 | AM88: =AA88/AA$79*1000 -> 0.51162939 | AN88: =AB88/AB$79*1000 -> 0.51162939 | AO88: =AC88/AC$79*1000 -> 0.51162939 | ... AR88: =AF88/AF$79*1000 -> 0.51162939 | AT88: =AH88/AT$78 -> 0.0048439247 | AU88: =AI88/AU$78 -> 0.0048983606 | AV88: =AJ88/AV$78 -> 0.0049924417 | AW88: =AK88/AW$78 -> 0.0050207361 | AX88: =AL88/AX$78 -> 0.0050207361 | AY88: =AM88/AY$78 -> 0.0050207361 | AZ88: =AN88/AZ$78 -> 0.0050207361 | BA88: =AO88/BA$78 -> 0.0050207361 | ... BD88: =AR88/BD$78 -> 0.0050207361
A89: =SUM(D89:F89) -> 40.42829 | C89: 生产耗用品 | D89: 9.05877 | E89: 26.81478 | F89: 4.55474 | G89: 11.92993 | H89: 3.63285 | P89: =SUM(D89:O89) -> 55.99107 | Q89: =P89/$P$79*1000 -> 0.11445857 | R89: =P89/$P$71 -> 0.0019235772 | T89: =Q89-Q41 -> 0.16841252 | V89: =D89+E89 -> 35.87355 | W89: =V89+F89 -> 40.42829 | X89: =W89+G89 -> 52.35822 | Y89: =X89+H89 -> 55.99107 | Z89: =Y89+I89 -> 55.99107 | AA89: =Z89+J89 -> 55.99107 | AB89: =AA89+K89 -> 55.99107 | AC89: =AB89+L89 -> 55.99107 | AD89: =AC89+M89 -> 55.99107 | ... AF89: =AE89+O89 -> 55.99107 | AH89: =V89/V$79*1000 -> 0.17593266 | AI89: =W89/W$79*1000 -> 0.12987715 | AJ89: =X89/X$79*1000 -> 0.12417431 | AK89: =Y89/Y$79*1000 -> 0.11445857 | AL89: =Z89/Z$79*1000 -> 0.11445857 | AM89: =AA89/AA$79*1000 -> 0.11445857 | AN89: =AB89/AB$79*1000 -> 0.11445857 | AO89: =AC89/AC$79*1000 -> 0.11445857 | ... AR89: =AF89/AF$79*1000 -> 0.11445857 | AT89: =AH89/AT$78 -> 0.0017264674 | AU89: =AI89/AU$78 -> 0.0012745142 | AV89: =AJ89/AV$78 -> 0.0012185508 | AW89: =AK89/AW$78 -> 0.0011232081 | AX89: =AL89/AX$78 -> 0.0011232081 | AY89: =AM89/AY$78 -> 0.0011232081 | AZ89: =AN89/AZ$78 -> 0.0011232081 | BA89: =AO89/BA$78 -> 0.0011232081 | ... BD89: =AR89/BD$78 -> 0.0011232081
A90: =SUM(D90:F90) -> -229.1995 | C90: 废品回收 | D90: -65.75498 | E90: -85.73821 | F90: -77.70631 | G90: -84.25962 | H90: -69.87748 | P90: =SUM(D90:O90) -> -383.3366 | Q90: =P90/$P$79*1000 -> -0.78362777 | R90: =P90/$P$71 -> -0.013169556 | T90: =Q90-Q42 -> 0.057061125 | V90: =D90+E90 -> -151.49319 | W90: =V90+F90 -> -229.1995 | X90: =W90+G90 -> -313.45912 | Y90: =X90+H90 -> -383.3366 | Z90: =Y90+I90 -> -383.3366 | AA90: =Z90+J90 -> -383.3366 | AB90: =AA90+K90 -> -383.3366 | AC90: =AB90+L90 -> -383.3366 | AD90: =AC90+M90 -> -383.3366 | ... AF90: =AE90+O90 -> -383.3366 | AH90: =V90/V$79*1000 -> -0.74295966 | AI90: =W90/W$79*1000 -> -0.7363106 | AJ90: =X90/X$79*1000 -> -0.74340893 | AK90: =Y90/Y$79*1000 -> -0.78362777 | AL90: =Z90/Z$79*1000 -> -0.78362777 | AM90: =AA90/AA$79*1000 -> -0.78362777 | AN90: =AB90/AB$79*1000 -> -0.78362777 | AO90: =AC90/AC$79*1000 -> -0.78362777 | ... AR90: =AF90/AF$79*1000 -> -0.78362777 | AT90: =AH90/AT$78 -> -0.0072908329 | AU90: =AI90/AU$78 -> -0.0072255842 | AV90: =AJ90/AV$78 -> -0.0072952417 | AW90: =AK90/AW$78 -> -0.0076899184 | AX90: =AL90/AX$78 -> -0.0076899184 | AY90: =AM90/AY$78 -> -0.0076899184 | AZ90: =AN90/AZ$78 -> -0.0076899184 | BA90: =AO90/BA$78 -> -0.0076899184 | ... BD90: =AR90/BD$78 -> -0.0076899184
A91: =SUM(D91:F91) -> 110.6043 | C91: 变动能源费 | D91: 38.54558 | E91: 45.86664 | F91: 26.19208 | G91: 34.37261 | H91: 15.64715 | P91: =SUM(D91:O91) -> 160.62406 | Q91: =P91/$P$79*1000 -> 0.32835235 | R91: =P91/$P$71 -> 0.0055182511 | T91: =Q91-Q43 -> -0.20782924 | V91: =D91+E91 -> 84.41222 | W91: =V91+F91 -> 110.6043 | X91: =W91+G91 -> 144.97691 | Y91: =X91+H91 -> 160.62406 | Z91: =Y91+I91 -> 160.62406 | AA91: =Z91+J91 -> 160.62406 | AB91: =AA91+K91 -> 160.62406 | AC91: =AB91+L91 -> 160.62406 | AD91: =AC91+M91 -> 160.62406 | ... AF91: =AE91+O91 -> 160.62406 | AH91: =V91/V$79*1000 -> 0.41397818 | AI91: =W91/W$79*1000 -> 0.35531979 | AJ91: =X91/X$79*1000 -> 0.34383153 | AK91: =Y91/Y$79*1000 -> 0.32835235 | AL91: =Z91/Z$79*1000 -> 0.32835235 | AM91: =AA91/AA$79*1000 -> 0.32835235 | AN91: =AB91/AB$79*1000 -> 0.32835235 | AO91: =AC91/AC$79*1000 -> 0.32835235 | ... AR91: =AF91/AF$79*1000 -> 0.32835235 | AT91: =AH91/AT$78 -> 0.0040624624 | AU91: =AI91/AU$78 -> 0.0034868343 | AV91: =AJ91/AV$78 -> 0.0033740974 | AW91: =AK91/AW$78 -> 0.0032221966 | AX91: =AL91/AX$78 -> 0.0032221966 | AY91: =AM91/AY$78 -> 0.0032221966 | AZ91: =AN91/AZ$78 -> 0.0032221966 | BA91: =AO91/BA$78 -> 0.0032221966 | ... BD91: =AR91/BD$78 -> 0.0032221966
A92: =SUM(D92:F92) -> 704.87437 | B92: 分摊 | C92: 分摊费用 | D92: 277.38785 | E92: 184 | F92: 243.48652 | G92: 195.35993 | H92: 304.41425 | P92: =SUM(D92:O92) -> 1204.6486 | Q92: =P92/$P$79*1000 -> 2.4625774 | R92: =P92/$P$71 -> 0.041385787 | T92: =Q92-Q44 -> -1.6594723 | V92: =D92+E92 -> 461.38785 | W92: =V92+F92 -> 704.87437 | X92: =W92+G92 -> 900.2343 | Y92: =X92+H92 -> 1204.6486 | Z92: =Y92+I92 -> 1204.6486 | AA92: =Z92+J92 -> 1204.6486 | AB92: =AA92+K92 -> 1204.6486 | AC92: =AB92+L92 -> 1204.6486 | AD92: =AC92+M92 -> 1204.6486 | ... AF92: =AE92+O92 -> 1204.6486 | AH92: =V92/V$79*1000 -> 2.2627589 | AI92: =W92/W$79*1000 -> 2.2644311 | AJ92: =X92/X$79*1000 -> 2.1350223 | AK92: =Y92/Y$79*1000 -> 2.4625774 | AL92: =Z92/Z$79*1000 -> 2.4625774 | AM92: =AA92/AA$79*1000 -> 2.4625774 | AN92: =AB92/AB$79*1000 -> 2.4625774 | AO92: =AC92/AC$79*1000 -> 2.4625774 | ... AR92: =AF92/AF$79*1000 -> 2.4625774 | AT92: =AH92/AT$78 -> 0.02220497 | AU92: =AI92/AU$78 -> 0.02222138 | AV92: =AJ92/AV$78 -> 0.020951462 | AW92: =AK92/AW$78 -> 0.024165835 | AX92: =AL92/AX$78 -> 0.024165835 | AY92: =AM92/AY$78 -> 0.024165835 | AZ92: =AN92/AZ$78 -> 0.024165835 | BA92: =AO92/BA$78 -> 0.024165835 | ... BD92: =AR92/BD$78 -> 0.024165835
A93: =SUM(D93:F93) -> 284.99285 | C93: IT Expense-Internal Charge Out | D93: 94.62519 | E93: 95.18383 | F93: 95.18383 | G93: 95.18383 | H93: 95.18383 | P93: =SUM(D93:O93) -> 475.36051 | V93: =D93+E93 -> 189.80902 | W93: =V93+F93 -> 284.99285 | X93: =W93+G93 -> 380.17668 | Y93: =X93+H93 -> 475.36051 | Z93: =Y93+I93 -> 475.36051 | AA93: =Z93+J93 -> 475.36051 | AB93: =AA93+K93 -> 475.36051 | AC93: =AB93+L93 -> 475.36051 | AD93: =AC93+M93 -> 475.36051 | ... AF93: =AE93+O93 -> 475.36051 | AH93: =V93/V$79*1000 -> 0.93086987 | AI93: =W93/W$79*1000 -> 0.91554849 | AJ93: =X93/X$79*1000 -> 0.90163827 | AK93: =Y93/Y$79*1000 -> 0.97174571 | AL93: =Z93/Z$79*1000 -> 0.97174571 | AM93: =AA93/AA$79*1000 -> 0.97174571 | AN93: =AB93/AB$79*1000 -> 0.97174571 | AO93: =AC93/AC$79*1000 -> 0.97174571 | ... AR93: =AF93/AF$79*1000 -> 0.97174571 | AT93: =AH93/AT$78 -> 0.0091348387 | AU93: =AI93/AU$78 -> 0.0089844865 | AV93: =AJ93/AV$78 -> 0.0088479824 | AW93: =AK93/AW$78 -> 0.0095359627 | AX93: =AL93/AX$78 -> 0.0095359627 | AY93: =AM93/AY$78 -> 0.0095359627 | AZ93: =AN93/AZ$78 -> 0.0095359627 | BA93: =AO93/BA$78 -> 0.0095359627 | ... BD93: =AR93/BD$78 -> 0.0095359627
A94: =SUM(D94:F94) -> 7.51242 | C94: Association dues | D94: 4.97102 | E94: 2.44438 | F94: 0.09702 | G94: 11.05664 | H94: =SUMIFS('[2]Renta CK TOTAL_2026'!$Q:$Q,'[2]Renta CK TOTAL_2026'!$AQ:$AQ,C94) -> 13.55702 | P94: =SUM(D94:O94) -> 32.12608 | V94: =D94+E94 -> 7.4154 | W94: =V94+F94 -> 7.51242 | X94: =W94+G94 -> 18.56906 | Y94: =X94+H94 -> 32.12608 | Z94: =Y94+I94 -> 32.12608 | AA94: =Z94+J94 -> 32.12608 | AB94: =AA94+K94 -> 32.12608 | AC94: =AB94+L94 -> 32.12608 | AD94: =AC94+M94 -> 32.12608 | ... AF94: =AE94+O94 -> 32.12608 | AH94: =V94/V$79*1000 -> 0.036366936 | AI94: =W94/W$79*1000 -> 0.024133885 | AJ94: =X94/X$79*1000 -> 0.044038933 | AK94: =Y94/Y$79*1000 -> 0.065673062 | AL94: =Z94/Z$79*1000 -> 0.065673062 | AM94: =AA94/AA$79*1000 -> 0.065673062 | AN94: =AB94/AB$79*1000 -> 0.065673062 | AO94: =AC94/AC$79*1000 -> 0.065673062 | ... AR94: =AF94/AF$79*1000 -> 0.065673062 | AT94: =AH94/AT$78 -> 0.00035687705 | AU94: =AI94/AU$78 -> 0.00023683133 | AV94: =AJ94/AV$78 -> 0.00043216411 | AW94: =AK94/AW$78 -> 0.00064446477 | AX94: =AL94/AX$78 -> 0.00064446477 | AY94: =AM94/AY$78 -> 0.00064446477 | AZ94: =AN94/AZ$78 -> 0.00064446477 | BA94: =AO94/BA$78 -> 0.00064446477 | ... BD94: =AR94/BD$78 -> 0.00064446477
A95: =SUM(D95:F95) -> 387.10799 | C95: G&A | D95: 177.79164 | E95: 61.11068 | F95: 148.20567 | G95: =G92-G93-G94 -> 89.11946 | H95: =H92-H93-H94 -> 195.6734 | P95: =SUM(D95:O95) -> 671.90085 | V95: =D95+E95 -> 238.90232 | W95: =V95+F95 -> 387.10799 | X95: =W95+G95 -> 476.22745 | Y95: =X95+H95 -> 671.90085 | Z95: =Y95+I95 -> 671.90085 | AA95: =Z95+J95 -> 671.90085 | AB95: =AA95+K95 -> 671.90085 | AC95: =AB95+L95 -> 671.90085 | AD95: =AC95+M95 -> 671.90085 | ... AF95: =AE95+O95 -> 671.90085 | AH95: =V95/V$79*1000 -> 1.1716354 | AI95: =W95/W$79*1000 -> 1.2435966 | AJ95: =X95/X$79*1000 -> 1.1294351 | AK95: =Y95/Y$79*1000 -> 1.3735192 | AL95: =Z95/Z$79*1000 -> 1.3735192 | AM95: =AA95/AA$79*1000 -> 1.3735192 | AN95: =AB95/AB$79*1000 -> 1.3735192 | AO95: =AC95/AC$79*1000 -> 1.3735192 | ... AR95: =AF95/AF$79*1000 -> 1.3735192 | AT95: =AH95/AT$78 -> 0.011497526 | AU95: =AI95/AU$78 -> 0.012203697 | AV95: =AJ95/AV$78 -> 0.011083405 | AW95: =AK95/AW$78 -> 0.013478657 | AX95: =AL95/AX$78 -> 0.013478657 | AY95: =AM95/AY$78 -> 0.013478657 | AZ95: =AN95/AZ$78 -> 0.013478657 | BA95: =AO95/BA$78 -> 0.013478657 | ... BD95: =AR95/BD$78 -> 0.013478657
A96: =SUM(D96:F96) -> 7438.1096 | B96: 合计 | D96: =SUM(D80:D92) -> 2493.7802 | E96: =SUM(E80:E92) -> 2351.7101 | F96: =SUM(F80:F92) -> 2592.6193 | G96: =SUM(G80:G92) -> 2090.0107 | H96: =SUM(H80:H92) -> 2105.3015 | I96: =SUM(I80:I92) -> 0 | J96: =SUM(J80:J92) -> 0 | K96: =SUM(K80:K92) -> 0 | ... P96: =SUM(P80:P92) -> 11633.422 | V96: =SUM(V80:V92) -> 4845.4904 | W96: =SUM(W80:W92) -> 7438.1096 | X96: =SUM(X80:X92) -> 9528.1203 | Y96: =SUM(Y80:Y92) -> 11633.422 | Z96: =SUM(Z80:Z92) -> 11633.422 | AA96: =SUM(AA80:AA92) -> 11633.422 | AB96: =SUM(AB80:AB92) -> 11633.422 | AC96: =SUM(AC80:AC92) -> 11633.422 | ... AF96: =SUM(AF80:AF92) -> 11633.422 | AH96: =V96/V$79*1000 -> 23.76347 | AI96: =W96/W$79*1000 -> 23.895161 | AJ96: =X96/X$79*1000 -> 22.597172 | AK96: =Y96/Y$79*1000 -> 23.781378 | AL96: =Z96/Z$79*1000 -> 23.781378 | AM96: =AA96/AA$79*1000 -> 23.781378 | AN96: =AB96/AB$79*1000 -> 23.781378 | AO96: =AC96/AC$79*1000 -> 23.781378 | ... AR96: =AF96/AF$79*1000 -> 23.781378 | AT96: =AH96/AT$78 -> 0.23319636 | AU96: =AI96/AU$78 -> 0.23448867 | AV96: =AJ96/AV$78 -> 0.22175121 | AW96: =AK96/AW$78 -> 0.23337209 | AX96: =AL96/AX$78 -> 0.23337209 | AY96: =AM96/AY$78 -> 0.23337209 | AZ96: =AN96/AZ$78 -> 0.23337209 | BA96: =AO96/BA$78 -> 0.23337209 | ... BD96: =AR96/BD$78 -> 0.23337209
A97: =A96/A79*1000 -> 23.895161 | B97: 单台 | D97: =D96/D79*1000 -> 25.548148 | E97: =E96/E79*1000 -> 22.12458 | F97: =F96/F79*1000 -> 24.14524 | G97: =G96/G79*1000 -> 18.936402 | H97: =H96/H79*1000 -> 31.175335 | I97: =I96/I79*1000 -> #DIV/0! | J97: =J96/J79*1000 -> #DIV/0! | K97: =K96/K79*1000 -> #DIV/0! | ... P97: =P96/P79*1000 -> 23.781378 | V97: =V96/V79*1000 -> 23.76347 | W97: =W96/W79*1000 -> 23.895161 | X97: =X96/X79*1000 -> 22.597172 | Y97: =Y96/Y79*1000 -> 23.781378 | Z97: =Z96/Z79*1000 -> 23.781378 | AA97: =AA96/AA79*1000 -> 23.781378 | AB97: =AB96/AB79*1000 -> 23.781378 | AC97: =AC96/AC79*1000 -> 23.781378 | ... AF97: =AF96/AF79*1000 -> 23.781378
A98: =SUM(D98:F98) -> 1042.4718 | B98: functional currency | D98: 402.85402 | E98: 250.48111 | F98: 389.13662 | G98: 232.9654 | H98: 153.05454 | Q98: =P98/$P$54*1000 -> 0 | V98: =D98+E98 -> 653.33513 | W98: =V98+F98 -> 1042.4718 | X98: =W98+G98 -> 1275.4371 | Y98: =X98+H98 -> 1428.4917 | Z98: =Y98+I98 -> 1428.4917 | AA98: =Z98+J98 -> 1428.4917 | AB98: =AA98+K98 -> 1428.4917 | AC98: =AB98+L98 -> 1428.4917 | AD98: =AC98+M98 -> 1428.4917 | ... AF98: =AE98+O98 -> 1428.4917 | AH98: =V98/V$79*1000 -> 3.2041153 | AI98: =W98/W$79*1000 -> 3.3489733 | AJ98: =X98/X$79*1000 -> 3.0248645 | AK98: =Y98/Y$79*1000 -> 2.9201641 | AL98: =Z98/Z$79*1000 -> 2.9201641 | AM98: =AA98/AA$79*1000 -> 2.9201641 | AN98: =AB98/AB$79*1000 -> 2.9201641 | AO98: =AC98/AC$79*1000 -> 2.9201641 | ... AR98: =AF98/AF$79*1000 -> 2.9201641 | AT98: =AH98/AT$78 -> 0.031442716 | AU98: =AI98/AU$78 -> 0.03286424 | AV98: =AJ98/AV$78 -> 0.029683687 | AW98: =AK98/AW$78 -> 0.028656237 | AX98: =AL98/AX$78 -> 0.028656237 | AY98: =AM98/AY$78 -> 0.028656237 | AZ98: =AN98/AZ$78 -> 0.028656237 | BA98: =AO98/BA$78 -> 0.028656237 | ... BD98: =AR98/BD$78 -> 0.028656237
A99: =A97/A78 -> 0.19116129
C101: 厨电26年预算 | Q101: =P99/P80 -> 0
A102: 年累 | C102: 科目 | D102: 25年1月 | E102: 25年2月 | F102: 25年3月 | G102: 25年4月 | H102: 25年5月 | I102: 25年6月 | J102: 25年7月 | K102: 25年8月 | L102: 25年9月 | M102: 25年10月 | N102: 25年11月 | O102: 25年12月 | P102: 合计 | Q102: 单台 | R102: 占比 | S102: 费率 | T102: 同比
A103: 125 | B103: 平均单价 | D103: 121 | E103: 121 | F103: 121 | G103: 121 | H103: 121 | I103: 121 | J103: 121 | K103: 121 | L103: 121 | M103: 121 | N103: 121 | O103: 121 | P103: =AVERAGE(D103:O103) -> 121 | Q103: =P103 -> 121 | AT103: =$P$103 -> 121 | AU103: =$P$103 -> 121 | AV103: =$P$103 -> 121 | AW103: =$P$103 -> 121 | AX103: =$P$103 -> 121 | AY103: =$P$103 -> 121 | AZ103: =$P$103 -> 121 | BA103: =$P$103 -> 121 | ... BD103: =$P$103 -> 121
A104: =SUM(D104:F104) -> 339612 | C104: 产量 | D104: 116704 | E104: 116204 | F104: 106704 | G104: 104704 | H104: 71805 | I104: 110105 | J104: 86206 | K104: 81605 | L104: 117305 | M104: 121005 | N104: 130155 | O104: 91305 | P104: =SUM(D104:O104) -> 1253807 | Q104: =P104/12 -> 104483.92 | V104: =D104+E104 -> 232908 | W104: =V104+F104 -> 339612 | X104: =W104+G104 -> 444316 | Y104: =X104+H104 -> 516121 | Z104: =Y104+I104 -> 626226 | AA104: =Z104+J104 -> 712432 | AB104: =AA104+K104 -> 794037 | AC104: =AB104+L104 -> 911342 | AD104: =AC104+M104 -> 1032347 | ... AF104: =AE104+O104 -> 1253807
...

Sheet 洗碗机
D1: =D49/D30 -> 0.14675346 | E1: =E49/E30 -> 0.15818577 | F1: =F49/F30 -> 0.17781446 | G1: =G49/G30 -> 0.147302 | H1: =H49/H30 -> 0.15731025 | I1: =I49/I30 -> 0.26181483 | J1: =J49/J30 -> 0.17144205 | K1: =K49/K30 -> 0.21333082 | ... M1: =M49/M30 -> 0.24648721
C2: 洗碗机24年实际 | V2: 额 | AH2: 单台 | AT2: 费率
B3: 千欧 | C3: 科目 | D3: 24年1月 | E3: 24年2月 | F3: 24年3月 | G3: 24年4月 | H3: 24年5月 | I3: 24年6月 | J3: 24年7月 | K3: 24年8月 | L3: 24年9月 | M3: 24年10月 | N3: 24年11月 | O3: 24年12月 | P3: 合计 | Q3: 单台 | R3: 占比 | S3: 费率 | T3: 同比 | U3: 备注 | V3: 2月年累 | W3: 3月年累 | X3: 4月年累 | Y3: 5月年累 | Z3: 6月年累 | AA3: 7月年累 | AB3: 8月年累 | AC3: 9月年累 | AD3: 10月年累 | AE3: 11月年累 | AF3: 12月年累 | AH3: 2月年累 | AI3: 3月年累 | AJ3: 4月年累 | AK3: 5月年累 | AL3: 6月年累 | AM3: 7月年累 | AN3: 8月年累 | AO3: 9月年累 | AP3: 10月年累 | AQ3: 11月年累 | AR3: 12月年累 | AT3: 2月年累 | AU3: 3月年累 | AV3: 4月年累 | AW3: 5月年累 | AX3: 6月年累 | AY3: 7月年累 | AZ3: 8月年累 | BA3: 9月年累 | BB3: 10月年累 | BC3: 11月年累 | BD3: 12月年累
B4: 平均单价 | D4: 220.46785 | E4: 218.43882 | F4: 223.78236 | G4: 212.8592 | H4: 220.17926 | I4: 211.15415 | J4: 223.01002 | K4: 206.60212 | L4: 204.99904 | M4: 213.45636 | N4: 216.72072 | O4: 209.83325 | P4: 214.58863 | AT4: =$P$4 -> 214.58863 | AU4: =$P$4 -> 214.58863 | AV4: =$P$4 -> 214.58863 | AW4: =$P$4 -> 214.58863 | AX4: =$P$4 -> 214.58863 | AY4: =$P$4 -> 214.58863 | AZ4: =$P$4 -> 214.58863 | BA4: =$P$4 -> 214.58863 | ... BD4: =$P$4 -> 214.58863
B5: 产量 | D5: 16045 | E5: 19752 | F5: 20037 | G5: 28043 | H5: 40794 | I5: 30976 | J5: 34477 | K5: 25578 | L5: 40104 | M5: 41187 | N5: 43110 | O5: 26153 | P5: =SUM(D5:O5) -> 366256 | V5: =D5+E5 -> 35797 | W5: =V5+F5 -> 55834 | X5: =W5+G5 -> 83877 | Y5: =X5+H5 -> 124671 | Z5: =Y5+I5 -> 155647 | AA5: =Z5+J5 -> 190124 | AB5: =AA5+K5 -> 215702 | AC5: =AB5+L5 -> 255806 | AD5: =AC5+M5 -> 296993 | ... AF5: =AE5+O5 -> 366256
B6: 固定制造 | C6: 折旧-含FC | D6: 693.49329 | E6: 717.40728 | F6: 723.68612 | G6: 743.40126 | H6: 743.25898 | I6: 752.0202 | J6: 754.21825 | K6: 753.71548 | L6: 717.30639 | M6: 760.20287 | N6: 767.91905 | O6: 770.30065 | P6: =SUM(D6:O6) -> 8896.9298 | Q6: =P6/$P$5*1000 -> 24.291561 | R6: =P6/$P$22 -> 0.42541809 | S6: =Q6/$P$4 -> 0.1132006 | V6: =D6+E6 -> 1410.9006 | W6: =V6+F6 -> 2134.5867 | X6: =W6+G6 -> 2877.988 | Y6: =X6+H6 -> 3621.2469 | Z6: =Y6+I6 -> 4373.2671 | AA6: =Z6+J6 -> 5127.4854 | AB6: =AA6+K6 -> 5881.2009 | AC6: =AB6+L6 -> 6598.5073 | AD6: =AC6+M6 -> 7358.7101 | ... AF6: =AE6+O6 -> 8896.9298 | AH6: =V6/V$5*1000 -> 39.413933 | AI6: =W6/W$5*1000 -> 38.230947 | AJ6: =X6/X$5*1000 -> 34.312004 | AK6: =Y6/Y$5*1000 -> 29.046426 | AL6: =Z6/Z$5*1000 -> 28.097343 | AM6: =AA6/AA$5*1000 -> 26.969164 | AN6: =AB6/AB$5*1000 -> 27.265398 | AO6: =AC6/AC$5*1000 -> 25.794967 | ... AR6: =AF6/AF$5*1000 -> 24.291561 | AT6: =AH6/AT$4 -> 0.18367205 | AU6: =AI6/AU$4 -> 0.17815924 | AV6: =AJ6/AV$4 -> 0.15989666 | AW6: =AK6/AW$4 -> 0.13535864 | AX6: =AL6/AX$4 -> 0.13093584 | AY6: =AM6/AY$4 -> 0.12567844 | AZ6: =AN6/AZ$4 -> 0.12705891 | BA6: =AO6/BA$4 -> 0.12020659 | ... BD6: =AR6/BD$4 -> 0.1132006
C7: 运营费 | D7: 41.67838 | E7: 55.156548 | F7: 48.297383 | G7: 51.990019 | H7: 47.703552 | I7: 45.908691 | J7: 47.465032 | K7: 47.103003 | L7: 35.360011 | M7: 26.587662 | N7: 23.861179 | O7: -29.551631 | P7: =SUM(D7:O7) -> 441.55983 | Q7: =P7/$P$5*1000 -> 1.2056044 | R7: =P7/$P$22 -> 0.021113749 | S7: =Q7/$P$4 -> 0.0056182118 | V7: =D7+E7 -> 96.834928 | W7: =V7+F7 -> 145.13231 | X7: =W7+G7 -> 197.12233 | Y7: =X7+H7 -> 244.82588 | Z7: =Y7+I7 -> 290.73457 | AA7: =Z7+J7 -> 338.1996 | AB7: =AA7+K7 -> 385.30261 | AC7: =AB7+L7 -> 420.66262 | AD7: =AC7+M7 -> 447.25028 | ... AF7: =AE7+O7 -> 441.55983 | AH7: =V7/V$5*1000 -> 2.7051129 | AI7: =W7/W$5*1000 -> 2.5993536 | AJ7: =X7/X$5*1000 -> 2.3501357 | AK7: =Y7/Y$5*1000 -> 1.9637757 | AL7: =Z7/Z$5*1000 -> 1.8679099 | AM7: =AA7/AA$5*1000 -> 1.778837 | AN7: =AB7/AB$5*1000 -> 1.7862728 | AO7: =AC7/AC$5*1000 -> 1.6444595 | ... AR7: =AF7/AF$5*1000 -> 1.2056044 | AT7: =AH7/AT$4 -> 0.012606041 | AU7: =AI7/AU$4 -> 0.012113194 | AV7: =AJ7/AV$4 -> 0.010951818 | AW7: =AK7/AW$4 -> 0.0091513503 | AX7: =AL7/AX$4 -> 0.0087046081 | AY7: =AM7/AY$4 -> 0.0082895213 | AZ7: =AN7/AZ$4 -> 0.0083241726 | BA7: =AO7/BA$4 -> 0.0076633117 | ... BD7: =AR7/BD$4 -> 0.0056182118
C8: 存货跌价准备 | D8: 2.4124044 | E8: 2.3799218 | F8: 2.2734083 | G8: 2.2819469 | H8: 2.2709562 | I8: 2.2576025 | J8: 24.39519 | K8: 23.46638 | L8: 34.459352 | M8: -3.0046152 | N8: 3.1614968 | O8: -70.456037 | P8: =SUM(D8:O8) -> 25.898008 | Q8: =P8/$P$5*1000 -> 0.070710125 | R8: =P8/$P$22 -> 0.0012383464 | S8: =Q8/$P$4 -> 0.00032951478 | U8: 1-6月按预算计入，7-11月按存货损失逻辑计提，12月调整全年总损失与预算一致 | V8: =D8+E8 -> 4.7923262 | W8: =V8+F8 -> 7.0657345 | X8: =W8+G8 -> 9.3476814 | Y8: =X8+H8 -> 11.618638 | Z8: =Y8+I8 -> 13.87624 | AA8: =Z8+J8 -> 38.27143 | AB8: =AA8+K8 -> 61.737811 | AC8: =AB8+L8 -> 96.197163 | AD8: =AC8+M8 -> 93.192547 | ... AF8: =AE8+O8 -> 25.898008 | AH8: =V8/V$5*1000 -> 0.13387508 | AI8: =W8/W$5*1000 -> 0.12654896 | AJ8: =X8/X$5*1000 -> 0.11144511 | AK8: =Y8/Y$5*1000 -> 0.093194389 | AL8: =Z8/Z$5*1000 -> 0.089151992 | AM8: =AA8/AA$5*1000 -> 0.20129721 | AN8: =AB8/AB$5*1000 -> 0.28621807 | AO8: =AC8/AC$5*1000 -> 0.37605515 | ... AR8: =AF8/AF$5*1000 -> 0.070710125 | AT8: =AH8/AT$4 -> 0.00062386847 | AU8: =AI8/AU$4 -> 0.00058972817 | AV8: =AJ8/AV$4 -> 0.00051934303 | AW8: =AK8/AW$4 -> 0.00043429323 | AX8: =AL8/AX$4 -> 0.00041545534 | AY8: =AM8/AY$4 -> 0.00093806093 | AZ8: =AN8/AZ$4 -> 0.0013337989 | BA8: =AO8/BA$4 -> 0.0017524468 | ... BD8: =AR8/BD$4 -> 0.00032951478
C9: 固定能源费 | D9: 15.853415 | E9: 2.8065187 | F9: 12.792874 | G9: 14.742858 | H9: 0.36925087 | I9: -0.93561413 | J9: -0.51922772 | K9: 2.0197317 | L9: -7.2759362 | M9: 10.990072 | N9: 8.7833785 | O9: 12.172465 | P9: =SUM(D9:O9) -> 71.799786 | Q9: =P9/$P$5*1000 -> 0.19603716 | R9: =P9/$P$22 -> 0.0034331987 | S9: =Q9/$P$4 -> 0.00091354869 | V9: =D9+E9 -> 18.659934 | W9: =V9+F9 -> 31.452808 | X9: =W9+G9 -> 46.195666 | Y9: =X9+H9 -> 46.564917 | Z9: =Y9+I9 -> 45.629303 | AA9: =Z9+J9 -> 45.110075 | AB9: =AA9+K9 -> 47.129807 | AC9: =AB9+L9 -> 39.853871 | AD9: =AC9+M9 -> 50.843943 | ... AF9: =AE9+O9 -> 71.799786 | AH9: =V9/V$5*1000 -> 0.52127089 | AI9: =W9/W$5*1000 -> 0.56332715 | AJ9: =X9/X$5*1000 -> 0.55075487 | AK9: =Y9/Y$5*1000 -> 0.3735024 | AL9: =Z9/Z$5*1000 -> 0.2931589 | AM9: =AA9/AA$5*1000 -> 0.2372666 | AN9: =AB9/AB$5*1000 -> 0.21849499 | AO9: =AC9/AC$5*1000 -> 0.15579725 | ... AR9: =AF9/AF$5*1000 -> 0.19603716 | AT9: =AH9/AT$4 -> 0.0024291636 | AU9: =AI9/AU$4 -> 0.0026251491 | AV9: =AJ9/AV$4 -> 0.0025665613 | AW9: =AK9/AW$4 -> 0.0017405507 | AX9: =AL9/AX$4 -> 0.0013661437 | AY9: =AM9/AY$4 -> 0.0011056812 | AZ9: =AN9/AZ$4 -> 0.001018204 | BA9: =AO9/BA$4 -> 0.00072602751 | ... BD9: =AR9/BD$4 -> 0.00091354869
C10: 间接人工成本-辅助人员 | D10: 141.39287 | E10: 163.26991 | F10: 232.81329 | G10: 209.461 | H10: 207.20338 | I10: 218.46197 | J10: 211.39031 | K10: 184.24578 | L10: 210.32647 | M10: 215.47687 | N10: 196.94675 | O10: 226.76557 | P10: =SUM(D10:O10) -> 2417.7542 | Q10: =P10/$P$5*1000 -> 6.6012684 | R10: =P10/$P$22 -> 0.11560801 | S10: =Q10/$P$4 -> 0.030762434 | V10: =D10+E10 -> 304.66278 | W10: =V10+F10 -> 537.47607 | X10: =W10+G10 -> 746.93707 | Y10: =X10+H10 -> 954.14045 | Z10: =Y10+I10 -> 1172.6024 | AA10: =Z10+J10 -> 1383.9927 | AB10: =AA10+K10 -> 1568.2385 | AC10: =AB10+L10 -> 1778.565 | AD10: =AC10+M10 -> 1994.0418 | ... AF10: =AE10+O10 -> 2417.7542 | AH10: =V10/V$5*1000 -> 8.5108468 | AI10: =W10/W$5*1000 -> 9.6263222 | AJ10: =X10/X$5*1000 -> 8.9051476 | AK10: =Y10/Y$5*1000 -> 7.653267 | AL10: =Z10/Z$5*1000 -> 7.5337297 | AM10: =AA10/AA$5*1000 -> 7.2794215 | AN10: =AB10/AB$5*1000 -> 7.2703939 | AO10: =AC10/AC$5*1000 -> 6.9527883 | ... AR10: =AF10/AF$5*1000 -> 6.6012684 | AT10: =AH10/AT$4 -> 0.03966122 | AU10: =AI10/AU$4 -> 0.044859424 | AV10: =AJ10/AV$4 -> 0.041498693 | AW10: =AK10/AW$4 -> 0.03566483 | AX10: =AL10/AX$4 -> 0.035107777 | AY10: =AM10/AY$4 -> 0.033922681 | AZ10: =AN10/AZ$4 -> 0.033880611 | BA10: =AO10/BA$4 -> 0.032400544 | ... BD10: =AR10/BD$4 -> 0.030762434
C11: 固定人工-白领 | D11: 107.27064 | E11: 78.509038 | F11: 102.15277 | G11: 76.224913 | H11: 76.06979 | I11: 87.458805 | J11: 97.956077 | K11: 105.76732 | L11: 91.584549 | M11: 101.63037 | N11: 93.126014 | O11: 73.281876 | P11: =SUM(D11:O11) -> 1091.0322 | Q11: =P11/$P$5*1000 -> 2.9788786 | R11: =P11/$P$22 -> 0.0521691 | S11: =Q11/$P$4 -> 0.01388181 | V11: =D11+E11 -> 185.77968 | W11: =V11+F11 -> 287.93246 | X11: =W11+G11 -> 364.15737 | Y11: =X11+H11 -> 440.22716 | Z11: =Y11+I11 -> 527.68597 | AA11: =Z11+J11 -> 625.64204 | AB11: =AA11+K11 -> 731.40936 | AC11: =AB11+L11 -> 822.99391 | AD11: =AC11+M11 -> 924.62428 | ... AF11: =AE11+O11 -> 1091.0322 | AH11: =V11/V$5*1000 -> 5.1898115 | AI11: =W11/W$5*1000 -> 5.1569377 | AJ11: =X11/X$5*1000 -> 4.3415641 | AK11: =Y11/Y$5*1000 -> 3.5311112 | AL11: =Z11/Z$5*1000 -> 3.3902739 | AM11: =AA11/AA$5*1000 -> 3.2907052 | AN11: =AB11/AB$5*1000 -> 3.3908325 | AO11: =AC11/AC$5*1000 -> 3.217258 | ... AR11: =AF11/AF$5*1000 -> 2.9788786 | AT11: =AH11/AT$4 -> 0.024184933 | AU11: =AI11/AU$4 -> 0.024031738 | AV11: =AJ11/AV$4 -> 0.020232032 | AW11: =AK11/AW$4 -> 0.016455258 | AX11: =AL11/AX$4 -> 0.015798945 | AY11: =AM11/AY$4 -> 0.015334947 | AZ11: =AN11/AZ$4 -> 0.015801548 | BA11: =AO11/BA$4 -> 0.014992677 | ... BD11: =AR11/BD$4 -> 0.01388181
C12: 半固定-班车/工作服 | D12: 112.39814 | E12: 128.4196 | F12: 125.55049 | G12: 145.57068 | H12: 147.18517 | I12: 175.52971 | J12: 151.57974 | K12: 63.211478 | L12: 89.006078 | M12: 169.34532 | N12: 133.35232 | O12: 81.284037 | P12: =SUM(D12:O12) -> 1522.4328 | Q12: =P12/$P$5*1000 -> 4.1567449 | R12: =P12/$P$22 -> 0.072797072 | S12: =Q12/$P$4 -> 0.01937076 | V12: =D12+E12 -> 240.81774 | W12: =V12+F12 -> 366.36823 | X12: =W12+G12 -> 511.93891 | Y12: =X12+H12 -> 659.12407 | Z12: =Y12+I12 -> 834.65378 | AA12: =Z12+J12 -> 986.23352 | AB12: =AA12+K12 -> 1049.445 | AC12: =AB12+L12 -> 1138.4511 | AD12: =AC12+M12 -> 1307.7964 | ... AF12: =AE12+O12 -> 1522.4328 | AH12: =V12/V$5*1000 -> 6.7273162 | AI12: =W12/W$5*1000 -> 6.5617406 | AJ12: =X12/X$5*1000 -> 6.103448 | AK12: =Y12/Y$5*1000 -> 5.2869077 | AL12: =Z12/Z$5*1000 -> 5.3624791 | AM12: =AA12/AA$5*1000 -> 5.1873173 | AN12: =AB12/AB$5*1000 -> 4.8652539 | AO12: =AC12/AC$5*1000 -> 4.4504471 | ... AR12: =AF12/AF$5*1000 -> 4.1567449 | AT12: =AH12/AT$4 -> 0.031349826 | AU12: =AI12/AU$4 -> 0.030578231 | AV12: =AJ12/AV$4 -> 0.028442551 | AW12: =AK12/AW$4 -> 0.024637409 | AX12: =AL12/AX$4 -> 0.024989577 | AY12: =AM12/AY$4 -> 0.02417331 | AZ12: =AN12/AZ$4 -> 0.022672469 | BA12: =AO12/BA$4 -> 0.020739436 | ... BD12: =AR12/BD$4 -> 0.01937076
B13: 变动制造 | C13: 直接人工 | D13: 176.22299 | E13: 187.42795 | F13: 161.89889 | G13: 381.84488 | H13: 379.4914 | I13: 380.58091 | J13: 335.67645 | K13: 348.85222 | L13: 419.63842 | M13: 436.15203 | N13: 417.8893 | O13: 362.92421 | P13: =SUM(D13:O13) -> 3988.5996 | Q13: =P13/$P$5*1000 -> 10.890196 | R13: =P13/$P$22 -> 0.19072 | S13: =Q13/$P$4 -> 0.050749176 | V13: =D13+E13 -> 363.65094 | W13: =V13+F13 -> 525.54983 | X13: =W13+G13 -> 907.39471 | Y13: =X13+H13 -> 1286.8861 | Z13: =Y13+I13 -> 1667.467 | AA13: =Z13+J13 -> 2003.1435 | AB13: =AA13+K13 -> 2351.9957 | AC13: =AB13+L13 -> 2771.6341 | AD13: =AC13+M13 -> 3207.7861 | ... AF13: =AE13+O13 -> 3988.5996 | AH13: =V13/V$5*1000 -> 10.158699 | AI13: =W13/W$5*1000 -> 9.4127203 | AJ13: =X13/X$5*1000 -> 10.818159 | AK13: =Y13/Y$5*1000 -> 10.322257 | AL13: =Z13/Z$5*1000 -> 10.713133 | AM13: =AA13/AA$5*1000 -> 10.535984 | AN13: =AB13/AB$5*1000 -> 10.903912 | AO13: =AC13/AC$5*1000 -> 10.834907 | ... AR13: =AF13/AF$5*1000 -> 10.890196 | AT13: =AH13/AT$4 -> 0.047340341 | AU13: =AI13/AU$4 -> 0.043864022 | AV13: =AJ13/AV$4 -> 0.050413477 | AW13: =AK13/AW$4 -> 0.048102535 | AX13: =AL13/AX$4 -> 0.049924048 | AY13: =AM13/AY$4 -> 0.049098521 | AZ13: =AN13/AZ$4 -> 0.050813095 | BA13: =AO13/BA$4 -> 0.050491523 | ... BD13: =AR13/BD$4 -> 0.050749176
C14: 废料 | D14: 6.1777953 | E14: 8.8702622 | F14: 8.8287262 | G14: 12.119958 | H14: 17.11322 | I14: 27.64894 | J14: 20.138327 | K14: 15.269898 | L14: 17.966306 | M14: 19.826863 | N14: 22.782967 | O14: 29.788027 | P14: =SUM(D14:O14) -> 206.53129 | Q14: =P14/$P$5*1000 -> 0.56389872 | R14: =P14/$P$22 -> 0.0098755581 | S14: =Q14/$P$4 -> 0.0026278127 | V14: =D14+E14 -> 15.048058 | W14: =V14+F14 -> 23.876784 | X14: =W14+G14 -> 35.996742 | Y14: =X14+H14 -> 53.109962 | Z14: =Y14+I14 -> 80.758902 | AA14: =Z14+J14 -> 100.89723 | AB14: =AA14+K14 -> 116.16713 | AC14: =AB14+L14 -> 134.13343 | AD14: =AC14+M14 -> 153.9603 | ... AF14: =AE14+O14 -> 206.53129 | AH14: =V14/V$5*1000 -> 0.42037203 | AI14: =W14/W$5*1000 -> 0.42763878 | AJ14: =X14/X$5*1000 -> 0.42916106 | AK14: =Y14/Y$5*1000 -> 0.42600093 | AL14: =Z14/Z$5*1000 -> 0.51885935 | AM14: =AA14/AA$5*1000 -> 0.5306917 | AN14: =AB14/AB$5*1000 -> 0.53855378 | AO14: =AC14/AC$5*1000 -> 0.52435609 | ... AR14: =AF14/AF$5*1000 -> 0.56389872 | AT14: =AH14/AT$4 -> 0.0019589669 | AU14: =AI14/AU$4 -> 0.0019928306 | AV14: =AJ14/AV$4 -> 0.0019999245 | AW14: =AK14/AW$4 -> 0.0019851981 | AX14: =AL14/AX$4 -> 0.0024179257 | AY14: =AM14/AY$4 -> 0.0024730654 | AZ14: =AN14/AZ$4 -> 0.0025097033 | BA14: =AO14/BA$4 -> 0.0024435409 | ... BD14: =AR14/BD$4 -> 0.0026278127
C15: 生产耗用品 | D15: 3.0204918 | E15: -0.018735044 | F15: 11.666519 | G15: 13.901597 | H15: 27.863799 | I15: 20.169839 | J15: 19.409081 | K15: -43.343411 | L15: -43.638753 | M15: 37.217597 | N15: 33.598589 | O15: 13.896027 | P15: =SUM(D15:O15) -> 93.742641 | Q15: =P15/$P$5*1000 -> 0.25594841 | R15: =P15/$P$22 -> 0.0044824244 | S15: =Q15/$P$4 -> 0.0011927399 | V15: =D15+E15 -> 3.0017568 | W15: =V15+F15 -> 14.668276 | X15: =W15+G15 -> 28.569873 | Y15: =X15+H15 -> 56.433672 | Z15: =Y15+I15 -> 76.603511 | AA15: =Z15+J15 -> 96.012592 | AB15: =AA15+K15 -> 52.669181 | AC15: =AB15+L15 -> 9.0304278 | AD15: =AC15+M15 -> 46.248025 | ... AF15: =AE15+O15 -> 93.742641 | AH15: =V15/V$5*1000 -> 0.083854982 | AI15: =W15/W$5*1000 -> 0.26271225 | AJ15: =X15/X$5*1000 -> 0.3406163 | AK15: =Y15/Y$5*1000 -> 0.45266078 | AL15: =Z15/Z$5*1000 -> 0.49216182 | AM15: =AA15/AA$5*1000 -> 0.50499985 | AN15: =AB15/AB$5*1000 -> 0.24417567 | AO15: =AC15/AC$5*1000 -> 0.035301861 | ... AR15: =AF15/AF$5*1000 -> 0.25594841 | AT15: =AH15/AT$4 -> 0.00039077086 | AU15: =AI15/AU$4 -> 0.0012242599 | AV15: =AJ15/AV$4 -> 0.0015872989 | AW15: =AK15/AW$4 -> 0.0021094351 | AX15: =AL15/AX$4 -> 0.0022935131 | AY15: =AM15/AY$4 -> 0.0023533393 | AZ15: =AN15/AZ$4 -> 0.001137878 | BA15: =AO15/BA$4 -> 0.00016450947 | ... BD15: =AR15/BD$4 -> 0.0011927399
C16: 废品收入 | D16: -14.284369 | E16: -25.630223 | F16: -32.167999 | G16: -35.083966 | H16: -47.524161 | I16: -37.520012 | J16: -44.53975 | K16: -30.517195 | L16: -52.371622 | M16: -55.766642 | N16: -47.080292 | O16: -34.88782 | P16: =SUM(D16:O16) -> -457.37405 | Q16: =P16/$P$5*1000 -> -1.2487824 | R16: =P16/$P$22 -> -0.021869926 | S16: =Q16/$P$4 -> -0.0058194249 | V16: =D16+E16 -> -39.914592 | W16: =V16+F16 -> -72.082591 | X16: =W16+G16 -> -107.16656 | Y16: =X16+H16 -> -154.69072 | Z16: =Y16+I16 -> -192.21073 | AA16: =Z16+J16 -> -236.75048 | AB16: =AA16+K16 -> -267.26767 | AC16: =AB16+L16 -> -319.6393 | AD16: =AC16+M16 -> -375.40594 | ... AF16: =AE16+O16 -> -457.37405 | AH16: =V16/V$5*1000 -> -1.1150262 | AI16: =W16/W$5*1000 -> -1.2910161 | AJ16: =X16/X$5*1000 -> -1.2776632 | AK16: =Y16/Y$5*1000 -> -1.2407915 | AL16: =Z16/Z$5*1000 -> -1.2349145 | AM16: =AA16/AA$5*1000 -> -1.2452425 | AN16: =AB16/AB$5*1000 -> -1.2390598 | AO16: =AC16/AC$5*1000 -> -1.2495379 | ... AR16: =AF16/AF$5*1000 -> -1.2487824 | AT16: =AH16/AT$4 -> -0.0051961103 | AU16: =AI16/AU$4 -> -0.0060162371 | AV16: =AJ16/AV$4 -> -0.0059540118 | AW16: =AK16/AW$4 -> -0.0057821867 | AX16: =AL16/AX$4 -> -0.0057547991 | AY16: =AM16/AY$4 -> -0.0058029285 | AZ16: =AN16/AZ$4 -> -0.0057741167 | BA16: =AO16/BA$4 -> -0.0058229457 | ... BD16: =AR16/BD$4 -> -0.0058194249
C17: 变动能源费 | D17: 15.260939 | E17: 16.728958 | F17: 28.902283 | G17: 42.214349 | H17: 25.406423 | I17: 23.364298 | J17: 36.044641 | K17: 20.945078 | L17: 22.465393 | M17: 28.385818 | N17: 21.868629 | O17: 17.809246 | P17: =SUM(D17:O17) -> 299.39606 | Q17: =P17/$P$5*1000 -> 0.81745024 | R17: =P17/$P$22 -> 0.014316006 | S17: =Q17/$P$4 -> 0.0038093829 | V17: =D17+E17 -> 31.989897 | W17: =V17+F17 -> 60.89218 | X17: =W17+G17 -> 103.10653 | Y17: =X17+H17 -> 128.51295 | Z17: =Y17+I17 -> 151.87725 | AA17: =Z17+J17 -> 187.92189 | AB17: =AA17+K17 -> 208.86697 | AC17: =AB17+L17 -> 231.33236 | AD17: =AC17+M17 -> 259.71818 | ... AF17: =AE17+O17 -> 299.39606 | AH17: =V17/V$5*1000 -> 0.89364742 | AI17: =W17/W$5*1000 -> 1.0905932 | AJ17: =X17/X$5*1000 -> 1.2292587 | AK17: =Y17/Y$5*1000 -> 1.0308167 | AL17: =Z17/Z$5*1000 -> 0.97578013 | AM17: =AA17/AA$5*1000 -> 0.98841752 | AN17: =AB17/AB$5*1000 -> 0.96831263 | AO17: =AC17/AC$5*1000 -> 0.90432735 | ... AR17: =AF17/AF$5*1000 -> 0.81745024 | AT17: =AH17/AT$4 -> 0.0041644678 | AU17: =AI17/AU$4 -> 0.0050822506 | AV17: =AJ17/AV$4 -> 0.0057284428 | AW17: =AK17/AW$4 -> 0.0048036876 | AX17: =AL17/AX$4 -> 0.0045472127 | AY17: =AM17/AY$4 -> 0.0046061039 | AZ17: =AN17/AZ$4 -> 0.0045124135 | BA17: =AO17/BA$4 -> 0.0042142371 | ... BD17: =AR17/BD$4 -> 0.0038093829
B18: 分摊 | C18: 分摊费用 | D18: 206.8425 | E18: 185.00261 | F18: 204.21713 | G18: 185.55594 | H18: 183.79462 | I18: 199.65015 | J18: 209.789 | K18: 202.34647 | L18: 186.28938 | M18: 202.46683 | N18: 220.02421 | O18: 129.09811 | P18: =SUM(D18:O18) -> 2315.077 | Q18: =P18/$P$5*1000 -> 6.3209257 | R18: =P18/$P$22 -> 0.11069837 | S18: =Q18/$P$4 -> 0.029456014 | V18: =D18+E18 -> 391.84512 | W18: =V18+F18 -> 596.06224 | X18: =W18+G18 -> 781.61819 | Y18: =X18+H18 -> 965.41281 | Z18: =Y18+I18 -> 1165.063 | AA18: =Z18+J18 -> 1374.852 | AB18: =AA18+K18 -> 1577.1984 | AC18: =AB18+L18 -> 1763.4878 | AD18: =AC18+M18 -> 1965.9546 | ... AF18: =AE18+O18 -> 2315.077 | AH18: =V18/V$5*1000 -> 10.946312 | AI18: =W18/W$5*1000 -> 10.675614 | AJ18: =X18/X$5*1000 -> 9.3186235 | AK18: =Y18/Y$5*1000 -> 7.7436838 | AL18: =Z18/Z$5*1000 -> 7.4852902 | AM18: =AA18/AA$5*1000 -> 7.2313436 | AN18: =AB18/AB$5*1000 -> 7.3119324 | AO18: =AC18/AC$5*1000 -> 6.8938485 | ... AR18: =AF18/AF$5*1000 -> 6.3209257 | AT18: =AH18/AT$4 -> 0.051010679 | AU18: =AI18/AU$4 -> 0.049749208 | AV18: =AJ18/AV$4 -> 0.043425524 | AW18: =AK18/AW$4 -> 0.03608618 | AX18: =AL18/AX$4 -> 0.034882045 | AY18: =AM18/AY$4 -> 0.033698634 | AZ18: =AN18/AZ$4 -> 0.034074184 | BA18: =AO18/BA$4 -> 0.03212588 | ... BD18: =AR18/BD$4 -> 0.029456014
C19: IT Expense-Internal Charge Out | D19: 132.42745 | E19: 135.81498 | F19: 131.60823 | G19: 131.51949 | H19: 149.6127 | I19: 131.91783 | J19: 150.50369 | K19: 133.68219 | L19: 132.36217 | M19: 143.13869 | N19: 131.41142 | O19: 131.98809 | P19: =SUM(D19:O19) -> 1635.9869 | V19: =D19+E19 -> 268.24242 | W19: =V19+F19 -> 399.85065 | X19: =W19+G19 -> 531.37015 | Y19: =X19+H19 -> 680.98285 | Z19: =Y19+I19 -> 812.90068 | AA19: =Z19+J19 -> 963.40437 | AB19: =AA19+K19 -> 1097.0866 | AC19: =AB19+L19 -> 1229.4487 | AD19: =AC19+M19 -> 1372.5874 | ... AF19: =AE19+O19 -> 1635.9869 | AH19: =V19/V$5*1000 -> 7.4934331 | AI19: =W19/W$5*1000 -> 7.1614187 | AJ19: =X19/X$5*1000 -> 6.3351115 | AK19: =Y19/Y$5*1000 -> 5.4622394 | AL19: =Z19/Z$5*1000 -> 5.2227199 | AM19: =AA19/AA$5*1000 -> 5.0672423 | AN19: =AB19/AB$5*1000 -> 5.0861214 | AO19: =AC19/AC$5*1000 -> 4.8061763 | ... AR19: =AF19/AF$5*1000 -> 4.4667853 | AT19: =AH19/AT$4 -> 0.034919992 | AU19: =AI19/AU$4 -> 0.033372778 | AV19: =AJ19/AV$4 -> 0.029522121 | AW19: =AK19/AW$4 -> 0.025454468 | AX19: =AL19/AX$4 -> 0.024338288 | AY19: =AM19/AY$4 -> 0.02361375 | AZ19: =AN19/AZ$4 -> 0.023701729 | BA19: =AO19/BA$4 -> 0.022397162 | ... BD19: =AR19/BD$4 -> 0.020815573
C20: Association dues | D20: 3.3545015 | E20: 7.758599 | F20: 1.8488279 | G20: 4.0580398 | H20: 4.4854916 | I20: 4.6407287 | J20: 4.2313761 | K20: 4.0877663 | L20: 3.5680554 | M20: 4.0062333 | N20: 4.1190319 | O20: 4.5717159 | P20: =SUM(D20:O20) -> 50.730367 | V20: =D20+E20 -> 11.113101 | W20: =V20+F20 -> 12.961928 | X20: =W20+G20 -> 17.019968 | Y20: =X20+H20 -> 21.50546 | Z20: =Y20+I20 -> 26.146188 | AA20: =Z20+J20 -> 30.377565 | AB20: =AA20+K20 -> 34.465331 | AC20: =AB20+L20 -> 38.033386 | AD20: =AC20+M20 -> 42.03962 | ... AF20: =AE20+O20 -> 50.730367 | AH20: =V20/V$5*1000 -> 0.31044782 | AI20: =W20/W$5*1000 -> 0.23215117 | AJ20: =X20/X$5*1000 -> 0.2029158 | AK20: =Y20/Y$5*1000 -> 0.17249769 | AL20: =Z20/Z$5*1000 -> 0.16798389 | AM20: =AA20/AA$5*1000 -> 0.15977764 | AN20: =AB20/AB$5*1000 -> 0.15978216 | AO20: =AC20/AC$5*1000 -> 0.14868059 | ... AR20: =AF20/AF$5*1000 -> 0.13851068 | AT20: =AH20/AT$4 -> 0.0014467114 | AU20: =AI20/AU$4 -> 0.0010818428 | AV20: =AJ20/AV$4 -> 0.00094560368 | AW20: =AK20/AW$4 -> 0.00080385291 | AX20: =AL20/AX$4 -> 0.00078281823 | AY20: =AM20/AY$4 -> 0.00074457647 | AZ20: =AN20/AZ$4 -> 0.00074459751 | BA20: =AO20/BA$4 -> 0.00069286331 | ... BD20: =AR20/BD$4 -> 0.00064547074
C21: G&A | D21: 71.060555 | E21: 41.429036 | F21: 70.760072 | G21: 49.978408 | H21: 29.696431 | I21: 63.091594 | J21: 55.053933 | K21: 64.576512 | L21: 50.359161 | M21: 55.32191 | N21: 84.493757 | O21: -7.4616996 | P21: =SUM(D21:O21) -> 628.35967 | V21: =D21+E21 -> 112.48959 | W21: =V21+F21 -> 183.24966 | X21: =W21+G21 -> 233.22807 | Y21: =X21+H21 -> 262.9245 | Z21: =Y21+I21 -> 326.0161 | AA21: =Z21+J21 -> 381.07003 | AB21: =AA21+K21 -> 445.64654 | AC21: =AB21+L21 -> 496.0057 | AD21: =AC21+M21 -> 551.32761 | ... AF21: =AE21+O21 -> 628.35967 | AH21: =V21/V$5*1000 -> 3.1424307 | AI21: =W21/W$5*1000 -> 3.2820443 | AJ21: =X21/X$5*1000 -> 2.7805962 | AK21: =Y21/Y$5*1000 -> 2.1089468 | AL21: =Z21/Z$5*1000 -> 2.0945864 | AM21: =AA21/AA$5*1000 -> 2.0043236 | AN21: =AB21/AB$5*1000 -> 2.0660288 | AO21: =AC21/AC$5*1000 -> 1.9389917 | ... AR21: =AF21/AF$5*1000 -> 1.7156297 | AT21: =AH21/AT$4 -> 0.014643976 | AU21: =AI21/AU$4 -> 0.015294586 | AV21: =AJ21/AV$4 -> 0.012957799 | AW21: =AK21/AW$4 -> 0.0098278589 | AX21: =AL21/AX$4 -> 0.0097609387 | AY21: =AM21/AY$4 -> 0.0093403069 | AZ21: =AN21/AZ$4 -> 0.0096278577 | BA21: =AO21/BA$4 -> 0.0090358547 | ... BD21: =AR21/BD$4 -> 0.0079949702
B22: 合计 | D22: =SUM(D6:D18) -> 1507.7395 | E22: =SUM(E6:E18) -> 1520.3296 | F22: =SUM(F6:F18) -> 1630.9119 | G22: =SUM(G6:G18) -> 1844.2254 | H22: =SUM(H6:H18) -> 1810.2064 | I22: =SUM(I6:I18) -> 1894.5955 | J22: =SUM(J6:J18) -> 1863.0031 | K22: =SUM(K6:K18) -> 1693.0822 | ... P22: =SUM(P6:P18) -> 20913.379 | V22: =SUM(V6:V18) -> 3028.0691 | W22: =SUM(W6:W18) -> 4658.981 | X22: =SUM(X6:X18) -> 6503.2065 | Y22: =SUM(Y6:Y18) -> 8313.4128 | Z22: =SUM(Z6:Z18) -> 10208.008 | AA22: =SUM(AA6:AA18) -> 12071.011 | AB22: =SUM(AB6:AB18) -> 13764.094 | AC22: =SUM(AC6:AC18) -> 15485.21 | ... AF22: =SUM(AF6:AF18) -> 20913.379 | AH22: =V22/V$5*1000 -> 84.590025 | AI22: =W22/W$5*1000 -> 83.44344 | AJ22: =X22/X$5*1000 -> 77.532654 | AK22: =Y22/Y$5*1000 -> 66.682812 | AL22: =Z22/Z$5*1000 -> 65.584356 | AM22: =AA22/AA$5*1000 -> 63.490204 | AN22: =AB22/AB$5*1000 -> 63.810691 | AO22: =AC22/AC$5*1000 -> 60.534975 | ... AR22: =AF22/AF$5*1000 -> 57.100441 | AT22: =AH22/AT$4 -> 0.39419622 | AU22: =AI22/AU$4 -> 0.38885304 | AV22: =AJ22/AV$4 -> 0.36130831 | AW22: =AK22/AW$4 -> 0.31074718 | AX22: =AL22/AX$4 -> 0.3056283 | AY22: =AM22/AY$4 -> 0.29586938 | AZ22: =AN22/AZ$4 -> 0.29736287 | BA22: =AO22/BA$4 -> 0.28209778 | ... BD22: =AR22/BD$4 -> 0.26609258
B23: 单台 | D23: =D22/D5*1000 -> 93.96943 | E23: =E22/E5*1000 -> 76.970921 | F23: =F22/F5*1000 -> 81.395013 | G23: =G22/G5*1000 -> 65.764199 | H23: =H22/H5*1000 -> 44.374329 | I23: =I22/I5*1000 -> 61.163336 | J23: =J22/J5*1000 -> 54.036114 | K23: =K22/K5*1000 -> 66.192909 | ... P23: =P22/P5*1000 -> 57.100441 | Q23: =P23 -> 57.100441 | S23: =Q23/$P$4 -> 0.26609258 | V23: =V22/V5*1000 -> 84.590025 | W23: =W22/W5*1000 -> 83.44344 | X23: =X22/X5*1000 -> 77.532654 | Y23: =Y22/Y5*1000 -> 66.682812 | Z23: =Z22/Z5*1000 -> 65.584356 | AA23: =AA22/AA5*1000 -> 63.490204 | AB23: =AB22/AB5*1000 -> 63.810691 | AC23: =AC22/AC5*1000 -> 60.534975 | ... AF23: =AF22/AF5*1000 -> 57.100441
B26: functional currency | D26: 565.60931 | E26: 565.60931 | F26: 565.60931 | G26: 565.60931 | H26: 565.60931 | I26: 565.60931 | J26: 565.60931 | K26: 565.60931 | L26: 565.60931 | M26: 565.60931 | N26: 565.60931 | O26: 482.93024 | P26: =SUM(D26:O26) -> 6704.6326 | Q26: =P26/$P$5*1000 -> 18.305864
Q27: =Q23-Q26 -> 38.794577 | S27: =Q27/P4 -> 0.1807858
C28: 洗碗机25年实际
A29: 年累 | C29: 科目 | D29: 25年1月 | E29: 25年2月 | F29: 25年3月 | G29: 25年4月 | H29: 25年5月 | I29: 25年6月 | J29: 25年7月 | K29: 25年8月 | L29: 25年9月 | M29: 25年10月 | N29: 25年11月 | O29: 25年12月 | P29: 合计 | Q29: 单台 | R29: 占比 | S29: 费率 | T29: 同比
A30: 222 | B30: 平均单价 | D30: 238.80897 | E30: 224.15352 | F30: 221.84897 | G30: 218.88846 | H30: 220.99255 | I30: 223.76947 | J30: 228.17739 | K30: 224.80468 | L30: 205.80772 | M30: 223.36513 | N30: 220 | O30: 212 | Q30: =AVERAGE(D30:O30) -> 221.88474 | S30: =AVERAGE(D30:O30) -> 221.88474 | AT30: =$S$30 -> 221.88474 | AU30: =$S$30 -> 221.88474 | AV30: =$S$30 -> 221.88474 | AW30: =$S$30 -> 221.88474 | AX30: =$S$30 -> 221.88474 | AY30: =$S$30 -> 221.88474 | AZ30: =$S$30 -> 221.88474 | BA30: =$S$30 -> 221.88474 | ... BD30: =$S$30 -> 221.88474
A31: =SUM(D31:F31) -> 140941 | C31: 产量 | D31: 48571 | E31: 46033 | F31: 46337 | G31: 49363 | H31: 53704 | I31: 29664 | J31: 41857 | K31: 31977 | L31: 28268 | M31: 26211 | N31: 34024 | O31: 42093 | P31: =SUM(D31:O31) -> 478102 | V31: =D31+E31 -> 94604 | W31: =V31+F31 -> 140941 | X31: =W31+G31 -> 190304 | Y31: =X31+H31 -> 244008 | Z31: =Y31+I31 -> 273672 | AA31: =Z31+J31 -> 315529 | AB31: =AA31+K31 -> 347506 | AC31: =AB31+L31 -> 375774 | AD31: =AC31+M31 -> 401985 | ... AF31: =AE31+O31 -> 478102
A32: =SUM(D32:F32) -> 1620.6203 | B32: 固定制造 | C32: 折旧 | D32: 546.80648 | E32: 512.30486 | F32: 561.50898 | G32: 550.63785 | H32: 579.549 | I32: 564.00175 | J32: 578.95374 | K32: =179.357147750699+398 -> 577.35715 | L32: =173.65131+391 -> 564.65131 | M32: 370.28689 | N32: 546.43939 | O32: 562 | P32: =SUM(D32:O32) -> 6514.4974 | Q32: =P32/$P$31*1000 -> 13.625748 | R32: =P32/$P$48 -> 0.32849159 | S32: =Q32/$S$30 -> 0.061409127 | U32: 含FC | V32: =D32+E32 -> 1059.1113 | W32: =V32+F32 -> 1620.6203 | X32: =W32+G32 -> 2171.2582 | Y32: =X32+H32 -> 2750.8072 | Z32: =Y32+I32 -> 3314.8089 | AA32: =Z32+J32 -> 3893.7627 | AB32: =AA32+K32 -> 4471.1198 | AC32: =AB32+L32 -> 5035.7711 | AD32: =AC32+M32 -> 5406.058 | ... AF32: =AE32+O32 -> 6514.4974 | AH32: =V32/V$31*1000 -> 11.195207 | AI32: =W32/W$31*1000 -> 11.498573 | AJ32: =X32/X$31*1000 -> 11.409419 | AK32: =Y32/Y$31*1000 -> 11.27343 | AL32: =Z32/Z$31*1000 -> 12.112342 | AM32: =AA32/AA$31*1000 -> 12.340427 | AN32: =AB32/AB$31*1000 -> 12.86631 | AO32: =AC32/AC$31*1000 -> 13.401063 | ... AR32: =AF32/AF$31*1000 -> 13.625748 | AT32: =AH32/AT$30 -> 0.050455055 | AU32: =AI32/AU$30 -> 0.051822278 | AV32: =AJ32/AV$30 -> 0.051420479 | AW32: =AK32/AW$30 -> 0.050807596 | AX32: =AL32/AX$30 -> 0.054588442 | AY32: =AM32/AY$30 -> 0.055616386 | AZ32: =AN32/AZ$30 -> 0.057986456 | BA32: =AO32/BA$30 -> 0.060396507 | ... BD32: =AR32/BD$30 -> 0.061409127
A33: =SUM(D33:F33) -> 147.2468 | C33: 运营费 | D33: 47.53431 | E33: 55.92441 | F33: 43.78808 | G33: 40.60267 | H33: 37.96418 | I33: 36.03309 | J33: 41.46116 | K33: 53.8334 | L33: 45.24103 | M33: 35.50089 | N33: 45.64884 | O33: -14.33268 | P33: =SUM(D33:O33) -> 469.19938 | Q33: =P33/$P$31*1000 -> 0.98137925 | R33: =P33/$P$48 -> 0.023659239 | S33: =Q33/$S$30 -> 0.0044229236 | V33: =D33+E33 -> 103.45872 | W33: =V33+F33 -> 147.2468 | X33: =W33+G33 -> 187.84947 | Y33: =X33+H33 -> 225.81365 | Z33: =Y33+I33 -> 261.84674 | AA33: =Z33+J33 -> 303.3079 | AB33: =AA33+K33 -> 357.1413 | AC33: =AB33+L33 -> 402.38233 | AD33: =AC33+M33 -> 437.88322 | ... AF33: =AE33+O33 -> 469.19938 | AH33: =V33/V$31*1000 -> 1.0935977 | AI33: =W33/W$31*1000 -> 1.0447407 | AJ33: =X33/X$31*1000 -> 0.98710206 | AK33: =Y33/Y$31*1000 -> 0.92543544 | AL33: =Z33/Z$31*1000 -> 0.95679039 | AM33: =AA33/AA$31*1000 -> 0.9612679 | AN33: =AB33/AB$31*1000 -> 1.027727 | AO33: =AC33/AC$31*1000 -> 1.0708094 | ... AR33: =AF33/AF$31*1000 -> 0.98137925 | AT33: =AH33/AT$30 -> 0.0049286749 | AU33: =AI33/AU$30 -> 0.0047084838 | AV33: =AJ33/AV$30 -> 0.0044487154 | AW33: =AK33/AW$30 -> 0.0041707935 | AX33: =AL33/AX$30 -> 0.0043121054 | AY33: =AM33/AY$30 -> 0.0043322849 | AZ33: =AN33/AZ$30 -> 0.0046318057 | BA33: =AO33/BA$30 -> 0.0048259714 | ... BD33: =AR33/BD$30 -> 0.0044229236
A34: =SUM(D34:F34) -> 6.68239 | C34: 存货跌价准备 | D34: 2.51573 | E34: 2.08333 | F34: 2.08333 | G34: 2.08333 | H34: 2.08333 | I34: 68.22525 | J34: 0 | K34: 0 | L34: 0 | M34: 35.02325 | N34: 32.76354 | O34: 91.92924 | P34: =SUM(D34:O34) -> 238.79033 | Q34: =P34/$P$31*1000 -> 0.49945478 | R34: =P34/$P$48 -> 0.012040931 | S34: =Q34/$S$30 -> 0.002250965 | U34: 1-5月按预算金额计入，6月按存货损失逻辑计提 | V34: =D34+E34 -> 4.59906 | W34: =V34+F34 -> 6.68239 | X34: =W34+G34 -> 8.76572 | Y34: =X34+H34 -> 10.84905 | Z34: =Y34+I34 -> 79.0743 | AA34: =Z34+J34 -> 79.0743 | AB34: =AA34+K34 -> 79.0743 | AC34: =AB34+L34 -> 79.0743 | AD34: =AC34+M34 -> 114.09755 | ... AF34: =AE34+O34 -> 238.79033 | AH34: =V34/V$31*1000 -> 0.048613801 | AI34: =W34/W$31*1000 -> 0.047412676 | AJ34: =X34/X$31*1000 -> 0.04606167 | AK34: =Y34/Y$31*1000 -> 0.044461862 | AL34: =Z34/Z$31*1000 -> 0.28893822 | AM34: =AA34/AA$31*1000 -> 0.25060866 | AN34: =AB34/AB$31*1000 -> 0.22754801 | AO34: =AC34/AC$31*1000 -> 0.21043047 | ... AR34: =AF34/AF$31*1000 -> 0.49945478 | AT34: =AH34/AT$30 -> 0.00021909484 | AU34: =AI34/AU$30 -> 0.00021368156 | AV34: =AJ34/AV$30 -> 0.00020759278 | AW34: =AK34/AW$30 -> 0.00020038269 | AX34: =AL34/AX$30 -> 0.0013021996 | AY34: =AM34/AY$30 -> 0.0011294542 | AZ34: =AN34/AZ$30 -> 0.0010255235 | BA34: =AO34/BA$30 -> 0.0009483774 | ... BD34: =AR34/BD$30 -> 0.002250965
A35: =SUM(D35:F35) -> 29.45393 | C35: 固定能源费 | D35: 7.05477 | E35: 11.48905 | F35: 10.91011 | G35: 5.5134295 | H35: 6.70539 | I35: -1.22429 | J35: 2.1998 | K35: 6.80514 | L35: 4.97422 | M35: 4.61945 | N35: 7.01973 | O35: 5.81834 | P35: =SUM(D35:O35) -> 71.885139 | Q35: =P35/$P$31*1000 -> 0.15035524 | R35: =P35/$P$48 -> 0.0036247867 | S35: =Q35/$S$30 -> 0.00067762766 | V35: =D35+E35 -> 18.54382 | W35: =V35+F35 -> 29.45393 | X35: =W35+G35 -> 34.967359 | Y35: =X35+H35 -> 41.672749 | Z35: =Y35+I35 -> 40.448459 | AA35: =Z35+J35 -> 42.648259 | AB35: =AA35+K35 -> 49.453399 | AC35: =AB35+L35 -> 54.427619 | AD35: =AC35+M35 -> 59.047069 | ... AF35: =AE35+O35 -> 71.885139 | AH35: =V35/V$31*1000 -> 0.19601518 | AI35: =W35/W$31*1000 -> 0.20898057 | AJ35: =X35/X$31*1000 -> 0.18374474 | AK35: =Y35/Y$31*1000 -> 0.17078436 | AL35: =Z35/Z$31*1000 -> 0.14779904 | AM35: =AA35/AA$31*1000 -> 0.13516431 | AN35: =AB35/AB$31*1000 -> 0.14230948 | AO35: =AC35/AC$31*1000 -> 0.14484137 | ... AR35: =AF35/AF$31*1000 -> 0.15035524 | AT35: =AH35/AT$30 -> 0.00088340992 | AU35: =AI35/AU$30 -> 0.0009418429 | AV35: =AJ35/AV$30 -> 0.00082810897 | AW35: =AK35/AW$30 -> 0.00076969853 | AX35: =AL35/AX$30 -> 0.00066610729 | AY35: =AM35/AY$30 -> 0.00060916452 | AZ35: =AN35/AZ$30 -> 0.0006413667 | BA35: =AO35/BA$30 -> 0.0006527775 | ... BD35: =AR35/BD$30 -> 0.00067762766
A36: =SUM(D36:F36) -> 615.03424 | C36: 间接人工成本-辅助人员 | D36: 208.04047 | E36: 161.36901 | F36: 245.62476 | G36: 210.35834 | H36: 241.29695 | I36: 266.21335 | J36: 155.68707 | K36: 193.16379 | L36: 188.38296 | M36: 209.28685 | N36: 225.24054 | O36: 270.27383 | P36: =SUM(D36:O36) -> 2574.9379 | Q36: =P36/$P$31*1000 -> 5.3857502 | R36: =P36/$P$48 -> 0.12984048 | S36: =Q36/$S$30 -> 0.024272738 | U36: 25年3月/9月各涨18% | V36: =D36+E36 -> 369.40948 | W36: =V36+F36 -> 615.03424 | X36: =W36+G36 -> 825.39258 | Y36: =X36+H36 -> 1066.6895 | Z36: =Y36+I36 -> 1332.9029 | AA36: =Z36+J36 -> 1488.5899 | AB36: =AA36+K36 -> 1681.7537 | AC36: =AB36+L36 -> 1870.1367 | AD36: =AC36+M36 -> 2079.4235 | ... AF36: =AE36+O36 -> 2574.9379 | AH36: =V36/V$31*1000 -> 3.9047977 | AI36: =W36/W$31*1000 -> 4.3637709 | AJ36: =X36/X$31*1000 -> 4.3372319 | AK36: =Y36/Y$31*1000 -> 4.3715351 | AL36: =Z36/Z$31*1000 -> 4.8704394 | AM36: =AA36/AA$31*1000 -> 4.7177595 | AN36: =AB36/AB$31*1000 -> 4.8394955 | AO36: =AC36/AC$31*1000 -> 4.9767592 | ... AR36: =AF36/AF$31*1000 -> 5.3857502 | AT36: =AH36/AT$30 -> 0.017598316 | AU36: =AI36/AU$30 -> 0.019666837 | AV36: =AJ36/AV$30 -> 0.019547229 | AW36: =AK36/AW$30 -> 0.019701829 | AX36: =AL36/AX$30 -> 0.021950313 | AY36: =AM36/AY$30 -> 0.021262208 | AZ36: =AN36/AZ$30 -> 0.021810854 | BA36: =AO36/BA$30 -> 0.022429479 | ... BD36: =AR36/BD$30 -> 0.024272738
A37: =SUM(D37:F37) -> 292.60501 | C37: 固定人工-白领 | D37: 134.31696 | E37: 123.20662 | F37: 35.08143 | G37: 56.46471 | H37: 81.27892 | I37: 104.58229 | J37: 98.92265 | K37: 86.21286 | L37: 83.67801 | M37: 80.27117 | N37: 81.65174 | O37: 81.00358 | P37: =SUM(D37:O37) -> 1046.6709 | Q37: =P37/$P$31*1000 -> 2.189221 | R37: =P37/$P$48 -> 0.05277807 | S37: =Q37/$S$30 -> 0.0098664785 | V37: =D37+E37 -> 257.52358 | W37: =V37+F37 -> 292.60501 | X37: =W37+G37 -> 349.06972 | Y37: =X37+H37 -> 430.34864 | Z37: =Y37+I37 -> 534.93093 | AA37: =Z37+J37 -> 633.85358 | AB37: =AA37+K37 -> 720.06644 | AC37: =AB37+L37 -> 803.74445 | AD37: =AC37+M37 -> 884.01562 | ... AF37: =AE37+O37 -> 1046.6709 | AH37: =V37/V$31*1000 -> 2.7221215 | AI37: =W37/W$31*1000 -> 2.0760816 | AJ37: =X37/X$31*1000 -> 1.8342742 | AK37: =Y37/Y$31*1000 -> 1.7636661 | AL37: =Z37/Z$31*1000 -> 1.9546425 | AM37: =AA37/AA$31*1000 -> 2.00886 | AN37: =AB37/AB$31*1000 -> 2.0720979 | AO37: =AC37/AC$31*1000 -> 2.1389038 | ... AR37: =AF37/AF$31*1000 -> 2.189221 | AT37: =AH37/AT$30 -> 0.012268178 | AU37: =AI37/AU$30 -> 0.0093565766 | AV37: =AJ37/AV$30 -> 0.0082667885 | AW37: =AK37/AW$30 -> 0.0079485688 | AX37: =AL37/AX$30 -> 0.0088092698 | AY37: =AM37/AY$30 -> 0.0090536194 | AZ37: =AN37/AZ$30 -> 0.0093386227 | BA37: =AO37/BA$30 -> 0.0096397068 | ... BD37: =AR37/BD$30 -> 0.0098664785
A38: =SUM(D38:F38) -> 421.28245 | C38: 半固定-班车/工作服 | D38: 106.56045 | E38: 153.96877 | F38: 160.75323 | G38: 126.39878 | H38: 134.84843 | I38: 121.74311 | J38: 124.63709 | K38: 83.61265 | L38: 148.55296 | M38: 105.02582 | N38: 145.71916 | O38: 140.57602 | P38: =SUM(D38:O38) -> 1552.3965 | Q38: =P38/$P$31*1000 -> 3.2469985 | R38: =P38/$P$48 -> 0.078279129 | S38: =Q38/$S$30 -> 0.014633717 | V38: =D38+E38 -> 260.52922 | W38: =V38+F38 -> 421.28245 | X38: =W38+G38 -> 547.68123 | Y38: =X38+H38 -> 682.52966 | Z38: =Y38+I38 -> 804.27277 | AA38: =Z38+J38 -> 928.90986 | AB38: =AA38+K38 -> 1012.5225 | AC38: =AB38+L38 -> 1161.0755 | AD38: =AC38+M38 -> 1266.1013 | ... AF38: =AE38+O38 -> 1552.3965 | AH38: =V38/V$31*1000 -> 2.7538922 | AI38: =W38/W$31*1000 -> 2.9890695 | AJ38: =X38/X$31*1000 -> 2.8779281 | AK38: =Y38/Y$31*1000 -> 2.797161 | AL38: =Z38/Z$31*1000 -> 2.9388201 | AM38: =AA38/AA$31*1000 -> 2.9439762 | AN38: =AB38/AB$31*1000 -> 2.9136835 | AO38: =AC38/AC$31*1000 -> 3.0898239 | ... AR38: =AF38/AF$31*1000 -> 3.2469985 | AT38: =AH38/AT$30 -> 0.012411364 | AU38: =AI38/AU$30 -> 0.013471271 | AV38: =AJ38/AV$30 -> 0.012970374 | AW38: =AK38/AW$30 -> 0.012606369 | AX38: =AL38/AX$30 -> 0.013244805 | AY38: =AM38/AY$30 -> 0.013268043 | AZ38: =AN38/AZ$30 -> 0.013131518 | BA38: =AO38/BA$30 -> 0.013925355 | ... BD38: =AR38/BD$30 -> 0.014633717
A39: =SUM(D39:F39) -> 1332.5627 | B39: 变动制造 | C39: 直接人工 | D39: 471.95897 | E39: 343.39069 | F39: 517.21307 | G39: 469.10102 | H39: 563.01003 | I39: 382.06162 | J39: 445.15222 | K39: 351.77623 | L39: 348.81104 | M39: 383.24932 | N39: 479.35477 | O39: 425.92802 | P39: =SUM(D39:O39) -> 5181.007 | Q39: =P39/$P$31*1000 -> 10.836614 | R39: =P39/$P$48 -> 0.26125073 | S39: =Q39/$S$30 -> 0.048838935 | U39: 25年3月/9月各涨18% | V39: =D39+E39 -> 815.34966 | W39: =V39+F39 -> 1332.5627 | X39: =W39+G39 -> 1801.6638 | Y39: =X39+H39 -> 2364.6738 | Z39: =Y39+I39 -> 2746.7354 | AA39: =Z39+J39 -> 3191.8876 | AB39: =AA39+K39 -> 3543.6638 | AC39: =AB39+L39 -> 3892.4749 | AD39: =AC39+M39 -> 4275.7242 | ... AF39: =AE39+O39 -> 5181.007 | AH39: =V39/V$31*1000 -> 8.6185538 | AI39: =W39/W$31*1000 -> 9.4547557 | AJ39: =X39/X$31*1000 -> 9.4672931 | AK39: =Y39/Y$31*1000 -> 9.6909682 | AL39: =Z39/Z$31*1000 -> 10.036596 | AM39: =AA39/AA$31*1000 -> 10.115988 | AN39: =AB39/AB$31*1000 -> 10.197418 | AO39: =AC39/AC$31*1000 -> 10.358553 | ... AR39: =AF39/AF$31*1000 -> 10.836614 | AT39: =AH39/AT$30 -> 0.038842481 | AU39: =AI39/AU$30 -> 0.042611113 | AV39: =AJ39/AV$30 -> 0.042667617 | AW39: =AK39/AW$30 -> 0.043675686 | AX39: =AL39/AX$30 -> 0.045233378 | AY39: =AM39/AY$30 -> 0.045591185 | AZ39: =AN39/AZ$30 -> 0.045958175 | BA39: =AO39/BA$30 -> 0.046684387 | ... BD39: =AR39/BD$30 -> 0.048838935
A40: =SUM(D40:F40) -> 68.68935 | C40: 废料 | D40: 23.19837 | E40: 22.59299 | F40: 22.89799 | G40: 22.60069 | H40: 28.23716 | I40: 20.36294 | J40: 17.41497 | K40: 17.02318 | L40: 17.83458 | M40: 16.49471 | N40: 17.37308 | O40: 46.35671 | P40: =SUM(D40:O40) -> 272.38737 | Q40: =P40/$P$31*1000 -> 0.56972648 | R40: =P40/$P$48 -> 0.013735052 | S40: =Q40/$S$30 -> 0.0025676686 | V40: =D40+E40 -> 45.79136 | W40: =V40+F40 -> 68.68935 | X40: =W40+G40 -> 91.29004 | Y40: =X40+H40 -> 119.5272 | Z40: =Y40+I40 -> 139.89014 | AA40: =Z40+J40 -> 157.30511 | AB40: =AA40+K40 -> 174.32829 | AC40: =AB40+L40 -> 192.16287 | AD40: =AC40+M40 -> 208.65758 | ... AF40: =AE40+O40 -> 272.38737 | AH40: =V40/V$31*1000 -> 0.48403196 | AI40: =W40/W$31*1000 -> 0.48736244 | AJ40: =X40/X$31*1000 -> 0.47970636 | AK40: =Y40/Y$31*1000 -> 0.48984951 | AL40: =Z40/Z$31*1000 -> 0.51115986 | AM40: =AA40/AA$31*1000 -> 0.49854406 | AN40: =AB40/AB$31*1000 -> 0.50165548 | AO40: =AC40/AC$31*1000 -> 0.51137883 | ... AR40: =AF40/AF$31*1000 -> 0.56972648 | AT40: =AH40/AT$30 -> 0.0021814568 | AU40: =AI40/AU$30 -> 0.0021964667 | AV40: =AJ40/AV$30 -> 0.002161962 | AW40: =AK40/AW$30 -> 0.0022076756 | AX40: =AL40/AX$30 -> 0.0023037179 | AY40: =AM40/AY$30 -> 0.0022468605 | AZ40: =AN40/AZ$30 -> 0.0022608832 | BA40: =AO40/BA$30 -> 0.0023047049 | ... BD40: =AR40/BD$30 -> 0.0025676686
A41: =SUM(D41:F41) -> 80.33706 | C41: 生产耗用品 | D41: 12.21136 | E41: 32.38083 | F41: 35.74487 | G41: -5.81218 | H41: 17.75677 | I41: 21.31818 | J41: 1.40104 | K41: 17.60299 | L41: 15.65114 | M41: 21.32774 | N41: 5.3692 | O41: -39.57972 | P41: =SUM(D41:O41) -> 135.37222 | Q41: =P41/$P$31*1000 -> 0.28314506 | R41: =P41/$P$48 -> 0.0068261038 | S41: =Q41/$S$30 -> 0.0012760907 | V41: =D41+E41 -> 44.59219 | W41: =V41+F41 -> 80.33706 | X41: =W41+G41 -> 74.52488 | Y41: =X41+H41 -> 92.28165 | Z41: =Y41+I41 -> 113.59983 | AA41: =Z41+J41 -> 115.00087 | AB41: =AA41+K41 -> 132.60386 | AC41: =AB41+L41 -> 148.255 | AD41: =AC41+M41 -> 169.58274 | ... AF41: =AE41+O41 -> 135.37222 | AH41: =V41/V$31*1000 -> 0.47135629 | AI41: =W41/W$31*1000 -> 0.5700049 | AJ41: =X41/X$31*1000 -> 0.39160964 | AK41: =Y41/Y$31*1000 -> 0.37819108 | AL41: =Z41/Z$31*1000 -> 0.41509482 | AM41: =AA41/AA$31*1000 -> 0.36447005 | AN41: =AB41/AB$31*1000 -> 0.38158725 | AO41: =AC41/AC$31*1000 -> 0.39453235 | ... AR41: =AF41/AF$31*1000 -> 0.28314506 | AT41: =AH41/AT$30 -> 0.0021243294 | AU41: =AI41/AU$30 -> 0.0025689234 | AV41: =AJ41/AV$30 -> 0.0017649237 | AW41: =AK41/AW$30 -> 0.0017044484 | AX41: =AL41/AX$30 -> 0.0018707678 | AY41: =AM41/AY$30 -> 0.0016426098 | AZ41: =AN41/AZ$30 -> 0.0017197544 | BA41: =AO41/BA$30 -> 0.0017780959 | ... BD41: =AR41/BD$30 -> 0.0012760907
A42: =SUM(D42:F42) -> -169.64689 | C42: 废品收入 | D42: -58.2364 | E42: -53.62907 | F42: -57.78142 | G42: -75.04936 | H42: -62.47757 | I42: -54.55736 | J42: -46.2918 | K42: -52.15434 | L42: -43.47965 | M42: -39.75619 | N42: -37.47416 | O42: -55.6909 | P42: =SUM(D42:O42) -> -636.57822 | Q42: =P42/$P$31*1000 -> -1.3314695 | R42: =P42/$P$48 -> -0.032099267 | S42: =Q42/$S$30 -> -0.0060007258 | V42: =D42+E42 -> -111.86547 | W42: =V42+F42 -> -169.64689 | X42: =W42+G42 -> -244.69625 | Y42: =X42+H42 -> -307.17382 | Z42: =Y42+I42 -> -361.73118 | AA42: =Z42+J42 -> -408.02298 | AB42: =AA42+K42 -> -460.17732 | AC42: =AB42+L42 -> -503.65697 | AD42: =AC42+M42 -> -543.41316 | ... AF42: =AE42+O42 -> -636.57822 | AH42: =V42/V$31*1000 -> -1.1824603 | AI42: =W42/W$31*1000 -> -1.2036731 | AJ42: =X42/X$31*1000 -> -1.2858177 | AK42: =Y42/Y$31*1000 -> -1.2588678 | AL42: =Z42/Z$31*1000 -> -1.3217691 | AM42: =AA42/AA$31*1000 -> -1.2931394 | AN42: =AB42/AB$31*1000 -> -1.3242284 | AO42: =AC42/AC$31*1000 -> -1.3403188 | ... AR42: =AF42/AF$31*1000 -> -1.3314695 | AT42: =AH42/AT$30 -> -0.0053291644 | AU42: =AI42/AU$30 -> -0.0054247674 | AV42: =AJ42/AV$30 -> -0.0057949803 | AW42: =AK42/AW$30 -> -0.0056735214 | AX42: =AL42/AX$30 -> -0.0059570075 | AY42: =AM42/AY$30 -> -0.0058279781 | AZ42: =AN42/AZ$30 -> -0.0059680915 | BA42: =AO42/BA$30 -> -0.0060406085 | ... BD42: =AR42/BD$30 -> -0.0060007258
A43: =SUM(D43:F43) -> 79.47878 | C43: 变动能源费 | D43: 25.36374 | E43: 23.35341 | F43: 30.76163 | G43: 27.43437 | H43: 39.84957 | I43: 25.1104 | J43: 29.59207 | K43: 21.32902 | L43: 20.16034 | M43: 13.90294 | N43: 21.9916 | O43: 21.00062 | P43: =SUM(D43:O43) -> 299.84971 | Q43: =P43/$P$31*1000 -> 0.62716682 | R43: =P43/$P$48 -> 0.015119832 | S43: =Q43/$S$30 -> 0.0028265433 | V43: =D43+E43 -> 48.71715 | W43: =V43+F43 -> 79.47878 | X43: =W43+G43 -> 106.91315 | Y43: =X43+H43 -> 146.76272 | Z43: =Y43+I43 -> 171.87312 | AA43: =Z43+J43 -> 201.46519 | AB43: =AA43+K43 -> 222.79421 | AC43: =AB43+L43 -> 242.95455 | AD43: =AC43+M43 -> 256.85749 | ... AF43: =AE43+O43 -> 299.84971 | AH43: =V43/V$31*1000 -> 0.51495867 | AI43: =W43/W$31*1000 -> 0.56391526 | AJ43: =X43/X$31*1000 -> 0.56180191 | AK43: =Y43/Y$31*1000 -> 0.60146684 | AL43: =Z43/Z$31*1000 -> 0.62802596 | AM43: =AA43/AA$31*1000 -> 0.63849976 | AN43: =AB43/AB$31*1000 -> 0.64112335 | AO43: =AC43/AC$31*1000 -> 0.64654433 | ... AR43: =AF43/AF$31*1000 -> 0.62716682 | AT43: =AH43/AT$30 -> 0.0023208386 | AU43: =AI43/AU$30 -> 0.0025414783 | AV43: =AJ43/AV$30 -> 0.0025319538 | AW43: =AK43/AW$30 -> 0.0027107175 | AX43: =AL43/AX$30 -> 0.0028304153 | AY43: =AM43/AY$30 -> 0.0028776191 | AZ43: =AN43/AZ$30 -> 0.0028894432 | BA43: =AO43/BA$30 -> 0.0029138747 | ... BD43: =AR43/BD$30 -> 0.0028265433 | BF43: =(N31-N5)/N5 -> -0.21076316
A44: =SUM(D44:F44) -> 638.00837 | B44: 分摊 | C44: 分摊费用 | D44: 174.89607 | E44: 243.79851 | F44: 219.31379 | G44: 161.26311 | H44: 196.88485 | I44: 184.02968 | J44: 188.28229 | K44: 176.98346 | L44: 203.39738 | M44: 207.85696 | N44: 187.40864 | O44: -32.98022 | P44: =SUM(D44:O44) -> 2111.1345 | Q44: =P44/$P$31*1000 -> 4.4156572 | R44: =P44/$P$48 -> 0.10645333 | S44: =Q44/$S$30 -> 0.01990068 | V44: =D44+E44 -> 418.69458 | W44: =V44+F44 -> 638.00837 | X44: =W44+G44 -> 799.27148 | Y44: =X44+H44 -> 996.15633 | Z44: =Y44+I44 -> 1180.186 | AA44: =Z44+J44 -> 1368.4683 | AB44: =AA44+K44 -> 1545.4518 | AC44: =AB44+L44 -> 1748.8491 | AD44: =AC44+M44 -> 1956.7061 | ... AF44: =AE44+O44 -> 2111.1345 | AH44: =V44/V$31*1000 -> 4.4257598 | AI44: =W44/W$31*1000 -> 4.5267762 | AJ44: =X44/X$31*1000 -> 4.199972 | AK44: =Y44/Y$31*1000 -> 4.0824741 | AL44: =Z44/Z$31*1000 -> 4.3124105 | AM44: =AA44/AA$31*1000 -> 4.3370603 | AN44: =AB44/AB$31*1000 -> 4.4472664 | AO44: =AC44/AC$31*1000 -> 4.6539919 | ... AR44: =AF44/AF$31*1000 -> 4.4156572 | AT44: =AH44/AT$30 -> 0.019946211 | AU44: =AI44/AU$30 -> 0.020401476 | AV44: =AJ44/AV$30 -> 0.018928621 | AW44: =AK44/AW$30 -> 0.018399075 | AX44: =AL44/AX$30 -> 0.019435363 | AY44: =AM44/AY$30 -> 0.019546456 | AZ44: =AN44/AZ$30 -> 0.020043138 | BA44: =AO44/BA$30 -> 0.020974817 | ... BD44: =AR44/BD$30 -> 0.01990068
A45: =SUM(D45:F45) -> 300.76464 | C45: IT Expense-Internal Charge Out | D45: 100.051 | E45: 100.68714 | F45: 100.0265 | G45: 100.04283 | H45: 110.01524 | I45: 100.04283 | J45: 100.04283 | K45: 100.04283 | L45: 110.01524 | M45: 110.01524 | N45: 100.04283 | O45: -118.98588 | P45: =SUM(D45:O45) -> 1012.0386 | Q45: =P45/$P$31*1000 -> 2.1167839 | S45: =Q45/$S$30 -> 0.0095400159 | V45: =D45+E45 -> 200.73814 | W45: =V45+F45 -> 300.76464 | X45: =W45+G45 -> 400.80747 | Y45: =X45+H45 -> 510.82271 | Z45: =Y45+I45 -> 610.86554 | AA45: =Z45+J45 -> 710.90837 | AB45: =AA45+K45 -> 810.9512 | AC45: =AB45+L45 -> 920.96644 | AD45: =AC45+M45 -> 1030.9817 | ... AF45: =AE45+O45 -> 1012.0386 | AH45: =V45/V$31*1000 -> 2.1218779 | AI45: =W45/W$31*1000 -> 2.1339755 | AJ45: =X45/X$31*1000 -> 2.1061432 | AK45: =Y45/Y$31*1000 -> 2.0934671 | AL45: =Z45/Z$31*1000 -> 2.2321083 | AM45: =AA45/AA$31*1000 -> 2.2530682 | AN45: =AB45/AB$31*1000 -> 2.3336322 | AO45: =AC45/AC$31*1000 -> 2.4508519 | ... AR45: =AF45/AF$31*1000 -> 2.1167839 | AT45: =AH45/AT$30 -> 0.0095629737 | AU45: =AI45/AU$30 -> 0.0096174956 | AV45: =AJ45/AV$30 -> 0.0094920596 | AW45: =AK45/AW$30 -> 0.0094349304 | AX45: =AL45/AX$30 -> 0.010059765 | AY45: =AM45/AY$30 -> 0.010154228 | AZ45: =AN45/AZ$30 -> 0.010517317 | BA45: =AO45/BA$30 -> 0.011045608 | ... BD45: =AR45/BD$30 -> 0.0095400159
A46: =SUM(D46:F46) -> 15.03925 | C46: Association dues | D46: 5.03429 | E46: 4.99367 | F46: 5.01129 | G46: 5.00712 | H46: 4.9626 | I46: 4.06732 | J46: 5.10556 | K46: 4.14821 | L46: 4.01824 | M46: 4.6376 | N46: 4.34861 | O46: 3.65034 | P46: =SUM(D46:O46) -> 54.98485 | Q46: =P46/$P$31*1000 -> 0.11500653 | S46: =Q46/$S$30 -> 0.00051831652 | V46: =D46+E46 -> 10.02796 | W46: =V46+F46 -> 15.03925 | X46: =W46+G46 -> 20.04637 | Y46: =X46+H46 -> 25.00897 | Z46: =Y46+I46 -> 29.07629 | AA46: =Z46+J46 -> 34.18185 | AB46: =AA46+K46 -> 38.33006 | AC46: =AB46+L46 -> 42.3483 | AD46: =AC46+M46 -> 46.9859 | ... AF46: =AE46+O46 -> 54.98485 | AH46: =V46/V$31*1000 -> 0.10599932 | AI46: =W46/W$31*1000 -> 0.106706 | AJ46: =X46/X$31*1000 -> 0.10533867 | AK46: =Y46/Y$31*1000 -> 0.10249242 | AL46: =Z46/Z$31*1000 -> 0.10624503 | AM46: =AA46/AA$31*1000 -> 0.10833188 | AN46: =AB46/AB$31*1000 -> 0.11030043 | AO46: =AC46/AC$31*1000 -> 0.1126962 | ... AR46: =AF46/AF$31*1000 -> 0.11500653 | AT46: =AH46/AT$30 -> 0.00047772246 | AU46: =AI46/AU$30 -> 0.00048090733 | AV46: =AJ46/AV$30 -> 0.00047474499 | AW46: =AK46/AW$30 -> 0.00046191738 | AX46: =AL46/AX$30 -> 0.00047882982 | AY46: =AM46/AY$30 -> 0.00048823493 | AZ46: =AN46/AZ$30 -> 0.00049710686 | BA46: =AO46/BA$30 -> 0.00050790422 | ... BD46: =AR46/BD$30 -> 0.00051831652 | BE46: =N49/N23 -> 1.1750185
A47: =SUM(D47:F47) -> 322.20448 | C47: G&A | D47: 69.81078 | E47: 138.1177 | F47: 114.276 | G47: 56.21316 | H47: 81.90701 | I47: 79.91953 | J47: 83.1339 | K47: 73 | L47: 89.3639 | M47: 93.20412 | N47: 83.0172 | O47: 82.35532 | P47: =SUM(D47:O47) -> 1044.3186 | Q47: =P47/$P$31*1000 -> 2.1843009 | S47: =Q47/$S$30 -> 0.0098443043 | V47: =D47+E47 -> 207.92848 | W47: =V47+F47 -> 322.20448 | X47: =W47+G47 -> 378.41764 | Y47: =X47+H47 -> 460.32465 | Z47: =Y47+I47 -> 540.24418 | AA47: =Z47+J47 -> 623.37808 | AB47: =AA47+K47 -> 696.37808 | AC47: =AB47+L47 -> 785.74198 | AD47: =AC47+M47 -> 878.9461 | ... AF47: =AE47+O47 -> 1044.3186 | AH47: =V47/V$31*1000 -> 2.1978825 | AI47: =W47/W$31*1000 -> 2.2860947 | AJ47: =X47/X$31*1000 -> 1.9884902 | AK47: =Y47/Y$31*1000 -> 1.8865146 | AL47: =Z47/Z$31*1000 -> 1.9740572 | AM47: =AA47/AA$31*1000 -> 1.9756602 | AN47: =AB47/AB$31*1000 -> 2.0039311 | AO47: =AC47/AC$31*1000 -> 2.0909961 | ... AR47: =AF47/AF$31*1000 -> 2.1843009 | AT47: =AH47/AT$30 -> 0.0099055147 | AU47: =AI47/AU$30 -> 0.010303073 | AV47: =AJ47/AV$30 -> 0.008961816 | AW47: =AK47/AW$30 -> 0.0085022277 | AX47: =AL47/AX$30 -> 0.0088967687 | AY47: =AM47/AY$30 -> 0.0089039931 | AZ47: =AN47/AZ$30 -> 0.0090314057 | BA47: =AO47/BA$30 -> 0.0094237943 | ... BD47: =AR47/BD$30 -> 0.0098443043
A48: =SUM(D48:F48) -> 5162.3545 | B48: 合计 | D48: =SUM(D32:D44) -> 1702.2213 | E48: =SUM(E32:E44) -> 1632.2334 | F48: =SUM(F32:F44) -> 1827.8999 | G48: =SUM(G32:G44) -> 1591.5968 | H48: =SUM(H32:H44) -> 1866.987 | I48: =SUM(I32:I44) -> 1737.9 | J48: =SUM(J32:J44) -> 1637.4123 | K48: =SUM(K32:K44) -> 1533.5455 | ... Q48: =SUM(Q32:Q44) -> 41.479747 | V48: =SUM(V32:V44) -> 3334.4547 | W48: =SUM(W32:W44) -> 5162.3545 | X48: =SUM(X32:X44) -> 6753.9513 | Y48: =SUM(Y32:Y44) -> 8620.9383 | Z48: =SUM(Z32:Z44) -> 10358.838 | AA48: =SUM(AA32:AA44) -> 11996.251 | AB48: =SUM(AB32:AB44) -> 13529.796 | AC48: =SUM(AC32:AC44) -> 15127.651 | ... AF48: =SUM(AF32:AF44) -> 19831.55 | AH48: =V48/V$31*1000 -> 35.246445 | AI48: =W48/W$31*1000 -> 36.62777 | AJ48: =X48/X$31*1000 -> 35.490328 | AK48: =Y48/Y$31*1000 -> 35.330556 | AL48: =Z48/Z$31*1000 -> 37.85129 | AM48: =AA48/AA$31*1000 -> 38.019487 | AN48: =AB48/AB$31*1000 -> 38.933993 | AO48: =AC48/AC$31*1000 -> 40.257313 | ... AR48: =AF48/AF$31*1000 -> 41.479747 | AT48: =AH48/AT$30 -> 0.15885024 | AU48: =AI48/AU$30 -> 0.16507566 | AV48: =AJ48/AV$30 -> 0.15994939 | AW48: =AK48/AW$30 -> 0.15922932 | AX48: =AL48/AX$30 -> 0.17058988 | AY48: =AM48/AY$30 -> 0.17134791 | AZ48: =AN48/AZ$30 -> 0.17546945 | BA48: =AO48/BA$30 -> 0.18143345 | ... BD48: =AR48/BD$30 -> 0.18694277
A49: =A48/A31*1000 -> 36.62777 | B49: 单台 | D49: =D48/D31*1000 -> 35.046041 | E49: =E48/E31*1000 -> 35.457898 | F49: =F48/F31*1000 -> 39.447954 | G49: =G48/G31*1000 -> 32.242707 | H49: =H48/H31*1000 -> 34.764394 | I49: =I48/I31*1000 -> 58.586165 | J49: =J48/J31*1000 -> 39.119199 | K49: =K48/K31*1000 -> 47.957767 | ... P49: =P48/P31*1000 -> 41.479747 | Q49: =P49 -> 41.479747 | S49: =Q49/$S$30 -> 0.18694277 | V49: =V48/V31*1000 -> 35.246445 | W49: =W48/W31*1000 -> 36.62777 | X49: =X48/X31*1000 -> 35.490328 | Y49: =Y48/Y31*1000 -> 35.330556 | Z49: =Z48/Z31*1000 -> 37.85129 | AA49: =AA48/AA31*1000 -> 38.019487 | AB49: =AB48/AB31*1000 -> 38.933993 | AC49: =AC48/AC31*1000 -> 40.257313 | ... AF49: =AF48/AF31*1000 -> 41.479747
A50: =SUM(D50:F50) -> 1087.1423 | B50: functional currency | D50: 377.12743 | E50: 334.21236 | F50: 375.80255 | G50: 361.671 | H50: 385.10541 | I50: 380.77777 | J50: 396 | K50: 398.06437 | L50: 390.71573 | M50: 240.08197 | N50: 376 | O50: 390.25287 | P50: =SUM(D50:O50) -> 4405.8115 | Q50: =P50/$P$31*1000 -> 9.2152124 | R50: =P50/$P$48 -> 0.22216173 | S50: =Q50/$S$30 -> 0.041531529
A51: =A49/A30 -> 0.16498996 | C51: 洗碗机25年预算 | Q51: =Q49-Q50 -> 32.264535 | S51: =Q51/S30 -> 0.14541124
C52: 科目 | D52: 25年1月 | E52: 25年2月 | F52: 25年3月 | G52: 25年4月 | H52: 25年5月 | I52: 25年6月 | J52: 25年7月 | K52: 25年8月 | L52: 25年9月 | M52: 25年10月 | N52: 25年11月 | O52: 25年12月 | P52: 合计 | Q52: 单台 | R52: 占比 | S52: 费率 | T52: 同比
B53: 平均单价 | D53: 238.80897 | E53: 226.19836 | F53: 223.23948 | G53: 224.25987 | H53: 225.65715 | I53: 223.82375 | J53: 224.48332 | K53: 224.47304 | L53: 223.98961 | M53: 225.05533 | N53: 225.1154 | O53: 225.71752 | P53: 225.66619 | AT53: =$P$53 -> 225.66619 | AU53: =$P$53 -> 225.66619 | AV53: =$P$53 -> 225.66619 | AW53: =$P$53 -> 225.66619 | AX53: =$P$53 -> 225.66619 | AY53: =$P$53 -> 225.66619 | AZ53: =$P$53 -> 225.66619 | BA53: =$P$53 -> 225.66619 | ... BD53: =$P$53 -> 225.66619
C54: 产量 | D54: 46728 | E54: 46020 | F54: 46020 | G54: 48321 | H54: 48321 | I54: 18408 | J54: 52923 | K54: 48321 | L54: 50622 | M54: 52923 | N54: 46020 | O54: 45373 | P54: =SUM(D54:O54) -> 550000 | V54: =D54+E54 -> 92748 | W54: =V54+F54 -> 138768 | X54: =W54+G54 -> 187089 | Y54: =X54+H54 -> 235410 | Z54: =Y54+I54 -> 253818 | AA54: =Z54+J54 -> 306741 | AB54: =AA54+K54 -> 355062 | AC54: =AB54+L54 -> 405684 | AD54: =AC54+M54 -> 458607 | ... AF54: =AE54+O54 -> 550000
B55: 固定制造 | C55: 折旧-不含FC | D55: 146.82976 | E55: 146.82976 | F55: 146.82976 | G55: 146.82976 | H55: 146.82976 | I55: 146.82976 | J55: 146.82976 | K55: 146.82976 | L55: 146.82976 | M55: 146.82976 | N55: 146.82976 | O55: 146.82976 | P55: =SUM(D55:O55) -> 1761.9571 | Q55: =P55/$P$54*1000 -> 3.2035584 | R55: =P55/$P$71 -> 0.13171185 | V55: =D55+E55 -> 293.65952 | W55: =V55+F55 -> 440.48928 | X55: =W55+G55 -> 587.31904 | Y55: =X55+H55 -> 734.1488 | Z55: =Y55+I55 -> 880.97856 | AA55: =Z55+J55 -> 1027.8083 | AB55: =AA55+K55 -> 1174.6381 | AC55: =AB55+L55 -> 1321.4678 | AD55: =AC55+M55 -> 1468.2976 | ... AF55: =AE55+O55 -> 1761.9571 | AH55: =V55/V$54*1000 -> 3.1662087 | AI55: =W55/W$54*1000 -> 3.1742857 | AJ55: =X55/X$54*1000 -> 3.1392494 | AK55: =Y55/Y$54*1000 -> 3.1185965 | AL55: =Z55/Z$54*1000 -> 3.4709066 | AM55: =AA55/AA$54*1000 -> 3.3507367 | AN55: =AB55/AB$54*1000 -> 3.3082619 | AO55: =AC55/AC$54*1000 -> 3.2573822 | ... AR55: =AF55/AF$54*1000 -> 3.2035584 | AT55: =AH55/$AT$53 -> 0.014030496 | AU55: =AI55/$AT$53 -> 0.014066288 | AV55: =AJ55/$AT$53 -> 0.013911031 | AW55: =AK55/$AT$53 -> 0.013819511 | AX55: =AL55/$AT$53 -> 0.015380711 | AY55: =AM55/$AT$53 -> 0.0148482 | AZ55: =AN55/$AT$53 -> 0.01465998 | BA55: =AO55/$AT$53 -> 0.014434516 | ... BD55: =AR55/$AT$53 -> 0.014196005
C56: 运营费 | D56: 30.43306 | E56: 30.43306 | F56: 30.43306 | G56: 30.43306 | H56: 30.43306 | I56: 30.43306 | J56: 30.43306 | K56: 30.43306 | L56: 30.43306 | M56: 30.43306 | N56: 30.43306 | O56: 30.43306 | P56: =SUM(D56:O56) -> 365.19672 | Q56: =P56/$P$54*1000 -> 0.66399404 | R56: =P56/$P$71 -> 0.027299605 | V56: =D56+E56 -> 60.86612 | W56: =V56+F56 -> 91.29918 | X56: =W56+G56 -> 121.73224 | Y56: =X56+H56 -> 152.1653 | Z56: =Y56+I56 -> 182.59836 | AA56: =Z56+J56 -> 213.03142 | AB56: =AA56+K56 -> 243.46448 | AC56: =AB56+L56 -> 273.89754 | AD56: =AC56+M56 -> 304.3306 | ... AF56: =AE56+O56 -> 365.19672 | AH56: =V56/V$54*1000 -> 0.65625264 | AI56: =W56/W$54*1000 -> 0.65792676 | AJ56: =X56/X$54*1000 -> 0.65066487 | AK56: =Y56/Y$54*1000 -> 0.64638418 | AL56: =Z56/Z$54*1000 -> 0.71940666 | AM56: =AA56/AA$54*1000 -> 0.69449933 | AN56: =AB56/AB$54*1000 -> 0.68569568 | AO56: =AC56/AC$54*1000 -> 0.67514997 | ... AR56: =AF56/AF$54*1000 -> 0.66399404 | AT56: =AH56/$AT$53 -> 0.002908068 | AU56: =AI56/$AT$53 -> 0.0029154866 | AV56: =AJ56/$AT$53 -> 0.0028833068 | AW56: =AK56/$AT$53 -> 0.0028643377 | AX56: =AL56/$AT$53 -> 0.003187924 | AY56: =AM56/$AT$53 -> 0.0030775515 | AZ56: =AN56/$AT$53 -> 0.0030385397 | BA56: =AO56/$AT$53 -> 0.0029918082 | ... BD56: =AR56/$AT$53 -> 0.0029423727
