Workbook
Name \1: #REF!
Name \2: #REF!
Name \3: #REF!
Name \4: #REF!
Name \A: #REF!
Name \B: #REF!
Name \C: #REF!
Name \P: #REF!
Name \Q: #REF!
Name \R: #REF!
Name \S: #REF!
Name \T: #REF!
Name \X: #REF!
Name ___CON1: #REF!
Name ___CON2: #REF!
Name ___ddn400: #REF!
Name ___ddn600: #REF!
Name ___E99999: #REF!
Name ___ETI2: #REF!
Name ___gon4: #REF!
Name ___IV999999: #REF!
Name ___IZ53: #REF!
Name ___JZ123: #REF!
Name ___lap1: #REF!
Name ___lap2: #REF!
Name ___LI1: OFFSET(#REF!,4,0,COUNTA(#REF!)-1,1)
Name ___LI10: OFFSET(#REF!,4,0,COUNTA(#REF!)-1,1)
Name ___LI11: OFFSET(#REF!,4,0,COUNTA(#REF!)-1,1)
Name ___LI12: OFFSET(#REF!,4,0,COUNTA(#REF!)-1,1)
Name ___LI13: OFFSET(#REF!,4,0,COUNTA(#REF!)-1,1)
Name ___LI14: OFFSET(#REF!,4,0,COUNTA(#REF!)-1,1)
Name ___LI15: OFFSET(#REF!,4,0,COUNTA(#REF!)-1,1)
Name ___LI16: OFFSET(#REF!,4,0,COUNTA(#REF!)-1,1)
Name ___LI17: OFFSET(#REF!,4,0,COUNTA(#REF!)-1,1)
Name ___LI18: OFFSET(#REF!,4,0,COUNTA(#REF!)-1,1)
Name ___LI19: OFFSET(#REF!,4,0,COUNTA(#REF!)-1,1)
Name ___LI2: OFFSET(#REF!,4,0,COUNTA(#REF!)-1,1)
Name ___LI20: OFFSET(#REF!,4,0,COUNTA(#REF!)-1,1)
Name ___LI21: OFFSET(#REF!,4,0,COUNTA(#REF!)-1,1)
Name ___LI22: OFFSET(#REF!,4,0,COUNTA(#REF!)-1,1)
Name ___LI23: OFFSET(#REF!,4,0,COUNTA(#REF!)-1,1)
Name ___LI24: OFFSET(#REF!,4,0,COUNTA(#REF!)-1,1)
Name ___LI25: OFFSET(#REF!,4,0,COUNTA(#REF!)-1,1)
Name ___LI3: OFFSET(#REF!,4,0,COUNTA(#REF!)-1,1)
Name ___LI30: OFFSET(#REF!,4,0,COUNTA(#REF!)-1,1)
Name ___LI4: OFFSET(#REF!,4,0,COUNTA(#REF!)-1,1)
Name ___LI5: OFFSET(#REF!,4,0,COUNTA(#REF!)-1,1)
Name ___LI6: OFFSET(#REF!,4,0,COUNTA(#REF!)-1,1)
Name ___LI7: OFFSET(#REF!,4,0,COUNTA(#REF!)-1,1)
Name ___LI8: OFFSET(#REF!,4,0,COUNTA(#REF!)-1,1)
Name ___LI9: OFFSET(#REF!,4,0,COUNTA(#REF!)-1,1)
Name ___LZ123: #REF!
Name ___MAC12: #REF!
Name ___MAC46: #REF!
Name ___MZ53: #REF!
Name ___NCL100: #REF!
Name ___NCL200: #REF!
Name ___NCL250: #REF!
Name ___NET2: #REF!
Name ___nin190: #REF!

Sheet CC
B2: MFG | C2: PTK4M00WAB
C3: PTK4M00WAC
C4: PTK4M00WAD
C5: PTK4M00WAE
C6: PTK4M00WAF
C7: PTK4M00WAG
C8: PTK4M00WAH
C9: PTK4M00WAI
C10: PTK4M00WAJ
C11: PTK4M00WAK
C12: PTK4M00WYD
B13: Overhead | C13: PTK4Y00WYE

Sheet DW 2026
B1: Renta DW Cost Evolution | D1: Volume | E1: 47357 | F1: 42593 | G1: 23002 | H1: 44096 | I1: 33043 | J1: 53186 | K1: 40831 | L1: 39000.001 | M1: 54085 | N1: 49968 | O1: 51936 | P1: 42190 | Q1: =+E1+F1+G1+H1+I1+J1+K1+L1+M1+N1+O1+P1 -> 521287
D2: FX Rates_HQE | E2: 50.745776 | F2: 51.632775 | G2: 51.093809 | H2: 52.45 | I2: 53.158395 | J2: 53.3 | K2: 53.76 | L2: 55.623333 | M2: 56.525 | N2: 57.283333 | O2: 58.041667 | P2: 58.8
D3: FX Rates_weighted average (Act TL/Act EUR) | E3: =+E245 -> 55.415196 | F3: =+F245 -> 52.908683 | G3: =+G245 -> 52.478115 | H3: =+H245 -> 0 | I3: =+I245 -> 0 | J3: =+J245 -> 0 | K3: =+K245 -> 0 | L3: =+L245 -> 0 | ... Q3: =+Q245 -> 0
A5: HQD PERIMETER | E5: Jan K€ | F5: Feb K€ | G5: Mar K€ | H5: Apr K€ | I5: May K€ | J5: June K€ | K5: July K€ | L5: Aug K€ | M5: Sep K€ | N5: Oct K€ | O5: Nov K€ | P5: DEC K€ | Q5: YTD K€
A6: YES | B6: 6666110101 | C6: 6666110101 Depreciation of buildings | D6: * CS_Depreciation | E6: =32.52614-E251 -> 9.5887601 | F6: 8.6135783 | G6: =32.53747-G251 -> 9.5496438 | H6: 7.5771286 | I6: 13.807534 | J6: 8.7067803 | K6: 8.7355413 | L6: 451.07175 | M6: 441.19345 | N6: 453.16818 | O6: 446.77673 | P6: 459.37043 | Q6: =F6+E6+G6+H6+I6+J6+K6+L6+M6+N6+O6+P6 -> 2318.1595
A7: YES | B7: 6666110106 | C7: 6666110106 Depreciation of R&D facilities | D7: * CS_Depreciation | E7: =0-E252 -> 0 | F7: 0 | G7: 0 | H7: 0 | I7: 0 | J7: 0 | K7: 0 | L7: 0 | M7: 0 | N7: 0 | O7: 0 | P7: 0 | Q7: =F7+E7+G7+H7+I7+J7+K7+L7+M7+N7+O7+P7 -> 0
A8: YES | B8: 6666110107 | C8: 6666110107 Depreciation of mold | D8: * CS_Depreciation | E8: =224.42191-E253 -> 92.462416 | F8: 87.582816 | G8: =224.82728-G253 -> 92.230816 | H8: -28.532337 | I8: 57.979578 | J8: 62.165871 | K8: 62.303587 | L8: -106.94686 | M8: -107.16719 | N8: -109.11171 | O8: -108.98445 | P8: -144.12936 | Q8: =F8+E8+G8+H8+I8+J8+K8+L8+M8+N8+O8+P8 -> -150.14683
A9: YES | B9: 6666110110 | C9: 6666110110 Depreciation-Plant & Machinery | D9: * CS_Depreciation | E9: =295.75794-E254 -> 63.749081 | F9: 57.049972 | G9: =296.41246-G254 -> 63.876727 | H9: 17.589213 | I9: 50.464631 | J9: 59.732843 | K9: 48.220076 | L9: -179.7257 | M9: -174.32048 | N9: -180.83947 | O9: -175.04577 | P9: -237.55234 | Q9: =F9+E9+G9+H9+I9+J9+K9+L9+M9+N9+O9+P9 -> -586.80122
A10: YES | B10: 6666110112 | C10: 6666110112 Depreciation of Furniture & Fixture | D10: * CS_Depreciation | E10: =8.94279-E255 -> 4.2473878 | F10: 3.5120625 | G10: =8.80315-G255 -> 4.0802573 | H10: -1.8538329 | I10: 1.4199062 | J10: 0.95259662 | K10: 2.3047451 | L10: -0.46773118 | M10: -0.46734558 | N10: -0.62049232 | O10: -0.52596366 | P10: -1.3658423 | Q10: =F10+E10+G10+H10+I10+J10+K10+L10+M10+N10+O10+P10 -> 11.215748
A11: YES | B11: 6666110204 | C11: 6666110204 Amortization of license, trademarks and | D11: * CS_Depreciation | E11: =0.25252-E256 -> 0.17412081 | F11: 0.17112992 | G11: =0.25252-G256 -> 0.17293485 | H11: -0.30079261 | I11: 0.0090222244 | J11: 0.049860056 | K11: 0.048564111 | L11: 1.6232069 | M11: 1.6769447 | N11: 1.6753436 | O11: 1.6162509 | P11: 1.6492861 | Q11: =F11+E11+G11+H11+I11+J11+K11+L11+M11+N11+O11+P11 -> 8.5658714
A12: YES | B12: 6666110207 | C12: 6666110207 Amortization of Software | D12: * CS_Depreciation | E12: =2.34991-E257 -> 1.1264639 | F12: 1.1066886 | G12: =2.34993-G257 -> 1.1187913 | H12: -1.5773002 | I12: -0.06417721 | J12: 0.43481723 | K12: 0.42483049 | L12: -1.1428264 | M12: -0.75593496 | N12: -0.92121231 | O12: -0.97125697 | P12: -1.274676 | Q12: =F12+E12+G12+H12+I12+J12+K12+L12+M12+N12+O12+P12 -> -2.4957925
A13: YES | B13: 6666110506 | C13: 6666110506 Amortization-Leasehold Improvement | D13: * CS_Depreciation | E13: =0-E258 -> 0 | F13: 0 | G13: 0 | H13: 0 | I13: 0 | J13: 0 | K13: 0 | L13: 0 | M13: 0 | N13: 0 | O13: 0 | P13: 0 | Q13: =F13+E13+G13+H13+I13+J13+K13+L13+M13+N13+O13+P13 -> 0
B14: FIX | C14: * CS_Depreciation | E14: =SUM(E6:E13) -> 171.34823 | F14: =SUM(F6:F13) -> 158.03625 | G14: =SUM(G6:G13) -> 171.02917 | H14: =SUM(H6:H13) -> -7.0979216 | I14: =SUM(I6:I13) -> 123.61649 | J14: =SUM(J6:J13) -> 132.04277 | K14: =SUM(K6:K13) -> 122.03734 | L14: =SUM(L6:L13) -> 164.41184 | ... Q14: =SUM(Q6:Q13) -> 1598.4973
A15: YES | B15: 5001010205 | C15: 5001010205 Unemployment Insurance -blue collar-Dire | D15: * CS_Direct Labour | E15: 7.61607 | F15: 6.3086 | G15: 6.05422 | H15: 5.8402799 | I15: 7.1399794 | J15: 6.57644 | K15: 5.76483 | L15: 0 | M15: 0 | N15: 0 | O15: 0 | P15: 0 | Q15: =F15+E15+G15+H15+I15+J15+K15+L15+M15+N15+O15+P15 -> 45.300419
A16: YES | B16: 6666010380 | C16: 6666010380 Incentive | D16: * CS_Direct Labour | E16: -1.8209 | F16: -1.58476 | G16: 0.192 | H16: -0.63535 | I16: -3.83977 | J16: -1.48382 | K16: -2.25762 | L16: 0 | M16: 0 | N16: 0 | O16: 0 | P16: 0 | Q16: =F16+E16+G16+H16+I16+J16+K16+L16+M16+N16+O16+P16 -> -11.43022
A17: YES | B17: 6666010019 | C17: 6666010019 Payroll Taxes - Blue Collar Direct | D17: * CS_Direct Labour | E17: 64.67305 | F17: 53.75998 | G17: 50.63986 | H17: 49.665935 | I17: 61.079734 | J17: 56.41294 | K17: 49.35098 | L17: 355.48086 | M17: 485.59337 | N17: 492.47378 | O17: 476.66858 | P17: 480.28353 | Q17: =F17+E17+G17+H17+I17+J17+K17+L17+M17+N17+O17+P17 -> 2676.0826
A18: YES | B18: 6666010183 | C18: 6666010183 Overtime-Blue Collar-Direct | D18: * CS_Direct Labour | E18: 10.50135 | F18: 13.3775 | G18: -9.43515 | H18: 21.249929 | I18: 16.554552 | J18: 8.86122 | K18: 9.75508 | L18: 0 | M18: 0 | N18: 0 | O18: 0 | P18: 0 | Q18: =F18+E18+G18+H18+I18+J18+K18+L18+M18+N18+O18+P18 -> 70.864481
A19: YES | B19: 6666010229 | C19: 6666010229 Staff Leaving Indemnity - Blue Collar Di | D19: * CS_Direct Labour | E19: 16.69101 | F19: 107.23839 | G19: -345.16488 | H19: 9.97066 | I19: 10.4602 | J19: 10.57159 | K19: 1.16773 | L19: 0 | M19: 0 | N19: 0 | O19: 0 | P19: 0 | Q19: =F19+E19+G19+H19+I19+J19+K19+L19+M19+N19+O19+P19 -> -189.0653
A20: YES | B20: 6666010188 | C20: 6666010188 Salary - Blue collar direct employees | D20: * CS_Direct Labour | E20: 357.71936 | F20: 277.99859 | G20: 573.04631 | H20: 277.01291 | I20: 381.56738 | J20: 312.0039 | K20: 277.45603 | L20: 0 | M20: 0 | N20: 0 | O20: 0 | P20: 0 | Q20: =F20+E20+G20+H20+I20+J20+K20+L20+M20+N20+O20+P20 -> 2456.8045
A21: YES | B21: 5102040406 | C21: 5102040406 Other revenue-Service/Secondment agreeme | D21: * CS_Direct Labour | E21: 0 | F21: 0 | G21: 0 | H21: 0 | I21: 0 | J21: 0 | K21: 0 | L21: 0 | M21: 0 | N21: 0 | O21: 0 | P21: 0 | Q21: =F21+E21+G21+H21+I21+J21+K21+L21+M21+N21+O21+P21 -> 0
A22: YES | B22: 6666010115 | C22: 6666010115 Salary-Blue collar direct employees-Accr | D22: * CS_Direct Labour | E22: -4.2657 | F22: 0.68853 | G22: 0.63223 | H22: 0.63007 | I22: 5.6858 | J22: -1.30866 | K22: 7.8172 | L22: 0 | M22: 0 | N22: 0 | O22: 0 | P22: 0 | Q22: =F22+E22+G22+H22+I22+J22+K22+L22+M22+N22+O22+P22 -> 9.87947
B23: VAR | C23: * CS_Direct Labour | E23: =SUM(E15:E22) -> 451.11424 | F23: =SUM(F15:F22) -> 457.78683 | G23: =SUM(G15:G22) -> 275.96459 | H23: =SUM(H15:H22) -> 363.73443 | I23: =SUM(I15:I22) -> 478.64787 | J23: =SUM(J15:J22) -> 391.63361 | K23: =SUM(K15:K22) -> 349.05423 | L23: =SUM(L15:L22) -> 355.48086 | ... Q23: =SUM(Q15:Q22) -> 5058.4359
A24: NO | B24: 8701530201 | C24: 8701530201 Scrap-Raw Material - Managerial | D24: * CS_SCRAP_VARIABLE | E24: 0 | F24: 0 | G24: 0 | H24: 0 | I24: 0 | J24: 0 | K24: 0 | L24: 0 | M24: 0 | N24: 0 | O24: 0 | P24: 0 | Q24: =F24+E24+G24+H24+I24+J24+K24+L24+M24+N24+O24+P24 -> 0
A25: NO | B25: 6666050309 | C25: 6666050309 SFG scrap | D25: * CS_SCRAP_VARIABLE | E25: 6.0635 | F25: 6.05671 | G25: 5.52431 | H25: 4.28283 | I25: 3.73302 | J25: 4.86599 | K25: 4.04197 | L25: 17.5076 | M25: 24.15908 | N25: 21.98592 | O25: 22.85184 | P25: 18.5636 | Q25: =F25+E25+G25+H25+I25+J25+K25+L25+M25+N25+O25+P25 -> 139.63637
A26: NO | B26: 6666050308 | C26: 6666050308 Raw material scrap | D26: * CS_SCRAP_VARIABLE | E26: 11.57396 | F26: 7.72351 | G26: 2.51955 | H26: 44.86048 | I26: 11.78646 | J26: 22.05431 | K26: 23.36611 | L26: 0 | M26: 0 | N26: 0 | O26: 0 | P26: 0 | Q26: =F26+E26+G26+H26+I26+J26+K26+L26+M26+N26+O26+P26 -> 123.88438
A27: NO | B27: 6666050306 | C27: 6666050306 Finished goods scrap | D27: * CS_SCRAP_VARIABLE | E27: 0.58819 | F27: 0.55747 | G27: 1.51094 | H27: 1.3141 | I27: 0.56572 | J27: 1.05008 | K27: 3.53734 | L27: 0 | M27: 0 | N27: 0 | O27: 0 | P27: 0 | Q27: =F27+E27+G27+H27+I27+J27+K27+L27+M27+N27+O27+P27 -> 9.12384
B28: VAR | C28: * CS_SCRAP_VARIABLE | E28: =SUM(E24:E27) -> 18.22565 | F28: =SUM(F24:F27) -> 14.33769 | G28: =SUM(G24:G27) -> 9.5548 | H28: =SUM(H24:H27) -> 50.45741 | I28: =SUM(I24:I27) -> 16.0852 | J28: =SUM(J24:J27) -> 27.97038 | K28: =SUM(K24:K27) -> 30.94542 | L28: =SUM(L24:L27) -> 17.5076 | ... Q28: =SUM(Q24:Q27) -> 272.64459
A29: YES | B29: 5102010151 | C29: 5102010151 Other Rev.-Interco-Epidemic problem comp | D29: * CS_Fix Cost | E29: 0 | F29: 0 | G29: 0 | H29: 0 | I29: 0 | J29: 0 | K29: 0 | L29: 0 | M29: 0 | N29: 0 | O29: 0 | P29: 0 | Q29: =F29+E29+G29+H29+I29+J29+K29+L29+M29+N29+O29+P29 -> 0
A30: YES | B30: 5001010200 | C30: 5001010200 Cost of Manufacture - Raw Material | D30: * CS_Fix Cost | E30: 0 | F30: 0.00046 | G30: -1.38193 | H30: 0 | I30: 0 | J30: 0 | K30: 0 | L30: 0 | M30: 0 | N30: 0 | O30: 0 | P30: 0 | Q30: =F30+E30+G30+H30+I30+J30+K30+L30+M30+N30+O30+P30 -> -1.38147
A31: YES | B31: 5001010201 | C31: 5001010201 Cost of Manufacture - Raw Material-Freig | D31: * CS_Fix Cost | E31: 0 | F31: 0 | G31: 0 | H31: 0 | I31: 0 | J31: 0 | K31: 0 | L31: 0 | M31: 0 | N31: 0 | O31: 0 | P31: 0 | Q31: =F31+E31+G31+H31+I31+J31+K31+L31+M31+N31+O31+P31 -> 0
A32: YES | B32: 5001010204 | C32: 5001010204 Cost of Manufacture - Finished Good | D32: * CS_Fix Cost | E32: 0 | F32: 0 | G32: 0.51622 | H32: 0 | I32: 0 | J32: 0 | K32: 0 | L32: 0 | M32: 0 | N32: 0 | O32: 0 | P32: 0
A33: YES | B33: 5207000011 | C33: 5207000011 Gain of tangible asset disposal | D33: * CS_Fix Cost | E33: 0 | F33: 0 | G33: 0 | H33: -0.01625 | I33: 0 | J33: 0 | K33: 0 | L33: 1.5 | M33: 1.5 | N33: 1.5 | O33: 1.5 | P33: 1.5 | Q33: =F33+E33+G33+H33+I33+J33+K33+L33+M33+N33+O33+P33 -> 7.48375
A34: YES | B34: 5207000012 | C34: 5207000012 Loss of tangible asset sold | D34: * CS_Fix Cost | E34: 0 | F34: 0 | G34: 0 | H34: 0 | I34: 0 | J34: 0 | K34: 0 | L34: 0 | M34: 0 | N34: 0 | O34: 0 | P34: 0 | Q34: =F34+E34+G34+H34+I34+J34+K34+L34+M34+N34+O34+P34 -> 0
A35: YES | B35: 5207000022 | C35: 5207000022 Loss of intangible asset disposal | D35: * CS_Fix Cost | E35: 0 | F35: 0 | G35: 0 | H35: 0 | I35: 0 | J35: 0 | K35: 0 | L35: 0 | M35: 0 | N35: 0 | O35: 0 | P35: 0 | Q35: =F35+E35+G35+H35+I35+J35+K35+L35+M35+N35+O35+P35 -> 0
A36: YES | B36: 5301060000 | C36: 5301060000 Other Income-Subsidy income | D36: * CS_Fix Cost | E36: 0 | F36: 0 | G36: 0 | H36: -0.14585 | I36: -0.0285 | J36: 0 | K36: 0 | L36: 0 | M36: 0 | N36: 0 | O36: 0 | P36: 0 | Q36: =F36+E36+G36+H36+I36+J36+K36+L36+M36+N36+O36+P36 -> -0.17435
A37: YES | B37: 5301999999 | C37: 5301999999 Non-operation revenue-Other | D37: * CS_Fix Cost | E37: 0 | F37: -0.00545 | G37: -0.09966 | H37: -0.41552 | I37: -0.39233 | J37: -0.28006 | K37: -0.96985 | L37: 0 | M37: 0 | N37: 0 | O37: 0 | P37: 0 | Q37: =F37+E37+G37+H37+I37+J37+K37+L37+M37+N37+O37+P37 -> -2.16287
A38: YES | B38: 5405030000 | C38: 5405030000 Other cost-others | D38: * CS_Fix Cost | E38: 0 | F38: 0 | G38: 0 | H38: 0 | I38: 0 | J38: 0 | K38: 0 | L38: 0 | M38: 0 | N38: 0 | O38: 0 | P38: 0 | Q38: =F38+E38+G38+H38+I38+J38+K38+L38+M38+N38+O38+P38 -> 0
A39: YES | B39: 5601050000 | C39: 5601050000 Non-Operating Expense - Penalty | D39: * CS_Fix Cost | E39: 0 | F39: 0 | G39: 0 | H39: 0 | I39: 0 | J39: 0 | K39: 0 | L39: 0 | M39: 0 | N39: 0 | O39: 0 | P39: 0 | Q39: =F39+E39+G39+H39+I39+J39+K39+L39+M39+N39+O39+P39 -> 0
A40: YES | B40: 5601050100 | C40: 5601050100 Non-operation Expense-Others | D40: * CS_Fix Cost | E40: 0 | F40: 0 | G40: 0 | H40: 0.128 | I40: 0.2642 | J40: 0 | K40: 0.68962 | L40: 0 | M40: 0 | N40: 0 | O40: 0 | P40: 0 | Q40: =F40+E40+G40+H40+I40+J40+K40+L40+M40+N40+O40+P40 -> 1.08182
A41: YES | B41: 5102040893 | C41: 5102040893 Other revenue-Charge out-Test Expense | D41: * CS_Fix Cost | E41: 0 | F41: 0 | G41: -0.25953 | H41: 0 | I41: 0 | J41: 0 | K41: 0 | L41: 0 | M41: 0 | N41: 0 | O41: 0 | P41: 0 | Q41: =F41+E41+G41+H41+I41+J41+K41+L41+M41+N41+O41+P41 -> -0.25953
A42: YES | B42: 5801000041 | C42: 5801000041 Previous year Sundry cost | D42: * CS_Fix Cost | E42: 0 | F42: 0 | G42: 0 | H42: 0 | I42: 0 | J42: 0 | K42: 0 | L42: 0 | M42: 0 | N42: 0 | O42: 0 | P42: 0 | Q42: =F42+E42+G42+H42+I42+J42+K42+L42+M42+N42+O42+P42 -> 0
A43: YES | B43: 6666010322 | C43: 6666010322 fuel allowance | D43: * CS_Fix Cost | E43: 1.46012 | F43: 0.36786 | G43: 1.18031 | H43: -1.53204 | I43: -0.58441 | J43: -0.00074 | K43: 0.00074 | L43: 1.837693 | M43: 1.8231081 | N43: 1.7917525 | O43: 1.7609361 | P43: 1.7306497 | Q43: =F43+E43+G43+H43+I43+J43+K43+L43+M43+N43+O43+P43 -> 9.8359793
A44: YES | B44: 6666020101 | C44: 6666020101 Entertainment | D44: * CS_Fix Cost | E44: 4.70552 | F44: 4.61778 | G44: 4.55447 | H44: -13.31884 | I44: 1.25782 | J44: 0.00104 | K44: 0.11232 | L44: 0 | M44: 0 | N44: 7.831 | O44: 7.831 | P44: 7.831 | Q44: =F44+E44+G44+H44+I44+J44+K44+L44+M44+N44+O44+P44 -> 25.42311
... A57: YES | B57: 6666020701 | C57: 6666020701 Enterprise Property Insurance | D57: * CS_Fix Cost | E57: 0 | F57: 0 | G57: 0 | H57: 0 | I57: 0 | J57: 0 | K57: 0 | L57: 0 | M57: 0 | N57: 0 | O57: 0 | P57: 0 | Q57: =F57+E57+G57+H57+I57+J57+K57+L57+M57+N57+O57+P57 -> 0
A58: YES | B58: 6666020801 | C58: 6666020801 Housing rental cost | D58: * CS_Fix Cost | F58: 1.56887 | G58: 0.95001 | H58: -2.55362 | I58: 0.29748 | J58: 5.18232 | K58: -0.61586 | L58: 1.1656562 | M58: 1.156405 | N58: 1.1365159 | O58: 1.116969 | P58: 1.0977582 | Q58: =F58+E58+G58+H58+I58+J58+K58+L58+M58+N58+O58+P58 -> 10.502504
A59: YES | B59: 6666020802 | C59: 6666020802 Equipment rental cost | D59: * CS_Fix Cost | E59: 10.7325 | F59: 10.758 | G59: 11.30733 | H59: 12.41071 | I59: 14.82192 | J59: 12.91982 | K59: 12.41264 | L59: 12.783 | M59: 12.783 | N59: 12.783 | O59: 12.783 | P59: 14.283 | Q59: =F59+E59+G59+H59+I59+J59+K59+L59+M59+N59+O59+P59 -> 150.77792
A60: YES | B60: 6666020803 | C60: 6666020803 Car rental cost | D60: * CS_Fix Cost | E60: 5.39995 | F60: 3.14635 | G60: 2.73879 | H60: 3.55751 | I60: 2.84186 | J60: 2.82137 | K60: 2.78333 | L60: 3.5373262 | M60: 3.5092522 | N60: 3.4488965 | O60: 3.3895789 | P60: 3.3312815 | Q60: =F60+E60+G60+H60+I60+J60+K60+L60+M60+N60+O60+P60 -> 40.505495
A61: YES | B61: 6666021100 | C61: 6666021100 Consulting fees | D61: * CS_Fix Cost | E61: 7.28324 | F61: 5.88308 | G61: 5.81703 | H61: -4.44739 | I61: 7.32294 | J61: 7.32201 | K61: 3.18081 | L61: 5.3509667 | M61: 5.3084987 | N61: 5.2171977 | O61: 5.1274671 | P61: 5.0392797 | Q61: =F61+E61+G61+H61+I61+J61+K61+L61+M61+N61+O61+P61 -> 58.40513
A62: YES | B62: 6666021104 | C62: 6666021104 Consulting expense-Technical | D62: * CS_Fix Cost | E62: 0 | F62: 0 | G62: 0 | H62: 0 | I62: 0 | J62: 0 | K62: 0 | L62: 0 | M62: 0 | N62: 0 | O62: 0 | P62: 0 | Q62: =F62+E62+G62+H62+I62+J62+K62+L62+M62+N62+O62+P62 -> 0
A63: YES | B63: 6666021200 | C63: 6666021200 Audit fee | D63: * CS_Fix Cost | E63: 0 | F63: 0 | G63: 0 | H63: 0 | I63: 0 | J63: 0 | K63: 0 | L63: 0 | M63: 0 | N63: 0 | O63: 0 | P63: 0 | Q63: =F63+E63+G63+H63+I63+J63+K63+L63+M63+N63+O63+P63 -> 0
A64: YES | B64: 6666021902 | C64: 6666021902 Cleaning fees | D64: * CS_Fix Cost | E64: 6.57244 | F64: 9.0083 | G64: 4.92773 | H64: 6.95777 | I64: 6.1241 | J64: 9.34958 | K64: 5.77202 | L64: 7.4043459 | M64: 7.3455812 | N64: 7.2192444 | O64: 7.0950805 | P64: 6.9730521 | Q64: =F64+E64+G64+H64+I64+J64+K64+L64+M64+N64+O64+P64 -> 84.749244
A65: YES | B65: 6666022100 | C65: 6666022100 Security | D65: * CS_Fix Cost | E65: 1.4246 | F65: 1.23972 | G65: 1.19478 | H65: 1.38688 | I65: 1.68529 | J65: 1.47789 | K65: 1.26879 | L65: 1.3712461 | M65: 1.3603632 | N65: 1.3369663 | O65: 1.3139718 | P65: 1.2913727 | Q65: =F65+E65+G65+H65+I65+J65+K65+L65+M65+N65+O65+P65 -> 16.35187
A66: YES | B66: 6666022300 | C66: 6666022300 Association dues | D66: * CS_Fix Cost | E66: 0 | F66: 0 | G66: 0 | H66: 0 | I66: 0 | J66: 0 | K66: 0 | L66: 0 | M66: 0 | N66: 0 | O66: 0 | P66: 0 | Q66: =F66+E66+G66+H66+I66+J66+K66+L66+M66+N66+O66+P66 -> 0
A67: YES | B67: 6666029700 | C67: 6666029700 Service fee recharge | D67: * CS_Fix Cost | E67: 0 | F67: 0 | G67: 0 | H67: 0 | I67: 0 | J67: 0 | K67: 0 | L67: 0 | M67: 0 | N67: 0 | O67: 0 | P67: 0 | Q67: =F67+E67+G67+H67+I67+J67+K67+L67+M67+N67+O67+P67 -> 0
A68: YES | B68: 6666029900 | C68: 6666029900 Sundry Expenses | D68: * CS_Fix Cost | E68: 0 | F68: 0.00778 | G68: 0 | H68: -0.0167 | I68: 0 | J68: 0 | K68: 5e-05 | L68: 0 | M68: 0 | N68: 0 | O68: 0 | P68: 0 | Q68: =F68+E68+G68+H68+I68+J68+K68+L68+M68+N68+O68+P68 -> -0.00887
A69: YES | B69: 6666029996 | C69: 6666029996 Non-deductible expense-travel. | D69: * CS_Fix Cost | E69: 0.0279 | F69: -0.02736 | G69: 0.03701 | H69: 0.00719 | I69: 0.01927 | J69: 0.03526 | K69: -0.05393 | L69: 0 | M69: 0 | N69: 0 | O69: 0 | P69: 0 | Q69: =F69+E69+G69+H69+I69+J69+K69+L69+M69+N69+O69+P69 -> 0.04534
A70: YES | B70: 6666029997 | C70: 6666029997 restructure cost | D70: * CS_Fix Cost | E70: 7.89403 | F70: -2.12126 | G70: 0 | H70: 0 | I70: 0 | J70: 0.26268 | K70: 0 | L70: 0.55414217 | M70: 0.54974421 | N70: 0.54028915 | O70: 0.53099671 | P70: 2.0035525 | Q70: =F70+E70+G70+H70+I70+J70+K70+L70+M70+N70+O70+P70 -> 10.214175
... A81: YES | B81: 6666021300 | C81: 6666021300 Legal fees | D81: * CS_Fix Cost | E81: 0 | F81: 0 | G81: 0 | H81: 0 | I81: 0 | J81: 0 | K81: 0.04081 | L81: 0 | M81: 0 | N81: 0 | O81: 0 | P81: 0 | Q81: =F81+E81+G81+H81+I81+J81+K81+L81+M81+N81+O81+P81 -> 0.04081
B82: FIX | C82: * CS_Fix Cost | E82: =SUM(E29:E79) -> 59.69145 | F82: =SUM(F29:F79) -> 49.31798 | G82: =SUM(G29:G79) -> 63.81704 | H82: =SUM(H29:H77) -> -0.03728 | I82: =SUM(I29:I77) -> 39.34302 | J82: =SUM(J29:J77) -> 53.66785 | K82: =SUM(K29:K81) -> 28.08369 | L82: =SUM(L29:L77) -> 52.334112 | M82: =SUM(M29:M77) -> 52.032119 | N82: =SUM(N29:N77) -> 59.213871 | O82: =SUM(O29:O77) -> 58.57579 | P82: =SUM(P29:P77) -> 60.930371 | Q82: =SUM(Q29:Q79) -> 575.62074
A83: YES | B83: 6666110203 | C83: 6666110203 Low value consumables | D83: * CS_Variable Cost | E83: 12.32638 | F83: 10.97019 | G83: 8.72217 | H83: 38.19678 | I83: 14.04682 | J83: 28.88567 | K83: 20.68405 | L83: 12.7328 | M83: 17.57024 | N83: 15.98976 | O83: 16.61952 | P83: 13.5008 | Q83: =F83+E83+G83+H83+I83+J83+K83+L83+M83+N83+O83+P83 -> 210.24518
A84: YES | B84: 5102040000 | C84: 5102040000 Other Revenue - Other | D84: * CS_Variable Cost | E84: -0.0002 | F84: -0.0008 | G84: 0 | H84: 0 | I84: 0 | J84: 0 | K84: 0 | L84: 0 | M84: 0 | N84: 0 | O84: 0 | P84: 0 | Q84: =F84+E84+G84+H84+I84+J84+K84+L84+M84+N84+O84+P84 -> -0.001
A85: NO | B85: 6666050307 | C85: 6666050307 Inventory count different-raw material | D85: * CS_Variable Cost | E85: -2.73228 | F85: -0.22595 | G85: -0.55567 | H85: 65.57718 | I85: 9.69518 | J85: -8.28034 | K85: -386.60405 | L85: 0 | M85: 0 | N85: 0 | O85: 0 | P85: 0 | Q85: =F85+E85+G85+H85+I85+J85+K85+L85+M85+N85+O85+P85 -> -323.12593
A86: NO | B86: 6666050312 | C86: 6666050312 Inventory count different- Semifinished | D86: * CS_Fix Cost | E86: 0 | F86: 0.07193 | G86: 0 | H86: 0 | I86: 0.36687 | J86: -0.63408 | K86: -4.53456 | L86: 0 | M86: 0 | N86: 0 | O86: 0 | P86: 0 | Q86: =F86+E86+G86+H86+I86+J86+K86+L86+M86+N86+O86+P86 -> -4.72984
B87: VAR | C87: * CS_Variable Cost | E87: =SUM(E83:E86) -> 9.5939 | F87: =SUM(F83:F86) -> 10.81537 | G87: =SUM(G83:G86) -> 8.1665 | H87: =SUM(H83:H86) -> 103.77396 | I87: =SUM(I83:I86) -> 24.10887 | J87: =SUM(J83:J86) -> 19.97125 | K87: =SUM(K83:K86) -> -370.45456 | L87: =SUM(L83:L86) -> 12.7328 | ... Q87: =SUM(Q83:Q86) -> -117.61159
A88: NO | B88: 6666100203 | C88: 6666100203 Provision for inventory devaluation - RM | D88: * CS_Obsolescence | E88: -26.06806 | F88: 5.09381 | G88: 200.17383 | H88: -177.1679 | I88: 46.022 | J88: -30.71528 | K88: 195.82189 | L88: 8.1849932 | M88: 8.120033 | N88: 7.9803764 | O88: 7.8431217 | P88: 7.7082278 | Q88: =F88+E88+G88+H88+I88+J88+K88+L88+M88+N88+O88+P88 -> 252.99704
B89: FIX | C89: * CS_Obsolescence | E89: =+E88 -> -26.06806 | F89: =+F88 -> 5.09381 | G89: =+G88 -> 200.17383 | H89: =+H88 -> -177.1679 | I89: =+I88 -> 46.022 | J89: =+J88 -> -30.71528 | K89: =+K88 -> 195.82189 | L89: =+L88 -> 8.1849932 | ... Q89: =+Q88 -> 252.99704
A90: NO | B90: 5301070000 | C90: 5301070000 Non-operation revenue-sales of scrapped | D90: * CS_Reselling | E90: -56.35548 | F90: -55.94882 | G90: -30.36642 | H90: -53.89348 | I90: -36.10485 | J90: -74.14161 | K90: -57.11693 | L90: -38.65851 | M90: -53.347193 | N90: -48.635137 | O90: -50.750044 | P90: -41.118432 | Q90: =F90+E90+G90+H90+I90+J90+K90+L90+M90+N90+O90+P90 -> -596.43691
B91: VAR | C91: * CS_Reselling | E91: =+E90 -> -56.35548 | F91: =+F90 -> -55.94882 | G91: =+G90 -> -30.36642 | H91: =+H90 -> -53.89348 | I91: =+I90 -> -36.10485 | J91: =+J90 -> -74.14161 | K91: =+K90 -> -57.11693 | L91: =+L90 -> -38.65851 | ... Q91: =+Q90 -> -596.43691
A92: YES | B92: 6666021602 | C92: 6666021602 Electricity | D92: * CS_Fix Utilities | E92: 4.28404 | F92: 4.07771 | G92: 3.54227 | H92: 3.80533 | I92: 1.46038 | J92: 2.00758 | K92: 0.55367 | L92: 5.0557236 | M92: 6.9785247 | N92: 6.3638679 | O92: 6.6425977 | P92: 5.4254565 | Q92: =F92+E92+G92+H92+I92+J92+K92+L92+M92+N92+O92+P92 -> 50.19715 | S92: 1000
A93: YES | B93: 6666021604 | C93: 6666021604 Oil & Gas man. Adj in Reporting | D93: * CS_Fix Utilities | J93: 0.11666099 | L93: 0.119333 | M93: 0.12094673 | N93: 0.54621763 | O93: 0.57014131 | P93: 0.47080134 | Q93: =F93+E93+G93+H93+I93+J93+K93+L93+M93+N93+O93+P93 -> 1.944101
B94: FIX | C94: * CS_Fix Utilities | E94: =SUM(E92:E93) -> 4.28404 | F94: =+SUM(F92:F93) -> 4.07771 | G94: =+SUM(G92:G93) -> 3.54227 | H94: =+SUM(H92:H93) -> 3.80533 | I94: =+SUM(I92:I93) -> 1.46038 | J94: =+SUM(J92:J93) -> 2.124241 | K94: =+SUM(K92:K93) -> 0.55367 | L94: =+SUM(L92:L93) -> 5.1750566 | M94: =+SUM(M92:M93) -> 7.0994714 | ... P94: =+SUM(P92:P93) -> 5.8962578 | Q94: =SUM(Q92:Q93) -> 52.141251
A95: YES | B95: 6666021600 | C95: 6666021600 Energy and power cost | D95: * CS_Variable Utilities | E95: 21.92376 | F95: 11.02913 | G95: 17.90784 | H95: 24.97601 | I95: 26.9343 | J95: 25.31079 | K95: 38.03884 | L95: 31.521011 | M95: 30.869231 | N95: 27.558775 | O95: 31.636832 | P95: 26.153177 | Q95: =F95+E95+G95+H95+I95+J95+K95+L95+M95+N95+O95+P95 -> 313.8597
A96: YES | B96: 6666021603 | C96: 6666021603 Water | D96: * CS_Variable Utilities | E96: 0.34576 | F96: 0.03003 | G96: 0.47697 | H96: 0.84538 | I96: 0.257 | J96: 0.57311 | K96: 0.61328 | L96: 0.96997018 | M96: 1.3388708 | N96: 1.2209453 | O96: 1.2744213 | P96: 1.0409056 | Q96: =F96+E96+G96+H96+I96+J96+K96+L96+M96+N96+O96+P96 -> 8.9866432
A97: YES | B97: 6666021604 | C97: 6666021604 Oil & Gas | D97: * CS_Variable Utilities | E97: 3.07265 | F97: 5.08638 | G97: 3.36814 | H97: 2.24703 | I97: 4.44632 | J97: 2.77675 | K97: 2.67599 | L97: 2.5122738 | M97: 5.0089662 | N97: 4.919153 | O97: 5.5013635 | P97: 4.4933337 | Q97: =F97+E97+G97+H97+I97+J97+K97+L97+M97+N97+O97+P97 -> 46.10835
A98: YES | B98: 6666021604 | C98: 6666021604 Oil & Gas man. Adj in Reporting | D98: * CS_Variable Utilities | Q98: =F98+E98+G98+H98+I98+J98+K98+L98+M98+N98+O98+P98 -> 0
B99: VAR | C99: * CS_Variable Utilities | E99: =SUM(E95:E98) -> 25.34217 | F99: =SUM(F95:F98) -> 16.14554 | G99: =SUM(G95:G98) -> 21.75295 | H99: =SUM(H95:H98) -> 28.06842 | I99: =SUM(I95:I98) -> 31.63762 | J99: =SUM(J95:J98) -> 28.66065 | K99: =SUM(K95:K98) -> 41.32811 | L99: =SUM(L95:L98) -> 35.003255 | ... Q99: =SUM(Q95:Q98) -> 368.95469
A100: YES | B100: 5001010206 | C100: 5001010206 Unemployment Insurance -blue collar-Indi | D100: * CS_Indirect Labour | E100: 3.05709 | F100: 2.68224 | G100: 3.30962 | H100: 3.2495801 | I100: 3.7782806 | J100: 3.56773 | K100: 3.28563 | L100: 0 | M100: 0 | N100: 0 | O100: 0 | P100: 0 | Q100: =F100+E100+G100+H100+I100+J100+K100+L100+M100+N100+O100+P100 -> 22.930171
A101: YES | B101: 6666010184 | C101: 6666010184 Salary&Additional Incentive-Blue Collar- | D101: * CS_Indirect Labour | E101: -0.14232 | F101: -0.13591 | G101: 0.01208 | H101: -0.10463 | I101: -1.56492 | J101: -0.69547 | K101: -0.89861 | L101: 0 | M101: 0 | N101: 0 | O101: 0 | P101: 0 | Q101: =F101+E101+G101+H101+I101+J101+K101+L101+M101+N101+O101+P101 -> -3.52978
A102: YES | B102: 6666010186 | C102: 6666010186 Overtime-Blue Collar-Indirect | D102: * CS_Indirect Labour | E102: 8.76637 | F102: 8.37007 | G102: -6.12628 | H102: 17.143771 | I102: 18.064008 | J102: 12.83036 | K102: 14.78249 | L102: 0 | M102: 0 | N102: 0 | O102: 0 | P102: 0 | Q102: =F102+E102+G102+H102+I102+J102+K102+L102+M102+N102+O102+P102 -> 73.830789
A103: YES | B103: 6666010189 | C103: 6666010189 Salary - Blue collar indirect employees | D103: * CS_Indirect Labour | E103: 27.21355 | F103: -104.27378 | G103: 109.07513 | H103: 1.04208 | I103: 2.1359 | J103: 0 | K103: 8.91 | L103: 0 | M103: 0 | N103: 0 | O103: 0 | P103: 0 | Q103: =F103+E103+G103+H103+I103+J103+K103+L103+M103+N103+O103+P103 -> 44.10288
A104: YES | B104: 6666010012 | C104: 6666010012 Payroll Taxes- Blue Collar Indirect | D104: * CS_Indirect Labour | E104: 28.9222 | F104: 25.55674 | G104: 29.55152 | H104: 29.028355 | I104: 34.040846 | J104: 31.74679 | K104: 29.39389 | L104: 0 | M104: 0 | N104: 0 | O104: 0 | P104: 0 | Q104: =F104+E104+G104+H104+I104+J104+K104+L104+M104+N104+O104+P104 -> 208.24034
A105: YES | B105: 6666010226 | C105: 6666010226 Staff Leaving Indemnity - Blue Collar In | D105: * CS_Indirect Labour | E105: 6.0301 | F105: 33.01952 | G105: -105.66898 | H105: 4.86469 | I105: 5.0691 | J105: 5.09175 | K105: 5.75958 | L105: 0 | M105: 0 | N105: 0 | O105: 0 | P105: 0 | Q105: =F105+E105+G105+H105+I105+J105+K105+L105+M105+N105+O105+P105 -> -45.83424
A106: YES | B106: 6666010102 | C106: 6666010102 Salary-Blue collar indirect employees- A | D106: * CS_Indirect Labour | E106: 162.67013 | F106: 245.11158 | G106: 159.33491 | H106: 156.69616 | I106: 186.2574 | J106: 176.69946 | K106: 164.56026 | L106: 248.2904 | M106: 233.8345 | N106: 218.04244 | O106: 213.64209 | P106: 280.51507 | Q106: =F106+E106+G106+H106+I106+J106+K106+L106+M106+N106+O106+P106 -> 2445.6544
B107: FIX | C107: * CS_Indirect Labour | E107: =SUM(E100:E106) -> 236.51712 | F107: =SUM(F100:F106) -> 210.33046 | G107: =SUM(G100:G106) -> 189.488 | H107: =SUM(H100:H106) -> 211.92001 | I107: =SUM(I100:I106) -> 247.78062 | J107: =SUM(J100:J106) -> 229.24062 | K107: =SUM(K100:K106) -> 225.79324 | L107: =SUM(L100:L106) -> 248.2904 | ... Q107: =SUM(Q100:Q106) -> 2745.3946
A108: YES | B108: 6666010196 | C108: 6666010196 Payroll Taxes-White Collar Employee | D108: * CS_Fixed Labour | E108: 15.8207 | F108: 13.14188 | G108: 15.49907 | H108: 14.48231 | I108: 15.51537 | J108: 15.13705 | K108: 13.98525 | L108: 0 | M108: 0 | N108: 0 | O108: 0 | P108: 0 | Q108: =F108+E108+G108+H108+I108+J108+K108+L108+M108+N108+O108+P108 -> 103.58163
A109: YES | B109: 6666010101 | C109: 6666010101 Salary - White collar employees | D109: * CS_Fixed Labour | E109: 83.51397 | F109: 89.32124 | G109: 80.79151 | H109: 106.71127 | I109: 102.21272 | J109: 87.00453 | K109: 80.02992 | L109: 102.13247 | M109: 107.52926 | N109: 101.02732 | O109: 99.707366 | P109: 98.421458 | Q109: =F109+E109+G109+H109+I109+J109+K109+L109+M109+N109+O109+P109 -> 1138.403
A110: YES | B110: 6666010199 | C110: 6666010199 Salary-White collar employees -Accrued | D110: * CS_Fixed Labour | E110: 13.11897 | F110: 6.13721 | G110: 5.34848 | H110: -37.71393 | I110: -12.53495 | J110: 6.61315 | K110: 6.53771 | L110: 0 | M110: 0 | N110: 0 | O110: 0 | P110: 0 | Q110: =F110+E110+G110+H110+I110+J110+K110+L110+M110+N110+O110+P110 -> -12.49336
A111: YES | B111: 6666010185 | C111: 6666010185 Salary&Additional Incentive-White Collar | D111: * CS_Fixed Labour | E111: -0.18544 | F111: -0.04739 | G111: 0 | H111: 0 | I111: -0.62646 | J111: -0.13696 | K111: -0.30538 | L111: 0 | M111: 0 | N111: 0 | O111: 0 | P111: 0 | Q111: =F111+E111+G111+H111+I111+J111+K111+L111+M111+N111+O111+P111 -> -1.30163
A112: YES | B112: 6666010207 | C112: 6666010207 Unemployment insurance companies to pay | D112: * CS_Fixed Labour | E112: 1.1587 | F112: 1.05736 | G112: 1.20639 | H112: 1.11995 | I112: 1.21575 | J112: 1.18697 | K112: 1.0785 | L112: 0 | M112: 0 | N112: 0 | O112: 0 | P112: 0 | Q112: =F112+E112+G112+H112+I112+J112+K112+L112+M112+N112+O112+P112 -> 8.02362
A113: YES | B113: 5102040406 | C113: 5102040406 Other revenue-Service/Secondment agreeme | D113: * CS_Direct Labour | E113: 0 | F113: 0 | G113: 0 | H113: 0 | I113: 0 | J113: 0 | K113: 0 | L113: 0 | M113: 0 | N113: 0 | O113: 0 | P113: 0 | Q113: =F113+E113+G113+H113+I113+J113+K113+L113+M113+N113+O113+P113 -> 0
A114: YES | B114: 6666010227 | C114: 6666010227 Staff Leaving Indemnity - White collar E | D114: * CS_Fixed Labour | E114: 1.74299 | F114: 1.44223 | G114: 1.59288 | H114: 1.66464 | I114: 1.7888 | J114: 1.79589 | K114: 1.8277 | L114: 0 | M114: 0 | N114: 0 | O114: 0 | P114: 0 | Q114: =F114+E114+G114+H114+I114+J114+K114+L114+M114+N114+O114+P114 -> 11.85513
B115: FIX | C115: * CS_Fixed Labour | E115: =SUM(E108:E114) -> 115.16989 | F115: =SUM(F108:F114) -> 111.05253 | G115: =SUM(G108:G114) -> 104.43833 | H115: =SUM(H108:H114) -> 86.26424 | I115: =SUM(I108:I114) -> 107.57123 | J115: =SUM(J108:J114) -> 111.60063 | K115: =SUM(K108:K114) -> 103.1537 | L115: =SUM(L108:L114) -> 102.13247 | ... Q115: =SUM(Q108:Q114) -> 1248.0684
A116: YES | B116: 6666020903 | C116: 6666020903 Other materials | D116: * CS_Semifix | E116: 0 | F116: 0 | G116: 0 | H116: 0 | I116: 0 | J116: 0 | K116: 0 | L116: 0 | M116: 0 | N116: 0 | O116: 0 | P116: 0 | Q116: =F116+E116+G116+H116+I116+J116+K116+L116+M116+N116+O116+P116 -> 0
A117: YES | B117: 6666010302 | C117: 6666010302 Medical expenses | D117: * CS_Semifix | E117: 4.80178 | F117: 4.71224 | G117: 4.624 | H117: -9.44158 | I117: -1.00414 | J117: 3.06121 | K117: 1.78803 | L117: 4.3524556 | M117: 4.3179123 | N117: 4.2436484 | O117: 4.1706619 | P117: 4.0989306 | Q117: =F117+E117+G117+H117+I117+J117+K117+L117+M117+N117+O117+P117 -> 29.725149
A118: YES | B118: 6666010314 | C118: 6666010314 Work uniforms | D118: * CS_Semifix | E118: 5.27735 | F118: 50.44541 | G118: 0.11913 | H118: 0.35103 | I118: 6.25963 | J118: 0 | K118: -0.96969 | L118: 1.5285849 | M118: 1.5045799 | N118: 1.4813172 | O118: 1.4595548 | P118: 1.4384226 | Q118: =F118+E118+G118+H118+I118+J118+K118+L118+M118+N118+O118+P118 -> 68.895319
A119: YES | B119: 6666010315 | C119: 6666010315 Social Aids | D119: * CS_Semifix | E119: 11.72316 | F119: 69.53264 | G119: 2.10075 | H119: 0.62074 | I119: 4.73636 | J119: 0.03505 | K119: 0 | L119: 10.711192 | M119: 10.626182 | N119: 10.541847 | O119: 10.360538 | P119: 10.182347 | Q119: =F119+E119+G119+H119+I119+J119+K119+L119+M119+N119+O119+P119 -> 141.17081
A120: YES | B120: 6666020401 | C120: 6666020401 local transportation - bus and taxi | D120: * CS_Semifix | E120: 31.34574 | F120: 36.94771 | G120: 25.87161 | H120: 40.55119 | I120: 35.94637 | J120: 38.19261 | K120: 37.50955 | L120: 35.52715 | M120: 80.694739 | N120: 37.832307 | O120: 39.559617 | P120: 31.440277 | Q120: =F120+E120+G120+H120+I120+J120+K120+L120+M120+N120+O120+P120 -> 471.41887
A121: YES | B121: 6666020402 | C121: 6666020402 Local transportation-transport subsidies | D121: * CS_Semifix | E121: 0 | F121: 0 | G121: 0 | H121: 0 | I121: 0 | J121: 0 | K121: 0 | L121: 0 | M121: 0 | N121: 0 | O121: 0 | P121: 0 | Q121: =F121+E121+G121+H121+I121+J121+K121+L121+M121+N121+O121+P121 -> 0
A122: YES | B122: 6666020502 | C122: 6666020502 Working meals | D122: * CS_Semifix | E122: 22.04347 | F122: 33.45617 | G122: 17.30111 | H122: 42.3881 | I122: 35.37475 | J122: 37.6714 | K122: 34.57257 | L122: 33.804386 | M122: 34.832862 | N122: 31.271858 | O122: 32.317986 | P122: 26.235267 | Q122: =F122+E122+G122+H122+I122+J122+K122+L122+M122+N122+O122+P122 -> 381.26993
A123: YES | B123: 6666020503 | C123: 6666020503 Office supplies | D123: * CS_Semifix | E123: 0.4098 | F123: 0.40442 | G123: 0 | H123: 0.87888 | I123: 0.37705 | J123: 0.42842 | K123: 0.24865 | L123: 1.6121534 | M123: 1.5993585 | N123: 1.5718511 | O123: 1.5448168 | P123: 1.5182475 | Q123: =F123+E123+G123+H123+I123+J123+K123+L123+M123+N123+O123+P123 -> 10.593647
...

Sheet 1+11 Renta DW _2026
B1: Renta DW Cost Evolution | D1: Volume | E1: 47357 | F1: 42000.001 | G1: 23500.001 | H1: 38000.001 | I1: 33000.001 | J1: 52500.001 | K1: 40672 | L1: 39704 | M1: 54907 | N1: 49968 | O1: 51936 | P1: 42190 | Q1: =+E1+F1+G1+H1+I1+J1+K1+L1+M1+N1+O1+P1 -> 515734.01
D2: FX Rates_HQE | E2: 50.75 | F2: 52.47 | G2: 53.1 | H2: 54.2 | I2: 55.3 | J2: 56.4 | K2: 57.2 | L2: 58 | M2: 58.8 | N2: 59.77 | O2: 60.74 | P2: 61.71
D3: FX Rates_weighted average (Act TL/Act EUR) | E3: =+E239 -> 55.144677 | F3: =+F239 -> 49.764623 | G3: =+G239 -> 48.288145 | H3: =+H239 -> 0 | I3: =+I239 -> 0 | J3: =+J239 -> 0 | K3: =+K239 -> 0 | L3: =+L239 -> 0 | ... Q3: =+Q239 -> 0
A5: HQD PERIMETER | E5: Jan K€ | F5: Feb K€ | G5: Mar K€ | H5: Apr K€ | I5: May K€ | J5: June K€ | K5: July K€ | L5: Aug K€ | M5: Sep K€ | N5: Oct K€ | O5: Nov K€ | P5: DEC K€ | Q5: YTD K€
A6: YES | B6: 6666110101 | C6: 6666110101 Depreciation of buildings | D6: * CS_Depreciation | E6: 9.5887601 | F6: 515.61681 | G6: 558.872 | H6: 545.80149 | I6: 556.90639 | J6: 546.48697 | K6: 575.81023 | L6: 575.98362 | M6: 562.53212 | N6: 577.53857 | O6: 567.49077 | P6: 589.55127 | Q6: =F6+E6+G6+H6+I6+J6+K6+L6+M6+N6+O6+P6 -> 6182.179
A7: YES | B7: 6666110106 | C7: 6666110106 Depreciation of R&D facilities | D7: * CS_Depreciation | E7: 0 | F7: 0 | G7: 0 | H7: 0 | I7: 0 | J7: 0 | K7: 0 | L7: 0 | M7: 0 | N7: 0 | O7: 0 | P7: 0 | Q7: =F7+E7+G7+H7+I7+J7+K7+L7+M7+N7+O7+P7 -> 0
A8: YES | B8: 6666110107 | C8: 6666110107 Depreciation of mold | D8: * CS_Depreciation | E8: 92.462416 | F8: -128.50944 | G8: -132.59646 | H8: -133.13995 | I8: -136.89071 | J8: -137.10294 | K8: -140.22303 | L8: -141.55231 | M8: -141.04043 | N8: -144.04446 | O8: -143.38387 | P8: -146.35032 | Q8: =F8+E8+G8+H8+I8+J8+K8+L8+M8+N8+O8+P8 -> -1432.3715
A9: YES | B9: 6666110110 | C9: 6666110110 Depreciation-Plant & Machinery | D9: * CS_Depreciation | E9: 63.749081 | F9: -231.74042 | G9: -259.88325 | H9: -251.50839 | I9: -259.51547 | J9: -251.33834 | K9: -259.08195 | L9: -258.72828 | M9: -250.19728 | N9: -259.46435 | O9: -251.88662 | P9: -261.15815 | Q9: =F9+E9+G9+H9+I9+J9+K9+L9+M9+N9+O9+P9 -> -2730.7534
A10: YES | B10: 6666110112 | C10: 6666110112 Depreciation of Furniture & Fixture | D10: * CS_Depreciation | E10: 4.2473878 | F10: -4.4504975 | G10: -4.7228927 | H10: -4.7190566 | I10: -3.5097491 | J10: -3.7738651 | K10: -3.8043345 | L10: -3.8799128 | M10: -3.8599245 | N10: -3.9632234 | O10: -3.9341218 | P10: -3.7400681 | Q10: =F10+E10+G10+H10+I10+J10+K10+L10+M10+N10+O10+P10 -> -40.110258
A11: YES | B11: 6666110204 | C11: 6666110204 Amortization of license, trademarks and | D11: * CS_Depreciation | E11: 0.17412081 | F11: -0.081380077 | G11: -0.079585154 | H11: -0.083786041 | I11: -0.087625725 | J11: -0.091313308 | K11: -0.093885298 | L11: -0.096366508 | M11: -0.098790682 | N11: -0.10104916 | O11: -0.10323224 | P11: -0.10537272 | Q11: =F11+E11+G11+H11+I11+J11+K11+L11+M11+N11+O11+P11 -> -0.84826609
A12: YES | B12: 6666110207 | C12: 6666110207 Amortization of Software | D12: * CS_Depreciation | E12: 1.1264639 | F12: -1.2419814 | G12: -1.2311387 | H12: -1.2580058 | I12: -1.2832001 | J12: -1.3067368 | K12: -1.3236228 | L12: -1.438198 | M12: -1.0452677 | N12: -1.219569 | O12: -1.265389 | P12: -1.274676 | Q12: =F12+E12+G12+H12+I12+J12+K12+L12+M12+N12+O12+P12 -> -12.761322
A13: YES | B13: 6666110506 | C13: 6666110506 Amortization-Leasehold Improvement | D13: * CS_Depreciation | E13: 0 | F13: 0 | G13: 0 | H13: 0 | I13: 0 | J13: 0 | K13: 0 | L13: 0 | M13: 0 | N13: 0 | O13: 0 | P13: 0 | Q13: =F13+E13+G13+H13+I13+J13+K13+L13+M13+N13+O13+P13 -> 0
B14: FIX | C14: * CS_Depreciation | E14: =SUM(E6:E13) -> 171.34823 | F14: =SUM(F6:F13) -> 149.59309 | G14: =SUM(G6:G13) -> 160.35867 | H14: =SUM(H6:H13) -> 155.0923 | I14: =SUM(I6:I13) -> 155.61965 | J14: =SUM(J6:J13) -> 152.87378 | K14: =SUM(K6:K13) -> 171.28341 | L14: =SUM(L6:L13) -> 170.28855 | ... Q14: =SUM(Q6:Q13) -> 1965.3342
A15: YES | B15: 5001010205 | C15: 5001010205 Unemployment Insurance -blue collar-Dire | D15: * CS_Direct Labour | E15: 7.61607 | F15: 0 | G15: 0 | H15: 0 | I15: 0 | J15: 0 | K15: 0 | L15: 0 | M15: 0 | N15: 0 | O15: 0 | P15: 0 | Q15: =F15+E15+G15+H15+I15+J15+K15+L15+M15+N15+O15+P15 -> 7.61607
A16: YES | B16: 6666010380 | C16: 6666010380 Incentive | D16: * CS_Direct Labour | E16: -1.8209 | F16: 0 | G16: 0 | H16: 0 | I16: 0 | J16: 0 | K16: 0 | L16: 0 | M16: 0 | N16: 0 | O16: 0 | P16: 0 | Q16: =F16+E16+G16+H16+I16+J16+K16+L16+M16+N16+O16+P16 -> -1.8209
A17: YES | B17: 6666010019 | C17: 6666010019 Payroll Taxes - Blue Collar Direct | D17: * CS_Direct Labour | E17: 64.67305 | F17: 483.16754 | G17: 486.95672 | H17: 464.96081 | I17: 528.14055 | J17: 497.00351 | K17: 446.30187 | L17: 457.45748 | M17: 552.86256 | N17: 505.68643 | O17: 482.52377 | P17: 489.09036 | Q17: =F17+E17+G17+H17+I17+J17+K17+L17+M17+N17+O17+P17 -> 5458.8246
A18: YES | B18: 6666010183 | C18: 6666010183 Overtime-Blue Collar-Direct | D18: * CS_Direct Labour | E18: 10.50135 | F18: 0 | G18: 0 | H18: 0 | I18: 0 | J18: 0 | K18: 0 | L18: 0 | M18: 0 | N18: 0 | O18: 0 | P18: 0 | Q18: =F18+E18+G18+H18+I18+J18+K18+L18+M18+N18+O18+P18 -> 10.50135
A19: YES | B19: 6666010229 | C19: 6666010229 Staff Leaving Indemnity - Blue Collar Di | D19: * CS_Direct Labour | E19: 16.69101 | F19: 0 | G19: 0 | H19: 0 | I19: 0 | J19: 0 | K19: 0 | L19: 0 | M19: 0 | N19: 0 | O19: 0 | P19: 0 | Q19: =F19+E19+G19+H19+I19+J19+K19+L19+M19+N19+O19+P19 -> 16.69101
A20: YES | B20: 6666010188 | C20: 6666010188 Salary - Blue collar direct employees | D20: * CS_Direct Labour | E20: 357.71936 | F20: 0 | G20: 0 | H20: 0 | I20: 0 | J20: 0 | K20: 0 | L20: 0 | M20: 0 | N20: 0 | O20: 0 | P20: 0 | Q20: =F20+E20+G20+H20+I20+J20+K20+L20+M20+N20+O20+P20 -> 357.71936
A21: YES | B21: 5102040406 | C21: 5102040406 Other revenue-Service/Secondment agreeme | D21: * CS_Direct Labour | E21: 0 | F21: 0 | G21: 0 | H21: 0 | I21: 0 | J21: 0 | K21: 0 | L21: 0 | M21: 0 | N21: 0 | O21: 0 | P21: 0 | Q21: =F21+E21+G21+H21+I21+J21+K21+L21+M21+N21+O21+P21 -> 0
A22: YES | B22: 6666010115 | C22: 6666010115 Salary-Blue collar direct employees-Accr | D22: * CS_Direct Labour | E22: -4.2657 | F22: 0 | G22: 0 | H22: 0 | I22: 0 | J22: 0 | K22: 0 | L22: 0 | M22: 0 | N22: 0 | O22: 0 | P22: 0 | Q22: =F22+E22+G22+H22+I22+J22+K22+L22+M22+N22+O22+P22 -> -4.2657
B23: VAR | C23: * CS_Direct Labour | E23: =SUM(E15:E22) -> 451.11424 | F23: =SUM(F15:F22) -> 483.16754 | G23: =SUM(G15:G22) -> 486.95672 | H23: =SUM(H15:H22) -> 464.96081 | I23: =SUM(I15:I22) -> 528.14055 | J23: =SUM(J15:J22) -> 497.00351 | K23: =SUM(K15:K22) -> 446.30187 | L23: =SUM(L15:L22) -> 457.45748 | ... Q23: =SUM(Q15:Q22) -> 5845.2658
A24: NO | B24: 8701530201 | C24: 8701530201 Scrap-Raw Material - Managerial | D24: * CS_SCRAP_VARIABLE | E24: 0 | F24: 0 | G24: 0 | H24: 0 | I24: 0 | J24: 0 | K24: 0 | L24: 0 | M24: 0 | N24: 0 | O24: 0 | P24: 0 | Q24: =F24+E24+G24+H24+I24+J24+K24+L24+M24+N24+O24+P24 -> 0
A25: NO | B25: 6666050309 | C25: 6666050309 SFG scrap | D25: * CS_SCRAP_VARIABLE | E25: 6.0635 | F25: 18.48 | G25: 10.34 | H25: 16.72 | I25: 14.52 | J25: 23.1 | K25: 17.89568 | L25: 17.46976 | M25: 24.15908 | N25: 21.98592 | O25: 22.85184 | P25: 18.5636 | Q25: =F25+E25+G25+H25+I25+J25+K25+L25+M25+N25+O25+P25 -> 212.14938
A26: NO | B26: 6666050308 | C26: 6666050308 Raw material scrap | D26: * CS_SCRAP_VARIABLE | E26: 11.57396 | F26: 0 | G26: 0 | H26: 0 | I26: 0 | J26: 0 | K26: 0 | L26: 0 | M26: 0 | N26: 0 | O26: 0 | P26: 0 | Q26: =F26+E26+G26+H26+I26+J26+K26+L26+M26+N26+O26+P26 -> 11.57396
A27: NO | B27: 6666050306 | C27: 6666050306 Finished goods scrap | D27: * CS_SCRAP_VARIABLE | E27: 0.58819 | F27: 0 | G27: 0 | H27: 0 | I27: 0 | J27: 0 | K27: 0 | L27: 0 | M27: 0 | N27: 0 | O27: 0 | P27: 0 | Q27: =F27+E27+G27+H27+I27+J27+K27+L27+M27+N27+O27+P27 -> 0.58819
B28: VAR | C28: * CS_SCRAP_VARIABLE | E28: =SUM(E24:E27) -> 18.22565 | F28: =SUM(F24:F27) -> 18.48 | G28: =SUM(G24:G27) -> 10.34 | H28: =SUM(H24:H27) -> 16.72 | I28: =SUM(I24:I27) -> 14.52 | J28: =SUM(J24:J27) -> 23.1 | K28: =SUM(K24:K27) -> 17.89568 | L28: =SUM(L24:L27) -> 17.46976 | ... Q28: =SUM(Q24:Q27) -> 224.31153
A29: YES | B29: 5102010151 | C29: 5102010151 Other Rev.-Interco-Epidemic problem comp | D29: * CS_Fix Cost | E29: 0 | F29: 0 | G29: 0 | H29: 0 | I29: 0 | J29: 0 | K29: 0 | L29: 0 | M29: 0 | N29: 0 | O29: 0 | P29: 0 | Q29: =F29+E29+G29+H29+I29+J29+K29+L29+M29+N29+O29+P29 -> 0
A30: YES | B30: 5001010200 | C30: 5001010200 Cost of Manufacture - Raw Material | D30: * CS_Fix Cost | E30: 0 | F30: 0 | G30: 0 | H30: 0 | I30: 0 | J30: 0 | K30: 0 | L30: 0 | M30: 0 | N30: 0 | O30: 0 | P30: 0 | Q30: =F30+E30+G30+H30+I30+J30+K30+L30+M30+N30+O30+P30 -> 0
A31: YES | B31: 5001010201 | C31: 5001010201 Cost of Manufacture - Raw Material-Freig | D31: * CS_Fix Cost | E31: 0 | F31: 0 | G31: 0 | H31: 0 | I31: 0 | J31: 0 | K31: 0 | L31: 0 | M31: 0 | N31: 0 | O31: 0 | P31: 0 | Q31: =F31+E31+G31+H31+I31+J31+K31+L31+M31+N31+O31+P31 -> 0
A32: YES | B32: 5001010204 | C32: 5001010204 Cost of Manufacture - Finished Good | D32: * CS_Fix Cost | E32: 0 | F32: 0 | G32: 0 | H32: 0 | I32: 0 | J32: 0 | K32: 0 | L32: 0 | M32: 0 | N32: 0 | O32: 0 | P32: 0
A33: YES | B33: 5207000011 | C33: 5207000011 Gain of tangible asset disposal | D33: * CS_Fix Cost | E33: 0 | F33: 0 | G33: 0 | H33: 0 | I33: 0 | J33: 0 | K33: 0 | L33: 0 | M33: 0 | N33: 0 | O33: 0 | P33: 0 | Q33: =F33+E33+G33+H33+I33+J33+K33+L33+M33+N33+O33+P33 -> 0
A34: YES | B34: 5207000012 | C34: 5207000012 Loss of tangible asset sold | D34: * CS_Fix Cost | E34: 0 | F34: 0 | G34: 0 | H34: 0 | I34: 0 | J34: 0 | K34: 0 | L34: 0 | M34: 0 | N34: 0 | O34: 0 | P34: 0 | Q34: =F34+E34+G34+H34+I34+J34+K34+L34+M34+N34+O34+P34 -> 0
A35: YES | B35: 5207000022 | C35: 5207000022 Loss of intangible asset disposal | D35: * CS_Fix Cost | E35: 0 | F35: 0 | G35: 0 | H35: 0 | I35: 0 | J35: 0 | K35: 0 | L35: 0 | M35: 0 | N35: 0 | O35: 0 | P35: 0 | Q35: =F35+E35+G35+H35+I35+J35+K35+L35+M35+N35+O35+P35 -> 0
A36: YES | B36: 5301060000 | C36: 5301060000 Other Income-Subsidy income | D36: * CS_Fix Cost | E36: 0 | F36: 0 | G36: 0 | H36: 0 | I36: 0 | J36: 0 | K36: 0 | L36: 0 | M36: 0 | N36: 0 | O36: 0 | P36: 0 | Q36: =F36+E36+G36+H36+I36+J36+K36+L36+M36+N36+O36+P36 -> 0
A37: YES | B37: 5301999999 | C37: 5301999999 Non-operation revenue-Other | D37: * CS_Fix Cost | E37: 0 | F37: 0 | G37: 0 | H37: 0 | I37: 0 | J37: 0 | K37: 0 | L37: 0 | M37: 0 | N37: 0 | O37: 0 | P37: 0 | Q37: =F37+E37+G37+H37+I37+J37+K37+L37+M37+N37+O37+P37 -> 0
A38: YES | B38: 5405030000 | C38: 5405030000 Other cost-others | D38: * CS_Fix Cost | E38: 0 | F38: 0 | G38: 0 | H38: 0 | I38: 0 | J38: 0 | K38: 0 | L38: 0 | M38: 0 | N38: 0 | O38: 0 | P38: 0 | Q38: =F38+E38+G38+H38+I38+J38+K38+L38+M38+N38+O38+P38 -> 0
A39: YES | B39: 5601050000 | C39: 5601050000 Non-Operating Expense - Penalty | D39: * CS_Fix Cost | E39: 0 | F39: 0 | G39: 0 | H39: 0 | I39: 0 | J39: 0 | K39: 0 | L39: 0 | M39: 0 | N39: 0 | O39: 0 | P39: 0 | Q39: =F39+E39+G39+H39+I39+J39+K39+L39+M39+N39+O39+P39 -> 0
A40: YES | B40: 5601050100 | C40: 5601050100 Non-operation Expense-Others | D40: * CS_Fix Cost | E40: 0 | F40: 0 | G40: 0 | H40: 0 | I40: 0 | J40: 0 | K40: 0 | L40: 0 | M40: 0 | N40: 0 | O40: 0 | P40: 0 | Q40: =F40+E40+G40+H40+I40+J40+K40+L40+M40+N40+O40+P40 -> 0
A41: YES | B41: 5102040893 | C41: 5102040893 Other revenue-Charge out-Test Expense | D41: * CS_Fix Cost | E41: 0 | F41: 0 | G41: 0 | H41: 0 | I41: 0 | J41: 0 | K41: 0 | L41: 0 | M41: 0 | N41: 0 | O41: 0 | P41: 0 | Q41: =F41+E41+G41+H41+I41+J41+K41+L41+M41+N41+O41+P41 -> 0
A42: YES | B42: 5801000041 | C42: 5801000041 Previous year Sundry cost | D42: * CS_Fix Cost | E42: 0 | F42: 0 | G42: 0 | H42: 0 | I42: 0 | J42: 0 | K42: 0 | L42: 0 | M42: 0 | N42: 0 | O42: 0 | P42: 0 | Q42: =F42+E42+G42+H42+I42+J42+K42+L42+M42+N42+O42+P42 -> 0
A43: YES | B43: 6666010322 | C43: 6666010322 fuel allowance | D43: * CS_Fix Cost | E43: 1.46012 | F43: 1.9896026 | G43: 1.952505 | H43: 1.9236502 | I43: 1.8952219 | J43: 1.8672137 | K43: 1.8523945 | L43: 1.837693 | M43: 1.8231081 | N43: 1.7917525 | O43: 1.7609361 | P43: 1.7306497 | Q43: =F43+E43+G43+H43+I43+J43+K43+L43+M43+N43+O43+P43 -> 21.884847
A44: YES | B44: 6666020101 | C44: 6666020101 Entertainment | D44: * CS_Fix Cost | E44: 4.70552 | F44: 4.6177799 | G44: 4.531678 | H44: 4.4647074 | I44: 4.3987265 | J44: 4.3337207 | K44: 4.299326 | L44: 4.2652044 | M44: 4.2313536 | N44: 4.1585785 | O44: 4.087055 | P44: 4.0167617 | Q44: =F44+E44+G44+H44+I44+J44+K44+L44+M44+N44+O44+P44 -> 52.110411
... A79: YES | B79: 5401020212 | C79: 5401020212 Local Transpor | D79: * CS_Fix Cost | E79: 0 | F79: 0 | G79: 0 | H79: 0 | I79: 0 | J79: 0 | K79: 0 | L79: 0 | M79: 0 | N79: 0 | O79: 0 | P79: 0 | Q79: =F79+E79+G79+H79+I79+J79+K79+L79+M79+N79+O79+P79 -> 0
B80: FIX | C80: * CS_Fix Cost | E80: =SUM(E29:E79) -> 60.95347 | F80: =SUM(F29:F79) -> 58.597318 | G80: =SUM(G29:G79) -> 57.743077 | H80: =SUM(H29:H79) -> 57.078642 | I80: =SUM(I29:I79) -> 56.424027 | J80: =SUM(J29:J79) -> 57.279085 | K80: =SUM(K29:K79) -> 55.437847 | L80: =SUM(L29:L79) -> 55.099316 | ... Q80: =SUM(Q29:Q79) -> 676.36568
A81: YES | B81: 6666110203 | C81: 6666110203 Low value consumables | D81: * CS_Variable Cost | E81: 12.32638 | F81: 13.44 | G81: 7.5200003 | H81: 12.16 | I81: 10.56 | J81: 16.8 | K81: 13.01504 | L81: 12.70528 | M81: 17.57024 | N81: 15.98976 | O81: 16.61952 | P81: 13.5008 | Q81: =F81+E81+G81+H81+I81+J81+K81+L81+M81+N81+O81+P81 -> 162.20702
A82: YES | B82: 5102040000 | C82: 5102040000 Other Revenue - Other | D82: * CS_Variable Cost | E82: -0.0002 | F82: 0 | G82: 0 | H82: 0 | I82: 0 | J82: 0 | K82: 0 | L82: 0 | M82: 0 | N82: 0 | O82: 0 | P82: 0 | Q82: =F82+E82+G82+H82+I82+J82+K82+L82+M82+N82+O82+P82 -> -0.0002
A83: NO | B83: 6666050307 | C83: 6666050307 Inventory count different-raw material | D83: * CS_Variable Cost | E83: -2.73228 | F83: 0 | G83: 0 | H83: 0 | I83: 0 | J83: 0 | K83: 0 | L83: 0 | M83: 0 | N83: 0 | O83: 0 | P83: 0 | Q83: =F83+E83+G83+H83+I83+J83+K83+L83+M83+N83+O83+P83 -> -2.73228
A84: NO | B84: 6666050312 | C84: 6666050312 Inventory count different- Semifinished | D84: * CS_Fix Cost | E84: 0 | F84: 0 | G84: 0 | H84: 0 | I84: 0 | J84: 0 | K84: 0 | L84: 0 | M84: 0 | N84: 0 | O84: 0 | P84: 0 | Q84: =F84+E84+G84+H84+I84+J84+K84+L84+M84+N84+O84+P84 -> 0
B85: VAR | C85: * CS_Variable Cost | E85: =SUM(E81:E84) -> 9.5939 | F85: =SUM(F81:F84) -> 13.44 | G85: =SUM(G81:G84) -> 7.5200003 | H85: =SUM(H81:H84) -> 12.16 | I85: =SUM(I81:I84) -> 10.56 | J85: =SUM(J81:J84) -> 16.8 | K85: =SUM(K81:K84) -> 13.01504 | L85: =SUM(L81:L84) -> 12.70528 | ... Q85: =SUM(Q81:Q84) -> 159.47454
A86: NO | B86: 6666100203 | C86: 6666100203 Provision for inventory devaluation - RM | D86: * CS_Obsolescence | E86: -26.06806 | F86: 8.861591 | G86: 8.6963601 | H86: 8.5678425 | I86: 8.4412241 | J86: 8.316477 | K86: 8.2504732 | L86: 8.1849932 | M86: 8.120033 | N86: 7.9803764 | O86: 7.8431217 | P86: 7.7082278 | Q86: =F86+E86+G86+H86+I86+J86+K86+L86+M86+N86+O86+P86 -> 64.90266
B87: FIX | C87: * CS_Obsolescence | E87: =+E86 -> -26.06806 | F87: =+F86 -> 8.861591 | G87: =+G86 -> 8.6963601 | H87: =+H86 -> 8.5678425 | I87: =+I86 -> 8.4412241 | J87: =+J86 -> 8.316477 | K87: =+K86 -> 8.2504732 | L87: =+L86 -> 8.1849932 | ... Q87: =+Q86 -> 64.90266
A88: NO | B88: 5301070000 | C88: 5301070000 Non-operation revenue-sales of scrapped | D88: * CS_Reselling | E88: -56.35548 | F88: -44.209518 | G88: -24.958316 | H88: -38.839629 | I88: -33.721599 | J88: -53.453138 | K88: -41.439964 | L88: -40.421594 | M88: -55.915497 | N88: -50.810573 | O88: -52.84099 | P88: -42.687767 | Q88: =F88+E88+G88+H88+I88+J88+K88+L88+M88+N88+O88+P88 -> -535.65406
B89: VAR | C89: * CS_Reselling | E89: =+E88 -> -56.35548 | F89: =+F88 -> -44.209518 | G89: =+G88 -> -24.958316 | H89: =+H88 -> -38.839629 | I89: =+I88 -> -33.721599 | J89: =+J88 -> -53.453138 | K89: =+K88 -> -41.439964 | L89: =+L88 -> -40.421594 | ... Q89: =+Q88 -> -535.65406
A90: YES | B90: 6666021602 | C90: 6666021602 Electricity | D90: * CS_Fix Utilities | E90: 8.56808 | F90: 4.4167253 | G90: 2.5037774 | H90: 4.0620853 | I90: 3.5369521 | J90: 6.4837984 | K90: 5.0369744 | L90: 4.9220107 | M90: 6.8215079 | N90: 6.2109733 | O90: 6.4731973 | P90: 5.2793358 | Q90: =F90+E90+G90+H90+I90+J90+K90+L90+M90+N90+O90+P90 -> 64.315418 | S90: 1000
A91: YES | B91: 6666021604 | C91: 6666021604 Oil & Gas man. Adj in Reporting | D91: * CS_Fix Utilities | E91: 0 | F91: 0.52299521 | G91: 0.28913437 | H91: 0.48100142 | I91: 0.31607755 | J91: 0.11237249 | K91: 0.10855216 | L91: 0.11617691 | M91: 0.11822543 | N91: 0.53309452 | O91: 0.55560149 | P91: 0.45812152 | Q91: =F91+E91+G91+H91+I91+J91+K91+L91+M91+N91+O91+P91 -> 3.6113531
B92: FIX | C92: * CS_Fix Utilities | E92: =SUM(E90:E91) -> 8.56808 | F92: =+SUM(F90:F91) -> 4.9397205 | G92: =+SUM(G90:G91) -> 2.7929118 | H92: =+SUM(H90:H91) -> 4.5430867 | I92: =+SUM(I90:I91) -> 3.8530296 | J92: =+SUM(J90:J91) -> 6.5961709 | K92: =+SUM(K90:K91) -> 5.1455266 | L92: =+SUM(L90:L91) -> 5.0381876 | M92: =+SUM(M90:M91) -> 6.9397333 | ... P92: =+SUM(P90:P91) -> 5.7374573 | Q92: =SUM(Q90:Q91) -> 67.926771
A93: YES | B93: 6666021600 | C93: 6666021600 Energy and power cost | D93: * CS_Variable Utilities | E93: 21.92376 | F93: 27.069836 | G93: 15.410674 | H93: 25.432441 | I93: 21.374298 | J93: 34.952011 | K93: 27.102594 | L93: 30.687349 | M93: 30.174673 | N93: 26.896663 | O93: 30.830025 | P93: 25.448809 | Q93: =F93+E93+G93+H93+I93+J93+K93+L93+M93+N93+O93+P93 -> 317.30313
A94: YES | B94: 6666021603 | C94: 6666021603 Water | D94: * CS_Variable Utilities | E94: 0.69152 | F94: 0.97773993 | G94: 0.55426656 | H94: 0.89923252 | I94: 0.78298265 | J94: 1.2439547 | K94: 0.96637304 | L94: 0.94431658 | M94: 1.3087462 | N94: 1.1916116 | O94: 1.2419208 | P94: 1.0128715 | Q94: =F94+E94+G94+H94+I94+J94+K94+L94+M94+N94+O94+P94 -> 11.815536
A95: YES | B95: 6666021604 | C95: 6666021604 Oil & Gas | D95: * CS_Variable Utilities | E95: 3.97728 | F95: 4.2206631 | G95: 2.3926326 | H95: 3.3641971 | I95: 2.8166198 | J95: 3.2219081 | K95: 2.502957 | L95: 2.4458296 | M95: 4.8962645 | N95: 4.8009682 | O95: 5.361067 | P95: 4.3723173 | Q95: =F95+E95+G95+H95+I95+J95+K95+L95+M95+N95+O95+P95 -> 44.372704
A96: YES | B96: 6666021604 | C96: 6666021604 Oil & Gas man. Adj in Reporting | D96: * CS_Variable Utilities | Q96: =F96+E96+G96+H96+I96+J96+K96+L96+M96+N96+O96+P96 -> 0
B97: VAR | C97: * CS_Variable Utilities | E97: =SUM(E93:E96) -> 26.59256 | F97: =SUM(F93:F96) -> 32.268239 | G97: =SUM(G93:G96) -> 18.357573 | H97: =SUM(H93:H96) -> 29.69587 | I97: =SUM(I93:I96) -> 24.9739 | J97: =SUM(J93:J96) -> 39.417873 | K97: =SUM(K93:K96) -> 30.571924 | L97: =SUM(L93:L96) -> 34.077495 | ... Q97: =SUM(Q93:Q96) -> 373.49137
A98: YES | B98: 5001010206 | C98: 5001010206 Unemployment Insurance -blue collar-Indi | D98: * CS_Indirect Labour | E98: 3.05709 | F98: 0 | G98: 0 | H98: 0 | I98: 0 | J98: 0 | K98: 0 | L98: 0 | M98: 0 | N98: 0 | O98: 0 | P98: 0 | Q98: =F98+E98+G98+H98+I98+J98+K98+L98+M98+N98+O98+P98 -> 3.05709
A99: YES | B99: 6666010184 | C99: 6666010184 Salary&Additional Incentive-Blue Collar- | D99: * CS_Indirect Labour | E99: -0.14232 | F99: 0 | G99: 0 | H99: 0 | I99: 0 | J99: 0 | K99: 0 | L99: 0 | M99: 0 | N99: 0 | O99: 0 | P99: 0 | Q99: =F99+E99+G99+H99+I99+J99+K99+L99+M99+N99+O99+P99 -> -0.14232
A100: YES | B100: 6666010186 | C100: 6666010186 Overtime-Blue Collar-Indirect | D100: * CS_Indirect Labour | E100: 8.76637 | F100: 0 | G100: 0 | H100: 0 | I100: 0 | J100: 0 | K100: 0 | L100: 0 | M100: 0 | N100: 0 | O100: 0 | P100: 0 | Q100: =F100+E100+G100+H100+I100+J100+K100+L100+M100+N100+O100+P100 -> 8.76637
A101: YES | B101: 6666010189 | C101: 6666010189 Salary - Blue collar indirect employees | D101: * CS_Indirect Labour | E101: 27.21355 | F101: 0 | G101: 0 | H101: 0 | I101: 0 | J101: 0 | K101: 0 | L101: 0 | M101: 0 | N101: 0 | O101: 0 | P101: 0 | Q101: =F101+E101+G101+H101+I101+J101+K101+L101+M101+N101+O101+P101 -> 27.21355
A102: YES | B102: 6666010012 | C102: 6666010012 Payroll Taxes- Blue Collar Indirect | D102: * CS_Indirect Labour | E102: 28.9222 | F102: 0 | G102: 0 | H102: 0 | I102: 0 | J102: 0 | K102: 0 | L102: 0 | M102: 0 | N102: 0 | O102: 0 | P102: 0 | Q102: =F102+E102+G102+H102+I102+J102+K102+L102+M102+N102+O102+P102 -> 28.9222
A103: YES | B103: 6666010226 | C103: 6666010226 Staff Leaving Indemnity - Blue Collar In | D103: * CS_Indirect Labour | E103: 6.0301 | F103: 0 | G103: 0 | H103: 0 | I103: 0 | J103: 0 | K103: 0 | L103: 0 | M103: 0 | N103: 0 | O103: 0 | P103: 0 | Q103: =F103+E103+G103+H103+I103+J103+K103+L103+M103+N103+O103+P103 -> 6.0301
A104: YES | B104: 6666010102 | C104: 6666010102 Salary-Blue collar indirect employees- A | D104: * CS_Indirect Labour | E104: 162.67013 | F104: 214.48241 | G104: 222.80617 | H104: 213.96039 | I104: 236.95514 | J104: 224.39063 | K104: 258.75691 | L104: 232.43647 | M104: 238.36332 | N104: 222.64599 | O104: 217.42964 | P104: 284.76513 | Q104: =F104+E104+G104+H104+I104+J104+K104+L104+M104+N104+O104+P104 -> 2729.6623
B105: FIX | C105: * CS_Indirect Labour | E105: =SUM(E98:E104) -> 236.51712 | F105: =SUM(F98:F104) -> 214.48241 | G105: =SUM(G98:G104) -> 222.80617 | H105: =SUM(H98:H104) -> 213.96039 | I105: =SUM(I98:I104) -> 236.95514 | J105: =SUM(J98:J104) -> 224.39063 | K105: =SUM(K98:K104) -> 258.75691 | L105: =SUM(L98:L104) -> 232.43647 | ... Q105: =SUM(Q98:Q104) -> 2803.5093
A106: YES | B106: 6666010196 | C106: 6666010196 Payroll Taxes-White Collar Employee | D106: * CS_Fixed Labour | E106: 15.8207 | F106: 0 | G106: 0 | H106: 0 | I106: 0 | J106: 0 | K106: 0 | L106: 0 | M106: 0 | N106: 0 | O106: 0 | P106: 0 | Q106: =F106+E106+G106+H106+I106+J106+K106+L106+M106+N106+O106+P106 -> 15.8207
A107: YES | B107: 6666010101 | C107: 6666010101 Salary - White collar employees | D107: * CS_Fixed Labour | E107: 83.51397 | F107: 114.33682 | G107: 104.53035 | H107: 105.61481 | I107: 111.61577 | J107: 107.92895 | K107: 100.07557 | L107: 100.55177 | M107: 105.38742 | N107: 98.798218 | O107: 97.220439 | P107: 95.692262 | Q107: =F107+E107+G107+H107+I107+J107+K107+L107+M107+N107+O107+P107 -> 1225.2663
A108: YES | B108: 6666010199 | C108: 6666010199 Salary-White collar employees -Accrued | D108: * CS_Fixed Labour | E108: 13.11897 | F108: 0 | G108: 0 | H108: 0 | I108: 0 | J108: 0 | K108: 0 | L108: 0 | M108: 0 | N108: 0 | O108: 0 | P108: 0 | Q108: =F108+E108+G108+H108+I108+J108+K108+L108+M108+N108+O108+P108 -> 13.11897
A109: YES | B109: 6666010185 | C109: 6666010185 Salary&Additional Incentive-White Collar | D109: * CS_Fixed Labour | E109: -0.18544 | F109: 0 | G109: 0 | H109: 0 | I109: 0 | J109: 0 | K109: 0 | L109: 0 | M109: 0 | N109: 0 | O109: 0 | P109: 0 | Q109: =F109+E109+G109+H109+I109+J109+K109+L109+M109+N109+O109+P109 -> -0.18544
A110: YES | B110: 6666010207 | C110: 6666010207 Unemployment insurance companies to pay | D110: * CS_Fixed Labour | E110: 1.1587 | F110: 0 | G110: 0 | H110: 0 | I110: 0 | J110: 0 | K110: 0 | L110: 0 | M110: 0 | N110: 0 | O110: 0 | P110: 0 | Q110: =F110+E110+G110+H110+I110+J110+K110+L110+M110+N110+O110+P110 -> 1.1587
A111: YES | B111: 5102040406 | C111: 5102040406 Other revenue-Service/Secondment agreeme | D111: * CS_Direct Labour | E111: 0 | F111: 0 | G111: 0 | H111: 0 | I111: 0 | J111: 0 | K111: 0 | L111: 0 | M111: 0 | N111: 0 | O111: 0 | P111: 0 | Q111: =F111+E111+G111+H111+I111+J111+K111+L111+M111+N111+O111+P111 -> 0
A112: YES | B112: 6666010227 | C112: 6666010227 Staff Leaving Indemnity - White collar E | D112: * CS_Fixed Labour | E112: 1.74299 | F112: 0 | G112: 0 | H112: 0 | I112: 0 | J112: 0 | K112: 0 | L112: 0 | M112: 0 | N112: 0 | O112: 0 | P112: 0 | Q112: =F112+E112+G112+H112+I112+J112+K112+L112+M112+N112+O112+P112 -> 1.74299
B113: FIX | C113: * CS_Fixed Labour | E113: =SUM(E106:E112) -> 115.16989 | F113: =SUM(F106:F112) -> 114.33682 | G113: =SUM(G106:G112) -> 104.53035 | H113: =SUM(H106:H112) -> 105.61481 | I113: =SUM(I106:I112) -> 111.61577 | J113: =SUM(J106:J112) -> 107.92895 | K113: =SUM(K106:K112) -> 100.07557 | L113: =SUM(L106:L112) -> 100.55177 | ... Q113: =SUM(Q106:Q112) -> 1256.9223
A114: YES | B114: 6666020903 | C114: 6666020903 Other materials | D114: * CS_Semifix | E114: 0 | F114: 0 | G114: 0 | H114: 0 | I114: 0 | J114: 0 | K114: 0 | L114: 0 | M114: 0 | N114: 0 | O114: 0 | P114: 0 | Q114: =F114+E114+G114+H114+I114+J114+K114+L114+M114+N114+O114+P114 -> 0
A115: YES | B115: 6666010302 | C115: 6666010302 Medical expenses | D115: * CS_Semifix | E115: 4.80178 | F115: 4.7122435 | G115: 4.6243803 | H115: 4.5560397 | I115: 4.488709 | J115: 4.4223734 | K115: 4.3872752 | L115: 4.3524556 | M115: 4.3179123 | N115: 4.2436484 | O115: 4.1706619 | P115: 4.0989306 | Q115: =F115+E115+G115+H115+I115+J115+K115+L115+M115+N115+O115+P115 -> 53.17641
A116: YES | B116: 6666010314 | C116: 6666010314 Work uniforms | D116: * CS_Semifix | E116: 5.27735 | F116: 56.128807 | G116: 1.622797 | H116: 1.6034213 | I116: 1.5708795 | J116: 1.5396324 | K116: 1.5096041 | L116: 1.4884907 | M116: 1.4679598 | N116: 1.4479876 | O116: 1.4244884 | P116: 1.4017397 | Q116: =F116+E116+G116+H116+I116+J116+K116+L116+M116+N116+O116+P116 -> 76.483158
A117: YES | B117: 6666010315 | C117: 6666010315 Social Aids | D117: * CS_Semifix | E117: 11.72316 | F117: 11.723163 | G117: 11.504576 | H117: 11.290065 | I117: 11.123217 | J117: 10.958834 | K117: 10.796881 | L117: 10.711192 | M117: 10.626182 | N117: 10.541847 | O117: 10.360538 | P117: 10.182347 | Q117: =F117+E117+G117+H117+I117+J117+K117+L117+M117+N117+O117+P117 -> 131.542
A118: YES | B118: 6666020401 | C118: 6666020401 local transportation - bus and taxi | D118: * CS_Semifix | E118: 31.34574 | F118: 33.72757 | G118: 34.91177 | H118: 32.648536 | I118: 21.500432 | J118: 32.955186 | K118: 28.814323 | L118: 27.234582 | M118: 37.032861 | N118: 32.950304 | O118: 35.195866 | P118: 28.044036 | Q118: =F118+E118+G118+H118+I118+J118+K118+L118+M118+N118+O118+P118 -> 376.36121
A119: YES | B119: 6666020402 | C119: 6666020402 Local transportation-transport subsidies | D119: * CS_Semifix | E119: 0 | F119: 0 | G119: 0 | H119: 0 | I119: 0 | J119: 0 | K119: 0 | L119: 0 | M119: 0 | N119: 0 | O119: 0 | P119: 0 | Q119: =F119+E119+G119+H119+I119+J119+K119+L119+M119+N119+O119+P119 -> 0
A120: YES | B120: 6666020502 | C120: 6666020502 Working meals | D120: * CS_Semifix | E120: 22.04347 | F120: 30.33312 | G120: 31.271916 | H120: 30.346874 | I120: 20.819763 | J120: 30.506218 | K120: 27.09094 | L120: 25.706649 | M120: 34.049122 | N120: 30.520538 | O120: 31.493808 | P120: 25.528687 | Q120: =F120+E120+G120+H120+I120+J120+K120+L120+M120+N120+O120+P120 -> 339.71111
A121: YES | B121: 6666020503 | C121: 6666020503 Office supplies | D121: * CS_Semifix | E121: 0.4098 | F121: 1.7454192 | G121: 1.7128745 | H121: 1.6875611 | I121: 1.6626218 | J121: 1.638051 | K121: 1.6250506 | L121: 1.6121534 | M121: 1.5993585 | N121: 1.5718511 | O121: 1.5448168 | P121: 1.5182475 | Q121: =F121+E121+G121+H121+I121+J121+K121+L121+M121+N121+O121+P121 -> 18.327806
A122: YES | B122: 6666021500 | C122: 6666021500 Repairs cost | D122: * CS_Semifix | E122: 0 | F122: 10 | G122: 7 | H122: 7 | I122: 7 | J122: 7 | K122: 7 | L122: 7 | M122: 7 | N122: 7 | O122: 7 | P122: 6 | Q122: =F122+E122+G122+H122+I122+J122+K122+L122+M122+N122+O122+P122 -> 79
A123: YES | B123: 6666021502 | C123: 6666021502 Repair & Maintain - Building&office | D123: * CS_Semifix | E123: 19 | F123: 32.921247 | G123: 32.307406 | H123: 31.829957 | I123: 31.359564 | J123: 30.896122 | K123: 30.650914 | L123: 30.407653 | M123: 30.166323 | N123: 29.647491 | O123: 29.137584 | P123: 28.636446 | Q123: =F123+E123+G123+H123+I123+J123+K123+L123+M123+N123+O123+P123 -> 356.96071
A124: YES | B124: 6666021503 | C124: 6666021503 Repair & Maintain - Tooling & Equipments | D124: * CS_Semifix | E124: 8.95545 | F124: 7.5 | G124: 7.5 | H124: 7.5 | I124: 7.5 | J124: 7.5 | K124: 7.5 | L124: 7.5 | M124: 7.5 | N124: 7.5 | O124: 7.5 | P124: 7.5 | Q124: =F124+E124+G124+H124+I124+J124+K124+L124+M124+N124+O124+P124 -> 91.45545
A125: YES | B125: 6666021505 | C125: 6666021505 Repairs & Maintenance - Vehicles | D125: * CS_Semifix | E125: 0 | F125: 0 | G125: 0 | H125: 0 | I125: 0 | J125: 0 | K125: 0 | L125: 0 | M125: 0 | N125: 0 | O125: 0 | P125: 0 | Q125: =F125+E125+G125+H125+I125+J125+K125+L125+M125+N125+O125+P125 -> 0
... A128: YES | B128: 6666091600 | C128: 6666091600 Garbage disposal charge | D128: * CS_Semifix | E128: 0.7778 | F128: 0.65664466 | G128: 0.64440104 | H128: 0.63487787 | I128: 0.62549544 | J128: 0.61625166 | K128: 0.61136078 | L128: 0.60650871 | M128: 0.60169515 | N128: 0.59134658 | O128: 0.581176 | P128: 0.57118034 | Q128: =F128+E128+G128+H128+I128+J128+K128+L128+M128+N128+O128+P128 -> 7.5187382
B129: FIX | C129: * CS_Semifix | E129: =SUM(E114:E128) -> 164.10092 | F129: =SUM(F114:F128) -> 241.57374 | G129: =SUM(G114:G128) -> 184.33206 | H129: =SUM(H114:H128) -> 179.63423 | I129: =SUM(I114:I128) -> 157.5028 | J129: =SUM(J114:J128) -> 177.21013 | K129: =SUM(K114:K128) -> 168.80685 | L129: =SUM(L114:L128) -> 165.08606 | ... Q129: =SUM(Q114:Q128) -> 2129.0955
D130: Manufacturing cost without Shares & Out of Perimeter | E130: =+E129+E113+E105+E97+E92+E89+E87+E85+E80+E28+E14+E23 -> 1179.7605 | F130: =+F129+F113+F105+F97+F92+F89+F87+F85+F80+F28+F14+F23 -> 1295.531 | G130: =+G129+G113+G105+G97+G92+G89+G87+G85+G80+G28+G14+G23 -> 1239.4756 | H130: =+H129+H113+H105+H97+H92+H89+H87+H85+H80+H28+H14+H23 -> 1209.1883 | I130: =+I129+I113+I105+I97+I92+I89+I87+I85+I80+I28+I14+I23 -> 1274.8845 | J130: =+J129+J113+J105+J97+J92+J89+J87+J85+J80+J28+J14+J23 -> 1257.4635 | K130: =+K129+K113+K105+K97+K92+K89+K87+K85+K80+K28+K14+K23 -> 1234.1011 | L130: =+L129+L113+L105+L97+L92+L89+L87+L85+L80+L28+L14+L23 -> 1217.9738 | ... Q130: =+Q129+Q113+Q105+Q97+Q92+Q89+Q87+Q85+Q80+Q28+Q14+Q23 -> 15030.946
A134: NO | B134: 6666110110 | C134: 6666110110 Depreciation-Plant & Machinery | E134: 0.0071 | F134: 0 | G134: 0 | H134: 0 | I134: 0 | J134: 0 | K134: 0 | L134: 0 | M134: 0 | N134: 0 | O134: 0 | P134: 0 | Q134: =F134+E134+G134+H134+I134+J134+K134+L134+M134+N134+O134+P134 -> 0.0071
A135: NO | B135: 6666110112 | C135: 6666110112 Depreciation of Furniture & Fixture | E135: 0.00395 | F135: 0.27989515 | G135: 0.27989515 | H135: 0.27989515 | I135: 0.27989515 | J135: 0.27989515 | K135: 0.27989515 | L135: 0.27989515 | M135: 0.27989515 | N135: 0.27989515 | O135: 0.27989515 | P135: 0.27989515 | Q135: =F135+E135+G135+H135+I135+J135+K135+L135+M135+N135+O135+P135 -> 3.0827966
A136: NO | B136: 6666110207 | C136: 6666110207 Amortization of Software | E136: 0.00013 | F136: 0 | G136: 0 | H136: 0 | I136: 0 | J136: 0 | K136: 0 | L136: 0 | M136: 0 | N136: 0 | O136: 0 | P136: 0 | Q136: =F136+E136+G136+H136+I136+J136+K136+L136+M136+N136+O136+P136 -> 0.00013
A137: NO | B137: 6666110506 | C137: 6666110506 Amortization-Leasehold Improvement | E137: 0.00727 | F137: 0 | G137: 0 | H137: 0 | I137: 0 | J137: 0 | K137: 0 | L137: 0 | M137: 0 | N137: 0 | O137: 0 | P137: 0 | Q137: =F137+E137+G137+H137+I137+J137+K137+L137+M137+N137+O137+P137 -> 0.00727
B138: CS_Depreci | C138: * CS_Depreciation | E138: =SUM(E134:E137) -> 0.01845 | F138: =SUM(F134:F137) -> 0.27989515 | G138: =SUM(G134:G137) -> 0.27989515 | H138: =SUM(H134:H137) -> 0.27989515 | I138: =SUM(I134:I137) -> 0.27989515 | J138: =SUM(J134:J137) -> 0.27989515 | K138: =SUM(K134:K137) -> 0.27989515 | L138: =SUM(L134:L137) -> 0.27989515 | ... Q138: =SUM(Q134:Q137) -> 3.0972966
A139: NO | B139: 6666010380 | C139: 6666010380 Incentive | E139: 0 | F139: 0 | G139: 0 | H139: 0 | I139: 0 | J139: 0 | K139: 0 | L139: 0 | M139: 0 | N139: 0 | O139: 0 | P139: 0 | Q139: =F139+E139+G139+H139+I139+J139+K139+L139+M139+N139+O139+P139 -> 0
A140: NO | B140: 5102040406 | C140: 5102040406 Other revenue-Servic | E140: 0 | F140: 0 | G140: 0 | H140: 0 | I140: 0 | J140: 0 | K140: 0 | L140: 0 | M140: 0 | N140: 0 | O140: 0 | P140: 0 | Q140: =F140+E140+G140+H140+I140+J140+K140+L140+M140+N140+O140+P140 -> 0
...

Sheet Renta DW _2025 
B1: Renta DW Cost Evolution | D1: Volume | E1: 48571 | H1: 46033 | K1: 46337 | N1: 49363 | Q1: 53704 | T1: 29664 | W1: 41857 | Z1: 31977 | AC1: 28268 | AF1: 26211 | AI1: 34024 | AL1: 42093 | AO1: =+E1+H1+K1+N1+Q1+T1+W1+Z1+AC1+AF1+AI1+AL1 -> 478102
D2: FX Rates | E2: 38.272236 | H2: 39.048375 | K2: 41.597869 | N2: 43.93 | Q2: =+Q229 -> 44.735418 | T2: =+T229 -> 46.437564 | W2: =+W229 -> 45.969819 | Z2: =+Z229 -> 47.671503 | AC2: =+AC229 -> 49.274771 | AF2: =+AF229 -> 47.314102 | AI2: =+AI229 -> 48.040247 | AL2: =+AL229 -> 48.608933 | AO2: =+AO229 -> 44.934681
A4: HQD PERIMETER | E4: Jan K€ | F4: Jan CPU € / pcs | H4: Feb K€ | I4: Feb CPU € / pcs | K4: Mar K€ | L4: Mar CPU € / pcs | N4: Apr K€ | O4: Apr CPU € / pcs | Q4: May K€ | R4: May CPU € / pcs | T4: June K€ | U4: June CPU € / pcs | W4: July K€ | X4: July CPU € / pcs | Z4: Aug K€ | AA4: Aug CPU € / pcs | AC4: Sep K€ | AD4: Sep CPU € / pcs | AF4: Oct K€ | AG4: Oct CPU € / pcs | AI4: Nov K€ | AJ4: Nov CPU € / pcs | AL4: DEC K€ | AM4: Dec CPU € / pcs | AO4: YTD K€ | AP4: YTD DEC CPU € / pcs
A5: YES | B5: 6666110101 | C5: 6666110101 Depreciation of buildings | D5: * CS_Depreciation | E5: 8.58079 | F5: =E5/$E$1*1000 -> 0.17666488 | H5: =27.05117-18.6560404444444 -> 8.3951296 | I5: =H5/$H$1*1000 -> 0.18237198 | K5: =29.88156-21.3282004444444 -> 8.5533596 | L5: =K5/$K$1*1000 -> 0.18459027 | N5: =28.96203-20.445 -> 8.51703 | O5: =N5/$N$1*1000 -> 0.17253874 | Q5: =30.08167-21.15308 -> 8.92859 | R5: =Q5/$Q$1*1000 -> 0.16625559 | T5: =29.67008-T235 -> 8.9335426 | U5: =T5/$T$1*1000 -> 0.30115772 | W5: =30.71618-W235 -> 9.0441604 | X5: =W5/$W$1*1000 -> 0.21607283 | Z5: =30.72552-Z235 -> 8.9882903 | AA5: =Z5/$Z$1*1000 -> 0.2810861 | AC5: =31.25161-AC235 -> 9.43073 | AD5: =AC5/$AC$1*1000 -> 0.33361858 | AF5: =32.26937-AF235 -> 9.699969 | AG5: =AF5/$AF$1*1000 -> 0.37007245 | AI5: =31.25416-AI235 -> 9.3732236 | AJ5: =AI5/$AI$1*1000 -> 0.27548859 | AL5: =32.52616-AL235 -> 9.7032255 | AM5: =AL5/$AL$1*1000 -> 0.23051874 | AO5: =H5+E5+K5+N5+Q5+T5+W5+Z5+AC5+AF5+AI5+AL5 -> 108.14804 | AP5: =AO5/$AO$1*1000 -> 0.22620286
A6: YES | B6: 6666110106 | C6: 6666110106 Depreciation of R&D facilities | D6: * CS_Depreciation | E6: 0 | F6: =E6/$E$1*1000 -> 0 | H6: 0 | I6: =H6/$H$1*1000 -> 0 | K6: 0 | L6: =K6/$K$1*1000 -> 0 | N6: 0 | O6: =N6/$N$1*1000 -> 0 | Q6: 0 | R6: =Q6/$Q$1*1000 -> 0 | T6: 0 | U6: =T6/$T$1*1000 -> 0 | W6: 0 | X6: =W6/$W$1*1000 -> 0 | Z6: 0 | AA6: =Z6/$Z$1*1000 -> 0 | AC6: 0 | AD6: =AC6/$AC$1*1000 -> 0 | AF6: 0 | AG6: =AF6/$AF$1*1000 -> 0 | AI6: 0 | AJ6: =AI6/$AI$1*1000 -> 0 | AL6: 0 | AM6: =AL6/$AL$1*1000 -> 0 | AO6: =H6+E6+K6+N6+Q6+T6+W6+Z6+AC6+AF6+AI6+AL6 -> 0 | AP6: =AO6/$AO$1*1000 -> 0
A7: YES | B7: 6666110107 | C7: 6666110107 Depreciation of mold | D7: * CS_Depreciation | E7: 90.54188 | F7: =E7/$E$1*1000 -> 1.864114 | H7: =208.59611-109.209985777778 -> 99.386124 | I7: =H7/$H$1*1000 -> 2.1590191 | K7: =222.76497-119.675125777778 -> 103.08984 | L7: =K7/$K$1*1000 -> 2.2247846 | N7: =221.08877-117.086 -> 104.00277 | O7: =N7/$N$1*1000 -> 2.1068973 | Q7: =230.92979-126.57762 -> 104.35217 | R7: =Q7/$Q$1*1000 -> 1.9430987 | T7: =226.52287-T237 -> 98.20495 | U7: =T7/$T$1*1000 -> 3.3105768 | W7: =232.94505-W237 -> 98.45024 | X7: =W7/$W$1*1000 -> 2.3520615 | Z7: =233.08123-Z237 -> 97.333463 | AA7: =Z7/$Z$1*1000 -> 3.0438585 | AC7: =229.28602-AC237 -> 94.49625 | AD7: =AC7/$AC$1*1000 -> 3.34287 | AF7: =118.01548-AF237 -> 74.032202 | AG7: =AF7/$AF$1*1000 -> 2.8244707 | AI7: =219.16417-AI237 -> 92.929818 | AJ7: =AI7/$AI$1*1000 -> 2.731302 | AL7: =223.42017-AL237 -> 92.937153 | AM7: =AL7/$AL$1*1000 -> 2.2079004 | AO7: =H7+E7+K7+N7+Q7+T7+W7+Z7+AC7+AF7+AI7+AL7 -> 1149.7569 | AP7: =AO7/$AO$1*1000 -> 2.4048359
A8: YES | B8: 6666110110 | C8: 6666110110 Depreciation-Plant & Machinery | D8: * CS_Depreciation | E8: 62.82441 | F8: =E8/$E$1*1000 -> 1.2934551 | H8: =261.00381-198.482281111111 -> 62.521529 | I8: =H8/$H$1*1000 -> 1.3581893 | K8: =290.93886-225.680081111111 -> 65.258779 | L8: =K8/$K$1*1000 -> 1.4083514 | N8: =284.06253-216.6537 -> 67.40883 | O8: =N8/$N$1*1000 -> 1.365574 | Q8: =299.32499-228.57031 -> 70.75468 | R8: =Q8/$Q$1*1000 -> 1.3174937 | T8: =288.81974-T238 -> 66.024395 | U8: =T8/$T$1*1000 -> 2.2257415 | W8: =297.80019-W238 -> 65.613057 | X8: =W8/$W$1*1000 -> 1.5675528 | Z8: =297.85265-Z238 -> 64.715916 | AA8: =Z8/$Z$1*1000 -> 2.023827 | AC8: =291.39958-AC238 -> 63.49677 | AD8: =AC8/$AC$1*1000 -> 2.246242 | AF8: =207.60475-AF238 -> 39.993225 | AG8: =AF8/$AF$1*1000 -> 1.5258184 | AI8: =283.72663-AI238 -> 61.671035 | AJ8: =AI8/$AI$1*1000 -> 1.8125745 | AL8: =294.42037-AL238 -> 63.391045 | AM8: =AL8/$AL$1*1000 -> 1.5059759 | AO8: =H8+E8+K8+N8+Q8+T8+W8+Z8+AC8+AF8+AI8+AL8 -> 753.67367 | AP8: =AO8/$AO$1*1000 -> 1.5763868
A9: YES | B9: 6666110112 | C9: 6666110112 Depreciation of Furniture & Fixture | D9: * CS_Depreciation | E9: 3.19741 | F9: =E9/$E$1*1000 -> 0.06582961 | H9: =6.81703-3.61013311111111 -> 3.2068969 | I9: =H9/$H$1*1000 -> 0.069665173 | K9: =8.46919-4.13525311111111 -> 4.3339369 | L9: =K9/$K$1*1000 -> 0.093530805 | N9: =8.46194-3.8942 -> 4.56774 | O9: =N9/$N$1*1000 -> 0.092533679 | Q9: =11.26201-5.21228 -> 6.04973 | R9: =Q9/$Q$1*1000 -> 0.11264952 | T9: =11.52002-T239 -> 6.1588719 | U9: =T9/$T$1*1000 -> 0.20762108 | W9: =11.70987-W239 -> 6.0246807 | X9: =W9/$W$1*1000 -> 0.14393484 | Z9: =11.77284-Z239 -> 5.4610633 | AA9: =Z9/$Z$1*1000 -> 0.17078098 | AC9: =9.89618-AC239 -> 4.84602 | AD9: =AC9/$AC$1*1000 -> 0.1714313 | AF9: =9.79722-AF239 -> 5.0633714 | AG9: =AF9/$AF$1*1000 -> 0.19317734 | AI9: =10.12633-AI239 -> 5.0687601 | AJ9: =AI9/$AI$1*1000 -> 0.14897602 | AL9: =8.94347-AL239 -> 4.310794 | AM9: =AL9/$AL$1*1000 -> 0.10241119 | AO9: =H9+E9+K9+N9+Q9+T9+W9+Z9+AC9+AF9+AI9+AL9 -> 58.289275 | AP9: =AO9/$AO$1*1000 -> 0.12191807
A10: YES | B10: 6666110204 | C10: 6666110204 Amortization of license, trademarks and | D10: * CS_Depreciation | E10: 0.00252 | F10: =E10/$E$1*1000 -> 5.1882811e-05 | H10: =0.25251--0.0561566666666667 -> 0.30866667 | I10: =H10/$H$1*1000 -> 0.0067053346 | K10: =0.25252-0.0561666666666667 -> 0.19635333 | L10: =K10/$K$1*1000 -> 0.0042375064 | N10: =0.25252-0.0562 -> 0.19632 | O10: =N10/$N$1*1000 -> 0.0039770678 | Q10: =0.25251-(50.73/1000) -> 0.20178 | R10: =Q10/$Q$1*1000 -> 0.003757262 | T10: =0.25252-T240 -> 0.1944745 | U10: =T10/$T$1*1000 -> 0.0065559096 | W10: =0.25252-W240 -> 0.18806389 | X10: =W10/$W$1*1000 -> 0.0044930094 | Z10: =0.25251-Z240 -> 0.18602561 | AA10: =Z10/$Z$1*1000 -> 0.0058174815 | AC10: =0.25252-AC240 -> 0.18222 | AD10: =AC10/$AC$1*1000 -> 0.0064461582 | AF10: =0.25252-AF240 -> 0.18151023 | AG10: =AF10/$AF$1*1000 -> 0.0069249641 | AI10: =0.25251-AI240 -> 0.18072725 | AJ10: =AI10/$AI$1*1000 -> 0.005311758 | AL10: =0.25252-AL240 -> 0.17682586 | AM10: =AL10/$AL$1*1000 -> 0.0042008378 | AO10: =H10+E10+K10+N10+Q10+T10+W10+Z10+AC10+AF10+AI10+AL10 -> 2.1954874 | AP10: =AO10/$AO$1*1000 -> 0.0045920899
A11: YES | B11: 6666110207 | C11: 6666110207 Amortization of Software | D11: * CS_Depreciation | E11: 3.61797 | F11: =E11/$E$1*1000 -> 0.074488275 | H11: =7.67016-4.05927644444445 -> 3.6108836 | I11: =H11/$H$1*1000 -> 0.078441196 | K11: =8.28781-4.67692644444444 -> 3.6108836 | L11: =K11/$K$1*1000 -> 0.077926572 | N11: =6.89599-3.2851 -> 3.61089 | O11: =N11/$N$1*1000 -> 0.073149728 | Q11: =6.78395-(3308.9/1000) -> 3.47505 | R11: =Q11/$Q$1*1000 -> 0.064707471 | T11: =6.30245-T241 -> 3.0508154 | U11: =T11/$T$1*1000 -> 0.10284572 | W11: =4.61586-W241 -> 2.8164364 | X11: =W11/$W$1*1000 -> 0.067287106 | Z11: =2.82269-Z241 -> 2.0440043 | AA11: =Z11/$Z$1*1000 -> 0.063921078 | AC11: =2.28113-AC241 -> 1.19932 | AD11: =AC11/$AC$1*1000 -> 0.042426772 | AF11: =2.34755-AF241 -> 1.2346426 | AG11: =AF11/$AF$1*1000 -> 0.047103988 | AI11: =2.31588-AI241 -> 1.2158296 | AJ11: =AI11/$AI$1*1000 -> 0.035734469 | AL11: =2.35319-AL241 -> 1.143964 | AM11: =AL11/$AL$1*1000 -> 0.027177061 | AO11: =H11+E11+K11+N11+Q11+T11+W11+Z11+AC11+AF11+AI11+AL11 -> 30.630689 | AP11: =AO11/$AO$1*1000 -> 0.064067269
A12: YES | B12: 6666110506 | C12: 6666110506 Amortization-Leasehold Improvement | D12: * CS_Depreciation | E12: 0.91407 | F12: =E12/$E$1*1000 -> 0.018819254 | H12: =0.91407-0.250798 -> 0.663272 | I12: =H12/$H$1*1000 -> 0.01440862 | K12: =0.91407-0.250798 -> 0.663272 | L12: =K12/$K$1*1000 -> 0.01431409 | N12: =0.91407-0.2508 -> 0.66327 | O12: =N12/$N$1*1000 -> 0.013436582 | Q12: =0.91407-(232.48/1000) -> 0.68159 | R12: =Q12/$Q$1*1000 -> 0.012691606 | T12: =0.91407-T242 -> 0.65692541 | U12: =T12/$T$1*1000 -> 0.022145544 | W12: =0.91407-W242 -> 0.63527068 | X12: =W12/$W$1*1000 -> 0.015177167 | Z12: =0.91408-Z242 -> 0.62838544 | AA12: =Z12/$Z$1*1000 -> 0.019651169 | AC12: 0 | AD12: =AC12/$AC$1*1000 -> 0 | AF12: 0 | AG12: =AF12/$AF$1*1000 -> 0 | AI12: 0 | AJ12: =AI12/$AI$1*1000 -> 0 | AL12: 0 | AM12: =AL12/$AL$1*1000 -> 0 | AO12: =H12+E12+K12+N12+Q12+T12+W12+Z12+AC12+AF12+AI12+AL12 -> 5.5060555 | AP12: =AO12/$AO$1*1000 -> 0.011516487
B13: FIX | C13: * CS_Depreciation | E13: 169.67905 | F13: =E13/$E$1*1000 -> 3.493423 | H13: =SUM(H5:H12) -> 178.0925 | I13: =H13/$H$1*1000 -> 3.8688007 | K13: =SUM(K5:K12) -> 185.70643 | L13: =K13/$K$1*1000 -> 4.0077353 | N13: =SUM(N5:N12) -> 188.96685 | O13: =N13/$N$1*1000 -> 3.8281071 | Q13: =SUM(Q5:Q12) -> 194.44359 | R13: =Q13/$Q$1*1000 -> 3.6206538 | T13: =SUM(T5:T12) -> 183.22398 | U13: =T13/$T$1*1000 -> 6.1766443 | W13: =SUM(W5:W12) -> 182.77191 | X13: =W13/$W$1*1000 -> 4.3665793 | Z13: =SUM(Z5:Z12) -> 179.35715 | AA13: =Z13/$Z$1*1000 -> 5.6089423 | AC13: =SUM(AC5:AC12) -> 173.65131 | AD13: =AC13/$AC$1*1000 -> 6.1430349 | AF13: =SUM(AF5:AF12) -> 130.20492 | AG13: =AF13/$AF$1*1000 -> 4.9675678 | AI13: =SUM(AI5:AI12) -> 170.43939 | AJ13: =AI13/$AI$1*1000 -> 5.0093873 | AL13: =SUM(AL5:AL12) -> 171.66301 | AM13: =AL13/$AL$1*1000 -> 4.0781842 | AO13: =SUM(AO5:AO12) -> 2108.2001 | AP13: =AO13/$AO$1*1000 -> 4.4095195
A14: YES | B14: 5001010205 | C14: 5001010205 Unemployment Insurance -blue collar-Dire | D14: * CS_Direct Labour | E14: 7.24866 | F14: =E14/$E$1*1000 -> 0.14923843 | H14: 6.31439 | I14: =H14/$H$1*1000 -> 0.13717094 | K14: 8.11537 | L14: =K14/$K$1*1000 -> 0.17513801 | N14: 7.33205 | O14: =N14/$N$1*1000 -> 0.14853331 | Q14: 9.34405 | R14: =Q14/$Q$1*1000 -> 0.1739917 | T14: 7.35114 | U14: =T14/$T$1*1000 -> 0.24781351 | W14: 6.70939 | X14: =W14/$W$1*1000 -> 0.16029314 | Z14: 4.55939 | AA14: =Z14/$Z$1*1000 -> 0.14258342 | AC14: 4.69046 | AD14: =AC14/$AC$1*1000 -> 0.16592826 | AF14: 4.86146 | AG14: =AF14/$AF$1*1000 -> 0.18547404 | AI14: 7.98073 | AJ14: =AI14/$AI$1*1000 -> 0.23456178 | AL14: 8.07355 | AM14: =AL14/$AL$1*1000 -> 0.19180268 | AO14: =H14+E14+K14+N14+Q14+T14+W14+Z14+AC14+AF14+AI14+AL14 -> 82.58064 | AP14: =AO14/$AO$1*1000 -> 0.17272599
A15: YES | B15: 6666010380 | C15: 6666010380 Incentive | D15: * CS_Direct Labour | E15: -1.66916 | F15: =E15/$E$1*1000 -> -0.034365362 | H15: -1.5004 | I15: =H15/$H$1*1000 -> -0.032594009 | K15: -1.56596 | L15: =K15/$K$1*1000 -> -0.033795023 | N15: -1.42469 | O15: =N15/$N$1*1000 -> -0.028861495 | Q15: -0.35328 | R15: =Q15/$Q$1*1000 -> -0.0065782809 | T15: -1.15203 | U15: =T15/$T$1*1000 -> -0.038835963 | W15: -1.09401 | X15: =W15/$W$1*1000 -> -0.026136847 | Z15: -0.95339 | AA15: =Z15/$Z$1*1000 -> -0.029814867 | AC15: 4.29009 | AD15: =AC15/$AC$1*1000 -> 0.15176489 | AF15: 4.40298 | AG15: =AF15/$AF$1*1000 -> 0.16798214 | AI15: 3.89863 | AJ15: =AI15/$AI$1*1000 -> 0.1145847 | AL15: 3.47141 | AM15: =AL15/$AL$1*1000 -> 0.082470007 | AO15: =H15+E15+K15+N15+Q15+T15+W15+Z15+AC15+AF15+AI15+AL15 -> 6.35019 | AP15: =AO15/$AO$1*1000 -> 0.013282082
A16: YES | B16: 6666010019 | C16: 6666010019 Payroll Taxes - Blue Collar Direct | D16: * CS_Direct Labour | E16: 57.92585 | F16: =E16/$E$1*1000 -> 1.1926016 | H16: 50.47935 | I16: =H16/$H$1*1000 -> 1.0965905 | K16: 64.9104 | L16: =K16/$K$1*1000 -> 1.400833 | N16: 58.63925 | O16: =N16/$N$1*1000 -> 1.1879191 | Q16: 73.69048 | R16: =Q16/$Q$1*1000 -> 1.37216 | T16: 58.78984 | U16: =T16/$T$1*1000 -> 1.9818581 | W16: 53.64949 | X16: =W16/$W$1*1000 -> 1.2817328 | Z16: 36.41908 | AA16: =Z16/$Z$1*1000 -> 1.1389148 | AC16: 37.40107 | AD16: =AC16/$AC$1*1000 -> 1.3230887 | AF16: 38.74085 | AG16: =AF16/$AF$1*1000 -> 1.4780378 | AI16: 63.85492 | AJ16: =AI16/$AI$1*1000 -> 1.8767611 | AL16: 64.57704 | AM16: =AL16/$AL$1*1000 -> 1.5341515 | AO16: =H16+E16+K16+N16+Q16+T16+W16+Z16+AC16+AF16+AI16+AL16 -> 659.07762 | AP16: =AO16/$AO$1*1000 -> 1.3785293
A17: YES | B17: 6666010183 | C17: 6666010183 Overtime-Blue Collar-Direct | D17: * CS_Direct Labour | E17: 13.55408 | F17: =E17/$E$1*1000 -> 0.27905705 | H17: 18.85745 | I17: =H17/$H$1*1000 -> 0.40965069 | K17: 26.26231 | L17: =K17/$K$1*1000 -> 0.56676759 | N17: 51.24566 | O17: =N17/$N$1*1000 -> 1.0381391 | Q17: 94.37846 | R17: =Q17/$Q$1*1000 -> 1.7573823 | T17: 20.87175 | U17: =T17/$T$1*1000 -> 0.70360538 | W17: 15.76442 | X17: =W17/$W$1*1000 -> 0.37662565 | Z17: 11.10426 | AA17: =Z17/$Z$1*1000 -> 0.34725772 | AC17: 11.05797 | AD17: =AC17/$AC$1*1000 -> 0.39118332 | AF17: 10.29058 | AG17: =AF17/$AF$1*1000 -> 0.39260539 | AI17: 24.6245 | AJ17: =AI17/$AI$1*1000 -> 0.72373913 | AL17: 19.13579 | AM17: =AL17/$AL$1*1000 -> 0.45460742 | AO17: =H17+E17+K17+N17+Q17+T17+W17+Z17+AC17+AF17+AI17+AL17 -> 317.14723 | AP17: =AO17/$AO$1*1000 -> 0.66334638
A18: YES | B18: 6666010229 | C18: 6666010229 Staff Leaving Indemnity - Blue Collar Di | D18: * CS_Direct Labour | E18: 31.74454 | F18: =E18/$E$1*1000 -> 0.65356983 | H18: -40.04254 | I18: =H18/$H$1*1000 -> -0.86986597 | K18: 11.24318 | L18: =K18/$K$1*1000 -> 0.24263936 | N18: 10.77437 | O18: =N18/$N$1*1000 -> 0.21826814 | Q18: 10.89326 | R18: =Q18/$Q$1*1000 -> 0.20283889 | T18: 11.22168 | U18: =T18/$T$1*1000 -> 0.37829288 | W18: 23.15531 | X18: =W18/$W$1*1000 -> 0.55320042 | Z18: 7.05833 | AA18: =Z18/$Z$1*1000 -> 0.22073146 | AC18: 7.16637 | AD18: =AC18/$AC$1*1000 -> 0.25351528 | AF18: 7.24789 | AG18: =AF18/$AF$1*1000 -> 0.27652093 | AI18: 13.57379 | AJ18: =AI18/$AI$1*1000 -> 0.39894751 | AL18: 14.07397 | AM18: =AL18/$AL$1*1000 -> 0.33435417 | AO18: =H18+E18+K18+N18+Q18+T18+W18+Z18+AC18+AF18+AI18+AL18 -> 108.11015 | AP18: =AO18/$AO$1*1000 -> 0.22612361
A19: YES | B19: 6666010188 | C19: 6666010188 Salary - Blue collar direct employees | D19: * CS_Direct Labour | E19: 362.36537 | F19: =E19/$E$1*1000 -> 7.4605293 | H19: 309.36539 | I19: =H19/$H$1*1000 -> 6.7205133 | K19: 408.16624 | L19: =K19/$K$1*1000 -> 8.8086462 | N19: 342.65633 | O19: =N19/$N$1*1000 -> 6.9415621 | Q19: 370.23077 | R19: =Q19/$Q$1*1000 -> 6.8939142 | T19: 287.47624 | U19: =T19/$T$1*1000 -> 9.6910814 | W19: 348.43376 | X19: =W19/$W$1*1000 -> 8.3243845 | Z19: 294.87662 | AA19: =Z19/$Z$1*1000 -> 9.2215223 | AC19: 283.45492 | AD19: =AC19/$AC$1*1000 -> 10.027413 | AF19: 316.22481 | AG19: =AF19/$AF$1*1000 -> 12.064584 | AI19: 362.38001 | AJ19: =AI19/$AI$1*1000 -> 10.650717 | AL19: 377.54838 | AM19: =AL19/$AL$1*1000 -> 8.9693864 | AO19: =H19+E19+K19+N19+Q19+T19+W19+Z19+AC19+AF19+AI19+AL19 -> 4063.1788 | AP19: =AO19/$AO$1*1000 -> 8.4985606
A20: YES | B20: 5102040406 | C20: 5102040406 Other revenue-Service/Secondment agreeme | D20: * CS_Direct Labour | E20: 0 | F20: =E20/$E$1*1000 -> 0 | H20: 0 | I20: =H20/$H$1*1000 -> 0 | K20: 0 | L20: =K20/$K$1*1000 -> 0 | N20: 0 | O20: =N20/$N$1*1000 -> 0 | Q20: 0 | R20: =Q20/$Q$1*1000 -> 0 | T20: 0 | U20: =T20/$T$1*1000 -> 0 | W20: 0 | X20: =W20/$W$1*1000 -> 0 | Z20: 0 | AA20: =Z20/$Z$1*1000 -> 0 | AC20: 0 | AD20: =AC20/$AC$1*1000 -> 0 | AF20: 0 | AG20: =AF20/$AF$1*1000 -> 0 | AI20: 0 | AJ20: =AI20/$AI$1*1000 -> 0 | AL20: 0 | AM20: =AL20/$AL$1*1000 -> 0 | AO20: =H20+E20+K20+N20+Q20+T20+W20+Z20+AC20+AF20+AI20+AL20 -> 0 | AP20: =AO20/$AO$1*1000 -> 0
A21: YES | B21: 6666010115 | C21: 6666010115 Salary-Blue collar direct employees-Accr | D21: * CS_Direct Labour | E21: 0.78963 | F21: =E21/$E$1*1000 -> 0.016257232 | H21: -0.08295 | I21: =H21/$H$1*1000 -> -0.0018019682 | K21: 0.08153 | L21: =K21/$K$1*1000 -> 0.001759501 | N21: -0.12195 | O21: =N21/$N$1*1000 -> -0.0024704738 | Q21: 4.82629 | R21: =Q21/$Q$1*1000 -> 0.089868352 | T21: -2.497 | U21: =T21/$T$1*1000 -> -0.084176106 | W21: -1.46614 | X21: =W21/$W$1*1000 -> -0.035027355 | Z21: -1.28806 | AA21: =Z21/$Z$1*1000 -> -0.040280827 | AC21: 0.75016 | AD21: =AC21/$AC$1*1000 -> 0.026537427 | AF21: 1.48075 | AG21: =AF21/$AF$1*1000 -> 0.056493457 | AI21: 3.04219 | AJ21: =AI21/$AI$1*1000 -> 0.089413061 | AL21: -60.95212 | AM21: =AL21/$AL$1*1000 -> -1.4480346 | AO21: =H21+E21+K21+N21+Q21+T21+W21+Z21+AC21+AF21+AI21+AL21 -> -55.43767 | AP21: =AO21/$AO$1*1000 -> -0.11595365
B22: VAR | C22: * CS_Direct Labour | E22: 471.95897 | F22: =E22/$E$1*1000 -> 9.7168881 | H22: =SUM(H14:H21) -> 343.39069 | I22: =H22/$H$1*1000 -> 7.4596635 | K22: =SUM(K14:K21) -> 517.21307 | L22: =K22/$K$1*1000 -> 11.161989 | N22: =SUM(N14:N21) -> 469.10102 | O22: =N22/$N$1*1000 -> 9.5030898 | Q22: =SUM(Q14:Q21) -> 563.01003 | R22: =Q22/$Q$1*1000 -> 10.483577 | T22: =SUM(T14:T21) -> 382.06162 | U22: =T22/$T$1*1000 -> 12.879639 | W22: =SUM(W14:W21) -> 445.15222 | X22: =W22/$W$1*1000 -> 10.635072 | Z22: =SUM(Z14:Z21) -> 351.77623 | AA22: =Z22/$Z$1*1000 -> 11.000914 | AC22: =SUM(AC14:AC21) -> 348.81104 | AD22: =AC22/$AC$1*1000 -> 12.339431 | AF22: =SUM(AF14:AF21) -> 383.24932 | AG22: =AF22/$AF$1*1000 -> 14.621698 | AI22: =SUM(AI14:AI21) -> 479.35477 | AJ22: =AI22/$AI$1*1000 -> 14.088725 | AL22: =SUM(AL14:AL21) -> 425.92802 | AM22: =AL22/$AL$1*1000 -> 10.118738 | AO22: =SUM(AO14:AO21) -> 5181.007 | AP22: =AO22/$AO$1*1000 -> 10.836614
A23: NO | B23: 8701530201 | C23: 8701530201 Scrap-Raw Material - Managerial | D23: * CS_SCRAP_VARIABLE | E23: 0 | F23: =E23/$E$1*1000 -> 0 | H23: 0 | I23: =H23/$H$1*1000 -> 0 | K23: 0 | L23: =K23/$K$1*1000 -> 0 | N23: 0 | O23: =N23/$N$1*1000 -> 0 | Q23: 0 | R23: =Q23/$Q$1*1000 -> 0 | T23: 0 | U23: =T23/$T$1*1000 -> 0 | W23: 0 | X23: =W23/$W$1*1000 -> 0 | AA23: =Z23/$Z$1*1000 -> 0 | AC23: 0 | AD23: =AC23/$AC$1*1000 -> 0 | AF23: 0 | AG23: =AF23/$AF$1*1000 -> 0 | AI23: 0 | AJ23: =AI23/$AI$1*1000 -> 0 | AL23: 0 | AM23: =AL23/$AL$1*1000 -> 0 | AO23: =H23+E23+K23+N23+Q23+T23+W23+Z23+AC23+AF23+AI23+AL23 -> 0 | AP23: =AO23/$AO$1*1000 -> 0
A24: NO | B24: 6666050309 | C24: 6666050309 SFG scrap | D24: * CS_SCRAP_VARIABLE | E24: 11.07122 | F24: =E24/$E$1*1000 -> 0.22793889 | H24: 15.19826 | I24: =H24/$H$1*1000 -> 0.3301601 | K24: 16.14383 | L24: =K24/$K$1*1000 -> 0.34840041 | N24: 12.85146 | O24: =N24/$N$1*1000 -> 0.26034601 | Q24: 15.24772 | R24: =Q24/$Q$1*1000 -> 0.2839215 | T24: 5.09867 | U24: =T24/$T$1*1000 -> 0.17188073 | W24: 5.68261 | X24: =W24/$W$1*1000 -> 0.13576248 | Z24: 4.55538 | AA24: =Z24/$Z$1*1000 -> 0.14245802 | AC24: 4.17634 | AD24: =AC24/$AC$1*1000 -> 0.14774091 | AF24: 6.77505 | AG24: =AF24/$AF$1*1000 -> 0.25848117 | AI24: 6.67286 | AJ24: =AI24/$AI$1*1000 -> 0.19612215 | AL24: 20.85026 | AM24: =AL24/$AL$1*1000 -> 0.49533794 | AO24: =H24+E24+K24+N24+Q24+T24+W24+Z24+AC24+AF24+AI24+AL24 -> 124.32366 | AP24: =AO24/$AO$1*1000 -> 0.26003585
A25: NO | B25: 6666050308 | C25: 6666050308 Raw material scrap | D25: * CS_SCRAP_VARIABLE | E25: 12.13983 | F25: =E25/$E$1*1000 -> 0.24993988 | H25: 7.13567 | I25: =H25/$H$1*1000 -> 0.15501206 | K25: 6.75416 | L25: =K25/$K$1*1000 -> 0.1457617 | N25: 9.48485 | O25: =N25/$N$1*1000 -> 0.19214493 | Q25: 12.98944 | R25: =Q25/$Q$1*1000 -> 0.241871 | T25: 15.08068 | U25: =T25/$T$1*1000 -> 0.50838323 | W25: 11.5278 | X25: =W25/$W$1*1000 -> 0.27540913 | Z25: 12.4678 | AA25: =Z25/$Z$1*1000 -> 0.38989899 | AC25: 13.43581 | AD25: =AC25/$AC$1*1000 -> 0.47530105 | AF25: 9.35193 | AG25: =AF25/$AF$1*1000 -> 0.35679409 | AI25: 10.2868 | AJ25: =AI25/$AI$1*1000 -> 0.30233953 | AL25: 24.54833 | AM25: =AL25/$AL$1*1000 -> 0.58319269 | AO25: =H25+E25+K25+N25+Q25+T25+W25+Z25+AC25+AF25+AI25+AL25 -> 145.2031 | AP25: =AO25/$AO$1*1000 -> 0.30370737
A26: NO | B26: 6666050306 | C26: 6666050306 Finished goods scrap | D26: * CS_SCRAP_VARIABLE | E26: -0.01268 | F26: =E26/$E$1*1000 -> -0.00026106113 | H26: 0.25906 | I26: =H26/$H$1*1000 -> 0.0056277019 | K26: 0 | L26: =K26/$K$1*1000 -> 0 | N26: 0.26438 | O26: =N26/$N$1*1000 -> 0.0053558333 | Q26: 0 | R26: =Q26/$Q$1*1000 -> 0 | T26: 0.18359 | U26: =T26/$T$1*1000 -> 0.0061889833 | W26: 0.20456 | X26: =W26/$W$1*1000 -> 0.0048871157 | AA26: =Z26/$Z$1*1000 -> 0 | AC26: 0.22243 | AD26: =AC26/$AC$1*1000 -> 0.0078686147 | AF26: 0.36773 | AG26: =AF26/$AF$1*1000 -> 0.014029606 | AI26: 0.41342 | AJ26: =AI26/$AI$1*1000 -> 0.012150835 | AL26: 0.95812 | AM26: =AL26/$AL$1*1000 -> 0.022761979 | AO26: =H26+E26+K26+N26+Q26+T26+W26+Z26+AC26+AF26+AI26+AL26 -> 2.86061 | AP26: =AO26/$AO$1*1000 -> 0.005983263
B27: VAR | C27: * CS_SCRAP_VARIABLE | E27: 23.19837 | F27: =E27/$E$1*1000 -> 0.47761771 | H27: =SUM(H23:H26) -> 22.59299 | I27: =H27/$H$1*1000 -> 0.49079986 | K27: =SUM(K23:K26) -> 22.89799 | L27: =K27/$K$1*1000 -> 0.49416212 | N27: =SUM(N23:N26) -> 22.60069 | O27: =N27/$N$1*1000 -> 0.45784677 | Q27: =SUM(Q23:Q26) -> 28.23716 | R27: =Q27/$Q$1*1000 -> 0.52579249 | T27: =SUM(T23:T26) -> 20.36294 | U27: =T27/$T$1*1000 -> 0.68645294 | W27: =SUM(W23:W26) -> 17.41497 | X27: =W27/$W$1*1000 -> 0.41605872 | Z27: =SUM(Z23:Z26) -> 17.02318 | AA27: =Z27/$Z$1*1000 -> 0.53235701 | AC27: =SUM(AC23:AC26) -> 17.83458 | AD27: =AC27/$AC$1*1000 -> 0.63091057 | AF27: =SUM(AF23:AF26) -> 16.49471 | AG27: =AF27/$AF$1*1000 -> 0.62930487 | AI27: =SUM(AI23:AI26) -> 17.37308 | AJ27: =AI27/$AI$1*1000 -> 0.51061251 | AL27: =SUM(AL23:AL26) -> 46.35671 | AM27: =AL27/$AL$1*1000 -> 1.1012926 | AO27: =SUM(AO23:AO26) -> 272.38737 | AP27: =AO27/$AO$1*1000 -> 0.56972648
A28: YES | B28: 5102010151 | C28: 5102010151 Other Rev.-Interco-Epidemic problem comp | D28: * CS_Fix Cost | E28: 0 | F28: =E28/$E$1*1000 -> 0 | H28: 0 | I28: =H28/$H$1*1000 -> 0 | K28: 0 | L28: =K28/$K$1*1000 -> 0 | N28: 0 | O28: =N28/$N$1*1000 -> 0 | Q28: 0 | R28: =Q28/$Q$1*1000 -> 0 | T28: 0 | U28: =T28/$T$1*1000 -> 0 | W28: 0 | X28: =W28/$W$1*1000 -> 0 | Z28: 0 | AA28: =Z28/$Z$1*1000 -> 0 | AC28: 0 | AD28: =AC28/$AC$1*1000 -> 0 | AF28: 0 | AG28: =AF28/$AF$1*1000 -> 0 | AI28: 0 | AJ28: =AI28/$AI$1*1000 -> 0 | AL28: 0 | AM28: =AL28/$AL$1*1000 -> 0 | AO28: =H28+E28+K28+N28+Q28+T28+W28+Z28+AC28+AF28+AI28+AL28 -> 0 | AP28: =AO28/$AO$1*1000 -> 0
A29: YES | B29: 5001010200 | C29: 5001010200 Cost of Manufacture - Raw Material | D29: * CS_Fix Cost | E29: 0.17197 | F29: =E29/$E$1*1000 -> 0.0035405901 | H29: 0 | I29: =H29/$H$1*1000 -> 0 | K29: 0 | L29: =K29/$K$1*1000 -> 0 | N29: 0 | O29: =N29/$N$1*1000 -> 0 | Q29: 0.01851 | R29: =Q29/$Q$1*1000 -> 0.00034466706 | T29: 0.00921 | U29: =T29/$T$1*1000 -> 0.00031047735 | W29: 0 | X29: =W29/$W$1*1000 -> 0 | Z29: 0 | AA29: =Z29/$Z$1*1000 -> 0 | AC29: 0.01387 | AD29: =AC29/$AC$1*1000 -> 0.00049066082 | AF29: 0.01495 | AG29: =AF29/$AF$1*1000 -> 0.00057037122 | AI29: 0 | AJ29: =AI29/$AI$1*1000 -> 0 | AL29: 0 | AM29: =AL29/$AL$1*1000 -> 0 | AO29: =H29+E29+K29+N29+Q29+T29+W29+Z29+AC29+AF29+AI29+AL29 -> 0.22851 | AP29: =AO29/$AO$1*1000 -> 0.0004779524
A30: YES | B30: 5001010201 | C30: 5001010201 Cost of Manufacture - Raw Material-Freig | D30: * CS_Fix Cost | E30: 0.00056 | F30: =E30/$E$1*1000 -> 1.1529513e-05 | H30: 0 | I30: =H30/$H$1*1000 -> 0 | K30: 0 | L30: =K30/$K$1*1000 -> 0 | N30: 0 | O30: =N30/$N$1*1000 -> 0 | Q30: 0.00247 | R30: =Q30/$Q$1*1000 -> 4.599285e-05 | T30: 0.17793 | U30: =T30/$T$1*1000 -> 0.0059981796 | W30: 0 | X30: =W30/$W$1*1000 -> 0 | Z30: 0 | AA30: =Z30/$Z$1*1000 -> 0 | AC30: 0.00228 | AD30: =AC30/$AC$1*1000 -> 8.0656573e-05 | AF30: 0 | AG30: =AF30/$AF$1*1000 -> 0 | AI30: 0 | AJ30: =AI30/$AI$1*1000 -> 0 | AL30: 0 | AM30: =AL30/$AL$1*1000 -> 0 | AO30: =H30+E30+K30+N30+Q30+T30+W30+Z30+AC30+AF30+AI30+AL30 -> 0.18324 | AP30: =AO30/$AO$1*1000 -> 0.0003832655
A31: YES | B31: 5207000011 | C31: 5207000011 Gain of tangible asset disposal | D31: * CS_Fix Cost | E31: 0 | F31: =E31/$E$1*1000 -> 0 | H31: 0 | I31: =H31/$H$1*1000 -> 0 | K31: 0 | L31: =K31/$K$1*1000 -> 0 | N31: 0 | O31: =N31/$N$1*1000 -> 0 | Q31: 0 | R31: =Q31/$Q$1*1000 -> 0 | T31: 0 | U31: =T31/$T$1*1000 -> 0 | W31: 0 | X31: =W31/$W$1*1000 -> 0 | Z31: 0 | AA31: =Z31/$Z$1*1000 -> 0 | AC31: 0 | AD31: =AC31/$AC$1*1000 -> 0 | AF31: 0 | AG31: =AF31/$AF$1*1000 -> 0 | AI31: 0 | AJ31: =AI31/$AI$1*1000 -> 0 | AL31: 0 | AM31: =AL31/$AL$1*1000 -> 0 | AO31: =H31+E31+K31+N31+Q31+T31+W31+Z31+AC31+AF31+AI31+AL31 -> 0 | AP31: =AO31/$AO$1*1000 -> 0
A32: YES | B32: 5207000012 | C32: 5207000012 Loss of tangible asset sold | D32: * CS_Fix Cost | E32: 0 | F32: =E32/$E$1*1000 -> 0 | H32: 0 | I32: =H32/$H$1*1000 -> 0 | K32: 0 | L32: =K32/$K$1*1000 -> 0 | N32: 0 | O32: =N32/$N$1*1000 -> 0 | Q32: 0 | R32: =Q32/$Q$1*1000 -> 0 | T32: 0 | U32: =T32/$T$1*1000 -> 0 | W32: 0 | X32: =W32/$W$1*1000 -> 0 | Z32: 0 | AA32: =Z32/$Z$1*1000 -> 0 | AC32: 0 | AD32: =AC32/$AC$1*1000 -> 0 | AF32: 0 | AG32: =AF32/$AF$1*1000 -> 0 | AI32: 0 | AJ32: =AI32/$AI$1*1000 -> 0 | AL32: 0 | AM32: =AL32/$AL$1*1000 -> 0 | AO32: =H32+E32+K32+N32+Q32+T32+W32+Z32+AC32+AF32+AI32+AL32 -> 0 | AP32: =AO32/$AO$1*1000 -> 0
A33: YES | B33: 5207000022 | C33: 5207000022 Loss of intangible asset disposal | D33: * CS_Fix Cost | E33: 0 | F33: =E33/$E$1*1000 -> 0 | H33: 0 | I33: =H33/$H$1*1000 -> 0 | K33: 0 | L33: =K33/$K$1*1000 -> 0 | N33: 0 | O33: =N33/$N$1*1000 -> 0 | Q33: 0 | R33: =Q33/$Q$1*1000 -> 0 | T33: 0 | U33: =T33/$T$1*1000 -> 0 | W33: 0 | X33: =W33/$W$1*1000 -> 0 | Z33: 0 | AA33: =Z33/$Z$1*1000 -> 0 | AC33: 0 | AD33: =AC33/$AC$1*1000 -> 0 | AF33: 0 | AG33: =AF33/$AF$1*1000 -> 0 | AI33: 0 | AJ33: =AI33/$AI$1*1000 -> 0 | AL33: 0 | AM33: =AL33/$AL$1*1000 -> 0 | AO33: =H33+E33+K33+N33+Q33+T33+W33+Z33+AC33+AF33+AI33+AL33 -> 0 | AP33: =AO33/$AO$1*1000 -> 0
A34: YES | B34: 5301060000 | C34: 5301060000 Other Income-Subsidy income | D34: * CS_Fix Cost | E34: 0 | F34: =E34/$E$1*1000 -> 0 | H34: 0 | I34: =H34/$H$1*1000 -> 0 | K34: 0 | L34: =K34/$K$1*1000 -> 0 | N34: 0 | O34: =N34/$N$1*1000 -> 0 | Q34: 0 | R34: =Q34/$Q$1*1000 -> 0 | T34: 0 | U34: =T34/$T$1*1000 -> 0 | W34: 0 | X34: =W34/$W$1*1000 -> 0 | Z34: 0 | AA34: =Z34/$Z$1*1000 -> 0 | AC34: 0 | AD34: =AC34/$AC$1*1000 -> 0 | AF34: 0 | AG34: =AF34/$AF$1*1000 -> 0 | AI34: 0 | AJ34: =AI34/$AI$1*1000 -> 0 | AL34: 0 | AM34: =AL34/$AL$1*1000 -> 0 | AO34: =H34+E34+K34+N34+Q34+T34+W34+Z34+AC34+AF34+AI34+AL34 -> 0 | AP34: =AO34/$AO$1*1000 -> 0
A35: YES | B35: 5301999999 | C35: 5301999999 Non-operation revenue-Other | D35: * CS_Fix Cost | E35: 0 | F35: =E35/$E$1*1000 -> 0 | H35: 0 | I35: =H35/$H$1*1000 -> 0 | K35: 0 | L35: =K35/$K$1*1000 -> 0 | N35: 0 | O35: =N35/$N$1*1000 -> 0 | Q35: 0 | R35: =Q35/$Q$1*1000 -> 0 | T35: 0 | U35: =T35/$T$1*1000 -> 0 | W35: 0 | X35: =W35/$W$1*1000 -> 0 | Z35: 0 | AA35: =Z35/$Z$1*1000 -> 0 | AC35: 0 | AD35: =AC35/$AC$1*1000 -> 0 | AF35: 0 | AG35: =AF35/$AF$1*1000 -> 0 | AI35: -0.06594 | AJ35: =AI35/$AI$1*1000 -> -0.0019380437 | AL35: 0 | AM35: =AL35/$AL$1*1000 -> 0 | AO35: =H35+E35+K35+N35+Q35+T35+W35+Z35+AC35+AF35+AI35+AL35 -> -0.06594 | AP35: =AO35/$AO$1*1000 -> -0.00013792036
A36: YES | B36: 5405030000 | C36: 5405030000 Other cost-others | D36: * CS_Fix Cost | E36: 0.0094 | F36: =E36/$E$1*1000 -> 0.00019353112 | H36: =13.41/1000 -> 0.01341 | I36: =H36/$H$1*1000 -> 0.00029131275 | K36: =738.36/1000 -> 0.73836 | L36: =K36/$K$1*1000 -> 0.015934566 | N36: 0.04654 | O36: =N36/$N$1*1000 -> 0.00094281142 | Q36: 0.00024 | R36: =Q36/$Q$1*1000 -> 4.4689409e-06 | T36: -0.03325 | U36: =T36/$T$1*1000 -> -0.0011208873 | W36: 0.1626 | X36: =W36/$W$1*1000 -> 0.0038846549 | Z36: 0.10378 | AA36: =Z36/$Z$1*1000 -> 0.0032454577 | AC36: 0.13156 | AD36: =AC36/$AC$1*1000 -> 0.0046540258 | AF36: 0 | AG36: =AF36/$AF$1*1000 -> 0 | AI36: 0.29868 | AJ36: =AI36/$AI$1*1000 -> 0.0087785093 | AL36: 0.00145 | AM36: =AL36/$AL$1*1000 -> 3.4447533e-05 | AO36: =H36+E36+K36+N36+Q36+T36+W36+Z36+AC36+AF36+AI36+AL36 -> 1.47277 | AP36: =AO36/$AO$1*1000 -> 0.0030804515
A37: YES | B37: 5601050000 | C37: 5601050000 Non-Operating Expense - Penalty | D37: * CS_Fix Cost | E37: 0 | F37: =E37/$E$1*1000 -> 0 | H37: 0 | I37: =H37/$H$1*1000 -> 0 | K37: 0 | L37: =K37/$K$1*1000 -> 0 | N37: 0 | O37: =N37/$N$1*1000 -> 0 | Q37: 0 | R37: =Q37/$Q$1*1000 -> 0 | T37: 0.002 | U37: =T37/$T$1*1000 -> 6.7421791e-05 | W37: 0.01063 | X37: =W37/$W$1*1000 -> 0.00025395991 | Z37: 0 | AA37: =Z37/$Z$1*1000 -> 0 | AC37: 0.05263 | AD37: =AC37/$AC$1*1000 -> 0.0018618226 | AF37: 0 | AG37: =AF37/$AF$1*1000 -> 0 | AI37: 0 | AJ37: =AI37/$AI$1*1000 -> 0 | AL37: 0 | AM37: =AL37/$AL$1*1000 -> 0 | AO37: =H37+E37+K37+N37+Q37+T37+W37+Z37+AC37+AF37+AI37+AL37 -> 0.06526 | AP37: =AO37/$AO$1*1000 -> 0.00013649807
A38: YES | B38: 5601050100 | C38: 5601050100 Non-operation Expense-Others | D38: * CS_Fix Cost | E38: 0.01682 | F38: =E38/$E$1*1000 -> 0.00034629717 | H38: 0 | I38: =H38/$H$1*1000 -> 0 | K38: 0 | L38: =K38/$K$1*1000 -> 0 | N38: 0 | O38: =N38/$N$1*1000 -> 0 | Q38: 0 | R38: =Q38/$Q$1*1000 -> 0 | T38: 0 | U38: =T38/$T$1*1000 -> 0 | W38: 0 | X38: =W38/$W$1*1000 -> 0 | Z38: 0 | AA38: =Z38/$Z$1*1000 -> 0 | AC38: 0 | AD38: =AC38/$AC$1*1000 -> 0 | AF38: 0 | AG38: =AF38/$AF$1*1000 -> 0 | AI38: 0 | AJ38: =AI38/$AI$1*1000 -> 0 | AL38: 0.03479 | AM38: =AL38/$AL$1*1000 -> 0.00082650322 | AO38: =H38+E38+K38+N38+Q38+T38+W38+Z38+AC38+AF38+AI38+AL38 -> 0.05161 | AP38: =AO38/$AO$1*1000 -> 0.00010794768
A39: YES | B39: 5102040893 | C39: 5102040893 Other revenue-Charge out-Test Expense | D39: * CS_Fix Cost | T39: 0 | U39: =T39/$T$1*1000 -> 0 | W39: 0 | X39: =W39/$W$1*1000 -> 0 | Z39: 0 | AA39: =Z39/$Z$1*1000 -> 0 | AC39: 0 | AD39: =AC39/$AC$1*1000 -> 0 | AF39: 0 | AG39: =AF39/$AF$1*1000 -> 0 | AI39: 0 | AJ39: =AI39/$AI$1*1000 -> 0 | AL39: 0 | AM39: =AL39/$AL$1*1000 -> 0 | AO39: =H39+E39+K39+N39+Q39+T39+W39+Z39+AC39+AF39+AI39+AL39 -> 0 | AP39: =AO39/$AO$1*1000 -> 0
A40: YES | B40: 5801000041 | C40: 5801000041 Previous year Sundry cost | D40: * CS_Fix Cost | E40: 0 | F40: =E40/$E$1*1000 -> 0 | H40: 0 | I40: =H40/$H$1*1000 -> 0 | K40: 0 | L40: =K40/$K$1*1000 -> 0 | N40: 0 | O40: =N40/$N$1*1000 -> 0 | Q40: 0 | R40: =Q40/$Q$1*1000 -> 0 | T40: 0 | U40: =T40/$T$1*1000 -> 0 | W40: 0 | X40: =W40/$W$1*1000 -> 0 | Z40: 0 | AA40: =Z40/$Z$1*1000 -> 0 | AC40: 0 | AD40: =AC40/$AC$1*1000 -> 0 | AF40: 0 | AG40: =AF40/$AF$1*1000 -> 0 | AI40: 0 | AJ40: =AI40/$AI$1*1000 -> 0 | AL40: 0 | AM40: =AL40/$AL$1*1000 -> 0 | AO40: =H40+E40+K40+N40+Q40+T40+W40+Z40+AC40+AF40+AI40+AL40 -> 0 | AP40: =AO40/$AO$1*1000 -> 0
A41: YES | B41: 6666010322 | C41: 6666010322 fuel allowance | D41: * CS_Fix Cost | E41: 2.19309 | F41: =E41/$E$1*1000 -> 0.045152251 | H41: 0.51196 | I41: =H41/$H$1*1000 -> 0.011121587 | K41: 2.69789 | L41: =K41/$K$1*1000 -> 0.058223234 | N41: 1.01857 | O41: =N41/$N$1*1000 -> 0.020634281 | Q41: 1.25877 | R41: =Q41/$Q$1*1000 -> 0.023439036 | T41: 1.28891 | U41: =T41/$T$1*1000 -> 0.04345031 | W41: 0.95107 | X41: =W41/$W$1*1000 -> 0.022721886 | Z41: 1.49429 | AA41: =Z41/$Z$1*1000 -> 0.04673015 | AC41: 1.20561 | AD41: =AC41/$AC$1*1000 -> 0.042649285 | AF41: 1.3803 | AG41: =AF41/$AF$1*1000 -> 0.052661096 | AI41: 0.62515 | AJ41: =AI41/$AI$1*1000 -> 0.018373795 | AL41: 1.46341 | AM41: =AL41/$AL$1*1000 -> 0.034766113 | AO41: =H41+E41+K41+N41+Q41+T41+W41+Z41+AC41+AF41+AI41+AL41 -> 16.08902 | AP41: =AO41/$AO$1*1000 -> 0.033651857
A42: YES | B42: 6666020101 | C42: 6666020101 Entertainment | D42: * CS_Fix Cost | E42: 0 | F42: =E42/$E$1*1000 -> 0 | H42: 6.83876 | I42: =H42/$H$1*1000 -> 0.14856212 | K42: 5.84951 | L42: =K42/$K$1*1000 -> 0.12623843 | N42: 5.145 | O42: =N42/$N$1*1000 -> 0.10422786 | Q42: 5.07662 | R42: =Q42/$Q$1*1000 -> 0.094529644 | T42: -4.30157 | U42: =T42/$T$1*1000 -> -0.14500978 | W42: 4.26751 | X42: =W42/$W$1*1000 -> 0.10195451 | Z42: 3.52541 | AA42: =Z42/$Z$1*1000 -> 0.1102483 | AC42: -0.60928 | AD42: =AC42/$AC$1*1000 -> -0.0215537 | AF42: 0.16573 | AG42: =AF42/$AF$1*1000 -> 0.0063229179 | AI42: -0.39021 | AJ42: =AI42/$AI$1*1000 -> -0.011468669 | AL42: -33.39257 | AM42: =AL42/$AL$1*1000 -> -0.79330459 | AO42: =H42+E42+K42+N42+Q42+T42+W42+Z42+AC42+AF42+AI42+AL42 -> -7.82509 | AP42: =AO42/$AO$1*1000 -> -0.016366989
A43: YES | B43: 6666020201 | C43: 6666020201 Domestic business travel | D43: * CS_Fix Cost | E43: 0.0026 | F43: =E43/$E$1*1000 -> 5.3529884e-05 | H43: 0.3025 | I43: =H43/$H$1*1000 -> 0.0065713727 | K43: 0.13764 | L43: =K43/$K$1*1000 -> 0.0029704124 | N43: 0 | O43: =N43/$N$1*1000 -> 0 | Q43: 0 | R43: =Q43/$Q$1*1000 -> 0 | T43: 8.55229 | U43: =T43/$T$1*1000 -> 0.28830535 | W43: 0 | X43: =W43/$W$1*1000 -> 0 | Z43: 0.07903 | AA43: =Z43/$Z$1*1000 -> 0.0024714639 | AC43: 0.00309 | AD43: =AC43/$AC$1*1000 -> 0.00010931088 | AF43: 0.18618 | AG43: =AF43/$AF$1*1000 -> 0.0071031246 | AI43: 0.01529 | AJ43: =AI43/$AI$1*1000 -> 0.00044938867 | AL43: 0.21907 | AM43: =AL43/$AL$1*1000 -> 0.0052044283 | AO43: =H43+E43+K43+N43+Q43+T43+W43+Z43+AC43+AF43+AI43+AL43 -> 9.49769 | AP43: =AO43/$AO$1*1000 -> 0.019865405
A44: YES | B44: 6666020202 | C44: 6666020202 Overseas business travel | D44: * CS_Fix Cost | E44: 0 | F44: =E44/$E$1*1000 -> 0 | H44: 0 | I44: =H44/$H$1*1000 -> 0 | K44: 0.16911 | L44: =K44/$K$1*1000 -> 0.0036495673 | N44: 0 | O44: =N44/$N$1*1000 -> 0 | Q44: 0.0106 | R44: =Q44/$Q$1*1000 -> 0.00019737822 | T44: 0.23982 | U44: =T44/$T$1*1000 -> 0.0080845469 | W44: 0.61255 | X44: =W44/$W$1*1000 -> 0.01463435 | Z44: 0.1768 | AA44: =Z44/$Z$1*1000 -> 0.005528974 | AC44: 0 | AD44: =AC44/$AC$1*1000 -> 0 | AF44: 0 | AG44: =AF44/$AF$1*1000 -> 0 | AI44: 0 | AJ44: =AI44/$AI$1*1000 -> 0 | AL44: 0.17168 | AM44: =AL44/$AL$1*1000 -> 0.0040785879 | AO44: =H44+E44+K44+N44+Q44+T44+W44+Z44+AC44+AF44+AI44+AL44 -> 1.38056 | AP44: =AO44/$AO$1*1000 -> 0.0028875847
A45: YES | B45: 6666020204 | C45: 6666020204 Travel expense pay to agency | D45: * CS_Fix Cost | E45: 0.02159 | F45: =E45/$E$1*1000 -> 0.00044450392 | H45: 0.02007 | I45: =H45/$H$1*1000 -> 0.00043599157 | K45: 0 | L45: =K45/$K$1*1000 -> 0 | N45: 0.01149 | O45: =N45/$N$1*1000 -> 0.00023276543 | Q45: 0.05588 | R45: =Q45/$Q$1*1000 -> 0.0010405184 | T45: 0.04219 | U45: =T45/$T$1*1000 -> 0.0014222627 | W45: 0.23422 | X45: =W45/$W$1*1000 -> 0.0055957188 | Z45: 3.81721 | AA45: =Z45/$Z$1*1000 -> 0.11937361 | AC45: 0.17052 | AD45: =AC45/$AC$1*1000 -> 0.0060322626 | AF45: -0.00016 | AG45: =AF45/$AF$1*1000 -> -6.1043074e-06 | AI45: 0 | AJ45: =AI45/$AI$1*1000 -> 0 | AL45: 0.15381 | AM45: =AL45/$AL$1*1000 -> 0.0036540517 | AO45: =H45+E45+K45+N45+Q45+T45+W45+Z45+AC45+AF45+AI45+AL45 -> 4.52682 | AP45: =AO45/$AO$1*1000 -> 0.0094683143
A46: YES | B46: 6666020205 | C46: 6666020205 Business travel-other | D46: * CS_Fix Cost | E46: 0 | F46: =E46/$E$1*1000 -> 0 | H46: 0 | I46: =H46/$H$1*1000 -> 0 | K46: 0 | L46: =K46/$K$1*1000 -> 0 | N46: 0 | O46: =N46/$N$1*1000 -> 0 | Q46: 0 | R46: =Q46/$Q$1*1000 -> 0 | T46: 0 | U46: =T46/$T$1*1000 -> 0 | W46: 0 | X46: =W46/$W$1*1000 -> 0 | Z46: 0 | AA46: =Z46/$Z$1*1000 -> 0 | AC46: 0 | AD46: =AC46/$AC$1*1000 -> 0 | AF46: 0 | AG46: =AF46/$AF$1*1000 -> 0 | AI46: -0.18314 | AJ46: =AI46/$AI$1*1000 -> -0.0053826711 | AL46: 0 | AM46: =AL46/$AL$1*1000 -> 0 | AO46: =H46+E46+K46+N46+Q46+T46+W46+Z46+AC46+AF46+AI46+AL46 -> -0.18314 | AP46: =AO46/$AO$1*1000 -> -0.00038305634
A47: YES | B47: 6666020301 | C47: 6666020301 Staff communic | D47: * CS_Fix Cost | E47: 0 | F47: =E47/$E$1*1000 -> 0 | H47: 1.18363 | I47: =H47/$H$1*1000 -> 0.025712641 | K47: 1.00936 | L47: =K47/$K$1*1000 -> 0.021783024 | N47: 0.50942 | O47: =N47/$N$1*1000 -> 0.010319875 | Q47: 0.66441 | R47: =Q47/$Q$1*1000 -> 0.012371704 | T47: -0.12345 | U47: =T47/$T$1*1000 -> -0.00416161 | W47: 0.36291 | X47: =W47/$W$1*1000 -> 0.0086702344 | Z47: 0.07827 | AA47: =Z47/$Z$1*1000 -> 0.0024476968 | AC47: 0.29109 | AD47: =AC47/$AC$1*1000 -> 0.01029751 | AF47: 0.77172 | AG47: =AF47/$AF$1*1000 -> 0.0294426 | AI47: 0.41515 | AJ47: =AI47/$AI$1*1000 -> 0.012201681 | AL47: -0.40917 | AM47: =AL47/$AL$1*1000 -> -0.0097206186 | AO47: =H47+E47+K47+N47+Q47+T47+W47+Z47+AC47+AF47+AI47+AL47 -> 4.75334 | AP47: =AO47/$AO$1*1000 -> 0.0099421044
A48: YES | B48: 6666020302 | C48: 6666020302 Communication Expenses | D48: * CS_Fix Cost | E48: 0 | F48: =E48/$E$1*1000 -> 0 | H48: 0 | I48: =H48/$H$1*1000 -> 0 | K48: 0 | L48: =K48/$K$1*1000 -> 0 | N48: 0 | O48: =N48/$N$1*1000 -> 0 | Q48: 0 | R48: =Q48/$Q$1*1000 -> 0 | T48: 0 | U48: =T48/$T$1*1000 -> 0 | W48: 0 | X48: =W48/$W$1*1000 -> 0 | Z48: 0 | AA48: =Z48/$Z$1*1000 -> 0 | AC48: 0 | AD48: =AC48/$AC$1*1000 -> 0 | AF48: 0 | AG48: =AF48/$AF$1*1000 -> 0 | AI48: 0 | AJ48: =AI48/$AI$1*1000 -> 0 | AL48: 0 | AM48: =AL48/$AL$1*1000 -> 0 | AO48: =H48+E48+K48+N48+Q48+T48+W48+Z48+AC48+AF48+AI48+AL48 -> 0 | AP48: =AO48/$AO$1*1000 -> 0
A49: YES | B49: 6666020403 | C49: 6666020403 Company car expense | D49: * CS_Fix Cost | T49: 0.00718 | W49: 0.02701 | X49: =W49/$W$1*1000 -> 0.0006452923 | Z49: 0 | AA49: =Z49/$Z$1*1000 -> 0 | AC49: 0 | AD49: =AC49/$AC$1*1000 -> 0 | AF49: 0 | AG49: =AF49/$AF$1*1000 -> 0 | AI49: 0 | AJ49: =AI49/$AI$1*1000 -> 0 | AL49: 0.13012 | AM49: =AL49/$AL$1*1000 -> 0.0030912503 | AO49: =H49+E49+K49+N49+Q49+T49+W49+Z49+AC49+AF49+AI49+AL49 -> 0.16431 | AP49: =AO49/$AO$1*1000 -> 0.00034367143
A50: YES | B50: 6666020405 | C50: 6666020405 Company car expense - maintenance fees | D50: * CS_Fix Cost | E50: 0 | F50: =E50/$E$1*1000 -> 0 | H50: 0 | I50: =H50/$H$1*1000 -> 0 | K50: 0 | L50: =K50/$K$1*1000 -> 0 | N50: 0 | O50: =N50/$N$1*1000 -> 0 | Q50: 0 | R50: =Q50/$Q$1*1000 -> 0 | T50: 0 | U50: =T50/$T$1*1000 -> 0 | W50: 0 | X50: =W50/$W$1*1000 -> 0 | Z50: 0 | AA50: =Z50/$Z$1*1000 -> 0 | AC50: 0 | AD50: =AC50/$AC$1*1000 -> 0 | AF50: 0 | AG50: =AF50/$AF$1*1000 -> 0 | AI50: 0 | AJ50: =AI50/$AI$1*1000 -> 0 | AL50: 0 | AM50: =AL50/$AL$1*1000 -> 0 | AO50: =H50+E50+K50+N50+Q50+T50+W50+Z50+AC50+AF50+AI50+AL50 -> 0 | AP50: =AO50/$AO$1*1000 -> 0
A51: YES | B51: 6666020495 | C51: 6666020495 Non-deductible expense-travel. | D51: * CS_Fix Cost | E51: 0.03156 | F51: =E51/$E$1*1000 -> 0.00064977044 | H51: 0.09104 | I51: =H51/$H$1*1000 -> 0.0019777116 | K51: 0.25476 | L51: =K51/$K$1*1000 -> 0.0054979822 | N51: 0.2377 | O51: =N51/$N$1*1000 -> 0.0048153475 | Q51: 0.10084 | R51: =Q51/$Q$1*1000 -> 0.0018777 | T51: 0.12813 | U51: =T51/$T$1*1000 -> 0.004319377 | W51: 0.11208 | X51: =W51/$W$1*1000 -> 0.0026776883 | Z51: 0.80861 | AA51: =Z51/$Z$1*1000 -> 0.025287238 | AC51: 0.21574 | AD51: =AC51/$AC$1*1000 -> 0.0076319513 | AF51: 0.00656 | AG51: =AF51/$AF$1*1000 -> 0.0002502766 | AI51: 0.08485 | AJ51: =AI51/$AI$1*1000 -> 0.0024938279 | AL51: 1.14024 | AM51: =AL51/$AL$1*1000 -> 0.02708859 | AO51: =H51+E51+K51+N51+Q51+T51+W51+Z51+AC51+AF51+AI51+AL51 -> 3.21211 | AP51: =AO51/$AO$1*1000 -> 0.0067184618
A52: YES | B52: 6666020504 | C52: 6666020504 Newspaper and Periodicals expenditure | D52: * CS_Fix Cost | E52: 0 | F52: =E52/$E$1*1000 -> 0 | H52: 0 | I52: =H52/$H$1*1000 -> 0 | K52: 0 | L52: =K52/$K$1*1000 -> 0 | N52: 0 | O52: =N52/$N$1*1000 -> 0 | Q52: 0.02649 | R52: =Q52/$Q$1*1000 -> 0.00049325935 | T52: 0 | U52: =T52/$T$1*1000 -> 0 | W52: 0.01248 | X52: =W52/$W$1*1000 -> 0.00029815801 | Z52: 0.26041 | AA52: =Z52/$Z$1*1000 -> 0.0081436658 | AC52: 0 | AD52: =AC52/$AC$1*1000 -> 0 | AF52: 0 | AG52: =AF52/$AF$1*1000 -> 0 | AI52: 0 | AJ52: =AI52/$AI$1*1000 -> 0 | AL52: 0 | AM52: =AL52/$AL$1*1000 -> 0 | AO52: =H52+E52+K52+N52+Q52+T52+W52+Z52+AC52+AF52+AI52+AL52 -> 0.29938 | AP52: =AO52/$AO$1*1000 -> 0.00062618437
A53: YES | B53: 6666020508 | C53: 6666020508 Postage | D53: * CS_Fix Cost | E53: 0 | F53: =E53/$E$1*1000 -> 0 | H53: 0 | I53: =H53/$H$1*1000 -> 0 | K53: 0 | L53: =K53/$K$1*1000 -> 0 | N53: 0.00496 | O53: =N53/$N$1*1000 -> 0.00010048012 | Q53: 0 | R53: =Q53/$Q$1*1000 -> 0 | T53: 0 | U53: =T53/$T$1*1000 -> 0 | W53: 0.01197 | X53: =W53/$W$1*1000 -> 0.00028597367 | Z53: 0 | AA53: =Z53/$Z$1*1000 -> 0 | AC53: 0.00744 | AD53: =AC53/$AC$1*1000 -> 0.00026319513 | AF53: 0 | AG53: =AF53/$AF$1*1000 -> 0 | AI53: 0 | AJ53: =AI53/$AI$1*1000 -> 0 | AL53: 0.0243 | AM53: =AL53/$AL$1*1000 -> 0.00057729314 | AO53: =H53+E53+K53+N53+Q53+T53+W53+Z53+AC53+AF53+AI53+AL53 -> 0.04867 | AP53: =AO53/$AO$1*1000 -> 0.00010179836
A54: YES | B54: 6666020602 | C54: 6666020602 Training costs Outside the group | D54: * CS_Fix Cost | E54: 0 | F54: =E54/$E$1*1000 -> 0 | H54: 0.55286 | I54: =H54/$H$1*1000 -> 0.01201008 | K54: 0.08608 | L54: =K54/$K$1*1000 -> 0.0018576947 | N54: 0 | O54: =N54/$N$1*1000 -> 0 | Q54: 0 | R54: =Q54/$Q$1*1000 -> 0 | T54: 0.1525 | U54: =T54/$T$1*1000 -> 0.0051409115 | W54: 1.40706 | X54: =W54/$W$1*1000 -> 0.033615883 | Z54: 1.37209 | AA54: =Z54/$Z$1*1000 -> 0.042908653 | AC54: 0.10931 | AD54: =AC54/$AC$1*1000 -> 0.0038669167 | AF54: 0.58105 | AG54: =AF54/$AF$1*1000 -> 0.022168174 | AI54: 0.44964 | AJ54: =AI54/$AI$1*1000 -> 0.013215377 | AL54: -0.00355 | AM54: =AL54/$AL$1*1000 -> -8.4337063e-05 | AO54: =H54+E54+K54+N54+Q54+T54+W54+Z54+AC54+AF54+AI54+AL54 -> 4.70704 | AP54: =AO54/$AO$1*1000 -> 0.0098452631
A55: YES | B55: 6666020701 | C55: 6666020701 Enterprise Property Insurance | D55: * CS_Fix Cost | E55: 0 | F55: =E55/$E$1*1000 -> 0 | H55: 0 | I55: =H55/$H$1*1000 -> 0 | K55: 0 | L55: =K55/$K$1*1000 -> 0 | N55: 0 | O55: =N55/$N$1*1000 -> 0 | Q55: 0 | R55: =Q55/$Q$1*1000 -> 0 | T55: 0 | U55: =T55/$T$1*1000 -> 0 | W55: 0 | X55: =W55/$W$1*1000 -> 0 | Z55: 0 | AA55: =Z55/$Z$1*1000 -> 0 | AC55: 0 | AD55: =AC55/$AC$1*1000 -> 0 | AF55: 0 | AG55: =AF55/$AF$1*1000 -> 0 | AI55: 0 | AJ55: =AI55/$AI$1*1000 -> 0 | AL55: 0 | AM55: =AL55/$AL$1*1000 -> 0 | AO55: =H55+E55+K55+N55+Q55+T55+W55+Z55+AC55+AF55+AI55+AL55 -> 0 | AP55: =AO55/$AO$1*1000 -> 0
A56: YES | B56: 6666020802 | C56: 6666020802 Equipment rental cost | D56: * CS_Fix Cost | E56: 15.5325 | F56: =E56/$E$1*1000 -> 0.31978959 | H56: 15.04068 | I56: =H56/$H$1*1000 -> 0.32673691 | K56: 5.99021 | L56: =K56/$K$1*1000 -> 0.12927488 | N56: 10.50561 | O56: =N56/$N$1*1000 -> 0.21282357 | Q56: 11.03322 | R56: =Q56/$Q$1*1000 -> 0.20544503 | T56: 7.36439 | U56: =T56/$T$1*1000 -> 0.24826018 | W56: 12.21214 | X56: =W56/$W$1*1000 -> 0.29175861 | Z56: 10.97025 | AA56: =Z56/$Z$1*1000 -> 0.34306689 | AC56: 10.758 | AD56: =AC56/$AC$1*1000 -> 0.38057167 | AF56: 10.8062 | AG56: =AF56/$AF$1*1000 -> 0.41227729 | AI56: 10.7098 | AJ56: =AI56/$AI$1*1000 -> 0.31477193 | AL56: 12.50106 | AM56: =AL56/$AL$1*1000 -> 0.29698667 | AO56: =H56+E56+K56+N56+Q56+T56+W56+Z56+AC56+AF56+AI56+AL56 -> 133.42406 | AP56: =AO56/$AO$1*1000 -> 0.27907028
A57: YES | B57: 6666020803 | C57: 6666020803 Car rental cost | D57: * CS_Fix Cost | E57: 4.81971 | F57: =E57/$E$1*1000 -> 0.099230199 | H57: 4.86478 | I57: =H57/$H$1*1000 -> 0.10568027 | K57: 4.7008 | L57: =K57/$K$1*1000 -> 0.10144809 | N57: 3.00868 | O57: =N57/$N$1*1000 -> 0.060950104 | Q57: 3.58813 | R57: =Q57/$Q$1*1000 -> 0.066813087 | T57: 4.63247 | U57: =T57/$T$1*1000 -> 0.15616471 | W57: 4.19444 | X57: =W57/$W$1*1000 -> 0.10020881 | Z57: 9.68104 | AA57: =Z57/$Z$1*1000 -> 0.3027501 | AC57: 6.35918 | AD57: =AC57/$AC$1*1000 -> 0.22496038 | AF57: -0.24146 | AG57: =AF57/$AF$1*1000 -> -0.0092121628 | AI57: 4.73164 | AJ57: =AI57/$AI$1*1000 -> 0.13906772 | AL57: 0.19891 | AM57: =AL57/$AL$1*1000 -> 0.0047254888 | AO57: =H57+E57+K57+N57+Q57+T57+W57+Z57+AC57+AF57+AI57+AL57 -> 50.53832 | AP57: =AO57/$AO$1*1000 -> 0.10570615
A58: YES | B58: 6666021100 | C58: 6666021100 Consulting fees | D58: * CS_Fix Cost | E58: 10.57577 | F58: =E58/$E$1*1000 -> 0.21773836 | H58: 9.71594 | I58: =H58/$H$1*1000 -> 0.21106467 | K58: 8.5915 | L58: =K58/$K$1*1000 -> 0.18541338 | N58: 6.58522 | O58: =N58/$N$1*1000 -> 0.13340397 | Q58: 6.37014 | R58: =Q58/$Q$1*1000 -> 0.11861575 | T58: 5.96825 | U58: =T58/$T$1*1000 -> 0.20119505 | W58: 6.48555 | X58: =W58/$W$1*1000 -> 0.15494541 | Z58: 6.32448 | AA58: =Z58/$Z$1*1000 -> 0.19778216 | AC58: 4.10628 | AD58: =AC58/$AC$1*1000 -> 0.14526249 | AF58: 4.06163 | AG58: =AF58/$AF$1*1000 -> 0.15495899 | AI58: 4.43257 | AJ58: =AI58/$AI$1*1000 -> 0.13027775 | AL58: -0.31331 | AM58: =AL58/$AL$1*1000 -> -0.0074432804 | AO58: =H58+E58+K58+N58+Q58+T58+W58+Z58+AC58+AF58+AI58+AL58 -> 72.90402 | AP58: =AO58/$AO$1*1000 -> 0.15248633
A59: YES | B59: 6666021104 | C59: 6666021104 Consulting expense-Technical | D59: * CS_Fix Cost | W59: -0.03701 | X59: =W59/$W$1*1000 -> -0.00088420097 | Z59: 0 | AA59: =Z59/$Z$1*1000 -> 0 | AC59: 0 | AD59: =AC59/$AC$1*1000 -> 0 | AF59: 0 | AG59: =AF59/$AF$1*1000 -> 0 | AI59: 0 | AJ59: =AI59/$AI$1*1000 -> 0 | AL59: 0 | AM59: =AL59/$AL$1*1000 -> 0 | AO59: =H59+E59+K59+N59+Q59+T59+W59+Z59+AC59+AF59+AI59+AL59 -> -0.03701 | AP59: =AO59/$AO$1*1000 -> -7.741026e-05
A60: YES | B60: 6666021200 | C60: 6666021200 Audit fee | D60: * CS_Fix Cost | AL60: -0.02719 | AM60: =AL60/$AL$1*1000 -> -0.00064595063 | AO60: =H60+E60+K60+N60+Q60+T60+W60+Z60+AC60+AF60+AI60+AL60 -> -0.02719 | AP60: =AO60/$AO$1*1000 -> -5.687071e-05
A61: YES | B61: 6666021902 | C61: 6666021902 Cleaning fees | D61: * CS_Fix Cost | E61: 7.13263 | F61: =E61/$E$1*1000 -> 0.14684956 | H61: 8.15543 | I61: =H61/$H$1*1000 -> 0.17716486 | K61: 8.7418 | L61: =K61/$K$1*1000 -> 0.18865701 | N61: 7.40652 | O61: =N61/$N$1*1000 -> 0.15004193 | Q61: 6.65347 | R61: =Q61/$Q$1*1000 -> 0.12389152 | T61: 6.07902 | U61: =T61/$T$1*1000 -> 0.20492921 | W61: 5.90889 | X61: =W61/$W$1*1000 -> 0.1411685 | Z61: 8.01798 | AA61: =Z61/$Z$1*1000 -> 0.2507421 | AC61: 6.6217 | AD61: =AC61/$AC$1*1000 -> 0.23424721 | AF61: 7.09478 | AG61: =AF61/$AF$1*1000 -> 0.27067949 | AI61: 7.77853 | AJ61: =AI61/$AI$1*1000 -> 0.22861892 | AL61: 3.87362 | AM61: =AL61/$AL$1*1000 -> 0.092025277 | AO61: =H61+E61+K61+N61+Q61+T61+W61+Z61+AC61+AF61+AI61+AL61 -> 83.46437 | AP61: =AO61/$AO$1*1000 -> 0.1745744
A62: YES | B62: 6666022100 | C62: 6666022100 Security | D62: * CS_Fix Cost | E62: 1.47911 | F62: =E62/$E$1*1000 -> 0.030452533 | H62: 1.22778 | I62: =H62/$H$1*1000 -> 0.026671735 | K62: 1.33541 | L62: =K62/$K$1*1000 -> 0.028819518 | N62: 1.29905 | O62: =N62/$N$1*1000 -> 0.026316269 | Q62: 1.32657 | R62: =Q62/$Q$1*1000 -> 0.024701512 | T62: 1.12761 | U62: =T62/$T$1*1000 -> 0.038012743 | W62: 1.03947 | X62: =W62/$W$1*1000 -> 0.024833839 | Z62: 0.82146 | AA62: =Z62/$Z$1*1000 -> 0.025689089 | AC62: 1.01704 | AD62: =AC62/$AC$1*1000 -> 0.035978492 | AF62: 1.11421 | AG62: =AF62/$AF$1*1000 -> 0.042509252 | AI62: 1.05209 | AJ62: =AI62/$AI$1*1000 -> 0.030921996 | AL62: 0.97938 | AM62: =AL62/$AL$1*1000 -> 0.023267052 | AO62: =H62+E62+K62+N62+Q62+T62+W62+Z62+AC62+AF62+AI62+AL62 -> 13.81918 | AP62: =AO62/$AO$1*1000 -> 0.028904251
A63: YES | B63: 6666022300 | C63: 6666022300 Association dues | D63: * CS_Fix Cost | E63: 0 | F63: =E63/$E$1*1000 -> 0 | H63: 0 | I63: =H63/$H$1*1000 -> 0 | K63: 0 | L63: =K63/$K$1*1000 -> 0 | N63: 0 | O63: =N63/$N$1*1000 -> 0 | Q63: 0 | R63: =Q63/$Q$1*1000 -> 0 | T63: 0 | U63: =T63/$T$1*1000 -> 0 | W63: 0 | X63: =W63/$W$1*1000 -> 0 | Z63: 0 | AA63: =Z63/$Z$1*1000 -> 0 | AC63: 0 | AD63: =AC63/$AC$1*1000 -> 0 | AF63: 0 | AG63: =AF63/$AF$1*1000 -> 0 | AI63: 0 | AJ63: =AI63/$AI$1*1000 -> 0 | AL63: 0 | AM63: =AL63/$AL$1*1000 -> 0 | AO63: =H63+E63+K63+N63+Q63+T63+W63+Z63+AC63+AF63+AI63+AL63 -> 0 | AP63: =AO63/$AO$1*1000 -> 0
A64: YES | B64: 6666029700 | C64: 6666029700 Service fee recharge | D64: * CS_Fix Cost | E64: 0 | F64: =E64/$E$1*1000 -> 0 | H64: 0 | I64: =H64/$H$1*1000 -> 0 | K64: 0 | L64: =K64/$K$1*1000 -> 0 | N64: 0 | O64: =N64/$N$1*1000 -> 0 | Q64: 0 | R64: =Q64/$Q$1*1000 -> 0 | T64: 0 | U64: =T64/$T$1*1000 -> 0 | W64: 0 | X64: =W64/$W$1*1000 -> 0 | Z64: 0 | AA64: =Z64/$Z$1*1000 -> 0 | AC64: 0 | AD64: =AC64/$AC$1*1000 -> 0 | AF64: 0 | AG64: =AF64/$AF$1*1000 -> 0 | AI64: 0 | AJ64: =AI64/$AI$1*1000 -> 0 | AL64: 0 | AM64: =AL64/$AL$1*1000 -> 0 | AO64: =H64+E64+K64+N64+Q64+T64+W64+Z64+AC64+AF64+AI64+AL64 -> 0 | AP64: =AO64/$AO$1*1000 -> 0
A65: YES | B65: 6666029900 | C65: 6666029900 Sundry Expenses | D65: * CS_Fix Cost | E65: 0 | F65: =E65/$E$1*1000 -> 0 | H65: 0 | I65: =H65/$H$1*1000 -> 0 | K65: 0 | L65: =K65/$K$1*1000 -> 0 | N65: 0 | O65: =N65/$N$1*1000 -> 0 | Q65: 0 | R65: =Q65/$Q$1*1000 -> 0 | T65: 0.0167 | U65: =T65/$T$1*1000 -> 0.00056297195 | W65: 0 | X65: =W65/$W$1*1000 -> 0 | Z65: 0 | AA65: =Z65/$Z$1*1000 -> 0 | AC65: 0 | AD65: =AC65/$AC$1*1000 -> 0 | AF65: 0 | AG65: =AF65/$AF$1*1000 -> 0 | AI65: 0 | AJ65: =AI65/$AI$1*1000 -> 0 | AL65: 0.05916 | AM65: =AL65/$AL$1*1000 -> 0.0014054593 | AO65: =H65+E65+K65+N65+Q65+T65+W65+Z65+AC65+AF65+AI65+AL65 -> 0.07586 | AP65: =AO65/$AO$1*1000 -> 0.00015866907
A66: YES | B66: 6666029996 | C66: 6666029996 Non-deductible expense-travel. | D66: * CS_Fix Cost | AF66: 0.103 | AG66: =AF66/$AF$1*1000 -> 0.0039296479 | AI66: 0 | AJ66: =AI66/$AI$1*1000 -> 0 | AL66: 0.07073 | AM66: =AL66/$AL$1*1000 -> 0.0016803269 | AO66: =H66+E66+K66+N66+Q66+T66+W66+Z66+AC66+AF66+AI66+AL66 -> 0.17373 | AP66: =AO66/$AO$1*1000 -> 0.00036337434
A67: YES | B67: 6666029997 | C67: 6666029997 restructure cost | D67: * CS_Fix Cost | E67: 0.66238 | F67: =E67/$E$1*1000 -> 0.013637356 | H67: 4.5982 | I67: =H67/$H$1*1000 -> 0.09988921 | K67: 0 | L67: =K67/$K$1*1000 -> 0 | N67: 0 | O67: =N67/$N$1*1000 -> 0 | Q67: 0 | R67: =Q67/$Q$1*1000 -> 0 | T67: 0 | U67: =T67/$T$1*1000 -> 0 | W67: 0 | X67: =W67/$W$1*1000 -> 0 | Z67: 0 | AA67: =Z67/$Z$1*1000 -> 0 | AC67: 8.24399 | AD67: =AC67/$AC$1*1000 -> 0.29163683 | AF67: 0 | AG67: =AF67/$AF$1*1000 -> 0 | AI67: 0 | AJ67: =AI67/$AI$1*1000 -> 0 | AL67: 1.43447 | AM67: =AL67/$AL$1*1000 -> 0.034078588 | AO67: =H67+E67+K67+N67+Q67+T67+W67+Z67+AC67+AF67+AI67+AL67 -> 14.93904 | AP67: =AO67/$AO$1*1000 -> 0.031246554
A68: YES | B68: 6666030702 | C68: 6666030702 R&D prototype purchased | D68: * CS_Fix Cost | E68: 0 | F68: =E68/$E$1*1000 -> 0 | H68: 0 | I68: =H68/$H$1*1000 -> 0 | K68: 0 | L68: =K68/$K$1*1000 -> 0 | N68: 0 | O68: =N68/$N$1*1000 -> 0 | Q68: 0 | R68: =Q68/$Q$1*1000 -> 0 | T68: 0 | U68: =T68/$T$1*1000 -> 0 | W68: 0 | X68: =W68/$W$1*1000 -> 0 | Z68: 0 | AA68: =Z68/$Z$1*1000 -> 0 | AC68: 0 | AD68: =AC68/$AC$1*1000 -> 0 | AF68: 0 | AG68: =AF68/$AF$1*1000 -> 0 | AI68: 0 | AJ68: =AI68/$AI$1*1000 -> 0 | AL68: 0 | AM68: =AL68/$AL$1*1000 -> 0 | AO68: =H68+E68+K68+N68+Q68+T68+W68+Z68+AC68+AF68+AI68+AL68 -> 0 | AP68: =AO68/$AO$1*1000 -> 0
A69: YES | B69: 6666031200 | C69: 6666031200 Instrument fee | D69: * CS_Fix Cost | E69: 0 | F69: =E69/$E$1*1000 -> 0 | H69: -0.00026 | I69: =H69/$H$1*1000 -> -5.648122e-06 | K69: -0.01434 | L69: =K69/$K$1*1000 -> -0.00030947191 | N69: -0.03 | O69: =N69/$N$1*1000 -> -0.00060774264 | Q69: 0 | R69: =Q69/$Q$1*1000 -> 0 | T69: 0 | U69: =T69/$T$1*1000 -> 0 | W69: 0 | X69: =W69/$W$1*1000 -> 0 | Z69: 0.0357 | AA69: =Z69/$Z$1*1000 -> 0.0011164274 | AC69: 0 | AD69: =AC69/$AC$1*1000 -> 0 | AF69: 0 | AG69: =AF69/$AF$1*1000 -> 0 | AI69: 0 | AJ69: =AI69/$AI$1*1000 -> 0 | AL69: 0 | AM69: =AL69/$AL$1*1000 -> 0 | AO69: =H69+E69+K69+N69+Q69+T69+W69+Z69+AC69+AF69+AI69+AL69 -> -0.0089 | AP69: =AO69/$AO$1*1000 -> -1.8615275e-05
A70: YES | B70: 6666050107 | C70: 6666050107 Special distribution costs | D70: * CS_Fix Cost | E70: 0 | F70: =E70/$E$1*1000 -> 0 | H70: 0 | I70: =H70/$H$1*1000 -> 0 | K70: 0.01244 | L70: =K70/$K$1*1000 -> 0.00026846796 | N70: 0 | O70: =N70/$N$1*1000 -> 0 | Q70: 0.01125 | R70: =Q70/$Q$1*1000 -> 0.0002094816 | T70: 0 | U70: =T70/$T$1*1000 -> 0 | W70: 0 | X70: =W70/$W$1*1000 -> 0 | Z70: 0 | AA70: =Z70/$Z$1*1000 -> 0 | AC70: -0.02369 | AD70: =AC70/$AC$1*1000 -> -0.00083805009 | AF70: 0 | AG70: =AF70/$AF$1*1000 -> 0 | AI70: 0 | AJ70: =AI70/$AI$1*1000 -> 0 | AL70: 0 | AM70: =AL70/$AL$1*1000 -> 0 | AO70: =H70+E70+K70+N70+Q70+T70+W70+Z70+AC70+AF70+AI70+AL70 -> -3.469447e-18 | AP70: =AO70/$AO$1*1000 -> -7.2567087e-21
A71: YES | B71: 6666050202 | C71: 6666050202 Custom clearance charge | D71: * CS_Fix Cost | AL71: 0.04008 | AM71: =AL71/$AL$1*1000 -> 0.00095217732 | AO71: =H71+E71+K71+N71+Q71+T71+W71+Z71+AC71+AF71+AI71+AL71 -> 0.04008 | AP71: =AO71/$AO$1*1000 -> 8.3831484e-05
A72: YES | B72: 6666070100 | C72: 6666070100 Software purchase, development and imple | D72: * CS_Fix Cost | E72: 0 | F72: =E72/$E$1*1000 -> 0 | H72: 0 | I72: =H72/$H$1*1000 -> 0 | K72: 0 | L72: =K72/$K$1*1000 -> 0 | N72: 0 | O72: =N72/$N$1*1000 -> 0 | Q72: 0 | R72: =Q72/$Q$1*1000 -> 0 | T72: 0 | U72: =T72/$T$1*1000 -> 0 | W72: 0 | X72: =W72/$W$1*1000 -> 0 | Z72: 0 | AA72: =Z72/$Z$1*1000 -> 0 | AC72: 0 | AD72: =AC72/$AC$1*1000 -> 0 | AF72: 0 | AG72: =AF72/$AF$1*1000 -> 0 | AI72: 0 | AJ72: =AI72/$AI$1*1000 -> 0 | AL72: 0 | AM72: =AL72/$AL$1*1000 -> 0 | AO72: =H72+E72+K72+N72+Q72+T72+W72+Z72+AC72+AF72+AI72+AL72 -> 0 | AP72: =AO72/$AO$1*1000 -> 0
A73: YES | B73: 6666070300 | C73: 6666070300 Software maintenance fees | D73: * CS_Fix Cost | E73: 0 | F73: =E73/$E$1*1000 -> 0 | H73: 0 | I73: =H73/$H$1*1000 -> 0 | K73: 0 | L73: =K73/$K$1*1000 -> 0 | N73: 0 | O73: =N73/$N$1*1000 -> 0 | Q73: 0 | R73: =Q73/$Q$1*1000 -> 0 | T73: 0 | U73: =T73/$T$1*1000 -> 0 | W73: 0 | X73: =W73/$W$1*1000 -> 0 | Z73: 0 | AA73: =Z73/$Z$1*1000 -> 0 | AC73: 0 | AD73: =AC73/$AC$1*1000 -> 0 | AF73: 0 | AG73: =AF73/$AF$1*1000 -> 0 | AI73: 0 | AJ73: =AI73/$AI$1*1000 -> 0 | AL73: 0 | AM73: =AL73/$AL$1*1000 -> 0 | AO73: =H73+E73+K73+N73+Q73+T73+W73+Z73+AC73+AF73+AI73+AL73 -> 0 | AP73: =AO73/$AO$1*1000 -> 0
A74: YES | B74: 6666070400 | C74: 6666070400 IT maint. & repairs hardware | D74: * CS_Fix Cost | E74: 4.88462 | F74: =E74/$E$1*1000 -> 0.10056659 | H74: 2.79422 | I74: =H74/$H$1*1000 -> 0.060700367 | K74: 2.74919 | L74: =K74/$K$1*1000 -> 0.059330341 | N74: 4.85391 | O74: =N74/$N$1*1000 -> 0.098330936 | Q74: 3.51618 | R74: =Q74/$Q$1*1000 -> 0.065473335 | T74: 4.70276 | U74: =T74/$T$1*1000 -> 0.15853425 | W74: 3.48559 | X74: =W74/$W$1*1000 -> 0.083273765 | Z74: 6.26659 | AA74: =Z74/$Z$1*1000 -> 0.19597179 | AC74: 6.68874 | AD74: =AC74/$AC$1*1000 -> 0.23661879 | AF74: 9.4562 | AG74: =AF74/$AF$1*1000 -> 0.36077219 | AI74: 15.69474 | AJ74: =AI74/$AI$1*1000 -> 0.46128439 | AL74: -2.68317 | AM74: =AL74/$AL$1*1000 -> -0.063743853 | AO74: =H74+E74+K74+N74+Q74+T74+W74+Z74+AC74+AF74+AI74+AL74 -> 62.40957 | AP74: =AO74/$AO$1*1000 -> 0.1305361
A75: YES | B75: 5401050201 | C75: 5401050201 COGS-Special a | D75: * CS_Fix Cost | AC75: =23.69/1000 -> 0.02369 | AD75: =AC75/$AC$1*1000 -> 0.00083805009 | AF75: 0 | AG75: =AF75/$AF$1*1000 -> 0 | AI75: 0 | AJ75: =AI75/$AI$1*1000 -> 0 | AL75: 0 | AM75: =AL75/$AL$1*1000 -> 0 | AO75: =H75+E75+K75+N75+Q75+T75+W75+Z75+AC75+AF75+AI75+AL75 -> 0.02369 | AP75: =AO75/$AO$1*1000 -> 4.9550096e-05
A76: YES | B76: 5401020212 | C76: 5401020212 Local Transpor | D76: * CS_Fix Cost | AC76: =-147.76/1000 -> -0.14776 | AD76: =AC76/$AC$1*1000 -> -0.0052271119 | AF76: 0 | AG76: =AF76/$AF$1*1000 -> 0 | AI76: 0 | AJ76: =AI76/$AI$1*1000 -> 0 | AL76: 0 | AM76: =AL76/$AL$1*1000 -> 0 | AO76: =H76+E76+K76+N76+Q76+T76+W76+Z76+AC76+AF76+AI76+AL76 -> -0.14776 | AP76: =AO76/$AO$1*1000 -> -0.00030905539
B77: FIX | C77: * CS_Fix Cost | E77: 47.53431 | F77: =E77/$E$1*1000 -> 0.97865619 | H77: =SUM(H28:H74) -> 55.911 | I77: =H77/$H$1*1000 -> 1.2145852 | K77: =SUM(K28:K74) -> 43.04972 | L77: =K77/$K$1*1000 -> 0.92905712 | N77: =SUM(N28:N74) -> 40.60267 | O77: =N77/$N$1*1000 -> 0.82253246 | Q77: =SUM(Q28:Q74) -> 39.71379 | R77: =Q77/$Q$1*1000 -> 0.73949408 | T77: =SUM(T28:T74) -> 36.03309 | U77: =T77/$T$1*1000 -> 1.2147077 | W77: =SUM(W28:W74) -> 41.46116 | X77: =W77/$W$1*1000 -> 0.99054304 | Z77: =SUM(Z28:Z74) -> 53.8334 | AA77: =Z77/$Z$1*1000 -> 1.6835038 | AC77: =SUM(AC28:AC76) -> 45.24103 | AD77: =AC77/$AC$1*1000 -> 1.6004326 | AF77: =SUM(AF28:AF76) -> 35.50089 | AG77: =AF77/$AF$1*1000 -> 1.3544271 | AI77: =SUM(AI28:AI76) -> 45.64884 | AJ77: =AI77/$AI$1*1000 -> 1.3416659 | AL77: =SUM(AL28:AL76) -> -14.33268 | AM77: =AL77/$AL$1*1000 -> -0.34050032 | AO77: =SUM(AO28:AO76) -> 470.19722 | AP77: =AO77/$AO$1*1000 -> 0.98346633
A78: YES | B78: 6666110203 | C78: 6666110203 Low value consumables | D78: * CS_Variable Cost | E78: 11.78262 | F78: =E78/$E$1*1000 -> 0.24258549 | H78: 13.57091 | I78: =H78/$H$1*1000 -> 0.29480829 | K78: 16.58684 | L78: =K78/$K$1*1000 -> 0.35796102 | N78: 9.57281 | O78: =N78/$N$1*1000 -> 0.19392683 | Q78: 19.10833 | R78: =Q78/$Q$1*1000 -> 0.35580832 | T78: 3.05345 | U78: =T78/$T$1*1000 -> 0.10293453 | W78: 14.97382 | X78: =W78/$W$1*1000 -> 0.35773753 | Z78: 16.68596 | AA78: =Z78/$Z$1*1000 -> 0.5218113 | AC78: 16.37718 | AD78: =AC78/$AC$1*1000 -> 0.57935404 | AF78: 20.44981 | AG78: =AF78/$AF$1*1000 -> 0.78019953 | AI78: 6.59996 | AJ78: =AI78/$AI$1*1000 -> 0.19397954 | AL78: -3.26878 | AM78: =AL78/$AL$1*1000 -> -0.077656142 | AO78: =H78+E78+K78+N78+Q78+T78+W78+Z78+AC78+AF78+AI78+AL78 -> 145.49291 | AP78: =AO78/$AO$1*1000 -> 0.30431354
A79: YES | B79: 5102040000 | C79: 5102040000 Other Revenue - Other | D79: * CS_Variable Cost | E79: 0 | F79: =E79/$E$1*1000 -> 0 | H79: 0 | I79: =H79/$H$1*1000 -> 0 | K79: 0 | L79: =K79/$K$1*1000 -> 0 | N79: 0 | O79: =N79/$N$1*1000 -> 0 | Q79: 0 | R79: =Q79/$Q$1*1000 -> 0 | T79: 0 | U79: =T79/$T$1*1000 -> 0 | W79: 0 | X79: =W79/$W$1*1000 -> 0 | Z79: 0 | AA79: =Z79/$Z$1*1000 -> 0 | AC79: -0.585 | AD79: =AC79/$AC$1*1000 -> -0.020694779 | AF79: -0.06056 | AG79: =AF79/$AF$1*1000 -> -0.0023104803 | AI79: 0 | AJ79: =AI79/$AI$1*1000 -> 0 | AL79: 0 | AM79: =AL79/$AL$1*1000 -> 0 | AO79: =H79+E79+K79+N79+Q79+T79+W79+Z79+AC79+AF79+AI79+AL79 -> -0.64556 | AP79: =AO79/$AO$1*1000 -> -0.0013502558
A80: NO | B80: 6666050307 | C80: 6666050307 Inventory count different-raw material | D80: * CS_Variable Cost | E80: 0.42874 | F80: =E80/$E$1*1000 -> 0.0088270779 | H80: -3.72335 | I80: =H80/$H$1*1000 -> -0.080884366 | K80: 19.15803 | L80: =K80/$K$1*1000 -> 0.41344994 | N80: -15.38499 | O80: =N80/$N$1*1000 -> -0.31167048 | Q80: -2.07812 | R80: =Q80/$Q$1*1000 -> -0.038695814 | T80: 18.26473 | U80: =T80/$T$1*1000 -> 0.6157204 | W80: -44.83412 | X80: =W80/$W$1*1000 -> -1.071126 | Z80: 0.88589 | AA80: =Z80/$Z$1*1000 -> 0.027703975 | AC80: -0.14104 | AD80: =AC80/$AC$1*1000 -> -0.0049893873 | AF80: 0.93849 | AG80: =AF80/$AF$1*1000 -> 0.035805196 | AI80: -1.50732 | AJ80: =AI80/$AI$1*1000 -> -0.044301669 | AL80: -41.75548 | AM80: =AL80/$AL$1*1000 -> -0.99198156 | AO80: =H80+E80+K80+N80+Q80+T80+W80+Z80+AC80+AF80+AI80+AL80 -> -69.74854 | AP80: =AO80/$AO$1*1000 -> -0.14588632
A81: NO | B81: 6666050312 | C81: 6666050312 Inventory count different- Semifinished | D81: * CS_Fix Cost | E81: 0 | F81: =E81/$E$1*1000 -> 0 | H81: 22.53327 | I81: =H81/$H$1*1000 -> 0.48950253 | K81: 0 | L81: =K81/$K$1*1000 -> 0 | N81: 0 | O81: =N81/$N$1*1000 -> 0 | Q81: 0.72656 | R81: =Q81/$Q$1*1000 -> 0.013528974 | T81: 0 | U81: =T81/$T$1*1000 -> 0 | W81: 31.26134 | X81: =W81/$W$1*1000 -> 0.7468605 | Z81: 0.03114 | AA81: =Z81/$Z$1*1000 -> 0.00097382494 | AC81: 0 | AD81: =AC81/$AC$1*1000 -> 0 | AF81: 0 | AG81: =AF81/$AF$1*1000 -> 0 | AI81: 0.27656 | AJ81: =AI81/$AI$1*1000 -> 0.00812838 | AL81: 5.44454 | AM81: =AL81/$AL$1*1000 -> 0.1293455 | AO81: =H81+E81+K81+N81+Q81+T81+W81+Z81+AC81+AF81+AI81+AL81 -> 60.27341 | AP81: =AO81/$AO$1*1000 -> 0.1260681
B82: VAR | C82: * CS_Variable Cost | E82: 12.21136 | F82: =E82/$E$1*1000 -> 0.25141257 | H82: =SUM(H78:H81) -> 32.38083 | I82: =H82/$H$1*1000 -> 0.70342645 | K82: =SUM(K78:K81) -> 35.74487 | L82: =K82/$K$1*1000 -> 0.77141097 | N82: =SUM(N78:N81) -> -5.81218 | O82: =N82/$N$1*1000 -> -0.11774365 | Q82: =SUM(Q78:Q81) -> 17.75677 | R82: =Q82/$Q$1*1000 -> 0.33064148 | T82: =SUM(T78:T81) -> 21.31818 | U82: =T82/$T$1*1000 -> 0.71865494 | W82: =SUM(W78:W81) -> 1.40104 | X82: =W82/$W$1*1000 -> 0.03347206 | Z82: =SUM(Z78:Z81) -> 17.60299 | AA82: =Z82/$Z$1*1000 -> 0.5504891 | AC82: =SUM(AC78:AC81) -> 15.65114 | AD82: =AC82/$AC$1*1000 -> 0.55366987 | AF82: =SUM(AF78:AF81) -> 21.32774 | AG82: =AF82/$AF$1*1000 -> 0.81369425 | AI82: =SUM(AI78:AI81) -> 5.3692 | AJ82: =AI82/$AI$1*1000 -> 0.15780625 | AL82: =SUM(AL78:AL81) -> -39.57972 | AM82: =AL82/$AL$1*1000 -> -0.94029221 | AO82: =SUM(AO78:AO81) -> 135.37222 | AP82: =AO82/$AO$1*1000 -> 0.28314506
A83: NO | B83: 6666100203 | C83: 6666100203 Provision for inventory devaluation - RM | D83: * CS_Obsolescence | E83: 2.51573 | F83: =E83/$E$1*1000 -> 0.051794898 | H83: 2.08333 | I83: =H83/$H$1*1000 -> 0.045257315 | K83: 2.08333 | L83: =K83/$K$1*1000 -> 0.044960399 | N83: 2.08333 | O83: =N83/$N$1*1000 -> 0.042204283 | Q83: 2.08333 | R83: =Q83/$Q$1*1000 -> 0.038792827 | T83: 68.22525 | U83: =T83/$T$1*1000 -> 2.2999343 | W83: 0 | X83: =W83/$W$1*1000 -> 0 | Z83: 0 | AA83: =Z83/$Z$1*1000 -> 0 | AC83: 0 | AD83: =AC83/$AC$1*1000 -> 0 | AF83: 35.02325 | AG83: =AF83/$AF$1*1000 -> 1.3362043 | AI83: 32.76354 | AJ83: =AI83/$AI$1*1000 -> 0.9629538 | AL83: 91.92924 | AM83: =AL83/$AL$1*1000 -> 2.1839555 | AO83: =H83+E83+K83+N83+Q83+T83+W83+Z83+AC83+AF83+AI83+AL83 -> 238.79033 | AP83: =AO83/$AO$1*1000 -> 0.49945478
B84: FIX | C84: * CS_Obsolescence | E84: 2.51573 | F84: =E84/$E$1*1000 -> 0.051794898 | H84: =+H83 -> 2.08333 | I84: =H84/$H$1*1000 -> 0.045257315 | K84: =+K83 -> 2.08333 | L84: =K84/$K$1*1000 -> 0.044960399 | N84: =+N83 -> 2.08333 | O84: =N84/$N$1*1000 -> 0.042204283 | Q84: =+Q83 -> 2.08333 | R84: =Q84/$Q$1*1000 -> 0.038792827 | T84: =+T83 -> 68.22525 | U84: =T84/$T$1*1000 -> 2.2999343 | W84: =+W83 -> 0 | X84: =W84/$W$1*1000 -> 0 | Z84: =+Z83 -> 0 | AA84: =Z84/$Z$1*1000 -> 0 | AC84: =+AC83 -> 0 | AD84: =AC84/$AC$1*1000 -> 0 | AF84: =+AF83 -> 35.02325 | AG84: =AF84/$AF$1*1000 -> 1.3362043 | AI84: =+AI83 -> 32.76354 | AJ84: =AI84/$AI$1*1000 -> 0.9629538 | AL84: =+AL83 -> 91.92924 | AM84: =AL84/$AL$1*1000 -> 2.1839555 | AO84: =+AO83 -> 238.79033 | AP84: =AO84/$AO$1*1000 -> 0.49945478
A85: NO | B85: 5301070000 | C85: 5301070000 Non-operation revenue-sales of scrapped | D85: * CS_Reselling | E85: -58.2364 | F85: =E85/$E$1*1000 -> -1.1989953 | H85: -53.62907 | I85: =H85/$H$1*1000 -> -1.1650136 | K85: -57.78142 | L85: =K85/$K$1*1000 -> -1.2469823 | N85: -75.04936 | O85: =N85/$N$1*1000 -> -1.5203565 | Q85: -62.47757 | R85: =Q85/$Q$1*1000 -> -1.163369 | T85: -54.55736 | U85: =T85/$T$1*1000 -> -1.8391775 | W85: -46.2918 | X85: =W85/$W$1*1000 -> -1.1059512 | Z85: -52.15434 | AA85: =Z85/$Z$1*1000 -> -1.6309954 | AC85: -43.47965 | AD85: =AC85/$AC$1*1000 -> -1.5381226 | AF85: -39.75619 | AG85: =AF85/$AF$1*1000 -> -1.516775 | AI85: -37.47416 | AJ85: =AI85/$AI$1*1000 -> -1.1014037 | AL85: -55.6909 | AM85: =AL85/$AL$1*1000 -> -1.3230442 | AO85: =H85+E85+K85+N85+Q85+T85+W85+Z85+AC85+AF85+AI85+AL85 -> -636.57822 | AP85: =AO85/$AO$1*1000 -> -1.3314695
B86: VAR | C86: * CS_Reselling | E86: -58.2364 | F86: =E86/$E$1*1000 -> -1.1989953 | H86: =+H85 -> -53.62907 | I86: =H86/$H$1*1000 -> -1.1650136 | K86: =+K85 -> -57.78142 | L86: =K86/$K$1*1000 -> -1.2469823 | N86: =+N85 -> -75.04936 | O86: =N86/$N$1*1000 -> -1.5203565 | Q86: =+Q85 -> -62.47757 | R86: =Q86/$Q$1*1000 -> -1.163369 | T86: =+T85 -> -54.55736 | U86: =T86/$T$1*1000 -> -1.8391775 | W86: =+W85 -> -46.2918 | X86: =W86/$W$1*1000 -> -1.1059512 | Z86: =+Z85 -> -52.15434 | AA86: =Z86/$Z$1*1000 -> -1.6309954 | AC86: =+AC85 -> -43.47965 | AD86: =AC86/$AC$1*1000 -> -1.5381226 | AF86: =+AF85 -> -39.75619 | AG86: =AF86/$AF$1*1000 -> -1.516775 | AI86: =+AI85 -> -37.47416 | AJ86: =AI86/$AI$1*1000 -> -1.1014037 | AL86: =+AL85 -> -55.6909 | AM86: =AL86/$AL$1*1000 -> -1.3230442 | AO86: =+AO85 -> -636.57822 | AP86: =AO86/$AO$1*1000 -> -1.3314695
A87: YES | B87: 6666021602 | C87: 6666021602 Electricity | D87: * CS_Fix Utilities | E87: 7.6782 | F87: =E87/$E$1*1000 -> 0.15808198 | H87: 7.30813 | I87: =H87/$H$1*1000 -> 0.1587585 | K87: 7.6688 | L87: =K87/$K$1*1000 -> 0.16550057 | N87: 5.51236 | O87: =N87/$N$1*1000 -> 0.11166987 | Q87: 6.00573 | R87: =Q87/$Q$1*1000 -> 0.11183022 | T87: -0.8493 | U87: =T87/$T$1*1000 -> -0.028630663 | W87: 1.91257 | X87: =W87/$W$1*1000 -> 0.045692955 | Z87: 6.3758 | AA87: =Z87/$Z$1*1000 -> 0.19938706 | AC87: 3.79127 | AD87: =AC87/$AC$1*1000 -> 0.13411879 | AF87: 2.94594 | AG87: =AF87/$AF$1*1000 -> 0.11239327 | AI87: 4.38108 | AJ87: =AI87/$AI$1*1000 -> 0.1287644 | AL87: 5.50782 | AM87: =AL87/$AL$1*1000 -> 0.13084883 | AO87: =H87+E87+K87+N87+Q87+T87+W87+Z87+AC87+AF87+AI87+AL87 -> 58.2384 | AP87: =AO87/$AO$1*1000 -> 0.12181166
A88: YES | B88: 6666021604 | C88: 6666021604 Oil & Gas man. Adj in Reporting | D88: * CS_Fix Utilities | E88: =-623.43/1000 -> -0.62343 | F88: =E88/$E$1*1000 -> -0.012835437 | H88: =4180.92/1000 -> 4.18092 | I88: =H88/$H$1*1000 -> 0.090824409 | K88: =+K93*-1 -> 3.24131 | L88: =K88/$K$1*1000 -> 0.069950795 | N88: =(+N93*-1) -> 1.06947 | O88: =N88/$N$1*1000 -> 0.021665417 | Q88: =699.66/1000 -> 0.69966 | R88: =Q88/$Q$1*1000 -> 0.01302808 | T88: =(+T93*-1) -> -0.37499 | U88: =T88/$T$1*1000 -> -0.012641249 | W88: 0.28723 | X88: =W88/$W$1*1000 -> 0.0068621736 | Z88: =429.34/1000 -> 0.42934 | AA88: =Z88/$Z$1*1000 -> 0.013426525 | AC88: =+AC93*-1 -> 1.18295 | AD88: =AC88/$AC$1*1000 -> 0.041847672 | AF88: 1.67351 | AG88: =AF88/$AF$1*1000 -> 0.063847621 | AI88: =2638.65/1000 -> 2.63865 | AJ88: =AI88/$AI$1*1000 -> 0.07755261 | AL88: =310.52/1000 -> 0.31052 | AM88: =AL88/$AL$1*1000 -> 0.0073769986 | AO88: =H88+E88+K88+N88+Q88+T88+W88+Z88+AC88+AF88+AI88+AL88 -> 14.71514 | AP88: =AO88/$AO$1*1000 -> 0.030778244
B89: FIX | C89: * CS_Fix Utilities | E89: =SUM(E87:E88) -> 7.05477 | F89: =E89/$E$1*1000 -> 0.14524655 | H89: =+SUM(H87:H88) -> 11.48905 | I89: =H89/$H$1*1000 -> 0.24958291 | K89: =+SUM(K87:K88) -> 10.91011 | L89: =K89/$K$1*1000 -> 0.23545137 | N89: =+SUM(N87:N88) -> 6.58183 | O89: =N89/$N$1*1000 -> 0.13333529 | Q89: =+SUM(Q87:Q88) -> 6.70539 | R89: =Q89/$Q$1*1000 -> 0.1248583 | T89: =+SUM(T87:T88) -> -1.22429 | U89: =T89/$T$1*1000 -> -0.041271912 | W89: =+SUM(W87:W88) -> 2.1998 | X89: =W89/$W$1*1000 -> 0.052555128 | Z89: =+SUM(Z87:Z88) -> 6.80514 | AA89: =Z89/$Z$1*1000 -> 0.21281358 | AC89: =+SUM(AC87:AC88) -> 4.97422 | AD89: =AC89/$AC$1*1000 -> 0.17596646 | AF89: =+SUM(AF87:AF88) -> 4.61945 | AG89: =AF89/$AF$1*1000 -> 0.17624089 | AI89: =+SUM(AI87:AI88) -> 7.01973 | AJ89: =AI89/$AI$1*1000 -> 0.20631701 | AL89: =+SUM(AL87:AL88) -> 5.81834 | AM89: =AL89/$AL$1*1000 -> 0.13822583 | AO89: =SUM(AO87:AO88) -> 72.95354 | AP89: =AO89/$AO$1*1000 -> 0.15258991
A90: YES | B90: 6666021600 | C90: 6666021600 Energy and power cost | D90: * CS_Variable Utilities | E90: 23.97933 | F90: =E90/$E$1*1000 -> 0.49369644 | H90: 23.12032 | I90: =H90/$H$1*1000 -> 0.50225534 | K90: 25.58471 | L90: =K90/$K$1*1000 -> 0.55214429 | N90: 24.88679 | O90: =N90/$N$1*1000 -> 0.50415878 | Q90: 34.66258 | R90: =Q90/$Q$1*1000 -> 0.64543758 | T90: 23.36705 | U90: =T90/$T$1*1000 -> 0.78772418 | W90: 26.80675 | X90: =W90/$W$1*1000 -> 0.64043649 | Z90: 20.20955 | AA90: =Z90/$Z$1*1000 -> 0.63200269 | AC90: 18.09736 | AD90: =AC90/$AC$1*1000 -> 0.64020659 | AF90: 12.75709 | AG90: =AF90/$AF$1*1000 -> 0.48670749 | AI90: 17.30138 | AJ90: =AI90/$AI$1*1000 -> 0.50850517 | AL90: 18.35881 | AM90: =AL90/$AL$1*1000 -> 0.43614877 | AO90: =H90+E90+K90+N90+Q90+T90+W90+Z90+AC90+AF90+AI90+AL90 -> 269.13172 | AP90: =AO90/$AO$1*1000 -> 0.56291695
A91: YES | B91: 6666021603 | C91: 6666021603 Water | D91: * CS_Variable Utilities | E91: 0.50497 | F91: =E91/$E$1*1000 -> 0.010396533 | H91: 0.82088 | I91: =H91/$H$1*1000 -> 0.017832425 | K91: 0.87109 | L91: =K91/$K$1*1000 -> 0.018799016 | N91: 0.701 | O91: =N91/$N$1*1000 -> 0.01420092 | Q91: 0.82863 | R91: =Q91/$Q$1*1000 -> 0.015429577 | T91: 0.61927 | U91: =T91/$T$1*1000 -> 0.020876146 | W91: 0.6947 | X91: =W91/$W$1*1000 -> 0.016596985 | Z91: 0.45612 | AA91: =Z91/$Z$1*1000 -> 0.014264002 | AC91: 0.70627 | AD91: =AC91/$AC$1*1000 -> 0.024984788 | AF91: 0.47045 | AG91: =AF91/$AF$1*1000 -> 0.017948571 | AI91: 1.49811 | AJ91: =AI91/$AI$1*1000 -> 0.044030978 | AL91: 1.11864 | AM91: =AL91/$AL$1*1000 -> 0.02657544 | AO91: =H91+E91+K91+N91+Q91+T91+W91+Z91+AC91+AF91+AI91+AL91 -> 9.29013 | AP91: =AO91/$AO$1*1000 -> 0.019431272
A92: YES | B92: 6666021604 | C92: 6666021604 Oil & Gas | D92: * CS_Variable Utilities | E92: 1.50287 | F92: =E92/$E$1*1000 -> 0.030941714 | H92: 3.59313 | I92: =H92/$H$1*1000 -> 0.078055525 | K92: 7.54714 | L92: =K92/$K$1*1000 -> 0.16287502 | N92: 2.91605 | O92: =N92/$N$1*1000 -> 0.059073598 | Q92: 5.05802 | R92: =Q92/$Q$1*1000 -> 0.094183301 | T92: 0.74909 | U92: =T92/$T$1*1000 -> 0.025252495 | W92: 2.37785 | X92: =W92/$W$1*1000 -> 0.056808897 | Z92: 1.09269 | AA92: =Z92/$Z$1*1000 -> 0.034171123 | AC92: 2.53966 | AD92: =AC92/$AC$1*1000 -> 0.089842224 | AF92: 2.34891 | AG92: =AF92/$AF$1*1000 -> 0.089615429 | AI92: 5.83076 | AJ92: =AI92/$AI$1*1000 -> 0.17137197 | AL92: 1.83369 | AM92: =AL92/$AL$1*1000 -> 0.043562825 | AO92: =H92+E92+K92+N92+Q92+T92+W92+Z92+AC92+AF92+AI92+AL92 -> 37.38986 | AP92: =AO92/$AO$1*1000 -> 0.078204776
A93: YES | B93: 6666021604 | C93: 6666021604 Oil & Gas man. Adj in Reporting | D93: * CS_Variable Utilities | E93: =+E88*-1 -> 0.62343 | F93: =E93/$E$1*1000 -> 0.012835437 | H93: =+H88*-1 -> -4.18092 | I93: =H93/$H$1*1000 -> -0.090824409 | K93: =-3241.31/1000 -> -3.24131 | L93: =K93/$K$1*1000 -> -0.069950795 | N93: -1.06947 | O93: =N93/$N$1*1000 -> -0.021665417 | Q93: =-699.66/1000 -> -0.69966 | R93: =Q93/$Q$1*1000 -> -0.01302808 | T93: 0.37499 | U93: =T93/$T$1*1000 -> 0.012641249 | W93: -0.28723 | X93: =W93/$W$1*1000 -> -0.0068621736 | Z93: =+Z88*-1 -> -0.42934 | AA93: =Z93/$Z$1*1000 -> -0.013426525 | AC93: =-1182.95/1000 -> -1.18295 | AD93: =AC93/$AC$1*1000 -> -0.041847672 | AF93: -1.67351 | AG93: =AF93/$AF$1*1000 -> -0.063847621 | AI93: =+AI88*-1 -> -2.63865 | AJ93: =AI93/$AI$1*1000 -> -0.07755261 | AL93: =+AL88*-1 -> -0.31052 | AM93: =AL93/$AL$1*1000 -> -0.0073769986 | AO93: =H93+E93+K93+N93+Q93+T93+W93+Z93+AC93+AF93+AI93+AL93 -> -14.71514 | AP93: =AO93/$AO$1*1000 -> -0.030778244
B94: VAR | C94: * CS_Variable Utilities | E94: =SUM(E90:E93) -> 26.6106 | F94: =E94/$E$1*1000 -> 0.54787013 | H94: =SUM(H90:H93) -> 23.35341 | I94: =H94/$H$1*1000 -> 0.50731888 | K94: =SUM(K90:K93) -> 30.76163 | L94: =K94/$K$1*1000 -> 0.66386754 | N94: =SUM(N90:N93) -> 27.43437 | O94: =N94/$N$1*1000 -> 0.55576788 | Q94: =SUM(Q90:Q93) -> 39.84957 | R94: =Q94/$Q$1*1000 -> 0.74202238 | T94: =SUM(T90:T93) -> 25.1104 | U94: =T94/$T$1*1000 -> 0.84649407 | W94: =SUM(W90:W93) -> 29.59207 | X94: =W94/$W$1*1000 -> 0.70698019 | Z94: =SUM(Z90:Z93) -> 21.32902 | AA94: =Z94/$Z$1*1000 -> 0.66701129 | AC94: =SUM(AC90:AC93) -> 20.16034 | AD94: =AC94/$AC$1*1000 -> 0.71318593 | AF94: =SUM(AF90:AF93) -> 13.90294 | AG94: =AF94/$AF$1*1000 -> 0.53042387 | AI94: =SUM(AI90:AI93) -> 21.9916 | AJ94: =AI94/$AI$1*1000 -> 0.64635551 | AL94: =SUM(AL90:AL93) -> 21.00062 | AM94: =AL94/$AL$1*1000 -> 0.49891003 | AO94: =SUM(AO90:AO93) -> 301.09657 | AP94: =AO94/$AO$1*1000 -> 0.62977476
A95: YES | B95: 5001010206 | C95: 5001010206 Unemployment Insurance -blue collar-Indi | D95: * CS_Indirect Labour | E95: 2.96763 | F95: =E95/$E$1*1000 -> 0.061098804 | H95: 2.63918 | I95: =H95/$H$1*1000 -> 0.057332349 | K95: 3.64004 | L95: =K95/$K$1*1000 -> 0.078555798 | N95: 3.17975 | O95: =N95/$N$1*1000 -> 0.064415655 | Q95: 3.75704 | R95: =Q95/$Q$1*1000 -> 0.06995829 | T95: 3.0831 | U95: =T95/$T$1*1000 -> 0.10393406 | W95: 2.74451 | X95: =W95/$W$1*1000 -> 0.065568722 | Z95: 2.28535 | AA95: =Z95/$Z$1*1000 -> 0.071468556 | AC95: 2.69426 | AD95: =AC95/$AC$1*1000 -> 0.095311306 | AF95: 2.79843 | AG95: =AF95/$AF$1*1000 -> 0.10676548 | AI95: 3.30868 | AJ95: =AI95/$AI$1*1000 -> 0.097245474 | AL95: 3.36423 | AM95: =AL95/$AL$1*1000 -> 0.07992374 | AO95: =H95+E95+K95+N95+Q95+T95+W95+Z95+AC95+AF95+AI95+AL95 -> 36.4622 | AP95: =AO95/$AO$1*1000 -> 0.076264479
A96: YES | B96: 6666010184 | C96: 6666010184 Salary&Additional Incentive-Blue Collar- | D96: * CS_Indirect Labour | E96: -0.18786 | F96: =E96/$E$1*1000 -> -0.00386774 | H96: -0.20091 | I96: =H96/$H$1*1000 -> -0.0043644777 | K96: -0.18151 | L96: =K96/$K$1*1000 -> -0.003917172 | N96: -0.16359 | O96: =N96/$N$1*1000 -> -0.0033140206 | Q96: -0.04302 | R96: =Q96/$Q$1*1000 -> -0.00080105765 | T96: -0.18993 | U96: =T96/$T$1*1000 -> -0.0064027104 | W96: -0.11753 | X96: =W96/$W$1*1000 -> -0.0028078935 | Z96: -0.11388 | AA96: =Z96/$Z$1*1000 -> -0.0035613097 | AC96: -0.13632 | AD96: =AC96/$AC$1*1000 -> -0.004822414 | AF96: -0.1461 | AG96: =AF96/$AF$1*1000 -> -0.0055739957 | AI96: -0.14444 | AJ96: =AI96/$AI$1*1000 -> -0.0042452387 | AL96: -0.14042 | AM96: =AL96/$AL$1*1000 -> -0.0033359466 | AO96: =H96+E96+K96+N96+Q96+T96+W96+Z96+AC96+AF96+AI96+AL96 -> -1.76551 | AP96: =AO96/$AO$1*1000 -> -0.0036927476
A97: YES | B97: 6666010186 | C97: 6666010186 Overtime-Blue Collar-Indirect | D97: * CS_Indirect Labour | E97: 8.61402 | F97: =E97/$E$1*1000 -> 0.17734904 | H97: 7.58823 | I97: =H97/$H$1*1000 -> 0.16484326 | K97: 15.49278 | L97: =K97/$K$1*1000 -> 0.33435009 | N97: 24.66363 | O97: =N97/$N$1*1000 -> 0.49963799 | Q97: 37.71537 | R97: =Q97/$Q$1*1000 -> 0.70228233 | T97: 13.38549 | U97: =T97/$T$1*1000 -> 0.45123685 | W97: 7.89925 | X97: =W97/$W$1*1000 -> 0.18871993 | Z97: 7.69636 | AA97: =Z97/$Z$1*1000 -> 0.24068424 | AC97: 9.38375 | AD97: =AC97/$AC$1*1000 -> 0.33195663 | AF97: 13.1475 | AG97: =AF97/$AF$1*1000 -> 0.50160238 | AI97: 14.14208 | AJ97: =AI97/$AI$1*1000 -> 0.41565013 | AL97: 15.69953 | AM97: =AL97/$AL$1*1000 -> 0.37297247 | AO97: =H97+E97+K97+N97+Q97+T97+W97+Z97+AC97+AF97+AI97+AL97 -> 175.42799 | AP97: =AO97/$AO$1*1000 -> 0.36692587
A98: YES | B98: 6666010189 | C98: 6666010189 Salary - Blue collar indirect employees | D98: * CS_Indirect Labour | E98: 0 | F98: =E98/$E$1*1000 -> 0 | H98: 0 | I98: =H98/$H$1*1000 -> 0 | K98: 0 | L98: =K98/$K$1*1000 -> 0 | N98: 0 | O98: =N98/$N$1*1000 -> 0 | Q98: 0 | R98: =Q98/$Q$1*1000 -> 0 | T98: 65.27708 | U98: =T98/$T$1*1000 -> 2.2005488 | W98: -24.39273 | X98: =W98/$W$1*1000 -> -0.58276346 | Z98: 38.84342 | AA98: =Z98/$Z$1*1000 -> 1.21473 | AC98: 6.234 | AD98: =AC98/$AC$1*1000 -> 0.22053205 | AF98: 7.7 | AG98: =AF98/$AF$1*1000 -> 0.29376979 | AI98: 4.17406 | AJ98: =AI98/$AI$1*1000 -> 0.12267987 | AL98: 33.69346 | AM98: =AL98/$AL$1*1000 -> 0.80045281 | AO98: =H98+E98+K98+N98+Q98+T98+W98+Z98+AC98+AF98+AI98+AL98 -> 131.52929 | AP98: =AO98/$AO$1*1000 -> 0.27510717
A99: YES | B99: 6666010012 | C99: 6666010012 Payroll Taxes- Blue Collar Indirect | D99: * CS_Indirect Labour | E99: 26.49929 | F99: =E99/$E$1*1000 -> 0.54557843 | H99: 23.5523 | I99: =H99/$H$1*1000 -> 0.51163948 | K99: 32.44252 | L99: =K99/$K$1*1000 -> 0.70014287 | N99: 28.5286 | O99: =N99/$N$1*1000 -> 0.57793489 | Q99: 33.28538 | R99: =Q99/$Q$1*1000 -> 0.61979331 | T99: 27.52062 | U99: =T99/$T$1*1000 -> 0.92774474 | W99: 24.49843 | X99: =W99/$W$1*1000 -> 0.58528872 | Z99: 20.6327 | AA99: =Z99/$Z$1*1000 -> 0.64523564 | AC99: 24.67427 | AD99: =AC99/$AC$1*1000 -> 0.87286932 | AF99: 25.86948 | AG99: =AF99/$AF$1*1000 -> 0.98697036 | AI99: 29.55751 | AJ99: =AI99/$AI$1*1000 -> 0.86872531 | AL99: 30.04093 | AM99: =AL99/$AL$1*1000 -> 0.71367995 | AO99: =H99+E99+K99+N99+Q99+T99+W99+Z99+AC99+AF99+AI99+AL99 -> 327.10203 | AP99: =AO99/$AO$1*1000 -> 0.68416788
A100: YES | B100: 6666010226 | C100: 6666010226 Staff Leaving Indemnity - Blue Collar In | D100: * CS_Indirect Labour | E100: 9.47822 | F100: =E100/$E$1*1000 -> 0.19514155 | H100: -8.08965 | I100: =H100/$H$1*1000 -> -0.17573589 | K100: 4.532 | L100: =K100/$K$1*1000 -> 0.09780521 | N100: 4.66232 | O100: =N100/$N$1*1000 -> 0.094449689 | Q100: -2.52969 | R100: =Q100/$Q$1*1000 -> -0.047104313 | T100: 4.55257 | U100: =T100/$T$1*1000 -> 0.15347121 | W100: 4.2343 | X100: =W100/$W$1*1000 -> 0.1011611 | Z100: 3.92727 | AA100: =Z100/$Z$1*1000 -> 0.12281546 | AC100: 3.96327 | AD100: =AC100/$AC$1*1000 -> 0.14020341 | AF100: 4.03693 | AG100: =AF100/$AF$1*1000 -> 0.15401663 | AI100: 5.05044 | AJ100: =AI100/$AI$1*1000 -> 0.14843757 | AL100: 5.01931 | AM100: =AL100/$AL$1*1000 -> 0.11924334 | AO100: =H100+E100+K100+N100+Q100+T100+W100+Z100+AC100+AF100+AI100+AL100 -> 38.83729 | AP100: =AO100/$AO$1*1000 -> 0.081232227
A101: YES | B101: 6666010102 | C101: 6666010102 Salary-Blue collar indirect employees- A | D101: * CS_Indirect Labour | E101: 160.66917 | F101: =E101/$E$1*1000 -> 3.3079239 | H101: 135.87986 | I101: =H101/$H$1*1000 -> 2.9517924 | K101: =189.69893 -> 189.69893 | L101: =K101/$K$1*1000 -> 4.0938975 | N101: 149.48763 | O101: =N101/$N$1*1000 -> 3.0283336 | Q101: 169.11187 | R101: =Q101/$Q$1*1000 -> 3.1489623 | T101: 152.58442 | U101: =T101/$T$1*1000 -> 5.1437574 | W101: 140.82084 | X101: =W101/$W$1*1000 -> 3.3643319 | Z101: 119.89257 | AA101: =Z101/$Z$1*1000 -> 3.7493376 | AC101: 141.56973 | AD101: =AC101/$AC$1*1000 -> 5.0081269 | AF101: 155.88061 | AG101: =AF101/$AF$1*1000 -> 5.9471447 | AI101: 169.15221 | AJ101: =AI101/$AI$1*1000 -> 4.9715557 | AL101: 182.59679 | AM101: =AL101/$AL$1*1000 -> 4.3379372 | AO101: =H101+E101+K101+N101+Q101+T101+W101+Z101+AC101+AF101+AI101+AL101 -> 1867.3446 | AP101: =AO101/$AO$1*1000 -> 3.9057453
...

Sheet Renta DW _2024 new format 
B1: Renta DW Cost Evolution | D1: Volume | F1: ='2024_ACT@ACT FX old format '!E3 -> 16045 | J1: ='2024_ACT@ACT FX old format '!F3 -> 19752 | N1: ='2024_ACT@ACT FX old format '!G3 -> 20037 | R1: ='2024_ACT@ACT FX old format '!H3 -> 28043 | V1: ='2024_ACT@ACT FX old format '!I3 -> 40794 | Z1: ='2024_ACT@ACT FX old format '!J3 -> 30976 | AD1: ='2024_ACT@ACT FX old format '!K3 -> 34477 | AH1: ='2024_ACT@ACT FX old format '!L3 -> 25578 | AL1: ='2024_ACT@ACT FX old format '!M3 -> 40104 | AP1: ='2024_ACT@ACT FX old format '!N3 -> 41187 | AT1: ='2024_ACT@ACT FX old format '!O3 -> 43110 | AX1: ='2024_ACT@ACT FX old format '!P3 -> 26153 | BB1: =SUM(E1:AX1) -> 366256
D2: FX Rates | F2: 32.8165 | J2: ='2024_ACT@ACT FX old format '!F2 -> 33.2644 | N2: ='2024_ACT@ACT FX old format '!G2 -> 34.8229 | R2: ='2024_ACT@ACT FX old format '!H2 -> 34.6926 | V2: ='2024_ACT@ACT FX old format '!I2 -> 34.8605 | Z2: ='2024_ACT@ACT FX old format '!J2 -> 35.0667 | AD2: ='2024_ACT@ACT FX old format '!K2 -> 35.6969 | AH2: ='2024_ACT@ACT FX old format '!L2 -> 37.1098 | AL2: ='2024_ACT@ACT FX old format '!M2 -> 37.823824 | AP2: ='2024_ACT@ACT FX old format '!N2 -> 37.347309 | AT2: ='2024_ACT@ACT FX old format '!O2 -> 36.6237 | AX2: ='2024_ACT@ACT FX old format '!P2 -> 36.65884 | BB2: =BA191/BB191 -> 35.655612
A4: Row Labels | E4: Jan KLC | F4: JAN K€ | G4: Jan CPU € / pcs | I4: FEB KLC | J4: FEB K€ | K4: CPU € / pcs | M4: March KLC | N4: March K€ | O4: CPU € / pcs | Q4: Apr KLC | R4: Apr K€ | S4: CPU € / pcs | U4: MAY KLC | V4: May K€ | W4: CPU € / pcs | Y4: June KLC | Z4: June K€ | AA4: CPU € / pcs | AC4: July KLC | AD4: July K€ | AE4: CPU € / pcs | AG4: Aug KLC | AH4: Aug K€ | AI4: CPU € / pcs | AK4: Sept KLC | AL4: Sept K€ | AM4: CPU € / pcs | AO4: Oct KLC | AP4: Oct K€ | AQ4: CPU € / pcs | AS4: Nov KLC | AT4: Nov K€ | AU4: CPU € / pcs | AW4: Dec KLC | AX4: Dec K€ | AY4: CPU € / pcs | BA4: FY KLC | BB4: FY K€ | BC4: CPU € / pcs
A5: 6666110101 | B5: 6666110101 | C5: 6666110101 Depreciation of buildings | D5: * CS_Depreciation | E5: =VLOOKUP(B5,'2024 by account '!$A$2:$M$102,2,0)/1000 -> 229.04796 | F5: =E5/$F$2 -> 6.9796584 | G5: =F5/$F$1*1000 -> 0.4350052 | I5: =VLOOKUP(B5,'2024 by account '!$A$2:$M$102,3,0)/1000 -> 215.43536 | J5: =I5/$J$2 -> 6.4764541 | K5: =J5/$J$1*1000 -> 0.32788852 | M5: =VLOOKUP(B5,'2024 by account '!$A$2:$M$102,4,0)/1000 -> 244.15648 | N5: =M5/$N$2 -> 7.011377 | O5: =N5/$N$1*1000 -> 0.3499215 | Q5: =VLOOKUP(B5,'2024 by account '!$A$2:$M$102,5,0)/1000 -> 249.92684 | R5: =Q5/$R$2 -> 7.2040389 | S5: =R5/$R$1*1000 -> 0.25689259 | U5: =VLOOKUP(B5,'2024 by account '!$A$2:$M$102,6,0)/1000 -> 244.15647 | V5: =U5/$V$2 -> 7.0038143 | W5: =V5/$V$1*1000 -> 0.17168736 | Y5: =VLOOKUP(B5,'2024 by account '!$A$2:$M$102,7,0)/1000 -> 236.28043 | Z5: =Y5/$Z$2 -> 6.7380287 | AA5: =Z5/$Z$1*1000 -> 0.21752417 | AC5: =VLOOKUP(B5,'2024 by account '!$A$2:$M$102,8,0)/1000 -> 244.15648 | AD5: =AC5/$AD$2 -> 6.839711 | AE5: =AD5/$AD$1*1000 -> 0.19838475 | AG5: =VLOOKUP(B5,'2024 by account '!$A$2:$M$102,9,0)/1000 -> 244.15647 | AH5: =AG5/$AH$2 -> 6.579299 | AI5: =AH5/$AH$1*1000 -> 0.25722492 | AK5: =VLOOKUP(B5,'2024 by account '!$A$2:$M$102,10,0)/1000 -> 236.28045 | AL5: =AK5/$AL$2 -> 6.2468684 | AM5: =AL5/$AL$1*1000 -> 0.15576672 | AO5: =VLOOKUP(B5,'2024 by account '!$A$2:$M$102,11,0)/1000 -> 263.51746 | AP5: =AO5/$AP$2 -> 7.0558621 | AQ5: =AP5/$AP$1*1000 -> 0.17131284 | AS5: =VLOOKUP(B5,'2024 by account '!$A$2:$M$102,12,0)/1000 -> 325.48604 | AT5: =AS5/$AT$2 -> 8.8873063 | AU5: =AT5/$AT$1*1000 -> 0.20615417 | AW5: =VLOOKUP(B5,'2024 by account '!$A$2:$M$102,13,0)/1000 -> 341.7917 | AX5: =AW5/$AX$2 -> 9.323582 | AY5: =AX5/$AX$1*1000 -> 0.35650143 | BA5: =SUM(AW5,AS5,AO5,AK5,AG5,AC5,Y5,U5,Q5,M5,I5,E5) -> 3074.3921 | BB5: =SUM(AX5,AT5,AP5,AL5,AH5,AD5,Z5,V5,R5,N5,J5,F5) -> 86.346 | BC5: =BB5/$BB$1*1000 -> 0.23575314
A6: 6666110106 | B6: 6666110106 | C6: 6666110106 Depreciation of R&D facilities | D6: * CS_Depreciation | E6: =VLOOKUP(B6,'2024 by account '!$A$2:$M$102,2,0)/1000 -> 119.52379 | F6: =E6/$F$2 -> 3.6421858 | G6: =F6/$F$1*1000 -> 0.22699818 | I6: =VLOOKUP(B6,'2024 by account '!$A$2:$M$102,3,0)/1000 -> 111.81259 | J6: =I6/$J$2 -> 3.3613289 | K6: =J6/$J$1*1000 -> 0.17017664 | M6: =VLOOKUP(B6,'2024 by account '!$A$2:$M$102,4,0)/1000 -> 119.52379 | N6: =M6/$N$2 -> 3.432333 | O6: =N6/$N$1*1000 -> 0.17129975 | Q6: =VLOOKUP(B6,'2024 by account '!$A$2:$M$102,5,0)/1000 -> 115.66819 | R6: =Q6/$R$2 -> 3.3340882 | S6: =R6/$R$1*1000 -> 0.118892 | U6: =VLOOKUP(B6,'2024 by account '!$A$2:$M$102,6,0)/1000 -> 119.52379 | V6: =U6/$V$2 -> 3.428631 | W6: =V6/$V$1*1000 -> 0.084047433 | Y6: =VLOOKUP(B6,'2024 by account '!$A$2:$M$102,7,0)/1000 -> 115.66819 | Z6: =Y6/$Z$2 -> 3.2985194 | AA6: =Z6/$Z$1*1000 -> 0.10648629 | AC6: =VLOOKUP(B6,'2024 by account '!$A$2:$M$102,8,0)/1000 -> 119.5238 | AD6: =AC6/$AD$2 -> 3.3482964 | AE6: =AD6/$AD$1*1000 -> 0.097116813 | AG6: =VLOOKUP(B6,'2024 by account '!$A$2:$M$102,9,0)/1000 -> 119.52379 | AH6: =AG6/$AH$2 -> 3.2208147 | AI6: =AH6/$AH$1*1000 -> 0.12592129 | AK6: =VLOOKUP(B6,'2024 by account '!$A$2:$M$102,10,0)/1000 -> -940.76793 | AL6: =AK6/$AL$2 -> -24.872364 | AM6: =AL6/$AL$1*1000 -> -0.6201966 | AO6: =VLOOKUP(B6,'2024 by account '!$A$2:$M$102,11,0)/1000 -> 0 | AP6: =AO6/$AP$2 -> 0 | AQ6: =AP6/$AP$1*1000 -> 0 | AS6: =VLOOKUP(B6,'2024 by account '!$A$2:$M$102,12,0)/1000 -> 0 | AT6: =AS6/$AT$2 -> 0 | AU6: =AT6/$AT$1*1000 -> 0 | AW6: =VLOOKUP(B6,'2024 by account '!$A$2:$M$102,13,0)/1000 -> 0 | AX6: =AW6/$AX$2 -> 0 | AY6: =AX6/$AX$1*1000 -> 0 | BA6: =SUM(AW6,AS6,AO6,AK6,AG6,AC6,Y6,U6,Q6,M6,I6,E6) -> -1.7053026e-13 | BB6: =SUM(AX6,AT6,AP6,AL6,AH6,AD6,Z6,V6,R6,N6,J6,F6) -> 2.193833 | BC6: =BB6/$BB$1*1000 -> 0.0059898896
A7: 6666110107 | B7: 6666110107 | C7: 6666110107 Depreciation of mold | D7: * CS_Depreciation | E7: =VLOOKUP(B7,'2024 by account '!$A$2:$M$102,2,0)/1000 -> 1169.8779 | F7: =E7/$F$2 -> 35.649076 | G7: =F7/$F$1*1000 -> 2.2218184 | I7: =VLOOKUP(B7,'2024 by account '!$A$2:$M$102,3,0)/1000 -> 1865.9822 | J7: =I7/$J$2 -> 56.09547 | K7: =J7/$J$1*1000 -> 2.8399894 | M7: =VLOOKUP(B7,'2024 by account '!$A$2:$M$102,4,0)/1000 -> 1963.7318 | N7: =M7/$N$2 -> 56.391965 | O7: =N7/$N$1*1000 -> 2.8143916 | Q7: =VLOOKUP(B7,'2024 by account '!$A$2:$M$102,5,0)/1000 -> 2713.8393 | R7: =Q7/$R$2 -> 78.225308 | S7: =R7/$R$1*1000 -> 2.7894772 | U7: =VLOOKUP(B7,'2024 by account '!$A$2:$M$102,6,0)/1000 -> 2884.2665 | V7: =U7/$V$2 -> 82.737383 | W7: =V7/$V$1*1000 -> 2.0281753 | Y7: =VLOOKUP(B7,'2024 by account '!$A$2:$M$102,7,0)/1000 -> 3089.3214 | Z7: =Y7/$Z$2 -> 88.098437 | AA7: =Z7/$Z$1*1000 -> 2.8440869 | AC7: =VLOOKUP(B7,'2024 by account '!$A$2:$M$102,8,0)/1000 -> 3173.6356 | AD7: =AC7/$AD$2 -> 88.905076 | AE7: =AD7/$AD$1*1000 -> 2.5786778 | AG7: =VLOOKUP(B7,'2024 by account '!$A$2:$M$102,9,0)/1000 -> 3413.35 | AH7: =AG7/$AH$2 -> 91.979745 | AI7: =AH7/$AH$1*1000 -> 3.5960492 | AK7: =VLOOKUP(B7,'2024 by account '!$A$2:$M$102,10,0)/1000 -> 3336.5313 | AL7: =AK7/$AL$2 -> 88.212427 | AM7: =AL7/$AL$1*1000 -> 2.1995917 | AO7: =VLOOKUP(B7,'2024 by account '!$A$2:$M$102,11,0)/1000 -> 3703.6766 | AP7: =AO7/$AP$2 -> 99.168502 | AQ7: =AP7/$AP$1*1000 -> 2.4077622 | AS7: =VLOOKUP(B7,'2024 by account '!$A$2:$M$102,12,0)/1000 -> 4072.314 | AT7: =AS7/$AT$2 -> 111.19341 | AU7: =AT7/$AT$1*1000 -> 2.579295 | AW7: =VLOOKUP(B7,'2024 by account '!$A$2:$M$102,13,0)/1000 -> 4067.6831 | AX7: =AW7/$AX$2 -> 110.9605 | AY7: =AX7/$AX$1*1000 -> 4.2427445 | BA7: =SUM(AW7,AS7,AO7,AK7,AG7,AC7,Y7,U7,Q7,M7,I7,E7) -> 35454.21 | BB7: =SUM(AX7,AT7,AP7,AL7,AH7,AD7,Z7,V7,R7,N7,J7,F7) -> 987.61729 | BC7: =BB7/$BB$1*1000 -> 2.6965218
A8: 6666110110 | B8: 6666110110 | C8: 6666110110 Depreciation-Plant & Machinery | D8: * CS_Depreciation | E8: =VLOOKUP(B8,'2024 by account '!$A$2:$M$102,2,0)/1000 -> 2547.0653 | F8: =E8/$F$2 -> 77.615385 | G8: =F8/$F$1*1000 -> 4.8373565 | I8: =VLOOKUP(B8,'2024 by account '!$A$2:$M$102,3,0)/1000 -> 2536.594 | J8: =I8/$J$2 -> 76.255517 | K8: =J8/$J$1*1000 -> 3.8606479 | M8: =VLOOKUP(B8,'2024 by account '!$A$2:$M$102,4,0)/1000 -> 2822.7838 | N8: =M8/$N$2 -> 81.061135 | O8: =N8/$N$1*1000 -> 4.0455724 | Q8: =VLOOKUP(B8,'2024 by account '!$A$2:$M$102,5,0)/1000 -> 2745.5952 | R8: =Q8/$R$2 -> 79.140657 | S8: =R8/$R$1*1000 -> 2.8221181 | U8: =VLOOKUP(B8,'2024 by account '!$A$2:$M$102,6,0)/1000 -> 2888.1313 | V8: =U8/$V$2 -> 82.848247 | W8: =V8/$V$1*1000 -> 2.0308929 | Y8: =VLOOKUP(B8,'2024 by account '!$A$2:$M$102,7,0)/1000 -> 2815.4894 | Z8: =Y8/$Z$2 -> 80.289544 | AA8: =Z8/$Z$1*1000 -> 2.591992 | AC8: =VLOOKUP(B8,'2024 by account '!$A$2:$M$102,8,0)/1000 -> 2907.5193 | AD8: =AC8/$AD$2 -> 81.450189 | AE8: =AD8/$AD$1*1000 -> 2.36245 | AG8: =VLOOKUP(B8,'2024 by account '!$A$2:$M$102,9,0)/1000 -> 2915.6696 | AH8: =AG8/$AH$2 -> 78.568724 | AI8: =AH8/$AH$1*1000 -> 3.0717305 | AK8: =VLOOKUP(B8,'2024 by account '!$A$2:$M$102,10,0)/1000 -> 2825.8864 | AL8: =AK8/$AL$2 -> 74.711812 | AM8: =AL8/$AL$1*1000 -> 1.8629516 | AO8: =VLOOKUP(B8,'2024 by account '!$A$2:$M$102,11,0)/1000 -> 2983.0141 | AP8: =AO8/$AP$2 -> 79.872263 | AQ8: =AP8/$AP$1*1000 -> 1.9392591 | AS8: =VLOOKUP(B8,'2024 by account '!$A$2:$M$102,12,0)/1000 -> 2675.1702 | AT8: =AS8/$AT$2 -> 73.044782 | AU8: =AT8/$AT$1*1000 -> 1.6943814 | AW8: =VLOOKUP(B8,'2024 by account '!$A$2:$M$102,13,0)/1000 -> 2750.0647 | AX8: =AW8/$AX$2 -> 75.017777 | AY8: =AX8/$AX$1*1000 -> 2.8684196 | BA8: =SUM(AW8,AS8,AO8,AK8,AG8,AC8,Y8,U8,Q8,M8,I8,E8) -> 33412.983 | BB8: =SUM(AX8,AT8,AP8,AL8,AH8,AD8,Z8,V8,R8,N8,J8,F8) -> 939.87603 | BC8: =BB8/$BB$1*1000 -> 2.5661724
A9: 6666110112 | B9: 6666110112 | C9: 6666110112 Depreciation of Furniture & Fixture | D9: * CS_Depreciation | E9: =VLOOKUP(B9,'2024 by account '!$A$2:$M$102,2,0)/1000 -> 89.08978 | F9: =E9/$F$2 -> 2.7147862 | G9: =F9/$F$1*1000 -> 0.16919826 | I9: =VLOOKUP(B9,'2024 by account '!$A$2:$M$102,3,0)/1000 -> 88.55739 | J9: =I9/$J$2 -> 2.6622272 | K9: =J9/$J$1*1000 -> 0.13478266 | M9: =VLOOKUP(B9,'2024 by account '!$A$2:$M$102,4,0)/1000 -> 213.36808 | N9: =M9/$N$2 -> 6.1272347 | O9: =N9/$N$1*1000 -> 0.30579601 | Q9: =VLOOKUP(B9,'2024 by account '!$A$2:$M$102,5,0)/1000 -> 206.48513 | R9: =Q9/$R$2 -> 5.9518494 | S9: =R9/$R$1*1000 -> 0.21224011 | U9: =VLOOKUP(B9,'2024 by account '!$A$2:$M$102,6,0)/1000 -> -119.77734 | V9: =U9/$V$2 -> -3.4359042 | W9: =V9/$V$1*1000 -> -0.084225726 | Y9: =VLOOKUP(B9,'2024 by account '!$A$2:$M$102,7,0)/1000 -> 99.15121 | Z9: =Y9/$Z$2 -> 2.8275033 | AA9: =Z9/$Z$1*1000 -> 0.091280453 | AC9: =VLOOKUP(B9,'2024 by account '!$A$2:$M$102,8,0)/1000 -> 102.44982 | AD9: =AC9/$AD$2 -> 2.8699921 | AE9: =AD9/$AD$1*1000 -> 0.083243672 | AG9: =VLOOKUP(B9,'2024 by account '!$A$2:$M$102,9,0)/1000 -> 102.44981 | AH9: =AG9/$AH$2 -> 2.7607212 | AI9: =AH9/$AH$1*1000 -> 0.10793343 | AK9: =VLOOKUP(B9,'2024 by account '!$A$2:$M$102,10,0)/1000 -> 99.0009 | AL9: =AK9/$AL$2 -> 2.6174218 | AM9: =AL9/$AL$1*1000 -> 0.065265853 | AO9: =VLOOKUP(B9,'2024 by account '!$A$2:$M$102,11,0)/1000 -> 131.91101 | AP9: =AO9/$AP$2 -> 3.5320085 | AQ9: =AP9/$AP$1*1000 -> 0.085755419 | AS9: =VLOOKUP(B9,'2024 by account '!$A$2:$M$102,12,0)/1000 -> 140.72117 | AT9: =AS9/$AT$2 -> 3.8423526 | AU9: =AT9/$AT$1*1000 -> 0.089129033 | AW9: =VLOOKUP(B9,'2024 by account '!$A$2:$M$102,13,0)/1000 -> 143.98687 | AX9: =AW9/$AX$2 -> 3.927753 | AY9: =AX9/$AX$1*1000 -> 0.15018365 | BA9: =SUM(AW9,AS9,AO9,AK9,AG9,AC9,Y9,U9,Q9,M9,I9,E9) -> 1297.3938 | BB9: =SUM(AX9,AT9,AP9,AL9,AH9,AD9,Z9,V9,R9,N9,J9,F9) -> 36.397946 | BC9: =BB9/$BB$1*1000 -> 0.099378428
A10: 6666110204 | B10: 6666110204 | C10: 6666110204 Amortization of license, trademarks and | D10: * CS_Depreciation | E10: =VLOOKUP(B10,'2024 by account '!$A$2:$M$102,2,0)/1000 -> 0 | F10: =E10/$F$2 -> 0 | G10: =F10/$F$1*1000 -> 0 | I10: =VLOOKUP(B10,'2024 by account '!$A$2:$M$102,3,0)/1000 -> 0 | J10: =I10/$J$2 -> 0 | K10: =J10/$J$1*1000 -> 0 | M10: =VLOOKUP(B10,'2024 by account '!$A$2:$M$102,4,0)/1000 -> 0 | N10: =M10/$N$2 -> 0 | O10: =N10/$N$1*1000 -> 0 | Q10: =VLOOKUP(B10,'2024 by account '!$A$2:$M$102,5,0)/1000 -> 0 | R10: =Q10/$R$2 -> 0 | S10: =R10/$R$1*1000 -> 0 | U10: =VLOOKUP(B10,'2024 by account '!$A$2:$M$102,6,0)/1000 -> 0 | V10: =U10/$V$2 -> 0 | W10: =V10/$V$1*1000 -> 0 | Y10: =VLOOKUP(B10,'2024 by account '!$A$2:$M$102,7,0)/1000 -> 8.8359 | Z10: =Y10/$Z$2 -> 0.2519741 | AA10: =Z10/$Z$1*1000 -> 0.0081344943 | AC10: =VLOOKUP(B10,'2024 by account '!$A$2:$M$102,8,0)/1000 -> 8.8359 | AD10: =AC10/$AD$2 -> 0.2475257 | AE10: =AD10/$AD$1*1000 -> 0.0071794441 | AG10: =VLOOKUP(B10,'2024 by account '!$A$2:$M$102,9,0)/1000 -> 8.8359 | AH10: =AG10/$AH$2 -> 0.23810153 | AI10: =AH10/$AH$1*1000 -> 0.0093088406 | AK10: =VLOOKUP(B10,'2024 by account '!$A$2:$M$102,10,0)/1000 -> 8.8359 | AL10: =AK10/$AL$2 -> 0.23360674 | AM10: =AL10/$AL$1*1000 -> 0.0058250233 | AO10: =VLOOKUP(B10,'2024 by account '!$A$2:$M$102,11,0)/1000 -> 8.8359 | AP10: =AO10/$AP$2 -> 0.23658733 | AQ10: =AP10/$AP$1*1000 -> 0.0057442234 | AS10: =VLOOKUP(B10,'2024 by account '!$A$2:$M$102,12,0)/1000 -> 8.83589 | AT10: =AS10/$AT$2 -> 0.24126153 | AU10: =AT10/$AT$1*1000 -> 0.0055964169 | AW10: =VLOOKUP(B10,'2024 by account '!$A$2:$M$102,13,0)/1000 -> 8.8359 | AX10: =AW10/$AX$2 -> 0.24103054 | AY10: =AX10/$AX$1*1000 -> 0.0092161718 | BA10: =SUM(AW10,AS10,AO10,AK10,AG10,AC10,Y10,U10,Q10,M10,I10,E10) -> 61.85129 | BB10: =SUM(AX10,AT10,AP10,AL10,AH10,AD10,Z10,V10,R10,N10,J10,F10) -> 1.6900875 | BC10: =BB10/$BB$1*1000 -> 0.0046144977
A11: 6666110207 | B11: 6666110207 | C11: 6666110207 Amortization of Software | D11: * CS_Depreciation | E11: =VLOOKUP(B11,'2024 by account '!$A$2:$M$102,2,0)/1000 -> 42.95255 | F11: =E11/$F$2 -> 1.3088705 | G11: =F11/$F$1*1000 -> 0.081574979 | I11: =VLOOKUP(B11,'2024 by account '!$A$2:$M$102,3,0)/1000 -> 231.95092 | J11: =I11/$J$2 -> 6.9729477 | K11: =J11/$J$1*1000 -> 0.35302489 | M11: =VLOOKUP(B11,'2024 by account '!$A$2:$M$102,4,0)/1000 -> 142.03351 | N11: =M11/$N$2 -> 4.0787387 | O11: =N11/$N$1*1000 -> 0.20356035 | Q11: =VLOOKUP(B11,'2024 by account '!$A$2:$M$102,5,0)/1000 -> 137.45174 | R11: =Q11/$R$2 -> 3.9619902 | S11: =R11/$R$1*1000 -> 0.14128268 | U11: =VLOOKUP(B11,'2024 by account '!$A$2:$M$102,6,0)/1000 -> 147.71371 | V11: =U11/$V$2 -> 4.2372803 | W11: =V11/$V$1*1000 -> 0.10387018 | Y11: =VLOOKUP(B11,'2024 by account '!$A$2:$M$102,7,0)/1000 -> 143.13192 | Z11: =Y11/$Z$2 -> 4.0817049 | AA11: =Z11/$Z$1*1000 -> 0.13176991 | AC11: =VLOOKUP(B11,'2024 by account '!$A$2:$M$102,8,0)/1000 -> 147.71372 | AD11: =AC11/$AD$2 -> 4.1379985 | AE11: =AD11/$AD$1*1000 -> 0.120022 | AG11: =VLOOKUP(B11,'2024 by account '!$A$2:$M$102,9,0)/1000 -> 147.71368 | AH11: =AG11/$AH$2 -> 3.9804494 | AI11: =AH11/$AH$1*1000 -> 0.15562004 | AK11: =VLOOKUP(B11,'2024 by account '!$A$2:$M$102,10,0)/1000 -> 143.13197 | AL11: =AK11/$AL$2 -> 3.784175 | AM11: =AL11/$AL$1*1000 -> 0.094359043 | AO11: =VLOOKUP(B11,'2024 by account '!$A$2:$M$102,11,0)/1000 -> 147.71368 | AP11: =AO11/$AP$2 -> 3.9551359 | AQ11: =AP11/$AP$1*1000 -> 0.096028744 | AS11: =VLOOKUP(B11,'2024 by account '!$A$2:$M$102,12,0)/1000 -> 157.90803 | AT11: =AS11/$AT$2 -> 4.3116351 | AU11: =AT11/$AT$1*1000 -> 0.10001473 | AW11: =VLOOKUP(B11,'2024 by account '!$A$2:$M$102,13,0)/1000 -> 162.48976 | AX11: =AW11/$AX$2 -> 4.432485 | AY11: =AX11/$AX$1*1000 -> 0.16948285 | BA11: =SUM(AW11,AS11,AO11,AK11,AG11,AC11,Y11,U11,Q11,M11,I11,E11) -> 1751.9052 | BB11: =SUM(AX11,AT11,AP11,AL11,AH11,AD11,Z11,V11,R11,N11,J11,F11) -> 49.243411 | BC11: =BB11/$BB$1*1000 -> 0.1344508
A12: 6666110506 | B12: 6666110506 | C12: 6666110506 Amortization-Leasehold Improvement | D12: * CS_Depreciation | E12: =VLOOKUP(B12,'2024 by account '!$A$2:$M$102,2,0)/1000 -> 0 | F12: =E12/$F$2 -> 0 | G12: =F12/$F$1*1000 -> 0 | I12: =VLOOKUP(B12,'2024 by account '!$A$2:$M$102,3,0)/1000 -> 0 | J12: =I12/$J$2 -> 0 | K12: =J12/$J$1*1000 -> 0 | M12: =VLOOKUP(B12,'2024 by account '!$A$2:$M$102,4,0)/1000 -> 0 | N12: =M12/$N$2 -> 0 | O12: =N12/$N$1*1000 -> 0 | Q12: =VLOOKUP(B12,'2024 by account '!$A$2:$M$102,5,0)/1000 -> 0 | R12: =Q12/$R$2 -> 0 | S12: =R12/$R$1*1000 -> 0 | U12: =VLOOKUP(B12,'2024 by account '!$A$2:$M$102,6,0)/1000 -> 29.84724 | V12: =U12/$V$2 -> 0.85619082 | W12: =V12/$V$1*1000 -> 0.020988156 | Y12: =VLOOKUP(B12,'2024 by account '!$A$2:$M$102,7,0)/1000 -> 29.84724 | Z12: =Y12/$Z$2 -> 0.85115623 | AA12: =Z12/$Z$1*1000 -> 0.027477926 | AC12: =VLOOKUP(B12,'2024 by account '!$A$2:$M$102,8,0)/1000 -> 29.84724 | AD12: =AC12/$AD$2 -> 0.83612975 | AE12: =AD12/$AD$1*1000 -> 0.024251813 | AG12: =VLOOKUP(B12,'2024 by account '!$A$2:$M$102,9,0)/1000 -> 29.84724 | AH12: =AG12/$AH$2 -> 0.80429536 | AI12: =AH12/$AH$1*1000 -> 0.03144481 | AK12: =VLOOKUP(B12,'2024 by account '!$A$2:$M$102,10,0)/1000 -> 29.84724 | AL12: =AK12/$AL$2 -> 0.78911218 | AM12: =AL12/$AL$1*1000 -> 0.019676645 | AO12: =VLOOKUP(B12,'2024 by account '!$A$2:$M$102,11,0)/1000 -> 29.84724 | AP12: =AO12/$AP$2 -> 0.79918048 | AQ12: =AP12/$AP$1*1000 -> 0.019403707 | AS12: =VLOOKUP(B12,'2024 by account '!$A$2:$M$102,12,0)/1000 -> 29.84725 | AT12: =AS12/$AT$2 -> 0.81497091 | AU12: =AT12/$AT$1*1000 -> 0.018904452 | AW12: =VLOOKUP(B12,'2024 by account '!$A$2:$M$102,13,0)/1000 -> 29.84724 | AX12: =AW12/$AX$2 -> 0.81418943 | AY12: =AX12/$AX$1*1000 -> 0.031131779 | BA12: =SUM(AW12,AS12,AO12,AK12,AG12,AC12,Y12,U12,Q12,M12,I12,E12) -> 238.77793 | BB12: =SUM(AX12,AT12,AP12,AL12,AH12,AD12,Z12,V12,R12,N12,J12,F12) -> 6.5652251 | BC12: =BB12/$BB$1*1000 -> 0.017925236
B13: FIX | C13: * CS_Depreciation | E13: =SUM(E5:E12) -> 4197.5573 | F13: =E13/$F$2 -> 127.90996 | G13: =F13/$F$1*1000 -> 7.9719515 | I13: =SUM(I5:I12) -> 5050.3325 | J13: =SUM(J5:J12) -> 151.82395 | K13: =J13/$J$1*1000 -> 7.68651 | M13: =SUM(M5:M12) -> 5505.5974 | N13: =SUM(N5:N12) -> 158.10278 | O13: =N13/$N$1*1000 -> 7.8905417 | Q13: =SUM(Q5:Q12) -> 6168.9664 | R13: =Q13/$R$2 -> 177.81793 | S13: =R13/$R$1*1000 -> 6.3409026 | U13: =SUM(U5:U12) -> 6193.8617 | V13: =U13/$V$2 -> 177.67564 | W13: =V13/$V$1*1000 -> 4.3554356 | Y13: =SUM(Y5:Y12) -> 6537.7257 | Z13: =Y13/$Z$2 -> 186.43687 | AA13: =Z13/$Z$1*1000 -> 6.0187522 | AC13: =SUM(AC5:AC12) -> 6733.6818 | AD13: =AC13/$AD$2 -> 188.63492 | AE13: =AD13/$AD$1*1000 -> 5.4713263 | AG13: =SUM(AG5:AG12) -> 6981.5465 | AH13: =AG13/$AH$2 -> 188.13215 | AI13: =AH13/$AH$1*1000 -> 7.355233 | AK13: =SUM(AK5:AK12) -> 5738.7463 | AL13: =AK13/$AL$2 -> 151.72306 | AM13: =AL13/$AL$1*1000 -> 3.78324 | AO13: =SUM(AO5:AO12) -> 7268.516 | AP13: =AO13/$AP$2 -> 194.61954 | AQ13: =AP13/$AP$1*1000 -> 4.7252662 | AS13: =SUM(AS5:AS12) -> 7410.2826 | AT13: =AS13/$AT$2 -> 202.33572 | AU13: =AT13/$AT$1*1000 -> 4.6934752 | AW13: =SUM(AW5:AW12) -> 7504.6993 | AX13: =AW13/$AX$2 -> 204.71731 | AY13: =AX13/$AX$1*1000 -> 7.82768 | BA13: =SUM(AW13,AS13,AO13,AK13,AG13,AC13,Y13,U13,Q13,M13,I13,E13) -> 75291.513 | BB13: =SUM(AX13,AT13,AP13,AL13,AH13,AD13,Z13,V13,R13,N13,J13,F13) -> 2109.9298 | BC13: =BB13/$BB$1*1000 -> 5.7608062
A14: 5001010205 | B14: 5001010205 | C14: 5001010205 Unemployment Insurance -blue collar-Dire | D14: * CS_Direct Labour | E14: =VLOOKUP(B14,'2024 by account '!$A$2:$M$102,2,0)/1000 -> 93.63996 | F14: =E14/$F$2 -> 2.8534414 | G14: =F14/$F$1*1000 -> 0.17783991 | I14: =VLOOKUP(B14,'2024 by account '!$A$2:$M$102,3,0)/1000 -> 278.32027 | J14: =I14/$J$2 -> 8.3669109 | K14: =J14/$J$1*1000 -> 0.42359816 | M14: =VLOOKUP(B14,'2024 by account '!$A$2:$M$102,4,0)/1000 -> 127.67943 | N14: =M14/$N$2 -> 3.6665364 | O14: =N14/$N$1*1000 -> 0.18298829 | Q14: =VLOOKUP(B14,'2024 by account '!$A$2:$M$102,5,0)/1000 -> 219.87927 | R14: =Q14/$R$2 -> 6.33793 | S14: =R14/$R$1*1000 -> 0.22600756 | U14: =VLOOKUP(B14,'2024 by account '!$A$2:$M$102,6,0)/1000 -> 219.76398 | V14: =U14/$V$2 -> 6.3040972 | W14: =V14/$V$1*1000 -> 0.15453491 | Y14: =VLOOKUP(B14,'2024 by account '!$A$2:$M$102,7,0)/1000 -> -1233.5907 | Z14: =Y14/$Z$2 -> -35.178409 | AA14: =Z14/$Z$1*1000 -> -1.1356666 | AC14: =VLOOKUP(B14,'2024 by account '!$A$2:$M$102,8,0)/1000 -> 127.96846 | AD14: =AC14/$AD$2 -> 3.584862 | AE14: =AD14/$AD$1*1000 -> 0.10397836 | AG14: =VLOOKUP(B14,'2024 by account '!$A$2:$M$102,9,0)/1000 -> 216.4907 | AH14: =AG14/$AH$2 -> 5.8337878 | AI14: =AH14/$AH$1*1000 -> 0.22807834 | AK14: =VLOOKUP(B14,'2024 by account '!$A$2:$M$102,10,0)/1000 -> 267.50368 | AL14: =AK14/$AL$2 -> 7.0723595 | AM14: =AL14/$AL$1*1000 -> 0.17635048 | AO14: =VLOOKUP(B14,'2024 by account '!$A$2:$M$102,11,0)/1000 -> 273.72953 | AP14: =AO14/$AP$2 -> 7.3292973 | AQ14: =AP14/$AP$1*1000 -> 0.17795172 | AS14: =VLOOKUP(B14,'2024 by account '!$A$2:$M$102,12,0)/1000 -> 255.52615 | AT14: =AS14/$AT$2 -> 6.9770709 | AU14: =AT14/$AT$1*1000 -> 0.16184344 | AW14: =VLOOKUP(B14,'2024 by account '!$A$2:$M$102,13,0)/1000 -> 256.71133 | AX14: =AW14/$AX$2 -> 7.0027129 | AY14: =AX14/$AX$1*1000 -> 0.26775945 | BA14: =SUM(AW14,AS14,AO14,AK14,AG14,AC14,Y14,U14,Q14,M14,I14,E14) -> 1103.6221 | BB14: =SUM(AX14,AT14,AP14,AL14,AH14,AD14,Z14,V14,R14,N14,J14,F14) -> 30.150597 | BC14: =BB14/$BB$1*1000 -> 0.082321102
A15: 6666010380 | B15: 6666010380 | C15: 6666010380 Incentive | D15: * CS_Direct Labour | E15: =VLOOKUP(B15,'2024 by account '!$A$2:$M$102,2,0)/1000 -> -15.29521 | F15: =E15/$F$2 -> -0.46608292 | G15: =F15/$F$1*1000 -> -0.029048483 | I15: =VLOOKUP(B15,'2024 by account '!$A$2:$M$102,3,0)/1000 -> -15.2952 | J15: =I15/$J$2 -> -0.45980688 | K15: =J15/$J$1*1000 -> -0.023279004 | M15: =VLOOKUP(B15,'2024 by account '!$A$2:$M$102,4,0)/1000 -> -14.26176 | N15: =M15/$N$2 -> -0.40955119 | O15: =N15/$N$1*1000 -> -0.020439746 | Q15: =VLOOKUP(B15,'2024 by account '!$A$2:$M$102,5,0)/1000 -> -51.17454 | R15: =Q15/$R$2 -> -1.4750852 | S15: =R15/$R$1*1000 -> -0.052600834 | U15: =VLOOKUP(B15,'2024 by account '!$A$2:$M$102,6,0)/1000 -> -43.87473 | V15: =U15/$V$2 -> -1.2585801 | W15: =V15/$V$1*1000 -> -0.030852087 | Y15: =VLOOKUP(B15,'2024 by account '!$A$2:$M$102,7,0)/1000 -> -44.25363 | Z15: =Y15/$Z$2 -> -1.2619844 | AA15: =Z15/$Z$1*1000 -> -0.040740717 | AC15: =VLOOKUP(B15,'2024 by account '!$A$2:$M$102,8,0)/1000 -> -45.88254 | AD15: =AC15/$AD$2 -> -1.2853368 | AE15: =AD15/$AD$1*1000 -> -0.037280994 | AG15: =VLOOKUP(B15,'2024 by account '!$A$2:$M$102,9,0)/1000 -> -47.3294 | AH15: =AG15/$AH$2 -> -1.2753882 | AI15: =AH15/$AH$1*1000 -> -0.049862701 | AK15: =VLOOKUP(B15,'2024 by account '!$A$2:$M$102,10,0)/1000 -> -50.9899 | AL15: =AK15/$AL$2 -> -1.3480895 | AM15: =AL15/$AL$1*1000 -> -0.033614839 | AO15: =VLOOKUP(B15,'2024 by account '!$A$2:$M$102,11,0)/1000 -> -49.40683 | AP15: =AO15/$AP$2 -> -1.322902 | AQ15: =AP15/$AP$1*1000 -> -0.032119407 | AS15: =VLOOKUP(B15,'2024 by account '!$A$2:$M$102,12,0)/1000 -> -45.20467 | AT15: =AS15/$AT$2 -> -1.234301 | AU15: =AT15/$AT$1*1000 -> -0.028631432 | AW15: =VLOOKUP(B15,'2024 by account '!$A$2:$M$102,13,0)/1000 -> -47.04062 | AX15: =AW15/$AX$2 -> -1.2831999 | AY15: =AX15/$AX$1*1000 -> -0.049065113 | BA15: =SUM(AW15,AS15,AO15,AK15,AG15,AC15,Y15,U15,Q15,M15,I15,E15) -> -470.00903 | BB15: =SUM(AX15,AT15,AP15,AL15,AH15,AD15,Z15,V15,R15,N15,J15,F15) -> -13.080308 | BC15: =BB15/$BB$1*1000 -> -0.035713567
A16: 6666010019 | B16: 6666010019 | C16: 6666010019 Payroll Taxes - Blue Collar Direct | D16: * CS_Direct Labour | E16: =VLOOKUP(B16,'2024 by account '!$A$2:$M$102,2,0)/1000 -> 735.87608 | F16: =E16/$F$2 -> 22.423966 | G16: =F16/$F$1*1000 -> 1.3975672 | I16: =VLOOKUP(B16,'2024 by account '!$A$2:$M$102,3,0)/1000 -> 2185.2993 | J16: =I16/$J$2 -> 65.694837 | K16: =J16/$J$1*1000 -> 3.325984 | M16: =VLOOKUP(B16,'2024 by account '!$A$2:$M$102,4,0)/1000 -> 1003.3241 | N16: =M16/$N$2 -> 28.812193 | O16: =N16/$N$1*1000 -> 1.4379494 | Q16: =VLOOKUP(B16,'2024 by account '!$A$2:$M$102,5,0)/1000 -> 1730.1727 | R16: =Q16/$R$2 -> 49.87152 | S16: =R16/$R$1*1000 -> 1.7783946 | U16: =VLOOKUP(B16,'2024 by account '!$A$2:$M$102,6,0)/1000 -> 1728.7086 | V16: =U16/$V$2 -> 49.589322 | W16: =V16/$V$1*1000 -> 1.2156033 | Y16: =VLOOKUP(B16,'2024 by account '!$A$2:$M$102,7,0)/1000 -> 1955.0052 | Z16: =Y16/$Z$2 -> 55.751045 | AA16: =Z16/$Z$1*1000 -> 1.7998142 | AC16: =VLOOKUP(B16,'2024 by account '!$A$2:$M$102,8,0)/1000 -> 1727.4339 | AD16: =AC16/$AD$2 -> 48.391707 | AE16: =AD16/$AD$1*1000 -> 1.4035939 | AG16: =VLOOKUP(B16,'2024 by account '!$A$2:$M$102,9,0)/1000 -> 1704.2015 | AH16: =AG16/$AH$2 -> 45.923218 | AI16: =AH16/$AH$1*1000 -> 1.7954187 | AK16: =VLOOKUP(B16,'2024 by account '!$A$2:$M$102,10,0)/1000 -> 2143.2484 | AL16: =AK16/$AL$2 -> 56.663979 | AM16: =AL16/$AL$1*1000 -> 1.4129259 | AO16: =VLOOKUP(B16,'2024 by account '!$A$2:$M$102,11,0)/1000 -> 2190.4237 | AP16: =AO16/$AP$2 -> 58.650108 | AQ16: =AP16/$AP$1*1000 -> 1.4239956 | AS16: =VLOOKUP(B16,'2024 by account '!$A$2:$M$102,12,0)/1000 -> 2043.1771 | AT16: =AS16/$AT$2 -> 55.788386 | AU16: =AT16/$AT$1*1000 -> 1.2940938 | AW16: =VLOOKUP(B16,'2024 by account '!$A$2:$M$102,13,0)/1000 -> 2052.716 | AX16: =AW16/$AX$2 -> 55.995115 | AY16: =AX16/$AX$1*1000 -> 2.141059 | BA16: =SUM(AW16,AS16,AO16,AK16,AG16,AC16,Y16,U16,Q16,M16,I16,E16) -> 21199.586 | BB16: =SUM(AX16,AT16,AP16,AL16,AH16,AD16,Z16,V16,R16,N16,J16,F16) -> 593.5554 | BC16: =BB16/$BB$1*1000 -> 1.6206025
A17: 6666010183 | B17: 6666010183 | C17: 6666010183 Overtime-Blue Collar-Direct | D17: * CS_Direct Labour | E17: =VLOOKUP(B17,'2024 by account '!$A$2:$M$102,2,0)/1000 -> 3.0032 | F17: =E17/$F$2 -> 0.091514939 | G17: =F17/$F$1*1000 -> 0.0057036422 | I17: =VLOOKUP(B17,'2024 by account '!$A$2:$M$102,3,0)/1000 -> 384.55487 | J17: =I17/$J$2 -> 11.560553 | K17: =J17/$J$1*1000 -> 0.5852852 | M17: =VLOOKUP(B17,'2024 by account '!$A$2:$M$102,4,0)/1000 -> 241.26001 | N17: =M17/$N$2 -> 6.9281998 | O17: =N17/$N$1*1000 -> 0.34577032 | Q17: =VLOOKUP(B17,'2024 by account '!$A$2:$M$102,5,0)/1000 -> 1361.6904 | R17: =Q17/$R$2 -> 39.250168 | S17: =R17/$R$1*1000 -> 1.3996423 | U17: =VLOOKUP(B17,'2024 by account '!$A$2:$M$102,6,0)/1000 -> 756.53928 | V17: =U17/$V$2 -> 21.701906 | W17: =V17/$V$1*1000 -> 0.53198768 | Y17: =VLOOKUP(B17,'2024 by account '!$A$2:$M$102,7,0)/1000 -> 326.00622 | Z17: =Y17/$Z$2 -> 9.2967465 | AA17: =Z17/$Z$1*1000 -> 0.3001274 | AC17: =VLOOKUP(B17,'2024 by account '!$A$2:$M$102,8,0)/1000 -> 555.05243 | AD17: =AC17/$AD$2 -> 15.549037 | AE17: =AD17/$AD$1*1000 -> 0.4509974 | AG17: =VLOOKUP(B17,'2024 by account '!$A$2:$M$102,9,0)/1000 -> 277.24708 | AH17: =AG17/$AH$2 -> 7.4709936 | AI17: =AH17/$AH$1*1000 -> 0.2920867 | AK17: =VLOOKUP(B17,'2024 by account '!$A$2:$M$102,10,0)/1000 -> 517.45021 | AL17: =AK17/$AL$2 -> 13.680537 | AM17: =AL17/$AL$1*1000 -> 0.34112649 | AO17: =VLOOKUP(B17,'2024 by account '!$A$2:$M$102,11,0)/1000 -> 953.19511 | AP17: =AO17/$AP$2 -> 25.522458 | AQ17: =AP17/$AP$1*1000 -> 0.61967266 | AS17: =VLOOKUP(B17,'2024 by account '!$A$2:$M$102,12,0)/1000 -> 782.80508 | AT17: =AS17/$AT$2 -> 21.374276 | AU17: =AT17/$AT$1*1000 -> 0.49580785 | AW17: =VLOOKUP(B17,'2024 by account '!$A$2:$M$102,13,0)/1000 -> 439.8043 | AX17: =AW17/$AX$2 -> 11.997224 | AY17: =AX17/$AX$1*1000 -> 0.45873221 | BA17: =SUM(AW17,AS17,AO17,AK17,AG17,AC17,Y17,U17,Q17,M17,I17,E17) -> 6598.6082 | BB17: =SUM(AX17,AT17,AP17,AL17,AH17,AD17,Z17,V17,R17,N17,J17,F17) -> 184.42361 | BC17: =BB17/$BB$1*1000 -> 0.50353745
A18: 6666010229 | B18: 6666010229 | C18: 6666010229 Staff Leaving Indemnity - Blue Collar Di | D18: * CS_Direct Labour | E18: =VLOOKUP(B18,'2024 by account '!$A$2:$M$102,2,0)/1000 -> 422.9396 | F18: =E18/$F$2 -> 12.888017 | G18: =F18/$F$1*1000 -> 0.80324193 | I18: =VLOOKUP(B18,'2024 by account '!$A$2:$M$102,3,0)/1000 -> 650.58637 | J18: =I18/$J$2 -> 19.558037 | K18: =J18/$J$1*1000 -> 0.99018009 | M18: =VLOOKUP(B18,'2024 by account '!$A$2:$M$102,4,0)/1000 -> 65.75232 | N18: =M18/$N$2 -> 1.888192 | O18: =N18/$N$1*1000 -> 0.094235263 | Q18: =VLOOKUP(B18,'2024 by account '!$A$2:$M$102,5,0)/1000 -> 356.45789 | R18: =Q18/$R$2 -> 10.274753 | S18: =R18/$R$1*1000 -> 0.36639278 | U18: =VLOOKUP(B18,'2024 by account '!$A$2:$M$102,6,0)/1000 -> 272.91219 | V18: =U18/$V$2 -> 7.8286941 | W18: =V18/$V$1*1000 -> 0.19190798 | Y18: =VLOOKUP(B18,'2024 by account '!$A$2:$M$102,7,0)/1000 -> 318.15728 | Z18: =Y18/$Z$2 -> 9.0729176 | AA18: =Z18/$Z$1*1000 -> 0.29290152 | AC18: =VLOOKUP(B18,'2024 by account '!$A$2:$M$102,8,0)/1000 -> 330.71258 | AD18: =AC18/$AD$2 -> 9.2644622 | AE18: =AD18/$AD$1*1000 -> 0.26871428 | AG18: =VLOOKUP(B18,'2024 by account '!$A$2:$M$102,9,0)/1000 -> 355.12886 | AH18: =AG18/$AH$2 -> 9.5696786 | AI18: =AH18/$AH$1*1000 -> 0.3741371 | AK18: =VLOOKUP(B18,'2024 by account '!$A$2:$M$102,10,0)/1000 -> 361.58152 | AL18: =AK18/$AL$2 -> 9.5596236 | AM18: =AL18/$AL$1*1000 -> 0.23837083 | AO18: =VLOOKUP(B18,'2024 by account '!$A$2:$M$102,11,0)/1000 -> 391.85944 | AP18: =AO18/$AP$2 -> 10.492307 | AQ18: =AP18/$AP$1*1000 -> 0.25474803 | AS18: =VLOOKUP(B18,'2024 by account '!$A$2:$M$102,12,0)/1000 -> 397.85932 | AT18: =AS18/$AT$2 -> 10.863439 | AU18: =AT18/$AT$1*1000 -> 0.25199347 | AW18: =VLOOKUP(B18,'2024 by account '!$A$2:$M$102,13,0)/1000 -> 415.06652 | AX18: =AW18/$AX$2 -> 11.322413 | AY18: =AX18/$AX$1*1000 -> 0.43292979 | BA18: =SUM(AW18,AS18,AO18,AK18,AG18,AC18,Y18,U18,Q18,M18,I18,E18) -> 4339.0139 | BB18: =SUM(AX18,AT18,AP18,AL18,AH18,AD18,Z18,V18,R18,N18,J18,F18) -> 122.58253 | BC18: =BB18/$BB$1*1000 -> 0.33469085
A19: 6666010188 | B19: 6666010188 | C19: 6666010188 Salary - Blue collar direct employees | D19: * CS_Direct Labour | E19: =VLOOKUP(B19,'2024 by account '!$A$2:$M$102,2,0)/1000 -> 4465.9794 | F19: =E19/$F$2 -> 136.08945 | G19: =F19/$F$1*1000 -> 8.4817356 | I19: =VLOOKUP(B19,'2024 by account '!$A$2:$M$102,3,0)/1000 -> 13639.447 | J19: =I19/$J$2 -> 410.03136 | K19: =J19/$J$1*1000 -> 20.758979 | M19: =VLOOKUP(B19,'2024 by account '!$A$2:$M$102,4,0)/1000 -> 4580.1428 | N19: =M19/$N$2 -> 131.52675 | O19: =N19/$N$1*1000 -> 6.5641936 | Q19: =VLOOKUP(B19,'2024 by account '!$A$2:$M$102,5,0)/1000 -> 9638.4984 | R19: =Q19/$R$2 -> 277.82577 | S19: =R19/$R$1*1000 -> 9.9071345 | U19: =VLOOKUP(B19,'2024 by account '!$A$2:$M$102,6,0)/1000 -> 10259.971 | V19: =U19/$V$2 -> 294.31509 | W19: =V19/$V$1*1000 -> 7.2146662 | Y19: =VLOOKUP(B19,'2024 by account '!$A$2:$M$102,7,0)/1000 -> 12027.994 | Z19: =Y19/$Z$2 -> 343.0033 | AA19: =Z19/$Z$1*1000 -> 11.073195 | AC19: =VLOOKUP(B19,'2024 by account '!$A$2:$M$102,8,0)/1000 -> 9147.0945 | AD19: =AC19/$AD$2 -> 256.24339 | AE19: =AD19/$AD$1*1000 -> 7.4322994 | AG19: =VLOOKUP(B19,'2024 by account '!$A$2:$M$102,9,0)/1000 -> 10575.982 | AH19: =AG19/$AH$2 -> 284.99162 | AI19: =AH19/$AH$1*1000 -> 11.14206 | AK19: =VLOOKUP(B19,'2024 by account '!$A$2:$M$102,10,0)/1000 -> 12607.756 | AL19: =AK19/$AL$2 -> 333.32843 | AM19: =AL19/$AL$1*1000 -> 8.3116006 | AO19: =VLOOKUP(B19,'2024 by account '!$A$2:$M$102,11,0)/1000 -> 12454.578 | AP19: =AO19/$AP$2 -> 333.47994 | AQ19: =AP19/$AP$1*1000 -> 8.096728 | AS19: =VLOOKUP(B19,'2024 by account '!$A$2:$M$102,12,0)/1000 -> 11929.47 | AT19: =AS19/$AT$2 -> 325.73088 | AU19: =AT19/$AT$1*1000 -> 7.5558079 | AW19: =VLOOKUP(B19,'2024 by account '!$A$2:$M$102,13,0)/1000 -> 10234.573 | AX19: =AW19/$AX$2 -> 279.18432 | AY19: =AX19/$AX$1*1000 -> 10.67504 | BA19: =SUM(AW19,AS19,AO19,AK19,AG19,AC19,Y19,U19,Q19,M19,I19,E19) -> 121561.49 | BB19: =SUM(AX19,AT19,AP19,AL19,AH19,AD19,Z19,V19,R19,N19,J19,F19) -> 3405.7503 | BC19: =BB19/$BB$1*1000 -> 9.2988246
A20: 5102040406 | B20: 5102040406 | C20: 5102040406 Other revenue-Service/Secondment agreeme | D20: * CS_Direct Labour | F20: =E20/$F$2 -> 0 | G20: =F20/$F$1*1000 -> 0 | K20: =J20/$J$1*1000 -> 0 | O20: =N20/$N$1*1000 -> 0 | R20: =Q20/$R$2 -> 0 | S20: =R20/$R$1*1000 -> 0 | V20: =U20/$V$2 -> 0 | W20: =V20/$V$1*1000 -> 0 | Z20: =Y20/$Z$2 -> 0 | AA20: =Z20/$Z$1*1000 -> 0 | AD20: =AC20/$AD$2 -> 0 | AE20: =AD20/$AD$1*1000 -> 0 | AH20: =AG20/$AH$2 -> 0 | AI20: =AH20/$AH$1*1000 -> 0 | AL20: =AK20/$AL$2 -> 0 | AM20: =AL20/$AL$1*1000 -> 0 | AP20: =AO20/$AP$2 -> 0 | AQ20: =AP20/$AP$1*1000 -> 0 | AT20: =AS20/$AT$2 -> 0 | AU20: =AT20/$AT$1*1000 -> 0 | AX20: =AW20/$AX$2 -> 0 | AY20: =AX20/$AX$1*1000 -> 0 | BA20: =SUM(AW20,AS20,AO20,AK20,AG20,AC20,Y20,U20,Q20,M20,I20,E20) -> 0 | BB20: =SUM(AX20,AT20,AP20,AL20,AH20,AD20,Z20,V20,R20,N20,J20,F20) -> 0 | BC20: =BB20/$BB$1*1000 -> 0
A21: 6666010115 | B21: 6666010115 | C21: 6666010115 Salary-Blue collar direct employees-Accr | D21: * CS_Direct Labour | E21: =VLOOKUP(B21,'2024 by account '!$A$2:$M$102,2,0)/1000 -> 76.87885 | F21: =E21/$F$2 -> 2.3426889 | G21: =F21/$F$1*1000 -> 0.14600741 | I21: =VLOOKUP(B21,'2024 by account '!$A$2:$M$102,3,0)/1000 -> -10888.235 | J21: =I21/$J$2 -> -327.32394 | K21: =J21/$J$1*1000 -> -16.571686 | M21: =VLOOKUP(B21,'2024 by account '!$A$2:$M$102,4,0)/1000 -> -366.10808 | N21: =M21/$N$2 -> -10.513429 | O21: =N21/$N$1*1000 -> -0.52470074 | Q21: =VLOOKUP(B21,'2024 by account '!$A$2:$M$102,5,0)/1000 -> -8.33235 | R21: =Q21/$R$2 -> -0.24017658 | S21: =R21/$R$1*1000 -> -0.0085645822 | U21: =VLOOKUP(B21,'2024 by account '!$A$2:$M$102,6,0)/1000 -> 35.23943 | V21: =U21/$V$2 -> 1.0108699 | W21: =V21/$V$1*1000 -> 0.024779867 | Y21: =VLOOKUP(B21,'2024 by account '!$A$2:$M$102,7,0)/1000 -> -3.60165 | Z21: =Y21/$Z$2 -> -0.10270855 | AA21: =Z21/$Z$1*1000 -> -0.0033157461 | AC21: =VLOOKUP(B21,'2024 by account '!$A$2:$M$102,8,0)/1000 -> 140.22936 | AD21: =AC21/$AD$2 -> 3.9283344 | AE21: =AD21/$AD$1*1000 -> 0.11394073 | AG21: =VLOOKUP(B21,'2024 by account '!$A$2:$M$102,9,0)/1000 -> -135.88477 | AH21: =AG21/$AH$2 -> -3.661695 | AI21: =AH21/$AH$1*1000 -> -0.14315799 | AK21: =VLOOKUP(B21,'2024 by account '!$A$2:$M$102,10,0)/1000 -> 25.77998 | AL21: =AK21/$AL$2 -> 0.68158048 | AM21: =AL21/$AL$1*1000 -> 0.016995324 | AO21: =VLOOKUP(B21,'2024 by account '!$A$2:$M$102,11,0)/1000 -> 74.7254 | AP21: =AO21/$AP$2 -> 2.0008242 | AQ21: =AP21/$AP$1*1000 -> 0.048579023 | AS21: =VLOOKUP(B21,'2024 by account '!$A$2:$M$102,12,0)/1000 -> -58.9807 | AT21: =AS21/$AT$2 -> -1.6104517 | AU21: =AT21/$AT$1*1000 -> -0.037356801 | AW21: =VLOOKUP(B21,'2024 by account '!$A$2:$M$102,13,0)/1000 -> -47.45002 | AX21: =AW21/$AX$2 -> -1.2943677 | AY21: =AX21/$AX$1*1000 -> -0.049492133 | BA21: =SUM(AW21,AS21,AO21,AK21,AG21,AC21,Y21,U21,Q21,M21,I21,E21) -> -11155.739 | BB21: =SUM(AX21,AT21,AP21,AL21,AH21,AD21,Z21,V21,R21,N21,J21,F21) -> -334.78247 | BC21: =BB21/$BB$1*1000 -> -0.91406686
B22: VAR | C22: * CS_Direct Labour | E22: =SUM(E14:E21) -> 5783.0218 | F22: =E22/$F$2 -> 176.22299 | G22: =F22/$F$1*1000 -> 10.983047 | I22: =SUM(I14:I21) -> 6234.6782 | J22: =SUM(J14:J21) -> 187.42795 | K22: =J22/$J$1*1000 -> 9.4890617 | M22: =SUM(M14:M21) -> 5637.7888 | N22: =SUM(N14:N21) -> 161.89889 | O22: =N22/$N$1*1000 -> 8.0799964 | Q22: =SUM(Q14:Q21) -> 13247.192 | R22: =Q22/$R$2 -> 381.84488 | S22: =R22/$R$1*1000 -> 13.616406 | U22: =SUM(U14:U21) -> 13229.26 | V22: =U22/$V$2 -> 379.4914 | W22: =V22/$V$1*1000 -> 9.3026279 | Y22: =SUM(Y14:Y21) -> 13345.717 | Z22: =Y22/$Z$2 -> 380.58091 | AA22: =Z22/$Z$1*1000 -> 12.286315 | AC22: =SUM(AC14:AC21) -> 11982.609 | AD22: =AC22/$AD$2 -> 335.67645 | AE22: =AD22/$AD$1*1000 -> 9.7362431 | AG22: =SUM(AG14:AG21) -> 12945.836 | AH22: =AG22/$AH$2 -> 348.85222 | AI22: =AH22/$AH$1*1000 -> 13.638761 | AK22: =SUM(AK14:AK21) -> 15872.33 | AL22: =AK22/$AL$2 -> 419.63842 | AM22: =AL22/$AL$1*1000 -> 10.463755 | AO22: =SUM(AO14:AO21) -> 16289.104 | AP22: =AO22/$AP$2 -> 436.15203 | AQ22: =AP22/$AP$1*1000 -> 10.589556 | AS22: =SUM(AS14:AS21) -> 15304.652 | AT22: =AS22/$AT$2 -> 417.8893 | AU22: =AT22/$AT$1*1000 -> 9.6935583 | AW22: =SUM(AW14:AW21) -> 13304.381 | AX22: =AW22/$AX$2 -> 362.92421 | AY22: =AX22/$AX$1*1000 -> 13.876963 | BA22: =SUM(AW22,AS22,AO22,AK22,AG22,AC22,Y22,U22,Q22,M22,I22,E22) -> 143176.57 | BB22: =SUM(AX22,AT22,AP22,AL22,AH22,AD22,Z22,V22,R22,N22,J22,F22) -> 3988.5996 | BC22: =BB22/$BB$1*1000 -> 10.890196
A23: 8701530201 | B23: 8701530201 | C23: 8701530201 Scrap-Raw Material - Managerial | D23: * CS_SCRAP_VARIABLE | E23: =VLOOKUP(B23,'2024 by account '!$A$2:$M$102,2,0)/1000 -> 0 | F23: =E23/$F$2 -> 0 | G23: =F23/$F$1*1000 -> 0 | I23: =VLOOKUP(B23,'2024 by account '!$A$2:$M$102,3,0)/1000 -> 0 | J23: =I23/$J$2 -> 0 | K23: =J23/$J$1*1000 -> 0 | M23: =VLOOKUP(B23,'2024 by account '!$A$2:$M$102,4,0)/1000 -> 0 | N23: =M23/$N$2 -> 0 | O23: =N23/$N$1*1000 -> 0 | Q23: =VLOOKUP(B23,'2024 by account '!$A$2:$M$102,5,0)/1000 -> 0 | R23: =Q23/$R$2 -> 0 | S23: =R23/$R$1*1000 -> 0 | U23: =VLOOKUP(B23,'2024 by account '!$A$2:$M$102,6,0)/1000 -> 0 | V23: =U23/$V$2 -> 0 | W23: =V23/$V$1*1000 -> 0 | Y23: =VLOOKUP(B23,'2024 by account '!$A$2:$M$102,7,0)/1000 -> 0 | Z23: =Y23/$Z$2 -> 0 | AA23: =Z23/$Z$1*1000 -> 0 | AC23: =VLOOKUP(B23,'2024 by account '!$A$2:$M$102,8,0)/1000 -> 0 | AD23: =AC23/$AD$2 -> 0 | AE23: =AD23/$AD$1*1000 -> 0 | AG23: =VLOOKUP(B23,'2024 by account '!$A$2:$M$102,9,0)/1000 -> 0 | AH23: =AG23/$AH$2 -> 0 | AI23: =AH23/$AH$1*1000 -> 0 | AK23: =VLOOKUP(B23,'2024 by account '!$A$2:$M$102,10,0)/1000 -> 0 | AL23: =AK23/$AL$2 -> 0 | AM23: =AL23/$AL$1*1000 -> 0 | AO23: =VLOOKUP(B23,'2024 by account '!$A$2:$M$102,11,0)/1000 -> 0 | AP23: =AO23/$AP$2 -> 0 | AQ23: =AP23/$AP$1*1000 -> 0 | AS23: =VLOOKUP(B23,'2024 by account '!$A$2:$M$102,12,0)/1000 -> 0 | AT23: =AS23/$AT$2 -> 0 | AU23: =AT23/$AT$1*1000 -> 0 | AW23: =VLOOKUP(B23,'2024 by account '!$A$2:$M$102,13,0)/1000 -> 0 | AX23: =AW23/$AX$2 -> 0 | AY23: =AX23/$AX$1*1000 -> 0 | BA23: =SUM(AW23,AS23,AO23,AK23,AG23,AC23,Y23,U23,Q23,M23,I23,E23) -> 0 | BB23: =SUM(AX23,AT23,AP23,AL23,AH23,AD23,Z23,V23,R23,N23,J23,F23) -> 0 | BC23: =BB23/$BB$1*1000 -> 0
A24: 6666050309 | B24: 6666050309 | C24: 6666050309 SFG scrap | D24: * CS_SCRAP_VARIABLE | E24: =VLOOKUP(B24,'2024 by account '!$A$2:$M$102,2,0)/1000 -> 248.528 | F24: =E24/$F$2 -> 7.5732634 | G24: =F24/$F$1*1000 -> 0.47200146 | I24: =VLOOKUP(B24,'2024 by account '!$A$2:$M$102,3,0)/1000 -> 213.3173 | J24: =I24/$J$2 -> 6.4127806 | K24: =J24/$J$1*1000 -> 0.32466488 | M24: =VLOOKUP(B24,'2024 by account '!$A$2:$M$102,4,0)/1000 -> 200.72754 | N24: =M24/$N$2 -> 5.7642396 | O24: =N24/$N$1*1000 -> 0.28767977 | Q24: =VLOOKUP(B24,'2024 by account '!$A$2:$M$102,5,0)/1000 -> 439.46484 | R24: =Q24/$R$2 -> 12.667394 | S24: =R24/$R$1*1000 -> 0.45171323 | U24: =VLOOKUP(B24,'2024 by account '!$A$2:$M$102,6,0)/1000 -> 622.70351 | V24: =U24/$V$2 -> 17.862725 | W24: =V24/$V$1*1000 -> 0.43787627 | Y24: =VLOOKUP(B24,'2024 by account '!$A$2:$M$102,7,0)/1000 -> 678.06636 | Z24: =Y24/$Z$2 -> 19.336475 | AA24: =Z24/$Z$1*1000 -> 0.62424053 | AC24: =VLOOKUP(B24,'2024 by account '!$A$2:$M$102,8,0)/1000 -> 463.74725 | AD24: =AC24/$AD$2 -> 12.991247 | AE24: =AD24/$AD$1*1000 -> 0.37680909 | AG24: =VLOOKUP(B24,'2024 by account '!$A$2:$M$102,9,0)/1000 -> 497.21587 | AH24: =AG24/$AH$2 -> 13.398506 | AI24: =AH24/$AH$1*1000 -> 0.5238293 | AK24: =VLOOKUP(B24,'2024 by account '!$A$2:$M$102,10,0)/1000 -> 528.54885 | AL24: =AK24/$AL$2 -> 13.973967 | AM24: =AL24/$AL$1*1000 -> 0.34844321 | AO24: =VLOOKUP(B24,'2024 by account '!$A$2:$M$102,11,0)/1000 -> 998.42047 | AP24: =AO24/$AP$2 -> 26.733398 | AQ24: =AP24/$AP$1*1000 -> 0.64907369 | AS24: =VLOOKUP(B24,'2024 by account '!$A$2:$M$102,12,0)/1000 -> 498.71391 | AT24: =AS24/$AT$2 -> 13.617245 | AU24: =AT24/$AT$1*1000 -> 0.31587208 | AW24: =VLOOKUP(B24,'2024 by account '!$A$2:$M$102,13,0)/1000 -> 356.59041 | AX24: =AW24/$AX$2 -> 9.7272693 | AY24: =AX24/$AX$1*1000 -> 0.37193704 | BA24: =SUM(AW24,AS24,AO24,AK24,AG24,AC24,Y24,U24,Q24,M24,I24,E24) -> 5746.0443 | BB24: =SUM(AX24,AT24,AP24,AL24,AH24,AD24,Z24,V24,R24,N24,J24,F24) -> 160.05851 | BC24: =BB24/$BB$1*1000 -> 0.43701266
A25: 6666050308 | B25: 6666050308 | C25: 6666050308 Raw material scrap | D25: * CS_SCRAP_VARIABLE | E25: =VLOOKUP(B25,'2024 by account '!$A$2:$M$102,2,0)/1000 -> -45.79438 | F25: =E25/$F$2 -> -1.3954681 | G25: =F25/$F$1*1000 -> -0.086972149 | I25: =VLOOKUP(B25,'2024 by account '!$A$2:$M$102,3,0)/1000 -> 25.18104 | J25: =I25/$J$2 -> 0.75699667 | K25: =J25/$J$1*1000 -> 0.038325064 | M25: =VLOOKUP(B25,'2024 by account '!$A$2:$M$102,4,0)/1000 -> 87.06643 | N25: =M25/$N$2 -> 2.5002636 | O25: =N25/$N$1*1000 -> 0.12478233 | Q25: =VLOOKUP(B25,'2024 by account '!$A$2:$M$102,5,0)/1000 -> -18.99198 | R25: =Q25/$R$2 -> -0.54743605 | S25: =R25/$R$1*1000 -> -0.019521308 | U25: =VLOOKUP(B25,'2024 by account '!$A$2:$M$102,6,0)/1000 -> -35.11939 | V25: =U25/$V$2 -> -1.0074265 | W25: =V25/$V$1*1000 -> -0.024695457 | Y25: =VLOOKUP(B25,'2024 by account '!$A$2:$M$102,7,0)/1000 -> 282.19544 | Z25: =Y25/$Z$2 -> 8.0473908 | AA25: =Z25/$Z$1*1000 -> 0.25979438 | AC25: =VLOOKUP(B25,'2024 by account '!$A$2:$M$102,8,0)/1000 -> 61.0478 | AD25: =AC25/$AD$2 -> 1.7101709 | AE25: =AD25/$AD$1*1000 -> 0.04960324 | AG25: =VLOOKUP(B25,'2024 by account '!$A$2:$M$102,9,0)/1000 -> 69.44699 | AH25: =AG25/$AH$2 -> 1.8713922 | AI25: =AH25/$AH$1*1000 -> 0.073164133 | AK25: =VLOOKUP(B25,'2024 by account '!$A$2:$M$102,10,0)/1000 -> 141.58387 | AL25: =AK25/$AL$2 -> 3.7432458 | AM25: =AL25/$AL$1*1000 -> 0.093338465 | AO25: =VLOOKUP(B25,'2024 by account '!$A$2:$M$102,11,0)/1000 -> -284.19875 | AP25: =AO25/$AP$2 -> -7.6096179 | AQ25: =AP25/$AP$1*1000 -> -0.18475776 | AS25: =VLOOKUP(B25,'2024 by account '!$A$2:$M$102,12,0)/1000 -> 327.33227 | AT25: =AS25/$AT$2 -> 8.9377171 | AU25: =AT25/$AT$1*1000 -> 0.20732352 | AW25: =VLOOKUP(B25,'2024 by account '!$A$2:$M$102,13,0)/1000 -> 605.26309 | AX25: =AW25/$AX$2 -> 16.510699 | AY25: =AX25/$AX$1*1000 -> 0.63131187 | BA25: =SUM(AW25,AS25,AO25,AK25,AG25,AC25,Y25,U25,Q25,M25,I25,E25) -> 1215.0124 | BB25: =SUM(AX25,AT25,AP25,AL25,AH25,AD25,Z25,V25,R25,N25,J25,F25) -> 33.517928 | BC25: =BB25/$BB$1*1000 -> 0.091515028
A26: 6666050306 | B26: 6666050306 | C26: 6666050306 Finished goods scrap | D26: * CS_SCRAP_VARIABLE | E26: =VLOOKUP(B26,'2024 by account '!$A$2:$M$102,2,0)/1000 -> 0 | F26: =E26/$F$2 -> 0 | G26: =F26/$F$1*1000 -> 0 | I26: =VLOOKUP(B26,'2024 by account '!$A$2:$M$102,3,0)/1000 -> 56.56561 | J26: =I26/$J$2 -> 1.7004849 | K26: =J26/$J$1*1000 -> 0.086091783 | M26: =VLOOKUP(B26,'2024 by account '!$A$2:$M$102,4,0)/1000 -> 19.64788 | N26: =M26/$N$2 -> 0.56422297 | O26: =N26/$N$1*1000 -> 0.028159054 | Q26: =VLOOKUP(B26,'2024 by account '!$A$2:$M$102,5,0)/1000 -> 0 | R26: =Q26/$R$2 -> 0 | S26: =R26/$R$1*1000 -> 0 | U26: =VLOOKUP(B26,'2024 by account '!$A$2:$M$102,6,0)/1000 -> 8.99129 | V26: =U26/$V$2 -> 0.257922 | W26: =V26/$V$1*1000 -> 0.0063225475 | Y26: =VLOOKUP(B26,'2024 by account '!$A$2:$M$102,7,0)/1000 -> 9.29528 | Z26: =Y26/$Z$2 -> 0.26507427 | AA26: =Z26/$Z$1*1000 -> 0.0085574081 | AC26: =VLOOKUP(B26,'2024 by account '!$A$2:$M$102,8,0)/1000 -> 194.08081 | AD26: =AC26/$AD$2 -> 5.4369094 | AE26: =AD26/$AD$1*1000 -> 0.15769671 | AG26: =VLOOKUP(B26,'2024 by account '!$A$2:$M$102,9,0)/1000 -> 0 | AH26: =AG26/$AH$2 -> 0 | AI26: =AH26/$AH$1*1000 -> 0 | AK26: =VLOOKUP(B26,'2024 by account '!$A$2:$M$102,10,0)/1000 -> 9.42167 | AL26: =AK26/$AL$2 -> 0.24909354 | AM26: =AL26/$AL$1*1000 -> 0.0062111893 | AO26: =VLOOKUP(B26,'2024 by account '!$A$2:$M$102,11,0)/1000 -> 26.25826 | AP26: =AO26/$AP$2 -> 0.70308306 | AQ26: =AP26/$AP$1*1000 -> 0.017070509 | AS26: =VLOOKUP(B26,'2024 by account '!$A$2:$M$102,12,0)/1000 -> 8.35038 | AT26: =AS26/$AT$2 -> 0.22800482 | AU26: =AT26/$AT$1*1000 -> 0.0052889078 | AW26: =VLOOKUP(B26,'2024 by account '!$A$2:$M$102,13,0)/1000 -> 130.141 | AX26: =AW26/$AX$2 -> 3.5500578 | AY26: =AX26/$AX$1*1000 -> 0.13574189 | BA26: =SUM(AW26,AS26,AO26,AK26,AG26,AC26,Y26,U26,Q26,M26,I26,E26) -> 462.75218 | BB26: =SUM(AX26,AT26,AP26,AL26,AH26,AD26,Z26,V26,R26,N26,J26,F26) -> 12.954853 | BC26: =BB26/$BB$1*1000 -> 0.035371032
B27: VAR | C27: * CS_SCRAP_VARIABLE | E27: =SUM(E23:E26) -> 202.73362 | F27: =E27/$F$2 -> 6.1777953 | G27: =F27/$F$1*1000 -> 0.38502931 | I27: =SUM(I23:I26) -> 295.06395 | J27: =SUM(J23:J26) -> 8.8702622 | K27: =J27/$J$1*1000 -> 0.44908172 | M27: =SUM(M23:M26) -> 307.44185 | N27: =SUM(N23:N26) -> 8.8287262 | O27: =N27/$N$1*1000 -> 0.44062116 | Q27: =SUM(Q23:Q26) -> 420.47286 | R27: =Q27/$R$2 -> 12.119958 | S27: =R27/$R$1*1000 -> 0.43219192 | U27: =SUM(U23:U26) -> 596.57541 | V27: =U27/$V$2 -> 17.11322 | W27: =V27/$V$1*1000 -> 0.41950336 | Y27: =SUM(Y23:Y26) -> 969.55708 | Z27: =Y27/$Z$2 -> 27.64894 | AA27: =Z27/$Z$1*1000 -> 0.89259233 | AC27: =SUM(AC23:AC26) -> 718.87586 | AD27: =AC27/$AD$2 -> 20.138327 | AE27: =AD27/$AD$1*1000 -> 0.58410904 | AG27: =SUM(AG23:AG26) -> 566.66286 | AH27: =AG27/$AH$2 -> 15.269898 | AI27: =AH27/$AH$1*1000 -> 0.59699343 | AK27: =SUM(AK23:AK26) -> 679.55439 | AL27: =AK27/$AL$2 -> 17.966306 | AM27: =AL27/$AL$1*1000 -> 0.44799287 | AO27: =SUM(AO23:AO26) -> 740.47998 | AP27: =AO27/$AP$2 -> 19.826863 | AQ27: =AP27/$AP$1*1000 -> 0.48138644 | AS27: =SUM(AS23:AS26) -> 834.39656 | AT27: =AS27/$AT$2 -> 22.782967 | AU27: =AT27/$AT$1*1000 -> 0.52848451 | AW27: =SUM(AW23:AW26) -> 1091.9945 | AX27: =AW27/$AX$2 -> 29.788027 | AY27: =AX27/$AX$1*1000 -> 1.1389908 | BA27: =SUM(AW27,AS27,AO27,AK27,AG27,AC27,Y27,U27,Q27,M27,I27,E27) -> 7423.8089 | BB27: =SUM(AX27,AT27,AP27,AL27,AH27,AD27,Z27,V27,R27,N27,J27,F27) -> 206.53129 | BC27: =BB27/$BB$1*1000 -> 0.56389872
A28: 5102010151 | B28: 5102010151 | C28: 5102010151 Other Rev.-Interco-Epidemic problem comp | D28: * CS_Fix Cost | E28: =VLOOKUP(B28,'2024 by account '!$A$2:$M$102,2,0)/1000 -> 0 | F28: =E28/$F$2 -> 0 | G28: =F28/$F$1*1000 -> 0 | I28: =VLOOKUP(B28,'2024 by account '!$A$2:$M$102,3,0)/1000 -> 0 | J28: =I28/$J$2 -> 0 | K28: =J28/$J$1*1000 -> 0 | M28: =VLOOKUP(B28,'2024 by account '!$A$2:$M$102,4,0)/1000 -> 0 | N28: =M28/$N$2 -> 0 | O28: =N28/$N$1*1000 -> 0 | Q28: =VLOOKUP(B28,'2024 by account '!$A$2:$M$102,5,0)/1000 -> 0 | R28: =Q28/$R$2 -> 0 | S28: =R28/$R$1*1000 -> 0 | U28: =VLOOKUP(B28,'2024 by account '!$A$2:$M$102,6,0)/1000 -> 0 | V28: =U28/$V$2 -> 0 | W28: =V28/$V$1*1000 -> 0 | Y28: =VLOOKUP(B28,'2024 by account '!$A$2:$M$102,7,0)/1000 -> 0 | Z28: =Y28/$Z$2 -> 0 | AA28: =Z28/$Z$1*1000 -> 0 | AC28: =VLOOKUP(B28,'2024 by account '!$A$2:$M$102,8,0)/1000 -> 0 | AD28: =AC28/$AD$2 -> 0 | AE28: =AD28/$AD$1*1000 -> 0 | AG28: =VLOOKUP(B28,'2024 by account '!$A$2:$M$102,9,0)/1000 -> 1e-05 | AH28: =AG28/$AH$2 -> 2.694706e-07 | AI28: =AH28/$AH$1*1000 -> 1.0535249e-08 | AK28: =VLOOKUP(B28,'2024 by account '!$A$2:$M$102,10,0)/1000 -> 0 | AL28: =AK28/$AL$2 -> 0 | AM28: =AL28/$AL$1*1000 -> 0 | AO28: =VLOOKUP(B28,'2024 by account '!$A$2:$M$102,11,0)/1000 -> 0 | AP28: =AO28/$AP$2 -> 0 | AQ28: =AP28/$AP$1*1000 -> 0 | AS28: =VLOOKUP(B28,'2024 by account '!$A$2:$M$102,12,0)/1000 -> 0 | AT28: =AS28/$AT$2 -> 0 | AU28: =AT28/$AT$1*1000 -> 0 | AW28: =VLOOKUP(B28,'2024 by account '!$A$2:$M$102,13,0)/1000 -> 0 | AX28: =AW28/$AX$2 -> 0 | AY28: =AX28/$AX$1*1000 -> 0 | BA28: =SUM(AW28,AS28,AO28,AK28,AG28,AC28,Y28,U28,Q28,M28,I28,E28) -> 1e-05 | BB28: =SUM(AX28,AT28,AP28,AL28,AH28,AD28,Z28,V28,R28,N28,J28,F28) -> 2.694706e-07 | BC28: =BB28/$BB$1*1000 -> 7.3574385e-10
B29: 5102040893 | C29: 5102040893 Other revenue-Charge out-Test Expense | D29: * CS_Fix Cost | E29: =VLOOKUP(B29,'2024 by account '!$A$2:$M$102,2,0)/1000 -> -130.9926 | F29: =E29/$F$2 -> -3.9916688 | G29: =F29/$F$1*1000 -> -0.24877961 | I29: =VLOOKUP(B29,'2024 by account '!$A$2:$M$102,3,0)/1000 -> 0 | J29: =I29/$J$2 -> 0 | K29: =J29/$J$1*1000 -> 0 | M29: =VLOOKUP(B29,'2024 by account '!$A$2:$M$102,4,0)/1000 -> 0 | N29: =M29/$N$2 -> 0 | O29: =N29/$N$1*1000 -> 0 | Q29: =VLOOKUP(B29,'2024 by account '!$A$2:$M$102,5,0)/1000 -> 0 | R29: =Q29/$R$2 -> 0 | S29: =R29/$R$1*1000 -> 0 | U29: =VLOOKUP(B29,'2024 by account '!$A$2:$M$102,6,0)/1000 -> 0 | V29: =U29/$V$2 -> 0 | W29: =V29/$V$1*1000 -> 0 | Y29: =VLOOKUP(B29,'2024 by account '!$A$2:$M$102,7,0)/1000 -> 0 | Z29: =Y29/$Z$2 -> 0 | AA29: =Z29/$Z$1*1000 -> 0 | AC29: =VLOOKUP(B29,'2024 by account '!$A$2:$M$102,8,0)/1000 -> 0 | AD29: =AC29/$AD$2 -> 0 | AE29: =AD29/$AD$1*1000 -> 0 | AG29: =VLOOKUP(B29,'2024 by account '!$A$2:$M$102,9,0)/1000 -> 0 | AH29: =AG29/$AH$2 -> 0 | AI29: =AH29/$AH$1*1000 -> 0 | AK29: =VLOOKUP(B29,'2024 by account '!$A$2:$M$102,10,0)/1000 -> 0 | AL29: =AK29/$AL$2 -> 0 | AM29: =AL29/$AL$1*1000 -> 0 | AO29: =VLOOKUP(B29,'2024 by account '!$A$2:$M$102,11,0)/1000 -> 0 | AP29: =AO29/$AP$2 -> 0 | AQ29: =AP29/$AP$1*1000 -> 0 | AS29: =VLOOKUP(B29,'2024 by account '!$A$2:$M$102,12,0)/1000 -> 0 | AT29: =AS29/$AT$2 -> 0 | AU29: =AT29/$AT$1*1000 -> 0 | AW29: =VLOOKUP(B29,'2024 by account '!$A$2:$M$102,13,0)/1000 -> 0.1 | AX29: =AW29/$AX$2 -> 0.002727855 | AY29: =AX29/$AX$1*1000 -> 0.00010430371 | BA29: =SUM(AW29,AS29,AO29,AK29,AG29,AC29,Y29,U29,Q29,M29,I29,E29) -> -130.8926 | BB29: =SUM(AX29,AT29,AP29,AL29,AH29,AD29,Z29,V29,R29,N29,J29,F29) -> -3.988941 | BC29: =BB29/$BB$1*1000 -> -0.010891128
A30: 5001010200 | B30: 5001010200 | C30: 5001010200 Cost of Manufacture - Raw Material | D30: * CS_Fix Cost | E30: =VLOOKUP(B30,'2024 by account '!$A$2:$M$102,2,0)/1000 -> 0 | F30: =E30/$F$2 -> 0 | G30: =F30/$F$1*1000 -> 0 | I30: =VLOOKUP(B30,'2024 by account '!$A$2:$M$102,3,0)/1000 -> -36.32398 | J30: =I30/$J$2 -> -1.0919776 | K30: =J30/$J$1*1000 -> -0.055284407 | M30: =VLOOKUP(B30,'2024 by account '!$A$2:$M$102,4,0)/1000 -> 4.035 | N30: =M30/$N$2 -> 0.11587203 | O30: =N30/$N$1*1000 -> 0.005782903 | Q30: =VLOOKUP(B30,'2024 by account '!$A$2:$M$102,5,0)/1000 -> 0 | R30: =Q30/$R$2 -> 0 | S30: =R30/$R$1*1000 -> 0 | U30: =VLOOKUP(B30,'2024 by account '!$A$2:$M$102,6,0)/1000 -> 3.07097 | V30: =U30/$V$2 -> 0.088093114 | W30: =V30/$V$1*1000 -> 0.0021594625 | Y30: =VLOOKUP(B30,'2024 by account '!$A$2:$M$102,7,0)/1000 -> 0 | Z30: =Y30/$Z$2 -> 0 | AA30: =Z30/$Z$1*1000 -> 0 | AC30: =VLOOKUP(B30,'2024 by account '!$A$2:$M$102,8,0)/1000 -> 0 | AD30: =AC30/$AD$2 -> 0 | AE30: =AD30/$AD$1*1000 -> 0 | AG30: =VLOOKUP(B30,'2024 by account '!$A$2:$M$102,9,0)/1000 -> 0 | AH30: =AG30/$AH$2 -> 0 | AI30: =AH30/$AH$1*1000 -> 0 | AK30: =VLOOKUP(B30,'2024 by account '!$A$2:$M$102,10,0)/1000 -> 0.66793 | AL30: =AK30/$AL$2 -> 0.017658976 | AM30: =AL30/$AL$1*1000 -> 0.00044032955 | AO30: =VLOOKUP(B30,'2024 by account '!$A$2:$M$102,11,0)/1000 -> 0.43734 | AP30: =AO30/$AP$2 -> 0.011710081 | AQ30: =AP30/$AP$1*1000 -> 0.00028431497 | AS30: =VLOOKUP(B30,'2024 by account '!$A$2:$M$102,12,0)/1000 -> 3.24422 | AT30: =AS30/$AT$2 -> 0.08858253 | AU30: =AT30/$AT$1*1000 -> 0.0020548024 | AW30: =VLOOKUP(B30,'2024 by account '!$A$2:$M$102,13,0)/1000 -> 0 | AX30: =AW30/$AX$2 -> 0 | AY30: =AX30/$AX$1*1000 -> 0 | BA30: =SUM(AW30,AS30,AO30,AK30,AG30,AC30,Y30,U30,Q30,M30,I30,E30) -> -24.86852 | BB30: =SUM(AX30,AT30,AP30,AL30,AH30,AD30,Z30,V30,R30,N30,J30,F30) -> -0.77006088 | BC30: =BB30/$BB$1*1000 -> -0.0021025209
A31: 5001010201 | B31: 5001010201 | C31: 5001010201 Cost of Manufacture - Raw Material-Freig | D31: * CS_Fix Cost | E31: =VLOOKUP(B31,'2024 by account '!$A$2:$M$102,2,0)/1000 -> 0 | F31: =E31/$F$2 -> 0 | G31: =F31/$F$1*1000 -> 0 | I31: =VLOOKUP(B31,'2024 by account '!$A$2:$M$102,3,0)/1000 -> 0 | J31: =I31/$J$2 -> 0 | K31: =J31/$J$1*1000 -> 0 | M31: =VLOOKUP(B31,'2024 by account '!$A$2:$M$102,4,0)/1000 -> 0.59102 | N31: =M31/$N$2 -> 0.016972165 | O31: =N31/$N$1*1000 -> 0.00084704122 | Q31: =VLOOKUP(B31,'2024 by account '!$A$2:$M$102,5,0)/1000 -> 0.62927 | R31: =Q31/$R$2 -> 0.01813845 | S31: =R31/$R$1*1000 -> 0.00064680848 | U31: =VLOOKUP(B31,'2024 by account '!$A$2:$M$102,6,0)/1000 -> 0 | V31: =U31/$V$2 -> 0 | W31: =V31/$V$1*1000 -> 0 | Y31: =VLOOKUP(B31,'2024 by account '!$A$2:$M$102,7,0)/1000 -> 0.56263 | Z31: =Y31/$Z$2 -> 0.016044566 | AA31: =Z31/$Z$1*1000 -> 0.00051796767 | AC31: =VLOOKUP(B31,'2024 by account '!$A$2:$M$102,8,0)/1000 -> 0 | AD31: =AC31/$AD$2 -> 0 | AE31: =AD31/$AD$1*1000 -> 0 | AG31: =VLOOKUP(B31,'2024 by account '!$A$2:$M$102,9,0)/1000 -> 0 | AH31: =AG31/$AH$2 -> 0 | AI31: =AH31/$AH$1*1000 -> 0 | AK31: =VLOOKUP(B31,'2024 by account '!$A$2:$M$102,10,0)/1000 -> 0.34287 | AL31: =AK31/$AL$2 -> 0.0090649217 | AM31: =AL31/$AL$1*1000 -> 0.00022603535 | AO31: =VLOOKUP(B31,'2024 by account '!$A$2:$M$102,11,0)/1000 -> 0 | AP31: =AO31/$AP$2 -> 0 | AQ31: =AP31/$AP$1*1000 -> 0 | AS31: =VLOOKUP(B31,'2024 by account '!$A$2:$M$102,12,0)/1000 -> 0.06808 | AT31: =AS31/$AT$2 -> 0.0018589056 | AU31: =AT31/$AT$1*1000 -> 4.3120055e-05 | AW31: =VLOOKUP(B31,'2024 by account '!$A$2:$M$102,13,0)/1000 -> 0 | AX31: =AW31/$AX$2 -> 0 | AY31: =AX31/$AX$1*1000 -> 0 | BA31: =SUM(AW31,AS31,AO31,AK31,AG31,AC31,Y31,U31,Q31,M31,I31,E31) -> 2.19387 | BB31: =SUM(AX31,AT31,AP31,AL31,AH31,AD31,Z31,V31,R31,N31,J31,F31) -> 0.062079009 | BC31: =BB31/$BB$1*1000 -> 0.00016949622
A32: 5207000011 | B32: 5207000011 | C32: 5207000011 Gain of tangible asset disposal | D32: * CS_Fix Cost | E32: =VLOOKUP(B32,'2024 by account '!$A$2:$M$102,2,0)/1000 -> 0 | F32: =E32/$F$2 -> 0 | G32: =F32/$F$1*1000 -> 0 | I32: =VLOOKUP(B32,'2024 by account '!$A$2:$M$102,3,0)/1000 -> 0 | J32: =I32/$J$2 -> 0 | K32: =J32/$J$1*1000 -> 0 | M32: =VLOOKUP(B32,'2024 by account '!$A$2:$M$102,4,0)/1000 -> -109.88595 | N32: =M32/$N$2 -> -3.1555657 | O32: =N32/$N$1*1000 -> -0.15748694 | Q32: =VLOOKUP(B32,'2024 by account '!$A$2:$M$102,5,0)/1000 -> 0 | R32: =Q32/$R$2 -> 0 | S32: =R32/$R$1*1000 -> 0 | U32: =VLOOKUP(B32,'2024 by account '!$A$2:$M$102,6,0)/1000 -> 0 | V32: =U32/$V$2 -> 0 | W32: =V32/$V$1*1000 -> 0 | Y32: =VLOOKUP(B32,'2024 by account '!$A$2:$M$102,7,0)/1000 -> 0 | Z32: =Y32/$Z$2 -> 0 | AA32: =Z32/$Z$1*1000 -> 0 | AC32: =VLOOKUP(B32,'2024 by account '!$A$2:$M$102,8,0)/1000 -> 0 | AD32: =AC32/$AD$2 -> 0 | AE32: =AD32/$AD$1*1000 -> 0 | AG32: =VLOOKUP(B32,'2024 by account '!$A$2:$M$102,9,0)/1000 -> 0 | AH32: =AG32/$AH$2 -> 0 | AI32: =AH32/$AH$1*1000 -> 0 | AK32: =VLOOKUP(B32,'2024 by account '!$A$2:$M$102,10,0)/1000 -> 0 | AL32: =AK32/$AL$2 -> 0 | AM32: =AL32/$AL$1*1000 -> 0 | AO32: =VLOOKUP(B32,'2024 by account '!$A$2:$M$102,11,0)/1000 -> 0 | AP32: =AO32/$AP$2 -> 0 | AQ32: =AP32/$AP$1*1000 -> 0 | AS32: =VLOOKUP(B32,'2024 by account '!$A$2:$M$102,12,0)/1000 -> -39.35582 | AT32: =AS32/$AT$2 -> -1.0745998 | AU32: =AT32/$AT$1*1000 -> -0.024926926 | AW32: =VLOOKUP(B32,'2024 by account '!$A$2:$M$102,13,0)/1000 -> 0 | AX32: =AW32/$AX$2 -> 0 | AY32: =AX32/$AX$1*1000 -> 0 | BA32: =SUM(AW32,AS32,AO32,AK32,AG32,AC32,Y32,U32,Q32,M32,I32,E32) -> -149.24177 | BB32: =SUM(AX32,AT32,AP32,AL32,AH32,AD32,Z32,V32,R32,N32,J32,F32) -> -4.2301655 | BC32: =BB32/$BB$1*1000 -> -0.011549751
A33: 5207000012 | B33: 5207000012 | C33: 5207000012 Loss of tangible asset sold | D33: * CS_Fix Cost | E33: =VLOOKUP(B33,'2024 by account '!$A$2:$M$102,2,0)/1000 -> 0 | F33: =E33/$F$2 -> 0 | G33: =F33/$F$1*1000 -> 0 | I33: =VLOOKUP(B33,'2024 by account '!$A$2:$M$102,3,0)/1000 -> 0 | J33: =I33/$J$2 -> 0 | K33: =J33/$J$1*1000 -> 0 | M33: =VLOOKUP(B33,'2024 by account '!$A$2:$M$102,4,0)/1000 -> 0 | N33: =M33/$N$2 -> 0 | O33: =N33/$N$1*1000 -> 0 | Q33: =VLOOKUP(B33,'2024 by account '!$A$2:$M$102,5,0)/1000 -> -28.81012 | R33: =Q33/$R$2 -> -0.83043992 | S33: =R33/$R$1*1000 -> -0.029613091 | U33: =VLOOKUP(B33,'2024 by account '!$A$2:$M$102,6,0)/1000 -> 0 | V33: =U33/$V$2 -> 0 | W33: =V33/$V$1*1000 -> 0 | Y33: =VLOOKUP(B33,'2024 by account '!$A$2:$M$102,7,0)/1000 -> 0 | Z33: =Y33/$Z$2 -> 0 | AA33: =Z33/$Z$1*1000 -> 0 | AC33: =VLOOKUP(B33,'2024 by account '!$A$2:$M$102,8,0)/1000 -> 0 | AD33: =AC33/$AD$2 -> 0 | AE33: =AD33/$AD$1*1000 -> 0 | AG33: =VLOOKUP(B33,'2024 by account '!$A$2:$M$102,9,0)/1000 -> 0 | AH33: =AG33/$AH$2 -> 0 | AI33: =AH33/$AH$1*1000 -> 0 | AK33: =VLOOKUP(B33,'2024 by account '!$A$2:$M$102,10,0)/1000 -> 0 | AL33: =AK33/$AL$2 -> 0 | AM33: =AL33/$AL$1*1000 -> 0 | AO33: =VLOOKUP(B33,'2024 by account '!$A$2:$M$102,11,0)/1000 -> 0 | AP33: =AO33/$AP$2 -> 0 | AQ33: =AP33/$AP$1*1000 -> 0 | AS33: =VLOOKUP(B33,'2024 by account '!$A$2:$M$102,12,0)/1000 -> 33.95411 | AT33: =AS33/$AT$2 -> 0.92710758 | AU33: =AT33/$AT$1*1000 -> 0.021505627 | AW33: =VLOOKUP(B33,'2024 by account '!$A$2:$M$102,13,0)/1000 -> 0 | AX33: =AW33/$AX$2 -> 0 | AY33: =AX33/$AX$1*1000 -> 0 | BA33: =SUM(AW33,AS33,AO33,AK33,AG33,AC33,Y33,U33,Q33,M33,I33,E33) -> 5.14399 | BB33: =SUM(AX33,AT33,AP33,AL33,AH33,AD33,Z33,V33,R33,N33,J33,F33) -> 0.096667662 | BC33: =BB33/$BB$1*1000 -> 0.00026393469
A34: 5207000022 | B34: 5207000022 | C34: 5207000022 Loss of intangible asset disposal | D34: * CS_Fix Cost | F34: =E34/$F$2 -> 0 | G34: =F34/$F$1*1000 -> 0 | K34: =J34/$J$1*1000 -> 0 | O34: =N34/$N$1*1000 -> 0 | R34: =Q34/$R$2 -> 0 | S34: =R34/$R$1*1000 -> 0 | V34: =U34/$V$2 -> 0 | W34: =V34/$V$1*1000 -> 0 | Z34: =Y34/$Z$2 -> 0 | AA34: =Z34/$Z$1*1000 -> 0 | AD34: =AC34/$AD$2 -> 0 | AE34: =AD34/$AD$1*1000 -> 0 | AH34: =AG34/$AH$2 -> 0 | AI34: =AH34/$AH$1*1000 -> 0 | AL34: =AK34/$AL$2 -> 0 | AM34: =AL34/$AL$1*1000 -> 0 | AP34: =AO34/$AP$2 -> 0 | AQ34: =AP34/$AP$1*1000 -> 0 | AT34: =AS34/$AT$2 -> 0 | AU34: =AT34/$AT$1*1000 -> 0 | AX34: =AW34/$AX$2 -> 0 | AY34: =AX34/$AX$1*1000 -> 0 | BA34: =SUM(AW34,AS34,AO34,AK34,AG34,AC34,Y34,U34,Q34,M34,I34,E34) -> 0 | BB34: =SUM(AX34,AT34,AP34,AL34,AH34,AD34,Z34,V34,R34,N34,J34,F34) -> 0 | BC34: =BB34/$BB$1*1000 -> 0
A35: 5301060000 | B35: 5301060000 | C35: 5301060000 Other Income-Subsidy income | D35: * CS_Fix Cost | F35: =E35/$F$2 -> 0 | G35: =F35/$F$1*1000 -> 0 | K35: =J35/$J$1*1000 -> 0 | O35: =N35/$N$1*1000 -> 0 | R35: =Q35/$R$2 -> 0 | S35: =R35/$R$1*1000 -> 0 | V35: =U35/$V$2 -> 0 | W35: =V35/$V$1*1000 -> 0 | Z35: =Y35/$Z$2 -> 0 | AA35: =Z35/$Z$1*1000 -> 0 | AD35: =AC35/$AD$2 -> 0 | AE35: =AD35/$AD$1*1000 -> 0 | AH35: =AG35/$AH$2 -> 0 | AI35: =AH35/$AH$1*1000 -> 0 | AL35: =AK35/$AL$2 -> 0 | AM35: =AL35/$AL$1*1000 -> 0 | AP35: =AO35/$AP$2 -> 0 | AQ35: =AP35/$AP$1*1000 -> 0 | AT35: =AS35/$AT$2 -> 0 | AU35: =AT35/$AT$1*1000 -> 0 | AX35: =AW35/$AX$2 -> 0 | AY35: =AX35/$AX$1*1000 -> 0 | BA35: =SUM(AW35,AS35,AO35,AK35,AG35,AC35,Y35,U35,Q35,M35,I35,E35) -> 0 | BB35: =SUM(AX35,AT35,AP35,AL35,AH35,AD35,Z35,V35,R35,N35,J35,F35) -> 0 | BC35: =BB35/$BB$1*1000 -> 0
