Workbook
Name \0: #REF!
Name \2: #REF!
Name \a: #REF!
Name \b: #REF!
Name \b1: #REF!
Name \m: #REF!
Name \p: '[4]FA-LISTING'!#REF!
Name \v: '[4]FA-LISTING'!#REF!
Name ___: #REF!
Name _______5월국내제품: #REF!
Name _______AEM14: #REF!
Name _______CAR05: #REF!
Name _______FED18: #REF!
Name _______GMC1: #REF!
Name _______GMC2: #REF!
Name ______ST2: #REF!
Name _____5월국내제품: #REF!
Name _____AEM14: #REF!
Name _____CAR05: #REF!
Name _____FED18: #REF!
Name _____GMC1: #REF!
Name _____GMC2: #REF!
Name ____5월국내제품: #REF!
Name ____AEM14: #REF!
Name ____CAR05: #REF!
Name ____FED18: #REF!
Name ____GMC1: #REF!
Name ____GMC2: #REF!
Name ____ST2: #REF!
Name ___5월국내제품: #REF!
Name ___AEM14: #REF!
Name ___CAR05: #REF!
Name ___FED18: #REF!
Name __5월국내제품: #REF!
Name __a66000: #REF!
Name __a69000: #REF!
Name __act2: #REF!
Name __act3: #REF!
Name __act4: #REF!
Name __AEM14: #REF!
Name __afo3: #REF!
Name __all22: [5]PLALL!$A$1:$BM$137
Name __CAR05: #REF!
Name __Col3: [6]Tables!$S$7
Name __Col6: [6]Tables!$S$12
Name __CSD3: #REF!
Name __DAT1: '[7]Raw materials'!#REF!
Name __DAT10: #REF!
Name __DAT11: #REF!
Name __DAT12: #REF!
Name __DAT13: #REF!
Name __DAT14: #REF!
Name __DAT15: #REF!
Name __DAT16: #REF!
Name __DAT17: #REF!
Name __DAT2: '[7]Raw materials'!#REF!
Name __DAT3: '[7]Raw materials'!#REF!
Name __DAT4: '[7]Raw materials'!#REF!
Name __DAT5: '[7]Raw materials'!#REF!
Name __DAT6: '[7]Raw materials'!#REF!

Sheet 洗碗机成本数据
A1: 分类 | B1: 指标 | C1: / | D1: 1月份 | E1: 2月份 | F1: 3月份 | G1: 4月份 | H1: 5月份 | I1: 6月份 | J1: 7月份 | K1: 8月份 | L1: 9月份 | M1: 10月份 | N1: 11月份 | O1: 12月份 | P1: 年度
A2: 洗碗机定单量 | B2: 洗碗机定单量 | C2: 同期 | D2: 48570 | E2: 46039 | F2: 46330 | G2: 49360 | H2: 53704 | I2: 29664 | J2: 41857 | K2: 31977 | L2: 28268 | M2: 26211 | N2: 34024 | O2: 42093 | P2: 478097
B3: 洗碗机定单量 | C3: 目标 | D3: 50463 | E3: 50450 | F3: 50440 | G3: 48050 | H3: 36788 | I3: 53265 | J3: 42049 | K3: 39150 | L3: 53732 | M3: 48548 | N3: 51408 | O3: 40676 | P3: 565019
B4: 洗碗机定单量 | C4: 26年 | D4: 47360 | E4: 42593 | F4: 23002 | G4: 40893 | H4: 33043 | I4: 53186 | J4: 41500 | K4: 39000.001 | L4: 54085 | M4: 49968 | N4: 51936 | O4: 42190 | P4: 518756
A5: 洗碗机定单量（累计） | B5: 洗碗机定单量（累计） | C5: 同期 | D5: =D2 -> 48570 | E5: =D5+E2 -> 94609 | F5: =E5+F2 -> 140939 | G5: =F5+G2 -> 190299 | H5: =G5+H2 -> 244003 | I5: =H5+I2 -> 273667 | J5: =I5+J2 -> 315524 | K5: =J5+K2 -> 347501 | L5: =K5+L2 -> 375769 | ... O5: =N5+O2 -> 478097 | P5: 19821.23
B6: 洗碗机定单量（累计） | C6: 目标 | D6: =D3 -> 50463 | E6: =D6+E3 -> 100913 | F6: =E6+F3 -> 151353 | G6: =F6+G3 -> 199403 | H6: =G6+H3 -> 236191 | I6: =H6+I3 -> 289456 | J6: =I6+J3 -> 331505 | K6: =J6+K3 -> 370655 | L6: =K6+L3 -> 424387 | ... O6: =N6+O3 -> 565019 | P6: =O6 -> 565019
B7: 洗碗机定单量（累计） | C7: 26年 | D7: =D4 -> 47360 | E7: =D7+E4 -> 89953 | F7: =E7+F4 -> 112955 | G7: =F7+G4 -> 153848 | H7: =G7+H4 -> 186891 | I7: =H7+I4 -> 240077 | J7: =I7+J4 -> 281577 | K7: =J7+K4 -> 320577 | L7: =K7+L4 -> 374662 | ... O7: =N7+O4 -> 518756 | P7: =O7 -> 518756
A8: 洗碗机费用金额 | B8: 洗碗机费用金额 | C8: 同期 | D8: 1702.4888 | E8: 1623.6996 | F8: 1825.8462 | G8: 1591.5968 | H8: 1866.987 | I8: 1737.9 | J8: 1637.4123 | K8: 1533.5455 | L8: 1597.8553 | M8: 1443.0898 | N8: 1758.5061 | O8: 1502.3028 | P8: =SUM(D8:O8) -> 19821.23
B9: 洗碗机费用金额 | C9: 目标 | D9: 1838.2556 | E9: 1852.3924 | F9: 1892.6678 | G9: 1849.6673 | H9: 1928.8688 | I9: 1870.4326 | J9: 1859.2351 | K9: 1842.1673 | L9: 1948.6868 | M9: 1894.9246 | N9: 1861.9628 | O9: 1947.1505 | P9: =SUM(D9:O9) -> 22586.412
B10: 洗碗机费用金额 | C10: 26年 | D10: 1778.218 | E10: 1749.5522 | F10: 1713 | G10: 900.77836 | H10: 1826 | I10: 1438.5835 | J10: 1663.9548 | K10: 1652.6359 | L10: 1816.2017 | M10: 1764.1942 | N10: 1739.899 | O10: 1797.8953 | P10: =SUM(D10:O10) -> 19840.913
A11: 洗碗机费用金额（累计） | B11: 洗碗机费用金额（累计） | C11: 同期 | D11: =D8 -> 1702.4888 | E11: =D11+E8 -> 3326.1883 | F11: =E11+F8 -> 5152.0345 | G11: =F11+G8 -> 6743.6313 | H11: =G11+H8 -> 8610.6183 | I11: =H11+I8 -> 10348.518 | J11: =I11+J8 -> 11985.931 | K11: =J11+K8 -> 13519.476 | L11: =K11+L8 -> 15117.331 | ... O11: =N11+O8 -> 19821.23 | P11: =O11 -> 19821.23
B12: 洗碗机费用金额（累计） | C12: 目标 | D12: =D9 -> 1838.2556 | E12: =D12+E9 -> 3690.648 | F12: =E12+F9 -> 5583.3158 | G12: =F12+G9 -> 7432.9831 | H12: =G12+H9 -> 9361.8519 | I12: =H12+I9 -> 11232.284 | J12: =I12+J9 -> 13091.52 | K12: =J12+K9 -> 14933.687 | L12: =K12+L9 -> 16882.374 | ... O12: =N12+O9 -> 22586.412 | P12: =O12 -> 22586.412
B13: 洗碗机费用金额（累计） | C13: 26年 | D13: =D10 -> 1778.218 | E13: =D13+E10 -> 3527.7702 | F13: =E13+F10 -> 5240.7702 | G13: =F13+G10 -> 6141.5486 | H13: =G13+H10 -> 7967.5486 | I13: =H13+I10 -> 9406.1321 | J13: =I13+J10 -> 11070.087 | K13: =J13+K10 -> 12722.723 | L13: =K13+L10 -> 14538.924 | ... O13: =N13+O10 -> 19840.913 | P13: =O13 -> 19840.913
A14: 洗碗机单台 | B14: 洗碗机单台 | C14: 同期 | D14: 35.046041 | E14: 35.45 | F14: 39.407954 | G14: 32.242707 | H14: 34.764394 | I14: 58.586165 | J14: 39.119199 | K14: 47.957767 | L14: 56.525234 | M14: 55.056648 | N14: 51.684284 | O14: 35.690087 | P14: 41.458596
B15: 洗碗机单台 | C15: 目标 | D15: 36.427791 | E15: 36.72 | F15: 37.525254 | G15: 38.494637 | H15: 52.432012 | I15: 35.115602 | J15: 44.215917 | K15: 47.054083 | L15: 36.266783 | M15: 39.031981 | N15: 36.219319 | O15: 47.869763 | P15: 39.974605
B16: 洗碗机单台 | C16: 26年 | D16: =D10/D4*1000 -> 37.546833 | E16: =E10/E4*1000 -> 41.076051 | F16: =F10/F4*1000 -> 74.471785 | G16: =G10/G4*1000 -> 22.027691 | H16: =H10/H4*1000 -> 55.261326 | I16: =I10/I4*1000 -> 27.048161 | J16: =J10/J4*1000 -> 40.095297 | K16: =K10/K4*1000 -> 42.375277 | ... P16: =P10/P4*1000 -> 38.247101
B17: 洗碗机单台 | C17: 当月单台目标完成率 | D17: =2-D16/D15 -> 0.96928055 | E17: =2-E16/E15 -> 0.88137117 | F17: =2-F16/F15 -> 0.015422249 | G17: =2-G16/G15 -> 1.4277725 | H17: =2-H16/H15 -> 0.94603841 | I17: =2-I16/I15 -> 1.2297395 | J17: =2-J16/J15 -> 1.0931931 | K17: =2-K16/K15 -> 1.0994346 | ... P17: =2-P16/P15 -> 1.0432151
B18: 洗碗机单台 | C18: 单台同期优化 | D18: =(D14-D16)/D14 -> -0.071357321 | E18: =(E14-E16)/E14 -> -0.15870382 | F18: =(F14-F16)/F14 -> -0.88976532 | G18: =(G14-G16)/G14 -> 0.31681634 | H18: =(H14-H16)/H14 -> -0.58959556 | I18: =(I14-I16)/I14 -> 0.53831829 | J18: =(J14-J16)/J14 -> -0.024951897 | K18: =(K14-K16)/K14 -> 0.1164043 | ... P18: =(P14-P16)/P14 -> 0.0774627
B19: 洗碗机制造费差额 | C19: 差额 | D19: =(D16-D14)*D4 -> 118437.49 | E19: =(E16-E14)*E4 -> 239630.37 | F19: =(F16-F14)*F4 -> 806538.24 | G19: =(G16-G14)*G4 -> -417722.67 | H19: =(H16-H14)*H4 -> 677280.13 | I19: =(I16-I14)*I4 -> -1677380.3 | J19: =(J16-J14)*J4 -> 40508.076 | K19: =(K16-K14)*K4 -> -217717.12 | ... P19: =(P16-P14)*P4 -> -1665982.2
A20: 洗碗机单台（累计） | B20: 洗碗机单台（累计） | C20: 同期 | D20: =D11/D5*1000 -> 35.052271 | E20: =E11/E5*1000 -> 35.157209 | F20: =F11/F5*1000 -> 36.555067 | G20: =G11/G5*1000 -> 35.43703 | H20: =H11/H5*1000 -> 35.288985 | I20: =I11/I5*1000 -> 37.814272 | J20: =J11/J5*1000 -> 37.987382 | K20: =K11/K5*1000 -> 38.904855 | ... P20: =P11/P5*1000 -> 1000
B21: 洗碗机单台（累计） | C21: 目标 | D21: =D12/D6*1000 -> 36.427791 | E21: =E12/E6*1000 -> 36.572572 | F21: =F12/F6*1000 -> 36.889363 | G21: =G12/G6*1000 -> 37.276185 | H21: =H12/H6*1000 -> 39.636785 | I21: =I12/I6*1000 -> 38.804808 | J21: =J12/J6*1000 -> 39.491168 | K21: =K12/K6*1000 -> 40.289992 | ... P21: =P12/P6*1000 -> 39.974605
B22: 洗碗机单台（累计） | C22: 26年 | D22: =D13/D7*1000 -> 37.546833 | E22: =E13/E7*1000 -> 39.217927 | F22: =F13/F7*1000 -> 46.396974 | G22: =G13/G7*1000 -> 39.919587 | H22: =H13/H7*1000 -> 42.632061 | I22: =I13/I7*1000 -> 39.179647 | J22: =J13/J7*1000 -> 39.314599 | K22: =K13/K7*1000 -> 39.686948 | ... P22: =P13/P7*1000 -> 38.247101
B23: 洗碗机单台（累计） | C23: 当月单台目标完成率 | D23: =2-D22/D21 -> 0.96928055 | E23: =2-E22/E21 -> 0.92766833 | F23: =2-F22/F21 -> 0.74226687 | G23: =2-G22/G21 -> 0.92908604 | H23: =2-H22/H21 -> 0.92443191 | I23: =2-I22/I21 -> 0.9903404 | J23: =2-J22/J21 -> 1.0044711 | K23: =2-K22/K21 -> 1.0149676 | ... P23: =2-P22/P21 -> 1.0432151
B24: 洗碗机单台（累计） | C24: 累计单台同期优化 | D24: =(D20-D22)/D20 -> -0.071166926 | E24: =(E20-E22)/E20 -> -0.11550174 | F24: =(F20-F22)/F20 -> -0.26923512 | G24: =(G20-G22)/G20 -> -0.1264936 | H24: =(H20-H22)/H20 -> -0.20808408 | I24: =(I20-I22)/I20 -> -0.036107402 | J24: =(J20-J22)/J20 -> -0.03493838 | K24: =(K20-K22)/K20 -> -0.0201027 | ... P24: =(P20-P22)/P20 -> 0.9617529
B25: 洗碗机制造费累计差额 | C25: 累计差额 | D25: =(D22-D20)*D7 -> 118142.47 | E25: =(E22-E20)*E7 -> 365273.85 | F25: =(F22-F20)*F7 -> 1111692.7 | G25: =(G22-G20)*G7 -> 689632.47 | H25: =(H22-H20)*H7 -> 1372354.8 | I25: =(I22-I20)*I7 -> 327795.16 | J25: =(J22-J20)*J7 -> 373713.94 | K25: =(K22-K20)*K7 -> 250720.91 | ... P25: =(P22-P20)*P7 -> -4.9891509e+08
A26: 洗碗机折旧费用 | B26: 洗碗机折旧费用 | C26: 同期 | D26: 547 | E26: 512 | F26: 562 | G26: 551 | H26: 580 | I26: 564 | J26: 579 | K26: 577 | L26: 565 | M26: 370 | N26: 546 | O26: 562 | P26: =SUM(D26:O26) -> 6515
B27: 洗碗机折旧费用 | C27: 目标 | D27: 577 | E27: 536 | F27: 582 | G27: 568 | H27: 580 | I27: 569 | J27: 599 | K27: 600 | L27: 586 | M27: 601 | N27: 591 | O27: 614 | P27: =SUM(D27:O27) -> 7003
B28: 洗碗机折旧费用 | C28: 26年 | D28: 564 | E28: 557 | F28: 565 | G28: 29.8973 | H28: 433.31502 | I28: 433 | J28: 479.85896 | K28: 480.14766 | L28: 469.5718 | M28: 475.19367 | N28: 475.19367 | O28: 494.2163 | P28: =SUM(D28:O28) -> 5456.3944
A29: 洗碗机折旧费用累计 | B29: 洗碗机折旧费用累计 | C29: 同期 | D29: =D26 -> 547 | E29: =D29+E26 -> 1059 | F29: =E29+F26 -> 1621 | G29: =F29+G26 -> 2172 | H29: =G29+H26 -> 2752 | I29: =H29+I26 -> 3316 | J29: =I29+J26 -> 3895 | K29: =J29+K26 -> 4472 | L29: =K29+L26 -> 5037 | ... O29: =N29+O26 -> 6515 | P29: =O29 -> 6515
B30: 洗碗机折旧费用累计 | C30: 目标 | D30: =D27 -> 577 | E30: =D30+E27 -> 1113 | F30: =E30+F27 -> 1695 | G30: =F30+G27 -> 2263 | H30: =G30+H27 -> 2843 | I30: =H30+I27 -> 3412 | J30: =I30+J27 -> 4011 | K30: =J30+K27 -> 4611 | L30: =K30+L27 -> 5197 | ... O30: =N30+O27 -> 7003 | P30: =O30 -> 7003
B31: 洗碗机折旧费用累计 | C31: 26年 | D31: =D28 -> 564 | E31: =D31+E28 -> 1121 | F31: =E31+F28 -> 1686 | G31: =F31+G28 -> 1715.8973 | H31: =G31+H28 -> 2149.2123 | I31: =H31+I28 -> 2582.2123 | J31: =I31+J28 -> 3062.0713 | K31: =J31+K28 -> 3542.2189 | L31: =K31+L28 -> 4011.7907 | ... O31: =N31+O28 -> 5456.3944 | P31: =O31 -> 5456.3944
A32: 洗碗机折旧单台 | B32: 洗碗机折旧单台 | C32: 同期 | D32: =D26/D2*1000 -> 11.262096 | E32: =E26/E2*1000 -> 11.121006 | F32: =F26/F2*1000 -> 12.130369 | G32: =G26/G2*1000 -> 11.162885 | H32: =H26/H2*1000 -> 10.79994 | I32: =I26/I2*1000 -> 19.012945 | J32: =J26/J2*1000 -> 13.832812 | K32: =K26/K2*1000 -> 18.044219 | ... O32: =O26/O2*1000 -> 13.351389 | P32: =P29/P2*1000 -> 13.626942
B33: 洗碗机折旧单台 | C33: 目标 | D33: =D27/D3*1000 -> 11.43412 | E33: =E27/E3*1000 -> 10.624381 | F33: =F27/F3*1000 -> 11.538462 | G33: =G27/G3*1000 -> 11.82102 | H33: =H27/H3*1000 -> 15.766011 | I33: =I27/I3*1000 -> 10.682437 | J33: =J27/J3*1000 -> 14.245285 | K33: =K27/K3*1000 -> 15.32567 | ... O33: =O27/O3*1000 -> 15.094896 | P33: =P30/P3*1000 -> 12.394273
B34: 洗碗机折旧单台 | C34: 26年 | D34: =D28/D4*1000 -> 11.908784 | E34: =E28/E4*1000 -> 13.077266 | F34: =F28/F4*1000 -> 24.563081 | G34: =G28/G4*1000 -> 0.73111046 | H34: =H28/H4*1000 -> 13.113671 | I34: =I28/I4*1000 -> 8.1412402 | J34: =J28/J4*1000 -> 11.562866 | K34: =K28/K4*1000 -> 12.311478 | ... O34: =O28/O4*1000 -> 11.714063 | P34: =P31/P4*1000 -> 10.518229
B35: 洗碗机折旧差额 | C35: 差额 | D35: =(D33-D32)*D4 -> 8147.0616 | E35: =(E33-E32)*E4 -> -21152.771 | F35: =(F33-F32)*F4 -> -13615.058 | G35: =(G33-G32)*G4 -> 26913.108 | H35: =(H33-H32)*H4 -> 164093.86 | I35: =(I33-I32)*I4 -> -443066.4 | J35: =(J33-J32)*J4 -> 17117.652 | K35: =(K33-K32)*K4 -> -106023.41 | ... P35: =(P33-P32)*P4 -> -639454.1
A36: 洗碗机折旧费用累计 | B36: 洗碗机折旧单台累计 | C36: 同期 | D36: =D29/D5*1000 -> 11.262096 | E36: =E29/E5*1000 -> 11.193438 | F36: =F29/F5*1000 -> 11.50143 | G36: =G29/G5*1000 -> 11.413618 | H36: =H29/H5*1000 -> 11.27855 | I36: =I29/I5*1000 -> 12.116916 | J36: =J29/J5*1000 -> 12.344544 | K36: =K29/K5*1000 -> 12.869028 | ... P36: =P29/P5*1000 -> 328.68797
B37: 洗碗机折旧单台累计 | C37: 目标 | D37: =D30/D6*1000 -> 11.43412 | E37: =E30/E6*1000 -> 11.029302 | F37: =F30/F6*1000 -> 11.198985 | G37: =G30/G6*1000 -> 11.348876 | H37: =H30/H6*1000 -> 12.036868 | I37: =I30/I6*1000 -> 11.787629 | J37: =J30/J6*1000 -> 12.099365 | K37: =K30/K6*1000 -> 12.44014 | ... P37: =P30/P6*1000 -> 12.394273
B38: 洗碗机折旧单台累计 | C38: 26年 | D38: =D31/D7*1000 -> 11.908784 | E38: =E31/E7*1000 -> 12.462064 | F38: =F31/F7*1000 -> 14.926298 | G38: =G31/G7*1000 -> 11.153199 | H38: =H31/H7*1000 -> 11.499817 | I38: =I31/I7*1000 -> 10.755767 | J38: =J31/J7*1000 -> 10.874721 | K38: =K31/K7*1000 -> 11.049511 | ... P38: =P31/P7*1000 -> 10.518229
B39: 洗碗机折旧单台差额 | C39: 差额 | D39: =(D38-D36)*D7 -> 30627.136 | E39: =(E38-E36)*E7 -> 114116.65 | F39: =(F38-F36)*F7 -> 386856.01 | G39: =(G38-G36)*G7 -> -40064.928 | H39: =(H38-H36)*H7 -> 41352.859 | I39: =(I38-I36)*I7 -> -326780.48 | J39: =(J38-J36)*J7 -> -413868.48 | K39: =(K38-K36)*K7 -> -583295.37 | ... P39: =(P38-P36)*P7 -> -1.6505247e+08
A40: 洗碗机变动费用 | B40: 洗碗机变动费用 | C40: 同期 | D40: =D8-D26 -> 1155.4888 | E40: =E8-E26 -> 1111.6996 | F40: =F8-F26 -> 1263.8462 | G40: =G8-G26 -> 1040.5968 | H40: =H8-H26 -> 1286.987 | I40: =I8-I26 -> 1173.9 | J40: =J8-J26 -> 1058.4123 | K40: =K8-K26 -> 956.54553 | ... P40: =P8-P26 -> 13306.23
B41: 洗碗机变动费用 | C41: 目标 | D41: =D9-D27 -> 1261.2556 | E41: =E9-E27 -> 1316.3924 | F41: =F9-F27 -> 1310.6678 | G41: =G9-G27 -> 1281.6673 | H41: =H9-H27 -> 1348.8688 | I41: =I9-I27 -> 1301.4326 | J41: =J9-J27 -> 1260.2351 | K41: =K9-K27 -> 1242.1673 | ... P41: =P9-P27 -> 15583.412
B42: 洗碗机变动费用 | C42: 26年 | D42: =D10-D28 -> 1214.218 | E42: =E10-E28 -> 1192.5522 | F42: =F10-F28 -> 1148 | G42: =G10-G28 -> 870.88106 | H42: =H10-H28 -> 1392.685 | I42: =I10-I28 -> 1005.5835 | J42: =J10-J28 -> 1184.0959 | K42: =K10-K28 -> 1172.4882 | ... P42: =P10-P28 -> 14384.519
A43: 洗碗机变动费用累计 | B43: 洗碗机变动费用累计 | C43: 同期 | D43: =D40 -> 1155.4888 | E43: =D43+E40 -> 2267.1883 | F43: =E43+F40 -> 3531.0345 | G43: =F43+G40 -> 4571.6313 | H43: =G43+H40 -> 5858.6183 | I43: =H43+I40 -> 7032.5183 | J43: =I43+J40 -> 8090.9306 | K43: =J43+K40 -> 9047.4761 | L43: =K43+L40 -> 10080.331 | ... O43: =N43+O40 -> 13306.23 | P43: =O43 -> 13306.23
B44: 洗碗机变动费用累计 | C44: 目标 | D44: =D41 -> 1261.2556 | E44: =D44+E41 -> 2577.648 | F44: =E44+F41 -> 3888.3158 | G44: =F44+G41 -> 5169.9831 | H44: =G44+H41 -> 6518.8519 | I44: =H44+I41 -> 7820.2845 | J44: =I44+J41 -> 9080.5196 | K44: =J44+K41 -> 10322.687 | L44: =K44+L41 -> 11685.374 | ... O44: =N44+O41 -> 15583.412 | P44: =O44 -> 15583.412
B45: 洗碗机变动费用累计 | C45: 26年 | D45: =D42 -> 1214.218 | E45: =D45+E42 -> 2406.7702 | F45: =E45+F42 -> 3554.7702 | G45: =F45+G42 -> 4425.6513 | H45: =G45+H42 -> 5818.3363 | I45: =H45+I42 -> 6823.9198 | J45: =I45+J42 -> 8008.0156 | K45: =J45+K42 -> 9180.5038 | L45: =K45+L42 -> 10527.134 | ... O45: =N45+O42 -> 14384.519 | P45: =O45 -> 14384.519
A46: 洗碗机变动单台 | B46: 洗碗机变动单台 | C46: 同期 | D46: =D40/D2*1000 -> 23.790175 | E46: =E40/E2*1000 -> 24.146909 | F46: =F40/F2*1000 -> 27.279218 | G46: =G40/G2*1000 -> 21.081782 | H46: =H40/H2*1000 -> 23.964453 | I46: =I40/I2*1000 -> 39.57322 | J46: =J40/J2*1000 -> 25.286387 | K46: =K40/K2*1000 -> 29.913548 | ... P46: =P40/P2*1000 -> 27.831654
B47: 洗碗机变动单台 | C47: 目标 | D47: =D41/D3*1000 -> 24.993671 | E47: =E41/E3*1000 -> 26.09301 | F47: =F41/F3*1000 -> 25.984691 | G47: =G41/G3*1000 -> 26.673617 | H47: =H41/H3*1000 -> 36.666001 | I47: =I41/I3*1000 -> 24.433165 | J47: =J41/J3*1000 -> 29.970632 | K47: =K41/K3*1000 -> 31.728412 | ... P47: =P41/P3*1000 -> 27.580332
B48: 洗碗机变动单台 | C48: 26年 | D48: =D42/D4*1000 -> 25.638049 | E48: =E42/E4*1000 -> 27.998784 | F48: =F42/F4*1000 -> 49.908704 | G48: =G42/G4*1000 -> 21.29658 | H48: =H42/H4*1000 -> 42.147655 | I48: =I42/I4*1000 -> 18.906921 | J48: =J42/J4*1000 -> 28.53243 | K48: =K42/K4*1000 -> 30.063799 | ... P48: =P42/P4*1000 -> 27.728872
B49: 洗碗机变动单台 | C49: 差额 | D49: =(D48-D46)*D4 -> 87515.336 | E49: =(E48-E46)*E4 -> 164062.91 | F49: =(F48-F46)*F4 -> 520523.43 | G49: =(G48-G46)*G4 -> 8783.7487 | H49: =(H48-H46)*H4 -> 600827.54 | I49: =(I48-I46)*I4 -> -1099157.8 | J49: =(J48-J46)*J4 -> 134710.81 | K49: =(K48-K46)*K4 -> 5859.7854 | ... P49: =(P48-P46)*P4 -> -53318.697
A50: 洗碗机变动单台（累计） | B50: 洗碗机变动单台（累计） | C50: 同期 | D50: =D43/D5*1000 -> 23.790175 | E50: =E43/E5*1000 -> 23.96377 | F50: =F43/F5*1000 -> 25.053637 | G50: =G43/G5*1000 -> 24.023412 | H50: =H43/H5*1000 -> 24.010435 | I50: =I43/I5*1000 -> 25.697356 | J50: =J43/J5*1000 -> 25.642837 | K50: =K43/K5*1000 -> 26.035828 | ... P50: =P43/P5*1000 -> 671.31203
B51: 洗碗机变动单台（累计） | C51: 目标 | D51: =D44/D6*1000 -> 24.993671 | E51: =E44/E6*1000 -> 25.54327 | F51: =F44/F6*1000 -> 25.690378 | G51: =G44/G6*1000 -> 25.927309 | H51: =H44/H6*1000 -> 27.599917 | I51: =I44/I6*1000 -> 27.017179 | J51: =J44/J6*1000 -> 27.391803 | K51: =K44/K6*1000 -> 27.849852 | ... P51: =P44/P6*1000 -> 27.580332
B52: 洗碗机变动单台（累计） | C52: 26年 | D52: =D45/D7*1000 -> 25.638049 | E52: =E45/E7*1000 -> 26.755864 | F52: =F45/F7*1000 -> 31.470676 | G52: =G45/G7*1000 -> 28.766388 | H52: =H45/H7*1000 -> 31.132244 | I52: =I45/I7*1000 -> 28.42388 | J52: =J45/J7*1000 -> 28.439878 | K52: =K45/K7*1000 -> 28.637437 | ... P52: =P45/P7*1000 -> 27.728872
B53: 洗碗机变动单台（累计）差额 | C53: 差额 | D53: =(D52-D50)*D7 -> 87515.336 | E53: =(E52-E50)*E7 -> 251157.2 | F53: =(F52-F50)*F7 -> 724836.68 | G53: =(G52-G50)*G7 -> 729697.4 | H53: =(H52-H50)*H7 -> 1331002 | I53: =(I52-I50)*I7 -> 654575.64 | J53: =(J52-J50)*J7 -> 787582.42 | K53: =(K52-K50)*K7 -> 834016.28 | ... P53: =(P52-P50)*P7 -> -3.3386262e+08
B54: 洗碗机变动单台（累计） | C54: 当月单台目标完成率 | D54: =2-D52/D51 -> 0.97421835 | E54: =2-E52/E51 -> 0.95252784 | F54: =2-F52/F51 -> 0.77500144 | G54: =2-G52/G51 -> 0.89049848 | H54: =2-H52/H51 -> 0.87201673 | I54: =2-I52/I51 -> 0.9479331 | J54: =2-J52/J51 -> 0.96173762 | K54: =2-K52/K51 -> 0.97172031 | ... P54: =2-P52/P51 -> 0.99461428
B55: 洗碗机变动单台（累计） | C55: 累计单台同期优化 | D55: =(D50-D52)/D50 -> -0.077673852 | E55: =(E50-E52)/E50 -> -0.11651312 | F55: =(F50-F52)/F50 -> -0.25613205 | G55: =(G50-G52)/G50 -> -0.19743141 | H55: =(H50-H52)/H50 -> -0.29661306 | I55: =(I50-I52)/I50 -> -0.10610133 | J55: =(J50-J52)/J50 -> -0.10907689 | K55: =(K50-K52)/K50 -> -0.099924223 | ... P55: =(P50-P52)/P50 -> 0.95869451
A56: 洗碗机制造费率 | B56: 洗碗机收入 | C56: 同期 | D56: 11599190 | E56: 10318459 | F56: 10279816 | G56: 10804991 | H56: 11868184 | I56: 6637897.4 | J56: 9550821.1 | K56: 7188579.4 | L56: 5817772.6 | M56: 5854623.5 | N56: 7485280 | O56: 8923716 | P56: 106138644
B57: 洗碗机收入 | C57: 目标 | D57: 11202786 | E57: 11199012 | F57: 11199234 | G57: 10667100 | H57: 8166936 | I57: 11824830 | J57: 9334878 | K57: 8691300 | L57: 11928504 | M57: 10777656 | N57: 11412576 | O57: 9030072 | P57: 125434884
B58: 洗碗机收入 | C58: 26年 | D58: 10892110 | E58: 9242681 | F58: =211*F4 -> 4853422 | G58: =217*G4 -> 8873781 | H58: =213*H4 -> 7038159
B59: 洗碗机收入(累计） | C59: 同期 | D59: =D56 -> 11599190 | E59: =D59+E56 -> 21917650 | F59: =E59+F56 -> 32197465 | G59: =F59+G56 -> 43002456 | H59: =G59+H56 -> 54870640 | I59: =H59+I56 -> 61508538 | J59: =I59+J56 -> 71059359 | K59: =J59+K56 -> 78247938 | L59: =K59+L56 -> 84065711 | ... O59: =N59+O56 -> 1.0632933e+08 | P59: =O59 -> 1.0632933e+08
B60: 洗碗机收入(累计） | C60: 目标 | D60: =D57 -> 11202786 | E60: =D60+E57 -> 22401798 | F60: =E60+F57 -> 33601032 | G60: =F60+G57 -> 44268132 | H60: =G60+H57 -> 52435068 | I60: =H60+I57 -> 64259898 | J60: =I60+J57 -> 73594776 | K60: =J60+K57 -> 82286076 | L60: =K60+L57 -> 94214580 | ... O60: =N60+O57 -> 125434884 | P60: =O60 -> 125434884
B61: 洗碗机收入(累计） | C61: 26年 | D61: =D58 -> 10892110 | E61: =D61+E58 -> 20134791 | F61: =E61+F58 -> 24988213 | G61: =F61+G58 -> 33861994 | H61: =G61+H58 -> 40900153
B62: 洗碗机制造费率 | C62: 同期 | D62: =D8/D56*1000 -> 0.14677652 | E62: =E8/E56*1000 -> 0.15735872 | F62: =F8/F56*1000 -> 0.17761468 | G62: =G8/G56*1000 -> 0.147302 | H62: =H8/H56*1000 -> 0.15731025 | I62: =I8/I56*1000 -> 0.26181483 | J62: =J8/J56*1000 -> 0.17144205 | K62: =K8/K56*1000 -> 0.21333082 | ... P62: =P8/P56*1000 -> 0.18674848
B63: 洗碗机制造费率 | C63: 目标 | D63: =D9/D57*1000 -> 0.16408915 | E63: =E9/E57*1000 -> 0.16540677 | F63: =F9/F57*1000 -> 0.16899976 | G63: =G9/G57*1000 -> 0.17339927 | H63: =H9/H57*1000 -> 0.23618023 | I63: =I9/I57*1000 -> 0.15817839 | J63: =J9/J57*1000 -> 0.1991708 | K63: =K9/K57*1000 -> 0.21195533 | ... P63: =P9/P57*1000 -> 0.18006483
B64: 洗碗机制造费率 | C64: 26年 | D64: =D10/D58*1000 -> 0.16325744 | E64: =E10/E58*1000 -> 0.18929056 | F64: =F10/F58*1000 -> 0.35294685 | G64: =G10/G58*1000 -> 0.1015101 | H64: =H10/H58*1000 -> 0.25944285
B65: 洗碗机制造费率（累计） | C65: 同期 | D65: =D11/D59*1000 -> 0.14677652 | E65: =E11/E59*1000 -> 0.15175844 | F65: =F11/F59*1000 -> 0.16001367 | G65: =G11/G59*1000 -> 0.15681968 | H65: =H11/H59*1000 -> 0.15692578 | I65: =I11/I59*1000 -> 0.16824523 | J65: =J11/J59*1000 -> 0.16867491 | K65: =K11/K59*1000 -> 0.17277741 | ... P65: =P11/P59*1000 -> 0.18641357
B66: 洗碗机制造费率（累计） | C66: 目标 | D66: =D12/D60*1000 -> 0.16408915 | E66: =E12/E60*1000 -> 0.16474785 | F66: =F12/F60*1000 -> 0.16616501 | G66: =G12/G60*1000 -> 0.16790822 | H66: =H12/H60*1000 -> 0.17854181 | I66: =I12/I60*1000 -> 0.17479462 | J66: =J12/J60*1000 -> 0.17788653 | K66: =K12/K60*1000 -> 0.18148498 | ... P66: =P12/P60*1000 -> 0.18006483
B67: 洗碗机制造费率（累计） | C67: 26年 | D67: =D13/D61*1000 -> 0.16325744 | E67: =E13/E61*1000 -> 0.17520769 | F67: =F13/F61*1000 -> 0.20972969 | G67: =G13/G61*1000 -> 0.18136996 | H67: =H13/H61*1000 -> 0.19480486
B68: 洗碗机G＆A制造费 | C68: 同期 | D68: 174.89607 | E68: 243.79851 | F68: 219.31379 | G68: 161.26311 | H68: 196.88485
C69: 目标
C70: 26年 | D70: 212.47293 | E70: 156.4507 | F70: 171.18389 | G70: 168.22711 | H70: 269.72394
B71: 洗碗机G＆A制造费累计 | C71: 同期 | D71: =D68 -> 174.89607 | E71: =D71+E68 -> 418.69458 | F71: =E71+F68 -> 638.00837 | G71: =F71+G68 -> 799.27148 | H71: =G71+H68 -> 996.15633 | I71: =H71+I68 -> 996.15633 | J71: =I71+J68 -> 996.15633 | K71: =J71+K68 -> 996.15633 | L71: =K71+L68 -> 996.15633 | ... O71: =N71+O68 -> 996.15633 | P71: =O71 -> 996.15633
C72: 目标 | D72: =D69 -> 0 | E72: =D72+E69 -> 0 | F72: =E72+F69 -> 0 | G72: =F72+G69 -> 0 | H72: =G72+H69 -> 0 | I72: =H72+I69 -> 0 | J72: =I72+J69 -> 0 | K72: =J72+K69 -> 0 | L72: =K72+L69 -> 0 | ... O72: =N72+O69 -> 0 | P72: =O72 -> 0
C73: 26年 | D73: =D70 -> 212.47293 | E73: =D73+E70 -> 368.92363 | F73: =E73+F70 -> 540.10752 | G73: =F73+G70 -> 708.33463 | H73: =G73+H70 -> 978.05857 | I73: =H73+I70 -> 978.05857 | J73: =I73+J70 -> 978.05857 | K73: =J73+K70 -> 978.05857 | L73: =K73+L70 -> 978.05857 | ... O73: =N73+O70 -> 978.05857 | P73: =O73 -> 978.05857
B74: 洗碗机G＆A单台累计 | C74: 同期 | D74: =D71/D5*1000 -> 3.6009074 | E74: =E71/E5*1000 -> 4.4255259 | F74: =F71/F5*1000 -> 4.5268405 | G74: =G71/G5*1000 -> 4.2000824 | H74: =H71/H5*1000 -> 4.0825577
C75: 目标
B76: =H76-H74 -> 1.1507524 | C76: 26年 | D76: =D73/D7*1000 -> 4.4863372 | E76: =E73/E7*1000 -> 4.1012932 | F76: =F73/F7*1000 -> 4.7816168 | G76: =G73/G7*1000 -> 4.6041198 | H76: =H73/H7*1000 -> 5.2333102
B77: 洗碗机直接人工制造费 | C77: 同期 | D77: 471.95897 | E77: 343.39069 | F77: 517.21307 | G77: 469.10102 | H77: 563.01003
C78: 目标
C79: 26年 | D79: 471.95897 | E79: 343.39069 | F79: 517.21307 | G79: 469.10102 | H79: 563.01003
B80: 洗碗机直接人工制造费累计 | C80: 同期 | D80: =D77 -> 471.95897 | E80: =D80+E77 -> 815.34966 | F80: =E80+F77 -> 1332.5627 | G80: =F80+G77 -> 1801.6637 | H80: =G80+H77 -> 2364.6738
C81: 目标 | D81: =D78 -> 0 | E81: =D81+E78 -> 0 | F81: =E81+F78 -> 0 | G81: =F81+G78 -> 0 | H81: =G81+H78 -> 0
C82: 26年 | D82: =D79 -> 471.95897 | E82: =D82+E79 -> 815.34966 | F82: =E82+F79 -> 1332.5627 | G82: =F82+G79 -> 1801.6637 | H82: =G82+H79 -> 2364.6738
B83: 洗碗机直接人工单台累计 | C83: 同期 | D83: =D80/D5*1000 -> 9.7170881 | E83: =E80/E5*1000 -> 8.6180983 | F83: =F80/F5*1000 -> 9.4548899 | G83: =G80/G5*1000 -> 9.4675419 | H83: =H80/H5*1000 -> 9.6911668
C84: 目标
B85: =H85-H83 -> 2.9615226 | C85: 26年 | D85: =D82/D7*1000 -> 9.9653499 | E85: =E82/E7*1000 -> 9.0641742 | F85: =F82/F7*1000 -> 11.797289 | G85: =G82/G7*1000 -> 11.710674 | H85: =H82/H7*1000 -> 12.652689
B86: 洗碗机间接人工制造费 | C86: 同期 | D86: 236.51712 | E86: 210.33046 | F86: 189.488 | G86: 211.92001 | H86: 247.78062
C87: 目标
C88: 26年 | D88: 208.04047 | E88: 161.36901 | F88: 245.62476 | G88: 210.35834 | H88: 241.29695
B89: 洗碗机间接人工制造费累计 | C89: 同期 | D89: =D86 -> 236.51712 | E89: =D89+E86 -> 446.84758 | F89: =E89+F86 -> 636.33558 | G89: =F89+G86 -> 848.25559 | H89: =G89+H86 -> 1096.0362
C90: 目标 | D90: =D87 -> 0 | E90: =D90+E87 -> 0 | F90: =E90+F87 -> 0 | G90: =F90+G87 -> 0 | H90: =G90+H87 -> 0
C91: 26年 | D91: =D88 -> 208.04047 | E91: =D91+E88 -> 369.40948 | F91: =E91+F88 -> 615.03424 | G91: =F91+G88 -> 825.39258 | H91: =G91+H88 -> 1066.6895
B92: 洗碗机间接人工单台累计 | C92: 同期 | D92: =D89/D5*1000 -> 4.8696133 | E92: =E89/E5*1000 -> 4.723098 | F92: =F89/F5*1000 -> 4.5149716 | G92: =G89/G5*1000 -> 4.4574884 | H92: =H89/H5*1000 -> 4.4918964
C93: 目标
B94: =H94-H92 -> 1.2156525 | C94: 26年 | D94: =D91/D7*1000 -> 4.3927464 | E94: =E91/E7*1000 -> 4.1066944 | F94: =F91/F7*1000 -> 5.4449492 | G94: =G91/G7*1000 -> 5.3649874 | H94: =H91/H7*1000 -> 5.7075489

Sheet 26年洗碗机费用指标到月测算汇总表 
B1: 土耳其洗碗机费用指标统计
B2: 一、年度预测： 产量预算：年度预算56.5万台↑14%，实际截至到6月 24万台↓12%（大差） 单台预测：25年单台达成41.5欧，26年目标40欧，预测达成38.25欧，同比↓7.7%；额收益166万欧 三、6月达成： 订单量预测：6月同期2.9万台，预测5.3万台，实际5.3万台，较同期↑79% 单台预测：6月同期58.59欧，实际单台费用27.05欧，较同期下54%；额优化167万欧 6月累计单台：6月同期37.81欧，6月实际39.18欧，累计单台↑3.6欧，额恶化32万欧
A3: 费 | B3: 序号 | C3: / | D3: 1月份 | E3: 2月份 | F3: 3月份 | G3: 4月份 | H3: 5月份 | I3: 6月份 | J3: 7月份 | K3: 8月份 | L3: 9月份 | M3: 10月份 | N3: 11月份 | O3: 12月份 | P3: 年度
B4: 费率 | C4: 销售收入（26年预测） | D4: 11387.793 | E4: 11383.957 | F4: 11384.182 | G4: 10843.261 | H4: 8301.8079 | I4: 12020.11 | J4: 9489.0377 | K4: 8834.8314 | L4: 12125.496 | M4: 10955.642 | N4: 11601.048 | O4: 9179.1981 | P4: 127506.36
C5: 销售收入（25年实际） | D5: 11599.19 | E5: 10318.459 | F5: 10279.816 | G5: 10804.991 | H5: 11868.184 | I5: 6637.8974 | J5: 9550.8211 | K5: 7188.5794 | L5: 5817.7726 | M5: 5854.6235 | N5: 7485.28 | O5: 8923.716 | P5: 106138.64
C6: 单价（同期） | D6: 238.80897 | E6: 224.15352 | F6: 221.84897 | G6: 218.88846 | H6: 220.99255 | I6: 223.76947 | J6: 228.17739 | K6: 224.80468 | L6: 205.80772 | M6: 223.36513 | N6: 220 | O6: 212 | P6: 222
C7: 单价（实际） | D7: 225.66619 | E7: 225.66619 | F7: 225.66619 | G7: 225.66619 | H7: 225.66619 | I7: 225.66619 | J7: 225.66619 | K7: 225.66619 | L7: 225.66619 | M7: 225.66619 | N7: 225.66619 | O7: 225.66619 | P7: 225.66619
C8: 制造费用（26年预测） | D8: 1838.2556 | E8: 1852.3924 | F8: 1893.0365 | G8: 1849.6673 | H8: 1928.8688 | I8: 1870.4326 | J8: 1859.2351 | K8: 1842.1673 | L8: 1948.6868 | M8: 1894.9246 | N8: 1861.9628 | O8: 1947.1505 | P8: 22586.78
C9: 制造费用（25年实际） | D9: 1702.2213 | E9: 1632.2334 | F9: 1827.8999 | G9: 1591.5968 | H9: 1866.987 | I9: 1737.9 | J9: 1637.4123 | K9: 1533.5455 | L9: 1597.8553 | M9: 1443.0898 | N9: 1758.5061 | O9: 1502.3028 | P9: 19831.55
C10: 同期 | D10: 0.14675346 | E10: 0.15818577 | F10: 0.17781446 | G10: 0.147302 | H10: 0.15731025 | I10: 0.26181483 | J10: 0.17144205 | K10: 0.21333082 | L10: 0.2746507 | M10: 0.24648721 | N10: 0.23492856 | O10: 0.16834947 | P10: 0.18684571
C11: 目标 | D11: 0.16142334 | E11: 0.16271955 | F11: 0.16628656 | G11: 0.17058221 | H11: 0.23234323 | I11: 0.15560861 | J11: 0.19593505 | K11: 0.20851188 | L11: 0.16070986 | M11: 0.17296335 | N11: 0.16049954 | O11: 0.21212643 | P11: 0.17714238
C12: 26年 | D12: =D8/D4 -> 0.16142334 | E12: =E8/E4 -> 0.16271955 | F12: =F8/F4 -> 0.16628656 | G12: =G8/G4 -> 0.17058221 | H12: =H8/H4 -> 0.23234323 | I12: =I8/I4 -> 0.15560861 | J12: =J8/J4 -> 0.19593505 | K12: =K8/K4 -> 0.20851188 | ... P12: =P8/P4 -> 0.17714238
B13: 降幅 | D13: =(D10-D12)/D10 -> -0.09996281 | E13: =(E10-E12)/E10 -> -0.028661121 | F13: =(F10-F12)/F10 -> 0.064831052 | G13: =(G10-G12)/G10 -> -0.15804409 | H13: =(H10-H12)/H10 -> -0.47697446 | I13: =(I10-I12)/I10 -> 0.40565396 | J13: =(J10-J12)/J10 -> -0.14286464 | K13: =(K10-K12)/K10 -> 0.022589029 | ... P13: =(P10-P12)/P10 -> 0.051932324
B14: 完成率 | D14: =2-D12/D11 -> 1 | E14: =2-E12/E11 -> 1 | F14: =2-F12/F11 -> 1 | G14: =2-G12/G11 -> 1 | H14: =2-H12/H11 -> 1 | I14: =2-I12/I11 -> 1 | J14: =2-J12/J11 -> 1 | K14: =2-K12/K11 -> 1 | ... O14: =2-O12/O11 -> 1
B15: 费率（累计） | C15: 累计销售收入（26年预测） | D15: =D4 -> 11387.793 | E15: =D15+E4 -> 22771.75 | F15: =E15+F4 -> 34155.932 | G15: =F15+G4 -> 44999.193 | H15: =G15+H4 -> 53301.001 | I15: =H15+I4 -> 65321.11 | J15: =I15+J4 -> 74810.148 | K15: =J15+K4 -> 83644.98 | L15: =K15+L4 -> 95770.476 | ... O15: =N15+O4 -> 127506.36 | P15: =O15 -> 127506.36
C16: 累计销售收入（25年实际） | D16: =D5 -> 11599.19 | E16: =D16+E5 -> 21917.65 | F16: =E16+F5 -> 32197.465 | G16: =F16+G5 -> 43002.456 | H16: =G16+H5 -> 54870.64 | I16: =H16+I5 -> 61508.538 | J16: =I16+J5 -> 71059.359 | K16: =J16+K5 -> 78247.938 | L16: =K16+L5 -> 84065.711 | ... O16: =N16+O5 -> 106329.33 | P16: =O16 -> 106329.33
C17: 累计制造费用（26年预测） | D17: =D8 -> 1838.2556 | E17: =D17+E8 -> 3690.648 | F17: =E17+F8 -> 5583.6845 | G17: =F17+G8 -> 7433.3518 | H17: =G17+H8 -> 9362.2206 | I17: =H17+I8 -> 11232.653 | J17: =I17+J8 -> 13091.888 | K17: =J17+K8 -> 14934.056 | L17: =K17+L8 -> 16882.742 | ... O17: =N17+O8 -> 22586.78 | P17: =O17 -> 22586.78
C18: 累计制造费用（25年实际） | D18: =D9 -> 1702.2213 | E18: =D18+E9 -> 3334.4547 | F18: =E18+F9 -> 5162.3545 | G18: =F18+G9 -> 6753.9513 | H18: =G18+H9 -> 8620.9383 | I18: =H18+I9 -> 10358.838 | J18: =I18+J9 -> 11996.251 | K18: =J18+K9 -> 13529.796 | L18: =K18+L9 -> 15127.651 | ... O18: =N18+O9 -> 19831.55 | P18: =O18 -> 19831.55
C19: 同期 | D19: =D18/D16 -> 0.14675346 | E19: =E18/E16 -> 0.1521356 | F19: =F18/F16 -> 0.16033419 | G19: =G18/G16 -> 0.15705966 | H19: =H18/H16 -> 0.15711386 | I19: =I18/I16 -> 0.16841302 | J19: =J18/J16 -> 0.16882014 | K19: =K18/K16 -> 0.1729093 | ... P19: =P18/P16 -> 0.18651063
C20: 目标 | D20: 0.16142334 | E20: 0.16207134 | F20: 0.16347627 | G20: 0.16518856 | H20: 0.17564812 | I20: 0.17196054 | J20: 0.1750015 | K20: 0.17854097 | L20: 0.17628337 | M20: 0.17594257 | N20: 0.1744285 | O20: 0.17714238 | P20: 0.17714238
C21: 26年 | D21: =D17/D15 -> 0.16142334 | E21: =E17/E15 -> 0.16207134 | F21: =F17/F15 -> 0.16347627 | G21: =G17/G15 -> 0.16518856 | H21: =H17/H15 -> 0.17564812 | I21: =I17/I15 -> 0.17196054 | J21: =J17/J15 -> 0.1750015 | K21: =K17/K15 -> 0.17854097 | ... P21: =P17/P15 -> 0.17714238
B22: 降幅 | D22: =(D19-D21)/D19 -> -0.09996281 | E22: =(E19-E21)/E19 -> -0.065308465 | F22: =(F19-F21)/F19 -> -0.019597081 | G22: =(G19-G21)/G19 -> -0.05175674 | H22: =(H19-H21)/H19 -> -0.11796704 | I22: =(I19-I21)/I19 -> -0.021064411 | J22: =(J19-J21)/J19 -> -0.036615098 | K22: =(K19-K21)/K19 -> -0.032570075 | ... O22: =(O19-O21)/O19 -> 0.050229047
B23: 完成率 | D23: =2-D21/D20 -> 1 | E23: =2-E21/E20 -> 1 | F23: =2-F21/F20 -> 1 | G23: =2-G21/G20 -> 1 | H23: =2-H21/H20 -> 1 | I23: =2-I21/I20 -> 1 | J23: =2-J21/J20 -> 1 | K23: 0.06 | L23: =2-L21/L20 -> 1 | M23: =2-M21/M20 -> 1 | N23: =2-N21/N20 -> 1 | O23: =2-O21/O20 -> 1
B24: 单台 | C24: 同期 | D24: 35.046041 | E24: 35.45 | F24: 39.407954 | G24: 32.242707 | H24: 34.764394 | I24: 58.586165 | J24: 39.119199 | K24: 47.957767 | L24: 56.525234 | M24: 55.056648 | N24: 51.684284 | O24: 35.690087 | P24: =P41/P48*1000 -> 41.458596
C25: 目标 | D25: 36.427791 | E25: 36.72 | F25: 37.525254 | G25: 38.494637 | H25: 52.432012 | I25: 35.115602 | J25: 44.215917 | K25: 47.054083 | L25: 36.266783 | M25: 39.031981 | N25: 36.219319 | O25: 47.869763 | P25: =P42/P49*1000 -> 39.974605 | R25: =P24-P26 -> 3.2114947
C26: 26年 | D26: 37.546833 | E26: 41.11 | F26: 74.476709 | G26: 22.053802 | H26: =H39/H50*1000 -> 55.261326 | I26: =I39/I50*1000 -> 27.048161 | J26: =J39/J50*1000 -> 40.095297 | K26: =K39/K50*1000 -> 42.375277 | L26: =L39/L50*1000 -> 33.580508 | M26: =M39/M50*1000 -> 35.306481 | N26: =N39/N50*1000 -> 33.500829 | O26: =O39/O50*1000 -> 42.614252 | P26: =P43/P50*1000 -> 38.247101 | R26: =R25*P50 -> 1665982.2
B27: 当月单台完成率 | D27: =2-D26/D25 -> 0.96928055 | E27: =2-E26/E25 -> 0.88044662 | F27: =2-F26/F25 -> 0.015291021 | G27: =2-G26/G25 -> 1.4270942 | H27: =2-H26/H25 -> 0.94603841 | I27: =2-I26/I25 -> 1.2297395 | J27: =2-J26/J25 -> 1.0931931 | K27: =2-K26/K25 -> 1.0994346 | ... P27: =2-P26/P25 -> 1.0432151
B28: 目标同期优化率 | D28: =D25/D24-1 -> 0.039426701 | E28: =E25/E24-1 -> 0.035825106 | F28: =F25/F24-1 -> -0.047774611 | G28: =G25/G24-1 -> 0.19390214 | H28: =H25/H24-1 -> 0.50821015 | I28: =I25/I24-1 -> -0.40061614 | J28: =J25/J24-1 -> 0.13028688 | K28: =K25/K24-1 -> -0.018843342 | ... O28: =O25/O24-1 -> 0.34126216
B29: 当月单台同期优化率 | D29: =(D24-D26)/D24 -> -0.071357321 | E29: =(E24-E26)/E24 -> -0.1596615 | F29: =(F24-F26)/F24 -> -0.88989028 | G29: =(G24-G26)/G24 -> 0.3160065 | H29: =(H24-H26)/H24 -> -0.58959556 | I29: =(I24-I26)/I24 -> 0.53831829 | J29: =(J24-J26)/J24 -> -0.024951897 | K29: =(K24-K26)/K24 -> 0.1164043 | ... P29: =(P24-P26)/P24 -> 0.0774627 | R29: =7.9*P50 -> 4098172.4
B30: 当月费用额
B31: 单台（累计） | C31: 同期 | D31: =D41/D48*1000 -> 35.052271 | E31: =E41/E56*1000 -> 35.157209 | F31: =F41/F56*1000 -> 36.555067 | G31: =G41/G56*1000 -> 35.43703 | H31: =H41/H56*1000 -> 35.288985 | I31: =I41/I56*1000 -> 37.814272 | J31: =J41/J56*1000 -> 37.987382 | K31: =K41/K56*1000 -> 38.904855 | L31: =L41/L56*1000 -> 40.230385 | ... O31: =O41/O56*1000 -> 41.458596 | P31: =P41/P48*1000 -> 41.458596
C32: 目标 | D32: =D42/D57*1000 -> 36.427791 | E32: =E42/E57*1000 -> 36.572572 | F32: =F42/F57*1000 -> 36.889363 | G32: =G42/G57*1000 -> 37.276185 | H32: =H42/H57*1000 -> 39.636785 | I32: =I42/I57*1000 -> 38.804808 | J32: =J42/J57*1000 -> 39.491168 | K32: =K42/K57*1000 -> 40.289992 | ... N32: =N42/N57*1000 -> 39.362137 | O32: 39.975046 | P32: =O32 -> 39.975046
C33: 26年 | D33: =D43/D58*1000 -> 37.546833 | E33: =E43/E58*1000 -> 39.217927 | F33: =F43/F58*1000 -> 46.396974 | G33: =G43/G58*1000 -> 39.919587 | H33: =H43/H58*1000 -> 42.632061 | I33: =I43/I58*1000 -> 39.179647 | J33: =J43/J58*1000 -> 39.314599 | K33: =K43/K58*1000 -> 39.686948 | ... P33: =P43/P58*1000 -> 38.247101
B34: 累计单台完成率 | D34: =2-D33/D32 -> 0.96928055 | E34: =2-E33/E32 -> 0.92766833 | F34: =2-F33/F32 -> 0.74226687 | G34: =2-G33/G32 -> 0.92908604 | H34: =2-H33/H32 -> 0.92443191 | I34: =2-I33/I32 -> 0.9903404 | J34: =2-J33/J32 -> 1.0044711 | K34: =2-K33/K32 -> 1.0149676 | ... O34: =2-O33/O32 -> 1.0432256 | P34: =O34 -> 1.0432256
B35: 累计单台同期优化率 | D35: =(D31-D33)/D31 -> -0.071166926 | E35: =(E31-E33)/E31 -> -0.11550174 | F35: =(F31-F33)/F31 -> -0.26923512 | G35: =(G31-G33)/G31 -> -0.1264936 | H35: =(H31-H33)/H31 -> -0.20808408 | I35: =(I31-I33)/I31 -> -0.036107402 | J35: =(J31-J33)/J31 -> -0.03493838 | K35: =(K31-K33)/K31 -> -0.0201027 | ... P35: =(P31-P33)/P31 -> 0.0774627
B36: 累计费用额 | D36: =D43 -> 1778.218 | E36: =E43 -> 3527.7702 | F36: =F43 -> 5240.7702 | G36: =G43 -> 6141.5486 | H36: =H43 -> 7967.5486 | I36: =I43 -> 9406.1321 | J36: =J43 -> 11070.087 | K36: =K43 -> 12722.723 | ... O36: =O43 -> 19840.913
B37: 费用金额 | C37: 同期 | D37: 1702.4888 | E37: 1623.6996 | F37: 1825.8462 | G37: 1591.5968 | H37: 1866.987 | I37: 1737.9 | J37: 1637.4123 | K37: 1533.5455 | L37: 1597.8553 | M37: 1443.0898 | N37: 1758.5061 | O37: 1502.3028 | P37: 19821.23
C38: 目标 | D38: 1838.2556 | E38: 1852.3924 | F38: 1892.6678 | G38: 1849.6673 | H38: 1928.8688 | I38: 1870.4326 | J38: 1859.2351 | K38: 1842.1673 | L38: 1948.6868 | M38: 1894.9246 | N38: 1861.9628 | O38: 1947.1505 | P38: 22586.412
C39: 26年 | D39: 1778.218 | E39: 1749.5522 | F39: 1713 | G39: 900.77836 | H39: 1826 | I39: =洗碗机6月!I237 -> 1438.5835 | J39: 1663.9548 | K39: 1652.6359 | L39: 1816.2017 | M39: 1764.1942 | N39: 1739.899 | O39: 1797.8953 | P39: 21453.77
C40: 自制费用额 | D40: 111.76974 | E40: 111.76974 | F40: 111.76974 | G40: 48.384889 | H40: 48.384889 | I40: 48.384889 | J40: 45.368222 | K40: 45.368222 | L40: 51.743222 | M40: 77.276555 | N40: 77.276555 | O40: 68.92201
B41: 费用金额（累计） | C41: 同期 | D41: =D37 -> 1702.4888 | E41: =D41+E37 -> 3326.1883 | F41: =E41+F37 -> 5152.0345 | G41: =F41+G37 -> 6743.6313 | H41: =G41+H37 -> 8610.6183 | I41: =H41+I37 -> 10348.518 | J41: =I41+J37 -> 11985.931 | K41: =J41+K37 -> 13519.476 | L41: =K41+L37 -> 15117.331 | ... O41: =N41+O37 -> 19821.23 | P41: =O41 -> 19821.23
C42: 目标 | D42: =D38 -> 1838.2556 | E42: =D42+E38 -> 3690.648 | F42: =E42+F38 -> 5583.3158 | G42: =F42+G38 -> 7432.9831 | H42: =G42+H38 -> 9361.8519 | I42: =H42+I38 -> 11232.284 | J42: =I42+J38 -> 13091.52 | K42: =J42+K38 -> 14933.687 | L42: =K42+L38 -> 16882.374 | ... O42: =N42+O38 -> 22586.412 | P42: =O42 -> 22586.412
C43: 26年 | D43: =D39 -> 1778.218 | E43: =D43+E39 -> 3527.7702 | F43: =E43+F39 -> 5240.7702 | G43: =F43+G39 -> 6141.5486 | H43: =G43+H39 -> 7967.5486 | I43: =H43+I39 -> 9406.1321 | J43: =I43+J39 -> 11070.087 | K43: =J43+K39 -> 12722.723 | L43: =K43+L39 -> 14538.924 | ... O43: =N43+O39 -> 19840.913 | P43: =O43 -> 19840.913
B44: 上涨因素 | C44: 项目 | D44: ①投资类折旧上涨3.38万； ②大件上涨111万元，玻璃二期100.4万元、叶轮自制5.73万元、消毒柜内胆2.63万元、烟机加强梁3.02万元 | E44: ①投资类折旧上涨3.38万； ②大件上涨111万元，玻璃二期100.4万元、叶轮自制5.73万元、消毒柜内胆2.63万元、烟机加强梁3.02万元 | F44: ①投资类折旧上涨3.38万； ②大件上涨111万元，玻璃二期100.4万元、叶轮自制5.73万元、消毒柜内胆2.63万元、烟机加强梁3.02万元 | G44: ①投资类折旧上涨6.94万 ②大件上涨48万元，玻璃二期18.83万元、叶轮自制13.91万元、消毒柜内胆12.63万元、烟机加强梁3.02万元 | H44: 投资类折旧上涨9.21万 ②大件上涨48万元，玻璃二期18.83万元、叶轮自制13.91万元、消毒柜内胆12.63万元、烟机加强梁3.02万元 | I44: ①投资类折旧上涨11.17万 ②大件上涨48万元，玻璃二期18.83万元、叶轮自制13.91万元、消毒柜内胆12.63万元、烟机加强梁3.02万元 | J44: ①投资类折旧上涨17.86万 ②大件上涨45万元，玻璃二期18.83万元、叶轮自制13.91万元、消毒柜内胆12.63万元 | K44: ①投资类折旧上涨20.65万 ②大件上涨45万元，玻璃二期18.83万元、叶轮自制13.91万元、消毒柜内胆12.63万元 | L44: ①投资类折旧上涨20.65万 ②大件上涨51万元，玻璃二期18.83万元、叶轮自制13.91万元、倒角玻璃6.38万元； | M44: ①投资类折旧上涨20.65万 ②大件上涨77万元，玻璃二期18.83万元、叶轮自制13.91万元、倒角玻璃6.38万元、低温丝印玻璃25.53万元 | N44: ①投资类折旧上涨20.65万 ②大件上涨77万元，玻璃二期18.83万元、叶轮自制13.91万元、倒角玻璃6.38万元、低温丝印玻璃25.53万元 | O44: ①投资类折旧上涨19.7万； ②大件上涨77万元，玻璃二期18.83万元、叶轮自制13.91万元、倒角玻璃6.38万元、低温丝印玻璃25.53万元 | P44: /
C45: 金额 | D45: 115.15272 | E45: 115.15272 | F45: 115.15272 | G45: 55.328649 | H45: 57.599119 | I45: 59.558535 | J45: 63.232502 | K45: 66.02085 | L45: 72.39585 | M45: 97.929184 | N45: 97.929184 | O45: 88.626362 | P45: =SUM(D45:O45) -> 1004.0784
B46: 下降因素 | C46: 项目 | D46: 1.人工降28万元：新增省人11人降10.83万：DFX2人、自动化8人、组织架构1人； 2.修理降5.82万元：新增1个项目钻磨线替代水刀降1.6万元； 3.其他降费13万元：新增9个项目降13万元 | E46: 1.人工降33万元：新增省人3人降5万：DFX1人；自动化2人；提效收益3万 2.能源降2.5万元：玻璃厂新增3条降费措施降2.5万元； 3.修理降5.82万元 4.其他降费13万元 | F46: 1.人工降26万元：新增省人3人降2.5万：DFX1人；简易自动化2人 2.能源降8万元：新增光伏项目降费5万元 3.修理降5.82万元 4..其他降费13万元 | G46: 1.人工降35万元：新增省人3人降2.5万：自动化3人； 2.能源降20万元：新增玻璃厂集中钢化项目降费9.5万元，前工序双拉伸降3.4万元； 3.修理降6.95万元：新增玻璃厂老员工代替实习生网板降费1.2万元； 4..其他降费13万元 | H46: 1.人工降36万元：新增省人4人降3.3万：DFX1人、精益1人、拉通模具2人； 2.能源降21万元：新增前处理二合一加工费项目 3.修理降4.6万元 4..其他降费13万元 | I46: 1.人工降44万元：新增省人4人降3.3万：简易自动化1人、自动化3人； 2.能源降27万元：新增前工序及玻璃厂提效减班次项目降6万元 3.修理降5.78万元,：新增激光切割替代水刀降费3.5万元 4..其他降费13万元 | J46: 1.人工降49万元：新增省人2人降1.6万：自动化2人 2.能源降28万元：新增激光切割降水费月降0.2万元； 3.修理降5.78万元, 4.其他降费13万元 | K46: 1.人工降57万元：新增省人3人降8.3万：DFX1人、精益2人、自动化10人 2.能源降28万元 3.修理降5.25万元 4.其他降费13万元 | L46: 1.人工降60万元：新增省人9人降5.8万：自动化7人、拉通模具2人 2.能源降28万元 3.修理降8.5万元：新增备件降费3.25万元； 4..其他降费19万元：新增公寓班车降费6.25万元 | M46: 1.人工降60万元 2.能源降28万元 3.修理降8.5万元： 4..其他降费19万元 | N46: 1.人工降60万元 2.能源降28万元 3.修理降8.5万元： 4..其他降费19万元 | O46: 1.人工降60万元 2.能源降28万元 3.修理降11.5万元：新增网板切换降费2万元； 4..其他降费19万元 | P46: /
C47: 金额 | D47: =#REF! -> #REF! | E47: =#REF! -> #REF! | F47: =#REF! -> #REF! | G47: =#REF! -> #REF! | H47: =#REF! -> #REF! | I47: =#REF! -> #REF! | J47: =#REF! -> #REF! | K47: =#REF! -> #REF! | ... O47: =#REF! -> #REF! | P47: =SUM(D47:O47) -> #REF!
A48: 单 | B48: 定单量 | C48: 同期 | D48: 48570 | E48: 46039 | F48: 46330 | G48: 49360 | H48: 53704 | I48: 29664 | J48: 41857 | K48: 31977 | L48: 28268 | M48: 26211 | N48: 34024 | O48: 42093 | P48: 478097
C49: 目标 | D49: 50463 | E49: 50450 | F49: 50440 | G49: 48050 | H49: 36788 | I49: 53265 | J49: 42049 | K49: 39150 | L49: 53732 | M49: 48548 | N49: 51408 | O49: 40676 | P49: 565019
C50: 26年 | D50: 47360 | E50: 42593 | F50: 23002 | G50: 40893 | H50: 33043 | I50: =洗碗机6月!E4 -> 53186 | J50: 41500 | K50: 39000.001 | L50: 54085 | M50: 49968 | N50: 51936 | O50: 42190 | P50: =SUM(D50:O50) -> 518756
C51: 增幅 | D51: =(D50-D48)/D48 -> -0.024912497 | E51: =(E50-E48)/E48 -> -0.074849584 | F51: =(F50-F48)/F48 -> -0.50351824 | G51: =(G50-G48)/G48 -> -0.17153566 | H51: =(H50-H48)/H48 -> -0.38471995 | I51: =(I50-I48)/I48 -> 0.79294768 | J51: =(J50-J48)/J48 -> -0.0085290393 | K51: =(K50-K48)/K48 -> 0.21962664 | ... P51: =(P50-P48)/P48 -> 0.085043414
B52: 定单量 | C52: 同期 | D52: 48571 | E52: 46033 | F52: 46337 | G52: 49363 | H52: 53704 | I52: 29664 | J52: 41857 | K52: 31977 | L52: 28268 | M52: 26211 | N52: 34024 | O52: 42093 | P52: =SUM(D52:O52) -> 478102
C53: 目标 | D53: 50463 | E53: 50446 | F53: 50440 | G53: 48050 | H53: 36788 | I53: 53265 | J53: 42049 | K53: 39150 | L53: 53732 | M53: 48548 | N53: 51408 | O53: 40676 | P53: =SUM(D53:O53) -> 565015
C54: 26年 | D54: 47360 | E54: 42593 | F54: 23500 | G54: 48050 | H54: 36788 | I54: 53265 | J54: 42049 | K54: 39150 | L54: 53732 | M54: 48548 | N54: 51408 | O54: 40676 | P54: =SUM(D54:O54) -> 527119
C55: 增幅 | D55: =(D54-D52)/D52 -> -0.024932573 | E55: =(E54-E52)/E52 -> -0.074728999 | F55: =(F54-F52)/F52 -> -0.49284589 | G55: =(G54-G52)/G52 -> -0.02659887 | H55: =(H54-H52)/H52 -> -0.31498585 | I55: =(I54-I52)/I52 -> 0.79561084 | J55: =(J54-J52)/J52 -> 0.0045870464 | K55: =(K54-K52)/K52 -> 0.22431748 | ... P55: =(P54-P52)/P52 -> 0.10252415
B56: 定单量（累计） | C56: 同期 | D56: =D48 -> 48570 | E56: =D56+E48 -> 94609 | F56: =E56+F48 -> 140939 | G56: =F56+G48 -> 190299 | H56: =G56+H48 -> 244003 | I56: =H56+I48 -> 273667 | J56: =I56+J48 -> 315524 | K56: =J56+K48 -> 347501 | L56: =K56+L48 -> 375769 | ... O56: =N56+O48 -> 478097 | P56: =O56 -> 478097
C57: 目标 | D57: =D49 -> 50463 | E57: =D57+E49 -> 100913 | F57: =E57+F49 -> 151353 | G57: =F57+G49 -> 199403 | H57: =G57+H49 -> 236191 | I57: =H57+I49 -> 289456 | J57: =I57+J49 -> 331505 | K57: =J57+K49 -> 370655 | L57: =K57+L49 -> 424387 | ... O57: =N57+O49 -> 565019 | P57: =O57 -> 565019
C58: 26年 | D58: =D50 -> 47360 | E58: =D58+E50 -> 89953 | F58: =E58+F50 -> 112955 | G58: =F58+G50 -> 153848 | H58: =G58+H50 -> 186891 | I58: =H58+I50 -> 240077 | J58: =I58+J50 -> 281577 | K58: =J58+K50 -> 320577 | L58: =K58+L50 -> 374662 | ... O58: =N58+O50 -> 518756 | P58: =O58 -> 518756
C59: 增幅 | D59: =(D58-D56)/D56 -> -0.024912497 | E59: =(E58-E56)/E56 -> -0.049213077 | F59: =(F58-F56)/F56 -> -0.19855398 | G59: =(G58-G56)/G56 -> -0.19154594 | H59: =(H58-H56)/H56 -> -0.2340627 | I59: =(I58-I56)/I56 -> -0.12274041 | J59: =(J58-J56)/J56 -> -0.10758928 | K59: =(K58-K56)/K56 -> -0.077478911 | ... P59: =(P58-P56)/P56 -> 0.085043414
B60: 标准台（累计） | C60: 同期 | D60: =D52 -> 48571 | E60: =D60+E52 -> 94604 | F60: =E60+F52 -> 140941 | G60: =F60+G52 -> 190304 | H60: =G60+H52 -> 244008 | I60: =H60+I52 -> 273672 | J60: =I60+J52 -> 315529 | K60: =J60+K52 -> 347506 | L60: =K60+L52 -> 375774 | ... O60: =N60+O52 -> 478102 | P60: =O60 -> 478102
C61: 目标 | D61: =D53 -> 50463 | E61: =D61+E53 -> 100909 | F61: =E61+F53 -> 151349 | G61: =F61+G53 -> 199399 | H61: =G61+H53 -> 236187 | I61: =H61+I53 -> 289452 | J61: =I61+J53 -> 331501 | K61: =J61+K53 -> 370651 | L61: =K61+L53 -> 424383 | ... O61: =N61+O53 -> 565015 | P61: =O61 -> 565015
C62: 26年 | D62: =D54 -> 47360 | E62: =D62+E54 -> 89953 | F62: =E62+F54 -> 113453 | G62: =F62+G54 -> 161503 | H62: =G62+H54 -> 198291 | I62: =H62+I54 -> 251556 | J62: =I62+J54 -> 293605 | K62: =J62+K54 -> 332755 | L62: =K62+L54 -> 386487 | ... O62: =N62+O54 -> 527119 | P62: =O62 -> 527119
C63: 增幅 | D63: =(D62-D60)/D60 -> -0.024932573 | E63: =(E62-E60)/E60 -> -0.049162826 | F63: =(F62-F60)/F60 -> -0.19503196 | G63: =(G62-G60)/G60 -> -0.15134206 | H63: =(H62-H60)/H60 -> -0.18735861 | I63: =(I62-I60)/I60 -> -0.080812067 | J63: =(J62-J60)/J60 -> -0.069483312 | K63: =(K62-K60)/K60 -> -0.042448188 | ... P63: =(P62-P60)/P60 -> 0.10252415
A64: 工作日 | C64: 同期 | D64: 22 | E64: 20 | F64: 20 | G64: 21 | H64: 21 | I64: 12 | J64: 19 | K64: 21 | L64: 22 | M64: 21 | N64: 20 | O64: 18 | P64: 237
C65: 26年 | D65: 20 | E65: 20 | F65: 20 | G65: 21 | H65: 14 | I65: =洗碗机6月!E5 -> 21 | J65: 17 | K65: 15 | L65: 21 | M65: 18 | N65: 20 | O65: 15 | P65: =SUM(D65:O65) -> 222
A66: 用人 | C66: 同期 | D66: 329.5 | E66: 325.5 | F66: 334 | G66: 334 | H66: 341 | I66: 356.79 | J66: 333.5 | K66: 228.33 | L66: 227 | M66: 227 | N66: 284 | O66: 344 | P66: =AVERAGE(D66:O66) -> 305.385
C67: 26年 | D67: 347 | E67: 319 | F67: 247 | G67: 355.5 | H67: 358.5 | I67: 356.5 | J67: 356.5 | K67: 363.5 | L67: 364.5 | M67: 362.5 | N67: 363.5 | O67: 364.5 | P67: =AVERAGE(D67:O67) -> 346.54167
A68: 人效（自然台） | C68: 同期 | D68: =D52/D64/D66 -> 6.7003725 | E68: =E52/E64/E66 -> 7.0711214 | F68: =F52/F64/F66 -> 6.9366766 | G68: =G52/G64/G66 -> 7.0377816 | H68: =H52/H64/H66 -> 7.4995112 | I68: =I52/I64/I66 -> 6.9284453 | J68: =J52/J64/J66 -> 6.6056972 | K68: =K52/K64/K66 -> 6.668919 | ... P68: =P52/P64/P66 -> 6.6057862
C69: 26年 | D69: =D54/D65/D67 -> 6.8242075 | E69: =E54/E65/E67 -> 6.6760188 | F69: =F54/F65/F67 -> 4.757085 | G69: =G54/G65/G67 -> 6.4362735 | H69: =H54/H65/H67 -> 7.329747 | I69: =I54/I65/I67 -> 7.1148067 | J69: =J54/J65/J67 -> 6.9382064 | K69: =K54/K65/K67 -> 7.1801926 | ... P69: =P54/P65/P67 -> 6.8517299
C70: 增幅 | D70: =(D69/D68)-1 -> 0.018481813 | E70: =(E69/E68)-1 -> -0.055875514 | F70: =(F69/F68)-1 -> -0.31421266 | G70: =(G69/G68)-1 -> -0.085468418 | H70: =(H69/H68)-1 -> -0.022636713 | I70: =(I69/I68)-1 -> 0.026898004 | J70: =(J69/J68)-1 -> 0.050336741 | K70: =(K69/K68)-1 -> 0.076665127 | ... P70: =(P69/P68)-1 -> 0.037231562
A71: 当月单台差异 | D71: =D25-D26 -> -1.1190418 | E71: =E25-E26 -> -4.39 | F71: =F25-F26 -> -36.951455 | G71: =G25-G26 -> 16.440835 | H71: =H25-H26 -> -2.8293146 | I71: =I25-I26 -> 8.0674414 | J71: =J25-J26 -> 4.1206202 | K71: =K25-K26 -> 4.6788055 | ... O71: =O25-O26 -> 5.255511
A72: 当月差异金额 | D72: =D71*D54 -> -52997.821 | E72: =E71*E54 -> -186983.27 | F72: =F71*F54 -> -868359.19 | G72: =G71*G54 -> 789982.12 | H72: =H71*H54 -> -104084.82 | I72: =I71*I54 -> 429712.27 | J72: =J71*J54 -> 173267.96 | K72: =K71*K54 -> 183175.24 | ... O72: =O71*O54 -> 213773.16
A73: 累计单台差异 | D73: =D32-D33 -> -1.1190418 | E73: =E32-E33 -> -2.6453552 | F73: =F32-F33 -> -9.5076111 | G73: =G32-G33 -> -2.6434019 | H73: =H32-H33 -> -2.9952762 | I73: =I32-I33 -> -0.37483885 | J73: =J32-J33 -> 0.17656867 | K73: =K32-K33 -> 0.60304394 | ... O73: =O32-O33 -> 1.727945
A74: 累计差异金额 | D74: =D73*D62 -> -52997.821 | E74: =E73*E62 -> -237957.64 | F74: =F73*F62 -> -1078667 | G74: =G73*G62 -> -426917.33 | H74: =H73*H62 -> -593936.31 | I74: =I73*I62 -> -94292.961 | J74: =J73*J62 -> 51841.444 | K74: =K73*K62 -> 200665.89 | ... O74: =O73*O62 -> 910832.62
A75: 折旧 | C75: 同期 | D75: 546.80648 | E75: 512.30486 | F75: 561.50898 | G75: 550.63785 | H75: 579.549 | I75: 564.00175 | J75: 578.95374 | K75: 577.35715 | L75: 564.65131 | M75: 370.28689 | N75: 546.43939 | O75: 562 | P75: =SUM(D75:O75) -> 6514.4974
C76: 26年 | D76: 577.48038 | E76: 536.48201 | F76: 581.85982 | G76: 568.23135 | H76: 433.31502 | I76: 569.22644 | J76: 599.40401 | K76: 599.6829 | L76: 585.57916 | M76: 601.43585 | N76: 590.72093 | O76: 613.63186 | P76: =SUM(D76:O76) -> 6857.0497
C77: 新增投资折旧 | D77: =D76-D75 -> 30.6739 | E77: =E76-E75 -> 24.177146 | F77: =F76-F75 -> 20.350843 | G77: =G76-G75 -> 17.593502 | H77: =H76-H75 -> -146.23398 | I77: =I76-I75 -> 5.2246908 | J77: =J76-J75 -> 20.450268 | K77: =K76-K75 -> 22.325757 | ... O77: =O76-O75 -> 51.631863 | P77: =SUM(D77:O77) -> 342.55234
A78: 日均排产 | C78: 同期 | D78: =D48/D64 -> 2207.7273 | E78: =E48/E64 -> 2301.95 | F78: =F48/F64 -> 2316.5 | G78: =G48/G64 -> 2350.4762 | H78: =H48/H64 -> 2557.3333 | I78: =I48/I64 -> 2472 | J78: =J48/J64 -> 2203 | K78: =K48/K64 -> 1522.7143 | ... P78: =P48/P64 -> 2017.2869
C79: 26年 | D79: =D50/D65 -> 2368 | E79: =E50/E65 -> 2129.65 | F79: =F50/F65 -> 1150.1 | G79: =G50/G65 -> 1947.2857 | H79: =H50/H65 -> 2360.2143 | I79: =I50/I65 -> 2532.6667 | J79: =J50/J65 -> 2441.1765 | K79: =K50/K65 -> 2600.0001 | ... P79: =P50/P65 -> 2336.7387
A80: 一线 | C80: 同期 | D80: 218 | E80: 218 | F80: 209 | G80: 208 | H80: 226 | I80: 239 | J80: 222 | K80: 133 | L80: 132 | M80: 132 | N80: 182 | O80: 234 | P80: =SUM(D80:O80) -> 2353
C81: 26年 | D81: 237 | E81: 215 | F81: 132 | G81: 222 | H81: 261 | I81: =洗碗机6月!E6 -> 261
A82: 辅助 | C82: 同期 | D82: 87 | E82: 85 | F82: 94 | G82: 93 | H82: 93 | I82: 91 | J82: 85 | K82: 70 | L82: 70 | M82: 70 | N82: 77 | O82: 85 | P82: =SUM(D82:O82) -> 1000
C83: 26年 | D83: 85 | E83: 82 | F83: 69 | G83: 79 | H83: 82 | I83: =洗碗机6月!E8 -> 82
A84: 一线＋辅助 | C84: 同期 | D84: =D82+D80 -> 305 | E84: =E82+E80 -> 303 | F84: =F82+F80 -> 303 | G84: =G82+G80 -> 301 | H84: =H82+H80 -> 319 | I84: =I82+I80 -> 330 | J84: =J82+J80 -> 307 | K84: =K82+K80 -> 203 | ... P84: =P82+P80 -> 3353
C85: 26年 | D85: =D83+D81 -> 322 | E85: =E83+E81 -> 297 | F85: =F83+F81 -> 201 | G85: =G83+G81 -> 301 | H85: =H83+H81 -> 343 | I85: =I83+I81 -> 343
A86: 累计用人 | C86: 同期 | D86: =D84 -> 305 | E86: =D86+E84 -> 608 | F86: =E86+F84 -> 911 | G86: =F86+G84 -> 1212 | H86: =G86+H84 -> 1531 | I86: =H86+I84 -> 1861 | J86: =I86+J84 -> 2168 | K86: =J86+K84 -> 2371 | L86: =K86+L84 -> 2573 | ... P86: =O86+P84 -> 6706
C87: 26年 | D87: =D85 -> 322 | E87: =D87+E85 -> 619 | F87: =E87+F85 -> 820 | G87: =F87+G85 -> 1121 | H87: =G87+H85 -> 1464 | I87: =H87+I85 -> 1807
A88: UPPH | C88: 同期 | D88: =D48/D84/D64/7.5 -> 0.96512668 | E88: =E48/E84/E64/7.5 -> 1.0129593 | F88: =F48/F84/F64/7.5 -> 1.0193619 | G88: =G48/G84/G64/7.5 -> 1.0411855 | H88: =H48/H84/H64/7.5 -> 1.0688959 | I88: =I48/I84/I64/7.5 -> 0.99878788 | J88: =J48/J84/J64/7.5 -> 0.9567861 | K88: =K48/K84/K64/7.5 -> 1.0001407 | ... O88: =O48/O84/O64/7.5 -> 0.97742947 | P88: =P48/P84/20/7.5 -> 0.95058555
C89: 26年 | D89: =D50/D85/D65/7.5 -> 0.9805383 | E89: =E50/E85/E65/7.5 -> 0.95607183 | F89: =F50/F85/F65/7.5 -> 0.76291874 | G89: =G50/G85/G65/7.5 -> 0.86258503 | H89: =H50/H85/H65/7.5 -> 0.91747883 | I89: =I50/I85/I65/7.5 -> 0.98451571
C90: 增幅 | D90: =(D89-D88)/D88 -> 0.0159685 | E90: =(E89-E88)/E88 -> -0.056159677 | F90: =(F89-F88)/F88 -> -0.25157227 | G90: =(G89-G88)/G88 -> -0.17153566 | H90: =(H89-H88)/H88 -> -0.14165742 | I90: =(I89-I88)/I88 -> -0.014289488
A91: UPPH(累计） | C91: 同期 | D91: =D56/D86/D64/7.5 -> 0.96512668 | E91: =E56/E86/E64/7.5 -> 1.0373794 | F91: =F56/F86/F64/7.5 -> 1.0313868 | G91: =G56/G86/G64/7.5 -> 0.99690398 | H91: =H56/H86/H64/7.5 -> 1.0119042 | I91: =I56/I86/20/7.5 -> 0.98035823 | J91: =J56/J86/J64/7.5 -> 1.0213116 | K91: =K56/K86/K64/7.5 -> 0.93055907 | L91: =L56/L86/L64/7.5 -> 0.88510994 | M91: =M56/M86/M64/7.5 -> 0.91973116 | N91: =N56/N86/N64/7.5 -> 0.95803999 | O91: =O56/O86/O64/7.5 -> 1.0562062 | P91: =P56/P86/20/7.5 -> 0.47529277
C92: 26年 | D92: =D58/D87/D65/7.5 -> 0.9805383 | E92: =E58/E87/E65/7.5 -> 0.96879914 | F92: =F58/F87/F65/7.5 -> 0.91833333 | G92: =G58/G87/G65/7.5 -> 0.87137618 | H92: =H58/H87/19/7.5 -> 0.89584412 | I92: =I58/I87/I65/7.5 -> 0.84355197
C93: 增幅 | D93: =(D92-D91)/D91 -> 0.0159685 | E93: =(E92-E91)/E91 -> -0.066109129 | F93: =(F92-F91)/F91 -> -0.10961302 | G93: =(G92-G91)/G91 -> -0.12591764 | H93: =(H92-H91)/H91 -> -0.11469477 | I93: =(I92-I91)/I91 -> -0.13954721

Sheet 洗碗机1月
A1: 总结：1月洗碗机单台制造费同比恶化2.43欧，同比恶化7%，额恶化12万欧 固定： 折旧单台恶化0.65欧，额差3.16万欧 变动： 6666021502、6666021503、6666021505、6666021506去年发生的总费用为1万欧元，今年发生的费用为8万欧元，单台恶化1.48 工资上涨：白领工资下降1%，蓝领工资上涨7%
A2: 维度 | B2: 指标 | C2: 25年实际 | D2: 26年预算 | E2: 预算差异 | F2: 26年实际 | G2: 实际比同期差异 | H2: 制造费差额 | I2: 差异原因
A4: 单 | B4: 产量 | C4: 48570 | D4: 50463 | E4: =D4-C4 -> 1893 | F4: 47360 | G4: =F4-C4 -> -1210 | I4: =(F4-D4)/D4 -> -0.061490597
A5: 时 | B5: 工作天数 | C5: 22 | D5: 20 | E5: =D5-C5 -> -2 | F5: 20 | G5: =F5-C5 -> -2
A6: 人 | B6: 直接人工 | C6: 218 | D6: 244 | E6: =D6-C6 -> 26 | F6: 237 | G6: =F6-C6 -> 19
B7: 人工工资 | C7: =E47/C6*1000 -> 1662.2265 | D7: =G47/D6*1000 -> 1650.6253 | E7: =D7-C7 -> -11.60119 | F7: =I47/F6*1000 -> 1509.3644 | G7: =F7-C7 -> -152.86208 | H7: =F7/C7-1 -> -0.091962246
B8: 间接人工 | C8: 87 | D8: 85 | E8: =D8-C8 -> -2 | F8: 85 | G8: =F8-C8 -> -2
B9: 间接人工工资 | C9: =E127/C8*1000 -> 1846.7721 | D9: =G127/D8*1000 -> 1841.488 | E9: =D9-C9 -> -5.2840483 | F9: =(I127+I124)/F8*1000 -> 2233.9256 | G9: =F9-C9 -> 387.15358 | H9: =F9/C9-1 -> 0.20963799
B10: 白领人数 | C10: 25 | D10: 27 | E10: =D10-C10 -> 2 | F10: 25 | G10: 0.1
B11: 白领人工工资 | C11: =(E130+E131)/C10*1000 -> 4248.7816 | D11: =(G130/D10*1000) -> 3384.9868 | E11: =D11-C11 -> -863.79476 | F11: =(I130+I131)/F10*1000 -> 3865.3176 | G11: =F11-C11 -> -383.464 | H11: =F11/C11-1 -> -0.090252697
A12: 效 | B12: UPPH | C12: =C4/C6/C5/7.5 -> 1.3502919 | D12: =D4/D6/D5/7.5 -> 1.3787705 | E12: =D12-C12 -> 0.028478582 | F12: =F4/F6/F5/7.5 -> 1.3322082 | G12: =F12-C12 -> -0.018083752
A13: 费 | B13: 单台制造费 | C13: =SUM(C14:C26) -> 35.046041 | D13: =SUM(D14:D26) -> 36.427791 | E13: =SUM(E14:E26) -> 1.3817498 | F13: =SUM(F14:F26) -> 37.48 | G13: =F13-C13 -> 2.4339586 | H13: =G13*$F$4 -> 115272.28
B14: 折旧 | C14: 11.25788 | D14: 11.443639 | E14: =D14-C14 -> 0.1857597 | F14: 11.91 | G14: =F14-C14 -> 0.65212028 | H14: =G14*$F$4 -> 30884.417
B15: 运营费 | C15: 0.97865619 | D15: 1.1529596 | E15: =D15-C15 -> 0.17430338 | F15: 1.26 | G15: =F15-C15 -> 0.28134381 | H15: =G15*$F$4 -> 13324.443
B16: 存货跌价准备 | C16: 0.051794898 | D16: 0.17894222 | E16: =D16-C16 -> 0.12714732 | F16: -0.55 | G16: =F16-C16 -> -0.6017949 | H16: =G16*$F$4 -> -28501.006
B17: 固定能源费 | C17: 0.14524655 | D17: 0.10814454 | E17: =D17-C17 -> -0.037102006 | F17: 0.1 | G17: =F17-C17 -> -0.045246546 | H17: =G17*$F$4 -> -2142.8764
B18: 间接人工成本-辅助人员 | C18: 4.2832239 | D18: 3.8592425 | E18: =D18-C18 -> -0.42398146 | F18: 4.99 | G18: =F18-C18 -> 0.70677606 | H18: =G18*$F$4 -> 33472.914
B19: 固定人工-白领 | C19: 2.7653736 | D19: 2.1120424 | E19: =D19-C19 -> -0.65333118 | F19: 2.43 | G19: =F19-C19 -> -0.33537358 | H19: =G19*$F$4 -> -15883.293
B20: 半固定-班车/工作服 | C20: 2.193911 | D20: 3.6270077 | E20: =D20-C20 -> 1.4330967 | F20: 3.47 | G20: =F20-C20 -> 1.276089 | H20: =G20*$F$4 -> 60435.576 | I20: 维修保养费用4个科目上升1.48
B21: 直接人工 | C21: 9.7168881 | D21: 9.6071653 | E21: =D21-C21 -> -0.1097228 | F21: 9.53 | G21: =F21-C21 -> -0.18688806 | H21: =G21*$F$4 -> -8851.0186
B22: 可回收废料 | C22: 0.47761771 | D22: 0.5438747 | E22: =D22-C22 -> 0.066256982 | F22: 0.38 | G22: =F22-C22 -> -0.097617714 | H22: =G22*$F$4 -> -4623.1749
B23: 生产耗用品 | C23: 0.25141257 | D23: 0.33153003 | E23: =D23-C23 -> 0.080117461 | F23: 0.2 | G23: =F23-C23 -> -0.051412571 | H23: =G23*$F$4 -> -2434.8994
B24: 废品回收 | C24: -1.1989953 | D24: -1.09399 | E24: =D24-C24 -> 0.1050053 | F24: -1.19 | G24: =F24-C24 -> 0.0089952853 | H24: =G24*$F$4 -> 426.01671
B25: 变动能源费 | C25: 0.52219925 | D25: 0.76326767 | E25: =D25-C25 -> 0.24106842 | F25: 0.46 | G25: =F25-C25 -> -0.062199255 | H25: =G25*$F$4 -> -2945.7567
B26: 园区分摊费用 | C26: 3.6008332 | D26: 3.7939652 | E26: =D26-C26 -> 0.19313194 | F26: 4.49 | G26: =F26-C26 -> 0.88916679 | H26: =G26*$F$4 -> 42110.939
B27: IT Expense-Internal Charge Out | C27: 2.0598917 | D27: 1.7973014 | E27: -0.1274777 | G27: =(F27/C27)-1 -> -1 | H27: =G27*$C$4 -> -48570
B28: Association dues | C28: 0.10364806 | D28: 0.12931195 | E28: 0.24760611 | G28: =(F28/C28)-1 -> -1 | H28: =G28*$C$4 -> -48570
B29: G&A | C29: 1.4372934 | D29: 1.8673518 | E29: 0.299214 | G29: =(F29/C29)-1 -> -1 | H29: =G29*$C$4 -> -48570
A30: 类型 | B30: 科目编号 | C30: 科目（英文） | D30: 科目（中文） | E30: K€ | F30: 同期台数 | G30: 46330 | H30: 预算台数 | I30: 50440 | J30: 实际台数 | K30: 42593
E31: 25年实际制造费 | F31: 25年实际单台 | G31: 26年预测制造费 | H31: 26年预测单台 | I31: 26年实际制造费 | J31: 26年实际单台 | K31: 同期与实际单台差 | L31: 26年预算与25年实际单台差 | M31: 26年实际与25年预算单台差 | N31: 与预算差异分析 | O31: 与同期差分析
A32: 折旧 | B32: 6666110101 | C32: 6666110101 Depreciation of buildings | D32: 建筑物折旧 | E32: 29.90899 | F32: 0.61579144 | G32: 32.511068 | H32: 0.64425556 | I32: 32.52614 | J32: 0.68678505 | K32: =J32-F32 -> 0.070993606 | L32: =H32-F32 -> 0.028464117 | M32: =J32-H32 -> 0.04252949
B33: 6666110106 | C33: 6666110106 Depreciation of R&D facilities | D33: 研发设施折旧 | E33: 0 | F33: 0 | G33: 0 | H33: 0 | I33: 0 | J33: 0 | K33: =J33-F33 -> 0 | L33: =H33-F33 -> 0 | M33: =J33-H33 -> 0
B34: 6666110107 | C34: 6666110107 Depreciation of mold | D34: 模具折旧 | E34: 210.86474 | F34: 4.3414606 | G34: 228.97844 | H34: 4.5375511 | I34: 224.42191 | J34: 4.7386383 | K34: =J34-F34 -> 0.39717773 | L34: =H34-F34 -> 0.19609052 | M34: =J34-H34 -> 0.20108721 | P34: 1.17
B35: 6666110110 | C35: 6666110110 Depreciation-Plant & Machinery | D35: 厂房及机械折旧 | E35: 288.50449 | F35: 5.9399731 | G35: 297.92456 | H35: 5.9038218 | I35: 295.75794 | J35: 6.2448889 | K35: =J35-F35 -> 0.30491588 | L35: =H35-F35 -> -0.036151294 | M35: =J35-H35 -> 0.34106718
B36: 6666110112 | C36: 6666110112 Depreciation of Furniture & Fixture | D36: 家具及装置折旧 | E36: 7.3326631 | F36: 0.15097103 | G36: 15.246977 | H36: 0.3021417 | I36: 8.94279 | J36: 0.1888258 | K36: =J36-F36 -> 0.037854769 | L36: =H36-F36 -> 0.15117066 | M36: =J36-H36 -> -0.1133159
B37: 6666110204 | C37: 6666110204 Amortization of license, trademarks and | D37: 许可证、商标及摊销 | E37: 0.058686667 | F37: 0.0012082904 | G37: 0.25252 | H37: 0.0050040624 | I37: 0.17412081 | J37: 0.0036765375 | K37: =J37-F37 -> 0.002468247 | L37: =H37-F37 -> 0.0037957719 | M37: =J37-H37 -> -0.0013275249
B38: 6666110207 | C38: 6666110207 Amortization of Software | D38: 软件摊销 | E38: 8.2948964 | F38: 0.1707823 | G38: 2.5668129 | H38: 0.050865246 | I38: 2.34991 | J38: 0.049618032 | K38: =J38-F38 -> -0.12116427 | L38: =H38-F38 -> -0.11991706 | M38: =J38-H38 -> -0.0012472143
B39: 6666110506 | C39: 6666110506 Amortization-Leasehold Improvement | D39: 租赁改良摊销 | E39: 1.164868 | F39: 0.023983282 | G39: 0 | H39: 0 | I39: 0 | J39: 0 | K39: =J39-F39 -> -0.023983282 | L39: =H39-F39 -> -0.023983282 | M39: =J39-H39 -> 0
B40: 6666110206 | C40: 6666110206 Amortization of Patents | D40: 专利摊销 | F40: 0 | H40: 0 | J40: 0 | K40: =J40-F40 -> 0 | L40: =H40-F40 -> 0 | M40: =J40-H40 -> 0
B41: FIX | C41: * CS_Depreciation | D41: * CS_折旧 | E41: 546.12934 | F41: 11.24417 | G41: 577.48038 | H41: 11.443639 | I41: 564.17281 | J41: 11.912433 | K41: =J41-F41 -> 0.66826268 | L41: =H41-F41 -> 0.19946944 | M41: =J41-H41 -> 0.46879325
A42: 直接人工 | B42: 5001010205 | C42: 5001010205 Unemployment Insurance -blue collar-Dire | D42: 失业保险-蓝领-直接 | E42: 7.24866 | F42: 0.14924151 | G42: 8.3247335 | H42: 0.16496708 | I42: 7.61607 | J42: 0.16081229 | K42: =J42-F42 -> 0.011570782 | L42: =H42-F42 -> 0.015725569 | M42: =J42-H42 -> -0.0041547869
B43: 6666010380 | C43: 6666010380 Incentive | D43: 激励 | E43: -1.66916 | F43: -0.03436607 | G43: -21.806476 | H43: -0.43212802 | I43: -1.8209 | J43: -0.038448057 | K43: =J43-F43 -> -0.0040819878 | L43: =H43-F43 -> -0.39776195 | M43: =J43-H43 -> 0.39367996
B44: 6666010019 | C44: 6666010019 Payroll Taxes - Blue Collar Direct | E44: 57.92585 | F44: 1.1926261 | G44: 86.369111 | H44: 1.7115334 | I44: 64.67305 | J44: 1.3655627 | K44: =J44-F44 -> 0.1729366 | L44: =H44-F44 -> 0.5189073 | M44: =J44-H44 -> -0.3459707 | O44: 为什么蓝领工资税上涨(需要咨询人力） | P44: =I44/D4*1000 -> 1.2815934
B45: 6666010183 | C45: 6666010183 Overtime-Blue Collar-Direct | D45: 蓝领加班费-直接 | E45: 13.55408 | F45: 0.2790628 | G45: 0 | H45: 0 | I45: 10.50135 | J45: 0.22173459 | K45: =J45-F45 -> -0.05732821 | L45: =H45-F45 -> -0.2790628 | M45: =J45-H45 -> 0.22173459
B46: 6666010229 | C46: 6666010229 Staff Leaving Indemnity - Blue Collar Di | D46: 蓝领离职赔偿-直接 | E46: 31.74454 | F46: 0.65358328 | G46: 9.1664449 | H46: 0.18164685 | I46: 16.69101 | J46: 0.35245075 | K46: =J46-F46 -> -0.30113254 | L46: =H46-F46 -> -0.47193643 | M46: =J46-H46 -> 0.1708039
B47: 6666010188 | C47: 6666010188 Salary - Blue collar direct employees | D47: 蓝领直接员工工资 | E47: 362.36537 | F47: 7.4606829 | G47: 402.75257 | H47: 7.9811459 | I47: 357.71936 | J47: 7.5536744 | K47: =J47-F47 -> 0.092991499 | L47: =H47-F47 -> 0.52046301 | M47: =J47-H47 -> -0.42747151 | N47: 单台下降0.43，费用下降4.5万 | P47: =I47/I30*1000 -> 7.0919778
B48: 5102040406 | C48: 5102040406 Other revenue-Service/Secondment agreeme | D48: 其他收入-服务/派遣协议 | E48: 0 | F48: 0 | G48: 0 | H48: 0 | I48: 0 | J48: 0 | K48: =J48-F48 -> 0 | L48: =H48-F48 -> 0 | M48: =J48-H48 -> 0
B49: 6666010115 | C49: 6666010115 Salary-Blue collar direct employees-Accr | D49: 蓝领直接员工工资-应计 | E49: 0.78963 | F49: 0.016257566 | G49: 0 | H49: 0 | I49: -4.2657 | J49: -0.090075385 | K49: =J49-F49 -> -0.10633295 | L49: =H49-F49 -> -0.016257566 | M49: =J49-H49 -> -0.090075385
B50: VAR | C50: * CS_Direct Labour | D50: * CS_直接劳动 | E50: 471.95897 | F50: 9.7170881 | G50: 484.80638 | H50: 9.6071653 | I50: 451.11424 | J50: 9.5258196 | K50: =J50-F50 -> -0.19126849 | L50: =H50-F50 -> -0.10992286 | M50: =J50-H50 -> -0.081345635
A51: 可回收废料 | B51: 8701530201 | C51: 8701530201 Scrap-Raw Material - Managerial | D51: 废料-原材料-管理 | E51: 0 | F51: 0 | G51: 0 | H51: 0 | I51: 0 | J51: 0 | K51: =J51-F51 -> 0 | L51: =H51-F51 -> 0 | M51: =J51-H51 -> 0
B52: 6666050309 | C52: 6666050309 SFG scrap | D52: SFG废料 | E52: 11.07122 | F52: 0.22794359 | G52: 27.445549 | H52: 0.5438747 | I52: 6.0635 | J52: 0.12803809 | K52: =J52-F52 -> -0.099905493 | L52: =H52-F52 -> 0.31593111 | M52: =J52-H52 -> -0.4158366 | N52: 单台下降0.42，费用下降2.1万
B53: 6666050308 | C53: 6666050308 Raw material scrap | D53: 原材料废料 | E53: 12.13983 | F53: 0.24994503 | G53: 0 | H53: 0 | I53: 11.57396 | J53: 0.24439808 | K53: =J53-F53 -> -0.0055469451 | L53: =H53-F53 -> -0.24994503 | M53: =J53-H53 -> 0.24439808
B54: 6666050306 | C54: 6666050306 Finished goods scrap | D54: 成品废料 | E54: -0.01268 | F54: -0.0002610665 | G54: 0 | H54: 0 | I54: 0.58819 | J54: 0.012420339 | K54: =J54-F54 -> 0.012681406 | L54: =H54-F54 -> 0.0002610665 | M54: =J54-H54 -> 0.012420339
B55: VAR | C55: * CS_SCRAP_VARIABLE | D55: * CS_废料变量 | E55: 23.19837 | F55: 0.47762755 | G55: 27.445549 | H55: 0.5438747 | I55: =SUM(I51:I54) -> 18.22565 | J55: =SUM(J51:J54) -> 0.38485652 | K55: =J55-F55 -> -0.092771032 | L55: =H55-F55 -> 0.066247148 | M55: =J55-H55 -> -0.15901818
A56: 组织运营 | B56: 5102010151 | C56: 5102010151 Other Rev.-Interco-Epidemic problem comp | D56: 其他收入-内部公司-疫情问题补偿 | E56: 0 | F56: 0 | G56: 0 | H56: 0 | I56: 0 | J56: 0 | K56: =J56-F56 -> 0 | L56: =H56-F56 -> 0 | M56: =J56-H56 -> 0
B57: 5001010200 | C57: 5001010200 Cost of Manufacture - Raw Material | D57: 制造成本-原材料 | E57: 0.17197 | F57: 0.003540663 | G57: 0 | H57: 0 | I57: 0 | J57: 0 | K57: =J57-F57 -> -0.003540663 | L57: =H57-F57 -> -0.003540663 | M57: =J57-H57 -> 0
B58: 5001010201 | C58: 5001010201 Cost of Manufacture - Raw Material-Freig | D58: 制造成本-原材料-运费 | E58: 0.00056 | F58: 1.1529751e-05 | G58: 0 | H58: 0 | I58: 0 | J58: 0 | K58: =J58-F58 -> -1.1529751e-05 | L58: =H58-F58 -> -1.1529751e-05 | M58: =J58-H58 -> 0
B59: 5207000011 | C59: 5207000011 Gain of tangible asset disposal | D59: 有形资产处置收益 | E59: 0 | F59: 0 | G59: 0 | H59: 0 | I59: 0 | J59: 0 | K59: =J59-F59 -> 0 | L59: =H59-F59 -> 0 | M59: =J59-H59 -> 0
B60: 5207000012 | C60: 5207000012 Loss of tangible asset sold | D60: 出售有形资产损失 | E60: 0 | F60: 0 | G60: 0 | H60: 0 | I60: 0 | J60: 0 | K60: =J60-F60 -> 0 | L60: =H60-F60 -> 0 | M60: =J60-H60 -> 0
B61: 5207000022 | C61: 5207000022 Loss of intangible asset disposal | D61: 无形资产处置损失 | E61: 0 | F61: 0 | G61: 0 | H61: 0 | I61: 0 | J61: 0 | K61: =J61-F61 -> 0 | L61: =H61-F61 -> 0 | M61: =J61-H61 -> 0
B62: 5301060000 | C62: 5301060000 Other Income-Subsidy income | D62: 其他收入-补贴收入 | E62: 0 | F62: 0 | G62: 0 | H62: 0 | I62: 0 | J62: 0 | K62: =J62-F62 -> 0 | L62: =H62-F62 -> 0 | M62: =J62-H62 -> 0
B63: 5301999999 | C63: 5301999999 Non-operation revenue-Other | D63: 非经营收入-其他 | E63: 0 | F63: 0 | G63: 0 | H63: 0 | I63: 0 | J63: 0 | K63: =J63-F63 -> 0 | L63: =H63-F63 -> 0 | M63: =J63-H63 -> 0
B64: 5405030000 | C64: 5405030000 Other cost-others | D64: 其他成本-其他 | E64: 0.0094 | F64: 0.0001935351 | G64: 0 | H64: 0 | I64: 0 | J64: 0 | K64: =J64-F64 -> -0.0001935351 | L64: =H64-F64 -> -0.0001935351 | M64: =J64-H64 -> 0
B65: 5601050000 | C65: 5601050000 Non-Operating Expense - Penalty | D65: 非经营费用-罚款 | E65: 0 | F65: 0 | G65: 0 | H65: 0 | I65: 0 | J65: 0 | K65: =J65-F65 -> 0 | L65: =H65-F65 -> 0 | M65: =J65-H65 -> 0
B66: 5601050100 | C66: 5601050100 Non-operation Expense-Others | D66: 非经营费用-其他 | E66: 0.01682 | F66: 0.0003463043 | G66: 0 | H66: 0 | I66: 0 | J66: 0 | K66: =J66-F66 -> -0.0003463043 | L66: =H66-F66 -> -0.0003463043 | M66: =J66-H66 -> 0
B67: 5102040893 | C67: 5102040893 Other revenue-Charge out-Test Expense | D67: 其他收入-费用支出-测试费用 | E67: 0 | F67: 0 | H67: 0 | I67: 0 | J67: 0 | K67: =J67-F67 -> 0 | L67: =H67-F67 -> 0 | M67: =J67-H67 -> 0
B68: 5801000041 | C68: 5801000041 Previous year Sundry cost | D68: 去年杂项成本 | E68: 0 | F68: 0 | G68: 0 | H68: 0 | I68: 0 | J68: 0 | K68: =J68-F68 -> 0 | L68: =H68-F68 -> 0 | M68: =J68-H68 -> 0
B69: 6666010322 | C69: 6666010322 fuel allowance | D69: 燃料津贴 | E69: 2.19309 | F69: 0.045153181 | G69: 2.027405 | H69: 0.04017607 | I69: 1.46012 | J69: 0.03083219 | K69: =J69-F69 -> -0.014320991 | L69: =H69-F69 -> -0.0049771111 | M69: =J69-H69 -> -0.0093438804
B70: 6666020101 | C70: 6666020101 Entertainment | D70: 娱乐 | E70: 0 | F70: 0 | G70: 4.7055177 | H70: 0.093246887 | I70: 4.70552 | J70: 0.099362713 | K70: =J70-F70 -> 0.099362713 | L70: =H70-F70 -> 0.093246887 | M70: =J70-H70 -> 0.0061158258
B71: 6666020201 | C71: 6666020201 Domestic business travel | D71: 国内商务旅行 | E71: 0.0026 | F71: 5.3530986e-05 | G71: 2.5561062 | H71: 0.050653077 | I71: 0 | J71: 0 | K71: =J71-F71 -> -5.3530986e-05 | L71: =H71-F71 -> 0.050599546 | M71: =J71-H71 -> -0.050653077
B72: 6666020202 | C72: 6666020202 Overseas business travel | D72: 海外商务旅行 | E72: 0 | F72: 0 | G72: 0 | H72: 0 | I72: 0 | J72: 0 | K72: =J72-F72 -> 0 | L72: =H72-F72 -> 0 | M72: =J72-H72 -> 0
B73: 6666020204 | C73: 6666020204 Travel expense pay to agency | D73: 支付给代理的旅行费用 | E73: 0.02159 | F73: 0.00044451307 | G73: 0 | H73: 0 | I73: 2.55611 | J73: 0.053975336 | K73: =J73-F73 -> 0.053530823 | L73: =H73-F73 -> -0.00044451307 | M73: =J73-H73 -> 0.053975336
B74: 6666020205 | C74: 6666020205 Business travel-other | D74: 商务旅行-其他 | E74: 0 | F74: 0 | G74: 0 | H74: 0 | I74: 0 | J74: 0 | K74: =J74-F74 -> 0 | L74: =H74-F74 -> 0 | M74: =J74-H74 -> 0
B75: 6666020301 | C75: 6666020301 Staff communic | D75: 员工通讯 | E75: 0 | F75: 0 | G75: 0.37888355 | H75: 0.0075081455 | I75: 0.27915 | J75: 0.0058945879 | K75: =J75-F75 -> 0.0058945879 | L75: =H75-F75 -> 0.0075081455 | M75: =J75-H75 -> -0.0016135576
B76: 6666020302 | C76: 6666020302 Communication Expenses | D76: 通讯费用 | E76: 0 | F76: 0 | G76: 0.043208927 | H76: 0.00085624968 | I76: 0 | J76: 0 | K76: =J76-F76 -> 0 | L76: =H76-F76 -> 0.00085624968 | M76: =J76-H76 -> -0.00085624968
B77: 6666020403 | C77: 6666020403 Company car expense | D77: 公司车辆费用 | E77: 0 | F77: 0 | H77: 0 | I77: 0 | J77: 0 | K77: =J77-F77 -> 0 | L77: =H77-F77 -> 0 | M77: =J77-H77 -> 0
B78: 6666020405 | C78: 6666020405 Company car expense - maintenance fees | D78: 公司车辆费用-维护费 | E78: 0 | F78: 0 | G78: 0 | H78: 0 | I78: 0 | J78: 0 | K78: =J78-F78 -> 0 | L78: =H78-F78 -> 0 | M78: =J78-H78 -> 0
B79: 6666020495 | C79: 6666020495 Non-deductible expense-travel. | D79: 不可扣除费用-旅行 | E79: 0.03156 | F79: 0.00064978382 | G79: 0 | H79: 0 | I79: 0.16316 | J79: 0.0034453196 | K79: =J79-F79 -> 0.0027955358 | L79: =H79-F79 -> -0.00064978382 | M79: =J79-H79 -> 0.0034453196
B80: 6666020504 | C80: 6666020504 Newspaper and Periodicals expenditure | D80: 报纸和期刊支出 | E80: 0 | F80: 0 | G80: 0.053640889 | H80: 0.0010629746 | I80: 0 | J80: 0 | K80: =J80-F80 -> 0 | L80: =H80-F80 -> 0.0010629746 | M80: =J80-H80 -> -0.0010629746
B81: 6666020508 | C81: 6666020508 Postage | D81: 邮资 | E81: 0 | F81: 0 | G81: 0.43933369 | H81: 0.0087060558 | I81: 0 | J81: 0 | K81: =J81-F81 -> 0 | L81: =H81-F81 -> 0.0087060558 | M81: =J81-H81 -> -0.0087060558
B82: 6666020602 | C82: 6666020602 Training costs Outside the group | D82: 集团外培训费用 | E82: 0 | F82: 0 | G82: 2.0012339 | H82: 0.03965745 | I82: 0 | J82: 0 | K82: =J82-F82 -> 0 | L82: =H82-F82 -> 0.03965745 | M82: =J82-H82 -> -0.03965745
B83: 6666020701 | C83: 6666020701 Enterprise Property Insurance | D83: 企业财产保险 | E83: 0 | F83: 0 | G83: 0 | H83: 0 | I83: 0 | J83: 0 | K83: =J83-F83 -> 0 | L83: =H83-F83 -> 0 | M83: =J83-H83 -> 0
B84: 6666020802 | C84: 6666020802 Equipment rental cost | D84: 设备租赁成本 | E84: 15.5325 | F84: 0.31979617 | G84: 12.783 | H84: 0.25331431 | I84: 10.7325 | J84: 0.22662964 | K84: =J84-F84 -> -0.093166528 | L84: =H84-F84 -> -0.066481861 | M84: =J84-H84 -> -0.026684667
B85: 6666020803 | C85: 6666020803 Car rental cost | D85: 汽车租赁成本 | E85: 4.81971 | F85: 0.099232242 | G85: 3.9024979 | H85: 0.077333846 | I85: 5.39995 | J85: 0.11402644 | K85: =J85-F85 -> 0.014794195 | L85: =H85-F85 -> -0.021898396 | M85: =J85-H85 -> 0.036692592
B86: 6666021100 | C86: 6666021100 Consulting fees | D86: 咨询费 | E86: 10.57577 | F86: 0.21774285 | G86: 5.9033673 | H86: 0.11698407 | I86: 7.28324 | J86: 0.15379437 | K86: =J86-F86 -> -0.063948475 | L86: =H86-F86 -> -0.10075877 | M86: =J86-H86 -> 0.036810297
B87: 6666021104 | C87: 6666021104 Consulting expense-Technical | D87: 技术咨询费用 | E87: 0 | F87: 0 | H87: 0 | I87: 0 | J87: 0 | K87: =J87-F87 -> 0 | L87: =H87-F87 -> 0 | M87: =J87-H87 -> 0
B88: 6666021902 | C88: 6666021902 Cleaning fees | D88: 清洁费 | E88: 7.13263 | F88: 0.14685258 | G88: 8.1687246 | H88: 0.16187553 | I88: 6.57244 | J88: 0.13878497 | K88: =J88-F88 -> -0.0080676102 | L88: =H88-F88 -> 0.015022941 | M88: =J88-H88 -> -0.023090551
B89: 6666022100 | C89: 6666022100 Security | D89: 保安 | E89: 1.47911 | F89: 0.03045316 | G89: 1.512805 | H89: 0.0299785 | I89: 1.4246 | J89: 0.030082142 | K89: =J89-F89 -> -0.00037101836 | L89: =H89-F89 -> -0.00047466089 | M89: =J89-H89 -> 0.00010364253
B90: 6666022300 | C90: 6666022300 Association dues | D90: 会费 | E90: 0 | F90: 0 | G90: 0 | H90: 0 | I90: 0 | J90: 0 | K90: =J90-F90 -> 0 | L90: =H90-F90 -> 0 | M90: =J90-H90 -> 0
B91: 6666029700 | C91: 6666029700 Service fee recharge | D91: 服务费回收费 | E91: 0 | F91: 0 | G91: 0 | H91: 0 | I91: 0 | J91: 0 | K91: =J91-F91 -> 0 | L91: =H91-F91 -> 0 | M91: =J91-H91 -> 0
B92: 6666029900 | C92: 6666029900 Sundry Expenses | D92: 杂项费用 | E92: 0 | F92: 0 | G92: 0 | H92: 0 | I92: 0 | J92: 0 | K92: =J92-F92 -> 0 | L92: =H92-F92 -> 0 | M92: =J92-H92 -> 0
B93: 6666029996 | C93: 6666029996 Non-deductible expense-travel. | D93: 不可扣除费用-旅行 | E93: 0 | F93: 0 | H93: 0 | I93: 0.0279 | J93: 0.00058914205 | K93: =J93-F93 -> 0.00058914205 | L93: =H93-F93 -> 0 | M93: =J93-H93 -> 0.00058914205
B94: 6666029997 | C94: 6666029997 restructure cost | D94: 重组成本 | E94: 0.66238 | F94: 0.013637636 | G94: 0.61134837 | H94: 0.012114784 | I94: 7.89403 | J94: 0.16669194 | K94: =J94-F94 -> 0.1530543 | L94: =H94-F94 -> -0.0015228519 | M94: =J94-H94 -> 0.15457715
B95: 6666030702 | C95: 6666030702 R&D prototype purchased | D95: R&D原型采购 | E95: 0 | F95: 0 | G95: 0 | H95: 0 | I95: 0 | J95: 0 | K95: =J95-F95 -> 0 | L95: =H95-F95 -> 0 | M95: =J95-H95 -> 0
B96: 6666031200 | C96: 6666031200 Instrument fee | D96: 仪器费用 | E96: 0 | F96: 0 | G96: 0 | H96: 0 | I96: 0 | J96: 0 | K96: =J96-F96 -> 0 | L96: =H96-F96 -> 0 | M96: =J96-H96 -> 0
B97: 6666050107 | C97: 6666050107 Special distribution costs | D97: 特殊分配成本 | E97: 0 | F97: 0 | G97: 0 | H97: 0 | I97: 0 | J97: 0 | K97: =J97-F97 -> 0 | L97: =H97-F97 -> 0 | M97: =J97-H97 -> 0
B98: 6666070100 | C98: 6666070100 Software purchase, development and imple | D98: 软件采购、开发及实施 | E98: 0 | F98: 0 | G98: 0 | H98: 0 | I98: 0 | J98: 0 | K98: =J98-F98 -> 0 | L98: =H98-F98 -> 0 | M98: =J98-H98 -> 0
B99: 6666070300 | C99: 6666070300 Software maintenance fees | D99: 软件维护费 | E99: 0 | F99: 0 | G99: 0 | H99: 0 | I99: 0 | J99: 0 | K99: =J99-F99 -> 0 | L99: =H99-F99 -> 0 | M99: =J99-H99 -> 0
B100: 6666070400 | C100: 6666070400 IT maint. & repairs hardware | D100: IT维护及硬件修理 | E100: 4.88462 | F100: 0.10056866 | G100: 13.094726 | H100: 0.25949162 | I100: 11.19273 | J100: 0.23634795 | K100: =J100-F100 -> 0.13577929 | L100: =H100-F100 -> 0.15892296 | M100: =J100-H100 -> -0.02314367
B101: 5401050201 | C101: 5401050201 COGS-Special a | D101: 销售成本-特殊项目 | E101: 0 | F101: 0 | H101: 0 | I101: 0 | J101: 0 | K101: =J101-F101 -> 0 | L101: =H101-F101 -> 0 | M101: =J101-H101 -> 0
...

Sheet 洗碗机2月
A1: 总结：2月洗碗机单台制造费同比恶化5.66欧，同比恶化16%，额恶化24万欧， 含直接人工和间接人工上涨12%（每人241欧总计7.1万欧），管理人员上涨5%（每人161欧总计0.3万欧） 固定：CP预算减少，产量↓8%，单台恶化1.2欧，额差5万欧 变动：恶化三项，单台恶化6.1欧，额差26万欧 集中发放直接员工离职补偿14万欧（同期没有） 集中发放间接员工离职补偿3万欧（同期没有） 集中发放员工福利差异8.5万欧（差异8.5万欧，其中5.1万欧为释放预提，3.4万欧为福利费谈判后上涨）
A2: 维度 | B2: 指标 | C2: 25年实际 | D2: 26年预算 | E2: 预算差异 | F2: 26年实际 | H2: 实际比同期差异 | I2: 制造费差额 | J2: 差异原因
A4: 单 | B4: 产量 | C4: 46039 | D4: 50450 | E4: 4420 | F4: 42593 | H4: -3437
A5: 时 | B5: 工作天数 | C5: 20 | D5: 20 | E5: 0 | F5: 20 | H5: 20
A6: 人 | B6: 直接人工人数 | C6: 218 | D6: 244 | E6: 26 | F6: 215 | H6: -3
B7: 直接人工平均工资 | C7: =E47/C6*1000 -> 1419.1073 | D7: =H47/D6*1000 -> 1788.3896 | E7: 574.15 | F7: =J47/F6*1000 -> 1293.0167 | H7: 555.86 | I7: =F7/C7-1 -> -0.088852053
B8: 间接人工人数 | C8: 85 | D8: 85 | E8: 0 | F8: 82 | H8: -3
B9: 间接人工平均工资 | C9: =E127/C8*1000 -> 1598.5866 | D9: =H127/D8*1000 -> 1970.9097 | E9: 552.94 | F9: =(J127+J124)/F8*1000 -> 1717.5341 | H9: 666.86 | I9: =F9/C9-1 -> 0.074407954
B10: 白领人数 | C10: 23 | D10: 27 | E10: 4 | F10: 22 | H10: -1
B11: 白领人工平均工资 | C11: =(E130+E131)/C10*1000 -> 4798.4057 | D11: =(H130/D10*1000) -> 3592.5642 | E11: -1162.64 | F11: =(J130+J131)/F10*1000 -> 4339.0205 | H11: -302.37 | I11: =F11/C11-1 -> -0.095737049
A12: 效 | B12: UPPH | C12: 1.41 | D12: 1.38 | E12: -0.03 | F12: 1.32 | H12: -0.09 | I12: =H12/C12
A13: 费 | B13: 单台制造费 | C13: 35.45 | D13: 36.72 | E13: 1.26 | F13: 41.11 | H13: 5.66 | I13: =H13*$C$4 -> 260580.74 | J13: 制造费用单台差异5.66
B14: 折旧 | C14: 11.13 | D14: 10.63 | E14: -0.49 | F14: 12.31 | G14: =F14*$F$4 -> 524319.83 | H14: 1.18 | I14: =H14*$F$4 -> 50259.74 | J14: 总额上升1.2万，产量下滑8%
B15: 运营费 | C15: 1.21 | D15: 1.16 | E15: -0.05 | F15: 1.16 | G15: =F15*$F$4 -> 49407.88 | H15: -0.05 | I15: =H15*$F$4 -> -2129.65
B16: 存货跌价准备 | C16: 0.05 | D16: 0.18 | E16: 0.13 | F16: 0.12 | G16: =F16*$F$4 -> 5111.16 | H16: 0.07 | I16: =H16*$F$4 -> 2981.51
B17: 固定能源费 | C17: 0.25 | D17: 0.11 | E17: -0.14 | F17: 0.1 | G17: =F17*$F$4 -> 4259.3 | H17: -0.15 | I17: =H17*$F$4 -> -6388.95
B18: 间接人工成本-辅助人员 | C18: 3.51 | D18: 4.11 | E18: 0.61 | F18: 4.94 | G18: =F18*$F$4 -> 210409.42 | H18: 1.43 | I18: =H18*$F$4 -> 60907.99 | J18: 辅助人员2人离职补偿，共计3万欧元，按同期可下降0.95
B19: 固定人工-白领 | C19: 2.68 | D19: 2.24 | E19: -0.44 | F19: 2.61 | G19: =F19*$F$4 -> 111167.73 | H19: -0.07 | I19: =H19*$F$4 -> -2981.51
B20: 半固定-班车/工作服 | C20: 3.34 | D20: 3.56 | E20: 0.22 | F20: 5.81 | G20: =F20*$F$4 -> 247465.33 | H20: 2.47 | I20: =H20*$F$4 -> 105204.71 | J20: 差异8.5万欧，其中5.1万欧为释放预提，3.4万欧为福利费谈判后上涨
B21: 直接人工 | C21: 7.46 | D21: 10.39 | E21: 2.93 | F21: 10.75 | G21: =F21*$F$4 -> 457874.75 | H21: 3.29 | I21: =H21*$F$4 -> 140130.97 | J21: 离职补偿本月集中发放共计14万欧元
B22: 可回收废料 | C22: 0.49 | D22: 0.54 | E22: 0.05 | F22: 0.34 | G22: =F22*$F$4 -> 14481.62 | H22: -0.15 | I22: =H22*$F$4 -> -6388.95
B23: 生产耗用品 | C23: 0.7 | D23: 0.33 | E23: -0.37 | F23: 0.25 | G23: =F23*$F$4 -> 10648.25 | H23: -0.34 | I23: =H23*$F$4 -> -14481.62
B24: 废品回收 | C24: -1.17 | D24: -1.1 | E24: 0.07 | F24: -1.31 | G24: =F24*$F$4 -> -55796.83 | H24: -0.14 | I24: =H24*$F$4 -> -5963.02
B25: 变动能源费 | C25: 0.51 | D25: 0.75 | E25: 0.24 | F25: 0.1 | G25: =F25*$F$4 -> 4259.3 | H25: -0.25 | I25: =H25*$F$4 -> -10648.25
B26: 园区分摊费用 | C26: 5.3 | D26: 3.8 | E26: -1.49 | F26: 3.67 | G26: =F26*$F$4 -> 156316.31 | H26: -1.63 | I26: =H26*$F$4 -> -69426.59
B27: IT Expense-Internal Charge Out | C27: 2.0598917 | D27: 1.7973014 | E27: -0.1274777 | G27: =F27*$F$4 -> 0 | H27: =(F27/C27)-1 -> -1
B28: Association dues | C28: 0.10364806 | D28: 0.12931195 | E28: 0.24760611 | G28: =F28*$F$4 -> 0 | H28: =(F28/C28)-1 -> -1
B29: G&A | C29: 1.4372934 | D29: 1.8673518 | E29: 0.299214 | G29: =F29*$F$4 -> 0 | H29: =(F29/C29)-1 -> -1
A30: 类型 | B30: 科目编号 | C30: 科目（英文） | D30: 科目（中文） | E30: K€ | F30: 同期台数 | H30: 46330 | I30: 预算台数 | J30: 50440 | K30: 42593
E31: 25年实际制造费 | F31: 25年实际单台 | H31: 26年预测制造费 | I31: 26年预测单台 | J31: 26年实际制造费 | K31: 同期与实际单台差 | L31: 26年预算与25年实际单台差 | M31: 26年实际与25年预算单台差 | N31: 与同期差分析 | O31: Budget-ACT VARIANCE Analysis
A32: 折旧 | B32: 6666110101 | C32: 6666110101 Depreciation of buildings | D32: 建筑物折旧 | E32: 27.05117 | F32: 0.58768564 | H32: 29.463954 | I32: 0.58402288 | J32: 29.47877 | K32: 0.69210363 | L32: 0.10441799 | M32: -0.0036627624
B33: 6666110106 | C33: 6666110106 Depreciation of R&D facilities | D33: 研发设施折旧 | E33: 0 | F33: 0 | H33: 0 | I33: 0 | J33: 0 | K33: 0 | L33: 0 | M33: 0
B34: 6666110107 | C34: 6666110107 Depreciation of mold | D34: 模具折旧 | E34: 208.59611 | F34: 4.5317426 | H34: 220.52585 | I34: 4.3711764 | J34: 216.09226 | K34: 5.0734219 | L34: 0.54167936 | M34: -0.16056618 | N34: 产量下滑8%，产量按同期单台可下降0.41 | P34: 1.17
B35: 6666110110 | C35: 6666110110 Depreciation-Plant & Machinery | D35: 厂房及机械折旧 | E35: 261.00381 | F35: 5.6702978 | H35: 269.49018 | I35: 5.3417281 | J35: 268.26628 | K35: 6.2983655 | L35: 0.62806761 | M35: -0.32856975 | N35: 产量下滑8%，产量按同期单台可下降0.52
B36: 6666110112 | C36: 6666110112 Depreciation of Furniture & Fixture | D36: 家具及装置折旧 | E36: 6.81703 | F36: 0.14809972 | H36: 14.298245 | I36: 0.28341418 | J36: 7.96256 | K36: 0.18694527 | L36: 0.038845555 | M36: 0.13531446
B37: 6666110204 | C37: 6666110204 Amortization of license, trademarks and | D37: 许可证、商标及摊销 | E37: 0.25251 | F37: 0.0054857701 | H37: 0.25251 | I37: 0.0050051536 | J37: 0.25251 | K37: 0.0059284389 | L37: 0.0004426688 | M37: -0.00048061653
B38: 6666110207 | C38: 6666110207 Amortization of Software | D38: 软件摊销 | E38: 7.67016 | F38: 0.16663393 | H38: 2.451265 | I38: 0.048588008 | J38: 2.34867 | K38: 0.05514216 | L38: -0.11149177 | M38: -0.11804593
B39: 6666110506 | C39: 6666110506 Amortization-Leasehold Improvement | D39: 租赁改良摊销 | E39: 0.663272 | F39: 0.014409559 | H39: 0 | I39: 0 | J39: 0 | K39: 0 | L39: -0.014409559 | M39: -0.014409559
B40: 6666110206 | C40: 6666110206 Amortization of Patents | D40: 专利摊销 | F40: 0 | I40: 0 | L40: 0 | M40: 0
B41: FIX | C41: * CS_Depreciation | D41: * CS_折旧 | E41: 512.05406 | F41: 11.124355 | H41: 536.48201 | I41: 10.633935 | J41: =SUM(J32:J40) -> 524.40105 | K41: 12.311907 | L41: 1.1875519 | M41: -0.49042033
A42: 直接人工 | B42: 5001010205 | C42: 5001010205 Unemployment Insurance -blue collar-Dire | D42: 失业保险-蓝领-直接 | E42: 6.31439 | F42: 0.13717988 | H42: 9.0070815 | I42: 0.17853482 | J42: 6.3086 | K42: 0.14811354 | L42: 0.010933657 | M42: 0.041354933
B43: 6666010380 | C43: 6666010380 Incentive | D43: 激励 | E43: -1.5004 | F43: -0.032596133 | H43: -23.502848 | I43: -0.46586419 | J43: -1.58476 | K43: -0.037207053 | L43: -0.0046109198 | M43: -0.43326806
B44: 6666010019 | C44: 6666010019 Payroll Taxes - Blue Collar Direct | E44: 50.47935 | F44: 1.096662 | H44: 93.44847 | I44: 1.8522987 | J44: 53.75998 | K44: 1.2621788 | L44: 0.1655168 | M44: 0.75563676
B45: 6666010183 | C45: 6666010183 Overtime-Blue Collar-Direct | D45: 蓝领加班费-直接 | E45: 18.85745 | F45: 0.40967738 | H45: 0 | I45: 0 | J45: 13.3775 | K45: 0.31407743 | L45: -0.095599954 | M45: -0.40967738
B46: 6666010229 | C46: 6666010229 Staff Leaving Indemnity - Blue Collar Di | D46: 蓝领离职赔偿-直接 | E46: -40.04254 | F46: -0.86992266 | H46: 8.9955298 | I46: 0.17830584 | J46: 107.23839 | K46: 2.5177468 | L46: 3.3876695 | M46: 1.0482285 | N46: 离职补偿本月集中发放，洗碗机二月份离职30人，1月份未结算，按同期单台可下降3.46 | P46: 60万欧
B47: 6666010188 | C47: 6666010188 Salary - Blue collar direct employees | D47: 蓝领直接员工工资 | E47: 309.36539 | F47: 6.7209513 | H47: 436.36707 | I47: 8.6494959 | J47: 277.99859 | K47: 6.526861 | L47: -0.19409035 | M47: 1.9285446
B48: 5102040406 | C48: 5102040406 Other revenue-Service/Secondment agreeme | D48: 其他收入-服务/派遣协议 | E48: 0 | F48: 0 | H48: 0 | I48: 0 | J48: 0 | K48: 0 | L48: 0 | M48: 0
B49: 6666010115 | C49: 6666010115 Salary-Blue collar direct employees-Accr | D49: 蓝领直接员工工资-应计 | E49: -0.08295 | F49: -0.0018020856 | H49: 0 | I49: 0 | J49: 0.68853 | K49: 0.016165332 | L49: 0.017967418 | M49: 0.0018020856
B50: VAR | C50: * CS_Direct Labour | D50: * CS_直接劳动 | E50: 343.39069 | F50: 7.4601497 | H50: 524.3153 | I50: 10.392771 | J50: =SUM(J42:J49) -> 457.78683 | K50: 10.747936 | L50: 3.2877861 | M50: 2.9326214
A51: 可回收废料 | B51: 8701530201 | C51: 8701530201 Scrap-Raw Material - Managerial | D51: 废料-原材料-管理 | E51: 0 | F51: 0 | H51: 0 | I51: 0 | J51: 0 | K51: 0 | L51: 0 | M51: 0
B52: 6666050309 | C52: 6666050309 SFG scrap | D52: SFG废料 | E52: 15.19826 | F52: 0.33018162 | H52: 27.445549 | I52: 0.54401484 | J52: 6.05671 | K52: 0.14219966 | L52: -0.18798196 | M52: 0.21383322
B53: 6666050308 | C53: 6666050308 Raw material scrap | D53: 原材料废料 | E53: 7.13567 | F53: 0.15502216 | H53: 0 | I53: 0 | J53: 7.72351 | K53: 0.18133285 | L53: 0.026310689 | M53: -0.15502216
B54: 6666050306 | C54: 6666050306 Finished goods scrap | D54: 成品废料 | E54: 0.25906 | F54: 0.0056280687 | H54: 0 | I54: 0 | J54: 0.55747 | K54: 0.013088301 | L54: 0.0074602322 | M54: -0.0056280687
B55: VAR | C55: * CS_SCRAP_VARIABLE | D55: * CS_废料变量 | E55: 22.59299 | F55: 0.49083185 | H55: 27.445549 | I55: 0.54401484 | J55: =SUM(J51:J54) -> 14.33769 | K55: 0.33662081 | L55: -0.15421104 | M55: 0.053182993
A56: 组织运营 | B56: 5102010151 | C56: 5102010151 Other Rev.-Interco-Epidemic problem comp | D56: 其他收入-内部公司-疫情问题补偿 | E56: 0 | F56: 0 | H56: 0 | I56: 0 | J56: 0 | K56: 0 | L56: 0 | M56: 0
B57: 5001010200 | C57: 5001010200 Cost of Manufacture - Raw Material | D57: 制造成本-原材料 | E57: 0 | F57: 0 | H57: 0 | I57: 0 | J57: 0.00046 | K57: 1.0799897e-05 | L57: 1.0799897e-05 | M57: 0
B58: 5001010201 | C58: 5001010201 Cost of Manufacture - Raw Material-Freig | D58: 制造成本-原材料-运费 | E58: 0 | F58: 0 | H58: 0 | I58: 0 | J58: 0 | K58: 0 | L58: 0 | M58: 0
B59: 5207000011 | C59: 5207000011 Gain of tangible asset disposal | D59: 有形资产处置收益 | E59: 0 | F59: 0 | H59: 0 | I59: 0 | J59: 0 | K59: 0 | L59: 0 | M59: 0
B60: 5207000012 | C60: 5207000012 Loss of tangible asset sold | D60: 出售有形资产损失 | E60: 0 | F60: 0 | H60: 0 | I60: 0 | J60: 0 | K60: 0 | L60: 0 | M60: 0
B61: 5207000022 | C61: 5207000022 Loss of intangible asset disposal | D61: 无形资产处置损失 | E61: 0 | F61: 0 | H61: 0 | I61: 0 | J61: 0 | K61: 0 | L61: 0 | M61: 0
B62: 5301060000 | C62: 5301060000 Other Income-Subsidy income | D62: 其他收入-补贴收入 | E62: 0 | F62: 0 | H62: 0 | I62: 0 | J62: 0 | K62: 0 | L62: 0 | M62: 0
B63: 5301999999 | C63: 5301999999 Non-operation revenue-Other | D63: 非经营收入-其他 | E63: 0 | F63: 0 | H63: 0 | I63: 0 | J63: -0.00545 | K63: -0.0001279553 | L63: -0.0001279553 | M63: 0
B64: 5405030000 | C64: 5405030000 Other cost-others | D64: 其他成本-其他 | E64: 0.01341 | F64: 0.00029133174 | H64: 0 | I64: 0 | J64: 0 | K64: 0 | L64: -0.00029133174 | M64: -0.00029133174
B65: 5601050000 | C65: 5601050000 Non-Operating Expense - Penalty | D65: 非经营费用-罚款 | E65: 0 | F65: 0 | H65: 0 | I65: 0 | J65: 0 | K65: 0 | L65: 0 | M65: 0
B66: 5601050100 | C66: 5601050100 Non-operation Expense-Others | D66: 非经营费用-其他 | E66: 0 | F66: 0 | H66: 0 | I66: 0 | J66: 0 | K66: 0 | L66: 0 | M66: 0
B67: 5102040893 | C67: 5102040893 Other revenue-Charge out-Test Expense | D67: 其他收入-费用支出-测试费用 | E67: 0 | F67: 0 | I67: 0 | J67: 0 | K67: 0 | L67: 0 | M67: 0
B68: 5801000041 | C68: 5801000041 Previous year Sundry cost | D68: 去年杂项成本 | E68: 0 | F68: 0 | H68: 0 | I68: 0 | J68: 0 | K68: 0 | L68: 0 | M68: 0
B69: 6666010322 | C69: 6666010322 fuel allowance | D69: 燃料津贴 | E69: 0.51196 | F69: 0.011122312 | H69: 1.9896026 | I69: 0.039437117 | J69: 0.36786 | K69: 0.0086366304 | L69: -0.0024856811 | M69: 0.028314806
B70: 6666020101 | C70: 6666020101 Entertainment | D70: 娱乐 | E70: 6.83876 | F70: 0.1485718 | H70: 4.6177799 | I70: 0.091531811 | J70: 4.61778 | K70: 0.10841641 | L70: -0.040155395 | M70: -0.05703999
B71: 6666020201 | C71: 6666020201 Domestic business travel | D71: 国内商务旅行 | E71: 0.3025 | F71: 0.006571801 | H71: 2.5084457 | I71: 0.049721422 | J71: 0 | K71: 0 | L71: -0.006571801 | M71: 0.043149621
B72: 6666020202 | C72: 6666020202 Overseas business travel | D72: 海外商务旅行 | E72: 0 | F72: 0 | H72: 0 | I72: 0 | J72: 0 | K72: 0 | L72: 0 | M72: 0
B73: 6666020204 | C73: 6666020204 Travel expense pay to agency | D73: 支付给代理的旅行费用 | E73: 0.02007 | F73: 0.00043601999 | H73: 0 | I73: 0 | J73: 2.50844 | K73: 0.058893245 | L73: 0.058457225 | M73: -0.00043601999
B74: 6666020205 | C74: 6666020205 Business travel-other | D74: 商务旅行-其他 | E74: 0 | F74: 0 | H74: 0 | I74: 0 | J74: 0 | K74: 0 | L74: 0 | M74: 0
B75: 6666020301 | C75: 6666020301 Staff communic | D75: 员工通讯 | E75: 1.18363 | F75: 0.025714317 | H75: 0.37181899 | I75: 0.0073700493 | J75: 0.02628 | K75: 0.00061700279 | L75: -0.025097314 | M75: -0.018344267
B76: 6666020302 | C76: 6666020302 Communication Expenses | D76: 通讯费用 | E76: 0 | F76: 0 | H76: 0.042403265 | I76: 0.0008405008 | J76: 0 | K76: 0 | L76: 0 | M76: 0.0008405008
B77: 6666020403 | C77: 6666020403 Company car expense | D77: 公司车辆费用 | F77: 0 | I77: 0 | J77: 0 | K77: 0 | L77: 0 | M77: 0
B78: 6666020405 | C78: 6666020405 Company car expense - maintenance fees | D78: 公司车辆费用-维护费 | E78: 0 | F78: 0 | H78: 0 | I78: 0 | J78: 0 | K78: 0 | L78: 0 | M78: 0
B79: 6666020495 | C79: 6666020495 Non-deductible expense-travel. | D79: 不可扣除费用-旅行 | E79: 0.09104 | F79: 0.0019778405 | H79: 0 | I79: 0 | J79: 0.36005 | K79: 0.008453267 | L79: 0.0064754264 | M79: -0.0019778405
B80: 6666020504 | C80: 6666020504 Newspaper and Periodicals expenditure | D80: 报纸和期刊支出 | E80: 0 | F80: 0 | H80: 0.052640716 | I80: 0.0010434235 | J80: 0 | K80: 0 | L80: 0 | M80: 0.0010434235
B81: 6666020508 | C81: 6666020508 Postage | D81: 邮资 | E81: 0 | F81: 0 | H81: 0.43114199 | I81: 0.0085459266 | J81: 0 | K81: 0 | L81: 0 | M81: 0.0085459266
B82: 6666020602 | C82: 6666020602 Training costs Outside the group | D82: 集团外培训费用 | E82: 0.55286 | F82: 0.012010862 | H82: 1.9639194 | I82: 0.038928037 | J82: 0.54443 | K82: 0.012782147 | L82: 0.00077128482 | M82: 0.026917174
B83: 6666020701 | C83: 6666020701 Enterprise Property Insurance | D83: 企业财产保险 | E83: 0 | F83: 0 | H83: 0 | I83: 0 | J83: 0 | K83: 0 | L83: 0 | M83: 0
B84: 6666020802 | C84: 6666020802 Equipment rental cost | D84: 设备租赁成本 | E84: 15.04068 | F84: 0.3267582 | H84: 12.783 | I84: 0.25337958 | J84: 10.758 | K84: 0.25257671 | L84: -0.074181487 | M84: -0.073378617
B85: 6666020803 | C85: 6666020803 Car rental cost | D85: 汽车租赁成本 | E85: 4.86478 | F85: 0.10568716 | H85: 3.8297329 | I85: 0.075911455 | J85: 3.14635 | K85: 0.07387012 | L85: -0.031817041 | M85: -0.029775705
B86: 6666021100 | C86: 6666021100 Consulting fees | D86: 咨询费 | E86: 9.71594 | F86: 0.21107843 | H86: 5.7932947 | I86: 0.1148324 | J86: 5.88308 | K86: 0.13812317 | L86: -0.072955261 | M86: -0.096246025
B87: 6666021104 | C87: 6666021104 Consulting expense-Technical | D87: 技术咨询费用 | E87: 0 | F87: 0 | I87: 0 | J87: 0 | K87: 0 | L87: 0 | M87: 0
B88: 6666021902 | C88: 6666021902 Cleaning fees | D88: 清洁费 | E88: 8.15543 | F88: 0.17717641 | H88: 8.0164128 | I88: 0.15889817 | J88: 9.0083 | K88: 0.21149719 | L88: 0.034320788 | M88: -0.018278235
B89: 6666022100 | C89: 6666022100 Security | D89: 保安 | E89: 1.22778 | F89: 0.026673474 | H89: 1.4845977 | I89: 0.029427109 | J89: 1.23972 | K89: 0.029106191 | L89: 0.0024327173 | M89: 0.0027536355
B90: 6666022300 | C90: 6666022300 Association dues | D90: 会费 | E90: 0 | F90: 0 | H90: 0 | I90: 0 | J90: 0 | K90: 0 | L90: 0 | M90: 0
B91: 6666029700 | C91: 6666029700 Service fee recharge | D91: 服务费回收费 | E91: 0 | F91: 0 | H91: 0 | I91: 0 | J91: 0 | K91: 0 | L91: 0 | M91: 0
B92: 6666029900 | C92: 6666029900 Sundry Expenses | D92: 杂项费用 | E92: 0 | F92: 0 | H92: 0 | I92: 0 | J92: 0.00778 | K92: 0.00018265912 | L92: 0.00018265912 | M92: 0
B93: 6666029996 | C93: 6666029996 Non-deductible expense-travel. | D93: 不可扣除费用-旅行 | E93: 0 | F93: 0 | I93: 0 | J93: -0.02736 | K93: -0.00064235907 | L93: -0.00064235907 | M93: 0
B94: 6666029997 | C94: 6666029997 restructure cost | D94: 重组成本 | E94: 4.5982 | F94: 0.09989572 | H94: 0.59994933 | I94: 0.011891959 | J94: -2.12126 | K94: -0.049803019 | L94: -0.14969874 | M94: -0.088003761
B95: 6666030702 | C95: 6666030702 R&D prototype purchased | D95: R&D原型采购 | E95: 0 | F95: 0 | H95: 0 | I95: 0 | J95: 0 | K95: 0 | L95: 0 | M95: 0
B96: 6666031200 | C96: 6666031200 Instrument fee | D96: 仪器费用 | E96: -0.00026 | F96: -5.6484901e-06 | H96: 0 | I96: 0 | J96: 0 | K96: 0 | L96: 5.6484901e-06 | M96: 5.6484901e-06
B97: 6666050107 | C97: 6666050107 Special distribution costs | D97: 特殊分配成本 | E97: 0 | F97: 0 | H97: 0 | I97: 0 | J97: 0 | K97: 0 | L97: 0 | M97: 0
B98: 6666070100 | C98: 6666070100 Software purchase, development and imple | D98: 软件采购、开发及实施 | E98: 0 | F98: 0 | H98: 0 | I98: 0 | J98: 0 | K98: 0 | L98: 0 | M98: 0
B99: 6666070300 | C99: 6666070300 Software maintenance fees | D99: 软件维护费 | E99: 0 | F99: 0 | H99: 0 | I99: 0 | J99: 0 | K99: 0 | L99: 0 | M99: 0
B100: 6666070400 | C100: 6666070400 IT maint. & repairs hardware | D100: IT维护及硬件修理 | E100: 2.79422 | F100: 0.060704323 | H100: 12.850565 | I100: 0.25471883 | J100: 11.39457 | K100: 0.26752213 | L100: 0.2068178 | M100: 0.19401451
B101: 5401050201 | C101: 5401050201 COGS-Special a | D101: 销售成本-特殊项目 | E101: 0 | F101: 0 | I101: 0 | J101: 0 | K101: 0 | L101: 0 | M101: 0
...

Sheet 洗碗机3月
A1: 总结：3月实际洗碗机单台恶化35.1欧；额恶化80.64万欧 通胀影响，定单量下降负影响72万，通胀影响9.5万 固定：洗碗机单台↑12.5欧，累计恶化28万 变动：洗碗机单台↑22.7欧，累计恶化52万 恶化原因：CP预算减少，产量↓50%
A2: 维度 | B2: 指标 | C2: 25年实际 | D2: 26年预算 | E2: 预算差异 | F2: 26年实际 | H2: 实际比同期差异 | I2: 制造费差额 | J2: 差异原因
A4: 单 | B4: 产量 | C4: 46330 | D4: 50440 | E4: =D4-C4 -> 4110 | F4: 23002 | H4: =F4-C4 -> -23328 | I4: / | J4: 订单量下滑49%
A5: 时 | B5: 工作天数 | C5: 20 | D5: 20 | E5: =D5-C5 -> 0 | F5: 20 | H5: =F5-C5 -> 0
A6: 人 | B6: 直接人工 | C6: 218 | D6: 244 | E6: =D6-C6 -> 26 | F6: 135 | H6: =F6-C6 -> -83
B7: 人工工资 | C7: =E47/C6*1000 -> 1872.3222 | D7: =H47/D6*1000 -> 1806.4003 | E7: =D7-C7 -> -65.921906 | F7: =J47/F6*1000 -> 0 | H7: =F7-C7 -> -1872.3222
B8: 间接人工 | C8: 94 | D8: 85 | E8: =D8-C8 -> -9 | F8: 85 | H8: =F8-C8 -> -9
B9: 间接人工工资 | C9: =E127/C8*1000 -> 2018.0737 | D9: =H127/D8*1000 -> 2009.2296 | E9: =D9-C9 -> -8.8440953 | F9: =(J127+J124)/F8*1000 -> 0 | H9: =F9-C9 -> -2018.0737
B10: 白领人数 | C10: 22 | D10: 27 | E10: =D10-C10 -> 5 | F10: 27 | H10: =F10-C10 -> 5
B11: 白领人工工资 | C11: =(E130+E131)/C10*1000 -> 1437.7168 | D11: =(H130/D10*1000) -> 3259.9326 | E11: =D11-C11 -> 1822.2157 | F11: =(J130+J131)/F10*1000 -> 0 | H11: =F11-C11 -> -1437.7168
A12: 效 | B12: UPPH | C12: =C4/C6/C5/7.5 -> 1.4168196 | D12: =D4/D6/D5 -> 10.336066 | E12: =D12-C12 -> 8.919246 | F12: =F4/F6/F5/7.5 -> 1.1359012 | H12: =F12-C12 -> -0.28091834
A13: 费 | B13: 单台制造费 | C13: =SUM(C14:C26) -> 39.407954 | D13: =SUM(D14:D26) -> 37.525254 | E13: =D13-C13 -> -1.8826997 | F13: =SUM(F14:F26) -> 0.18215807 | G13: =F13*$F$4 -> 4190 | H13: =F13-C13 -> -39.225796 | I13: =H13*$F$4 -> -902271.76
B14: 折旧 | C14: 12.11794 | D14: 11.534082 | E14: =D14-C14 -> -0.58385812 | F14: =K41 -> 0 | G14: =F14*$F$4 -> 0 | H14: =F14-C14 -> -12.11794 | I14: =H14*$F$4 -> -278736.85 | J14: 订单量下滑49%
B15: 运营费 | C15: 0.94499169 | D15: 1.1446286 | E15: =D15-C15 -> 0.19963686 | F15: =K104 -> 0 | G15: =F15*$F$4 -> 0 | H15: =F15-C15 -> -0.94499169 | I15: =H15*$F$4 -> -21736.699 | J15: 订单量下滑49%
B16: 存货跌价准备 | C16: 0.044960399 | D16: 0.17238607 | E16: =D16-C16 -> 0.12742567 | F16: =K111 -> 0 | G16: =F16*$F$4 -> 0 | H16: =F16-C16 -> -0.044960399 | I16: =H16*$F$4 -> -1034.1791
B17: 固定能源费 | C17: =0.235451367157995-0.04 -> 0.19545137 | D17: 0.10997077 | E17: =D17-C17 -> -0.085480595 | F17: =K117 -> 0 | G17: =F17*$F$4 -> 0 | H17: =F17-C17 -> -0.19545137 | I17: =H17*$F$4 -> -4495.7723
B18: 间接人工成本-辅助人员 | C18: 5.3008343 | D18: 4.2015022 | E18: =D18-C18 -> -1.0993321 | F18: =K128 -> 0 | G18: =F18*$F$4 -> 0 | H18: =F18-C18 -> -5.3008343 | I18: =H18*$F$4 -> -121929.79 | J18: 订单量下滑49%
B19: 固定人工-白领 | C19: 0.75709325 | D19: 2.0346606 | E19: =D19-C19 -> 1.2775674 | F19: =K136 -> 0 | G19: =F19*$F$4 -> 0 | H19: =F19-C19 -> -0.75709325 | I19: =H19*$F$4 -> -17414.659
B20: 半固定-班车/工作服 | C20: 3.4692196 | D20: 3.5026887 | E20: =D20-C20 -> 0.033469062 | F20: =K149 -> 0 | G20: =F20*$F$4 -> 0 | H20: =F20-C20 -> -3.4692196 | I20: =H20*$F$4 -> -79798.99 | L20: =K20/G13 -> 0
B21: 直接人工 | C21: 11.161989 | D21: 10.493562 | E21: =D21-C21 -> -0.66842713 | F21: =K50 -> 0 | G21: =F21*$F$4 -> 0 | H21: =F21-C21 -> -11.161989 | I21: =H21*$F$4 -> -256748.06
B22: 可回收废料 | C22: 0.49416212 | D22: 0.54404719 | E22: =D22-C22 -> 0.049885077 | F22: =K55 -> 0 | G22: =F22*$F$4 -> 0 | H22: =F22-C22 -> -0.49416212 | I22: =H22*$F$4 -> -11366.717
B23: 生产耗用品 | C23: 0.77141097 | D23: 0.33163518 | E23: =D23-C23 -> -0.43977579 | F23: =K109 -> 0 | G23: =F23*$F$4 -> 0 | H23: =F23-C23 -> -0.77141097 | I23: =H23*$F$4 -> -17743.995
B24: 废品回收 | C24: -1.2469823 | D24: -1.1002428 | E24: =D24-C24 -> 0.14673953 | F24: =K113 -> 0 | G24: =F24*$F$4 -> 0 | H24: =F24-C24 -> 1.2469823 | I24: =H24*$F$4 -> 28683.087
B25: 变动能源费 | C25: 0.66386754 | D25: 0.7521668 | E25: =D25-C25 -> 0.088299265 | F25: =K120 -> 0.18215807 | G25: =F25*$F$4 -> 4190 | H25: =F25-C25 -> -0.48170946 | I25: =H25*$F$4 -> -11080.281
B26: 园区分摊费用 | C26: 4.7330166 | D26: 3.8041678 | E26: =D26-C26 -> -0.92884877 | F26: =K221 -> 0 | G26: =F26*$F$4 -> 0 | H26: =F26-C26 -> -4.7330166 | I26: =H26*$F$4 -> -108868.85 | J26: 订单量下滑49%
B27: IT Expense-Internal Charge Out | C27: 2.0598917 | D27: 1.7973014 | E27: -0.1274777 | H27: =(F27/C27)-1 -> -1 | J27: =H27-#REF! -> #REF!
B28: Association dues | C28: 0.10364806 | D28: 0.12931195 | E28: 0.24760611 | H28: =(F28/C28)-1 -> -1 | J28: =H28-#REF! -> #REF!
B29: G&A | C29: 1.4372934 | D29: 1.8673518 | E29: 0.299214 | H29: =(F29/C29)-1 -> -1 | J29: =H29-#REF! -> #REF!
A30: 类型 | C30: 科目（英文） | D30: 科目（中文） | E30: K€ | F30: 同期台数 | H30: 46330 | I30: 预算台数 | J30: 50440 | K30: 实际台数 | L30: 23002
E31: 25年实际制造费 | F31: 25年实际单台 | H31: 26年预测制造费 | I31: 26年预测单台 | J31: 26年实际制造费 | K31: 26年实际单台 | L31: 同期与实际单台差 | M31: 实际与预算的差 | N31: 与同期差分析
A32: 折旧 | B32: 6666110101 | C32: 6666110101 Depreciation of buildings | D32: 建筑物折旧 | E32: 29.88156 | F32: 0.64497216 | H32: 32.511138 | I32: =H32/$J$30*1000 -> 0.64455072 | K32: =J32/$F$4*1000 -> 0 | L32: =K32-F32 -> -0.64497216 | M32: =K32-I32 -> -0.64455072
B33: 6666110106 | C33: 6666110106 Depreciation of R&D facilities | D33: 研发设施折旧 | E33: 0 | F33: 0 | H33: 0 | I33: =H33/$J$30*1000 -> 0 | K33: =J33/$F$4*1000 -> 0 | L33: =K33-F33 -> 0 | M33: =K33-I33 -> 0
B34: 6666110107 | C34: 6666110107 Depreciation of mold | D34: 模具折旧 | E34: 222.76497 | F34: 4.808223 | H34: 229.95889 | I34: =H34/$J$30*1000 -> 4.5590581 | K34: =J34/$F$4*1000 -> 0 | L34: =K34-F34 -> -4.808223 | M34: =K34-I34 -> -4.5590581
B35: 6666110110 | C35: 6666110110 Depreciation-Plant & Machinery | D35: 厂房及机械折旧 | E35: 290.93886 | F35: 6.2797077 | H35: 301.0103 | I35: =H35/$J$30*1000 -> 5.9676903 | K35: =J35/$F$4*1000 -> 0 | L35: =K35-F35 -> -6.2797077 | M35: =K35-I35 -> -5.9676903
B36: 6666110112 | C36: 6666110112 Depreciation of Furniture & Fixture | D36: 家具及装置折旧 | E36: 8.46919 | F36: 0.18280142 | H36: 15.560153 | I36: =H36/$J$30*1000 -> 0.30848837 | K36: =J36/$F$4*1000 -> 0 | L36: =K36-F36 -> -0.18280142 | M36: =K36-I36 -> -0.30848837
B37: 6666110204 | C37: 6666110204 Amortization of license, trademarks and | D37: 许可证、商标及摊销 | E37: 0.25252 | F37: 0.0054504641 | H37: 0.25252 | I37: =H37/$J$30*1000 -> 0.0050063442 | K37: =J37/$F$4*1000 -> 0 | L37: =K37-F37 -> -0.0054504641 | M37: =K37-I37 -> -0.0050063442
B38: 6666110207 | C38: 6666110207 Amortization of Software | D38: 软件摊销 | E38: 8.28781 | F38: 0.17888647 | H38: 2.5668229 | I38: =H38/$J$30*1000 -> 0.050888639 | K38: =J38/$F$4*1000 -> 0 | L38: =K38-F38 -> -0.17888647 | M38: =K38-I38 -> -0.050888639
B39: 6666110506 | C39: 6666110506 Amortization-Leasehold Improvement | D39: 租赁改良摊销 | E39: 0.663272 | F39: 0.014316253 | H39: 0 | I39: =H39/$J$30*1000 -> 0 | K39: =J39/$F$4*1000 -> 0 | L39: =K39-F39 -> -0.014316253 | M39: =K39-I39 -> 0
B40: 6666110206 | C40: 6666110206 Amortization of Patents | D40: 专利摊销 | F40: 0 | I40: =H40/$J$30*1000 -> 0 | K40: =J40/$F$4*1000 -> 0 | L40: =K40-F40 -> 0 | M40: =K40-I40 -> 0
B41: FIX | C41: * CS_Depreciation | D41: * CS_折旧 | E41: =SUM(E32:E40) -> 561.25818 | F41: 12.114357 | H41: =SUM(H32:H40) -> 581.85982 | I41: =H41/$J$30*1000 -> 11.535682 | J41: =SUM(J32:J40) -> 0 | K41: =J41/$F$4*1000 -> 0 | L41: =K41-F41 -> -12.114357 | M41: =SUM(M32:M40) -> -11.535682
A42: 直接人工 | B42: 5001010205 | C42: 5001010205 Unemployment Insurance -blue collar-Dire | D42: 失业保险-蓝领-直接 | E42: 8.11537 | F42: 0.17516447 | H42: 9.0985919 | I42: =H42/$J$30*1000 -> 0.18038445 | K42: =J42/$F$4*1000 -> 0 | L42: =K42-F42 -> -0.17516447 | M42: =K42-I42 -> -0.18038445
B43: 6666010380 | C43: 6666010380 Incentive | D43: 激励 | E43: -1.56596 | F43: -0.03380013 | H43: -23.717256 | I43: =H43/$J$30*1000 -> -0.4702073 | K43: =J43/$F$4*1000 -> 0 | L43: =K43-F43 -> 0.03380013 | M43: =K43-I43 -> 0.4702073
B44: 6666010019 | C44: 6666010019 Payroll Taxes - Blue Collar Direct | E44: 64.9104 | F44: 1.4010447 | H44: 94.397891 | I44: =H44/$J$30*1000 -> 1.8714887 | K44: =J44/$F$4*1000 -> 0 | L44: =K44-F44 -> -1.4010447 | M44: =K44-I44 -> -1.8714887
B45: 6666010183 | C45: 6666010183 Overtime-Blue Collar-Direct | D45: 蓝领加班费-直接 | E45: 26.26231 | F45: 0.56685323 | H45: 0 | I45: =H45/$J$30*1000 -> 0 | K45: =J45/$F$4*1000 -> 0 | L45: =K45-F45 -> -0.56685323 | M45: =K45-I45 -> 0 | O45: =E45-J45 -> 26.26231
B46: 6666010229 | C46: 6666010229 Staff Leaving Indemnity - Blue Collar Di | D46: 蓝领离职赔偿-直接 | E46: 11.24318 | F46: 0.24267602 | H46: 8.8278016 | I46: =H46/$J$30*1000 -> 0.17501589 | K46: =J46/$F$4*1000 -> 0 | L46: =K46-F46 -> -0.24267602 | M46: =K46-I46 -> -0.17501589
B47: 6666010188 | C47: 6666010188 Salary - Blue collar direct employees | D47: 蓝领直接员工工资 | E47: 408.16624 | F47: 8.8099771 | H47: 440.76167 | I47: =H47/$J$30*1000 -> 8.7383361 | K47: =J47/$F$4*1000 -> 0 | L47: =K47-F47 -> -8.8099771 | M47: =K47-I47 -> -8.7383361
B48: 5102040406 | C48: 5102040406 Other revenue-Service/Secondment agreeme | D48: 其他收入-服务/派遣协议 | E48: 0 | F48: 0 | H48: 0 | I48: =H48/$J$30*1000 -> 0 | K48: =J48/$F$4*1000 -> 0 | L48: =K48-F48 -> 0 | M48: =K48-I48 -> 0
B49: 6666010115 | C49: 6666010115 Salary-Blue collar direct employees-Accr | D49: 蓝领直接员工工资-应计 | E49: 0.08153 | F49: 0.0017597669 | H49: 0 | I49: =H49/$J$30*1000 -> 0 | K49: =J49/$F$4*1000 -> 0 | L49: =K49-F49 -> -0.0017597669 | M49: =K49-I49 -> 0
B50: VAR | C50: * CS_Direct Labour | D50: * CS_直接劳动 | E50: 517.21307 | F50: 11.163675 | H50: 529 | I50: =H50/$J$30*1000 -> 10.487708 | J50: =SUM(J42:J49) -> 0 | K50: =J50/$F$4*1000 -> 0 | L50: =K50-F50 -> -11.163675 | M50: =SUM(M42:M49) -> -10.495018
A51: 可回收废料 | B51: 8701530201 | C51: 8701530201 Scrap-Raw Material - Managerial | D51: 废料-原材料-管理 | E51: 0 | F51: 0 | H51: 0 | I51: =H51/$J$30*1000 -> 0 | K51: =J51/$F$4*1000 -> 0 | L51: =K51-F51 -> 0 | M51: =K51-I51 -> 0
B52: 6666050309 | C52: 6666050309 SFG scrap | D52: SFG废料 | E52: 16.14383 | F52: 0.34845305 | H52: 27.445549 | I52: =H52/$J$30*1000 -> 0.5441227 | K52: =J52/$F$4*1000 -> 0 | L52: =K52-F52 -> -0.34845305 | M52: =K52-I52 -> -0.5441227
B53: 6666050308 | C53: 6666050308 Raw material scrap | D53: 原材料废料 | E53: 6.75416 | F53: 0.14578373 | H53: 0 | I53: =H53/$J$30*1000 -> 0 | K53: =J53/$F$4*1000 -> 0 | L53: =K53-F53 -> -0.14578373 | M53: =K53-I53 -> 0
B54: 6666050306 | C54: 6666050306 Finished goods scrap | D54: 成品废料 | E54: 0 | F54: 0 | H54: 0 | I54: =H54/$J$30*1000 -> 0 | K54: =J54/$F$4*1000 -> 0 | L54: =K54-F54 -> 0 | M54: =K54-I54 -> 0
B55: VAR | C55: * CS_SCRAP_VARIABLE | D55: * CS_废料变量 | E55: 22.89799 | F55: 0.49423678 | H55: 27.445549 | I55: =H55/$J$30*1000 -> 0.5441227 | J55: =SUM(J51:J54) -> 0 | K55: =SUM(K51:K54) -> 0 | L55: =K55-F55 -> -0.49423678 | M55: =SUM(M51:M54) -> -0.5441227
A56: 组织运营 | B56: 5102010151 | C56: 5102010151 Other Rev.-Interco-Epidemic problem comp | D56: 其他收入-内部公司-疫情问题补偿 | E56: 0 | F56: 0 | H56: 0 | I56: =H56/$J$30*1000 -> 0 | K56: =J56/$F$4*1000 -> 0 | L56: =K56-F56 -> 0 | M56: =K56-I56 -> 0
B57: 5001010200 | C57: 5001010200 Cost of Manufacture - Raw Material | D57: 制造成本-原材料 | E57: 0 | F57: 0 | H57: 0 | I57: =H57/$J$30*1000 -> 0 | K57: =J57/$F$4*1000 -> 0 | L57: =K57-F57 -> 0 | M57: =K57-I57 -> 0
B58: 5001010201 | C58: 5001010201 Cost of Manufacture - Raw Material-Freig | D58: 制造成本-原材料-运费 | E58: 0 | F58: 0 | H58: 0 | I58: =H58/$J$30*1000 -> 0 | K58: =J58/$F$4*1000 -> 0 | L58: =K58-F58 -> 0 | M58: =K58-I58 -> 0
B59: 5207000011 | C59: 5207000011 Gain of tangible asset disposal | D59: 有形资产处置收益 | E59: 0 | F59: 0 | H59: 0 | I59: =H59/$J$30*1000 -> 0 | K59: =J59/$F$4*1000 -> 0 | L59: =K59-F59 -> 0 | M59: =K59-I59 -> 0
B60: 5207000012 | C60: 5207000012 Loss of tangible asset sold | D60: 出售有形资产损失 | E60: 0 | F60: 0 | H60: 0 | I60: =H60/$J$30*1000 -> 0 | K60: =J60/$F$4*1000 -> 0 | L60: =K60-F60 -> 0 | M60: =K60-I60 -> 0
B61: 5207000022 | C61: 5207000022 Loss of intangible asset disposal | D61: 无形资产处置损失 | E61: 0 | F61: 0 | H61: 0 | I61: =H61/$J$30*1000 -> 0 | K61: =J61/$F$4*1000 -> 0 | L61: =K61-F61 -> 0 | M61: =K61-I61 -> 0
B62: 5301060000 | C62: 5301060000 Other Income-Subsidy income | D62: 其他收入-补贴收入 | E62: 0 | F62: 0 | H62: 0 | I62: =H62/$J$30*1000 -> 0 | K62: =J62/$F$4*1000 -> 0 | L62: =K62-F62 -> 0 | M62: =K62-I62 -> 0
B63: 5301999999 | C63: 5301999999 Non-operation revenue-Other | D63: 非经营收入-其他 | E63: 0 | F63: 0 | H63: 0 | I63: =H63/$J$30*1000 -> 0 | K63: =J63/$F$4*1000 -> 0 | L63: =K63-F63 -> 0 | M63: =K63-I63 -> 0
B64: 5405030000 | C64: 5405030000 Other cost-others | D64: 其他成本-其他 | E64: 0.73836 | F64: 0.015936974 | H64: 0 | I64: =H64/$J$30*1000 -> 0 | K64: =J64/$F$4*1000 -> 0 | L64: =K64-F64 -> -0.015936974 | M64: =K64-I64 -> 0
B65: 5601050000 | C65: 5601050000 Non-Operating Expense - Penalty | D65: 非经营费用-罚款 | E65: 0 | F65: 0 | H65: 0 | I65: =H65/$J$30*1000 -> 0 | K65: =J65/$F$4*1000 -> 0 | L65: =K65-F65 -> 0 | M65: =K65-I65 -> 0
B66: 5601050100 | C66: 5601050100 Non-operation Expense-Others | D66: 非经营费用-其他 | E66: 0 | F66: 0 | H66: 0 | I66: =H66/$J$30*1000 -> 0 | K66: =J66/$F$4*1000 -> 0 | L66: =K66-F66 -> 0 | M66: =K66-I66 -> 0
B67: 5102040893 | C67: 5102040893 Other revenue-Charge out-Test Expense | D67: 其他收入-费用支出-测试费用 | E67: 0 | F67: 0 | I67: =H67/$J$30*1000 -> 0 | K67: =J67/$F$4*1000 -> 0 | L67: =K67-F67 -> 0 | M67: =K67-I67 -> 0
B68: 5801000041 | C68: 5801000041 Previous year Sundry cost | D68: 去年杂项成本 | E68: 0 | F68: 0 | H68: 0 | I68: =H68/$J$30*1000 -> 0 | K68: =J68/$F$4*1000 -> 0 | L68: =K68-F68 -> 0 | M68: =K68-I68 -> 0
B69: 6666010322 | C69: 6666010322 fuel allowance | D69: 燃料津贴 | E69: 2.69789 | F69: 0.058232031 | H69: 1.952505 | I69: =H69/$J$30*1000 -> 0.038709456 | K69: =J69/$F$4*1000 -> 0 | L69: =K69-F69 -> -0.058232031 | M69: =K69-I69 -> -0.038709456
B70: 6666020101 | C70: 6666020101 Entertainment | D70: 娱乐 | E70: 5.84951 | F70: 0.1262575 | H70: 4.531678 | I70: =H70/$J$30*1000 -> 0.089842942 | K70: =J70/$F$4*1000 -> 0 | L70: =K70-F70 -> -0.1262575 | M70: =K70-I70 -> -0.089842942
B71: 6666020201 | C71: 6666020201 Domestic business travel | D71: 国内商务旅行 | E71: 0.13764 | F71: 0.0029708612 | H71: 2.4616739 | I71: =H71/$J$30*1000 -> 0.048804004 | K71: =J71/$F$4*1000 -> 0 | L71: =K71-F71 -> -0.0029708612 | M71: =K71-I71 -> -0.048804004
B72: 6666020202 | C72: 6666020202 Overseas business travel | D72: 海外商务旅行 | E72: 0.16911 | F72: 0.0036501187 | H72: 0 | I72: =H72/$J$30*1000 -> 0 | K72: =J72/$F$4*1000 -> 0 | L72: =K72-F72 -> -0.0036501187 | M72: =K72-I72 -> 0
B73: 6666020204 | C73: 6666020204 Travel expense pay to agency | D73: 支付给代理的旅行费用 | E73: 0 | F73: 0 | H73: 0 | I73: =H73/$J$30*1000 -> 0 | K73: =J73/$F$4*1000 -> 0 | L73: =K73-F73 -> 0 | M73: =K73-I73 -> 0
B74: 6666020205 | C74: 6666020205 Business travel-other | D74: 商务旅行-其他 | E74: 0 | F74: 0 | H74: 0 | I74: =H74/$J$30*1000 -> 0 | K74: =J74/$F$4*1000 -> 0 | L74: =K74-F74 -> 0 | M74: =K74-I74 -> 0
B75: 6666020301 | C75: 6666020301 Staff communic | D75: 员工通讯 | E75: 1.00936 | F75: 0.021786316 | H75: 0.36488615 | I75: =H75/$J$30*1000 -> 0.0072340632 | K75: =J75/$F$4*1000 -> 0 | L75: =K75-F75 -> -0.021786316 | M75: =K75-I75 -> -0.0072340632
B76: 6666020302 | C76: 6666020302 Communication Expenses | D76: 通讯费用 | E76: 0 | F76: 0 | H76: 0.041612626 | I76: =H76/$J$30*1000 -> 0.00082499258 | K76: =J76/$F$4*1000 -> 0 | L76: =K76-F76 -> 0 | M76: =K76-I76 -> -0.00082499258
B77: 6666020403 | C77: 6666020403 Company car expense | D77: 公司车辆费用 | F77: 0 | I77: =H77/$J$30*1000 -> 0 | K77: =J77/$F$4*1000 -> 0 | L77: =K77-F77 -> 0 | M77: =K77-I77 -> 0
B78: 6666020405 | C78: 6666020405 Company car expense - maintenance fees | D78: 公司车辆费用-维护费 | E78: 0 | F78: 0 | H78: 0 | I78: =H78/$J$30*1000 -> 0 | K78: =J78/$F$4*1000 -> 0 | L78: =K78-F78 -> 0 | M78: =K78-I78 -> 0
B79: 6666020495 | C79: 6666020495 Non-deductible expense-travel. | D79: 不可扣除费用-旅行 | E79: 0.25476 | F79: 0.0054988129 | H79: 0 | I79: =H79/$J$30*1000 -> 0 | K79: =J79/$F$4*1000 -> 0 | L79: =K79-F79 -> -0.0054988129 | M79: =K79-I79 -> 0
B80: 6666020504 | C80: 6666020504 Newspaper and Periodicals expenditure | D80: 报纸和期刊支出 | E80: 0 | F80: 0 | H80: 0.051659191 | I80: =H80/$J$30*1000 -> 0.0010241711 | K80: =J80/$F$4*1000 -> 0 | L80: =K80-F80 -> 0 | M80: =K80-I80 -> -0.0010241711
B81: 6666020508 | C81: 6666020508 Postage | D81: 邮资 | E81: 0 | F81: 0 | H81: 0.42310304 | I81: =H81/$J$30*1000 -> 0.0083882442 | K81: =J81/$F$4*1000 -> 0 | L81: =K81-F81 -> 0 | M81: =K81-I81 -> -0.0083882442
B82: 6666020602 | C82: 6666020602 Training costs Outside the group | D82: 集团外培训费用 | E82: 0.08608 | F82: 0.0018579754 | H82: 1.9273007 | I82: =H82/$J$30*1000 -> 0.038209769 | K82: =J82/$F$4*1000 -> 0 | L82: =K82-F82 -> -0.0018579754 | M82: =K82-I82 -> -0.038209769
B83: 6666020701 | C83: 6666020701 Enterprise Property Insurance | D83: 企业财产保险 | E83: 0 | F83: 0 | H83: 0 | I83: =H83/$J$30*1000 -> 0 | K83: =J83/$F$4*1000 -> 0 | L83: =K83-F83 -> 0 | M83: =K83-I83 -> 0
B84: 6666020802 | C84: 6666020802 Equipment rental cost | D84: 设备租赁成本 | E84: 5.99021 | F84: 0.12929441 | H84: 12.783 | I84: =H84/$J$30*1000 -> 0.25342982 | K84: =J84/$F$4*1000 -> 0 | L84: =K84-F84 -> -0.12929441 | M84: =K84-I84 -> -0.25342982
B85: 6666020803 | C85: 6666020803 Car rental cost | D85: 汽车租赁成本 | E85: 4.7008 | F85: 0.10146341 | H85: 3.7583248 | I85: =H85/$J$30*1000 -> 0.0745108 | K85: =J85/$F$4*1000 -> 0 | L85: =K85-F85 -> -0.10146341 | M85: =K85-I85 -> -0.0745108
B86: 6666021100 | C86: 6666021100 Consulting fees | D86: 咨询费 | E86: 8.5915 | F86: 0.1854414 | H86: 5.6852745 | I86: =H86/$J$30*1000 -> 0.11271361 | K86: =J86/$F$4*1000 -> 0 | L86: =K86-F86 -> -0.1854414 | M86: =K86-I86 -> -0.11271361
B87: 6666021104 | C87: 6666021104 Consulting expense-Technical | D87: 技术咨询费用 | E87: 0 | F87: 0 | I87: =H87/$J$30*1000 -> 0 | K87: =J87/$F$4*1000 -> 0 | L87: =K87-F87 -> 0 | M87: =K87-I87 -> 0
B88: 6666021902 | C88: 6666021902 Cleaning fees | D88: 清洁费 | E88: 8.7418 | F88: 0.18868552 | H88: 7.8669409 | I88: =H88/$J$30*1000 -> 0.15596631 | K88: =J88/$F$4*1000 -> 0 | L88: =K88-F88 -> -0.18868552 | M88: =K88-I88 -> -0.15596631
B89: 6666022100 | C89: 6666022100 Security | D89: 保安 | E89: 1.33541 | F89: 0.028823872 | H89: 1.4569163 | I89: =H89/$J$30*1000 -> 0.028884145 | K89: =J89/$F$4*1000 -> 0 | L89: =K89-F89 -> -0.028823872 | M89: =K89-I89 -> -0.028884145
B90: 6666022300 | C90: 6666022300 Association dues | D90: 会费 | E90: 0 | F90: 0 | H90: 0 | I90: =H90/$J$30*1000 -> 0 | K90: =J90/$F$4*1000 -> 0 | L90: =K90-F90 -> 0 | M90: =K90-I90 -> 0
B91: 6666029700 | C91: 6666029700 Service fee recharge | D91: 服务费回收费 | E91: 0 | F91: 0 | H91: 0 | I91: =H91/$J$30*1000 -> 0 | K91: =J91/$F$4*1000 -> 0 | L91: =K91-F91 -> 0 | M91: =K91-I91 -> 0
B92: 6666029900 | C92: 6666029900 Sundry Expenses | D92: 杂项费用 | E92: 0 | F92: 0 | H92: 0 | I92: =H92/$J$30*1000 -> 0 | K92: =J92/$F$4*1000 -> 0 | L92: =K92-F92 -> 0 | M92: =K92-I92 -> 0
B93: 6666029996 | C93: 6666029996 Non-deductible expense-travel. | D93: 不可扣除费用-旅行 | E93: 0 | F93: 0 | I93: =H93/$J$30*1000 -> 0 | K93: =J93/$F$4*1000 -> 0 | L93: =K93-F93 -> 0 | M93: =K93-I93 -> 0
B94: 6666029997 | C94: 6666029997 restructure cost | D94: 重组成本 | E94: 0 | F94: 0 | H94: 0.58876284 | I94: =H94/$J$30*1000 -> 0.011672538 | K94: =J94/$F$4*1000 -> 0 | L94: =K94-F94 -> 0 | M94: =K94-I94 -> -0.011672538
B95: 6666030702 | C95: 6666030702 R&D prototype purchased | D95: R&D原型采购 | E95: 0 | F95: 0 | H95: 0 | I95: =H95/$J$30*1000 -> 0 | K95: =J95/$F$4*1000 -> 0 | L95: =K95-F95 -> 0 | M95: =K95-I95 -> 0
B96: 6666031200 | C96: 6666031200 Instrument fee | D96: 仪器费用 | E96: -0.01434 | F96: -0.00030951867 | H96: 0 | I96: =H96/$J$30*1000 -> 0 | K96: =J96/$F$4*1000 -> 0 | L96: =K96-F96 -> 0.00030951867 | M96: =K96-I96 -> 0
B97: 6666050107 | C97: 6666050107 Special distribution costs | D97: 特殊分配成本 | E97: 0.01244 | F97: 0.00026850853 | H97: 0 | I97: =H97/$J$30*1000 -> 0 | K97: =J97/$F$4*1000 -> 0 | L97: =K97-F97 -> -0.00026850853 | M97: =K97-I97 -> 0
B98: 6666070100 | C98: 6666070100 Software purchase, development and imple | D98: 软件采购、开发及实施 | E98: 0 | F98: 0 | H98: 0 | I98: =H98/$J$30*1000 -> 0 | K98: =J98/$F$4*1000 -> 0 | L98: =K98-F98 -> 0 | M98: =K98-I98 -> 0
B99: 6666070300 | C99: 6666070300 Software maintenance fees | D99: 软件维护费 | E99: 0 | F99: 0 | H99: 0 | I99: =H99/$J$30*1000 -> 0 | K99: =J99/$F$4*1000 -> 0 | L99: =K99-F99 -> 0 | M99: =K99-I99 -> 0
B100: 6666070400 | C100: 6666070400 IT maint. & repairs hardware | D100: IT维护及硬件修理 | E100: 2.74919 | F100: 0.059339305 | H100: 12.610957 | I100: =H100/$J$30*1000 -> 0.25001897 | K100: =J100/$F$4*1000 -> 0 | L100: =K100-F100 -> -0.059339305 | M100: =K100-I100 -> -0.25001897
B101: 5401050201 | C101: 5401050201 COGS-Special a | D101: 销售成本-特殊项目 | E101: 0 | F101: 0 | I101: =H101/$J$30*1000 -> 0 | K101: =J101/$F$4*1000 -> 0 | L101: =K101-F101 -> 0 | M101: =K101-I101 -> 0
...

Sheet 洗碗机4月
B1: 1月费用总结： ①单：1月同期35欧元/台，订单量4.86万台，预测单台费用36.4欧元/台，较同期↑3.9%；实际37.48欧元/台，较同期↑6% 共梳理出8个问题
A2: 总结：4月洗碗机单台下降10.19欧；降费41.6万欧 上涨因素：25万欧（定单量下降恶化15万欧，通胀恶化10万欧），下降因素：降费项目59万欧_x000b_固定：洗碗机4月折旧期限延长降费53万，订单量下降0.9万，负影响10万 变动：恶化4项，优化1项 1.存货跌价准备释放预提（超期库存钢卷加工成本成品）-18万欧 2.固定人工同期释放预提-4.19万欧 3.物耗：10万欧的钢卷制成半成品料废=2.6万 4.生产耗用：①钢卷半成品呆滞-6.6万欧 ② 一次性购买了5.6.7三个月的oil预防战争带来的涨价-4万欧 _x000b_
A3: 维度 | B3: 指标 | C3: 25年实际 | D3: 26年预算 | E3: 预算差异 | F3: 26年实际 | G3: 实际比同期差异 | I3: 制造费差额 | J3: 差异原因
A5: 单 | B5: 产量 | C5: 49360 | D5: 48050 | E5: =D5-C5 -> -1310 | F5: 40893 | G5: =F5-C5 -> -8467 | I5: /
A6: 时 | B6: 工作天数 | C6: 21 | D6: 19 | E6: =D6-C6 -> -2 | F6: 21 | G6: =F6-C6 -> 0
A7: 人 | B7: 直接人工 | C7: 218 | D7: 244 | E7: =D7-C7 -> 26 | F7: 222 | G7: =F7-C7 -> 4
B8: 直接人工工资 | C8: =E51/C7*1000 -> 1571.818 | D8: =G51/D7*1000 -> 1737.4776 | E8: =D8-C8 -> 165.65955 | F8: =J51/F7*1000 -> 0 | G8: =F8-C8 -> -1571.818
B9: 间接人工 | C9: 93 | D9: 85 | E9: =D9-C9 -> -8 | F9: 79 | G9: =F9-C9 -> -14
B10: 间接人工工资 | C10: =E131/C9*1000 -> 1607.3939 | D10: =G131/D9*1000 -> 1935.1706 | E10: =D10-C10 -> 327.77671 | F10: =G131/F9*1000 -> 2082.1456 | G10: =F10-C10 -> 474.75169
B11: 白领人数 | C11: 23 | D11: 27 | E11: =D11-C11 -> 4 | F11: 25 | G11: =F11-C11 -> 2
B12: 白领人工工资 | C12: =E134/C11*1000 -> 3754.4496 | D12: =G134/D11*1000 -> 3320.6683 | E12: =D12-C12 -> -433.78127 | F12: =G134/F11*1000 -> 3586.3218 | G12: =F12-C12 -> -168.1278
B13: 一线加辅助 | C13: =C7+C9 -> 311 | F13: =F7+F9 -> 301
B14: 工资 | C14: =E51+E131 -> 492.14396 | F14: =G51+G131 -> 588.43403
B15: 蓝领工资4月 | C15: =C14/C13*1000 -> 1582.4565 | F15: =F14/F13*1000 -> 1954.9303
A16: 效 | B16: UPPH | C16: =C5/C6/C7/7.5 -> 1.4376001 | D16: =D5/D6/D7/7.5 -> 1.3819385 | E16: =D16-C16 -> -0.055661664 | F16: =F5/F6/F7/7.5 -> 1.169541 | G16: =F16-C16 -> -0.26805915
A17: 费 | B17: 单台制造费 | C17: =SUM(C18:C30) -> 32.242707 | D17: =SUM(D18:D30) -> 38.494637 | E17: =D17-C17 -> 6.2519298 | F17: =SUM(F18:F30) -> 4.7344333 | G17: =F17-C17 -> -27.508274 | I17: =G17*$F$5 -> -1124895.8
B18: 折旧 | C18: 11.15487 | D18: 11.825835 | E18: =D18-C18 -> 0.67096456 | F18: =K45 -> 0 | G18: =F18-C18 -> -11.15487 | H18: =G18*$F$5 -> -456156.1 | I18: =G18*$F$5 -> -456156.1
B19: 运营费 | C19: 0.82253246 | D19: 1.187901 | E19: =D19-C19 -> 0.36536851 | F19: =K108 -> -0.00097816252 | G19: =F19-C19 -> -0.82351063 | H19: =G19*$F$5 -> -33675.82 | I19: =G19*$F$5 -> -33675.82 | J19: 清洁及安保团队月均降费8千欧-去年延续项目
B20: 存货跌价准备 | C20: 0.042204283 | D20: 0.17831098 | E20: =D20-C20 -> 0.1361067 | F20: =K115 -> 0 | G20: =F20-C20 -> -0.042204283 | H20: =G20*$F$5 -> -1725.8597 | I20: =G20*$F$5 -> -1725.8597 | J20: 为了消耗多余钢卷，把钢卷做成了半成品，冲减了3月的计提
B21: 固定能源费 | C21: 0.11169154 | D21: 0.1097176 | E21: =D21-C21 -> -0.0019739369 | F21: =K121 -> 0.09316998 | G21: =F21-C21 -> -0.018521559 | H21: =G21*$F$5 -> -757.40213 | I21: =G21*$F$5 -> -757.40213
B22: 间接人工成本-辅助人员 | C22: 4.2614578 | D22: 4.2601306 | E22: =D22-C22 -> -0.0013272011 | F22: =K132 -> 0 | G22: =F22-C22 -> -4.2614578 | H22: =G22*$F$5 -> -174263.79 | I22: =G22*$F$5 -> -174263.79
B23: 固定人工-白领 | C23: 1.1438671 | D23: 2.1712517 | E23: =D23-C23 -> 1.0273847 | F23: =K140 -> 0 | G23: =F23-C23 -> -1.1438671 | H23: =G23*$F$5 -> -46776.156 | I23: =G23*$F$5 -> -46776.156 | J23: 固定人工同期释放预提4.19万欧
B24: 半固定-班车/工作服 | C24: 2.5605976 | D24: 3.6878066 | E24: =D24-C24 -> 1.127209 | F24: =K153 -> 2.1089184 | G24: =F24-C24 -> -0.45167922 | H24: =G24*$F$5 -> -18470.518 | I24: =G24*$F$5 -> -18470.518
B25: 直接人工 | C25: 9.5030898 | D25: 10.602259 | E25: =D25-C25 -> 1.0991691 | F25: =K54 -> 0 | G25: =F25-C25 -> -9.5030898 | H25: =G25*$F$5 -> -388609.85 | I25: =G25*$F$5 -> -388609.85
B26: 可回收废料 | C26: 0.45784677 | D26: 0.40211803 | E26: =D26-C26 -> -0.055728738 | F26: 1.26 | G26: =F26-C26 -> 0.80215323 | H26: =G26*$F$5 -> 32802.452 | I26: =G26*$F$5 -> 32802.452 | J26: 钢卷制造成半成品产生了26千欧的废料
B27: 生产耗用品 | C27: -0.11774365 | D27: 0.33077003 | E27: =D27-C27 -> 0.44851369 | F27: =K113 -> 0 | G27: =F27-C27 -> 0.11774365 | H27: =G27*$F$5 -> 4814.8912 | I27: =G27*$F$5 -> 4814.8912 | J27: 一次性购买了5.6.7三个月的oil预防战争带来的涨价-4万欧 原材料库存损失此从17万调整至6.6万
B28: 废品回收 | C28: -1.5203565 | D28: -0.99579161 | E28: =D28-C28 -> 0.52456493 | F28: =K117 -> 0 | G28: =F28-C28 -> 1.5203565 | H28: =G28*$F$5 -> 62171.94 | I28: =G28*$F$5 -> 62171.94
B29: 变动能源费 | C29: 0.55576788 | D29: 0.74367454 | E29: =D29-C29 -> 0.18790666 | F29: =K124 -> 0.68642555 | G29: =F29-C29 -> 0.13065767 | H29: =G29*$F$5 -> 5342.984 | I29: =G29*$F$5 -> 5342.984
B30: 园区分摊费用 | C30: 3.2668823 | D30: 3.9906542 | E30: =D30-C30 -> 0.72377188 | F30: =K224 -> 0.58689751 | G30: =F30-C30 -> -2.6799848 | H30: =G30*$F$5 -> -109592.62 | I30: =G30*$F$5 -> -109592.62 | J30: 产量下降17%
B31: IT Expense-Internal Charge Out | C31: 2.0266765 | D31: 0.13958524 | E31: -0.1274777 | G31: =(F31/C31)-1 -> -1 | I31: =#REF!/$C$5 -> #REF!
B32: Association dues | C32: 0.10143468 | D32: 1.9635097 | E32: 0.24760611 | G32: =(F32/C32)-1 -> -1 | I32: =#REF!/$C$5 -> #REF!
B33: G&A | C33: 1.1387711 | D33: 1.8673518 | E33: 0.299214 | G33: =(F33/C33)-1 -> -1 | I33: =#REF!/$C$5 -> #REF!
A34: 类型 | B34: 科目编号 | C34: 科目（英文） | D34: 科目（中文） | E34: K€ | F34: 同期台数 | G34: 46330 | I34: 预算台数 | J34: 23500 | K34: 实际台数 | L34: 40893
E35: 25年实际制造费 | F35: 25年实际单台 | G35: 26年预测制造费 | I35: 26年预测单台 | J35: 26年实际制造费 | K35: 26年实际单台 | L35: 预算与实际单台差 | M35: 与同期差分析
A36: 折旧 | B36: 6666110101 | C36: 6666110101 Depreciation of buildings | D36: 建筑物折旧 | E36: 28.96203 | F36: 0.58675101 | G36: 31.49535 | I36: 0.65547035 | K36: =J36/$L$34*1000 -> 0
B37: 6666110106 | C37: 6666110106 Depreciation of R&D facilities | D37: 研发设施折旧 | E37: 0 | F37: 0 | G37: 0 | I37: 0 | K37: =J37/$L$34*1000 -> 0
B38: 6666110107 | C38: 6666110107 Depreciation of mold | D38: 模具折旧 | E38: 221.08877 | F38: 4.479108 | G38: 226.93983 | I38: 4.7229934 | K38: =J38/$L$34*1000 -> 0 | N38: 1.17
B39: 6666110110 | C39: 6666110110 Depreciation-Plant & Machinery | D39: 厂房及机械折旧 | E39: 284.06253 | F39: 5.7549135 | G39: 291.77164 | I39: 6.0722506 | K39: =J39/$L$34*1000 -> 0
B40: 6666110112 | C40: 6666110112 Depreciation of Furniture & Fixture | D40: 家具及装置折旧 | E40: 8.46194 | F40: 0.17143314 | G40: 15.243714 | I40: 0.31724691 | K40: =J40/$L$34*1000 -> 0
B41: 6666110204 | C41: 6666110204 Amortization of license, trademarks and | D41: 许可证、商标及摊销 | E41: 0.25252 | F41: 0.0051158833 | G41: 0.25252 | I41: 0.005255359 | K41: =J41/$L$34*1000 -> 0
B42: 6666110207 | C42: 6666110207 Amortization of Software | D42: 软件摊销 | E42: 6.89599 | F42: 0.13970806 | G42: 2.5282936 | I42: 0.052617973 | K42: =J42/$L$34*1000 -> 0
B43: 6666110506 | C43: 6666110506 Amortization-Leasehold Improvement | D43: 租赁改良摊销 | E43: 0.66327 | F43: 0.013437399 | G43: 0 | I43: 0 | K43: =J43/$L$34*1000 -> 0
B44: 6666110206 | C44: 6666110206 Amortization of Patents | D44: 专利摊销 | F44: 0 | I44: 0 | K44: =J44/$L$34*1000 -> 0
B45: FIX | C45: * CS_Depreciation | D45: * CS_折旧 | E45: 550.38705 | F45: 11.150467 | G45: 568.23135 | I45: 11.825835 | J45: =SUM(J36:J44) -> 0 | K45: =J45/$L$34*1000 -> 0
A46: 直接人工 | B46: 5001010205 | C46: 5001010205 Unemployment Insurance -blue collar-Dire | D46: 失业保险-蓝领-直接 | E46: 7.33205 | F46: 0.14854234 | G46: 8.7606392 | I46: 0.1823234 | K46: =J46/$L$34*1000 -> 0
B47: 6666010380 | C47: 6666010380 Incentive | D47: 激励 | E47: -1.42469 | F47: -0.02886325 | G47: -22.855605 | I47: -0.47566294 | K47: =J47/$L$34*1000 -> 0
B48: 6666010019 | C48: 6666010019 Payroll Taxes - Blue Collar Direct | E48: 58.63925 | F48: 1.1879913 | G48: 90.891632 | I48: 1.8916052 | K48: =J48/$L$34*1000 -> 0
B49: 6666010183 | C49: 6666010183 Overtime-Blue Collar-Direct | D49: 蓝领加班费-直接 | E49: 51.24566 | F49: 1.0382022 | G49: 0 | I49: 0 | K49: =J49/$L$34*1000 -> 0
B50: 6666010229 | C50: 6666010229 Staff Leaving Indemnity - Blue Collar Di | D50: 蓝领离职赔偿-直接 | E50: 10.77437 | F50: 0.2182814 | G50: ？ | I50: 0.18100607 | K50: =J50/$L$34*1000 -> 0
B51: 6666010188 | C51: 6666010188 Salary - Blue collar direct employees | D51: 蓝领直接员工工资 | E51: 342.65633 | F51: 6.941984 | G51: 423.94453 | I51: 8.8229871 | K51: =J51/$L$34*1000 -> 0
B52: 5102040406 | C52: 5102040406 Other revenue-Service/Secondment agreeme | D52: 其他收入-服务/派遣协议 | E52: 0 | F52: 0 | G52: 0 | I52: 0 | K52: =J52/$L$34*1000 -> 0
B53: 6666010115 | C53: 6666010115 Salary-Blue collar direct employees-Accr | D53: 蓝领直接员工工资-应计 | E53: -0.12195 | F53: -0.002470624 | G53: 0 | I53: 0 | K53: =J53/$L$34*1000 -> 0
B54: VAR | C54: * CS_Direct Labour | D54: * CS_直接劳动 | E54: 469.10102 | F54: 9.5036673 | G54: 509.43854 | I54: 10.602259 | J54: =SUM(J46:J53) -> 0 | K54: =J54/$L$34*1000 -> 0
A55: 可回收废料 | B55: 8701530201 | C55: 8701530201 Scrap-Raw Material - Managerial | D55: 废料-原材料-管理 | E55: 0 | F55: 0 | G55: 0 | I55: 0 | K55: =J55/$L$34*1000 -> 0
B56: 6666050309 | C56: 6666050309 SFG scrap | D56: SFG废料 | E56: 12.85146 | F56: 0.26036183 | G56: 19.321771 | I56: 0.40211803 | K56: =J56/$L$34*1000 -> 0
B57: 6666050308 | C57: 6666050308 Raw material scrap | D57: 原材料废料 | E57: 9.48485 | F57: 0.1921566 | G57: 0 | I57: 0 | K57: =J57/$L$34*1000 -> 0
B58: 6666050306 | C58: 6666050306 Finished goods scrap | D58: 成品废料 | E58: 0.26438 | F58: 0.0053561588 | G58: 0 | I58: 0 | K58: =J58/$L$34*1000 -> 0
B59: VAR | C59: * CS_SCRAP_VARIABLE | D59: * CS_废料变量 | E59: 22.60069 | F59: 0.45787459 | G59: 19.321771 | I59: 0.40211803 | J59: =SUM(J55:J58) -> 0 | K59: =J59/$L$34*1000 -> 0
A60: 组织运营 | B60: 5102010151 | C60: 5102010151 Other Rev.-Interco-Epidemic problem comp | D60: 其他收入-内部公司-疫情问题补偿 | E60: 0 | F60: 0 | G60: 0 | I60: 0 | K60: =J60/$L$34*1000 -> 0
B61: 5001010200 | C61: 5001010200 Cost of Manufacture - Raw Material | D61: 制造成本-原材料 | E61: 0 | F61: 0 | G61: 0 | I61: 0 | K61: =J61/$L$34*1000 -> 0
B62: 5001010201 | C62: 5001010201 Cost of Manufacture - Raw Material-Freig | D62: 制造成本-原材料-运费 | E62: 0 | F62: 0 | G62: 0 | I62: 0 | K62: =J62/$L$34*1000 -> 0
B63: 5207000011 | C63: 5207000011 Gain of tangible asset disposal | D63: 有形资产处置收益 | E63: 0 | F63: 0 | G63: 0 | I63: 0 | K63: =J63/$L$34*1000 -> 0
B64: 5207000012 | C64: 5207000012 Loss of tangible asset sold | D64: 出售有形资产损失 | E64: 0 | F64: 0 | G64: 0 | I64: 0 | K64: =J64/$L$34*1000 -> 0
B65: 5207000022 | C65: 5207000022 Loss of intangible asset disposal | D65: 无形资产处置损失 | E65: 0 | F65: 0 | G65: 0 | I65: 0 | K65: =J65/$L$34*1000 -> 0
B66: 5301060000 | C66: 5301060000 Other Income-Subsidy income | D66: 其他收入-补贴收入 | E66: 0 | F66: 0 | G66: 0 | I66: 0 | K66: =J66/$L$34*1000 -> 0
B67: 5301999999 | C67: 5301999999 Non-operation revenue-Other | D67: 非经营收入-其他 | E67: 0 | F67: 0 | G67: 0 | I67: 0 | K67: =J67/$L$34*1000 -> 0
B68: 5405030000 | C68: 5405030000 Other cost-others | D68: 其他成本-其他 | E68: 0.04654 | F68: 0.00094286872 | G68: 0 | I68: 0 | K68: =J68/$L$34*1000 -> 0
B69: 5601050000 | C69: 5601050000 Non-Operating Expense - Penalty | D69: 非经营费用-罚款 | E69: 0 | F69: 0 | G69: 0 | I69: 0 | K69: =J69/$L$34*1000 -> 0
B70: 5601050100 | C70: 5601050100 Non-operation Expense-Others | D70: 非经营费用-其他 | E70: 0 | F70: 0 | G70: 0 | I70: 0 | K70: =J70/$L$34*1000 -> 0
B71: 5102040893 | C71: 5102040893 Other revenue-Charge out-Test Expense | D71: 其他收入-费用支出-测试费用 | E71: 0 | F71: 0 | I71: 0 | K71: =J71/$L$34*1000 -> 0
B72: 5801000041 | C72: 5801000041 Previous year Sundry cost | D72: 去年杂项成本 | E72: 0 | F72: 0 | G72: 0 | I72: 0 | K72: =J72/$L$34*1000 -> 0
B73: 6666010322 | C73: 6666010322 fuel allowance | D73: 燃料津贴 | E73: 1.01857 | F73: 0.020635535 | G73: 1.9236502 | I73: 0.040034344 | K73: =J73/$L$34*1000 -> 0
B74: 6666020101 | C74: 6666020101 Entertainment | D74: 娱乐 | E74: 5.145 | F74: 0.1042342 | G74: 4.4647074 | I74: 0.092917947 | K74: =J74/$L$34*1000 -> 0
B75: 6666020201 | C75: 6666020201 Domestic business travel | D75: 国内商务旅行 | E75: 0 | F75: 0 | G75: 2.4252945 | I75: 0.050474392 | K75: =J75/$L$34*1000 -> 0
B76: 6666020202 | C76: 6666020202 Overseas business travel | D76: 海外商务旅行 | E76: 0 | F76: 0 | G76: 0 | I76: 0 | K76: =J76/$L$34*1000 -> 0
B77: 6666020204 | C77: 6666020204 Travel expense pay to agency | D77: 支付给代理的旅行费用 | E77: 0.01149 | F77: 0.00023277958 | G77: 0 | I77: 0 | K77: =J77/$L$34*1000 -> 0
B78: 6666020205 | C78: 6666020205 Business travel-other | D78: 商务旅行-其他 | E78: 0 | F78: 0 | G78: 0 | I78: 0 | K78: =J78/$L$34*1000 -> 0
B79: 6666020301 | C79: 6666020301 Staff communic | D79: 员工通讯 | E79: 0.50942 | F79: 0.010320502 | G79: 0.35949374 | I79: 0.0074816596 | K79: =J79/$L$34*1000 -> 0
B80: 6666020302 | C80: 6666020302 Communication Expenses | D80: 通讯费用 | E80: 0 | F80: 0 | G80: 0.040997661 | I80: 0.00085322915 | K80: =J80/$L$34*1000 -> 0
B81: 6666020403 | C81: 6666020403 Company car expense | D81: 公司车辆费用 | F81: 0 | I81: 0 | K81: =J81/$L$34*1000 -> 0
B82: 6666020405 | C82: 6666020405 Company car expense - maintenance fees | D82: 公司车辆费用-维护费 | E82: 0 | F82: 0 | G82: 0 | I82: 0 | K82: =J82/$L$34*1000 -> 0
B83: 6666020495 | C83: 6666020495 Non-deductible expense-travel. | D83: 不可扣除费用-旅行 | E83: 0.2377 | F83: 0.0048156402 | G83: 0 | I83: 0 | K83: =J83/$L$34*1000 -> 0
B84: 6666020504 | C84: 6666020504 Newspaper and Periodicals expenditure | D84: 报纸和期刊支出 | E84: 0 | F84: 0 | G84: 0.050895755 | I84: 0.0010592249 | K84: =J84/$L$34*1000 -> 0
B85: 6666020508 | C85: 6666020508 Postage | D85: 邮资 | E85: 0.00496 | F85: 0.00010048622 | G85: 0.41685028 | I85: 0.0086753441 | K85: =J85/$L$34*1000 -> 0
B86: 6666020602 | C86: 6666020602 Training costs Outside the group | D86: 集团外培训费用 | E86: 0 | F86: 0 | G86: 1.8988185 | I86: 0.039517554 | K86: =J86/$L$34*1000 -> 0
B87: 6666020701 | C87: 6666020701 Enterprise Property Insurance | D87: 企业财产保险 | E87: 0 | F87: 0 | G87: 0 | I87: 0 | K87: =J87/$L$34*1000 -> 0
B88: 6666020802 | C88: 6666020802 Equipment rental cost | D88: 设备租赁成本 | E88: 10.50561 | F88: 0.21283651 | G88: 12.783 | I88: 0.26603538 | K88: =J88/$L$34*1000 -> 0
B89: 6666020803 | C89: 6666020803 Car rental cost | D89: 汽车租赁成本 | E89: 3.00868 | F89: 0.060953809 | G89: 3.702783 | I89: 0.077061041 | K89: =J89/$L$34*1000 -> 0
B90: 6666021100 | C90: 6666021100 Consulting fees | D90: 咨询费 | E90: 6.58522 | F90: 0.13341207 | G90: 5.6012556 | I90: 0.1165714 | K90: =J90/$L$34*1000 -> 0
B91: 6666021104 | C91: 6666021104 Consulting expense-Technical | D91: 技术咨询费用 | E91: 0 | F91: 0 | I91: 0 | K91: =J91/$L$34*1000 -> 0
B92: 6666021902 | C92: 6666021902 Cleaning fees | D92: 清洁费 | E92: 7.40652 | F92: 0.15005105 | G92: 7.7506807 | I92: 0.16130449 | K92: =J92/$L$34*1000 -> 0
B93: 6666022100 | C93: 6666022100 Security | D93: 保安 | E93: 1.29905 | F93: 0.026317869 | G93: 1.4353855 | I93: 0.029872747 | K93: =J93/$L$34*1000 -> 0
B94: 6666022300 | C94: 6666022300 Association dues | D94: 会费 | E94: 0 | F94: 0 | G94: 0 | I94: 0 | K94: =J94/$L$34*1000 -> 0
B95: 6666029700 | C95: 6666029700 Service fee recharge | D95: 服务费回收费 | E95: 0 | F95: 0 | G95: 0 | I95: 0 | K95: =J95/$L$34*1000 -> 0
B96: 6666029900 | C96: 6666029900 Sundry Expenses | D96: 杂项费用 | E96: 0 | F96: 0 | G96: 0 | I96: 0 | K96: =J96/$L$34*1000 -> 0
B97: 6666029996 | C97: 6666029996 Non-deductible expense-travel. | D97: 不可扣除费用-旅行 | E97: 0 | F97: 0 | I97: 0 | K97: =J97/$L$34*1000 -> 0
B98: 6666029997 | C98: 6666029997 restructure cost | D98: 重组成本 | E98: 0 | F98: 0 | G98: 0.58006191 | I98: 0.012072048 | K98: =J98/$L$34*1000 -> 0
B99: 6666030702 | C99: 6666030702 R&D prototype purchased | D99: R&D原型采购 | E99: 0 | F99: 0 | G99: 0 | I99: 0 | K99: =J99/$L$34*1000 -> 0
B100: 6666031200 | C100: 6666031200 Instrument fee | D100: 仪器费用 | E100: -0.03 | F100: -0.00060777958 | G100: 0 | I100: 0 | K100: =J100/$L$34*1000 -> 0
B101: 6666050107 | C101: 6666050107 Special distribution costs | D101: 特殊分配成本 | E101: 0 | F101: 0 | G101: 0 | I101: 0 | K101: =J101/$L$34*1000 -> 0
...

Sheet 洗碗机5月
B1: 1月费用总结： ①单：1月同期35欧元/台，订单量4.86万台，预测单台费用36.4欧元/台，较同期↑3.9%；实际37.48欧元/台，较同期↑6% 共梳理出8个问题
A2: 5月费用实际：_x000b_①单台：5月实际55.28欧，5月同期30.17欧。较同期↑20.52欧，恶化68万。_x000b_②主要影响：人工工资上涨及通胀影响约11万欧；_x000b_③扣除影响后：单台↑17.20欧，恶化57万欧 ④固定费用异常：折旧整体降费15万，单台恶化2.33欧，影响7.68万欧，原因：产量下降38%,假期错月，次月补差 ⑤变动费用异常：蓝领直接员工工资与预算差异5.8万欧，原因： 1. 制造费影响：加班费未预测，+15.0。 2. 单价/价格影响：节日福利科目预测时人工录入错误。，+30.0。 3. 单价/价格影响：薪资结构影响，+6.0。 4. 单价/价格影响：还未休年假计提，+5.5。 5. 单价/价格影响：离职补偿金，+1.5。 库存跌价准备-原材料与预算差异3.8万欧，原因： 1.Super-entry 项目转产青岛，相关项目零件库龄风险增加：+65K。 2.其他活跃物料风险下降：-27K。 _x000b_
A3: 预测和实际的差（不考虑产量因素）： 总费用实际与4＋8预测差异13.2万欧 1,折旧费用：差异-2.5万欧 2.变动费用：①直接人工：差异5.8万欧 ②生产耗用：差异1.3万欧-具体哪个科目未知 ③变动能源：差异1.0万欧 ②存货跌价准备：差异3.8万欧 3.园区分摊费用：① 5601050100 非经营费用-其他：差异5.3万欧
A4: 维度 | B4: 指标 | C4: 25年实际 | D4: 26年预算 | E4: 26年实际 | F4: 实际比同期差异 | G4: 制造费差额 | H4: 差异原因
A6: 单 | B6: 产量 | C6: 53704 | D6: 36788 | E6: 33043 | F6: =E6-C6 -> -20661
A7: 时 | B7: 工作天数 | C7: 21 | D7: 14 | E7: 21 | F7: =IF(E7="","",E7-C7) -> 0 | I7: =110000/E6 -> 3.3289956
A8: 人 | B8: 直接人工 | C8: 226 | D8: 247 | E8: 164 | F8: -62
B9: 直接人工工资 | C9: =E46/C8*1000 -> 1638.1892 | D9: =G46/D8*1000 -> 1948.6038 | E9: 2918.5846 | F9: 1280.3954
B10: 间接人工 | C10: 93 | D10: 85 | E10: 75 | F10: -18
B11: 间接人工工资 | C11: =E126/C10*1000 -> 1818.4072 | D11: =G126/D10*1000 -> 2196.4172 | E11: 3303.7415 | F11: 1485.3343
B12: 白领人数 | C12: 23 | D12: 27 | E12: 24.67 | F12: 1.67
B13: 白领人工工资 | C13: =E129/C12*1000 -> 2829.583 | D13: =G129/D12*1000 -> 3529.4159 | E13: 4360.4066 | F13: 1530.8235
A14: 效 | B14: UPPH | C14: =C6/C7/(C8+C10)/7.5 -> 1.0688959 | D14: =D6/D7/(D8+D10)/7.5 -> 1.0553069 | E14: =E6/E7/(E8+E10)/7.5 -> 0.87781098 | F14: =IF(E14="","",E14-C14) -> -0.19108487
A15: 费 | B15: 单台制造费 | C15: =SUM(C16:C28) -> 34.764394 | D15: =SUM(D16:D28) -> 52.432012 | E15: =SUM(E16:E28) -> 55.281223 | F15: =E15-C15 -> 20.516829 | G15: =F15*$E$6 -> 677937.58
B16: 折旧 | C16: 10.791543 | D16: 15.772406 | E16: =$J$40 -> 13.113671 | F16: =E16-C16 -> 2.3221282 | G16: =F16*$E$6 -> 76730.081 | H16: =E16*E6 -> 433315.02 | I16: =H16/C6 -> 8.06858
B17: 运营费 | C17: 0.70691531 | D17: 1.5337617 | E17: =$J$103 -> 1.1906613 | F17: =E17-C17 -> 0.48374595 | G17: =F17*$E$6 -> 15984.417 | H17: =E16-I16 -> 5.0450907 | I17: =H17*E6 -> 166704.93
B18: 存货跌价准备 | C18: 0.038792827 | D18: 0.22945591 | E18: =$J$110 -> 1.3927912 | F18: =E18-C18 -> 1.3539984 | G18: =F18*$E$6 -> 44740.169
B19: 固定能源费 | C19: 0.1248583 | D19: 0.095942022 | E19: =$J$116 -> 0.04419635 | F19: =E19-C19 -> -0.080661947 | G19: =F19*$E$6 -> -2665.3127
B20: 间接人工成本-辅助人员 | C20: 4.4930908 | D20: 6.2108564 | E20: =$J$127 -> 7.4987324 | F20: =E20-C20 -> 3.0056416 | G20: =F20*$E$6 -> 99315.415
B21: 固定人工-白领 | C21: 1.5134612 | D21: 3.0107146 | E21: =$J$135 -> 3.2554922 | F21: =E21-C21 -> 1.742031 | G21: =F21*$E$6 -> 57561.932
B22: 半固定-班车/工作服 | C22: 2.5109569 | D22: 4.2326322 | E22: =$J$148 -> 5.0600651 | F22: =E22-C22 -> 2.5491082 | G22: =F22*$E$6 -> 84230.181
B23: 直接人工 | C23: 10.483577 | D23: 15.731221 | E23: =$J$49 -> 14.485606 | F23: =E23-C23 -> 4.0020287 | G23: =F23*$E$6 -> 132239.03
B24: 可回收废料 | C24: 0.52579249 | D24: 0.3955878 | E24: =$J$54 -> 0.48679599 | F24: =E24-C24 -> -0.038996499 | G24: =F24*$E$6 -> -1288.5613
B25: 生产耗用品 | C25: 0.33064148 | D25: 0.3183375 | E25: =$J$108 -> 0.7296211 | F25: =E25-C25 -> 0.39897962 | G25: =F25*$E$6 -> 13183.484
B26: 废品回收 | C26: -1.163369 | D26: -0.98422491 | E26: =$J$112 -> -1.0926626 | F26: =E26-C26 -> 0.070706432 | G26: =F26*$E$6 -> 2336.3526
B27: 变动能源费 | C27: 0.74202238 | D27: 0.65296291 | E27: =$J$119 -> 0.95746815 | F27: =E27-C27 -> 0.21544577 | G27: =F27*$E$6 -> 7118.9744
B28: 园区分摊费用 | C28: 3.6661115 | D28: 5.2323577 | E28: =$J$219 -> 8.1587852 | F28: =E28-C28 -> 4.4926738 | G28: =F28*$E$6 -> 148451.42
A29: 类型 | B29: 科目编号 | C29: 科目（英文） | D29: 科目（中文） | E29: K€ | F29: 同期台数 | G29: 46330 | H29: 预算台数 | I29: 23500 | J29: 实际台数 | K29: 33043 | N29: 4＋8预测产量 | O29: 36000
E30: 25年实际制造费 | F30: 25年实际单台 | G30: 26年预算制造费 | H30: 26年预算单台 | I30: 26年实际制造费 | J30: 26年实际单台 | K30: 同期与实际单台差 | L30: 预算与实际单台差 | M30: 与同期差分析 | N30: 26年预测制造费 | O30: 26年预测单台 | P30: 26年预测单台 | Q30: 费用差 | R30: 预测与实际单台差
A31: 折旧 | B31: 6666110101 | C31: 6666110101 Depreciation of buildings | D31: 建筑物折旧 | E31: 30.081668 | F31: 0.56018004 | G31: 32.511052 | H31: 0.88393289 | I31: 31.88331 | J31: 0.96490361 | K31: =J31-F31 -> 0.40472357 | L31: 0.08097072 | N31: 449.59836 | O31: =N31*1000/$O$29 -> 12.488843 | P31: =O31 -> 12.488843 | R31: =J31-P31 -> -11.52394
B32: 6666110106 | C32: 6666110106 Depreciation of R&D facilities | D32: 研发设施折旧 | E32: 0 | F32: 0 | G32: 0 | H32: 0 | I32: 0 | J32: 0 | K32: =J32-F32 -> 0 | L32: 0 | N32: 0 | O32: =N32*1000/$O$29 -> 0 | P32: =O32 -> 0 | R32: =J32-P32 -> 0
B33: 6666110107 | C33: 6666110107 Depreciation of mold | D33: 模具折旧 | E33: 230.92979 | F33: 4.3003685 | G33: 230.14195 | H33: 6.2572581 | I33: 163.43183 | J33: 4.9460349 | K33: =J33-F33 -> 0.64566641 | L33: -1.3112232 | M33: =K33*$K$29 -> 21334.755 | N33: 2.22095 | O33: =N33*1000/$O$29 -> 0.061693056 | P33: =O33 -> 0.061693056 | R33: =J33-P33 -> 4.8843418
B34: 6666110110 | C34: 6666110110 Depreciation-Plant & Machinery | D34: 厂房及机械折旧 | E34: 299.32499 | F34: 5.5740222 | G34: 300.83235 | H34: 8.1792374 | I34: 232.99299 | J34: 7.0512057 | K34: =J34-F34 -> 1.4771835 | L34: -1.1280317 | M34: =K34*$K$29 -> 48810.576 | N34: 4.4154389 | O34: =N34*1000/$O$29 -> 0.12265108 | P34: =O34 -> 0.12265108 | R34: =J34-P34 -> 6.9285546
B35: 6666110112 | C35: 6666110112 Depreciation of Furniture & Fixture | D35: 家具及装置折旧 | E35: 11.262015 | F35: 0.20972095 | G35: 13.930613 | H35: 0.37875512 | I35: 3.99885 | J35: 0.12101958 | K35: =J35-F35 -> -0.088701365 | L35: -0.25773554 | N35: 2.3742258 | O35: =N35*1000/$O$29 -> 0.065950717 | P35: =O35 -> 0.065950717 | R35: =J35-P35 -> 0.055068864
B36: 6666110204 | C36: 6666110204 Amortization of license, trademarks and | D36: 许可证、商标及摊销 | E36: 0.25251497 | F36: 0.0047023272 | G36: 0.25251 | H36: 0.006865416 | I36: 0.07576 | J36: 0.00229277 | K36: =J36-F36 -> -0.0024095572 | L36: -0.004572646 | N36: 0 | O36: =N36*1000/$O$29 -> 0 | P36: =O36 -> 0 | R36: =J36-P36 -> 0.00229277
B37: 6666110207 | C37: 6666110207 Amortization of Software | D37: 软件摊销 | E37: 6.7839525 | F37: 0.12633059 | G37: 2.5668029 | H37: 0.069788008 | I37: 0.93228 | J37: 0.028214145 | K37: =J37-F37 -> -0.098116441 | L37: -0.041573863 | N37: 0 | O37: =N37*1000/$O$29 -> 0 | P37: =O37 -> 0 | R37: =J37-P37 -> 0.028214145
B38: 6666110506 | C38: 6666110506 Amortization-Leasehold Improvement | D38: 租赁改良摊销 | E38: 0.68159 | F38: 0.012692551 | G38: 0 | H38: 0 | I38: 0 | J38: 0 | K38: =J38-F38 -> -0.012692551 | L38: 0 | N38: 0 | O38: =N38*1000/$O$29 -> 0 | P38: =O38 -> 0 | R38: =J38-P38 -> 0
B39: 6666110206 | C39: 6666110206 Amortization of Patents | D39: 专利摊销 | F39: 0 | H39: 0 | I39: 0 | J39: 0 | K39: =J39-F39 -> 0 | L39: 0 | N39: 0 | O39: =N39*1000/$O$29 -> 0 | P39: =O39 -> 0 | R39: =J39-P39 -> 0
B40: FIX | C40: * CS_Depreciation | D40: * CS_折旧 | E40: 579.31652 | F40: 10.788017 | G40: 580.23528 | H40: 15.775837 | I40: 433.31502 | J40: 13.113671 | K40: =J40-F40 -> 2.3256536 | L40: -2.6621663 | M40: =K40*$K$29 -> 76846.572 | N40: =SUM(N31:N39) -> 458.60897 | O40: =N40*1000/$O$29 -> 12.739138 | P40: =O40 -> 12.739138 | Q40: =I40-N40 -> -25.293954 | R40: =J40-P40 -> 0.37453252
A41: 直接人工 | B41: 5001010205 | C41: 5001010205 Unemployment Insurance -blue collar-Dire | D41: 失业保险-蓝领-直接 | E41: 9.34405 | F41: 0.17400466 | G41: 10.118543 | H41: 0.27510992 | I41: 7.1399794 | J41: 0.21608145 | K41: =J41-F41 -> 0.042076795 | L41: -0.059028468 | N41: 0 | O41: =N41*1000/$O$29 -> 0 | P41: =O41 -> 0 | R41: =J41-P41 -> 0.21608145
B42: 6666010380 | C42: 6666010380 Incentive | D42: 激励 | E42: -0.35328 | F42: -0.0065787709 | G42: -26.252196 | H42: -0.71376281 | I42: -3.83977 | J42: -0.11620525 | K42: =J42-F42 -> -0.10962648 | L42: 0.59755757 | N42: 0 | O42: =N42*1000/$O$29 -> 0 | P42: =O42 -> 0 | R42: =J42-P42 -> -0.11620525
B43: 6666010019 | C43: 6666010019 Payroll Taxes - Blue Collar Direct | E43: 73.69048 | F43: 1.3722622 | G43: 104.97988 | H43: 2.8542654 | I43: 61.079734 | J43: 1.8484924 | K43: =J43-F43 -> 0.47623018 | L43: -1.005773 | N43: 420.50179 | O43: =N43*1000/$O$29 -> 11.680605 | P43: =O43 -> 11.680605 | R43: =J43-P43 -> -9.8321128
B44: 6666010183 | C44: 6666010183 Overtime-Blue Collar-Direct | D44: 蓝领加班费-直接 | E44: 94.37846 | F44: 1.7575132 | G44: 0 | H44: 0 | I44: 16.554552 | J44: 0.50100028 | K44: =J44-F44 -> -1.2565129 | L44: 0.50100028 | M44: =K44*$K$29 -> -41518.957 | N44: 0 | O44: =N44*1000/$O$29 -> 0 | P44: =O44 -> 0 | R44: =J44-P44 -> 0.50100028
B45: 6666010229 | C45: 6666010229 Staff Leaving Indemnity - Blue Collar Di | D45: 蓝领离职赔偿-直接 | E45: 10.89326 | F45: 0.202854 | G45: 8.5688093 | H45: 0.2329747 | I45: 10.4602 | J45: 0.31656327 | K45: =J45-F45 -> 0.11370926 | L45: 0.08358857 | N45: 0 | O45: =N45*1000/$O$29 -> 0 | P45: =O45 -> 0 | R45: =J45-P45 -> 0.31656327
B46: 6666010188 | C46: 6666010188 Salary - Blue collar direct employees | D46: 蓝领直接员工工资 | E46: 370.23077 | F46: 6.8944277 | G46: 481.30513 | H46: 13.086056 | I46: 381.56738 | J46: 11.547601 | K46: =J46-F46 -> 4.6531732 | L46: -1.5384548 | M46: =K46*$K$29 -> 153754.8 | N46: 0 | O46: =N46*1000/$O$29 -> 0 | P46: =O46 -> 0 | R46: =J46-P46 -> 11.547601
B47: 5102040406 | C47: 5102040406 Other revenue-Service/Secondment agreeme | D47: 其他收入-服务/派遣协议 | E47: 0 | F47: 0 | G47: 0 | H47: 0 | I47: 0 | J47: 0 | K47: =J47-F47 -> 0 | L47: 0 | N47: 0 | O47: =N47*1000/$O$29 -> 0 | P47: =O47 -> 0 | R47: =J47-P47 -> 0
B48: 6666010115 | C48: 6666010115 Salary-Blue collar direct employees-Accr | D48: 蓝领直接员工工资-应计 | E48: 4.82629 | F48: 0.089875047 | G48: 0 | H48: 0 | I48: 5.6858 | J48: 0.17207275 | K48: =J48-F48 -> 0.082197707 | L48: 0.17207275 | N48: 0 | O48: =N48*1000/$O$29 -> 0 | P48: =O48 -> 0 | R48: =J48-P48 -> 0.17207275
B49: VAR | C49: * CS_Direct Labour | D49: * CS_直接劳动 | E49: 563.01003 | F49: 10.484358 | G49: 578.72017 | H49: 15.734643 | I49: 478.64787 | J49: 14.485606 | K49: =J49-F49 -> 4.0012478 | L49: -1.2490371 | M49: =K49*$K$29 -> 132213.23 | N49: =SUM(N41:N48) -> 420.50179 | O49: =N49*1000/$O$29 -> 11.680605 | P49: =O49 -> 11.680605 | Q49: =I49-N49 -> 58.146088 | R49: =J49-P49 -> 2.8050007
A50: 可回收废料 | B50: 8701530201 | C50: 8701530201 Scrap-Raw Material - Managerial | D50: 废料-原材料-管理 | E50: 0 | F50: 0 | G50: 0 | H50: 0 | I50: 0 | J50: 0 | K50: =J50-F50 -> 0 | L50: 0 | N50: 0 | O50: =N50*1000/$O$29 -> 0 | P50: =O50 -> 0 | R50: =J50-P50 -> 0
B51: 6666050309 | C51: 6666050309 SFG scrap | D51: SFG废料 | E51: 15.24772 | F51: 0.28394264 | G51: 14.552884 | H51: 0.39567385 | I51: 3.73302 | J51: 0.11297461 | K51: =J51-F51 -> -0.17096804 | L51: -0.28269924 | N51: 14.74 | O51: =N51*1000/$O$29 -> 0.40944444 | P51: =O51 -> 0.40944444 | R51: =J51-P51 -> -0.29646984
B52: 6666050308 | C52: 6666050308 Raw material scrap | D52: 原材料废料 | E52: 12.98944 | F52: 0.24188901 | G52: 0 | H52: 0 | I52: 11.78646 | J52: 0.35670066 | K52: =J52-F52 -> 0.11481165 | L52: 0.35670066 | N52: 0 | O52: =N52*1000/$O$29 -> 0 | P52: =O52 -> 0 | R52: =J52-P52 -> 0.35670066
B53: 6666050306 | C53: 6666050306 Finished goods scrap | D53: 成品废料 | E53: 0 | F53: 0 | G53: 0 | H53: 0 | I53: 0.56572 | J53: 0.017120721 | K53: =J53-F53 -> 0.017120721 | L53: 0.017120721 | N53: 0 | O53: =N53*1000/$O$29 -> 0 | P53: =O53 -> 0 | R53: =J53-P53 -> 0.017120721
B54: VAR | C54: * CS_SCRAP_VARIABLE | D54: * CS_废料变量 | E54: 28.23716 | F54: 0.52583166 | G54: 14.552884 | H54: 0.39567385 | I54: 16.0852 | J54: 0.48679599 | K54: =J54-F54 -> -0.039035664 | L54: 0.091122145 | N54: =SUM(N50:N53) -> 14.74 | O54: =N54*1000/$O$29 -> 0.40944444 | P54: =O54 -> 0.40944444 | Q54: =I54-N54 -> 1.3452 | R54: =J54-P54 -> 0.077351549
A55: 组织运营 | B55: 5102010151 | C55: 5102010151 Other Rev.-Interco-Epidemic problem comp | D55: 其他收入-内部公司-疫情问题补偿 | E55: 0 | F55: 0 | G55: 0 | H55: 0 | I55: 0 | J55: 0 | K55: =J55-F55 -> 0 | L55: 0 | N55: 0 | O55: =N55*1000/$O$29 -> 0 | P55: =O55 -> 0 | R55: =J55-P55 -> 0
B56: 5001010200 | C56: 5001010200 Cost of Manufacture - Raw Material | D56: 制造成本-原材料 | E56: 0.01851 | F56: 0.00034469274 | G56: 0 | H56: 0 | I56: 0 | J56: 0 | K56: =J56-F56 -> -0.00034469274 | L56: 0 | N56: 0 | O56: =N56*1000/$O$29 -> 0 | P56: =O56 -> 0 | R56: =J56-P56 -> 0
B57: 5001010201 | C57: 5001010201 Cost of Manufacture - Raw Material-Freig | D57: 制造成本-原材料-运费 | E57: 0.00247 | F57: 4.5996276e-05 | G57: 0 | H57: 0 | I57: 0 | J57: 0 | K57: =J57-F57 -> -4.5996276e-05 | L57: 0 | N57: 0 | O57: =N57*1000/$O$29 -> 0 | P57: =O57 -> 0 | R57: =J57-P57 -> 0
B58: 5207000011 | C58: 5207000011 Gain of tangible asset disposal | D58: 有形资产处置收益 | E58: 0 | F58: 0 | G58: 0 | H58: 0 | I58: 0 | J58: 0 | K58: =J58-F58 -> 0 | L58: 0 | N58: 1.5 | O58: =N58*1000/$O$29 -> 0.041666667 | P58: =O58 -> 0.041666667 | R58: =J58-P58 -> -0.041666667
B59: 5207000012 | C59: 5207000012 Loss of tangible asset sold | D59: 出售有形资产损失 | E59: 0 | F59: 0 | G59: 0 | H59: 0 | I59: 0 | J59: 0 | K59: =J59-F59 -> 0 | L59: 0 | N59: 0 | O59: =N59*1000/$O$29 -> 0 | P59: =O59 -> 0 | R59: =J59-P59 -> 0
B60: 5207000022 | C60: 5207000022 Loss of intangible asset disposal | D60: 无形资产处置损失 | E60: 0 | F60: 0 | G60: 0 | H60: 0 | I60: 0 | J60: 0 | K60: =J60-F60 -> 0 | L60: 0 | N60: 0 | O60: =N60*1000/$O$29 -> 0 | P60: =O60 -> 0 | R60: =J60-P60 -> 0
B61: 5301060000 | C61: 5301060000 Other Income-Subsidy income | D61: 其他收入-补贴收入 | E61: 0 | F61: 0 | G61: 0 | H61: 0 | I61: -0.0285 | J61: -0.00086251248 | K61: =J61-F61 -> -0.00086251248 | L61: -0.00086251248 | N61: 0 | O61: =N61*1000/$O$29 -> 0 | P61: =O61 -> 0 | R61: =J61-P61 -> -0.00086251248
B62: 5301999999 | C62: 5301999999 Non-operation revenue-Other | D62: 非经营收入-其他 | E62: 0 | F62: 0 | G62: 0 | H62: 0 | I62: -0.39233 | J62: -0.011873317 | K62: =J62-F62 -> -0.011873317 | L62: -0.011873317 | N62: 0 | O62: =N62*1000/$O$29 -> 0 | P62: =O62 -> 0 | R62: =J62-P62 -> -0.011873317
B63: 5405030000 | C63: 5405030000 Other cost-others | D63: 其他成本-其他 | E63: 0.00024 | F63: 4.4692737e-06 | G63: 0 | H63: 0 | I63: -0.08243 | J63: -0.0024946282 | K63: =J63-F63 -> -0.0024990975 | L63: -0.0024946282 | N63: 0 | O63: =N63*1000/$O$29 -> 0 | P63: =O63 -> 0 | R63: =J63-P63 -> -0.0024946282
B64: 5601050000 | C64: 5601050000 Non-Operating Expense - Penalty | D64: 非经营费用-罚款 | E64: 0 | F64: 0 | G64: 0 | H64: 0 | I64: 0 | J64: 0 | K64: =J64-F64 -> 0 | L64: 0 | N64: 0 | O64: =N64*1000/$O$29 -> 0 | P64: =O64 -> 0 | R64: =J64-P64 -> 0
B65: 5601050100 | C65: 5601050100 Non-operation Expense-Others | D65: 非经营费用-其他 | E65: 0 | F65: 0 | G65: 0 | H65: 0 | I65: 0.2642 | J65: 0.007995642 | K65: =J65-F65 -> 0.007995642 | L65: 0.007995642 | N65: 0 | O65: =N65*1000/$O$29 -> 0 | P65: =O65 -> 0 | R65: =J65-P65 -> 0.007995642
B66: 5102040893 | C66: 5102040893 Other revenue-Charge out-Test Expense | D66: 其他收入-费用支出-测试费用 | E66: 0 | F66: 0 | H66: 0 | I66: 0 | J66: 0 | K66: =J66-F66 -> 0 | L66: 0 | N66: 0 | O66: =N66*1000/$O$29 -> 0 | P66: =O66 -> 0 | R66: =J66-P66 -> 0
B67: 5801000041 | C67: 5801000041 Previous year Sundry cost | D67: 去年杂项成本 | E67: 0 | F67: 0 | G67: 0 | H67: 0 | I67: 0 | J67: 0 | K67: =J67-F67 -> 0 | L67: 0 | N67: 0 | O67: =N67*1000/$O$29 -> 0 | P67: =O67 -> 0 | R67: =J67-P67 -> 0
B68: 6666010322 | C68: 6666010322 fuel allowance | D68: 燃料津贴 | E68: 1.25877 | F68: 0.023440782 | G68: 1.8952219 | H68: 0.0515286 | I68: -0.58441 | J68: -0.017686348 | K68: =J68-F68 -> -0.04112713 | L68: -0.069214948 | N68: 1.8952219 | O68: =N68*1000/$O$29 -> 0.052645053 | P68: =O68 -> 0.052645053 | R68: =J68-P68 -> -0.070331401
B69: 6666020101 | C69: 6666020101 Entertainment | D69: 娱乐 | E69: 5.07662 | F69: 0.094536685 | G69: 4.3987265 | H69: 0.11959561 | I69: 1.25782 | J69: 0.038066156 | K69: =J69-F69 -> -0.056470529 | L69: -0.081529452 | N69: 7.4642973 | O69: =N69*1000/$O$29 -> 0.20734159 | P69: =O69 -> 0.20734159 | R69: =J69-P69 -> -0.16927544
B70: 6666020201 | C70: 6666020201 Domestic business travel | D70: 国内商务旅行 | E70: 0 | F70: 0 | G70: 2.3894527 | H70: 0.064966088 | I70: 0.18603 | J70: 0.0056299367 | K70: =J70-F70 -> 0.0056299367 | L70: -0.059336152 | N70: 2.3894527 | O70: =N70*1000/$O$29 -> 0.066373687 | P70: =O70 -> 0.066373687 | R70: =J70-P70 -> -0.06074375
B71: 6666020202 | C71: 6666020202 Overseas business travel | D71: 海外商务旅行 | E71: 0.0106 | F71: 0.00019739292 | G71: 0 | H71: 0 | I71: 0.03439 | J71: 0.0010407651 | K71: =J71-F71 -> 0.00084337214 | L71: 0.0010407651 | N71: 0 | O71: =N71*1000/$O$29 -> 0 | P71: =O71 -> 0 | R71: =J71-P71 -> 0.0010407651
B72: 6666020204 | C72: 6666020204 Travel expense pay to agency | D72: 支付给代理的旅行费用 | E72: 0.05588 | F72: 0.0010405959 | G72: 0 | H72: 0 | I72: 1.80797 | J72: 0.054715674 | K72: =J72-F72 -> 0.053675078 | L72: 0.054715674 | N72: 0 | O72: =N72*1000/$O$29 -> 0 | P72: =O72 -> 0 | R72: =J72-P72 -> 0.054715674
B73: 6666020205 | C73: 6666020205 Business travel-other | D73: 商务旅行-其他 | E73: 0 | F73: 0 | G73: 0 | H73: 0 | I73: 0 | J73: 0 | K73: =J73-F73 -> 0 | L73: 0 | N73: 0 | O73: =N73*1000/$O$29 -> 0 | P73: =O73 -> 0 | R73: =J73-P73 -> 0
B74: 6666020301 | C74: 6666020301 Staff communic | D74: 员工通讯 | E74: 0.66441 | F74: 0.012372626 | G74: 0.35418103 | H74: 0.009629718 | I74: 0.20424 | J74: 0.0061810368 | K74: =J74-F74 -> -0.0061915889 | L74: -0.0034486811 | N74: 0.35418103 | O74: =N74*1000/$O$29 -> 0.0098383619 | P74: =O74 -> 0.0098383619 | R74: =J74-P74 -> -0.003657325
B75: 6666020302 | C75: 6666020302 Communication Expenses | D75: 通讯费用 | E75: 0 | F75: 0 | G75: 0.040391784 | H75: 0.0010981997 | I75: 0 | J75: 0 | K75: =J75-F75 -> 0 | L75: -0.0010981997 | N75: 0.040391784 | O75: =N75*1000/$O$29 -> 0.001121994 | P75: =O75 -> 0.001121994 | R75: =J75-P75 -> -0.001121994
B76: 6666020403 | C76: 6666020403 Company car expense | D76: 公司车辆费用 | F76: 0 | H76: 0 | I76: 0 | J76: 0 | K76: =J76-F76 -> 0 | L76: 0 | N76: 0 | O76: =N76*1000/$O$29 -> 0 | P76: =O76 -> 0 | R76: =J76-P76 -> 0
B77: 6666020405 | C77: 6666020405 Company car expense - maintenance fees | D77: 公司车辆费用-维护费 | E77: 0 | F77: 0 | G77: 0 | H77: 0 | I77: 0 | J77: 0 | K77: =J77-F77 -> 0 | L77: 0 | N77: 0 | O77: =N77*1000/$O$29 -> 0 | P77: =O77 -> 0 | R77: =J77-P77 -> 0
B78: 6666020495 | C78: 6666020495 Non-deductible expense-travel. | D78: 不可扣除费用-旅行 | E78: 0.10084 | F78: 0.0018778399 | G78: 0 | H78: 0 | I78: 1.05546 | J78: 0.031942015 | K78: =J78-F78 -> 0.030064175 | L78: 0.031942015 | N78: 0 | O78: =N78*1000/$O$29 -> 0 | P78: =O78 -> 0 | R78: =J78-P78 -> 0.031942015
B79: 6666020504 | C79: 6666020504 Newspaper and Periodicals expenditure | D79: 报纸和期刊支出 | E79: 0.02649 | F79: 0.00049329609 | G79: 0.050143601 | H79: 0.0013633388 | I79: 0 | J79: 0 | K79: =J79-F79 -> -0.00049329609 | L79: -0.0013633388 | N79: 0.050143601 | O79: =N79*1000/$O$29 -> 0.0013928778 | P79: =O79 -> 0.0013928778 | R79: =J79-P79 -> -0.0013928778
B80: 6666020508 | C80: 6666020508 Postage | D80: 邮资 | E80: 0 | F80: 0 | G80: 0.41068993 | H80: 0.011166121 | I80: 0.0622 | J80: 0.0018823957 | K80: =J80-F80 -> 0.0018823957 | L80: -0.0092837254 | N80: 0.41068993 | O80: =N80*1000/$O$29 -> 0.011408054 | P80: =O80 -> 0.011408054 | R80: =J80-P80 -> -0.0095256581
B81: 6666020602 | C81: 6666020602 Training costs Outside the group | D81: 集团外培训费用 | E81: 0 | F81: 0 | G81: 1.8707571 | H81: 0.050863434 | I81: 0.0025 | J81: 7.565899e-05 | K81: =J81-F81 -> 7.565899e-05 | L81: -0.050787775 | N81: 1.8707571 | O81: =N81*1000/$O$29 -> 0.051965475 | P81: =O81 -> 0.051965475 | R81: =J81-P81 -> -0.051889816
B82: 6666020701 | C82: 6666020701 Enterprise Property Insurance | D82: 企业财产保险 | E82: 0 | F82: 0 | G82: 0 | H82: 0 | I82: 0 | J82: 0 | K82: =J82-F82 -> 0 | L82: 0 | N82: 0 | O82: =N82*1000/$O$29 -> 0 | P82: =O82 -> 0 | R82: =J82-P82 -> 0
B83: 6666020802 | C83: 6666020802 Equipment rental cost | D83: 设备租赁成本 | E83: 11.03322 | F83: 0.20546034 | G83: 12.783 | H83: 0.34755302 | I83: 14.82192 | J83: 0.4485646 | K83: =J83-F83 -> 0.24310426 | L83: 0.10101158 | N83: 12.783 | O83: =N83*1000/$O$29 -> 0.35508333 | P83: =O83 -> 0.35508333 | R83: =J83-P83 -> 0.093481264
B84: 6666020803 | C84: 6666020803 Car rental cost | D84: 汽车租赁成本 | E84: 3.58813 | F84: 0.066818063 | G84: 3.6480621 | H84: 0.099186027 | I84: 2.84186 | J84: 0.086004903 | K84: =J84-F84 -> 0.019186839 | L84: -0.013181124 | N84: 3.6480621 | O84: =N84*1000/$O$29 -> 0.10133506 | P84: =O84 -> 0.10133506 | R84: =J84-P84 -> -0.015330155
B85: 6666021100 | C85: 6666021100 Consulting fees | D85: 咨询费 | E85: 6.37014 | F85: 0.11862458 | G85: 5.5184785 | H85: 0.1500402 | I85: 7.32294 | J85: 0.2216185 | K85: =J85-F85 -> 0.10299392 | L85: 0.071578299 | N85: 5.5184785 | O85: =N85*1000/$O$29 -> 0.15329107 | P85: =O85 -> 0.15329107 | R85: =J85-P85 -> 0.068327428
B86: 6666021104 | C86: 6666021104 Consulting expense-Technical | D86: 技术咨询费用 | E86: 0 | F86: 0 | H86: 0 | I86: 0 | J86: 0 | K86: =J86-F86 -> 0 | L86: 0 | N86: 0 | O86: =N86*1000/$O$29 -> 0 | P86: =O86 -> 0 | R86: =J86-P86 -> 0
B87: 6666021902 | C87: 6666021902 Cleaning fees | D87: 清洁费 | E87: 6.65347 | F87: 0.12390074 | G87: 7.6361386 | H87: 0.2076166 | I87: 6.1241 | J87: 0.18533729 | K87: =J87-F87 -> 0.061436543 | L87: -0.022279314 | N87: 7.6361386 | O87: =N87*1000/$O$29 -> 0.21211496 | P87: =O87 -> 0.21211496 | R87: =J87-P87 -> -0.026777674
B88: 6666022100 | C88: 6666022100 Security | D88: 保安 | E88: 1.32657 | F88: 0.024703352 | G88: 1.4141729 | H88: 0.038449507 | I88: 1.68529 | J88: 0.051002936 | K88: =J88-F88 -> 0.026299584 | L88: 0.012553428 | N88: 1.4141729 | O88: =N88*1000/$O$29 -> 0.03928258 | P88: =O88 -> 0.03928258 | R88: =J88-P88 -> 0.011720356
B89: 6666022300 | C89: 6666022300 Association dues | D89: 会费 | E89: 0 | F89: 0 | G89: 0 | H89: 0 | I89: 0 | J89: 0 | K89: =J89-F89 -> 0 | L89: 0 | N89: 0 | O89: =N89*1000/$O$29 -> 0 | P89: =O89 -> 0 | R89: =J89-P89 -> 0
B90: 6666029700 | C90: 6666029700 Service fee recharge | D90: 服务费回收费 | E90: 0 | F90: 0 | G90: 0 | H90: 0 | I90: 0 | J90: 0 | K90: =J90-F90 -> 0 | L90: 0 | N90: 0 | O90: =N90*1000/$O$29 -> 0 | P90: =O90 -> 0 | R90: =J90-P90 -> 0
B91: 6666029900 | C91: 6666029900 Sundry Expenses | D91: 杂项费用 | E91: 0 | F91: 0 | G91: 0 | H91: 0 | I91: 0 | J91: 0 | K91: =J91-F91 -> 0 | L91: 0 | N91: 0 | O91: =N91*1000/$O$29 -> 0 | P91: =O91 -> 0 | R91: =J91-P91 -> 0
B92: 6666029996 | C92: 6666029996 Non-deductible expense-travel. | D92: 不可扣除费用-旅行 | E92: 0 | F92: 0 | H92: 0 | I92: 0.01927 | J92: 0.00058317949 | K92: =J92-F92 -> 0.00058317949 | L92: 0.00058317949 | N92: 0 | O92: =N92*1000/$O$29 -> 0 | P92: =O92 -> 0 | R92: =J92-P92 -> 0.00058317949
B93: 6666029997 | C93: 6666029997 restructure cost | D93: 重组成本 | E93: 0 | F93: 0 | G93: 0.57148957 | H93: 0.015538052 | I93: 0 | J93: 0 | K93: =J93-F93 -> 0 | L93: -0.015538052 | N93: 0.57148957 | O93: =N93*1000/$O$29 -> 0.01587471 | P93: =O93 -> 0.01587471 | R93: =J93-P93 -> -0.01587471
B94: 6666030702 | C94: 6666030702 R&D prototype purchased | D94: R&D原型采购 | E94: 0 | F94: 0 | G94: 0 | H94: 0 | I94: 0 | J94: 0 | K94: =J94-F94 -> 0 | L94: 0 | N94: 0 | O94: =N94*1000/$O$29 -> 0 | P94: =O94 -> 0 | R94: =J94-P94 -> 0
B95: 6666031200 | C95: 6666031200 Instrument fee | D95: 仪器费用 | E95: 0 | F95: 0 | G95: 0 | H95: 0 | I95: 0 | J95: 0 | K95: =J95-F95 -> 0 | L95: 0 | N95: 0 | O95: =N95*1000/$O$29 -> 0 | P95: =O95 -> 0 | R95: =J95-P95 -> 0
B96: 6666050107 | C96: 6666050107 Special distribution costs | D96: 特殊分配成本 | E96: 0.01125 | F96: 0.00020949721 | G96: 0 | H96: 0 | I96: 0 | J96: 0 | K96: =J96-F96 -> -0.00020949721 | L96: 0 | N96: 0 | O96: =N96*1000/$O$29 -> 0 | P96: =O96 -> 0 | R96: =J96-P96 -> 0
B97: 6666070100 | C97: 6666070100 Software purchase, development and imple | D97: 软件采购、开发及实施 | E97: 0 | F97: 0 | G97: 0 | H97: 0 | I97: 0 | J97: 0 | K97: =J97-F97 -> 0 | L97: 0 | N97: 0 | O97: =N97*1000/$O$29 -> 0 | P97: =O97 -> 0 | R97: =J97-P97 -> 0
B98: 6666070300 | C98: 6666070300 Software maintenance fees | D98: 软件维护费 | E98: 0 | F98: 0 | G98: 0 | H98: 0 | I98: 0 | J98: 0 | K98: =J98-F98 -> 0 | L98: 0 | N98: 0 | O98: =N98*1000/$O$29 -> 0 | P98: =O98 -> 0 | R98: =J98-P98 -> 0
B99: 6666070400 | C99: 6666070400 IT maint. & repairs hardware | D99: IT维护及硬件修理 | E99: 3.51618 | F99: 0.065478212 | G99: 12.240973 | H99: 0.33281603 | I99: 2.44302 | J99: 0.07393457 | K99: =J99-F99 -> 0.0084563578 | L99: -0.25888146 | N99: 12.240973 | O99: =N99*1000/$O$29 -> 0.34002704 | P99: =O99 -> 0.34002704 | R99: =J99-P99 -> -0.26609247
B100: 5401050201 | C100: 5401050201 COGS-Special a | D100: 销售成本-特殊项目 | E100: 0 | F100: 0 | H100: 0 | I100: 0 | J100: 0 | K100: =J100-F100 -> 0 | L100: 0 | N100: 0 | O100: =N100*1000/$O$29 -> 0 | P100: =O100 -> 0 | R100: =J100-P100 -> 0
B101: 5401020212 | C101: 5401020212 Local Transpor | D101: 本地运输 | E101: 0 | F101: 0 | H101: 0 | I101: 0 | J101: 0 | K101: =J101-F101 -> 0 | L101: 0 | N101: 0 | O101: =N101*1000/$O$29 -> 0 | P101: =O101 -> 0 | R101: =J101-P101 -> 0
...

Sheet 洗碗机6月
B1: 1月费用总结： ①单：1月同期35欧元/台，订单量4.86万台，预测单台费用36.4欧元/台，较同期↑3.9%；实际37.48欧元/台，较同期↑6% 共梳理出8个问题
A2: 维度 | B2: 指标 | C2: 25年实际 | D2: 26年预算 | E2: 26年实际 | F2: 实际比同期差异 | G2: 制造费差额 | H2: 差异原因
A4: 单 | B4: 产量 | C4: 29664 | D4: 53265 | E4: 53186
A5: 时 | B5: 工作天数 | C5: 21 | D5: 14 | E5: 21
A6: 人 | B6: 直接人工 | C6: 226 | D6: 247 | E6: 261
B7: 直接人工工资 | C7: =E47/C6*1000 -> 1638.1892 | D7: =G47/D6*1000 -> 1948.6038 | E7: =I47/E6*1000 -> 1195.4172
B8: 间接人工 | C8: 93 | D8: 85 | E8: 82
B9: 间接人工工资 | C9: =E130/C8*1000 -> 1818.4072 | D9: =G130/D8*1000 -> 2196.4172 | E9: =I130/E8*1000 -> 2154.8715
B10: 白领人数 | C10: 23 | D10: 27 | E10: 25
B11: 白领人工工资 | C11: =E133/C10*1000 -> 2829.583 | D11: =G133/D10*1000 -> 3529.4159 | E11: =I133/E10*1000 -> 3480.1812
A12: 效 | B12: UPPH | C12: =C4/C5/(C6+C8)/7.5 -> 0.59041648 | D12: =D4/D5/(D6+D8)/7.5 -> 1.527969 | E12: =E4/E5/(E6+E8)/7.5 -> 0.98451571
A13: 费 | B13: 单台制造费 | C13: 58.586165 | D13: 35.115602 | E13: 27.048161 | F13: -31.538004 | G13: -1677380.3 | H13: =E13*$E$4 -> 1438583.5
B14: 折旧 | C14: 10.791543 | D14: 15.772406 | E14: 8.1496992 | F14: -2.6418433 | G14: -140509.08 | H14: =E14*$E$4 -> 433449.9
B15: 运营费 | C15: 0.70691531 | D15: 1.5337617 | E15: 1.0090607 | F15: 0.30214534 | G15: 16069.902 | H15: =E15*$E$4 -> 53667.9
B16: 存货跌价准备 | C16: 0.038792827 | D16: 0.22945591 | E16: -0.57750724 | F16: -0.61630007 | G16: -32778.535 | H16: =E16*$E$4 -> -30715.3
B17: 固定能源费 | C17: 0.1248583 | D17: 0.095942022 | E17: 0.039939082 | F17: -0.084919216 | G17: -4516.5134 | H17: =E17*$E$4 -> 2124.2
B18: 间接人工成本-辅助人员 | C18: 4.4930908 | D18: 6.2108564 | E18: 4.3101681 | F18: -0.18292274 | G18: -9728.9289 | H18: =E18*$E$4 -> 229240.6
B19: 固定人工-白领 | C19: 1.5134612 | D19: 3.0107146 | E19: 2.0983078 | F19: 0.58484663 | G19: 31105.653 | H19: =E19*$E$4 -> 111600.6
B20: 半固定-班车/工作服 | C20: 2.5109569 | D20: 4.2326322 | E20: 2.0936111 | F20: -0.41734581 | G20: -22196.954 | H20: =E20*$E$4 -> 111350.8
B21: 直接人工 | C21: 10.483577 | D21: 15.731221 | E21: 7.3634716 | F21: -3.1201056 | G21: -165945.94 | H21: =E21*$E$4 -> 391633.6
B22: 可回收废料 | C22: 0.52579249 | D22: 0.3955878 | E22: 0.52589779 | F22: 0.00010530047 | G22: 5.6005109 | H22: =E22*$E$4 -> 27970.4
B23: 生产耗用品 | C23: 0.33064148 | D23: 0.3183375 | E23: 0.37549919 | F23: 0.044857712 | G23: 2385.8023 | H23: =E23*$E$4 -> 19971.3
B24: 废品回收 | C24: -1.163369 | D24: -0.98422491 | E24: -1.3940059 | F24: -0.23063692 | G24: -12266.655 | H24: =E24*$E$4 -> -74141.6
B25: 变动能源费 | C25: 0.74202238 | D25: 0.65296291 | E25: 0.53887677 | F25: -0.20314561 | G25: -10804.502 | H25: =E25*$E$4 -> 28660.7
B26: 园区分摊费用 | C26: 3.6661115 | D26: 5.2323577 | E26: 2.512524 | F26: -1.1535875 | G26: -61354.704 | H26: =E26*$E$4 -> 133631.1
B27: IT Expense-Internal Charge Out | C27: 1.5251566 | D27: 0.13958524 | E27: -0.1274777 | G27: =(F27/C27)-1 -> -1 | H27: =#REF!/$C$4 -> #REF!
B28: Association dues | C28: 0.10143468 | D28: 1.9635097 | E28: 0.24760611 | G28: =(F28/C28)-1 -> -1 | H28: =#REF!/$C$4 -> #REF!
B29: G&A | C29: 1.1387711 | D29: 1.8673518 | E29: 0.299214 | G29: =(F29/C29)-1 -> -1 | H29: =#REF!/$C$4 -> #REF!
A30: 类型 | B30: 科目编号 | C30: 科目（英文） | D30: 科目（中文） | E30: K€ | F30: 同期台数 | G30: 29664 | H30: 预算台数 | I30: 53265 | J30: 实际台数 | K30: 53186
E31: 25年实际制造费 | F31: 25年实际单台 | G31: 26年预测制造费 | H31: 26年预测单台 | I31: 26年实际制造费 | J31: 26年实际单台 | K31: 同期与实际单台差 | L31: 预算与实际单台差 | M31: 与同期差分析
A32: 折旧 | B32: 6666110101 | C32: 6666110101 Depreciation of buildings | D32: 建筑物折旧 | E32: 30.081668 | F32: 0.56018004 | G32: 32.511052 | H32: 0.88393289 | I32: 31.01022 | J32: 0.58305231
B33: 6666110106 | C33: 6666110106 Depreciation of R&D facilities | D33: 研发设施折旧 | E33: 0 | F33: 0 | G33: 0 | H33: 0 | I33: 0 | J33: 0
B34: 6666110107 | C34: 6666110107 Depreciation of mold | D34: 模具折旧 | E34: 230.92979 | F34: 4.3003685 | G34: 230.14195 | H34: 6.2572581 | I34: 161.26505 | J34: 3.0320959 | N34: 1.17
B35: 6666110110 | C35: 6666110110 Depreciation-Plant & Machinery | D35: 厂房及机械折旧 | E35: 299.32499 | F35: 5.5740222 | G35: 300.83235 | H35: 8.1792374 | I35: 237.37205 | J35: 4.4630551
B36: 6666110112 | C36: 6666110112 Depreciation of Furniture & Fixture | D36: 家具及装置折旧 | E36: 11.262015 | F36: 0.20972095 | G36: 13.930613 | H36: 0.37875512 | I36: 2.7967 | J36: 0.052583387
B37: 6666110204 | C37: 6666110204 Amortization of license, trademarks and | D37: 许可证、商标及摊销 | E37: 0.25251497 | F37: 0.0047023272 | G37: 0.25251 | H37: 0.006865416 | I37: 0.07575 | J37: 0.001424247
B38: 6666110207 | C38: 6666110207 Amortization of Software | D38: 软件摊销 | E38: 6.7839525 | F38: 0.12633059 | G38: 2.5668029 | H38: 0.069788008 | I38: 0.93009 | J38: 0.017487497
B39: 6666110506 | C39: 6666110506 Amortization-Leasehold Improvement | D39: 租赁改良摊销 | E39: 0.68159 | F39: 0.012692551 | G39: 0 | H39: 0 | I39: 0 | J39: 0
B40: 6666110206 | C40: 6666110206 Amortization of Patents | D40: 专利摊销 | F40: 0 | H40: 0 | I40: 0 | J40: 0
B41: FIX | C41: * CS_Depreciation | D41: * CS_折旧 | E41: 824.01968 | F41: 27.778441 | G41: 569.22644 | H41: 10.686688 | I41: 433.44986 | J41: 8.1496984
A42: 直接人工 | B42: 5001010205 | C42: 5001010205 Unemployment Insurance -blue collar-Dire | D42: 失业保险-蓝领-直接 | E42: 9.34405 | F42: 0.17400466 | G42: 10.118543 | H42: 0.27510992 | I42: 6.57644 | J42: 0.12364983
B43: 6666010380 | C43: 6666010380 Incentive | D43: 激励 | E43: -0.35328 | F43: -0.0065787709 | G43: -26.252196 | H43: -0.71376281 | I43: -1.48382 | J43: -0.027898695
B44: 6666010019 | C44: 6666010019 Payroll Taxes - Blue Collar Direct | E44: 73.69048 | F44: 1.3722622 | G44: 104.97988 | H44: 2.8542654 | I44: 56.41294 | J44: 1.0606727
B45: 6666010183 | C45: 6666010183 Overtime-Blue Collar-Direct | D45: 蓝领加班费-直接 | E45: 94.37846 | F45: 1.7575132 | G45: 0 | H45: 0 | I45: 8.86122 | J45: 0.16660813
B46: 6666010229 | C46: 6666010229 Staff Leaving Indemnity - Blue Collar Di | D46: 蓝领离职赔偿-直接 | E46: 10.89326 | F46: 0.202854 | G46: 8.5688093 | H46: 0.2329747 | I46: 10.57159 | J46: 0.1987664
B47: 6666010188 | C47: 6666010188 Salary - Blue collar direct employees | D47: 蓝领直接员工工资 | E47: 370.23077 | F47: 6.8944277 | G47: 481.30513 | H47: 13.086056 | I47: 312.0039 | J47: 5.8662787
B48: 5102040406 | C48: 5102040406 Other revenue-Service/Secondment agreeme | D48: 其他收入-服务/派遣协议 | E48: 0 | F48: 0 | G48: 0 | H48: 0
B49: 6666010115 | C49: 6666010115 Salary-Blue collar direct employees-Accr | D49: 蓝领直接员工工资-应计 | E49: 4.82629 | F49: 0.089875047 | G49: 0 | H49: 0 | I49: -1.30866 | J49: -0.024605347
B50: VAR | C50: * CS_Direct Labour | D50: * CS_直接劳动 | E50: 382.06162 | F50: 12.879639 | G50: 502.71051 | H50: 9.4379144 | I50: 391.63361 | J50: 7.3634718
A51: 可回收废料 | B51: 8701530201 | C51: 8701530201 Scrap-Raw Material - Managerial | D51: 废料-原材料-管理 | E51: 0 | F51: 0 | G51: 0 | H51: 0 | I51: 0 | J51: 0
B52: 6666050309 | C52: 6666050309 SFG scrap | D52: SFG废料 | E52: 15.24772 | F52: 0.28394264 | G52: 14.552884 | H52: 0.39567385 | I52: 4.86599 | J52: 0.091490054
B53: 6666050308 | C53: 6666050308 Raw material scrap | D53: 原材料废料 | E53: 12.98944 | F53: 0.24188901 | G53: 0 | H53: 0 | I53: 22.05431 | J53: 0.41466382
B54: 6666050306 | C54: 6666050306 Finished goods scrap | D54: 成品废料 | E54: 0 | F54: 0 | G54: 0 | H54: 0 | I54: 1.05008 | J54: 0.019743542
B55: VAR | C55: * CS_SCRAP_VARIABLE | D55: * CS_废料变量 | E55: 20.36294 | F55: 0.68645294 | G55: 21.229326 | H55: 0.39856052 | I55: 27.97038 | J55: 0.52589742
A56: 组织运营 | B56: 5102010151 | C56: 5102010151 Other Rev.-Interco-Epidemic problem comp | D56: 其他收入-内部公司-疫情问题补偿 | E56: 0 | F56: 0 | G56: 0 | H56: 0 | I56: 0 | J56: 0
B57: 5001010200 | C57: 5001010200 Cost of Manufacture - Raw Material | D57: 制造成本-原材料 | E57: 0.01851 | F57: 0.00034469274 | G57: 0 | H57: 0 | I57: 0 | J57: 0
B58: 5001010201 | C58: 5001010201 Cost of Manufacture - Raw Material-Freig | D58: 制造成本-原材料-运费 | E58: 0.00247 | F58: 4.5996276e-05 | G58: 0 | H58: 0 | I58: 0 | J58: 0
B59: 5207000011 | C59: 5207000011 Gain of tangible asset disposal | D59: 有形资产处置收益 | E59: 0 | F59: 0 | G59: 0 | H59: 0 | I59: 0 | J59: 0
B60: 5207000012 | C60: 5207000012 Loss of tangible asset sold | D60: 出售有形资产损失 | E60: 0 | F60: 0 | G60: 0 | H60: 0 | I60: 0 | J60: 0
B61: 5207000022 | C61: 5207000022 Loss of intangible asset disposal | D61: 无形资产处置损失 | E61: 0 | F61: 0 | G61: 0 | H61: 0 | I61: 0 | J61: 0
B62: 5301060000 | C62: 5301060000 Other Income-Subsidy income | D62: 其他收入-补贴收入 | E62: 0 | F62: 0 | G62: 0 | H62: 0 | I62: 0 | J62: 0
B63: 5301999999 | C63: 5301999999 Non-operation revenue-Other | D63: 非经营收入-其他 | E63: 0 | F63: 0 | G63: 0 | H63: 0 | I63: -0.28006 | J63: -0.0052656714
B64: 5405030000 | C64: 5405030000 Other cost-others | D64: 其他成本-其他 | E64: 0.00024 | F64: 4.4692737e-06 | G64: 0 | H64: 0 | I64: 0 | J64: 0
B65: 5601050000 | C65: 5601050000 Non-Operating Expense - Penalty | D65: 非经营费用-罚款 | E65: 0 | F65: 0 | G65: 0 | H65: 0 | I65: 0 | J65: 0
B66: 5601050100 | C66: 5601050100 Non-operation Expense-Others | D66: 非经营费用-其他 | E66: 0 | F66: 0 | G66: 0 | H66: 0 | I66: 0 | J66: 0
B67: 5102040893 | C67: 5102040893 Other revenue-Charge out-Test Expense | D67: 其他收入-费用支出-测试费用 | E67: 0 | F67: 0 | H67: 0 | I67: 0 | J67: 0
B68: 5801000041 | C68: 5801000041 Previous year Sundry cost | D68: 去年杂项成本 | E68: 0 | F68: 0 | G68: 0 | H68: 0 | I68: 0 | J68: 0
B69: 6666010322 | C69: 6666010322 fuel allowance | D69: 燃料津贴 | E69: 1.25877 | F69: 0.023440782 | G69: 1.8952219 | H69: 0.0515286 | I69: -0.00074 | J69: -1.3913436e-05
B70: 6666020101 | C70: 6666020101 Entertainment | D70: 娱乐 | E70: 5.07662 | F70: 0.094536685 | G70: 4.3987265 | H70: 0.11959561 | I70: 0.00104 | J70: 1.9554018e-05
B71: 6666020201 | C71: 6666020201 Domestic business travel | D71: 国内商务旅行 | E71: 0 | F71: 0 | G71: 2.3894527 | H71: 0.064966088 | I71: 0.03142 | J71: 0.00059075697
B72: 6666020202 | C72: 6666020202 Overseas business travel | D72: 海外商务旅行 | E72: 0.0106 | F72: 0.00019739292 | G72: 0 | H72: 0 | I72: 0.25368 | J72: 0.0047696762
B73: 6666020204 | C73: 6666020204 Travel expense pay to agency | D73: 支付给代理的旅行费用 | E73: 0.05588 | F73: 0.0010405959 | G73: 0 | H73: 0 | I73: 2.67529 | J73: 0.050300643
B74: 6666020205 | C74: 6666020205 Business travel-other | D74: 商务旅行-其他 | E74: 0 | F74: 0 | G74: 0 | H74: 0 | I74: 0 | J74: 0
B75: 6666020301 | C75: 6666020301 Staff communic | D75: 员工通讯 | E75: 0.66441 | F75: 0.012372626 | G75: 0.35418103 | H75: 0.009629718 | I75: 0.07333 | J75: 0.0013787463
B76: 6666020302 | C76: 6666020302 Communication Expenses | D76: 通讯费用 | E76: 0 | F76: 0 | G76: 0.040391784 | H76: 0.0010981997 | I76: 0 | J76: 0
B77: 6666020403 | C77: 6666020403 Company car expense | D77: 公司车辆费用 | F77: 0 | H77: 0 | I77: 0 | J77: 0
B78: 6666020405 | C78: 6666020405 Company car expense - maintenance fees | D78: 公司车辆费用-维护费 | E78: 0 | F78: 0 | G78: 0 | H78: 0 | I78: 0 | J78: 0
B79: 6666020495 | C79: 6666020495 Non-deductible expense-travel. | D79: 不可扣除费用-旅行 | E79: 0.10084 | F79: 0.0018778399 | G79: 0 | H79: 0 | I79: 0.62974 | J79: 0.011840334
B80: 6666020504 | C80: 6666020504 Newspaper and Periodicals expenditure | D80: 报纸和期刊支出 | E80: 0.02649 | F80: 0.00049329609 | G80: 0.050143601 | H80: 0.0013633388 | I80: 0 | J80: 0
B81: 6666020508 | C81: 6666020508 Postage | D81: 邮资 | E81: 0 | F81: 0 | G81: 0.41068993 | H81: 0.011166121 | I81: 0.04565 | J81: 0.00085830858
B82: 6666020602 | C82: 6666020602 Training costs Outside the group | D82: 集团外培训费用 | E82: 0 | F82: 0 | G82: 1.8707571 | H82: 0.050863434 | I82: 8.46272 | J82: 0.15911556
B83: 6666020701 | C83: 6666020701 Enterprise Property Insurance | D83: 企业财产保险 | E83: 0 | F83: 0 | G83: 0 | H83: 0 | I83: 0 | J83: 0
B84: 6666020802 | C84: 6666020802 Equipment rental cost | D84: 设备租赁成本 | E84: 11.03322 | F84: 0.20546034 | G84: 12.783 | H84: 0.34755302 | I84: 12.91982 | J84: 0.24291769
B85: 6666020803 | C85: 6666020803 Car rental cost | D85: 汽车租赁成本 | E85: 3.58813 | F85: 0.066818063 | G85: 3.6480621 | H85: 0.099186027 | I85: 2.82137 | J85: 0.05304723
B86: 6666021100 | C86: 6666021100 Consulting fees | D86: 咨询费 | E86: 6.37014 | F86: 0.11862458 | G86: 5.5184785 | H86: 0.1500402 | I86: 7.32201 | J86: 0.137668
B87: 6666021104 | C87: 6666021104 Consulting expense-Technical | D87: 技术咨询费用 | E87: 0 | F87: 0 | H87: 0 | I87: 0 | J87: 0
B88: 6666021902 | C88: 6666021902 Cleaning fees | D88: 清洁费 | E88: 6.65347 | F88: 0.12390074 | G88: 7.6361386 | H88: 0.2076166 | I88: 9.34958 | J88: 0.17579025
B89: 6666022100 | C89: 6666022100 Security | D89: 保安 | E89: 1.32657 | F89: 0.024703352 | G89: 1.4141729 | H89: 0.038449507 | I89: 1.47789 | J89: 0.0277872
B90: 6666022300 | C90: 6666022300 Association dues | D90: 会费 | E90: 0 | F90: 0 | G90: 0 | H90: 0 | I90: 0 | J90: 0
B91: 6666029700 | C91: 6666029700 Service fee recharge | D91: 服务费回收费 | E91: 0 | F91: 0 | G91: 0 | H91: 0 | I91: 0 | J91: 0
B92: 6666029900 | C92: 6666029900 Sundry Expenses | D92: 杂项费用 | E92: 0 | F92: 0 | G92: 0 | H92: 0 | I92: 0 | J92: 0
B93: 6666029996 | C93: 6666029996 Non-deductible expense-travel. | D93: 不可扣除费用-旅行 | E93: 0 | F93: 0 | H93: 0 | I93: 0.03526 | J93: 0.00066295642
B94: 6666029997 | C94: 6666029997 restructure cost | D94: 重组成本 | E94: 0 | F94: 0 | G94: 0.57148957 | H94: 0.015538052 | I94: 0.26268 | J94: 0.0049388937
B95: 6666030702 | C95: 6666030702 R&D prototype purchased | D95: R&D原型采购 | E95: 0 | F95: 0 | G95: 0 | H95: 0 | I95: 0 | J95: 0
B96: 6666031200 | C96: 6666031200 Instrument fee | D96: 仪器费用 | E96: 0 | F96: 0 | G96: 0 | H96: 0 | I96: 0 | J96: 0
B97: 6666050107 | C97: 6666050107 Special distribution costs | D97: 特殊分配成本 | E97: 0.01125 | F97: 0.00020949721 | G97: 0 | H97: 0 | I97: 0 | J97: 0
B98: 6666070100 | C98: 6666070100 Software purchase, development and imple | D98: 软件采购、开发及实施 | E98: 0 | F98: 0 | G98: 0 | H98: 0 | I98: 0 | J98: 0
B99: 6666070300 | C99: 6666070300 Software maintenance fees | D99: 软件维护费 | E99: 0 | F99: 0 | G99: 0 | H99: 0 | I99: 0 | J99: 0
B100: 6666070400 | C100: 6666070400 IT maint. & repairs hardware | D100: IT维护及硬件修理 | E100: 3.51618 | F100: 0.065478212 | G100: 12.240973 | H100: 0.33281603 | I100: 2.41852 | J100: 0.045472869
B101: 5401050201 | C101: 5401050201 COGS-Special a | D101: 销售成本-特殊项目 | E101: 0 | F101: 0 | H101: 0 | I101: 0 | J101: 0
...

Sheet DW  2026
A1: 1月费用总结： ①单：1月同期35欧元/台，订单量4.86万台，预测单台费用36.4欧元/台，较同期↑3.9%；实际37.48欧元/台，较同期↑6% 共梳理出8个问题
A2: KPI | B2: ACT 2025 | C2: Budget | D2: Budget-ACT VARIANCE | E2: Act | F2: CPU-Y0Y | G2: Analysis
A4: QTY | B4: 478100 | C4: 565020 | D4: =C4-B4 -> 86920
A5: Work days | B5: 237 | C5: 220 | D5: =C5-B5 -> -17
A6: Direct Labour | B6: 2372 | C6: 2969 | D6: =C6-B6 -> 597
A7: Direct Labour avrerage salary | B7: =0.114397955970597*1000 -> 114.39796 | C7: =0.113723208386452*1000 -> 113.72321 | D7: =C7-B7 -> -0.67474758 | G7: Direct Labour crease，Why decrease？ 人数上涨，工资下降
A8: indirect Labour | B8: 1000 | C8: 1020 | D8: =C8-B8 -> 20
A9: indirect Labour avrerage salary | B9: =2575/B8*1000 -> 2575 | C9: =2701/C8*1000 -> 2648.0392 | D9: =C9-B9 -> 73.039216
A10: Fixed Labour | B10: 293 | C10: 323 | D10: =C10-B10 -> 30
A11: Fixed avrerage salary | B11: =1047/B10*1000 -> 3573.3788 | C11: =1249/C10*1000 -> 3866.8731 | D11: =C11-B11 -> 293.49423 | G11: Why crease 上涨293万
A12: UPH | B12: 10.3048 | C12: 10.400748 | D12: =C12-B12 -> 0.095948021
A13: CPU | B13: =SUM(B14:B26) -> 42.496033 | C13: =SUM(C14:C26) -> 39.975046 | D13: =C13-B13 -> -2.5209874
A14: CS_Depreciation | B14: 13.955205 | C14: 12.395924 | D14: =C14-B14 -> -1.5592803
A15: CS_Fix Cost | B15: 1.0082632 | C15: 1.1921554 | D15: =C15-B15 -> 0.18389221 | G15: Why crease？ 固定人工预测上涨0.18
A16: CS_Obsolescence | B16: 0.50954071 | C16: 0.17698546 | D16: =C16-B16 -> -0.33255524
A17: CS_Fix Utilities | B17: 0.15380524 | C17: 0.11597097 | D17: =C17-B17 -> -0.037834271
A18: Indirect Labour | B18: 5.5151107 | C18: 4.7809268 | D18: =C18-B18 -> -0.73418393
A19: Fixed Labour | B19: 2.2433178 | C19: 2.2112842 | D19: =C19-B19 -> -0.0320336
A20: CS_Semifix | B20: 3.325059 | C20: 3.8154444 | D20: =C20-B20 -> 0.49038533 | G20: Why crease？ 半固定单台上涨0.49
A21: CS_Direct Labour | B21: 11.095745 | C21: 10.755978 | D21: =C21-B21 -> -0.3397671
A22: CS_SCRAP_VARIABLE | B22: 0.58196637 | C22: 0.44001178 | D22: =C22-B22 -> -0.14195459
A23: CS_Variable Cost | B23: 0.2931156 | C23: 0.32747707 | D23: =C23-B23 -> 0.034361472
A24: CS_Reselling | B24: -1.3629003 | C24: -1.0365156 | D24: =C24-B24 -> 0.32638466
A25: CS_Variable Utilities | B25: 0.64202061 | C25: 0.71735626 | D25: =C25-B25 -> 0.075335649
A26: GMA | B26: 4.535785 | C26: 4.0820473 | D26: =C26-B26 -> -0.45373768
A27: IT Expense-Internal Charge Out | B27: 2.0598917 | C27: 1.7973014 | D27: -0.1274777 | F27: =(E27/B27)-1 -> -1
A28: Association dues | B28: 0.10364806 | C28: 0.12931195 | D28: 0.24760611 | F28: =(E28/B28)-1 -> -1
A29: G&A | B29: 1.4372934 | C29: 1.8673518 | D29: 0.299214 | F29: =(E29/B29)-1 -> -1
A30: 类型 | B30: CODE | C30: Description | D30: Description(CN) | E30: K€ | F30: QTY-2025 | G30: 478100 | H30: Budget-QTY | I30: 565020 | J30: ACT-QTY
E31: MFG-2025 | F31: CPU-2025 | G31: Budget-2026 | H31: Budget-CPU-2026 | I31: ACT-2026 | J31: ACT-CPU-2026 | K31: CPU-Y0Y | L31: Budget-ACT VARIANCE | M31: CPU-Y0Y Analysis | N31: Budget-ACT VARIANCE Analysis
A32: 折旧 | B32: 6666110101 | C32: 6666110101 Depreciation of buildings | D32: 建筑物折旧 | E32: 364.2985 | F32: 0.76197134 | G32: 383.10318 | H32: 0.67803473 | L32: =H32-F32 -> -0.083936614
B33: 6666110106 | C33: 6666110106 Depreciation of R&D facilities | D33: 研发设施折旧 | E33: 0 | F33: 0 | G33: 0 | H33: 0 | L33: =H33-F33 -> 0
B34: 6666110107 | C34: 6666110107 Depreciation of mold | D34: 模具折旧 | E34: 2576.6794 | F34: 5.3894151 | G34: 2795.0328 | H34: 4.9467857 | L34: =H34-F34 -> -0.44262943
B35: 6666110110 | C35: 6666110110 Depreciation-Plant & Machinery | D35: 厂房及机械折旧 | E35: 3385.4586 | F35: 7.081068 | G35: 3606.3598 | H35: 6.3827118 | L35: =H35-F35 -> -0.69835619
B36: 6666110112 | C36: 6666110112 Depreciation of Furniture & Fixture | D36: 家具及装置折旧 | E36: 116.10877 | F36: 0.24285457 | G36: 175.22479 | H36: 0.31012139 | L36: =H36-F36 -> 0.067266822
B37: 6666110204 | C37: 6666110204 Amortization of license, trademarks and | D37: 许可证、商标及摊销 | E37: 2.8363716 | F37: 0.0059325907 | G37: 3.0302 | H37: 0.005362996 | L37: =H37-F37 -> -0.00056959475
B38: 6666110207 | C38: 6666110207 Amortization of Software | D38: 软件摊销 | E38: 60.971559 | F38: 0.12752888 | G38: 41.219178 | H38: 0.072951715 | L38: =H38-F38 -> -0.054577168
B39: 6666110506 | C39: 6666110506 Amortization-Leasehold Improvement | D39: 租赁改良摊销 | E39: 7.5633708 | F39: 0.015819642 | G39: 0 | H39: 0 | L39: =H39-F39 -> -0.015819642
B40: 6666110206 | C40: 6666110206 Amortization of Patents | D40: 专利摊销 | F40: 0 | G40: 0 | H40: 0 | L40: =H40-F40 -> 0
B41: FIX | C41: * CS_Depreciation | D41: * CS_折旧 | E41: 6513.9165 | F41: 13.62459 | G41: 7003.97 | H41: 12.395968 | L41: =H41-F41 -> -1.2286218
A42: 直接人工 | B42: 5001010205 | C42: 5001010205 Unemployment Insurance -blue collar-Dire | D42: 失业保险-蓝领-直接 | E42: 82.58064 | F42: 0.17272671 | G42: 110.38167 | H42: 0.19535887 | L42: =H42-F42 -> 0.022632162
B43: 6666010380 | C43: 6666010380 Incentive | D43: 激励 | E43: 6.35019 | F43: 0.013282138 | G43: -287.17262 | H43: -0.50825213 | L43: =H43-F43 -> -0.52153427 | N43: 在2025年，社会安全额外支付了21千欧元。然而，为了详细解释差异，我们需要人力资源部门。因为劳动成本的计算是由他们完成的。
B44: 6666010019 | C44: 6666010019 Payroll Taxes - Blue Collar Direct | E44: 659.07762 | F44: 1.3785351 | G44: 1145.2098 | H44: 2.0268483 | L44: =H44-F44 -> 0.64831322 | N44: 这个账户与直接劳动工资税有关。由于工资金额和人力成本的增加（2025法案218至2026预算247），该账户有所增加。然而，为了详细解释差异，我们需要人力资源部门。因为劳动成本的计算是由他们完成的。
B45: 6666010183 | C45: 6666010183 Overtime-Blue Collar-Direct | D45: 蓝领加班费-直接 | E45: 317.14723 | F45: 0.66334915 | G45: 0 | H45: 0 | L45: =H45-F45 -> -0.66334915
B46: 6666010229 | C46: 6666010229 Staff Leaving Indemnity - Blue Collar Di | D46: 蓝领离职赔偿-直接 | E46: 108.11015 | F46: 0.22612456 | G46: 101.51214 | H46: 0.17966115 | L46: =H46-F46 -> -0.046463402
B47: 6666010188 | C47: 6666010188 Salary - Blue collar direct employees | D47: 蓝领直接员工工资 | E47: 4063.1788 | F47: 8.4985962 | G47: 5007.4329 | H47: 8.8623994 | L47: =H47-F47 -> 0.3638032
B48: 5102040406 | C48: 5102040406 Other revenue-Service/Secondment agreeme | D48: 其他收入-服务/派遣协议 | E48: 0 | F48: 0 | G48: 0 | H48: 0 | L48: =H48-F48 -> 0
B49: 6666010115 | C49: 6666010115 Salary-Blue collar direct employees-Accr | D49: 蓝领直接员工工资-应计 | E49: -55.43767 | F49: -0.11595413 | G49: 0 | H49: 0 | L49: =H49-F49 -> 0.11595413
B50: VAR | C50: * CS_Direct Labour | D50: * CS_直接劳动 | E50: 5181.007 | F50: 10.83666 | G50: 6077.3639 | H50: 10.756016 | L50: =H50-F50 -> -0.080644114
A51: 可回收废料 | B51: 8701530201 | C51: 8701530201 Scrap-Raw Material - Managerial | D51: 废料-原材料-管理 | E51: 0 | F51: 0 | G51: 0 | H51: 0 | L51: =H51-F51 -> 0
B52: 6666050309 | C52: 6666050309 SFG scrap | D52: SFG废料 | E52: 124.32366 | F52: 0.26003694 | G52: 248.61634 | H52: 0.44001334 | L52: =H52-F52 -> 0.1799764
B53: 6666050308 | C53: 6666050308 Raw material scrap | D53: 原材料废料 | E53: 145.2031 | F53: 0.30370864 | G53: 0 | H53: 0 | L53: =H53-F53 -> -0.30370864 | N53: 我们应该考虑废料的总金额以便进行比较。2025年实际废料成本包括原材料、半成品和成品废料。然而在预算中，我们将总废料金额计入一个账户，因为我们不知道账户之间的分配。
B54: 6666050306 | C54: 6666050306 Finished goods scrap | D54: 成品废料 | E54: 2.86061 | F54: 0.005983288 | G54: 0 | H54: 0 | L54: =H54-F54 -> -0.005983288
B55: VAR | C55: * CS_SCRAP_VARIABLE | D55: * CS_废料变量 | E55: 272.38737 | F55: 0.56972886 | G55: 248.61634 | H55: 0.44001334 | L55: =H55-F55 -> -0.12971553
A56: 组织运营 | B56: 5102010151 | C56: 5102010151 Other Rev.-Interco-Epidemic problem comp | D56: 其他收入-内部公司-疫情问题补偿 | E56: 0 | F56: 0 | G56: 0 | H56: 0 | L56: =H56-F56 -> 0
B57: 5001010200 | C57: 5001010200 Cost of Manufacture - Raw Material | D57: 制造成本-原材料 | E57: 0.22851 | F57: 0.0004779544 | G57: 0 | H57: 0 | L57: =H57-F57 -> -0.0004779544
B58: 5001010201 | C58: 5001010201 Cost of Manufacture - Raw Material-Freig | D58: 制造成本-原材料-运费 | E58: 0.18324 | F58: 0.0003832671 | G58: 0 | H58: 0 | L58: =H58-F58 -> -0.0003832671
B59: 5207000011 | C59: 5207000011 Gain of tangible asset disposal | D59: 有形资产处置收益 | E59: 0 | F59: 0 | G59: 0 | H59: 0 | L59: =H59-F59 -> 0
B60: 5207000012 | C60: 5207000012 Loss of tangible asset sold | D60: 出售有形资产损失 | E60: 0 | F60: 0 | G60: 0 | H60: 0 | L60: =H60-F60 -> 0
B61: 5207000022 | C61: 5207000022 Loss of intangible asset disposal | D61: 无形资产处置损失 | E61: 0 | F61: 0 | G61: 0 | H61: 0 | L61: =H61-F61 -> 0
B62: 5301060000 | C62: 5301060000 Other Income-Subsidy income | D62: 其他收入-补贴收入 | E62: 0 | F62: 0 | G62: 0 | H62: 0 | L62: =H62-F62 -> 0
B63: 5301999999 | C63: 5301999999 Non-operation revenue-Other | D63: 非经营收入-其他 | E63: -0.06594 | F63: -0.00013792094 | G63: 0 | H63: 0 | L63: =H63-F63 -> 0.00013792094
B64: 5405030000 | C64: 5405030000 Other cost-others | D64: 其他成本-其他 | E64: 1.47277 | F64: 0.0030804643 | G64: 0 | H64: 0 | L64: =H64-F64 -> -0.0030804643
B65: 5601050000 | C65: 5601050000 Non-Operating Expense - Penalty | D65: 非经营费用-罚款 | E65: 0.06526 | F65: 0.00013649864 | G65: 0 | H65: 0 | L65: =H65-F65 -> -0.00013649864
B66: 5601050100 | C66: 5601050100 Non-operation Expense-Others | D66: 非经营费用-其他 | E66: 0.05161 | F66: 0.00010794813 | G66: 0 | H66: 0 | L66: =H66-F66 -> -0.00010794813
B67: 5102040893 | C67: 5102040893 Other revenue-Charge out-Test Expense | D67: 其他收入-费用支出-测试费用 | E67: 0 | F67: 0 | G67: 0 | H67: 0 | L67: =H67-F67 -> 0
B68: 5801000041 | C68: 5801000041 Previous year Sundry cost | D68: 去年杂项成本 | E68: 0 | F68: 0 | G68: 0 | H68: 0 | L68: =H68-F68 -> 0
B69: 6666010322 | C69: 6666010322 fuel allowance | D69: 燃料津贴 | E69: 16.08902 | F69: 0.033651997 | G69: 22.452132 | H69: 0.03973688 | L69: =H69-F69 -> 0.006084883
B70: 6666020101 | C70: 6666020101 Entertainment | D70: 娱乐 | E70: -7.82509 | F70: -0.016367057 | G70: 52.110409 | H70: 0.092227548 | L70: =H70-F70 -> 0.10859461 | N70: 这个账户中有一些与工会协议相关的费用（野餐、早餐等）。在2025年我们没有使用这笔预算。然而，我们必须为这个账户做预算，以防工会要求支出。
B71: 6666020201 | C71: 6666020201 Domestic business travel | D71: 国内商务旅行 | E71: 9.49769 | F71: 0.019865488 | G71: 28.307139 | H71: 0.050099357 | L71: =H71-F71 -> 0.030233868 | N71: 2026年为总部同事增加19千欧元的额外预算
B72: 6666020202 | C72: 6666020202 Overseas business travel | D72: 海外商务旅行 | E72: 1.38056 | F72: 0.0028875967 | G72: 0 | H72: 0 | L72: =H72-F72 -> -0.0028875967
B73: 6666020204 | C73: 6666020204 Travel expense pay to agency | D73: 支付给代理的旅行费用 | E73: 4.52682 | F73: 0.0094683539 | G73: 0 | H73: 0 | L73: =H73-F73 -> -0.0094683539
B74: 6666020205 | C74: 6666020205 Business travel-other | D74: 商务旅行-其他 | E74: -0.18314 | F74: -0.00038305794 | G74: 0 | H74: 0 | L74: =H74-F74 -> 0.00038305794
B75: 6666020301 | C75: 6666020301 Staff communic | D75: 员工通讯 | E75: 4.75334 | F75: 0.009942146 | G75: 4.1958777 | H75: 0.0074260693 | L75: =H75-F75 -> -0.0025160767
B76: 6666020302 | C76: 6666020302 Communication Expenses | D76: 通讯费用 | E76: 0 | F76: 0 | G76: 0.4785095 | H76: 0.00084688948 | L76: =H76-F76 -> 0.00084688948
B77: 6666020403 | C77: 6666020403 Company car expense | D77: 公司车辆费用 | F77: 0 | G77: 0 | H77: 0 | L77: =H77-F77 -> 0
B78: 6666020405 | C78: 6666020405 Company car expense - maintenance fees | D78: 公司车辆费用-维护费 | E78: 0 | F78: 0 | G78: 0 | H78: 0 | L78: =H78-F78 -> 0
B79: 6666020495 | C79: 6666020495 Non-deductible expense-travel. | D79: 不可扣除费用-旅行 | E79: 3.21211 | F79: 0.0067184899 | G79: 0 | H79: 0 | L79: =H79-F79 -> -0.0067184899
B80: 6666020504 | C80: 6666020504 Newspaper and Periodicals expenditure | D80: 报纸和期刊支出 | E80: 0.29938 | F80: 0.00062618699 | G80: 0.59403638 | H80: 0.0010513546 | L80: =H80-F80 -> 0.00042516761
B81: 6666020508 | C81: 6666020508 Postage | D81: 邮资 | E81: 0.04867 | F81: 0.00010179879 | G81: 4.865322 | H81: 0.0086108845 | L81: =H81-F81 -> 0.0085090857
B82: 6666020602 | C82: 6666020602 Training costs Outside the group | D82: 集团外培训费用 | E82: 4.70704 | F82: 0.0098453043 | G82: 22.162305 | H82: 0.03922393 | L82: =H82-F82 -> 0.029378626 | N82: 5千欧元的设备许可费加上2026年生产需求的10千欧元额外预算
B83: 6666020701 | C83: 6666020701 Enterprise Property Insurance | D83: 企业财产保险 | E83: 0 | F83: 0 | G83: 0 | H83: 0 | L83: =H83-F83 -> 0
B84: 6666020802 | C84: 6666020802 Equipment rental cost | D84: 设备租赁成本 | E84: 133.42406 | F84: 0.27907145 | G84: 156.396 | H84: 0.27679728 | L84: =H84-F84 -> -0.002274168
B85: 6666020803 | C85: 6666020803 Car rental cost | D85: 汽车租赁成本 | E85: 50.53832 | F85: 0.10570659 | G85: 43.217511 | H85: 0.076488462 | L85: =H85-F85 -> -0.029218127
B86: 6666021100 | C86: 6666021100 Consulting fees | D86: 咨询费 | E86: 72.90402 | F86: 0.15248697 | G86: 65.375779 | H86: 0.11570525 | L86: =H86-F86 -> -0.036781721
B87: 6666021104 | C87: 6666021104 Consulting expense-Technical | D87: 技术咨询费用 | E87: -0.03701 | F87: -7.7410584e-05 | G87: 0 | H87: 0 | L87: =H87-F87 -> 7.7410584e-05
B88: 6666021902 | C88: 6666021902 Cleaning fees | D88: 清洁费 | E88: 83.46437 | F88: 0.17457513 | G88: 90.463072 | H88: 0.16010596 | L88: =H88-F88 -> -0.014469167
B89: 6666022100 | C89: 6666022100 Security | D89: 保安 | E89: 13.81918 | F89: 0.028904371 | G89: 16.753287 | H89: 0.029650786 | L89: =H89-F89 -> 0.00074641454
B90: 6666022300 | C90: 6666022300 Association dues | D90: 会费 | E90: 0 | F90: 0 | G90: 0 | H90: 0 | L90: =H90-F90 -> 0
B91: 6666029700 | C91: 6666029700 Service fee recharge | D91: 服务费回收费 | E91: 0 | F91: 0 | G91: 0 | H91: 0 | L91: =H91-F91 -> 0
B92: 6666029900 | C92: 6666029900 Sundry Expenses | D92: 杂项费用 | E92: 0.07586 | F92: 0.00015866973 | G92: 0 | H92: 0 | L92: =H92-F92 -> -0.00015866973
B93: 6666029996 | C93: 6666029996 Non-deductible expense-travel. | D93: 不可扣除费用-旅行 | E93: 0.17373 | F93: 0.00036337586 | G93: 0 | H93: 0 | L93: =H93-F93 -> -0.00036337586
B94: 6666029997 | C94: 6666029997 restructure cost | D94: 重组成本 | E94: 14.93904 | F94: 0.031246685 | G94: 8.251956 | H94: 0.014604715 | L94: =H94-F94 -> -0.01664197
... B99: 6666070300 | C99: 6666070300 Software maintenance fees | D99: 软件维护费 | E99: 0 | F99: 0 | G99: 0 | H99: 0 | L99: =H99-F99 -> 0
B100: 6666070400 | C100: 6666070400 IT maint. & repairs hardware | D100: IT维护及硬件修理 | E100: 62.40957 | F100: 0.13053665 | G100: 145.01519 | H100: 0.25665496 | L100: =H100-F100 -> 0.12611831 | N100: 我有一个25预算与26预算的比较。请查看黄色表格。如果您需要更多细节，我需要与IT团队沟通。
B101: 5401050201 | C101: 5401050201 COGS-Special a | D101: 销售成本-特殊项目 | E101: 0.02369 | F101: 4.9550303e-05 | G101: 0 | H101: 0 | L101: =H101-F101 -> -4.9550303e-05
B102: 5401020212 | C102: 5401020212 Local Transpor | D102: 本地运输 | E102: -0.14776 | F102: -0.00030905668 | G102: 0 | H102: 0 | L102: =H102-F102 -> 0.00030905668
B103: 6666020801 | C103: 6666020801 - HOUSING RENTAL COST | D103: 6666020801 - 住房租赁成本 | F103: 0 | G103: 12.955488 | H103: 0.022929256 | L103: =H103-F103 -> 0.022929256
A104: 生产耗用 | B104: FIX | C104: * CS_Fix Cost | D104: * CS_固定成本 | E104: 470.02002 | F104: 0.98309981 | G104: 673.59401 | H104: 1.1921596 | L104: =H104-F104 -> 0.20905977
B105: 6666110203 | C105: 6666110203 Low value consumables | D105: 低值易耗品 | E105: 145.49291 | F105: 0.30431481 | G105: 185.03175 | H105: 0.32747823 | L105: =H105-F105 -> 0.023163422
...

Sheet 25年降费项目-洗碗机
A1: Candy洗碗机项目制造总结
A2: 25年全年单台↓15.62欧，额收益1036万欧，上涨因素：146万欧（通胀负影响146万欧），下降因素：规模上涨926万，收益降费项目268万（新增262万欧，持续收益6万欧） | I2: 实际收益
A3: 序号 | B3: 主导方 | C3: 分类 | D3: 核心策略/路径 | E3: 关键项目 | F3: 责任人 | G3: 到位时间 | H3: 实际月累差额 | I3: 1月 | J3: 2月 | K3: 3月 | L3: 4月 | M3: 5月 | N3: 6月 | O3: 7月 | P3: 8月 | Q3: 9月 | R3: 10月 | S3: 11月 | T3: 12月
A4: 1 | B4: / | C4: 上涨因素 | D4: 订单量-折旧 | E4: 订单量上涨31%，折旧全年持续收益663万欧 | F4: 李想 | G4: 46023 | H4: =SUM(I4:T4) -> 6630773.9 | I4: 1552518.1 | J4: 1159647.8 | K4: 1112067.1 | L4: 757942.42 | M4: 398927.74 | N4: 156166.36 | O4: 336709.26 | P4: 364919.81 | Q4: -59045.458 | R4: 113498.71 | S4: 59630.608 | T4: 677791.43
A5: 2 | B5: / | C5: 上涨因素 | D5: 订单量-其他 | E5: 订单量上涨31%，半固定、白领工资、运营、园区费用等全年持续收益263万欧 | F5: 李想 | G5: 46023 | H5: =SUM(I5:T5) -> 2631934 | I5: 999706.91 | J5: 463576.49 | K5: 673449.94 | L5: 446203.11 | M5: 142378.64 | N5: -25115.486 | O5: 188754.89 | P5: 147523.56 | Q5: -183157.04 | R5: -145001.4 | S5: -119555.94 | T5: 43170.305
A6: 3 | B6: / | C6: 上涨因素 | D6: 通胀影响-直接人工工资上涨 | E6: 直接人工和间接人工上涨21%，每人上涨361欧，总计影响122万欧 | F6: 李想 | G6: 46023 | H6: =SUM(I6:T6) -> -1219976.2 | I6: -110347.79 | J6: -109624.2 | K6: -112880.36 | L6: -112518.57 | M6: -115412.93 | N6: -119392.69 | O6: -111071.38 | P6: -73444.595 | Q6: -73082.799 | R6: -73082.799 | S6: -93705.173 | T6: -115412.93
A7: 4 | B7: / | C7: 上涨因素 | D7: 通胀影响-管理人工工资上涨 | E7: 管理人员上涨5%，每人308欧，总计影响9万欧 | F7: 李想 | G7: 46023 | H7: =SUM(I7:T7) -> -90188.113 | I7: -7551.1201 | J7: -6934.7021 | K7: -6780.5976 | L7: -7088.8066 | M7: -6780.5976 | N7: -8256.9187 | O7: -8167.538 | P7: -7806.9335 | Q7: -7705.2246 | R7: -7705.2246 | S7: -7705.2246 | T7: -7705.2246
A8: 5 | B8: / | C8: 上涨因素 | D8: 通胀影响-其他 | E8: 除工资科目和折旧外其余科目全部受通胀影响8% | F8: 李想 | G8: 46023 | H8: =SUM(I8:T8) -> -151722.18 | I8: -11923.478 | J8: -16626.988 | K8: -16917.475 | L8: -11648.224 | M8: -14227.46 | N8: -12178.829 | O8: -11957.47 | P8: -10990.992 | Q8: -14074.781 | R8: -10822.61 | S8: -13544.912 | T8: -6808.9548
A9: 6 | B9: 土方 | C9: 降费项目 | D9: 线速提升 34.2秒 ==> 32.72秒 (105件到110件) | E9: / | F9: 李想 | G9: 46023 | H9: =SUM(I9:T9) -> 115972.7 | I9: 10150.45 | J9: 9826.93 | K9: 10251.55 | L9: 10251.55 | M9: 10678.7 | N9: 3670.69 | O9: 10739.36 | P9: 10678.7 | Q9: 11105.85 | R9: 10251.55 | S9: 10678.7 | T9: 7688.67
A10: 7 | B10: 土方 | C10: 降费项目 | D10: 集水器线速 36秒 ==> 30秒 | E10: / | F10: 李想 | G10: 46023 | H10: =SUM(I10:T10) -> 56467.89 | I10: 4942.32 | J10: 4784.8 | K10: 4991.55 | L10: 4991.55 | M10: 5199.53 | N10: 1787.29 | O10: 5229.07 | P10: 5199.53 | Q10: 5407.51 | R10: 4991.55 | S10: 5199.53 | T10: 3743.66
A11: 8 | B11: 土方 | C11: 降费项目 | D11: 内门生产线速度从36秒提升至30秒 | E11: / | F11: 李想 | G11: 46023 | H11: =SUM(I11:T11) -> 71178.01 | I11: 6229.82 | J11: 6031.26 | K11: 6291.87 | L11: 6291.87 | M11: 6554.03 | N11: 2252.88 | O11: 6591.26 | P11: 6554.03 | Q11: 6816.19 | R11: 6291.87 | S11: 6554.03 | T11: 4718.9
A12: 9 | B12: 土方 | C12: 降费项目 | D12: 生产线速度提升，从32.72秒提升至30秒（产量从110件提升至120件） | E12: / | F12: 李想 | G12: 46204 | H12: =SUM(I12:T12) -> 202208.83 | I12: 17698.23 | J12: 17134.14 | K12: 17874.5 | L12: 17874.5 | M12: 18619.27 | N12: 6400.18 | O12: 18725.04 | P12: 18619.27 | Q12: 19364.05 | R12: 17874.5 | S12: 18619.27 | T12: 13405.88
A13: 10 | B13: 土方 | C13: 降费项目 | D13: 直接劳动TC-装配线平衡（移除多余操作员） | E13: / | F13: 李想 | G13: 1.2026年1月 2.7月落地 3.7月落地 4.10月落地 | H13: =SUM(I13:T13) -> 142356.04 | I13: 12459.64 | J13: 12062.52 | K13: 12583.74 | L13: 12583.74 | M13: 13108.06 | N13: 4505.76 | O13: 13182.52 | P13: 13108.06 | Q13: 13632.39 | R13: 12583.74 | S13: 13108.06 | T13: 9437.81
A14: 11 | B14: 土方 | C14: 降费项目 | D14: QS部件喂料自动化 | E14: / | F14: 李想 | G14: 46174 | H14: =SUM(I14:T14) -> 15048.38 | N14: 852.26 | O14: 2493.46 | P14: 2479.38 | Q14: 2578.55 | R14: 2380.2 | S14: 2479.38 | T14: 1785.15
A15: 12 | B15: 土方 | C15: 降费项目 | D15: 轮毂和油底壳螺钉紧固自动化 | E15: / | F15: 李想 | G15: 46174 | H15: =SUM(I15:T15) -> 22841.28 | N15: 1293.61 | O15: 3784.72 | P15: 3763.34 | Q15: 3913.87 | R15: 3612.8 | S15: 3763.34 | T15: 2709.6
A16: 13 | B16: 土方 | C16: 降费项目 | D16: 效率提升（2%） | E16: / | F16: 李想 | G16: 46054 | H16: =SUM(I16:T16) -> 109000 | I16: 9540.17 | J16: 9236.1 | K16: 9635.19 | L16: 9635.19 | M16: 10036.66 | N16: 3450 | O16: 10093.67 | P16: 10036.66 | Q16: 10438.12 | R16: 9635.19 | S16: 10036.66 | T16: 7226.39
A17: 14 | B17: 土方 | C17: 降费项目 | D17: 因生产力提升项目直接减少人力成本 | E17: / | F17: 李想 | G17: 46023 | H17: =SUM(I17:T17) -> 26000.04 | I17: 2166.67 | J17: 2166.67 | K17: 2166.67 | L17: 2166.67 | M17: 2166.67 | N17: 2166.67 | O17: 2166.67 | P17: 2166.67 | Q17: 2166.67 | R17: 2166.67 | S17: 2166.67 | T17: 2166.67
A18: 15 | B18: 土方 | C18: 降费项目 | D18: 通过将压缩机的热空气转移到市场区域来回收利用 | E18: / | F18: 李想 | G18: 46023 | H18: =SUM(I18:T18) -> 2347.68 | I18: 195.64 | J18: 195.64 | K18: 195.64 | L18: 195.64 | M18: 195.64 | N18: 195.64 | O18: 195.64 | P18: 195.64 | Q18: 195.64 | R18: 195.64 | S18: 195.64 | T18: 195.64
A19: 16 | B19: 土方 | C19: 降费项目 | D19: 为减轻电枢设计新布局并调整灯光 | E19: / | F19: 李想 | G19: 46023 | H19: =SUM(I19:T19) -> 2136 | I19: 178 | J19: 178 | K19: 178 | L19: 178 | M19: 178 | N19: 178 | O19: 178 | P19: 178 | Q19: 178 | R19: 178 | S19: 178 | T19: 178
A20: 17 | B20: 土方 | C20: 降费项目 | D20: 燃料成本 | E20: / | F20: 李想 | G20: 46023 | H20: =SUM(I20:T20) -> 646.32 | I20: 53.86 | J20: 53.86 | K20: 53.86 | L20: 53.86 | M20: 53.86 | N20: 53.86 | O20: 53.86 | P20: 53.86 | Q20: 53.86 | R20: 53.86 | S20: 53.86 | T20: 53.86
A21: 18 | B21: 土方 | C21: 降费项目 | D21: 制服成本 | E21: / | F21: 李想 | G21: 46023 | H21: =SUM(I21:T21) -> 52072.44 | I21: 4339.37 | J21: 4339.37 | K21: 4339.37 | L21: 4339.37 | M21: 4339.37 | N21: 4339.37 | O21: 4339.37 | P21: 4339.37 | Q21: 4339.37 | R21: 4339.37 | S21: 4339.37 | T21: 4339.37
A22: 19 | B22: 土方 | C22: 降费项目 | D22: 人力成本减少项目半固定成本收益 | E22: / | F22: 李想 | G22: 46023 | H22: =SUM(I22:T22) -> 28370.04 | I22: 2364.17 | J22: 2364.17 | K22: 2364.17 | L22: 2364.17 | M22: 2364.17 | N22: 2364.17 | O22: 2364.17 | P22: 2364.17 | Q22: 2364.17 | R22: 2364.17 | S22: 2364.17 | T22: 2364.17
A23: 20 | B23: 土方 | C23: 降费项目 | D23: DW - 油底壳区域/电机部件 - 人力成本减少 | E23: / | F23: 李想 | G23: 46023 | H23: =SUM(I23:T23) -> 26000.04 | I23: 2166.67 | J23: 2166.67 | K23: 2166.67 | L23: 2166.67 | M23: 2166.67 | N23: 2166.67 | O23: 2166.67 | P23: 2166.67 | Q23: 2166.67 | R23: 2166.67 | S23: 2166.67 | T23: 2166.67
A24: 21 | B24: 土方 | C24: 降费项目 | D24: DW - 塑料部件 - 人力成本减少 | E24: / | F24: 李想 | G24: 46023 | H24: =SUM(I24:T24) -> 26000.04 | I24: 2166.67 | J24: 2166.67 | K24: 2166.67 | L24: 2166.67 | M24: 2166.67 | N24: 2166.67 | O24: 2166.67 | P24: 2166.67 | Q24: 2166.67 | R24: 2166.67 | S24: 2166.67 | T24: 2166.67
A25: 22 | B25: 土方 | C25: 降费项目 | D25: DW - 软水器 - 空气断路 - 人力成本减少 | E25: / | F25: 李想 | G25: 46023 | H25: =SUM(I25:T25) -> 26000.04 | I25: 2166.67 | J25: 2166.67 | K25: 2166.67 | L25: 2166.67 | M25: 2166.67 | N25: 2166.67 | O25: 2166.67 | P25: 2166.67 | Q25: 2166.67 | R25: 2166.67 | S25: 2166.67 | T25: 2166.67
A26: 23 | B26: 土方 | C26: 降费项目 | D26: DW - 卸货区 - 人力成本减少 | E26: / | F26: 李想 | G26: 46023 | H26: =SUM(I26:T26) -> 26000.04 | I26: 2166.67 | J26: 2166.67 | K26: 2166.67 | L26: 2166.67 | M26: 2166.67 | N26: 2166.67 | O26: 2166.67 | P26: 2166.67 | Q26: 2166.67 | R26: 2166.67 | S26: 2166.67 | T26: 2166.67
A27: 24 | B27: 土方 | C27: 降费项目 | D27: DW - 大型部件重新包装 - 人力成本减少 | E27: / | F27: 李想 | G27: 46023 | H27: =SUM(I27:T27) -> 26000.04 | I27: 2166.67 | J27: 2166.67 | K27: 2166.67 | L27: 2166.67 | M27: 2166.67 | N27: 2166.67 | O27: 2166.67 | P27: 2166.67 | Q27: 2166.67 | R27: 2166.67 | S27: 2166.67 | T27: 2166.67
... A39: 36 | B39: 土方 | C39: 降费项目 | D39: 维护备件优化 - 一次性 | E39: / | F39: 李想 | G39: 46023 | H39: =SUM(I39:T39) -> 60000 | I39: 5000 | J39: 5000 | K39: 5000 | L39: 5000 | M39: 5000 | N39: 5000 | O39: 5000 | P39: 5000 | Q39: 5000 | R39: 5000 | S39: 5000 | T39: 5000
A40: 37 | B40: 土方 | C40: 降费项目 | D40: 产能提升 | E40: / | F40: 李想 | G40: 46023 | H40: =SUM(I40:T40) -> 221029.86 | J40: 23796.175 | K40: 23796.175 | L40: 24985.984 | M40: 27769.443 | N40: 15338.76 | O40: 21643.557 | P40: 16534.774 | Q40: 14927.162 | R40: 13444.167 | S40: 17593.243 | T40: 21200.417
A41: 38 | B41: 土方 | C41: 降费项目 | D41: 生产能源耗费 | E41: / | F41: 李想 | G41: 46023 | H41: =SUM(I41:T41) -> 43000 | I41: 3649.014 | J41: 3593.7259 | K41: 3593.7259 | L41: 3773.4122 | M41: 3773.4122 | N41: 1437.178 | O41: 4132.7848 | P41: 3773.4122 | Q41: 3953.0985 | R41: 4132.7848 | S41: 3593.7259 | T41: 3593.7259
A42: 39 | B42: 土方 | C42: 降费项目 | D42: 卖废 | E42: / | F42: 李想 | G42: 46023 | H42: =SUM(I42:T42) -> 25000 | I42: 2121.5198 | J42: 2089.3755 | K42: 2089.3755 | L42: 2193.8443 | M42: 2193.8443 | N42: 835.5686 | O42: 2402.7818 | P42: 2193.8443 | Q42: 2298.3131 | R42: 2402.7818 | S42: 2089.3755 | T42: 2089.3755
A43: 40 | B43: 土方 | C43: 降费项目 | D43: 其他变量（生产耗材，库存调整） | E43: / | F43: 李想 | G43: 46082 | H43: =SUM(I43:T43) -> 60000 | I43: 0 | J43: 0 | K43: 10000 | L43: 10000 | M43: 10000 | N43: 10000 | O43: 10000 | P43: 10000 | Q43: 0 | R43: 0 | S43: 0 | T43: 0
A44: 41 | B44: 土方 | C44: 降费项目 | D44: 消耗品减少 - 一次性 | E44: / | F44: 李想 | G44: 46082 | H44: =SUM(I44:T44) -> 70000 | I44: 0 | J44: 0 | K44: 10000 | L44: 10000 | M44: 10000 | N44: 10000 | O44: 10000 | P44: 10000 | Q44: 0 | R44: 0 | S44: 0 | T44: 10000
A45: 42 | B45: 土方 | C45: 降费项目 | D45: 人力成本减少 | E45: / | F45: 李想 | G45: 46023 | H45: =SUM(I45:T45) -> 62050 | J45: 2600 | K45: 4100 | L45: 6150 | M45: 6150 | N45: 6150 | O45: 6150 | P45: 6150 | Q45: 6150 | R45: 6150 | S45: 6150 | T45: 6150
A46: 43 | B46: 土方 | C46: 降费项目 | D46: 人力成本减少 | E46: / | F46: 李想 | G46: 46113 | H46: =SUM(I46:T46) -> 36900 | L46: 4100 | M46: 4100 | N46: 4100 | O46: 4100 | P46: 4100 | Q46: 4100 | R46: 4100 | S46: 4100 | T46: 4100
A47: 44 | B47: 土方 | C47: 降费项目 | D47: 人力成本减少 | E47: / | F47: 李想 | G47: 46023 | H47: =SUM(I47:T47) -> 128456 | I47: 7456 | J47: 11000 | K47: 11000 | L47: 11000 | M47: 11000 | N47: 11000 | O47: 11000 | P47: 11000 | Q47: 11000 | R47: 11000 | S47: 11000 | T47: 11000
A48: 45 | B48: 土方 | C48: 降费项目 | D48: 人力成本减少带来的收益 | E48: / | F48: 李想 | G48: 46054 | H48: =SUM(I48:T48) -> 16800 | J48: 560 | K48: 1120 | L48: 1680 | M48: 1680 | N48: 1680 | O48: 1680 | P48: 1680 | Q48: 1680 | R48: 1680 | S48: 1680 | T48: 1680
A49: 46 | B49: 土方 | C49: 降费项目 | D49: 工作日减少 | E49: / | F49: 李想 | G49: 46023 | H49: =SUM(I49:T49) -> 30000 | I49: 2500 | J49: 2500 | K49: 2500 | L49: 2500 | M49: 2500 | N49: 2500 | O49: 2500 | P49: 2500 | Q49: 2500 | R49: 2500 | S49: 2500 | T49: 2500
A50: 47 | B50: 土方 | C50: 降费项目 | D50: 工作日减少 | E50: / | F50: 李想 | G50: 46023 | H50: =SUM(I50:T50) -> 19800 | I50: 1650 | J50: 1650 | K50: 1650 | L50: 1650 | M50: 1650 | N50: 1650 | O50: 1650 | P50: 1650 | Q50: 1650 | R50: 1650 | S50: 1650 | T50: 1650
A51: 48 | B51: 土方 | C51: 降费项目 | D51: 效率提升 | E51: / | F51: 李想 | G51: 46023 | H51: =SUM(I51:T51) -> 18000 | I51: 1500 | J51: 1500 | K51: 1500 | L51: 1500 | M51: 1500 | N51: 1500 | O51: 1500 | P51: 1500 | Q51: 1500 | R51: 1500 | S51: 1500 | T51: 1500
A52: 49 | B52: 土方 | C52: 降费项目 | D52: 维护 - 一次性 | E52: / | F52: 李想 | G52: 46023 | H52: =SUM(I52:T52) -> 130000 | I52: 10000 | J52: 10000 | K52: 10000 | L52: 10000 | M52: 10000 | N52: 10000 | O52: 10000 | P52: 10000 | Q52: 10000 | R52: 10000 | S52: 10000 | T52: 20000
A53: 50 | B53: 土方 | C53: 降费项目 | D53: Edenred税消除 | E53: / | F53: 李想 | G53: 46023 | H53: =SUM(I53:T53) -> -20000.04 | I53: -1666.67 | J53: -1666.67 | K53: -1666.67 | L53: -1666.67 | M53: -1666.67 | N53: -1666.67 | O53: -1666.67 | P53: -1666.67 | Q53: -1666.67 | R53: -1666.67 | S53: -1666.67 | T53: -1666.67
A54: 51 | B54: 土方 | C54: 降费项目 | D54: 人力成本减少 | E54: / | F54: 李想 | G54: 46023 | H54: =SUM(I54:T54) -> 12000 | I54: 1000 | J54: 1000 | K54: 1000 | L54: 1000 | M54: 1000 | N54: 1000 | O54: 1000 | P54: 1000 | Q54: 1000 | R54: 1000 | S54: 1000 | T54: 1000
A55: 52 | B55: 土方 | C55: 降费项目 | D55: 折旧减少 - 一次性 | E55: / | F55: 李想 | G55: 46023 | H55: =SUM(I55:T55) -> 406079.64 | I55: 50529.431 | J55: 50529.431 | K55: 50529.431 | L55: 42415.224 | M55: 42415.224 | N55: 42415.224 | O55: 25264.716 | P55: 25264.716 | Q55: 25264.716 | R55: 17150.509 | S55: 17150.509 | T55: 17150.509
A56: 53 | B56: 土方 | C56: 延续项目 | D56: 24年延续项目 | E56: / | F56: 李想 | G56: 46023 | H56: 60000 | I56: 15000 | J56: 15000 | K56: 15000 | L56: 15000

Sheet 26年降费项目-洗碗机
A1: Candy洗碗机项目制造总结
A2: 26年SBU降费目标85万，现梳理影响因素及项目296万,保障度150% 26年5月累计单台↑7.37欧，额恶化137万欧，上涨因素：178万欧（定单量下降负影响128万欧，通胀负影响50万欧），下降因素：降费项目100万（新增93万欧，持续收益7万欧），园区分摊下降1万 26年重点推进降费项目13个，5已落地收益100万，W23新挖掘1个
A3: 序号 | B3: 主导方 | C3: 分类 | D3: 核心策略/路径 | E3: 关键项目 | F3: 土耳其责任人 | G3: 责任人 | H3: 到位时间 | I3: 预计影响 | J3: 实际月累差额 | K3: 进展 | L3: 1月 | M3: 2月 | N3: 3月 | O3: 4月 | P3: 5月 | Q3: 6月 | R3: 7月 | S3: 8月 | T3: 9月 | U3: 10月 | V3: 11月 | W3: 12月 | X3: 1月 | Y3: 2月 | Z3: 3月 | AA3: 4月 | AB3: 5月 | AC3: 6月 | AD3: 7月 | AE3: 8月 | AF3: 9月 | AG3: 10月 | AH3: 11月 | AI3: 12月
A4: 1 | B4: / | C4: 上涨因素 | D4: 订单量-折旧 | E4: 订单量上涨18%，折旧全年持续收益65万欧 | G4: 李想 | H4: 46023 | I4: 644719 | J4: =SUM(X4:AB4) -> -634306.12 | K4: 订单量下滑19%，折旧影响47万欧 | L4: -8147.0616 | M4: 21152.771 | N4: 13615.058 | O4: -26913.108 | P4: -178778.53 | Q4: 454012.7 | R4: -17117.652 | S4: 106023.41 | T4: 491161.4 | U4: 86779.928 | V4: 236372.72 | W4: -73558.588 | X4: -30627.136 | Y4: -50322.987 | Z4: =-286652 -> -286652 | AA4: -100000 | AB4: -166704
A5: 2 | B5: / | C5: 上涨因素 | D5: 订单量-直接、间接人工 | E5: 如果订单量恶化，直接、间接员工无法裁员导致的影响 | G5: 李想 | H5: 46023 | I5: =SUM(K5:V5) -> 0 | J5: =SUM(X5:AB5) -> -198297 | K5: 5月订单量下降，直接、间接员工影响10万欧 | L5: 0 | M5: 0 | N5: 0 | O5: 0 | P5: 0 | Q5: 0 | R5: 0 | S5: 0 | T5: 0 | U5: 0 | V5: 0 | W5: 0 | X5: 57776 | Y5: -123424 | Z5: -33862 | AA5: 0 | AB5: -98787
A6: 3 | B6: / | C6: 上涨因素 | D6: 订单量-其他 | E6: 订单量上涨18%，半固定、白领工资、运营、园区费用等全年持续收益44.2万欧 | G6: 李想 | H6: 46023 | I6: =SUM(K6:V6) -> 690011.19 | J6: =SUM(X6:AB6) -> -450327 | K6: 订单量下滑19%，半固定、运营、园区费用影响53万欧 | L6: =-62435.1547019647*(51/56) -> -56860.587 | M6: =89386.5094733414*(51/56) -> 81405.571 | N6: =-29449.4262278466*(51/56) -> -26820.013 | O6: =-162306.500567043*(51/56) -> -147814.85 | P6: =-212405.386395815*(51/56) -> -193440.62 | Q6: =362170.452294098*(51/56) -> 329833.8 | R6: =-82468.0916948369*(51/56) -> -75104.869 | S6: =-34553.7451901179*(51/56) -> -31468.589 | T6: =360826.124865029*(51/56) -> 328609.51 | U6: =316878.345288374*(51/56) -> 288585.64 | V6: =212016.223059487*(51/56) -> 193086.2 | W6: =-271656.706239918*(51/56) -> -247401.64 | X6: -69343 | Y6: -27259 | Z6: -404409 | AA6: -27052 | AB6: 77736
A7: 4 | B7: / | C7: 上涨因素 | D7: 通胀影响-直接人工工资上涨 | E7: 直接人工和间接人工上涨12%，每人上涨241欧，总计影响96万欧 | G7: 李想 | H7: 46023 | I7: =SUM(K7:V7) -> -880132 | J7: =SUM(X7:AB7) -> -370899 | K7: 总人次3989，截至4月影响29万欧 | L7: -79289 | M7: -79289 | N7: -79289 | O7: -79289 | P7: -80012 | Q7: -79530 | R7: -79530 | S7: -80976 | T7: -81217 | U7: -80735 | V7: -80976 | W7: -81217 | X7: -79289 | Y7: -79289 | Z7: -53020 | AA7: -79289 | AB7: -80012
A8: 5 | B8: / | C8: 上涨因素 | D8: 通胀影响-管理人工工资上涨 | E8: 管理人员上涨5%，每人161欧 | G8: 李想 | H8: 46023 | I8: =SUM(K8:V8) -> -47575.5 | J8: =SUM(X8:AB8) -> -21332.5 | K8: 总人次323，截至4月影响2万欧 | L8: -4266.5 | M8: -4266.5 | N8: -4266.5 | O8: -4266.5 | P8: -4266.5 | Q8: -4266.5 | R8: -4266.5 | S8: -4427.5 | T8: -4427.5 | U8: -4427.5 | V8: -4427.5 | W8: -4427.5 | X8: -4266.5 | Y8: -4266.5 | Z8: -4266.5 | AA8: -4266.5 | AB8: -4266.5
A9: 6 | B9: / | C9: 上涨因素 | D9: 通胀影响-其他 | E9: 除工资科目和折旧外其余科目全部受通胀影响8% | G9: 李想 | H9: 46023 | I9: =SUM(K9:V9) -> -256385.51 | J9: =SUM(X9:AB9) -> -117407.31 | K9: 截至4月累计影响9万欧 | L9: -24153.245 | M9: -23860.796 | N9: -23573.237 | O9: -23294.139 | P9: -20111.665 | Q9: -24424.287 | R9: -22619.353 | S9: -22048.085 | T9: -24347.846 | U9: -23676.767 | V9: -24276.087 | W9: -22437.21 | X9: -21014 | Y9: -26260.796 | Z9: -23573.237 | AA9: -23294.139 | AB9: -23265.139
A10: 7 | B10: / | C10: 上涨因素 | D10: 园区分摊费用 | E10: IT费用降费 分摊逻辑-产量改为产值 | G10: 李想 | H10: 46023 | I10: =SUM(K10:V10) -> 30462.256 | J10: =SUM(X10:AB10) -> 13358.839 | K10: 截至4月降费1万 | L10: -16558.794 | M10: 51879.986 | N10: 27404.936 | O10: -30487.823 | P10: 4396.8737 | Q10: -7728.1599 | R10: -4072.4732 | S10: -15271.256 | T10: 10458.095 | U10: 15393.499 | V10: -4952.6274 | W10: -225774.27 | X10: -21018.066 | Y10: 35467.824 | Z10: 27908.854 | AA10: -34119.773 | AB10: 5120
A11: 8 | B11: 土方 | C11: 延续项目 | D11: 25年延续项目 | E11: 1.轮毂和油底壳螺钉紧固自动化 2.QS部件喂料自动化 3.人力成本减少 | G11: 李想 | H11: 46023 | I11: =SUM(K11:V11) -> 73569.854 | J11: =SUM(X11:AB11) -> 70786.944 | K11: / | L11: 37185.091 | M11: 20865.136 | N11: 9953.8086 | O11: 2782.9092 | P11: 2782.9092 | Q11: 0 | R11: 0 | S11: 0 | T11: 0 | U11: 0 | V11: 0 | W11: 0 | X11: 37185.091 | Y11: 20865.136 | Z11: 9953.8086 | AA11: 2782.9092 | AB11: 0
A12: 9 | B12: 土方 | C12: 提效 | D12: 提升单台生产效率，减少单台成本 | E12: UPH提升至130 | F12: A.Civelek / A.Civelek /BCA | G12: 李想 | H12: 46023 | I12: =SUM(K12:V12) -> 67591.229 | J12: =SUM(X12:AB12) -> 26753.407 | K12: 已落地 | L12: 6665.0242 | M12: 5994.5388 | N12: 3237.3015 | O12: 6206.071 | P12: 4650.4718 | Q12: 7454.7163 | R12: 5713.481 | S12: 5600.0446 | T12: 7727.6112 | U12: 7032.4963 | V12: 7309.4726 | W12: 5937.8206 | X12: 6665.0242 | Y12: 5994.5388 | Z12: 3237.3015 | AA12: 6206.071 | AB12: 4650.4718
A13: 10 | B13: 土方 | C13: 直接员工降费 | D13: 用工结构调整：提前谈判清退固定员工，回收期12~15个月 | E13: 蓝领工人合同工替换高工资正式工。 | F13: E.KAraca | G13: 李想 | H13: 46023 | I13: =SUM(K13:V13) -> 292000 | J13: =SUM(X13:AB13) -> 76666.667 | K13: 已替换81人 | L13: 0 | M13: 0 | N13: 0 | O13: 21000 | P13: 41666.667 | Q13: 41666.667 | R13: 41666.667 | S13: 41666.667 | T13: 41666.667 | U13: 41666.667 | V13: 21000 | W13: 21000 | X13: 0 | Y13: 0 | Z13: 14000 | AA13: 21000 | AB13: 41666.667
A14: 11 | B14: 土方、中方 | C14: 直接员工降费 | D14: 锁定26年到月需求、生产、库存预算，均衡生产策略，消除25年分流浪费42万欧（只有一个工厂有），加班费损失80万欧 | E14: 26年不产生分流费、加班费 | G14: 李想 | H14: 46023 | I14: =SUM(K14:V14) -> 360000 | J14: =SUM(X14:AB14) -> 38100 | K14: 1月加班费减少5100，2月加班费减少3000 | L14: 0 | M14: 0 | N14: 40000 | O14: 40000 | P14: 40000 | Q14: 40000 | R14: 40000 | S14: 40000 | T14: 40000 | U14: 40000 | V14: 40000 | W14: 40000 | X14: 5100 | Y14: 3000 | Z14: 0 | AA14: 30000 | AB14: 0
A15: 12 | B15: 土方、中方 | C15: 直接员工降费 | D15: 模块化成套供货 | E15: 洗碗机预装8个项目18个人模块化成套，17万欧（不包含材料上涨） | G15: 李想 | H15: 46204 | I15: =SUM(K15:V15) -> 120000 | J15: =SUM(X15:AB15) -> 0 | K15: 进度：1月份已完成与供应商购买价格谈判 ，目前无进展 | L15: 0 | M15: 0 | N15: 0 | O15: 0 | P15: 0 | Q15: 0 | R15: 0 | S15: 0 | T15: 0 | U15: 60000 | V15: 60000 | W15: 70000 | X15: 0 | Y15: 0 | Z15: 0 | AA15: 0 | AB15: 0
A16: 13 | B16: 土方、中方 | C16: 间接员工降费 | D16: 对标国内工厂优化空间： DW 84人，初步机会10个，（master替班16人） | E16: 1.第一阶段1人（物流减少一人，岗位合并）-土方主导 2.第一阶段1人（物流减少一人，岗位合并）-土方主导 3.第一阶段1人（物流减少一人，岗位合并）-土方主导 4.DW辅助人员84人，初步机会10个-中方主导 | F16: A.Civelek / E.Erbaş | G16: 李想 | H16: 1.2026年1月 2.7月落地 3.7月落地 4.10月落地 | I16: =SUM(K16:V16) -> 106549.4 | J16: =SUM(X16:AB16) -> 13445.52 | K16: 1.已落地 2.无进展 3.无进展 4.无进展 | L16: 0 | M16: 2240.88 | N16: 2240.88 | O16: 4481.88 | P16: 4481.88 | Q16: 4481.88 | R16: 11838.88 | S16: 19195.78 | T16: 19195.78 | U16: 19195.78 | V16: 19195.78 | W16: 19195.78 | X16: 0 | Y16: 2240.88 | Z16: 2240.88 | AA16: 4481.88 | AB16: 4481.88
A17: 14 | B17: 土方 | C17: 备件费用 | D17: 冲压润滑收集循环使用 | E17: 848欧一桶，每月节省0.85桶 | F17: A.Civelek /BCA | G17: 李想 | H17: 46023 | I17: =SUM(K17:V17) -> 11000 | J17: =SUM(X17:AB17) -> 5000 | K17: 已落地 | L17: 1000 | M17: 1000 | N17: 1000 | O17: 1000 | P17: 1000 | Q17: 1000 | R17: 1000 | S17: 1000 | T17: 1000 | U17: 1000 | V17: 1000 | W17: 1000 | X17: 1000 | Y17: 1000 | Z17: 1000 | AA17: 1000 | AB17: 1000
A18: 15 | B18: 土方 | C18: 能源费用 | D18: 工厂空调设备节能运行优化 | E18: 电单价0.057欧//Kwh | F18: A.Civelek | G18: 李想 | H18: 46054 | I18: =SUM(K18:V18) -> 6300 | J18: =SUM(X18:AB18) -> 2100 | K18: 已落地 | L18: 0 | M18: 0 | N18: 700 | O18: 700 | P18: 700 | Q18: 700 | R18: 700 | S18: 700 | T18: 700 | U18: 700 | V18: 700 | W18: 700 | X18: 0 | Y18: 0 | Z18: 700 | AA18: 700 | AB18: 700
A19: 16 | B19: 土方 | C19: 能源费用 | D19: 工厂照明节能优化 | E19: 电单价0.057欧//Kwh | F19: A.Civelek /BCA | G19: 李想 | H19: 46054 | I19: =SUM(K19:V19) -> 2005.2 | J19: =SUM(X19:AB19) -> 668.4 | K19: 已落地 | L19: 0 | M19: 0 | N19: 222.8 | O19: 222.8 | P19: 222.8 | Q19: 222.8 | R19: 222.8 | S19: 222.8 | T19: 222.8 | U19: 222.8 | V19: 222.8 | W19: 222.8 | X19: 0 | Y19: 0 | Z19: 222.8 | AA19: 222.8 | AB19: 222.8
A20: 17 | B20: 土方 | C20: 生产提效 | D20: 注塑件节拍改进（减少3秒） | E20: 节拍62S-59S，效率提升 | F20: A.Civelek | G20: 李想 | H20: 46023 | I20: =SUM(K20:V20) -> 6381.8018 | J20: =SUM(X20:AB20) -> 2525.9926 | K20: 已落地 | L20: 629.2956 | M20: 565.98998 | N20: 305.65824 | O20: 585.96235 | P20: 439.0864 | Q20: 703.85644 | R20: 539.45318 | S20: 528.74278 | T20: 729.62252 | U20: 663.99144 | V20: 690.14288 | W20: 560.63478 | X20: 629.2956 | Y20: 565.98998 | Z20: 305.65824 | AA20: 585.96235 | AB20: 439.0864
A21: 18 | B21: 中方 | C21: 直接员工降费 | D21: 减少人员宽放损失 | E21: 26年预算人员出勤总工时宽放6%预留12个人，实际缺勤率在4%左右，计划优化2-4人 | G21: 李想 | H21: 46235 | I21: =SUM(K21:V21) -> 20160 | J21: =SUM(X21:AB21) -> 0 | K21: 1.申请人力部门提供全员出勤率数据，以及宽放人员日常岗位排布明细 2.建议推动宽放人员实现三家工厂统筹共享、统一调配， 3.需现场核实：日常少量人员缺勤（1-2 人）对产线整体生产效率的实际影响，合理评估现有宽放比例的必要性。 | T21: =2240*3 -> 6720 | U21: =2240*3 -> 6720 | V21: =2240*3 -> 6720 | W21: =2240*3 -> 6720
A22: 19 | B22: 中方 | C22: 组织运营费 | D22: 叉车租赁费降低 | E22: 1.丰田叉车合同11月到期后，更换报价最低供应商 2.排查产能负荷率，目标减少5%叉车数量 | G22: 李想 | H22: 46235 | I22: =SUM(K22:V22) -> 3600 | J22: =SUM(X22:AB22) -> 0 | K22: 1，提升负荷率，研究提效，节约2辆叉车 | T22: 1200 | U22: 1200 | V22: 1200 | W22: 1200
A23: 20 | B23: 土方 | C23: 直接员工降费 | D23: 宜家订单纸壳上料工序效率提升 | F23: A.Civelek | G23: 李想 | H23: 46082 | I23: =SUM(K23:V23) -> 3608.6944 | J23: =SUM(X23:AB23) -> 902.17361 | O23: 451.08681 | P23: 451.08681 | Q23: 451.08681 | R23: 451.08681 | S23: 451.08681 | T23: 451.08681 | U23: 451.08681 | V23: 451.08681 | W23: 451.08681 | AA23: 451.08681 | AB23: 451.08681
A24: 21 | B24: 土方 | C24: 直接员工降费 | D24: 包装线速优化 | F24: A.Civelek /BCA | G24: 李想 | H24: 46174 | I24: =SUM(K24:V24) -> 12793.441 | J24: =SUM(X24:AB24) -> 1827.6344 | P24: 1827.6344 | Q24: 1827.6344 | R24: 1827.6344 | S24: 1827.6344 | T24: 1827.6344 | U24: 1827.6344 | V24: 1827.6344 | W24: 1827.6344 | AB24: 1827.6344
A25: 22 | B25: 中方 | C25: 折旧降费 | D25: 折旧费用优化 | E25: 部分设备、模具折旧年限10→30 | F25: A.Civelek | G25: 李想 | H25: 46113 | I25: =SUM(K25:V25) -> 1466877.9 | J25: =SUM(X25:AB25) -> 665389.26 | K25: 已落地53万欧，全年预算160万欧 | O25: 530340.03 | P25: 135049.23 | Q25: 132585.21 | R25: 135048.46 | S25: 135042.68 | T25: 132130.96 | U25: 134574.27 | V25: 132107.03 | W25: 134287.34 | AA25: 530340.03 | AB25: 135049.23
B26: 中方、土方 | C26: 降存货跌价准备 | D26: 超期原材料、半成品消耗 | E26: 与开发达成一致，超期原材料加工成半成品 | G26: 李想 | H26: 46113 | I26: 88000 | J26: =SUM(X26:AB26) -> 88000 | O26: 88000 | AA26: 88000
